{
  "identify": "TPD-93-自緝-33-20040623-1",
  "court": {
    "name": "臺灣臺北地方法院",
    "code": "TPD"
  },
  "division": {
    "name": "刑事",
    "code": "M"
  },
  "year": 93,
  "word": "自緝",
  "number": "33",
  "jcheck": "1",
  "reason": "過失傷害",
  "content": "臺灣臺北地方法院刑事判決                          九十三年度自緝字第三三號\n    自  訴  人  乙○○\n    被      告  甲○○\n右列被告因過失傷害案件，經自訴人提起自訴，及台灣台北地方法院檢察署移送併辦\n（八十七年度偵字第一一八一一號），本院判決如左：\n    主  文\n本件免訴。\n    理  由\n一、自訴意旨略以：甲○○於民國八十六年十一月八日晚間十時五十五分許，駕駛車\n    號Ｋ四─二二一五號自小客貨車搭載乙○○，行經華中橋（北往南）時發生車禍\n    ，致乙○○受有右側髖關節骨折脫臼合併坐骨神經麻痺、兩側脛非骨開放性骨折\n    、右側膝關節前十字韌帶斷裂等傷害，因認被告甲○○涉犯刑法第二百八十四條\n    第一項後段過失致重傷罪等語。\n二、按案件時效已完成者，應諭知免訴之判決，且得不經言詞辯論為之，刑事訴訟法\n    第三百零二條第二款、第三百零七條定有明文，依同法第三百四十三條，亦為自\n    訴程序所準用。\n三、查被告甲○○於八十六年十一月八日涉犯過失致重傷罪，經檢察官於八十七年六\n    月九日開始偵查，嗣自訴人提起自訴，於同年七月三十日繫屬於本院，檢察官即\n    停止偵查，檢卷移送本院併案審理，又因被告逃匿，經本院於同年九月十四日發\n    布通緝，致審判之程序不能開始。刑法第二百八十四條第一項後段規定過失致重\n    傷罪之法定刑為一年以下有期徒刑、拘役或五百元以下罰金，故依刑法第八十條\n    第一項第三款規定，本件追訴權時效期間為五年，再依刑法第八十三條之規定，\n    本件時效停止原因已達前述五年期間之四分之一，即一年三月以上，是時效停止\n    原因視為消滅，故本件追訴權之時效迄至九十三年五月十四日業已完成。依照首\n    開說明，爰不經言詞辯論，逕為諭知免訴之判決。\n四、台灣台北地方法院檢察署移送併辦之八十七年度偵字第一一八一一號被告涉犯過\n    失致重傷罪部分，與本案係事實上同一案件，本院自得並予審理，附此敘明。\n據上論斷，應依刑事訴訟法第三百四十三條、第三百零二條第二款、第三百零七條，\n判決如主文。\n中      華      民      國    九十三    年      六      月    二十三    日\n                                    臺灣臺北地方法院刑事第七庭\n                                        審判長法  官  梁耀鑌\n                                              法  官  林欣蓉\n                                              法  官  蕭清清\n右正本證明與原本無異。\n如不服本判決，應於判決送達後十日內，向本院提出上訴狀。\n                                              書記官  劉麗英\n中      華      民      國    九十三    年      六      月    二十五    日\n",
  "structure": {
    "main": "本件免訴。",
    "reason": "一、自訴意旨略以：甲○○於民國八十六年十一月八日晚間十時五十五分許，駕駛車\n    號Ｋ四─二二一五號自小客貨車搭載乙○○，行經華中橋（北往南）時發生車禍\n    ，致乙○○受有右側髖關節骨折脫臼合併坐骨神經麻痺、兩側脛非骨開放性骨折\n    、右側膝關節前十字韌帶斷裂等傷害，因認被告甲○○涉犯刑法第二百八十四條\n    第一項後段過失致重傷罪等語。\n二、按案件時效已完成者，應諭知免訴之判決，且得不經言詞辯論為之，刑事訴訟法\n    第三百零二條第二款、第三百零七條定有明文，依同法第三百四十三條，亦為自\n    訴程序所準用。\n三、查被告甲○○於八十六年十一月八日涉犯過失致重傷罪，經檢察官於八十七年六\n    月九日開始偵查，嗣自訴人提起自訴，於同年七月三十日繫屬於本院，檢察官即\n    停止偵查，檢卷移送本院併案審理，又因被告逃匿，經本院於同年九月十四日發\n    布通緝，致審判之程序不能開始。刑法第二百八十四條第一項後段規定過失致重\n    傷罪之法定刑為一年以下有期徒刑、拘役或五百元以下罰金，故依刑法第八十條\n    第一項第三款規定，本件追訴權時效期間為五年，再依刑法第八十三條之規定，\n    本件時效停止原因已達前述五年期間之四分之一，即一年三月以上，是時效停止\n    原因視為消滅，故本件追訴權之時效迄至九十三年五月十四日業已完成。依照首\n    開說明，爰不經言詞辯論，逕為諭知免訴之判決。\n四、台灣台北地方法院檢察署移送併辦之八十七年度偵字第一一八一一號被告涉犯過\n    失致重傷罪部分，與本案係事實上同一案件，本院自得並予審理，附此敘明。\n據上論斷，應依刑事訴訟法第三百四十三條、第三百零二條第二款、第三百零七條，\n判決如主文。"
  },
  "search": "臺灣臺北地方法院刑事判決九十三年度自緝字第三三號自訴人乙○○被告甲○○右列被告因過失傷害案件，經自訴人提起自訴，及台灣台北地方法院檢察署移送併辦（八十七年度偵字第一一八一一號），本院判決如左：主文本件免訴。理由一、自訴意旨略以：甲○○於民國八十六年十一月八日晚間十時五十五分許，駕駛車號Ｋ四─二二一五號自小客貨車搭載乙○○，行經華中橋（北往南）時發生車禍，致乙○○受有右側髖關節骨折脫臼合併坐骨神經麻痺、兩側脛非骨開放性骨折、右側膝關節前十字韌帶斷裂等傷害，因認被告甲○○涉犯刑法第二百八十四條第一項後段過失致重傷罪等語。二、按案件時效已完成者，應諭知免訴之判決，且得不經言詞辯論為之，刑事訴訟法第三百零二條第二款、第三百零七條定有明文，依同法第三百四十三條，亦為自訴程序所準用。三、查被告甲○○於八十六年十一月八日涉犯過失致重傷罪，經檢察官於八十七年六月九日開始偵查，嗣自訴人提起自訴，於同年七月三十日繫屬於本院，檢察官即停止偵查，檢卷移送本院併案審理，又因被告逃匿，經本院於同年九月十四日發布通緝，致審判之程序不能開始。刑法第二百八十四條第一項後段規定過失致重傷罪之法定刑為一年以下有期徒刑、拘役或五百元以下罰金，故依刑法第八十條第一項第三款規定，本件追訴權時效期間為五年，再依刑法第八十三條之規定，本件時效停止原因已達前述五年期間之四分之一，即一年三月以上，是時效停止原因視為消滅，故本件追訴權之時效迄至九十三年五月十四日業已完成。依照首開說明，爰不經言詞辯論，逕為諭知免訴之判決。四、台灣台北地方法院檢察署移送併辦之八十七年度偵字第一一八一一號被告涉犯過失致重傷罪部分，與本案係事實上同一案件，本院自得並予審理，附此敘明。據上論斷，應依刑事訴訟法第三百四十三條、第三百零二條第二款、第三百零七條，判決如主文。中華民國九十三年六月二十三日臺灣臺北地方法院刑事第七庭審判長法官梁耀鑌法官林欣蓉法官蕭清清右正本證明與原本無異。如不服本判決，應於判決送達後十日內，向本院提出上訴狀。書記官劉麗英中華民國九十三年六月二十五日",
  "characters": {
    "judges": [
      "梁耀鑌",
      "林欣蓉",
      "蕭清清"
    ],
    "prosecutors": [

    ],
    "lawyers": [

    ],
    "clerks": [
      "劉麗英"
    ],
    "plaintiffs": [

    ],
    "defendants": [
      "甲○○",
      "右列被告因過失傷害案件，經自訴人提起自訴，及台灣台北地方法院檢察署移送併辦",
      "（八十七年度偵字第一一八一一號），本院判決如左："
    ],
    "prosecutor_office": [

    ],
    "creditors": [

    ],
    "debtors": [

    ],
    "judicial_associate_officer": [

    ]
  },
  "adjudged_at": "2004-06-23",
  "created_at": "2016-02-06 09:43:05",
  "updated_at": "2016-02-06 09:43:05"
}