{
  "identify": "TPH-100-聲-217-20110128-1",
  "court": {
    "name": "臺灣高等法院",
    "code": "TPH"
  },
  "division": {
    "name": "刑事",
    "code": "M"
  },
  "year": 100,
  "word": "聲",
  "number": "217",
  "jcheck": "1",
  "reason": "保護管束",
  "content": "臺灣高等法院刑事裁定                  100年度聲字第217號\n聲  請  人  臺灣高等法院檢察署檢察官\n受  刑  人  趙國榮\n上列受刑人因詐欺罪案件，聲請人聲請付保護管束（100年度執\n聲付字第49號），本院裁定如下：\n    主  文\n趙國榮假釋中付保護管束。\n    理  由\n一、本件受刑人趙國榮因詐欺罪案件，經本院97年度上易字第24\n    59號判決判處有期徒刑10月確定，另犯偽造貨幣罪經臺灣士\n    林地方法院95年度訴字第741號判處有期徒刑2年緩刑3年，\n    緩刑期內並付保護管束，並經臺灣士林地方法院98年撤緩字\n    第14號撤銷緩刑確定，於民國98年6月9日入監執行。茲經法\n    務部於100年1月19日核准假釋出獄，此有該部矯正署民國10\n    0年1月19日，法授矯字第10000008081號函及所附假釋出獄\n    人交付保護管束名冊一份在卷可稽。\n二、依刑法第93條第2項規定，假釋出獄者，在假釋中付保護管\n    束，爰准如聲請人所請，裁定如主文。\n中    華    民    國   100    年    1     月    28    日\n                  刑事第二十三庭審判長法  官  童有德\n                                      法  官  劉方慈\n                                      法  官  陳祐治\n以上正本證明與原本無異。\n不得抗告。\n                                      書記官  張詠婷\n中    華    民    國   100    年    1     月    28    日",
  "structure": {
    "main": "趙國榮假釋中付保護管束。",
    "reason": "一、本件受刑人趙國榮因詐欺罪案件，經本院97年度上易字第24\n    59號判決判處有期徒刑10月確定，另犯偽造貨幣罪經臺灣士\n    林地方法院95年度訴字第741號判處有期徒刑2年緩刑3年，\n    緩刑期內並付保護管束，並經臺灣士林地方法院98年撤緩字\n    第14號撤銷緩刑確定，於民國98年6月9日入監執行。茲經法\n    務部於100年1月19日核准假釋出獄，此有該部矯正署民國10\n    0年1月19日，法授矯字第10000008081號函及所附假釋出獄\n    人交付保護管束名冊一份在卷可稽。\n二、依刑法第93條第2項規定，假釋出獄者，在假釋中付保護管\n    束，爰准如聲請人所請，裁定如主文。"
  },
  "search": "臺灣高等法院刑事裁定100年度聲字第217號聲請人臺灣高等法院檢察署檢察官受刑人趙國榮上列受刑人因詐欺罪案件，聲請人聲請付保護管束（100年度執聲付字第49號），本院裁定如下：主文趙國榮假釋中付保護管束。理由一、本件受刑人趙國榮因詐欺罪案件，經本院97年度上易字第2459號判決判處有期徒刑10月確定，另犯偽造貨幣罪經臺灣士林地方法院95年度訴字第741號判處有期徒刑2年緩刑3年，緩刑期內並付保護管束，並經臺灣士林地方法院98年撤緩字第14號撤銷緩刑確定，於民國98年6月9日入監執行。茲經法務部於100年1月19日核准假釋出獄，此有該部矯正署民國100年1月19日，法授矯字第10000008081號函及所附假釋出獄人交付保護管束名冊一份在卷可稽。二、依刑法第93條第2項規定，假釋出獄者，在假釋中付保護管束，爰准如聲請人所請，裁定如主文。中華民國100年1月28日刑事第二十三庭審判長法官童有德法官劉方慈法官陳祐治以上正本證明與原本無異。不得抗告。書記官張詠婷中華民國100年1月28日",
  "characters": {
    "judges": [
      "童有德",
      "劉方慈",
      "陳祐治"
    ],
    "prosecutors": [

    ],
    "lawyers": [

    ],
    "clerks": [
      "張詠婷"
    ],
    "plaintiffs": [

    ],
    "defendants": [

    ],
    "prosecutor_office": [
      "臺灣高等法院檢察署檢察官"
    ],
    "creditors": [

    ],
    "debtors": [

    ],
    "judicial_associate_officer": [

    ]
  },
  "adjudged_at": "2011-01-28",
  "created_at": "2016-02-13 05:01:12",
  "updated_at": "2016-02-13 05:01:12"
}