{
  "identify": "TYD-92-重附民-12-20040129-1",
  "court": {
    "name": "臺灣桃園地方法院",
    "code": "TYD"
  },
  "division": {
    "name": "刑事",
    "code": "M"
  },
  "year": 92,
  "word": "重附民",
  "number": "12",
  "jcheck": "1",
  "reason": "請求賠償損害",
  "content": "臺灣桃園地方法院刑事附帶民事訴訟判決            九十二年度重附民字第一二號\n    原      告  丙○○○試機有限公司\n    法定代理人  黃桂才\n    被      告  甲○○科技有限公司  設桃園縣八德市○○街四五號\n    被  告兼右\n    法定代理人  乙○○\n右列被告等因竊盜等案件（本院九十一年度易字第一六九三號），經原告提起附帶民\n事訴訟，請求損害賠償，本院判決如左：\n    主  文\n原告之訴駁回。\n    事  實\n甲、原告方面：原告之聲明及陳述均如附件起訴狀所載。\n乙、被告方面：被告未提出書狀亦未以言詞作任何聲明及陳述。\n    理  由\n一、按刑事訴訟諭知無罪、免訴或不受理之判決者，應以判決駁回原告之訴，刑事訴\n    訟法第五百零三條第一項前段定有明文。\n二、查本件被告乙○○所涉教唆竊盜、違犯著作權法等案件，已於民國九十三年一月\n    二十九日分經本院為無罪、不受理判決，依首揭法條之規定，本件原告所提附帶\n    民事訴訟自應予以駁回。\n三、依刑事訴訟法第五百零三條第一項前段，判決如主文。\n中      華      民      國      九十三     年     一      月    二十九  日\n                              臺灣桃園地方法院刑事第一庭\n                                  審判長法  官   吳爭奇\n                                        法  官   胡芷瑜\n                                        法  官   黃梅淑\n右正本證明與原本無異。\n如不服本判決，非對於刑事訴訟之判決有上訴時，不得上訴。應於判決送達後十日內\n向本院提出上訴狀( 應附繕本 )，上訴於\n臺灣高等法院。\n                                        書記官   孫立文\n中        華        民        國   九十三   年   一   月    三十    日\n",
  "structure": {
    "main": "原告之訴駁回。",
    "fact": "甲、原告方面：原告之聲明及陳述均如附件起訴狀所載。\n乙、被告方面：被告未提出書狀亦未以言詞作任何聲明及陳述。",
    "reason": "一、按刑事訴訟諭知無罪、免訴或不受理之判決者，應以判決駁回原告之訴，刑事訴\n    訟法第五百零三條第一項前段定有明文。\n二、查本件被告乙○○所涉教唆竊盜、違犯著作權法等案件，已於民國九十三年一月\n    二十九日分經本院為無罪、不受理判決，依首揭法條之規定，本件原告所提附帶\n    民事訴訟自應予以駁回。\n三、依刑事訴訟法第五百零三條第一項前段，判決如主文。\n中      華      民      國      九十三     年     一      月    二十九  日\n                              臺灣桃園地方法院刑事第一庭\n                                  審判長法  官   吳爭奇\n                                        法  官   胡芷瑜\n                                        法  官   黃梅淑\n右正本證明與原本無異。\n如不服本判決，非對於刑事訴訟之判決有上訴時，不得上訴。應於判決送達後十日內\n向本院提出上訴狀( 應附繕本 )，上訴於\n臺灣高等法院。\n                                        書記官   孫立文"
  },
  "search": "臺灣桃園地方法院刑事附帶民事訴訟判決九十二年度重附民字第一二號原告丙○○○試機有限公司法定代理人黃桂才被告甲○○科技有限公司設桃園縣八德市○○街四五號被告兼右法定代理人乙○○右列被告等因竊盜等案件（本院九十一年度易字第一六九三號），經原告提起附帶民事訴訟，請求損害賠償，本院判決如左：主文原告之訴駁回。事實甲、原告方面：原告之聲明及陳述均如附件起訴狀所載。乙、被告方面：被告未提出書狀亦未以言詞作任何聲明及陳述。理由一、按刑事訴訟諭知無罪、免訴或不受理之判決者，應以判決駁回原告之訴，刑事訴訟法第五百零三條第一項前段定有明文。二、查本件被告乙○○所涉教唆竊盜、違犯著作權法等案件，已於民國九十三年一月二十九日分經本院為無罪、不受理判決，依首揭法條之規定，本件原告所提附帶民事訴訟自應予以駁回。三、依刑事訴訟法第五百零三條第一項前段，判決如主文。中華民國九十三年一月二十九日臺灣桃園地方法院刑事第一庭審判長法官吳爭奇法官胡芷瑜法官黃梅淑右正本證明與原本無異。如不服本判決，非對於刑事訴訟之判決有上訴時，不得上訴。應於判決送達後十日內向本院提出上訴狀(應附繕本)，上訴於臺灣高等法院。書記官孫立文中華民國九十三年一月三十日",
  "characters": {
    "judges": [
      "吳爭奇",
      "胡芷瑜",
      "黃梅淑"
    ],
    "prosecutors": [

    ],
    "lawyers": [

    ],
    "clerks": [
      "孫立文"
    ],
    "plaintiffs": [
      "丙"
    ],
    "defendants": [
      "甲○○科技有限公司  設桃園縣八德市○○街四五號"
    ],
    "prosecutor_office": [

    ],
    "creditors": [

    ],
    "debtors": [

    ],
    "judicial_associate_officer": [

    ]
  },
  "adjudged_at": "2004-01-29",
  "created_at": "2016-02-06 06:00:53",
  "updated_at": "2016-02-06 06:00:53"
}