{
  "identify": "TPB-90-訴-5306-20020514-1",
  "court": {
    "name": "臺北高等行政法院",
    "code": "TPB"
  },
  "division": {
    "name": "行政",
    "code": "A"
  },
  "year": 90,
  "word": "訴",
  "number": "5306",
  "jcheck": "1",
  "reason": "戒嚴時期不當叛亂暨匪諜審判案件補償金",
  "content": "臺北高等行政法院裁定                              九十年度訴字第五三○六號\n    原      告  甲○\n    被      告  財團法人戒嚴時期不當叛亂暨匪諜審判案件補償基金會\n    代  表  人  乙○○（董事長）\n    訴訟代理人  張樹萱律師\n右當事人間因戒嚴時期不當叛亂暨匪諜審判案件補償金事件，原告不服行政院中華民\n國九十年七月十三日台九十訴字第○三九八六○號訴願決定，提起行政訴訟，本院裁\n定如左：\n    主  文\n原告之訴駁回。\n訴訟費用由原告負擔。\n    理  由\n一、按訴願之提起，應自行政處分達到或公告期滿之次日起三十日內為之。訴願之提\n    起，以原行政處分機關或受理訴願機關收受訴願書之日期為準。又提起訴願逾法\n    定期間者，應為不受理之決定，分別為訴願法第十四條第一項、第三項及第七十\n    七條第二款所明定。\n二、本件原告因戒嚴時期不當叛亂暨匪諜審判案件補償金事件，於九十年一月十七日\n    收受被告九十年一月十日（九○）基修法癸字第○三九九號函之處分，此有經原\n    告女兒張泰倫簽收之掛號郵件收件回執影本附原處分卷可稽。核計其提起訴願之\n    三十日法定不變期間，應自九十年一月十八日起算，因原告住台北市，毋庸扣除\n    在途期間，是迄至九十年二月十六日（星期五）即已屆滿。原告遲至九十年二月\n    十九日始提起訴願，此有被告蓋於訴願書上之收件日期章戳可按，是其訴願之提\n    起，顯已逾越首開法定不變期間，即屬於不合法。訴願決定就程序上予以駁回，\n    自無不合。原告復對之提起行政訴訟，並主張訴願之提起應以其於八十九年二月\n    十六日十五時掛號郵寄之日期為準，因與首揭訴願法第十四條第三項之規定不符\n    ，尚不足取，原告之訴難謂合法，應予駁回。其實體上之主張及陳述，已無審究\n    之必要，併此敘明。\n三、次按，依行政訴訟法第七條規定得合併之請求，以因合併提起之行政訴訟所生損\n    害賠償或其他財產上之給付為限（參照陳大法官計男所著「行政訴訟法釋論」第\n    二○五頁）。查本件原告起訴不合法，已如前述，則其合併提起之損害賠償之訴\n    ，依前開說明，自非法之所許，應併予駁回。\n四、依行政訴訟法第一百零七條第一項第十款、第一百零四條、民事訴訟法第九十五\n    條、第七十八條，裁定如主文。\n中    華    民    國    九十一      年      五        月      十四      日\n                               臺 北 高 等 行 政 法 院  第 六 庭\n                                           審 判 長 法  官  林樹埔\n                                                    法  官  闕銘富\n                                                    法  官  曹瑞卿\n右為正本係照原本作成。\n如不服本裁定，應於送達後十日內向本院提出抗告狀（須按他造人數附繕本）。\n中    華    民    國    九十一      年      五        月      十四      日\n                                                    書記官  方偉皓\n",
  "structure": {
    "main": "原告之訴駁回。\n訴訟費用由原告負擔。",
    "reason": "一、按訴願之提起，應自行政處分達到或公告期滿之次日起三十日內為之。訴願之提\n    起，以原行政處分機關或受理訴願機關收受訴願書之日期為準。又提起訴願逾法\n    定期間者，應為不受理之決定，分別為訴願法第十四條第一項、第三項及第七十\n    七條第二款所明定。\n二、本件原告因戒嚴時期不當叛亂暨匪諜審判案件補償金事件，於九十年一月十七日\n    收受被告九十年一月十日（九○）基修法癸字第○三九九號函之處分，此有經原\n    告女兒張泰倫簽收之掛號郵件收件回執影本附原處分卷可稽。核計其提起訴願之\n    三十日法定不變期間，應自九十年一月十八日起算，因原告住台北市，毋庸扣除\n    在途期間，是迄至九十年二月十六日（星期五）即已屆滿。原告遲至九十年二月\n    十九日始提起訴願，此有被告蓋於訴願書上之收件日期章戳可按，是其訴願之提\n    起，顯已逾越首開法定不變期間，即屬於不合法。訴願決定就程序上予以駁回，\n    自無不合。原告復對之提起行政訴訟，並主張訴願之提起應以其於八十九年二月\n    十六日十五時掛號郵寄之日期為準，因與首揭訴願法第十四條第三項之規定不符\n    ，尚不足取，原告之訴難謂合法，應予駁回。其實體上之主張及陳述，已無審究\n    之必要，併此敘明。\n三、次按，依行政訴訟法第七條規定得合併之請求，以因合併提起之行政訴訟所生損\n    害賠償或其他財產上之給付為限（參照陳大法官計男所著「行政訴訟法釋論」第\n    二○五頁）。查本件原告起訴不合法，已如前述，則其合併提起之損害賠償之訴\n    ，依前開說明，自非法之所許，應併予駁回。\n四、依行政訴訟法第一百零七條第一項第十款、第一百零四條、民事訴訟法第九十五\n    條、第七十八條，裁定如主文。"
  },
  "search": "臺北高等行政法院裁定九十年度訴字第五三○六號原告甲○被告財團法人戒嚴時期不當叛亂暨匪諜審判案件補償基金會代表人乙○○（董事長）訴訟代理人張樹萱律師右當事人間因戒嚴時期不當叛亂暨匪諜審判案件補償金事件，原告不服行政院中華民國九十年七月十三日台九十訴字第○三九八六○號訴願決定，提起行政訴訟，本院裁定如左：主文原告之訴駁回。訴訟費用由原告負擔。理由一、按訴願之提起，應自行政處分達到或公告期滿之次日起三十日內為之。訴願之提起，以原行政處分機關或受理訴願機關收受訴願書之日期為準。又提起訴願逾法定期間者，應為不受理之決定，分別為訴願法第十四條第一項、第三項及第七十七條第二款所明定。二、本件原告因戒嚴時期不當叛亂暨匪諜審判案件補償金事件，於九十年一月十七日收受被告九十年一月十日（九○）基修法癸字第○三九九號函之處分，此有經原告女兒張泰倫簽收之掛號郵件收件回執影本附原處分卷可稽。核計其提起訴願之三十日法定不變期間，應自九十年一月十八日起算，因原告住台北市，毋庸扣除在途期間，是迄至九十年二月十六日（星期五）即已屆滿。原告遲至九十年二月十九日始提起訴願，此有被告蓋於訴願書上之收件日期章戳可按，是其訴願之提起，顯已逾越首開法定不變期間，即屬於不合法。訴願決定就程序上予以駁回，自無不合。原告復對之提起行政訴訟，並主張訴願之提起應以其於八十九年二月十六日十五時掛號郵寄之日期為準，因與首揭訴願法第十四條第三項之規定不符，尚不足取，原告之訴難謂合法，應予駁回。其實體上之主張及陳述，已無審究之必要，併此敘明。三、次按，依行政訴訟法第七條規定得合併之請求，以因合併提起之行政訴訟所生損害賠償或其他財產上之給付為限（參照陳大法官計男所著「行政訴訟法釋論」第二○五頁）。查本件原告起訴不合法，已如前述，則其合併提起之損害賠償之訴，依前開說明，自非法之所許，應併予駁回。四、依行政訴訟法第一百零七條第一項第十款、第一百零四條、民事訴訟法第九十五條、第七十八條，裁定如主文。中華民國九十一年五月十四日臺北高等行政法院第六庭審判長法官林樹埔法官闕銘富法官曹瑞卿右為正本係照原本作成。如不服本裁定，應於送達後十日內向本院提出抗告狀（須按他造人數附繕本）。中華民國九十一年五月十四日書記官方偉皓",
  "characters": {
    "judges": [
      "林樹埔",
      "闕銘富",
      "曹瑞卿"
    ],
    "prosecutors": [

    ],
    "lawyers": [
      "張樹萱"
    ],
    "clerks": [
      "方偉皓"
    ],
    "plaintiffs": [
      "甲"
    ],
    "defendants": [
      "財團法人戒嚴時期不當叛亂暨匪諜審判案件補償基金會"
    ],
    "prosecutor_office": [

    ],
    "creditors": [

    ],
    "debtors": [

    ],
    "judicial_associate_officer": [

    ]
  },
  "adjudged_at": "2002-05-14",
  "created_at": "2016-02-04 12:48:50",
  "updated_at": "2016-02-04 12:48:50"
}