{
  "identify": "MLD-94-易-285-20050830-2",
  "court": {
    "name": "臺灣苗栗地方法院",
    "code": "MLD"
  },
  "division": {
    "name": "刑事",
    "code": "M"
  },
  "year": 94,
  "word": "易",
  "number": "285",
  "jcheck": "2",
  "reason": "竊盜",
  "content": "臺灣苗栗地方法院刑事判決             94年度易字第285號\n公  訴  人  臺灣苗栗地方法院檢察署檢察官\n被      告  甲○○\n上列被告因竊盜案件，經檢察官提起公訴（94年度偵字第525 號\n），本院依簡式審判程序，判決如下：\n    主  文\n甲○○攜帶兇器、踰越牆垣竊盜，累犯，處有期徒刑玖月。\n扣案之管鉗、老虎鉗、固定夾及螺絲起子各壹支，均沒收。\n    犯罪事實及理由\n一、本件犯罪事實及證據名稱，與檢察官起訴書之記載相同，茲\n    引用之（如附件）。\n二、應適用之法條：\n  (一)刑事訴訟法第273 條之1 第1 項、第299 條第1 項前段、第\n    310 條之2、第454 條第2 項。\n  (二)刑法第321 條第1 項第2 款、第3 款、第47條、第38條第1\n    項第2 款。\n三、如不服本件判決，自本判決送達之日起10日內，得向本院提\n    起上訴。\n本案經檢察官郭靜文到庭執行職務。\n中    華    民    國    94    年    8     月    30    日\n                  刑事第二庭    法  官  林燦都\n以上正本證明與原本無異。\n如不服本判決，應於送達後10日內向本院提出上訴狀（須附繕本\n），上訴於臺灣高等法院臺中分院。\n                                書記官  陳建分\n中    華    民    國    94    年    8     月    30    日\n附記論罪之法條全文：\n刑法第321條\n犯竊盜罪而有左列情形之一者，處 6 月以上、 5 年以下有期徒\n刑：\n一  於夜間侵入住宅或有人居住之建築物、船艦或隱匿其內而犯\n    之者。\n二  毀越門扇、牆垣或其他安全設備而犯之者。\n三  攜帶兇器而犯之者。\n四  結夥三人以上而犯之者。\n五  乘火災、水災或其他災害之際而犯之者。\n六  在車站或埠頭而犯之者。\n前項之未遂犯罰之。\n",
  "structure": {
    "main": "甲○○攜帶兇器、踰越牆垣竊盜，累犯，處有期徒刑玖月。\n扣案之管鉗、老虎鉗、固定夾及螺絲起子各壹支，均沒收。",
    "fact": "一、本件犯罪事實及證據名稱，與檢察官起訴書之記載相同，茲\n    引用之（如附件）。\n二、應適用之法條：\n  (一)刑事訴訟法第273 條之1 第1 項、第299 條第1 項前段、第\n    310 條之2、第454 條第2 項。\n  (二)刑法第321 條第1 項第2 款、第3 款、第47條、第38條第1\n    項第2 款。\n三、如不服本件判決，自本判決送達之日起10日內，得向本院提\n    起上訴。\n本案經檢察官郭靜文到庭執行職務。",
    "reason": "一、本件犯罪事實及證據名稱，與檢察官起訴書之記載相同，茲\n    引用之（如附件）。\n二、應適用之法條：\n  (一)刑事訴訟法第273 條之1 第1 項、第299 條第1 項前段、第\n    310 條之2、第454 條第2 項。\n  (二)刑法第321 條第1 項第2 款、第3 款、第47條、第38條第1\n    項第2 款。\n三、如不服本件判決，自本判決送達之日起10日內，得向本院提\n    起上訴。\n本案經檢察官郭靜文到庭執行職務。"
  },
  "search": "臺灣苗栗地方法院刑事判決94年度易字第285號公訴人臺灣苗栗地方法院檢察署檢察官被告甲○○上列被告因竊盜案件，經檢察官提起公訴（94年度偵字第525號），本院依簡式審判程序，判決如下：主文甲○○攜帶兇器、踰越牆垣竊盜，累犯，處有期徒刑玖月。扣案之管鉗、老虎鉗、固定夾及螺絲起子各壹支，均沒收。犯罪事實及理由一、本件犯罪事實及證據名稱，與檢察官起訴書之記載相同，茲引用之（如附件）。二、應適用之法條：(一)刑事訴訟法第273條之1第1項、第299條第1項前段、第310條之2、第454條第2項。(二)刑法第321條第1項第2款、第3款、第47條、第38條第1項第2款。三、如不服本件判決，自本判決送達之日起10日內，得向本院提起上訴。本案經檢察官郭靜文到庭執行職務。中華民國94年8月30日刑事第二庭法官林燦都以上正本證明與原本無異。如不服本判決，應於送達後10日內向本院提出上訴狀（須附繕本），上訴於臺灣高等法院臺中分院。書記官陳建分中華民國94年8月30日附記論罪之法條全文：刑法第321條犯竊盜罪而有左列情形之一者，處6月以上、5年以下有期徒刑：一於夜間侵入住宅或有人居住之建築物、船艦或隱匿其內而犯之者。二毀越門扇、牆垣或其他安全設備而犯之者。三攜帶兇器而犯之者。四結夥三人以上而犯之者。五乘火災、水災或其他災害之際而犯之者。六在車站或埠頭而犯之者。前項之未遂犯罰之。",
  "characters": {
    "judges": [
      "林燦都"
    ],
    "prosecutors": [
      "郭靜文"
    ],
    "lawyers": [

    ],
    "clerks": [
      "陳建分"
    ],
    "plaintiffs": [

    ],
    "defendants": [
      "甲○○"
    ],
    "prosecutor_office": [
      "臺灣苗栗地方法院檢察署檢察官"
    ],
    "creditors": [

    ],
    "debtors": [

    ],
    "judicial_associate_officer": [

    ]
  },
  "adjudged_at": "2005-08-30",
  "created_at": "2016-02-06 22:42:24",
  "updated_at": "2016-02-06 22:42:24"
}