{
  "identify": "SLD-94-交易-204-20050829-1",
  "court": {
    "name": "臺灣士林地方法院",
    "code": "SLD"
  },
  "division": {
    "name": "刑事",
    "code": "M"
  },
  "year": 94,
  "word": "交易",
  "number": "204",
  "jcheck": "1",
  "reason": "過失傷害",
  "content": "臺灣士林地方法院刑事判決\n公  訴  人  臺灣士林地方法院檢察署檢察官\n被      告  甲○○\n上列被告因過失傷害案件，經檢察官聲請簡易判決處刑（94年度\n偵字第3050號），本院認本件不宜以簡易判決處刑，改用通常訴\n訟程序審理，並判決如下：\n    主  文\n本件公訴不受理。\n    理  由\n一、聲請簡易判決處刑意旨略以：甲○○於民國93年9 月8 日中\n    午12時50分許，駕駛車牌號碼7915-FG 號自小客車，沿臺北\n    市○○區○○路由西向東方向行駛，行經該路與光明路之交\n    岔路口，欲左轉光明路而行經行人穿越道時，原應注意汽車\n    行近行人穿越道前，應減速慢行，遇有行人穿越時，無論有\n    無交通警察指揮或號誌指示，均應暫停讓行人優先通過，而\n    依當時情形又無不能注意之情事，竟疏未暫停讓行人先行，\n    不慎擦撞正欲穿越人行道之行人乙○○，致其受有左跟腱斷\n    裂之傷害，因認被告甲○○涉有刑法第284 條第1 項前段之\n    過失傷害罪嫌等語。\n二、按告訴乃論之罪，告訴人於第一審辯論終結前得撤回其告訴\n    ，又告訴經撤回者，應諭知不受理之判決，並得不經言詞辯\n    論為之，刑事訴訟法第238條第1項、第303條第3款、第307\n    條分別定有明文。\n三、查本件告訴人乙○○告訴被告甲○○過失傷害案件，聲請簡\n    易判決處刑書認被告係觸犯刑法第284 條第1 項前段之罪，\n    依同法第287 條前段之規定，須告訴乃論。茲據告訴人乙○\n    ○於94年8 月10日具狀撤回其告訴，有撤回告訴狀1 紙附卷\n    可稽，依照首開說明，本件爰不經言詞辯論，逕為不受理之\n    諭知。\n據上論斷，應依刑事訴訟法第452條、第303條第3款、第307條，\n判決如主文。\n中    華    民    國    94    年    8     月    29    日\n                  刑事第四庭審判長法  官    林秀鳳\n                                  法  官    高雅敏\n                                  法  官    許碧惠\n以上正本證明與原本無異。\n如不服本判決，應於判決送達後10日內，向本院提出上訴狀。\n                                  書記官    徐仁豐\n中    華    民    國    94    年    8     月    31    日\n",
  "structure": {
    "main": "本件公訴不受理。",
    "reason": "一、聲請簡易判決處刑意旨略以：甲○○於民國93年9 月8 日中\n    午12時50分許，駕駛車牌號碼7915-FG 號自小客車，沿臺北\n    市○○區○○路由西向東方向行駛，行經該路與光明路之交\n    岔路口，欲左轉光明路而行經行人穿越道時，原應注意汽車\n    行近行人穿越道前，應減速慢行，遇有行人穿越時，無論有\n    無交通警察指揮或號誌指示，均應暫停讓行人優先通過，而\n    依當時情形又無不能注意之情事，竟疏未暫停讓行人先行，\n    不慎擦撞正欲穿越人行道之行人乙○○，致其受有左跟腱斷\n    裂之傷害，因認被告甲○○涉有刑法第284 條第1 項前段之\n    過失傷害罪嫌等語。\n二、按告訴乃論之罪，告訴人於第一審辯論終結前得撤回其告訴\n    ，又告訴經撤回者，應諭知不受理之判決，並得不經言詞辯\n    論為之，刑事訴訟法第238條第1項、第303條第3款、第307\n    條分別定有明文。\n三、查本件告訴人乙○○告訴被告甲○○過失傷害案件，聲請簡\n    易判決處刑書認被告係觸犯刑法第284 條第1 項前段之罪，\n    依同法第287 條前段之規定，須告訴乃論。茲據告訴人乙○\n    ○於94年8 月10日具狀撤回其告訴，有撤回告訴狀1 紙附卷\n    可稽，依照首開說明，本件爰不經言詞辯論，逕為不受理之\n    諭知。\n據上論斷，應依刑事訴訟法第452條、第303條第3款、第307條，\n判決如主文。"
  },
  "search": "臺灣士林地方法院刑事判決公訴人臺灣士林地方法院檢察署檢察官被告甲○○上列被告因過失傷害案件，經檢察官聲請簡易判決處刑（94年度偵字第3050號），本院認本件不宜以簡易判決處刑，改用通常訴訟程序審理，並判決如下：主文本件公訴不受理。理由一、聲請簡易判決處刑意旨略以：甲○○於民國93年9月8日中午12時50分許，駕駛車牌號碼7915-FG號自小客車，沿臺北市○○區○○路由西向東方向行駛，行經該路與光明路之交岔路口，欲左轉光明路而行經行人穿越道時，原應注意汽車行近行人穿越道前，應減速慢行，遇有行人穿越時，無論有無交通警察指揮或號誌指示，均應暫停讓行人優先通過，而依當時情形又無不能注意之情事，竟疏未暫停讓行人先行，不慎擦撞正欲穿越人行道之行人乙○○，致其受有左跟腱斷裂之傷害，因認被告甲○○涉有刑法第284條第1項前段之過失傷害罪嫌等語。二、按告訴乃論之罪，告訴人於第一審辯論終結前得撤回其告訴，又告訴經撤回者，應諭知不受理之判決，並得不經言詞辯論為之，刑事訴訟法第238條第1項、第303條第3款、第307條分別定有明文。三、查本件告訴人乙○○告訴被告甲○○過失傷害案件，聲請簡易判決處刑書認被告係觸犯刑法第284條第1項前段之罪，依同法第287條前段之規定，須告訴乃論。茲據告訴人乙○○於94年8月10日具狀撤回其告訴，有撤回告訴狀1紙附卷可稽，依照首開說明，本件爰不經言詞辯論，逕為不受理之諭知。據上論斷，應依刑事訴訟法第452條、第303條第3款、第307條，判決如主文。中華民國94年8月29日刑事第四庭審判長法官林秀鳳法官高雅敏法官許碧惠以上正本證明與原本無異。如不服本判決，應於判決送達後10日內，向本院提出上訴狀。書記官徐仁豐中華民國94年8月31日",
  "characters": {
    "judges": [
      "林秀鳳",
      "高雅敏",
      "許碧惠"
    ],
    "prosecutors": [

    ],
    "lawyers": [

    ],
    "clerks": [
      "徐仁豐"
    ],
    "plaintiffs": [

    ],
    "defendants": [
      "甲○○"
    ],
    "prosecutor_office": [
      "臺灣士林地方法院檢察署檢察官"
    ],
    "creditors": [

    ],
    "debtors": [

    ],
    "judicial_associate_officer": [

    ]
  },
  "adjudged_at": "2005-08-29",
  "created_at": "2016-02-06 22:35:03",
  "updated_at": "2016-02-06 22:35:03"
}