{
  "identify": "TPD-94-訴-3267-20050830-2",
  "court": {
    "name": "臺灣臺北地方法院",
    "code": "TPD"
  },
  "division": {
    "name": "民事",
    "code": "V"
  },
  "year": 94,
  "word": "訴",
  "number": "3267",
  "jcheck": "2",
  "reason": "清償借款",
  "content": "臺灣臺北地方法院民事裁定              94年度訴字第3267號\n原      告  南山人壽保險股份有限公司\n法定代理人  謝仕榮\n被      告  甲○○\n                        之1\n            乙○○\n上列當事人間清償借款事件，本院裁定如下：\n    主  文\n原告之訴駁回。\n訴訟費用由原告負擔。\n    理  由\n一、按提起民事訴訟，應依民事訴訟法第77條之13規定繳納裁判\n    費，此為必須具備之程式。次按，依民事訴訟法第519條第1\n    項規定以支付命令之聲請視為起訴或聲請調解者，仍應依第\n    77條之13或第77條之20規定全額徵收裁判費或聲請費，同法\n    第77條之21亦定有明文。\n二、經查，本件原告因清償借款事件，曾聲請對被告等發支付命\n    令，惟被告等已於法定期間內聲明異議，應以支付命令之聲\n    請視為起訴。原告僅繳納部分裁判費，經本院於民國94年8\n    月12日裁定命原告於收受裁定後5日內補正，此項裁定已於9\n    4年8月18日送達原告，有送達回證在卷可稽，原告逾期迄今\n    仍未補正，有本院裁判費答詢表附卷足參，是原告起訴自非\n    合法，應予駁回。\n三、依民事訴訟法第249條第1項第6款、第95條、第78條，裁定\n    如主文。\n中    華    民    國    94    年    8     月    30    日\n                  民事第三庭    法  官  鄭佾瑩\n以上正本係照原本作成\n如不服本裁定應於送達後10日內向本院提出抗告狀，並繳納抗告\n費新臺幣1,000元\n中    華    民    國    94    年    8     月    30    日\n                                書記官  方美雲\n",
  "structure": {
    "main": "原告之訴駁回。\n訴訟費用由原告負擔。",
    "reason": "一、按提起民事訴訟，應依民事訴訟法第77條之13規定繳納裁判\n    費，此為必須具備之程式。次按，依民事訴訟法第519條第1\n    項規定以支付命令之聲請視為起訴或聲請調解者，仍應依第\n    77條之13或第77條之20規定全額徵收裁判費或聲請費，同法\n    第77條之21亦定有明文。\n二、經查，本件原告因清償借款事件，曾聲請對被告等發支付命\n    令，惟被告等已於法定期間內聲明異議，應以支付命令之聲\n    請視為起訴。原告僅繳納部分裁判費，經本院於民國94年8\n    月12日裁定命原告於收受裁定後5日內補正，此項裁定已於9\n    4年8月18日送達原告，有送達回證在卷可稽，原告逾期迄今\n    仍未補正，有本院裁判費答詢表附卷足參，是原告起訴自非\n    合法，應予駁回。\n三、依民事訴訟法第249條第1項第6款、第95條、第78條，裁定\n    如主文。"
  },
  "search": "臺灣臺北地方法院民事裁定94年度訴字第3267號原告南山人壽保險股份有限公司法定代理人謝仕榮被告甲○○之1乙○○上列當事人間清償借款事件，本院裁定如下：主文原告之訴駁回。訴訟費用由原告負擔。理由一、按提起民事訴訟，應依民事訴訟法第77條之13規定繳納裁判費，此為必須具備之程式。次按，依民事訴訟法第519條第1項規定以支付命令之聲請視為起訴或聲請調解者，仍應依第77條之13或第77條之20規定全額徵收裁判費或聲請費，同法第77條之21亦定有明文。二、經查，本件原告因清償借款事件，曾聲請對被告等發支付命令，惟被告等已於法定期間內聲明異議，應以支付命令之聲請視為起訴。原告僅繳納部分裁判費，經本院於民國94年8月12日裁定命原告於收受裁定後5日內補正，此項裁定已於94年8月18日送達原告，有送達回證在卷可稽，原告逾期迄今仍未補正，有本院裁判費答詢表附卷足參，是原告起訴自非合法，應予駁回。三、依民事訴訟法第249條第1項第6款、第95條、第78條，裁定如主文。中華民國94年8月30日民事第三庭法官鄭佾瑩以上正本係照原本作成如不服本裁定應於送達後10日內向本院提出抗告狀，並繳納抗告費新臺幣1,000元中華民國94年8月30日書記官方美雲",
  "characters": {
    "judges": [
      "鄭佾瑩"
    ],
    "prosecutors": [

    ],
    "lawyers": [

    ],
    "clerks": [
      "方美雲"
    ],
    "plaintiffs": [
      "南山人壽保險股份有限公司"
    ],
    "defendants": [
      "甲○○"
    ],
    "prosecutor_office": [

    ],
    "creditors": [

    ],
    "debtors": [

    ],
    "judicial_associate_officer": [

    ]
  },
  "adjudged_at": "2005-08-30",
  "created_at": "2016-02-06 22:41:04",
  "updated_at": "2016-02-06 22:41:04"
}