{
  "identify": "KSD-93-簡-6351-20050105-1",
  "court": {
    "name": "臺灣高雄地方法院",
    "code": "KSD"
  },
  "division": {
    "name": "刑事",
    "code": "M"
  },
  "year": 93,
  "word": "簡",
  "number": "6351",
  "jcheck": "1",
  "reason": "違反自來水法",
  "content": "臺灣高雄地方法院刑事簡易判決                    九十三年度簡字第六三五一號\n    聲  請  人  臺灣高雄地方法院檢察署檢察官\n    被      告  甲○○  男  七.\n右列被告因違反自來水法案件，經檢察官聲請以簡易判決處刑（九十三年度偵字第二二\n五五八號），本院判決如左：\n    主  文\n甲○○未經自來水事業許可，在自來水事業供水管線上取水，處罰金壹仟元，如易服\n勞役，以佰元折算壹日。扣案塑膠管壹支沒收之。\n    事實及理由\n一、本案犯罪事實及證據，均引用檢察官聲請簡易判決處刑書之記載（如附件）。惟\n    證據欄：有關「 (１)被告甲○○於警詢時及檢察官偵訊中之自白。」，應更正\n    記載為：「 (１)被告甲○○於警詢、偵查及本院調查時之自白。」\n二、核被告甲○○所為，係犯違反自來水法第九十八條第一款之竊水罪。又自來水法\n    之竊水罪與刑法第三百二十條第一項之竊盜罪，二罪間有法條競合之特別關係，\n    即自來水法第九十八條第一款之竊水罪即含有竊盜罪之本質，為刑法第三百二十\n    條第一項竊盜罪之特別規定，故依特別法優於普通法之法條競合關係，應依自來\n    水法第九十八條第一款規定論處，附此敘明。茲審酌被告現年七十五歲，一時失\n    慮，貪圖小利而竊取自來水，影響自來水公司之利益，其行為自應加以處罰，然\n    其犯後已坦承犯行，且竊取時間短暫，已賠償水費損失，又無前科，素行良好，\n    有臺灣高等法院被告全國前案紀錄表在卷可按等一切犯罪情狀，爰量處如文主所\n    示之刑，並諭知易服勞役之折算之標準，以示儆懲。扣案塑膠管一支，為被告所\n    有，且為供犯本罪所用之物，業據被告供承在卷，爰併依刑法第三十八條第一項\n    第二款規定宣告沒收。\n三、依刑事訴訟法第四百四十九條第一項前段、第三項、第四百五十四條第二項、第\n    四百五十條第一項，刑法第十一條前段、第四十二條第二項、第三十八條第一項\n    第二款，罰金罰鍰提高標準條例第一條前段、第二條，逕以簡易判決處如主文所\n    示之刑。\n如不服本判決，應於判決送達之日起十日內，向本院提出上訴狀。\n中      華      民      國      九十四      年      一      月    五    日\n                                    臺灣高雄地方法院高雄簡易庭\n                                        法  官  陳月雯\n右正本證明與原本無異。\n                                        書記官  林佳蓉\n中      華      民      國      九十四      年      一      月    六    日\n附錄本判決論罪科刑法條全文\n自來水法第九十八條第一款：\n有左列行為之一者為竊水，處五年以下有期徒刑、拘役或五百元以下罰金：\n  一  未經自來水事業許可，在自來水事業供水管線上取水者。\n",
  "structure": {
    "main": "甲○○未經自來水事業許可，在自來水事業供水管線上取水，處罰金壹仟元，如易服\n勞役，以佰元折算壹日。扣案塑膠管壹支沒收之。",
    "fact": "一、本案犯罪事實及證據，均引用檢察官聲請簡易判決處刑書之記載（如附件）。惟\n    證據欄：有關「 (１)被告甲○○於警詢時及檢察官偵訊中之自白。」，應更正\n    記載為：「 (１)被告甲○○於警詢、偵查及本院調查時之自白。」\n二、核被告甲○○所為，係犯違反自來水法第九十八條第一款之竊水罪。又自來水法\n    之竊水罪與刑法第三百二十條第一項之竊盜罪，二罪間有法條競合之特別關係，\n    即自來水法第九十八條第一款之竊水罪即含有竊盜罪之本質，為刑法第三百二十\n    條第一項竊盜罪之特別規定，故依特別法優於普通法之法條競合關係，應依自來\n    水法第九十八條第一款規定論處，附此敘明。茲審酌被告現年七十五歲，一時失\n    慮，貪圖小利而竊取自來水，影響自來水公司之利益，其行為自應加以處罰，然\n    其犯後已坦承犯行，且竊取時間短暫，已賠償水費損失，又無前科，素行良好，\n    有臺灣高等法院被告全國前案紀錄表在卷可按等一切犯罪情狀，爰量處如文主所\n    示之刑，並諭知易服勞役之折算之標準，以示儆懲。扣案塑膠管一支，為被告所\n    有，且為供犯本罪所用之物，業據被告供承在卷，爰併依刑法第三十八條第一項\n    第二款規定宣告沒收。\n三、依刑事訴訟法第四百四十九條第一項前段、第三項、第四百五十四條第二項、第\n    四百五十條第一項，刑法第十一條前段、第四十二條第二項、第三十八條第一項\n    第二款，罰金罰鍰提高標準條例第一條前段、第二條，逕以簡易判決處如主文所\n    示之刑。\n如不服本判決，應於判決送達之日起十日內，向本院提出上訴狀。",
    "reason": "一、本案犯罪事實及證據，均引用檢察官聲請簡易判決處刑書之記載（如附件）。惟\n    證據欄：有關「 (１)被告甲○○於警詢時及檢察官偵訊中之自白。」，應更正\n    記載為：「 (１)被告甲○○於警詢、偵查及本院調查時之自白。」\n二、核被告甲○○所為，係犯違反自來水法第九十八條第一款之竊水罪。又自來水法\n    之竊水罪與刑法第三百二十條第一項之竊盜罪，二罪間有法條競合之特別關係，\n    即自來水法第九十八條第一款之竊水罪即含有竊盜罪之本質，為刑法第三百二十\n    條第一項竊盜罪之特別規定，故依特別法優於普通法之法條競合關係，應依自來\n    水法第九十八條第一款規定論處，附此敘明。茲審酌被告現年七十五歲，一時失\n    慮，貪圖小利而竊取自來水，影響自來水公司之利益，其行為自應加以處罰，然\n    其犯後已坦承犯行，且竊取時間短暫，已賠償水費損失，又無前科，素行良好，\n    有臺灣高等法院被告全國前案紀錄表在卷可按等一切犯罪情狀，爰量處如文主所\n    示之刑，並諭知易服勞役之折算之標準，以示儆懲。扣案塑膠管一支，為被告所\n    有，且為供犯本罪所用之物，業據被告供承在卷，爰併依刑法第三十八條第一項\n    第二款規定宣告沒收。\n三、依刑事訴訟法第四百四十九條第一項前段、第三項、第四百五十四條第二項、第\n    四百五十條第一項，刑法第十一條前段、第四十二條第二項、第三十八條第一項\n    第二款，罰金罰鍰提高標準條例第一條前段、第二條，逕以簡易判決處如主文所\n    示之刑。\n如不服本判決，應於判決送達之日起十日內，向本院提出上訴狀。"
  },
  "search": "臺灣高雄地方法院刑事簡易判決九十三年度簡字第六三五一號聲請人臺灣高雄地方法院檢察署檢察官被告甲○○男七.右列被告因違反自來水法案件，經檢察官聲請以簡易判決處刑（九十三年度偵字第二二五五八號），本院判決如左：主文甲○○未經自來水事業許可，在自來水事業供水管線上取水，處罰金壹仟元，如易服勞役，以佰元折算壹日。扣案塑膠管壹支沒收之。事實及理由一、本案犯罪事實及證據，均引用檢察官聲請簡易判決處刑書之記載（如附件）。惟證據欄：有關「(１)被告甲○○於警詢時及檢察官偵訊中之自白。」，應更正記載為：「(１)被告甲○○於警詢、偵查及本院調查時之自白。」二、核被告甲○○所為，係犯違反自來水法第九十八條第一款之竊水罪。又自來水法之竊水罪與刑法第三百二十條第一項之竊盜罪，二罪間有法條競合之特別關係，即自來水法第九十八條第一款之竊水罪即含有竊盜罪之本質，為刑法第三百二十條第一項竊盜罪之特別規定，故依特別法優於普通法之法條競合關係，應依自來水法第九十八條第一款規定論處，附此敘明。茲審酌被告現年七十五歲，一時失慮，貪圖小利而竊取自來水，影響自來水公司之利益，其行為自應加以處罰，然其犯後已坦承犯行，且竊取時間短暫，已賠償水費損失，又無前科，素行良好，有臺灣高等法院被告全國前案紀錄表在卷可按等一切犯罪情狀，爰量處如文主所示之刑，並諭知易服勞役之折算之標準，以示儆懲。扣案塑膠管一支，為被告所有，且為供犯本罪所用之物，業據被告供承在卷，爰併依刑法第三十八條第一項第二款規定宣告沒收。三、依刑事訴訟法第四百四十九條第一項前段、第三項、第四百五十四條第二項、第四百五十條第一項，刑法第十一條前段、第四十二條第二項、第三十八條第一項第二款，罰金罰鍰提高標準條例第一條前段、第二條，逕以簡易判決處如主文所示之刑。如不服本判決，應於判決送達之日起十日內，向本院提出上訴狀。中華民國九十四年一月五日臺灣高雄地方法院高雄簡易庭法官陳月雯右正本證明與原本無異。書記官林佳蓉中華民國九十四年一月六日附錄本判決論罪科刑法條全文自來水法第九十八條第一款：有左列行為之一者為竊水，處五年以下有期徒刑、拘役或五百元以下罰金：一未經自來水事業許可，在自來水事業供水管線上取水者。",
  "characters": {
    "judges": [
      "陳月雯"
    ],
    "prosecutors": [

    ],
    "lawyers": [

    ],
    "clerks": [
      "林佳蓉"
    ],
    "plaintiffs": [

    ],
    "defendants": [
      "甲○○  男  七.",
      "右列被告因違反自來水法案件，經檢察官聲請以簡易判決處刑（九十三年度偵字第二二",
      "五五八號），本院判決如左："
    ],
    "prosecutor_office": [
      "臺灣高雄地方法院檢察署檢察官"
    ],
    "creditors": [

    ],
    "debtors": [

    ],
    "judicial_associate_officer": [

    ]
  },
  "adjudged_at": "2005-01-05",
  "created_at": "2016-02-07 01:33:02",
  "updated_at": "2016-02-07 01:33:02"
}