{
  "identify": "TYD-93-桃簡-1991-20050106-1",
  "court": {
    "name": "臺灣桃園地方法院",
    "code": "TYD"
  },
  "division": {
    "name": "刑事",
    "code": "M"
  },
  "year": 93,
  "word": "桃簡",
  "number": "1991",
  "jcheck": "1",
  "reason": "妨害公務",
  "content": "臺灣桃園地方法院刑事簡易判決        93年度桃簡字第1991號\n聲  請  人  臺灣桃園地方法院檢察署檢察官\n被      告  甲○○  男三十四歲.\n                      弄十一之.\n上列被告因妨害公務案件，經檢察官聲請以簡易判決處刑（93年\n度偵字第10929 號），本院判決如下：\n    主  文\n甲○○隱匿公務員委託第三人掌管之物品，處有期徒刑伍月，如\n易科罰金，以佰元折算壹日。\n    事  實及理  由\n一、本件犯罪事實及證據除犯罪時間更正為約九十二年一月十日\n    左右外，其餘引用檢察官聲請簡易判決處刑書之記載。\n二、被告雖否認搬離聲請書所載之代保管物品，辯稱伊不知情云\n    云。然查警方查獲被告之處所，乃係被告向江生財所租者，\n    租期自九十一年十一月十日起至九十二年十一月九日止，此\n    經被告及證人江生財供明，並有廠房租賃契約書影本在卷可\n    稽。上開處所既為被告所租，且警方係在九十二年一月四日\n    查獲，並將前述物品存放該處交被告保管；而台灣桃園地方\n    法院檢察署檢察官則係於九十二年十月二十二日前往同一處\n    所欲執行沒入前述物品之處分，上開物品自查扣起至檢察官\n    執行日止，尚在被告租用之期間內，被告對之仍有實際管領\n    力，該處除被告外，其他人未經被告之許可，自不得擅自進\n    出，第三人自不可能輕易將該些物品取走。又該些物品係專\n    供製造酒類之器具及包裝，對一般人而言，幾無交易之價值\n    ，故一般人無故拿取上開物品之可能性甚低。兼以上開物品\n    之體積甚大，非隨手可拿取藏匿之物，更不可能於被告不知\n    情之下搬離而去，縱有竊賊潛入上開處所，其所盜取者，亦\n    必為質輕價高之物，何至於連空酒瓶、包裝紙盒均悉取去？\n    亦見被告所辯之不可採。再者，被告於警詢稱伊於九十二年\n    八月初始知上開物品遭不明人士走，其既已於九十二年八月\n    初知遭他人搬走，何以不於當時即向警方或檢察官陳報，以\n    免其保管之責，何以必待檢察官到場執行，發覺其犯罪時，\n    始以不知情之語搪塞？綜上所論，足見本件警方查扣後交被\n    告代為保管之物，係由被告搬移而隱匿者，被告空言否認，\n    無非卸責之詞，不足採信，其犯行足堪認定。\n三、被告係犯刑法第一百三十八條、第一百三十九條之罪。與被\n    告一同前去載運上開物品者，不能證明其知情，故不論其為\n    共同正犯。被告一行為而犯上開二罪名，應從較重之刑法一\n    百三十八條之罪論處。被告於查扣後數日即搬離至他處而隱\n    匿之，視國家禁令於無物，其藐視公權力之心態實不可取，\n    本院審酌被告犯罪之手段、所隱匿物品之數量、價值及被告\n    犯後態度等一切情狀，量處如主文所示之刑，並諭知易科罰\n    金之折算標準。\n四、依刑事訴訟法第四四九條第一項前段、第四五四條第二項，\n    刑法第一三八條、第一三九條、第五十五條、第四十一條第\n    一項前段，罰金罰鍰提高標準條例第一條、第二條，逕以簡\n    易判決處如主文所示之刑。\n五、如不服本判決，得於判決書送達之翌日起十日內，以書狀敘\n    述理由，向本庭提出上訴。\n中    華    民    國  九十四  年    一    月    六    日\n                            法  官  林明洲\n以上正本證明與原本無異。\n                            書記官  黃泰能\n中    華    民    國    94    年    1     月    6     日\n本案論罪科刑主要法條：\n中華民國刑法第138條\n(妨害職務上掌管之文書物品罪)\n毀棄、損壞或隱匿公務員職務上掌管或委託第三人掌管之文書、\n圖畫、物品，或致令不堪用者，處五年以下有期徒刑。\n中華民國刑法第139條\n(污損封印、查封標示或違背其效力罪)\n損壞、除去或污穢公務員所施之封印或查封之標示，或為違背其\n效力之行為者，處一年以下有期徒刑、拘役或三百元以下罰金。\n",
  "structure": {
    "main": "甲○○隱匿公務員委託第三人掌管之物品，處有期徒刑伍月，如\n易科罰金，以佰元折算壹日。",
    "fact": "一、本件犯罪事實及證據除犯罪時間更正為約九十二年一月十日\n    左右外，其餘引用檢察官聲請簡易判決處刑書之記載。\n二、被告雖否認搬離聲請書所載之代保管物品，辯稱伊不知情云\n    云。然查警方查獲被告之處所，乃係被告向江生財所租者，\n    租期自九十一年十一月十日起至九十二年十一月九日止，此\n    經被告及證人江生財供明，並有廠房租賃契約書影本在卷可\n    稽。上開處所既為被告所租，且警方係在九十二年一月四日\n    查獲，並將前述物品存放該處交被告保管；而台灣桃園地方\n    法院檢察署檢察官則係於九十二年十月二十二日前往同一處\n    所欲執行沒入前述物品之處分，上開物品自查扣起至檢察官\n    執行日止，尚在被告租用之期間內，被告對之仍有實際管領\n    力，該處除被告外，其他人未經被告之許可，自不得擅自進\n    出，第三人自不可能輕易將該些物品取走。又該些物品係專\n    供製造酒類之器具及包裝，對一般人而言，幾無交易之價值\n    ，故一般人無故拿取上開物品之可能性甚低。兼以上開物品\n    之體積甚大，非隨手可拿取藏匿之物，更不可能於被告不知\n    情之下搬離而去，縱有竊賊潛入上開處所，其所盜取者，亦\n    必為質輕價高之物，何至於連空酒瓶、包裝紙盒均悉取去？\n    亦見被告所辯之不可採。再者，被告於警詢稱伊於九十二年\n    八月初始知上開物品遭不明人士走，其既已於九十二年八月\n    初知遭他人搬走，何以不於當時即向警方或檢察官陳報，以\n    免其保管之責，何以必待檢察官到場執行，發覺其犯罪時，\n    始以不知情之語搪塞？綜上所論，足見本件警方查扣後交被\n    告代為保管之物，係由被告搬移而隱匿者，被告空言否認，\n    無非卸責之詞，不足採信，其犯行足堪認定。\n三、被告係犯刑法第一百三十八條、第一百三十九條之罪。與被\n    告一同前去載運上開物品者，不能證明其知情，故不論其為\n    共同正犯。被告一行為而犯上開二罪名，應從較重之刑法一\n    百三十八條之罪論處。被告於查扣後數日即搬離至他處而隱\n    匿之，視國家禁令於無物，其藐視公權力之心態實不可取，\n    本院審酌被告犯罪之手段、所隱匿物品之數量、價值及被告\n    犯後態度等一切情狀，量處如主文所示之刑，並諭知易科罰\n    金之折算標準。\n四、依刑事訴訟法第四四九條第一項前段、第四五四條第二項，\n    刑法第一三八條、第一三九條、第五十五條、第四十一條第\n    一項前段，罰金罰鍰提高標準條例第一條、第二條，逕以簡\n    易判決處如主文所示之刑。\n五、如不服本判決，得於判決書送達之翌日起十日內，以書狀敘\n    述理由，向本庭提出上訴。",
    "reason": "一、本件犯罪事實及證據除犯罪時間更正為約九十二年一月十日\n    左右外，其餘引用檢察官聲請簡易判決處刑書之記載。\n二、被告雖否認搬離聲請書所載之代保管物品，辯稱伊不知情云\n    云。然查警方查獲被告之處所，乃係被告向江生財所租者，\n    租期自九十一年十一月十日起至九十二年十一月九日止，此\n    經被告及證人江生財供明，並有廠房租賃契約書影本在卷可\n    稽。上開處所既為被告所租，且警方係在九十二年一月四日\n    查獲，並將前述物品存放該處交被告保管；而台灣桃園地方\n    法院檢察署檢察官則係於九十二年十月二十二日前往同一處\n    所欲執行沒入前述物品之處分，上開物品自查扣起至檢察官\n    執行日止，尚在被告租用之期間內，被告對之仍有實際管領\n    力，該處除被告外，其他人未經被告之許可，自不得擅自進\n    出，第三人自不可能輕易將該些物品取走。又該些物品係專\n    供製造酒類之器具及包裝，對一般人而言，幾無交易之價值\n    ，故一般人無故拿取上開物品之可能性甚低。兼以上開物品\n    之體積甚大，非隨手可拿取藏匿之物，更不可能於被告不知\n    情之下搬離而去，縱有竊賊潛入上開處所，其所盜取者，亦\n    必為質輕價高之物，何至於連空酒瓶、包裝紙盒均悉取去？\n    亦見被告所辯之不可採。再者，被告於警詢稱伊於九十二年\n    八月初始知上開物品遭不明人士走，其既已於九十二年八月\n    初知遭他人搬走，何以不於當時即向警方或檢察官陳報，以\n    免其保管之責，何以必待檢察官到場執行，發覺其犯罪時，\n    始以不知情之語搪塞？綜上所論，足見本件警方查扣後交被\n    告代為保管之物，係由被告搬移而隱匿者，被告空言否認，\n    無非卸責之詞，不足採信，其犯行足堪認定。\n三、被告係犯刑法第一百三十八條、第一百三十九條之罪。與被\n    告一同前去載運上開物品者，不能證明其知情，故不論其為\n    共同正犯。被告一行為而犯上開二罪名，應從較重之刑法一\n    百三十八條之罪論處。被告於查扣後數日即搬離至他處而隱\n    匿之，視國家禁令於無物，其藐視公權力之心態實不可取，\n    本院審酌被告犯罪之手段、所隱匿物品之數量、價值及被告\n    犯後態度等一切情狀，量處如主文所示之刑，並諭知易科罰\n    金之折算標準。\n四、依刑事訴訟法第四四九條第一項前段、第四五四條第二項，\n    刑法第一三八條、第一三九條、第五十五條、第四十一條第\n    一項前段，罰金罰鍰提高標準條例第一條、第二條，逕以簡\n    易判決處如主文所示之刑。\n五、如不服本判決，得於判決書送達之翌日起十日內，以書狀敘\n    述理由，向本庭提出上訴。"
  },
  "search": "臺灣桃園地方法院刑事簡易判決93年度桃簡字第1991號聲請人臺灣桃園地方法院檢察署檢察官被告甲○○男三十四歲.弄十一之.上列被告因妨害公務案件，經檢察官聲請以簡易判決處刑（93年度偵字第10929號），本院判決如下：主文甲○○隱匿公務員委託第三人掌管之物品，處有期徒刑伍月，如易科罰金，以佰元折算壹日。事實及理由一、本件犯罪事實及證據除犯罪時間更正為約九十二年一月十日左右外，其餘引用檢察官聲請簡易判決處刑書之記載。二、被告雖否認搬離聲請書所載之代保管物品，辯稱伊不知情云云。然查警方查獲被告之處所，乃係被告向江生財所租者，租期自九十一年十一月十日起至九十二年十一月九日止，此經被告及證人江生財供明，並有廠房租賃契約書影本在卷可稽。上開處所既為被告所租，且警方係在九十二年一月四日查獲，並將前述物品存放該處交被告保管；而台灣桃園地方法院檢察署檢察官則係於九十二年十月二十二日前往同一處所欲執行沒入前述物品之處分，上開物品自查扣起至檢察官執行日止，尚在被告租用之期間內，被告對之仍有實際管領力，該處除被告外，其他人未經被告之許可，自不得擅自進出，第三人自不可能輕易將該些物品取走。又該些物品係專供製造酒類之器具及包裝，對一般人而言，幾無交易之價值，故一般人無故拿取上開物品之可能性甚低。兼以上開物品之體積甚大，非隨手可拿取藏匿之物，更不可能於被告不知情之下搬離而去，縱有竊賊潛入上開處所，其所盜取者，亦必為質輕價高之物，何至於連空酒瓶、包裝紙盒均悉取去？亦見被告所辯之不可採。再者，被告於警詢稱伊於九十二年八月初始知上開物品遭不明人士走，其既已於九十二年八月初知遭他人搬走，何以不於當時即向警方或檢察官陳報，以免其保管之責，何以必待檢察官到場執行，發覺其犯罪時，始以不知情之語搪塞？綜上所論，足見本件警方查扣後交被告代為保管之物，係由被告搬移而隱匿者，被告空言否認，無非卸責之詞，不足採信，其犯行足堪認定。三、被告係犯刑法第一百三十八條、第一百三十九條之罪。與被告一同前去載運上開物品者，不能證明其知情，故不論其為共同正犯。被告一行為而犯上開二罪名，應從較重之刑法一百三十八條之罪論處。被告於查扣後數日即搬離至他處而隱匿之，視國家禁令於無物，其藐視公權力之心態實不可取，本院審酌被告犯罪之手段、所隱匿物品之數量、價值及被告犯後態度等一切情狀，量處如主文所示之刑，並諭知易科罰金之折算標準。四、依刑事訴訟法第四四九條第一項前段、第四五四條第二項，刑法第一三八條、第一三九條、第五十五條、第四十一條第一項前段，罰金罰鍰提高標準條例第一條、第二條，逕以簡易判決處如主文所示之刑。五、如不服本判決，得於判決書送達之翌日起十日內，以書狀敘述理由，向本庭提出上訴。中華民國九十四年一月六日法官林明洲以上正本證明與原本無異。書記官黃泰能中華民國94年1月6日本案論罪科刑主要法條：中華民國刑法第138條(妨害職務上掌管之文書物品罪)毀棄、損壞或隱匿公務員職務上掌管或委託第三人掌管之文書、圖畫、物品，或致令不堪用者，處五年以下有期徒刑。中華民國刑法第139條(污損封印、查封標示或違背其效力罪)損壞、除去或污穢公務員所施之封印或查封之標示，或為違背其效力之行為者，處一年以下有期徒刑、拘役或三百元以下罰金。",
  "characters": {
    "judges": [
      "林明洲"
    ],
    "prosecutors": [

    ],
    "lawyers": [

    ],
    "clerks": [
      "黃泰能"
    ],
    "plaintiffs": [

    ],
    "defendants": [
      "甲○○  男三十四歲."
    ],
    "prosecutor_office": [
      "臺灣桃園地方法院檢察署檢察官"
    ],
    "creditors": [

    ],
    "debtors": [

    ],
    "judicial_associate_officer": [

    ]
  },
  "adjudged_at": "2005-01-06",
  "created_at": "2016-02-07 01:31:53",
  "updated_at": "2016-02-07 01:31:53"
}