{
  "identify": "KSD-99-簡上-431-20110308-1",
  "court": {
    "name": "臺灣高雄地方法院",
    "code": "KSD"
  },
  "division": {
    "name": "刑事",
    "code": "M"
  },
  "year": 99,
  "word": "簡上",
  "number": "431",
  "jcheck": "1",
  "reason": "賭博",
  "content": "臺灣高雄地方法院刑事判決             99年度簡上字第431號\n上  訴  人\n即  被  告  蔡宗煙\n            涂秀青\n上二人共同\n選任辯護人  李慶榮律師\n上  訴  人\n即  被  告  邱怡仁\n            王朝弘\n上列上訴人因賭博案件，不服本院中華民國99年7月30日98年度\n審簡字第19號第一審刑事簡易判決（聲請簡易判決處刑案號：\n臺灣高雄地方法院檢察署97年度偵字第17344號），提起上訴，\n本院管轄第二審之合議庭認不得以簡易判決處刑，改依通常程序\n審理，並自為第一審判決如下：\n    主  文\n原判決撤銷。\n蔡宗煙、涂秀青、邱怡仁、王朝弘均無罪。\n    理  由\n甲、證據能力之審酌：\n    被告以外之人於審判外之言詞或書面陳述，除法律有規定者\n    外，不得作為證據；被告以外之人於審判外之陳述，雖不符\n    刑事訴訟法第159 條之1 至之4 之規定，然經當事人於審判\n    程序同意作為證據，法院審酌該言詞陳述或書面陳述作成時\n    之情況，認為適當者，亦得為證據，刑事訴訟法第159 條之\n    5 第1 項定有明文。本判決後開引用具有傳聞證據性質之證\n    據資料，已經檢察官、上訴人即被告蔡宗煙、涂秀青及其辯\n    護人、上訴人即被告邱怡仁、王朝弘於審理期日同意為證據\n    使用，是其縱無刑事訴訟法第159條之1至第159條之4或其他\n    傳聞法則例外之情形，亦經本院審酌該證據作成之情況，既\n    無違法取得情事，復無證明力明顯過低等情形，以得供做法\n    院判斷事實之依據為適當，認為均有證據能力，自得作為本\n    案證據之用。\n乙、實體部分：\n一、聲請簡易判決處刑意旨略以：被告蔡宗煙向高雄市政府申請\n    領有電子遊戲場業營利事業登記證，自民國95年4月20日起\n    ，在高雄市○○區○○路268號公眾得出入之「金明星遊藝\n    場」內，擺設如附表一所示之「樂透大亨」等電子遊戲機台\n    共39  台之賭博性電玩機具，供人把玩，與不特定之客人賭\n    博財物；復自不詳時間起，以月薪新臺幣（下同）1萬8,000\n    元之代價，僱用被告涂秀青在該遊藝場內擔任店員，另自不\n    詳時間起，以不詳月薪，僱用被告邱怡仁（綽號「阿仁」）\n    擔任該遊藝場車手，渠等共同基於在公眾得出入之場所賭博\n    財物之犯意聯絡，由被告涂秀青在場負責開分、洗分工作，\n    賭博方式係由不特定之賭客，先交付現金予被告涂秀青後，\n    任選如附表一所示之電子遊戲機台，由被告涂秀青依1：1、\n    1 ：5或1：50之比例開分後，再押注分數與機器對賭，如有\n    押中，可得倍數不等之分數，如未押中，則由電子遊戲機台\n    將賭客所押注之分數沒入，藉此射悻之賭博方式計算輸贏，\n    待賭客打玩完畢後，再由被告涂秀青為其洗分，以1分兌換\n    現金1元之比例，由被告涂秀青告知賭客至該遊藝場外某處\n    等候，並通知被告邱怡仁前往指定地點，將現金交付賭客，\n    據此與不特定之賭客賭博財物。適於97年5月6日15時30分許\n    ，有被告即賭客王朝弘至該遊藝場把玩電子遊戲機台「樂透\n    大亨」水果盤，於同日16時10分許，被告王朝弘要求被告涂\n    秀青洗分並換取現金3,600元，被告涂秀青即詢問被告王朝\n    弘所騎乘機車之車號，並告知被告王朝弘至高雄市○○區○\n    ○路與民壯路口，綽號「阿仁」之男子會交付現金，被告王\n    朝弘旋騎乘車牌號碼HR8－177號機車前往指定地點向被告邱\n    怡仁領取3,600元後，騎乘上開機車離去，嗣為警持本院核\n    發之搜索票，於同日16時25分許，在高雄市○○○路「人形\n    町日本料理店」前查獲，並在被告王朝弘身上扣得賭資\n    3,600 元；警方復於同日20時10分許，至上開遊藝場執行搜\n    索而查獲，並扣得如附表一所示之賭博性電子遊戲機台39台\n    （含IC  板47塊）及如附表二所示之物，因認被告蔡宗煙、\n    涂秀青、邱怡仁及王朝弘，均涉有刑法第266條第1項之賭博\n    罪嫌。\n二、按犯罪事實應依證據認定之，無證據不得認定犯罪事實；不\n    能證明被告犯罪者，應諭知無罪之判決，刑事訴訟法第154\n    條第2 項、第301 第1 項分別定有明文。又檢察官對於起訴\n    之犯罪事實，應負提出證據及說服之實質舉證責任，倘其所\n    提出之證據，不足為被告有罪之積極證明，或其指出證明之\n    方法，無從說服法院以形成被告有罪之心證，基於無罪推定\n    之原則，自應為被告無罪判決之諭知（最高法院92年台上字\n    第128號判例意旨參照）。檢察官認被告蔡宗煙、涂秀青、\n    邱怡仁及王朝弘涉有賭博罪嫌，無非以被告王朝弘警詢陳述\n    、員警職務報告、扣押筆錄、扣押物品目錄表、高雄市政府\n    警察局三民第二分局臨檢現場紀錄表、保管條、金明星遊藝\n    場暨娟檳榔攤平面地點及兌換賭資路線圖、金明星遊藝場機\n    台擺設及娟檳榔攤有關位置圖等、現場照片52張在卷足憑，\n    及被告王朝弘身上扣得3,600元、扣案如附表一所示之電子\n    遊戲機台共39台（含IC板47塊）；如附表二所示之物為其論\n    據。\n三、訊據告蔡宗煙、涂秀青、邱怡仁及王朝弘固坦承被告王朝弘\n    於97年5月6日15時30分許，至金明星遊藝場把玩電子遊戲機\n    臺「樂透大亨」水果盤，於同日16時10分許，經被告涂秀青\n    告知至高雄市○○區○○路與民壯路口，綽號「阿仁」之男\n    子會交付現金，被告王朝弘旋騎乘機車前往指定地點向邱怡\n    仁領取3,600元之事實，惟均堅詞否認賭博犯行，(一)被告蔡\n    宗煙辯稱：我所經營金明星遊藝場，沒有洗分兌換現金等語\n    ；(二)被告涂秀青辯稱：我沒有與王朝弘賭博財物，我交付王\n    朝弘3,600元並非賭金，是王朝弘進入店內交現金5,000元給\n    我，後來王朝弘只打1,400元，所以我就返還王朝弘3,600元\n    ，我怕新客人會誤會店裡面有在洗分、換現金，剛好邱怡仁\n    說他要離開，我就拜託他將3,600元還給王朝弘等語；(三)被\n    告邱怡仁辯稱：我是去金明星遊藝場把玩電玩，不是該店員\n    工，我剛要離開，順便幫涂秀青拿錢給王朝弘等語；(四)被告\n    王朝弘辯稱：我拿5,000元寄放於店員涂秀青，先以1,000元\n    開500分，之後陸陸續續開分直到我要離開，我就要求店員\n    涂秀青將我寄放所剩本金3,600元還我，涂秀青告訴我阿仁\n    會到覺民及民壯路口還我錢，我到該路口等阿仁，隨後阿仁\n    騎車到後，問我欠多少錢，我說3,600元，阿仁就拿3,600元\n    給我等語，經查：\n(一)檢察官以被告王朝弘首次警詢坦承有兌換現金等情，認為案\n    重初供，應為可採等語，惟被告王朝弘於本院審理時及檢察\n    官訊問時均堅稱：第1次警詢過程中，我本來不同意夜間訊\n    問，警員說我承認的話就可以離開，所以我才同意繼續訊問\n    ，但是訊問完警員沒有放我走，我一直待到翌日凌晨4時許\n    才離開警局等語，觀諸被告王朝弘97年5月6日警詢筆錄記載\n    過程，起初被告王朝弘未坦承自己以把玩機台所得積分兌換\n    現金乙事，並稱被告王怡仁所交付3,600元，店員返還其所\n    寄放之本金等語，中途經警詢問：「現在為18時25分，是否\n    同意夜間詢問」，王朝弘本表明不同意，警再追問：「為何\n    不同意夜間詢問」，王朝弘稱因為要去安親班載小孩，嗣表\n    示同意夜間詢問，此時警再詢問如何兌換賭資時，被告王朝\n    弘始改稱自己有兌換現金，係由店員跟伊約好地點，叫車手\n    至指定地點換取我所贏得的賭資等語，是被告王朝弘供詞轉\n    折，已有啟人疑竇之處，再參以被告王朝弘改稱有兌換現金\n    後，其供稱：「寄分卡1分可以兌換新臺幣1元；寄分卡可以\n    適用於打玩遊藝場所陳列各類機台；各類機台開分比例不同\n    ，如水果盤係1：50，即新臺幣1元可以開50分把玩機臺，麻\n    將機台係1：1，火車機台係1：5」等語，衡情，設若部分機\n    臺係以新臺幣1元開5分或50分把玩，何以兌換現金時，卻均\n    可以以1分兌換新臺幣1元，如此豈不形成顧客以新臺幣1元\n    開5分或50分把玩機臺，卻可故意不把玩機臺，而以5分或50\n    分的積分兌換新臺幣5元或50元之不合理現象，足認其供稱\n    兌換現金之比例，顯與常理不合，再參以被告王朝弘於翌日\n    凌晨3時40分所製作第2次警詢中，則完全否認有兌換現金情\n    事。是本件從被告王朝弘首次警詢原否認兌換現金，後改稱\n    有兌換現金之轉折，且所供兌換現金比例，顯與常理不合，\n    嗣於翌日深夜第2次警詢又改稱沒有兌換現金等過程觀之，\n    已不能排除被告王朝弘於首次警詢中，坦承自己有兌換現金\n    乙事，係為使自己可以提早離開警局，而為與事實不符之供\n    述，嗣因不能如願提早離開，而在翌日凌晨第2次警詢則否\n    認有兌換現金之可能，如此檢察官是否能以案重初供為由，\n    而以被告王朝弘首次警詢所稱內容，據認被告等人賭博犯行\n    ，已屬有疑。\n(二)再者，檢察官以被告涂秀青稱：「我怕新客人會誤會店裡面\n    有在洗分、換現金，剛好邱怡仁說他要離開，我就拜託他將\n    3,600元還給王朝弘；我認識（邱怡仁），不太熟悉」；被\n    告邱怡仁則稱：「涂秀青告訴我被告王朝弘旁邊坐1個類似\n    警察的人，怕別人懷疑，所以才要我這樣做；之前見過王朝\n    弘1、2次面」，而認為被告邱怡仁僅見過王朝弘1、2次，被\n    告涂秀青卻將要交付王朝弘賭金，委託不熟識之被告邱怡仁\n    代為交付，被告涂秀青難道不擔心該筆款項遭被告邱怡仁侵\n    吞而求償無門等語，固屬有見，然此充其量僅能證明被告涂\n    秀青，就委託被告邱怡仁轉交現金予被告王朝弘乙事，或有\n    思慮不周，或處事不夠謹慎之處，然尚不足直接證明被告涂\n    秀青交付王朝弘3,600元即為賭金。再者，被告涂秀青為避\n    免其他客人誤會，往後紛紛要求以積分兌換現金，徒增困擾\n    ，因而不欲將被告王朝弘所寄放之本金，於店內返還予被告\n    王朝弘，此部分與一般常情並無明顯違悖之處，是檢察官以\n    上所舉證據，尚不足證明被告涂秀青交付王朝弘之3,600元\n    ，即為賭資。\n(三)又檢察官以證人即查獲員警陳榮顯偵訊結證：「我們發現客\n    人到店內贏了分數後，到櫃檯跟店員講要洗分，就是要換現\n    金，店員會聯絡車手，要車手在店外某路口等待客人換現金\n    ，然後店員會告訴客人前往該地點，等客人到之後，車手會\n    先跟客人稍微聊一下，再要客人到其他地方，再將現金交給\n    客人」等語(偵卷第118頁、第119頁)，認被告蔡宗煙、涂秀\n    青及邱怡仁涉嫌賭博犯行。惟證人陳榮顯於本院審理時證稱\n    ：「本件係96年底開始調查，我們跟監是很遠的觀看，所以\n    沒有辦法看到現金交易，是依據經驗大膽假設後，再聲請搜\n    索票進行查證，真正確認有現金交易的就是查獲的那一次」\n    等語(本院簡上卷第74頁)，從而，證人陳榮顯偵訊中所述兌\n    換現金乙情，並非其親自見聞，而係依其經驗假設而得，且\n    警方從96年底開始進行調查跟監乙情，並無相關證據在卷可\n    佐，如此自不能遽以認定被告蔡宗煙、涂秀青及邱怡仁，自\n    95年4月20日起至97年5月6日止，長達2年之時間，反覆在金\n    明星遊藝場與不特定人賭博財物。\n(四)末以，本件被告蔡宗煙所經營之金明星遊藝場，領有營利事\n    業登記證，有高雄市政府高市府建二商字第81865095號營利\n    事務登記證1紙在卷可憑(偵卷第70頁) ，是其遊藝場內所擺\n    放之機臺，並非賭博性電玩機具，除非經營者與顧客利用該\n    機具射倖性所得積分，予以兌換財物，籍此賭博財物，始可\n    以賭博罪相繩，然以上證據，均不足證明被告王朝弘於97年\n    5  月6日查獲當日有以所得積分兌換財物乙事，且就被告王\n    朝弘該次以多少積分及比例兌換現金3,600元乙事，亦未載\n    明，而員警自96年底才開始本件調查跟監乙情，並無相關卷\n    證可資佐證，何以檢察官認被告蔡宗煙、涂秀青及邱怡仁係\n    自95年4月20日起開始反覆為賭博犯行，且員警自承其偵訊\n    中所述兌換現金乙情，係依其經驗假設而得，如此實不足證\n    明被告蔡宗煙、涂秀青及邱怡仁長達2年時間，反覆將顧客\n    把玩機臺所得積分，予以兌換現金之賭博犯行。從而，檢察\n    官所舉證據，既不能證明被告蔡宗煙、涂秀青、邱怡仁及王\n    朝弘等人有何兌換現金之事實，即與賭博罪之構成要件不符\n    ，應為無罪諭知。原審判決就全部被告予以論科，尚有未洽\n    ，被告蔡宗煙、涂秀青、邱怡仁及王朝弘上訴，為有理由，\n    本院自應就原判決予以撤銷改判為被告蔡宗煙、涂秀青、邱\n    怡仁及王朝弘均無罪之諭知。\n四、末按法院得為簡易判決處刑者，以所科之刑係宣告緩刑、得\n    易科罰金之有期徒刑及拘役或罰金為限；於檢察官聲請以簡\n    易判決處刑之案件，經法院認應為無罪判決之諭知者，應適\n    用通常程序審判之，刑事訴訟法第449 條第3 項、第451 條\n    之1 第4 項但書第3 款、第452 條分別規定甚明。又地方法\n    院簡易庭對被告為簡易判決處刑後，經提起上訴，而地方法\n    院合議庭認應為無罪判決之諭知者，依同法第455 條之1 第\n    3項準用第369條第2 項之規定意旨，應由該地方法院合議庭\n    撤銷簡易庭之判決，改依第一審通常程序審判。其所為判決\n    ，應屬於「第一審判決」，檢察官仍得依通常上訴程序上訴\n    於管轄第二審之高等法院（參照最高法院91年度臺非字第21\n    號判例意旨）。本件既經本院認應為無罪之諭知，已不符合\n    得為簡易判決處刑之情形，除撤銷原審判決外，並應逕行改\n    依第一審通常程序判決之，檢察官如不服本判決，仍得於法\n    定上訴期間內，向管轄之第二審法院提起上訴，併此敘明。\n據上論斷，應依刑事訴訟法第452 條、第455 條之1 、第3 項、\n第369 條第1 項前段、第364 條、第301 條第1 項，判決如主文\n。\n本案經檢察官曾財和到庭執行職務。\n中    華    民    國   100    年    3     月    8     日\n                  刑事第八庭    審判長法  官  王伯文\n                                      法  官  何秀燕\n                                      法  官  陳俊宏\n以上正本證明與原本無異。\n如不服本判決應於收受判決後10日內向本院提出上訴書狀，並應\n敘述具體理由。其未敘述上訴理由者，應於上訴期間屆滿後20日\n內向本院補提理由書(均須按他造當事人之人數附繕本)「切勿逕\n送上級法院」。\n                                      書記官  胡美儀\n中    華    民    國   100    年    3     月    8     日\n附表一：\n ┌──┬──────┬─────┬─────┐\n │編號│扣案物品名稱│數量（台）│備      註│\n ├──┼──────┼─────┼─────┤\n │ 1  │樂透大亨    │    16    │含IC板16塊│\n ├──┼──────┼─────┼─────┤\n │ 2  │鑽石賓果    │     6    │含IC板6 塊│\n ├──┼──────┼─────┼─────┤\n │ 3  │中華迷13    │     5    │含IC板5 塊│\n ├──┼──────┼─────┼─────┤\n │ 4  │超八        │     3    │含IC板3 塊│\n ├──┼──────┼─────┼─────┤\n │ 5  │福爾摩沙    │     3    │含IC板3 塊│\n ├──┼──────┼─────┼─────┤\n │ 6  │滿貫大亨    │     3    │含IC板3 塊│\n ├──┼──────┼─────┼─────┤\n │ 7  │皇冠列車    │     2    │含IC板2 塊│\n ├──┼──────┼─────┼─────┤\n │ 8  │加州飛艇（8 │     1    │含IC板9 塊│\n │    │人座）      │          │          │\n └──┴──────┴─────┴─────┘\n 附表二：\n ┌──┬──────┬────┬───────┐\n │編號│扣案物品名稱│數    量│備註          │\n ├──┼──────┼────┼───────┤\n │ 1  │新臺幣      │6,300 元│1,000元2張、  │\n │    │            │        │500元6張、100 │\n │    │            │        │元13張        │\n ├──┼──────┼────┼───────┤\n │ 2  │寄分卡      │27張    │1,000分8張、  │\n │    │            │        │500分6張、100 │\n │    │            │        │分13張        │\n ├──┼──────┼────┼───────┤\n │ 3  │新臺幣      │10,000元│1,000元6張、  │\n │    │            │        │500元6張、100 │\n │    │            │        │元10張        │\n ├──┼──────┼────┼───────┤\n │ 4  │寄分卡      │32張    │1,000分8張、  │\n │    │            │        │500分6張、100 │\n │    │            │        │分18張        │\n ├──┼──────┼────┼───────┤\n │ 5  │新臺幣（櫃臺│15,200元│1,000元6張、  │\n │    │內）        │        │500元8張、100 │\n │    │            │        │元52張        │\n ├──┼──────┼────┼───────┤\n │ 6  │寄分卡（櫃臺│140 張  │1,000分46張、 │\n │    │內）        │        │500分12張、100│\n │    │            │        │分82張        │\n ├──┼──────┼────┼───────┤\n │ 7  │監視系統主機│1 台    │              │\n │    │電腦        │        │              │\n ├──┼──────┼────┼───────┤\n │ 8  │日報表      │1 張    │              │\n ├──┼──────┼────┼───────┤\n │ 9  │電子遊戲機台│47塊    │詳如附表一    │\n │    │IC板        │        │              │\n ├──┼──────┼────┼───────┤\n │ 10 │開洗分鑰匙  │2 支    │              │\n └──┴──────┴────┴───────┘",
  "structure": {
    "main": "原判決撤銷。\n蔡宗煙、涂秀青、邱怡仁、王朝弘均無罪。",
    "reason": "甲、證據能力之審酌：\n    被告以外之人於審判外之言詞或書面陳述，除法律有規定者\n    外，不得作為證據；被告以外之人於審判外之陳述，雖不符\n    刑事訴訟法第159 條之1 至之4 之規定，然經當事人於審判\n    程序同意作為證據，法院審酌該言詞陳述或書面陳述作成時\n    之情況，認為適當者，亦得為證據，刑事訴訟法第159 條之\n    5 第1 項定有明文。本判決後開引用具有傳聞證據性質之證\n    據資料，已經檢察官、上訴人即被告蔡宗煙、涂秀青及其辯\n    護人、上訴人即被告邱怡仁、王朝弘於審理期日同意為證據\n    使用，是其縱無刑事訴訟法第159條之1至第159條之4或其他\n    傳聞法則例外之情形，亦經本院審酌該證據作成之情況，既\n    無違法取得情事，復無證明力明顯過低等情形，以得供做法\n    院判斷事實之依據為適當，認為均有證據能力，自得作為本\n    案證據之用。\n乙、實體部分：\n一、聲請簡易判決處刑意旨略以：被告蔡宗煙向高雄市政府申請\n    領有電子遊戲場業營利事業登記證，自民國95年4月20日起\n    ，在高雄市○○區○○路268號公眾得出入之「金明星遊藝\n    場」內，擺設如附表一所示之「樂透大亨」等電子遊戲機台\n    共39  台之賭博性電玩機具，供人把玩，與不特定之客人賭\n    博財物；復自不詳時間起，以月薪新臺幣（下同）1萬8,000\n    元之代價，僱用被告涂秀青在該遊藝場內擔任店員，另自不\n    詳時間起，以不詳月薪，僱用被告邱怡仁（綽號「阿仁」）\n    擔任該遊藝場車手，渠等共同基於在公眾得出入之場所賭博\n    財物之犯意聯絡，由被告涂秀青在場負責開分、洗分工作，\n    賭博方式係由不特定之賭客，先交付現金予被告涂秀青後，\n    任選如附表一所示之電子遊戲機台，由被告涂秀青依1：1、\n    1 ：5或1：50之比例開分後，再押注分數與機器對賭，如有\n    押中，可得倍數不等之分數，如未押中，則由電子遊戲機台\n    將賭客所押注之分數沒入，藉此射悻之賭博方式計算輸贏，\n    待賭客打玩完畢後，再由被告涂秀青為其洗分，以1分兌換\n    現金1元之比例，由被告涂秀青告知賭客至該遊藝場外某處\n    等候，並通知被告邱怡仁前往指定地點，將現金交付賭客，\n    據此與不特定之賭客賭博財物。適於97年5月6日15時30分許\n    ，有被告即賭客王朝弘至該遊藝場把玩電子遊戲機台「樂透\n    大亨」水果盤，於同日16時10分許，被告王朝弘要求被告涂\n    秀青洗分並換取現金3,600元，被告涂秀青即詢問被告王朝\n    弘所騎乘機車之車號，並告知被告王朝弘至高雄市○○區○\n    ○路與民壯路口，綽號「阿仁」之男子會交付現金，被告王\n    朝弘旋騎乘車牌號碼HR8－177號機車前往指定地點向被告邱\n    怡仁領取3,600元後，騎乘上開機車離去，嗣為警持本院核\n    發之搜索票，於同日16時25分許，在高雄市○○○路「人形\n    町日本料理店」前查獲，並在被告王朝弘身上扣得賭資\n    3,600 元；警方復於同日20時10分許，至上開遊藝場執行搜\n    索而查獲，並扣得如附表一所示之賭博性電子遊戲機台39台\n    （含IC  板47塊）及如附表二所示之物，因認被告蔡宗煙、\n    涂秀青、邱怡仁及王朝弘，均涉有刑法第266條第1項之賭博\n    罪嫌。\n二、按犯罪事實應依證據認定之，無證據不得認定犯罪事實；不\n    能證明被告犯罪者，應諭知無罪之判決，刑事訴訟法第154\n    條第2 項、第301 第1 項分別定有明文。又檢察官對於起訴\n    之犯罪事實，應負提出證據及說服之實質舉證責任，倘其所\n    提出之證據，不足為被告有罪之積極證明，或其指出證明之\n    方法，無從說服法院以形成被告有罪之心證，基於無罪推定\n    之原則，自應為被告無罪判決之諭知（最高法院92年台上字\n    第128號判例意旨參照）。檢察官認被告蔡宗煙、涂秀青、\n    邱怡仁及王朝弘涉有賭博罪嫌，無非以被告王朝弘警詢陳述\n    、員警職務報告、扣押筆錄、扣押物品目錄表、高雄市政府\n    警察局三民第二分局臨檢現場紀錄表、保管條、金明星遊藝\n    場暨娟檳榔攤平面地點及兌換賭資路線圖、金明星遊藝場機\n    台擺設及娟檳榔攤有關位置圖等、現場照片52張在卷足憑，\n    及被告王朝弘身上扣得3,600元、扣案如附表一所示之電子\n    遊戲機台共39台（含IC板47塊）；如附表二所示之物為其論\n    據。\n三、訊據告蔡宗煙、涂秀青、邱怡仁及王朝弘固坦承被告王朝弘\n    於97年5月6日15時30分許，至金明星遊藝場把玩電子遊戲機\n    臺「樂透大亨」水果盤，於同日16時10分許，經被告涂秀青\n    告知至高雄市○○區○○路與民壯路口，綽號「阿仁」之男\n    子會交付現金，被告王朝弘旋騎乘機車前往指定地點向邱怡\n    仁領取3,600元之事實，惟均堅詞否認賭博犯行，(一)被告蔡\n    宗煙辯稱：我所經營金明星遊藝場，沒有洗分兌換現金等語\n    ；(二)被告涂秀青辯稱：我沒有與王朝弘賭博財物，我交付王\n    朝弘3,600元並非賭金，是王朝弘進入店內交現金5,000元給\n    我，後來王朝弘只打1,400元，所以我就返還王朝弘3,600元\n    ，我怕新客人會誤會店裡面有在洗分、換現金，剛好邱怡仁\n    說他要離開，我就拜託他將3,600元還給王朝弘等語；(三)被\n    告邱怡仁辯稱：我是去金明星遊藝場把玩電玩，不是該店員\n    工，我剛要離開，順便幫涂秀青拿錢給王朝弘等語；(四)被告\n    王朝弘辯稱：我拿5,000元寄放於店員涂秀青，先以1,000元\n    開500分，之後陸陸續續開分直到我要離開，我就要求店員\n    涂秀青將我寄放所剩本金3,600元還我，涂秀青告訴我阿仁\n    會到覺民及民壯路口還我錢，我到該路口等阿仁，隨後阿仁\n    騎車到後，問我欠多少錢，我說3,600元，阿仁就拿3,600元\n    給我等語，經查：\n(一)檢察官以被告王朝弘首次警詢坦承有兌換現金等情，認為案\n    重初供，應為可採等語，惟被告王朝弘於本院審理時及檢察\n    官訊問時均堅稱：第1次警詢過程中，我本來不同意夜間訊\n    問，警員說我承認的話就可以離開，所以我才同意繼續訊問\n    ，但是訊問完警員沒有放我走，我一直待到翌日凌晨4時許\n    才離開警局等語，觀諸被告王朝弘97年5月6日警詢筆錄記載\n    過程，起初被告王朝弘未坦承自己以把玩機台所得積分兌換\n    現金乙事，並稱被告王怡仁所交付3,600元，店員返還其所\n    寄放之本金等語，中途經警詢問：「現在為18時25分，是否\n    同意夜間詢問」，王朝弘本表明不同意，警再追問：「為何\n    不同意夜間詢問」，王朝弘稱因為要去安親班載小孩，嗣表\n    示同意夜間詢問，此時警再詢問如何兌換賭資時，被告王朝\n    弘始改稱自己有兌換現金，係由店員跟伊約好地點，叫車手\n    至指定地點換取我所贏得的賭資等語，是被告王朝弘供詞轉\n    折，已有啟人疑竇之處，再參以被告王朝弘改稱有兌換現金\n    後，其供稱：「寄分卡1分可以兌換新臺幣1元；寄分卡可以\n    適用於打玩遊藝場所陳列各類機台；各類機台開分比例不同\n    ，如水果盤係1：50，即新臺幣1元可以開50分把玩機臺，麻\n    將機台係1：1，火車機台係1：5」等語，衡情，設若部分機\n    臺係以新臺幣1元開5分或50分把玩，何以兌換現金時，卻均\n    可以以1分兌換新臺幣1元，如此豈不形成顧客以新臺幣1元\n    開5分或50分把玩機臺，卻可故意不把玩機臺，而以5分或50\n    分的積分兌換新臺幣5元或50元之不合理現象，足認其供稱\n    兌換現金之比例，顯與常理不合，再參以被告王朝弘於翌日\n    凌晨3時40分所製作第2次警詢中，則完全否認有兌換現金情\n    事。是本件從被告王朝弘首次警詢原否認兌換現金，後改稱\n    有兌換現金之轉折，且所供兌換現金比例，顯與常理不合，\n    嗣於翌日深夜第2次警詢又改稱沒有兌換現金等過程觀之，\n    已不能排除被告王朝弘於首次警詢中，坦承自己有兌換現金\n    乙事，係為使自己可以提早離開警局，而為與事實不符之供\n    述，嗣因不能如願提早離開，而在翌日凌晨第2次警詢則否\n    認有兌換現金之可能，如此檢察官是否能以案重初供為由，\n    而以被告王朝弘首次警詢所稱內容，據認被告等人賭博犯行\n    ，已屬有疑。\n(二)再者，檢察官以被告涂秀青稱：「我怕新客人會誤會店裡面\n    有在洗分、換現金，剛好邱怡仁說他要離開，我就拜託他將\n    3,600元還給王朝弘；我認識（邱怡仁），不太熟悉」；被\n    告邱怡仁則稱：「涂秀青告訴我被告王朝弘旁邊坐1個類似\n    警察的人，怕別人懷疑，所以才要我這樣做；之前見過王朝\n    弘1、2次面」，而認為被告邱怡仁僅見過王朝弘1、2次，被\n    告涂秀青卻將要交付王朝弘賭金，委託不熟識之被告邱怡仁\n    代為交付，被告涂秀青難道不擔心該筆款項遭被告邱怡仁侵\n    吞而求償無門等語，固屬有見，然此充其量僅能證明被告涂\n    秀青，就委託被告邱怡仁轉交現金予被告王朝弘乙事，或有\n    思慮不周，或處事不夠謹慎之處，然尚不足直接證明被告涂\n    秀青交付王朝弘3,600元即為賭金。再者，被告涂秀青為避\n    免其他客人誤會，往後紛紛要求以積分兌換現金，徒增困擾\n    ，因而不欲將被告王朝弘所寄放之本金，於店內返還予被告\n    王朝弘，此部分與一般常情並無明顯違悖之處，是檢察官以\n    上所舉證據，尚不足證明被告涂秀青交付王朝弘之3,600元\n    ，即為賭資。\n(三)又檢察官以證人即查獲員警陳榮顯偵訊結證：「我們發現客\n    人到店內贏了分數後，到櫃檯跟店員講要洗分，就是要換現\n    金，店員會聯絡車手，要車手在店外某路口等待客人換現金\n    ，然後店員會告訴客人前往該地點，等客人到之後，車手會\n    先跟客人稍微聊一下，再要客人到其他地方，再將現金交給\n    客人」等語(偵卷第118頁、第119頁)，認被告蔡宗煙、涂秀\n    青及邱怡仁涉嫌賭博犯行。惟證人陳榮顯於本院審理時證稱\n    ：「本件係96年底開始調查，我們跟監是很遠的觀看，所以\n    沒有辦法看到現金交易，是依據經驗大膽假設後，再聲請搜\n    索票進行查證，真正確認有現金交易的就是查獲的那一次」\n    等語(本院簡上卷第74頁)，從而，證人陳榮顯偵訊中所述兌\n    換現金乙情，並非其親自見聞，而係依其經驗假設而得，且\n    警方從96年底開始進行調查跟監乙情，並無相關證據在卷可\n    佐，如此自不能遽以認定被告蔡宗煙、涂秀青及邱怡仁，自\n    95年4月20日起至97年5月6日止，長達2年之時間，反覆在金\n    明星遊藝場與不特定人賭博財物。\n(四)末以，本件被告蔡宗煙所經營之金明星遊藝場，領有營利事\n    業登記證，有高雄市政府高市府建二商字第81865095號營利\n    事務登記證1紙在卷可憑(偵卷第70頁) ，是其遊藝場內所擺\n    放之機臺，並非賭博性電玩機具，除非經營者與顧客利用該\n    機具射倖性所得積分，予以兌換財物，籍此賭博財物，始可\n    以賭博罪相繩，然以上證據，均不足證明被告王朝弘於97年\n    5  月6日查獲當日有以所得積分兌換財物乙事，且就被告王\n    朝弘該次以多少積分及比例兌換現金3,600元乙事，亦未載\n    明，而員警自96年底才開始本件調查跟監乙情，並無相關卷\n    證可資佐證，何以檢察官認被告蔡宗煙、涂秀青及邱怡仁係\n    自95年4月20日起開始反覆為賭博犯行，且員警自承其偵訊\n    中所述兌換現金乙情，係依其經驗假設而得，如此實不足證\n    明被告蔡宗煙、涂秀青及邱怡仁長達2年時間，反覆將顧客\n    把玩機臺所得積分，予以兌換現金之賭博犯行。從而，檢察\n    官所舉證據，既不能證明被告蔡宗煙、涂秀青、邱怡仁及王\n    朝弘等人有何兌換現金之事實，即與賭博罪之構成要件不符\n    ，應為無罪諭知。原審判決就全部被告予以論科，尚有未洽\n    ，被告蔡宗煙、涂秀青、邱怡仁及王朝弘上訴，為有理由，\n    本院自應就原判決予以撤銷改判為被告蔡宗煙、涂秀青、邱\n    怡仁及王朝弘均無罪之諭知。\n四、末按法院得為簡易判決處刑者，以所科之刑係宣告緩刑、得\n    易科罰金之有期徒刑及拘役或罰金為限；於檢察官聲請以簡\n    易判決處刑之案件，經法院認應為無罪判決之諭知者，應適\n    用通常程序審判之，刑事訴訟法第449 條第3 項、第451 條\n    之1 第4 項但書第3 款、第452 條分別規定甚明。又地方法\n    院簡易庭對被告為簡易判決處刑後，經提起上訴，而地方法\n    院合議庭認應為無罪判決之諭知者，依同法第455 條之1 第\n    3項準用第369條第2 項之規定意旨，應由該地方法院合議庭\n    撤銷簡易庭之判決，改依第一審通常程序審判。其所為判決\n    ，應屬於「第一審判決」，檢察官仍得依通常上訴程序上訴\n    於管轄第二審之高等法院（參照最高法院91年度臺非字第21\n    號判例意旨）。本件既經本院認應為無罪之諭知，已不符合\n    得為簡易判決處刑之情形，除撤銷原審判決外，並應逕行改\n    依第一審通常程序判決之，檢察官如不服本判決，仍得於法\n    定上訴期間內，向管轄之第二審法院提起上訴，併此敘明。\n據上論斷，應依刑事訴訟法第452 條、第455 條之1 、第3 項、\n第369 條第1 項前段、第364 條、第301 條第1 項，判決如主文\n。\n本案經檢察官曾財和到庭執行職務。"
  },
  "search": "臺灣高雄地方法院刑事判決99年度簡上字第431號上訴人即被告蔡宗煙涂秀青上二人共同選任辯護人李慶榮律師上訴人即被告邱怡仁王朝弘上列上訴人因賭博案件，不服本院中華民國99年7月30日98年度審簡字第19號第一審刑事簡易判決（聲請簡易判決處刑案號：臺灣高雄地方法院檢察署97年度偵字第17344號），提起上訴，本院管轄第二審之合議庭認不得以簡易判決處刑，改依通常程序審理，並自為第一審判決如下：主文原判決撤銷。蔡宗煙、涂秀青、邱怡仁、王朝弘均無罪。理由甲、證據能力之審酌：被告以外之人於審判外之言詞或書面陳述，除法律有規定者外，不得作為證據；被告以外之人於審判外之陳述，雖不符刑事訴訟法第159條之1至之4之規定，然經當事人於審判程序同意作為證據，法院審酌該言詞陳述或書面陳述作成時之情況，認為適當者，亦得為證據，刑事訴訟法第159條之5第1項定有明文。本判決後開引用具有傳聞證據性質之證據資料，已經檢察官、上訴人即被告蔡宗煙、涂秀青及其辯護人、上訴人即被告邱怡仁、王朝弘於審理期日同意為證據使用，是其縱無刑事訴訟法第159條之1至第159條之4或其他傳聞法則例外之情形，亦經本院審酌該證據作成之情況，既無違法取得情事，復無證明力明顯過低等情形，以得供做法院判斷事實之依據為適當，認為均有證據能力，自得作為本案證據之用。乙、實體部分：一、聲請簡易判決處刑意旨略以：被告蔡宗煙向高雄市政府申請領有電子遊戲場業營利事業登記證，自民國95年4月20日起，在高雄市○○區○○路268號公眾得出入之「金明星遊藝場」內，擺設如附表一所示之「樂透大亨」等電子遊戲機台共39台之賭博性電玩機具，供人把玩，與不特定之客人賭博財物；復自不詳時間起，以月薪新臺幣（下同）1萬8,000元之代價，僱用被告涂秀青在該遊藝場內擔任店員，另自不詳時間起，以不詳月薪，僱用被告邱怡仁（綽號「阿仁」）擔任該遊藝場車手，渠等共同基於在公眾得出入之場所賭博財物之犯意聯絡，由被告涂秀青在場負責開分、洗分工作，賭博方式係由不特定之賭客，先交付現金予被告涂秀青後，任選如附表一所示之電子遊戲機台，由被告涂秀青依1：1、1：5或1：50之比例開分後，再押注分數與機器對賭，如有押中，可得倍數不等之分數，如未押中，則由電子遊戲機台將賭客所押注之分數沒入，藉此射悻之賭博方式計算輸贏，待賭客打玩完畢後，再由被告涂秀青為其洗分，以1分兌換現金1元之比例，由被告涂秀青告知賭客至該遊藝場外某處等候，並通知被告邱怡仁前往指定地點，將現金交付賭客，據此與不特定之賭客賭博財物。適於97年5月6日15時30分許，有被告即賭客王朝弘至該遊藝場把玩電子遊戲機台「樂透大亨」水果盤，於同日16時10分許，被告王朝弘要求被告涂秀青洗分並換取現金3,600元，被告涂秀青即詢問被告王朝弘所騎乘機車之車號，並告知被告王朝弘至高雄市○○區○○路與民壯路口，綽號「阿仁」之男子會交付現金，被告王朝弘旋騎乘車牌號碼HR8－177號機車前往指定地點向被告邱怡仁領取3,600元後，騎乘上開機車離去，嗣為警持本院核發之搜索票，於同日16時25分許，在高雄市○○○路「人形町日本料理店」前查獲，並在被告王朝弘身上扣得賭資3,600元；警方復於同日20時10分許，至上開遊藝場執行搜索而查獲，並扣得如附表一所示之賭博性電子遊戲機台39台（含IC板47塊）及如附表二所示之物，因認被告蔡宗煙、涂秀青、邱怡仁及王朝弘，均涉有刑法第266條第1項之賭博罪嫌。二、按犯罪事實應依證據認定之，無證據不得認定犯罪事實；不能證明被告犯罪者，應諭知無罪之判決，刑事訴訟法第154條第2項、第301第1項分別定有明文。又檢察官對於起訴之犯罪事實，應負提出證據及說服之實質舉證責任，倘其所提出之證據，不足為被告有罪之積極證明，或其指出證明之方法，無從說服法院以形成被告有罪之心證，基於無罪推定之原則，自應為被告無罪判決之諭知（最高法院92年台上字第128號判例意旨參照）。檢察官認被告蔡宗煙、涂秀青、邱怡仁及王朝弘涉有賭博罪嫌，無非以被告王朝弘警詢陳述、員警職務報告、扣押筆錄、扣押物品目錄表、高雄市政府警察局三民第二分局臨檢現場紀錄表、保管條、金明星遊藝場暨娟檳榔攤平面地點及兌換賭資路線圖、金明星遊藝場機台擺設及娟檳榔攤有關位置圖等、現場照片52張在卷足憑，及被告王朝弘身上扣得3,600元、扣案如附表一所示之電子遊戲機台共39台（含IC板47塊）；如附表二所示之物為其論據。三、訊據告蔡宗煙、涂秀青、邱怡仁及王朝弘固坦承被告王朝弘於97年5月6日15時30分許，至金明星遊藝場把玩電子遊戲機臺「樂透大亨」水果盤，於同日16時10分許，經被告涂秀青告知至高雄市○○區○○路與民壯路口，綽號「阿仁」之男子會交付現金，被告王朝弘旋騎乘機車前往指定地點向邱怡仁領取3,600元之事實，惟均堅詞否認賭博犯行，(一)被告蔡宗煙辯稱：我所經營金明星遊藝場，沒有洗分兌換現金等語；(二)被告涂秀青辯稱：我沒有與王朝弘賭博財物，我交付王朝弘3,600元並非賭金，是王朝弘進入店內交現金5,000元給我，後來王朝弘只打1,400元，所以我就返還王朝弘3,600元，我怕新客人會誤會店裡面有在洗分、換現金，剛好邱怡仁說他要離開，我就拜託他將3,600元還給王朝弘等語；(三)被告邱怡仁辯稱：我是去金明星遊藝場把玩電玩，不是該店員工，我剛要離開，順便幫涂秀青拿錢給王朝弘等語；(四)被告王朝弘辯稱：我拿5,000元寄放於店員涂秀青，先以1,000元開500分，之後陸陸續續開分直到我要離開，我就要求店員涂秀青將我寄放所剩本金3,600元還我，涂秀青告訴我阿仁會到覺民及民壯路口還我錢，我到該路口等阿仁，隨後阿仁騎車到後，問我欠多少錢，我說3,600元，阿仁就拿3,600元給我等語，經查：(一)檢察官以被告王朝弘首次警詢坦承有兌換現金等情，認為案重初供，應為可採等語，惟被告王朝弘於本院審理時及檢察官訊問時均堅稱：第1次警詢過程中，我本來不同意夜間訊問，警員說我承認的話就可以離開，所以我才同意繼續訊問，但是訊問完警員沒有放我走，我一直待到翌日凌晨4時許才離開警局等語，觀諸被告王朝弘97年5月6日警詢筆錄記載過程，起初被告王朝弘未坦承自己以把玩機台所得積分兌換現金乙事，並稱被告王怡仁所交付3,600元，店員返還其所寄放之本金等語，中途經警詢問：「現在為18時25分，是否同意夜間詢問」，王朝弘本表明不同意，警再追問：「為何不同意夜間詢問」，王朝弘稱因為要去安親班載小孩，嗣表示同意夜間詢問，此時警再詢問如何兌換賭資時，被告王朝弘始改稱自己有兌換現金，係由店員跟伊約好地點，叫車手至指定地點換取我所贏得的賭資等語，是被告王朝弘供詞轉折，已有啟人疑竇之處，再參以被告王朝弘改稱有兌換現金後，其供稱：「寄分卡1分可以兌換新臺幣1元；寄分卡可以適用於打玩遊藝場所陳列各類機台；各類機台開分比例不同，如水果盤係1：50，即新臺幣1元可以開50分把玩機臺，麻將機台係1：1，火車機台係1：5」等語，衡情，設若部分機臺係以新臺幣1元開5分或50分把玩，何以兌換現金時，卻均可以以1分兌換新臺幣1元，如此豈不形成顧客以新臺幣1元開5分或50分把玩機臺，卻可故意不把玩機臺，而以5分或50分的積分兌換新臺幣5元或50元之不合理現象，足認其供稱兌換現金之比例，顯與常理不合，再參以被告王朝弘於翌日凌晨3時40分所製作第2次警詢中，則完全否認有兌換現金情事。是本件從被告王朝弘首次警詢原否認兌換現金，後改稱有兌換現金之轉折，且所供兌換現金比例，顯與常理不合，嗣於翌日深夜第2次警詢又改稱沒有兌換現金等過程觀之，已不能排除被告王朝弘於首次警詢中，坦承自己有兌換現金乙事，係為使自己可以提早離開警局，而為與事實不符之供述，嗣因不能如願提早離開，而在翌日凌晨第2次警詢則否認有兌換現金之可能，如此檢察官是否能以案重初供為由，而以被告王朝弘首次警詢所稱內容，據認被告等人賭博犯行，已屬有疑。(二)再者，檢察官以被告涂秀青稱：「我怕新客人會誤會店裡面有在洗分、換現金，剛好邱怡仁說他要離開，我就拜託他將3,600元還給王朝弘；我認識（邱怡仁），不太熟悉」；被告邱怡仁則稱：「涂秀青告訴我被告王朝弘旁邊坐1個類似警察的人，怕別人懷疑，所以才要我這樣做；之前見過王朝弘1、2次面」，而認為被告邱怡仁僅見過王朝弘1、2次，被告涂秀青卻將要交付王朝弘賭金，委託不熟識之被告邱怡仁代為交付，被告涂秀青難道不擔心該筆款項遭被告邱怡仁侵吞而求償無門等語，固屬有見，然此充其量僅能證明被告涂秀青，就委託被告邱怡仁轉交現金予被告王朝弘乙事，或有思慮不周，或處事不夠謹慎之處，然尚不足直接證明被告涂秀青交付王朝弘3,600元即為賭金。再者，被告涂秀青為避免其他客人誤會，往後紛紛要求以積分兌換現金，徒增困擾，因而不欲將被告王朝弘所寄放之本金，於店內返還予被告王朝弘，此部分與一般常情並無明顯違悖之處，是檢察官以上所舉證據，尚不足證明被告涂秀青交付王朝弘之3,600元，即為賭資。(三)又檢察官以證人即查獲員警陳榮顯偵訊結證：「我們發現客人到店內贏了分數後，到櫃檯跟店員講要洗分，就是要換現金，店員會聯絡車手，要車手在店外某路口等待客人換現金，然後店員會告訴客人前往該地點，等客人到之後，車手會先跟客人稍微聊一下，再要客人到其他地方，再將現金交給客人」等語(偵卷第118頁、第119頁)，認被告蔡宗煙、涂秀青及邱怡仁涉嫌賭博犯行。惟證人陳榮顯於本院審理時證稱：「本件係96年底開始調查，我們跟監是很遠的觀看，所以沒有辦法看到現金交易，是依據經驗大膽假設後，再聲請搜索票進行查證，真正確認有現金交易的就是查獲的那一次」等語(本院簡上卷第74頁)，從而，證人陳榮顯偵訊中所述兌換現金乙情，並非其親自見聞，而係依其經驗假設而得，且警方從96年底開始進行調查跟監乙情，並無相關證據在卷可佐，如此自不能遽以認定被告蔡宗煙、涂秀青及邱怡仁，自95年4月20日起至97年5月6日止，長達2年之時間，反覆在金明星遊藝場與不特定人賭博財物。(四)末以，本件被告蔡宗煙所經營之金明星遊藝場，領有營利事業登記證，有高雄市政府高市府建二商字第81865095號營利事務登記證1紙在卷可憑(偵卷第70頁)，是其遊藝場內所擺放之機臺，並非賭博性電玩機具，除非經營者與顧客利用該機具射倖性所得積分，予以兌換財物，籍此賭博財物，始可以賭博罪相繩，然以上證據，均不足證明被告王朝弘於97年5月6日查獲當日有以所得積分兌換財物乙事，且就被告王朝弘該次以多少積分及比例兌換現金3,600元乙事，亦未載明，而員警自96年底才開始本件調查跟監乙情，並無相關卷證可資佐證，何以檢察官認被告蔡宗煙、涂秀青及邱怡仁係自95年4月20日起開始反覆為賭博犯行，且員警自承其偵訊中所述兌換現金乙情，係依其經驗假設而得，如此實不足證明被告蔡宗煙、涂秀青及邱怡仁長達2年時間，反覆將顧客把玩機臺所得積分，予以兌換現金之賭博犯行。從而，檢察官所舉證據，既不能證明被告蔡宗煙、涂秀青、邱怡仁及王朝弘等人有何兌換現金之事實，即與賭博罪之構成要件不符，應為無罪諭知。原審判決就全部被告予以論科，尚有未洽，被告蔡宗煙、涂秀青、邱怡仁及王朝弘上訴，為有理由，本院自應就原判決予以撤銷改判為被告蔡宗煙、涂秀青、邱怡仁及王朝弘均無罪之諭知。四、末按法院得為簡易判決處刑者，以所科之刑係宣告緩刑、得易科罰金之有期徒刑及拘役或罰金為限；於檢察官聲請以簡易判決處刑之案件，經法院認應為無罪判決之諭知者，應適用通常程序審判之，刑事訴訟法第449條第3項、第451條之1第4項但書第3款、第452條分別規定甚明。又地方法院簡易庭對被告為簡易判決處刑後，經提起上訴，而地方法院合議庭認應為無罪判決之諭知者，依同法第455條之1第3項準用第369條第2項之規定意旨，應由該地方法院合議庭撤銷簡易庭之判決，改依第一審通常程序審判。其所為判決，應屬於「第一審判決」，檢察官仍得依通常上訴程序上訴於管轄第二審之高等法院（參照最高法院91年度臺非字第21號判例意旨）。本件既經本院認應為無罪之諭知，已不符合得為簡易判決處刑之情形，除撤銷原審判決外，並應逕行改依第一審通常程序判決之，檢察官如不服本判決，仍得於法定上訴期間內，向管轄之第二審法院提起上訴，併此敘明。據上論斷，應依刑事訴訟法第452條、第455條之1、第3項、第369條第1項前段、第364條、第301條第1項，判決如主文。本案經檢察官曾財和到庭執行職務。中華民國100年3月8日刑事第八庭審判長法官王伯文法官何秀燕法官陳俊宏以上正本證明與原本無異。如不服本判決應於收受判決後10日內向本院提出上訴書狀，並應敘述具體理由。其未敘述上訴理由者，應於上訴期間屆滿後20日內向本院補提理由書(均須按他造當事人之人數附繕本)「切勿逕送上級法院」。書記官胡美儀中華民國100年3月8日附表一：┌──┬──────┬─────┬─────┐│編號│扣案物品名稱│數量（台）│備註│├──┼──────┼─────┼─────┤│1│樂透大亨│16│含IC板16塊│├──┼──────┼─────┼─────┤│2│鑽石賓果│6│含IC板6塊│├──┼──────┼─────┼─────┤│3│中華迷13│5│含IC板5塊│├──┼──────┼─────┼─────┤│4│超八│3│含IC板3塊│├──┼──────┼─────┼─────┤│5│福爾摩沙│3│含IC板3塊│├──┼──────┼─────┼─────┤│6│滿貫大亨│3│含IC板3塊│├──┼──────┼─────┼─────┤│7│皇冠列車│2│含IC板2塊│├──┼──────┼─────┼─────┤│8│加州飛艇（8│1│含IC板9塊│││人座）│││└──┴──────┴─────┴─────┘附表二：┌──┬──────┬────┬───────┐│編號│扣案物品名稱│數量│備註│├──┼──────┼────┼───────┤│1│新臺幣│6,300元│1,000元2張、│││││500元6張、100│││││元13張│├──┼──────┼────┼───────┤│2│寄分卡│27張│1,000分8張、│││││500分6張、100│││││分13張│├──┼──────┼────┼───────┤│3│新臺幣│10,000元│1,000元6張、│││││500元6張、100│││││元10張│├──┼──────┼────┼───────┤│4│寄分卡│32張│1,000分8張、│││││500分6張、100│││││分18張│├──┼──────┼────┼───────┤│5│新臺幣（櫃臺│15,200元│1,000元6張、│││內）││500元8張、100│││││元52張│├──┼──────┼────┼───────┤│6│寄分卡（櫃臺│140張│1,000分46張、│││內）││500分12張、100│││││分82張│├──┼──────┼────┼───────┤│7│監視系統主機│1台││││電腦│││├──┼──────┼────┼───────┤│8│日報表│1張││├──┼──────┼────┼───────┤│9│電子遊戲機台│47塊│詳如附表一│││IC板│││├──┼──────┼────┼───────┤│10│開洗分鑰匙│2支││└──┴──────┴────┴───────┘",
  "characters": {
    "judges": [
      "王伯文",
      "何秀燕",
      "陳俊宏"
    ],
    "prosecutors": [
      "曾財和"
    ],
    "lawyers": [
      "李慶榮"
    ],
    "clerks": [
      "胡美儀"
    ],
    "plaintiffs": [

    ],
    "defendants": [
      "蔡宗煙",
      "邱怡仁"
    ],
    "prosecutor_office": [

    ],
    "creditors": [

    ],
    "debtors": [

    ],
    "judicial_associate_officer": [

    ]
  },
  "adjudged_at": "2011-03-08",
  "created_at": "2016-02-13 20:12:05",
  "updated_at": "2016-02-13 20:12:05"
}