{
  "identify": "TCD-100-易-522-20110308-1",
  "court": {
    "name": "臺灣臺中地方法院",
    "code": "TCD"
  },
  "division": {
    "name": "刑事",
    "code": "M"
  },
  "year": 100,
  "word": "易",
  "number": "522",
  "jcheck": "1",
  "reason": "傷害等",
  "content": "臺灣臺中地方法院刑事判決              100年度易字第522號\n公  訴  人  臺灣臺中地方法院檢察署檢察官\n被      告  陳朝陽\n            陳正煒\n            陳揚昇\n上列被告等因傷害等案件，經檢察官提起公訴(99年度偵字第267\n62號)，本院就傷害部分判決如下：\n    主    文\n本件公訴不受理。\n    理    由\n一、公訴意旨略以:被告陳朝陽為被告陳正煒、陳揚昇之父。緣\n    被告陳朝陽於民國99年10月23日，在臺中縣霧峰鄉(現改制\n    為臺中市霧峰區○○○路1066號「亞殿遊戲場」，與告訴人\n    謝戎芃發生口角，遂對告訴人心生不滿。後被告陳朝陽於99\n    年10月24日下午4時30分，在臺中縣大里市(現改制為臺中市\n    大里區○○○○路259號「新地球遊戲場」，又巧遇告訴人時\n    ，即夥同被告陳正煒、陳揚昇及2名姓名年籍不詳之友人(按\n    :其等涉恐嚇危害安全部分，由本院另逕以簡易判決處刑)，\n    共同基於傷害及恐嚇危害安全之犯意聯絡，分別以徒手、持\n    掃把、竹竿等物，毆打告訴人，致告訴人受有頭部外傷併左\n    臉瘀青、上下唇腫脹、擦傷、雙上臂、雙前臂、背部、頸部\n    、胸壁多處瘀青、左手第5指擦傷等之傷害。被告陳朝陽等\n    人見告訴人已無力抵抗，被告陳朝陽即喝令告訴人跪下，並\n    向告訴人恫稱:「跪下來，不然要繼續打你」等語，以此加\n    害告訴人身體之事，恐嚇告訴人，被告陳正煒、陳揚昇等人\n    則在旁附和，告訴人見此情狀，乃心生畏懼致危害於告訴人\n    之安全，因認被告等係犯刑法第277條第1項之普通傷害罪嫌\n    。\n二、按告訴乃論之罪，告訴人於第一審辯論終結前得撤回其告訴\n    ，又告訴經撤回者，應諭知不受理之判決，並得不經言詞辯\n    論為之，刑事訴訟法第238條第1項、第303條第3款、第307\n    條分別定有明文。本件被告陳朝陽、陳正煒、陳揚昇等3人\n    共同涉犯之普通傷害罪，依刑法第287條前段規定須告訴乃\n    論。茲告訴人業於100年3月3日具狀撤回告訴，有聲請撤回\n    告訴狀1份附卷可稽，是告訴人既於第一審言詞辯論終結前\n    撤回其告訴，揆諸前揭法條規定，爰不經言詞辯論，諭知不\n    受理之判決。\n據上論斷，應依刑事訴訟法第303條第3款、第307條，判決如主\n文。\n中    華    民    國   100    年    3     月    8     日\n                    刑事第三庭    法  官  丁智慧\n上正本證明與原本無異。\n如不服本判決應於收受判決後10日內向本院提出上訴書狀，並應\n敘述具體理由；其未敘述上訴理由者，應於上訴期間屆滿後20日\n內向本院補提理由書（均須按他造當事人之人數附繕本）「切勿\n逕送上級法院」。\n                                  書記官  王志\n中    華    民    國   100    年    3     月    8     日",
  "structure": {
    "main": "本件公訴不受理。",
    "reason": "一、公訴意旨略以:被告陳朝陽為被告陳正煒、陳揚昇之父。緣\n    被告陳朝陽於民國99年10月23日，在臺中縣霧峰鄉(現改制\n    為臺中市霧峰區○○○路1066號「亞殿遊戲場」，與告訴人\n    謝戎芃發生口角，遂對告訴人心生不滿。後被告陳朝陽於99\n    年10月24日下午4時30分，在臺中縣大里市(現改制為臺中市\n    大里區○○○○路259號「新地球遊戲場」，又巧遇告訴人時\n    ，即夥同被告陳正煒、陳揚昇及2名姓名年籍不詳之友人(按\n    :其等涉恐嚇危害安全部分，由本院另逕以簡易判決處刑)，\n    共同基於傷害及恐嚇危害安全之犯意聯絡，分別以徒手、持\n    掃把、竹竿等物，毆打告訴人，致告訴人受有頭部外傷併左\n    臉瘀青、上下唇腫脹、擦傷、雙上臂、雙前臂、背部、頸部\n    、胸壁多處瘀青、左手第5指擦傷等之傷害。被告陳朝陽等\n    人見告訴人已無力抵抗，被告陳朝陽即喝令告訴人跪下，並\n    向告訴人恫稱:「跪下來，不然要繼續打你」等語，以此加\n    害告訴人身體之事，恐嚇告訴人，被告陳正煒、陳揚昇等人\n    則在旁附和，告訴人見此情狀，乃心生畏懼致危害於告訴人\n    之安全，因認被告等係犯刑法第277條第1項之普通傷害罪嫌\n    。\n二、按告訴乃論之罪，告訴人於第一審辯論終結前得撤回其告訴\n    ，又告訴經撤回者，應諭知不受理之判決，並得不經言詞辯\n    論為之，刑事訴訟法第238條第1項、第303條第3款、第307\n    條分別定有明文。本件被告陳朝陽、陳正煒、陳揚昇等3人\n    共同涉犯之普通傷害罪，依刑法第287條前段規定須告訴乃\n    論。茲告訴人業於100年3月3日具狀撤回告訴，有聲請撤回\n    告訴狀1份附卷可稽，是告訴人既於第一審言詞辯論終結前\n    撤回其告訴，揆諸前揭法條規定，爰不經言詞辯論，諭知不\n    受理之判決。\n據上論斷，應依刑事訴訟法第303條第3款、第307條，判決如主\n文。"
  },
  "search": "臺灣臺中地方法院刑事判決100年度易字第522號公訴人臺灣臺中地方法院檢察署檢察官被告陳朝陽陳正煒陳揚昇上列被告等因傷害等案件，經檢察官提起公訴(99年度偵字第26762號)，本院就傷害部分判決如下：主文本件公訴不受理。理由一、公訴意旨略以:被告陳朝陽為被告陳正煒、陳揚昇之父。緣被告陳朝陽於民國99年10月23日，在臺中縣霧峰鄉(現改制為臺中市霧峰區○○○路1066號「亞殿遊戲場」，與告訴人謝戎芃發生口角，遂對告訴人心生不滿。後被告陳朝陽於99年10月24日下午4時30分，在臺中縣大里市(現改制為臺中市大里區○○○○路259號「新地球遊戲場」，又巧遇告訴人時，即夥同被告陳正煒、陳揚昇及2名姓名年籍不詳之友人(按:其等涉恐嚇危害安全部分，由本院另逕以簡易判決處刑)，共同基於傷害及恐嚇危害安全之犯意聯絡，分別以徒手、持掃把、竹竿等物，毆打告訴人，致告訴人受有頭部外傷併左臉瘀青、上下唇腫脹、擦傷、雙上臂、雙前臂、背部、頸部、胸壁多處瘀青、左手第5指擦傷等之傷害。被告陳朝陽等人見告訴人已無力抵抗，被告陳朝陽即喝令告訴人跪下，並向告訴人恫稱:「跪下來，不然要繼續打你」等語，以此加害告訴人身體之事，恐嚇告訴人，被告陳正煒、陳揚昇等人則在旁附和，告訴人見此情狀，乃心生畏懼致危害於告訴人之安全，因認被告等係犯刑法第277條第1項之普通傷害罪嫌。二、按告訴乃論之罪，告訴人於第一審辯論終結前得撤回其告訴，又告訴經撤回者，應諭知不受理之判決，並得不經言詞辯論為之，刑事訴訟法第238條第1項、第303條第3款、第307條分別定有明文。本件被告陳朝陽、陳正煒、陳揚昇等3人共同涉犯之普通傷害罪，依刑法第287條前段規定須告訴乃論。茲告訴人業於100年3月3日具狀撤回告訴，有聲請撤回告訴狀1份附卷可稽，是告訴人既於第一審言詞辯論終結前撤回其告訴，揆諸前揭法條規定，爰不經言詞辯論，諭知不受理之判決。據上論斷，應依刑事訴訟法第303條第3款、第307條，判決如主文。中華民國100年3月8日刑事第三庭法官丁智慧上正本證明與原本無異。如不服本判決應於收受判決後10日內向本院提出上訴書狀，並應敘述具體理由；其未敘述上訴理由者，應於上訴期間屆滿後20日內向本院補提理由書（均須按他造當事人之人數附繕本）「切勿逕送上級法院」。書記官王志中華民國100年3月8日",
  "characters": {
    "judges": [
      "丁智慧"
    ],
    "prosecutors": [

    ],
    "lawyers": [

    ],
    "clerks": [
      "王志"
    ],
    "plaintiffs": [

    ],
    "defendants": [
      "陳朝陽"
    ],
    "prosecutor_office": [
      "臺灣臺中地方法院檢察署檢察官"
    ],
    "creditors": [

    ],
    "debtors": [

    ],
    "judicial_associate_officer": [

    ]
  },
  "adjudged_at": "2011-03-08",
  "created_at": "2016-02-13 20:13:27",
  "updated_at": "2016-02-13 20:13:27"
}