{
  "identify": "TPD-100-除-526-20110309-1",
  "court": {
    "name": "臺灣臺北地方法院",
    "code": "TPD"
  },
  "division": {
    "name": "民事",
    "code": "V"
  },
  "year": 100,
  "word": "除",
  "number": "526",
  "jcheck": "1",
  "reason": "除權判決（票據）",
  "content": "臺灣臺北地方法院民事判決              100年度除字第526號\n聲  請  人  吳靜雯\n上列聲請人聲請除權判決事件，本院判決如下：\n    主  文\n如附表所示之證券無效。\n訴訟費用由聲請人負擔。\n    理  由\n一、上開證券，經本院以99年度司催字第2260號公示催告。\n二、所定申報權利期間，已於民國99年12月23日屆滿，迄今無人\n    申報權利。\n三、依民事訴訟法第564條第1項，判決如主文。\n中    華    民    國   100    年    3     月    9     日\n                  民事第七庭    法  官  陳婷玉\n以上正本證明係照原本作成。\n本判決不得上訴。\n中    華    民    國   100    年    3     月    9     日\n                                書記官  吳鸝稻\n┌────────────────────────────────────────┐\n│附表：                                                        100年度除字第526號│\n├──┬───────┬──────┬──────┬─────────┬─────┤\n│編號│發    票    人│付  款  人  │發  票  日  │票面金額（新台幣）│支票號碼  │\n├──┼───────┼──────┼──────┼─────────┼─────┤\n│001 │華南商業銀行復│華南商業銀行│99年4月21日 │5,000元           │CD0000000 │\n│    │興分行  黃│復興分行    │            │                  │          │\n└──┴───────┴──────┴──────┴─────────┴─────┘",
  "structure": {
    "main": "如附表所示之證券無效。\n訴訟費用由聲請人負擔。",
    "reason": "一、上開證券，經本院以99年度司催字第2260號公示催告。\n二、所定申報權利期間，已於民國99年12月23日屆滿，迄今無人\n    申報權利。\n三、依民事訴訟法第564條第1項，判決如主文。"
  },
  "search": "臺灣臺北地方法院民事判決100年度除字第526號聲請人吳靜雯上列聲請人聲請除權判決事件，本院判決如下：主文如附表所示之證券無效。訴訟費用由聲請人負擔。理由一、上開證券，經本院以99年度司催字第2260號公示催告。二、所定申報權利期間，已於民國99年12月23日屆滿，迄今無人申報權利。三、依民事訴訟法第564條第1項，判決如主文。中華民國100年3月9日民事第七庭法官陳婷玉以上正本證明係照原本作成。本判決不得上訴。中華民國100年3月9日書記官吳鸝稻┌────────────────────────────────────────┐│附表：100年度除字第526號│├──┬───────┬──────┬──────┬─────────┬─────┤│編號│發票人│付款人│發票日│票面金額（新台幣）│支票號碼│├──┼───────┼──────┼──────┼─────────┼─────┤│001│華南商業銀行復│華南商業銀行│99年4月21日│5,000元│CD0000000│││興分行黃│復興分行││││└──┴───────┴──────┴──────┴─────────┴─────┘",
  "characters": {
    "judges": [
      "陳婷玉"
    ],
    "prosecutors": [

    ],
    "lawyers": [

    ],
    "clerks": [
      "吳鸝稻"
    ],
    "plaintiffs": [

    ],
    "defendants": [

    ],
    "prosecutor_office": [
      "吳靜雯"
    ],
    "creditors": [

    ],
    "debtors": [

    ],
    "judicial_associate_officer": [

    ]
  },
  "adjudged_at": "2011-03-09",
  "created_at": "2016-02-13 20:29:20",
  "updated_at": "2016-02-13 20:29:20"
}