{
  "identify": "TYD-99-訴-939-20110308-2",
  "court": {
    "name": "臺灣桃園地方法院",
    "code": "TYD"
  },
  "division": {
    "name": "刑事",
    "code": "M"
  },
  "year": 99,
  "word": "訴",
  "number": "939",
  "jcheck": "2",
  "reason": "誣告等",
  "content": "臺灣桃園地方法院刑事判決               99年度訴字第939號\n公  訴  人  臺灣桃園地方法院檢察署檢察官\n被      告  王長孝\n上列被告因誣告等案件，經檢察官提起公訴（99年度偵字第1806\n9號），本院判決如下：\n    主  文\n王長孝行使偽造私文書，足以生損害於公眾及他人，累犯，處有\n期徒刑肆月，扣案如附表所示偽造之借據肆紙均沒收。又意圖他\n人受刑事處分，向該管公務員誣告，累犯，處有期徒刑伍月，扣\n案如附表所示偽造之借據肆紙均沒收。應執行有期徒刑捌月，扣\n案如附表所示偽造之借據肆紙均沒收。\n    事  實\n一、王長孝於民國97年間，因違反毒品危害防制條例案件，經本\n    院以97年度桃簡字第2300號判決判處有期徒刑3 月確定，於\n    97年10月20日易科罰金執行完畢。詎其猶不知悔改，分別為\n    下列犯行：(一)王長孝於96年間委託林慶炫辦理大陸地區配偶\n    仲介事宜，陸續於如附表所示之時間支付林慶炫總計新臺幣\n    （下同）12萬元之代辦費用，林慶炫則簽立如附表所示偽造\n    前內容之手寫收據4 紙予王長孝收執，王長孝竟基於意圖為\n    自己不法之所有及行使偽造私文書之犯意，明知林慶炫未曾\n    於如附表所示時間向其借貸如附表所示之4 筆款項，於其收\n    受上開4紙收據後至97年11月4日間某時，在其位於桃園縣桃\n    園市○○○街38號住處，將前揭4 紙收據各增寫如附表所示\n    之文字，以此方式偽造成如附表所示偽造後之內容，表彰係\n    林慶炫名義書寫之借據4紙，偽造完成後，旋於97年11月4日\n    某時，以前揭偽造之借據影本為附件，具狀向本院桃園民事\n    簡易庭起訴請求林慶炫清償借款，復接續前開行使偽造私文\n    書之犯意，於97年12月2 日在本院桃園簡易庭行調解程序時\n    ，提出前開偽造之收據4 紙供該承辦法官核對而行使之，因\n    當日林慶炫經合法通知未到庭答辯，致使本院97年度桃簡字\n    第1483號民事案件承辦法官陷於錯誤，於97年12月16日一造\n    辯論判決王長孝之訴全部勝訴確定，足以生損害於林慶炫。\n    (二)前開民事判決確定後，林慶炫之財產因遭法院強制執行，\n    經林慶炫閱卷後，查知上情，林慶炫於98年4月6日具狀向臺\n    灣桃園地方法院檢察署（下稱桃園地檢署）對王長孝提出詐\n    欺及偽造文書之告訴。詎王長孝因林慶炫對其提出前開告訴\n    ，為求反制林慶炫，明知上開借據係其用以詐騙法院而自行\n    偽造，且其與林慶炫間並無前揭12萬元之借款債務，竟另基\n    於行使偽造私文書及意圖他人受刑事處分之犯意，於98年 8\n    月16日上午7 時50分，前往桃園縣政府警察局桃園分局埔子\n    派出所（下稱埔子派出所），向該派出所職司刑事偵查輔助\n    機關之警員洪耀武提出前揭偽造之借據影本4 紙，申告林慶\n    炫向其提出前揭借據4 紙而謊稱繳納房屋貸款等理由詐騙12\n    萬元即避不見面云云，以此虛偽之借款事實對林慶炫提出詐\n    欺及背信之告訴，嗣桃園縣政府警察局桃園分局於98年10月\n    13日將林慶炫所涉詐欺及背信案件報請桃園地檢署併案偵辦\n    。詎王長孝竟承前犯意，於98年10月23日桃園地檢署檢察官\n    就其所涉詐欺及偽造文書案件訊問時，提出前揭偽造之借據\n    4 紙供該承辦檢察官核對而行使之，復於99年3月3日桃園地\n    檢署檢察官就其與林慶炫所涉案件訊問時，提出前揭偽造之\n    借據4 紙供該承辦檢察官核對，藉此使該承辦檢察官信其所\n    述為真實而行使之，經該承辦檢察官認前揭偽造之收據係該\n    案件之重要證物而當庭扣押，嗣經偵查結果，該承辦檢察官\n    因認前開扣案如附表所示之收據4 紙，均係王長孝所偽造，\n    並認林慶炫所涉詐欺、背信罪嫌嫌疑不足，以99年度偵字第\n    18068號為不起訴處分，始查知上情。\n二、案經林慶炫訴請臺灣桃園地方法院檢察署檢察官偵查起訴。\n    理  由\n一、證據能力：\n(一)、按被告以外之人，於審判外之言詞或書面陳述，除法律有規\n    定者外，不得作為證據。刑事訴訟法第159條第1項定有明文\n    。被告以外之人（包括證人、鑑定人、告訴人、被害人及共\n    同被告等）於審判外之言詞或書面陳述，即所謂傳聞證據。\n    由於傳聞證據有悖法院直接審理及言詞審理之精神，妨礙當\n    事人之反對詰問權，影響程序正義之實現，除法律有規定（\n    例如同法第159條第2項、同法第159條之1至之5、同法第206\n    條等）外，原則不具證據能力。查證人林慶炫於桃園縣政府\n    警察局桃園分局之陳述（見臺灣桃園地方法院檢察署98年度\n    他字第1544號卷第24-25 頁背面），屬於被告以外之人於審\n    判外之言詞及書面陳述，被告明確主張上開證人之陳述無證\n    據能力，公訴人復未指出上開陳述有何特別可信之情形，本\n    院既查無上開例外得以之作為證據之各種情形，因此認定上\n    開陳述，應無證據能力。\n(二)、次按被告以外之人於偵訊中向檢察官所為之陳述，除顯有不\n    可信之情況者外，得為證據，刑事訴訟法第159條之1第2 項\n    定有明文。而所謂不可信情況之認定，法院應審酌被告以外\n    之人於陳述時之外在環境及情況，例如：陳述時之心理狀況\n    、有無受到外力干擾等，以為判斷之依據，故係決定陳述有\n    無證據能力，而非決定陳述內容之證明力。是被告以外之人\n    前於偵查中已具結而為證述，除反對該項供述得具有證據能\n    力之一方，已釋明「顯有不可信之情況」之理由外，皆得為\n    證據；又司法實務運作上，咸認偵查中檢察官向被告以外之\n    人所取得之陳述，原則上均能遵守法律規定，不致違法取供\n    ，被告以外之人於偵查中依法應具結者已具結，向檢察官所\n    為之陳述，原則上具有證據能力。另未經被告詰問之被告以\n    外之人於偵查中向檢察官所為之陳述，依刑事訴訟法第 159\n    條之1第2項之規定，原則上屬於法律規定為有證據能力之傳\n    聞證據，於例外顯有不可信之情況，始否定其得為證據。是\n    得為證據之被告以外之人於偵查中所為之陳述，因其陳述未\n    經被告詰問，應認屬於未經合法調查之證據，並非無證據能\n    力，而禁止證據之使用。惟是否行使詰問權，屬被告之自由\n    ，倘被告於審判中捨棄詰問權，或證人客觀上有不能受詰問\n    之情形，自無不當剝奪被告詰問權行使之可言（最高法院99\n    年度臺上字第4125號判決參照) 。被告雖於本準備程序時明\n    確表示證人林慶炫於檢察官訊問時之證述無證據能力云云（\n    見本院99年度審訴字第1786號卷第31頁），惟查，證人林慶\n    炫於檢察官訊問時係以證人身分作證，經檢察官告以具結之\n    義務及偽證之處罰，並經具結而陳述，且無證據顯示其等所\n    為證言係遭受強暴、脅迫、詐欺、利誘等外力干擾取得，並\n    無顯不可信之情況，故其於檢察官偵訊中之證述，揆諸前開\n    說明，自有證據能力。而被告迄至言詞辯論終結前，均未聲\n    請傳喚詰問上開證人，且於審判期日經審判長詢問尚有何證\n    據請求調查時，亦皆答稱沒有，被告既已認無傳喚上開證人\n    之必要，則無不當剝奪被告詰問權之行使。是本院於審判期\n    日依法定程序提示上開證人於檢察官訊問時之筆錄，並告以\n    要旨，即已為合法調查，自得作為證據。\n(三)、至本院認定事實所引用之其他證據資料，並無證據證明係公\n    務員違背法定程序所取得，且被告對其證據能力未表示爭執\n    ，迄至言詞辯論終結前亦未再聲明異議，經核亦無顯有不可\n    信之情況與不得作為證據之情形，本院審酌上開證據資料製\n    作時之情況，尚無違法不當及證明力明顯過低之瑕疵，認為\n    以之作為證據應屬適當，是依刑事訴訟法第159條至第159條\n    之5規定，均認有證據能力。\n二、訊據被告王長孝固不否認其於被害人林慶炫交付之收據上增\n    寫如附表所示之文字，且於前揭時間持向本院桃園簡易庭對\n    被害人林慶炫起訴請求清償借款並提出供承辦法官核對而獲\n    勝訴判決確定，及其於前揭時間持向埔子派出所警員對被害\n    人林慶炫涉犯詐欺、背信之事實提出告訴，並先、後於前揭\n    時間，在桃園地檢署檢察官偵查中再提出前揭借據供該承辦\n    檢察官核對之事實，惟矢口否認有行使或偽造私文書、詐欺\n    及誣告之犯行，辯稱：伊委請林慶炫仲介伊大陸配偶，曾交\n    付林慶炫11萬元之代辦費，惟系爭4 紙借據與上開代辦費用\n    無關，林慶炫確於借據上所載之日期向伊借錢，伊先後在住\n    處如數將現金借予林慶炫後，林慶炫即簽立借據交予伊，伊\n    外甥女張紜瑄及父親王偉忠皆有看到伊借錢給林慶炫，伊拿\n    到收據後就在借據上填寫「借據」2 字，並謄抄其上之日期\n    於借據下方，至如附表編號1 所示借據上所載「辦資料」也\n    是伊填寫的，因為林慶炫第一次向伊借錢時表示要繳交房貸\n    ，因此伊才寫「辦資料」，另附表編號2 所示借據上所載「\n    辦機票」則是林慶炫自己寫的，伊告訴林慶炫隨便寫理由就\n    可以，因為伊不怕林慶炫跑掉，伊並沒有偽造借據及誣告林\n    慶炫云云。經查：\n(一)、被告於97年11月4 日具狀對被害人林慶炫提起清償債務之民\n    事訴訟，並將如附表所示增寫後之借據4 紙影本提出於本院\n    桃園簡易庭，嗣於97年12月2 日本院桃園簡易庭97年度桃簡\n    字第1483號清償債務案件調解時，提出前開借據4 紙供承辦\n    法官核對而行使之，經本院桃園簡易庭承辦法官審理結果，\n    認被害人林慶炫經合法通知未到庭且被告已提出前揭借據為\n    證，以一造辯論判決被告全部勝訴確定，嗣被告持上開民事\n    確定判決對被害人林慶炫之財產聲請強制執行等情，為被告\n    所不否認，並有如附表所示之收據4 紙扣案可查，及本院桃\n    院永98司執珩字第14243 號債權憑證、執行命令等件影本在\n    卷可稽（見桃園地檢署98年度他字第1544號卷第33- 37頁）\n    ，且經本院審閱本院97年度桃簡字第1483號卷附97年11月 4\n    日起訴狀、97年12月2 日調解程序筆錄、民事判決、確定證\n    明書無訛（見本院97年度桃簡字第1483號影卷第4-9、15、1\n    9-21、24頁），此部分事實，應堪認定。又被告於98年8 月\n    16日前往埔子派出所向職司刑事偵查輔助之司法警察洪耀武\n    申告被害人林慶炫於附表所示之日期向其借款12萬元，隨即\n    避不見面云云，對被害人林慶炫提出詐欺及背信告訴，案經\n    桃園縣政府警察局桃園分局於98年10月12日報請桃園地檢署\n    併該署99年度他字第1544號被告詐欺案件偵辦，被告於98年\n    10月23日承辦檢察官就其所涉詐欺等案件訊問時，提出前揭\n    收據4紙予檢察官拍照存證，復於99年3月3 日該承辦檢察官\n    就其與被害人林慶炫所涉詐欺案件訊問時，再提出前揭收據\n    4 紙予檢察官核對，經該檢察官當場扣案，嗣被害人林慶炫\n    所涉詐欺等案件，經該檢察官偵查結果，認前開收據4 紙均\n    係被告增註文字於上，非被害人林慶炫向被告借款，被害人\n    林慶炫罪嫌不足，而以99年度偵字第18068 號為不起訴處分\n    ，被告不服聲請再議，經臺灣高等法院檢察署以99年度上聲\n    議第6904號駁回其再議之聲請而確定之事實，亦為被告所不\n    否認，且有埔子派出所98年8 月16日調查筆錄、桃園地檢署\n    98年10月23日及99年3月3日訊問筆錄、桃園地檢署檢察官99\n    年度偵字第18068 號不起訴處分書、臺灣高等法院檢察署99\n    年度上聲議字第6904號處分書在卷可稽（見同上他字卷第68\n    、73-74、145頁、桃園地檢署99年度偵字第18068號影卷第4\n    頁及背面、本院99年度訴字第939 號卷第33頁），亦堪認定\n    。\n(二)、被告雖辯稱被害人林慶炫係向其借錢而簽發如附表所示之借\n    據交予其收執云云，惟據證人林慶炫於檢察官訊問時證稱：\n    4張收據上之「借據」2字都是被告所寫，筆跡明顯不同，編\n    號1所示收據下方之「中華民國元月5日」是被告所寫，其他\n    記載則為伊於96年1月5日在被告家中客廳所填寫，因被告想\n    要去大陸結婚，伊要請別人辦一些結婚資料，例如公證、台\n    胞證、入台證等費用；編號2 所示收據上方「借據」、最後\n    一行「中華民國96年1 月10日」是被告所寫，其他記載則是\n    伊於96年1月10日在被告家中客廳所寫；編號3所示收據上方\n    「借據」、「拿」、最後一行「中華民國96年1 月13日」、\n    「Ｚ000000000」是被告自行填寫，其他記載則是於96年1月1\n    3 日在大陸福建住宿處，伊向被告拿4萬元時所寫；編號4所\n    示收據上方「96年7月8日」應為「96年1月8日」，被告將「\n    1」改成「7」，「借據」、「中華民國96年7月8日」亦是被\n    告所寫，其他記載則是伊於96年1月8日在被告家中客廳所寫\n    ，拿錢的目的就是要辦機票，這筆錢應該接續在編號1 後面\n    ，因為辦機票是去大陸娶新娘的第2個程序，編號1部分算是\n    定金，辦妥之後就要訂機票，再接著是編號2 的錢應該算是\n    第3 個程序，算是在大陸婚宴的相關雜費支出，這些費用要\n    先跟被告拿，以免被告後悔，編號3的錢應該是第4個程序，\n    是伊與被告已經在大陸，還有陸續在大陸拍照、住宿的費用\n    ，伊與被告的費用分開算，故這4 筆金錢是伊幫被告娶大陸\n    新娘支出的相關費用，有行程表可證；伊於96年1月8日去拿\n    機票，所以才跟被告拿錢，機票1 人是14,900元，伊機票錢\n    也是被告出的，有相關帳款明細可以證明，另外被告結婚時\n    在大陸的時間是96年1 月12日至同年月19日，伊與被告有合\n    照照片；如果伊是向被告借錢，不可能寫辦機票、辦資料等\n    字句，實際上的代辦費用就是這4 筆單據所載，被告並沒有\n    於95年12月30日在其住處1 次交付11萬元的沒人酬勞給伊等\n    語（見同上他字卷第129- 131頁），證人林慶炫證述情節與\n    常情並無相悖之處，且審閱證人林慶炫於檢察官訊問時提出\n    之友福旅行社有限公司應收帳款明細表、旅客行程表、被告\n    迎娶大陸配偶照片及卷附被告入出境查詢結果（見同上他字\n    卷第141-143 頁背面、本院99年度939 號卷第12頁），循皆\n    與其前開證述為被告代辦台胞證、訂機票及與被告一同前往\n    大陸地區之時間、情節均相符，堪認證人林慶炫確曾於96年\n    1月5日委託友福旅行辦理其與被告前往大陸地區使用之台胞\n    證簽章，且於96年1月8日支付其與被告2 人之機票費及前述\n    簽章費用共計29,800元，渠2人搭乘96年1月12日班機前往大\n    陸地區為被告迎娶大陸配偶等情，應屬事實，證人林慶炫前\n    開證述情節應非虛假而具有相當之可信度。\n(三)、至被告辯稱其於如附表所示之日期，在其家中將借款交付被\n    害人林慶炫云云，惟查：\n  1.被告於警詢時先係辯稱：借據上所載之「借據」2 字及日期\n    都是伊所寫，伊沒有將「96年1月8日」改為「96年7月8日」\n    ，這都是林慶炫在現場向伊拿錢時，要伊自行加上「借據」\n    2 字及押上日期；林慶炫打電話給伊表示需錢繳納房租，所\n    以伊才借錢給林慶炫，伊於95年12月30日就一次將仲介大陸\n    配偶之費用11萬元交予林慶炫，而林慶炫提供之借據係伊結\n    婚後，林慶炫私底下向伊借的，與娶大陸配偶一事不相關云\n    云（見同上他字卷第20頁背面-21 頁背面），然觀諸前開友\n    福旅行社有限公司旅客行程表、被告迎娶大陸配偶照片及被\n    告入出境查詢結果可知，被告應係於96年1 月12日至同年月\n    19日前往大陸地區迎娶大陸配偶，則若被告所辯其係於婚後\n    始貸予被害人林慶炫如附表所示之金錢一節屬實，則其顯非\n    於附表編號1、2號所示之96年1月5日、同年1 月10日將金錢\n    貸予被害人林慶炫，而被告於收受與實際借貸日期不相符之\n    收據時，除未向被害人林慶炫要求更正，顯與常情相違外，\n    甚且被告於向本院桃園簡易庭具狀對被害人林慶炫提出清償\n    債務之民事訴訟時，其事實仍記載被害人林慶炫係於96年 1\n    月5日、96年1月10日向其借款等情，有該起訴狀、存證信函\n    影本在卷可查（見本院97年度桃簡字第1483號影卷第5、7頁\n    ），被告於本院審理時亦稱：林慶炫向伊借12萬元的時間就\n    是4 張借據上所記載的日期（見本院99年度訴字第939 號卷\n    第44頁），與其辯稱結婚後始貸予被害人林慶炫金錢一節，\n    明顯不一，被告此部分所辯，要難採信。\n  2.被告於98年7月15日檢察官訊問時則供陳：這4張借據是林慶\n    炫向伊借款時親自簽名、蓋手印，至「借據」2 字及日期是\n    在伊家中，當著伊父親、姐姐及林慶炫面前，伊增添上去的\n    ，伊填寫時去林慶炫沒有意見云云（見同上他卷第45頁），\n    然於98年8月5日檢察官訊問時旋即改稱：林慶炫簽立借據時\n    ，伊父親王偉忠有在家，但是伊父親當時在看電視，沒有親\n    眼目睹伊簽立借據，但王偉忠知道林慶炫向伊借款，錢是伊\n    交給林慶炫，並不是王偉忠交給林慶炫云云（見同上他字卷\n    第50頁）。觀諸被告前、後所述其父親王偉忠有無目睹被害\n    人林慶炫簽立如附表所示收據及其在該收據上增寫如附表所\n    示之文字，說詞反覆。而證人王偉忠於檢察官訊問時證稱：\n    伊認識林慶炫，林慶炫要幫被告介紹大陸新娘，故曾到伊家\n    中收取仲介費，伊拿給被告快13萬元，由被告在伊家中交給\n    林慶炫，錢都被林慶炫拿去了，但伊不知道林慶炫將錢用到\n    何處；伊有看過卷附的借據，這是林慶炫另外向被告借的錢\n    ，上面「辦機票」等字是林慶炫自己寫的，伊不清楚這樣寫\n    是不是辦理借到大陸新娘的費用，伊也沒有看到林慶炫與被\n    告在寫借據等情（見同上偵卷第50頁），證人王偉忠雖證述\n    扣案之借據均係被害人林慶炫向被告借款時所書立之憑據，\n    且如附表編號2 所示借據上之「辦機票」等文字係被害人林\n    慶炫所填寫，惟觀諸證人王偉忠上開證述，其未親眼目睹被\n    害人林慶炫與被告借款情節，亦未見到被害人林慶炫與被告\n    簽立借據之經過，且就借據上因何記載「辦機票」一節，亦\n    證述其不知情，則其所述該借據所載內容係被害人林慶炫向\n    被告借款云云，顯係其個人自行推測之詞，不足採信，反可\n    徵之被告所辯其於如附表所示之借據4 紙增寫文字，係在證\n    人王偉忠及被害人林慶炫面前所填載，而被害人林慶炫當時\n    亦無意見云云，應屬虛構，不足採信。\n  3.再者，被告於99年2月4日檢察官訊問時先係辯稱：這4 筆借\n    款時間都是在借據上所載時間，地點都在伊家中客廳，由林\n    慶炫親自向伊借的，至於林慶炫為何不寫「借據」等字，伊\n    不清楚云云；經檢察官究明其既已於96年1 月13日隨同被害\n    人林慶炫前往大陸，如何能於99年1 月12日在其家中將借款\n    交予被害人林慶炫，被告隨即改稱：應該是96年1 月12日凌\n    晨在機場交給林慶炫的，是林慶炫說到機場再將錢交給他云\n    云（見同上他字卷第131 頁），被告就其在何時、地將所稱\n    之借款交予被害人林慶炫一節，前後所述情節差距甚大；被\n    告於99年11月8 日本院準備程序時復再辯稱：借款金額是林\n    慶炫與伊父親王偉忠接洽的，如附表所示之借據係於借據上\n    所載日期在伊家中所寫，林慶炫分4 次向伊父親王偉忠借錢\n    ，96年1月5日拿15,000元、96年1 月10日拿30,000元、96年\n    1月13日拿40,000元、96年7月8 日拿35,000元，且均係伊父\n    親王偉忠在桃園縣桃園市○○○街38號家中拿現金給林慶炫\n    云云（見本院99年度審訴字第1786號卷第29頁背面-30 頁）\n    ，被告辯稱於如附表所示借據所載之時間貸予被害人林慶炫\n    金錢，除與警詢時所辯係婚後始貸予被害人林慶炫不符外，\n    其所辯於96年1 月13日在住處借予被害人林慶炫40,000元，\n    亦核與前揭友福旅行社有限公司旅客行程表及卷附被告入出\n    境資訊連結作業查詢結果（見本院99年度訴字第939 號卷第\n    12頁）所示，被告與被害人林慶炫係於96年1 月12日經由香\n    港地區轉機至大陸福建省福州市之事實顯然不符，此外，其\n    辯稱係證人王偉忠在住處將現金交予被害人林慶炫一節，更\n    與其先前於檢察官訊問時所辯：錢係伊交給林慶炫，並不是\n    王偉忠交給林慶炫云云（見同上他字卷第50頁）及於本院審\n    理時所辯：林慶炫第1、2次來借錢時，伊有跟伊父親說，伊\n    父親沒有說話，只有點頭，錢伊就從家裡拿出來，林慶炫來\n    借第3 次錢時，錢從家裡拿出來，這次伊沒有告訴伊父親等\n    情（見本院99年度訴字第939 號卷第44頁背面），核屬迥異\n    ，況依證人王偉忠在偵查中之供述可知，證人王偉忠並無借\n    款予被害人林慶炫，是被告前後不一之辯解，均無足採信。\n  4.被告於本院準備程序時固再辯稱：林慶炫先以電話和伊聯絡\n    借錢一事，然後林慶炫就到伊家拿錢，伊將錢當場清點給林\n    慶炫，伊父親王偉忠、外甥女張紜瑄均在場，張紜瑄每筆借\n    款都有見到云云（見本院99年度訴字第939 號卷第13頁背面\n    -14、22頁背面-23頁背面），被告辯稱係其將金錢交予被害\n    人林慶炫，核與其前述由證人王偉忠將金錢交予被害人林慶\n    炫一情，自相矛盾，且證人張紜瑄於本院審理時證稱：伊有\n    見到林慶炫到伊與被告之住處，林慶炫來的時候都在1 樓，\n    伊有時候從2樓下去1樓廚房拿東西時，有看到林慶炫，但伊\n    不知道被告與林慶炫之間有無債務關係，伊只知道渠2 人有\n    講到金錢，但情形伊不清楚，林慶炫簽立4 張借據時，伊沒\n    有在場，伊亦不暸解渠2人為何要簽立這4張借據等語（見本\n    院99年度訴字第939 號卷第23-23 背面頁），證人張紜瑄未\n    親見被告貸予被害人林慶炫如附表所示借據內容之4 筆金錢\n    ，與被告所辯其將金錢貸交予被害人林慶炫時，證人張紜瑄\n    皆有見到云云不符，被告此部分所辯，顯屬虛妄之詞。又被\n    告於本院審理時另辯稱：於96年1 月13日那筆借款是伊與林\n    慶炫到了福州金山大飯店後，林慶炫向伊借的，伊是在飯店\n    房間將錢交給林慶炫，但是林慶炫寫錯日期，正確日期應該\n    是96年1月12日，林慶炫寫成96年1月13日云云（見本院99年\n    度訴字第939 號卷第24頁），不僅與被告於檢察官訊問時辯\n    稱其係於96年1 月12日在機場交予被害人林慶炫等情相悖（\n    見同上他字卷第131 頁），復與被告於本院準備程序、審理\n    時歷次所辯該4 筆借款均在其家中以現金清點交予被害人林\n    慶炫云云不符，益徵被告諸多辯解，實屬臨訟卸責之詞。\n  5.至被告於本院審理時雖再辯稱：林慶炫向伊借貸如附表編號\n    4 所示之金錢時，伊父親從中國信託商業銀行之帳戶內提領\n    出來，再借予被害人林慶炫云云（見本院99年度訴字第 939\n    號卷第44頁背面），惟觀諸被告提出之中國信託商業銀行提\n    款憑證影本（見同上他字卷第65頁），僅足證明被告之父親\n    王偉忠曾於96年5 月14日自其帳戶轉匯10萬元至被告帳戶內\n    ，然此與被告所稱之第4 筆借款日期96年7月8日相距甚遠，\n    是此部分並無法為有利於被告之認定。\n  6.觀諸被告上開所辯，被告對於借款之時間、地點、金錢之來\n    源，多次供述互有歧異，已非可採；另衡諸社會上個人間消\n    費借貸常情，率皆由借貸人書立借貸意旨之借據交予貸與人\n    收執，要無可能在借據上記載與消費借貸事實無關聯之其他\n    事由，然觀之卷附被害人林慶炫交予被告收執之如附表所示\n    收據4紙，其中編號1收據記載「辦資料」，另編號2 之收據\n    則記載「辦機票」，均非一般消費借貸往來下，借貸人書寫\n    之事由甚明，反係與被害人林慶炫前開證述為被告辦理大陸\n    結婚事宜所收取之費用、機票費等情較相符合。從而，被告\n    辯稱其分別於如附表所示之時間貸予被告如附表所示之金錢\n    ，係屬虛構而非僅出於主觀上之誤認，且如附表所示之收據\n    4 紙，亦非被害人林慶炫於如附表所示之時間交予被告收執\n    之「借據」，而係被告將被害人林慶炫前所交付之「收據」\n    ，偽造成被害人林慶炫名義之借據後，再持以行使，並於被\n    害人林慶炫對其提出偽造文書及詐欺告訴後，復以此虛構之\n    借款事實對被害人林慶炫提出詐欺及背信告訴，應堪認定。\n(四)、綜上所述，本案事證明確，被告犯行洵堪認定，應依法論科\n    。\n二、論罪科刑：\n(一)、核被告就犯罪事實一、(一)所為，係犯刑法第216條、第210條\n    之行使偽造私文書罪及刑法第339條第2項詐欺得利罪。公訴\n    人認被告此部分犯行係涉犯刑法第339條第3項、第2 項之詐\n    欺得利未遂罪云云，惟按上訴人因權利人提起民事訴訟向其\n    追取租仔，先後在受訴法院提出偽契，主張受當該田，及已\n    代為贖回，否認付租義務，自係連續行使偽造私文書，以詐\n    術圖得財產上不法之利益，既經民事判決勝訴確定在案，其\n    詐欺即屬既遂，最高法院29年上字第2118號判例可資參照。\n    查被告提出如附表所示之偽造收據4 紙向本院桃園簡易庭主\n    張其對被害人林慶炫有12萬元之消費借貸債權，致本院承辦\n    法官陷於錯誤而以97年度桃簡字第1483號案件判決被告勝訴\n    確定在案，已認定如前所述，揆諸上開見解，被告前開詐欺\n    犯行，應屬既遂，公訴人認被告詐欺得利犯行僅屬未遂，容\n    有誤會，惟既遂、未遂乃犯罪之階段行為，毋庸變更起訴法\n    條，附此敘明。又按行使影本，作用與原本相同，偽造私文\n    書後，持以行使其影本，偽造之低度行為為高度之行使行為\n    所吸收，應論以行使偽造私文書罪，最高法院70年臺上字第\n    1107號判例參照。查被告偽造如附表所示之收據4 紙後復持\n    影本及原本以行使，其偽造之低度行為則為行使之高度行為\n    所吸收，不另論罪。又被告所犯2 次行使偽造私文書之犯行\n    ，均係出於其向本院訛稱被害人林慶炫曾向其借貸之目的而\n    為之，侵害之法益相同，各行為之獨立性極為薄弱，依一般\n    社會健全觀念，在時間差距上難以強行分開，在刑法評價上\n    ，以視為數個舉動之接續施行，合為包括之一行為予以評價\n    ，較為合理，顯係基於單一行使偽造私文書犯意下之接續行\n    為，只論以接續犯之單純一罪為已足。又被告以一行使偽造\n    之私文書方法，同時觸犯行使偽造私文書罪及詐欺得利罪，\n    為想像競合犯，應從一重之行使偽造私文書罪處斷。\n(二)、按刑法上之誣告罪，本不限於所告事實全屬虛偽時，始能成\n    立，倘所告事實之一部分係出於故意虛構，仍不得謂非誣告\n    。最高法院20年上字第662 號判例意旨可資參照。查被告係\n    以虛構之借款情節，向埔子派出所職司刑事偵查輔助之司法\n    警察洪耀武申告被害人林慶炫涉犯背信、詐欺罪嫌，已認定\n    如前所述，則被告與被害人林慶炫間縱另有債權債務關係存\n    在，惟被害人林慶炫既未曾於如附表所示之時間向被告借貸\n    金錢，被告竟仍提出如附表所示借據4 紙，指訴被害人林慶\n    炫於如附表所示時間向其借款4 次之事實而告訴被害人林慶\n    炫涉犯詐欺、背信罪嫌，顯有以此虛構之事實，使被害人林\n    慶炫受刑事追訴之意圖及故意，甚為灼然。核被告就犯罪事\n    實一、(二)所為，係犯刑法第216條、第210條之行使偽造私文\n    書罪、第169條第1項誣告罪。又按刑法第169條第2項之偽造\n    證據及使用罪，原屬同條第1 項誣告之預備行為，因其犯罪\n    之危險性較為重大，故不必實行誣告，仍予獨立處罰，如果\n    偽造此項證據持以誣告，除另犯其他罪名外，按照低度行為\n    吸收於高度行為之原則，祇應論以第一項之誣告罪名，不應\n    再適用第2 項從重處斷；次按意圖他人受刑事處分，向該管\n    公務員誣告，同時復使用偽造之證據，則其使用偽造證據之\n    行為，應為誣告行為所吸收，除應成立刑法第169條第1項之\n    罪外，固不應再以同條第2 項之罪相繩，但其使用偽造證據\n    ，若更觸犯其他罪名時，仍係一行為而犯數罪，應依刑法第\n    55條從一重處斷，不能並謂其所觸犯之其他罪名，亦為誣告\n    行為所吸收，而不得再行論處。最高法院30年上字第194 號\n    、28年上字第4086號判例意旨可資參照。查被告意圖他人受\n    刑事處分，向該管公務員誣告被害人林慶炫涉犯詐欺、背信\n    罪嫌，同時復使用偽造之證據，其使用偽造證據之低度行為\n    ，均為誣告之高度行為所吸收，不另論罪，公訴人雖未就被\n    告使用偽造證據之犯行起訴，惟該部分犯行與已敘及部分，\n    有吸收犯之實質上一罪關係，為起訴效力所及，本院自得併\n    予審理。又被告使用偽造證據之行為為誣告行為所吸收，而\n    其係以一行為同時犯行使偽造私文書罪及誣告罪，為想像競\n    合犯，自應從一重之誣告罪處斷。\n(三)、被告所犯上述偽造私文書罪及誣告罪，犯意各別，行為互殊\n    ，應予分論併罰。又被告有如事實欄所載之犯罪科刑紀錄及\n    執行情形，此有臺灣高等法院被告前案紀錄表在卷可稽，其\n    於受有期徒刑執行完畢後，5 年內故意再犯本件有期徒刑以\n    上之罪，均為累犯，均應依刑法第47條第1 項規定加重其刑\n    。爰審酌被告偽造證據，對被害人林慶炫提出民事告訴並濫\n    行提出詐欺及背信告訴，嚴重妨害司法公正性，並足使林慶\n    炫受有刑事處分之危險，造成司法調查程序之無益進行，妨\n    害司法正義之實現，且於犯後猶狡詞卸責，態度難認良好，\n    併其品行、犯罪動機、目的、手段、生活狀況、智識程度及\n    所生之損害等一切情狀，分別量處如主文所示之刑，並定其\n    應執行之刑，以示懲儆。\n三、沒收：扣案之如附表所示收據4 紙，均為供被告犯本罪所用\n    之物，且均屬被告所有，應依刑法第38條第1項第2款之規定\n    ，分別於被告所犯行使偽造文書罪、誣告罪所宣告之主刑項\n    下，分別諭知沒收。\n據上論斷，應依刑事訴訟法第299條第1 項前段，刑法第第216條\n、第210條、第339條第2項、第169條第1項、第47條第1項、第55\n條、第51條第5款、第38條第1項第2款，刑法施行法第1條之1 ，\n判決如主文。\n本案經檢察官蔡正傑到庭執行職務。\n中    華    民    國    100   年     3     月    8    日\n            刑事第四庭 審判長 法  官  張淑華\n                              法  官  張宇葭\n                              法  官  林維斌\n以上正本證明與原本無異。\n如不服本判決應於收受判決後10日內向本院提出上訴書狀，並應\n敘述具體理由。其未敘述上訴理由者，應於上訴期間屆滿後20日\n內向本院補提理由書( 均須按他造當事人之人數附繕本) 「切勿\n逕送上級法院」。\n                               書記官  鄭嘉惠\n中    華    民    國   100    年    3     月    9     日\n附表：\n  ┌──┬──────┬────────────┬────────────┬────────┐\n  │編號│  日期      │偽造前之內容            │偽造後之內容            │王長孝補增之內容│\n  ├──┼──────┼────────────┼────────────┼────────┤\n  │ 1  │96年1 月5 日│15,000元於1月5日拿      │借據15,000元於1月5日拿  │借據、中華民國96│\n  │    │            │15,000辦資料            │15,000辦資料            │年元月5日       │\n  │    │            │   林慶炫               │   林慶炫Ｚ000000000     │                │\n  │    │            │Ｚ000000000              │中華民國96年元月5日     │                │\n  ├──┼──────┼────────────┼────────────┼────────┤\n  │ 2  │96年1月8日  │96年1月8日拿3萬5仟元整  │96年7月8日拿3萬5仟元整  │借據、1月改為7月│\n  │    │            │  辦機票                │     辦機票借據         │、中華民國96年7 │\n  │    │            │  林慶炫                │     林慶炫             │月8 日          │\n  │    │            │  Ｚ000000000            │     Ｚ000000000         │                │\n  │    │            │                        │ 中華民國96年7月8日     │                │\n  ├──┼──────┼────────────┼────────────┼────────┤\n  │ 3  │96年1月10日 │ 96年1月10日            │  96年1月10日借據       │借據、中華民國96│\n  │    │            │  拿3 萬                │   拿3萬林慶炫          │年1月10日       │\n  │    │            │  林慶炫                │   Ｚ000000000           │                │\n  │    │            │  Ｚ000000000            │中華民國96年1月10日     │                │\n  ├──┼──────┼────────────┼────────────┼────────┤\n  │ 4  │96年1月13日 │ 96年1月13日            │借據  96年1月13日       │借據、拿、中華民│\n  │    │            │ 拿4萬林慶炫            │    拿4萬林慶炫         │國96年1月13日、 │\n  │    │            │    Ｚ000000000          │    Ｚ000000000          │Ｚ000000000      │\n  │    │            │中華民國96年1月13日     │中華民國96年1月13日     │                │\n  └──┴──────┴────────────┴────────────┴────────┘",
  "structure": {
    "main": "王長孝行使偽造私文書，足以生損害於公眾及他人，累犯，處有\n期徒刑肆月，扣案如附表所示偽造之借據肆紙均沒收。又意圖他\n人受刑事處分，向該管公務員誣告，累犯，處有期徒刑伍月，扣\n案如附表所示偽造之借據肆紙均沒收。應執行有期徒刑捌月，扣\n案如附表所示偽造之借據肆紙均沒收。",
    "fact": "一、王長孝於民國97年間，因違反毒品危害防制條例案件，經本\n    院以97年度桃簡字第2300號判決判處有期徒刑3 月確定，於\n    97年10月20日易科罰金執行完畢。詎其猶不知悔改，分別為\n    下列犯行：(一)王長孝於96年間委託林慶炫辦理大陸地區配偶\n    仲介事宜，陸續於如附表所示之時間支付林慶炫總計新臺幣\n    （下同）12萬元之代辦費用，林慶炫則簽立如附表所示偽造\n    前內容之手寫收據4 紙予王長孝收執，王長孝竟基於意圖為\n    自己不法之所有及行使偽造私文書之犯意，明知林慶炫未曾\n    於如附表所示時間向其借貸如附表所示之4 筆款項，於其收\n    受上開4紙收據後至97年11月4日間某時，在其位於桃園縣桃\n    園市○○○街38號住處，將前揭4 紙收據各增寫如附表所示\n    之文字，以此方式偽造成如附表所示偽造後之內容，表彰係\n    林慶炫名義書寫之借據4紙，偽造完成後，旋於97年11月4日\n    某時，以前揭偽造之借據影本為附件，具狀向本院桃園民事\n    簡易庭起訴請求林慶炫清償借款，復接續前開行使偽造私文\n    書之犯意，於97年12月2 日在本院桃園簡易庭行調解程序時\n    ，提出前開偽造之收據4 紙供該承辦法官核對而行使之，因\n    當日林慶炫經合法通知未到庭答辯，致使本院97年度桃簡字\n    第1483號民事案件承辦法官陷於錯誤，於97年12月16日一造\n    辯論判決王長孝之訴全部勝訴確定，足以生損害於林慶炫。\n    (二)前開民事判決確定後，林慶炫之財產因遭法院強制執行，\n    經林慶炫閱卷後，查知上情，林慶炫於98年4月6日具狀向臺\n    灣桃園地方法院檢察署（下稱桃園地檢署）對王長孝提出詐\n    欺及偽造文書之告訴。詎王長孝因林慶炫對其提出前開告訴\n    ，為求反制林慶炫，明知上開借據係其用以詐騙法院而自行\n    偽造，且其與林慶炫間並無前揭12萬元之借款債務，竟另基\n    於行使偽造私文書及意圖他人受刑事處分之犯意，於98年 8\n    月16日上午7 時50分，前往桃園縣政府警察局桃園分局埔子\n    派出所（下稱埔子派出所），向該派出所職司刑事偵查輔助\n    機關之警員洪耀武提出前揭偽造之借據影本4 紙，申告林慶\n    炫向其提出前揭借據4 紙而謊稱繳納房屋貸款等理由詐騙12\n    萬元即避不見面云云，以此虛偽之借款事實對林慶炫提出詐\n    欺及背信之告訴，嗣桃園縣政府警察局桃園分局於98年10月\n    13日將林慶炫所涉詐欺及背信案件報請桃園地檢署併案偵辦\n    。詎王長孝竟承前犯意，於98年10月23日桃園地檢署檢察官\n    就其所涉詐欺及偽造文書案件訊問時，提出前揭偽造之借據\n    4 紙供該承辦檢察官核對而行使之，復於99年3月3日桃園地\n    檢署檢察官就其與林慶炫所涉案件訊問時，提出前揭偽造之\n    借據4 紙供該承辦檢察官核對，藉此使該承辦檢察官信其所\n    述為真實而行使之，經該承辦檢察官認前揭偽造之收據係該\n    案件之重要證物而當庭扣押，嗣經偵查結果，該承辦檢察官\n    因認前開扣案如附表所示之收據4 紙，均係王長孝所偽造，\n    並認林慶炫所涉詐欺、背信罪嫌嫌疑不足，以99年度偵字第\n    18068號為不起訴處分，始查知上情。\n二、案經林慶炫訴請臺灣桃園地方法院檢察署檢察官偵查起訴。",
    "reason": "一、證據能力：\n(一)、按被告以外之人，於審判外之言詞或書面陳述，除法律有規\n    定者外，不得作為證據。刑事訴訟法第159條第1項定有明文\n    。被告以外之人（包括證人、鑑定人、告訴人、被害人及共\n    同被告等）於審判外之言詞或書面陳述，即所謂傳聞證據。\n    由於傳聞證據有悖法院直接審理及言詞審理之精神，妨礙當\n    事人之反對詰問權，影響程序正義之實現，除法律有規定（\n    例如同法第159條第2項、同法第159條之1至之5、同法第206\n    條等）外，原則不具證據能力。查證人林慶炫於桃園縣政府\n    警察局桃園分局之陳述（見臺灣桃園地方法院檢察署98年度\n    他字第1544號卷第24-25 頁背面），屬於被告以外之人於審\n    判外之言詞及書面陳述，被告明確主張上開證人之陳述無證\n    據能力，公訴人復未指出上開陳述有何特別可信之情形，本\n    院既查無上開例外得以之作為證據之各種情形，因此認定上\n    開陳述，應無證據能力。\n(二)、次按被告以外之人於偵訊中向檢察官所為之陳述，除顯有不\n    可信之情況者外，得為證據，刑事訴訟法第159條之1第2 項\n    定有明文。而所謂不可信情況之認定，法院應審酌被告以外\n    之人於陳述時之外在環境及情況，例如：陳述時之心理狀況\n    、有無受到外力干擾等，以為判斷之依據，故係決定陳述有\n    無證據能力，而非決定陳述內容之證明力。是被告以外之人\n    前於偵查中已具結而為證述，除反對該項供述得具有證據能\n    力之一方，已釋明「顯有不可信之情況」之理由外，皆得為\n    證據；又司法實務運作上，咸認偵查中檢察官向被告以外之\n    人所取得之陳述，原則上均能遵守法律規定，不致違法取供\n    ，被告以外之人於偵查中依法應具結者已具結，向檢察官所\n    為之陳述，原則上具有證據能力。另未經被告詰問之被告以\n    外之人於偵查中向檢察官所為之陳述，依刑事訴訟法第 159\n    條之1第2項之規定，原則上屬於法律規定為有證據能力之傳\n    聞證據，於例外顯有不可信之情況，始否定其得為證據。是\n    得為證據之被告以外之人於偵查中所為之陳述，因其陳述未\n    經被告詰問，應認屬於未經合法調查之證據，並非無證據能\n    力，而禁止證據之使用。惟是否行使詰問權，屬被告之自由\n    ，倘被告於審判中捨棄詰問權，或證人客觀上有不能受詰問\n    之情形，自無不當剝奪被告詰問權行使之可言（最高法院99\n    年度臺上字第4125號判決參照) 。被告雖於本準備程序時明\n    確表示證人林慶炫於檢察官訊問時之證述無證據能力云云（\n    見本院99年度審訴字第1786號卷第31頁），惟查，證人林慶\n    炫於檢察官訊問時係以證人身分作證，經檢察官告以具結之\n    義務及偽證之處罰，並經具結而陳述，且無證據顯示其等所\n    為證言係遭受強暴、脅迫、詐欺、利誘等外力干擾取得，並\n    無顯不可信之情況，故其於檢察官偵訊中之證述，揆諸前開\n    說明，自有證據能力。而被告迄至言詞辯論終結前，均未聲\n    請傳喚詰問上開證人，且於審判期日經審判長詢問尚有何證\n    據請求調查時，亦皆答稱沒有，被告既已認無傳喚上開證人\n    之必要，則無不當剝奪被告詰問權之行使。是本院於審判期\n    日依法定程序提示上開證人於檢察官訊問時之筆錄，並告以\n    要旨，即已為合法調查，自得作為證據。\n(三)、至本院認定事實所引用之其他證據資料，並無證據證明係公\n    務員違背法定程序所取得，且被告對其證據能力未表示爭執\n    ，迄至言詞辯論終結前亦未再聲明異議，經核亦無顯有不可\n    信之情況與不得作為證據之情形，本院審酌上開證據資料製\n    作時之情況，尚無違法不當及證明力明顯過低之瑕疵，認為\n    以之作為證據應屬適當，是依刑事訴訟法第159條至第159條\n    之5規定，均認有證據能力。\n二、訊據被告王長孝固不否認其於被害人林慶炫交付之收據上增\n    寫如附表所示之文字，且於前揭時間持向本院桃園簡易庭對\n    被害人林慶炫起訴請求清償借款並提出供承辦法官核對而獲\n    勝訴判決確定，及其於前揭時間持向埔子派出所警員對被害\n    人林慶炫涉犯詐欺、背信之事實提出告訴，並先、後於前揭\n    時間，在桃園地檢署檢察官偵查中再提出前揭借據供該承辦\n    檢察官核對之事實，惟矢口否認有行使或偽造私文書、詐欺\n    及誣告之犯行，辯稱：伊委請林慶炫仲介伊大陸配偶，曾交\n    付林慶炫11萬元之代辦費，惟系爭4 紙借據與上開代辦費用\n    無關，林慶炫確於借據上所載之日期向伊借錢，伊先後在住\n    處如數將現金借予林慶炫後，林慶炫即簽立借據交予伊，伊\n    外甥女張紜瑄及父親王偉忠皆有看到伊借錢給林慶炫，伊拿\n    到收據後就在借據上填寫「借據」2 字，並謄抄其上之日期\n    於借據下方，至如附表編號1 所示借據上所載「辦資料」也\n    是伊填寫的，因為林慶炫第一次向伊借錢時表示要繳交房貸\n    ，因此伊才寫「辦資料」，另附表編號2 所示借據上所載「\n    辦機票」則是林慶炫自己寫的，伊告訴林慶炫隨便寫理由就\n    可以，因為伊不怕林慶炫跑掉，伊並沒有偽造借據及誣告林\n    慶炫云云。經查：\n(一)、被告於97年11月4 日具狀對被害人林慶炫提起清償債務之民\n    事訴訟，並將如附表所示增寫後之借據4 紙影本提出於本院\n    桃園簡易庭，嗣於97年12月2 日本院桃園簡易庭97年度桃簡\n    字第1483號清償債務案件調解時，提出前開借據4 紙供承辦\n    法官核對而行使之，經本院桃園簡易庭承辦法官審理結果，\n    認被害人林慶炫經合法通知未到庭且被告已提出前揭借據為\n    證，以一造辯論判決被告全部勝訴確定，嗣被告持上開民事\n    確定判決對被害人林慶炫之財產聲請強制執行等情，為被告\n    所不否認，並有如附表所示之收據4 紙扣案可查，及本院桃\n    院永98司執珩字第14243 號債權憑證、執行命令等件影本在\n    卷可稽（見桃園地檢署98年度他字第1544號卷第33- 37頁）\n    ，且經本院審閱本院97年度桃簡字第1483號卷附97年11月 4\n    日起訴狀、97年12月2 日調解程序筆錄、民事判決、確定證\n    明書無訛（見本院97年度桃簡字第1483號影卷第4-9、15、1\n    9-21、24頁），此部分事實，應堪認定。又被告於98年8 月\n    16日前往埔子派出所向職司刑事偵查輔助之司法警察洪耀武\n    申告被害人林慶炫於附表所示之日期向其借款12萬元，隨即\n    避不見面云云，對被害人林慶炫提出詐欺及背信告訴，案經\n    桃園縣政府警察局桃園分局於98年10月12日報請桃園地檢署\n    併該署99年度他字第1544號被告詐欺案件偵辦，被告於98年\n    10月23日承辦檢察官就其所涉詐欺等案件訊問時，提出前揭\n    收據4紙予檢察官拍照存證，復於99年3月3 日該承辦檢察官\n    就其與被害人林慶炫所涉詐欺案件訊問時，再提出前揭收據\n    4 紙予檢察官核對，經該檢察官當場扣案，嗣被害人林慶炫\n    所涉詐欺等案件，經該檢察官偵查結果，認前開收據4 紙均\n    係被告增註文字於上，非被害人林慶炫向被告借款，被害人\n    林慶炫罪嫌不足，而以99年度偵字第18068 號為不起訴處分\n    ，被告不服聲請再議，經臺灣高等法院檢察署以99年度上聲\n    議第6904號駁回其再議之聲請而確定之事實，亦為被告所不\n    否認，且有埔子派出所98年8 月16日調查筆錄、桃園地檢署\n    98年10月23日及99年3月3日訊問筆錄、桃園地檢署檢察官99\n    年度偵字第18068 號不起訴處分書、臺灣高等法院檢察署99\n    年度上聲議字第6904號處分書在卷可稽（見同上他字卷第68\n    、73-74、145頁、桃園地檢署99年度偵字第18068號影卷第4\n    頁及背面、本院99年度訴字第939 號卷第33頁），亦堪認定\n    。\n(二)、被告雖辯稱被害人林慶炫係向其借錢而簽發如附表所示之借\n    據交予其收執云云，惟據證人林慶炫於檢察官訊問時證稱：\n    4張收據上之「借據」2字都是被告所寫，筆跡明顯不同，編\n    號1所示收據下方之「中華民國元月5日」是被告所寫，其他\n    記載則為伊於96年1月5日在被告家中客廳所填寫，因被告想\n    要去大陸結婚，伊要請別人辦一些結婚資料，例如公證、台\n    胞證、入台證等費用；編號2 所示收據上方「借據」、最後\n    一行「中華民國96年1 月10日」是被告所寫，其他記載則是\n    伊於96年1月10日在被告家中客廳所寫；編號3所示收據上方\n    「借據」、「拿」、最後一行「中華民國96年1 月13日」、\n    「Ｚ000000000」是被告自行填寫，其他記載則是於96年1月1\n    3 日在大陸福建住宿處，伊向被告拿4萬元時所寫；編號4所\n    示收據上方「96年7月8日」應為「96年1月8日」，被告將「\n    1」改成「7」，「借據」、「中華民國96年7月8日」亦是被\n    告所寫，其他記載則是伊於96年1月8日在被告家中客廳所寫\n    ，拿錢的目的就是要辦機票，這筆錢應該接續在編號1 後面\n    ，因為辦機票是去大陸娶新娘的第2個程序，編號1部分算是\n    定金，辦妥之後就要訂機票，再接著是編號2 的錢應該算是\n    第3 個程序，算是在大陸婚宴的相關雜費支出，這些費用要\n    先跟被告拿，以免被告後悔，編號3的錢應該是第4個程序，\n    是伊與被告已經在大陸，還有陸續在大陸拍照、住宿的費用\n    ，伊與被告的費用分開算，故這4 筆金錢是伊幫被告娶大陸\n    新娘支出的相關費用，有行程表可證；伊於96年1月8日去拿\n    機票，所以才跟被告拿錢，機票1 人是14,900元，伊機票錢\n    也是被告出的，有相關帳款明細可以證明，另外被告結婚時\n    在大陸的時間是96年1 月12日至同年月19日，伊與被告有合\n    照照片；如果伊是向被告借錢，不可能寫辦機票、辦資料等\n    字句，實際上的代辦費用就是這4 筆單據所載，被告並沒有\n    於95年12月30日在其住處1 次交付11萬元的沒人酬勞給伊等\n    語（見同上他字卷第129- 131頁），證人林慶炫證述情節與\n    常情並無相悖之處，且審閱證人林慶炫於檢察官訊問時提出\n    之友福旅行社有限公司應收帳款明細表、旅客行程表、被告\n    迎娶大陸配偶照片及卷附被告入出境查詢結果（見同上他字\n    卷第141-143 頁背面、本院99年度939 號卷第12頁），循皆\n    與其前開證述為被告代辦台胞證、訂機票及與被告一同前往\n    大陸地區之時間、情節均相符，堪認證人林慶炫確曾於96年\n    1月5日委託友福旅行辦理其與被告前往大陸地區使用之台胞\n    證簽章，且於96年1月8日支付其與被告2 人之機票費及前述\n    簽章費用共計29,800元，渠2人搭乘96年1月12日班機前往大\n    陸地區為被告迎娶大陸配偶等情，應屬事實，證人林慶炫前\n    開證述情節應非虛假而具有相當之可信度。\n(三)、至被告辯稱其於如附表所示之日期，在其家中將借款交付被\n    害人林慶炫云云，惟查：\n  1.被告於警詢時先係辯稱：借據上所載之「借據」2 字及日期\n    都是伊所寫，伊沒有將「96年1月8日」改為「96年7月8日」\n    ，這都是林慶炫在現場向伊拿錢時，要伊自行加上「借據」\n    2 字及押上日期；林慶炫打電話給伊表示需錢繳納房租，所\n    以伊才借錢給林慶炫，伊於95年12月30日就一次將仲介大陸\n    配偶之費用11萬元交予林慶炫，而林慶炫提供之借據係伊結\n    婚後，林慶炫私底下向伊借的，與娶大陸配偶一事不相關云\n    云（見同上他字卷第20頁背面-21 頁背面），然觀諸前開友\n    福旅行社有限公司旅客行程表、被告迎娶大陸配偶照片及被\n    告入出境查詢結果可知，被告應係於96年1 月12日至同年月\n    19日前往大陸地區迎娶大陸配偶，則若被告所辯其係於婚後\n    始貸予被害人林慶炫如附表所示之金錢一節屬實，則其顯非\n    於附表編號1、2號所示之96年1月5日、同年1 月10日將金錢\n    貸予被害人林慶炫，而被告於收受與實際借貸日期不相符之\n    收據時，除未向被害人林慶炫要求更正，顯與常情相違外，\n    甚且被告於向本院桃園簡易庭具狀對被害人林慶炫提出清償\n    債務之民事訴訟時，其事實仍記載被害人林慶炫係於96年 1\n    月5日、96年1月10日向其借款等情，有該起訴狀、存證信函\n    影本在卷可查（見本院97年度桃簡字第1483號影卷第5、7頁\n    ），被告於本院審理時亦稱：林慶炫向伊借12萬元的時間就\n    是4 張借據上所記載的日期（見本院99年度訴字第939 號卷\n    第44頁），與其辯稱結婚後始貸予被害人林慶炫金錢一節，\n    明顯不一，被告此部分所辯，要難採信。\n  2.被告於98年7月15日檢察官訊問時則供陳：這4張借據是林慶\n    炫向伊借款時親自簽名、蓋手印，至「借據」2 字及日期是\n    在伊家中，當著伊父親、姐姐及林慶炫面前，伊增添上去的\n    ，伊填寫時去林慶炫沒有意見云云（見同上他卷第45頁），\n    然於98年8月5日檢察官訊問時旋即改稱：林慶炫簽立借據時\n    ，伊父親王偉忠有在家，但是伊父親當時在看電視，沒有親\n    眼目睹伊簽立借據，但王偉忠知道林慶炫向伊借款，錢是伊\n    交給林慶炫，並不是王偉忠交給林慶炫云云（見同上他字卷\n    第50頁）。觀諸被告前、後所述其父親王偉忠有無目睹被害\n    人林慶炫簽立如附表所示收據及其在該收據上增寫如附表所\n    示之文字，說詞反覆。而證人王偉忠於檢察官訊問時證稱：\n    伊認識林慶炫，林慶炫要幫被告介紹大陸新娘，故曾到伊家\n    中收取仲介費，伊拿給被告快13萬元，由被告在伊家中交給\n    林慶炫，錢都被林慶炫拿去了，但伊不知道林慶炫將錢用到\n    何處；伊有看過卷附的借據，這是林慶炫另外向被告借的錢\n    ，上面「辦機票」等字是林慶炫自己寫的，伊不清楚這樣寫\n    是不是辦理借到大陸新娘的費用，伊也沒有看到林慶炫與被\n    告在寫借據等情（見同上偵卷第50頁），證人王偉忠雖證述\n    扣案之借據均係被害人林慶炫向被告借款時所書立之憑據，\n    且如附表編號2 所示借據上之「辦機票」等文字係被害人林\n    慶炫所填寫，惟觀諸證人王偉忠上開證述，其未親眼目睹被\n    害人林慶炫與被告借款情節，亦未見到被害人林慶炫與被告\n    簽立借據之經過，且就借據上因何記載「辦機票」一節，亦\n    證述其不知情，則其所述該借據所載內容係被害人林慶炫向\n    被告借款云云，顯係其個人自行推測之詞，不足採信，反可\n    徵之被告所辯其於如附表所示之借據4 紙增寫文字，係在證\n    人王偉忠及被害人林慶炫面前所填載，而被害人林慶炫當時\n    亦無意見云云，應屬虛構，不足採信。\n  3.再者，被告於99年2月4日檢察官訊問時先係辯稱：這4 筆借\n    款時間都是在借據上所載時間，地點都在伊家中客廳，由林\n    慶炫親自向伊借的，至於林慶炫為何不寫「借據」等字，伊\n    不清楚云云；經檢察官究明其既已於96年1 月13日隨同被害\n    人林慶炫前往大陸，如何能於99年1 月12日在其家中將借款\n    交予被害人林慶炫，被告隨即改稱：應該是96年1 月12日凌\n    晨在機場交給林慶炫的，是林慶炫說到機場再將錢交給他云\n    云（見同上他字卷第131 頁），被告就其在何時、地將所稱\n    之借款交予被害人林慶炫一節，前後所述情節差距甚大；被\n    告於99年11月8 日本院準備程序時復再辯稱：借款金額是林\n    慶炫與伊父親王偉忠接洽的，如附表所示之借據係於借據上\n    所載日期在伊家中所寫，林慶炫分4 次向伊父親王偉忠借錢\n    ，96年1月5日拿15,000元、96年1 月10日拿30,000元、96年\n    1月13日拿40,000元、96年7月8 日拿35,000元，且均係伊父\n    親王偉忠在桃園縣桃園市○○○街38號家中拿現金給林慶炫\n    云云（見本院99年度審訴字第1786號卷第29頁背面-30 頁）\n    ，被告辯稱於如附表所示借據所載之時間貸予被害人林慶炫\n    金錢，除與警詢時所辯係婚後始貸予被害人林慶炫不符外，\n    其所辯於96年1 月13日在住處借予被害人林慶炫40,000元，\n    亦核與前揭友福旅行社有限公司旅客行程表及卷附被告入出\n    境資訊連結作業查詢結果（見本院99年度訴字第939 號卷第\n    12頁）所示，被告與被害人林慶炫係於96年1 月12日經由香\n    港地區轉機至大陸福建省福州市之事實顯然不符，此外，其\n    辯稱係證人王偉忠在住處將現金交予被害人林慶炫一節，更\n    與其先前於檢察官訊問時所辯：錢係伊交給林慶炫，並不是\n    王偉忠交給林慶炫云云（見同上他字卷第50頁）及於本院審\n    理時所辯：林慶炫第1、2次來借錢時，伊有跟伊父親說，伊\n    父親沒有說話，只有點頭，錢伊就從家裡拿出來，林慶炫來\n    借第3 次錢時，錢從家裡拿出來，這次伊沒有告訴伊父親等\n    情（見本院99年度訴字第939 號卷第44頁背面），核屬迥異\n    ，況依證人王偉忠在偵查中之供述可知，證人王偉忠並無借\n    款予被害人林慶炫，是被告前後不一之辯解，均無足採信。\n  4.被告於本院準備程序時固再辯稱：林慶炫先以電話和伊聯絡\n    借錢一事，然後林慶炫就到伊家拿錢，伊將錢當場清點給林\n    慶炫，伊父親王偉忠、外甥女張紜瑄均在場，張紜瑄每筆借\n    款都有見到云云（見本院99年度訴字第939 號卷第13頁背面\n    -14、22頁背面-23頁背面），被告辯稱係其將金錢交予被害\n    人林慶炫，核與其前述由證人王偉忠將金錢交予被害人林慶\n    炫一情，自相矛盾，且證人張紜瑄於本院審理時證稱：伊有\n    見到林慶炫到伊與被告之住處，林慶炫來的時候都在1 樓，\n    伊有時候從2樓下去1樓廚房拿東西時，有看到林慶炫，但伊\n    不知道被告與林慶炫之間有無債務關係，伊只知道渠2 人有\n    講到金錢，但情形伊不清楚，林慶炫簽立4 張借據時，伊沒\n    有在場，伊亦不暸解渠2人為何要簽立這4張借據等語（見本\n    院99年度訴字第939 號卷第23-23 背面頁），證人張紜瑄未\n    親見被告貸予被害人林慶炫如附表所示借據內容之4 筆金錢\n    ，與被告所辯其將金錢貸交予被害人林慶炫時，證人張紜瑄\n    皆有見到云云不符，被告此部分所辯，顯屬虛妄之詞。又被\n    告於本院審理時另辯稱：於96年1 月13日那筆借款是伊與林\n    慶炫到了福州金山大飯店後，林慶炫向伊借的，伊是在飯店\n    房間將錢交給林慶炫，但是林慶炫寫錯日期，正確日期應該\n    是96年1月12日，林慶炫寫成96年1月13日云云（見本院99年\n    度訴字第939 號卷第24頁），不僅與被告於檢察官訊問時辯\n    稱其係於96年1 月12日在機場交予被害人林慶炫等情相悖（\n    見同上他字卷第131 頁），復與被告於本院準備程序、審理\n    時歷次所辯該4 筆借款均在其家中以現金清點交予被害人林\n    慶炫云云不符，益徵被告諸多辯解，實屬臨訟卸責之詞。\n  5.至被告於本院審理時雖再辯稱：林慶炫向伊借貸如附表編號\n    4 所示之金錢時，伊父親從中國信託商業銀行之帳戶內提領\n    出來，再借予被害人林慶炫云云（見本院99年度訴字第 939\n    號卷第44頁背面），惟觀諸被告提出之中國信託商業銀行提\n    款憑證影本（見同上他字卷第65頁），僅足證明被告之父親\n    王偉忠曾於96年5 月14日自其帳戶轉匯10萬元至被告帳戶內\n    ，然此與被告所稱之第4 筆借款日期96年7月8日相距甚遠，\n    是此部分並無法為有利於被告之認定。\n  6.觀諸被告上開所辯，被告對於借款之時間、地點、金錢之來\n    源，多次供述互有歧異，已非可採；另衡諸社會上個人間消\n    費借貸常情，率皆由借貸人書立借貸意旨之借據交予貸與人\n    收執，要無可能在借據上記載與消費借貸事實無關聯之其他\n    事由，然觀之卷附被害人林慶炫交予被告收執之如附表所示\n    收據4紙，其中編號1收據記載「辦資料」，另編號2 之收據\n    則記載「辦機票」，均非一般消費借貸往來下，借貸人書寫\n    之事由甚明，反係與被害人林慶炫前開證述為被告辦理大陸\n    結婚事宜所收取之費用、機票費等情較相符合。從而，被告\n    辯稱其分別於如附表所示之時間貸予被告如附表所示之金錢\n    ，係屬虛構而非僅出於主觀上之誤認，且如附表所示之收據\n    4 紙，亦非被害人林慶炫於如附表所示之時間交予被告收執\n    之「借據」，而係被告將被害人林慶炫前所交付之「收據」\n    ，偽造成被害人林慶炫名義之借據後，再持以行使，並於被\n    害人林慶炫對其提出偽造文書及詐欺告訴後，復以此虛構之\n    借款事實對被害人林慶炫提出詐欺及背信告訴，應堪認定。\n(四)、綜上所述，本案事證明確，被告犯行洵堪認定，應依法論科\n    。\n二、論罪科刑：\n(一)、核被告就犯罪事實一、(一)所為，係犯刑法第216條、第210條\n    之行使偽造私文書罪及刑法第339條第2項詐欺得利罪。公訴\n    人認被告此部分犯行係涉犯刑法第339條第3項、第2 項之詐\n    欺得利未遂罪云云，惟按上訴人因權利人提起民事訴訟向其\n    追取租仔，先後在受訴法院提出偽契，主張受當該田，及已\n    代為贖回，否認付租義務，自係連續行使偽造私文書，以詐\n    術圖得財產上不法之利益，既經民事判決勝訴確定在案，其\n    詐欺即屬既遂，最高法院29年上字第2118號判例可資參照。\n    查被告提出如附表所示之偽造收據4 紙向本院桃園簡易庭主\n    張其對被害人林慶炫有12萬元之消費借貸債權，致本院承辦\n    法官陷於錯誤而以97年度桃簡字第1483號案件判決被告勝訴\n    確定在案，已認定如前所述，揆諸上開見解，被告前開詐欺\n    犯行，應屬既遂，公訴人認被告詐欺得利犯行僅屬未遂，容\n    有誤會，惟既遂、未遂乃犯罪之階段行為，毋庸變更起訴法\n    條，附此敘明。又按行使影本，作用與原本相同，偽造私文\n    書後，持以行使其影本，偽造之低度行為為高度之行使行為\n    所吸收，應論以行使偽造私文書罪，最高法院70年臺上字第\n    1107號判例參照。查被告偽造如附表所示之收據4 紙後復持\n    影本及原本以行使，其偽造之低度行為則為行使之高度行為\n    所吸收，不另論罪。又被告所犯2 次行使偽造私文書之犯行\n    ，均係出於其向本院訛稱被害人林慶炫曾向其借貸之目的而\n    為之，侵害之法益相同，各行為之獨立性極為薄弱，依一般\n    社會健全觀念，在時間差距上難以強行分開，在刑法評價上\n    ，以視為數個舉動之接續施行，合為包括之一行為予以評價\n    ，較為合理，顯係基於單一行使偽造私文書犯意下之接續行\n    為，只論以接續犯之單純一罪為已足。又被告以一行使偽造\n    之私文書方法，同時觸犯行使偽造私文書罪及詐欺得利罪，\n    為想像競合犯，應從一重之行使偽造私文書罪處斷。\n(二)、按刑法上之誣告罪，本不限於所告事實全屬虛偽時，始能成\n    立，倘所告事實之一部分係出於故意虛構，仍不得謂非誣告\n    。最高法院20年上字第662 號判例意旨可資參照。查被告係\n    以虛構之借款情節，向埔子派出所職司刑事偵查輔助之司法\n    警察洪耀武申告被害人林慶炫涉犯背信、詐欺罪嫌，已認定\n    如前所述，則被告與被害人林慶炫間縱另有債權債務關係存\n    在，惟被害人林慶炫既未曾於如附表所示之時間向被告借貸\n    金錢，被告竟仍提出如附表所示借據4 紙，指訴被害人林慶\n    炫於如附表所示時間向其借款4 次之事實而告訴被害人林慶\n    炫涉犯詐欺、背信罪嫌，顯有以此虛構之事實，使被害人林\n    慶炫受刑事追訴之意圖及故意，甚為灼然。核被告就犯罪事\n    實一、(二)所為，係犯刑法第216條、第210條之行使偽造私文\n    書罪、第169條第1項誣告罪。又按刑法第169條第2項之偽造\n    證據及使用罪，原屬同條第1 項誣告之預備行為，因其犯罪\n    之危險性較為重大，故不必實行誣告，仍予獨立處罰，如果\n    偽造此項證據持以誣告，除另犯其他罪名外，按照低度行為\n    吸收於高度行為之原則，祇應論以第一項之誣告罪名，不應\n    再適用第2 項從重處斷；次按意圖他人受刑事處分，向該管\n    公務員誣告，同時復使用偽造之證據，則其使用偽造證據之\n    行為，應為誣告行為所吸收，除應成立刑法第169條第1項之\n    罪外，固不應再以同條第2 項之罪相繩，但其使用偽造證據\n    ，若更觸犯其他罪名時，仍係一行為而犯數罪，應依刑法第\n    55條從一重處斷，不能並謂其所觸犯之其他罪名，亦為誣告\n    行為所吸收，而不得再行論處。最高法院30年上字第194 號\n    、28年上字第4086號判例意旨可資參照。查被告意圖他人受\n    刑事處分，向該管公務員誣告被害人林慶炫涉犯詐欺、背信\n    罪嫌，同時復使用偽造之證據，其使用偽造證據之低度行為\n    ，均為誣告之高度行為所吸收，不另論罪，公訴人雖未就被\n    告使用偽造證據之犯行起訴，惟該部分犯行與已敘及部分，\n    有吸收犯之實質上一罪關係，為起訴效力所及，本院自得併\n    予審理。又被告使用偽造證據之行為為誣告行為所吸收，而\n    其係以一行為同時犯行使偽造私文書罪及誣告罪，為想像競\n    合犯，自應從一重之誣告罪處斷。\n(三)、被告所犯上述偽造私文書罪及誣告罪，犯意各別，行為互殊\n    ，應予分論併罰。又被告有如事實欄所載之犯罪科刑紀錄及\n    執行情形，此有臺灣高等法院被告前案紀錄表在卷可稽，其\n    於受有期徒刑執行完畢後，5 年內故意再犯本件有期徒刑以\n    上之罪，均為累犯，均應依刑法第47條第1 項規定加重其刑\n    。爰審酌被告偽造證據，對被害人林慶炫提出民事告訴並濫\n    行提出詐欺及背信告訴，嚴重妨害司法公正性，並足使林慶\n    炫受有刑事處分之危險，造成司法調查程序之無益進行，妨\n    害司法正義之實現，且於犯後猶狡詞卸責，態度難認良好，\n    併其品行、犯罪動機、目的、手段、生活狀況、智識程度及\n    所生之損害等一切情狀，分別量處如主文所示之刑，並定其\n    應執行之刑，以示懲儆。\n三、沒收：扣案之如附表所示收據4 紙，均為供被告犯本罪所用\n    之物，且均屬被告所有，應依刑法第38條第1項第2款之規定\n    ，分別於被告所犯行使偽造文書罪、誣告罪所宣告之主刑項\n    下，分別諭知沒收。\n據上論斷，應依刑事訴訟法第299條第1 項前段，刑法第第216條\n、第210條、第339條第2項、第169條第1項、第47條第1項、第55\n條、第51條第5款、第38條第1項第2款，刑法施行法第1條之1 ，\n判決如主文。\n本案經檢察官蔡正傑到庭執行職務。\n中    華    民    國    100   年     3     月    8    日\n            刑事第四庭 審判長 法  官  張淑華\n                              法  官  張宇葭\n                              法  官  林維斌\n以上正本證明與原本無異。\n如不服本判決應於收受判決後10日內向本院提出上訴書狀，並應\n敘述具體理由。其未敘述上訴理由者，應於上訴期間屆滿後20日\n內向本院補提理由書( 均須按他造當事人之人數附繕本) 「切勿\n逕送上級法院」。\n                               書記官  鄭嘉惠"
  },
  "search": "臺灣桃園地方法院刑事判決99年度訴字第939號公訴人臺灣桃園地方法院檢察署檢察官被告王長孝上列被告因誣告等案件，經檢察官提起公訴（99年度偵字第18069號），本院判決如下：主文王長孝行使偽造私文書，足以生損害於公眾及他人，累犯，處有期徒刑肆月，扣案如附表所示偽造之借據肆紙均沒收。又意圖他人受刑事處分，向該管公務員誣告，累犯，處有期徒刑伍月，扣案如附表所示偽造之借據肆紙均沒收。應執行有期徒刑捌月，扣案如附表所示偽造之借據肆紙均沒收。事實一、王長孝於民國97年間，因違反毒品危害防制條例案件，經本院以97年度桃簡字第2300號判決判處有期徒刑3月確定，於97年10月20日易科罰金執行完畢。詎其猶不知悔改，分別為下列犯行：(一)王長孝於96年間委託林慶炫辦理大陸地區配偶仲介事宜，陸續於如附表所示之時間支付林慶炫總計新臺幣（下同）12萬元之代辦費用，林慶炫則簽立如附表所示偽造前內容之手寫收據4紙予王長孝收執，王長孝竟基於意圖為自己不法之所有及行使偽造私文書之犯意，明知林慶炫未曾於如附表所示時間向其借貸如附表所示之4筆款項，於其收受上開4紙收據後至97年11月4日間某時，在其位於桃園縣桃園市○○○街38號住處，將前揭4紙收據各增寫如附表所示之文字，以此方式偽造成如附表所示偽造後之內容，表彰係林慶炫名義書寫之借據4紙，偽造完成後，旋於97年11月4日某時，以前揭偽造之借據影本為附件，具狀向本院桃園民事簡易庭起訴請求林慶炫清償借款，復接續前開行使偽造私文書之犯意，於97年12月2日在本院桃園簡易庭行調解程序時，提出前開偽造之收據4紙供該承辦法官核對而行使之，因當日林慶炫經合法通知未到庭答辯，致使本院97年度桃簡字第1483號民事案件承辦法官陷於錯誤，於97年12月16日一造辯論判決王長孝之訴全部勝訴確定，足以生損害於林慶炫。(二)前開民事判決確定後，林慶炫之財產因遭法院強制執行，經林慶炫閱卷後，查知上情，林慶炫於98年4月6日具狀向臺灣桃園地方法院檢察署（下稱桃園地檢署）對王長孝提出詐欺及偽造文書之告訴。詎王長孝因林慶炫對其提出前開告訴，為求反制林慶炫，明知上開借據係其用以詐騙法院而自行偽造，且其與林慶炫間並無前揭12萬元之借款債務，竟另基於行使偽造私文書及意圖他人受刑事處分之犯意，於98年8月16日上午7時50分，前往桃園縣政府警察局桃園分局埔子派出所（下稱埔子派出所），向該派出所職司刑事偵查輔助機關之警員洪耀武提出前揭偽造之借據影本4紙，申告林慶炫向其提出前揭借據4紙而謊稱繳納房屋貸款等理由詐騙12萬元即避不見面云云，以此虛偽之借款事實對林慶炫提出詐欺及背信之告訴，嗣桃園縣政府警察局桃園分局於98年10月13日將林慶炫所涉詐欺及背信案件報請桃園地檢署併案偵辦。詎王長孝竟承前犯意，於98年10月23日桃園地檢署檢察官就其所涉詐欺及偽造文書案件訊問時，提出前揭偽造之借據4紙供該承辦檢察官核對而行使之，復於99年3月3日桃園地檢署檢察官就其與林慶炫所涉案件訊問時，提出前揭偽造之借據4紙供該承辦檢察官核對，藉此使該承辦檢察官信其所述為真實而行使之，經該承辦檢察官認前揭偽造之收據係該案件之重要證物而當庭扣押，嗣經偵查結果，該承辦檢察官因認前開扣案如附表所示之收據4紙，均係王長孝所偽造，並認林慶炫所涉詐欺、背信罪嫌嫌疑不足，以99年度偵字第18068號為不起訴處分，始查知上情。二、案經林慶炫訴請臺灣桃園地方法院檢察署檢察官偵查起訴。理由一、證據能力：(一)、按被告以外之人，於審判外之言詞或書面陳述，除法律有規定者外，不得作為證據。刑事訴訟法第159條第1項定有明文。被告以外之人（包括證人、鑑定人、告訴人、被害人及共同被告等）於審判外之言詞或書面陳述，即所謂傳聞證據。由於傳聞證據有悖法院直接審理及言詞審理之精神，妨礙當事人之反對詰問權，影響程序正義之實現，除法律有規定（例如同法第159條第2項、同法第159條之1至之5、同法第206條等）外，原則不具證據能力。查證人林慶炫於桃園縣政府警察局桃園分局之陳述（見臺灣桃園地方法院檢察署98年度他字第1544號卷第24-25頁背面），屬於被告以外之人於審判外之言詞及書面陳述，被告明確主張上開證人之陳述無證據能力，公訴人復未指出上開陳述有何特別可信之情形，本院既查無上開例外得以之作為證據之各種情形，因此認定上開陳述，應無證據能力。(二)、次按被告以外之人於偵訊中向檢察官所為之陳述，除顯有不可信之情況者外，得為證據，刑事訴訟法第159條之1第2項定有明文。而所謂不可信情況之認定，法院應審酌被告以外之人於陳述時之外在環境及情況，例如：陳述時之心理狀況、有無受到外力干擾等，以為判斷之依據，故係決定陳述有無證據能力，而非決定陳述內容之證明力。是被告以外之人前於偵查中已具結而為證述，除反對該項供述得具有證據能力之一方，已釋明「顯有不可信之情況」之理由外，皆得為證據；又司法實務運作上，咸認偵查中檢察官向被告以外之人所取得之陳述，原則上均能遵守法律規定，不致違法取供，被告以外之人於偵查中依法應具結者已具結，向檢察官所為之陳述，原則上具有證據能力。另未經被告詰問之被告以外之人於偵查中向檢察官所為之陳述，依刑事訴訟法第159條之1第2項之規定，原則上屬於法律規定為有證據能力之傳聞證據，於例外顯有不可信之情況，始否定其得為證據。是得為證據之被告以外之人於偵查中所為之陳述，因其陳述未經被告詰問，應認屬於未經合法調查之證據，並非無證據能力，而禁止證據之使用。惟是否行使詰問權，屬被告之自由，倘被告於審判中捨棄詰問權，或證人客觀上有不能受詰問之情形，自無不當剝奪被告詰問權行使之可言（最高法院99年度臺上字第4125號判決參照)。被告雖於本準備程序時明確表示證人林慶炫於檢察官訊問時之證述無證據能力云云（見本院99年度審訴字第1786號卷第31頁），惟查，證人林慶炫於檢察官訊問時係以證人身分作證，經檢察官告以具結之義務及偽證之處罰，並經具結而陳述，且無證據顯示其等所為證言係遭受強暴、脅迫、詐欺、利誘等外力干擾取得，並無顯不可信之情況，故其於檢察官偵訊中之證述，揆諸前開說明，自有證據能力。而被告迄至言詞辯論終結前，均未聲請傳喚詰問上開證人，且於審判期日經審判長詢問尚有何證據請求調查時，亦皆答稱沒有，被告既已認無傳喚上開證人之必要，則無不當剝奪被告詰問權之行使。是本院於審判期日依法定程序提示上開證人於檢察官訊問時之筆錄，並告以要旨，即已為合法調查，自得作為證據。(三)、至本院認定事實所引用之其他證據資料，並無證據證明係公務員違背法定程序所取得，且被告對其證據能力未表示爭執，迄至言詞辯論終結前亦未再聲明異議，經核亦無顯有不可信之情況與不得作為證據之情形，本院審酌上開證據資料製作時之情況，尚無違法不當及證明力明顯過低之瑕疵，認為以之作為證據應屬適當，是依刑事訴訟法第159條至第159條之5規定，均認有證據能力。二、訊據被告王長孝固不否認其於被害人林慶炫交付之收據上增寫如附表所示之文字，且於前揭時間持向本院桃園簡易庭對被害人林慶炫起訴請求清償借款並提出供承辦法官核對而獲勝訴判決確定，及其於前揭時間持向埔子派出所警員對被害人林慶炫涉犯詐欺、背信之事實提出告訴，並先、後於前揭時間，在桃園地檢署檢察官偵查中再提出前揭借據供該承辦檢察官核對之事實，惟矢口否認有行使或偽造私文書、詐欺及誣告之犯行，辯稱：伊委請林慶炫仲介伊大陸配偶，曾交付林慶炫11萬元之代辦費，惟系爭4紙借據與上開代辦費用無關，林慶炫確於借據上所載之日期向伊借錢，伊先後在住處如數將現金借予林慶炫後，林慶炫即簽立借據交予伊，伊外甥女張紜瑄及父親王偉忠皆有看到伊借錢給林慶炫，伊拿到收據後就在借據上填寫「借據」2字，並謄抄其上之日期於借據下方，至如附表編號1所示借據上所載「辦資料」也是伊填寫的，因為林慶炫第一次向伊借錢時表示要繳交房貸，因此伊才寫「辦資料」，另附表編號2所示借據上所載「辦機票」則是林慶炫自己寫的，伊告訴林慶炫隨便寫理由就可以，因為伊不怕林慶炫跑掉，伊並沒有偽造借據及誣告林慶炫云云。經查：(一)、被告於97年11月4日具狀對被害人林慶炫提起清償債務之民事訴訟，並將如附表所示增寫後之借據4紙影本提出於本院桃園簡易庭，嗣於97年12月2日本院桃園簡易庭97年度桃簡字第1483號清償債務案件調解時，提出前開借據4紙供承辦法官核對而行使之，經本院桃園簡易庭承辦法官審理結果，認被害人林慶炫經合法通知未到庭且被告已提出前揭借據為證，以一造辯論判決被告全部勝訴確定，嗣被告持上開民事確定判決對被害人林慶炫之財產聲請強制執行等情，為被告所不否認，並有如附表所示之收據4紙扣案可查，及本院桃院永98司執珩字第14243號債權憑證、執行命令等件影本在卷可稽（見桃園地檢署98年度他字第1544號卷第33-37頁），且經本院審閱本院97年度桃簡字第1483號卷附97年11月4日起訴狀、97年12月2日調解程序筆錄、民事判決、確定證明書無訛（見本院97年度桃簡字第1483號影卷第4-9、15、19-21、24頁），此部分事實，應堪認定。又被告於98年8月16日前往埔子派出所向職司刑事偵查輔助之司法警察洪耀武申告被害人林慶炫於附表所示之日期向其借款12萬元，隨即避不見面云云，對被害人林慶炫提出詐欺及背信告訴，案經桃園縣政府警察局桃園分局於98年10月12日報請桃園地檢署併該署99年度他字第1544號被告詐欺案件偵辦，被告於98年10月23日承辦檢察官就其所涉詐欺等案件訊問時，提出前揭收據4紙予檢察官拍照存證，復於99年3月3日該承辦檢察官就其與被害人林慶炫所涉詐欺案件訊問時，再提出前揭收據4紙予檢察官核對，經該檢察官當場扣案，嗣被害人林慶炫所涉詐欺等案件，經該檢察官偵查結果，認前開收據4紙均係被告增註文字於上，非被害人林慶炫向被告借款，被害人林慶炫罪嫌不足，而以99年度偵字第18068號為不起訴處分，被告不服聲請再議，經臺灣高等法院檢察署以99年度上聲議第6904號駁回其再議之聲請而確定之事實，亦為被告所不否認，且有埔子派出所98年8月16日調查筆錄、桃園地檢署98年10月23日及99年3月3日訊問筆錄、桃園地檢署檢察官99年度偵字第18068號不起訴處分書、臺灣高等法院檢察署99年度上聲議字第6904號處分書在卷可稽（見同上他字卷第68、73-74、145頁、桃園地檢署99年度偵字第18068號影卷第4頁及背面、本院99年度訴字第939號卷第33頁），亦堪認定。(二)、被告雖辯稱被害人林慶炫係向其借錢而簽發如附表所示之借據交予其收執云云，惟據證人林慶炫於檢察官訊問時證稱：4張收據上之「借據」2字都是被告所寫，筆跡明顯不同，編號1所示收據下方之「中華民國元月5日」是被告所寫，其他記載則為伊於96年1月5日在被告家中客廳所填寫，因被告想要去大陸結婚，伊要請別人辦一些結婚資料，例如公證、台胞證、入台證等費用；編號2所示收據上方「借據」、最後一行「中華民國96年1月10日」是被告所寫，其他記載則是伊於96年1月10日在被告家中客廳所寫；編號3所示收據上方「借據」、「拿」、最後一行「中華民國96年1月13日」、「Ｚ000000000」是被告自行填寫，其他記載則是於96年1月13日在大陸福建住宿處，伊向被告拿4萬元時所寫；編號4所示收據上方「96年7月8日」應為「96年1月8日」，被告將「1」改成「7」，「借據」、「中華民國96年7月8日」亦是被告所寫，其他記載則是伊於96年1月8日在被告家中客廳所寫，拿錢的目的就是要辦機票，這筆錢應該接續在編號1後面，因為辦機票是去大陸娶新娘的第2個程序，編號1部分算是定金，辦妥之後就要訂機票，再接著是編號2的錢應該算是第3個程序，算是在大陸婚宴的相關雜費支出，這些費用要先跟被告拿，以免被告後悔，編號3的錢應該是第4個程序，是伊與被告已經在大陸，還有陸續在大陸拍照、住宿的費用，伊與被告的費用分開算，故這4筆金錢是伊幫被告娶大陸新娘支出的相關費用，有行程表可證；伊於96年1月8日去拿機票，所以才跟被告拿錢，機票1人是14,900元，伊機票錢也是被告出的，有相關帳款明細可以證明，另外被告結婚時在大陸的時間是96年1月12日至同年月19日，伊與被告有合照照片；如果伊是向被告借錢，不可能寫辦機票、辦資料等字句，實際上的代辦費用就是這4筆單據所載，被告並沒有於95年12月30日在其住處1次交付11萬元的沒人酬勞給伊等語（見同上他字卷第129-131頁），證人林慶炫證述情節與常情並無相悖之處，且審閱證人林慶炫於檢察官訊問時提出之友福旅行社有限公司應收帳款明細表、旅客行程表、被告迎娶大陸配偶照片及卷附被告入出境查詢結果（見同上他字卷第141-143頁背面、本院99年度939號卷第12頁），循皆與其前開證述為被告代辦台胞證、訂機票及與被告一同前往大陸地區之時間、情節均相符，堪認證人林慶炫確曾於96年1月5日委託友福旅行辦理其與被告前往大陸地區使用之台胞證簽章，且於96年1月8日支付其與被告2人之機票費及前述簽章費用共計29,800元，渠2人搭乘96年1月12日班機前往大陸地區為被告迎娶大陸配偶等情，應屬事實，證人林慶炫前開證述情節應非虛假而具有相當之可信度。(三)、至被告辯稱其於如附表所示之日期，在其家中將借款交付被害人林慶炫云云，惟查：1.被告於警詢時先係辯稱：借據上所載之「借據」2字及日期都是伊所寫，伊沒有將「96年1月8日」改為「96年7月8日」，這都是林慶炫在現場向伊拿錢時，要伊自行加上「借據」2字及押上日期；林慶炫打電話給伊表示需錢繳納房租，所以伊才借錢給林慶炫，伊於95年12月30日就一次將仲介大陸配偶之費用11萬元交予林慶炫，而林慶炫提供之借據係伊結婚後，林慶炫私底下向伊借的，與娶大陸配偶一事不相關云云（見同上他字卷第20頁背面-21頁背面），然觀諸前開友福旅行社有限公司旅客行程表、被告迎娶大陸配偶照片及被告入出境查詢結果可知，被告應係於96年1月12日至同年月19日前往大陸地區迎娶大陸配偶，則若被告所辯其係於婚後始貸予被害人林慶炫如附表所示之金錢一節屬實，則其顯非於附表編號1、2號所示之96年1月5日、同年1月10日將金錢貸予被害人林慶炫，而被告於收受與實際借貸日期不相符之收據時，除未向被害人林慶炫要求更正，顯與常情相違外，甚且被告於向本院桃園簡易庭具狀對被害人林慶炫提出清償債務之民事訴訟時，其事實仍記載被害人林慶炫係於96年1月5日、96年1月10日向其借款等情，有該起訴狀、存證信函影本在卷可查（見本院97年度桃簡字第1483號影卷第5、7頁），被告於本院審理時亦稱：林慶炫向伊借12萬元的時間就是4張借據上所記載的日期（見本院99年度訴字第939號卷第44頁），與其辯稱結婚後始貸予被害人林慶炫金錢一節，明顯不一，被告此部分所辯，要難採信。2.被告於98年7月15日檢察官訊問時則供陳：這4張借據是林慶炫向伊借款時親自簽名、蓋手印，至「借據」2字及日期是在伊家中，當著伊父親、姐姐及林慶炫面前，伊增添上去的，伊填寫時去林慶炫沒有意見云云（見同上他卷第45頁），然於98年8月5日檢察官訊問時旋即改稱：林慶炫簽立借據時，伊父親王偉忠有在家，但是伊父親當時在看電視，沒有親眼目睹伊簽立借據，但王偉忠知道林慶炫向伊借款，錢是伊交給林慶炫，並不是王偉忠交給林慶炫云云（見同上他字卷第50頁）。觀諸被告前、後所述其父親王偉忠有無目睹被害人林慶炫簽立如附表所示收據及其在該收據上增寫如附表所示之文字，說詞反覆。而證人王偉忠於檢察官訊問時證稱：伊認識林慶炫，林慶炫要幫被告介紹大陸新娘，故曾到伊家中收取仲介費，伊拿給被告快13萬元，由被告在伊家中交給林慶炫，錢都被林慶炫拿去了，但伊不知道林慶炫將錢用到何處；伊有看過卷附的借據，這是林慶炫另外向被告借的錢，上面「辦機票」等字是林慶炫自己寫的，伊不清楚這樣寫是不是辦理借到大陸新娘的費用，伊也沒有看到林慶炫與被告在寫借據等情（見同上偵卷第50頁），證人王偉忠雖證述扣案之借據均係被害人林慶炫向被告借款時所書立之憑據，且如附表編號2所示借據上之「辦機票」等文字係被害人林慶炫所填寫，惟觀諸證人王偉忠上開證述，其未親眼目睹被害人林慶炫與被告借款情節，亦未見到被害人林慶炫與被告簽立借據之經過，且就借據上因何記載「辦機票」一節，亦證述其不知情，則其所述該借據所載內容係被害人林慶炫向被告借款云云，顯係其個人自行推測之詞，不足採信，反可徵之被告所辯其於如附表所示之借據4紙增寫文字，係在證人王偉忠及被害人林慶炫面前所填載，而被害人林慶炫當時亦無意見云云，應屬虛構，不足採信。3.再者，被告於99年2月4日檢察官訊問時先係辯稱：這4筆借款時間都是在借據上所載時間，地點都在伊家中客廳，由林慶炫親自向伊借的，至於林慶炫為何不寫「借據」等字，伊不清楚云云；經檢察官究明其既已於96年1月13日隨同被害人林慶炫前往大陸，如何能於99年1月12日在其家中將借款交予被害人林慶炫，被告隨即改稱：應該是96年1月12日凌晨在機場交給林慶炫的，是林慶炫說到機場再將錢交給他云云（見同上他字卷第131頁），被告就其在何時、地將所稱之借款交予被害人林慶炫一節，前後所述情節差距甚大；被告於99年11月8日本院準備程序時復再辯稱：借款金額是林慶炫與伊父親王偉忠接洽的，如附表所示之借據係於借據上所載日期在伊家中所寫，林慶炫分4次向伊父親王偉忠借錢，96年1月5日拿15,000元、96年1月10日拿30,000元、96年1月13日拿40,000元、96年7月8日拿35,000元，且均係伊父親王偉忠在桃園縣桃園市○○○街38號家中拿現金給林慶炫云云（見本院99年度審訴字第1786號卷第29頁背面-30頁），被告辯稱於如附表所示借據所載之時間貸予被害人林慶炫金錢，除與警詢時所辯係婚後始貸予被害人林慶炫不符外，其所辯於96年1月13日在住處借予被害人林慶炫40,000元，亦核與前揭友福旅行社有限公司旅客行程表及卷附被告入出境資訊連結作業查詢結果（見本院99年度訴字第939號卷第12頁）所示，被告與被害人林慶炫係於96年1月12日經由香港地區轉機至大陸福建省福州市之事實顯然不符，此外，其辯稱係證人王偉忠在住處將現金交予被害人林慶炫一節，更與其先前於檢察官訊問時所辯：錢係伊交給林慶炫，並不是王偉忠交給林慶炫云云（見同上他字卷第50頁）及於本院審理時所辯：林慶炫第1、2次來借錢時，伊有跟伊父親說，伊父親沒有說話，只有點頭，錢伊就從家裡拿出來，林慶炫來借第3次錢時，錢從家裡拿出來，這次伊沒有告訴伊父親等情（見本院99年度訴字第939號卷第44頁背面），核屬迥異，況依證人王偉忠在偵查中之供述可知，證人王偉忠並無借款予被害人林慶炫，是被告前後不一之辯解，均無足採信。4.被告於本院準備程序時固再辯稱：林慶炫先以電話和伊聯絡借錢一事，然後林慶炫就到伊家拿錢，伊將錢當場清點給林慶炫，伊父親王偉忠、外甥女張紜瑄均在場，張紜瑄每筆借款都有見到云云（見本院99年度訴字第939號卷第13頁背面-14、22頁背面-23頁背面），被告辯稱係其將金錢交予被害人林慶炫，核與其前述由證人王偉忠將金錢交予被害人林慶炫一情，自相矛盾，且證人張紜瑄於本院審理時證稱：伊有見到林慶炫到伊與被告之住處，林慶炫來的時候都在1樓，伊有時候從2樓下去1樓廚房拿東西時，有看到林慶炫，但伊不知道被告與林慶炫之間有無債務關係，伊只知道渠2人有講到金錢，但情形伊不清楚，林慶炫簽立4張借據時，伊沒有在場，伊亦不暸解渠2人為何要簽立這4張借據等語（見本院99年度訴字第939號卷第23-23背面頁），證人張紜瑄未親見被告貸予被害人林慶炫如附表所示借據內容之4筆金錢，與被告所辯其將金錢貸交予被害人林慶炫時，證人張紜瑄皆有見到云云不符，被告此部分所辯，顯屬虛妄之詞。又被告於本院審理時另辯稱：於96年1月13日那筆借款是伊與林慶炫到了福州金山大飯店後，林慶炫向伊借的，伊是在飯店房間將錢交給林慶炫，但是林慶炫寫錯日期，正確日期應該是96年1月12日，林慶炫寫成96年1月13日云云（見本院99年度訴字第939號卷第24頁），不僅與被告於檢察官訊問時辯稱其係於96年1月12日在機場交予被害人林慶炫等情相悖（見同上他字卷第131頁），復與被告於本院準備程序、審理時歷次所辯該4筆借款均在其家中以現金清點交予被害人林慶炫云云不符，益徵被告諸多辯解，實屬臨訟卸責之詞。5.至被告於本院審理時雖再辯稱：林慶炫向伊借貸如附表編號4所示之金錢時，伊父親從中國信託商業銀行之帳戶內提領出來，再借予被害人林慶炫云云（見本院99年度訴字第939號卷第44頁背面），惟觀諸被告提出之中國信託商業銀行提款憑證影本（見同上他字卷第65頁），僅足證明被告之父親王偉忠曾於96年5月14日自其帳戶轉匯10萬元至被告帳戶內，然此與被告所稱之第4筆借款日期96年7月8日相距甚遠，是此部分並無法為有利於被告之認定。6.觀諸被告上開所辯，被告對於借款之時間、地點、金錢之來源，多次供述互有歧異，已非可採；另衡諸社會上個人間消費借貸常情，率皆由借貸人書立借貸意旨之借據交予貸與人收執，要無可能在借據上記載與消費借貸事實無關聯之其他事由，然觀之卷附被害人林慶炫交予被告收執之如附表所示收據4紙，其中編號1收據記載「辦資料」，另編號2之收據則記載「辦機票」，均非一般消費借貸往來下，借貸人書寫之事由甚明，反係與被害人林慶炫前開證述為被告辦理大陸結婚事宜所收取之費用、機票費等情較相符合。從而，被告辯稱其分別於如附表所示之時間貸予被告如附表所示之金錢，係屬虛構而非僅出於主觀上之誤認，且如附表所示之收據4紙，亦非被害人林慶炫於如附表所示之時間交予被告收執之「借據」，而係被告將被害人林慶炫前所交付之「收據」，偽造成被害人林慶炫名義之借據後，再持以行使，並於被害人林慶炫對其提出偽造文書及詐欺告訴後，復以此虛構之借款事實對被害人林慶炫提出詐欺及背信告訴，應堪認定。(四)、綜上所述，本案事證明確，被告犯行洵堪認定，應依法論科。二、論罪科刑：(一)、核被告就犯罪事實一、(一)所為，係犯刑法第216條、第210條之行使偽造私文書罪及刑法第339條第2項詐欺得利罪。公訴人認被告此部分犯行係涉犯刑法第339條第3項、第2項之詐欺得利未遂罪云云，惟按上訴人因權利人提起民事訴訟向其追取租仔，先後在受訴法院提出偽契，主張受當該田，及已代為贖回，否認付租義務，自係連續行使偽造私文書，以詐術圖得財產上不法之利益，既經民事判決勝訴確定在案，其詐欺即屬既遂，最高法院29年上字第2118號判例可資參照。查被告提出如附表所示之偽造收據4紙向本院桃園簡易庭主張其對被害人林慶炫有12萬元之消費借貸債權，致本院承辦法官陷於錯誤而以97年度桃簡字第1483號案件判決被告勝訴確定在案，已認定如前所述，揆諸上開見解，被告前開詐欺犯行，應屬既遂，公訴人認被告詐欺得利犯行僅屬未遂，容有誤會，惟既遂、未遂乃犯罪之階段行為，毋庸變更起訴法條，附此敘明。又按行使影本，作用與原本相同，偽造私文書後，持以行使其影本，偽造之低度行為為高度之行使行為所吸收，應論以行使偽造私文書罪，最高法院70年臺上字第1107號判例參照。查被告偽造如附表所示之收據4紙後復持影本及原本以行使，其偽造之低度行為則為行使之高度行為所吸收，不另論罪。又被告所犯2次行使偽造私文書之犯行，均係出於其向本院訛稱被害人林慶炫曾向其借貸之目的而為之，侵害之法益相同，各行為之獨立性極為薄弱，依一般社會健全觀念，在時間差距上難以強行分開，在刑法評價上，以視為數個舉動之接續施行，合為包括之一行為予以評價，較為合理，顯係基於單一行使偽造私文書犯意下之接續行為，只論以接續犯之單純一罪為已足。又被告以一行使偽造之私文書方法，同時觸犯行使偽造私文書罪及詐欺得利罪，為想像競合犯，應從一重之行使偽造私文書罪處斷。(二)、按刑法上之誣告罪，本不限於所告事實全屬虛偽時，始能成立，倘所告事實之一部分係出於故意虛構，仍不得謂非誣告。最高法院20年上字第662號判例意旨可資參照。查被告係以虛構之借款情節，向埔子派出所職司刑事偵查輔助之司法警察洪耀武申告被害人林慶炫涉犯背信、詐欺罪嫌，已認定如前所述，則被告與被害人林慶炫間縱另有債權債務關係存在，惟被害人林慶炫既未曾於如附表所示之時間向被告借貸金錢，被告竟仍提出如附表所示借據4紙，指訴被害人林慶炫於如附表所示時間向其借款4次之事實而告訴被害人林慶炫涉犯詐欺、背信罪嫌，顯有以此虛構之事實，使被害人林慶炫受刑事追訴之意圖及故意，甚為灼然。核被告就犯罪事實一、(二)所為，係犯刑法第216條、第210條之行使偽造私文書罪、第169條第1項誣告罪。又按刑法第169條第2項之偽造證據及使用罪，原屬同條第1項誣告之預備行為，因其犯罪之危險性較為重大，故不必實行誣告，仍予獨立處罰，如果偽造此項證據持以誣告，除另犯其他罪名外，按照低度行為吸收於高度行為之原則，祇應論以第一項之誣告罪名，不應再適用第2項從重處斷；次按意圖他人受刑事處分，向該管公務員誣告，同時復使用偽造之證據，則其使用偽造證據之行為，應為誣告行為所吸收，除應成立刑法第169條第1項之罪外，固不應再以同條第2項之罪相繩，但其使用偽造證據，若更觸犯其他罪名時，仍係一行為而犯數罪，應依刑法第55條從一重處斷，不能並謂其所觸犯之其他罪名，亦為誣告行為所吸收，而不得再行論處。最高法院30年上字第194號、28年上字第4086號判例意旨可資參照。查被告意圖他人受刑事處分，向該管公務員誣告被害人林慶炫涉犯詐欺、背信罪嫌，同時復使用偽造之證據，其使用偽造證據之低度行為，均為誣告之高度行為所吸收，不另論罪，公訴人雖未就被告使用偽造證據之犯行起訴，惟該部分犯行與已敘及部分，有吸收犯之實質上一罪關係，為起訴效力所及，本院自得併予審理。又被告使用偽造證據之行為為誣告行為所吸收，而其係以一行為同時犯行使偽造私文書罪及誣告罪，為想像競合犯，自應從一重之誣告罪處斷。(三)、被告所犯上述偽造私文書罪及誣告罪，犯意各別，行為互殊，應予分論併罰。又被告有如事實欄所載之犯罪科刑紀錄及執行情形，此有臺灣高等法院被告前案紀錄表在卷可稽，其於受有期徒刑執行完畢後，5年內故意再犯本件有期徒刑以上之罪，均為累犯，均應依刑法第47條第1項規定加重其刑。爰審酌被告偽造證據，對被害人林慶炫提出民事告訴並濫行提出詐欺及背信告訴，嚴重妨害司法公正性，並足使林慶炫受有刑事處分之危險，造成司法調查程序之無益進行，妨害司法正義之實現，且於犯後猶狡詞卸責，態度難認良好，併其品行、犯罪動機、目的、手段、生活狀況、智識程度及所生之損害等一切情狀，分別量處如主文所示之刑，並定其應執行之刑，以示懲儆。三、沒收：扣案之如附表所示收據4紙，均為供被告犯本罪所用之物，且均屬被告所有，應依刑法第38條第1項第2款之規定，分別於被告所犯行使偽造文書罪、誣告罪所宣告之主刑項下，分別諭知沒收。據上論斷，應依刑事訴訟法第299條第1項前段，刑法第第216條、第210條、第339條第2項、第169條第1項、第47條第1項、第55條、第51條第5款、第38條第1項第2款，刑法施行法第1條之1，判決如主文。本案經檢察官蔡正傑到庭執行職務。中華民國100年3月8日刑事第四庭審判長法官張淑華法官張宇葭法官林維斌以上正本證明與原本無異。如不服本判決應於收受判決後10日內向本院提出上訴書狀，並應敘述具體理由。其未敘述上訴理由者，應於上訴期間屆滿後20日內向本院補提理由書(均須按他造當事人之人數附繕本)「切勿逕送上級法院」。書記官鄭嘉惠中華民國100年3月9日附表：┌──┬──────┬────────────┬────────────┬────────┐│編號│日期│偽造前之內容│偽造後之內容│王長孝補增之內容│├──┼──────┼────────────┼────────────┼────────┤│1│96年1月5日│15,000元於1月5日拿│借據15,000元於1月5日拿│借據、中華民國96││││15,000辦資料│15,000辦資料│年元月5日││││林慶炫│林慶炫Ｚ000000000│││││Ｚ000000000│中華民國96年元月5日││├──┼──────┼────────────┼────────────┼────────┤│2│96年1月8日│96年1月8日拿3萬5仟元整│96年7月8日拿3萬5仟元整│借據、1月改為7月││││辦機票│辦機票借據│、中華民國96年7││││林慶炫│林慶炫│月8日││││Ｚ000000000│Ｚ000000000││││││中華民國96年7月8日││├──┼──────┼────────────┼────────────┼────────┤│3│96年1月10日│96年1月10日│96年1月10日借據│借據、中華民國96││││拿3萬│拿3萬林慶炫│年1月10日││││林慶炫│Ｚ000000000│││││Ｚ000000000│中華民國96年1月10日││├──┼──────┼────────────┼────────────┼────────┤│4│96年1月13日│96年1月13日│借據96年1月13日│借據、拿、中華民││││拿4萬林慶炫│拿4萬林慶炫│國96年1月13日、││││Ｚ000000000│Ｚ000000000│Ｚ000000000││││中華民國96年1月13日│中華民國96年1月13日││└──┴──────┴────────────┴────────────┴────────┘",
  "characters": {
    "judges": [
      "張淑華",
      "張宇葭",
      "林維斌"
    ],
    "prosecutors": [
      "蔡正傑"
    ],
    "lawyers": [

    ],
    "clerks": [
      "鄭嘉惠"
    ],
    "plaintiffs": [

    ],
    "defendants": [
      "王長孝"
    ],
    "prosecutor_office": [
      "臺灣桃園地方法院檢察署檢察官"
    ],
    "creditors": [

    ],
    "debtors": [

    ],
    "judicial_associate_officer": [

    ]
  },
  "adjudged_at": "2011-03-08",
  "created_at": "2016-02-13 20:31:01",
  "updated_at": "2016-02-13 20:31:01"
}