{
  "identify": "TYD-94-壢簡-529-20050502-1",
  "court": {
    "name": "臺灣桃園地方法院",
    "code": "TYD"
  },
  "division": {
    "name": "刑事",
    "code": "M"
  },
  "year": 94,
  "word": "壢簡",
  "number": "529",
  "jcheck": "1",
  "reason": "違反動產擔保交易法",
  "content": "臺灣桃園地方法院刑事簡易判決         94年度壢簡字第529號\n聲  請  人  臺灣桃園地方法院檢察署檢察官\n被      告  甲  ○\n                      五號\n上列被告因違反動產擔保交易法案件，經檢察官聲請以簡易判決處刑（\n94年度偵字第2584號），本院判決如下：\n    主  文\n甲○動產擔保交易之債務人，意圖不法利益，將標的物出質，致\n生損害於債權人，處拘役二十日，如易科罰金，以三百元折算一\n日。緩刑二年。\n    事  實及理  由\n一、本件犯罪事實及證據除補充被告將動產抵押之標的出質，亦\n    致生損害於債權人外，其餘引用檢察官聲請簡易判決處刑書\n    之記載。\n二、被告係犯動產擔保交易法第三八條之罪。本院審酌被告犯罪\n    之動機、所未償還之款項、犯罪所生危害及犯後態度等一切\n    情狀，量處如主文所示之刑，並諭知易科罰金之折算標準。\n    查被告前未受罪刑之宣告，有其前案紀錄表在卷可稽，其偶\n    犯本件雖非可取，然其因智慮不週而犯本罪，且事後亦受裕\n    融公司之強制執行，其犯後態度良好，經此刑之宣告後，當\n    足促其警惕，信無再犯之虞，本院因認所宣告之刑，以暫不\n    執行為適當，爰併宣告緩刑二年，以勵自新。\n三、依刑事訴訟法第四四九條第一項、第四五四條第二項，動產\n    擔保交易法第三八條、刑法第十一條前段、第四一條第一項\n    前段、第七四條第一款，罰金罰鍰提高標準條例第一條、第\n    二條，逕以簡易判決處刑如主文。\n四、如不服本判決，得於判決書送達之日起十日內，以書狀敘述\n    理由，向本庭提出上訴。\n中    華    民    國    94    年    5     月    2     日\n                                法  官  林明洲\n以上正本證明與原本無異。\n如不服本判決，應於判決送達後10日內向本院提出上訴狀（應附\n繕本），上訴於本院合議庭。\n                                書記官  顏美惠\n中    華    民    國    94    年    5     月    2     日\n附錄論罪科刑依據之法條\n動產擔保交易法第38條\n (處分標的物之處罰)\n動產擔保交易之債務人，意圖不法之利益，將標的物遷移、出賣\n、出質、移轉、抵押或為其他處分，致生損害於債權人者，處三\n年以下有期徒刑、拘役或科或併科六千元以下之罰金。\n",
  "structure": {
    "main": "甲○動產擔保交易之債務人，意圖不法利益，將標的物出質，致\n生損害於債權人，處拘役二十日，如易科罰金，以三百元折算一\n日。緩刑二年。",
    "fact": "一、本件犯罪事實及證據除補充被告將動產抵押之標的出質，亦\n    致生損害於債權人外，其餘引用檢察官聲請簡易判決處刑書\n    之記載。\n二、被告係犯動產擔保交易法第三八條之罪。本院審酌被告犯罪\n    之動機、所未償還之款項、犯罪所生危害及犯後態度等一切\n    情狀，量處如主文所示之刑，並諭知易科罰金之折算標準。\n    查被告前未受罪刑之宣告，有其前案紀錄表在卷可稽，其偶\n    犯本件雖非可取，然其因智慮不週而犯本罪，且事後亦受裕\n    融公司之強制執行，其犯後態度良好，經此刑之宣告後，當\n    足促其警惕，信無再犯之虞，本院因認所宣告之刑，以暫不\n    執行為適當，爰併宣告緩刑二年，以勵自新。\n三、依刑事訴訟法第四四九條第一項、第四五四條第二項，動產\n    擔保交易法第三八條、刑法第十一條前段、第四一條第一項\n    前段、第七四條第一款，罰金罰鍰提高標準條例第一條、第\n    二條，逕以簡易判決處刑如主文。\n四、如不服本判決，得於判決書送達之日起十日內，以書狀敘述\n    理由，向本庭提出上訴。",
    "reason": "一、本件犯罪事實及證據除補充被告將動產抵押之標的出質，亦\n    致生損害於債權人外，其餘引用檢察官聲請簡易判決處刑書\n    之記載。\n二、被告係犯動產擔保交易法第三八條之罪。本院審酌被告犯罪\n    之動機、所未償還之款項、犯罪所生危害及犯後態度等一切\n    情狀，量處如主文所示之刑，並諭知易科罰金之折算標準。\n    查被告前未受罪刑之宣告，有其前案紀錄表在卷可稽，其偶\n    犯本件雖非可取，然其因智慮不週而犯本罪，且事後亦受裕\n    融公司之強制執行，其犯後態度良好，經此刑之宣告後，當\n    足促其警惕，信無再犯之虞，本院因認所宣告之刑，以暫不\n    執行為適當，爰併宣告緩刑二年，以勵自新。\n三、依刑事訴訟法第四四九條第一項、第四五四條第二項，動產\n    擔保交易法第三八條、刑法第十一條前段、第四一條第一項\n    前段、第七四條第一款，罰金罰鍰提高標準條例第一條、第\n    二條，逕以簡易判決處刑如主文。\n四、如不服本判決，得於判決書送達之日起十日內，以書狀敘述\n    理由，向本庭提出上訴。"
  },
  "search": "臺灣桃園地方法院刑事簡易判決94年度壢簡字第529號聲請人臺灣桃園地方法院檢察署檢察官被告甲○五號上列被告因違反動產擔保交易法案件，經檢察官聲請以簡易判決處刑（94年度偵字第2584號），本院判決如下：主文甲○動產擔保交易之債務人，意圖不法利益，將標的物出質，致生損害於債權人，處拘役二十日，如易科罰金，以三百元折算一日。緩刑二年。事實及理由一、本件犯罪事實及證據除補充被告將動產抵押之標的出質，亦致生損害於債權人外，其餘引用檢察官聲請簡易判決處刑書之記載。二、被告係犯動產擔保交易法第三八條之罪。本院審酌被告犯罪之動機、所未償還之款項、犯罪所生危害及犯後態度等一切情狀，量處如主文所示之刑，並諭知易科罰金之折算標準。查被告前未受罪刑之宣告，有其前案紀錄表在卷可稽，其偶犯本件雖非可取，然其因智慮不週而犯本罪，且事後亦受裕融公司之強制執行，其犯後態度良好，經此刑之宣告後，當足促其警惕，信無再犯之虞，本院因認所宣告之刑，以暫不執行為適當，爰併宣告緩刑二年，以勵自新。三、依刑事訴訟法第四四九條第一項、第四五四條第二項，動產擔保交易法第三八條、刑法第十一條前段、第四一條第一項前段、第七四條第一款，罰金罰鍰提高標準條例第一條、第二條，逕以簡易判決處刑如主文。四、如不服本判決，得於判決書送達之日起十日內，以書狀敘述理由，向本庭提出上訴。中華民國94年5月2日法官林明洲以上正本證明與原本無異。如不服本判決，應於判決送達後10日內向本院提出上訴狀（應附繕本），上訴於本院合議庭。書記官顏美惠中華民國94年5月2日附錄論罪科刑依據之法條動產擔保交易法第38條(處分標的物之處罰)動產擔保交易之債務人，意圖不法之利益，將標的物遷移、出賣、出質、移轉、抵押或為其他處分，致生損害於債權人者，處三年以下有期徒刑、拘役或科或併科六千元以下之罰金。",
  "characters": {
    "judges": [
      "林明洲"
    ],
    "prosecutors": [

    ],
    "lawyers": [

    ],
    "clerks": [
      "顏美惠"
    ],
    "plaintiffs": [

    ],
    "defendants": [
      "甲  ○"
    ],
    "prosecutor_office": [
      "臺灣桃園地方法院檢察署檢察官"
    ],
    "creditors": [

    ],
    "debtors": [

    ],
    "judicial_associate_officer": [

    ]
  },
  "adjudged_at": "2005-05-02",
  "created_at": "2016-02-06 15:49:12",
  "updated_at": "2016-02-06 15:49:12"
}