{
  "identify": "CHD-100-交簡-1481-20110725-1",
  "court": {
    "name": "臺灣彰化地方法院",
    "code": "CHD"
  },
  "division": {
    "name": "刑事",
    "code": "M"
  },
  "year": 100,
  "word": "交簡",
  "number": "1481",
  "jcheck": "1",
  "reason": "公共危險",
  "content": "臺灣彰化地方法院刑事簡易判決       100年度交簡字第1481號\n聲  請  人  臺灣彰化地方法院檢察署檢察官\n被      告  李坤澤\n上列被告因公共危險案件，經檢察官聲請以簡易判決處刑（100\n年度偵字第5007號），本院判決如下：\n    主    文\n李坤澤服用酒類，不能安全駕駛動力交通工具而駕駛，處有期徒\n刑月，如易科罰金，以新臺幣壹仟元折算壹日。\n    事實及理由\n一、李坤澤前因公共危險案件，經臺灣彰化地方法院檢察署檢察\n    官於民國98年6月11日，以98年度緩字第2368號為緩起訴處\n    分確定（未構成累犯）。詎其仍不知悔改，自100年2月7日\n    晚上7時許起，迄同日晚上10時許止，在彰化縣彰化市○○\n    路某處參加友人喜宴，飲用啤酒後，已達不能安全駕駛動力\n    交通工具之程度，竟酒後無照騎乘車牌號碼JRP—425號重型\n    機車，自彰化市○○路另一友人住處出發，欲返回於臺中市\n    南屯區○○里○○路○段501號6樓住處。嗣於翌（8）日凌晨\n    0 時許，行經彰化縣彰化市大肚溪橋北上機車道時，因酒後\n    注意能力減弱，不慎重心失控因而人車倒地，受有頭部外傷\n    併蜘蛛膜下腔出血、創傷性左側股骨幹骨折、左側脛骨與腓\n    骨上端閉鎖性骨折等傷害。經警據報到場處理，並將李坤澤\n    送醫急救並抽血檢測，測得血液中酒精濃度為211.3MG/DL（\n    換算成呼氣酒精濃度約為每公升1.056毫克）而查悉上情。\n    案經彰化縣警察局彰化分局報告臺灣彰化地方法院檢察署檢\n    察官偵查並聲請簡易判決處刑。\n二、上揭犯罪事實，業據被告李坤澤於警詢及偵訊時均坦承不諱\n    ，並有彰化基督教醫院檢驗報告、前開醫院診斷書、道路交\n    通事故現場圖、調查報告表（一）、（二）、刑法第185 條\n    之3案件酒精測試觀察記錄表、彰化縣警察局舉發違反道路\n    管理事件通知單、證號查詢機車駕駛人、車號查詢重型機車\n    車籍，及現場照片10張在卷可稽。而所謂不能安全駕駛，並\n    無一定之數值可供界定，係由法院以一般社會通念之客觀標\n    準，足生公共危險時即足。目前行政機關取締酒後駕車之參\n    考標準，係參考美國、德國及日本等國家所進行之酒精濃度\n    與精神狀態之測試實驗，各項實驗均發現凡呼氣中酒精濃度\n    達每公升0. 55毫克時，就人之生理方面，已產生視覺反應\n    遲鈍、影像不能集中、同時不能看清前方路況及車旁照後鏡\n    等狀況，及駕駛能力已受有影響、肇事率已為一般人正常人\n    10倍之事實。被告於肇事受傷後，經警送醫急救並抽血檢測\n    ，測得其血液酒精濃度為211.3MG/DL（換算為呼氣酒精濃度\n    達每公升1.056毫克），依一般社會通念，已達不能安全駕\n    駛之程度。被告服用酒類不能駕駛動力交通工具而駕駛之犯\n    行，足堪認定。\n三、核被告所為，係犯刑法第185條之3服用酒類不能安全駕駛動\n    力交通工具而駕駛罪。爰審酌被告前已有1次酒後駕車之記\n    錄，雖不構成累犯，但明知酒精成分對人之意識能力具有不\n    良影響，飲酒後會導致對周遭事務之辨識及反應能力較平常\n    狀況薄弱，且酒後不能駕駛車輛業經政府三申五令宣導，詎\n    仍不知警惕，復在飲酒後已達不能安全駕駛之情況下執意駕\n    駛動力交通工具上路，對一般往來之人車均生高度危險性，\n    更罔顧自己及他人生命、身體、健康、財產安全，且因而肇\n    事，惟念其犯後坦承犯行，非無悔意等一切情狀，量處如主\n    文所示之刑，並諭知如易科罰金之折算標準，以資懲儆。\n四、據上論斷，應依刑事訴訟法第449條第1項前段、第454條第1\n    項，刑法第185條之3、第41條第1項，刑法施行法第1條之1\n    第1項，逕以簡易判決處刑如主文。\n五、如不服本簡易判決，得於簡易判決書送達之日起10日內，以\n    書狀敘述理由，向本院提出上訴（須附繕本）。\n中    華    民    國   100    年    7     月    25    日\n                            交通法庭  法  官  郭玄義\n以上正本證明與原本無異。\n如不服本件判決，得自收受送達之日起10日內，表明上訴理由，\n向本院提起上訴狀（須附繕本）。\n中    華    民    國   100    年    7     月    25    日\n                                      書記官  林婷儀\n【附錄本案論罪科刑法條全文】：\n中華民國刑法第185 條之3\n服用毒品、麻醉藥品、酒類或其他相類之物，不能安全駕駛動力\n交通工具而駕駛者，處1 年以下有期徒刑、拘役或科或併科15萬\n元以下罰金。",
  "structure": {
    "main": "李坤澤服用酒類，不能安全駕駛動力交通工具而駕駛，處有期徒\n刑月，如易科罰金，以新臺幣壹仟元折算壹日。",
    "fact": "一、李坤澤前因公共危險案件，經臺灣彰化地方法院檢察署檢察\n    官於民國98年6月11日，以98年度緩字第2368號為緩起訴處\n    分確定（未構成累犯）。詎其仍不知悔改，自100年2月7日\n    晚上7時許起，迄同日晚上10時許止，在彰化縣彰化市○○\n    路某處參加友人喜宴，飲用啤酒後，已達不能安全駕駛動力\n    交通工具之程度，竟酒後無照騎乘車牌號碼JRP—425號重型\n    機車，自彰化市○○路另一友人住處出發，欲返回於臺中市\n    南屯區○○里○○路○段501號6樓住處。嗣於翌（8）日凌晨\n    0 時許，行經彰化縣彰化市大肚溪橋北上機車道時，因酒後\n    注意能力減弱，不慎重心失控因而人車倒地，受有頭部外傷\n    併蜘蛛膜下腔出血、創傷性左側股骨幹骨折、左側脛骨與腓\n    骨上端閉鎖性骨折等傷害。經警據報到場處理，並將李坤澤\n    送醫急救並抽血檢測，測得血液中酒精濃度為211.3MG/DL（\n    換算成呼氣酒精濃度約為每公升1.056毫克）而查悉上情。\n    案經彰化縣警察局彰化分局報告臺灣彰化地方法院檢察署檢\n    察官偵查並聲請簡易判決處刑。\n二、上揭犯罪事實，業據被告李坤澤於警詢及偵訊時均坦承不諱\n    ，並有彰化基督教醫院檢驗報告、前開醫院診斷書、道路交\n    通事故現場圖、調查報告表（一）、（二）、刑法第185 條\n    之3案件酒精測試觀察記錄表、彰化縣警察局舉發違反道路\n    管理事件通知單、證號查詢機車駕駛人、車號查詢重型機車\n    車籍，及現場照片10張在卷可稽。而所謂不能安全駕駛，並\n    無一定之數值可供界定，係由法院以一般社會通念之客觀標\n    準，足生公共危險時即足。目前行政機關取締酒後駕車之參\n    考標準，係參考美國、德國及日本等國家所進行之酒精濃度\n    與精神狀態之測試實驗，各項實驗均發現凡呼氣中酒精濃度\n    達每公升0. 55毫克時，就人之生理方面，已產生視覺反應\n    遲鈍、影像不能集中、同時不能看清前方路況及車旁照後鏡\n    等狀況，及駕駛能力已受有影響、肇事率已為一般人正常人\n    10倍之事實。被告於肇事受傷後，經警送醫急救並抽血檢測\n    ，測得其血液酒精濃度為211.3MG/DL（換算為呼氣酒精濃度\n    達每公升1.056毫克），依一般社會通念，已達不能安全駕\n    駛之程度。被告服用酒類不能駕駛動力交通工具而駕駛之犯\n    行，足堪認定。\n三、核被告所為，係犯刑法第185條之3服用酒類不能安全駕駛動\n    力交通工具而駕駛罪。爰審酌被告前已有1次酒後駕車之記\n    錄，雖不構成累犯，但明知酒精成分對人之意識能力具有不\n    良影響，飲酒後會導致對周遭事務之辨識及反應能力較平常\n    狀況薄弱，且酒後不能駕駛車輛業經政府三申五令宣導，詎\n    仍不知警惕，復在飲酒後已達不能安全駕駛之情況下執意駕\n    駛動力交通工具上路，對一般往來之人車均生高度危險性，\n    更罔顧自己及他人生命、身體、健康、財產安全，且因而肇\n    事，惟念其犯後坦承犯行，非無悔意等一切情狀，量處如主\n    文所示之刑，並諭知如易科罰金之折算標準，以資懲儆。\n四、據上論斷，應依刑事訴訟法第449條第1項前段、第454條第1\n    項，刑法第185條之3、第41條第1項，刑法施行法第1條之1\n    第1項，逕以簡易判決處刑如主文。\n五、如不服本簡易判決，得於簡易判決書送達之日起10日內，以\n    書狀敘述理由，向本院提出上訴（須附繕本）。",
    "reason": "一、李坤澤前因公共危險案件，經臺灣彰化地方法院檢察署檢察\n    官於民國98年6月11日，以98年度緩字第2368號為緩起訴處\n    分確定（未構成累犯）。詎其仍不知悔改，自100年2月7日\n    晚上7時許起，迄同日晚上10時許止，在彰化縣彰化市○○\n    路某處參加友人喜宴，飲用啤酒後，已達不能安全駕駛動力\n    交通工具之程度，竟酒後無照騎乘車牌號碼JRP—425號重型\n    機車，自彰化市○○路另一友人住處出發，欲返回於臺中市\n    南屯區○○里○○路○段501號6樓住處。嗣於翌（8）日凌晨\n    0 時許，行經彰化縣彰化市大肚溪橋北上機車道時，因酒後\n    注意能力減弱，不慎重心失控因而人車倒地，受有頭部外傷\n    併蜘蛛膜下腔出血、創傷性左側股骨幹骨折、左側脛骨與腓\n    骨上端閉鎖性骨折等傷害。經警據報到場處理，並將李坤澤\n    送醫急救並抽血檢測，測得血液中酒精濃度為211.3MG/DL（\n    換算成呼氣酒精濃度約為每公升1.056毫克）而查悉上情。\n    案經彰化縣警察局彰化分局報告臺灣彰化地方法院檢察署檢\n    察官偵查並聲請簡易判決處刑。\n二、上揭犯罪事實，業據被告李坤澤於警詢及偵訊時均坦承不諱\n    ，並有彰化基督教醫院檢驗報告、前開醫院診斷書、道路交\n    通事故現場圖、調查報告表（一）、（二）、刑法第185 條\n    之3案件酒精測試觀察記錄表、彰化縣警察局舉發違反道路\n    管理事件通知單、證號查詢機車駕駛人、車號查詢重型機車\n    車籍，及現場照片10張在卷可稽。而所謂不能安全駕駛，並\n    無一定之數值可供界定，係由法院以一般社會通念之客觀標\n    準，足生公共危險時即足。目前行政機關取締酒後駕車之參\n    考標準，係參考美國、德國及日本等國家所進行之酒精濃度\n    與精神狀態之測試實驗，各項實驗均發現凡呼氣中酒精濃度\n    達每公升0. 55毫克時，就人之生理方面，已產生視覺反應\n    遲鈍、影像不能集中、同時不能看清前方路況及車旁照後鏡\n    等狀況，及駕駛能力已受有影響、肇事率已為一般人正常人\n    10倍之事實。被告於肇事受傷後，經警送醫急救並抽血檢測\n    ，測得其血液酒精濃度為211.3MG/DL（換算為呼氣酒精濃度\n    達每公升1.056毫克），依一般社會通念，已達不能安全駕\n    駛之程度。被告服用酒類不能駕駛動力交通工具而駕駛之犯\n    行，足堪認定。\n三、核被告所為，係犯刑法第185條之3服用酒類不能安全駕駛動\n    力交通工具而駕駛罪。爰審酌被告前已有1次酒後駕車之記\n    錄，雖不構成累犯，但明知酒精成分對人之意識能力具有不\n    良影響，飲酒後會導致對周遭事務之辨識及反應能力較平常\n    狀況薄弱，且酒後不能駕駛車輛業經政府三申五令宣導，詎\n    仍不知警惕，復在飲酒後已達不能安全駕駛之情況下執意駕\n    駛動力交通工具上路，對一般往來之人車均生高度危險性，\n    更罔顧自己及他人生命、身體、健康、財產安全，且因而肇\n    事，惟念其犯後坦承犯行，非無悔意等一切情狀，量處如主\n    文所示之刑，並諭知如易科罰金之折算標準，以資懲儆。\n四、據上論斷，應依刑事訴訟法第449條第1項前段、第454條第1\n    項，刑法第185條之3、第41條第1項，刑法施行法第1條之1\n    第1項，逕以簡易判決處刑如主文。\n五、如不服本簡易判決，得於簡易判決書送達之日起10日內，以\n    書狀敘述理由，向本院提出上訴（須附繕本）。"
  },
  "search": "臺灣彰化地方法院刑事簡易判決100年度交簡字第1481號聲請人臺灣彰化地方法院檢察署檢察官被告李坤澤上列被告因公共危險案件，經檢察官聲請以簡易判決處刑（100年度偵字第5007號），本院判決如下：主文李坤澤服用酒類，不能安全駕駛動力交通工具而駕駛，處有期徒刑月，如易科罰金，以新臺幣壹仟元折算壹日。事實及理由一、李坤澤前因公共危險案件，經臺灣彰化地方法院檢察署檢察官於民國98年6月11日，以98年度緩字第2368號為緩起訴處分確定（未構成累犯）。詎其仍不知悔改，自100年2月7日晚上7時許起，迄同日晚上10時許止，在彰化縣彰化市○○路某處參加友人喜宴，飲用啤酒後，已達不能安全駕駛動力交通工具之程度，竟酒後無照騎乘車牌號碼JRP—425號重型機車，自彰化市○○路另一友人住處出發，欲返回於臺中市南屯區○○里○○路○段501號6樓住處。嗣於翌（8）日凌晨0時許，行經彰化縣彰化市大肚溪橋北上機車道時，因酒後注意能力減弱，不慎重心失控因而人車倒地，受有頭部外傷併蜘蛛膜下腔出血、創傷性左側股骨幹骨折、左側脛骨與腓骨上端閉鎖性骨折等傷害。經警據報到場處理，並將李坤澤送醫急救並抽血檢測，測得血液中酒精濃度為211.3MG/DL（換算成呼氣酒精濃度約為每公升1.056毫克）而查悉上情。案經彰化縣警察局彰化分局報告臺灣彰化地方法院檢察署檢察官偵查並聲請簡易判決處刑。二、上揭犯罪事實，業據被告李坤澤於警詢及偵訊時均坦承不諱，並有彰化基督教醫院檢驗報告、前開醫院診斷書、道路交通事故現場圖、調查報告表（一）、（二）、刑法第185條之3案件酒精測試觀察記錄表、彰化縣警察局舉發違反道路管理事件通知單、證號查詢機車駕駛人、車號查詢重型機車車籍，及現場照片10張在卷可稽。而所謂不能安全駕駛，並無一定之數值可供界定，係由法院以一般社會通念之客觀標準，足生公共危險時即足。目前行政機關取締酒後駕車之參考標準，係參考美國、德國及日本等國家所進行之酒精濃度與精神狀態之測試實驗，各項實驗均發現凡呼氣中酒精濃度達每公升0.55毫克時，就人之生理方面，已產生視覺反應遲鈍、影像不能集中、同時不能看清前方路況及車旁照後鏡等狀況，及駕駛能力已受有影響、肇事率已為一般人正常人10倍之事實。被告於肇事受傷後，經警送醫急救並抽血檢測，測得其血液酒精濃度為211.3MG/DL（換算為呼氣酒精濃度達每公升1.056毫克），依一般社會通念，已達不能安全駕駛之程度。被告服用酒類不能駕駛動力交通工具而駕駛之犯行，足堪認定。三、核被告所為，係犯刑法第185條之3服用酒類不能安全駕駛動力交通工具而駕駛罪。爰審酌被告前已有1次酒後駕車之記錄，雖不構成累犯，但明知酒精成分對人之意識能力具有不良影響，飲酒後會導致對周遭事務之辨識及反應能力較平常狀況薄弱，且酒後不能駕駛車輛業經政府三申五令宣導，詎仍不知警惕，復在飲酒後已達不能安全駕駛之情況下執意駕駛動力交通工具上路，對一般往來之人車均生高度危險性，更罔顧自己及他人生命、身體、健康、財產安全，且因而肇事，惟念其犯後坦承犯行，非無悔意等一切情狀，量處如主文所示之刑，並諭知如易科罰金之折算標準，以資懲儆。四、據上論斷，應依刑事訴訟法第449條第1項前段、第454條第1項，刑法第185條之3、第41條第1項，刑法施行法第1條之1第1項，逕以簡易判決處刑如主文。五、如不服本簡易判決，得於簡易判決書送達之日起10日內，以書狀敘述理由，向本院提出上訴（須附繕本）。中華民國100年7月25日交通法庭法官郭玄義以上正本證明與原本無異。如不服本件判決，得自收受送達之日起10日內，表明上訴理由，向本院提起上訴狀（須附繕本）。中華民國100年7月25日書記官林婷儀【附錄本案論罪科刑法條全文】：中華民國刑法第185條之3服用毒品、麻醉藥品、酒類或其他相類之物，不能安全駕駛動力交通工具而駕駛者，處1年以下有期徒刑、拘役或科或併科15萬元以下罰金。",
  "characters": {
    "judges": [
      "郭玄義"
    ],
    "prosecutors": [

    ],
    "lawyers": [

    ],
    "clerks": [
      "林婷儀"
    ],
    "plaintiffs": [

    ],
    "defendants": [
      "李坤澤"
    ],
    "prosecutor_office": [
      "臺灣彰化地方法院檢察署檢察官"
    ],
    "creditors": [

    ],
    "debtors": [

    ],
    "judicial_associate_officer": [

    ]
  },
  "adjudged_at": "2011-07-25",
  "created_at": "2016-02-14 02:25:01",
  "updated_at": "2016-02-14 02:25:01"
}