{
  "identify": "TCD-100-自-50-20110725-1",
  "court": {
    "name": "臺灣臺中地方法院",
    "code": "TCD"
  },
  "division": {
    "name": "刑事",
    "code": "M"
  },
  "year": 100,
  "word": "自",
  "number": "50",
  "jcheck": "1",
  "reason": "詐欺等",
  "content": "臺灣臺中地方法院刑事裁定  100年度自字第50號\n自  訴  人  莊萬豐\n被      告  張昭保\n            黃淑鈴\n上列被告等因詐欺等案件，經自訴人提起自訴，本院裁定如左：\n    主    文\n自訴人應於本裁定送達後五日內委任律師為自訴代理人。\n    理    由\n一、按自訴人應委任代理人到場，但法院認為必要時，得命本人\n    到場，前項代理人應選任律師充之；又檢察官於審判期日所\n    得為之訴訟行為，於自訴程序，由自訴代理人為之，自訴人\n    未委任代理人，法院應定期間以裁定命其委任代理人，逾期\n    仍不委任者，應諭知不受理判決，刑事訴訟法第三十七條、\n    第三百二十九條規定自明。\n二、自訴人提起本件自訴，並未依法委任律師為代理人，揆諸前\n    開規定，爰命自訴人於收受本裁定送達後五日內委任律師為\n    代理人，逾期駁回其訴訟。\n三、依刑事訴訟法第三百二十九條第二項前段，裁定如主文。\n中    華    民    國   100    年    7     月    25    日\n                  刑事第七庭  審判長法  官  洪俊誠\n                                    法  官  巫淑芳\n                                    法  官  張德寬\n上正本證明與原本無異。\n本件不得抗告。\n                                    書記官  王麗雯\n中    華    民    國   100    年    7     月    25    日",
  "structure": {
    "main": "自訴人應於本裁定送達後五日內委任律師為自訴代理人。",
    "reason": "一、按自訴人應委任代理人到場，但法院認為必要時，得命本人\n    到場，前項代理人應選任律師充之；又檢察官於審判期日所\n    得為之訴訟行為，於自訴程序，由自訴代理人為之，自訴人\n    未委任代理人，法院應定期間以裁定命其委任代理人，逾期\n    仍不委任者，應諭知不受理判決，刑事訴訟法第三十七條、\n    第三百二十九條規定自明。\n二、自訴人提起本件自訴，並未依法委任律師為代理人，揆諸前\n    開規定，爰命自訴人於收受本裁定送達後五日內委任律師為\n    代理人，逾期駁回其訴訟。\n三、依刑事訴訟法第三百二十九條第二項前段，裁定如主文。"
  },
  "search": "臺灣臺中地方法院刑事裁定100年度自字第50號自訴人莊萬豐被告張昭保黃淑鈴上列被告等因詐欺等案件，經自訴人提起自訴，本院裁定如左：主文自訴人應於本裁定送達後五日內委任律師為自訴代理人。理由一、按自訴人應委任代理人到場，但法院認為必要時，得命本人到場，前項代理人應選任律師充之；又檢察官於審判期日所得為之訴訟行為，於自訴程序，由自訴代理人為之，自訴人未委任代理人，法院應定期間以裁定命其委任代理人，逾期仍不委任者，應諭知不受理判決，刑事訴訟法第三十七條、第三百二十九條規定自明。二、自訴人提起本件自訴，並未依法委任律師為代理人，揆諸前開規定，爰命自訴人於收受本裁定送達後五日內委任律師為代理人，逾期駁回其訴訟。三、依刑事訴訟法第三百二十九條第二項前段，裁定如主文。中華民國100年7月25日刑事第七庭審判長法官洪俊誠法官巫淑芳法官張德寬上正本證明與原本無異。本件不得抗告。書記官王麗雯中華民國100年7月25日",
  "characters": {
    "judges": [
      "洪俊誠",
      "巫淑芳",
      "張德寬"
    ],
    "prosecutors": [

    ],
    "lawyers": [
      "自訴人應於本裁定送達後五日內委任"
    ],
    "clerks": [
      "王麗雯"
    ],
    "plaintiffs": [

    ],
    "defendants": [
      "張昭保"
    ],
    "prosecutor_office": [

    ],
    "creditors": [

    ],
    "debtors": [

    ],
    "judicial_associate_officer": [

    ]
  },
  "adjudged_at": "2011-07-25",
  "created_at": "2016-02-14 02:31:12",
  "updated_at": "2016-02-14 02:31:12"
}