{
  "identify": "TYD-100-桃智簡-1-20110725-1",
  "court": {
    "name": "臺灣桃園地方法院",
    "code": "TYD"
  },
  "division": {
    "name": "刑事",
    "code": "M"
  },
  "year": 100,
  "word": "桃智簡",
  "number": "1",
  "jcheck": "1",
  "reason": "違反商標法",
  "content": "臺灣桃園地方法院刑事簡易判決        100年度桃智簡字第1號\n聲  請  人  臺灣桃園地方法院檢察署檢察官\n被      告  李雅琴\n上列被告因違反商標法案件，經檢察官聲請以簡易判決處刑（99\n年度偵字第26754 號），本院判決如下：\n    主      文\n李雅琴共同明知為未得商標權人同意，於同一商品，使用相同之\n註冊商標之商品而販賣，處有期徒刑貳月，如易科罰金，以新臺\n幣壹仟元折算壹日。緩刑貳年。扣案如附表一、二所示之仿冒商\n標商品，均沒收。\n    事實及理由\n一、本件犯罪事實及證據，除於犯罪事實欄第23行「編號1 至18\n    」更正為「編號1 至9 」、「編號19」更正為「編號10」，\n    第24行「編號20」更正為「編號11」、「編號21」更正為「\n    編號12」，第25行「編號1 至7 」更正為「編號1 至6 」之\n    外，其餘均引用檢察官聲請簡易判決處刑書所載（如附件）\n    。\n二、核被告李雅琴所為，係犯商標法第82條之販賣仿冒商標商品\n    罪。其意圖販賣而陳列仿冒商標商品之低度行為，為販賣之\n    高度行為所吸收，不另論罪。又按刑事法若干犯罪之行為態\n    樣，本質上原具有反覆、延續實行之特徵，立法時既予特別\n    歸類，定為犯罪構成要件之行為要素，則行為人基於概括之\n    犯意，在密切接近之一定時、地持續實行之複次行為，倘依\n    社會通念，於客觀上認為符合一個反覆、延續性之行為觀念\n    者，於刑法評價上，即應僅成立一罪，俾免有重複評價、刑\n    度超過罪責與不法內涵之疑慮；學理上所稱「集合犯」之職\n    業性、營業性或收集性等具有重複特質之犯罪均屬之，例如\n    經營、從事業務、收集、販賣、製造、散布等行為概念者，\n    均屬包括一罪之集合犯概念（最高法院95年度台上字第1079\n    號、第3937號、第4686號判決意旨參照）。經查，被告自民\n    國97年間某日起開始販售上開仿冒商標商品至99年6 月5 日\n    上午11時許為警查獲止，先後雖有多次販賣之行為，然因係\n    基於營利之單一目的，於密集期間內，以相同之方式販賣上\n    開仿冒商標商品，具有反覆、延續實行之特徵，在行為概念\n    上，應評價認係包括一罪之集合犯，縱有多次販賣之舉措，\n    仍應評價認係包括一罪之集合犯。又被告以一販賣仿冒商標\n    商品之犯意，同時販賣上開仿冒「HELLO KITTY 」、「Cinn\n    amoroll 」、「Osaru No Monkichi 」、「Kerokerokeropp\n    i 」、「DORAEMON」等商標圖樣之商品，而侵害5 個商標專\n    用權，係一行為而犯數罪名，為同種想像競合犯，應依刑法\n    第55條之規定，從一重處斷。\n三、爰審酌被告為圖牟利，竟非法販賣仿冒商標商品，非但易使\n    民眾對商品品質判斷造成混淆，使商標專用權人合法商品之\n    信譽與品質受質疑，影響商標專用權人之商譽及正常可得收\n    益，對我國保護智慧財產權之國際形象受損，所生危害非輕\n    ，惟念及被告犯後已與告訴人日商三麗鷗股份有限公司達成\n    和解，併斟酌其犯罪之動機、目的、手段、品行、生活狀況\n    、智識程度，及扣案之仿冒商標商品之數量多達數百件、所\n    獲不法利益多寡、犯後態度等一切情狀，量處如主文所示之\n    刑，並於斟酌本案犯罪情節及被告資力等節後，諭知如主文\n    所示之易科罰金折算標準，以資懲戒。末查，被告前未曾因\n    故意犯罪受有期徒刑以上刑之宣告，有臺灣高等法院被告前\n    案紀錄表1 份在卷可稽，其因一時失慮，偶罹刑典，且已與\n    告訴人日商三麗鷗股份有限公司和解，取得告訴人宥恕，經\n    此刑之宣告後，應知所警惕，信無再犯之虞，本院因認所宣\n    告之刑以暫不執行為適當，爰依刑法第74條第1 項第1 款之\n    規定諭知緩刑2 年，以啟自新。扣案如附表一、二所示之仿\n    冒「HELLO KITTY 」、「Cinnamoroll 」、「Osaru No Mon\n    kichi 」、「Kerokerokeroppi 」等商標商品共219 件，仿\n    冒「DORAEMON」商標之商品共74件，均係仿冒商標之商品，\n    不問屬於犯人與否，應依商標法第83條規定沒收之。至扣案\n    之「DORAEMON」麥粥婉餐具組9 套、叉匙組14套，業經國際\n    影視有限公司鑑定為合法授權商品，是不應予沒收，附此敘\n    明。\n四、據上論斷，應依刑事訴訟法第449 條第1 項前段、第3 項、\n    第450 條第1 項、第454 條第2 項，商標法第82條、第83條\n    ，刑法第11條、第55條、第41條第1 項前段、第74條第1 項\n    第1款，逕以簡易判決處刑如主文。\n五、如不服本判決，得於判決書送達之翌日起10日內，以書狀敘\n    述理由（須附繕本），向本庭合議庭提起上訴。\n中    華    民    國   100    年    7     月    25    日\n                  刑事第二庭  法  官  陳秋君\n以上正本證明與原本無異。\n如不服本判決，應於判決送達後10日內向本院提出上訴狀（應附\n繕本）。\n                              書記官  吳采蓉\n中    華    民    國   100    年    8     月    2     日\n附錄本案論罪科刑法條全文：\n商標法第82條\n明知為前條商品而販賣、意圖販賣而陳列、輸出或輸入者，處1\n年以下有期徒刑、拘役或科或併科新臺幣5 萬元以下罰金。\n附表一：（日商三麗鷗股份有限公司之註冊商標）\n┌──┬─────────────────┬─────┐\n│編號│扣案物品                          │數量（件）│\n├──┼─────────────────┼─────┤\n│1   │仿冒HELLO KITTY上衣               │51        │\n├──┼─────────────────┼─────┤\n│2   │仿冒HELLO KITTY計算機             │1         │\n├──┼─────────────────┼─────┤\n│3   │仿冒HELLO KITTY保暖手套           │4         │\n├──┼─────────────────┼─────┤\n│4   │仿冒HELLO KITTY耳罩               │8         │\n├──┼─────────────────┼─────┤\n│5   │仿冒HELLO KITTY鍋子               │11        │\n├──┼─────────────────┼─────┤\n│6   │仿冒HELLO KITTY雨衣               │2         │\n├──┼─────────────────┼─────┤\n│7   │仿冒HELLO KITTY驅蚊手環           │38        │\n├──┼─────────────────┼─────┤\n│8   │仿冒HELLO KITTY夜燈               │6         │\n├──┼─────────────────┼─────┤\n│9   │仿冒HELLO KITTY置物籃             │5         │\n├──┼─────────────────┼─────┤\n│10  │仿冒HELLO KITTY筆電保護貼         │3         │\n├──┼─────────────────┼─────┤\n│11  │仿冒HELLO KITTY內褲               │2         │\n├──┼─────────────────┼─────┤\n│12  │仿冒HELLO KITTY手提袋             │7         │\n├──┼─────────────────┼─────┤\n│13  │仿冒HELLO KITTY袖套               │10        │\n├──┼─────────────────┼─────┤\n│14  │仿冒HELLO KITTY滑鼠               │3         │\n├──┼─────────────────┼─────┤\n│15  │仿冒HELLO KITTY電子驅蚊器         │14        │\n├──┼─────────────────┼─────┤\n│16  │仿冒HELLO KITTY便利貼             │2         │\n├──┼─────────────────┼─────┤\n│17  │仿冒HELLO KITTY眼罩               │1         │\n├──┼─────────────────┼─────┤\n│18  │仿冒HELLO KITTY保暖電子滑鼠墊     │10        │\n├──┼─────────────────┼─────┤\n│19  │仿冒Cinnamoroll上衣               │2         │\n├──┼─────────────────┼─────┤\n│20  │仿冒Osaru No Monkichi 保暖手套    │3         │\n├──┼─────────────────┼─────┤\n│21  │仿冒Kerokerokeroppi護膝           │36        │\n├──┼─────────────────┼─────┤\n│    │                              合計│共219件   │\n└──┴─────────────────┴─────┘\n附表二：（日商小學館股份有限公司之註冊商標）\n┌──┬─────────────────┬─────┐\n│編號│扣案物品                          │數量      │\n├──┼─────────────────┼─────┤\n│1   │仿冒DORAEMON智能筷子              │3         │\n├──┼─────────────────┼─────┤\n│2   │仿冒DORAEMON上衣                  │48        │\n├──┼─────────────────┼─────┤\n│3   │仿冒DORAEMON貼紙                  │1         │\n├──┼─────────────────┼─────┤\n│4   │仿冒DORAEMON筆電保護貼            │5         │\n├──┼─────────────────┼─────┤\n│5   │仿冒DORAEMON夜燈                  │6         │\n├──┼─────────────────┼─────┤\n│6   │仿冒DORAEMON鍋子                  │5         │\n├──┼─────────────────┼─────┤\n│7   │仿冒DORAEMON電子保暖滑鼠墊        │6         │\n├──┼─────────────────┼─────┤\n│    │                              合計│共74件    │\n└──┴─────────────────┴─────┘",
  "structure": {
    "main": "李雅琴共同明知為未得商標權人同意，於同一商品，使用相同之\n註冊商標之商品而販賣，處有期徒刑貳月，如易科罰金，以新臺\n幣壹仟元折算壹日。緩刑貳年。扣案如附表一、二所示之仿冒商\n標商品，均沒收。",
    "fact": "一、本件犯罪事實及證據，除於犯罪事實欄第23行「編號1 至18\n    」更正為「編號1 至9 」、「編號19」更正為「編號10」，\n    第24行「編號20」更正為「編號11」、「編號21」更正為「\n    編號12」，第25行「編號1 至7 」更正為「編號1 至6 」之\n    外，其餘均引用檢察官聲請簡易判決處刑書所載（如附件）\n    。\n二、核被告李雅琴所為，係犯商標法第82條之販賣仿冒商標商品\n    罪。其意圖販賣而陳列仿冒商標商品之低度行為，為販賣之\n    高度行為所吸收，不另論罪。又按刑事法若干犯罪之行為態\n    樣，本質上原具有反覆、延續實行之特徵，立法時既予特別\n    歸類，定為犯罪構成要件之行為要素，則行為人基於概括之\n    犯意，在密切接近之一定時、地持續實行之複次行為，倘依\n    社會通念，於客觀上認為符合一個反覆、延續性之行為觀念\n    者，於刑法評價上，即應僅成立一罪，俾免有重複評價、刑\n    度超過罪責與不法內涵之疑慮；學理上所稱「集合犯」之職\n    業性、營業性或收集性等具有重複特質之犯罪均屬之，例如\n    經營、從事業務、收集、販賣、製造、散布等行為概念者，\n    均屬包括一罪之集合犯概念（最高法院95年度台上字第1079\n    號、第3937號、第4686號判決意旨參照）。經查，被告自民\n    國97年間某日起開始販售上開仿冒商標商品至99年6 月5 日\n    上午11時許為警查獲止，先後雖有多次販賣之行為，然因係\n    基於營利之單一目的，於密集期間內，以相同之方式販賣上\n    開仿冒商標商品，具有反覆、延續實行之特徵，在行為概念\n    上，應評價認係包括一罪之集合犯，縱有多次販賣之舉措，\n    仍應評價認係包括一罪之集合犯。又被告以一販賣仿冒商標\n    商品之犯意，同時販賣上開仿冒「HELLO KITTY 」、「Cinn\n    amoroll 」、「Osaru No Monkichi 」、「Kerokerokeropp\n    i 」、「DORAEMON」等商標圖樣之商品，而侵害5 個商標專\n    用權，係一行為而犯數罪名，為同種想像競合犯，應依刑法\n    第55條之規定，從一重處斷。\n三、爰審酌被告為圖牟利，竟非法販賣仿冒商標商品，非但易使\n    民眾對商品品質判斷造成混淆，使商標專用權人合法商品之\n    信譽與品質受質疑，影響商標專用權人之商譽及正常可得收\n    益，對我國保護智慧財產權之國際形象受損，所生危害非輕\n    ，惟念及被告犯後已與告訴人日商三麗鷗股份有限公司達成\n    和解，併斟酌其犯罪之動機、目的、手段、品行、生活狀況\n    、智識程度，及扣案之仿冒商標商品之數量多達數百件、所\n    獲不法利益多寡、犯後態度等一切情狀，量處如主文所示之\n    刑，並於斟酌本案犯罪情節及被告資力等節後，諭知如主文\n    所示之易科罰金折算標準，以資懲戒。末查，被告前未曾因\n    故意犯罪受有期徒刑以上刑之宣告，有臺灣高等法院被告前\n    案紀錄表1 份在卷可稽，其因一時失慮，偶罹刑典，且已與\n    告訴人日商三麗鷗股份有限公司和解，取得告訴人宥恕，經\n    此刑之宣告後，應知所警惕，信無再犯之虞，本院因認所宣\n    告之刑以暫不執行為適當，爰依刑法第74條第1 項第1 款之\n    規定諭知緩刑2 年，以啟自新。扣案如附表一、二所示之仿\n    冒「HELLO KITTY 」、「Cinnamoroll 」、「Osaru No Mon\n    kichi 」、「Kerokerokeroppi 」等商標商品共219 件，仿\n    冒「DORAEMON」商標之商品共74件，均係仿冒商標之商品，\n    不問屬於犯人與否，應依商標法第83條規定沒收之。至扣案\n    之「DORAEMON」麥粥婉餐具組9 套、叉匙組14套，業經國際\n    影視有限公司鑑定為合法授權商品，是不應予沒收，附此敘\n    明。\n四、據上論斷，應依刑事訴訟法第449 條第1 項前段、第3 項、\n    第450 條第1 項、第454 條第2 項，商標法第82條、第83條\n    ，刑法第11條、第55條、第41條第1 項前段、第74條第1 項\n    第1款，逕以簡易判決處刑如主文。\n五、如不服本判決，得於判決書送達之翌日起10日內，以書狀敘\n    述理由（須附繕本），向本庭合議庭提起上訴。",
    "reason": "一、本件犯罪事實及證據，除於犯罪事實欄第23行「編號1 至18\n    」更正為「編號1 至9 」、「編號19」更正為「編號10」，\n    第24行「編號20」更正為「編號11」、「編號21」更正為「\n    編號12」，第25行「編號1 至7 」更正為「編號1 至6 」之\n    外，其餘均引用檢察官聲請簡易判決處刑書所載（如附件）\n    。\n二、核被告李雅琴所為，係犯商標法第82條之販賣仿冒商標商品\n    罪。其意圖販賣而陳列仿冒商標商品之低度行為，為販賣之\n    高度行為所吸收，不另論罪。又按刑事法若干犯罪之行為態\n    樣，本質上原具有反覆、延續實行之特徵，立法時既予特別\n    歸類，定為犯罪構成要件之行為要素，則行為人基於概括之\n    犯意，在密切接近之一定時、地持續實行之複次行為，倘依\n    社會通念，於客觀上認為符合一個反覆、延續性之行為觀念\n    者，於刑法評價上，即應僅成立一罪，俾免有重複評價、刑\n    度超過罪責與不法內涵之疑慮；學理上所稱「集合犯」之職\n    業性、營業性或收集性等具有重複特質之犯罪均屬之，例如\n    經營、從事業務、收集、販賣、製造、散布等行為概念者，\n    均屬包括一罪之集合犯概念（最高法院95年度台上字第1079\n    號、第3937號、第4686號判決意旨參照）。經查，被告自民\n    國97年間某日起開始販售上開仿冒商標商品至99年6 月5 日\n    上午11時許為警查獲止，先後雖有多次販賣之行為，然因係\n    基於營利之單一目的，於密集期間內，以相同之方式販賣上\n    開仿冒商標商品，具有反覆、延續實行之特徵，在行為概念\n    上，應評價認係包括一罪之集合犯，縱有多次販賣之舉措，\n    仍應評價認係包括一罪之集合犯。又被告以一販賣仿冒商標\n    商品之犯意，同時販賣上開仿冒「HELLO KITTY 」、「Cinn\n    amoroll 」、「Osaru No Monkichi 」、「Kerokerokeropp\n    i 」、「DORAEMON」等商標圖樣之商品，而侵害5 個商標專\n    用權，係一行為而犯數罪名，為同種想像競合犯，應依刑法\n    第55條之規定，從一重處斷。\n三、爰審酌被告為圖牟利，竟非法販賣仿冒商標商品，非但易使\n    民眾對商品品質判斷造成混淆，使商標專用權人合法商品之\n    信譽與品質受質疑，影響商標專用權人之商譽及正常可得收\n    益，對我國保護智慧財產權之國際形象受損，所生危害非輕\n    ，惟念及被告犯後已與告訴人日商三麗鷗股份有限公司達成\n    和解，併斟酌其犯罪之動機、目的、手段、品行、生活狀況\n    、智識程度，及扣案之仿冒商標商品之數量多達數百件、所\n    獲不法利益多寡、犯後態度等一切情狀，量處如主文所示之\n    刑，並於斟酌本案犯罪情節及被告資力等節後，諭知如主文\n    所示之易科罰金折算標準，以資懲戒。末查，被告前未曾因\n    故意犯罪受有期徒刑以上刑之宣告，有臺灣高等法院被告前\n    案紀錄表1 份在卷可稽，其因一時失慮，偶罹刑典，且已與\n    告訴人日商三麗鷗股份有限公司和解，取得告訴人宥恕，經\n    此刑之宣告後，應知所警惕，信無再犯之虞，本院因認所宣\n    告之刑以暫不執行為適當，爰依刑法第74條第1 項第1 款之\n    規定諭知緩刑2 年，以啟自新。扣案如附表一、二所示之仿\n    冒「HELLO KITTY 」、「Cinnamoroll 」、「Osaru No Mon\n    kichi 」、「Kerokerokeroppi 」等商標商品共219 件，仿\n    冒「DORAEMON」商標之商品共74件，均係仿冒商標之商品，\n    不問屬於犯人與否，應依商標法第83條規定沒收之。至扣案\n    之「DORAEMON」麥粥婉餐具組9 套、叉匙組14套，業經國際\n    影視有限公司鑑定為合法授權商品，是不應予沒收，附此敘\n    明。\n四、據上論斷，應依刑事訴訟法第449 條第1 項前段、第3 項、\n    第450 條第1 項、第454 條第2 項，商標法第82條、第83條\n    ，刑法第11條、第55條、第41條第1 項前段、第74條第1 項\n    第1款，逕以簡易判決處刑如主文。\n五、如不服本判決，得於判決書送達之翌日起10日內，以書狀敘\n    述理由（須附繕本），向本庭合議庭提起上訴。"
  },
  "search": "臺灣桃園地方法院刑事簡易判決100年度桃智簡字第1號聲請人臺灣桃園地方法院檢察署檢察官被告李雅琴上列被告因違反商標法案件，經檢察官聲請以簡易判決處刑（99年度偵字第26754號），本院判決如下：主文李雅琴共同明知為未得商標權人同意，於同一商品，使用相同之註冊商標之商品而販賣，處有期徒刑貳月，如易科罰金，以新臺幣壹仟元折算壹日。緩刑貳年。扣案如附表一、二所示之仿冒商標商品，均沒收。事實及理由一、本件犯罪事實及證據，除於犯罪事實欄第23行「編號1至18」更正為「編號1至9」、「編號19」更正為「編號10」，第24行「編號20」更正為「編號11」、「編號21」更正為「編號12」，第25行「編號1至7」更正為「編號1至6」之外，其餘均引用檢察官聲請簡易判決處刑書所載（如附件）。二、核被告李雅琴所為，係犯商標法第82條之販賣仿冒商標商品罪。其意圖販賣而陳列仿冒商標商品之低度行為，為販賣之高度行為所吸收，不另論罪。又按刑事法若干犯罪之行為態樣，本質上原具有反覆、延續實行之特徵，立法時既予特別歸類，定為犯罪構成要件之行為要素，則行為人基於概括之犯意，在密切接近之一定時、地持續實行之複次行為，倘依社會通念，於客觀上認為符合一個反覆、延續性之行為觀念者，於刑法評價上，即應僅成立一罪，俾免有重複評價、刑度超過罪責與不法內涵之疑慮；學理上所稱「集合犯」之職業性、營業性或收集性等具有重複特質之犯罪均屬之，例如經營、從事業務、收集、販賣、製造、散布等行為概念者，均屬包括一罪之集合犯概念（最高法院95年度台上字第1079號、第3937號、第4686號判決意旨參照）。經查，被告自民國97年間某日起開始販售上開仿冒商標商品至99年6月5日上午11時許為警查獲止，先後雖有多次販賣之行為，然因係基於營利之單一目的，於密集期間內，以相同之方式販賣上開仿冒商標商品，具有反覆、延續實行之特徵，在行為概念上，應評價認係包括一罪之集合犯，縱有多次販賣之舉措，仍應評價認係包括一罪之集合犯。又被告以一販賣仿冒商標商品之犯意，同時販賣上開仿冒「HELLOKITTY」、「Cinnamoroll」、「OsaruNoMonkichi」、「Kerokerokeroppi」、「DORAEMON」等商標圖樣之商品，而侵害5個商標專用權，係一行為而犯數罪名，為同種想像競合犯，應依刑法第55條之規定，從一重處斷。三、爰審酌被告為圖牟利，竟非法販賣仿冒商標商品，非但易使民眾對商品品質判斷造成混淆，使商標專用權人合法商品之信譽與品質受質疑，影響商標專用權人之商譽及正常可得收益，對我國保護智慧財產權之國際形象受損，所生危害非輕，惟念及被告犯後已與告訴人日商三麗鷗股份有限公司達成和解，併斟酌其犯罪之動機、目的、手段、品行、生活狀況、智識程度，及扣案之仿冒商標商品之數量多達數百件、所獲不法利益多寡、犯後態度等一切情狀，量處如主文所示之刑，並於斟酌本案犯罪情節及被告資力等節後，諭知如主文所示之易科罰金折算標準，以資懲戒。末查，被告前未曾因故意犯罪受有期徒刑以上刑之宣告，有臺灣高等法院被告前案紀錄表1份在卷可稽，其因一時失慮，偶罹刑典，且已與告訴人日商三麗鷗股份有限公司和解，取得告訴人宥恕，經此刑之宣告後，應知所警惕，信無再犯之虞，本院因認所宣告之刑以暫不執行為適當，爰依刑法第74條第1項第1款之規定諭知緩刑2年，以啟自新。扣案如附表一、二所示之仿冒「HELLOKITTY」、「Cinnamoroll」、「OsaruNoMonkichi」、「Kerokerokeroppi」等商標商品共219件，仿冒「DORAEMON」商標之商品共74件，均係仿冒商標之商品，不問屬於犯人與否，應依商標法第83條規定沒收之。至扣案之「DORAEMON」麥粥婉餐具組9套、叉匙組14套，業經國際影視有限公司鑑定為合法授權商品，是不應予沒收，附此敘明。四、據上論斷，應依刑事訴訟法第449條第1項前段、第3項、第450條第1項、第454條第2項，商標法第82條、第83條，刑法第11條、第55條、第41條第1項前段、第74條第1項第1款，逕以簡易判決處刑如主文。五、如不服本判決，得於判決書送達之翌日起10日內，以書狀敘述理由（須附繕本），向本庭合議庭提起上訴。中華民國100年7月25日刑事第二庭法官陳秋君以上正本證明與原本無異。如不服本判決，應於判決送達後10日內向本院提出上訴狀（應附繕本）。書記官吳采蓉中華民國100年8月2日附錄本案論罪科刑法條全文：商標法第82條明知為前條商品而販賣、意圖販賣而陳列、輸出或輸入者，處1年以下有期徒刑、拘役或科或併科新臺幣5萬元以下罰金。附表一：（日商三麗鷗股份有限公司之註冊商標）┌──┬─────────────────┬─────┐│編號│扣案物品│數量（件）│├──┼─────────────────┼─────┤│1│仿冒HELLOKITTY上衣│51│├──┼─────────────────┼─────┤│2│仿冒HELLOKITTY計算機│1│├──┼─────────────────┼─────┤│3│仿冒HELLOKITTY保暖手套│4│├──┼─────────────────┼─────┤│4│仿冒HELLOKITTY耳罩│8│├──┼─────────────────┼─────┤│5│仿冒HELLOKITTY鍋子│11│├──┼─────────────────┼─────┤│6│仿冒HELLOKITTY雨衣│2│├──┼─────────────────┼─────┤│7│仿冒HELLOKITTY驅蚊手環│38│├──┼─────────────────┼─────┤│8│仿冒HELLOKITTY夜燈│6│├──┼─────────────────┼─────┤│9│仿冒HELLOKITTY置物籃│5│├──┼─────────────────┼─────┤│10│仿冒HELLOKITTY筆電保護貼│3│├──┼─────────────────┼─────┤│11│仿冒HELLOKITTY內褲│2│├──┼─────────────────┼─────┤│12│仿冒HELLOKITTY手提袋│7│├──┼─────────────────┼─────┤│13│仿冒HELLOKITTY袖套│10│├──┼─────────────────┼─────┤│14│仿冒HELLOKITTY滑鼠│3│├──┼─────────────────┼─────┤│15│仿冒HELLOKITTY電子驅蚊器│14│├──┼─────────────────┼─────┤│16│仿冒HELLOKITTY便利貼│2│├──┼─────────────────┼─────┤│17│仿冒HELLOKITTY眼罩│1│├──┼─────────────────┼─────┤│18│仿冒HELLOKITTY保暖電子滑鼠墊│10│├──┼─────────────────┼─────┤│19│仿冒Cinnamoroll上衣│2│├──┼─────────────────┼─────┤│20│仿冒OsaruNoMonkichi保暖手套│3│├──┼─────────────────┼─────┤│21│仿冒Kerokerokeroppi護膝│36│├──┼─────────────────┼─────┤││合計│共219件│└──┴─────────────────┴─────┘附表二：（日商小學館股份有限公司之註冊商標）┌──┬─────────────────┬─────┐│編號│扣案物品│數量│├──┼─────────────────┼─────┤│1│仿冒DORAEMON智能筷子│3│├──┼─────────────────┼─────┤│2│仿冒DORAEMON上衣│48│├──┼─────────────────┼─────┤│3│仿冒DORAEMON貼紙│1│├──┼─────────────────┼─────┤│4│仿冒DORAEMON筆電保護貼│5│├──┼─────────────────┼─────┤│5│仿冒DORAEMON夜燈│6│├──┼─────────────────┼─────┤│6│仿冒DORAEMON鍋子│5│├──┼─────────────────┼─────┤│7│仿冒DORAEMON電子保暖滑鼠墊│6│├──┼─────────────────┼─────┤││合計│共74件│└──┴─────────────────┴─────┘",
  "characters": {
    "judges": [
      "陳秋君"
    ],
    "prosecutors": [

    ],
    "lawyers": [

    ],
    "clerks": [
      "吳采蓉"
    ],
    "plaintiffs": [

    ],
    "defendants": [
      "李雅琴"
    ],
    "prosecutor_office": [
      "臺灣桃園地方法院檢察署檢察官"
    ],
    "creditors": [

    ],
    "debtors": [

    ],
    "judicial_associate_officer": [

    ]
  },
  "adjudged_at": "2011-07-25",
  "created_at": "2016-02-14 02:32:02",
  "updated_at": "2016-02-14 02:32:02"
}