{
  "identify": "TPB-90-訴-5763-20020913-1",
  "court": {
    "name": "臺北高等行政法院",
    "code": "TPB"
  },
  "division": {
    "name": "行政",
    "code": "A"
  },
  "year": 90,
  "word": "訴",
  "number": "5763",
  "jcheck": "1",
  "reason": "限制出境",
  "content": "臺北高等行政法院判決                            九十年度訴字第五七六三號\n                              .\n    原      告    甲○○\n    訴訟代理人    林月雪律師\n                  江鶴鵬律師\n    被      告    財政部\n    代  表  人    李庸三部長.\n    訴訟代理人    乙○\n                  丙○○\n右當事人間因限制出境事件，原告不服行政院中華民國九十年八月八日臺九十訴字第\n○四四○七八號訴願決定，提起行政訴訟。本院判決如左：\n    主  文\n訴願決定及原處分均撤銷。\n訴訟費用由被告負擔。\n    事  實\n一緣原告係忠勵有限公司（以下簡稱忠勵公司）負責人，被告所屬臺灣省南區國稅局\n  以忠勵公司欠繳民國（下同）八十四及八十五年度營利事業所得稅本稅、滯納金及\n  滯納利息計新臺幣（下同）二、○四六、三九六元，乃依限制欠稅人或欠稅營利事\n  業負責人出境實施辦法（以下簡稱限制出境實施辦法）第二條第一項規定函報被告\n  以九十年二月二十七日臺財稅字第○九○○○一○八○一號函請內政部警政署入出\n  境管理局（以下簡稱境管局）限制原告出境，經境管局以九十年三月九日（九○）\n  境愛岑字第三二五六三號書函禁止原告出國。原告不服，以其因需資金週轉，乃自\n  報紙上找一位自稱「邱創揆」之代書幫忙辦理貸款，俟其交付其本人及其兄弟杜貴\n  宏、杜世忠之身分證影本資料後，邱創揆即失其行蹤，直至八十四年二月起陸續有\n  電器廠商及銀行等向其等催收帳款時，始知其等身分證資料被人冒用，嗣後經查獲\n  冒用者為王忠輝，其因遭人冒用姓名被訴竊盜案，業獲臺灣新竹地方法院檢察署檢\n  察官為不起訴處分，其被人冒用姓名開立甲存帳戶簽發支票案，現正由臺灣臺南地\n  方法院審理中；又其一直擔任廚師工作，未曾設立忠勵公司，被告未詳加查明即逕\n  行課稅，又限制其出境，實難甘服等語，提起訴願，遭決定駁回，遂向本院提起行\n  政訴訟。\n二兩造聲明：\n  (一)原告聲明：如主文所示。\n  (二)被告聲明：原告之訴駁回。\n三兩造爭點：\n  原告主張其身分證資料遭冒用設立忠勵公司，被告未詳查即以該公司欠稅而限制原\n  告出境，顯有違誤，是否可採？\n  (一)原告主張之理由：\n    1.查原告於八十三年七月間因需資金週轉，乃自報紙上找一位自稱「邱創揆」之\n      代書幫忙辦理銀行貸款，俟原告交付原告及杜貴宏、杜世忠（係原告之弟、兄\n      ）之身分證影本資料後，代書「邱創揆」即失其行蹤，原告始知受騙，距自八\n      十四年二月起陸續有電器廠商、汽車經銷商及銀行分別向原告、杜貴宏及杜世\n      忠催收帳款，令原告深感莫名，與上開公司連絡始知，原告及原告弟兄等人之\n      身分證資料被人冒用偽造身分證，原告及原告弟兄等三人曾至臺北縣板橋市調\n      查站檢舉做筆錄，證明身分證資料被人冒用情事。\n    2.原告曾因遭人冒用姓名，而被訴竊盜，在臺灣新竹地方法院檢察署（八十六年\n      度偵字第二二二五號），嗣後以不起訴處分，被人冒用姓名開立甲存帳戶簽發\n      支票，由債權人王西安向原告聲請支付命令（八十四年度促字第二五六號）經\n      原告提出異議，原告一直擔任廚師工作，未曾設立忠勵公司，被告於九十一年\n      七月二十四日鈞院調查時所提出申請設立忠勵公司之負責人「甲○○」之身分\n      證影本，該身分證影本上之照片顯非原告本人，由此可知，忠勵公司並非原告\n      設立。\n    3.綜上所述，忠勵公司並非原告所設立，被告未詳加查明即逕行課稅，並限制出\n      境，令原告難以甘服，請鈞院鑒核，撤銷原處分及訴願決定，俾保原告合法權\n      益。\n  (二)被告主張之理由：\n    1.本件原告係忠勵公司之負責人，該公司滯欠已確定八十四及八十五年度營利事\n      業所得稅、滯納金及滯納利息計二、○四六、三九六元，被告所屬臺灣省南區\n      國稅局以其欠繳稅款，已達限制出境實施辦法第二條第一項限制出境金額標準\n      ，乃依稅捐稽徵法第二十四條第三項規定，函報經被告以九十年二月二十七日\n      臺財稅第○九○○○一○八○一號函轉境管局限制原告出境，揆諸相關規定，\n      並無不合。\n    2.原告訴稱其一直擔任廚師工作，未曾設立忠勵公司，因身分證資料遭王忠輝或\n      其同夥換貼照片使用，以致被訴竊盜，案經臺灣新竹地方法院檢察署以不起訴\n      處分，又被冒用姓名開立甲存帳戶簽發支票，債權人向原告聲請支付命令，經\n      原告提出異議，現由臺灣臺南地方法院民事庭審理中，忠勵公司並非原告所設\n      立，原處分未詳加查明即因該公司欠稅而限制原告出境，難以甘服等語，惟查\n      稽徵機關依規定報請限制營利事業負責人出境時，依被告六十八年七月十八日\n      臺財稅第三四九二七號函釋，應以依法得代表該營利事業之法定代理人為限；\n      所謂「依法得代表該營利事業之法定代理人」，係指依公司法規定，經經濟部\n      發給執照上所記載之公司負責人，亦為被告八十三年九月二十二日臺財稅第八\n      三○四三二○二七號函釋有案。本件忠勵公司於經濟部之公司設立登記資料，\n      負責人為原告，被告依相關規定限制該公司負責人即原告出境，於法並無不合\n      。原告雖稱因遭人冒用姓名而被訴竊盜及開立甲存帳戶簽發支票，並提示剪報\n      資料證明其身分遭王忠輝冒用行騙，惟該剪報資料並非法院終局判決，尚難證\n      明其確係被冒名登記為忠勵公司之負責人，所訴核無可採。\n    3.綜上論結，原處分及訴願決定並無違誤，請駁回原告之訴，以維稅政。\n    理  由\n一本件原告起訴後，被告之代表人已由顏慶章更換為李庸三，被告新代表人李庸三具\n  狀聲明承受訴訟，於法有據，應予准許，合先敘明。\n二按「納稅義務人欠繳應納稅捐達一定金額者，得由司法機關或財政部，函請內政部\n  入出境管理局，限制其出境；其為營利事業者，得限制其負責人出境‧‧‧」又「\n  在中華民國境內居住之個人或在中華民國境內之營利事業，其已確定之應納稅捐或\n  關稅逾法定繳納期限尚未繳納，其欠繳稅款及已確定之罰鍰單計或合計，個人在五\n  十萬元以上，營利事業在一百萬元以上者，由稅捐稽徵機關或海關報請財政部函請\n  內政部入出境管理局限制該欠稅人或欠稅營利事業負責人出境。」稅捐稽徵法第二\n  十四條第三項前段及限制欠稅人或欠稅營利事業負責人出境實施辦法第二條第一項\n  固定有明文。惟依上開法條規定，欠稅納稅義務人之營利事業被限制出境者，應以\n  其負責人為限，若不知情經確實證明係被冒用為負責人者，則無適用餘地。\n三本件原告登記為忠勵公司負責人，被告所屬臺灣省南區國稅局以忠勵公司欠繳八十\n  四及八十五年度營利事業所得稅本稅、滯納金及滯納利息計二、○四六、三九六元\n  ，乃層報被告函請境管局限制原告出境，經境管局函告原告禁止出國。原告不服，\n  以其因需資金週轉，乃自報紙上找一位自稱「邱創揆」之代書幫忙辦理貸款，俟其\n  交付其本人及其兄弟杜貴宏、杜世忠之身分證影本資料後，邱創揆即失其行蹤，直\n  至八十四年二月起陸續有電器廠商及銀行等向其等催收帳款時，始知其等身分證資\n  料被人冒用，嗣後經查獲冒用者為王忠輝，其因遭人冒用姓名被訴竊盜案，業獲臺\n  灣新竹地方法院檢察署檢察官為不起訴處分，其被人冒用姓名開立甲存帳戶簽發支\n  票案，現正由臺灣臺南地方法院審理中；又其一直擔任廚師工作，未曾設立忠勵公\n  司，被告未詳加查明即限制其出境，實難甘服等語，提起訴願，遭決定駁回，復起\n  訴主張其身分證資料遭冒用設立忠勵公司，被告未詳查即以該公司欠稅而限制原告\n  出境，顯有違誤，詳如其起訴狀事實欄所載理由等語。查本件原告主張其一直擔任\n  廚師工作，係不知情被冒用登記為忠勵公司負責人等情，業據其提出台灣新竹地方\n  法院檢察署檢察官八十六年度偵字第二二二五號不起訴處分書載明：「甲○○確係\n  遭人冒用身分證（以真的身分證換貼他人照片之方式），向台灣省建設廳申請設立\n  『忠勵有限公司』，設址在台南縣永康市○○里○○路六八九之六十五號，代表人\n  為甲○○，並取得經濟部公司執照及台南縣政府營利事業登記證。」又被告提示當\n  時忠勵公司之營利事業統一發證申請書所附甲○○身分證照片、職業欄、住址欄，\n  均已遭換貼、偽造，有上開不起訴處分書及申請書暨照片附卷可憑，以上原告被冒\n  用登記為忠勵公司負責人之事實，並經原告之弟即證人杜世忠到庭證述甚詳，復為\n  被告之訴訟代理人於準備程序期日及言詞辯論期日所不爭執，原告之主張，自堪信\n  為真實。從而，被告未經查證即函請境管局限制其出境，顯有違誤，訴願決定，未\n  予糾正，予以駁回，亦有疏誤，原告起訴，執以指摘，非無理由，爰將訴願決定及\n  原處分均予撤銷，以昭折服。\n四據上論結，本件原告之訴為有理由，依行政訴訟法第九十八條第三項前段，判決如\n  主文。\n中      華      民      國    九十一    年      九      月     十三     日\n                            臺 北 高 等 行 政 法 院  第 一 庭\n                                           審 判 長  法    官  王立杰\n                                                     法    官  劉介中\n                                                     法    官  黃本仁\n右為正本係照原本作成。\n如不服本判決，應於送達後二十日內，向本院提出上訴狀並表明上訴理由，如於本判\n決宣示後送達前提起上訴者，應於判決送達後二十日內補提上訴理由書（須按他造人\n數附繕本）。\n中      華      民      國    九十一    年      九      月     十六     日\n                                                     書 記 官  姚國華\n",
  "structure": {
    "main": "訴願決定及原處分均撤銷。\n訴訟費用由被告負擔。",
    "fact": "一緣原告係忠勵有限公司（以下簡稱忠勵公司）負責人，被告所屬臺灣省南區國稅局\n  以忠勵公司欠繳民國（下同）八十四及八十五年度營利事業所得稅本稅、滯納金及\n  滯納利息計新臺幣（下同）二、○四六、三九六元，乃依限制欠稅人或欠稅營利事\n  業負責人出境實施辦法（以下簡稱限制出境實施辦法）第二條第一項規定函報被告\n  以九十年二月二十七日臺財稅字第○九○○○一○八○一號函請內政部警政署入出\n  境管理局（以下簡稱境管局）限制原告出境，經境管局以九十年三月九日（九○）\n  境愛岑字第三二五六三號書函禁止原告出國。原告不服，以其因需資金週轉，乃自\n  報紙上找一位自稱「邱創揆」之代書幫忙辦理貸款，俟其交付其本人及其兄弟杜貴\n  宏、杜世忠之身分證影本資料後，邱創揆即失其行蹤，直至八十四年二月起陸續有\n  電器廠商及銀行等向其等催收帳款時，始知其等身分證資料被人冒用，嗣後經查獲\n  冒用者為王忠輝，其因遭人冒用姓名被訴竊盜案，業獲臺灣新竹地方法院檢察署檢\n  察官為不起訴處分，其被人冒用姓名開立甲存帳戶簽發支票案，現正由臺灣臺南地\n  方法院審理中；又其一直擔任廚師工作，未曾設立忠勵公司，被告未詳加查明即逕\n  行課稅，又限制其出境，實難甘服等語，提起訴願，遭決定駁回，遂向本院提起行\n  政訴訟。\n二兩造聲明：\n  (一)原告聲明：如主文所示。\n  (二)被告聲明：原告之訴駁回。\n三兩造爭點：\n  原告主張其身分證資料遭冒用設立忠勵公司，被告未詳查即以該公司欠稅而限制原\n  告出境，顯有違誤，是否可採？\n  (一)原告主張之理由：\n    1.查原告於八十三年七月間因需資金週轉，乃自報紙上找一位自稱「邱創揆」之\n      代書幫忙辦理銀行貸款，俟原告交付原告及杜貴宏、杜世忠（係原告之弟、兄\n      ）之身分證影本資料後，代書「邱創揆」即失其行蹤，原告始知受騙，距自八\n      十四年二月起陸續有電器廠商、汽車經銷商及銀行分別向原告、杜貴宏及杜世\n      忠催收帳款，令原告深感莫名，與上開公司連絡始知，原告及原告弟兄等人之\n      身分證資料被人冒用偽造身分證，原告及原告弟兄等三人曾至臺北縣板橋市調\n      查站檢舉做筆錄，證明身分證資料被人冒用情事。\n    2.原告曾因遭人冒用姓名，而被訴竊盜，在臺灣新竹地方法院檢察署（八十六年\n      度偵字第二二二五號），嗣後以不起訴處分，被人冒用姓名開立甲存帳戶簽發\n      支票，由債權人王西安向原告聲請支付命令（八十四年度促字第二五六號）經\n      原告提出異議，原告一直擔任廚師工作，未曾設立忠勵公司，被告於九十一年\n      七月二十四日鈞院調查時所提出申請設立忠勵公司之負責人「甲○○」之身分\n      證影本，該身分證影本上之照片顯非原告本人，由此可知，忠勵公司並非原告\n      設立。\n    3.綜上所述，忠勵公司並非原告所設立，被告未詳加查明即逕行課稅，並限制出\n      境，令原告難以甘服，請鈞院鑒核，撤銷原處分及訴願決定，俾保原告合法權\n      益。\n  (二)被告主張之理由：\n    1.本件原告係忠勵公司之負責人，該公司滯欠已確定八十四及八十五年度營利事\n      業所得稅、滯納金及滯納利息計二、○四六、三九六元，被告所屬臺灣省南區\n      國稅局以其欠繳稅款，已達限制出境實施辦法第二條第一項限制出境金額標準\n      ，乃依稅捐稽徵法第二十四條第三項規定，函報經被告以九十年二月二十七日\n      臺財稅第○九○○○一○八○一號函轉境管局限制原告出境，揆諸相關規定，\n      並無不合。\n    2.原告訴稱其一直擔任廚師工作，未曾設立忠勵公司，因身分證資料遭王忠輝或\n      其同夥換貼照片使用，以致被訴竊盜，案經臺灣新竹地方法院檢察署以不起訴\n      處分，又被冒用姓名開立甲存帳戶簽發支票，債權人向原告聲請支付命令，經\n      原告提出異議，現由臺灣臺南地方法院民事庭審理中，忠勵公司並非原告所設\n      立，原處分未詳加查明即因該公司欠稅而限制原告出境，難以甘服等語，惟查\n      稽徵機關依規定報請限制營利事業負責人出境時，依被告六十八年七月十八日\n      臺財稅第三四九二七號函釋，應以依法得代表該營利事業之法定代理人為限；\n      所謂「依法得代表該營利事業之法定代理人」，係指依公司法規定，經經濟部\n      發給執照上所記載之公司負責人，亦為被告八十三年九月二十二日臺財稅第八\n      三○四三二○二七號函釋有案。本件忠勵公司於經濟部之公司設立登記資料，\n      負責人為原告，被告依相關規定限制該公司負責人即原告出境，於法並無不合\n      。原告雖稱因遭人冒用姓名而被訴竊盜及開立甲存帳戶簽發支票，並提示剪報\n      資料證明其身分遭王忠輝冒用行騙，惟該剪報資料並非法院終局判決，尚難證\n      明其確係被冒名登記為忠勵公司之負責人，所訴核無可採。\n    3.綜上論結，原處分及訴願決定並無違誤，請駁回原告之訴，以維稅政。",
    "reason": "一本件原告起訴後，被告之代表人已由顏慶章更換為李庸三，被告新代表人李庸三具\n  狀聲明承受訴訟，於法有據，應予准許，合先敘明。\n二按「納稅義務人欠繳應納稅捐達一定金額者，得由司法機關或財政部，函請內政部\n  入出境管理局，限制其出境；其為營利事業者，得限制其負責人出境‧‧‧」又「\n  在中華民國境內居住之個人或在中華民國境內之營利事業，其已確定之應納稅捐或\n  關稅逾法定繳納期限尚未繳納，其欠繳稅款及已確定之罰鍰單計或合計，個人在五\n  十萬元以上，營利事業在一百萬元以上者，由稅捐稽徵機關或海關報請財政部函請\n  內政部入出境管理局限制該欠稅人或欠稅營利事業負責人出境。」稅捐稽徵法第二\n  十四條第三項前段及限制欠稅人或欠稅營利事業負責人出境實施辦法第二條第一項\n  固定有明文。惟依上開法條規定，欠稅納稅義務人之營利事業被限制出境者，應以\n  其負責人為限，若不知情經確實證明係被冒用為負責人者，則無適用餘地。\n三本件原告登記為忠勵公司負責人，被告所屬臺灣省南區國稅局以忠勵公司欠繳八十\n  四及八十五年度營利事業所得稅本稅、滯納金及滯納利息計二、○四六、三九六元\n  ，乃層報被告函請境管局限制原告出境，經境管局函告原告禁止出國。原告不服，\n  以其因需資金週轉，乃自報紙上找一位自稱「邱創揆」之代書幫忙辦理貸款，俟其\n  交付其本人及其兄弟杜貴宏、杜世忠之身分證影本資料後，邱創揆即失其行蹤，直\n  至八十四年二月起陸續有電器廠商及銀行等向其等催收帳款時，始知其等身分證資\n  料被人冒用，嗣後經查獲冒用者為王忠輝，其因遭人冒用姓名被訴竊盜案，業獲臺\n  灣新竹地方法院檢察署檢察官為不起訴處分，其被人冒用姓名開立甲存帳戶簽發支\n  票案，現正由臺灣臺南地方法院審理中；又其一直擔任廚師工作，未曾設立忠勵公\n  司，被告未詳加查明即限制其出境，實難甘服等語，提起訴願，遭決定駁回，復起\n  訴主張其身分證資料遭冒用設立忠勵公司，被告未詳查即以該公司欠稅而限制原告\n  出境，顯有違誤，詳如其起訴狀事實欄所載理由等語。查本件原告主張其一直擔任\n  廚師工作，係不知情被冒用登記為忠勵公司負責人等情，業據其提出台灣新竹地方\n  法院檢察署檢察官八十六年度偵字第二二二五號不起訴處分書載明：「甲○○確係\n  遭人冒用身分證（以真的身分證換貼他人照片之方式），向台灣省建設廳申請設立\n  『忠勵有限公司』，設址在台南縣永康市○○里○○路六八九之六十五號，代表人\n  為甲○○，並取得經濟部公司執照及台南縣政府營利事業登記證。」又被告提示當\n  時忠勵公司之營利事業統一發證申請書所附甲○○身分證照片、職業欄、住址欄，\n  均已遭換貼、偽造，有上開不起訴處分書及申請書暨照片附卷可憑，以上原告被冒\n  用登記為忠勵公司負責人之事實，並經原告之弟即證人杜世忠到庭證述甚詳，復為\n  被告之訴訟代理人於準備程序期日及言詞辯論期日所不爭執，原告之主張，自堪信\n  為真實。從而，被告未經查證即函請境管局限制其出境，顯有違誤，訴願決定，未\n  予糾正，予以駁回，亦有疏誤，原告起訴，執以指摘，非無理由，爰將訴願決定及\n  原處分均予撤銷，以昭折服。\n四據上論結，本件原告之訴為有理由，依行政訴訟法第九十八條第三項前段，判決如\n  主文。\n中      華      民      國    九十一    年      九      月     十三     日\n                            臺 北 高 等 行 政 法 院  第 一 庭\n                                           審 判 長  法    官  王立杰\n                                                     法    官  劉介中\n                                                     法    官  黃本仁\n右為正本係照原本作成。\n如不服本判決，應於送達後二十日內，向本院提出上訴狀並表明上訴理由，如於本判\n決宣示後送達前提起上訴者，應於判決送達後二十日內補提上訴理由書（須按他造人\n數附繕本）。"
  },
  "search": "臺北高等行政法院判決九十年度訴字第五七六三號.原告甲○○訴訟代理人林月雪律師江鶴鵬律師被告財政部代表人李庸三部長.訴訟代理人乙○丙○○右當事人間因限制出境事件，原告不服行政院中華民國九十年八月八日臺九十訴字第○四四○七八號訴願決定，提起行政訴訟。本院判決如左：主文訴願決定及原處分均撤銷。訴訟費用由被告負擔。事實一緣原告係忠勵有限公司（以下簡稱忠勵公司）負責人，被告所屬臺灣省南區國稅局以忠勵公司欠繳民國（下同）八十四及八十五年度營利事業所得稅本稅、滯納金及滯納利息計新臺幣（下同）二、○四六、三九六元，乃依限制欠稅人或欠稅營利事業負責人出境實施辦法（以下簡稱限制出境實施辦法）第二條第一項規定函報被告以九十年二月二十七日臺財稅字第○九○○○一○八○一號函請內政部警政署入出境管理局（以下簡稱境管局）限制原告出境，經境管局以九十年三月九日（九○）境愛岑字第三二五六三號書函禁止原告出國。原告不服，以其因需資金週轉，乃自報紙上找一位自稱「邱創揆」之代書幫忙辦理貸款，俟其交付其本人及其兄弟杜貴宏、杜世忠之身分證影本資料後，邱創揆即失其行蹤，直至八十四年二月起陸續有電器廠商及銀行等向其等催收帳款時，始知其等身分證資料被人冒用，嗣後經查獲冒用者為王忠輝，其因遭人冒用姓名被訴竊盜案，業獲臺灣新竹地方法院檢察署檢察官為不起訴處分，其被人冒用姓名開立甲存帳戶簽發支票案，現正由臺灣臺南地方法院審理中；又其一直擔任廚師工作，未曾設立忠勵公司，被告未詳加查明即逕行課稅，又限制其出境，實難甘服等語，提起訴願，遭決定駁回，遂向本院提起行政訴訟。二兩造聲明：(一)原告聲明：如主文所示。(二)被告聲明：原告之訴駁回。三兩造爭點：原告主張其身分證資料遭冒用設立忠勵公司，被告未詳查即以該公司欠稅而限制原告出境，顯有違誤，是否可採？(一)原告主張之理由：1.查原告於八十三年七月間因需資金週轉，乃自報紙上找一位自稱「邱創揆」之代書幫忙辦理銀行貸款，俟原告交付原告及杜貴宏、杜世忠（係原告之弟、兄）之身分證影本資料後，代書「邱創揆」即失其行蹤，原告始知受騙，距自八十四年二月起陸續有電器廠商、汽車經銷商及銀行分別向原告、杜貴宏及杜世忠催收帳款，令原告深感莫名，與上開公司連絡始知，原告及原告弟兄等人之身分證資料被人冒用偽造身分證，原告及原告弟兄等三人曾至臺北縣板橋市調查站檢舉做筆錄，證明身分證資料被人冒用情事。2.原告曾因遭人冒用姓名，而被訴竊盜，在臺灣新竹地方法院檢察署（八十六年度偵字第二二二五號），嗣後以不起訴處分，被人冒用姓名開立甲存帳戶簽發支票，由債權人王西安向原告聲請支付命令（八十四年度促字第二五六號）經原告提出異議，原告一直擔任廚師工作，未曾設立忠勵公司，被告於九十一年七月二十四日鈞院調查時所提出申請設立忠勵公司之負責人「甲○○」之身分證影本，該身分證影本上之照片顯非原告本人，由此可知，忠勵公司並非原告設立。3.綜上所述，忠勵公司並非原告所設立，被告未詳加查明即逕行課稅，並限制出境，令原告難以甘服，請鈞院鑒核，撤銷原處分及訴願決定，俾保原告合法權益。(二)被告主張之理由：1.本件原告係忠勵公司之負責人，該公司滯欠已確定八十四及八十五年度營利事業所得稅、滯納金及滯納利息計二、○四六、三九六元，被告所屬臺灣省南區國稅局以其欠繳稅款，已達限制出境實施辦法第二條第一項限制出境金額標準，乃依稅捐稽徵法第二十四條第三項規定，函報經被告以九十年二月二十七日臺財稅第○九○○○一○八○一號函轉境管局限制原告出境，揆諸相關規定，並無不合。2.原告訴稱其一直擔任廚師工作，未曾設立忠勵公司，因身分證資料遭王忠輝或其同夥換貼照片使用，以致被訴竊盜，案經臺灣新竹地方法院檢察署以不起訴處分，又被冒用姓名開立甲存帳戶簽發支票，債權人向原告聲請支付命令，經原告提出異議，現由臺灣臺南地方法院民事庭審理中，忠勵公司並非原告所設立，原處分未詳加查明即因該公司欠稅而限制原告出境，難以甘服等語，惟查稽徵機關依規定報請限制營利事業負責人出境時，依被告六十八年七月十八日臺財稅第三四九二七號函釋，應以依法得代表該營利事業之法定代理人為限；所謂「依法得代表該營利事業之法定代理人」，係指依公司法規定，經經濟部發給執照上所記載之公司負責人，亦為被告八十三年九月二十二日臺財稅第八三○四三二○二七號函釋有案。本件忠勵公司於經濟部之公司設立登記資料，負責人為原告，被告依相關規定限制該公司負責人即原告出境，於法並無不合。原告雖稱因遭人冒用姓名而被訴竊盜及開立甲存帳戶簽發支票，並提示剪報資料證明其身分遭王忠輝冒用行騙，惟該剪報資料並非法院終局判決，尚難證明其確係被冒名登記為忠勵公司之負責人，所訴核無可採。3.綜上論結，原處分及訴願決定並無違誤，請駁回原告之訴，以維稅政。理由一本件原告起訴後，被告之代表人已由顏慶章更換為李庸三，被告新代表人李庸三具狀聲明承受訴訟，於法有據，應予准許，合先敘明。二按「納稅義務人欠繳應納稅捐達一定金額者，得由司法機關或財政部，函請內政部入出境管理局，限制其出境；其為營利事業者，得限制其負責人出境‧‧‧」又「在中華民國境內居住之個人或在中華民國境內之營利事業，其已確定之應納稅捐或關稅逾法定繳納期限尚未繳納，其欠繳稅款及已確定之罰鍰單計或合計，個人在五十萬元以上，營利事業在一百萬元以上者，由稅捐稽徵機關或海關報請財政部函請內政部入出境管理局限制該欠稅人或欠稅營利事業負責人出境。」稅捐稽徵法第二十四條第三項前段及限制欠稅人或欠稅營利事業負責人出境實施辦法第二條第一項固定有明文。惟依上開法條規定，欠稅納稅義務人之營利事業被限制出境者，應以其負責人為限，若不知情經確實證明係被冒用為負責人者，則無適用餘地。三本件原告登記為忠勵公司負責人，被告所屬臺灣省南區國稅局以忠勵公司欠繳八十四及八十五年度營利事業所得稅本稅、滯納金及滯納利息計二、○四六、三九六元，乃層報被告函請境管局限制原告出境，經境管局函告原告禁止出國。原告不服，以其因需資金週轉，乃自報紙上找一位自稱「邱創揆」之代書幫忙辦理貸款，俟其交付其本人及其兄弟杜貴宏、杜世忠之身分證影本資料後，邱創揆即失其行蹤，直至八十四年二月起陸續有電器廠商及銀行等向其等催收帳款時，始知其等身分證資料被人冒用，嗣後經查獲冒用者為王忠輝，其因遭人冒用姓名被訴竊盜案，業獲臺灣新竹地方法院檢察署檢察官為不起訴處分，其被人冒用姓名開立甲存帳戶簽發支票案，現正由臺灣臺南地方法院審理中；又其一直擔任廚師工作，未曾設立忠勵公司，被告未詳加查明即限制其出境，實難甘服等語，提起訴願，遭決定駁回，復起訴主張其身分證資料遭冒用設立忠勵公司，被告未詳查即以該公司欠稅而限制原告出境，顯有違誤，詳如其起訴狀事實欄所載理由等語。查本件原告主張其一直擔任廚師工作，係不知情被冒用登記為忠勵公司負責人等情，業據其提出台灣新竹地方法院檢察署檢察官八十六年度偵字第二二二五號不起訴處分書載明：「甲○○確係遭人冒用身分證（以真的身分證換貼他人照片之方式），向台灣省建設廳申請設立『忠勵有限公司』，設址在台南縣永康市○○里○○路六八九之六十五號，代表人為甲○○，並取得經濟部公司執照及台南縣政府營利事業登記證。」又被告提示當時忠勵公司之營利事業統一發證申請書所附甲○○身分證照片、職業欄、住址欄，均已遭換貼、偽造，有上開不起訴處分書及申請書暨照片附卷可憑，以上原告被冒用登記為忠勵公司負責人之事實，並經原告之弟即證人杜世忠到庭證述甚詳，復為被告之訴訟代理人於準備程序期日及言詞辯論期日所不爭執，原告之主張，自堪信為真實。從而，被告未經查證即函請境管局限制其出境，顯有違誤，訴願決定，未予糾正，予以駁回，亦有疏誤，原告起訴，執以指摘，非無理由，爰將訴願決定及原處分均予撤銷，以昭折服。四據上論結，本件原告之訴為有理由，依行政訴訟法第九十八條第三項前段，判決如主文。中華民國九十一年九月十三日臺北高等行政法院第一庭審判長法官王立杰法官劉介中法官黃本仁右為正本係照原本作成。如不服本判決，應於送達後二十日內，向本院提出上訴狀並表明上訴理由，如於本判決宣示後送達前提起上訴者，應於判決送達後二十日內補提上訴理由書（須按他造人數附繕本）。中華民國九十一年九月十六日書記官姚國華",
  "characters": {
    "judges": [
      "王立杰",
      "劉介中",
      "黃本仁"
    ],
    "prosecutors": [

    ],
    "lawyers": [
      "林月雪",
      "江鶴鵬"
    ],
    "clerks": [

    ],
    "plaintiffs": [
      "甲"
    ],
    "defendants": [
      "財政部"
    ],
    "prosecutor_office": [

    ],
    "creditors": [

    ],
    "debtors": [

    ],
    "judicial_associate_officer": [

    ]
  },
  "adjudged_at": "2002-09-13",
  "created_at": "2016-02-04 17:42:46",
  "updated_at": "2016-02-04 17:42:46"
}