{
  "identify": "KLD-94-訴-140-20050328-1",
  "court": {
    "name": "臺灣基隆地方法院",
    "code": "KLD"
  },
  "division": {
    "name": "刑事",
    "code": "M"
  },
  "year": 94,
  "word": "訴",
  "number": "140",
  "jcheck": "1",
  "reason": "毒品危害防制條例",
  "content": "臺灣基隆地方法院刑事判決        94年度訴字第140號\n公  訴  人  臺灣基隆地方法院檢察署檢察官\n被      告  甲○○  男  46歲.\n上列被告因毒品危害防制條例案件，經檢察官提起公訴（94年度\n毒偵字第335 號），並經本院合議庭裁定由受命法官獨任進行簡\n式審判程序，判決如下：\n    主      文\n甲○○施用第一級毒品，累犯，處有期徒刑柒月；又施用第二級\n毒品，累犯，處有期徒刑肆月。應執行有期徒刑拾月。\n    事實及理由\n一、本件犯罪事實應補充：「甲○○前因麻藥、煙毒等罪，經本\n    院裁定應執行刑為有期徒刑10年4 月。其於民國94年1 月20\n    日凌晨1 時許（起訴書誤繕為94年1 月20日採尿前之4日 內\n    某時），在基隆市○○路52之1 號2 樓友人住處（起訴書誤\n    繕為在不詳地點），將第二級毒品安非他命放置於吸食器內\n    加熱吸取煙霧之方式，施用第二級毒品安非他命1 次」、證\n    據應補充：「被告於本院準備程序及審判程序之自白」、應\n    適用之法條應補充：「被告持有第一、二級毒品海洛因、安\n    非他命係供施用，其持有之低度行為應為施用之高度行為所\n    吸收，不另論罪」外，餘犯罪事實、證據及應適用之法條均\n    引用如附件檢察官起訴書之記載。\n二、據上論斷，應依刑事訴訟法第273 條之1 第1 項、第284 條\n    之1 、第299 條第1 項前段、第310 條之2 、第454 條第2\n    項，毒品危害防制條例第10條第1 項、第2 項、第23條第2\n    項，刑法第11條前段、第47條、第51條第5 款，判決如主文\n    。\n本案經檢察官林伯宇到庭執行職務。\n中    華    民    國    94    年    3     月    28    日\n                  刑事第二庭法  官    何怡穎\n以上正本證明與原本無異。\n對於本件判決如有不服，應於收受送達後10日內，向本院提出上\n訴書狀，上訴於臺灣高等法院，並按他造當事人之人數附具繕本\n。\n中    華    民    國    94    年    3     月    28    日\n                            書記官    李繼業\n附錄本案論罪科刑法條：\n毒品危害防制條例第10條\n施用第一級毒品者，處6 月以上5 年以下有期徒刑。\n施用第二級毒品者，處3 年以下有期徒刑。\n",
  "structure": {
    "main": "甲○○施用第一級毒品，累犯，處有期徒刑柒月；又施用第二級\n毒品，累犯，處有期徒刑肆月。應執行有期徒刑拾月。",
    "fact": "一、本件犯罪事實應補充：「甲○○前因麻藥、煙毒等罪，經本\n    院裁定應執行刑為有期徒刑10年4 月。其於民國94年1 月20\n    日凌晨1 時許（起訴書誤繕為94年1 月20日採尿前之4日 內\n    某時），在基隆市○○路52之1 號2 樓友人住處（起訴書誤\n    繕為在不詳地點），將第二級毒品安非他命放置於吸食器內\n    加熱吸取煙霧之方式，施用第二級毒品安非他命1 次」、證\n    據應補充：「被告於本院準備程序及審判程序之自白」、應\n    適用之法條應補充：「被告持有第一、二級毒品海洛因、安\n    非他命係供施用，其持有之低度行為應為施用之高度行為所\n    吸收，不另論罪」外，餘犯罪事實、證據及應適用之法條均\n    引用如附件檢察官起訴書之記載。\n二、據上論斷，應依刑事訴訟法第273 條之1 第1 項、第284 條\n    之1 、第299 條第1 項前段、第310 條之2 、第454 條第2\n    項，毒品危害防制條例第10條第1 項、第2 項、第23條第2\n    項，刑法第11條前段、第47條、第51條第5 款，判決如主文\n    。\n本案經檢察官林伯宇到庭執行職務。",
    "reason": "一、本件犯罪事實應補充：「甲○○前因麻藥、煙毒等罪，經本\n    院裁定應執行刑為有期徒刑10年4 月。其於民國94年1 月20\n    日凌晨1 時許（起訴書誤繕為94年1 月20日採尿前之4日 內\n    某時），在基隆市○○路52之1 號2 樓友人住處（起訴書誤\n    繕為在不詳地點），將第二級毒品安非他命放置於吸食器內\n    加熱吸取煙霧之方式，施用第二級毒品安非他命1 次」、證\n    據應補充：「被告於本院準備程序及審判程序之自白」、應\n    適用之法條應補充：「被告持有第一、二級毒品海洛因、安\n    非他命係供施用，其持有之低度行為應為施用之高度行為所\n    吸收，不另論罪」外，餘犯罪事實、證據及應適用之法條均\n    引用如附件檢察官起訴書之記載。\n二、據上論斷，應依刑事訴訟法第273 條之1 第1 項、第284 條\n    之1 、第299 條第1 項前段、第310 條之2 、第454 條第2\n    項，毒品危害防制條例第10條第1 項、第2 項、第23條第2\n    項，刑法第11條前段、第47條、第51條第5 款，判決如主文\n    。\n本案經檢察官林伯宇到庭執行職務。"
  },
  "search": "臺灣基隆地方法院刑事判決94年度訴字第140號公訴人臺灣基隆地方法院檢察署檢察官被告甲○○男46歲.上列被告因毒品危害防制條例案件，經檢察官提起公訴（94年度毒偵字第335號），並經本院合議庭裁定由受命法官獨任進行簡式審判程序，判決如下：主文甲○○施用第一級毒品，累犯，處有期徒刑柒月；又施用第二級毒品，累犯，處有期徒刑肆月。應執行有期徒刑拾月。事實及理由一、本件犯罪事實應補充：「甲○○前因麻藥、煙毒等罪，經本院裁定應執行刑為有期徒刑10年4月。其於民國94年1月20日凌晨1時許（起訴書誤繕為94年1月20日採尿前之4日內某時），在基隆市○○路52之1號2樓友人住處（起訴書誤繕為在不詳地點），將第二級毒品安非他命放置於吸食器內加熱吸取煙霧之方式，施用第二級毒品安非他命1次」、證據應補充：「被告於本院準備程序及審判程序之自白」、應適用之法條應補充：「被告持有第一、二級毒品海洛因、安非他命係供施用，其持有之低度行為應為施用之高度行為所吸收，不另論罪」外，餘犯罪事實、證據及應適用之法條均引用如附件檢察官起訴書之記載。二、據上論斷，應依刑事訴訟法第273條之1第1項、第284條之1、第299條第1項前段、第310條之2、第454條第2項，毒品危害防制條例第10條第1項、第2項、第23條第2項，刑法第11條前段、第47條、第51條第5款，判決如主文。本案經檢察官林伯宇到庭執行職務。中華民國94年3月28日刑事第二庭法官何怡穎以上正本證明與原本無異。對於本件判決如有不服，應於收受送達後10日內，向本院提出上訴書狀，上訴於臺灣高等法院，並按他造當事人之人數附具繕本。中華民國94年3月28日書記官李繼業附錄本案論罪科刑法條：毒品危害防制條例第10條施用第一級毒品者，處6月以上5年以下有期徒刑。施用第二級毒品者，處3年以下有期徒刑。",
  "characters": {
    "judges": [
      "何怡穎"
    ],
    "prosecutors": [
      "林伯宇"
    ],
    "lawyers": [

    ],
    "clerks": [
      "李繼業"
    ],
    "plaintiffs": [

    ],
    "defendants": [
      "甲○○  男  46歲."
    ],
    "prosecutor_office": [
      "臺灣基隆地方法院檢察署檢察官"
    ],
    "creditors": [

    ],
    "debtors": [

    ],
    "judicial_associate_officer": [

    ]
  },
  "adjudged_at": "2005-03-28",
  "created_at": "2016-02-07 07:15:43",
  "updated_at": "2016-02-07 07:15:43"
}