{
  "identify": "KSD-93-簡-6015-20041213-1",
  "court": {
    "name": "臺灣高雄地方法院",
    "code": "KSD"
  },
  "division": {
    "name": "刑事",
    "code": "M"
  },
  "year": 93,
  "word": "簡",
  "number": "6015",
  "jcheck": "1",
  "reason": "竊盜",
  "content": "臺灣高雄地方法院刑事簡易判決                    九十三年度簡字第六一五號\n    聲  請  人  臺灣高雄地方法院檢察署檢察官\n    被      告  甲○○\n右列被告因竊盜案件，經檢察官聲請簡易判決處刑（九十三年度偵字第一八一二八號\n），本院判決如左：\n    主  文\n甲○○竊盜，處有期徒刑貳月，如易科罰金，以佰元折算壹日。\n    事實及理由\n一、本件犯罪事實及證據，均引用檢察官聲請簡易判決處刑書之記載（如附件）。\n二、核被告所為，係犯刑法第三百二十條第一項之竊盜罪。爰審酌被告為貪圖小利，\n    竟以竊取他人財物方式，暨得財物，行為實屬不該，且犯罪後否認犯行，態度非\n    佳，但所竊之物價值非鉅，對被害人之損失尚輕，並參以被害人已領回失竊童鞋\n    等一切情狀，量處如主文所示之刑，並諭知易科罰金之折算標準。\n三、依刑事訴訟法第四百四十九條第一項、第三項、第四百五十四條第二項，刑法第\n    三百二十條第一項、第四十一條第一項，罰金罰鍰提高標準條例第一條前段、第\n    二條，逕以簡易判決處如主文所示之刑。\n四、如不服本判決，得於判決書送達之日起十日內，以書狀敘述理由，向本庭提出上\n    訴。\n中      華      民      國    九十三    年     十二     月     十三     日\n                                臺灣高雄地方法院高雄簡易庭\n                                    法  官  劉惠娟\n右正本證明與原本無異。\n                                    書記官  陳素徵\n中      華      民      國    九十三    年     十二     月     十五     日\n",
  "structure": {
    "main": "甲○○竊盜，處有期徒刑貳月，如易科罰金，以佰元折算壹日。",
    "fact": "一、本件犯罪事實及證據，均引用檢察官聲請簡易判決處刑書之記載（如附件）。\n二、核被告所為，係犯刑法第三百二十條第一項之竊盜罪。爰審酌被告為貪圖小利，\n    竟以竊取他人財物方式，暨得財物，行為實屬不該，且犯罪後否認犯行，態度非\n    佳，但所竊之物價值非鉅，對被害人之損失尚輕，並參以被害人已領回失竊童鞋\n    等一切情狀，量處如主文所示之刑，並諭知易科罰金之折算標準。\n三、依刑事訴訟法第四百四十九條第一項、第三項、第四百五十四條第二項，刑法第\n    三百二十條第一項、第四十一條第一項，罰金罰鍰提高標準條例第一條前段、第\n    二條，逕以簡易判決處如主文所示之刑。\n四、如不服本判決，得於判決書送達之日起十日內，以書狀敘述理由，向本庭提出上\n    訴。",
    "reason": "一、本件犯罪事實及證據，均引用檢察官聲請簡易判決處刑書之記載（如附件）。\n二、核被告所為，係犯刑法第三百二十條第一項之竊盜罪。爰審酌被告為貪圖小利，\n    竟以竊取他人財物方式，暨得財物，行為實屬不該，且犯罪後否認犯行，態度非\n    佳，但所竊之物價值非鉅，對被害人之損失尚輕，並參以被害人已領回失竊童鞋\n    等一切情狀，量處如主文所示之刑，並諭知易科罰金之折算標準。\n三、依刑事訴訟法第四百四十九條第一項、第三項、第四百五十四條第二項，刑法第\n    三百二十條第一項、第四十一條第一項，罰金罰鍰提高標準條例第一條前段、第\n    二條，逕以簡易判決處如主文所示之刑。\n四、如不服本判決，得於判決書送達之日起十日內，以書狀敘述理由，向本庭提出上\n    訴。"
  },
  "search": "臺灣高雄地方法院刑事簡易判決九十三年度簡字第六一五號聲請人臺灣高雄地方法院檢察署檢察官被告甲○○右列被告因竊盜案件，經檢察官聲請簡易判決處刑（九十三年度偵字第一八一二八號），本院判決如左：主文甲○○竊盜，處有期徒刑貳月，如易科罰金，以佰元折算壹日。事實及理由一、本件犯罪事實及證據，均引用檢察官聲請簡易判決處刑書之記載（如附件）。二、核被告所為，係犯刑法第三百二十條第一項之竊盜罪。爰審酌被告為貪圖小利，竟以竊取他人財物方式，暨得財物，行為實屬不該，且犯罪後否認犯行，態度非佳，但所竊之物價值非鉅，對被害人之損失尚輕，並參以被害人已領回失竊童鞋等一切情狀，量處如主文所示之刑，並諭知易科罰金之折算標準。三、依刑事訴訟法第四百四十九條第一項、第三項、第四百五十四條第二項，刑法第三百二十條第一項、第四十一條第一項，罰金罰鍰提高標準條例第一條前段、第二條，逕以簡易判決處如主文所示之刑。四、如不服本判決，得於判決書送達之日起十日內，以書狀敘述理由，向本庭提出上訴。中華民國九十三年十二月十三日臺灣高雄地方法院高雄簡易庭法官劉惠娟右正本證明與原本無異。書記官陳素徵中華民國九十三年十二月十五日",
  "characters": {
    "judges": [
      "劉惠娟"
    ],
    "prosecutors": [

    ],
    "lawyers": [

    ],
    "clerks": [
      "陳素徵"
    ],
    "plaintiffs": [

    ],
    "defendants": [
      "甲○○",
      "右列被告因竊盜案件，經檢察官聲請簡易判決處刑（九十三年度偵字第一八一二八號",
      "），本院判決如左："
    ],
    "prosecutor_office": [
      "臺灣高雄地方法院檢察署檢察官"
    ],
    "creditors": [

    ],
    "debtors": [

    ],
    "judicial_associate_officer": [

    ]
  },
  "adjudged_at": "2004-12-13",
  "created_at": "2016-02-06 07:00:38",
  "updated_at": "2016-02-06 07:00:38"
}