{
  "identify": "TYD-93-桃交簡-1616-20041213-1",
  "court": {
    "name": "臺灣桃園地方法院",
    "code": "TYD"
  },
  "division": {
    "name": "刑事",
    "code": "M"
  },
  "year": 93,
  "word": "桃交簡",
  "number": "1616",
  "jcheck": "1",
  "reason": "過失傷害等",
  "content": "臺灣桃園地方法院刑事簡易判決              九十三年度桃交簡字第一六一六號\n    聲  請  人  台灣桃園地方法院檢察署檢察官\n    被      告  乙○    男  五.\n右列被告因公共危險案件，經檢察官聲請以簡易判決處刑（九十三年度偵字第一四七\n二八號），本院判決如左：\n    主      文\n乙○服用酒類，不能安全駕駛動力交通工具而駕駛，處有期徒刑貳月，如易科罰金以\n佰元折算壹日，緩刑貳年。\n    事實及理由\n一、本件除應補充被告乙○前未曾受有期徒刑以上刑之宣告，有台灣高等法院被告全\n    國前案紀錄表一份在卷可稽，素行尚端，僅因一失慮致罹刑章，事後就過失傷害\n    部分復積極與告訴人甲○○尋求並達成和解賠償己行滋生之損害，且已獲取告訴\n    人之宥恕暨撤回告訴（此部分另為不受理之判決），有和解書、刑事撤回告訴聲\n    請狀各一份附卷足憑，堪認有知錯、規過遷善之悛悔實據，復受本次罪刑之科處\n    ，當足收警惕懲儆之效，信無再犯之虞，本院因認對其宣告之刑以暫不執行為適\n    當，爰併諭知緩刑二年，以勵自新等此各情外，餘犯罪事實、證據暨所犯罪名胥\n    同於附件檢察官聲請簡易判決處刑書之記載，茲引用之。\n二、應依刑事訴訟法第四百四十九條第一項、第四百五十四條第二項，刑法第一百八\n    十五條之三、第四十一條第一項前段、第七十四條第二款，罰金罰鍰提高標準條\n    例第二條，逕以簡易判決處如主文所示之刑。\n三、如不服本判決，應於送達後十日內向本院提出上訴狀，上訴於本院合議庭。\n中      華      民      國    九十三    年     十二     月     十三     日\n                              臺灣桃園地方法院交通法庭\n                                  法  官  蔡榮澤\n右正本證明與原本無異。\n                                  書記官  林怡君\n中      華      民      國    九十三    年     十二     月     十三     日\n附本件論罪科刑依據之法條：\n刑法第一百八十五條之三\n服用毒品、麻醉藥品、酒類或其他相類之物，不能安全駕駛動力交通工具而駕駛者，\n處一年以下有期徒刑、拘役或三萬元以下罰金。\n",
  "structure": {
    "main": "乙○服用酒類，不能安全駕駛動力交通工具而駕駛，處有期徒刑貳月，如易科罰金以\n佰元折算壹日，緩刑貳年。",
    "fact": "一、本件除應補充被告乙○前未曾受有期徒刑以上刑之宣告，有台灣高等法院被告全\n    國前案紀錄表一份在卷可稽，素行尚端，僅因一失慮致罹刑章，事後就過失傷害\n    部分復積極與告訴人甲○○尋求並達成和解賠償己行滋生之損害，且已獲取告訴\n    人之宥恕暨撤回告訴（此部分另為不受理之判決），有和解書、刑事撤回告訴聲\n    請狀各一份附卷足憑，堪認有知錯、規過遷善之悛悔實據，復受本次罪刑之科處\n    ，當足收警惕懲儆之效，信無再犯之虞，本院因認對其宣告之刑以暫不執行為適\n    當，爰併諭知緩刑二年，以勵自新等此各情外，餘犯罪事實、證據暨所犯罪名胥\n    同於附件檢察官聲請簡易判決處刑書之記載，茲引用之。\n二、應依刑事訴訟法第四百四十九條第一項、第四百五十四條第二項，刑法第一百八\n    十五條之三、第四十一條第一項前段、第七十四條第二款，罰金罰鍰提高標準條\n    例第二條，逕以簡易判決處如主文所示之刑。\n三、如不服本判決，應於送達後十日內向本院提出上訴狀，上訴於本院合議庭。",
    "reason": "一、本件除應補充被告乙○前未曾受有期徒刑以上刑之宣告，有台灣高等法院被告全\n    國前案紀錄表一份在卷可稽，素行尚端，僅因一失慮致罹刑章，事後就過失傷害\n    部分復積極與告訴人甲○○尋求並達成和解賠償己行滋生之損害，且已獲取告訴\n    人之宥恕暨撤回告訴（此部分另為不受理之判決），有和解書、刑事撤回告訴聲\n    請狀各一份附卷足憑，堪認有知錯、規過遷善之悛悔實據，復受本次罪刑之科處\n    ，當足收警惕懲儆之效，信無再犯之虞，本院因認對其宣告之刑以暫不執行為適\n    當，爰併諭知緩刑二年，以勵自新等此各情外，餘犯罪事實、證據暨所犯罪名胥\n    同於附件檢察官聲請簡易判決處刑書之記載，茲引用之。\n二、應依刑事訴訟法第四百四十九條第一項、第四百五十四條第二項，刑法第一百八\n    十五條之三、第四十一條第一項前段、第七十四條第二款，罰金罰鍰提高標準條\n    例第二條，逕以簡易判決處如主文所示之刑。\n三、如不服本判決，應於送達後十日內向本院提出上訴狀，上訴於本院合議庭。"
  },
  "search": "臺灣桃園地方法院刑事簡易判決九十三年度桃交簡字第一六一六號聲請人台灣桃園地方法院檢察署檢察官被告乙○男五.右列被告因公共危險案件，經檢察官聲請以簡易判決處刑（九十三年度偵字第一四七二八號），本院判決如左：主文乙○服用酒類，不能安全駕駛動力交通工具而駕駛，處有期徒刑貳月，如易科罰金以佰元折算壹日，緩刑貳年。事實及理由一、本件除應補充被告乙○前未曾受有期徒刑以上刑之宣告，有台灣高等法院被告全國前案紀錄表一份在卷可稽，素行尚端，僅因一失慮致罹刑章，事後就過失傷害部分復積極與告訴人甲○○尋求並達成和解賠償己行滋生之損害，且已獲取告訴人之宥恕暨撤回告訴（此部分另為不受理之判決），有和解書、刑事撤回告訴聲請狀各一份附卷足憑，堪認有知錯、規過遷善之悛悔實據，復受本次罪刑之科處，當足收警惕懲儆之效，信無再犯之虞，本院因認對其宣告之刑以暫不執行為適當，爰併諭知緩刑二年，以勵自新等此各情外，餘犯罪事實、證據暨所犯罪名胥同於附件檢察官聲請簡易判決處刑書之記載，茲引用之。二、應依刑事訴訟法第四百四十九條第一項、第四百五十四條第二項，刑法第一百八十五條之三、第四十一條第一項前段、第七十四條第二款，罰金罰鍰提高標準條例第二條，逕以簡易判決處如主文所示之刑。三、如不服本判決，應於送達後十日內向本院提出上訴狀，上訴於本院合議庭。中華民國九十三年十二月十三日臺灣桃園地方法院交通法庭法官蔡榮澤右正本證明與原本無異。書記官林怡君中華民國九十三年十二月十三日附本件論罪科刑依據之法條：刑法第一百八十五條之三服用毒品、麻醉藥品、酒類或其他相類之物，不能安全駕駛動力交通工具而駕駛者，處一年以下有期徒刑、拘役或三萬元以下罰金。",
  "characters": {
    "judges": [
      "蔡榮澤"
    ],
    "prosecutors": [

    ],
    "lawyers": [

    ],
    "clerks": [
      "林怡君"
    ],
    "plaintiffs": [

    ],
    "defendants": [
      "乙○    男  五.",
      "右列被告因公共危險案件，經檢察官聲請以簡易判決處刑（九十三年度偵字第一四七",
      "二八號），本院判決如左："
    ],
    "prosecutor_office": [
      "台灣桃園地方法院檢察署檢察官"
    ],
    "creditors": [

    ],
    "debtors": [

    ],
    "judicial_associate_officer": [

    ]
  },
  "adjudged_at": "2004-12-13",
  "created_at": "2016-02-06 07:02:26",
  "updated_at": "2016-02-06 07:02:26"
}