{
  "identify": "MLD-94-易-280-20050729-2",
  "court": {
    "name": "臺灣苗栗地方法院",
    "code": "MLD"
  },
  "division": {
    "name": "刑事",
    "code": "M"
  },
  "year": 94,
  "word": "易",
  "number": "280",
  "jcheck": "2",
  "reason": "竊盜",
  "content": "臺灣苗栗地方法院刑事判決               94年度易字第280號\n公  訴  人  臺灣苗栗地方法院檢察署檢察官\n被      告  乙○○\n                    （現於臺灣臺中監獄苗栗分監執行中）\n上列被告因竊盜案件，經檢察官提起公訴（94年度偵字第916 號\n）及移送併案審理（94年度偵字第1726號），本院依簡式審判程\n序，判決如下：\n    主  文\n乙○○連續攜帶兇器竊盜，累犯，處有期徒刑壹年肆月。\n    事  實\n一、乙○○曾犯竊盜罪，經法院分別判處有期徒刑6 月、7 月確\n    定，經接續執行，甫於民國92年5 月15日因縮短刑期而執行\n    完畢。詎仍不知悔改，復基於為自己不法所有之概括犯意，\n    連續於：(1)94年2 月間某日乘借住友人羅紹勳位於苗栗市鳳\n    形山莊3 號住處之機會，徒手竊取羅紹勳所有放置於該處之\n    抽油煙機1 台、千斤頂1 個、扳手、鐵鉗及鑽子各1 支、隨\n    身聽1 台等物；(2)同年3 月9 日10時許，在苗栗市○○路4\n    巷8 號前，持其所有而足供兇器使用之起子1 支（未據扣案\n    ），撬開甲○○所有而停放於該處之車牌號碼ＭＤ─9855號\n    自小客車右前車門，竊取甲○○所有而放於車內之便帽1 頂\n    、太陽眼鏡4 付、汽車定檢費收據2 張及停車費收據2 張等\n    物（價值計約新臺幣3500元）；(3)同年3 月9 日14、15時許\n    ，在同市○○路68號前，見丙○○所有之電焊機及電切割器\n    各1 台，放置於車牌號碼ＭＪ─8767號自小貨車上無人看管\n    ，認有機可乘，遂徒手竊取該電焊機及電切割器，得手後，\n    以其向不知情之胡坤財所借得之車牌號碼Ｆ79─839 號重型\n    機車載運離去現場，欲變賣得款以供己花用。嗣於94年3 月\n    9 日15時55分許，因其將置有上開電焊機、電切割器等贓物\n    之上述重型機車停放在同市○○路「金萬年遊藝場」前，為\n    警認其行跡可疑，而盤檢查獲。\n二、案經苗栗縣警察局苗栗分局移送臺灣苗栗地方法院檢察署檢\n    察官偵查起訴及移送併案審理。\n    理  由\n一、訊據被告對於上揭連續竊盜之事實均坦承不諱，核與被害人\n    羅紹勳、甲○○、丙○○分別於警訊時之指訴及證人胡坤財\n    於警訊時之證述大致相符，並有照片多幀、贓物認領保管單\n    3 紙等附卷可證。綜上各節，足認被告上述自白確與事實相\n    符，而堪採信。是本件事證已臻明確，被告犯行洵堪認定。\n二、核被告上述竊取羅紹勳、丙○○財物之行為，係犯刑法第\n    320 條第1 項之竊盜罪；竊取甲○○財物之行為，係犯同法\n    第321 條第1 項第3 款之加重竊盜罪。其先後3 次竊盜之行\n    為，時間緊接，所犯係基本構成要件相同之罪名，顯係出於\n    概括之犯意反覆為之，為連續犯，應依刑法第56條之規定論\n    以加重竊盜1 罪，並加重其刑。又被告受有如事實欄所載罪\n    刑執行情形，有臺灣高等法院被告前案紀錄表在卷可按，其\n    受有期徒刑執行完畢後，5 年以內再犯本件有期徒刑以上之\n    罪，為累犯，應依刑法第47條規定遞加重其刑。爰審酌被告\n    前有竊盜之犯罪紀錄，甫經執行完畢，竟再犯本件竊盜罪，\n    足徵其惡性非淺暨其犯罪之動機、目的、手段，犯罪所生之\n    危害及犯罪後尚知坦承全部犯行之態度等一切情狀，並審酌\n    公訴人之具體求刑，量處如主文所示之刑。至被告持以行竊\n    之起子，因未據扣案，為免將來執行之困難，爰不宣告沒收\n    ，附此敘明。\n三、查被告上述竊取羅紹勳所有之抽油煙機等物之犯行，雖未據\n    檢察官起訴，惟因與起訴部分具有連續犯之裁判上一罪關係\n    ，已如上述，而為起訴效力所及，本院自得併為審理，併此\n    指明。\n據上論斷，應依刑事訴訟法第273 條之1 第1 項、第299 條第1\n項前段，刑法第56條、第321 條第1 項第3 款，第47條，判決如\n主文。\n本案經檢察官郭靜文到庭執行職務。\n中    華    民    國    94    年    7     月    29    日\n                  刑事第二庭    法  官  林燦都\n以上正本證明與原本無異。\n如不服本判決，應於送達後10日內向本院提出上訴狀（須附繕本\n），上訴於臺灣高等法院臺中分院。\n                                書記官  陳建分\n中    華    民    國    94    年    7     月    29    日\n附錄論罪科刑法條\n中華民國刑法第321條\n犯竊盜罪而有左列情形之一者，處 6 月以上、 5 年以下有期徒\n刑：\n一  於夜間侵入住宅或有人居住之建築物、船艦或隱匿其內而犯\n之者。\n二  毀越門扇、牆垣或其他安全設備而犯之者。\n三  攜帶兇器而犯之者。\n四  結夥三人以上而犯之者。\n五  乘火災、水災或其他災害之際而犯之者。\n六  在車站或埠頭而犯之者。\n前項之未遂犯罰之。\n",
  "structure": {
    "main": "乙○○連續攜帶兇器竊盜，累犯，處有期徒刑壹年肆月。",
    "fact": "一、乙○○曾犯竊盜罪，經法院分別判處有期徒刑6 月、7 月確\n    定，經接續執行，甫於民國92年5 月15日因縮短刑期而執行\n    完畢。詎仍不知悔改，復基於為自己不法所有之概括犯意，\n    連續於：(1)94年2 月間某日乘借住友人羅紹勳位於苗栗市鳳\n    形山莊3 號住處之機會，徒手竊取羅紹勳所有放置於該處之\n    抽油煙機1 台、千斤頂1 個、扳手、鐵鉗及鑽子各1 支、隨\n    身聽1 台等物；(2)同年3 月9 日10時許，在苗栗市○○路4\n    巷8 號前，持其所有而足供兇器使用之起子1 支（未據扣案\n    ），撬開甲○○所有而停放於該處之車牌號碼ＭＤ─9855號\n    自小客車右前車門，竊取甲○○所有而放於車內之便帽1 頂\n    、太陽眼鏡4 付、汽車定檢費收據2 張及停車費收據2 張等\n    物（價值計約新臺幣3500元）；(3)同年3 月9 日14、15時許\n    ，在同市○○路68號前，見丙○○所有之電焊機及電切割器\n    各1 台，放置於車牌號碼ＭＪ─8767號自小貨車上無人看管\n    ，認有機可乘，遂徒手竊取該電焊機及電切割器，得手後，\n    以其向不知情之胡坤財所借得之車牌號碼Ｆ79─839 號重型\n    機車載運離去現場，欲變賣得款以供己花用。嗣於94年3 月\n    9 日15時55分許，因其將置有上開電焊機、電切割器等贓物\n    之上述重型機車停放在同市○○路「金萬年遊藝場」前，為\n    警認其行跡可疑，而盤檢查獲。\n二、案經苗栗縣警察局苗栗分局移送臺灣苗栗地方法院檢察署檢\n    察官偵查起訴及移送併案審理。",
    "reason": "一、訊據被告對於上揭連續竊盜之事實均坦承不諱，核與被害人\n    羅紹勳、甲○○、丙○○分別於警訊時之指訴及證人胡坤財\n    於警訊時之證述大致相符，並有照片多幀、贓物認領保管單\n    3 紙等附卷可證。綜上各節，足認被告上述自白確與事實相\n    符，而堪採信。是本件事證已臻明確，被告犯行洵堪認定。\n二、核被告上述竊取羅紹勳、丙○○財物之行為，係犯刑法第\n    320 條第1 項之竊盜罪；竊取甲○○財物之行為，係犯同法\n    第321 條第1 項第3 款之加重竊盜罪。其先後3 次竊盜之行\n    為，時間緊接，所犯係基本構成要件相同之罪名，顯係出於\n    概括之犯意反覆為之，為連續犯，應依刑法第56條之規定論\n    以加重竊盜1 罪，並加重其刑。又被告受有如事實欄所載罪\n    刑執行情形，有臺灣高等法院被告前案紀錄表在卷可按，其\n    受有期徒刑執行完畢後，5 年以內再犯本件有期徒刑以上之\n    罪，為累犯，應依刑法第47條規定遞加重其刑。爰審酌被告\n    前有竊盜之犯罪紀錄，甫經執行完畢，竟再犯本件竊盜罪，\n    足徵其惡性非淺暨其犯罪之動機、目的、手段，犯罪所生之\n    危害及犯罪後尚知坦承全部犯行之態度等一切情狀，並審酌\n    公訴人之具體求刑，量處如主文所示之刑。至被告持以行竊\n    之起子，因未據扣案，為免將來執行之困難，爰不宣告沒收\n    ，附此敘明。\n三、查被告上述竊取羅紹勳所有之抽油煙機等物之犯行，雖未據\n    檢察官起訴，惟因與起訴部分具有連續犯之裁判上一罪關係\n    ，已如上述，而為起訴效力所及，本院自得併為審理，併此\n    指明。\n據上論斷，應依刑事訴訟法第273 條之1 第1 項、第299 條第1\n項前段，刑法第56條、第321 條第1 項第3 款，第47條，判決如\n主文。\n本案經檢察官郭靜文到庭執行職務。\n中    華    民    國    94    年    7     月    29    日\n                  刑事第二庭    法  官  林燦都\n以上正本證明與原本無異。\n如不服本判決，應於送達後10日內向本院提出上訴狀（須附繕本\n），上訴於臺灣高等法院臺中分院。\n                                書記官  陳建分"
  },
  "search": "臺灣苗栗地方法院刑事判決94年度易字第280號公訴人臺灣苗栗地方法院檢察署檢察官被告乙○○（現於臺灣臺中監獄苗栗分監執行中）上列被告因竊盜案件，經檢察官提起公訴（94年度偵字第916號）及移送併案審理（94年度偵字第1726號），本院依簡式審判程序，判決如下：主文乙○○連續攜帶兇器竊盜，累犯，處有期徒刑壹年肆月。事實一、乙○○曾犯竊盜罪，經法院分別判處有期徒刑6月、7月確定，經接續執行，甫於民國92年5月15日因縮短刑期而執行完畢。詎仍不知悔改，復基於為自己不法所有之概括犯意，連續於：(1)94年2月間某日乘借住友人羅紹勳位於苗栗市鳳形山莊3號住處之機會，徒手竊取羅紹勳所有放置於該處之抽油煙機1台、千斤頂1個、扳手、鐵鉗及鑽子各1支、隨身聽1台等物；(2)同年3月9日10時許，在苗栗市○○路4巷8號前，持其所有而足供兇器使用之起子1支（未據扣案），撬開甲○○所有而停放於該處之車牌號碼ＭＤ─9855號自小客車右前車門，竊取甲○○所有而放於車內之便帽1頂、太陽眼鏡4付、汽車定檢費收據2張及停車費收據2張等物（價值計約新臺幣3500元）；(3)同年3月9日14、15時許，在同市○○路68號前，見丙○○所有之電焊機及電切割器各1台，放置於車牌號碼ＭＪ─8767號自小貨車上無人看管，認有機可乘，遂徒手竊取該電焊機及電切割器，得手後，以其向不知情之胡坤財所借得之車牌號碼Ｆ79─839號重型機車載運離去現場，欲變賣得款以供己花用。嗣於94年3月9日15時55分許，因其將置有上開電焊機、電切割器等贓物之上述重型機車停放在同市○○路「金萬年遊藝場」前，為警認其行跡可疑，而盤檢查獲。二、案經苗栗縣警察局苗栗分局移送臺灣苗栗地方法院檢察署檢察官偵查起訴及移送併案審理。理由一、訊據被告對於上揭連續竊盜之事實均坦承不諱，核與被害人羅紹勳、甲○○、丙○○分別於警訊時之指訴及證人胡坤財於警訊時之證述大致相符，並有照片多幀、贓物認領保管單3紙等附卷可證。綜上各節，足認被告上述自白確與事實相符，而堪採信。是本件事證已臻明確，被告犯行洵堪認定。二、核被告上述竊取羅紹勳、丙○○財物之行為，係犯刑法第320條第1項之竊盜罪；竊取甲○○財物之行為，係犯同法第321條第1項第3款之加重竊盜罪。其先後3次竊盜之行為，時間緊接，所犯係基本構成要件相同之罪名，顯係出於概括之犯意反覆為之，為連續犯，應依刑法第56條之規定論以加重竊盜1罪，並加重其刑。又被告受有如事實欄所載罪刑執行情形，有臺灣高等法院被告前案紀錄表在卷可按，其受有期徒刑執行完畢後，5年以內再犯本件有期徒刑以上之罪，為累犯，應依刑法第47條規定遞加重其刑。爰審酌被告前有竊盜之犯罪紀錄，甫經執行完畢，竟再犯本件竊盜罪，足徵其惡性非淺暨其犯罪之動機、目的、手段，犯罪所生之危害及犯罪後尚知坦承全部犯行之態度等一切情狀，並審酌公訴人之具體求刑，量處如主文所示之刑。至被告持以行竊之起子，因未據扣案，為免將來執行之困難，爰不宣告沒收，附此敘明。三、查被告上述竊取羅紹勳所有之抽油煙機等物之犯行，雖未據檢察官起訴，惟因與起訴部分具有連續犯之裁判上一罪關係，已如上述，而為起訴效力所及，本院自得併為審理，併此指明。據上論斷，應依刑事訴訟法第273條之1第1項、第299條第1項前段，刑法第56條、第321條第1項第3款，第47條，判決如主文。本案經檢察官郭靜文到庭執行職務。中華民國94年7月29日刑事第二庭法官林燦都以上正本證明與原本無異。如不服本判決，應於送達後10日內向本院提出上訴狀（須附繕本），上訴於臺灣高等法院臺中分院。書記官陳建分中華民國94年7月29日附錄論罪科刑法條中華民國刑法第321條犯竊盜罪而有左列情形之一者，處6月以上、5年以下有期徒刑：一於夜間侵入住宅或有人居住之建築物、船艦或隱匿其內而犯之者。二毀越門扇、牆垣或其他安全設備而犯之者。三攜帶兇器而犯之者。四結夥三人以上而犯之者。五乘火災、水災或其他災害之際而犯之者。六在車站或埠頭而犯之者。前項之未遂犯罰之。",
  "characters": {
    "judges": [
      "林燦都"
    ],
    "prosecutors": [
      "郭靜文"
    ],
    "lawyers": [

    ],
    "clerks": [
      "陳建分"
    ],
    "plaintiffs": [

    ],
    "defendants": [
      "乙○○"
    ],
    "prosecutor_office": [
      "臺灣苗栗地方法院檢察署檢察官"
    ],
    "creditors": [

    ],
    "debtors": [

    ],
    "judicial_associate_officer": [

    ]
  },
  "adjudged_at": "2005-07-29",
  "created_at": "2016-02-07 08:58:46",
  "updated_at": "2016-02-07 08:58:46"
}