{
  "identify": "TYD-94-易-153-20050309-1",
  "court": {
    "name": "臺灣桃園地方法院",
    "code": "TYD"
  },
  "division": {
    "name": "刑事",
    "code": "M"
  },
  "year": 94,
  "word": "易",
  "number": "153",
  "jcheck": "1",
  "reason": "毒品危害防制條例",
  "content": "臺灣桃園地方法院刑事判決               94年度易字第153號\n公  訴  人  臺灣桃園地方法院檢察署檢察官\n被      告  甲○○  男  42歲.\n選任辯護人  喬國偉律師\n上列被告因違反毒品危害防制條例案件，經檢察官提起公訴（93\n年度毒偵字第13233 號），被告於本院準備程序進行中，就被訴\n事實為有罪之陳述，經告知簡式審判程序之旨，聽取當事人及辯\n護人之意見後，本院裁定由受命法官獨任依簡式審判程序審理，\n檢察官復聲請改依協商程序而為判決，本院判決如下：\n    主  文\n甲○○持有第一級毒品達淨重伍公克以上，處有期徒刑陸月，如\n易科罰金以佰元折算壹日。扣案之第一級毒品海洛因（驗餘淨\n重伍點貳肆公克）、第二級毒品甲基安非他命（驗餘實秤毛重陸\n點陸玖陸公克）沒收銷燬之；用以放置前述海洛因之包裝袋壹個\n、放置前述甲基安非他命之包裝袋玖個沒收。\n    事實及理由\n一、犯罪事實：甲○○明知海洛因、甲基安非他命分屬毒品危害\n    防制條例列管之第一級、第二級毒品，不得非法持有，竟於\n    民國92年12月中旬，在桃園縣龍潭鄉○○○○道附近，向友\n    人利錦明（已歿）購得海洛因1 包（淨重5.24公克）、甲基\n    安非他命9 包（驗餘實秤毛重6.696 公克），並將之藏放在\n    桃園縣龍潭鄉上林村13鄰溝西2 號祖厝內而持有之。嗣93年\n    3 月4 日14時50分許在上址為警查獲，並扣得上開毒品。\n二、證據：\n(一)被告於本院審理時之自白。\n(二)證人黃琦景、黃阿木、林忠義於檢察官訊問時之證詞。\n(三)扣案之第一級毒品海洛因1 包（驗餘淨重5.24公克）、第二\n    級毒品甲基安非他命9 包（驗餘實秤毛重6.696 公克）。\n(四)法務部調查局調科壹字第080008157 號鑑定通知書、行政院\n    衛生署管制藥品管理局管檢字第0930009431號檢驗成績書。\n三、被告就起訴書所載之犯罪事實已認罪，經辯護人協助其進行\n    協商，當事人雙方於審判外達成協商之合意，合意內容為：\n    被告願受如主文所示之科刑。經查，被告之自白，有上開證\n    據足認屬實，並與本院認定之事實相符，參酌被告犯罪之動\n    機、目的、手段、持有毒品之數量及犯後態度等情狀，上開\n    協商內容尚無不當之處，本案復查無刑事訴訟法第455 條之\n    4 第1 項其餘各款所列情形，檢察官聲請改依協商程序而為\n    判決，本院爰不經言詞辯論，於協商合意範圍內為協商判決\n    。\n四、應適用之法條：刑事訴訟法第273 條之1 第1 項、第455 條\n    之2 第1 項、第455 條之4 第2 項、第455 條之8 ，毒品危\n    害防制條例第11第1 項、第2 項、第4 項、第18條第1 項前\n    段，刑法第11條前段、第55條、第41條第1 項前段、第38條\n    第1 項第2 款，罰金罰鍰提高標準條例第2 條。\n五、本判決除有刑事訴訟法第455 條之4 第1 項第1 款、第2 款\n    、第4 款、第6 款、第7 款所定情形之一，或違反同條第2\n    項規定者外，不得上訴。\n六、如有前述例外得上訴之情形，又不服本件判決，得自收受判\n    決送達之日起10日內，向本院提出上訴書狀，上訴於第二審\n    法院。\n中    華    民    國    94    年    3     月    9     日\n                  刑事第十庭    法  官  許炎灶\n以上正本證明與原本無異。\n                              書記官  文巧雲\n中    華    民    國    94    年    3     月    9     日\n附錄本案論罪科刑法條：毒品危害防制條例第11條。\n",
  "structure": {
    "main": "甲○○持有第一級毒品達淨重伍公克以上，處有期徒刑陸月，如\n易科罰金以佰元折算壹日。扣案之第一級毒品海洛因（驗餘淨\n重伍點貳肆公克）、第二級毒品甲基安非他命（驗餘實秤毛重陸\n點陸玖陸公克）沒收銷燬之；用以放置前述海洛因之包裝袋壹個\n、放置前述甲基安非他命之包裝袋玖個沒收。",
    "fact": "一、犯罪事實：甲○○明知海洛因、甲基安非他命分屬毒品危害\n    防制條例列管之第一級、第二級毒品，不得非法持有，竟於\n    民國92年12月中旬，在桃園縣龍潭鄉○○○○道附近，向友\n    人利錦明（已歿）購得海洛因1 包（淨重5.24公克）、甲基\n    安非他命9 包（驗餘實秤毛重6.696 公克），並將之藏放在\n    桃園縣龍潭鄉上林村13鄰溝西2 號祖厝內而持有之。嗣93年\n    3 月4 日14時50分許在上址為警查獲，並扣得上開毒品。\n二、證據：\n(一)被告於本院審理時之自白。\n(二)證人黃琦景、黃阿木、林忠義於檢察官訊問時之證詞。\n(三)扣案之第一級毒品海洛因1 包（驗餘淨重5.24公克）、第二\n    級毒品甲基安非他命9 包（驗餘實秤毛重6.696 公克）。\n(四)法務部調查局調科壹字第080008157 號鑑定通知書、行政院\n    衛生署管制藥品管理局管檢字第0930009431號檢驗成績書。\n三、被告就起訴書所載之犯罪事實已認罪，經辯護人協助其進行\n    協商，當事人雙方於審判外達成協商之合意，合意內容為：\n    被告願受如主文所示之科刑。經查，被告之自白，有上開證\n    據足認屬實，並與本院認定之事實相符，參酌被告犯罪之動\n    機、目的、手段、持有毒品之數量及犯後態度等情狀，上開\n    協商內容尚無不當之處，本案復查無刑事訴訟法第455 條之\n    4 第1 項其餘各款所列情形，檢察官聲請改依協商程序而為\n    判決，本院爰不經言詞辯論，於協商合意範圍內為協商判決\n    。\n四、應適用之法條：刑事訴訟法第273 條之1 第1 項、第455 條\n    之2 第1 項、第455 條之4 第2 項、第455 條之8 ，毒品危\n    害防制條例第11第1 項、第2 項、第4 項、第18條第1 項前\n    段，刑法第11條前段、第55條、第41條第1 項前段、第38條\n    第1 項第2 款，罰金罰鍰提高標準條例第2 條。\n五、本判決除有刑事訴訟法第455 條之4 第1 項第1 款、第2 款\n    、第4 款、第6 款、第7 款所定情形之一，或違反同條第2\n    項規定者外，不得上訴。\n六、如有前述例外得上訴之情形，又不服本件判決，得自收受判\n    決送達之日起10日內，向本院提出上訴書狀，上訴於第二審\n    法院。",
    "reason": "一、犯罪事實：甲○○明知海洛因、甲基安非他命分屬毒品危害\n    防制條例列管之第一級、第二級毒品，不得非法持有，竟於\n    民國92年12月中旬，在桃園縣龍潭鄉○○○○道附近，向友\n    人利錦明（已歿）購得海洛因1 包（淨重5.24公克）、甲基\n    安非他命9 包（驗餘實秤毛重6.696 公克），並將之藏放在\n    桃園縣龍潭鄉上林村13鄰溝西2 號祖厝內而持有之。嗣93年\n    3 月4 日14時50分許在上址為警查獲，並扣得上開毒品。\n二、證據：\n(一)被告於本院審理時之自白。\n(二)證人黃琦景、黃阿木、林忠義於檢察官訊問時之證詞。\n(三)扣案之第一級毒品海洛因1 包（驗餘淨重5.24公克）、第二\n    級毒品甲基安非他命9 包（驗餘實秤毛重6.696 公克）。\n(四)法務部調查局調科壹字第080008157 號鑑定通知書、行政院\n    衛生署管制藥品管理局管檢字第0930009431號檢驗成績書。\n三、被告就起訴書所載之犯罪事實已認罪，經辯護人協助其進行\n    協商，當事人雙方於審判外達成協商之合意，合意內容為：\n    被告願受如主文所示之科刑。經查，被告之自白，有上開證\n    據足認屬實，並與本院認定之事實相符，參酌被告犯罪之動\n    機、目的、手段、持有毒品之數量及犯後態度等情狀，上開\n    協商內容尚無不當之處，本案復查無刑事訴訟法第455 條之\n    4 第1 項其餘各款所列情形，檢察官聲請改依協商程序而為\n    判決，本院爰不經言詞辯論，於協商合意範圍內為協商判決\n    。\n四、應適用之法條：刑事訴訟法第273 條之1 第1 項、第455 條\n    之2 第1 項、第455 條之4 第2 項、第455 條之8 ，毒品危\n    害防制條例第11第1 項、第2 項、第4 項、第18條第1 項前\n    段，刑法第11條前段、第55條、第41條第1 項前段、第38條\n    第1 項第2 款，罰金罰鍰提高標準條例第2 條。\n五、本判決除有刑事訴訟法第455 條之4 第1 項第1 款、第2 款\n    、第4 款、第6 款、第7 款所定情形之一，或違反同條第2\n    項規定者外，不得上訴。\n六、如有前述例外得上訴之情形，又不服本件判決，得自收受判\n    決送達之日起10日內，向本院提出上訴書狀，上訴於第二審\n    法院。"
  },
  "search": "臺灣桃園地方法院刑事判決94年度易字第153號公訴人臺灣桃園地方法院檢察署檢察官被告甲○○男42歲.選任辯護人喬國偉律師上列被告因違反毒品危害防制條例案件，經檢察官提起公訴（93年度毒偵字第13233號），被告於本院準備程序進行中，就被訴事實為有罪之陳述，經告知簡式審判程序之旨，聽取當事人及辯護人之意見後，本院裁定由受命法官獨任依簡式審判程序審理，檢察官復聲請改依協商程序而為判決，本院判決如下：主文甲○○持有第一級毒品達淨重伍公克以上，處有期徒刑陸月，如易科罰金以佰元折算壹日。扣案之第一級毒品海洛因（驗餘淨重伍點貳肆公克）、第二級毒品甲基安非他命（驗餘實秤毛重陸點陸玖陸公克）沒收銷燬之；用以放置前述海洛因之包裝袋壹個、放置前述甲基安非他命之包裝袋玖個沒收。事實及理由一、犯罪事實：甲○○明知海洛因、甲基安非他命分屬毒品危害防制條例列管之第一級、第二級毒品，不得非法持有，竟於民國92年12月中旬，在桃園縣龍潭鄉○○○○道附近，向友人利錦明（已歿）購得海洛因1包（淨重5.24公克）、甲基安非他命9包（驗餘實秤毛重6.696公克），並將之藏放在桃園縣龍潭鄉上林村13鄰溝西2號祖厝內而持有之。嗣93年3月4日14時50分許在上址為警查獲，並扣得上開毒品。二、證據：(一)被告於本院審理時之自白。(二)證人黃琦景、黃阿木、林忠義於檢察官訊問時之證詞。(三)扣案之第一級毒品海洛因1包（驗餘淨重5.24公克）、第二級毒品甲基安非他命9包（驗餘實秤毛重6.696公克）。(四)法務部調查局調科壹字第080008157號鑑定通知書、行政院衛生署管制藥品管理局管檢字第0930009431號檢驗成績書。三、被告就起訴書所載之犯罪事實已認罪，經辯護人協助其進行協商，當事人雙方於審判外達成協商之合意，合意內容為：被告願受如主文所示之科刑。經查，被告之自白，有上開證據足認屬實，並與本院認定之事實相符，參酌被告犯罪之動機、目的、手段、持有毒品之數量及犯後態度等情狀，上開協商內容尚無不當之處，本案復查無刑事訴訟法第455條之4第1項其餘各款所列情形，檢察官聲請改依協商程序而為判決，本院爰不經言詞辯論，於協商合意範圍內為協商判決。四、應適用之法條：刑事訴訟法第273條之1第1項、第455條之2第1項、第455條之4第2項、第455條之8，毒品危害防制條例第11第1項、第2項、第4項、第18條第1項前段，刑法第11條前段、第55條、第41條第1項前段、第38條第1項第2款，罰金罰鍰提高標準條例第2條。五、本判決除有刑事訴訟法第455條之4第1項第1款、第2款、第4款、第6款、第7款所定情形之一，或違反同條第2項規定者外，不得上訴。六、如有前述例外得上訴之情形，又不服本件判決，得自收受判決送達之日起10日內，向本院提出上訴書狀，上訴於第二審法院。中華民國94年3月9日刑事第十庭法官許炎灶以上正本證明與原本無異。書記官文巧雲中華民國94年3月9日附錄本案論罪科刑法條：毒品危害防制條例第11條。",
  "characters": {
    "judges": [
      "許炎灶"
    ],
    "prosecutors": [

    ],
    "lawyers": [
      "喬國偉"
    ],
    "clerks": [
      "文巧雲"
    ],
    "plaintiffs": [

    ],
    "defendants": [
      "甲○○  男  42歲."
    ],
    "prosecutor_office": [
      "臺灣桃園地方法院檢察署檢察官"
    ],
    "creditors": [

    ],
    "debtors": [

    ],
    "judicial_associate_officer": [

    ]
  },
  "adjudged_at": "2005-03-09",
  "created_at": "2016-02-07 07:01:51",
  "updated_at": "2016-02-07 07:01:51"
}