{
  "identify": "CHD-94-聲-2268-20051207-1",
  "court": {
    "name": "臺灣彰化地方法院",
    "code": "CHD"
  },
  "division": {
    "name": "刑事",
    "code": "M"
  },
  "year": 94,
  "word": "聲",
  "number": "2268",
  "jcheck": "1",
  "reason": "聲請裁定沒入保證金",
  "content": "臺灣彰化地方法院刑事裁定              94年度聲字第2268號\n聲  請  人  臺灣彰化地方法院檢察署檢察官\n被      告  甲○○\n具  保  人  陳祈合\n上列聲請人聲請沒入保證金（94年度執聲沒字第299號），本院\n裁定如下：\n    主  文\n聲請駁回。\n    理  由\n一、聲請意旨略以：具保人陳祈合因被告違反毒品危害防制條例\n    案件，經依臺灣南投地方法院檢察署檢察官指定之保證金額\n    新臺幣（下同）五千元，現金保證後，將被告釋放。茲因被\n    告逃匿，依刑事訴訟法第一百十八條第一項之規定，聲請沒\n    入具保人繳納之保證金等語。\n二、經查：被告業於民國九十四年十一月二十六日入監服刑，有\n    臺灣高等法院在監在押全國紀錄表一份存卷可稽，被告逃匿\n    之情形已不復存在，從而聲請人聲請沒入保證金，為無理由\n    ，應予駁回。\n三、依刑事訴訟法第一百二十一條第一項，裁定如主文。\n中    華    民    國    94    年    12    月    7     日\n                  刑事第三庭    法  官  姚銘鴻\n以上正本證明與原本無異。\n如不服本裁定，應於裁定送達後5日內向本院提出抗告狀 (須附\n繕本 )。\n中    華    民    國    94    年    12    月    7     日\n                                書記官  謝志鑫\n",
  "structure": {
    "main": "聲請駁回。",
    "reason": "一、聲請意旨略以：具保人陳祈合因被告違反毒品危害防制條例\n    案件，經依臺灣南投地方法院檢察署檢察官指定之保證金額\n    新臺幣（下同）五千元，現金保證後，將被告釋放。茲因被\n    告逃匿，依刑事訴訟法第一百十八條第一項之規定，聲請沒\n    入具保人繳納之保證金等語。\n二、經查：被告業於民國九十四年十一月二十六日入監服刑，有\n    臺灣高等法院在監在押全國紀錄表一份存卷可稽，被告逃匿\n    之情形已不復存在，從而聲請人聲請沒入保證金，為無理由\n    ，應予駁回。\n三、依刑事訴訟法第一百二十一條第一項，裁定如主文。"
  },
  "search": "臺灣彰化地方法院刑事裁定94年度聲字第2268號聲請人臺灣彰化地方法院檢察署檢察官被告甲○○具保人陳祈合上列聲請人聲請沒入保證金（94年度執聲沒字第299號），本院裁定如下：主文聲請駁回。理由一、聲請意旨略以：具保人陳祈合因被告違反毒品危害防制條例案件，經依臺灣南投地方法院檢察署檢察官指定之保證金額新臺幣（下同）五千元，現金保證後，將被告釋放。茲因被告逃匿，依刑事訴訟法第一百十八條第一項之規定，聲請沒入具保人繳納之保證金等語。二、經查：被告業於民國九十四年十一月二十六日入監服刑，有臺灣高等法院在監在押全國紀錄表一份存卷可稽，被告逃匿之情形已不復存在，從而聲請人聲請沒入保證金，為無理由，應予駁回。三、依刑事訴訟法第一百二十一條第一項，裁定如主文。中華民國94年12月7日刑事第三庭法官姚銘鴻以上正本證明與原本無異。如不服本裁定，應於裁定送達後5日內向本院提出抗告狀(須附繕本)。中華民國94年12月7日書記官謝志鑫",
  "characters": {
    "judges": [
      "姚銘鴻"
    ],
    "prosecutors": [

    ],
    "lawyers": [

    ],
    "clerks": [
      "謝志鑫"
    ],
    "plaintiffs": [

    ],
    "defendants": [
      "甲○○",
      "具  保  人  陳祈合"
    ],
    "prosecutor_office": [
      "臺灣彰化地方法院檢察署檢察官"
    ],
    "creditors": [

    ],
    "debtors": [

    ],
    "judicial_associate_officer": [

    ]
  },
  "adjudged_at": "2005-12-07",
  "created_at": "2016-02-07 03:49:33",
  "updated_at": "2016-02-07 03:49:33"
}