{
  "identify": "KSD-94-聲-4268-20051207-1",
  "court": {
    "name": "臺灣高雄地方法院",
    "code": "KSD"
  },
  "division": {
    "name": "刑事",
    "code": "M"
  },
  "year": 94,
  "word": "聲",
  "number": "4268",
  "jcheck": "1",
  "reason": "聲請單獨宣告沒收違禁物",
  "content": "臺灣高雄地方法院刑事裁定              94年度聲字第4268號\n聲  請  人  臺灣高雄地方法院檢察署檢察官\n被      告  甲○○\n上列被告因毒品案件，經檢察官聲請單獨宣告沒收違禁物（94年\n度聲沒字第1608 號）， 本院裁定如下：\n    主  文\n扣案第一級毒品海洛因貳包（淨重零點參參公克，包裝重零點伍\n參公克），沒收銷燬之。\n    理  由\n一、按違禁物得單獨宣告沒收；又查獲之毒品及專供製造或施用\n    毒品之器具，不問屬於犯人與否，均沒收銷燬之；刑法第40\n    條但書、毒品危害防制條例第18條第1 項前段分別定有明文\n    。\n二、本件聲請意旨略以：被告前因施用毒品案件，經臺灣高雄地\n    方法院檢察署檢察官以94年度戒毒偵字第525 號為不起訴處\n    分確定。本件扣案之海洛因2 包為第一級毒品（淨重0.33公\n    克，包裝重0.53公克），爰依法聲請宣告沒收銷燬之。\n三、經查：上情與卷附之臺灣高雄地方法院檢察署檢察官94年度\n    戒毒偵字第525 號不起訴處分書、法務部調查局93年5 月12\n    日第000000000 號鑑定通知書各1 紙互核相符，本院認聲請\n    為正當，又空包裝袋因與殘留袋上毒品渣質無法析離，應將\n    之同視為第一級毒品，從而不問屬於犯人與否，依上開規定\n    宣告，應予沒收銷燬；至鑑驗所耗損之毒品，既已滅失，自\n    無庸宣告沒收銷燬，附此敘明，爰依刑事訴訟法第220 條，\n    毒品危害防制條例第18條第1 項前段、刑法第40條但書，裁\n    定如主文。\n中    華    民    國    94    年    12    月    7     日\n                  刑事第十四庭  法  官  林瑋桓\n以上正本證明與原本無異。\n如不服本裁定，應於送達後5日內，向本院提出抗告狀。\n中    華    民    國    94    年    12    月    7     日\n                                書記官  謝群育\n",
  "structure": {
    "main": "扣案第一級毒品海洛因貳包（淨重零點參參公克，包裝重零點伍\n參公克），沒收銷燬之。",
    "reason": "一、按違禁物得單獨宣告沒收；又查獲之毒品及專供製造或施用\n    毒品之器具，不問屬於犯人與否，均沒收銷燬之；刑法第40\n    條但書、毒品危害防制條例第18條第1 項前段分別定有明文\n    。\n二、本件聲請意旨略以：被告前因施用毒品案件，經臺灣高雄地\n    方法院檢察署檢察官以94年度戒毒偵字第525 號為不起訴處\n    分確定。本件扣案之海洛因2 包為第一級毒品（淨重0.33公\n    克，包裝重0.53公克），爰依法聲請宣告沒收銷燬之。\n三、經查：上情與卷附之臺灣高雄地方法院檢察署檢察官94年度\n    戒毒偵字第525 號不起訴處分書、法務部調查局93年5 月12\n    日第000000000 號鑑定通知書各1 紙互核相符，本院認聲請\n    為正當，又空包裝袋因與殘留袋上毒品渣質無法析離，應將\n    之同視為第一級毒品，從而不問屬於犯人與否，依上開規定\n    宣告，應予沒收銷燬；至鑑驗所耗損之毒品，既已滅失，自\n    無庸宣告沒收銷燬，附此敘明，爰依刑事訴訟法第220 條，\n    毒品危害防制條例第18條第1 項前段、刑法第40條但書，裁\n    定如主文。"
  },
  "search": "臺灣高雄地方法院刑事裁定94年度聲字第4268號聲請人臺灣高雄地方法院檢察署檢察官被告甲○○上列被告因毒品案件，經檢察官聲請單獨宣告沒收違禁物（94年度聲沒字第1608號），本院裁定如下：主文扣案第一級毒品海洛因貳包（淨重零點參參公克，包裝重零點伍參公克），沒收銷燬之。理由一、按違禁物得單獨宣告沒收；又查獲之毒品及專供製造或施用毒品之器具，不問屬於犯人與否，均沒收銷燬之；刑法第40條但書、毒品危害防制條例第18條第1項前段分別定有明文。二、本件聲請意旨略以：被告前因施用毒品案件，經臺灣高雄地方法院檢察署檢察官以94年度戒毒偵字第525號為不起訴處分確定。本件扣案之海洛因2包為第一級毒品（淨重0.33公克，包裝重0.53公克），爰依法聲請宣告沒收銷燬之。三、經查：上情與卷附之臺灣高雄地方法院檢察署檢察官94年度戒毒偵字第525號不起訴處分書、法務部調查局93年5月12日第000000000號鑑定通知書各1紙互核相符，本院認聲請為正當，又空包裝袋因與殘留袋上毒品渣質無法析離，應將之同視為第一級毒品，從而不問屬於犯人與否，依上開規定宣告，應予沒收銷燬；至鑑驗所耗損之毒品，既已滅失，自無庸宣告沒收銷燬，附此敘明，爰依刑事訴訟法第220條，毒品危害防制條例第18條第1項前段、刑法第40條但書，裁定如主文。中華民國94年12月7日刑事第十四庭法官林瑋桓以上正本證明與原本無異。如不服本裁定，應於送達後5日內，向本院提出抗告狀。中華民國94年12月7日書記官謝群育",
  "characters": {
    "judges": [
      "林瑋桓"
    ],
    "prosecutors": [

    ],
    "lawyers": [

    ],
    "clerks": [
      "謝群育"
    ],
    "plaintiffs": [

    ],
    "defendants": [
      "甲○○"
    ],
    "prosecutor_office": [
      "臺灣高雄地方法院檢察署檢察官"
    ],
    "creditors": [

    ],
    "debtors": [

    ],
    "judicial_associate_officer": [

    ]
  },
  "adjudged_at": "2005-12-07",
  "created_at": "2016-02-07 03:52:39",
  "updated_at": "2016-02-07 03:52:39"
}