{
  "identify": "TYD-94-桃交簡-2114-20051207-1",
  "court": {
    "name": "臺灣桃園地方法院",
    "code": "TYD"
  },
  "division": {
    "name": "刑事",
    "code": "M"
  },
  "year": 94,
  "word": "桃交簡",
  "number": "2114",
  "jcheck": "1",
  "reason": "公共危險",
  "content": "臺灣桃園地方法院刑事簡易判決      94年度桃交簡字第2114號\n聲  請  人  臺灣桃園地方法院檢察署檢察官\n被      告  甲○○\n上列被告因公共危險案件，經檢察官聲請以簡易判決處刑（94年\n度偵字第13826號），本院判決如下：\n    主  文\n甲○○服用酒類，不能安全駕駛動力交通工具而駕駛，處罰金玖\n仟元，如易服勞役，以參佰元折算壹日。\n    事實及理由\n一、犯罪事實：甲○○明知其服用酒類後已不能安全駕駛動力交\n    通工具，竟於民國94年7 月12日下午3 時許，在桃園縣蘆竹\n    鄉○○路○ 段某餐廳內飲酒後，仍駕駛車號0796-KQ 號自用\n    小客車沿南山路往南崁方向行駛，嗣於同日下午3 時15分許\n    ，行經南山路2 段394 巷口欲迴轉時，果因酒後不能安全駕\n    駛，不慎撞及蕭婉倩所騎駛之車號HRH-925 號機車，致蕭婉\n    倩人車倒地而受有左髖骨挫傷、右前臂擦傷之傷害（傷害部\n    分未據告訴），警方據報前往處理後始查知上情。\n二、上開犯罪事實，業據被告甲○○坦承不諱，雖其酒精濃度測\n    試結果僅為每公升0.31毫克，然參酌證人即被害人蕭婉倩於\n    偵查中具結證稱：事發當時被告怪怪的，一直要強拉我起來\n    ，感覺有喝酒等語，及證人即當日查獲被告之警員沈宏昌於\n    偵查中具結證稱：當日被告反應有點慢，注意力無法集中、\n    語無倫次、多話，會說些與案件無關的話，身體站不住，會\n    左右搖晃等語，足徵被告確呈酒醉狀態，已達無法安全駕駛\n    動力交通工具之程度，此外，並有呼氣酒精濃度測試紀錄表\n    、刑法第185 條之3 案件測試觀察紀錄表、汽車駕駛人酒後\n    生理協調平衡檢測紀錄表、道路交通事故現場圖、調查報告\n    表(一)、(二)各1 紙、現場照片8 張在卷可稽，是被告之自白與\n    事實相符，本件事證已經明確，被告之犯行堪予認定，應依\n    法論科。\n三、核被告所為，係犯刑法第185 條之3 服用酒類不能安全駕駛\n    動力交通工具而駕駛罪。爰審酌被告呼氣酒精濃度僅為每公\n    升0.31毫克，然其確已無法安全駕駛動力交通工具，且因此\n    與蕭婉倩所駕駛之上開機車發生碰撞，致蕭婉倩受傷，及其\n    犯罪後已坦承犯行等一切情狀，量處如主文所示之刑，並諭\n    知易服勞役之折算標準。\n四、依刑事訴訟法第449 條第1 項前段，刑法第185 條之3 、第\n    42條第2 項，罰金罰鍰提高標準條例第2 條，逕以簡易判決\n    處刑如主文。\n五、如不服本判決，應於送達後10日內向本院提出上訴狀，上訴\n    於本院合議庭。\n中    華    民    國    94    年    12    月    7     日\n                  交通法庭    法  官  魏于傑\n上正本證明與原本無異。\n                              書記官  林怡君\n中    華    民    國    94    年    12    月    12    日\n本案論罪科刑主要法條：\n中華民國刑法第185條之3\n服用毒品、麻醉藥品、酒類或其他相類之物，不能安全駕駛動力\n交通工具而駕駛者，處一年以下有期徒刑、拘役或三萬元以下罰\n金。\n",
  "structure": {
    "main": "甲○○服用酒類，不能安全駕駛動力交通工具而駕駛，處罰金玖\n仟元，如易服勞役，以參佰元折算壹日。",
    "fact": "一、犯罪事實：甲○○明知其服用酒類後已不能安全駕駛動力交\n    通工具，竟於民國94年7 月12日下午3 時許，在桃園縣蘆竹\n    鄉○○路○ 段某餐廳內飲酒後，仍駕駛車號0796-KQ 號自用\n    小客車沿南山路往南崁方向行駛，嗣於同日下午3 時15分許\n    ，行經南山路2 段394 巷口欲迴轉時，果因酒後不能安全駕\n    駛，不慎撞及蕭婉倩所騎駛之車號HRH-925 號機車，致蕭婉\n    倩人車倒地而受有左髖骨挫傷、右前臂擦傷之傷害（傷害部\n    分未據告訴），警方據報前往處理後始查知上情。\n二、上開犯罪事實，業據被告甲○○坦承不諱，雖其酒精濃度測\n    試結果僅為每公升0.31毫克，然參酌證人即被害人蕭婉倩於\n    偵查中具結證稱：事發當時被告怪怪的，一直要強拉我起來\n    ，感覺有喝酒等語，及證人即當日查獲被告之警員沈宏昌於\n    偵查中具結證稱：當日被告反應有點慢，注意力無法集中、\n    語無倫次、多話，會說些與案件無關的話，身體站不住，會\n    左右搖晃等語，足徵被告確呈酒醉狀態，已達無法安全駕駛\n    動力交通工具之程度，此外，並有呼氣酒精濃度測試紀錄表\n    、刑法第185 條之3 案件測試觀察紀錄表、汽車駕駛人酒後\n    生理協調平衡檢測紀錄表、道路交通事故現場圖、調查報告\n    表(一)、(二)各1 紙、現場照片8 張在卷可稽，是被告之自白與\n    事實相符，本件事證已經明確，被告之犯行堪予認定，應依\n    法論科。\n三、核被告所為，係犯刑法第185 條之3 服用酒類不能安全駕駛\n    動力交通工具而駕駛罪。爰審酌被告呼氣酒精濃度僅為每公\n    升0.31毫克，然其確已無法安全駕駛動力交通工具，且因此\n    與蕭婉倩所駕駛之上開機車發生碰撞，致蕭婉倩受傷，及其\n    犯罪後已坦承犯行等一切情狀，量處如主文所示之刑，並諭\n    知易服勞役之折算標準。\n四、依刑事訴訟法第449 條第1 項前段，刑法第185 條之3 、第\n    42條第2 項，罰金罰鍰提高標準條例第2 條，逕以簡易判決\n    處刑如主文。\n五、如不服本判決，應於送達後10日內向本院提出上訴狀，上訴\n    於本院合議庭。",
    "reason": "一、犯罪事實：甲○○明知其服用酒類後已不能安全駕駛動力交\n    通工具，竟於民國94年7 月12日下午3 時許，在桃園縣蘆竹\n    鄉○○路○ 段某餐廳內飲酒後，仍駕駛車號0796-KQ 號自用\n    小客車沿南山路往南崁方向行駛，嗣於同日下午3 時15分許\n    ，行經南山路2 段394 巷口欲迴轉時，果因酒後不能安全駕\n    駛，不慎撞及蕭婉倩所騎駛之車號HRH-925 號機車，致蕭婉\n    倩人車倒地而受有左髖骨挫傷、右前臂擦傷之傷害（傷害部\n    分未據告訴），警方據報前往處理後始查知上情。\n二、上開犯罪事實，業據被告甲○○坦承不諱，雖其酒精濃度測\n    試結果僅為每公升0.31毫克，然參酌證人即被害人蕭婉倩於\n    偵查中具結證稱：事發當時被告怪怪的，一直要強拉我起來\n    ，感覺有喝酒等語，及證人即當日查獲被告之警員沈宏昌於\n    偵查中具結證稱：當日被告反應有點慢，注意力無法集中、\n    語無倫次、多話，會說些與案件無關的話，身體站不住，會\n    左右搖晃等語，足徵被告確呈酒醉狀態，已達無法安全駕駛\n    動力交通工具之程度，此外，並有呼氣酒精濃度測試紀錄表\n    、刑法第185 條之3 案件測試觀察紀錄表、汽車駕駛人酒後\n    生理協調平衡檢測紀錄表、道路交通事故現場圖、調查報告\n    表(一)、(二)各1 紙、現場照片8 張在卷可稽，是被告之自白與\n    事實相符，本件事證已經明確，被告之犯行堪予認定，應依\n    法論科。\n三、核被告所為，係犯刑法第185 條之3 服用酒類不能安全駕駛\n    動力交通工具而駕駛罪。爰審酌被告呼氣酒精濃度僅為每公\n    升0.31毫克，然其確已無法安全駕駛動力交通工具，且因此\n    與蕭婉倩所駕駛之上開機車發生碰撞，致蕭婉倩受傷，及其\n    犯罪後已坦承犯行等一切情狀，量處如主文所示之刑，並諭\n    知易服勞役之折算標準。\n四、依刑事訴訟法第449 條第1 項前段，刑法第185 條之3 、第\n    42條第2 項，罰金罰鍰提高標準條例第2 條，逕以簡易判決\n    處刑如主文。\n五、如不服本判決，應於送達後10日內向本院提出上訴狀，上訴\n    於本院合議庭。"
  },
  "search": "臺灣桃園地方法院刑事簡易判決94年度桃交簡字第2114號聲請人臺灣桃園地方法院檢察署檢察官被告甲○○上列被告因公共危險案件，經檢察官聲請以簡易判決處刑（94年度偵字第13826號），本院判決如下：主文甲○○服用酒類，不能安全駕駛動力交通工具而駕駛，處罰金玖仟元，如易服勞役，以參佰元折算壹日。事實及理由一、犯罪事實：甲○○明知其服用酒類後已不能安全駕駛動力交通工具，竟於民國94年7月12日下午3時許，在桃園縣蘆竹鄉○○路○段某餐廳內飲酒後，仍駕駛車號0796-KQ號自用小客車沿南山路往南崁方向行駛，嗣於同日下午3時15分許，行經南山路2段394巷口欲迴轉時，果因酒後不能安全駕駛，不慎撞及蕭婉倩所騎駛之車號HRH-925號機車，致蕭婉倩人車倒地而受有左髖骨挫傷、右前臂擦傷之傷害（傷害部分未據告訴），警方據報前往處理後始查知上情。二、上開犯罪事實，業據被告甲○○坦承不諱，雖其酒精濃度測試結果僅為每公升0.31毫克，然參酌證人即被害人蕭婉倩於偵查中具結證稱：事發當時被告怪怪的，一直要強拉我起來，感覺有喝酒等語，及證人即當日查獲被告之警員沈宏昌於偵查中具結證稱：當日被告反應有點慢，注意力無法集中、語無倫次、多話，會說些與案件無關的話，身體站不住，會左右搖晃等語，足徵被告確呈酒醉狀態，已達無法安全駕駛動力交通工具之程度，此外，並有呼氣酒精濃度測試紀錄表、刑法第185條之3案件測試觀察紀錄表、汽車駕駛人酒後生理協調平衡檢測紀錄表、道路交通事故現場圖、調查報告表(一)、(二)各1紙、現場照片8張在卷可稽，是被告之自白與事實相符，本件事證已經明確，被告之犯行堪予認定，應依法論科。三、核被告所為，係犯刑法第185條之3服用酒類不能安全駕駛動力交通工具而駕駛罪。爰審酌被告呼氣酒精濃度僅為每公升0.31毫克，然其確已無法安全駕駛動力交通工具，且因此與蕭婉倩所駕駛之上開機車發生碰撞，致蕭婉倩受傷，及其犯罪後已坦承犯行等一切情狀，量處如主文所示之刑，並諭知易服勞役之折算標準。四、依刑事訴訟法第449條第1項前段，刑法第185條之3、第42條第2項，罰金罰鍰提高標準條例第2條，逕以簡易判決處刑如主文。五、如不服本判決，應於送達後10日內向本院提出上訴狀，上訴於本院合議庭。中華民國94年12月7日交通法庭法官魏于傑上正本證明與原本無異。書記官林怡君中華民國94年12月12日本案論罪科刑主要法條：中華民國刑法第185條之3服用毒品、麻醉藥品、酒類或其他相類之物，不能安全駕駛動力交通工具而駕駛者，處一年以下有期徒刑、拘役或三萬元以下罰金。",
  "characters": {
    "judges": [
      "魏于傑"
    ],
    "prosecutors": [

    ],
    "lawyers": [

    ],
    "clerks": [
      "林怡君"
    ],
    "plaintiffs": [

    ],
    "defendants": [
      "甲○○"
    ],
    "prosecutor_office": [
      "臺灣桃園地方法院檢察署檢察官"
    ],
    "creditors": [

    ],
    "debtors": [

    ],
    "judicial_associate_officer": [

    ]
  },
  "adjudged_at": "2005-12-07",
  "created_at": "2016-02-07 03:54:25",
  "updated_at": "2016-02-07 03:54:25"
}