{
  "identify": "TCD-94-中簡-1970-20050726-1",
  "court": {
    "name": "臺灣臺中地方法院",
    "code": "TCD"
  },
  "division": {
    "name": "刑事",
    "code": "M"
  },
  "year": 94,
  "word": "中簡",
  "number": "1970",
  "jcheck": "1",
  "reason": "贓物",
  "content": "臺灣臺中地方法院刑事簡易判決        94年度中簡字第1970號\n聲  請  人  台灣台中地方法院檢察署檢察官\n被      告  甲○○\n上列被告因贓物案件，經檢察官聲請以簡易判決處刑（94年度速\n偵字第2545號），本院判決如下：\n    主  文\n甲○○收受贓物，處有期徒刑參月，如易科罰金，以參佰元折算\n壹日。\n    犯罪事實及理由\n一、本案犯罪事實欄一、第二行「UTL-702」應更正為「VTU-702\n    」號外，其餘之犯罪事實、證據，及應適用之法條均引用檢\n    察官聲請簡易判決處刑書之記載外，並適用刑法第四十一條\n    第一項前段，罰金罰鍰提高標準條例第一條前段、第二條。\n二、依刑事訴訟法第四百四十九條第一項前段、第四百五十四條\n    第二項，逕以簡易判決處如主文所示之刑。\n如不服本判決，應於判決送達後十日內，向本院提出上訴狀（須\n附繕本）。\n中    華    民    國    94    年    7    月    26     日\n                            臺中簡易庭\n                                法  官  郭瑞祥\n上正本證明與原本無異。\n中    華    民    國    94    年    7    月    26     日\n                                書記官  王淑燕\n附錄本案論罪科刑法條全文\n中華民國刑法第349條\n 收受贓物者，處三年以下有期徒刑、拘役或五百元以下罰金。\n搬運、寄藏、故買贓物或為牙保者，處五年以下有期徒刑、拘役\n或科或併科一千元以下罰金。\n因贓物變得之財物，以贓物論。\n",
  "structure": {
    "main": "甲○○收受贓物，處有期徒刑參月，如易科罰金，以參佰元折算\n壹日。",
    "fact": "一、本案犯罪事實欄一、第二行「UTL-702」應更正為「VTU-702\n    」號外，其餘之犯罪事實、證據，及應適用之法條均引用檢\n    察官聲請簡易判決處刑書之記載外，並適用刑法第四十一條\n    第一項前段，罰金罰鍰提高標準條例第一條前段、第二條。\n二、依刑事訴訟法第四百四十九條第一項前段、第四百五十四條\n    第二項，逕以簡易判決處如主文所示之刑。\n如不服本判決，應於判決送達後十日內，向本院提出上訴狀（須\n附繕本）。",
    "reason": "一、本案犯罪事實欄一、第二行「UTL-702」應更正為「VTU-702\n    」號外，其餘之犯罪事實、證據，及應適用之法條均引用檢\n    察官聲請簡易判決處刑書之記載外，並適用刑法第四十一條\n    第一項前段，罰金罰鍰提高標準條例第一條前段、第二條。\n二、依刑事訴訟法第四百四十九條第一項前段、第四百五十四條\n    第二項，逕以簡易判決處如主文所示之刑。\n如不服本判決，應於判決送達後十日內，向本院提出上訴狀（須\n附繕本）。"
  },
  "search": "臺灣臺中地方法院刑事簡易判決94年度中簡字第1970號聲請人台灣台中地方法院檢察署檢察官被告甲○○上列被告因贓物案件，經檢察官聲請以簡易判決處刑（94年度速偵字第2545號），本院判決如下：主文甲○○收受贓物，處有期徒刑參月，如易科罰金，以參佰元折算壹日。犯罪事實及理由一、本案犯罪事實欄一、第二行「UTL-702」應更正為「VTU-702」號外，其餘之犯罪事實、證據，及應適用之法條均引用檢察官聲請簡易判決處刑書之記載外，並適用刑法第四十一條第一項前段，罰金罰鍰提高標準條例第一條前段、第二條。二、依刑事訴訟法第四百四十九條第一項前段、第四百五十四條第二項，逕以簡易判決處如主文所示之刑。如不服本判決，應於判決送達後十日內，向本院提出上訴狀（須附繕本）。中華民國94年7月26日臺中簡易庭法官郭瑞祥上正本證明與原本無異。中華民國94年7月26日書記官王淑燕附錄本案論罪科刑法條全文中華民國刑法第349條收受贓物者，處三年以下有期徒刑、拘役或五百元以下罰金。搬運、寄藏、故買贓物或為牙保者，處五年以下有期徒刑、拘役或科或併科一千元以下罰金。因贓物變得之財物，以贓物論。",
  "characters": {
    "judges": [
      "郭瑞祥"
    ],
    "prosecutors": [

    ],
    "lawyers": [

    ],
    "clerks": [
      "王淑燕"
    ],
    "plaintiffs": [

    ],
    "defendants": [
      "甲○○"
    ],
    "prosecutor_office": [
      "台灣台中地方法院檢察署檢察官"
    ],
    "creditors": [

    ],
    "debtors": [

    ],
    "judicial_associate_officer": [

    ]
  },
  "adjudged_at": "2005-07-26",
  "created_at": "2016-02-07 08:38:06",
  "updated_at": "2016-02-07 08:38:06"
}