{
  "identify": "KSD-100-簡-336-20110324-1",
  "court": {
    "name": "臺灣高雄地方法院",
    "code": "KSD"
  },
  "division": {
    "name": "刑事",
    "code": "M"
  },
  "year": 100,
  "word": "簡",
  "number": "336",
  "jcheck": "1",
  "reason": "毒品危害防制條例",
  "content": "臺灣高雄地方法院刑事簡易判決          100年度簡字第336號\n聲  請  人  臺灣高雄地方法院檢察署檢察官\n被      告  林清源\n上列被告因違反毒品危害防制條例案件，經檢察官聲請以簡易判\n決處刑（99年度偵字第33778 號），本院判決如下：\n    主  文\n林清源持有第二級毒品，累犯，處有期徒刑參月，如易科罰金，\n以新臺幣壹仟元折算壹日。扣案之第二級毒品甲基安非他命壹包\n（含包裝袋壹只，驗餘淨重零點壹捌玖公克），沒收銷燬之。\n    事實及理由\n一、林清源前因竊盜案件，經臺灣屏東地方法院以97年度易字第\n    314 號判決判處有期徒刑1 年確定，嗣於民國99年4 月27日\n    假釋付保護管束結束，未經撤銷假釋，以執行論（構成累犯\n    ）。詎其猶不知悔改，基於持有第二級毒品甲基安非他命之\n    犯意，於99年9 月2 日0 時30分許，在高雄市○○區○○路\n    與林森路口之某網咖內，以新台幣1000元之代價向真實姓名\n    不詳綽號「偉仔」之人購得第二級毒品甲基安非他命1 小包\n    （毛重0.3 公克，驗後淨重0.189 公克）而非法持有之。嗣\n    於同日1 時10分許，在高雄市新興區○○○路267 號前因行\n    跡可疑為警盤查而查獲，並扣得上開甲基安非他命1 小包。\n二、本件之證據，除補充「高雄市政府警察局保安警察大隊扣押\n    物品清單、查獲現場圖3張」外，均引用檢察官聲請簡易判\n    決處刑書之記載（如附件）。\n三、核被告林清源所為，係犯毒品危害防制條例第11條第2 項之\n    持有第二級毒品罪。又被告有如聲請簡易判決處刑書所載之\n    犯罪科刑及執行情形，有臺灣高等法院被告前案紀錄表1 份\n    在卷可憑，其於假釋期滿未經撤銷視為徒刑執行完畢後，5\n    年以內故意再犯本件有期徒刑以上之罪，為累犯，應依刑法\n    第47條第1 項規定，加重其刑。爰審酌被告持有毒品之重量\n    、數量非鉅，時間甚短，而其持有毒品原係為供自己施用，\n    未及施用即為警查獲之犯罪動機，然前有違反毒品危害防制\n    條例前科，有上揭前案紀錄表可參，素行非佳，兼衡其犯後\n    坦承犯行，態度尚可等一切情狀，量處如主文所示之刑，並\n    諭知易科罰金之折算標準，以資儆懲。\n四、扣案之白色粉末1 包，經送檢驗結果，確含有甲基安非他命\n    成分（毛重0.3   公克，驗前淨重0.194   公克，驗餘淨重\n    0.189 公克），此有高雄市立醫學大學附設中和紀念醫院99\n    年11月16日出具之檢驗報告1 紙在卷可參，足認上開扣案物\n    含有第二級毒品甲基安非他命，而屬違禁物無訛，應依毒品\n    危害防制條例第18條第1 項前段規定，宣告沒收銷燬之。而\n    包裝上開毒品之包裝袋1 只，因鑑定單位一般係以傾倒之方\n    式，將包裝袋內之毒品倒出而與包裝袋分離而稱重，必要時\n    ，輔以刮杓刮取袋內毒品，然無論依何種方式分離，包裝袋\n    內均有極微量之毒品殘留，足認上開包裝袋1 只，其內分別\n    含有極微量之而無法析離，應整體視為查獲之第二級毒品，\n    依毒品危害防制條例第18條第1 項前段之規定，諭知沒收銷\n    燬之。又鑑驗耗用之上開第二級毒品甲基安非他命既已滅失\n    ，自毋庸宣告沒收銷燬之，併此敘明。\n五、依刑事訴訟法第449  條第1 項前段、第3 項、第450 條第1\n    項、第454 條第2 項，毒品危害防制條例第11條第2 項、第\n    18條第1  項前段，刑法第11條前段、第47條第1  項、第41\n    條第1 項前段，逕以簡易判決處刑如主文。\n六、如不服本判決，得自收受送達之日起10日內向本院提出上訴\n    狀，上訴於本院第二審合議庭（須附繕本）。\n中    華    民    國  100     年    3     月    24  日\n                  高雄簡易庭  法  官    沈宗興\n以上正本證明與原本無異。\n如不服本判決，應於判決送達之日起10日內向本院提出上訴書狀\n。\n中    華    民    國   100    年    3     月    24    日\n                              書記官    楊雅蘭\n附錄本判決論罪之法條：\n毒品危害防制條例第11條\n持有第一級毒品者，處3 年以下有期徒刑、拘役或新臺幣5 萬元\n以下罰金。\n持有第二級毒品者，處二年以下有期徒刑、拘役或新臺幣三萬元\n以下罰金。\n附件：\n臺灣高雄地方法院檢察署檢察官聲請簡易判決處刑書\n                                     99年度偵字第33778號\n    被      告  林清源  男  36歲（民國○○年○月○○日生）\n                        住屏東縣枋山鄉加祿村3鄰加祿89號\n                        國民身分證統一編號：Ｚ000000000號\n上列被告因毒品危害防制條例案件，經偵查終結，認為宜以簡易\n判決處刑，茲將犯罪事實及證據並所犯法條分敘如下：\n        犯罪事實\n一、林清源前因竊盜案件，經法院判決有期徒刑1年確定，於民\n    國99年4月7日假釋，於99年4月27日保護管束期滿執行完畢\n    。詎其猶不知悔改，基於持有第二級毒品甲基安非他命之犯\n    意，於99年9月2日0時30分許，在高雄市○○區○○路與林\n    森路口之某網咖內，以新台幣1000元之代價向真實姓名不詳\n    綽號「偉仔」之人購得第二級毒品甲基安非他命1小包（驗\n    後淨重0.189公克）而非法持有之。嗣於同日1時10分許，在\n    高雄市新興區○○○路267號前因行跡可疑為警盤查而查獲\n    ，並扣得上開甲基安非他命1小包。\n二、案經高雄市政府警察局移送偵辦。\n        證據並所犯法條\n一、證據清單\n┌──┬────────────┬─────────────┐\n│編號│    證  據  清  單      │      待  證  事  項      │\n├──┼────────────┼─────────────┤\n│ 1  │被告林清源於警詢及偵查中│被告於上開時、地購得上開毒│\n│    │之供述                  │品後為警查獲之事實。      │\n├──┼────────────┼─────────────┤\n│ 2  │高雄市政府警察局扣押筆錄│被告於上開時、地為警查扣之│\n│    │、扣押物品目錄表、高雄醫│毒品確含甲基安非他命成分之│\n│    │學大學附設中和紀念醫院99│事實。                    │\n│    │年11月16日檢驗報告      │                          │\n└──┴────────────┴─────────────┘\n二、核被告林清源所為，係犯毒品危害防制條例第11條第2項之\n    持有第二級毒品罪嫌。被告曾受有期徒刑之執行完畢，有本\n    署刑案查註紀錄表在卷可按，其於5年內故意再犯本件有期\n    徒刑以上之罪，為累犯，請依刑法第47條第1項之規定加重\n    其刑。另扣案之第二級毒品甲基安非他命，請依毒品危害防\n    制條例第18條第1項之規定沒收銷毀之。\n三、依刑事訴訟法第451條第1項聲請逕以簡易判決處刑。\n    此    致\n臺灣高雄地方法院\n中    華    民    國    99    年    12    月    17    日\n                                檢  察  官  羅瑞昌\n參考法條：\n毒品危害防制條例第11條\n持有第一級毒品者，處 3 年以下有期徒刑、拘役或新臺幣 5 萬\n元以下罰金。\n持有第二級毒品者，處 2 年以下有期徒刑、拘役或新臺幣 3 萬\n元以下罰金。\n持有第一級毒品純質淨重十公克以上者，處 1 年以上 7 年以下\n有期徒刑，得併科新臺幣 1 百萬元以下罰金。\n持有第二級毒品純質淨重二十公克以上者，處 6 月以上 5 年以\n下有期徒刑，得併科新臺幣 70 萬元以下罰金。\n持有第三級毒品純質淨重二十公克以上者，處 3 年以下有期徒\n刑，得併科新臺幣 30 萬元以下罰金。\n持有第四級毒品純質淨重二十公克以上者，處 1 年以下有期徒\n刑，得併科新臺幣 10 萬元以下罰金。\n持有專供製造或施用第一級、第二級毒品之器具者，處 1 年以\n下有期徒刑、拘役或新臺幣 1 萬元以下罰金。\n中華民國刑法第47條\n受徒刑之執行完畢，或一部之執行而赦免後，五年以內故意再犯\n有期徒刑以上之罪者，為累犯，加重本刑至二分之一。\n第98條第2項關於因強制工作而免其刑之執行者，於受強制工作\n處分之執行完畢或一部之執行而免除後，五年以內故意再犯有期\n徒刑以上之罪者，以累犯論。\n附記事項：本件係依刑事訴訟法簡易程序辦理，法院簡易庭得不\n傳喚被告、輔佐人、告訴人、告發人等出庭即以簡易判決處刑；\n被告、被害人、告訴人等對告訴乃論案件如已達成民事和解而要\n撤回告訴或對非告訴乃論案件認有受傳喚到庭陳述意見之必要時\n，請即另以書狀向簡易法庭陳述或請求傳訊。",
  "structure": {
    "main": "林清源持有第二級毒品，累犯，處有期徒刑參月，如易科罰金，\n以新臺幣壹仟元折算壹日。扣案之第二級毒品甲基安非他命壹包\n（含包裝袋壹只，驗餘淨重零點壹捌玖公克），沒收銷燬之。",
    "fact": "一、林清源前因竊盜案件，經臺灣屏東地方法院以97年度易字第\n    314 號判決判處有期徒刑1 年確定，嗣於民國99年4 月27日\n    假釋付保護管束結束，未經撤銷假釋，以執行論（構成累犯\n    ）。詎其猶不知悔改，基於持有第二級毒品甲基安非他命之\n    犯意，於99年9 月2 日0 時30分許，在高雄市○○區○○路\n    與林森路口之某網咖內，以新台幣1000元之代價向真實姓名\n    不詳綽號「偉仔」之人購得第二級毒品甲基安非他命1 小包\n    （毛重0.3 公克，驗後淨重0.189 公克）而非法持有之。嗣\n    於同日1 時10分許，在高雄市新興區○○○路267 號前因行\n    跡可疑為警盤查而查獲，並扣得上開甲基安非他命1 小包。\n二、本件之證據，除補充「高雄市政府警察局保安警察大隊扣押\n    物品清單、查獲現場圖3張」外，均引用檢察官聲請簡易判\n    決處刑書之記載（如附件）。\n三、核被告林清源所為，係犯毒品危害防制條例第11條第2 項之\n    持有第二級毒品罪。又被告有如聲請簡易判決處刑書所載之\n    犯罪科刑及執行情形，有臺灣高等法院被告前案紀錄表1 份\n    在卷可憑，其於假釋期滿未經撤銷視為徒刑執行完畢後，5\n    年以內故意再犯本件有期徒刑以上之罪，為累犯，應依刑法\n    第47條第1 項規定，加重其刑。爰審酌被告持有毒品之重量\n    、數量非鉅，時間甚短，而其持有毒品原係為供自己施用，\n    未及施用即為警查獲之犯罪動機，然前有違反毒品危害防制\n    條例前科，有上揭前案紀錄表可參，素行非佳，兼衡其犯後\n    坦承犯行，態度尚可等一切情狀，量處如主文所示之刑，並\n    諭知易科罰金之折算標準，以資儆懲。\n四、扣案之白色粉末1 包，經送檢驗結果，確含有甲基安非他命\n    成分（毛重0.3   公克，驗前淨重0.194   公克，驗餘淨重\n    0.189 公克），此有高雄市立醫學大學附設中和紀念醫院99\n    年11月16日出具之檢驗報告1 紙在卷可參，足認上開扣案物\n    含有第二級毒品甲基安非他命，而屬違禁物無訛，應依毒品\n    危害防制條例第18條第1 項前段規定，宣告沒收銷燬之。而\n    包裝上開毒品之包裝袋1 只，因鑑定單位一般係以傾倒之方\n    式，將包裝袋內之毒品倒出而與包裝袋分離而稱重，必要時\n    ，輔以刮杓刮取袋內毒品，然無論依何種方式分離，包裝袋\n    內均有極微量之毒品殘留，足認上開包裝袋1 只，其內分別\n    含有極微量之而無法析離，應整體視為查獲之第二級毒品，\n    依毒品危害防制條例第18條第1 項前段之規定，諭知沒收銷\n    燬之。又鑑驗耗用之上開第二級毒品甲基安非他命既已滅失\n    ，自毋庸宣告沒收銷燬之，併此敘明。\n五、依刑事訴訟法第449  條第1 項前段、第3 項、第450 條第1\n    項、第454 條第2 項，毒品危害防制條例第11條第2 項、第\n    18條第1  項前段，刑法第11條前段、第47條第1  項、第41\n    條第1 項前段，逕以簡易判決處刑如主文。\n六、如不服本判決，得自收受送達之日起10日內向本院提出上訴\n    狀，上訴於本院第二審合議庭（須附繕本）。",
    "reason": "一、林清源前因竊盜案件，經臺灣屏東地方法院以97年度易字第\n    314 號判決判處有期徒刑1 年確定，嗣於民國99年4 月27日\n    假釋付保護管束結束，未經撤銷假釋，以執行論（構成累犯\n    ）。詎其猶不知悔改，基於持有第二級毒品甲基安非他命之\n    犯意，於99年9 月2 日0 時30分許，在高雄市○○區○○路\n    與林森路口之某網咖內，以新台幣1000元之代價向真實姓名\n    不詳綽號「偉仔」之人購得第二級毒品甲基安非他命1 小包\n    （毛重0.3 公克，驗後淨重0.189 公克）而非法持有之。嗣\n    於同日1 時10分許，在高雄市新興區○○○路267 號前因行\n    跡可疑為警盤查而查獲，並扣得上開甲基安非他命1 小包。\n二、本件之證據，除補充「高雄市政府警察局保安警察大隊扣押\n    物品清單、查獲現場圖3張」外，均引用檢察官聲請簡易判\n    決處刑書之記載（如附件）。\n三、核被告林清源所為，係犯毒品危害防制條例第11條第2 項之\n    持有第二級毒品罪。又被告有如聲請簡易判決處刑書所載之\n    犯罪科刑及執行情形，有臺灣高等法院被告前案紀錄表1 份\n    在卷可憑，其於假釋期滿未經撤銷視為徒刑執行完畢後，5\n    年以內故意再犯本件有期徒刑以上之罪，為累犯，應依刑法\n    第47條第1 項規定，加重其刑。爰審酌被告持有毒品之重量\n    、數量非鉅，時間甚短，而其持有毒品原係為供自己施用，\n    未及施用即為警查獲之犯罪動機，然前有違反毒品危害防制\n    條例前科，有上揭前案紀錄表可參，素行非佳，兼衡其犯後\n    坦承犯行，態度尚可等一切情狀，量處如主文所示之刑，並\n    諭知易科罰金之折算標準，以資儆懲。\n四、扣案之白色粉末1 包，經送檢驗結果，確含有甲基安非他命\n    成分（毛重0.3   公克，驗前淨重0.194   公克，驗餘淨重\n    0.189 公克），此有高雄市立醫學大學附設中和紀念醫院99\n    年11月16日出具之檢驗報告1 紙在卷可參，足認上開扣案物\n    含有第二級毒品甲基安非他命，而屬違禁物無訛，應依毒品\n    危害防制條例第18條第1 項前段規定，宣告沒收銷燬之。而\n    包裝上開毒品之包裝袋1 只，因鑑定單位一般係以傾倒之方\n    式，將包裝袋內之毒品倒出而與包裝袋分離而稱重，必要時\n    ，輔以刮杓刮取袋內毒品，然無論依何種方式分離，包裝袋\n    內均有極微量之毒品殘留，足認上開包裝袋1 只，其內分別\n    含有極微量之而無法析離，應整體視為查獲之第二級毒品，\n    依毒品危害防制條例第18條第1 項前段之規定，諭知沒收銷\n    燬之。又鑑驗耗用之上開第二級毒品甲基安非他命既已滅失\n    ，自毋庸宣告沒收銷燬之，併此敘明。\n五、依刑事訴訟法第449  條第1 項前段、第3 項、第450 條第1\n    項、第454 條第2 項，毒品危害防制條例第11條第2 項、第\n    18條第1  項前段，刑法第11條前段、第47條第1  項、第41\n    條第1 項前段，逕以簡易判決處刑如主文。\n六、如不服本判決，得自收受送達之日起10日內向本院提出上訴\n    狀，上訴於本院第二審合議庭（須附繕本）。"
  },
  "search": "臺灣高雄地方法院刑事簡易判決100年度簡字第336號聲請人臺灣高雄地方法院檢察署檢察官被告林清源上列被告因違反毒品危害防制條例案件，經檢察官聲請以簡易判決處刑（99年度偵字第33778號），本院判決如下：主文林清源持有第二級毒品，累犯，處有期徒刑參月，如易科罰金，以新臺幣壹仟元折算壹日。扣案之第二級毒品甲基安非他命壹包（含包裝袋壹只，驗餘淨重零點壹捌玖公克），沒收銷燬之。事實及理由一、林清源前因竊盜案件，經臺灣屏東地方法院以97年度易字第314號判決判處有期徒刑1年確定，嗣於民國99年4月27日假釋付保護管束結束，未經撤銷假釋，以執行論（構成累犯）。詎其猶不知悔改，基於持有第二級毒品甲基安非他命之犯意，於99年9月2日0時30分許，在高雄市○○區○○路與林森路口之某網咖內，以新台幣1000元之代價向真實姓名不詳綽號「偉仔」之人購得第二級毒品甲基安非他命1小包（毛重0.3公克，驗後淨重0.189公克）而非法持有之。嗣於同日1時10分許，在高雄市新興區○○○路267號前因行跡可疑為警盤查而查獲，並扣得上開甲基安非他命1小包。二、本件之證據，除補充「高雄市政府警察局保安警察大隊扣押物品清單、查獲現場圖3張」外，均引用檢察官聲請簡易判決處刑書之記載（如附件）。三、核被告林清源所為，係犯毒品危害防制條例第11條第2項之持有第二級毒品罪。又被告有如聲請簡易判決處刑書所載之犯罪科刑及執行情形，有臺灣高等法院被告前案紀錄表1份在卷可憑，其於假釋期滿未經撤銷視為徒刑執行完畢後，5年以內故意再犯本件有期徒刑以上之罪，為累犯，應依刑法第47條第1項規定，加重其刑。爰審酌被告持有毒品之重量、數量非鉅，時間甚短，而其持有毒品原係為供自己施用，未及施用即為警查獲之犯罪動機，然前有違反毒品危害防制條例前科，有上揭前案紀錄表可參，素行非佳，兼衡其犯後坦承犯行，態度尚可等一切情狀，量處如主文所示之刑，並諭知易科罰金之折算標準，以資儆懲。四、扣案之白色粉末1包，經送檢驗結果，確含有甲基安非他命成分（毛重0.3公克，驗前淨重0.194公克，驗餘淨重0.189公克），此有高雄市立醫學大學附設中和紀念醫院99年11月16日出具之檢驗報告1紙在卷可參，足認上開扣案物含有第二級毒品甲基安非他命，而屬違禁物無訛，應依毒品危害防制條例第18條第1項前段規定，宣告沒收銷燬之。而包裝上開毒品之包裝袋1只，因鑑定單位一般係以傾倒之方式，將包裝袋內之毒品倒出而與包裝袋分離而稱重，必要時，輔以刮杓刮取袋內毒品，然無論依何種方式分離，包裝袋內均有極微量之毒品殘留，足認上開包裝袋1只，其內分別含有極微量之而無法析離，應整體視為查獲之第二級毒品，依毒品危害防制條例第18條第1項前段之規定，諭知沒收銷燬之。又鑑驗耗用之上開第二級毒品甲基安非他命既已滅失，自毋庸宣告沒收銷燬之，併此敘明。五、依刑事訴訟法第449條第1項前段、第3項、第450條第1項、第454條第2項，毒品危害防制條例第11條第2項、第18條第1項前段，刑法第11條前段、第47條第1項、第41條第1項前段，逕以簡易判決處刑如主文。六、如不服本判決，得自收受送達之日起10日內向本院提出上訴狀，上訴於本院第二審合議庭（須附繕本）。中華民國100年3月24日高雄簡易庭法官沈宗興以上正本證明與原本無異。如不服本判決，應於判決送達之日起10日內向本院提出上訴書狀。中華民國100年3月24日書記官楊雅蘭附錄本判決論罪之法條：毒品危害防制條例第11條持有第一級毒品者，處3年以下有期徒刑、拘役或新臺幣5萬元以下罰金。持有第二級毒品者，處二年以下有期徒刑、拘役或新臺幣三萬元以下罰金。附件：臺灣高雄地方法院檢察署檢察官聲請簡易判決處刑書99年度偵字第33778號被告林清源男36歲（民國○○年○月○○日生）住屏東縣枋山鄉加祿村3鄰加祿89號國民身分證統一編號：Ｚ000000000號上列被告因毒品危害防制條例案件，經偵查終結，認為宜以簡易判決處刑，茲將犯罪事實及證據並所犯法條分敘如下：犯罪事實一、林清源前因竊盜案件，經法院判決有期徒刑1年確定，於民國99年4月7日假釋，於99年4月27日保護管束期滿執行完畢。詎其猶不知悔改，基於持有第二級毒品甲基安非他命之犯意，於99年9月2日0時30分許，在高雄市○○區○○路與林森路口之某網咖內，以新台幣1000元之代價向真實姓名不詳綽號「偉仔」之人購得第二級毒品甲基安非他命1小包（驗後淨重0.189公克）而非法持有之。嗣於同日1時10分許，在高雄市新興區○○○路267號前因行跡可疑為警盤查而查獲，並扣得上開甲基安非他命1小包。二、案經高雄市政府警察局移送偵辦。證據並所犯法條一、證據清單┌──┬────────────┬─────────────┐│編號│證據清單│待證事項│├──┼────────────┼─────────────┤│1│被告林清源於警詢及偵查中│被告於上開時、地購得上開毒│││之供述│品後為警查獲之事實。│├──┼────────────┼─────────────┤│2│高雄市政府警察局扣押筆錄│被告於上開時、地為警查扣之│││、扣押物品目錄表、高雄醫│毒品確含甲基安非他命成分之│││學大學附設中和紀念醫院99│事實。│││年11月16日檢驗報告││└──┴────────────┴─────────────┘二、核被告林清源所為，係犯毒品危害防制條例第11條第2項之持有第二級毒品罪嫌。被告曾受有期徒刑之執行完畢，有本署刑案查註紀錄表在卷可按，其於5年內故意再犯本件有期徒刑以上之罪，為累犯，請依刑法第47條第1項之規定加重其刑。另扣案之第二級毒品甲基安非他命，請依毒品危害防制條例第18條第1項之規定沒收銷毀之。三、依刑事訴訟法第451條第1項聲請逕以簡易判決處刑。此致臺灣高雄地方法院中華民國99年12月17日檢察官羅瑞昌參考法條：毒品危害防制條例第11條持有第一級毒品者，處3年以下有期徒刑、拘役或新臺幣5萬元以下罰金。持有第二級毒品者，處2年以下有期徒刑、拘役或新臺幣3萬元以下罰金。持有第一級毒品純質淨重十公克以上者，處1年以上7年以下有期徒刑，得併科新臺幣1百萬元以下罰金。持有第二級毒品純質淨重二十公克以上者，處6月以上5年以下有期徒刑，得併科新臺幣70萬元以下罰金。持有第三級毒品純質淨重二十公克以上者，處3年以下有期徒刑，得併科新臺幣30萬元以下罰金。持有第四級毒品純質淨重二十公克以上者，處1年以下有期徒刑，得併科新臺幣10萬元以下罰金。持有專供製造或施用第一級、第二級毒品之器具者，處1年以下有期徒刑、拘役或新臺幣1萬元以下罰金。中華民國刑法第47條受徒刑之執行完畢，或一部之執行而赦免後，五年以內故意再犯有期徒刑以上之罪者，為累犯，加重本刑至二分之一。第98條第2項關於因強制工作而免其刑之執行者，於受強制工作處分之執行完畢或一部之執行而免除後，五年以內故意再犯有期徒刑以上之罪者，以累犯論。附記事項：本件係依刑事訴訟法簡易程序辦理，法院簡易庭得不傳喚被告、輔佐人、告訴人、告發人等出庭即以簡易判決處刑；被告、被害人、告訴人等對告訴乃論案件如已達成民事和解而要撤回告訴或對非告訴乃論案件認有受傳喚到庭陳述意見之必要時，請即另以書狀向簡易法庭陳述或請求傳訊。",
  "characters": {
    "judges": [
      "沈宗興"
    ],
    "prosecutors": [

    ],
    "lawyers": [

    ],
    "clerks": [
      "楊雅蘭"
    ],
    "plaintiffs": [

    ],
    "defendants": [
      "林清源",
      "林清源  男  36歲（民國○○年○月○○日生）"
    ],
    "prosecutor_office": [
      "臺灣高雄地方法院檢察署檢察官"
    ],
    "creditors": [

    ],
    "debtors": [

    ],
    "judicial_associate_officer": [

    ]
  },
  "adjudged_at": "2011-03-24",
  "created_at": "2016-02-13 21:18:53",
  "updated_at": "2016-02-13 21:18:53"
}