{
  "identify": "KSD-99-易-1882-20110324-3",
  "court": {
    "name": "臺灣高雄地方法院",
    "code": "KSD"
  },
  "division": {
    "name": "刑事",
    "code": "M"
  },
  "year": 99,
  "word": "易",
  "number": "1882",
  "jcheck": "3",
  "reason": "詐欺",
  "content": "臺灣高雄地方法院刑事判決              99年度易字第1882號\n公  訴  人  臺灣高雄地方法院檢察署檢察官\n被      告  李富銘\n上列被告因詐欺案件，經檢察官提起公訴（臺灣高雄地方法院檢\n察署98年度偵字第26986 號）及移送併辦（臺灣臺南地方法院檢\n察署99年度偵字第2456號、臺灣桃園地方法院檢察署99年度偵字\n第1149號），本院判決如下：\n    主  文\n李富銘幫助犯詐欺取財罪，累犯，處有期徒刑月，如易科罰金\n，以新臺幣壹仟元折算壹日。\n    事  實\n一、李富銘前因恐嚇案件，經臺灣高等法院高雄分院以92年度上\n    易字第1374號判處有期徒刑7 月確定，復因違反動產擔保交\n    易法案件，經臺灣臺南地方法院以92年度南簡字第873 號判\n    處有期徒刑4 月確定，上開二案件之宣告刑經合併定其應執\n    行刑為有期徒刑10月，並於94年6 月30日縮刑期滿執行完畢\n    出監。詎猶不知悔改，其可預見一般取得他人行動電話門號\n    使用之行徑，常與財產犯罪所需有密切之關聯，可能係為掩\n    飾不法犯行，避免有偵查犯罪權限之執法人員循線查緝，以\n    確保犯罪所得之不法利益，並掩人耳目。竟基於縱有人以其\n    提供之行動電話門號實施詐欺取財犯行，亦不違背其本意之\n    幫助犯意，而於民國98年5 月12日至同年5 月24日期間內之\n    某日時許，將其於同年5 月12日向和信電訊股份有限公司（\n    下稱和信電訊公司）所申辦門號0000000000號行動電話晶片\n    卡1 張及向統一超商所申辦門號0000000000號行動電話晶片\n    卡1 張，在不詳地點交付予不法集團成員使用，嗣該不法集\n    團成員隨即使用上開行動電話門號作為犯罪工具，而分別為\n    下列犯行：\n(一)、不法集團成員基於意圖為自己不法所有之犯意，在露天拍賣\n    網站上佯登「【內行人市場】☆FUJIFILM FinePix F200 EX\n    R 附8G☆現貨售完為止☆原廠保固☆」之不實拍賣網頁，經\n    吳政憲於98年5 月25日上午11時30分許上網瀏覽前揭網頁後\n    ，誤信為真而直接上網下標購買，並依上開網頁所刊登聯絡\n    電話即李富銘所申辦前揭行動電話門號0000000000號聯絡賣\n    方，並隨即依不法集團成員所傳送之電話簡訊指示於同日中\n    午12時5 分許前往自動櫃員機轉帳買賣價金新臺幣（下同）\n    7,150 元至宋韶華（已歿，另經臺灣高雄地方法院檢察署為\n    不起訴處分）所申設華南商業銀行帳號000000000000號帳戶\n    內，隨即遭不法集團成員提領一空，嗣因吳政憲遲未接獲所\n    購買之上開商品而察覺有異，經再度撥打上開行動電話門號\n    後均無人接聽，始覺受騙而報警處理。\n(二)、不法集團成員另基於意圖為自己不法所有之犯意，在雅虎奇\n    摩拍賣網站上佯登販售諾基亞5800手機之不實拍賣訊息，經\n    謝智凱於98年5 月24日下午2 時許上網瀏覽前揭網頁後，誤\n    信為真，而依該網頁所刊登聯絡電話即李富銘所申辦前揭行\n    動電話門號0000000000號聯絡賣方進行議價，並隨即依不法\n    集團成員電話指示於同日晚間8 時30分許前往設於台南市○\n    ○路○段114 號永豐銀行自動櫃員機轉帳買賣價金計7,150\n    元至宋韶華上開華南商業銀行帳戶內，隨經不法集團成員提\n    領一空，嗣因謝智凱遲未接獲所購買之上開商品始覺受騙而\n    報警處理。\n(三)、不法集團成員復於98年5 月12日至同年7 月2 日期間內之某\n    日時許，在不詳地點將上開李富銘所申辦之0000000000號行\n    動電話門號交付予李訓達，李訓達、陳文賓（二人所涉輸入\n    禁藥犯嫌，業經臺灣桃園地方法院檢察署另案偵查）明知「\n    Sildenafil」成分之藥品，依藥事法第39條規定，應向行政\n    院衛生署申請查驗登記，並經核准發給藥品許可證，始得輸\n    入或製造，竟基於未經核准輸入禁藥之犯意聯絡，推由李訓\n    達於98年6 、7 月間某日向大陸地區年籍不詳自稱「何源」\n    之男子購買含有「Sildenafil」成分之「威爾剛」禁藥共計\n    2,050 顆後，隨即將該等禁藥夾藏於電腦螢幕切換器中，於\n    98年7 月2 日以航空郵寄方式自大陸地區輸入，並由陳文賓\n    出具個案委任書，同時於貨運單上填載李富銘上開行動電話\n    門號作為收貨人聯絡電話，委託不知情之聯邦快遞報關行報\n    關員向財政部臺北關稅局，申報進口上開電腦螢幕切換器貨\n    物1 批，而將上開禁藥運輸入境，嗣於98年7  月2 日上午9\n    時許，經財政部臺北關稅局海關人員於快遞專區查驗貨物時\n    ，發現上開夾藏之禁藥並加以查扣，而悉上情。\n二、案經吳憲政訴由高雄市政府警察局苓雅分局報請臺灣高雄地\n    方法院檢察署檢察官偵查起訴及謝智凱訴由臺南市政府警察\n    局第四分局報請臺灣臺南地方法院檢察署檢察官移送併辦、\n    內政部警政署航空警察隊報請臺灣桃園地方法院檢察署檢察\n    官移送併辦。\n    理  由\n壹、程序方面：\n    按被告以外之人於審判外之陳述，雖不符刑事訴訟法第159\n    條之1 至第159 條之4 之規定，而經當事人於審判程序同意\n    作為證據，法院審酌該言詞陳述或書面陳述作成時之情況，\n    認為適當者，亦得為證據；又當事人、代理人或辯護人於法\n    院調查證據時，知有第159 條第1 項不得為證據之情形，而\n    未於言詞辯論終結前聲明異議者，視為有前項之同意，刑事\n    訴訟法第159 條第1 項、第159 條之5 分別定有明文。查本\n    判決所引用屬於傳聞證據之部分，均已依法踐行調查證據程\n    序，且當事人於審判程序亦同意作為證據，而經本院審酌證\n    據資料作成時之情況，並無違法不當及證明力明顯過低之瑕\n    疵，亦無依法應排除其證據能力之情形，認以之作為證據應\n    屬適當，故自有證據能力。\n貳、實體方面：\n一、訊據被告李富銘固坦承行動電話門號0000000000號、000000\n    0000號（下均稱系爭行動電話門號）均係由其申辦之事實，\n    惟矢口否認涉有上開犯行，辯稱：伊前因酒駕案件遭通緝，\n    故委其友人出面代理向地檢署申請裁判書俾以向監理單位辦\n    理註銷罰單，惟因其友人於申請時誤將伊慣用之行動電話門\n    號號碼記載留存於申請書內，伊為避免行蹤暴露，始另行申\n    請上開門號，並將所申領門號晶片卡放置於其機車前方置物\n    箱內，惟於申領後數日內即於台南縣仁德鄉後壁村保安宮附\n    近遭竊，伊並未將上開門號交與不法集團使用云云，經查：\n(一)、被告於98年5 月12日分別向和信電訊公司、統一超商申領行\n    動電話門號0000000000號、0000000000號使用一節，除為被\n    告所不爭執外，尚有卷附和信電訊公司98年10月8 日和信（\n    企管）字第09821000237 號函附行動電話門號0000000000號\n    申設人資本資料暨申請書影本1 份、安源通訊代統一超商函\n    覆行動電話門號0000000000號申設人基本資料暨申請書影本\n    1 份可稽（見偵一卷第83至85頁，偵三卷第19頁、第32 頁\n    ）；又不法集團成員分別於前開網頁刊登不實內容之網路商\n    品拍賣訊息，致被害人吳政憲、謝智凱均陷於錯誤，而於上\n    揭時地分別撥打被告上開所申設行動電話門號0000000000號\n    聯絡不法集團成員，並先後依不法集團成員指示操作自動櫃\n    員機各匯款7,150 元至宋韶華所申設華南商業銀行帳號0000\n    00000000號帳戶內，隨即遭不法集團成員提領一空，而受詐\n    騙等情，除據證人即被害人吳政憲、謝智凱於警詢時證述明\n    確外（見警一卷第1 至2 頁，偵一卷第7 至8 頁），尚有卷\n    附高雄市政府警察局苓雅分局三多路派出所受理詐騙帳戶通\n    報警示簡便格式表、內政部警政署反詐騙案件記錄表、自動\n    櫃員機交易明細表、露天拍賣網頁資料、奇摩拍賣網頁資料\n    、宋韶華之華南銀行帳戶000000000000號開戶印鑑卡暨存款\n    往來明細表等件可憑（見警一卷第9 至17頁、第25至26頁，\n    偵一卷第17至19頁、第20至26頁）；另李訓達自不法集團成\n    員取得被告所申設行動電話門號0000000000號後，隨即與陳\n    文賓基於未經核准輸入禁藥之犯意聯絡，推由李訓達於98年\n    6 、7 月間某日向大陸地區年籍不詳自稱「何源」之男子購\n    買含有上開「Sildenafil」成分之「威爾剛」禁藥2,050 顆\n    後，隨即將該等禁藥夾藏於電腦螢幕切換器中，於98年7 月\n    2 日以航空郵寄方式自大陸地區輸入，並由陳文賓出具個案\n    委任書，同時於貨運單上填載被告所申設行動電話門號0000\n    000000號作為收貨人聯絡電話，委託不知情之聯邦快遞報關\n    行報關員向財政部臺北關稅局，申報進口上開電腦螢幕切換\n    器貨物1 批，而將上開禁藥運輸入境等情，固為陳文賓於另\n    案偵查中所否認，惟業經李訓達於偵查中供述明確（見偵三\n    卷第129 至134 頁），且有卷附個案委任書、行政院衛生署\n    98年8 月5 日衛署藥字第0980021480號函覆說明、行政院衛\n    生署藥物食品檢驗局98年7 月23日藥檢壹字第0980014594號\n    函覆說明暨檢驗報告書、貨運單、航空警察局安全檢察隊X\n    光檢查儀注檢貨物報告表等件可佐（見偵三卷第12至13頁、\n    第26至29頁、第33頁、第36至38頁），是以，被告前開行動\n    電話門號0000000000號、0000000000號分別遭利用作為詐欺\n    取財、輸入禁藥等犯罪使用之事實，應均可認定。\n(二)、至被告就其申辦系爭行動電話門號之原因一節，雖稱係因友\n    人不慎將其所慣用之行動電話門號留存於地檢署，其擔心司\n    法機關追蹤其行蹤，始另行申辦系爭行動電話門號云云，然\n    審之被告既已慮及司法機關可能經由行動電話門號追蹤其行\n    蹤之情，衡諸常理，其為躲避查緝，理應經由其他管道取得\n    使用他人名義申辦之行動電話門號以作為對外聯絡用途，豈\n    有再度以自己名義申領行動電話門號之理，況且，證人即為\n    被告申請裁判書之友人李玉雲於本院審理時證述：我記得是\n    在我幫被告向地檢署申請裁判書的前一天早上約7 、8 時許\n    ，被告騎機車到我家旁邊的廟旁涼亭內找我喝酒，我便騎被\n    告機車前往他處買米酒，買完酒後，我將酒放置於被告機車\n    前方的置物箱內，當時我看到置物箱內放置有七星牌香菸、\n    包葉檳榔及以透明夾鏈袋裝的2 片晶片卡等物品，回到涼亭\n    後我便與被告一起喝酒，因為我沒有香菸抽，所以被告叫我\n    到機車置物箱去拿煙，我因而發現放置於置物箱內的物品全\n    部不見了，因為喝酒時涼亭內尚有幾名年輕人在場，所以我\n    們想說應該飲酒期間我抱小孩回家去泡牛奶、被告離開涼亭\n    取上廁所時，那幾名年輕人乘機取走上開物品，但我與被告\n    都出去找後均無結果，後來被告認為該遭竊物品價值不高，\n    所以我們就回到涼亭繼續喝酒等語（見本院卷第129  至123\n    頁），固與被告於本院審理時供稱晶片卡遺失當時情形（見\n    本院卷第116 至119 頁），大致相符，然核之被告前稱係因\n    央請友人代為向地檢署申請裁判書時，友人誤將其慣用之行\n    動電話門號留存於申請書內之故，始另行申請本件系爭行動\n    電話門號使用之情，與證人李玉雲上述：晶片卡係伊代被告\n    向地檢署申請裁判書之前1 日遺失等語，顯有極大出入，是\n    以，渠等所述晶片卡遺失情節，是否屬實，自非無疑，再者\n    ，佐之一般人對於日常生活中所發生之事實記憶內容，往往\n    隨時間經過而逐漸淡忘或模糊，此為眾所周知之理，參以被\n    告於警詢時猶稱：不記得曾申辦系爭行動電話門號等語（見\n    偵一卷第74頁），惟至與其申請電話時間相隔年餘之本院審\n    理期日，經隔離被告、證人李玉雲進行訊問後，被告卻能具\n    體陳述：晶片卡遺失當日所嚼食之檳榔是包葉仔，與李玉雲\n    所飲用之酒類為米酒等顯非重要之日常生活細節（見本院卷\n    第118 頁），甚者，就遺失晶片卡當日所發生與其平日生活\n    習性無涉之相關事項，復能具體描述：伊平常所抽香菸品牌\n    為『WEST』，但當日放在機車置物箱與晶片卡同時遺失之香\n    菸則為其他友人贈送之七星牌香菸，晶片卡遺失時係使用透\n    明夾鏈袋包裝，當日在涼亭喝酒時尚有數名年輕人在場，上\n    開物品該等年輕人趁其去上廁所、李玉雲抱小孩回家泡牛奶\n    時偷取云云（見本院卷第117 、119 頁），衡以被告於距離\n    其所稱遺失晶片卡日期較近之警詢時，尚且無從記憶是否曾\n    申領系爭行動電話門號使用之重要事實，然歷經年餘後之本\n    院審理期日時對於晶片卡遺失時諸多不甚重要日常生活細節\n    卻記憶清晰，且與證人李玉雲上開證述內容完全相符，而無\n    出入，此實亦與常情有悖，由此益見被告所辯遺失晶片卡云\n    云，當非可採。此外，參以被告於偵查中供承：迄至98年7\n    月間為止，我仍使用原所申領之行動電話門號0000000000號\n    作為對外聯絡用途等語（見偵一卷第70頁、偵三卷第17頁）\n    ，復佐以被告自承迄今猶未將系爭行動電話門號辦理停話一\n    節（見本院卷第52頁），則被告於申領系爭行動電話門號後\n    ，既依舊使用原行動電話門號作為對外聯絡之工具，而未曾\n    使用系爭行動電話門號，復未將系爭行動電話門號辦理停話\n    ，則其確係將該等行動電話門號交付予他人使用之事實，當\n    可推認。\n(三)、按我國行動電話通信業者對於申辦行動電話門號使用並無特\n    殊資格及使用目的之限制，故凡有正當目的使用行動電話門\n    號之必要者，均可自行前往業者門市或特約經銷處辦請使用\n    ，殊無借用他人名義所申辦行動電話門號使用之理。倘不自\n    行申辦行動電話門號，反無故向他人借用行動電話門號卡使\n    用，依常理得認為其借用他人行動電話門號晶片卡使用之行\n    徑，極可能與財產犯罪密切相關，並藉此規避有犯罪偵查權\n    限之機關循線追查之可能。且現今媒體報導中，或以中獎、\n    退稅、家人遭擄、信用卡款對帳、金融卡密碼外洩、疑似遭\n    人盜領存款、張揚不可告人隱私等事由，利用他人名義所申\n    辦之行動電話門號作為聯繫工具，詐騙被害人至金融機構櫃\n    檯電匯，抑或持金融卡至自動櫃員機依其指示操作，使被害\n    人在不知情之狀況下依指示操作匯出或存入款項後，隨即將\n    之提領一空之詐騙手法，層出不窮，依一般人之智識及社會\n    生活經驗，極易認知收受門號晶片卡者悖於常情未使用自己\n    之門號而使用他人門號，顯為遂行通聯紀錄不易循線追查之\n    目的，自可產生該收受門號晶片卡者係用於不法財產犯罪之\n    認識。本件被告係將系爭行動電話門號交付予他人使用之事\n    實，業如前述，衡以被告係屬高中肄業以及其前揭辯稱變更\n    行動電話門號可逃避警方查緝等內容，足認依被告之智識程\n    度及生活經驗而言，對於行動電話門號交付予他人使用可能\n    遭利用作為財產犯罪用途一節，知之甚詳，是其猶將所申請\n    之系爭行動電話門號提供予不法集團使用，則其確有容認該\n    等門號供他人作為詐欺犯罪時使用之不確定故意，應堪認定\n    。\n(四)、又刑法上之幫助犯，係對於犯罪與正犯有共同之認識，而以\n    幫助之意思，對於正犯資以助力，而未參與實施犯罪之行為\n    者而言，是以如未參與實施犯罪構成要件之行為，而係出於\n    幫助之意思提供助力，即屬幫助犯，而非共同正犯。另幫助\n    犯係從屬於正犯而成立，並無獨立性，故幫助犯須對正犯之\n    犯罪事實，具有共同認識而加以助力，始能成立，其所應負\n    責任，亦以與正犯有同一認識之事實為限，若正犯所犯之事\n    實，超過其共同認識之範圍時，則幫助者事前既不知情，自\n    不負責，而應僅就其所認識之範圍負責（即所犯重於所知，\n    從其所知）。本件被告交付系爭行動電話門號予不法集團後\n    ，該不法集團除利用系爭0000000000號行動電話門號作為遂\n    行犯罪事實欄一(一)、(二)詐欺取財犯行之聯絡工具外，復另將\n    系爭0000000000號行動電話門號交付予李訓達、陳文賓等2\n    人作為遂行犯罪事實欄一(三)輸入禁藥犯行之聯絡工具，俱如\n    前述，惟將行動電話門號交付、出售他人使用，雖有幫助他\n    人為不法行為之不確定故意，然依常情而論，行為人主觀上\n    應只限於認知其所交付行動電話門號，有可能作為於類如詐\n    欺被害人之財產犯罪用途，蓋此為多數犯罪類型，而不及於\n    其他非財產犯罪類型，此外，復查無積極證據可資證明被告\n    對於李訓達、陳文賓等2 人前開輸入禁藥犯行有所認識，是\n    依前述，本件犯罪事實欄一(三)之正犯雖係成立輸入禁藥罪，\n    惟仍應認被告就此僅具幫助詐欺取財之不確定故意，附此敘\n    明。\n(五)、綜上所述，本件被告犯行事證明確，應依法予以論科。\n二、論罪科刑：\n(一)、核被告所為，係犯刑法第30條第1 項前段、第339 條第1項\n    之幫助詐欺取財罪，公訴意旨雖認被告就犯罪事實欄一(三)係\n    犯幫助輸入禁藥罪，惟被告此部分犯行僅具幫助詐欺取財之\n    不確定故意，所犯應為幫助詐欺取財罪，已如前述，因被告\n    所犯之社會基本事實同一，本院自得變更起訴法條。被告以\n    一提供系爭行動電話門號之行為，幫助不法集團成員分別詐\n    取被害人吳憲政、謝智凱之財物及李訓達、陳文賓輸入禁藥\n    ，觸犯數個幫助詐欺取財之罪名，為想像競合犯，應從一重\n    處斷；至檢察官移送併辦之如犯罪事實欄一(二)(三)部分，與本\n    件業經起訴之如犯罪事實欄一(一)部分具有想像競合犯之裁判\n    上一罪關係，自均為起訴效力所及，本院應併予審理；另被\n    告有如犯罪事實欄所載之有期徒刑執行完畢紀錄，有臺灣高\n    等法院被告前案紀錄表在卷可按，其於有期徒刑之執行完畢\n    後5 年內，故意再犯本件有期徒刑以上之罪，為累犯，應依\n    刑法第47條第1 項之規定加重其刑。又被告以幫助他人詐欺\n    取財之意思，參與犯罪構成要件以外之行為，為從犯，應依\n    刑法第30條第2 項規定減輕其刑，並先加重後減輕之。爰審\n    酌被告提供系爭行動電話門號幫助他人遂行犯罪，致使真正\n    犯罪者難以被查獲，助長社會犯罪風氣，行為確實可議，暨\n    兼衡被害人吳憲政、謝智凱因遭詐騙所受損害金額尚屬非鉅\n    ，被告幫助李訓達等人輸入禁藥對社會所造成之潛在危害，\n    以及被告之犯罪目的、手段、智識程度、經濟狀況等一切情\n    狀，量處如主文所示之刑，以資儆懲，併諭知如主文所示之\n    易科罰金折算標準。\n(二)、末按共同正犯因相互間利用他人之行為，以遂行其犯意之實\n    現，本於責任共同之原則，有關沒收部分，對於共犯間供犯\n    罪所用之物，自均應為沒收之諭知，惟幫助犯僅係對於犯罪\n    構成要件以外行為為加工，並無共同犯罪之意思，自不適用\n    該責任共同原則，對於正犯所有供犯罪所用之物或犯罪所得\n    之物，亦為沒收之諭知（參見最高法院91年臺上字第5583號\n    判決意旨）。查犯罪事實欄一(三)所扣案「威爾剛」2,050 顆\n    ，經採樣鑑定後認均屬含有「Sildenafil」西藥成分之藥品\n    ，未經行政院衛生署依藥事法第39條規定核准輸入進口，並\n    無衛生署核發之藥品輸入許可證，為同法第22條第2 款規定\n    之禁藥等情，有卷附前開行政院衛生署98年8 月5 日衛署藥\n    字第098002 1480 號函覆說明、行政院衛生署藥物食品檢驗\n    局98年7 月23日藥檢壹字第0980014594號函覆說明暨檢驗報\n    告書可稽，又上開禁藥固屬犯罪事實欄一(三)輸入禁藥犯行正\n    犯李訓達、陳文賓所用之物，惟被告就該等輸入禁藥犯行既\n    僅提供幫助行為，非屬共同正犯，揆諸上開說明，自無從依\n    刑法第38條規定併為沒收諭知，併此序明。\n據上論斷，應依刑事訴訟法第299 條第1 項前段、第300 條，刑\n法第339 條第1 項、第30條第1 項前段、第2 項、第55條、第47\n條第1 項、第41條第1 項前段，刑法施行法第1 條之1 ，判決如\n主文。\n本案經檢察官鄧藤墩到庭執行職務。\n中    華    民    國     100    年    3   月    24    日\n                  刑事第十八庭  審判長法  官  黃宗揚\n                                      法  官  高瑞聰\n                                      法  官  鄭子文\n以上正本證明與原本無異。\n如不服本判決應於收受判決後10日內向本院提出上訴書狀，並應\n敘述具體理由。其未敘述上訴理由者，應於上訴期間屆滿後20日\n內向本院補提理由書(均須按他造當事人之人數附繕本)「切勿逕\n送上級法院」。\n中    華    民    國     100   年     3   月    24    日\n                                      書記官  王立山\n附錄本案論罪科刑法條：\n中華民國刑法第339條\n（普通詐欺罪）\n意圖為自己或第三人不法之所有，以詐術使人將本人或第三人之\n物交付者，處5 年以下有期徒刑、拘役或科或併科1 千元以下罰\n金。\n以前項方法得財產上不法之利益或使第三人得之者，亦同。\n前二項之未遂犯罰之。",
  "structure": {
    "main": "李富銘幫助犯詐欺取財罪，累犯，處有期徒刑月，如易科罰金\n，以新臺幣壹仟元折算壹日。",
    "fact": "一、李富銘前因恐嚇案件，經臺灣高等法院高雄分院以92年度上\n    易字第1374號判處有期徒刑7 月確定，復因違反動產擔保交\n    易法案件，經臺灣臺南地方法院以92年度南簡字第873 號判\n    處有期徒刑4 月確定，上開二案件之宣告刑經合併定其應執\n    行刑為有期徒刑10月，並於94年6 月30日縮刑期滿執行完畢\n    出監。詎猶不知悔改，其可預見一般取得他人行動電話門號\n    使用之行徑，常與財產犯罪所需有密切之關聯，可能係為掩\n    飾不法犯行，避免有偵查犯罪權限之執法人員循線查緝，以\n    確保犯罪所得之不法利益，並掩人耳目。竟基於縱有人以其\n    提供之行動電話門號實施詐欺取財犯行，亦不違背其本意之\n    幫助犯意，而於民國98年5 月12日至同年5 月24日期間內之\n    某日時許，將其於同年5 月12日向和信電訊股份有限公司（\n    下稱和信電訊公司）所申辦門號0000000000號行動電話晶片\n    卡1 張及向統一超商所申辦門號0000000000號行動電話晶片\n    卡1 張，在不詳地點交付予不法集團成員使用，嗣該不法集\n    團成員隨即使用上開行動電話門號作為犯罪工具，而分別為\n    下列犯行：\n(一)、不法集團成員基於意圖為自己不法所有之犯意，在露天拍賣\n    網站上佯登「【內行人市場】☆FUJIFILM FinePix F200 EX\n    R 附8G☆現貨售完為止☆原廠保固☆」之不實拍賣網頁，經\n    吳政憲於98年5 月25日上午11時30分許上網瀏覽前揭網頁後\n    ，誤信為真而直接上網下標購買，並依上開網頁所刊登聯絡\n    電話即李富銘所申辦前揭行動電話門號0000000000號聯絡賣\n    方，並隨即依不法集團成員所傳送之電話簡訊指示於同日中\n    午12時5 分許前往自動櫃員機轉帳買賣價金新臺幣（下同）\n    7,150 元至宋韶華（已歿，另經臺灣高雄地方法院檢察署為\n    不起訴處分）所申設華南商業銀行帳號000000000000號帳戶\n    內，隨即遭不法集團成員提領一空，嗣因吳政憲遲未接獲所\n    購買之上開商品而察覺有異，經再度撥打上開行動電話門號\n    後均無人接聽，始覺受騙而報警處理。\n(二)、不法集團成員另基於意圖為自己不法所有之犯意，在雅虎奇\n    摩拍賣網站上佯登販售諾基亞5800手機之不實拍賣訊息，經\n    謝智凱於98年5 月24日下午2 時許上網瀏覽前揭網頁後，誤\n    信為真，而依該網頁所刊登聯絡電話即李富銘所申辦前揭行\n    動電話門號0000000000號聯絡賣方進行議價，並隨即依不法\n    集團成員電話指示於同日晚間8 時30分許前往設於台南市○\n    ○路○段114 號永豐銀行自動櫃員機轉帳買賣價金計7,150\n    元至宋韶華上開華南商業銀行帳戶內，隨經不法集團成員提\n    領一空，嗣因謝智凱遲未接獲所購買之上開商品始覺受騙而\n    報警處理。\n(三)、不法集團成員復於98年5 月12日至同年7 月2 日期間內之某\n    日時許，在不詳地點將上開李富銘所申辦之0000000000號行\n    動電話門號交付予李訓達，李訓達、陳文賓（二人所涉輸入\n    禁藥犯嫌，業經臺灣桃園地方法院檢察署另案偵查）明知「\n    Sildenafil」成分之藥品，依藥事法第39條規定，應向行政\n    院衛生署申請查驗登記，並經核准發給藥品許可證，始得輸\n    入或製造，竟基於未經核准輸入禁藥之犯意聯絡，推由李訓\n    達於98年6 、7 月間某日向大陸地區年籍不詳自稱「何源」\n    之男子購買含有「Sildenafil」成分之「威爾剛」禁藥共計\n    2,050 顆後，隨即將該等禁藥夾藏於電腦螢幕切換器中，於\n    98年7 月2 日以航空郵寄方式自大陸地區輸入，並由陳文賓\n    出具個案委任書，同時於貨運單上填載李富銘上開行動電話\n    門號作為收貨人聯絡電話，委託不知情之聯邦快遞報關行報\n    關員向財政部臺北關稅局，申報進口上開電腦螢幕切換器貨\n    物1 批，而將上開禁藥運輸入境，嗣於98年7  月2 日上午9\n    時許，經財政部臺北關稅局海關人員於快遞專區查驗貨物時\n    ，發現上開夾藏之禁藥並加以查扣，而悉上情。\n二、案經吳憲政訴由高雄市政府警察局苓雅分局報請臺灣高雄地\n    方法院檢察署檢察官偵查起訴及謝智凱訴由臺南市政府警察\n    局第四分局報請臺灣臺南地方法院檢察署檢察官移送併辦、\n    內政部警政署航空警察隊報請臺灣桃園地方法院檢察署檢察\n    官移送併辦。",
    "reason": "壹、程序方面：\n    按被告以外之人於審判外之陳述，雖不符刑事訴訟法第159\n    條之1 至第159 條之4 之規定，而經當事人於審判程序同意\n    作為證據，法院審酌該言詞陳述或書面陳述作成時之情況，\n    認為適當者，亦得為證據；又當事人、代理人或辯護人於法\n    院調查證據時，知有第159 條第1 項不得為證據之情形，而\n    未於言詞辯論終結前聲明異議者，視為有前項之同意，刑事\n    訴訟法第159 條第1 項、第159 條之5 分別定有明文。查本\n    判決所引用屬於傳聞證據之部分，均已依法踐行調查證據程\n    序，且當事人於審判程序亦同意作為證據，而經本院審酌證\n    據資料作成時之情況，並無違法不當及證明力明顯過低之瑕\n    疵，亦無依法應排除其證據能力之情形，認以之作為證據應\n    屬適當，故自有證據能力。\n貳、實體方面：\n一、訊據被告李富銘固坦承行動電話門號0000000000號、000000\n    0000號（下均稱系爭行動電話門號）均係由其申辦之事實，\n    惟矢口否認涉有上開犯行，辯稱：伊前因酒駕案件遭通緝，\n    故委其友人出面代理向地檢署申請裁判書俾以向監理單位辦\n    理註銷罰單，惟因其友人於申請時誤將伊慣用之行動電話門\n    號號碼記載留存於申請書內，伊為避免行蹤暴露，始另行申\n    請上開門號，並將所申領門號晶片卡放置於其機車前方置物\n    箱內，惟於申領後數日內即於台南縣仁德鄉後壁村保安宮附\n    近遭竊，伊並未將上開門號交與不法集團使用云云，經查：\n(一)、被告於98年5 月12日分別向和信電訊公司、統一超商申領行\n    動電話門號0000000000號、0000000000號使用一節，除為被\n    告所不爭執外，尚有卷附和信電訊公司98年10月8 日和信（\n    企管）字第09821000237 號函附行動電話門號0000000000號\n    申設人資本資料暨申請書影本1 份、安源通訊代統一超商函\n    覆行動電話門號0000000000號申設人基本資料暨申請書影本\n    1 份可稽（見偵一卷第83至85頁，偵三卷第19頁、第32 頁\n    ）；又不法集團成員分別於前開網頁刊登不實內容之網路商\n    品拍賣訊息，致被害人吳政憲、謝智凱均陷於錯誤，而於上\n    揭時地分別撥打被告上開所申設行動電話門號0000000000號\n    聯絡不法集團成員，並先後依不法集團成員指示操作自動櫃\n    員機各匯款7,150 元至宋韶華所申設華南商業銀行帳號0000\n    00000000號帳戶內，隨即遭不法集團成員提領一空，而受詐\n    騙等情，除據證人即被害人吳政憲、謝智凱於警詢時證述明\n    確外（見警一卷第1 至2 頁，偵一卷第7 至8 頁），尚有卷\n    附高雄市政府警察局苓雅分局三多路派出所受理詐騙帳戶通\n    報警示簡便格式表、內政部警政署反詐騙案件記錄表、自動\n    櫃員機交易明細表、露天拍賣網頁資料、奇摩拍賣網頁資料\n    、宋韶華之華南銀行帳戶000000000000號開戶印鑑卡暨存款\n    往來明細表等件可憑（見警一卷第9 至17頁、第25至26頁，\n    偵一卷第17至19頁、第20至26頁）；另李訓達自不法集團成\n    員取得被告所申設行動電話門號0000000000號後，隨即與陳\n    文賓基於未經核准輸入禁藥之犯意聯絡，推由李訓達於98年\n    6 、7 月間某日向大陸地區年籍不詳自稱「何源」之男子購\n    買含有上開「Sildenafil」成分之「威爾剛」禁藥2,050 顆\n    後，隨即將該等禁藥夾藏於電腦螢幕切換器中，於98年7 月\n    2 日以航空郵寄方式自大陸地區輸入，並由陳文賓出具個案\n    委任書，同時於貨運單上填載被告所申設行動電話門號0000\n    000000號作為收貨人聯絡電話，委託不知情之聯邦快遞報關\n    行報關員向財政部臺北關稅局，申報進口上開電腦螢幕切換\n    器貨物1 批，而將上開禁藥運輸入境等情，固為陳文賓於另\n    案偵查中所否認，惟業經李訓達於偵查中供述明確（見偵三\n    卷第129 至134 頁），且有卷附個案委任書、行政院衛生署\n    98年8 月5 日衛署藥字第0980021480號函覆說明、行政院衛\n    生署藥物食品檢驗局98年7 月23日藥檢壹字第0980014594號\n    函覆說明暨檢驗報告書、貨運單、航空警察局安全檢察隊X\n    光檢查儀注檢貨物報告表等件可佐（見偵三卷第12至13頁、\n    第26至29頁、第33頁、第36至38頁），是以，被告前開行動\n    電話門號0000000000號、0000000000號分別遭利用作為詐欺\n    取財、輸入禁藥等犯罪使用之事實，應均可認定。\n(二)、至被告就其申辦系爭行動電話門號之原因一節，雖稱係因友\n    人不慎將其所慣用之行動電話門號留存於地檢署，其擔心司\n    法機關追蹤其行蹤，始另行申辦系爭行動電話門號云云，然\n    審之被告既已慮及司法機關可能經由行動電話門號追蹤其行\n    蹤之情，衡諸常理，其為躲避查緝，理應經由其他管道取得\n    使用他人名義申辦之行動電話門號以作為對外聯絡用途，豈\n    有再度以自己名義申領行動電話門號之理，況且，證人即為\n    被告申請裁判書之友人李玉雲於本院審理時證述：我記得是\n    在我幫被告向地檢署申請裁判書的前一天早上約7 、8 時許\n    ，被告騎機車到我家旁邊的廟旁涼亭內找我喝酒，我便騎被\n    告機車前往他處買米酒，買完酒後，我將酒放置於被告機車\n    前方的置物箱內，當時我看到置物箱內放置有七星牌香菸、\n    包葉檳榔及以透明夾鏈袋裝的2 片晶片卡等物品，回到涼亭\n    後我便與被告一起喝酒，因為我沒有香菸抽，所以被告叫我\n    到機車置物箱去拿煙，我因而發現放置於置物箱內的物品全\n    部不見了，因為喝酒時涼亭內尚有幾名年輕人在場，所以我\n    們想說應該飲酒期間我抱小孩回家去泡牛奶、被告離開涼亭\n    取上廁所時，那幾名年輕人乘機取走上開物品，但我與被告\n    都出去找後均無結果，後來被告認為該遭竊物品價值不高，\n    所以我們就回到涼亭繼續喝酒等語（見本院卷第129  至123\n    頁），固與被告於本院審理時供稱晶片卡遺失當時情形（見\n    本院卷第116 至119 頁），大致相符，然核之被告前稱係因\n    央請友人代為向地檢署申請裁判書時，友人誤將其慣用之行\n    動電話門號留存於申請書內之故，始另行申請本件系爭行動\n    電話門號使用之情，與證人李玉雲上述：晶片卡係伊代被告\n    向地檢署申請裁判書之前1 日遺失等語，顯有極大出入，是\n    以，渠等所述晶片卡遺失情節，是否屬實，自非無疑，再者\n    ，佐之一般人對於日常生活中所發生之事實記憶內容，往往\n    隨時間經過而逐漸淡忘或模糊，此為眾所周知之理，參以被\n    告於警詢時猶稱：不記得曾申辦系爭行動電話門號等語（見\n    偵一卷第74頁），惟至與其申請電話時間相隔年餘之本院審\n    理期日，經隔離被告、證人李玉雲進行訊問後，被告卻能具\n    體陳述：晶片卡遺失當日所嚼食之檳榔是包葉仔，與李玉雲\n    所飲用之酒類為米酒等顯非重要之日常生活細節（見本院卷\n    第118 頁），甚者，就遺失晶片卡當日所發生與其平日生活\n    習性無涉之相關事項，復能具體描述：伊平常所抽香菸品牌\n    為『WEST』，但當日放在機車置物箱與晶片卡同時遺失之香\n    菸則為其他友人贈送之七星牌香菸，晶片卡遺失時係使用透\n    明夾鏈袋包裝，當日在涼亭喝酒時尚有數名年輕人在場，上\n    開物品該等年輕人趁其去上廁所、李玉雲抱小孩回家泡牛奶\n    時偷取云云（見本院卷第117 、119 頁），衡以被告於距離\n    其所稱遺失晶片卡日期較近之警詢時，尚且無從記憶是否曾\n    申領系爭行動電話門號使用之重要事實，然歷經年餘後之本\n    院審理期日時對於晶片卡遺失時諸多不甚重要日常生活細節\n    卻記憶清晰，且與證人李玉雲上開證述內容完全相符，而無\n    出入，此實亦與常情有悖，由此益見被告所辯遺失晶片卡云\n    云，當非可採。此外，參以被告於偵查中供承：迄至98年7\n    月間為止，我仍使用原所申領之行動電話門號0000000000號\n    作為對外聯絡用途等語（見偵一卷第70頁、偵三卷第17頁）\n    ，復佐以被告自承迄今猶未將系爭行動電話門號辦理停話一\n    節（見本院卷第52頁），則被告於申領系爭行動電話門號後\n    ，既依舊使用原行動電話門號作為對外聯絡之工具，而未曾\n    使用系爭行動電話門號，復未將系爭行動電話門號辦理停話\n    ，則其確係將該等行動電話門號交付予他人使用之事實，當\n    可推認。\n(三)、按我國行動電話通信業者對於申辦行動電話門號使用並無特\n    殊資格及使用目的之限制，故凡有正當目的使用行動電話門\n    號之必要者，均可自行前往業者門市或特約經銷處辦請使用\n    ，殊無借用他人名義所申辦行動電話門號使用之理。倘不自\n    行申辦行動電話門號，反無故向他人借用行動電話門號卡使\n    用，依常理得認為其借用他人行動電話門號晶片卡使用之行\n    徑，極可能與財產犯罪密切相關，並藉此規避有犯罪偵查權\n    限之機關循線追查之可能。且現今媒體報導中，或以中獎、\n    退稅、家人遭擄、信用卡款對帳、金融卡密碼外洩、疑似遭\n    人盜領存款、張揚不可告人隱私等事由，利用他人名義所申\n    辦之行動電話門號作為聯繫工具，詐騙被害人至金融機構櫃\n    檯電匯，抑或持金融卡至自動櫃員機依其指示操作，使被害\n    人在不知情之狀況下依指示操作匯出或存入款項後，隨即將\n    之提領一空之詐騙手法，層出不窮，依一般人之智識及社會\n    生活經驗，極易認知收受門號晶片卡者悖於常情未使用自己\n    之門號而使用他人門號，顯為遂行通聯紀錄不易循線追查之\n    目的，自可產生該收受門號晶片卡者係用於不法財產犯罪之\n    認識。本件被告係將系爭行動電話門號交付予他人使用之事\n    實，業如前述，衡以被告係屬高中肄業以及其前揭辯稱變更\n    行動電話門號可逃避警方查緝等內容，足認依被告之智識程\n    度及生活經驗而言，對於行動電話門號交付予他人使用可能\n    遭利用作為財產犯罪用途一節，知之甚詳，是其猶將所申請\n    之系爭行動電話門號提供予不法集團使用，則其確有容認該\n    等門號供他人作為詐欺犯罪時使用之不確定故意，應堪認定\n    。\n(四)、又刑法上之幫助犯，係對於犯罪與正犯有共同之認識，而以\n    幫助之意思，對於正犯資以助力，而未參與實施犯罪之行為\n    者而言，是以如未參與實施犯罪構成要件之行為，而係出於\n    幫助之意思提供助力，即屬幫助犯，而非共同正犯。另幫助\n    犯係從屬於正犯而成立，並無獨立性，故幫助犯須對正犯之\n    犯罪事實，具有共同認識而加以助力，始能成立，其所應負\n    責任，亦以與正犯有同一認識之事實為限，若正犯所犯之事\n    實，超過其共同認識之範圍時，則幫助者事前既不知情，自\n    不負責，而應僅就其所認識之範圍負責（即所犯重於所知，\n    從其所知）。本件被告交付系爭行動電話門號予不法集團後\n    ，該不法集團除利用系爭0000000000號行動電話門號作為遂\n    行犯罪事實欄一(一)、(二)詐欺取財犯行之聯絡工具外，復另將\n    系爭0000000000號行動電話門號交付予李訓達、陳文賓等2\n    人作為遂行犯罪事實欄一(三)輸入禁藥犯行之聯絡工具，俱如\n    前述，惟將行動電話門號交付、出售他人使用，雖有幫助他\n    人為不法行為之不確定故意，然依常情而論，行為人主觀上\n    應只限於認知其所交付行動電話門號，有可能作為於類如詐\n    欺被害人之財產犯罪用途，蓋此為多數犯罪類型，而不及於\n    其他非財產犯罪類型，此外，復查無積極證據可資證明被告\n    對於李訓達、陳文賓等2 人前開輸入禁藥犯行有所認識，是\n    依前述，本件犯罪事實欄一(三)之正犯雖係成立輸入禁藥罪，\n    惟仍應認被告就此僅具幫助詐欺取財之不確定故意，附此敘\n    明。\n(五)、綜上所述，本件被告犯行事證明確，應依法予以論科。\n二、論罪科刑：\n(一)、核被告所為，係犯刑法第30條第1 項前段、第339 條第1項\n    之幫助詐欺取財罪，公訴意旨雖認被告就犯罪事實欄一(三)係\n    犯幫助輸入禁藥罪，惟被告此部分犯行僅具幫助詐欺取財之\n    不確定故意，所犯應為幫助詐欺取財罪，已如前述，因被告\n    所犯之社會基本事實同一，本院自得變更起訴法條。被告以\n    一提供系爭行動電話門號之行為，幫助不法集團成員分別詐\n    取被害人吳憲政、謝智凱之財物及李訓達、陳文賓輸入禁藥\n    ，觸犯數個幫助詐欺取財之罪名，為想像競合犯，應從一重\n    處斷；至檢察官移送併辦之如犯罪事實欄一(二)(三)部分，與本\n    件業經起訴之如犯罪事實欄一(一)部分具有想像競合犯之裁判\n    上一罪關係，自均為起訴效力所及，本院應併予審理；另被\n    告有如犯罪事實欄所載之有期徒刑執行完畢紀錄，有臺灣高\n    等法院被告前案紀錄表在卷可按，其於有期徒刑之執行完畢\n    後5 年內，故意再犯本件有期徒刑以上之罪，為累犯，應依\n    刑法第47條第1 項之規定加重其刑。又被告以幫助他人詐欺\n    取財之意思，參與犯罪構成要件以外之行為，為從犯，應依\n    刑法第30條第2 項規定減輕其刑，並先加重後減輕之。爰審\n    酌被告提供系爭行動電話門號幫助他人遂行犯罪，致使真正\n    犯罪者難以被查獲，助長社會犯罪風氣，行為確實可議，暨\n    兼衡被害人吳憲政、謝智凱因遭詐騙所受損害金額尚屬非鉅\n    ，被告幫助李訓達等人輸入禁藥對社會所造成之潛在危害，\n    以及被告之犯罪目的、手段、智識程度、經濟狀況等一切情\n    狀，量處如主文所示之刑，以資儆懲，併諭知如主文所示之\n    易科罰金折算標準。\n(二)、末按共同正犯因相互間利用他人之行為，以遂行其犯意之實\n    現，本於責任共同之原則，有關沒收部分，對於共犯間供犯\n    罪所用之物，自均應為沒收之諭知，惟幫助犯僅係對於犯罪\n    構成要件以外行為為加工，並無共同犯罪之意思，自不適用\n    該責任共同原則，對於正犯所有供犯罪所用之物或犯罪所得\n    之物，亦為沒收之諭知（參見最高法院91年臺上字第5583號\n    判決意旨）。查犯罪事實欄一(三)所扣案「威爾剛」2,050 顆\n    ，經採樣鑑定後認均屬含有「Sildenafil」西藥成分之藥品\n    ，未經行政院衛生署依藥事法第39條規定核准輸入進口，並\n    無衛生署核發之藥品輸入許可證，為同法第22條第2 款規定\n    之禁藥等情，有卷附前開行政院衛生署98年8 月5 日衛署藥\n    字第098002 1480 號函覆說明、行政院衛生署藥物食品檢驗\n    局98年7 月23日藥檢壹字第0980014594號函覆說明暨檢驗報\n    告書可稽，又上開禁藥固屬犯罪事實欄一(三)輸入禁藥犯行正\n    犯李訓達、陳文賓所用之物，惟被告就該等輸入禁藥犯行既\n    僅提供幫助行為，非屬共同正犯，揆諸上開說明，自無從依\n    刑法第38條規定併為沒收諭知，併此序明。\n據上論斷，應依刑事訴訟法第299 條第1 項前段、第300 條，刑\n法第339 條第1 項、第30條第1 項前段、第2 項、第55條、第47\n條第1 項、第41條第1 項前段，刑法施行法第1 條之1 ，判決如\n主文。\n本案經檢察官鄧藤墩到庭執行職務。\n中    華    民    國     100    年    3   月    24    日\n                  刑事第十八庭  審判長法  官  黃宗揚\n                                      法  官  高瑞聰\n                                      法  官  鄭子文\n以上正本證明與原本無異。\n如不服本判決應於收受判決後10日內向本院提出上訴書狀，並應\n敘述具體理由。其未敘述上訴理由者，應於上訴期間屆滿後20日\n內向本院補提理由書(均須按他造當事人之人數附繕本)「切勿逕\n送上級法院」。"
  },
  "search": "臺灣高雄地方法院刑事判決99年度易字第1882號公訴人臺灣高雄地方法院檢察署檢察官被告李富銘上列被告因詐欺案件，經檢察官提起公訴（臺灣高雄地方法院檢察署98年度偵字第26986號）及移送併辦（臺灣臺南地方法院檢察署99年度偵字第2456號、臺灣桃園地方法院檢察署99年度偵字第1149號），本院判決如下：主文李富銘幫助犯詐欺取財罪，累犯，處有期徒刑月，如易科罰金，以新臺幣壹仟元折算壹日。事實一、李富銘前因恐嚇案件，經臺灣高等法院高雄分院以92年度上易字第1374號判處有期徒刑7月確定，復因違反動產擔保交易法案件，經臺灣臺南地方法院以92年度南簡字第873號判處有期徒刑4月確定，上開二案件之宣告刑經合併定其應執行刑為有期徒刑10月，並於94年6月30日縮刑期滿執行完畢出監。詎猶不知悔改，其可預見一般取得他人行動電話門號使用之行徑，常與財產犯罪所需有密切之關聯，可能係為掩飾不法犯行，避免有偵查犯罪權限之執法人員循線查緝，以確保犯罪所得之不法利益，並掩人耳目。竟基於縱有人以其提供之行動電話門號實施詐欺取財犯行，亦不違背其本意之幫助犯意，而於民國98年5月12日至同年5月24日期間內之某日時許，將其於同年5月12日向和信電訊股份有限公司（下稱和信電訊公司）所申辦門號0000000000號行動電話晶片卡1張及向統一超商所申辦門號0000000000號行動電話晶片卡1張，在不詳地點交付予不法集團成員使用，嗣該不法集團成員隨即使用上開行動電話門號作為犯罪工具，而分別為下列犯行：(一)、不法集團成員基於意圖為自己不法所有之犯意，在露天拍賣網站上佯登「【內行人市場】☆FUJIFILMFinePixF200EXR附8G☆現貨售完為止☆原廠保固☆」之不實拍賣網頁，經吳政憲於98年5月25日上午11時30分許上網瀏覽前揭網頁後，誤信為真而直接上網下標購買，並依上開網頁所刊登聯絡電話即李富銘所申辦前揭行動電話門號0000000000號聯絡賣方，並隨即依不法集團成員所傳送之電話簡訊指示於同日中午12時5分許前往自動櫃員機轉帳買賣價金新臺幣（下同）7,150元至宋韶華（已歿，另經臺灣高雄地方法院檢察署為不起訴處分）所申設華南商業銀行帳號000000000000號帳戶內，隨即遭不法集團成員提領一空，嗣因吳政憲遲未接獲所購買之上開商品而察覺有異，經再度撥打上開行動電話門號後均無人接聽，始覺受騙而報警處理。(二)、不法集團成員另基於意圖為自己不法所有之犯意，在雅虎奇摩拍賣網站上佯登販售諾基亞5800手機之不實拍賣訊息，經謝智凱於98年5月24日下午2時許上網瀏覽前揭網頁後，誤信為真，而依該網頁所刊登聯絡電話即李富銘所申辦前揭行動電話門號0000000000號聯絡賣方進行議價，並隨即依不法集團成員電話指示於同日晚間8時30分許前往設於台南市○○路○段114號永豐銀行自動櫃員機轉帳買賣價金計7,150元至宋韶華上開華南商業銀行帳戶內，隨經不法集團成員提領一空，嗣因謝智凱遲未接獲所購買之上開商品始覺受騙而報警處理。(三)、不法集團成員復於98年5月12日至同年7月2日期間內之某日時許，在不詳地點將上開李富銘所申辦之0000000000號行動電話門號交付予李訓達，李訓達、陳文賓（二人所涉輸入禁藥犯嫌，業經臺灣桃園地方法院檢察署另案偵查）明知「Sildenafil」成分之藥品，依藥事法第39條規定，應向行政院衛生署申請查驗登記，並經核准發給藥品許可證，始得輸入或製造，竟基於未經核准輸入禁藥之犯意聯絡，推由李訓達於98年6、7月間某日向大陸地區年籍不詳自稱「何源」之男子購買含有「Sildenafil」成分之「威爾剛」禁藥共計2,050顆後，隨即將該等禁藥夾藏於電腦螢幕切換器中，於98年7月2日以航空郵寄方式自大陸地區輸入，並由陳文賓出具個案委任書，同時於貨運單上填載李富銘上開行動電話門號作為收貨人聯絡電話，委託不知情之聯邦快遞報關行報關員向財政部臺北關稅局，申報進口上開電腦螢幕切換器貨物1批，而將上開禁藥運輸入境，嗣於98年7月2日上午9時許，經財政部臺北關稅局海關人員於快遞專區查驗貨物時，發現上開夾藏之禁藥並加以查扣，而悉上情。二、案經吳憲政訴由高雄市政府警察局苓雅分局報請臺灣高雄地方法院檢察署檢察官偵查起訴及謝智凱訴由臺南市政府警察局第四分局報請臺灣臺南地方法院檢察署檢察官移送併辦、內政部警政署航空警察隊報請臺灣桃園地方法院檢察署檢察官移送併辦。理由壹、程序方面：按被告以外之人於審判外之陳述，雖不符刑事訴訟法第159條之1至第159條之4之規定，而經當事人於審判程序同意作為證據，法院審酌該言詞陳述或書面陳述作成時之情況，認為適當者，亦得為證據；又當事人、代理人或辯護人於法院調查證據時，知有第159條第1項不得為證據之情形，而未於言詞辯論終結前聲明異議者，視為有前項之同意，刑事訴訟法第159條第1項、第159條之5分別定有明文。查本判決所引用屬於傳聞證據之部分，均已依法踐行調查證據程序，且當事人於審判程序亦同意作為證據，而經本院審酌證據資料作成時之情況，並無違法不當及證明力明顯過低之瑕疵，亦無依法應排除其證據能力之情形，認以之作為證據應屬適當，故自有證據能力。貳、實體方面：一、訊據被告李富銘固坦承行動電話門號0000000000號、0000000000號（下均稱系爭行動電話門號）均係由其申辦之事實，惟矢口否認涉有上開犯行，辯稱：伊前因酒駕案件遭通緝，故委其友人出面代理向地檢署申請裁判書俾以向監理單位辦理註銷罰單，惟因其友人於申請時誤將伊慣用之行動電話門號號碼記載留存於申請書內，伊為避免行蹤暴露，始另行申請上開門號，並將所申領門號晶片卡放置於其機車前方置物箱內，惟於申領後數日內即於台南縣仁德鄉後壁村保安宮附近遭竊，伊並未將上開門號交與不法集團使用云云，經查：(一)、被告於98年5月12日分別向和信電訊公司、統一超商申領行動電話門號0000000000號、0000000000號使用一節，除為被告所不爭執外，尚有卷附和信電訊公司98年10月8日和信（企管）字第09821000237號函附行動電話門號0000000000號申設人資本資料暨申請書影本1份、安源通訊代統一超商函覆行動電話門號0000000000號申設人基本資料暨申請書影本1份可稽（見偵一卷第83至85頁，偵三卷第19頁、第32頁）；又不法集團成員分別於前開網頁刊登不實內容之網路商品拍賣訊息，致被害人吳政憲、謝智凱均陷於錯誤，而於上揭時地分別撥打被告上開所申設行動電話門號0000000000號聯絡不法集團成員，並先後依不法集團成員指示操作自動櫃員機各匯款7,150元至宋韶華所申設華南商業銀行帳號000000000000號帳戶內，隨即遭不法集團成員提領一空，而受詐騙等情，除據證人即被害人吳政憲、謝智凱於警詢時證述明確外（見警一卷第1至2頁，偵一卷第7至8頁），尚有卷附高雄市政府警察局苓雅分局三多路派出所受理詐騙帳戶通報警示簡便格式表、內政部警政署反詐騙案件記錄表、自動櫃員機交易明細表、露天拍賣網頁資料、奇摩拍賣網頁資料、宋韶華之華南銀行帳戶000000000000號開戶印鑑卡暨存款往來明細表等件可憑（見警一卷第9至17頁、第25至26頁，偵一卷第17至19頁、第20至26頁）；另李訓達自不法集團成員取得被告所申設行動電話門號0000000000號後，隨即與陳文賓基於未經核准輸入禁藥之犯意聯絡，推由李訓達於98年6、7月間某日向大陸地區年籍不詳自稱「何源」之男子購買含有上開「Sildenafil」成分之「威爾剛」禁藥2,050顆後，隨即將該等禁藥夾藏於電腦螢幕切換器中，於98年7月2日以航空郵寄方式自大陸地區輸入，並由陳文賓出具個案委任書，同時於貨運單上填載被告所申設行動電話門號0000000000號作為收貨人聯絡電話，委託不知情之聯邦快遞報關行報關員向財政部臺北關稅局，申報進口上開電腦螢幕切換器貨物1批，而將上開禁藥運輸入境等情，固為陳文賓於另案偵查中所否認，惟業經李訓達於偵查中供述明確（見偵三卷第129至134頁），且有卷附個案委任書、行政院衛生署98年8月5日衛署藥字第0980021480號函覆說明、行政院衛生署藥物食品檢驗局98年7月23日藥檢壹字第0980014594號函覆說明暨檢驗報告書、貨運單、航空警察局安全檢察隊X光檢查儀注檢貨物報告表等件可佐（見偵三卷第12至13頁、第26至29頁、第33頁、第36至38頁），是以，被告前開行動電話門號0000000000號、0000000000號分別遭利用作為詐欺取財、輸入禁藥等犯罪使用之事實，應均可認定。(二)、至被告就其申辦系爭行動電話門號之原因一節，雖稱係因友人不慎將其所慣用之行動電話門號留存於地檢署，其擔心司法機關追蹤其行蹤，始另行申辦系爭行動電話門號云云，然審之被告既已慮及司法機關可能經由行動電話門號追蹤其行蹤之情，衡諸常理，其為躲避查緝，理應經由其他管道取得使用他人名義申辦之行動電話門號以作為對外聯絡用途，豈有再度以自己名義申領行動電話門號之理，況且，證人即為被告申請裁判書之友人李玉雲於本院審理時證述：我記得是在我幫被告向地檢署申請裁判書的前一天早上約7、8時許，被告騎機車到我家旁邊的廟旁涼亭內找我喝酒，我便騎被告機車前往他處買米酒，買完酒後，我將酒放置於被告機車前方的置物箱內，當時我看到置物箱內放置有七星牌香菸、包葉檳榔及以透明夾鏈袋裝的2片晶片卡等物品，回到涼亭後我便與被告一起喝酒，因為我沒有香菸抽，所以被告叫我到機車置物箱去拿煙，我因而發現放置於置物箱內的物品全部不見了，因為喝酒時涼亭內尚有幾名年輕人在場，所以我們想說應該飲酒期間我抱小孩回家去泡牛奶、被告離開涼亭取上廁所時，那幾名年輕人乘機取走上開物品，但我與被告都出去找後均無結果，後來被告認為該遭竊物品價值不高，所以我們就回到涼亭繼續喝酒等語（見本院卷第129至123頁），固與被告於本院審理時供稱晶片卡遺失當時情形（見本院卷第116至119頁），大致相符，然核之被告前稱係因央請友人代為向地檢署申請裁判書時，友人誤將其慣用之行動電話門號留存於申請書內之故，始另行申請本件系爭行動電話門號使用之情，與證人李玉雲上述：晶片卡係伊代被告向地檢署申請裁判書之前1日遺失等語，顯有極大出入，是以，渠等所述晶片卡遺失情節，是否屬實，自非無疑，再者，佐之一般人對於日常生活中所發生之事實記憶內容，往往隨時間經過而逐漸淡忘或模糊，此為眾所周知之理，參以被告於警詢時猶稱：不記得曾申辦系爭行動電話門號等語（見偵一卷第74頁），惟至與其申請電話時間相隔年餘之本院審理期日，經隔離被告、證人李玉雲進行訊問後，被告卻能具體陳述：晶片卡遺失當日所嚼食之檳榔是包葉仔，與李玉雲所飲用之酒類為米酒等顯非重要之日常生活細節（見本院卷第118頁），甚者，就遺失晶片卡當日所發生與其平日生活習性無涉之相關事項，復能具體描述：伊平常所抽香菸品牌為『WEST』，但當日放在機車置物箱與晶片卡同時遺失之香菸則為其他友人贈送之七星牌香菸，晶片卡遺失時係使用透明夾鏈袋包裝，當日在涼亭喝酒時尚有數名年輕人在場，上開物品該等年輕人趁其去上廁所、李玉雲抱小孩回家泡牛奶時偷取云云（見本院卷第117、119頁），衡以被告於距離其所稱遺失晶片卡日期較近之警詢時，尚且無從記憶是否曾申領系爭行動電話門號使用之重要事實，然歷經年餘後之本院審理期日時對於晶片卡遺失時諸多不甚重要日常生活細節卻記憶清晰，且與證人李玉雲上開證述內容完全相符，而無出入，此實亦與常情有悖，由此益見被告所辯遺失晶片卡云云，當非可採。此外，參以被告於偵查中供承：迄至98年7月間為止，我仍使用原所申領之行動電話門號0000000000號作為對外聯絡用途等語（見偵一卷第70頁、偵三卷第17頁），復佐以被告自承迄今猶未將系爭行動電話門號辦理停話一節（見本院卷第52頁），則被告於申領系爭行動電話門號後，既依舊使用原行動電話門號作為對外聯絡之工具，而未曾使用系爭行動電話門號，復未將系爭行動電話門號辦理停話，則其確係將該等行動電話門號交付予他人使用之事實，當可推認。(三)、按我國行動電話通信業者對於申辦行動電話門號使用並無特殊資格及使用目的之限制，故凡有正當目的使用行動電話門號之必要者，均可自行前往業者門市或特約經銷處辦請使用，殊無借用他人名義所申辦行動電話門號使用之理。倘不自行申辦行動電話門號，反無故向他人借用行動電話門號卡使用，依常理得認為其借用他人行動電話門號晶片卡使用之行徑，極可能與財產犯罪密切相關，並藉此規避有犯罪偵查權限之機關循線追查之可能。且現今媒體報導中，或以中獎、退稅、家人遭擄、信用卡款對帳、金融卡密碼外洩、疑似遭人盜領存款、張揚不可告人隱私等事由，利用他人名義所申辦之行動電話門號作為聯繫工具，詐騙被害人至金融機構櫃檯電匯，抑或持金融卡至自動櫃員機依其指示操作，使被害人在不知情之狀況下依指示操作匯出或存入款項後，隨即將之提領一空之詐騙手法，層出不窮，依一般人之智識及社會生活經驗，極易認知收受門號晶片卡者悖於常情未使用自己之門號而使用他人門號，顯為遂行通聯紀錄不易循線追查之目的，自可產生該收受門號晶片卡者係用於不法財產犯罪之認識。本件被告係將系爭行動電話門號交付予他人使用之事實，業如前述，衡以被告係屬高中肄業以及其前揭辯稱變更行動電話門號可逃避警方查緝等內容，足認依被告之智識程度及生活經驗而言，對於行動電話門號交付予他人使用可能遭利用作為財產犯罪用途一節，知之甚詳，是其猶將所申請之系爭行動電話門號提供予不法集團使用，則其確有容認該等門號供他人作為詐欺犯罪時使用之不確定故意，應堪認定。(四)、又刑法上之幫助犯，係對於犯罪與正犯有共同之認識，而以幫助之意思，對於正犯資以助力，而未參與實施犯罪之行為者而言，是以如未參與實施犯罪構成要件之行為，而係出於幫助之意思提供助力，即屬幫助犯，而非共同正犯。另幫助犯係從屬於正犯而成立，並無獨立性，故幫助犯須對正犯之犯罪事實，具有共同認識而加以助力，始能成立，其所應負責任，亦以與正犯有同一認識之事實為限，若正犯所犯之事實，超過其共同認識之範圍時，則幫助者事前既不知情，自不負責，而應僅就其所認識之範圍負責（即所犯重於所知，從其所知）。本件被告交付系爭行動電話門號予不法集團後，該不法集團除利用系爭0000000000號行動電話門號作為遂行犯罪事實欄一(一)、(二)詐欺取財犯行之聯絡工具外，復另將系爭0000000000號行動電話門號交付予李訓達、陳文賓等2人作為遂行犯罪事實欄一(三)輸入禁藥犯行之聯絡工具，俱如前述，惟將行動電話門號交付、出售他人使用，雖有幫助他人為不法行為之不確定故意，然依常情而論，行為人主觀上應只限於認知其所交付行動電話門號，有可能作為於類如詐欺被害人之財產犯罪用途，蓋此為多數犯罪類型，而不及於其他非財產犯罪類型，此外，復查無積極證據可資證明被告對於李訓達、陳文賓等2人前開輸入禁藥犯行有所認識，是依前述，本件犯罪事實欄一(三)之正犯雖係成立輸入禁藥罪，惟仍應認被告就此僅具幫助詐欺取財之不確定故意，附此敘明。(五)、綜上所述，本件被告犯行事證明確，應依法予以論科。二、論罪科刑：(一)、核被告所為，係犯刑法第30條第1項前段、第339條第1項之幫助詐欺取財罪，公訴意旨雖認被告就犯罪事實欄一(三)係犯幫助輸入禁藥罪，惟被告此部分犯行僅具幫助詐欺取財之不確定故意，所犯應為幫助詐欺取財罪，已如前述，因被告所犯之社會基本事實同一，本院自得變更起訴法條。被告以一提供系爭行動電話門號之行為，幫助不法集團成員分別詐取被害人吳憲政、謝智凱之財物及李訓達、陳文賓輸入禁藥，觸犯數個幫助詐欺取財之罪名，為想像競合犯，應從一重處斷；至檢察官移送併辦之如犯罪事實欄一(二)(三)部分，與本件業經起訴之如犯罪事實欄一(一)部分具有想像競合犯之裁判上一罪關係，自均為起訴效力所及，本院應併予審理；另被告有如犯罪事實欄所載之有期徒刑執行完畢紀錄，有臺灣高等法院被告前案紀錄表在卷可按，其於有期徒刑之執行完畢後5年內，故意再犯本件有期徒刑以上之罪，為累犯，應依刑法第47條第1項之規定加重其刑。又被告以幫助他人詐欺取財之意思，參與犯罪構成要件以外之行為，為從犯，應依刑法第30條第2項規定減輕其刑，並先加重後減輕之。爰審酌被告提供系爭行動電話門號幫助他人遂行犯罪，致使真正犯罪者難以被查獲，助長社會犯罪風氣，行為確實可議，暨兼衡被害人吳憲政、謝智凱因遭詐騙所受損害金額尚屬非鉅，被告幫助李訓達等人輸入禁藥對社會所造成之潛在危害，以及被告之犯罪目的、手段、智識程度、經濟狀況等一切情狀，量處如主文所示之刑，以資儆懲，併諭知如主文所示之易科罰金折算標準。(二)、末按共同正犯因相互間利用他人之行為，以遂行其犯意之實現，本於責任共同之原則，有關沒收部分，對於共犯間供犯罪所用之物，自均應為沒收之諭知，惟幫助犯僅係對於犯罪構成要件以外行為為加工，並無共同犯罪之意思，自不適用該責任共同原則，對於正犯所有供犯罪所用之物或犯罪所得之物，亦為沒收之諭知（參見最高法院91年臺上字第5583號判決意旨）。查犯罪事實欄一(三)所扣案「威爾剛」2,050顆，經採樣鑑定後認均屬含有「Sildenafil」西藥成分之藥品，未經行政院衛生署依藥事法第39條規定核准輸入進口，並無衛生署核發之藥品輸入許可證，為同法第22條第2款規定之禁藥等情，有卷附前開行政院衛生署98年8月5日衛署藥字第0980021480號函覆說明、行政院衛生署藥物食品檢驗局98年7月23日藥檢壹字第0980014594號函覆說明暨檢驗報告書可稽，又上開禁藥固屬犯罪事實欄一(三)輸入禁藥犯行正犯李訓達、陳文賓所用之物，惟被告就該等輸入禁藥犯行既僅提供幫助行為，非屬共同正犯，揆諸上開說明，自無從依刑法第38條規定併為沒收諭知，併此序明。據上論斷，應依刑事訴訟法第299條第1項前段、第300條，刑法第339條第1項、第30條第1項前段、第2項、第55條、第47條第1項、第41條第1項前段，刑法施行法第1條之1，判決如主文。本案經檢察官鄧藤墩到庭執行職務。中華民國100年3月24日刑事第十八庭審判長法官黃宗揚法官高瑞聰法官鄭子文以上正本證明與原本無異。如不服本判決應於收受判決後10日內向本院提出上訴書狀，並應敘述具體理由。其未敘述上訴理由者，應於上訴期間屆滿後20日內向本院補提理由書(均須按他造當事人之人數附繕本)「切勿逕送上級法院」。中華民國100年3月24日書記官王立山附錄本案論罪科刑法條：中華民國刑法第339條（普通詐欺罪）意圖為自己或第三人不法之所有，以詐術使人將本人或第三人之物交付者，處5年以下有期徒刑、拘役或科或併科1千元以下罰金。以前項方法得財產上不法之利益或使第三人得之者，亦同。前二項之未遂犯罰之。",
  "characters": {
    "judges": [
      "黃宗揚",
      "高瑞聰",
      "鄭子文"
    ],
    "prosecutors": [
      "鄧藤墩"
    ],
    "lawyers": [

    ],
    "clerks": [
      "王立山"
    ],
    "plaintiffs": [

    ],
    "defendants": [
      "李富銘"
    ],
    "prosecutor_office": [
      "臺灣高雄地方法院檢察署檢察官"
    ],
    "creditors": [

    ],
    "debtors": [

    ],
    "judicial_associate_officer": [

    ]
  },
  "adjudged_at": "2011-03-24",
  "created_at": "2016-02-13 21:25:44",
  "updated_at": "2016-02-13 21:25:44"
}