{
  "identify": "KSD-99-訴-166-20110325-1",
  "court": {
    "name": "臺灣高雄地方法院",
    "code": "KSD"
  },
  "division": {
    "name": "刑事",
    "code": "M"
  },
  "year": 99,
  "word": "訴",
  "number": "166",
  "jcheck": "1",
  "reason": "違反臺灣地區與大陸地區人民關係條例等",
  "content": "臺灣高雄地方法院刑事裁定               99年度訴字第166號\n公  訴  人  臺灣高雄地方法院檢察署檢察官\n被      告  陳兆明\n被      告  方彥興\n被      告  曾昭銘\n被      告  涂豐\n上列被告因違反臺灣地區與大陸地區人民關係條例等案件，本院\n裁定如下：\n    主  文\n本件由受命法官獨任逕以簡易判決處刑。\n    理  由\n一、本件被告陳兆明、方彥興、曾昭銘、涂豐因違反臺灣地區\n    與大陸地區人民關係條例等案件，經檢察官依通常程序起訴\n    ，而被告自白犯罪，本院認為宜由受命法官獨任逕以簡易判\n    決處刑。\n二、依刑事訴訟法第220條、第449條第2項，裁定如主文。\n中    華    民    國   100    年    3     月    25    日\n                  刑事第十四庭  審判長法  官  陳銘珠\n                                      法  官  李俊霖\n                                      法  官  謝琬萍\n以上正本證明與原本無異。\n不得抗告。\n中    華    民    國   100    年    3     月    25    日\n                                      書記官 陳玉娥",
  "structure": {
    "main": "本件由受命法官獨任逕以簡易判決處刑。",
    "reason": "一、本件被告陳兆明、方彥興、曾昭銘、涂豐因違反臺灣地區\n    與大陸地區人民關係條例等案件，經檢察官依通常程序起訴\n    ，而被告自白犯罪，本院認為宜由受命法官獨任逕以簡易判\n    決處刑。\n二、依刑事訴訟法第220條、第449條第2項，裁定如主文。"
  },
  "search": "臺灣高雄地方法院刑事裁定99年度訴字第166號公訴人臺灣高雄地方法院檢察署檢察官被告陳兆明被告方彥興被告曾昭銘被告涂豐上列被告因違反臺灣地區與大陸地區人民關係條例等案件，本院裁定如下：主文本件由受命法官獨任逕以簡易判決處刑。理由一、本件被告陳兆明、方彥興、曾昭銘、涂豐因違反臺灣地區與大陸地區人民關係條例等案件，經檢察官依通常程序起訴，而被告自白犯罪，本院認為宜由受命法官獨任逕以簡易判決處刑。二、依刑事訴訟法第220條、第449條第2項，裁定如主文。中華民國100年3月25日刑事第十四庭審判長法官陳銘珠法官李俊霖法官謝琬萍以上正本證明與原本無異。不得抗告。中華民國100年3月25日書記官陳玉娥",
  "characters": {
    "judges": [
      "陳銘珠",
      "李俊霖",
      "謝琬萍"
    ],
    "prosecutors": [

    ],
    "lawyers": [

    ],
    "clerks": [

    ],
    "plaintiffs": [

    ],
    "defendants": [
      "陳兆明",
      "被      告  方彥興",
      "被      告  曾昭銘",
      "被      告  涂豐"
    ],
    "prosecutor_office": [
      "臺灣高雄地方法院檢察署檢察官"
    ],
    "creditors": [

    ],
    "debtors": [

    ],
    "judicial_associate_officer": [

    ]
  },
  "adjudged_at": "2011-03-25",
  "created_at": "2016-02-13 21:05:42",
  "updated_at": "2016-02-13 21:05:42"
}