{
  "identify": "TCD-100-訴-488-20110324-1",
  "court": {
    "name": "臺灣臺中地方法院",
    "code": "TCD"
  },
  "division": {
    "name": "刑事",
    "code": "M"
  },
  "year": 100,
  "word": "訴",
  "number": "488",
  "jcheck": "1",
  "reason": "毒品危害防制條例",
  "content": "臺灣臺中地方法院刑事判決              100年度訴字第488號\n公  訴  人  臺灣臺中地方法院檢察署檢察官\n被      告  廖良啟\n上列被告因施用毒品案件，經檢察官提起公訴(100年度毒偵字第\n140號)，被告於本院準備程序進行中就被訴事實為有罪之陳述，\n經本院合議庭裁定由受命法官獨任進行簡式審判程序，判決如下\n：\n    主  文\n廖良啟施用第一級毒品，累犯，處有期徒刑玖月。\n    犯罪事實及理由\n一、犯罪事實：\n(一)廖良啟前於民國96年間因施用毒品案件，經本院裁定送觀察\n    、勒戒後，認無繼續施用毒品之傾向，於97年3月18日觀察\n    、勒戒執行完畢釋放；同年又因詐欺案件，經本院以96年度\n    易字第1855號判處有期徒刑3月確定，於97年5月26日執行完\n    畢。仍不知悔改，無法戒除毒癮，復基於施用第一級毒品海\n    洛因之犯意，於99年11月9日下午2時許，在其位於臺中縣神\n    岡鄉 (已於99年12月25日改制為臺中市神岡區○○○路575巷\n    87號住處內，以將海洛因摻水稀釋後，再以針筒注射入人體\n    之方式，施用第一級毒品海洛因1次。嗣於99年11月12日上\n    午9時許，為警持臺灣臺中地方法院檢察署檢察官核發之強\n    制採驗尿液許可書至其上址住處，將其帶回警局採集尿液送\n    驗，結果呈現嗎啡(海洛因進入人體後水解之反應)陽性反應\n    ，始查悉上情。\n(二)案經臺中縣警察局豐原分局 (已於99年12月25日改制為臺中\n    市政府警察局豐原分局)報請臺灣臺中地方法院檢察署檢察\n    官偵查起訴。\n二、理由：\n(一)本案被告廖良啟所犯係死刑、無期徒刑、最輕本刑為3年以\n    上有期徒刑以外之罪，被告於準備程序中就被訴事實為有罪\n    之陳述，經告知簡式審判程序之旨，並聽取公訴人及被告之\n    意見後，本院合議庭認為適宜而依刑事訴訟法第273條之1第\n    1項規定，裁定由受命法官獨任進行簡式審判程序，且依同\n    法第273條之2、第159條第2項之規定，不適用傳聞法則有關\n    限制證據能力之相關規定，合先敘明。\n(二)據以論罪之證據名稱：\n    1.被告廖良啟於本院準備程序時之自白。\n    2.臺灣臺中地方法院檢察署檢察官強制到場(強制採驗尿液)\n      許可書、應受尿液採驗人尿液檢體採集送驗紀錄表、中山\n      醫學大學附設醫院檢驗科藥物檢測中心尿液檢驗報告各1\n      紙。\n    3.臺灣臺中地方法院檢察署刑案資料查註紀錄表、臺灣高等\n      法院被告前案紀錄表各1份。\n    4.綜上各節相互佐證，被告自白核與事實相符，應堪採信，\n      本案事證明確，被告犯行堪以認定，應予依法論科。\n(三)論罪與量刑：\n    1.按海洛因為毒品危害防制條例第2條第2項第1款所明定之\n      第一級毒品。核被告廖良啟所為，係犯毒品危害防制條例\n      第10條第1項之施用第一級毒品罪。被告為供己施用而於\n      施用前持有第一級毒品之低度行為，為其施用之高度行為\n      所吸收，不另論罪。\n    2.查被告有如犯罪事實欄所載論罪科刑執行情形，有卷附臺\n      灣高等法院被告前案紀錄表1份可按，其受有期徒刑執行\n      完畢後5年以內再故意犯本案法定刑為有期徒刑之罪，為\n      累犯，應依刑法第47條第1項規定加重其刑。\n    3.爰審酌被告前經觀察、勒戒之執行，又因施用毒品案件，\n      先後經本院以98年度訴字第181號、第1423號、第2831號\n      分別判處有期徒刑7月、4月、7月、8月，合併定應執行有\n      期徒刑1年9月確定，於99年7月30日假釋交付保護管束，\n      仍未能戒斷其施用毒品之惡習，於保護管束期間猶因施用\n      海洛因再犯本案，無視於毒品對於自身健康之戕害及國家\n      對於杜絕毒品犯罪之禁令，顯未衷心悛悔，漠視法令之禁\n      制，惟兼衡酌其施用海洛因所生危害實以自戕健康為主，\n      於他人尚無明顯重大危害，及犯後終能供認無隱，態度尚\n      佳等一切情狀，量處如主文所示之刑。\n三、應適用之法條：\n    依刑事訴訟法第273條之1第1項、第299條第1項前段、第310\n    條之2、第454條，毒品危害防制條例第10條第1項，刑法第1\n    1條前段、第47條第1項，判決如主文。\n本案經檢察官陳永豐到庭執行職務。\n中    華    民    國   100    年    3     月    24    日\n                  刑事第十七庭    法  官  簡芳潔\n以上正本證明與原本無異。\n如不服本判決應於收受送達後10日內向本院提出上訴書狀，並應\n敘述具體理由；其未敘述上訴理由者，應於上訴期間屆滿後20日\n內向本院補提理由書（均須按他造當事人之人數附繕本）「切勿\n逕送上級法院」。\n                                  書記官  余怜儀\n中    華    民    國   100    年    3     月    24    日\n附錄論罪科刑法條全文：\n毒品危害防制條例第10條\n施用第一級毒品者，處6月以上5年以下有期徒刑。\n施用第二級毒品者，處3年以下有期徒刑。",
  "structure": {
    "main": "廖良啟施用第一級毒品，累犯，處有期徒刑玖月。",
    "fact": "一、犯罪事實：\n(一)廖良啟前於民國96年間因施用毒品案件，經本院裁定送觀察\n    、勒戒後，認無繼續施用毒品之傾向，於97年3月18日觀察\n    、勒戒執行完畢釋放；同年又因詐欺案件，經本院以96年度\n    易字第1855號判處有期徒刑3月確定，於97年5月26日執行完\n    畢。仍不知悔改，無法戒除毒癮，復基於施用第一級毒品海\n    洛因之犯意，於99年11月9日下午2時許，在其位於臺中縣神\n    岡鄉 (已於99年12月25日改制為臺中市神岡區○○○路575巷\n    87號住處內，以將海洛因摻水稀釋後，再以針筒注射入人體\n    之方式，施用第一級毒品海洛因1次。嗣於99年11月12日上\n    午9時許，為警持臺灣臺中地方法院檢察署檢察官核發之強\n    制採驗尿液許可書至其上址住處，將其帶回警局採集尿液送\n    驗，結果呈現嗎啡(海洛因進入人體後水解之反應)陽性反應\n    ，始查悉上情。\n(二)案經臺中縣警察局豐原分局 (已於99年12月25日改制為臺中\n    市政府警察局豐原分局)報請臺灣臺中地方法院檢察署檢察\n    官偵查起訴。\n二、理由：\n(一)本案被告廖良啟所犯係死刑、無期徒刑、最輕本刑為3年以\n    上有期徒刑以外之罪，被告於準備程序中就被訴事實為有罪\n    之陳述，經告知簡式審判程序之旨，並聽取公訴人及被告之\n    意見後，本院合議庭認為適宜而依刑事訴訟法第273條之1第\n    1項規定，裁定由受命法官獨任進行簡式審判程序，且依同\n    法第273條之2、第159條第2項之規定，不適用傳聞法則有關\n    限制證據能力之相關規定，合先敘明。\n(二)據以論罪之證據名稱：\n    1.被告廖良啟於本院準備程序時之自白。\n    2.臺灣臺中地方法院檢察署檢察官強制到場(強制採驗尿液)\n      許可書、應受尿液採驗人尿液檢體採集送驗紀錄表、中山\n      醫學大學附設醫院檢驗科藥物檢測中心尿液檢驗報告各1\n      紙。\n    3.臺灣臺中地方法院檢察署刑案資料查註紀錄表、臺灣高等\n      法院被告前案紀錄表各1份。\n    4.綜上各節相互佐證，被告自白核與事實相符，應堪採信，\n      本案事證明確，被告犯行堪以認定，應予依法論科。\n(三)論罪與量刑：\n    1.按海洛因為毒品危害防制條例第2條第2項第1款所明定之\n      第一級毒品。核被告廖良啟所為，係犯毒品危害防制條例\n      第10條第1項之施用第一級毒品罪。被告為供己施用而於\n      施用前持有第一級毒品之低度行為，為其施用之高度行為\n      所吸收，不另論罪。\n    2.查被告有如犯罪事實欄所載論罪科刑執行情形，有卷附臺\n      灣高等法院被告前案紀錄表1份可按，其受有期徒刑執行\n      完畢後5年以內再故意犯本案法定刑為有期徒刑之罪，為\n      累犯，應依刑法第47條第1項規定加重其刑。\n    3.爰審酌被告前經觀察、勒戒之執行，又因施用毒品案件，\n      先後經本院以98年度訴字第181號、第1423號、第2831號\n      分別判處有期徒刑7月、4月、7月、8月，合併定應執行有\n      期徒刑1年9月確定，於99年7月30日假釋交付保護管束，\n      仍未能戒斷其施用毒品之惡習，於保護管束期間猶因施用\n      海洛因再犯本案，無視於毒品對於自身健康之戕害及國家\n      對於杜絕毒品犯罪之禁令，顯未衷心悛悔，漠視法令之禁\n      制，惟兼衡酌其施用海洛因所生危害實以自戕健康為主，\n      於他人尚無明顯重大危害，及犯後終能供認無隱，態度尚\n      佳等一切情狀，量處如主文所示之刑。\n三、應適用之法條：\n    依刑事訴訟法第273條之1第1項、第299條第1項前段、第310\n    條之2、第454條，毒品危害防制條例第10條第1項，刑法第1\n    1條前段、第47條第1項，判決如主文。\n本案經檢察官陳永豐到庭執行職務。",
    "reason": "一、犯罪事實：\n(一)廖良啟前於民國96年間因施用毒品案件，經本院裁定送觀察\n    、勒戒後，認無繼續施用毒品之傾向，於97年3月18日觀察\n    、勒戒執行完畢釋放；同年又因詐欺案件，經本院以96年度\n    易字第1855號判處有期徒刑3月確定，於97年5月26日執行完\n    畢。仍不知悔改，無法戒除毒癮，復基於施用第一級毒品海\n    洛因之犯意，於99年11月9日下午2時許，在其位於臺中縣神\n    岡鄉 (已於99年12月25日改制為臺中市神岡區○○○路575巷\n    87號住處內，以將海洛因摻水稀釋後，再以針筒注射入人體\n    之方式，施用第一級毒品海洛因1次。嗣於99年11月12日上\n    午9時許，為警持臺灣臺中地方法院檢察署檢察官核發之強\n    制採驗尿液許可書至其上址住處，將其帶回警局採集尿液送\n    驗，結果呈現嗎啡(海洛因進入人體後水解之反應)陽性反應\n    ，始查悉上情。\n(二)案經臺中縣警察局豐原分局 (已於99年12月25日改制為臺中\n    市政府警察局豐原分局)報請臺灣臺中地方法院檢察署檢察\n    官偵查起訴。\n二、理由：\n(一)本案被告廖良啟所犯係死刑、無期徒刑、最輕本刑為3年以\n    上有期徒刑以外之罪，被告於準備程序中就被訴事實為有罪\n    之陳述，經告知簡式審判程序之旨，並聽取公訴人及被告之\n    意見後，本院合議庭認為適宜而依刑事訴訟法第273條之1第\n    1項規定，裁定由受命法官獨任進行簡式審判程序，且依同\n    法第273條之2、第159條第2項之規定，不適用傳聞法則有關\n    限制證據能力之相關規定，合先敘明。\n(二)據以論罪之證據名稱：\n    1.被告廖良啟於本院準備程序時之自白。\n    2.臺灣臺中地方法院檢察署檢察官強制到場(強制採驗尿液)\n      許可書、應受尿液採驗人尿液檢體採集送驗紀錄表、中山\n      醫學大學附設醫院檢驗科藥物檢測中心尿液檢驗報告各1\n      紙。\n    3.臺灣臺中地方法院檢察署刑案資料查註紀錄表、臺灣高等\n      法院被告前案紀錄表各1份。\n    4.綜上各節相互佐證，被告自白核與事實相符，應堪採信，\n      本案事證明確，被告犯行堪以認定，應予依法論科。\n(三)論罪與量刑：\n    1.按海洛因為毒品危害防制條例第2條第2項第1款所明定之\n      第一級毒品。核被告廖良啟所為，係犯毒品危害防制條例\n      第10條第1項之施用第一級毒品罪。被告為供己施用而於\n      施用前持有第一級毒品之低度行為，為其施用之高度行為\n      所吸收，不另論罪。\n    2.查被告有如犯罪事實欄所載論罪科刑執行情形，有卷附臺\n      灣高等法院被告前案紀錄表1份可按，其受有期徒刑執行\n      完畢後5年以內再故意犯本案法定刑為有期徒刑之罪，為\n      累犯，應依刑法第47條第1項規定加重其刑。\n    3.爰審酌被告前經觀察、勒戒之執行，又因施用毒品案件，\n      先後經本院以98年度訴字第181號、第1423號、第2831號\n      分別判處有期徒刑7月、4月、7月、8月，合併定應執行有\n      期徒刑1年9月確定，於99年7月30日假釋交付保護管束，\n      仍未能戒斷其施用毒品之惡習，於保護管束期間猶因施用\n      海洛因再犯本案，無視於毒品對於自身健康之戕害及國家\n      對於杜絕毒品犯罪之禁令，顯未衷心悛悔，漠視法令之禁\n      制，惟兼衡酌其施用海洛因所生危害實以自戕健康為主，\n      於他人尚無明顯重大危害，及犯後終能供認無隱，態度尚\n      佳等一切情狀，量處如主文所示之刑。\n三、應適用之法條：\n    依刑事訴訟法第273條之1第1項、第299條第1項前段、第310\n    條之2、第454條，毒品危害防制條例第10條第1項，刑法第1\n    1條前段、第47條第1項，判決如主文。\n本案經檢察官陳永豐到庭執行職務。"
  },
  "search": "臺灣臺中地方法院刑事判決100年度訴字第488號公訴人臺灣臺中地方法院檢察署檢察官被告廖良啟上列被告因施用毒品案件，經檢察官提起公訴(100年度毒偵字第140號)，被告於本院準備程序進行中就被訴事實為有罪之陳述，經本院合議庭裁定由受命法官獨任進行簡式審判程序，判決如下：主文廖良啟施用第一級毒品，累犯，處有期徒刑玖月。犯罪事實及理由一、犯罪事實：(一)廖良啟前於民國96年間因施用毒品案件，經本院裁定送觀察、勒戒後，認無繼續施用毒品之傾向，於97年3月18日觀察、勒戒執行完畢釋放；同年又因詐欺案件，經本院以96年度易字第1855號判處有期徒刑3月確定，於97年5月26日執行完畢。仍不知悔改，無法戒除毒癮，復基於施用第一級毒品海洛因之犯意，於99年11月9日下午2時許，在其位於臺中縣神岡鄉(已於99年12月25日改制為臺中市神岡區○○○路575巷87號住處內，以將海洛因摻水稀釋後，再以針筒注射入人體之方式，施用第一級毒品海洛因1次。嗣於99年11月12日上午9時許，為警持臺灣臺中地方法院檢察署檢察官核發之強制採驗尿液許可書至其上址住處，將其帶回警局採集尿液送驗，結果呈現嗎啡(海洛因進入人體後水解之反應)陽性反應，始查悉上情。(二)案經臺中縣警察局豐原分局(已於99年12月25日改制為臺中市政府警察局豐原分局)報請臺灣臺中地方法院檢察署檢察官偵查起訴。二、理由：(一)本案被告廖良啟所犯係死刑、無期徒刑、最輕本刑為3年以上有期徒刑以外之罪，被告於準備程序中就被訴事實為有罪之陳述，經告知簡式審判程序之旨，並聽取公訴人及被告之意見後，本院合議庭認為適宜而依刑事訴訟法第273條之1第1項規定，裁定由受命法官獨任進行簡式審判程序，且依同法第273條之2、第159條第2項之規定，不適用傳聞法則有關限制證據能力之相關規定，合先敘明。(二)據以論罪之證據名稱：1.被告廖良啟於本院準備程序時之自白。2.臺灣臺中地方法院檢察署檢察官強制到場(強制採驗尿液)許可書、應受尿液採驗人尿液檢體採集送驗紀錄表、中山醫學大學附設醫院檢驗科藥物檢測中心尿液檢驗報告各1紙。3.臺灣臺中地方法院檢察署刑案資料查註紀錄表、臺灣高等法院被告前案紀錄表各1份。4.綜上各節相互佐證，被告自白核與事實相符，應堪採信，本案事證明確，被告犯行堪以認定，應予依法論科。(三)論罪與量刑：1.按海洛因為毒品危害防制條例第2條第2項第1款所明定之第一級毒品。核被告廖良啟所為，係犯毒品危害防制條例第10條第1項之施用第一級毒品罪。被告為供己施用而於施用前持有第一級毒品之低度行為，為其施用之高度行為所吸收，不另論罪。2.查被告有如犯罪事實欄所載論罪科刑執行情形，有卷附臺灣高等法院被告前案紀錄表1份可按，其受有期徒刑執行完畢後5年以內再故意犯本案法定刑為有期徒刑之罪，為累犯，應依刑法第47條第1項規定加重其刑。3.爰審酌被告前經觀察、勒戒之執行，又因施用毒品案件，先後經本院以98年度訴字第181號、第1423號、第2831號分別判處有期徒刑7月、4月、7月、8月，合併定應執行有期徒刑1年9月確定，於99年7月30日假釋交付保護管束，仍未能戒斷其施用毒品之惡習，於保護管束期間猶因施用海洛因再犯本案，無視於毒品對於自身健康之戕害及國家對於杜絕毒品犯罪之禁令，顯未衷心悛悔，漠視法令之禁制，惟兼衡酌其施用海洛因所生危害實以自戕健康為主，於他人尚無明顯重大危害，及犯後終能供認無隱，態度尚佳等一切情狀，量處如主文所示之刑。三、應適用之法條：依刑事訴訟法第273條之1第1項、第299條第1項前段、第310條之2、第454條，毒品危害防制條例第10條第1項，刑法第11條前段、第47條第1項，判決如主文。本案經檢察官陳永豐到庭執行職務。中華民國100年3月24日刑事第十七庭法官簡芳潔以上正本證明與原本無異。如不服本判決應於收受送達後10日內向本院提出上訴書狀，並應敘述具體理由；其未敘述上訴理由者，應於上訴期間屆滿後20日內向本院補提理由書（均須按他造當事人之人數附繕本）「切勿逕送上級法院」。書記官余怜儀中華民國100年3月24日附錄論罪科刑法條全文：毒品危害防制條例第10條施用第一級毒品者，處6月以上5年以下有期徒刑。施用第二級毒品者，處3年以下有期徒刑。",
  "characters": {
    "judges": [
      "簡芳潔"
    ],
    "prosecutors": [
      "陳永豐"
    ],
    "lawyers": [

    ],
    "clerks": [
      "余怜儀"
    ],
    "plaintiffs": [

    ],
    "defendants": [
      "廖良啟"
    ],
    "prosecutor_office": [
      "臺灣臺中地方法院檢察署檢察官"
    ],
    "creditors": [

    ],
    "debtors": [

    ],
    "judicial_associate_officer": [

    ]
  },
  "adjudged_at": "2011-03-24",
  "created_at": "2016-02-13 21:15:17",
  "updated_at": "2016-02-13 21:15:17"
}