{
  "identify": "TPD-100-簡-759-20110325-1",
  "court": {
    "name": "臺灣臺北地方法院",
    "code": "TPD"
  },
  "division": {
    "name": "刑事",
    "code": "M"
  },
  "year": 100,
  "word": "簡",
  "number": "759",
  "jcheck": "1",
  "reason": "傷害",
  "content": "臺灣臺北地方法院刑事簡易判決          100年度簡字第759號\n聲  請  人  臺灣臺北地方法院檢察署檢察官\n被      告  廖志展\n上列被告因傷害案件，經檢察官聲請以簡易判決處刑（99年度偵\n字第26354號），本院判決如下：\n    主  文\n廖志展傷害人之身體，處有期徒刑肆月，如易科罰金，以新臺幣\n壹仟元折算壹日。\n    事實及理由\n一、廖志展係址設臺北市中正區○○○路61號2 樓「東一排骨」\n    餐廳老闆之子，張靖誼則於址設同棟61號5樓之6「臺灣省金\n    銀珠寶商業同業公會聯合會」擔任總幹事。張靖誼於民國99\n    年5月7日12時30分許，返回該大樓1 樓樓梯時，因地面濕滑\n    險些跌到而向該大樓管理員反應，該餐廳員工即與張靖誼發\n    生爭執，廖志展竟基於傷害之犯意，在該處電梯徒手拉扯、\n    推打張靖誼，並以左手手肘撞擊張靖誼胸口，使張靖誼受有\n    右前臂瘀傷、左上臂（聲請簡易判決處刑書誤載為右上臂）\n    瘀傷、前胸瘀傷等傷害。案經張靖誼訴由臺北市政府警察局\n    中正第一局報告臺灣臺北地方法院檢察署檢察官偵查起訴。\n二、訊據被告廖志展對於上揭事實坦承不諱（見本院100年3月14\n    日訊問筆錄第2 頁），核與證人即告訴人張靖誼之證述相符\n    （見臺灣臺北地方法院檢察署99年度偵字第26354號卷第5頁\n    至第7頁及第27頁至第28頁），且有聯合醫院和平院區99年5\n    月10日診斷證明書及臺灣臺北地方法院檢察署100年1 月3日\n    勘驗筆錄附卷可稽（見同上偵卷第9 頁、第32頁至第39頁）\n    ，足證被告任意性自白與事實相符，事證明確，犯行堪以認\n    定，應予依法論科。\n三、核被告所為，係犯刑法第277條第1項之傷害罪。爰審酌被告\n    僅因細故，即在上開大樓住戶得出入之場所，對身高、年齡\n    與之有相當差距而在該大樓任職之告訴人施暴之犯罪動機、\n    手段，告訴人所受傷害之程度，及於偵查中仍矢口否認犯行\n    ，迨於本院訊問時始坦承犯行，然未能與告訴人達成和解等\n    一切情狀，量處如主文所示之刑，並諭知易科罰金之折算標\n    準。\n四、據上論斷，應依刑事訴訟法第449條第1項、第3項，刑法第2\n    77條第1項、第41條第1項前段，刑法施行法第1條之1第1 項\n    、第2項前段，逕以簡易判決處刑如主文。\n五、如不服本判決，得自收受送達之日起10日內向本院提出上訴\n    狀，上訴於本院第二審合議庭（須附繕本）。\n中    華    民    國   100    年    3     月    25    日\n                       刑事第十四庭  法  官  賴武志\n上正本證明與原本無異。\n如不服本判決應於收受送達後10日內向本院提出上訴書狀，上訴\n於本院第二審合議庭，並應敘述具體理由；其未敘述上訴理由者\n，應於上訴期間屆滿後20日內向本院補提理由書（均須按他造當\n事人之人數附繕本）「切勿逕送上級法院」。告訴人或被害人如\n對於本判決不服者，應具備理由請求檢察官上訴，其上訴期間之\n計算係以檢察官收受判決正本之日期為準。\n                                     書記官  劉麗英\n中    華    民    國   100    年    3     月    25    日\n附錄本案論罪科刑法條：\n刑法第277條（普通傷害罪）\n傷害人之身體或健康者，處3年以下有期徒刑、拘役或1千元以下\n罰金。\n犯前項之罪因而致人於死者，處無期徒刑或7 年以上有期徒刑；\n致重傷者，處3年以上10年以下有期徒刑。",
  "structure": {
    "main": "廖志展傷害人之身體，處有期徒刑肆月，如易科罰金，以新臺幣\n壹仟元折算壹日。",
    "fact": "一、廖志展係址設臺北市中正區○○○路61號2 樓「東一排骨」\n    餐廳老闆之子，張靖誼則於址設同棟61號5樓之6「臺灣省金\n    銀珠寶商業同業公會聯合會」擔任總幹事。張靖誼於民國99\n    年5月7日12時30分許，返回該大樓1 樓樓梯時，因地面濕滑\n    險些跌到而向該大樓管理員反應，該餐廳員工即與張靖誼發\n    生爭執，廖志展竟基於傷害之犯意，在該處電梯徒手拉扯、\n    推打張靖誼，並以左手手肘撞擊張靖誼胸口，使張靖誼受有\n    右前臂瘀傷、左上臂（聲請簡易判決處刑書誤載為右上臂）\n    瘀傷、前胸瘀傷等傷害。案經張靖誼訴由臺北市政府警察局\n    中正第一局報告臺灣臺北地方法院檢察署檢察官偵查起訴。\n二、訊據被告廖志展對於上揭事實坦承不諱（見本院100年3月14\n    日訊問筆錄第2 頁），核與證人即告訴人張靖誼之證述相符\n    （見臺灣臺北地方法院檢察署99年度偵字第26354號卷第5頁\n    至第7頁及第27頁至第28頁），且有聯合醫院和平院區99年5\n    月10日診斷證明書及臺灣臺北地方法院檢察署100年1 月3日\n    勘驗筆錄附卷可稽（見同上偵卷第9 頁、第32頁至第39頁）\n    ，足證被告任意性自白與事實相符，事證明確，犯行堪以認\n    定，應予依法論科。\n三、核被告所為，係犯刑法第277條第1項之傷害罪。爰審酌被告\n    僅因細故，即在上開大樓住戶得出入之場所，對身高、年齡\n    與之有相當差距而在該大樓任職之告訴人施暴之犯罪動機、\n    手段，告訴人所受傷害之程度，及於偵查中仍矢口否認犯行\n    ，迨於本院訊問時始坦承犯行，然未能與告訴人達成和解等\n    一切情狀，量處如主文所示之刑，並諭知易科罰金之折算標\n    準。\n四、據上論斷，應依刑事訴訟法第449條第1項、第3項，刑法第2\n    77條第1項、第41條第1項前段，刑法施行法第1條之1第1 項\n    、第2項前段，逕以簡易判決處刑如主文。\n五、如不服本判決，得自收受送達之日起10日內向本院提出上訴\n    狀，上訴於本院第二審合議庭（須附繕本）。",
    "reason": "一、廖志展係址設臺北市中正區○○○路61號2 樓「東一排骨」\n    餐廳老闆之子，張靖誼則於址設同棟61號5樓之6「臺灣省金\n    銀珠寶商業同業公會聯合會」擔任總幹事。張靖誼於民國99\n    年5月7日12時30分許，返回該大樓1 樓樓梯時，因地面濕滑\n    險些跌到而向該大樓管理員反應，該餐廳員工即與張靖誼發\n    生爭執，廖志展竟基於傷害之犯意，在該處電梯徒手拉扯、\n    推打張靖誼，並以左手手肘撞擊張靖誼胸口，使張靖誼受有\n    右前臂瘀傷、左上臂（聲請簡易判決處刑書誤載為右上臂）\n    瘀傷、前胸瘀傷等傷害。案經張靖誼訴由臺北市政府警察局\n    中正第一局報告臺灣臺北地方法院檢察署檢察官偵查起訴。\n二、訊據被告廖志展對於上揭事實坦承不諱（見本院100年3月14\n    日訊問筆錄第2 頁），核與證人即告訴人張靖誼之證述相符\n    （見臺灣臺北地方法院檢察署99年度偵字第26354號卷第5頁\n    至第7頁及第27頁至第28頁），且有聯合醫院和平院區99年5\n    月10日診斷證明書及臺灣臺北地方法院檢察署100年1 月3日\n    勘驗筆錄附卷可稽（見同上偵卷第9 頁、第32頁至第39頁）\n    ，足證被告任意性自白與事實相符，事證明確，犯行堪以認\n    定，應予依法論科。\n三、核被告所為，係犯刑法第277條第1項之傷害罪。爰審酌被告\n    僅因細故，即在上開大樓住戶得出入之場所，對身高、年齡\n    與之有相當差距而在該大樓任職之告訴人施暴之犯罪動機、\n    手段，告訴人所受傷害之程度，及於偵查中仍矢口否認犯行\n    ，迨於本院訊問時始坦承犯行，然未能與告訴人達成和解等\n    一切情狀，量處如主文所示之刑，並諭知易科罰金之折算標\n    準。\n四、據上論斷，應依刑事訴訟法第449條第1項、第3項，刑法第2\n    77條第1項、第41條第1項前段，刑法施行法第1條之1第1 項\n    、第2項前段，逕以簡易判決處刑如主文。\n五、如不服本判決，得自收受送達之日起10日內向本院提出上訴\n    狀，上訴於本院第二審合議庭（須附繕本）。"
  },
  "search": "臺灣臺北地方法院刑事簡易判決100年度簡字第759號聲請人臺灣臺北地方法院檢察署檢察官被告廖志展上列被告因傷害案件，經檢察官聲請以簡易判決處刑（99年度偵字第26354號），本院判決如下：主文廖志展傷害人之身體，處有期徒刑肆月，如易科罰金，以新臺幣壹仟元折算壹日。事實及理由一、廖志展係址設臺北市中正區○○○路61號2樓「東一排骨」餐廳老闆之子，張靖誼則於址設同棟61號5樓之6「臺灣省金銀珠寶商業同業公會聯合會」擔任總幹事。張靖誼於民國99年5月7日12時30分許，返回該大樓1樓樓梯時，因地面濕滑險些跌到而向該大樓管理員反應，該餐廳員工即與張靖誼發生爭執，廖志展竟基於傷害之犯意，在該處電梯徒手拉扯、推打張靖誼，並以左手手肘撞擊張靖誼胸口，使張靖誼受有右前臂瘀傷、左上臂（聲請簡易判決處刑書誤載為右上臂）瘀傷、前胸瘀傷等傷害。案經張靖誼訴由臺北市政府警察局中正第一局報告臺灣臺北地方法院檢察署檢察官偵查起訴。二、訊據被告廖志展對於上揭事實坦承不諱（見本院100年3月14日訊問筆錄第2頁），核與證人即告訴人張靖誼之證述相符（見臺灣臺北地方法院檢察署99年度偵字第26354號卷第5頁至第7頁及第27頁至第28頁），且有聯合醫院和平院區99年5月10日診斷證明書及臺灣臺北地方法院檢察署100年1月3日勘驗筆錄附卷可稽（見同上偵卷第9頁、第32頁至第39頁），足證被告任意性自白與事實相符，事證明確，犯行堪以認定，應予依法論科。三、核被告所為，係犯刑法第277條第1項之傷害罪。爰審酌被告僅因細故，即在上開大樓住戶得出入之場所，對身高、年齡與之有相當差距而在該大樓任職之告訴人施暴之犯罪動機、手段，告訴人所受傷害之程度，及於偵查中仍矢口否認犯行，迨於本院訊問時始坦承犯行，然未能與告訴人達成和解等一切情狀，量處如主文所示之刑，並諭知易科罰金之折算標準。四、據上論斷，應依刑事訴訟法第449條第1項、第3項，刑法第277條第1項、第41條第1項前段，刑法施行法第1條之1第1項、第2項前段，逕以簡易判決處刑如主文。五、如不服本判決，得自收受送達之日起10日內向本院提出上訴狀，上訴於本院第二審合議庭（須附繕本）。中華民國100年3月25日刑事第十四庭法官賴武志上正本證明與原本無異。如不服本判決應於收受送達後10日內向本院提出上訴書狀，上訴於本院第二審合議庭，並應敘述具體理由；其未敘述上訴理由者，應於上訴期間屆滿後20日內向本院補提理由書（均須按他造當事人之人數附繕本）「切勿逕送上級法院」。告訴人或被害人如對於本判決不服者，應具備理由請求檢察官上訴，其上訴期間之計算係以檢察官收受判決正本之日期為準。書記官劉麗英中華民國100年3月25日附錄本案論罪科刑法條：刑法第277條（普通傷害罪）傷害人之身體或健康者，處3年以下有期徒刑、拘役或1千元以下罰金。犯前項之罪因而致人於死者，處無期徒刑或7年以上有期徒刑；致重傷者，處3年以上10年以下有期徒刑。",
  "characters": {
    "judges": [
      "賴武志"
    ],
    "prosecutors": [

    ],
    "lawyers": [

    ],
    "clerks": [
      "劉麗英"
    ],
    "plaintiffs": [

    ],
    "defendants": [
      "廖志展"
    ],
    "prosecutor_office": [
      "臺灣臺北地方法院檢察署檢察官"
    ],
    "creditors": [

    ],
    "debtors": [

    ],
    "judicial_associate_officer": [

    ]
  },
  "adjudged_at": "2011-03-25",
  "created_at": "2016-02-13 21:06:08",
  "updated_at": "2016-02-13 21:06:08"
}