{
  "identify": "ULD-100-偵聲-38-20110324-1",
  "court": {
    "name": "臺灣雲林地方法院",
    "code": "ULD"
  },
  "division": {
    "name": "刑事",
    "code": "M"
  },
  "year": 100,
  "word": "偵聲",
  "number": "38",
  "jcheck": "1",
  "reason": "聲請具保停止羈押",
  "content": "臺灣雲林地方法院刑事裁定             100年度偵聲字第38號\n聲請  人即\n選任辯護人  陳姝樺律師\n被      告  張綾芝\n上列聲請人即被告因詐欺案件（100 年度偵字第621 號），於偵\n查中聲請具保停止羈押，本院裁定如下：\n    主  文\n聲請駁回。\n    理  由\n一、聲請意旨略以：被告業已於警詢及偵查中將相關案情據實陳\n    述，被告無湮滅證據及勾串共犯之可能。且被告目前已懷孕\n    15週左右，因為看守所之環境壓力甚大，且飲食方面因被告\n    初期害喜以致食不下嚥，營養恐怕不足，為避免因葉酸攝取\n    不足會造成胎兒發育不良，爰聲請准予被告具保停止羈押等\n    語。\n二、本件被告張綾芝犯詐欺案件，前經本院認為犯刑法第339 條\n    第1 項之罪，嫌疑重大，有事實足認為有湮滅證據及勾串共\n    犯之虞，並有反覆實施同一犯罪之虞，而有刑事訴訟法第1\n    條第1 項第2 款、第101 條之1 第1 項第7 款之情形，非予\n    羈押，顯難進行追訴，而有羈押之必要，於民國100 年1 月\n    20日執行羈押，並禁止接見通信，並自100 年3 月20日起延\n    長羈押2 月在案，並禁止接見通信。\n三、聲請人雖以前詞聲請具保停止羈押，惟經本院徵詢檢察官之\n    意見，檢察官函覆稱：被告張綾芝原聲請羈押及裁定延長羈\n    押之理由均屬俱在，認仍有羈押之必要等語，有臺灣雲林地\n    方法院檢察署100 年3 月22日雲檢文義100 偵621 字第0812\n    4 號函1 份在卷可按。本院另再函詢法務部矯正署雲林看守\n    所被告之身體狀況，該所函覆稱：被告於100 年2 月14日回\n    診追蹤仍持續用藥治療，至今被告尚無不適症狀，在所期間\n    均定期安排所內特約醫師診療及超音波檢查，目前懷孕15週\n    5 天，身體狀況穩定，現由本所有關人員繼續觀察照護中等\n    情，亦有有法務部矯正署雲林看守所100 年3 月23日雲所衛\n    字第1004000006號函附卷足證。因此，被告雖已懷孕約15週\n    5 天，然按羈押之被告懷胎5 月以上或生產後2 月未滿者，\n    如經具保聲請停止羈押，不得駁回，刑事訴訟法第114 條第\n    2 款定有明文，被告上述情形，仍不符合上開法定應停止羈\n    押之規定，併此敘明。\n四、綜上所述，本案被告之羈押事由及必要性均仍存在，自無從\n    以具保、責付或限制住居等侵害較小之手段代替。聲請人所\n    請聲請具保停止羈押，尚難准許，應予駁回。\n五、依刑事訴訟法第220 條，裁定如主文。\n中    華    民    國   100    年    3     月    24    日\n                  刑事第二庭  法  官  文昌\n以上正本證明與原本無異。\n如不服本裁定，應於裁定送達後5 日內向本院提出抗告狀（須附\n繕本）。\n                              書記官  張簡純靜\n中    華    民    國   100    年    3     月    24    日",
  "structure": {
    "main": "聲請駁回。",
    "reason": "一、聲請意旨略以：被告業已於警詢及偵查中將相關案情據實陳\n    述，被告無湮滅證據及勾串共犯之可能。且被告目前已懷孕\n    15週左右，因為看守所之環境壓力甚大，且飲食方面因被告\n    初期害喜以致食不下嚥，營養恐怕不足，為避免因葉酸攝取\n    不足會造成胎兒發育不良，爰聲請准予被告具保停止羈押等\n    語。\n二、本件被告張綾芝犯詐欺案件，前經本院認為犯刑法第339 條\n    第1 項之罪，嫌疑重大，有事實足認為有湮滅證據及勾串共\n    犯之虞，並有反覆實施同一犯罪之虞，而有刑事訴訟法第1\n    條第1 項第2 款、第101 條之1 第1 項第7 款之情形，非予\n    羈押，顯難進行追訴，而有羈押之必要，於民國100 年1 月\n    20日執行羈押，並禁止接見通信，並自100 年3 月20日起延\n    長羈押2 月在案，並禁止接見通信。\n三、聲請人雖以前詞聲請具保停止羈押，惟經本院徵詢檢察官之\n    意見，檢察官函覆稱：被告張綾芝原聲請羈押及裁定延長羈\n    押之理由均屬俱在，認仍有羈押之必要等語，有臺灣雲林地\n    方法院檢察署100 年3 月22日雲檢文義100 偵621 字第0812\n    4 號函1 份在卷可按。本院另再函詢法務部矯正署雲林看守\n    所被告之身體狀況，該所函覆稱：被告於100 年2 月14日回\n    診追蹤仍持續用藥治療，至今被告尚無不適症狀，在所期間\n    均定期安排所內特約醫師診療及超音波檢查，目前懷孕15週\n    5 天，身體狀況穩定，現由本所有關人員繼續觀察照護中等\n    情，亦有有法務部矯正署雲林看守所100 年3 月23日雲所衛\n    字第1004000006號函附卷足證。因此，被告雖已懷孕約15週\n    5 天，然按羈押之被告懷胎5 月以上或生產後2 月未滿者，\n    如經具保聲請停止羈押，不得駁回，刑事訴訟法第114 條第\n    2 款定有明文，被告上述情形，仍不符合上開法定應停止羈\n    押之規定，併此敘明。\n四、綜上所述，本案被告之羈押事由及必要性均仍存在，自無從\n    以具保、責付或限制住居等侵害較小之手段代替。聲請人所\n    請聲請具保停止羈押，尚難准許，應予駁回。\n五、依刑事訴訟法第220 條，裁定如主文。"
  },
  "search": "臺灣雲林地方法院刑事裁定100年度偵聲字第38號聲請人即選任辯護人陳姝樺律師被告張綾芝上列聲請人即被告因詐欺案件（100年度偵字第621號），於偵查中聲請具保停止羈押，本院裁定如下：主文聲請駁回。理由一、聲請意旨略以：被告業已於警詢及偵查中將相關案情據實陳述，被告無湮滅證據及勾串共犯之可能。且被告目前已懷孕15週左右，因為看守所之環境壓力甚大，且飲食方面因被告初期害喜以致食不下嚥，營養恐怕不足，為避免因葉酸攝取不足會造成胎兒發育不良，爰聲請准予被告具保停止羈押等語。二、本件被告張綾芝犯詐欺案件，前經本院認為犯刑法第339條第1項之罪，嫌疑重大，有事實足認為有湮滅證據及勾串共犯之虞，並有反覆實施同一犯罪之虞，而有刑事訴訟法第1條第1項第2款、第101條之1第1項第7款之情形，非予羈押，顯難進行追訴，而有羈押之必要，於民國100年1月20日執行羈押，並禁止接見通信，並自100年3月20日起延長羈押2月在案，並禁止接見通信。三、聲請人雖以前詞聲請具保停止羈押，惟經本院徵詢檢察官之意見，檢察官函覆稱：被告張綾芝原聲請羈押及裁定延長羈押之理由均屬俱在，認仍有羈押之必要等語，有臺灣雲林地方法院檢察署100年3月22日雲檢文義100偵621字第08124號函1份在卷可按。本院另再函詢法務部矯正署雲林看守所被告之身體狀況，該所函覆稱：被告於100年2月14日回診追蹤仍持續用藥治療，至今被告尚無不適症狀，在所期間均定期安排所內特約醫師診療及超音波檢查，目前懷孕15週5天，身體狀況穩定，現由本所有關人員繼續觀察照護中等情，亦有有法務部矯正署雲林看守所100年3月23日雲所衛字第1004000006號函附卷足證。因此，被告雖已懷孕約15週5天，然按羈押之被告懷胎5月以上或生產後2月未滿者，如經具保聲請停止羈押，不得駁回，刑事訴訟法第114條第2款定有明文，被告上述情形，仍不符合上開法定應停止羈押之規定，併此敘明。四、綜上所述，本案被告之羈押事由及必要性均仍存在，自無從以具保、責付或限制住居等侵害較小之手段代替。聲請人所請聲請具保停止羈押，尚難准許，應予駁回。五、依刑事訴訟法第220條，裁定如主文。中華民國100年3月24日刑事第二庭法官文昌以上正本證明與原本無異。如不服本裁定，應於裁定送達後5日內向本院提出抗告狀（須附繕本）。書記官張簡純靜中華民國100年3月24日",
  "characters": {
    "judges": [
      "文昌"
    ],
    "prosecutors": [

    ],
    "lawyers": [
      "陳姝樺"
    ],
    "clerks": [
      "張簡純靜"
    ],
    "plaintiffs": [

    ],
    "defendants": [
      "張綾芝"
    ],
    "prosecutor_office": [

    ],
    "creditors": [

    ],
    "debtors": [

    ],
    "judicial_associate_officer": [

    ]
  },
  "adjudged_at": "2011-03-24",
  "created_at": "2016-02-13 21:20:22",
  "updated_at": "2016-02-13 21:20:22"
}