{
  "identify": "KLD-100-基交簡-710-20111205-1",
  "court": {
    "name": "臺灣基隆地方法院",
    "code": "KLD"
  },
  "division": {
    "name": "刑事",
    "code": "M"
  },
  "year": 100,
  "word": "基交簡",
  "number": "710",
  "jcheck": "1",
  "reason": "業務過失致死",
  "content": "臺灣基隆地方法院刑事簡易判決      100年度基交簡字第710號\n聲  請  人  臺灣基隆地方法院檢察署檢察官\n被      告  李靆璘\n上列被告因業務過失致死案件，經檢察官聲請以簡易判決處刑（\n100年度偵字第3678號），本院判決如下：\n    主      文\n李靆璘從事業務之人，因業務上之過失致人於死，處有期徒刑壹\n年陸月。緩刑年。\n    事實及理由\n一、李靆璘考領有普通重型機車駕駛執照，平日係以騎駛機車派\n    送報紙為業之送報生，乃從事業務之人。其於民國100 年 7\n    月27日清晨5 時許，騎駛車牌號碼983－JBG號普通重型機車\n    ，沿新北市瑞芳區○○○路由瑞芳往基隆方向行駛，先跨越\n    雙黃實線逆向駛至魚坑路195 之1 號（在基隆往瑞芳方向\n    車道旁）下車遞送報紙，隨即又跨上前揭機車，欲跨越雙黃\n    實線至瑞芳往基隆方向車道往基隆方向行駛，其本應注意起\n    駛前應顯示方向燈，注意前後左右有無車輛，並應讓行進中\n    之車輛優先通行，且應注意汽車在設有慢車道之雙向二車道\n    ，應在遵行車道內行駛，且在劃有分向限制線之路段，不得\n    駛入來車之車道內；依當時天候為晴天，日間有晨光，舖裝\n    柏油之路面乾燥、無缺陷、無障礙物，視距良好，並無不能\n    注意之情事，然其疏未注意及此，在設有分向限制線（雙黃\n    實線）之魚坑路上，由前述195 之1 號路邊貿然起駛，欲\n    先逆向斜斜穿越魚坑路由基隆往瑞芳方向之車道，再跨越\n    雙黃實線至對向車道（即瑞芳往基隆方向）行駛；適有亦領\n    有普通重型機車駕駛執照之謝育泰騎駛車牌號碼988－HLJ號\n    普通重型機車，沿魚坑路由基隆往瑞芳方向直行，見狀煞\n    避不及，二車在魚坑路195 之4 號前方發生碰撞，李靆璘\n    及謝育泰均人車倒地，李靆璘連人帶車倒臥在瑞芳往基隆方\n    向車道上，謝育泰則人車倒臥在基隆往瑞芳方向車道上，因\n    謝育泰於配帶安全帽時並未將安全帽穩固戴在頭上，故其倒\n    地時，安全帽係飛落滾至對向車道（即瑞芳往基隆方向車道\n    ），頭部重創。經警據報到場處理，將謝育泰及李靆璘均送\n    往醫院進行急救，然謝育泰因外傷性蜘蛛網膜下腔出血、外\n    傷性頸動脈假性動脈瘤破裂、敗血症合併疑似急性呼吸窘迫\n    症、心肺衰竭等原因，傷勢過重，經急救數日後，仍於 100\n    年7 月30日9 時9 分心跳停止不治死亡。案經謝育泰之母賴\n    嘉惠訴由新北市政府警察局瑞芳分局報請臺灣基隆地方法院\n    檢察署檢察官偵查後聲請以簡易判決處刑。\n二、證據及理由：\n  (一)上揭犯罪事實，業據被告李靆璘於警詢及偵訊時自承在卷（\n    惟於警詢時陳稱在里長家送完報紙後，係欲迴轉往瑞芳方向\n    行駛），復經證人即在場之周清標於警詢及檢察官偵訊時證\n    述綦詳，且經證人即告訴人賴嘉惠於檢察官偵訊時證述在卷\n    ，並有被告之駕駛執照、行車執照、被害人謝育泰之駕駛執\n    照、行車執照，道路交通事故現場圖、道路交通事故調查報\n    告表(一)(二)、道路交通事故當事人酒精測定紀錄表、基隆長庚\n    紀念醫院血液檢驗報告（二人均無酒精反應）、現場照片17\n    張、基隆長庚紀念醫院診斷證明書、臺灣基隆地方法院檢察\n    署檢驗報告書、相驗屍體證明書、相驗屍體照片12張在卷可\n    稽。\n  (二)按汽車起駛前應顯示方向燈，注意前後左右有無障礙或車輛\n    行人，並應讓行進中之車輛行人優先通行，道路交通安全規\n    則第89條第1 項第6 款定有明文。次按雙黃實線設於路段中\n    ，用以分隔對向車道，並雙向禁止超車、跨越或迴轉；汽車\n    在設有慢車道之雙向二車道行駛時，均應在遵行車道內行駛\n    ，且在劃有分向限制線之路段，不得駛入來車之車道內；道\n    路交通標誌標線號誌設置規則第149 條第1 項第1 款第8 目\n    、道路交通安全規則第97條第2 項、第1 項第1 、2 款分別\n    定有明文。被告為成年領有普通重型機車駕駛執照之人，對\n    於前揭規定顯難諉為不知，其於騎駛機車時，自應遵守前揭\n    規定。查證人周清標於警詢時曾證稱：被告係從瑞芳往基隆\n    方向車道直接橫越道路過來，從伊住家（195 號）前經過，\n    要送隔壁195 之1 號（里長家）之報紙，她下車後，將報紙\n    扔下，伊聽到她加足油門往外騎之聲音，一下子就聽到碰的\n    很大一聲，伊往左前方道路看，二部機車及騎士均倒在地上\n    等語，於偵訊時亦為相同之陳述；而被告於警詢時曾供稱：\n    伊從瑞芳區先送柑坪里，再送三爪子坑路後，沿路送東和里\n    、魚坑里、大寮，再返家休息等語，可見其送報路線應係\n    由瑞芳往基隆方向移動，參酌卷附現場圖及現場照片顯示，\n    魚坑路係設有慢車道之雙向二車道，路面中央有分向限制\n    線（雙黃實線）；被告係在里長住處（195 之1 號）前方起\n    駛，被害人所騎機車之刮地痕係在基隆往瑞芳方向車道上接\n    近雙黃實線處開始往瑞芳方向延伸，被害人人車最後位置係\n    在里長住處（195 之1 號）前方，被告人車最後位置係在對\n    向車道（瑞芳往基隆方向車道），被害人之機車車頭毀損、\n    被告之機車左前側車身毀損等情，可見被告從路旁起駛時，\n    係往左前方（對基隆往瑞芳方向車道而言，已屬逆向）行駛\n    至刮地痕開始處附近與被害人發生碰撞，並因閃避動作及碰\n    撞之作用力致其人車最後位置係在里長住處前方之對向車道\n    上，準此，足認被告在該處送完報紙後，應係有意穿越魚\n    坑路由基隆往瑞芳方向車道，再跨越雙黃實線至對向之瑞芳\n    往基隆方向車道行駛，然其逆向斜斜穿越魚坑路由基隆往\n    瑞芳方向車道，在尚未跨越雙黃實線時，已先與被害人騎駛\n    之機車發生碰撞肇事。依上開卷證資料可知，被告從路旁起\n    駛時，顯然並未先注意前後左右有無車輛，亦未讓行進中之\n    車輛優先通行，由於其係逆向且欲跨越雙黃實線，此等行進\n    方向使正在直行之被害人無法事先反應及時煞避，因而發生\n    本件交通事故。因此，被告就本件事故顯然具有過失甚明，\n    且應就本件事故之發生負全部之肇事責任（亦即就碰撞肇事\n    之原因負全部責任），新北市政府車輛行車事故鑑定委員會\n    提出之鑑定意見，亦認定被告係肇事之唯一原因，而被害人\n    無肇事因素（偵查卷第65至66頁）。惟按機器腳踏車駕駛人\n    及附載座人應依下列規定配戴安全帽：三配帶時安全帽應正\n    面朝前及位置正確，於顎下繫緊扣環，安全帽並應適合頭形\n    ，穩固戴在頭上，不致上下左右晃動，且不可遮蔽視線，道\n    路交通安全規則第88條第2 項第3 款定有明文，前開規定本\n    即在保障機器腳踏車駕駛人之生命、身體安全，降低事故發\n    生時所生之損害。依卷附現場圖及照片觀之，警方至現場處\n    理時，被害人係仰躺在地，頭部未著安全帽，其安全帽係位\n    在對向車道（瑞芳往基隆方向車道）上，距離對向車道之快\n    慢車道分隔線僅1公尺（快車道寬3.7公尺），而被害人仰躺\n    時頭部係壓在雙黃線上，該處留有一灘血跡，客觀跡證顯示\n    被害人之安全帽應係碰撞之際飛落滾至對向車道上，其倒地\n    時頭部並未受到安全帽之保護；準此，足認被害人於騎駛機\n    車時並未將安全帽於顎下繫緊扣環且穩固戴在頭上，於兩車\n    碰撞時，其安全帽飛落，致頭部直接著地受創。而被害人經\n    送醫急救結果，仍因外傷性蜘蛛網膜下腔出血、外傷性頸動\n    脈假性動脈瘤破裂、敗血症合併疑似急性呼吸窘迫症、心肺\n    衰竭等原因，不治死亡；準此可知，被告就上開事故之發生\n    確實有過失，且其過失行為與被害人死亡結果具有因果關係\n    ，然被害人疏未正確佩帶安全帽，對於死亡結果之發生亦與\n    有原因。\n  (三)又按過失致人於死罪之規範目的，係在處罰行為人因個人之\n    過失而致他人死亡之行為，祗以加害人之有過失為致死亡之\n    一原因為已足，不因被害人亦有過失而影響於犯罪之成立（\n    院字第631 號解釋意旨參照），有關被害人與有過失一節，\n    僅係民事賠償責任之過失比例分配問題，並不因此影響被告\n    過失責任有無之認定。本案係被告騎駛機車有重大違規行為\n    ，導致碰撞發生，被害人因而死亡，應由被告就「交通事故\n    之發生」負全部過失責任（被害人僅就死亡結果之發生與有\n    原因），且其係執行派送報紙之業務之際發生上開情形，自\n    應負業務過失致人於死罪之刑事責任。本案事證明確，被告\n    犯行足堪認定。\n三、核被告所為，係犯刑法第276 條第2 項之業務過失致人於死\n    罪。本案係員警至肇事現場處理及詢問附近民眾而確認被告\n    係肇事者等情，有道路交通事故肇事人自首情形紀錄表附卷\n    可憑，是被告尚無刑法第62條自首規定之適用。爰審酌被告\n    於本案前並無任何前科紀錄，有臺灣高等法院被告前案紀錄\n    表存卷可佐，其因一時疏忽肇事，剝奪被害人之寶貴生命，\n    使被害人正值壯年之年輕生命因此逝去；雖被害人未正確佩\n    戴安全帽與有原因，然而，若不是被告有如此重大之違規行\n    為，亦不至於發生本件無法彌補之後果，亦使被害人之家屬\n    承受失去至親之精神上打擊及難以撫平之遺憾暨傷痛，其犯\n    罪所生損害實屬重大；參酌其犯後雖坦承有過失且承認犯罪\n    ，然對於車行方向並未如實陳述，並審酌其事後已與告訴人\n    即被害人之母達成民事和解（參卷附調解筆錄），暨其家中\n    係中低收入戶（參卷附新北市瑞芳區公所中低收入證明書）\n    之生活狀況等一切情狀，量處如主文所示之刑，以資懲儆。\n    又被告係因一時疏忽，致罹刑章，其自身亦因本件交通事故\n    受傷（卷附基隆長庚紀念醫院出具之診斷證明書參照），且\n    其有一名未成年之女兒仍仰賴其扶養（參前揭中低收入證明\n    書及卷附全戶戶籍資料），堪認其經此偵查及審判教訓，當\n    知警惕，信無再犯之虞，本院認前揭所宣告之刑，以暫不執\n    行為適當，爰併諭知緩刑3 年，以勵自新。\n四、依刑事訴訟法第449 條第1 項，刑法第276 條第2 項、第74\n    條第1 項第1 款，刑法施行法第1 條之1 第1 項、第2 項前\n    段，逕以簡易判決處刑如主文。\n五、自簡易判決送達之日起10日內，得向本院提起上訴（須附繕\n    本）。\n中    華    民    國   100    年    12    月    5     日\n                  基隆簡易庭  法  官  張婷妮\n以上正本證明與原本無異。\n如不服本判決，應於判決送達後10日內，向本院提出上訴書狀，\n敘述上訴理由，上訴於本院合議庭，並按他造當事人之人數附具\n繕本。\n中    華    民    國   100    年    12    月    5     日\n                              書記官  連懿婷\n附錄本案論罪科刑法條\n中華民國刑法第276條第2項\n從事業務之人，因業務上之過失犯前項之罪者，處五年以下有期\n徒刑或拘役，得併科三千元以下罰金。",
  "structure": {
    "main": "李靆璘從事業務之人，因業務上之過失致人於死，處有期徒刑壹\n年陸月。緩刑年。",
    "fact": "一、李靆璘考領有普通重型機車駕駛執照，平日係以騎駛機車派\n    送報紙為業之送報生，乃從事業務之人。其於民國100 年 7\n    月27日清晨5 時許，騎駛車牌號碼983－JBG號普通重型機車\n    ，沿新北市瑞芳區○○○路由瑞芳往基隆方向行駛，先跨越\n    雙黃實線逆向駛至魚坑路195 之1 號（在基隆往瑞芳方向\n    車道旁）下車遞送報紙，隨即又跨上前揭機車，欲跨越雙黃\n    實線至瑞芳往基隆方向車道往基隆方向行駛，其本應注意起\n    駛前應顯示方向燈，注意前後左右有無車輛，並應讓行進中\n    之車輛優先通行，且應注意汽車在設有慢車道之雙向二車道\n    ，應在遵行車道內行駛，且在劃有分向限制線之路段，不得\n    駛入來車之車道內；依當時天候為晴天，日間有晨光，舖裝\n    柏油之路面乾燥、無缺陷、無障礙物，視距良好，並無不能\n    注意之情事，然其疏未注意及此，在設有分向限制線（雙黃\n    實線）之魚坑路上，由前述195 之1 號路邊貿然起駛，欲\n    先逆向斜斜穿越魚坑路由基隆往瑞芳方向之車道，再跨越\n    雙黃實線至對向車道（即瑞芳往基隆方向）行駛；適有亦領\n    有普通重型機車駕駛執照之謝育泰騎駛車牌號碼988－HLJ號\n    普通重型機車，沿魚坑路由基隆往瑞芳方向直行，見狀煞\n    避不及，二車在魚坑路195 之4 號前方發生碰撞，李靆璘\n    及謝育泰均人車倒地，李靆璘連人帶車倒臥在瑞芳往基隆方\n    向車道上，謝育泰則人車倒臥在基隆往瑞芳方向車道上，因\n    謝育泰於配帶安全帽時並未將安全帽穩固戴在頭上，故其倒\n    地時，安全帽係飛落滾至對向車道（即瑞芳往基隆方向車道\n    ），頭部重創。經警據報到場處理，將謝育泰及李靆璘均送\n    往醫院進行急救，然謝育泰因外傷性蜘蛛網膜下腔出血、外\n    傷性頸動脈假性動脈瘤破裂、敗血症合併疑似急性呼吸窘迫\n    症、心肺衰竭等原因，傷勢過重，經急救數日後，仍於 100\n    年7 月30日9 時9 分心跳停止不治死亡。案經謝育泰之母賴\n    嘉惠訴由新北市政府警察局瑞芳分局報請臺灣基隆地方法院\n    檢察署檢察官偵查後聲請以簡易判決處刑。\n二、證據及理由：\n  (一)上揭犯罪事實，業據被告李靆璘於警詢及偵訊時自承在卷（\n    惟於警詢時陳稱在里長家送完報紙後，係欲迴轉往瑞芳方向\n    行駛），復經證人即在場之周清標於警詢及檢察官偵訊時證\n    述綦詳，且經證人即告訴人賴嘉惠於檢察官偵訊時證述在卷\n    ，並有被告之駕駛執照、行車執照、被害人謝育泰之駕駛執\n    照、行車執照，道路交通事故現場圖、道路交通事故調查報\n    告表(一)(二)、道路交通事故當事人酒精測定紀錄表、基隆長庚\n    紀念醫院血液檢驗報告（二人均無酒精反應）、現場照片17\n    張、基隆長庚紀念醫院診斷證明書、臺灣基隆地方法院檢察\n    署檢驗報告書、相驗屍體證明書、相驗屍體照片12張在卷可\n    稽。\n  (二)按汽車起駛前應顯示方向燈，注意前後左右有無障礙或車輛\n    行人，並應讓行進中之車輛行人優先通行，道路交通安全規\n    則第89條第1 項第6 款定有明文。次按雙黃實線設於路段中\n    ，用以分隔對向車道，並雙向禁止超車、跨越或迴轉；汽車\n    在設有慢車道之雙向二車道行駛時，均應在遵行車道內行駛\n    ，且在劃有分向限制線之路段，不得駛入來車之車道內；道\n    路交通標誌標線號誌設置規則第149 條第1 項第1 款第8 目\n    、道路交通安全規則第97條第2 項、第1 項第1 、2 款分別\n    定有明文。被告為成年領有普通重型機車駕駛執照之人，對\n    於前揭規定顯難諉為不知，其於騎駛機車時，自應遵守前揭\n    規定。查證人周清標於警詢時曾證稱：被告係從瑞芳往基隆\n    方向車道直接橫越道路過來，從伊住家（195 號）前經過，\n    要送隔壁195 之1 號（里長家）之報紙，她下車後，將報紙\n    扔下，伊聽到她加足油門往外騎之聲音，一下子就聽到碰的\n    很大一聲，伊往左前方道路看，二部機車及騎士均倒在地上\n    等語，於偵訊時亦為相同之陳述；而被告於警詢時曾供稱：\n    伊從瑞芳區先送柑坪里，再送三爪子坑路後，沿路送東和里\n    、魚坑里、大寮，再返家休息等語，可見其送報路線應係\n    由瑞芳往基隆方向移動，參酌卷附現場圖及現場照片顯示，\n    魚坑路係設有慢車道之雙向二車道，路面中央有分向限制\n    線（雙黃實線）；被告係在里長住處（195 之1 號）前方起\n    駛，被害人所騎機車之刮地痕係在基隆往瑞芳方向車道上接\n    近雙黃實線處開始往瑞芳方向延伸，被害人人車最後位置係\n    在里長住處（195 之1 號）前方，被告人車最後位置係在對\n    向車道（瑞芳往基隆方向車道），被害人之機車車頭毀損、\n    被告之機車左前側車身毀損等情，可見被告從路旁起駛時，\n    係往左前方（對基隆往瑞芳方向車道而言，已屬逆向）行駛\n    至刮地痕開始處附近與被害人發生碰撞，並因閃避動作及碰\n    撞之作用力致其人車最後位置係在里長住處前方之對向車道\n    上，準此，足認被告在該處送完報紙後，應係有意穿越魚\n    坑路由基隆往瑞芳方向車道，再跨越雙黃實線至對向之瑞芳\n    往基隆方向車道行駛，然其逆向斜斜穿越魚坑路由基隆往\n    瑞芳方向車道，在尚未跨越雙黃實線時，已先與被害人騎駛\n    之機車發生碰撞肇事。依上開卷證資料可知，被告從路旁起\n    駛時，顯然並未先注意前後左右有無車輛，亦未讓行進中之\n    車輛優先通行，由於其係逆向且欲跨越雙黃實線，此等行進\n    方向使正在直行之被害人無法事先反應及時煞避，因而發生\n    本件交通事故。因此，被告就本件事故顯然具有過失甚明，\n    且應就本件事故之發生負全部之肇事責任（亦即就碰撞肇事\n    之原因負全部責任），新北市政府車輛行車事故鑑定委員會\n    提出之鑑定意見，亦認定被告係肇事之唯一原因，而被害人\n    無肇事因素（偵查卷第65至66頁）。惟按機器腳踏車駕駛人\n    及附載座人應依下列規定配戴安全帽：三配帶時安全帽應正\n    面朝前及位置正確，於顎下繫緊扣環，安全帽並應適合頭形\n    ，穩固戴在頭上，不致上下左右晃動，且不可遮蔽視線，道\n    路交通安全規則第88條第2 項第3 款定有明文，前開規定本\n    即在保障機器腳踏車駕駛人之生命、身體安全，降低事故發\n    生時所生之損害。依卷附現場圖及照片觀之，警方至現場處\n    理時，被害人係仰躺在地，頭部未著安全帽，其安全帽係位\n    在對向車道（瑞芳往基隆方向車道）上，距離對向車道之快\n    慢車道分隔線僅1公尺（快車道寬3.7公尺），而被害人仰躺\n    時頭部係壓在雙黃線上，該處留有一灘血跡，客觀跡證顯示\n    被害人之安全帽應係碰撞之際飛落滾至對向車道上，其倒地\n    時頭部並未受到安全帽之保護；準此，足認被害人於騎駛機\n    車時並未將安全帽於顎下繫緊扣環且穩固戴在頭上，於兩車\n    碰撞時，其安全帽飛落，致頭部直接著地受創。而被害人經\n    送醫急救結果，仍因外傷性蜘蛛網膜下腔出血、外傷性頸動\n    脈假性動脈瘤破裂、敗血症合併疑似急性呼吸窘迫症、心肺\n    衰竭等原因，不治死亡；準此可知，被告就上開事故之發生\n    確實有過失，且其過失行為與被害人死亡結果具有因果關係\n    ，然被害人疏未正確佩帶安全帽，對於死亡結果之發生亦與\n    有原因。\n  (三)又按過失致人於死罪之規範目的，係在處罰行為人因個人之\n    過失而致他人死亡之行為，祗以加害人之有過失為致死亡之\n    一原因為已足，不因被害人亦有過失而影響於犯罪之成立（\n    院字第631 號解釋意旨參照），有關被害人與有過失一節，\n    僅係民事賠償責任之過失比例分配問題，並不因此影響被告\n    過失責任有無之認定。本案係被告騎駛機車有重大違規行為\n    ，導致碰撞發生，被害人因而死亡，應由被告就「交通事故\n    之發生」負全部過失責任（被害人僅就死亡結果之發生與有\n    原因），且其係執行派送報紙之業務之際發生上開情形，自\n    應負業務過失致人於死罪之刑事責任。本案事證明確，被告\n    犯行足堪認定。\n三、核被告所為，係犯刑法第276 條第2 項之業務過失致人於死\n    罪。本案係員警至肇事現場處理及詢問附近民眾而確認被告\n    係肇事者等情，有道路交通事故肇事人自首情形紀錄表附卷\n    可憑，是被告尚無刑法第62條自首規定之適用。爰審酌被告\n    於本案前並無任何前科紀錄，有臺灣高等法院被告前案紀錄\n    表存卷可佐，其因一時疏忽肇事，剝奪被害人之寶貴生命，\n    使被害人正值壯年之年輕生命因此逝去；雖被害人未正確佩\n    戴安全帽與有原因，然而，若不是被告有如此重大之違規行\n    為，亦不至於發生本件無法彌補之後果，亦使被害人之家屬\n    承受失去至親之精神上打擊及難以撫平之遺憾暨傷痛，其犯\n    罪所生損害實屬重大；參酌其犯後雖坦承有過失且承認犯罪\n    ，然對於車行方向並未如實陳述，並審酌其事後已與告訴人\n    即被害人之母達成民事和解（參卷附調解筆錄），暨其家中\n    係中低收入戶（參卷附新北市瑞芳區公所中低收入證明書）\n    之生活狀況等一切情狀，量處如主文所示之刑，以資懲儆。\n    又被告係因一時疏忽，致罹刑章，其自身亦因本件交通事故\n    受傷（卷附基隆長庚紀念醫院出具之診斷證明書參照），且\n    其有一名未成年之女兒仍仰賴其扶養（參前揭中低收入證明\n    書及卷附全戶戶籍資料），堪認其經此偵查及審判教訓，當\n    知警惕，信無再犯之虞，本院認前揭所宣告之刑，以暫不執\n    行為適當，爰併諭知緩刑3 年，以勵自新。\n四、依刑事訴訟法第449 條第1 項，刑法第276 條第2 項、第74\n    條第1 項第1 款，刑法施行法第1 條之1 第1 項、第2 項前\n    段，逕以簡易判決處刑如主文。\n五、自簡易判決送達之日起10日內，得向本院提起上訴（須附繕\n    本）。",
    "reason": "一、李靆璘考領有普通重型機車駕駛執照，平日係以騎駛機車派\n    送報紙為業之送報生，乃從事業務之人。其於民國100 年 7\n    月27日清晨5 時許，騎駛車牌號碼983－JBG號普通重型機車\n    ，沿新北市瑞芳區○○○路由瑞芳往基隆方向行駛，先跨越\n    雙黃實線逆向駛至魚坑路195 之1 號（在基隆往瑞芳方向\n    車道旁）下車遞送報紙，隨即又跨上前揭機車，欲跨越雙黃\n    實線至瑞芳往基隆方向車道往基隆方向行駛，其本應注意起\n    駛前應顯示方向燈，注意前後左右有無車輛，並應讓行進中\n    之車輛優先通行，且應注意汽車在設有慢車道之雙向二車道\n    ，應在遵行車道內行駛，且在劃有分向限制線之路段，不得\n    駛入來車之車道內；依當時天候為晴天，日間有晨光，舖裝\n    柏油之路面乾燥、無缺陷、無障礙物，視距良好，並無不能\n    注意之情事，然其疏未注意及此，在設有分向限制線（雙黃\n    實線）之魚坑路上，由前述195 之1 號路邊貿然起駛，欲\n    先逆向斜斜穿越魚坑路由基隆往瑞芳方向之車道，再跨越\n    雙黃實線至對向車道（即瑞芳往基隆方向）行駛；適有亦領\n    有普通重型機車駕駛執照之謝育泰騎駛車牌號碼988－HLJ號\n    普通重型機車，沿魚坑路由基隆往瑞芳方向直行，見狀煞\n    避不及，二車在魚坑路195 之4 號前方發生碰撞，李靆璘\n    及謝育泰均人車倒地，李靆璘連人帶車倒臥在瑞芳往基隆方\n    向車道上，謝育泰則人車倒臥在基隆往瑞芳方向車道上，因\n    謝育泰於配帶安全帽時並未將安全帽穩固戴在頭上，故其倒\n    地時，安全帽係飛落滾至對向車道（即瑞芳往基隆方向車道\n    ），頭部重創。經警據報到場處理，將謝育泰及李靆璘均送\n    往醫院進行急救，然謝育泰因外傷性蜘蛛網膜下腔出血、外\n    傷性頸動脈假性動脈瘤破裂、敗血症合併疑似急性呼吸窘迫\n    症、心肺衰竭等原因，傷勢過重，經急救數日後，仍於 100\n    年7 月30日9 時9 分心跳停止不治死亡。案經謝育泰之母賴\n    嘉惠訴由新北市政府警察局瑞芳分局報請臺灣基隆地方法院\n    檢察署檢察官偵查後聲請以簡易判決處刑。\n二、證據及理由：\n  (一)上揭犯罪事實，業據被告李靆璘於警詢及偵訊時自承在卷（\n    惟於警詢時陳稱在里長家送完報紙後，係欲迴轉往瑞芳方向\n    行駛），復經證人即在場之周清標於警詢及檢察官偵訊時證\n    述綦詳，且經證人即告訴人賴嘉惠於檢察官偵訊時證述在卷\n    ，並有被告之駕駛執照、行車執照、被害人謝育泰之駕駛執\n    照、行車執照，道路交通事故現場圖、道路交通事故調查報\n    告表(一)(二)、道路交通事故當事人酒精測定紀錄表、基隆長庚\n    紀念醫院血液檢驗報告（二人均無酒精反應）、現場照片17\n    張、基隆長庚紀念醫院診斷證明書、臺灣基隆地方法院檢察\n    署檢驗報告書、相驗屍體證明書、相驗屍體照片12張在卷可\n    稽。\n  (二)按汽車起駛前應顯示方向燈，注意前後左右有無障礙或車輛\n    行人，並應讓行進中之車輛行人優先通行，道路交通安全規\n    則第89條第1 項第6 款定有明文。次按雙黃實線設於路段中\n    ，用以分隔對向車道，並雙向禁止超車、跨越或迴轉；汽車\n    在設有慢車道之雙向二車道行駛時，均應在遵行車道內行駛\n    ，且在劃有分向限制線之路段，不得駛入來車之車道內；道\n    路交通標誌標線號誌設置規則第149 條第1 項第1 款第8 目\n    、道路交通安全規則第97條第2 項、第1 項第1 、2 款分別\n    定有明文。被告為成年領有普通重型機車駕駛執照之人，對\n    於前揭規定顯難諉為不知，其於騎駛機車時，自應遵守前揭\n    規定。查證人周清標於警詢時曾證稱：被告係從瑞芳往基隆\n    方向車道直接橫越道路過來，從伊住家（195 號）前經過，\n    要送隔壁195 之1 號（里長家）之報紙，她下車後，將報紙\n    扔下，伊聽到她加足油門往外騎之聲音，一下子就聽到碰的\n    很大一聲，伊往左前方道路看，二部機車及騎士均倒在地上\n    等語，於偵訊時亦為相同之陳述；而被告於警詢時曾供稱：\n    伊從瑞芳區先送柑坪里，再送三爪子坑路後，沿路送東和里\n    、魚坑里、大寮，再返家休息等語，可見其送報路線應係\n    由瑞芳往基隆方向移動，參酌卷附現場圖及現場照片顯示，\n    魚坑路係設有慢車道之雙向二車道，路面中央有分向限制\n    線（雙黃實線）；被告係在里長住處（195 之1 號）前方起\n    駛，被害人所騎機車之刮地痕係在基隆往瑞芳方向車道上接\n    近雙黃實線處開始往瑞芳方向延伸，被害人人車最後位置係\n    在里長住處（195 之1 號）前方，被告人車最後位置係在對\n    向車道（瑞芳往基隆方向車道），被害人之機車車頭毀損、\n    被告之機車左前側車身毀損等情，可見被告從路旁起駛時，\n    係往左前方（對基隆往瑞芳方向車道而言，已屬逆向）行駛\n    至刮地痕開始處附近與被害人發生碰撞，並因閃避動作及碰\n    撞之作用力致其人車最後位置係在里長住處前方之對向車道\n    上，準此，足認被告在該處送完報紙後，應係有意穿越魚\n    坑路由基隆往瑞芳方向車道，再跨越雙黃實線至對向之瑞芳\n    往基隆方向車道行駛，然其逆向斜斜穿越魚坑路由基隆往\n    瑞芳方向車道，在尚未跨越雙黃實線時，已先與被害人騎駛\n    之機車發生碰撞肇事。依上開卷證資料可知，被告從路旁起\n    駛時，顯然並未先注意前後左右有無車輛，亦未讓行進中之\n    車輛優先通行，由於其係逆向且欲跨越雙黃實線，此等行進\n    方向使正在直行之被害人無法事先反應及時煞避，因而發生\n    本件交通事故。因此，被告就本件事故顯然具有過失甚明，\n    且應就本件事故之發生負全部之肇事責任（亦即就碰撞肇事\n    之原因負全部責任），新北市政府車輛行車事故鑑定委員會\n    提出之鑑定意見，亦認定被告係肇事之唯一原因，而被害人\n    無肇事因素（偵查卷第65至66頁）。惟按機器腳踏車駕駛人\n    及附載座人應依下列規定配戴安全帽：三配帶時安全帽應正\n    面朝前及位置正確，於顎下繫緊扣環，安全帽並應適合頭形\n    ，穩固戴在頭上，不致上下左右晃動，且不可遮蔽視線，道\n    路交通安全規則第88條第2 項第3 款定有明文，前開規定本\n    即在保障機器腳踏車駕駛人之生命、身體安全，降低事故發\n    生時所生之損害。依卷附現場圖及照片觀之，警方至現場處\n    理時，被害人係仰躺在地，頭部未著安全帽，其安全帽係位\n    在對向車道（瑞芳往基隆方向車道）上，距離對向車道之快\n    慢車道分隔線僅1公尺（快車道寬3.7公尺），而被害人仰躺\n    時頭部係壓在雙黃線上，該處留有一灘血跡，客觀跡證顯示\n    被害人之安全帽應係碰撞之際飛落滾至對向車道上，其倒地\n    時頭部並未受到安全帽之保護；準此，足認被害人於騎駛機\n    車時並未將安全帽於顎下繫緊扣環且穩固戴在頭上，於兩車\n    碰撞時，其安全帽飛落，致頭部直接著地受創。而被害人經\n    送醫急救結果，仍因外傷性蜘蛛網膜下腔出血、外傷性頸動\n    脈假性動脈瘤破裂、敗血症合併疑似急性呼吸窘迫症、心肺\n    衰竭等原因，不治死亡；準此可知，被告就上開事故之發生\n    確實有過失，且其過失行為與被害人死亡結果具有因果關係\n    ，然被害人疏未正確佩帶安全帽，對於死亡結果之發生亦與\n    有原因。\n  (三)又按過失致人於死罪之規範目的，係在處罰行為人因個人之\n    過失而致他人死亡之行為，祗以加害人之有過失為致死亡之\n    一原因為已足，不因被害人亦有過失而影響於犯罪之成立（\n    院字第631 號解釋意旨參照），有關被害人與有過失一節，\n    僅係民事賠償責任之過失比例分配問題，並不因此影響被告\n    過失責任有無之認定。本案係被告騎駛機車有重大違規行為\n    ，導致碰撞發生，被害人因而死亡，應由被告就「交通事故\n    之發生」負全部過失責任（被害人僅就死亡結果之發生與有\n    原因），且其係執行派送報紙之業務之際發生上開情形，自\n    應負業務過失致人於死罪之刑事責任。本案事證明確，被告\n    犯行足堪認定。\n三、核被告所為，係犯刑法第276 條第2 項之業務過失致人於死\n    罪。本案係員警至肇事現場處理及詢問附近民眾而確認被告\n    係肇事者等情，有道路交通事故肇事人自首情形紀錄表附卷\n    可憑，是被告尚無刑法第62條自首規定之適用。爰審酌被告\n    於本案前並無任何前科紀錄，有臺灣高等法院被告前案紀錄\n    表存卷可佐，其因一時疏忽肇事，剝奪被害人之寶貴生命，\n    使被害人正值壯年之年輕生命因此逝去；雖被害人未正確佩\n    戴安全帽與有原因，然而，若不是被告有如此重大之違規行\n    為，亦不至於發生本件無法彌補之後果，亦使被害人之家屬\n    承受失去至親之精神上打擊及難以撫平之遺憾暨傷痛，其犯\n    罪所生損害實屬重大；參酌其犯後雖坦承有過失且承認犯罪\n    ，然對於車行方向並未如實陳述，並審酌其事後已與告訴人\n    即被害人之母達成民事和解（參卷附調解筆錄），暨其家中\n    係中低收入戶（參卷附新北市瑞芳區公所中低收入證明書）\n    之生活狀況等一切情狀，量處如主文所示之刑，以資懲儆。\n    又被告係因一時疏忽，致罹刑章，其自身亦因本件交通事故\n    受傷（卷附基隆長庚紀念醫院出具之診斷證明書參照），且\n    其有一名未成年之女兒仍仰賴其扶養（參前揭中低收入證明\n    書及卷附全戶戶籍資料），堪認其經此偵查及審判教訓，當\n    知警惕，信無再犯之虞，本院認前揭所宣告之刑，以暫不執\n    行為適當，爰併諭知緩刑3 年，以勵自新。\n四、依刑事訴訟法第449 條第1 項，刑法第276 條第2 項、第74\n    條第1 項第1 款，刑法施行法第1 條之1 第1 項、第2 項前\n    段，逕以簡易判決處刑如主文。\n五、自簡易判決送達之日起10日內，得向本院提起上訴（須附繕\n    本）。"
  },
  "search": "臺灣基隆地方法院刑事簡易判決100年度基交簡字第710號聲請人臺灣基隆地方法院檢察署檢察官被告李靆璘上列被告因業務過失致死案件，經檢察官聲請以簡易判決處刑（100年度偵字第3678號），本院判決如下：主文李靆璘從事業務之人，因業務上之過失致人於死，處有期徒刑壹年陸月。緩刑年。事實及理由一、李靆璘考領有普通重型機車駕駛執照，平日係以騎駛機車派送報紙為業之送報生，乃從事業務之人。其於民國100年7月27日清晨5時許，騎駛車牌號碼983－JBG號普通重型機車，沿新北市瑞芳區○○○路由瑞芳往基隆方向行駛，先跨越雙黃實線逆向駛至魚坑路195之1號（在基隆往瑞芳方向車道旁）下車遞送報紙，隨即又跨上前揭機車，欲跨越雙黃實線至瑞芳往基隆方向車道往基隆方向行駛，其本應注意起駛前應顯示方向燈，注意前後左右有無車輛，並應讓行進中之車輛優先通行，且應注意汽車在設有慢車道之雙向二車道，應在遵行車道內行駛，且在劃有分向限制線之路段，不得駛入來車之車道內；依當時天候為晴天，日間有晨光，舖裝柏油之路面乾燥、無缺陷、無障礙物，視距良好，並無不能注意之情事，然其疏未注意及此，在設有分向限制線（雙黃實線）之魚坑路上，由前述195之1號路邊貿然起駛，欲先逆向斜斜穿越魚坑路由基隆往瑞芳方向之車道，再跨越雙黃實線至對向車道（即瑞芳往基隆方向）行駛；適有亦領有普通重型機車駕駛執照之謝育泰騎駛車牌號碼988－HLJ號普通重型機車，沿魚坑路由基隆往瑞芳方向直行，見狀煞避不及，二車在魚坑路195之4號前方發生碰撞，李靆璘及謝育泰均人車倒地，李靆璘連人帶車倒臥在瑞芳往基隆方向車道上，謝育泰則人車倒臥在基隆往瑞芳方向車道上，因謝育泰於配帶安全帽時並未將安全帽穩固戴在頭上，故其倒地時，安全帽係飛落滾至對向車道（即瑞芳往基隆方向車道），頭部重創。經警據報到場處理，將謝育泰及李靆璘均送往醫院進行急救，然謝育泰因外傷性蜘蛛網膜下腔出血、外傷性頸動脈假性動脈瘤破裂、敗血症合併疑似急性呼吸窘迫症、心肺衰竭等原因，傷勢過重，經急救數日後，仍於100年7月30日9時9分心跳停止不治死亡。案經謝育泰之母賴嘉惠訴由新北市政府警察局瑞芳分局報請臺灣基隆地方法院檢察署檢察官偵查後聲請以簡易判決處刑。二、證據及理由：(一)上揭犯罪事實，業據被告李靆璘於警詢及偵訊時自承在卷（惟於警詢時陳稱在里長家送完報紙後，係欲迴轉往瑞芳方向行駛），復經證人即在場之周清標於警詢及檢察官偵訊時證述綦詳，且經證人即告訴人賴嘉惠於檢察官偵訊時證述在卷，並有被告之駕駛執照、行車執照、被害人謝育泰之駕駛執照、行車執照，道路交通事故現場圖、道路交通事故調查報告表(一)(二)、道路交通事故當事人酒精測定紀錄表、基隆長庚紀念醫院血液檢驗報告（二人均無酒精反應）、現場照片17張、基隆長庚紀念醫院診斷證明書、臺灣基隆地方法院檢察署檢驗報告書、相驗屍體證明書、相驗屍體照片12張在卷可稽。(二)按汽車起駛前應顯示方向燈，注意前後左右有無障礙或車輛行人，並應讓行進中之車輛行人優先通行，道路交通安全規則第89條第1項第6款定有明文。次按雙黃實線設於路段中，用以分隔對向車道，並雙向禁止超車、跨越或迴轉；汽車在設有慢車道之雙向二車道行駛時，均應在遵行車道內行駛，且在劃有分向限制線之路段，不得駛入來車之車道內；道路交通標誌標線號誌設置規則第149條第1項第1款第8目、道路交通安全規則第97條第2項、第1項第1、2款分別定有明文。被告為成年領有普通重型機車駕駛執照之人，對於前揭規定顯難諉為不知，其於騎駛機車時，自應遵守前揭規定。查證人周清標於警詢時曾證稱：被告係從瑞芳往基隆方向車道直接橫越道路過來，從伊住家（195號）前經過，要送隔壁195之1號（里長家）之報紙，她下車後，將報紙扔下，伊聽到她加足油門往外騎之聲音，一下子就聽到碰的很大一聲，伊往左前方道路看，二部機車及騎士均倒在地上等語，於偵訊時亦為相同之陳述；而被告於警詢時曾供稱：伊從瑞芳區先送柑坪里，再送三爪子坑路後，沿路送東和里、魚坑里、大寮，再返家休息等語，可見其送報路線應係由瑞芳往基隆方向移動，參酌卷附現場圖及現場照片顯示，魚坑路係設有慢車道之雙向二車道，路面中央有分向限制線（雙黃實線）；被告係在里長住處（195之1號）前方起駛，被害人所騎機車之刮地痕係在基隆往瑞芳方向車道上接近雙黃實線處開始往瑞芳方向延伸，被害人人車最後位置係在里長住處（195之1號）前方，被告人車最後位置係在對向車道（瑞芳往基隆方向車道），被害人之機車車頭毀損、被告之機車左前側車身毀損等情，可見被告從路旁起駛時，係往左前方（對基隆往瑞芳方向車道而言，已屬逆向）行駛至刮地痕開始處附近與被害人發生碰撞，並因閃避動作及碰撞之作用力致其人車最後位置係在里長住處前方之對向車道上，準此，足認被告在該處送完報紙後，應係有意穿越魚坑路由基隆往瑞芳方向車道，再跨越雙黃實線至對向之瑞芳往基隆方向車道行駛，然其逆向斜斜穿越魚坑路由基隆往瑞芳方向車道，在尚未跨越雙黃實線時，已先與被害人騎駛之機車發生碰撞肇事。依上開卷證資料可知，被告從路旁起駛時，顯然並未先注意前後左右有無車輛，亦未讓行進中之車輛優先通行，由於其係逆向且欲跨越雙黃實線，此等行進方向使正在直行之被害人無法事先反應及時煞避，因而發生本件交通事故。因此，被告就本件事故顯然具有過失甚明，且應就本件事故之發生負全部之肇事責任（亦即就碰撞肇事之原因負全部責任），新北市政府車輛行車事故鑑定委員會提出之鑑定意見，亦認定被告係肇事之唯一原因，而被害人無肇事因素（偵查卷第65至66頁）。惟按機器腳踏車駕駛人及附載座人應依下列規定配戴安全帽：三配帶時安全帽應正面朝前及位置正確，於顎下繫緊扣環，安全帽並應適合頭形，穩固戴在頭上，不致上下左右晃動，且不可遮蔽視線，道路交通安全規則第88條第2項第3款定有明文，前開規定本即在保障機器腳踏車駕駛人之生命、身體安全，降低事故發生時所生之損害。依卷附現場圖及照片觀之，警方至現場處理時，被害人係仰躺在地，頭部未著安全帽，其安全帽係位在對向車道（瑞芳往基隆方向車道）上，距離對向車道之快慢車道分隔線僅1公尺（快車道寬3.7公尺），而被害人仰躺時頭部係壓在雙黃線上，該處留有一灘血跡，客觀跡證顯示被害人之安全帽應係碰撞之際飛落滾至對向車道上，其倒地時頭部並未受到安全帽之保護；準此，足認被害人於騎駛機車時並未將安全帽於顎下繫緊扣環且穩固戴在頭上，於兩車碰撞時，其安全帽飛落，致頭部直接著地受創。而被害人經送醫急救結果，仍因外傷性蜘蛛網膜下腔出血、外傷性頸動脈假性動脈瘤破裂、敗血症合併疑似急性呼吸窘迫症、心肺衰竭等原因，不治死亡；準此可知，被告就上開事故之發生確實有過失，且其過失行為與被害人死亡結果具有因果關係，然被害人疏未正確佩帶安全帽，對於死亡結果之發生亦與有原因。(三)又按過失致人於死罪之規範目的，係在處罰行為人因個人之過失而致他人死亡之行為，祗以加害人之有過失為致死亡之一原因為已足，不因被害人亦有過失而影響於犯罪之成立（院字第631號解釋意旨參照），有關被害人與有過失一節，僅係民事賠償責任之過失比例分配問題，並不因此影響被告過失責任有無之認定。本案係被告騎駛機車有重大違規行為，導致碰撞發生，被害人因而死亡，應由被告就「交通事故之發生」負全部過失責任（被害人僅就死亡結果之發生與有原因），且其係執行派送報紙之業務之際發生上開情形，自應負業務過失致人於死罪之刑事責任。本案事證明確，被告犯行足堪認定。三、核被告所為，係犯刑法第276條第2項之業務過失致人於死罪。本案係員警至肇事現場處理及詢問附近民眾而確認被告係肇事者等情，有道路交通事故肇事人自首情形紀錄表附卷可憑，是被告尚無刑法第62條自首規定之適用。爰審酌被告於本案前並無任何前科紀錄，有臺灣高等法院被告前案紀錄表存卷可佐，其因一時疏忽肇事，剝奪被害人之寶貴生命，使被害人正值壯年之年輕生命因此逝去；雖被害人未正確佩戴安全帽與有原因，然而，若不是被告有如此重大之違規行為，亦不至於發生本件無法彌補之後果，亦使被害人之家屬承受失去至親之精神上打擊及難以撫平之遺憾暨傷痛，其犯罪所生損害實屬重大；參酌其犯後雖坦承有過失且承認犯罪，然對於車行方向並未如實陳述，並審酌其事後已與告訴人即被害人之母達成民事和解（參卷附調解筆錄），暨其家中係中低收入戶（參卷附新北市瑞芳區公所中低收入證明書）之生活狀況等一切情狀，量處如主文所示之刑，以資懲儆。又被告係因一時疏忽，致罹刑章，其自身亦因本件交通事故受傷（卷附基隆長庚紀念醫院出具之診斷證明書參照），且其有一名未成年之女兒仍仰賴其扶養（參前揭中低收入證明書及卷附全戶戶籍資料），堪認其經此偵查及審判教訓，當知警惕，信無再犯之虞，本院認前揭所宣告之刑，以暫不執行為適當，爰併諭知緩刑3年，以勵自新。四、依刑事訴訟法第449條第1項，刑法第276條第2項、第74條第1項第1款，刑法施行法第1條之1第1項、第2項前段，逕以簡易判決處刑如主文。五、自簡易判決送達之日起10日內，得向本院提起上訴（須附繕本）。中華民國100年12月5日基隆簡易庭法官張婷妮以上正本證明與原本無異。如不服本判決，應於判決送達後10日內，向本院提出上訴書狀，敘述上訴理由，上訴於本院合議庭，並按他造當事人之人數附具繕本。中華民國100年12月5日書記官連懿婷附錄本案論罪科刑法條中華民國刑法第276條第2項從事業務之人，因業務上之過失犯前項之罪者，處五年以下有期徒刑或拘役，得併科三千元以下罰金。",
  "characters": {
    "judges": [
      "張婷妮"
    ],
    "prosecutors": [

    ],
    "lawyers": [

    ],
    "clerks": [
      "連懿婷"
    ],
    "plaintiffs": [

    ],
    "defendants": [
      "李靆璘"
    ],
    "prosecutor_office": [
      "臺灣基隆地方法院檢察署檢察官"
    ],
    "creditors": [

    ],
    "debtors": [

    ],
    "judicial_associate_officer": [

    ]
  },
  "adjudged_at": "2011-12-05",
  "created_at": "2016-02-13 11:05:52",
  "updated_at": "2016-02-13 11:05:52"
}