{
  "identify": "TPD-100-審交易-241-20111206-1",
  "court": {
    "name": "臺灣臺北地方法院",
    "code": "TPD"
  },
  "division": {
    "name": "刑事",
    "code": "M"
  },
  "year": 100,
  "word": "審交易",
  "number": "241",
  "jcheck": "1",
  "reason": "過失傷害",
  "content": "臺灣臺北地方法院刑事判決          100年度審交易字第241號\n公  訴  人  臺灣臺北地方法院檢察署檢察官\n被      告  邱耿豪\n            朱光宇\n上列被告因過失傷害案件，經檢察官提起公訴(100年度偵字第14\n024號、第19777號），本院判決如下：\n    主  文\n本件公訴均不受理。\n    理  由\n一、公訴意旨略以：被告即告訴人邱耿豪於民國100年3月28日上\n    午8 時18分，在臺北市○○區○○路74號前，本應注意車輛\n    起駛前應顯示方向燈，注意前後左右有無障礙或車輛行人，\n    並應讓行進中之車輛行人優先通行，依當時情形並無不能注\n    意之情事，竟疏未注意行進中之車輛，即貿然發動停靠在青\n    年路74號前(東往西方向）之車牌號碼BEY-089號機車駛入青\n    年路，適有被告即告訴人朱光宇騎乘車牌號碼286-CGK 號重\n    型機車，沿臺北市○○區○○路東往西方向行駛，本應注意\n    行車速度，依速限標誌或標線之規定，無標誌或標線者，行\n    車時速不得超過50公里，亦應注意車前狀況，隨時採取必要\n    之安全措施，而當時並無不能注意之情事，竟疏於注意，貿\n    然以超過速限50公里速度駛至該路段74號前，2 車遂發生碰\n    撞，造成人車倒地，被告邱耿豪因而受有左踝及左足背挫傷\n    、韌帶扭傷之傷害，被告朱光宇則受有右側雙踝骨折、右側\n    腓骨骨折、左下肢傷口之傷害，因認被告2 人均涉犯刑法第\n    284條第1項前段之過失傷害罪嫌。\n二、按告訴乃論之罪，告訴人於第一審辯論終結前得撤回其告訴\n    ;又告訴經撤回者，應諭知不受理之判決，刑事訴訟法第238\n    條第1項、第303條第3款分別定有明文。\n三、經查本件被告互告過失傷害案件部分，依刑法第287 條前段\n    之規定，須告訴乃論。茲因告訴人即被告2 人均已互相撤回\n    告訴，有被告2人於100年12月6日所提出刑事撤回告訴狀各1\n    份在卷可稽。揆諸前開說明，本件爰不經言詞辯論，逕為諭\n    知不受理判決。\n據上論斷，應依刑事訴訟法第303條第3 款、第307條，判決如主\n文。\n本案經檢察官鄭東到庭執行職務。\n中    華    民    國   100    年    12    月    6     日\n                  刑事第二十庭  法  官  呂政燁\n以上正本證明與原本無異。\n如不服本判決應於收受送達後10日內向本院提出上訴書狀，並應\n敘述具體理由；其未敘述上訴理由者，應於上訴期間屆滿後20日\n內向本院補提理由書（均須按他造當事人之人數附繕本）「切勿\n逕送上級法院」。告訴人或被害人如對於本判決不服者，應具備\n理由請求檢察官上訴，其上訴期間之計算係以檢察官收受判決正\n本之日期為準。\n                                書記官  楊湘雯\n中    華    民    國   100    年    12    月    6     日",
  "structure": {
    "main": "本件公訴均不受理。",
    "reason": "一、公訴意旨略以：被告即告訴人邱耿豪於民國100年3月28日上\n    午8 時18分，在臺北市○○區○○路74號前，本應注意車輛\n    起駛前應顯示方向燈，注意前後左右有無障礙或車輛行人，\n    並應讓行進中之車輛行人優先通行，依當時情形並無不能注\n    意之情事，竟疏未注意行進中之車輛，即貿然發動停靠在青\n    年路74號前(東往西方向）之車牌號碼BEY-089號機車駛入青\n    年路，適有被告即告訴人朱光宇騎乘車牌號碼286-CGK 號重\n    型機車，沿臺北市○○區○○路東往西方向行駛，本應注意\n    行車速度，依速限標誌或標線之規定，無標誌或標線者，行\n    車時速不得超過50公里，亦應注意車前狀況，隨時採取必要\n    之安全措施，而當時並無不能注意之情事，竟疏於注意，貿\n    然以超過速限50公里速度駛至該路段74號前，2 車遂發生碰\n    撞，造成人車倒地，被告邱耿豪因而受有左踝及左足背挫傷\n    、韌帶扭傷之傷害，被告朱光宇則受有右側雙踝骨折、右側\n    腓骨骨折、左下肢傷口之傷害，因認被告2 人均涉犯刑法第\n    284條第1項前段之過失傷害罪嫌。\n二、按告訴乃論之罪，告訴人於第一審辯論終結前得撤回其告訴\n    ;又告訴經撤回者，應諭知不受理之判決，刑事訴訟法第238\n    條第1項、第303條第3款分別定有明文。\n三、經查本件被告互告過失傷害案件部分，依刑法第287 條前段\n    之規定，須告訴乃論。茲因告訴人即被告2 人均已互相撤回\n    告訴，有被告2人於100年12月6日所提出刑事撤回告訴狀各1\n    份在卷可稽。揆諸前開說明，本件爰不經言詞辯論，逕為諭\n    知不受理判決。\n據上論斷，應依刑事訴訟法第303條第3 款、第307條，判決如主\n文。\n本案經檢察官鄭東到庭執行職務。"
  },
  "search": "臺灣臺北地方法院刑事判決100年度審交易字第241號公訴人臺灣臺北地方法院檢察署檢察官被告邱耿豪朱光宇上列被告因過失傷害案件，經檢察官提起公訴(100年度偵字第14024號、第19777號），本院判決如下：主文本件公訴均不受理。理由一、公訴意旨略以：被告即告訴人邱耿豪於民國100年3月28日上午8時18分，在臺北市○○區○○路74號前，本應注意車輛起駛前應顯示方向燈，注意前後左右有無障礙或車輛行人，並應讓行進中之車輛行人優先通行，依當時情形並無不能注意之情事，竟疏未注意行進中之車輛，即貿然發動停靠在青年路74號前(東往西方向）之車牌號碼BEY-089號機車駛入青年路，適有被告即告訴人朱光宇騎乘車牌號碼286-CGK號重型機車，沿臺北市○○區○○路東往西方向行駛，本應注意行車速度，依速限標誌或標線之規定，無標誌或標線者，行車時速不得超過50公里，亦應注意車前狀況，隨時採取必要之安全措施，而當時並無不能注意之情事，竟疏於注意，貿然以超過速限50公里速度駛至該路段74號前，2車遂發生碰撞，造成人車倒地，被告邱耿豪因而受有左踝及左足背挫傷、韌帶扭傷之傷害，被告朱光宇則受有右側雙踝骨折、右側腓骨骨折、左下肢傷口之傷害，因認被告2人均涉犯刑法第284條第1項前段之過失傷害罪嫌。二、按告訴乃論之罪，告訴人於第一審辯論終結前得撤回其告訴;又告訴經撤回者，應諭知不受理之判決，刑事訴訟法第238條第1項、第303條第3款分別定有明文。三、經查本件被告互告過失傷害案件部分，依刑法第287條前段之規定，須告訴乃論。茲因告訴人即被告2人均已互相撤回告訴，有被告2人於100年12月6日所提出刑事撤回告訴狀各1份在卷可稽。揆諸前開說明，本件爰不經言詞辯論，逕為諭知不受理判決。據上論斷，應依刑事訴訟法第303條第3款、第307條，判決如主文。本案經檢察官鄭東到庭執行職務。中華民國100年12月6日刑事第二十庭法官呂政燁以上正本證明與原本無異。如不服本判決應於收受送達後10日內向本院提出上訴書狀，並應敘述具體理由；其未敘述上訴理由者，應於上訴期間屆滿後20日內向本院補提理由書（均須按他造當事人之人數附繕本）「切勿逕送上級法院」。告訴人或被害人如對於本判決不服者，應具備理由請求檢察官上訴，其上訴期間之計算係以檢察官收受判決正本之日期為準。書記官楊湘雯中華民國100年12月6日",
  "characters": {
    "judges": [
      "呂政燁"
    ],
    "prosecutors": [

    ],
    "lawyers": [

    ],
    "clerks": [
      "楊湘雯"
    ],
    "plaintiffs": [

    ],
    "defendants": [
      "邱耿豪"
    ],
    "prosecutor_office": [
      "臺灣臺北地方法院檢察署檢察官"
    ],
    "creditors": [

    ],
    "debtors": [

    ],
    "judicial_associate_officer": [

    ]
  },
  "adjudged_at": "2011-12-06",
  "created_at": "2016-02-13 11:18:59",
  "updated_at": "2016-02-13 11:18:59"
}