{
  "identify": "CYD-94-訴-594-20051124-1",
  "court": {
    "name": "臺灣嘉義地方法院",
    "code": "CYD"
  },
  "division": {
    "name": "民事",
    "code": "V"
  },
  "year": 94,
  "word": "訴",
  "number": "594",
  "jcheck": "1",
  "reason": "損害賠償",
  "content": "臺灣嘉義地方法院民事裁定  94年度訴字第594號\n原      告  乙○○\n法定代理人  丙○○\n被      告  甲○○\n當事人間請求損害賠償事件，本院裁定如下：\n    主  文\n原告之訴駁回。\n訴訟費用由原告負擔。\n    理  由\n一、按原告提起民事訴訟應依民事訴訟法第七十七條之十三規定\n    之計算標準繳納裁判費，此為訴訟合法所必須具備之程式。\n二、原告起訴未繳納裁判費，業經本院以九十四年度補字第二○\n    四號民事裁定應於裁定送達後五日內補正，上開裁定於民國\n    九十四年十月二十八日送達，而至今尚未繳納等情，有上開\n    裁定一份、送達證書及民事科查詢簡答表各一紙附卷為憑，\n    故其起訴不合程式，訴不合法，應予駁回。\n三、依民事訴訟法第二百四十九條第一項第六款、第九十五條、\n    第七十八條，裁定如主文。\n中    華    民    國    94    年    11    月    24    日\n            民二庭審判長法  官  黃國益\n                        法  官  林福來\n                        法  官  陳琪媛\n以上正本係照原本作成\n如對本裁定抗告應於送達後10日內向本院提出抗告狀\n中    華    民    國    94    年    11    月    24    日\n                        書記官  林柑杏\n",
  "structure": {
    "main": "原告之訴駁回。\n訴訟費用由原告負擔。",
    "reason": "一、按原告提起民事訴訟應依民事訴訟法第七十七條之十三規定\n    之計算標準繳納裁判費，此為訴訟合法所必須具備之程式。\n二、原告起訴未繳納裁判費，業經本院以九十四年度補字第二○\n    四號民事裁定應於裁定送達後五日內補正，上開裁定於民國\n    九十四年十月二十八日送達，而至今尚未繳納等情，有上開\n    裁定一份、送達證書及民事科查詢簡答表各一紙附卷為憑，\n    故其起訴不合程式，訴不合法，應予駁回。\n三、依民事訴訟法第二百四十九條第一項第六款、第九十五條、\n    第七十八條，裁定如主文。"
  },
  "search": "臺灣嘉義地方法院民事裁定94年度訴字第594號原告乙○○法定代理人丙○○被告甲○○當事人間請求損害賠償事件，本院裁定如下：主文原告之訴駁回。訴訟費用由原告負擔。理由一、按原告提起民事訴訟應依民事訴訟法第七十七條之十三規定之計算標準繳納裁判費，此為訴訟合法所必須具備之程式。二、原告起訴未繳納裁判費，業經本院以九十四年度補字第二○四號民事裁定應於裁定送達後五日內補正，上開裁定於民國九十四年十月二十八日送達，而至今尚未繳納等情，有上開裁定一份、送達證書及民事科查詢簡答表各一紙附卷為憑，故其起訴不合程式，訴不合法，應予駁回。三、依民事訴訟法第二百四十九條第一項第六款、第九十五條、第七十八條，裁定如主文。中華民國94年11月24日民二庭審判長法官黃國益法官林福來法官陳琪媛以上正本係照原本作成如對本裁定抗告應於送達後10日內向本院提出抗告狀中華民國94年11月24日書記官林柑杏",
  "characters": {
    "judges": [
      "黃國益",
      "林福來",
      "陳琪媛"
    ],
    "prosecutors": [

    ],
    "lawyers": [

    ],
    "clerks": [
      "林柑杏"
    ],
    "plaintiffs": [
      "乙"
    ],
    "defendants": [
      "甲○○",
      "當事人間請求損害賠償事件，本院裁定如下："
    ],
    "prosecutor_office": [

    ],
    "creditors": [

    ],
    "debtors": [

    ],
    "judicial_associate_officer": [

    ]
  },
  "adjudged_at": "2005-11-24",
  "created_at": "2016-02-07 01:08:38",
  "updated_at": "2016-02-07 01:08:38"
}