{
  "identify": "KSD-94-易-1835-20051123-1",
  "court": {
    "name": "臺灣高雄地方法院",
    "code": "KSD"
  },
  "division": {
    "name": "刑事",
    "code": "M"
  },
  "year": 94,
  "word": "易",
  "number": "1835",
  "jcheck": "1",
  "reason": "恐嚇取財等",
  "content": "臺灣高雄地方法院刑事裁定              94年度易字第1835號\n公  訴  人  臺灣高雄地方法院檢察署檢察官\n被      告  乙○○\n                    （現羈押於臺灣高雄看守所）\n            甲○○\n                    （現羈押於臺灣高雄看守所）\n上列被告因恐嚇取財等案件，經檢察官提起公訴（94年偵字\n21144 號），聲請具保停止羈押，本院裁定如下：\n    主  文\n乙○○提出新台幣肆萬元之保證書或保證金後，准予停止羈押。\n甲○○提出新台幣貳萬元之保證書或保證金後，准予停止羈押。\n    理  由\n本件被告乙○○、甲○○前經本院執行羈押。茲聲請人以被告之\n身分，聲請停止羈押，經核符合規定，准予乙○○提出新台幣（\n下同）40,000元、甲○○提出20,000元之保證書或證金後，停止\n羈押，爰依刑事訴訟法第111 條、第121 條第1 項，裁定如主文\n。\n中    華    民    國    94    年    11    月    23    日\n                  刑事第十一庭  審判長法  官   何秀燕\n                                      法  官   戰諭威\n                                      法  官   楊智守\n以上正本證明與原本無異。\n如不服本裁定，應於送達後5日內，向本院提出抗告狀。\n中    華    民    國    94    年    11    月    23    日\n                                      書記官  王美玲\n",
  "structure": {
    "main": "乙○○提出新台幣肆萬元之保證書或保證金後，准予停止羈押。\n甲○○提出新台幣貳萬元之保證書或保證金後，准予停止羈押。",
    "reason": "本件被告乙○○、甲○○前經本院執行羈押。茲聲請人以被告之\n身分，聲請停止羈押，經核符合規定，准予乙○○提出新台幣（\n下同）40,000元、甲○○提出20,000元之保證書或證金後，停止\n羈押，爰依刑事訴訟法第111 條、第121 條第1 項，裁定如主文\n。"
  },
  "search": "臺灣高雄地方法院刑事裁定94年度易字第1835號公訴人臺灣高雄地方法院檢察署檢察官被告乙○○（現羈押於臺灣高雄看守所）甲○○（現羈押於臺灣高雄看守所）上列被告因恐嚇取財等案件，經檢察官提起公訴（94年偵字21144號），聲請具保停止羈押，本院裁定如下：主文乙○○提出新台幣肆萬元之保證書或保證金後，准予停止羈押。甲○○提出新台幣貳萬元之保證書或保證金後，准予停止羈押。理由本件被告乙○○、甲○○前經本院執行羈押。茲聲請人以被告之身分，聲請停止羈押，經核符合規定，准予乙○○提出新台幣（下同）40,000元、甲○○提出20,000元之保證書或證金後，停止羈押，爰依刑事訴訟法第111條、第121條第1項，裁定如主文。中華民國94年11月23日刑事第十一庭審判長法官何秀燕法官戰諭威法官楊智守以上正本證明與原本無異。如不服本裁定，應於送達後5日內，向本院提出抗告狀。中華民國94年11月23日書記官王美玲",
  "characters": {
    "judges": [
      "何秀燕",
      "戰諭威",
      "楊智守"
    ],
    "prosecutors": [

    ],
    "lawyers": [

    ],
    "clerks": [
      "王美玲"
    ],
    "plaintiffs": [

    ],
    "defendants": [
      "乙○○"
    ],
    "prosecutor_office": [
      "臺灣高雄地方法院檢察署檢察官"
    ],
    "creditors": [

    ],
    "debtors": [

    ],
    "judicial_associate_officer": [

    ]
  },
  "adjudged_at": "2005-11-23",
  "created_at": "2016-02-07 01:07:04",
  "updated_at": "2016-02-07 01:07:04"
}