{
  "identify": "KSH-94-聲-423-20051124-1",
  "court": {
    "name": "臺灣高等法院",
    "code": "KSH"
  },
  "division": {
    "name": "刑事",
    "code": "M"
  },
  "year": 94,
  "word": "聲",
  "number": "423",
  "jcheck": "1",
  "reason": "聲請定其應執行刑",
  "content": "臺灣高等法院高雄分院刑事裁定           94年度聲字第423號\n聲  請  人  臺灣高等法院高雄分院檢察署檢察官\n受  刑  人  甲○○\n                    （現在台灣屏東監獄執行中）\n上列聲請人因受刑人數罪併罰有二裁判以上，聲請定其應執行之\n刑，本院裁定如下：\n    主  文\n甲○○因毒品危害防制條例等參罪，分別處如附表所示之刑，應\n執行有期徒刑拾壹年肆月。\n    理  由\n受刑人甲○○因聲請定其應執行刑等三罪，經最高法院暨臺灣高\n雄地方法院先後判處如附表所示之刑，均經分別確定在案。茲檢\n察官聲請定其應執行之刑，本院審核認聲請為正當，應定其應執\n行之刑。爰依刑事訴訟法第477 條第1 項、刑法第53條、第51條\n第5 款，裁定如主文。\n中    華    民    國    94    年    11    月    24    日\n            刑事第五庭  審判長法  官  曾永宗\n                              法  官  陳明富\n                              法  官  任森銓\n以上正本證明與原本無異。\n如不服本裁定應於送達後5 日內向本院提出抗告狀。\n中    華    民    國    94    年    11    月    24    日\n                              書記官  蘇恒仁\n",
  "structure": {
    "main": "甲○○因毒品危害防制條例等參罪，分別處如附表所示之刑，應\n執行有期徒刑拾壹年肆月。",
    "reason": "受刑人甲○○因聲請定其應執行刑等三罪，經最高法院暨臺灣高\n雄地方法院先後判處如附表所示之刑，均經分別確定在案。茲檢\n察官聲請定其應執行之刑，本院審核認聲請為正當，應定其應執\n行之刑。爰依刑事訴訟法第477 條第1 項、刑法第53條、第51條\n第5 款，裁定如主文。"
  },
  "search": "臺灣高等法院高雄分院刑事裁定94年度聲字第423號聲請人臺灣高等法院高雄分院檢察署檢察官受刑人甲○○（現在台灣屏東監獄執行中）上列聲請人因受刑人數罪併罰有二裁判以上，聲請定其應執行之刑，本院裁定如下：主文甲○○因毒品危害防制條例等參罪，分別處如附表所示之刑，應執行有期徒刑拾壹年肆月。理由受刑人甲○○因聲請定其應執行刑等三罪，經最高法院暨臺灣高雄地方法院先後判處如附表所示之刑，均經分別確定在案。茲檢察官聲請定其應執行之刑，本院審核認聲請為正當，應定其應執行之刑。爰依刑事訴訟法第477條第1項、刑法第53條、第51條第5款，裁定如主文。中華民國94年11月24日刑事第五庭審判長法官曾永宗法官陳明富法官任森銓以上正本證明與原本無異。如不服本裁定應於送達後5日內向本院提出抗告狀。中華民國94年11月24日書記官蘇恒仁",
  "characters": {
    "judges": [
      "曾永宗",
      "陳明富",
      "任森銓"
    ],
    "prosecutors": [

    ],
    "lawyers": [

    ],
    "clerks": [
      "蘇恒仁"
    ],
    "plaintiffs": [

    ],
    "defendants": [

    ],
    "prosecutor_office": [
      "臺灣高等法院高雄分院檢察署檢察官"
    ],
    "creditors": [

    ],
    "debtors": [

    ],
    "judicial_associate_officer": [

    ]
  },
  "adjudged_at": "2005-11-24",
  "created_at": "2016-02-07 01:05:42",
  "updated_at": "2016-02-07 01:05:42"
}