{
  "identify": "TPD-94-易-1561-20051123-2",
  "court": {
    "name": "臺灣臺北地方法院",
    "code": "TPD"
  },
  "division": {
    "name": "刑事",
    "code": "M"
  },
  "year": 94,
  "word": "易",
  "number": "1561",
  "jcheck": "2",
  "reason": "竊盜",
  "content": "臺灣臺北地方法院刑事判決              94年度易字第1561號\n公  訴  人  臺灣臺北地方法院檢察署檢察官\n被      告  甲○○\n上列被告因竊盜案件，經檢察官提起公訴（94年度偵字第17165\n號），本院於準備程序中經訊問被告自白犯罪後，並經本院合議\n庭裁定認為宜以簡式審判程序審理，判決如下：\n    主    文\n甲○○攜帶兇器竊盜，累犯，處有期徒刑捌月。\n    事    實\n一、甲○○前因偽造文書及詐欺等案件，經本院於民國93年2 月\n    17日以93年度簡字第248 號刑事簡易判決分別判處有期徒刑\n    4 月及3 月，應執行有期徒刑5 月，並於同年3 月15日確定\n    ，嗣於同年4 月6 日易科罰金執行完畢。詎仍不知悔改，竟\n    意圖為己不法之所有，於94年7 月28日凌晨1 時許，攜帶其\n    所有客觀上足以對人之生命、身體具有危險性可供兇器使用\n    之老虎鉗1 支，至臺北縣深坑鄉○○路○ 段197 號前，持前\n    揭老虎鉗竊取乙○○所有停放在該處之車號CRC-683 號重型\n    機車之車牌1 面，得手後，將該車牌懸掛在其所有已遭監理\n    機關吊銷執照之車號HOE-520 號重型機車上，供己使用。嗣\n    於同年9 月14日凌晨1 時10分許，因騎乘該機車行經臺北市\n    信義區○○○路○ 段與富陽街口時為警查獲。\n二、案經臺北市政府警察局信義分局報請臺灣臺北地方法院檢察\n    署檢察官偵查起訴，本院於準備程序中經訊問被告自白犯罪\n    後，並經本院合議庭裁定認為宜以簡式審判程序審理。\n    理    由\n一、前揭事實業據被告甲○○於警詢、偵查、本院準備程序及審\n    理時均自始供承不諱，核與被害人乙○○於警詢時之指訴情\n    節相符。此外，復有臺北市政府警察局信義分局贓物認領保\n    管單、臺北市政府警察局信義分局車牌遺失尋獲電腦輸入單\n    、車輛竊盜、車牌失竊資料個別查詢報表及及現場照片5 幀\n    在卷（見偵查卷第19頁至第20頁、第23頁、第26頁至第28頁\n    ）可稽。基此，堪認被告之自白核與事實相符，自得採為論\n    罪之依據。本件事證已臻明確，被告上揭犯行洵堪認定。\n二、按老虎鉗在客觀上具有危險性，足以殺傷人之生命、身體，\n    為兇器之一種。核被告攜帶老虎鉗竊取他人財物之行為，係\n    犯刑法第321 條第1 項第3 款之攜帶兇器竊盜罪。又被告前\n    因偽造文書及詐欺等案件，經本院於93年2 月17日以93年度\n    簡字第248 號刑事簡易判決分別判處有期徒刑4 月及3 月，\n    應執行有期徒刑5 月，並於同年3 月15日確定，嗣於同年4\n    月6 日易科罰金執行完畢，此有臺灣高等法院被告前案紀錄\n    表1 份在卷（見本院卷第5 頁）可證，其於五年之內，再犯\n    本件有期徒刑以上之罪，係屬累犯，應依刑法第47條之規定\n    加重其刑。爰審酌被告之犯罪動機、目的、手段、品行、智\n    識程度，致被害人所生之損害，及其犯罪後於警詢、偵查、\n    本院準備程序及審理時均能自始坦認犯行，態度尚稱良好等\n    一切情狀，量處如主文所示之刑。至被告所有供犯罪所用之\n    老虎鉗1 支，並未扣案，且據被告於本院審理時供稱業已將\n    該老虎鉗丟棄（見本院卷第22頁），為避免日後執行之困難\n    ，本院爰不予宣告沒收，附此敘明。\n據上論斷，應依刑事訴訟法第273 條之1 第1 項、第299 條第1\n項前段，刑法第321 條第1 項第3 款、第47條，判決如主文。\n本案經檢察官黃紋綦到庭執行職務。\n中    華    民    國    94    年    11    月    23    日\n                  刑事第七庭法  官  蔡正雄\n上正本證明與原本無異。\n如不服本判決，應於判決送達後10日內向本院提出上訴狀（應抄\n附繕本）。告訴人或被害人如對於本判決不服者，應具備理由請\n求檢察官上訴，其上訴期間之計算係以檢察官收受判決正本之日\n期為準。\n                            書記官  葉潔如\n中    華    民    國    94    年    11    月    23    日\n附錄本案論罪科刑所依據之法條：\n中華民國刑法第321條\n(加重竊盜罪)\n犯竊盜罪而有左列情形之一者，處6 月以上、5 年以下有期徒刑\n：\n一  於夜間侵入住宅或有人居住之建築物、船艦或隱匿其內而犯\n    之者。\n二  毀越門扇、牆垣或其他安全設備而犯之者。\n三  攜帶兇器而犯之者。\n四  結夥三人以上而犯之者。\n五  乘火災、水災或其他災害之際而犯之者。\n六  在車站或埠頭而犯之者。\n前項之未遂犯罰之。\n",
  "structure": {
    "main": "甲○○攜帶兇器竊盜，累犯，處有期徒刑捌月。",
    "fact": "一、甲○○前因偽造文書及詐欺等案件，經本院於民國93年2 月\n    17日以93年度簡字第248 號刑事簡易判決分別判處有期徒刑\n    4 月及3 月，應執行有期徒刑5 月，並於同年3 月15日確定\n    ，嗣於同年4 月6 日易科罰金執行完畢。詎仍不知悔改，竟\n    意圖為己不法之所有，於94年7 月28日凌晨1 時許，攜帶其\n    所有客觀上足以對人之生命、身體具有危險性可供兇器使用\n    之老虎鉗1 支，至臺北縣深坑鄉○○路○ 段197 號前，持前\n    揭老虎鉗竊取乙○○所有停放在該處之車號CRC-683 號重型\n    機車之車牌1 面，得手後，將該車牌懸掛在其所有已遭監理\n    機關吊銷執照之車號HOE-520 號重型機車上，供己使用。嗣\n    於同年9 月14日凌晨1 時10分許，因騎乘該機車行經臺北市\n    信義區○○○路○ 段與富陽街口時為警查獲。\n二、案經臺北市政府警察局信義分局報請臺灣臺北地方法院檢察\n    署檢察官偵查起訴，本院於準備程序中經訊問被告自白犯罪\n    後，並經本院合議庭裁定認為宜以簡式審判程序審理。",
    "reason": "一、前揭事實業據被告甲○○於警詢、偵查、本院準備程序及審\n    理時均自始供承不諱，核與被害人乙○○於警詢時之指訴情\n    節相符。此外，復有臺北市政府警察局信義分局贓物認領保\n    管單、臺北市政府警察局信義分局車牌遺失尋獲電腦輸入單\n    、車輛竊盜、車牌失竊資料個別查詢報表及及現場照片5 幀\n    在卷（見偵查卷第19頁至第20頁、第23頁、第26頁至第28頁\n    ）可稽。基此，堪認被告之自白核與事實相符，自得採為論\n    罪之依據。本件事證已臻明確，被告上揭犯行洵堪認定。\n二、按老虎鉗在客觀上具有危險性，足以殺傷人之生命、身體，\n    為兇器之一種。核被告攜帶老虎鉗竊取他人財物之行為，係\n    犯刑法第321 條第1 項第3 款之攜帶兇器竊盜罪。又被告前\n    因偽造文書及詐欺等案件，經本院於93年2 月17日以93年度\n    簡字第248 號刑事簡易判決分別判處有期徒刑4 月及3 月，\n    應執行有期徒刑5 月，並於同年3 月15日確定，嗣於同年4\n    月6 日易科罰金執行完畢，此有臺灣高等法院被告前案紀錄\n    表1 份在卷（見本院卷第5 頁）可證，其於五年之內，再犯\n    本件有期徒刑以上之罪，係屬累犯，應依刑法第47條之規定\n    加重其刑。爰審酌被告之犯罪動機、目的、手段、品行、智\n    識程度，致被害人所生之損害，及其犯罪後於警詢、偵查、\n    本院準備程序及審理時均能自始坦認犯行，態度尚稱良好等\n    一切情狀，量處如主文所示之刑。至被告所有供犯罪所用之\n    老虎鉗1 支，並未扣案，且據被告於本院審理時供稱業已將\n    該老虎鉗丟棄（見本院卷第22頁），為避免日後執行之困難\n    ，本院爰不予宣告沒收，附此敘明。\n據上論斷，應依刑事訴訟法第273 條之1 第1 項、第299 條第1\n項前段，刑法第321 條第1 項第3 款、第47條，判決如主文。\n本案經檢察官黃紋綦到庭執行職務。\n中    華    民    國    94    年    11    月    23    日\n                  刑事第七庭法  官  蔡正雄\n上正本證明與原本無異。\n如不服本判決，應於判決送達後10日內向本院提出上訴狀（應抄\n附繕本）。告訴人或被害人如對於本判決不服者，應具備理由請\n求檢察官上訴，其上訴期間之計算係以檢察官收受判決正本之日\n期為準。\n                            書記官  葉潔如"
  },
  "search": "臺灣臺北地方法院刑事判決94年度易字第1561號公訴人臺灣臺北地方法院檢察署檢察官被告甲○○上列被告因竊盜案件，經檢察官提起公訴（94年度偵字第17165號），本院於準備程序中經訊問被告自白犯罪後，並經本院合議庭裁定認為宜以簡式審判程序審理，判決如下：主文甲○○攜帶兇器竊盜，累犯，處有期徒刑捌月。事實一、甲○○前因偽造文書及詐欺等案件，經本院於民國93年2月17日以93年度簡字第248號刑事簡易判決分別判處有期徒刑4月及3月，應執行有期徒刑5月，並於同年3月15日確定，嗣於同年4月6日易科罰金執行完畢。詎仍不知悔改，竟意圖為己不法之所有，於94年7月28日凌晨1時許，攜帶其所有客觀上足以對人之生命、身體具有危險性可供兇器使用之老虎鉗1支，至臺北縣深坑鄉○○路○段197號前，持前揭老虎鉗竊取乙○○所有停放在該處之車號CRC-683號重型機車之車牌1面，得手後，將該車牌懸掛在其所有已遭監理機關吊銷執照之車號HOE-520號重型機車上，供己使用。嗣於同年9月14日凌晨1時10分許，因騎乘該機車行經臺北市信義區○○○路○段與富陽街口時為警查獲。二、案經臺北市政府警察局信義分局報請臺灣臺北地方法院檢察署檢察官偵查起訴，本院於準備程序中經訊問被告自白犯罪後，並經本院合議庭裁定認為宜以簡式審判程序審理。理由一、前揭事實業據被告甲○○於警詢、偵查、本院準備程序及審理時均自始供承不諱，核與被害人乙○○於警詢時之指訴情節相符。此外，復有臺北市政府警察局信義分局贓物認領保管單、臺北市政府警察局信義分局車牌遺失尋獲電腦輸入單、車輛竊盜、車牌失竊資料個別查詢報表及及現場照片5幀在卷（見偵查卷第19頁至第20頁、第23頁、第26頁至第28頁）可稽。基此，堪認被告之自白核與事實相符，自得採為論罪之依據。本件事證已臻明確，被告上揭犯行洵堪認定。二、按老虎鉗在客觀上具有危險性，足以殺傷人之生命、身體，為兇器之一種。核被告攜帶老虎鉗竊取他人財物之行為，係犯刑法第321條第1項第3款之攜帶兇器竊盜罪。又被告前因偽造文書及詐欺等案件，經本院於93年2月17日以93年度簡字第248號刑事簡易判決分別判處有期徒刑4月及3月，應執行有期徒刑5月，並於同年3月15日確定，嗣於同年4月6日易科罰金執行完畢，此有臺灣高等法院被告前案紀錄表1份在卷（見本院卷第5頁）可證，其於五年之內，再犯本件有期徒刑以上之罪，係屬累犯，應依刑法第47條之規定加重其刑。爰審酌被告之犯罪動機、目的、手段、品行、智識程度，致被害人所生之損害，及其犯罪後於警詢、偵查、本院準備程序及審理時均能自始坦認犯行，態度尚稱良好等一切情狀，量處如主文所示之刑。至被告所有供犯罪所用之老虎鉗1支，並未扣案，且據被告於本院審理時供稱業已將該老虎鉗丟棄（見本院卷第22頁），為避免日後執行之困難，本院爰不予宣告沒收，附此敘明。據上論斷，應依刑事訴訟法第273條之1第1項、第299條第1項前段，刑法第321條第1項第3款、第47條，判決如主文。本案經檢察官黃紋綦到庭執行職務。中華民國94年11月23日刑事第七庭法官蔡正雄上正本證明與原本無異。如不服本判決，應於判決送達後10日內向本院提出上訴狀（應抄附繕本）。告訴人或被害人如對於本判決不服者，應具備理由請求檢察官上訴，其上訴期間之計算係以檢察官收受判決正本之日期為準。書記官葉潔如中華民國94年11月23日附錄本案論罪科刑所依據之法條：中華民國刑法第321條(加重竊盜罪)犯竊盜罪而有左列情形之一者，處6月以上、5年以下有期徒刑：一於夜間侵入住宅或有人居住之建築物、船艦或隱匿其內而犯之者。二毀越門扇、牆垣或其他安全設備而犯之者。三攜帶兇器而犯之者。四結夥三人以上而犯之者。五乘火災、水災或其他災害之際而犯之者。六在車站或埠頭而犯之者。前項之未遂犯罰之。",
  "characters": {
    "judges": [
      "蔡正雄"
    ],
    "prosecutors": [
      "黃紋綦"
    ],
    "lawyers": [

    ],
    "clerks": [
      "葉潔如"
    ],
    "plaintiffs": [

    ],
    "defendants": [
      "甲○○"
    ],
    "prosecutor_office": [
      "臺灣臺北地方法院檢察署檢察官"
    ],
    "creditors": [

    ],
    "debtors": [

    ],
    "judicial_associate_officer": [

    ]
  },
  "adjudged_at": "2005-11-23",
  "created_at": "2016-02-07 01:02:12",
  "updated_at": "2016-02-07 01:02:12"
}