{
  "identify": "TTD-94-訴-98-20051124-2",
  "court": {
    "name": "臺灣臺東地方法院",
    "code": "TTD"
  },
  "division": {
    "name": "刑事",
    "code": "M"
  },
  "year": 94,
  "word": "訴",
  "number": "98",
  "jcheck": "2",
  "reason": "業務侵占",
  "content": "臺灣臺東地方法院刑事判決                94年度訴字第98號\n公  訴  人  臺灣臺東地方法院檢察署檢察官\n被      告  乙○○\n選任辯護人  丙○○律師\n上列被告因業務侵占案件，檢察官提起公訴（93年度偵字第1962\n、1963、1964號）後，被告於本院準備程序為有罪之陳述，經合\n議庭裁定由受命法官依簡式審判程序獨任審理，又經檢察官聲請\n改依協商程序而為判決，本院判決如左：\n    主  文\n乙○○連續意圖為自己不法之所有，而侵占對於業務上所持有之\n物，處有期徒刑貳年。緩刑參年。\n    事實及理由\n一、本件犯罪事實及證據均引用檢察官起訴書之記載（如附件）\n    。\n二、本件經檢察官徵詢告訴人臺東縣成功鎮農會代理人甲○○、\n    丁○○之意見後，與被告於審判外達成協商之合意且被告已\n    認罪，其合意內容為：被告願受科刑範圍為有期徒刑2 年，\n    緩刑3年。經查，上開協商合意並無刑事訴訟法第455條之 4\n    第1 項所列情形之一，檢察官聲請改依協商程序而為判決，\n    本院爰不經言詞辯論，於協商合意範圍內為協商判決，合予\n    敘明。\n三、應適用之法條：刑事訴訟法第455條4第2 項、第455條之8、\n    第454條第2項、第273條之1第1項，刑法第56條、第215條、\n    第336條第2項、第55條後段、第74條第1款。\n四、本判決除有刑事訴訟法第455條之4第1項第1 款、第2款、第\n    4款、第6款、第7款所定情形之一，或違反同條第2項規定者\n    ，得自收受判決送達之日起10日內，向本院提出上訴書狀，\n    上訴於第二審法院外，不得上訴。\n中    華    民    國    94    年    11    月    24    日\n                  刑事第一庭    法  官  黃珮茹\n以上正本證明與原本無異。\n                                書記官  徐源坤\n中    華    民    國    94    年    11    月    24    日\n附錄論罪法條：\n中華民國刑法第215條(業務上文書登載不實罪)\n從事業務之人，明知為不實之事項，而登載於其業務上作成之文\n書，足以生損害於公眾或他人者，處三年以下有期徒刑、拘役或\n五百元以下罰金。\n中華民國刑法第336條第2項 (業務侵占罪)\n對於業務上所持有之物，犯前條第一項之罪者，處六月以上五年\n以下有期徒刑，得併科三千元以下罰金。\n中華民國刑法第56條\n(連續犯)\n連續數行為而犯同一之罪名者，以一罪論。但得加重其刑至二分\n之一。\n中華民國刑法第55條後段\n(想像競合及牽連犯)\n一行為而觸犯數罪名，或犯一罪而其方法或結果之行為犯他罪名\n者，從一重處斷。\n中華民國刑法第74條第1款\n(緩刑要件)\n受二年以下有期徒刑、拘役或罰金之宣告，而有左列情形之一，\n認為以暫不執行為適當者，得宣告二年以上五年以下之緩刑，其\n期間自裁判確定之日起算：\n一、未曾受有期徒刑以上刑之宣告者。\n二、前受有期徒刑以上刑之宣告，執行完畢或赦免後，五年以內\n    未曾受有期徒刑以上刑之宣告者。\n",
  "structure": {
    "main": "乙○○連續意圖為自己不法之所有，而侵占對於業務上所持有之\n物，處有期徒刑貳年。緩刑參年。",
    "fact": "一、本件犯罪事實及證據均引用檢察官起訴書之記載（如附件）\n    。\n二、本件經檢察官徵詢告訴人臺東縣成功鎮農會代理人甲○○、\n    丁○○之意見後，與被告於審判外達成協商之合意且被告已\n    認罪，其合意內容為：被告願受科刑範圍為有期徒刑2 年，\n    緩刑3年。經查，上開協商合意並無刑事訴訟法第455條之 4\n    第1 項所列情形之一，檢察官聲請改依協商程序而為判決，\n    本院爰不經言詞辯論，於協商合意範圍內為協商判決，合予\n    敘明。\n三、應適用之法條：刑事訴訟法第455條4第2 項、第455條之8、\n    第454條第2項、第273條之1第1項，刑法第56條、第215條、\n    第336條第2項、第55條後段、第74條第1款。\n四、本判決除有刑事訴訟法第455條之4第1項第1 款、第2款、第\n    4款、第6款、第7款所定情形之一，或違反同條第2項規定者\n    ，得自收受判決送達之日起10日內，向本院提出上訴書狀，\n    上訴於第二審法院外，不得上訴。",
    "reason": "一、本件犯罪事實及證據均引用檢察官起訴書之記載（如附件）\n    。\n二、本件經檢察官徵詢告訴人臺東縣成功鎮農會代理人甲○○、\n    丁○○之意見後，與被告於審判外達成協商之合意且被告已\n    認罪，其合意內容為：被告願受科刑範圍為有期徒刑2 年，\n    緩刑3年。經查，上開協商合意並無刑事訴訟法第455條之 4\n    第1 項所列情形之一，檢察官聲請改依協商程序而為判決，\n    本院爰不經言詞辯論，於協商合意範圍內為協商判決，合予\n    敘明。\n三、應適用之法條：刑事訴訟法第455條4第2 項、第455條之8、\n    第454條第2項、第273條之1第1項，刑法第56條、第215條、\n    第336條第2項、第55條後段、第74條第1款。\n四、本判決除有刑事訴訟法第455條之4第1項第1 款、第2款、第\n    4款、第6款、第7款所定情形之一，或違反同條第2項規定者\n    ，得自收受判決送達之日起10日內，向本院提出上訴書狀，\n    上訴於第二審法院外，不得上訴。"
  },
  "search": "臺灣臺東地方法院刑事判決94年度訴字第98號公訴人臺灣臺東地方法院檢察署檢察官被告乙○○選任辯護人丙○○律師上列被告因業務侵占案件，檢察官提起公訴（93年度偵字第1962、1963、1964號）後，被告於本院準備程序為有罪之陳述，經合議庭裁定由受命法官依簡式審判程序獨任審理，又經檢察官聲請改依協商程序而為判決，本院判決如左：主文乙○○連續意圖為自己不法之所有，而侵占對於業務上所持有之物，處有期徒刑貳年。緩刑參年。事實及理由一、本件犯罪事實及證據均引用檢察官起訴書之記載（如附件）。二、本件經檢察官徵詢告訴人臺東縣成功鎮農會代理人甲○○、丁○○之意見後，與被告於審判外達成協商之合意且被告已認罪，其合意內容為：被告願受科刑範圍為有期徒刑2年，緩刑3年。經查，上開協商合意並無刑事訴訟法第455條之4第1項所列情形之一，檢察官聲請改依協商程序而為判決，本院爰不經言詞辯論，於協商合意範圍內為協商判決，合予敘明。三、應適用之法條：刑事訴訟法第455條4第2項、第455條之8、第454條第2項、第273條之1第1項，刑法第56條、第215條、第336條第2項、第55條後段、第74條第1款。四、本判決除有刑事訴訟法第455條之4第1項第1款、第2款、第4款、第6款、第7款所定情形之一，或違反同條第2項規定者，得自收受判決送達之日起10日內，向本院提出上訴書狀，上訴於第二審法院外，不得上訴。中華民國94年11月24日刑事第一庭法官黃珮茹以上正本證明與原本無異。書記官徐源坤中華民國94年11月24日附錄論罪法條：中華民國刑法第215條(業務上文書登載不實罪)從事業務之人，明知為不實之事項，而登載於其業務上作成之文書，足以生損害於公眾或他人者，處三年以下有期徒刑、拘役或五百元以下罰金。中華民國刑法第336條第2項(業務侵占罪)對於業務上所持有之物，犯前條第一項之罪者，處六月以上五年以下有期徒刑，得併科三千元以下罰金。中華民國刑法第56條(連續犯)連續數行為而犯同一之罪名者，以一罪論。但得加重其刑至二分之一。中華民國刑法第55條後段(想像競合及牽連犯)一行為而觸犯數罪名，或犯一罪而其方法或結果之行為犯他罪名者，從一重處斷。中華民國刑法第74條第1款(緩刑要件)受二年以下有期徒刑、拘役或罰金之宣告，而有左列情形之一，認為以暫不執行為適當者，得宣告二年以上五年以下之緩刑，其期間自裁判確定之日起算：一、未曾受有期徒刑以上刑之宣告者。二、前受有期徒刑以上刑之宣告，執行完畢或赦免後，五年以內未曾受有期徒刑以上刑之宣告者。",
  "characters": {
    "judges": [
      "黃珮茹"
    ],
    "prosecutors": [

    ],
    "lawyers": [

    ],
    "clerks": [
      "徐源坤"
    ],
    "plaintiffs": [

    ],
    "defendants": [
      "乙○○"
    ],
    "prosecutor_office": [
      "臺灣臺東地方法院檢察署檢察官"
    ],
    "creditors": [

    ],
    "debtors": [

    ],
    "judicial_associate_officer": [

    ]
  },
  "adjudged_at": "2005-11-24",
  "created_at": "2016-02-07 01:05:32",
  "updated_at": "2016-02-07 01:05:32"
}