{
  "identify": "HLD-100-花簡-627-20110930-1",
  "court": {
    "name": "臺灣花蓮地方法院",
    "code": "HLD"
  },
  "division": {
    "name": "刑事",
    "code": "M"
  },
  "year": 100,
  "word": "花簡",
  "number": "627",
  "jcheck": "1",
  "reason": "竊盜",
  "content": "臺灣花蓮地方法院刑事簡易判決        100年度花簡字第627號\n聲  請  人  臺灣花蓮地方法院檢察署檢察官\n被      告  張小萍\n上列被告因竊盜案件，經檢察官聲請以簡易判決處刑 （100年度\n偵字第3102號），本院判決如下：\n    主  文\n張小萍犯竊盜罪，累犯，處有期徒刑肆月，如易科罰金，以新臺\n幣壹仟元折算壹日。\n    事實及理由\n一、張小萍前於民國97年間因偽造文書案件，經臺灣宜蘭地方法\n    院判處有期徒刑4月，並經減刑為有期徒刑2月，97年7月8日\n    縮刑期滿執行完畢。詎仍不知悔改，意圖為自己不法之所有\n    ，於100年3月上旬某日，在財團法人佛教花蓮慈濟綜合醫院\n    門診大樓1樓之「愛心小舖」（現為 「精進小站」）店內，\n    趁張娟寧在店內參觀而疏於注意之際，徒手竊取張娟寧所有\n    並放置於店內置物架上之紅白色NOKIA手機1支（型號：N723\n    0、序號：000000000000000），得手後再於100年3月18日將\n    之以新臺幣1,000 元之價格售予不知情之合眾電訊行。嗣因\n    警執行查贓勤務循線查獲。案經花蓮縣警察局花蓮分局報請\n    臺灣花蓮地方法院檢察署檢察官偵查後聲請簡易判決處刑。\n二、上揭事實，業據被告張小萍於偵查中供承不諱，並有被害人\n    張娟寧之指訴、證人沈雅惠之證述明確，此外，復有被告將\n    上開手機售予合重電訊之切結書、通聯調閱查詢單各乙紙在\n    卷可憑，是本件事證明確，被告犯行應堪認定，應依法論科\n    。\n三、核被告所為，係犯刑法第320條第1項之竊盜罪。被告有前揭\n    科刑及執行記錄，有臺灣高等法院被告前案紀錄表附卷可稽\n    ，其於 5年以內再犯本件有期徒刑以上之罪，為累犯，依刑\n    法第47條第 1項規定，加重其刑。爰審酌被告有多次前科紀\n    錄，素行不良，有臺灣高等法院被告前案紀錄表 1份在卷可\n    查，不思循正當途徑獲取財物，因貪圖不法利益而竊取他人\n    財物，竊後復將之變賣，增加查緝困難，兼衡其犯罪之動機\n    、目的、手段等一切情狀，量處如主文所示之刑，並諭知易\n    科罰金之折算標準，以示懲儆。\n四、依刑事訴訟法第449條第1項前段、第454條第1項，刑法第32\n    0條第1項、第47條第1項、第41條第1項前段，刑法施行法第\n    1條之1，逕以簡易判決處如主文所示。\n五、如不服本判決，得自收受送達之日起10日內，向本院提起上\n    訴。\n中    華    民    國    100    年   9    月    30     日\n                  花蓮簡易庭     法  官  林陳松\n上列正本證明與原本無異。\n如對本判決不服，應於送達後10日內，向本院提出上訴狀（應抄\n附繕本）告訴人或被害人如對於本判決不服者，應具備理由請求\n檢察官上訴，其上訴期間之計算係以檢察官收受判決正本之日期\n為準。\n中    華    民    國   100    年    9     月    30    日\n                                  書記官\n附錄本判決論罪之法律條文：\n中華民國刑法第320條第1項：\n意圖為自己或第三人不法之所有，而竊取他人之動產者，為竊盜\n罪，處5年以下有期徒刑、拘役或5百元以下罰金。",
  "structure": {
    "main": "張小萍犯竊盜罪，累犯，處有期徒刑肆月，如易科罰金，以新臺\n幣壹仟元折算壹日。",
    "fact": "一、張小萍前於民國97年間因偽造文書案件，經臺灣宜蘭地方法\n    院判處有期徒刑4月，並經減刑為有期徒刑2月，97年7月8日\n    縮刑期滿執行完畢。詎仍不知悔改，意圖為自己不法之所有\n    ，於100年3月上旬某日，在財團法人佛教花蓮慈濟綜合醫院\n    門診大樓1樓之「愛心小舖」（現為 「精進小站」）店內，\n    趁張娟寧在店內參觀而疏於注意之際，徒手竊取張娟寧所有\n    並放置於店內置物架上之紅白色NOKIA手機1支（型號：N723\n    0、序號：000000000000000），得手後再於100年3月18日將\n    之以新臺幣1,000 元之價格售予不知情之合眾電訊行。嗣因\n    警執行查贓勤務循線查獲。案經花蓮縣警察局花蓮分局報請\n    臺灣花蓮地方法院檢察署檢察官偵查後聲請簡易判決處刑。\n二、上揭事實，業據被告張小萍於偵查中供承不諱，並有被害人\n    張娟寧之指訴、證人沈雅惠之證述明確，此外，復有被告將\n    上開手機售予合重電訊之切結書、通聯調閱查詢單各乙紙在\n    卷可憑，是本件事證明確，被告犯行應堪認定，應依法論科\n    。\n三、核被告所為，係犯刑法第320條第1項之竊盜罪。被告有前揭\n    科刑及執行記錄，有臺灣高等法院被告前案紀錄表附卷可稽\n    ，其於 5年以內再犯本件有期徒刑以上之罪，為累犯，依刑\n    法第47條第 1項規定，加重其刑。爰審酌被告有多次前科紀\n    錄，素行不良，有臺灣高等法院被告前案紀錄表 1份在卷可\n    查，不思循正當途徑獲取財物，因貪圖不法利益而竊取他人\n    財物，竊後復將之變賣，增加查緝困難，兼衡其犯罪之動機\n    、目的、手段等一切情狀，量處如主文所示之刑，並諭知易\n    科罰金之折算標準，以示懲儆。\n四、依刑事訴訟法第449條第1項前段、第454條第1項，刑法第32\n    0條第1項、第47條第1項、第41條第1項前段，刑法施行法第\n    1條之1，逕以簡易判決處如主文所示。\n五、如不服本判決，得自收受送達之日起10日內，向本院提起上\n    訴。",
    "reason": "一、張小萍前於民國97年間因偽造文書案件，經臺灣宜蘭地方法\n    院判處有期徒刑4月，並經減刑為有期徒刑2月，97年7月8日\n    縮刑期滿執行完畢。詎仍不知悔改，意圖為自己不法之所有\n    ，於100年3月上旬某日，在財團法人佛教花蓮慈濟綜合醫院\n    門診大樓1樓之「愛心小舖」（現為 「精進小站」）店內，\n    趁張娟寧在店內參觀而疏於注意之際，徒手竊取張娟寧所有\n    並放置於店內置物架上之紅白色NOKIA手機1支（型號：N723\n    0、序號：000000000000000），得手後再於100年3月18日將\n    之以新臺幣1,000 元之價格售予不知情之合眾電訊行。嗣因\n    警執行查贓勤務循線查獲。案經花蓮縣警察局花蓮分局報請\n    臺灣花蓮地方法院檢察署檢察官偵查後聲請簡易判決處刑。\n二、上揭事實，業據被告張小萍於偵查中供承不諱，並有被害人\n    張娟寧之指訴、證人沈雅惠之證述明確，此外，復有被告將\n    上開手機售予合重電訊之切結書、通聯調閱查詢單各乙紙在\n    卷可憑，是本件事證明確，被告犯行應堪認定，應依法論科\n    。\n三、核被告所為，係犯刑法第320條第1項之竊盜罪。被告有前揭\n    科刑及執行記錄，有臺灣高等法院被告前案紀錄表附卷可稽\n    ，其於 5年以內再犯本件有期徒刑以上之罪，為累犯，依刑\n    法第47條第 1項規定，加重其刑。爰審酌被告有多次前科紀\n    錄，素行不良，有臺灣高等法院被告前案紀錄表 1份在卷可\n    查，不思循正當途徑獲取財物，因貪圖不法利益而竊取他人\n    財物，竊後復將之變賣，增加查緝困難，兼衡其犯罪之動機\n    、目的、手段等一切情狀，量處如主文所示之刑，並諭知易\n    科罰金之折算標準，以示懲儆。\n四、依刑事訴訟法第449條第1項前段、第454條第1項，刑法第32\n    0條第1項、第47條第1項、第41條第1項前段，刑法施行法第\n    1條之1，逕以簡易判決處如主文所示。\n五、如不服本判決，得自收受送達之日起10日內，向本院提起上\n    訴。"
  },
  "search": "臺灣花蓮地方法院刑事簡易判決100年度花簡字第627號聲請人臺灣花蓮地方法院檢察署檢察官被告張小萍上列被告因竊盜案件，經檢察官聲請以簡易判決處刑（100年度偵字第3102號），本院判決如下：主文張小萍犯竊盜罪，累犯，處有期徒刑肆月，如易科罰金，以新臺幣壹仟元折算壹日。事實及理由一、張小萍前於民國97年間因偽造文書案件，經臺灣宜蘭地方法院判處有期徒刑4月，並經減刑為有期徒刑2月，97年7月8日縮刑期滿執行完畢。詎仍不知悔改，意圖為自己不法之所有，於100年3月上旬某日，在財團法人佛教花蓮慈濟綜合醫院門診大樓1樓之「愛心小舖」（現為「精進小站」）店內，趁張娟寧在店內參觀而疏於注意之際，徒手竊取張娟寧所有並放置於店內置物架上之紅白色NOKIA手機1支（型號：N7230、序號：000000000000000），得手後再於100年3月18日將之以新臺幣1,000元之價格售予不知情之合眾電訊行。嗣因警執行查贓勤務循線查獲。案經花蓮縣警察局花蓮分局報請臺灣花蓮地方法院檢察署檢察官偵查後聲請簡易判決處刑。二、上揭事實，業據被告張小萍於偵查中供承不諱，並有被害人張娟寧之指訴、證人沈雅惠之證述明確，此外，復有被告將上開手機售予合重電訊之切結書、通聯調閱查詢單各乙紙在卷可憑，是本件事證明確，被告犯行應堪認定，應依法論科。三、核被告所為，係犯刑法第320條第1項之竊盜罪。被告有前揭科刑及執行記錄，有臺灣高等法院被告前案紀錄表附卷可稽，其於5年以內再犯本件有期徒刑以上之罪，為累犯，依刑法第47條第1項規定，加重其刑。爰審酌被告有多次前科紀錄，素行不良，有臺灣高等法院被告前案紀錄表1份在卷可查，不思循正當途徑獲取財物，因貪圖不法利益而竊取他人財物，竊後復將之變賣，增加查緝困難，兼衡其犯罪之動機、目的、手段等一切情狀，量處如主文所示之刑，並諭知易科罰金之折算標準，以示懲儆。四、依刑事訴訟法第449條第1項前段、第454條第1項，刑法第320條第1項、第47條第1項、第41條第1項前段，刑法施行法第1條之1，逕以簡易判決處如主文所示。五、如不服本判決，得自收受送達之日起10日內，向本院提起上訴。中華民國100年9月30日花蓮簡易庭法官林陳松上列正本證明與原本無異。如對本判決不服，應於送達後10日內，向本院提出上訴狀（應抄附繕本）告訴人或被害人如對於本判決不服者，應具備理由請求檢察官上訴，其上訴期間之計算係以檢察官收受判決正本之日期為準。中華民國100年9月30日書記官附錄本判決論罪之法律條文：中華民國刑法第320條第1項：意圖為自己或第三人不法之所有，而竊取他人之動產者，為竊盜罪，處5年以下有期徒刑、拘役或5百元以下罰金。",
  "characters": {
    "judges": [
      "林陳松"
    ],
    "prosecutors": [

    ],
    "lawyers": [

    ],
    "clerks": [
      "附錄本判決論罪之法律條文："
    ],
    "plaintiffs": [

    ],
    "defendants": [
      "張小萍"
    ],
    "prosecutor_office": [
      "臺灣花蓮地方法院檢察署檢察官"
    ],
    "creditors": [

    ],
    "debtors": [

    ],
    "judicial_associate_officer": [

    ]
  },
  "adjudged_at": "2011-09-30",
  "created_at": "2016-02-12 15:28:46",
  "updated_at": "2016-02-12 15:28:46"
}