{
  "identify": "ILD-100-易-322-20110930-1",
  "court": {
    "name": "臺灣宜蘭地方法院",
    "code": "ILD"
  },
  "division": {
    "name": "刑事",
    "code": "M"
  },
  "year": 100,
  "word": "易",
  "number": "322",
  "jcheck": "1",
  "reason": "竊盜",
  "content": "臺灣宜蘭地方法院刑事判決              100年度易字第322號\n公  訴  人  臺灣宜蘭地方法院檢察署檢察官\n被      告  鄒佳安\n上列被告因竊盜案件，經檢察官提起公訴（100年度偵字第1476\n號），本院判決如下：\n    主  文\n鄒佳安犯竊盜罪，處拘役拾日，如易科罰金，以新臺幣壹仟元折\n算壹日。\n    犯 罪 事 實\n一、鄒佳安因缺錢返回住所，竟意圖為自己不法之所有，於民國\n    100年3月24日下午6時55分許，在宜蘭縣羅東鎮○○路○段27\n    巷12號前空地，見蔡國忠所有車號2622－KN號自用小客車未\n    鎖，即進入車內，竊取蔡國忠所有放在排檔桿前方飲料架上\n    內有硬幣新台幣（下同）311元之布製鉛筆盒1個得手。旋即\n    為蔡國忠發現而報警，為警當場查獲。\n二、案經蔡國忠訴由宜蘭縣政府警察局羅東分局報請臺灣宜蘭地\n    方法院檢察署檢察官偵查起訴。\n    理  由\n一、按被告以外之人於審判外之言詞或書面陳述，除法律有規定\n    者外，不得作為證據。又被告以外之人於審判外之陳述，雖\n    不符合同法第159條之1至第159條之4之規定，但經當事人於\n    審判程序同意作為證據，法院審酌該言詞陳述或書面陳述作\n    成之情況，認為適當者，亦得為證據，刑事訴訟法第159條\n    第1項及第159條之5第1項定有明文。本院以下所採用被告鄒\n    佳安以外之人於審判外之言詞陳述，當事人於本院準備程序\n    及審判期日中均表示同意做為審理資料，本院審酌上開證據\n    資料製作時之情況，尚無違法不當之瑕疵，亦認為以之作為\n    證據應屬適當，依刑事訴訟法第159條之5第1項規定，認前\n    揭證據資料均有證據能力，合先敘明。\n二、被告對於上開犯罪事實，於警詢、偵查及本院審理時均坦承\n    不諱，且有告訴人蔡國忠於警詢之證述可參，復有贓物認領\n    保管單1紙在卷可憑，並有失竊現場照片及贓物照片存卷可\n    查。事證明確，被告犯行應堪認定。\n三、核被告所為，係犯刑法第320條第1項之竊盜罪。爰審酌被告\n    年輕識淺，因饑寒起盜心之情狀、其行為對被害人造成之損\n    害僅311元，尚屬輕微，並其生活狀況、智識程度不佳，及\n    犯罪後坦承犯行，尚知悔悟之態度等一切情狀，量處如主文\n    所示之刑，並諭知易科罰金之折算標準。\n據上論斷，應依刑事訴訟法第284條之1、第299條第1項前段，刑\n法第320條第1項，第41條第1項前段，刑法施行法第1條之1第1項\n、第2項前段判決如主文。\n本案經檢察官簡志祥到庭執行職務\n中    華    民    國   100    年    9     月    30    日\n                  刑事第四庭  法  官  謝佩玲\n以上正本證明與原本無異。\n如不服本判決應於收受送達後十日內向本院提出上訴書狀，並應\n敘述具體理由；其未敘述上述理由者，應於上訴期間屆滿後二十\n日內向本院補提理由書(均須按他造當事人之人數附繕本)「切勿\n逕送上級法院」。\n                              書記官  李玉雲\n中    華    民    國   100    年    9     月    30    日\n附錄本案論罪科刑法條全文：\n中華民國刑法第320條第1項\n意圖為自己或第三人不法之所有，而竊取他人之動產者，為竊盜\n罪，處5年以下有期徒刑、拘役或5百元以下罰金。",
  "structure": {
    "main": "鄒佳安犯竊盜罪，處拘役拾日，如易科罰金，以新臺幣壹仟元折\n算壹日。\n    犯 罪",
    "reason": "一、按被告以外之人於審判外之言詞或書面陳述，除法律有規定\n    者外，不得作為證據。又被告以外之人於審判外之陳述，雖\n    不符合同法第159條之1至第159條之4之規定，但經當事人於\n    審判程序同意作為證據，法院審酌該言詞陳述或書面陳述作\n    成之情況，認為適當者，亦得為證據，刑事訴訟法第159條\n    第1項及第159條之5第1項定有明文。本院以下所採用被告鄒\n    佳安以外之人於審判外之言詞陳述，當事人於本院準備程序\n    及審判期日中均表示同意做為審理資料，本院審酌上開證據\n    資料製作時之情況，尚無違法不當之瑕疵，亦認為以之作為\n    證據應屬適當，依刑事訴訟法第159條之5第1項規定，認前\n    揭證據資料均有證據能力，合先敘明。\n二、被告對於上開犯罪事實，於警詢、偵查及本院審理時均坦承\n    不諱，且有告訴人蔡國忠於警詢之證述可參，復有贓物認領\n    保管單1紙在卷可憑，並有失竊現場照片及贓物照片存卷可\n    查。事證明確，被告犯行應堪認定。\n三、核被告所為，係犯刑法第320條第1項之竊盜罪。爰審酌被告\n    年輕識淺，因饑寒起盜心之情狀、其行為對被害人造成之損\n    害僅311元，尚屬輕微，並其生活狀況、智識程度不佳，及\n    犯罪後坦承犯行，尚知悔悟之態度等一切情狀，量處如主文\n    所示之刑，並諭知易科罰金之折算標準。\n據上論斷，應依刑事訴訟法第284條之1、第299條第1項前段，刑\n法第320條第1項，第41條第1項前段，刑法施行法第1條之1第1項\n、第2項前段判決如主文。\n本案經檢察官簡志祥到庭執行職務"
  },
  "search": "臺灣宜蘭地方法院刑事判決100年度易字第322號公訴人臺灣宜蘭地方法院檢察署檢察官被告鄒佳安上列被告因竊盜案件，經檢察官提起公訴（100年度偵字第1476號），本院判決如下：主文鄒佳安犯竊盜罪，處拘役拾日，如易科罰金，以新臺幣壹仟元折算壹日。犯罪事實一、鄒佳安因缺錢返回住所，竟意圖為自己不法之所有，於民國100年3月24日下午6時55分許，在宜蘭縣羅東鎮○○路○段27巷12號前空地，見蔡國忠所有車號2622－KN號自用小客車未鎖，即進入車內，竊取蔡國忠所有放在排檔桿前方飲料架上內有硬幣新台幣（下同）311元之布製鉛筆盒1個得手。旋即為蔡國忠發現而報警，為警當場查獲。二、案經蔡國忠訴由宜蘭縣政府警察局羅東分局報請臺灣宜蘭地方法院檢察署檢察官偵查起訴。理由一、按被告以外之人於審判外之言詞或書面陳述，除法律有規定者外，不得作為證據。又被告以外之人於審判外之陳述，雖不符合同法第159條之1至第159條之4之規定，但經當事人於審判程序同意作為證據，法院審酌該言詞陳述或書面陳述作成之情況，認為適當者，亦得為證據，刑事訴訟法第159條第1項及第159條之5第1項定有明文。本院以下所採用被告鄒佳安以外之人於審判外之言詞陳述，當事人於本院準備程序及審判期日中均表示同意做為審理資料，本院審酌上開證據資料製作時之情況，尚無違法不當之瑕疵，亦認為以之作為證據應屬適當，依刑事訴訟法第159條之5第1項規定，認前揭證據資料均有證據能力，合先敘明。二、被告對於上開犯罪事實，於警詢、偵查及本院審理時均坦承不諱，且有告訴人蔡國忠於警詢之證述可參，復有贓物認領保管單1紙在卷可憑，並有失竊現場照片及贓物照片存卷可查。事證明確，被告犯行應堪認定。三、核被告所為，係犯刑法第320條第1項之竊盜罪。爰審酌被告年輕識淺，因饑寒起盜心之情狀、其行為對被害人造成之損害僅311元，尚屬輕微，並其生活狀況、智識程度不佳，及犯罪後坦承犯行，尚知悔悟之態度等一切情狀，量處如主文所示之刑，並諭知易科罰金之折算標準。據上論斷，應依刑事訴訟法第284條之1、第299條第1項前段，刑法第320條第1項，第41條第1項前段，刑法施行法第1條之1第1項、第2項前段判決如主文。本案經檢察官簡志祥到庭執行職務中華民國100年9月30日刑事第四庭法官謝佩玲以上正本證明與原本無異。如不服本判決應於收受送達後十日內向本院提出上訴書狀，並應敘述具體理由；其未敘述上述理由者，應於上訴期間屆滿後二十日內向本院補提理由書(均須按他造當事人之人數附繕本)「切勿逕送上級法院」。書記官李玉雲中華民國100年9月30日附錄本案論罪科刑法條全文：中華民國刑法第320條第1項意圖為自己或第三人不法之所有，而竊取他人之動產者，為竊盜罪，處5年以下有期徒刑、拘役或5百元以下罰金。",
  "characters": {
    "judges": [
      "謝佩玲"
    ],
    "prosecutors": [
      "簡志祥"
    ],
    "lawyers": [

    ],
    "clerks": [
      "李玉雲"
    ],
    "plaintiffs": [

    ],
    "defendants": [
      "鄒佳安"
    ],
    "prosecutor_office": [
      "臺灣宜蘭地方法院檢察署檢察官"
    ],
    "creditors": [

    ],
    "debtors": [

    ],
    "judicial_associate_officer": [

    ]
  },
  "adjudged_at": "2011-09-30",
  "created_at": "2016-02-12 15:37:41",
  "updated_at": "2016-02-12 15:37:41"
}