{
  "identify": "TPD-100-訴-1064-20110930-3",
  "court": {
    "name": "臺灣臺北地方法院",
    "code": "TPD"
  },
  "division": {
    "name": "刑事",
    "code": "M"
  },
  "year": 100,
  "word": "訴",
  "number": "1064",
  "jcheck": "3",
  "reason": "毒品危害防制條例",
  "content": "臺灣臺北地方法院刑事裁定             100年度訴字第1064號\n公  訴  人  臺灣臺北地方法院檢察署檢察官\n被      告  蘇國生\n指定辯護人  本院公設辯護人唐禎琪\n上列被告因毒品危害防制條例案件，本院裁定如下：\n    主  文\n蘇國生自民國壹佰年玖月參拾日起撤銷羈押。\n    理  由\n一、按羈押於其原因消滅時，應即撤銷羈押，將被告釋放，刑事\n    訴訟法第107條第1項定有明文。查被告蘇國生前經本院於民\n    國100年9月9 日起執行羈押。茲因被告另違反槍砲彈藥刀械\n    管制條例案件，經臺灣士林地方法院以98年度審訴字第 512\n    號判決判處有期徒刑1年10月、緩刑3年，嗣經臺灣板橋地方\n    法院以100 年度撤緩字第17號裁定撤銷上開緩刑之宣告確定\n    ，於100年9月30日起，經臺灣臺北地方法院檢察署檢察官移\n    送法務部矯正署臺北監獄執行，有該署檢察官100 年度執助\n    節字第1589號執行指揮書及臺灣高等法院被告前案紀錄表附\n    卷可稽。被告既已另因他案執行在監，應認原羈押原因已消\n    滅，爰予撤銷羈押。\n二、依刑事訴訟法第107條第1項、第121條第1項，裁定如主文。\n中    華    民    國   100    年    9     月    30    日\n                  刑事第十四庭  審判長法  官  吳冠霆\n                                      法  官  李殷君\n                                      法  官  賴武志\n以上正本證明與原本無異。\n如不服本裁定，應於裁定送達後5 日內向本院提出抗告狀。\n                                      書記官  劉麗英\n中    華    民    國   100    年    9     月    30    日",
  "structure": {
    "main": "蘇國生自民國壹佰年玖月參拾日起撤銷羈押。",
    "reason": "一、按羈押於其原因消滅時，應即撤銷羈押，將被告釋放，刑事\n    訴訟法第107條第1項定有明文。查被告蘇國生前經本院於民\n    國100年9月9 日起執行羈押。茲因被告另違反槍砲彈藥刀械\n    管制條例案件，經臺灣士林地方法院以98年度審訴字第 512\n    號判決判處有期徒刑1年10月、緩刑3年，嗣經臺灣板橋地方\n    法院以100 年度撤緩字第17號裁定撤銷上開緩刑之宣告確定\n    ，於100年9月30日起，經臺灣臺北地方法院檢察署檢察官移\n    送法務部矯正署臺北監獄執行，有該署檢察官100 年度執助\n    節字第1589號執行指揮書及臺灣高等法院被告前案紀錄表附\n    卷可稽。被告既已另因他案執行在監，應認原羈押原因已消\n    滅，爰予撤銷羈押。\n二、依刑事訴訟法第107條第1項、第121條第1項，裁定如主文。"
  },
  "search": "臺灣臺北地方法院刑事裁定100年度訴字第1064號公訴人臺灣臺北地方法院檢察署檢察官被告蘇國生指定辯護人本院公設辯護人唐禎琪上列被告因毒品危害防制條例案件，本院裁定如下：主文蘇國生自民國壹佰年玖月參拾日起撤銷羈押。理由一、按羈押於其原因消滅時，應即撤銷羈押，將被告釋放，刑事訴訟法第107條第1項定有明文。查被告蘇國生前經本院於民國100年9月9日起執行羈押。茲因被告另違反槍砲彈藥刀械管制條例案件，經臺灣士林地方法院以98年度審訴字第512號判決判處有期徒刑1年10月、緩刑3年，嗣經臺灣板橋地方法院以100年度撤緩字第17號裁定撤銷上開緩刑之宣告確定，於100年9月30日起，經臺灣臺北地方法院檢察署檢察官移送法務部矯正署臺北監獄執行，有該署檢察官100年度執助節字第1589號執行指揮書及臺灣高等法院被告前案紀錄表附卷可稽。被告既已另因他案執行在監，應認原羈押原因已消滅，爰予撤銷羈押。二、依刑事訴訟法第107條第1項、第121條第1項，裁定如主文。中華民國100年9月30日刑事第十四庭審判長法官吳冠霆法官李殷君法官賴武志以上正本證明與原本無異。如不服本裁定，應於裁定送達後5日內向本院提出抗告狀。書記官劉麗英中華民國100年9月30日",
  "characters": {
    "judges": [
      "吳冠霆",
      "李殷君",
      "賴武志"
    ],
    "prosecutors": [

    ],
    "lawyers": [

    ],
    "clerks": [
      "劉麗英"
    ],
    "plaintiffs": [

    ],
    "defendants": [
      "蘇國生"
    ],
    "prosecutor_office": [
      "臺灣臺北地方法院檢察署檢察官"
    ],
    "creditors": [

    ],
    "debtors": [

    ],
    "judicial_associate_officer": [

    ]
  },
  "adjudged_at": "2011-09-30",
  "created_at": "2016-02-12 15:34:43",
  "updated_at": "2016-02-12 15:34:43"
}