{
  "identify": "CYD-100-建-13-20111129-1",
  "court": {
    "name": "臺灣嘉義地方法院",
    "code": "CYD"
  },
  "division": {
    "name": "民事",
    "code": "V"
  },
  "year": 100,
  "word": "建",
  "number": "13",
  "jcheck": "1",
  "reason": "給付工程款",
  "content": "臺灣嘉義地方法院民事判決               100年度建字第13號\n原      告  張課即亞克工程行\n被      告  東大億營造股份有限公司\n法定代理人  李東晃\n上列當事人間請求給付工程款事件，本院於民國100年11月15日\n言詞辯論終結，判決如下：\n    主  文\n被告應給付原告新臺幣836,630元，及自民國100年5月25日起至\n清償日止，按週年利率5%計算之利息。\n原告其餘之訴駁回。\n訴訟費用由被告負擔71%，餘由原告負擔。\n    事實及理由\n甲、程序方面\n壹、按合併提起之事件，一為適用民事訴訟法第427條第1項之事\n    件，一為適用同條第2項之事件，如訴訟標的金額或價額合\n    併計算已逾同法條所定新臺幣（下同）50萬元之數額，則應\n    適用通常訴訟程序（民國94年11月25日台灣高等法院暨所屬\n    法院研討結果之多數說、81年6月1日司法院第19期司法業務\n    研究會司法院第一廳研究意見參照）。查原告起訴請求被告\n    給付票款880,000元、工程款290,700元，雖一為適用民事訴\n    訟法第427條第1項之事件，一為適用同條第2項之事件，然\n    依前開說明，訴訟標的金額合併計算已逾50萬元之數額，本\n    件訴訟程序自應適用通常訴訟程序，合先敘明。\n貳、次按言詞辯論期日，當事人之一造不到場者，得依到場當事\n    人之聲請，由其一造辯論而為判決，民事訴訟法第385條第1\n    項前段定有明文。查本件被告經合法通知，而未於言詞辯論\n    期日到場，有本院言詞辯論筆錄、報到單、送達證書等在卷\n    可證；且核無民事訴訟法第386條各款所列情形，爰依原告\n    之聲請，由其一造辯論而為判決。\n乙、實體方面\n壹、原告主張：\n一、被告簽發號碼分別為0000000、0000000、0000000，面額各\n    為185,000元、200,000元、225,000元之支票3張，交由原告\n    向他人借款共61萬元，兩造各分得一半使用，其中305,000\n    元票款應由被告清償，原告持有前開支票，爰請求被告給付\n    305,000元。被告另簽發號碼為0000000、面額為270,000元\n    之支票，由原告背書後持向他人借款，嗣執票人向原告請求\n    給付票款，業由原告清償完畢，並取得該支票。爰依票據關\n    係請求被告給付前開票款。\n二、兩造於100年3月30日訂立工程合約，由被告將其所承包台灣\n    糖業公司大林糖廠行政大樓第二期增建工程之油漆工程轉包\n    與原告，原告已於同年5月10日完工且驗收，惟被告仍拒絕\n    給付工程款290,700元，迭經催討，仍不置理，爰依系爭工\n    程契約請求被告給付前開工程款。\n三、對被告抗辯之陳述：\n（一）原告所承包之系爭工程均已完工，僅係有部分手印於油漆\n      上之小瑕疵，因被告拒不給付系爭工程款，故原告迄今仍\n      未修補。\n（二）依系爭契約約定，於系爭工程完工後，被告即應給付系爭\n      工程款之90%，其餘10%則於業主驗收合格後，被告始有給\n      付之義務。\n四、並聲明：（一）被告應給付原告1,170,700元，及自100年5\n    月25日起至清償日止，按週年利率5%計算之利息。（二）訴\n    訟費用由被告負擔。\n貳、被告則以：\n一、系爭號碼分別為0000000、0000000、0000000，面額各為185\n    , 000元、200,000元、225,000元之支票3張，係兩造共同使\n    用，應各負擔305,000元，原告尚借支票85,000元，故原告\n    應負擔390,000元。\n二、原告未完成其所承包之系爭油漆工程，經協調改善部分工程\n    ，原告仍置之不理，致被告遭業主罰違約金58萬元與履約保\n    證金29萬元，前開損失應由原告負責等語，資為抗辯。\n參、得心證之理由\n一、按執票人於提示期限內，為付款之提示而被拒絕時，對於前\n    手得行使追索權；執票人向支票債務人行使追索權時，得請\n    求自為付款提示日起之利息，如無約定利率者，依年利六釐\n    計算，票據法第131條第1項前段、第133條分別著有明文。\n    查：\n（一）系爭票據號碼分別為0000000、0000000、0000000，面額\n      各為185,000元、200,000元、225,000元之支票3張，係被\n      告所簽發，但為兩造共同使用，應各負擔305,000元；原\n      告分別於100年5月25日、100年5月10日、100年5月25日提\n      示前開支票後不獲付款等事實，為兩造所不爭，並有支票\n      與其退票理由單在卷可證，自堪信為真實。且原告主張就\n      前開支票3張，僅請求被告給付前開305,000元（見本院10\n      0年10月18日言詞辯論筆錄），則原告依前開追索權之規\n      定請求被告給付前開305,000元，自屬有據。\n（二）被告所簽發號碼為0000000、面額為270,000元之支票，經\n      原告於100年5月20日提示不獲付款之事實，亦有支票與其\n      退票理由單在卷可證，亦堪信為真實。故原告依前開追索\n      權之規定請求被告給付前開270,000元，亦屬有據。\n（三）故原告依前開票據關係，請求被告給付票款合計575,000\n      元，與自100年5月25日起至清償日止，按週年利率5%計算\n      之利息，應予准許；至超過部分之其餘請求，則無理由，\n      應予駁回。\n（四）至被告所抗辯原告尚借支票85,000元云云，然被告迄未舉\n      證證明其前開抗辯為真正，自不足採。\n二、次按民法第490條規定：稱承攬者，謂當事人約定，一方為\n    他方完成一定之工作，他方俟工作完成，給付報酬之契約。\n    又同法第505條第1項規定：報酬應於工作交付時給付之，無\n    須交付者，應於工作完成時給付之；同條第2項規定：工作\n    係分部交付，而報酬係就各部分定之者，應於每部分交付時\n    ，給付該部分之報酬。足見除當事人間另有特約外，定作人\n    僅對於承攬人完成之工作，負有給付報酬之義務（最高法院\n    84年度台上字第2227號判決要旨參照）。另按遲延之債務，\n    以支付金錢為標的者，債權人得請求依法定利率計算之遲延\n    利息；但約定利率較高者，仍從其約定利率；應負利息之債\n    務，其利率未經約定，亦無法律可據者，週年利率為5%，民\n    法第233條第1項、第203條亦有規定。查：\n（一）被告將其所承包台灣糖業公司大林糖廠行政大樓第二期增\n      建工程之油漆工程轉包與原告，工程款為290,700元，且\n      系爭工程已於100年5月10日完工與驗收等事實，為兩造所\n      不爭；與兩造約定若工程完工，被告即應給付系爭工程款\n      90%，其餘10%則於驗收合格後給付；及系爭工程雖完工但\n      因有小瑕疵，而未驗收合格等事實，亦據證人陳寶田結證\n      明確（見本院100年11月15日言詞辯論筆錄），復有工程\n      合約書在卷可證，自均堪信為真實。\n（二）則兩造就系爭工程款報酬既另有前開特約，且系爭工程未\n      驗收合格，則依前開說明，原告於目前僅得請求被告給付\n      系爭工程款290,700元之90%即261,630元，至超過部分之\n      其餘請求則屬無據。\n（三）又被告就前開應給付之工程款報酬，自100年5月11日起即\n      應負遲延責任，原告自得請求被告給付前開261,630元之\n      自100年5月11日起至清償日止之法定遲延利息。然原告僅\n      請求被告給付前開261,630元之自100年5月25日起至清償\n      日止之法定遲延利息，自屬有據；至超過部分之其餘請求\n      則屬無據。\n（四）故原告依系爭承攬契約請求被告給付261,630元，及自100\n      年5月25日起至清償日止，按週年利率5%計算之利息，為\n      有理由；至超過部分之其餘請求則屬無據。\n（五）至被告雖抗辯原告未完成所承包之系爭油漆工程，致被告\n      遭業主罰違約金58萬元與履約保證金29萬元，前開損失應\n      由原告負責云云。然被告亦未舉證證明其前開抗辯為真正\n      ，自不足取。\n三、綜上所述，原告依票據追索權、承攬契約報酬請求權等法律\n    關係，請求被告給付836,630元（計算方式：575,000元＋26\n    1,630元＝836,630元），及自100年5月25日起至清償日止，\n    按週年利率5%計算之利息，為有理由，應予准許；至超過部\n    分之其餘請求，則無理由，應予駁回。\n四、按法院為終局判決時，應依職權為訴訟費用之裁判；各當事\n    人一部勝訴、一部敗訴者，其訴訟費用，由法院酌量情形，\n    命兩造以比例分擔或命一造負擔，或命兩造各自負擔其支出\n    之訴訟費用，民事訴訟法第87條第1項、第79條分別定有明\n    文。查本院既為被告前開一部勝訴、一部敗訴之終局判決，\n    則法院酌量前開勝訴與敗訴比例等情形，因認本件訴訟費用\n    自應由被告負擔71%，餘由原告負擔，爰判決如主文第3項所\n    示。\n中    華    民    國    100    年    11   月    29    日\n                  民一庭法  官  陳和\n以上正本係照原本作成\n如對本判決上訴須於判決送達後20日內向本院提出上訴狀\n如委任律師提起上訴者，應一併繳納上訴審裁判費。\n中    華    民    國    100    年    11   月    29    日\n                            書記官  劉怡欣",
  "structure": {
    "main": "被告應給付原告新臺幣836,630元，及自民國100年5月25日起至\n清償日止，按週年利率5%計算之利息。\n原告其餘之訴駁回。\n訴訟費用由被告負擔71%，餘由原告負擔。",
    "fact": "甲、程序方面\n壹、按合併提起之事件，一為適用民事訴訟法第427條第1項之事\n    件，一為適用同條第2項之事件，如訴訟標的金額或價額合\n    併計算已逾同法條所定新臺幣（下同）50萬元之數額，則應\n    適用通常訴訟程序（民國94年11月25日台灣高等法院暨所屬\n    法院研討結果之多數說、81年6月1日司法院第19期司法業務\n    研究會司法院第一廳研究意見參照）。查原告起訴請求被告\n    給付票款880,000元、工程款290,700元，雖一為適用民事訴\n    訟法第427條第1項之事件，一為適用同條第2項之事件，然\n    依前開說明，訴訟標的金額合併計算已逾50萬元之數額，本\n    件訴訟程序自應適用通常訴訟程序，合先敘明。\n貳、次按言詞辯論期日，當事人之一造不到場者，得依到場當事\n    人之聲請，由其一造辯論而為判決，民事訴訟法第385條第1\n    項前段定有明文。查本件被告經合法通知，而未於言詞辯論\n    期日到場，有本院言詞辯論筆錄、報到單、送達證書等在卷\n    可證；且核無民事訴訟法第386條各款所列情形，爰依原告\n    之聲請，由其一造辯論而為判決。\n乙、實體方面\n壹、原告主張：\n一、被告簽發號碼分別為0000000、0000000、0000000，面額各\n    為185,000元、200,000元、225,000元之支票3張，交由原告\n    向他人借款共61萬元，兩造各分得一半使用，其中305,000\n    元票款應由被告清償，原告持有前開支票，爰請求被告給付\n    305,000元。被告另簽發號碼為0000000、面額為270,000元\n    之支票，由原告背書後持向他人借款，嗣執票人向原告請求\n    給付票款，業由原告清償完畢，並取得該支票。爰依票據關\n    係請求被告給付前開票款。\n二、兩造於100年3月30日訂立工程合約，由被告將其所承包台灣\n    糖業公司大林糖廠行政大樓第二期增建工程之油漆工程轉包\n    與原告，原告已於同年5月10日完工且驗收，惟被告仍拒絕\n    給付工程款290,700元，迭經催討，仍不置理，爰依系爭工\n    程契約請求被告給付前開工程款。\n三、對被告抗辯之陳述：\n（一）原告所承包之系爭工程均已完工，僅係有部分手印於油漆\n      上之小瑕疵，因被告拒不給付系爭工程款，故原告迄今仍\n      未修補。\n（二）依系爭契約約定，於系爭工程完工後，被告即應給付系爭\n      工程款之90%，其餘10%則於業主驗收合格後，被告始有給\n      付之義務。\n四、並聲明：（一）被告應給付原告1,170,700元，及自100年5\n    月25日起至清償日止，按週年利率5%計算之利息。（二）訴\n    訟費用由被告負擔。\n貳、被告則以：\n一、系爭號碼分別為0000000、0000000、0000000，面額各為185\n    , 000元、200,000元、225,000元之支票3張，係兩造共同使\n    用，應各負擔305,000元，原告尚借支票85,000元，故原告\n    應負擔390,000元。\n二、原告未完成其所承包之系爭油漆工程，經協調改善部分工程\n    ，原告仍置之不理，致被告遭業主罰違約金58萬元與履約保\n    證金29萬元，前開損失應由原告負責等語，資為抗辯。\n參、得心證之理由\n一、按執票人於提示期限內，為付款之提示而被拒絕時，對於前\n    手得行使追索權；執票人向支票債務人行使追索權時，得請\n    求自為付款提示日起之利息，如無約定利率者，依年利六釐\n    計算，票據法第131條第1項前段、第133條分別著有明文。\n    查：\n（一）系爭票據號碼分別為0000000、0000000、0000000，面額\n      各為185,000元、200,000元、225,000元之支票3張，係被\n      告所簽發，但為兩造共同使用，應各負擔305,000元；原\n      告分別於100年5月25日、100年5月10日、100年5月25日提\n      示前開支票後不獲付款等事實，為兩造所不爭，並有支票\n      與其退票理由單在卷可證，自堪信為真實。且原告主張就\n      前開支票3張，僅請求被告給付前開305,000元（見本院10\n      0年10月18日言詞辯論筆錄），則原告依前開追索權之規\n      定請求被告給付前開305,000元，自屬有據。\n（二）被告所簽發號碼為0000000、面額為270,000元之支票，經\n      原告於100年5月20日提示不獲付款之事實，亦有支票與其\n      退票理由單在卷可證，亦堪信為真實。故原告依前開追索\n      權之規定請求被告給付前開270,000元，亦屬有據。\n（三）故原告依前開票據關係，請求被告給付票款合計575,000\n      元，與自100年5月25日起至清償日止，按週年利率5%計算\n      之利息，應予准許；至超過部分之其餘請求，則無理由，\n      應予駁回。\n（四）至被告所抗辯原告尚借支票85,000元云云，然被告迄未舉\n      證證明其前開抗辯為真正，自不足採。\n二、次按民法第490條規定：稱承攬者，謂當事人約定，一方為\n    他方完成一定之工作，他方俟工作完成，給付報酬之契約。\n    又同法第505條第1項規定：報酬應於工作交付時給付之，無\n    須交付者，應於工作完成時給付之；同條第2項規定：工作\n    係分部交付，而報酬係就各部分定之者，應於每部分交付時\n    ，給付該部分之報酬。足見除當事人間另有特約外，定作人\n    僅對於承攬人完成之工作，負有給付報酬之義務（最高法院\n    84年度台上字第2227號判決要旨參照）。另按遲延之債務，\n    以支付金錢為標的者，債權人得請求依法定利率計算之遲延\n    利息；但約定利率較高者，仍從其約定利率；應負利息之債\n    務，其利率未經約定，亦無法律可據者，週年利率為5%，民\n    法第233條第1項、第203條亦有規定。查：\n（一）被告將其所承包台灣糖業公司大林糖廠行政大樓第二期增\n      建工程之油漆工程轉包與原告，工程款為290,700元，且\n      系爭工程已於100年5月10日完工與驗收等事實，為兩造所\n      不爭；與兩造約定若工程完工，被告即應給付系爭工程款\n      90%，其餘10%則於驗收合格後給付；及系爭工程雖完工但\n      因有小瑕疵，而未驗收合格等事實，亦據證人陳寶田結證\n      明確（見本院100年11月15日言詞辯論筆錄），復有工程\n      合約書在卷可證，自均堪信為真實。\n（二）則兩造就系爭工程款報酬既另有前開特約，且系爭工程未\n      驗收合格，則依前開說明，原告於目前僅得請求被告給付\n      系爭工程款290,700元之90%即261,630元，至超過部分之\n      其餘請求則屬無據。\n（三）又被告就前開應給付之工程款報酬，自100年5月11日起即\n      應負遲延責任，原告自得請求被告給付前開261,630元之\n      自100年5月11日起至清償日止之法定遲延利息。然原告僅\n      請求被告給付前開261,630元之自100年5月25日起至清償\n      日止之法定遲延利息，自屬有據；至超過部分之其餘請求\n      則屬無據。\n（四）故原告依系爭承攬契約請求被告給付261,630元，及自100\n      年5月25日起至清償日止，按週年利率5%計算之利息，為\n      有理由；至超過部分之其餘請求則屬無據。\n（五）至被告雖抗辯原告未完成所承包之系爭油漆工程，致被告\n      遭業主罰違約金58萬元與履約保證金29萬元，前開損失應\n      由原告負責云云。然被告亦未舉證證明其前開抗辯為真正\n      ，自不足取。\n三、綜上所述，原告依票據追索權、承攬契約報酬請求權等法律\n    關係，請求被告給付836,630元（計算方式：575,000元＋26\n    1,630元＝836,630元），及自100年5月25日起至清償日止，\n    按週年利率5%計算之利息，為有理由，應予准許；至超過部\n    分之其餘請求，則無理由，應予駁回。\n四、按法院為終局判決時，應依職權為訴訟費用之裁判；各當事\n    人一部勝訴、一部敗訴者，其訴訟費用，由法院酌量情形，\n    命兩造以比例分擔或命一造負擔，或命兩造各自負擔其支出\n    之訴訟費用，民事訴訟法第87條第1項、第79條分別定有明\n    文。查本院既為被告前開一部勝訴、一部敗訴之終局判決，\n    則法院酌量前開勝訴與敗訴比例等情形，因認本件訴訟費用\n    自應由被告負擔71%，餘由原告負擔，爰判決如主文第3項所\n    示。",
    "reason": "甲、程序方面\n壹、按合併提起之事件，一為適用民事訴訟法第427條第1項之事\n    件，一為適用同條第2項之事件，如訴訟標的金額或價額合\n    併計算已逾同法條所定新臺幣（下同）50萬元之數額，則應\n    適用通常訴訟程序（民國94年11月25日台灣高等法院暨所屬\n    法院研討結果之多數說、81年6月1日司法院第19期司法業務\n    研究會司法院第一廳研究意見參照）。查原告起訴請求被告\n    給付票款880,000元、工程款290,700元，雖一為適用民事訴\n    訟法第427條第1項之事件，一為適用同條第2項之事件，然\n    依前開說明，訴訟標的金額合併計算已逾50萬元之數額，本\n    件訴訟程序自應適用通常訴訟程序，合先敘明。\n貳、次按言詞辯論期日，當事人之一造不到場者，得依到場當事\n    人之聲請，由其一造辯論而為判決，民事訴訟法第385條第1\n    項前段定有明文。查本件被告經合法通知，而未於言詞辯論\n    期日到場，有本院言詞辯論筆錄、報到單、送達證書等在卷\n    可證；且核無民事訴訟法第386條各款所列情形，爰依原告\n    之聲請，由其一造辯論而為判決。\n乙、實體方面\n壹、原告主張：\n一、被告簽發號碼分別為0000000、0000000、0000000，面額各\n    為185,000元、200,000元、225,000元之支票3張，交由原告\n    向他人借款共61萬元，兩造各分得一半使用，其中305,000\n    元票款應由被告清償，原告持有前開支票，爰請求被告給付\n    305,000元。被告另簽發號碼為0000000、面額為270,000元\n    之支票，由原告背書後持向他人借款，嗣執票人向原告請求\n    給付票款，業由原告清償完畢，並取得該支票。爰依票據關\n    係請求被告給付前開票款。\n二、兩造於100年3月30日訂立工程合約，由被告將其所承包台灣\n    糖業公司大林糖廠行政大樓第二期增建工程之油漆工程轉包\n    與原告，原告已於同年5月10日完工且驗收，惟被告仍拒絕\n    給付工程款290,700元，迭經催討，仍不置理，爰依系爭工\n    程契約請求被告給付前開工程款。\n三、對被告抗辯之陳述：\n（一）原告所承包之系爭工程均已完工，僅係有部分手印於油漆\n      上之小瑕疵，因被告拒不給付系爭工程款，故原告迄今仍\n      未修補。\n（二）依系爭契約約定，於系爭工程完工後，被告即應給付系爭\n      工程款之90%，其餘10%則於業主驗收合格後，被告始有給\n      付之義務。\n四、並聲明：（一）被告應給付原告1,170,700元，及自100年5\n    月25日起至清償日止，按週年利率5%計算之利息。（二）訴\n    訟費用由被告負擔。\n貳、被告則以：\n一、系爭號碼分別為0000000、0000000、0000000，面額各為185\n    , 000元、200,000元、225,000元之支票3張，係兩造共同使\n    用，應各負擔305,000元，原告尚借支票85,000元，故原告\n    應負擔390,000元。\n二、原告未完成其所承包之系爭油漆工程，經協調改善部分工程\n    ，原告仍置之不理，致被告遭業主罰違約金58萬元與履約保\n    證金29萬元，前開損失應由原告負責等語，資為抗辯。\n參、得心證之理由\n一、按執票人於提示期限內，為付款之提示而被拒絕時，對於前\n    手得行使追索權；執票人向支票債務人行使追索權時，得請\n    求自為付款提示日起之利息，如無約定利率者，依年利六釐\n    計算，票據法第131條第1項前段、第133條分別著有明文。\n    查：\n（一）系爭票據號碼分別為0000000、0000000、0000000，面額\n      各為185,000元、200,000元、225,000元之支票3張，係被\n      告所簽發，但為兩造共同使用，應各負擔305,000元；原\n      告分別於100年5月25日、100年5月10日、100年5月25日提\n      示前開支票後不獲付款等事實，為兩造所不爭，並有支票\n      與其退票理由單在卷可證，自堪信為真實。且原告主張就\n      前開支票3張，僅請求被告給付前開305,000元（見本院10\n      0年10月18日言詞辯論筆錄），則原告依前開追索權之規\n      定請求被告給付前開305,000元，自屬有據。\n（二）被告所簽發號碼為0000000、面額為270,000元之支票，經\n      原告於100年5月20日提示不獲付款之事實，亦有支票與其\n      退票理由單在卷可證，亦堪信為真實。故原告依前開追索\n      權之規定請求被告給付前開270,000元，亦屬有據。\n（三）故原告依前開票據關係，請求被告給付票款合計575,000\n      元，與自100年5月25日起至清償日止，按週年利率5%計算\n      之利息，應予准許；至超過部分之其餘請求，則無理由，\n      應予駁回。\n（四）至被告所抗辯原告尚借支票85,000元云云，然被告迄未舉\n      證證明其前開抗辯為真正，自不足採。\n二、次按民法第490條規定：稱承攬者，謂當事人約定，一方為\n    他方完成一定之工作，他方俟工作完成，給付報酬之契約。\n    又同法第505條第1項規定：報酬應於工作交付時給付之，無\n    須交付者，應於工作完成時給付之；同條第2項規定：工作\n    係分部交付，而報酬係就各部分定之者，應於每部分交付時\n    ，給付該部分之報酬。足見除當事人間另有特約外，定作人\n    僅對於承攬人完成之工作，負有給付報酬之義務（最高法院\n    84年度台上字第2227號判決要旨參照）。另按遲延之債務，\n    以支付金錢為標的者，債權人得請求依法定利率計算之遲延\n    利息；但約定利率較高者，仍從其約定利率；應負利息之債\n    務，其利率未經約定，亦無法律可據者，週年利率為5%，民\n    法第233條第1項、第203條亦有規定。查：\n（一）被告將其所承包台灣糖業公司大林糖廠行政大樓第二期增\n      建工程之油漆工程轉包與原告，工程款為290,700元，且\n      系爭工程已於100年5月10日完工與驗收等事實，為兩造所\n      不爭；與兩造約定若工程完工，被告即應給付系爭工程款\n      90%，其餘10%則於驗收合格後給付；及系爭工程雖完工但\n      因有小瑕疵，而未驗收合格等事實，亦據證人陳寶田結證\n      明確（見本院100年11月15日言詞辯論筆錄），復有工程\n      合約書在卷可證，自均堪信為真實。\n（二）則兩造就系爭工程款報酬既另有前開特約，且系爭工程未\n      驗收合格，則依前開說明，原告於目前僅得請求被告給付\n      系爭工程款290,700元之90%即261,630元，至超過部分之\n      其餘請求則屬無據。\n（三）又被告就前開應給付之工程款報酬，自100年5月11日起即\n      應負遲延責任，原告自得請求被告給付前開261,630元之\n      自100年5月11日起至清償日止之法定遲延利息。然原告僅\n      請求被告給付前開261,630元之自100年5月25日起至清償\n      日止之法定遲延利息，自屬有據；至超過部分之其餘請求\n      則屬無據。\n（四）故原告依系爭承攬契約請求被告給付261,630元，及自100\n      年5月25日起至清償日止，按週年利率5%計算之利息，為\n      有理由；至超過部分之其餘請求則屬無據。\n（五）至被告雖抗辯原告未完成所承包之系爭油漆工程，致被告\n      遭業主罰違約金58萬元與履約保證金29萬元，前開損失應\n      由原告負責云云。然被告亦未舉證證明其前開抗辯為真正\n      ，自不足取。\n三、綜上所述，原告依票據追索權、承攬契約報酬請求權等法律\n    關係，請求被告給付836,630元（計算方式：575,000元＋26\n    1,630元＝836,630元），及自100年5月25日起至清償日止，\n    按週年利率5%計算之利息，為有理由，應予准許；至超過部\n    分之其餘請求，則無理由，應予駁回。\n四、按法院為終局判決時，應依職權為訴訟費用之裁判；各當事\n    人一部勝訴、一部敗訴者，其訴訟費用，由法院酌量情形，\n    命兩造以比例分擔或命一造負擔，或命兩造各自負擔其支出\n    之訴訟費用，民事訴訟法第87條第1項、第79條分別定有明\n    文。查本院既為被告前開一部勝訴、一部敗訴之終局判決，\n    則法院酌量前開勝訴與敗訴比例等情形，因認本件訴訟費用\n    自應由被告負擔71%，餘由原告負擔，爰判決如主文第3項所\n    示。"
  },
  "search": "臺灣嘉義地方法院民事判決100年度建字第13號原告張課即亞克工程行被告東大億營造股份有限公司法定代理人李東晃上列當事人間請求給付工程款事件，本院於民國100年11月15日言詞辯論終結，判決如下：主文被告應給付原告新臺幣836,630元，及自民國100年5月25日起至清償日止，按週年利率5%計算之利息。原告其餘之訴駁回。訴訟費用由被告負擔71%，餘由原告負擔。事實及理由甲、程序方面壹、按合併提起之事件，一為適用民事訴訟法第427條第1項之事件，一為適用同條第2項之事件，如訴訟標的金額或價額合併計算已逾同法條所定新臺幣（下同）50萬元之數額，則應適用通常訴訟程序（民國94年11月25日台灣高等法院暨所屬法院研討結果之多數說、81年6月1日司法院第19期司法業務研究會司法院第一廳研究意見參照）。查原告起訴請求被告給付票款880,000元、工程款290,700元，雖一為適用民事訴訟法第427條第1項之事件，一為適用同條第2項之事件，然依前開說明，訴訟標的金額合併計算已逾50萬元之數額，本件訴訟程序自應適用通常訴訟程序，合先敘明。貳、次按言詞辯論期日，當事人之一造不到場者，得依到場當事人之聲請，由其一造辯論而為判決，民事訴訟法第385條第1項前段定有明文。查本件被告經合法通知，而未於言詞辯論期日到場，有本院言詞辯論筆錄、報到單、送達證書等在卷可證；且核無民事訴訟法第386條各款所列情形，爰依原告之聲請，由其一造辯論而為判決。乙、實體方面壹、原告主張：一、被告簽發號碼分別為0000000、0000000、0000000，面額各為185,000元、200,000元、225,000元之支票3張，交由原告向他人借款共61萬元，兩造各分得一半使用，其中305,000元票款應由被告清償，原告持有前開支票，爰請求被告給付305,000元。被告另簽發號碼為0000000、面額為270,000元之支票，由原告背書後持向他人借款，嗣執票人向原告請求給付票款，業由原告清償完畢，並取得該支票。爰依票據關係請求被告給付前開票款。二、兩造於100年3月30日訂立工程合約，由被告將其所承包台灣糖業公司大林糖廠行政大樓第二期增建工程之油漆工程轉包與原告，原告已於同年5月10日完工且驗收，惟被告仍拒絕給付工程款290,700元，迭經催討，仍不置理，爰依系爭工程契約請求被告給付前開工程款。三、對被告抗辯之陳述：（一）原告所承包之系爭工程均已完工，僅係有部分手印於油漆上之小瑕疵，因被告拒不給付系爭工程款，故原告迄今仍未修補。（二）依系爭契約約定，於系爭工程完工後，被告即應給付系爭工程款之90%，其餘10%則於業主驗收合格後，被告始有給付之義務。四、並聲明：（一）被告應給付原告1,170,700元，及自100年5月25日起至清償日止，按週年利率5%計算之利息。（二）訴訟費用由被告負擔。貳、被告則以：一、系爭號碼分別為0000000、0000000、0000000，面額各為185,000元、200,000元、225,000元之支票3張，係兩造共同使用，應各負擔305,000元，原告尚借支票85,000元，故原告應負擔390,000元。二、原告未完成其所承包之系爭油漆工程，經協調改善部分工程，原告仍置之不理，致被告遭業主罰違約金58萬元與履約保證金29萬元，前開損失應由原告負責等語，資為抗辯。參、得心證之理由一、按執票人於提示期限內，為付款之提示而被拒絕時，對於前手得行使追索權；執票人向支票債務人行使追索權時，得請求自為付款提示日起之利息，如無約定利率者，依年利六釐計算，票據法第131條第1項前段、第133條分別著有明文。查：（一）系爭票據號碼分別為0000000、0000000、0000000，面額各為185,000元、200,000元、225,000元之支票3張，係被告所簽發，但為兩造共同使用，應各負擔305,000元；原告分別於100年5月25日、100年5月10日、100年5月25日提示前開支票後不獲付款等事實，為兩造所不爭，並有支票與其退票理由單在卷可證，自堪信為真實。且原告主張就前開支票3張，僅請求被告給付前開305,000元（見本院100年10月18日言詞辯論筆錄），則原告依前開追索權之規定請求被告給付前開305,000元，自屬有據。（二）被告所簽發號碼為0000000、面額為270,000元之支票，經原告於100年5月20日提示不獲付款之事實，亦有支票與其退票理由單在卷可證，亦堪信為真實。故原告依前開追索權之規定請求被告給付前開270,000元，亦屬有據。（三）故原告依前開票據關係，請求被告給付票款合計575,000元，與自100年5月25日起至清償日止，按週年利率5%計算之利息，應予准許；至超過部分之其餘請求，則無理由，應予駁回。（四）至被告所抗辯原告尚借支票85,000元云云，然被告迄未舉證證明其前開抗辯為真正，自不足採。二、次按民法第490條規定：稱承攬者，謂當事人約定，一方為他方完成一定之工作，他方俟工作完成，給付報酬之契約。又同法第505條第1項規定：報酬應於工作交付時給付之，無須交付者，應於工作完成時給付之；同條第2項規定：工作係分部交付，而報酬係就各部分定之者，應於每部分交付時，給付該部分之報酬。足見除當事人間另有特約外，定作人僅對於承攬人完成之工作，負有給付報酬之義務（最高法院84年度台上字第2227號判決要旨參照）。另按遲延之債務，以支付金錢為標的者，債權人得請求依法定利率計算之遲延利息；但約定利率較高者，仍從其約定利率；應負利息之債務，其利率未經約定，亦無法律可據者，週年利率為5%，民法第233條第1項、第203條亦有規定。查：（一）被告將其所承包台灣糖業公司大林糖廠行政大樓第二期增建工程之油漆工程轉包與原告，工程款為290,700元，且系爭工程已於100年5月10日完工與驗收等事實，為兩造所不爭；與兩造約定若工程完工，被告即應給付系爭工程款90%，其餘10%則於驗收合格後給付；及系爭工程雖完工但因有小瑕疵，而未驗收合格等事實，亦據證人陳寶田結證明確（見本院100年11月15日言詞辯論筆錄），復有工程合約書在卷可證，自均堪信為真實。（二）則兩造就系爭工程款報酬既另有前開特約，且系爭工程未驗收合格，則依前開說明，原告於目前僅得請求被告給付系爭工程款290,700元之90%即261,630元，至超過部分之其餘請求則屬無據。（三）又被告就前開應給付之工程款報酬，自100年5月11日起即應負遲延責任，原告自得請求被告給付前開261,630元之自100年5月11日起至清償日止之法定遲延利息。然原告僅請求被告給付前開261,630元之自100年5月25日起至清償日止之法定遲延利息，自屬有據；至超過部分之其餘請求則屬無據。（四）故原告依系爭承攬契約請求被告給付261,630元，及自100年5月25日起至清償日止，按週年利率5%計算之利息，為有理由；至超過部分之其餘請求則屬無據。（五）至被告雖抗辯原告未完成所承包之系爭油漆工程，致被告遭業主罰違約金58萬元與履約保證金29萬元，前開損失應由原告負責云云。然被告亦未舉證證明其前開抗辯為真正，自不足取。三、綜上所述，原告依票據追索權、承攬契約報酬請求權等法律關係，請求被告給付836,630元（計算方式：575,000元＋261,630元＝836,630元），及自100年5月25日起至清償日止，按週年利率5%計算之利息，為有理由，應予准許；至超過部分之其餘請求，則無理由，應予駁回。四、按法院為終局判決時，應依職權為訴訟費用之裁判；各當事人一部勝訴、一部敗訴者，其訴訟費用，由法院酌量情形，命兩造以比例分擔或命一造負擔，或命兩造各自負擔其支出之訴訟費用，民事訴訟法第87條第1項、第79條分別定有明文。查本院既為被告前開一部勝訴、一部敗訴之終局判決，則法院酌量前開勝訴與敗訴比例等情形，因認本件訴訟費用自應由被告負擔71%，餘由原告負擔，爰判決如主文第3項所示。中華民國100年11月29日民一庭法官陳和以上正本係照原本作成如對本判決上訴須於判決送達後20日內向本院提出上訴狀如委任律師提起上訴者，應一併繳納上訴審裁判費。中華民國100年11月29日書記官劉怡欣",
  "characters": {
    "judges": [
      "陳和"
    ],
    "prosecutors": [

    ],
    "lawyers": [
      "如委任"
    ],
    "clerks": [

    ],
    "plaintiffs": [
      "張課即亞克工程行"
    ],
    "defendants": [
      "東大億營造股份有限公司"
    ],
    "prosecutor_office": [

    ],
    "creditors": [

    ],
    "debtors": [

    ],
    "judicial_associate_officer": [

    ]
  },
  "adjudged_at": "2011-11-29",
  "created_at": "2016-02-13 00:58:44",
  "updated_at": "2016-02-13 00:58:44"
}