{
  "identify": "PCD-100-簡上-903-20111130-1",
  "court": {
    "name": "臺灣新北地方法院",
    "code": "PCD"
  },
  "division": {
    "name": "刑事",
    "code": "M"
  },
  "year": 100,
  "word": "簡上",
  "number": "903",
  "jcheck": "1",
  "reason": "傷害",
  "content": "臺灣板橋地方法院刑事判決            100年度簡上字第903號\n上  訴  人\n即  被  告  蘇麟盛\n上列上訴人即被告因傷害案件，不服本院於中華民國100 年8 月\n17日以100 年度簡字第5495號所為之第一審判決（聲請簡易判決\n處刑案號：100 年度偵字第18008 號），提起上訴，本院管轄之\n第二審合議庭判決如下：\n    主  文\n上訴駁回。\n    事實及理由\n一、本案經本院審理結果，認第一審以被告蘇麟盛罪證明確，適\n    用刑事訴訟法第四百四十九條第一項前段、第三項、刑法第\n    二十八條、第二百七十七條第一項、第四十七條第一項、第\n    四十一條第一項前段，刑法施行法第一條之一等規定，並審\n    酌被告與李嘉辰、張家瑞、蔡嘉旭等共犯（以上三人業經原\n    審判決確定）於案發時均係在監執行或收押之人犯，本應靜\n    心反省，竟僅因細故與告訴人邱顯源發生口角，即共同徒手\n    毆打告訴人頭部及身體，使告訴人身心受創，法治觀念實有\n    不足，兼衡其素行、智識程度、犯罪之動機、目的、手段及\n    坦承犯行之犯後態度等一切情狀，判處被告有期徒刑三月，\n    如易科罰金，以新臺幣一千元折算一日，其認事用法均無違\n    誤，量刑亦屬妥適，應予維持，並引用第一審刑事簡易判決\n    書所記載之事實、證據及理由（如附件）。\n二、被告上訴意旨略以：伊出獄後有再回監所探視邱顯源，邱顯\n    源表示願意原諒伊，故提起上訴云云，並未具體指摘原判決\n    有何違誤。況有關刑之量定，乃實體法上賦予法院得為自由\n    裁量之事項，倘原審法院量刑未逾越法律所規定之範圍，又\n    無濫用權限之情形，即不得任意指摘為違法。原審業已審酌\n    如前所載之一切情狀，而判處被告有期徒刑三月，經核實屬\n    允當。是以被告提起上訴，為無理由，應予駁回。\n三、被告經合法傳喚，無正當理由未於審判期日到庭，有送達證\n    書一份在卷可稽，爰依刑事訴訟法第三百七十一條規定，不\n    待其陳述，逕行判決。\n據上論斷，應依刑事訴訟法第四百五十五條之一第一項、第三項\n、第三百六十八條、第三百七十一條、第三百七十三條，判決如\n主文。\n本案經檢察官郭峻豪到庭執行職務。\n中    華    民    國   100    年    11    月    30    日\n                  刑事第十五庭  審判長法  官  劉元斐\n                                      法  官  陳世旻\n                                      法  官  毛彥程\n上列正本證明與原本無異。\n不得上訴。\n                                      書記官  陳金鳳\n中    華    民    國  100     年    12    月    6     日",
  "structure": {
    "main": "上訴駁回。",
    "fact": "一、本案經本院審理結果，認第一審以被告蘇麟盛罪證明確，適\n    用刑事訴訟法第四百四十九條第一項前段、第三項、刑法第\n    二十八條、第二百七十七條第一項、第四十七條第一項、第\n    四十一條第一項前段，刑法施行法第一條之一等規定，並審\n    酌被告與李嘉辰、張家瑞、蔡嘉旭等共犯（以上三人業經原\n    審判決確定）於案發時均係在監執行或收押之人犯，本應靜\n    心反省，竟僅因細故與告訴人邱顯源發生口角，即共同徒手\n    毆打告訴人頭部及身體，使告訴人身心受創，法治觀念實有\n    不足，兼衡其素行、智識程度、犯罪之動機、目的、手段及\n    坦承犯行之犯後態度等一切情狀，判處被告有期徒刑三月，\n    如易科罰金，以新臺幣一千元折算一日，其認事用法均無違\n    誤，量刑亦屬妥適，應予維持，並引用第一審刑事簡易判決\n    書所記載之事實、證據及理由（如附件）。\n二、被告上訴意旨略以：伊出獄後有再回監所探視邱顯源，邱顯\n    源表示願意原諒伊，故提起上訴云云，並未具體指摘原判決\n    有何違誤。況有關刑之量定，乃實體法上賦予法院得為自由\n    裁量之事項，倘原審法院量刑未逾越法律所規定之範圍，又\n    無濫用權限之情形，即不得任意指摘為違法。原審業已審酌\n    如前所載之一切情狀，而判處被告有期徒刑三月，經核實屬\n    允當。是以被告提起上訴，為無理由，應予駁回。\n三、被告經合法傳喚，無正當理由未於審判期日到庭，有送達證\n    書一份在卷可稽，爰依刑事訴訟法第三百七十一條規定，不\n    待其陳述，逕行判決。\n據上論斷，應依刑事訴訟法第四百五十五條之一第一項、第三項\n、第三百六十八條、第三百七十一條、第三百七十三條，判決如\n主文。\n本案經檢察官郭峻豪到庭執行職務。",
    "reason": "一、本案經本院審理結果，認第一審以被告蘇麟盛罪證明確，適\n    用刑事訴訟法第四百四十九條第一項前段、第三項、刑法第\n    二十八條、第二百七十七條第一項、第四十七條第一項、第\n    四十一條第一項前段，刑法施行法第一條之一等規定，並審\n    酌被告與李嘉辰、張家瑞、蔡嘉旭等共犯（以上三人業經原\n    審判決確定）於案發時均係在監執行或收押之人犯，本應靜\n    心反省，竟僅因細故與告訴人邱顯源發生口角，即共同徒手\n    毆打告訴人頭部及身體，使告訴人身心受創，法治觀念實有\n    不足，兼衡其素行、智識程度、犯罪之動機、目的、手段及\n    坦承犯行之犯後態度等一切情狀，判處被告有期徒刑三月，\n    如易科罰金，以新臺幣一千元折算一日，其認事用法均無違\n    誤，量刑亦屬妥適，應予維持，並引用第一審刑事簡易判決\n    書所記載之事實、證據及理由（如附件）。\n二、被告上訴意旨略以：伊出獄後有再回監所探視邱顯源，邱顯\n    源表示願意原諒伊，故提起上訴云云，並未具體指摘原判決\n    有何違誤。況有關刑之量定，乃實體法上賦予法院得為自由\n    裁量之事項，倘原審法院量刑未逾越法律所規定之範圍，又\n    無濫用權限之情形，即不得任意指摘為違法。原審業已審酌\n    如前所載之一切情狀，而判處被告有期徒刑三月，經核實屬\n    允當。是以被告提起上訴，為無理由，應予駁回。\n三、被告經合法傳喚，無正當理由未於審判期日到庭，有送達證\n    書一份在卷可稽，爰依刑事訴訟法第三百七十一條規定，不\n    待其陳述，逕行判決。\n據上論斷，應依刑事訴訟法第四百五十五條之一第一項、第三項\n、第三百六十八條、第三百七十一條、第三百七十三條，判決如\n主文。\n本案經檢察官郭峻豪到庭執行職務。"
  },
  "search": "臺灣板橋地方法院刑事判決100年度簡上字第903號上訴人即被告蘇麟盛上列上訴人即被告因傷害案件，不服本院於中華民國100年8月17日以100年度簡字第5495號所為之第一審判決（聲請簡易判決處刑案號：100年度偵字第18008號），提起上訴，本院管轄之第二審合議庭判決如下：主文上訴駁回。事實及理由一、本案經本院審理結果，認第一審以被告蘇麟盛罪證明確，適用刑事訴訟法第四百四十九條第一項前段、第三項、刑法第二十八條、第二百七十七條第一項、第四十七條第一項、第四十一條第一項前段，刑法施行法第一條之一等規定，並審酌被告與李嘉辰、張家瑞、蔡嘉旭等共犯（以上三人業經原審判決確定）於案發時均係在監執行或收押之人犯，本應靜心反省，竟僅因細故與告訴人邱顯源發生口角，即共同徒手毆打告訴人頭部及身體，使告訴人身心受創，法治觀念實有不足，兼衡其素行、智識程度、犯罪之動機、目的、手段及坦承犯行之犯後態度等一切情狀，判處被告有期徒刑三月，如易科罰金，以新臺幣一千元折算一日，其認事用法均無違誤，量刑亦屬妥適，應予維持，並引用第一審刑事簡易判決書所記載之事實、證據及理由（如附件）。二、被告上訴意旨略以：伊出獄後有再回監所探視邱顯源，邱顯源表示願意原諒伊，故提起上訴云云，並未具體指摘原判決有何違誤。況有關刑之量定，乃實體法上賦予法院得為自由裁量之事項，倘原審法院量刑未逾越法律所規定之範圍，又無濫用權限之情形，即不得任意指摘為違法。原審業已審酌如前所載之一切情狀，而判處被告有期徒刑三月，經核實屬允當。是以被告提起上訴，為無理由，應予駁回。三、被告經合法傳喚，無正當理由未於審判期日到庭，有送達證書一份在卷可稽，爰依刑事訴訟法第三百七十一條規定，不待其陳述，逕行判決。據上論斷，應依刑事訴訟法第四百五十五條之一第一項、第三項、第三百六十八條、第三百七十一條、第三百七十三條，判決如主文。本案經檢察官郭峻豪到庭執行職務。中華民國100年11月30日刑事第十五庭審判長法官劉元斐法官陳世旻法官毛彥程上列正本證明與原本無異。不得上訴。書記官陳金鳳中華民國100年12月6日",
  "characters": {
    "judges": [
      "劉元斐",
      "陳世旻",
      "毛彥程"
    ],
    "prosecutors": [
      "郭峻豪"
    ],
    "lawyers": [

    ],
    "clerks": [
      "陳金鳳"
    ],
    "plaintiffs": [

    ],
    "defendants": [
      "蘇麟盛"
    ],
    "prosecutor_office": [

    ],
    "creditors": [

    ],
    "debtors": [

    ],
    "judicial_associate_officer": [

    ]
  },
  "adjudged_at": "2011-11-30",
  "created_at": "2016-02-13 01:05:20",
  "updated_at": "2016-02-13 01:05:20"
}