{
  "identify": "PTD-100-簡-1922-20111130-1",
  "court": {
    "name": "臺灣屏東地方法院",
    "code": "PTD"
  },
  "division": {
    "name": "刑事",
    "code": "M"
  },
  "year": 100,
  "word": "簡",
  "number": "1922",
  "jcheck": "1",
  "reason": "違反家庭暴力防治法",
  "content": "臺灣屏東地方法院刑事簡易判決         100年度簡字第1922號\n聲  請  人  臺灣屏東地方法院檢察署檢察官\n被      告  鄭錦誠\n上列被告因違反家庭暴力防治法案件，經檢察官聲請以簡易判決\n處刑（100 年度偵字第8086 號），本院判決如下：\n    主  文\n鄭錦誠犯違反保護令罪，累犯，處拘役拾日，如易科罰金，以\n新臺幣壹仟元折算壹日。\n    事實及理由\n一、本案認定被告鄭錦誠之犯罪事實及證據，與檢察官聲請簡易\n    判決處刑書之記載相同，茲引用之（如附件）。\n二、查被告與被害人鄭甘秀霞係母子關係，二人間具有家庭暴力\n    防治法第3 條第3 款所定之家庭成員關係，被告違反本院10\n    0 年度暫家護字第383 號民事暫時保護令，以穢語辱罵被害\n    人，對其實施騷擾行為，核係犯家庭暴力防治法第61條第2\n    款之違反保護令罪。復被告有如聲請簡易判決處刑書所載前\n    科執行紀錄，有臺灣高等法院被告前案紀錄表在卷可稽，其\n    於受有期徒刑執行完畢後，5 年以內故意再犯本件有期徒刑\n    以上之罪，為累犯，應依法加重其刑。爰審酌被告於收受本\n    院所核發之民事暫時保護令後，竟漠視保護令所表彰之國家\n    公權力及對被害人保護之作用，再次對被害人為本件犯行，\n    實屬可議，惟念其尚知坦承犯行，頗有悔意，暨考量其違反\n    保護令之犯罪動機、手段、情節及其智識程度、生活狀況等\n    一切情狀，量處如主文所示之刑，並依其資力、職業及社會\n    地位等節，諭知易科罰金之折算標準。\n三、應依刑事訴訟法第449 條第1 項前段、第454 條第2 項，家\n    庭暴力防治法第61條第2 款，刑法第11條前段、第47條第1\n    項、第41條第1 項前段，逕以簡易判決處如主文所示之刑。\n中    華    民    國  100     年    11    月    30    日\n                  刑事第二庭    法  官  羅森德\n以上正本證明與原本無異。\n如不服本判決，得於判決書送達之翌日起10日內，以書狀敘述理\n由，向本庭提出上訴。\n中    華    民    國  100     年    11    月    30    日\n                                書記官  盧姝伶\n附錄本判決論罪科刑法條全文\n家庭暴力防治法第61條：\n違反法院依第13條、第15條所為之下列裁定者，為本法所稱違反\n保護令罪，處3 年以下有期徒刑、拘役或科或併科新台幣10萬元\n以下罰金。\n一、禁止實施家庭暴力行為。\n二、禁止騷擾、接觸、跟蹤、通話、通信或其他非必要之聯絡行\n    為。\n三、遷出住居所。\n四、遠離住居所、工作場所、學校或其他特定場所。\n五、完成加害人處遇計畫。",
  "structure": {
    "main": "鄭錦誠犯違反保護令罪，累犯，處拘役拾日，如易科罰金，以\n新臺幣壹仟元折算壹日。",
    "fact": "一、本案認定被告鄭錦誠之犯罪事實及證據，與檢察官聲請簡易\n    判決處刑書之記載相同，茲引用之（如附件）。\n二、查被告與被害人鄭甘秀霞係母子關係，二人間具有家庭暴力\n    防治法第3 條第3 款所定之家庭成員關係，被告違反本院10\n    0 年度暫家護字第383 號民事暫時保護令，以穢語辱罵被害\n    人，對其實施騷擾行為，核係犯家庭暴力防治法第61條第2\n    款之違反保護令罪。復被告有如聲請簡易判決處刑書所載前\n    科執行紀錄，有臺灣高等法院被告前案紀錄表在卷可稽，其\n    於受有期徒刑執行完畢後，5 年以內故意再犯本件有期徒刑\n    以上之罪，為累犯，應依法加重其刑。爰審酌被告於收受本\n    院所核發之民事暫時保護令後，竟漠視保護令所表彰之國家\n    公權力及對被害人保護之作用，再次對被害人為本件犯行，\n    實屬可議，惟念其尚知坦承犯行，頗有悔意，暨考量其違反\n    保護令之犯罪動機、手段、情節及其智識程度、生活狀況等\n    一切情狀，量處如主文所示之刑，並依其資力、職業及社會\n    地位等節，諭知易科罰金之折算標準。\n三、應依刑事訴訟法第449 條第1 項前段、第454 條第2 項，家\n    庭暴力防治法第61條第2 款，刑法第11條前段、第47條第1\n    項、第41條第1 項前段，逕以簡易判決處如主文所示之刑。",
    "reason": "一、本案認定被告鄭錦誠之犯罪事實及證據，與檢察官聲請簡易\n    判決處刑書之記載相同，茲引用之（如附件）。\n二、查被告與被害人鄭甘秀霞係母子關係，二人間具有家庭暴力\n    防治法第3 條第3 款所定之家庭成員關係，被告違反本院10\n    0 年度暫家護字第383 號民事暫時保護令，以穢語辱罵被害\n    人，對其實施騷擾行為，核係犯家庭暴力防治法第61條第2\n    款之違反保護令罪。復被告有如聲請簡易判決處刑書所載前\n    科執行紀錄，有臺灣高等法院被告前案紀錄表在卷可稽，其\n    於受有期徒刑執行完畢後，5 年以內故意再犯本件有期徒刑\n    以上之罪，為累犯，應依法加重其刑。爰審酌被告於收受本\n    院所核發之民事暫時保護令後，竟漠視保護令所表彰之國家\n    公權力及對被害人保護之作用，再次對被害人為本件犯行，\n    實屬可議，惟念其尚知坦承犯行，頗有悔意，暨考量其違反\n    保護令之犯罪動機、手段、情節及其智識程度、生活狀況等\n    一切情狀，量處如主文所示之刑，並依其資力、職業及社會\n    地位等節，諭知易科罰金之折算標準。\n三、應依刑事訴訟法第449 條第1 項前段、第454 條第2 項，家\n    庭暴力防治法第61條第2 款，刑法第11條前段、第47條第1\n    項、第41條第1 項前段，逕以簡易判決處如主文所示之刑。"
  },
  "search": "臺灣屏東地方法院刑事簡易判決100年度簡字第1922號聲請人臺灣屏東地方法院檢察署檢察官被告鄭錦誠上列被告因違反家庭暴力防治法案件，經檢察官聲請以簡易判決處刑（100年度偵字第8086號），本院判決如下：主文鄭錦誠犯違反保護令罪，累犯，處拘役拾日，如易科罰金，以新臺幣壹仟元折算壹日。事實及理由一、本案認定被告鄭錦誠之犯罪事實及證據，與檢察官聲請簡易判決處刑書之記載相同，茲引用之（如附件）。二、查被告與被害人鄭甘秀霞係母子關係，二人間具有家庭暴力防治法第3條第3款所定之家庭成員關係，被告違反本院100年度暫家護字第383號民事暫時保護令，以穢語辱罵被害人，對其實施騷擾行為，核係犯家庭暴力防治法第61條第2款之違反保護令罪。復被告有如聲請簡易判決處刑書所載前科執行紀錄，有臺灣高等法院被告前案紀錄表在卷可稽，其於受有期徒刑執行完畢後，5年以內故意再犯本件有期徒刑以上之罪，為累犯，應依法加重其刑。爰審酌被告於收受本院所核發之民事暫時保護令後，竟漠視保護令所表彰之國家公權力及對被害人保護之作用，再次對被害人為本件犯行，實屬可議，惟念其尚知坦承犯行，頗有悔意，暨考量其違反保護令之犯罪動機、手段、情節及其智識程度、生活狀況等一切情狀，量處如主文所示之刑，並依其資力、職業及社會地位等節，諭知易科罰金之折算標準。三、應依刑事訴訟法第449條第1項前段、第454條第2項，家庭暴力防治法第61條第2款，刑法第11條前段、第47條第1項、第41條第1項前段，逕以簡易判決處如主文所示之刑。中華民國100年11月30日刑事第二庭法官羅森德以上正本證明與原本無異。如不服本判決，得於判決書送達之翌日起10日內，以書狀敘述理由，向本庭提出上訴。中華民國100年11月30日書記官盧姝伶附錄本判決論罪科刑法條全文家庭暴力防治法第61條：違反法院依第13條、第15條所為之下列裁定者，為本法所稱違反保護令罪，處3年以下有期徒刑、拘役或科或併科新台幣10萬元以下罰金。一、禁止實施家庭暴力行為。二、禁止騷擾、接觸、跟蹤、通話、通信或其他非必要之聯絡行為。三、遷出住居所。四、遠離住居所、工作場所、學校或其他特定場所。五、完成加害人處遇計畫。",
  "characters": {
    "judges": [
      "羅森德"
    ],
    "prosecutors": [

    ],
    "lawyers": [

    ],
    "clerks": [
      "盧姝伶"
    ],
    "plaintiffs": [

    ],
    "defendants": [
      "鄭錦誠"
    ],
    "prosecutor_office": [
      "臺灣屏東地方法院檢察署檢察官"
    ],
    "creditors": [

    ],
    "debtors": [

    ],
    "judicial_associate_officer": [

    ]
  },
  "adjudged_at": "2011-11-30",
  "created_at": "2016-02-13 01:34:53",
  "updated_at": "2016-02-13 01:34:53"
}