{
  "identify": "KSD-93-訴-2795-20110329-2",
  "court": {
    "name": "臺灣高雄地方法院",
    "code": "KSD"
  },
  "division": {
    "name": "民事",
    "code": "V"
  },
  "year": 93,
  "word": "訴",
  "number": "2795",
  "jcheck": "2",
  "reason": "分割共有物",
  "content": "臺灣高雄地方法院民事裁定              93年度訴字第2795號\n原      告  蘇漢鈺\n訴訟代理人  張榮作律師\n被      告  歐清木\n被      告  歐蔡遠\n被      告  歐清福\n被      告  劉金菊\n被      告  劉歐寶珠\n被      告  歐美雪\n被      告  歐麗娣\n被      告  歐麗惠\n被      告  歐志宏\n被      告  歐志杰\n被      告  歐月芬\n被      告  歐建偉\n被      告  廖聰郁\n被      告  黃朝崑\n被      告  黃老昇\n被      告  歐金池\n被      告  歐金樹\n被      告  陳耀雅(即陳歐葉之.\n被      告  陳珠吻(即陳歐葉之.\n被      告  陳月珠(即陳歐葉之.\n被      告  陳珠忍(即陳歐葉之.\n被      告  陳珠盆(即陳歐葉之.\n被      告  陳珠芬(即陳歐葉之.\n被      告  歐怨\n被      告  葉再為\n被      告  葉再得\n被      告  葉再成\n被      告  葉義國\n被      告  邱葉順治\n被      告  劉葉禁\n被      告  蘇葉花\n被      告  鄭李程鑾\n被      告  林程玉蕉\n被      告  程鈺心\n被      告  洪國田\n被      告  程國濱\n被      告  蘇鄭阿妙\n被      告  蘇俊文\n被      告  蘇建明\n被      告  蘇頌斌\n被      告  蘇雅馨\n被      告  高蘇富美\n被      告  蘇千合\n被      告  劉蘇素蘭\n被      告  蘇婉瑜\n被      告  陳永寧\n被      告  歐清吉\n被      告  陳英彬\n被      告  沈茂吉\n被      告  葉榮昌\n被      告  蘇榮亮\n被      告  歐金獅\n被      告  歐彥德\n被      告  歐威慶\n被      告  歐慶祥\n被      告  蘇經舜\n被      告  蘇志聰\n訴訟代理人  蘇王勤\n被      告  蘇陳阿珠\n被      告  陳明全\n被      告  郭淑珠\n被      告  陳亦萱\n被      告  陳奕婷\n被      告  陳易楓\n被      告  陳美如\n被      告  陳玲吟\n被      告  蘇祺能\n訴訟代理人  蘇惠瑛\n被      告  葉克銘\n被      告  陳俊傑\n前列二人共同\n兼訴訟代理  陳永寧\n人\n前列十三人共同\n訴訟代理人  李來清\n被      告  黃茂榮\n被      告  陳展方\n當事人間請求分割共有物事件，本院裁定如下：\n      主  文\n本件因被告陳永寧陳報系爭土地之買賣市價，及原告所陳報之分\n割方案因被告中有取得系爭土地相鄰之土地，致原分割方案有調\n整之必要，爰再開準備程序，並訂於民國100 年4 月14日上午10\n時，在本院高雄簡易庭第五法庭續行準備程序。\n中    華    民    國   100    年    3     月    29    日\n                  民事第二庭法  官  陳嘉惠\n正本係照原本作成。\n中    華    民    國   100    年    3     月    29    日\n                                書記官  莊豐源",
  "structure": {
  },
  "search": "臺灣高雄地方法院民事裁定93年度訴字第2795號原告蘇漢鈺訴訟代理人張榮作律師被告歐清木被告歐蔡遠被告歐清福被告劉金菊被告劉歐寶珠被告歐美雪被告歐麗娣被告歐麗惠被告歐志宏被告歐志杰被告歐月芬被告歐建偉被告廖聰郁被告黃朝崑被告黃老昇被告歐金池被告歐金樹被告陳耀雅(即陳歐葉之.被告陳珠吻(即陳歐葉之.被告陳月珠(即陳歐葉之.被告陳珠忍(即陳歐葉之.被告陳珠盆(即陳歐葉之.被告陳珠芬(即陳歐葉之.被告歐怨被告葉再為被告葉再得被告葉再成被告葉義國被告邱葉順治被告劉葉禁被告蘇葉花被告鄭李程鑾被告林程玉蕉被告程鈺心被告洪國田被告程國濱被告蘇鄭阿妙被告蘇俊文被告蘇建明被告蘇頌斌被告蘇雅馨被告高蘇富美被告蘇千合被告劉蘇素蘭被告蘇婉瑜被告陳永寧被告歐清吉被告陳英彬被告沈茂吉被告葉榮昌被告蘇榮亮被告歐金獅被告歐彥德被告歐威慶被告歐慶祥被告蘇經舜被告蘇志聰訴訟代理人蘇王勤被告蘇陳阿珠被告陳明全被告郭淑珠被告陳亦萱被告陳奕婷被告陳易楓被告陳美如被告陳玲吟被告蘇祺能訴訟代理人蘇惠瑛被告葉克銘被告陳俊傑前列二人共同兼訴訟代理陳永寧人前列十三人共同訴訟代理人李來清被告黃茂榮被告陳展方當事人間請求分割共有物事件，本院裁定如下：主文本件因被告陳永寧陳報系爭土地之買賣市價，及原告所陳報之分割方案因被告中有取得系爭土地相鄰之土地，致原分割方案有調整之必要，爰再開準備程序，並訂於民國100年4月14日上午10時，在本院高雄簡易庭第五法庭續行準備程序。中華民國100年3月29日民事第二庭法官陳嘉惠正本係照原本作成。中華民國100年3月29日書記官莊豐源",
  "characters": {
    "judges": [
      "陳嘉惠"
    ],
    "prosecutors": [

    ],
    "lawyers": [
      "張榮作"
    ],
    "clerks": [

    ],
    "plaintiffs": [
      "蘇漢鈺"
    ],
    "defendants": [
      "歐清木",
      "被      告  歐蔡遠",
      "被      告  歐清福",
      "被      告  劉金菊",
      "被      告  劉歐寶珠",
      "被      告  歐美雪",
      "被      告  歐麗娣",
      "被      告  歐麗惠",
      "被      告  歐志宏",
      "被      告  歐志杰",
      "被      告  歐月芬",
      "被      告  歐建偉",
      "被      告  廖聰郁",
      "被      告  黃朝崑",
      "被      告  黃老昇",
      "被      告  歐金池",
      "被      告  歐金樹",
      "被      告  陳耀雅(即陳歐葉之.",
      "被      告  陳珠吻(即陳歐葉之.",
      "被      告  陳月珠(即陳歐葉之.",
      "被      告  陳珠忍(即陳歐葉之.",
      "被      告  陳珠盆(即陳歐葉之.",
      "被      告  陳珠芬(即陳歐葉之.",
      "被      告  歐怨",
      "被      告  葉再為",
      "被      告  葉再得",
      "被      告  葉再成",
      "被      告  葉義國",
      "被      告  邱葉順治",
      "被      告  劉葉禁",
      "被      告  蘇葉花",
      "被      告  鄭李程鑾",
      "被      告  林程玉蕉",
      "被      告  程鈺心",
      "被      告  洪國田",
      "被      告  程國濱",
      "被      告  蘇鄭阿妙",
      "被      告  蘇俊文",
      "被      告  蘇建明",
      "被      告  蘇頌斌",
      "被      告  蘇雅馨",
      "被      告  高蘇富美",
      "被      告  蘇千合",
      "被      告  劉蘇素蘭",
      "被      告  蘇婉瑜",
      "被      告  陳永寧",
      "被      告  歐清吉",
      "被      告  陳英彬",
      "被      告  沈茂吉",
      "被      告  葉榮昌",
      "被      告  蘇榮亮",
      "被      告  歐金獅",
      "被      告  歐彥德",
      "被      告  歐威慶",
      "被      告  歐慶祥",
      "被      告  蘇經舜",
      "被      告  蘇志聰",
      "蘇陳阿珠",
      "被      告  陳明全",
      "被      告  郭淑珠",
      "被      告  陳亦萱",
      "被      告  陳奕婷",
      "被      告  陳易楓",
      "被      告  陳美如",
      "被      告  陳玲吟",
      "被      告  蘇祺能",
      "葉克銘",
      "被      告  陳俊傑",
      "前列二人共同",
      "兼訴訟代理  陳永寧",
      "黃茂榮",
      "被      告  陳展方",
      "當事人間請求分割共有物事件，本院裁定如下："
    ],
    "prosecutor_office": [

    ],
    "creditors": [

    ],
    "debtors": [

    ],
    "judicial_associate_officer": [

    ]
  },
  "adjudged_at": "2011-03-29",
  "created_at": "2016-02-13 20:57:40",
  "updated_at": "2016-02-13 20:57:40"
}