{
  "identify": "TPB-100-再-1-20110328-1",
  "court": {
    "name": "臺北高等行政法院",
    "code": "TPB"
  },
  "division": {
    "name": "行政",
    "code": "A"
  },
  "year": 100,
  "word": "再",
  "number": "1",
  "jcheck": "1",
  "reason": "醫師法",
  "content": "臺北高等行政法院裁定\n                                        100年度再字第1號\n再審原  告  陳南谷\n再審被  告  行政院衛生署\n代  表  人  邱文達（署長）住同上\n上列當事人間醫師法事件，再審原告對最高行政法院中華民國98\n年3 月19日98年度判字第264 號判決，以有行政訴訟法第273 條\n第1 項第9 款、第10款、第13款及第14款事由，提起再審之訴，\n經最高行政法院以99年度裁字第3073號裁定移送本院，本院裁定\n如下：\n    主  文\n再審之訴駁回。\n再審訴訟費用由再審原告負擔。\n    理  由\n一、本件再審原告起訴時，再審被告之代表人為楊志良，嗣於訴\n    訟中再審被告代表人變更為邱文達，茲據再審被告新任代表\n    人具狀聲明承受訴訟，核無不合，應予准許。\n二、按提起再審之訴，應依行政訴訟法第277 條第1 項第4 款表\n    明再審理由，此為必須具備之程式。所謂表明再審理由，必\n    須指明確定判決有如何合於行政訴訟法第273 條或第274 條\n    所定再審事由之具體情事，始為相當。倘僅泛言有再審事由\n    而無具體情事者，仍難謂已合法表明再審理由。所提再審之\n    訴，即屬不合法。\n三、本件再審原告對於最高行政法院98年度判字第264 號判決及\n    本院95年度訴字第1473號確定判決，提起再審之訴，主張有\n    行政訴訟法第273 條第1 項第9 款、第10款、第13款及第14\n    款之事由，再審原告起訴主張略以：再審原告完全依據中醫\n    師檢覈辦法之相關規定及簡章須知報名參加考試，並依照駐\n    巴拉圭大使館、外交部、考選部之行文提供相關文件供核，\n    並經實質審查後通過考試，取得中醫師資格；惟考選部認定\n    再審原告不具備中醫師檢覈辦法所定「在國外居住行醫5年\n    以上」之資格，進而撤銷再審原告中醫師檢覈應考資格、考\n    試及格資格及中醫師執照，其所依據者僅係考選部86年3 月\n    10日中醫師檢覈委員會第212 次會議之決議，然該決議僅係\n    內部作業規定，且係考選部當年提供資料及調查錯誤，考選\n    部、外交部、北機組明知原處分錯誤，卻罔顧原告權益，應\n    即主動作業，而非被動要求再審原告等待法院恢復再審原告\n    中醫師執照云云。\n四、經查，再審原告原於89年3 月間以巴拉圭華僑身分向考選部\n    申請中醫師檢覈，經考選部中醫師檢覈委員會審議通過，准\n    予參加中醫師檢覈筆試，並經筆試及格，取得考試及格證書\n    。嗣經考選部以再審原告不符中醫師檢覈筆試資格，報請考\n    試院撤銷再審原告考試及格資格並吊銷其考試及格證書。再\n    審被告即依考試院前開處分，撤銷再審原告原持有之中醫師\n    證書，並命其繳回證書註銷，本件再審原告提起再審之訴，\n    雖主張有行政訴訟法第273 條第1 項第9 款、第10款、第13\n    款及第14款之事由，然核其起訴內容，均係對於原處分所憑\n    之考試院前述撤銷再審原告中醫師考試及格資格處分，認有\n    調查錯誤之違法情事，及說明其對於前訴訟程序確定判決不\n    服之理由，惟對於上開確定判決，究有如何合於行政訴訟法\n    第273 條第1 項第9 款、第10款、第13款及第14款規定之具\n    體情事，則未據敘明，依上開規定及說明，其再審之訴自非\n    合法。\n五、依行政訴訟法第278 條第1 項、第104 條、民事訴訟法第95\n    條、第78條，裁定如主文。\n中    華    民    國    100   年    3     月    28    日\n                   臺北高等行政法院第三庭\n                             審判長法  官  許瑞助\n                                   法  官  林玫君\n                                   法  官  劉穎怡\n上為正本係照原本作成。\n如不服本裁定，應於送達後10日內向本院提出抗告狀（須按他造\n人數附繕本）。\n中    華    民    國    100   年    3     月    28    日\n                                   書記官  林苑珍",
  "structure": {
    "main": "再審之訴駁回。\n再審訴訟費用由再審原告負擔。",
    "reason": "一、本件再審原告起訴時，再審被告之代表人為楊志良，嗣於訴\n    訟中再審被告代表人變更為邱文達，茲據再審被告新任代表\n    人具狀聲明承受訴訟，核無不合，應予准許。\n二、按提起再審之訴，應依行政訴訟法第277 條第1 項第4 款表\n    明再審理由，此為必須具備之程式。所謂表明再審理由，必\n    須指明確定判決有如何合於行政訴訟法第273 條或第274 條\n    所定再審事由之具體情事，始為相當。倘僅泛言有再審事由\n    而無具體情事者，仍難謂已合法表明再審理由。所提再審之\n    訴，即屬不合法。\n三、本件再審原告對於最高行政法院98年度判字第264 號判決及\n    本院95年度訴字第1473號確定判決，提起再審之訴，主張有\n    行政訴訟法第273 條第1 項第9 款、第10款、第13款及第14\n    款之事由，再審原告起訴主張略以：再審原告完全依據中醫\n    師檢覈辦法之相關規定及簡章須知報名參加考試，並依照駐\n    巴拉圭大使館、外交部、考選部之行文提供相關文件供核，\n    並經實質審查後通過考試，取得中醫師資格；惟考選部認定\n    再審原告不具備中醫師檢覈辦法所定「在國外居住行醫5年\n    以上」之資格，進而撤銷再審原告中醫師檢覈應考資格、考\n    試及格資格及中醫師執照，其所依據者僅係考選部86年3 月\n    10日中醫師檢覈委員會第212 次會議之決議，然該決議僅係\n    內部作業規定，且係考選部當年提供資料及調查錯誤，考選\n    部、外交部、北機組明知原處分錯誤，卻罔顧原告權益，應\n    即主動作業，而非被動要求再審原告等待法院恢復再審原告\n    中醫師執照云云。\n四、經查，再審原告原於89年3 月間以巴拉圭華僑身分向考選部\n    申請中醫師檢覈，經考選部中醫師檢覈委員會審議通過，准\n    予參加中醫師檢覈筆試，並經筆試及格，取得考試及格證書\n    。嗣經考選部以再審原告不符中醫師檢覈筆試資格，報請考\n    試院撤銷再審原告考試及格資格並吊銷其考試及格證書。再\n    審被告即依考試院前開處分，撤銷再審原告原持有之中醫師\n    證書，並命其繳回證書註銷，本件再審原告提起再審之訴，\n    雖主張有行政訴訟法第273 條第1 項第9 款、第10款、第13\n    款及第14款之事由，然核其起訴內容，均係對於原處分所憑\n    之考試院前述撤銷再審原告中醫師考試及格資格處分，認有\n    調查錯誤之違法情事，及說明其對於前訴訟程序確定判決不\n    服之理由，惟對於上開確定判決，究有如何合於行政訴訟法\n    第273 條第1 項第9 款、第10款、第13款及第14款規定之具\n    體情事，則未據敘明，依上開規定及說明，其再審之訴自非\n    合法。\n五、依行政訴訟法第278 條第1 項、第104 條、民事訴訟法第95\n    條、第78條，裁定如主文。"
  },
  "search": "臺北高等行政法院裁定100年度再字第1號再審原告陳南谷再審被告行政院衛生署代表人邱文達（署長）住同上上列當事人間醫師法事件，再審原告對最高行政法院中華民國98年3月19日98年度判字第264號判決，以有行政訴訟法第273條第1項第9款、第10款、第13款及第14款事由，提起再審之訴，經最高行政法院以99年度裁字第3073號裁定移送本院，本院裁定如下：主文再審之訴駁回。再審訴訟費用由再審原告負擔。理由一、本件再審原告起訴時，再審被告之代表人為楊志良，嗣於訴訟中再審被告代表人變更為邱文達，茲據再審被告新任代表人具狀聲明承受訴訟，核無不合，應予准許。二、按提起再審之訴，應依行政訴訟法第277條第1項第4款表明再審理由，此為必須具備之程式。所謂表明再審理由，必須指明確定判決有如何合於行政訴訟法第273條或第274條所定再審事由之具體情事，始為相當。倘僅泛言有再審事由而無具體情事者，仍難謂已合法表明再審理由。所提再審之訴，即屬不合法。三、本件再審原告對於最高行政法院98年度判字第264號判決及本院95年度訴字第1473號確定判決，提起再審之訴，主張有行政訴訟法第273條第1項第9款、第10款、第13款及第14款之事由，再審原告起訴主張略以：再審原告完全依據中醫師檢覈辦法之相關規定及簡章須知報名參加考試，並依照駐巴拉圭大使館、外交部、考選部之行文提供相關文件供核，並經實質審查後通過考試，取得中醫師資格；惟考選部認定再審原告不具備中醫師檢覈辦法所定「在國外居住行醫5年以上」之資格，進而撤銷再審原告中醫師檢覈應考資格、考試及格資格及中醫師執照，其所依據者僅係考選部86年3月10日中醫師檢覈委員會第212次會議之決議，然該決議僅係內部作業規定，且係考選部當年提供資料及調查錯誤，考選部、外交部、北機組明知原處分錯誤，卻罔顧原告權益，應即主動作業，而非被動要求再審原告等待法院恢復再審原告中醫師執照云云。四、經查，再審原告原於89年3月間以巴拉圭華僑身分向考選部申請中醫師檢覈，經考選部中醫師檢覈委員會審議通過，准予參加中醫師檢覈筆試，並經筆試及格，取得考試及格證書。嗣經考選部以再審原告不符中醫師檢覈筆試資格，報請考試院撤銷再審原告考試及格資格並吊銷其考試及格證書。再審被告即依考試院前開處分，撤銷再審原告原持有之中醫師證書，並命其繳回證書註銷，本件再審原告提起再審之訴，雖主張有行政訴訟法第273條第1項第9款、第10款、第13款及第14款之事由，然核其起訴內容，均係對於原處分所憑之考試院前述撤銷再審原告中醫師考試及格資格處分，認有調查錯誤之違法情事，及說明其對於前訴訟程序確定判決不服之理由，惟對於上開確定判決，究有如何合於行政訴訟法第273條第1項第9款、第10款、第13款及第14款規定之具體情事，則未據敘明，依上開規定及說明，其再審之訴自非合法。五、依行政訴訟法第278條第1項、第104條、民事訴訟法第95條、第78條，裁定如主文。中華民國100年3月28日臺北高等行政法院第三庭審判長法官許瑞助法官林玫君法官劉穎怡上為正本係照原本作成。如不服本裁定，應於送達後10日內向本院提出抗告狀（須按他造人數附繕本）。中華民國100年3月28日書記官林苑珍",
  "characters": {
    "judges": [
      "許瑞助",
      "林玫君",
      "劉穎怡"
    ],
    "prosecutors": [

    ],
    "lawyers": [

    ],
    "clerks": [

    ],
    "plaintiffs": [
      "陳南谷"
    ],
    "defendants": [
      "行政院衛生署"
    ],
    "prosecutor_office": [

    ],
    "creditors": [

    ],
    "debtors": [

    ],
    "judicial_associate_officer": [

    ]
  },
  "adjudged_at": "2011-03-28",
  "created_at": "2016-02-13 20:52:33",
  "updated_at": "2016-02-13 20:52:33"
}