{
  "identify": "CYD-94-嘉簡-1290-20051115-1",
  "court": {
    "name": "臺灣嘉義地方法院",
    "code": "CYD"
  },
  "division": {
    "name": "刑事",
    "code": "M"
  },
  "year": 94,
  "word": "嘉簡",
  "number": "1290",
  "jcheck": "1",
  "reason": "家暴傷害",
  "content": "臺灣嘉義地方法院刑事簡易判決        94年度嘉簡字第1290號\n聲  請  人  臺灣嘉義地方法院檢察署檢察官\n被      告  甲○○\n上列被告因家暴傷害案件，經檢察官聲請以簡易判決處刑（94年\n度偵字第5361號），本院判決如下：\n    主  文\n甲○○傷害人之身體，累犯，處拘役肆拾日，如易科罰金，以參\n佰元折算壹日。\n    事實及理由\n一、本件犯罪事實及證據，除犯罪事實部分應補充「甲○○前於\n    民國八十九年間因違背安全駕駛致交通危險罪案件，經本院\n    八十九年度交易字第二一四號刑事判決判處有期徒刑二月，\n    如易科罰金三百元折算一日確定，於八十九年十一月八日易\n    科罰金執行完畢。詎仍不知悔改」等語外，餘均引用檢察官\n    聲請簡易判決處刑書之記載(如附件)。\n二、被告甲○○曾犯上開公共危險罪，經本院判處有期徒刑二月\n    確定，於八十九年十一月八日易科罰金執行完畢，有台灣高\n    等法院被告前案紀錄表可憑，其於五年以內再犯最重本刑有\n    期徒刑以上刑之本罪，為累犯，應依刑法第四十七條規定加\n    重其刑。\n三、依刑事訴訟法第四百四十九條第一項前段、第四百五十四條\n    第二項，刑法第二百七十七條第一項、第四十七條、四十一\n    條第一項前段，罰金罰鍰提高標準條例第一條前段、第二條\n    逕以簡易判決處刑如主文。\n四、如不服本判決，應於判決送達後十日內向本院提出上訴狀（\n    應附繕本）。\n中    華    民    國    94    年    11    月    15    日\n                          嘉義簡易庭 法  官  游悅晨\n中    華    民    國    94    年    11    月    15    日\n                                     書記官  李銷勳\n附錄本判決論罪科刑法條全文\n刑法第277條第1項:\n傷害人之身體或健康者, 處3年以下有期徒刑、拘役或1000元以\n下罰金。\n",
  "structure": {
    "main": "甲○○傷害人之身體，累犯，處拘役肆拾日，如易科罰金，以參\n佰元折算壹日。",
    "fact": "一、本件犯罪事實及證據，除犯罪事實部分應補充「甲○○前於\n    民國八十九年間因違背安全駕駛致交通危險罪案件，經本院\n    八十九年度交易字第二一四號刑事判決判處有期徒刑二月，\n    如易科罰金三百元折算一日確定，於八十九年十一月八日易\n    科罰金執行完畢。詎仍不知悔改」等語外，餘均引用檢察官\n    聲請簡易判決處刑書之記載(如附件)。\n二、被告甲○○曾犯上開公共危險罪，經本院判處有期徒刑二月\n    確定，於八十九年十一月八日易科罰金執行完畢，有台灣高\n    等法院被告前案紀錄表可憑，其於五年以內再犯最重本刑有\n    期徒刑以上刑之本罪，為累犯，應依刑法第四十七條規定加\n    重其刑。\n三、依刑事訴訟法第四百四十九條第一項前段、第四百五十四條\n    第二項，刑法第二百七十七條第一項、第四十七條、四十一\n    條第一項前段，罰金罰鍰提高標準條例第一條前段、第二條\n    逕以簡易判決處刑如主文。\n四、如不服本判決，應於判決送達後十日內向本院提出上訴狀（\n    應附繕本）。",
    "reason": "一、本件犯罪事實及證據，除犯罪事實部分應補充「甲○○前於\n    民國八十九年間因違背安全駕駛致交通危險罪案件，經本院\n    八十九年度交易字第二一四號刑事判決判處有期徒刑二月，\n    如易科罰金三百元折算一日確定，於八十九年十一月八日易\n    科罰金執行完畢。詎仍不知悔改」等語外，餘均引用檢察官\n    聲請簡易判決處刑書之記載(如附件)。\n二、被告甲○○曾犯上開公共危險罪，經本院判處有期徒刑二月\n    確定，於八十九年十一月八日易科罰金執行完畢，有台灣高\n    等法院被告前案紀錄表可憑，其於五年以內再犯最重本刑有\n    期徒刑以上刑之本罪，為累犯，應依刑法第四十七條規定加\n    重其刑。\n三、依刑事訴訟法第四百四十九條第一項前段、第四百五十四條\n    第二項，刑法第二百七十七條第一項、第四十七條、四十一\n    條第一項前段，罰金罰鍰提高標準條例第一條前段、第二條\n    逕以簡易判決處刑如主文。\n四、如不服本判決，應於判決送達後十日內向本院提出上訴狀（\n    應附繕本）。"
  },
  "search": "臺灣嘉義地方法院刑事簡易判決94年度嘉簡字第1290號聲請人臺灣嘉義地方法院檢察署檢察官被告甲○○上列被告因家暴傷害案件，經檢察官聲請以簡易判決處刑（94年度偵字第5361號），本院判決如下：主文甲○○傷害人之身體，累犯，處拘役肆拾日，如易科罰金，以參佰元折算壹日。事實及理由一、本件犯罪事實及證據，除犯罪事實部分應補充「甲○○前於民國八十九年間因違背安全駕駛致交通危險罪案件，經本院八十九年度交易字第二一四號刑事判決判處有期徒刑二月，如易科罰金三百元折算一日確定，於八十九年十一月八日易科罰金執行完畢。詎仍不知悔改」等語外，餘均引用檢察官聲請簡易判決處刑書之記載(如附件)。二、被告甲○○曾犯上開公共危險罪，經本院判處有期徒刑二月確定，於八十九年十一月八日易科罰金執行完畢，有台灣高等法院被告前案紀錄表可憑，其於五年以內再犯最重本刑有期徒刑以上刑之本罪，為累犯，應依刑法第四十七條規定加重其刑。三、依刑事訴訟法第四百四十九條第一項前段、第四百五十四條第二項，刑法第二百七十七條第一項、第四十七條、四十一條第一項前段，罰金罰鍰提高標準條例第一條前段、第二條逕以簡易判決處刑如主文。四、如不服本判決，應於判決送達後十日內向本院提出上訴狀（應附繕本）。中華民國94年11月15日嘉義簡易庭法官游悅晨中華民國94年11月15日書記官李銷勳附錄本判決論罪科刑法條全文刑法第277條第1項:傷害人之身體或健康者,處3年以下有期徒刑、拘役或1000元以下罰金。",
  "characters": {
    "judges": [
      "游悅晨"
    ],
    "prosecutors": [

    ],
    "lawyers": [

    ],
    "clerks": [
      "李銷勳"
    ],
    "plaintiffs": [

    ],
    "defendants": [
      "甲○○"
    ],
    "prosecutor_office": [
      "臺灣嘉義地方法院檢察署檢察官"
    ],
    "creditors": [

    ],
    "debtors": [

    ],
    "judicial_associate_officer": [

    ]
  },
  "adjudged_at": "2005-11-15",
  "created_at": "2016-02-06 23:15:22",
  "updated_at": "2016-02-06 23:15:22"
}