{
  "identify": "TPD-93-訴-1268-20051115-1",
  "court": {
    "name": "臺灣臺北地方法院",
    "code": "TPD"
  },
  "division": {
    "name": "刑事",
    "code": "M"
  },
  "year": 93,
  "word": "訴",
  "number": "1268",
  "jcheck": "1",
  "reason": "違反著作權法",
  "content": "臺灣臺北地方法院刑事判決              93年度訴字第1268號\n公  訴  人  臺灣臺北地方法院檢察署檢察官\n被      告  錸捷科技股份有限公司\n兼  上一人\n代  表  人  甲○○\n上  一  人\n選任辯護人  葉建廷律師\n            左涵湄律師\n上列被告因違反著作權法案件，經檢察官提起公訴（92年度偵字\n第23206號、93年度偵字第12684號），本院判決如下：\n    主  文\n本件公訴不受理。\n    理  由\n一、公訴意旨略以：被告甲○○係被告錸捷科技股份有限公司（\n    下稱錸捷公司）之總經理，明知告訴人東森華榮傳播事業股\n    份有限公司（嗣變更名稱為東森電視事業股份有限公司，下\n    稱東森公司）經營之「ET-TODAY東森新聞網」網站（網址：\n    www.ettoday.com ，下稱東森網站）內各項著作之著作權利\n    均屬告訴人東森公司所有，竟未經告訴人東森公司同意或授\n    權，自民國90年1 月下旬起將告訴人東森公司登載在前揭網\n    站上「2001/01/19閱讀臺灣最好的路徑21世紀春節27條新行\n    程」、「2001/1/22擁抱自然/避寒好去處墾丁逍遙遊」等數\n    十篇旅遊報導語文著作，擅自重製於被告錸捷公司「ET-MAL\n    L 」之網站（網址：www.et-mall.com.tw，下稱錸捷網站）\n    ，並公開傳輸供網友觀覽，並以此銷售廣告牟利，期間長達\n    一年以上，因認被告甲○○涉犯92年7月9日修正公布之著作\n    權法第91條第1 項意圖營利而以重製之方法侵害他人之著作\n    財產權之罪嫌，又被告甲○○係法人錸捷公司之總經理，為\n    被告錸捷公司之受雇人，其因執行業務涉犯上開著作權法第\n    91條第1 項罪嫌，其代表之法人即被告錸捷公司涉犯依同法\n    第101條第1項，應科以同法第91條第1項之罰金罪嫌。\n二、按告訴乃論之罪，告訴人於第一審辯論終結前得撤回其告訴\n    ；又告訴經撤回者，應諭知不受理之判決；又不受理之判決\n    ，得不經言詞辯論為之，刑事訴訟法第238條第1 項、第303\n    條第3款及第307條分別定有明文。\n三、查本件告訴人東森公司告訴被告甲○○、錸捷公司違反著作\n    權法案件，起訴書認被告甲○○係犯92年7月9日修正公布之\n    著作權法第91條第1 項意圖營利而以重製之方法侵害他人之\n    著作財產權之罪，被告錸捷公司涉犯依同法第101條第1項，\n    應科以同法第91條第1 項之罰金罪。92年7月9日修正公布之\n    著作權法第91條第1 項意圖營利而以重製之方法侵害他人之\n    著作財產權罪，依同法第100 條前段之規定，須告訴乃論。\n    茲據告訴人東森公司於94年11月11日具狀撤回其告訴，此有\n    該刑事撤回告訴狀附卷可稽，依照上開說明，本件爰不經言\n    詞辯論，逕為諭知不受理之判決。\n四、被告錸捷公司之代表人原為林進榮，於94年6 月22日變更為\n    被告甲○○，有公司基本資料查詢結果1 份附卷可憑。又告\n    訴人原名稱為東森華榮傳播事業股份有限公司，於94年6月8\n    日變更名稱為東森電視事業股份有限公司之情，亦有經濟部\n    94年6月8日經授商字第09401101620 號函及公司變更登記表\n    在卷可考，附此敘明。\n據上論斷，應依刑事訴訟法第303條第3 款、第307條，判決如主\n文。\n中    華    民    國    94    年    11    月    15    日\n                  刑事第五庭審判長法  官  黃程暉\n                                  法  官  李宜娟\n                                  法  官  賴秀蘭\n以上正本證明與原本無異。\n如不服本判決，應於送達後10日內，向本院提出上訴狀。\n                                  書記官  陳惠娟\n中    華    民    國    94    年    11    月    16    日\n",
  "structure": {
    "main": "本件公訴不受理。",
    "reason": "一、公訴意旨略以：被告甲○○係被告錸捷科技股份有限公司（\n    下稱錸捷公司）之總經理，明知告訴人東森華榮傳播事業股\n    份有限公司（嗣變更名稱為東森電視事業股份有限公司，下\n    稱東森公司）經營之「ET-TODAY東森新聞網」網站（網址：\n    www.ettoday.com ，下稱東森網站）內各項著作之著作權利\n    均屬告訴人東森公司所有，竟未經告訴人東森公司同意或授\n    權，自民國90年1 月下旬起將告訴人東森公司登載在前揭網\n    站上「2001/01/19閱讀臺灣最好的路徑21世紀春節27條新行\n    程」、「2001/1/22擁抱自然/避寒好去處墾丁逍遙遊」等數\n    十篇旅遊報導語文著作，擅自重製於被告錸捷公司「ET-MAL\n    L 」之網站（網址：www.et-mall.com.tw，下稱錸捷網站）\n    ，並公開傳輸供網友觀覽，並以此銷售廣告牟利，期間長達\n    一年以上，因認被告甲○○涉犯92年7月9日修正公布之著作\n    權法第91條第1 項意圖營利而以重製之方法侵害他人之著作\n    財產權之罪嫌，又被告甲○○係法人錸捷公司之總經理，為\n    被告錸捷公司之受雇人，其因執行業務涉犯上開著作權法第\n    91條第1 項罪嫌，其代表之法人即被告錸捷公司涉犯依同法\n    第101條第1項，應科以同法第91條第1項之罰金罪嫌。\n二、按告訴乃論之罪，告訴人於第一審辯論終結前得撤回其告訴\n    ；又告訴經撤回者，應諭知不受理之判決；又不受理之判決\n    ，得不經言詞辯論為之，刑事訴訟法第238條第1 項、第303\n    條第3款及第307條分別定有明文。\n三、查本件告訴人東森公司告訴被告甲○○、錸捷公司違反著作\n    權法案件，起訴書認被告甲○○係犯92年7月9日修正公布之\n    著作權法第91條第1 項意圖營利而以重製之方法侵害他人之\n    著作財產權之罪，被告錸捷公司涉犯依同法第101條第1項，\n    應科以同法第91條第1 項之罰金罪。92年7月9日修正公布之\n    著作權法第91條第1 項意圖營利而以重製之方法侵害他人之\n    著作財產權罪，依同法第100 條前段之規定，須告訴乃論。\n    茲據告訴人東森公司於94年11月11日具狀撤回其告訴，此有\n    該刑事撤回告訴狀附卷可稽，依照上開說明，本件爰不經言\n    詞辯論，逕為諭知不受理之判決。\n四、被告錸捷公司之代表人原為林進榮，於94年6 月22日變更為\n    被告甲○○，有公司基本資料查詢結果1 份附卷可憑。又告\n    訴人原名稱為東森華榮傳播事業股份有限公司，於94年6月8\n    日變更名稱為東森電視事業股份有限公司之情，亦有經濟部\n    94年6月8日經授商字第09401101620 號函及公司變更登記表\n    在卷可考，附此敘明。\n據上論斷，應依刑事訴訟法第303條第3 款、第307條，判決如主\n文。"
  },
  "search": "臺灣臺北地方法院刑事判決93年度訴字第1268號公訴人臺灣臺北地方法院檢察署檢察官被告錸捷科技股份有限公司兼上一人代表人甲○○上一人選任辯護人葉建廷律師左涵湄律師上列被告因違反著作權法案件，經檢察官提起公訴（92年度偵字第23206號、93年度偵字第12684號），本院判決如下：主文本件公訴不受理。理由一、公訴意旨略以：被告甲○○係被告錸捷科技股份有限公司（下稱錸捷公司）之總經理，明知告訴人東森華榮傳播事業股份有限公司（嗣變更名稱為東森電視事業股份有限公司，下稱東森公司）經營之「ET-TODAY東森新聞網」網站（網址：www.ettoday.com，下稱東森網站）內各項著作之著作權利均屬告訴人東森公司所有，竟未經告訴人東森公司同意或授權，自民國90年1月下旬起將告訴人東森公司登載在前揭網站上「2001/01/19閱讀臺灣最好的路徑21世紀春節27條新行程」、「2001/1/22擁抱自然/避寒好去處墾丁逍遙遊」等數十篇旅遊報導語文著作，擅自重製於被告錸捷公司「ET-MALL」之網站（網址：www.et-mall.com.tw，下稱錸捷網站），並公開傳輸供網友觀覽，並以此銷售廣告牟利，期間長達一年以上，因認被告甲○○涉犯92年7月9日修正公布之著作權法第91條第1項意圖營利而以重製之方法侵害他人之著作財產權之罪嫌，又被告甲○○係法人錸捷公司之總經理，為被告錸捷公司之受雇人，其因執行業務涉犯上開著作權法第91條第1項罪嫌，其代表之法人即被告錸捷公司涉犯依同法第101條第1項，應科以同法第91條第1項之罰金罪嫌。二、按告訴乃論之罪，告訴人於第一審辯論終結前得撤回其告訴；又告訴經撤回者，應諭知不受理之判決；又不受理之判決，得不經言詞辯論為之，刑事訴訟法第238條第1項、第303條第3款及第307條分別定有明文。三、查本件告訴人東森公司告訴被告甲○○、錸捷公司違反著作權法案件，起訴書認被告甲○○係犯92年7月9日修正公布之著作權法第91條第1項意圖營利而以重製之方法侵害他人之著作財產權之罪，被告錸捷公司涉犯依同法第101條第1項，應科以同法第91條第1項之罰金罪。92年7月9日修正公布之著作權法第91條第1項意圖營利而以重製之方法侵害他人之著作財產權罪，依同法第100條前段之規定，須告訴乃論。茲據告訴人東森公司於94年11月11日具狀撤回其告訴，此有該刑事撤回告訴狀附卷可稽，依照上開說明，本件爰不經言詞辯論，逕為諭知不受理之判決。四、被告錸捷公司之代表人原為林進榮，於94年6月22日變更為被告甲○○，有公司基本資料查詢結果1份附卷可憑。又告訴人原名稱為東森華榮傳播事業股份有限公司，於94年6月8日變更名稱為東森電視事業股份有限公司之情，亦有經濟部94年6月8日經授商字第09401101620號函及公司變更登記表在卷可考，附此敘明。據上論斷，應依刑事訴訟法第303條第3款、第307條，判決如主文。中華民國94年11月15日刑事第五庭審判長法官黃程暉法官李宜娟法官賴秀蘭以上正本證明與原本無異。如不服本判決，應於送達後10日內，向本院提出上訴狀。書記官陳惠娟中華民國94年11月16日",
  "characters": {
    "judges": [
      "黃程暉",
      "李宜娟",
      "賴秀蘭"
    ],
    "prosecutors": [

    ],
    "lawyers": [
      "葉建廷",
      "左涵湄"
    ],
    "clerks": [
      "陳惠娟"
    ],
    "plaintiffs": [

    ],
    "defendants": [
      "錸捷科技股份有限公司",
      "兼  上一人",
      "代  表  人  甲○○"
    ],
    "prosecutor_office": [
      "臺灣臺北地方法院檢察署檢察官"
    ],
    "creditors": [

    ],
    "debtors": [

    ],
    "judicial_associate_officer": [

    ]
  },
  "adjudged_at": "2005-11-15",
  "created_at": "2016-02-06 23:14:39",
  "updated_at": "2016-02-06 23:14:39"
}