{
  "identify": "TPD-94-訴-5396-20051115-1",
  "court": {
    "name": "臺灣臺北地方法院",
    "code": "TPD"
  },
  "division": {
    "name": "民事",
    "code": "V"
  },
  "year": 94,
  "word": "訴",
  "number": "5396",
  "jcheck": "1",
  "reason": "清償借款",
  "content": "臺灣臺北地方法院民事判決              94年度訴字第5396號\n原      告  台北國際商業銀行股份有限公司\n法定代理人  乙○○\n訴訟代理人  丙○○\n被      告  甲○○\n上列當事人間清償借款事件，本院於民國94年11月8日言詞辯論\n終結，判決如下：\n    主  文\n被告應給付原告新台幣柒拾伍萬捌仟柒佰拾肆元，及自民國九\n十四年八月一日起至清償日止，按年息百分之九點五計算之利息\n，暨自民國九十四年九月一日起至清償日止，其逾期在六個月以\n內者，按上開利率百分之十，逾期在六個月以上者，超過部分，\n按上開利率百分之二十計付違約金。\n訴訟費用由被告負擔。\n    事  實\n甲、原告方面：\n一、聲明：如主文第1項所示。\n二、陳述：\n（一）被告於民國94年1月31日向原告借得新台幣（下同）80萬\n      元，借期自94年1月31日起至101年1月31日止，簽立借據\n      約定書，約定如未按期清償，逾期6個月以內應另按前開\n      利率10%，逾期6個月以上者，應另按約定利率20%計付違\n      約金，並約定自貸放日起依年息9.5%採固定利率，按月計\n      息。\n（二）嗣被告對前開借款本息僅繳至94年7月31日，依借據第3條\n      約定，債務應視為到期，原告本於消費借貸法律關係，請\n      求被告一次給付所欠本金758,734元及利息、違約金。\n三、證據：提出借據影本及被告繳款查詢紀錄單等件為證。\n乙、被告方面：\n    被告未於言詞辯論期日到場，亦未提出準備書狀作何聲明或\n    陳述。\n    理  由\n一、本件被告未於言詞辯論期日到場，核無民事訴訟法第386 條\n    各款所列情形，爰依原告之聲請，由其一造辯論而為判決。\n二、原告主張之事實，已據其提出與所述相符之借據影本及被告\n    繳款查詢紀錄單等件為證；而浩未提出聲明和陳述，亦未提\n    出答辯狀以供本院審酌，應認原告之主張為可採信。從而，\n    原告本於消費借貸法律關係，請求被告給付758,734元，及\n    自94年8月1日起至清償日止，按年息9.5%計算之利息，暨自\n    94年9月1日清償日止，其逾期在六個月以內者，按上開利率\n    10%，逾期在六個月以上者，超過部分，按上開利率20%計付\n    違約金，為有理由，應予准許。\n三、結論：本件原告之訴為有理由，依民事訴訟法第385條第1項\n    前段、第78條、，判決如主文。\n中    華    民    國    94    年    11    月    15    日\n                  民事第三庭    法  官  李維心\n以上正本係照原本作成\n如對本判決上訴，須於判決送達後20日內向本院提出上訴狀\n中    華    民    國    94    年    11    月    15    日\n                                書記官  詹雪娥\n",
  "structure": {
    "main": "被告應給付原告新台幣柒拾伍萬捌仟柒佰拾肆元，及自民國九\n十四年八月一日起至清償日止，按年息百分之九點五計算之利息\n，暨自民國九十四年九月一日起至清償日止，其逾期在六個月以\n內者，按上開利率百分之十，逾期在六個月以上者，超過部分，\n按上開利率百分之二十計付違約金。\n訴訟費用由被告負擔。",
    "fact": "甲、原告方面：\n一、聲明：如主文第1項所示。\n二、陳述：\n（一）被告於民國94年1月31日向原告借得新台幣（下同）80萬\n      元，借期自94年1月31日起至101年1月31日止，簽立借據\n      約定書，約定如未按期清償，逾期6個月以內應另按前開\n      利率10%，逾期6個月以上者，應另按約定利率20%計付違\n      約金，並約定自貸放日起依年息9.5%採固定利率，按月計\n      息。\n（二）嗣被告對前開借款本息僅繳至94年7月31日，依借據第3條\n      約定，債務應視為到期，原告本於消費借貸法律關係，請\n      求被告一次給付所欠本金758,734元及利息、違約金。\n三、證據：提出借據影本及被告繳款查詢紀錄單等件為證。\n乙、被告方面：\n    被告未於言詞辯論期日到場，亦未提出準備書狀作何聲明或\n    陳述。",
    "reason": "一、本件被告未於言詞辯論期日到場，核無民事訴訟法第386 條\n    各款所列情形，爰依原告之聲請，由其一造辯論而為判決。\n二、原告主張之事實，已據其提出與所述相符之借據影本及被告\n    繳款查詢紀錄單等件為證；而浩未提出聲明和陳述，亦未提\n    出答辯狀以供本院審酌，應認原告之主張為可採信。從而，\n    原告本於消費借貸法律關係，請求被告給付758,734元，及\n    自94年8月1日起至清償日止，按年息9.5%計算之利息，暨自\n    94年9月1日清償日止，其逾期在六個月以內者，按上開利率\n    10%，逾期在六個月以上者，超過部分，按上開利率20%計付\n    違約金，為有理由，應予准許。\n三、結論：本件原告之訴為有理由，依民事訴訟法第385條第1項\n    前段、第78條、，判決如主文。\n中    華    民    國    94    年    11    月    15    日\n                  民事第三庭    法  官  李維心\n以上正本係照原本作成\n如對本判決上訴，須於判決送達後20日內向本院提出上訴狀"
  },
  "search": "臺灣臺北地方法院民事判決94年度訴字第5396號原告台北國際商業銀行股份有限公司法定代理人乙○○訴訟代理人丙○○被告甲○○上列當事人間清償借款事件，本院於民國94年11月8日言詞辯論終結，判決如下：主文被告應給付原告新台幣柒拾伍萬捌仟柒佰拾肆元，及自民國九十四年八月一日起至清償日止，按年息百分之九點五計算之利息，暨自民國九十四年九月一日起至清償日止，其逾期在六個月以內者，按上開利率百分之十，逾期在六個月以上者，超過部分，按上開利率百分之二十計付違約金。訴訟費用由被告負擔。事實甲、原告方面：一、聲明：如主文第1項所示。二、陳述：（一）被告於民國94年1月31日向原告借得新台幣（下同）80萬元，借期自94年1月31日起至101年1月31日止，簽立借據約定書，約定如未按期清償，逾期6個月以內應另按前開利率10%，逾期6個月以上者，應另按約定利率20%計付違約金，並約定自貸放日起依年息9.5%採固定利率，按月計息。（二）嗣被告對前開借款本息僅繳至94年7月31日，依借據第3條約定，債務應視為到期，原告本於消費借貸法律關係，請求被告一次給付所欠本金758,734元及利息、違約金。三、證據：提出借據影本及被告繳款查詢紀錄單等件為證。乙、被告方面：被告未於言詞辯論期日到場，亦未提出準備書狀作何聲明或陳述。理由一、本件被告未於言詞辯論期日到場，核無民事訴訟法第386條各款所列情形，爰依原告之聲請，由其一造辯論而為判決。二、原告主張之事實，已據其提出與所述相符之借據影本及被告繳款查詢紀錄單等件為證；而浩未提出聲明和陳述，亦未提出答辯狀以供本院審酌，應認原告之主張為可採信。從而，原告本於消費借貸法律關係，請求被告給付758,734元，及自94年8月1日起至清償日止，按年息9.5%計算之利息，暨自94年9月1日清償日止，其逾期在六個月以內者，按上開利率10%，逾期在六個月以上者，超過部分，按上開利率20%計付違約金，為有理由，應予准許。三、結論：本件原告之訴為有理由，依民事訴訟法第385條第1項前段、第78條、，判決如主文。中華民國94年11月15日民事第三庭法官李維心以上正本係照原本作成如對本判決上訴，須於判決送達後20日內向本院提出上訴狀中華民國94年11月15日書記官詹雪娥",
  "characters": {
    "judges": [
      "李維心"
    ],
    "prosecutors": [

    ],
    "lawyers": [

    ],
    "clerks": [
      "詹雪娥"
    ],
    "plaintiffs": [
      "台北國際商業銀行股份有限公司"
    ],
    "defendants": [
      "甲○○"
    ],
    "prosecutor_office": [

    ],
    "creditors": [

    ],
    "debtors": [

    ],
    "judicial_associate_officer": [

    ]
  },
  "adjudged_at": "2005-11-15",
  "created_at": "2016-02-06 23:12:47",
  "updated_at": "2016-02-06 23:12:47"
}