{
  "identify": "TYD-94-訴-1541-20051115-1",
  "court": {
    "name": "臺灣桃園地方法院",
    "code": "TYD"
  },
  "division": {
    "name": "刑事",
    "code": "M"
  },
  "year": 94,
  "word": "訴",
  "number": "1541",
  "jcheck": "1",
  "reason": "毒品危害防制條例",
  "content": "臺灣桃園地方法院刑事判決              94年度訴字第1541號\n公  訴  人  臺灣桃園地方法院檢察署檢察官\n被      告  甲○○\n指定辯護人  本院公設辯護人吳勇毅\n上列被告因違反毒品危害防制條例案件，經檢察官提起公訴（94\n年度毒偵字第3334號），被告於準備程序進行中，就被訴事實為\n有罪之陳述，本院告知其簡式審判程序之旨，聽取當事人意見後\n，裁定由受命法官獨任依簡式審判程序審理，檢察官復聲請改依\n協商程序而為判決，茲判決如下：\n    主  文\n甲○○連續施用第一級毒品，累犯，處有期徒刑玖月。扣案之第\n一級毒品海洛因捌包（合計驗餘淨重參點零捌公克，含極微量海\n洛因殘渣之外包裝捌個合計重壹點柒玖公克）沒收銷燬。\n    事實及理由\n一、犯罪事實：甲○○前因違反家庭暴力防治法案件，經臺灣板\n    橋地方法院於民國90年4 月9 日以89年度重簡字第709 號判\n    決判處有期徒刑3 月確定，並於90年5 月25日易科罰金執行\n    完畢；另因施用毒品案件，經臺灣新竹地方法院於90年7 月\n    27日以90年度毒聲字第1198號裁定送觀察、勒戒，因無繼續\n    施用毒品傾向，於91年1 月25日執行完畢釋放出所，且由臺\n    灣新竹地方法院檢察署檢察官於同日以91年度毒偵緝字第6\n    號為不起訴處分在案。詎其仍未悔改，復於上開觀察、勒戒\n    執行完畢釋放後5 年內，基於施用第一級毒品海洛因之概括\n    犯意，自94年4 月21日上午7 時許起至94年9 月初某日某時\n    止，在其桃園縣桃園市○○路322 巷26號3 樓、桃園縣桃園\n    市○○路296 巷24號住處內，以將第一級毒品海洛因置入香\n    菸內點燃吸食之方式，連續施用第一級毒品海洛因多次，平\n    均每2 日即施用1 次。嗣分別於94年4 月22日晚間10時40分\n    許、94年6 月6 日上午11時30分許，在桃園縣桃園市○○街\n    與文化街口、桃園縣桃園市○○路與中正路口，為警查獲，\n    94年4 月22日被查獲時，並在其身上扣得第一級毒品海洛因\n    8 包（合計驗餘淨重3.08公克，含極微量海洛因殘渣之外包\n    裝8 個合計重1.79公克）。\n二、證據：\n(一)被告甲○○於警詢及本院審理時之自白。\n(二)臺北市政府警察局中正第一分局94年4 月移送煙毒麻醉藥品\n    人犯尿液檢體對照表（尿液檢體編號：011084）、臺灣檢驗\n    科技股份有限公司濫用藥物尿液檢驗報告（尿液檢體編號：\n    011084）；臺灣尖端先進生技醫藥股份有限公司濫用藥物檢\n    驗報告（尿液檢體編號：C7-276）。\n(三)扣案之第一級毒品海洛因8 包（合計驗餘淨重3.08公克，含\n    極微量海洛因殘渣之外包裝8個合計重 1.79公克）。\n(四)法務部調查局94年6 月17日調科壹字第080009415 號鑑定通\n    知書。\n(五)臺灣高等法院被告全國前案紀錄表。\n三、被告就上開犯罪事實已認罪，經本院指定公設辯護人協助其\n    進行協商，當事人雙方於審判外達成如主文所示科刑之合意\n    。經查，被告之自白，有上開證據足認屬實，並與本院認定\n    之事實相符，審酌被告之犯罪行為主要係戕害自身，並未直\n    接積極損害他人之利益，且犯後坦承犯行，態度尚稱良好，\n    暨其施用毒品之動機、目的、手段、施用毒品之次數及其素\n    行等情狀，上開協商內容尚無不當之處，本案復查無刑事訴\n    訟法第455 條之4 第1 項各款所列情形，檢察官聲請改依協\n    商程序而為判決，本院爰不經言詞辯論，於協商合意範圍內\n    為協商判決。\n四、應適用之法條：刑事訴訟法第273 條之1 第1 項、第455 條\n    之2 第1 項、第455 條之4 第2 項、第455 條之8 、第 454\n    條第2 項，毒品危害防制條例第10條第1 項、第18條第1 項\n    前段，刑法第11條、第56條、第47條。\n五、本判決除有刑事訴訟法第455 條之4 第1 項第1 款、第2 款\n    、第4 款、第6 款、第7 款所定情形之一，或違反同條第 2\n    項規定者外，不得上訴。\n六、如有前述例外得上訴之情形，又不服本件判決，得自收受判\n    決送達之日起10日內，向本院提出上訴書狀，上訴於第二審\n    法院。\n中    華    民    國    94    年    11    月    15    日\n                     刑事第十庭    法  官  許炎灶\n以上正本證明與原本無異。\n                                   書記官  文巧雲\n中    華    民    國    94    年    11    月    17    日\n附錄本案論罪科刑法條：毒品危害防制條例第10條第1 項。\n施用第一級毒品者，處 6 月以上 5 年以下有期徒刑。\n",
  "structure": {
    "main": "甲○○連續施用第一級毒品，累犯，處有期徒刑玖月。扣案之第\n一級毒品海洛因捌包（合計驗餘淨重參點零捌公克，含極微量海\n洛因殘渣之外包裝捌個合計重壹點柒玖公克）沒收銷燬。",
    "fact": "一、犯罪事實：甲○○前因違反家庭暴力防治法案件，經臺灣板\n    橋地方法院於民國90年4 月9 日以89年度重簡字第709 號判\n    決判處有期徒刑3 月確定，並於90年5 月25日易科罰金執行\n    完畢；另因施用毒品案件，經臺灣新竹地方法院於90年7 月\n    27日以90年度毒聲字第1198號裁定送觀察、勒戒，因無繼續\n    施用毒品傾向，於91年1 月25日執行完畢釋放出所，且由臺\n    灣新竹地方法院檢察署檢察官於同日以91年度毒偵緝字第6\n    號為不起訴處分在案。詎其仍未悔改，復於上開觀察、勒戒\n    執行完畢釋放後5 年內，基於施用第一級毒品海洛因之概括\n    犯意，自94年4 月21日上午7 時許起至94年9 月初某日某時\n    止，在其桃園縣桃園市○○路322 巷26號3 樓、桃園縣桃園\n    市○○路296 巷24號住處內，以將第一級毒品海洛因置入香\n    菸內點燃吸食之方式，連續施用第一級毒品海洛因多次，平\n    均每2 日即施用1 次。嗣分別於94年4 月22日晚間10時40分\n    許、94年6 月6 日上午11時30分許，在桃園縣桃園市○○街\n    與文化街口、桃園縣桃園市○○路與中正路口，為警查獲，\n    94年4 月22日被查獲時，並在其身上扣得第一級毒品海洛因\n    8 包（合計驗餘淨重3.08公克，含極微量海洛因殘渣之外包\n    裝8 個合計重1.79公克）。\n二、證據：\n(一)被告甲○○於警詢及本院審理時之自白。\n(二)臺北市政府警察局中正第一分局94年4 月移送煙毒麻醉藥品\n    人犯尿液檢體對照表（尿液檢體編號：011084）、臺灣檢驗\n    科技股份有限公司濫用藥物尿液檢驗報告（尿液檢體編號：\n    011084）；臺灣尖端先進生技醫藥股份有限公司濫用藥物檢\n    驗報告（尿液檢體編號：C7-276）。\n(三)扣案之第一級毒品海洛因8 包（合計驗餘淨重3.08公克，含\n    極微量海洛因殘渣之外包裝8個合計重 1.79公克）。\n(四)法務部調查局94年6 月17日調科壹字第080009415 號鑑定通\n    知書。\n(五)臺灣高等法院被告全國前案紀錄表。\n三、被告就上開犯罪事實已認罪，經本院指定公設辯護人協助其\n    進行協商，當事人雙方於審判外達成如主文所示科刑之合意\n    。經查，被告之自白，有上開證據足認屬實，並與本院認定\n    之事實相符，審酌被告之犯罪行為主要係戕害自身，並未直\n    接積極損害他人之利益，且犯後坦承犯行，態度尚稱良好，\n    暨其施用毒品之動機、目的、手段、施用毒品之次數及其素\n    行等情狀，上開協商內容尚無不當之處，本案復查無刑事訴\n    訟法第455 條之4 第1 項各款所列情形，檢察官聲請改依協\n    商程序而為判決，本院爰不經言詞辯論，於協商合意範圍內\n    為協商判決。\n四、應適用之法條：刑事訴訟法第273 條之1 第1 項、第455 條\n    之2 第1 項、第455 條之4 第2 項、第455 條之8 、第 454\n    條第2 項，毒品危害防制條例第10條第1 項、第18條第1 項\n    前段，刑法第11條、第56條、第47條。\n五、本判決除有刑事訴訟法第455 條之4 第1 項第1 款、第2 款\n    、第4 款、第6 款、第7 款所定情形之一，或違反同條第 2\n    項規定者外，不得上訴。\n六、如有前述例外得上訴之情形，又不服本件判決，得自收受判\n    決送達之日起10日內，向本院提出上訴書狀，上訴於第二審\n    法院。",
    "reason": "一、犯罪事實：甲○○前因違反家庭暴力防治法案件，經臺灣板\n    橋地方法院於民國90年4 月9 日以89年度重簡字第709 號判\n    決判處有期徒刑3 月確定，並於90年5 月25日易科罰金執行\n    完畢；另因施用毒品案件，經臺灣新竹地方法院於90年7 月\n    27日以90年度毒聲字第1198號裁定送觀察、勒戒，因無繼續\n    施用毒品傾向，於91年1 月25日執行完畢釋放出所，且由臺\n    灣新竹地方法院檢察署檢察官於同日以91年度毒偵緝字第6\n    號為不起訴處分在案。詎其仍未悔改，復於上開觀察、勒戒\n    執行完畢釋放後5 年內，基於施用第一級毒品海洛因之概括\n    犯意，自94年4 月21日上午7 時許起至94年9 月初某日某時\n    止，在其桃園縣桃園市○○路322 巷26號3 樓、桃園縣桃園\n    市○○路296 巷24號住處內，以將第一級毒品海洛因置入香\n    菸內點燃吸食之方式，連續施用第一級毒品海洛因多次，平\n    均每2 日即施用1 次。嗣分別於94年4 月22日晚間10時40分\n    許、94年6 月6 日上午11時30分許，在桃園縣桃園市○○街\n    與文化街口、桃園縣桃園市○○路與中正路口，為警查獲，\n    94年4 月22日被查獲時，並在其身上扣得第一級毒品海洛因\n    8 包（合計驗餘淨重3.08公克，含極微量海洛因殘渣之外包\n    裝8 個合計重1.79公克）。\n二、證據：\n(一)被告甲○○於警詢及本院審理時之自白。\n(二)臺北市政府警察局中正第一分局94年4 月移送煙毒麻醉藥品\n    人犯尿液檢體對照表（尿液檢體編號：011084）、臺灣檢驗\n    科技股份有限公司濫用藥物尿液檢驗報告（尿液檢體編號：\n    011084）；臺灣尖端先進生技醫藥股份有限公司濫用藥物檢\n    驗報告（尿液檢體編號：C7-276）。\n(三)扣案之第一級毒品海洛因8 包（合計驗餘淨重3.08公克，含\n    極微量海洛因殘渣之外包裝8個合計重 1.79公克）。\n(四)法務部調查局94年6 月17日調科壹字第080009415 號鑑定通\n    知書。\n(五)臺灣高等法院被告全國前案紀錄表。\n三、被告就上開犯罪事實已認罪，經本院指定公設辯護人協助其\n    進行協商，當事人雙方於審判外達成如主文所示科刑之合意\n    。經查，被告之自白，有上開證據足認屬實，並與本院認定\n    之事實相符，審酌被告之犯罪行為主要係戕害自身，並未直\n    接積極損害他人之利益，且犯後坦承犯行，態度尚稱良好，\n    暨其施用毒品之動機、目的、手段、施用毒品之次數及其素\n    行等情狀，上開協商內容尚無不當之處，本案復查無刑事訴\n    訟法第455 條之4 第1 項各款所列情形，檢察官聲請改依協\n    商程序而為判決，本院爰不經言詞辯論，於協商合意範圍內\n    為協商判決。\n四、應適用之法條：刑事訴訟法第273 條之1 第1 項、第455 條\n    之2 第1 項、第455 條之4 第2 項、第455 條之8 、第 454\n    條第2 項，毒品危害防制條例第10條第1 項、第18條第1 項\n    前段，刑法第11條、第56條、第47條。\n五、本判決除有刑事訴訟法第455 條之4 第1 項第1 款、第2 款\n    、第4 款、第6 款、第7 款所定情形之一，或違反同條第 2\n    項規定者外，不得上訴。\n六、如有前述例外得上訴之情形，又不服本件判決，得自收受判\n    決送達之日起10日內，向本院提出上訴書狀，上訴於第二審\n    法院。"
  },
  "search": "臺灣桃園地方法院刑事判決94年度訴字第1541號公訴人臺灣桃園地方法院檢察署檢察官被告甲○○指定辯護人本院公設辯護人吳勇毅上列被告因違反毒品危害防制條例案件，經檢察官提起公訴（94年度毒偵字第3334號），被告於準備程序進行中，就被訴事實為有罪之陳述，本院告知其簡式審判程序之旨，聽取當事人意見後，裁定由受命法官獨任依簡式審判程序審理，檢察官復聲請改依協商程序而為判決，茲判決如下：主文甲○○連續施用第一級毒品，累犯，處有期徒刑玖月。扣案之第一級毒品海洛因捌包（合計驗餘淨重參點零捌公克，含極微量海洛因殘渣之外包裝捌個合計重壹點柒玖公克）沒收銷燬。事實及理由一、犯罪事實：甲○○前因違反家庭暴力防治法案件，經臺灣板橋地方法院於民國90年4月9日以89年度重簡字第709號判決判處有期徒刑3月確定，並於90年5月25日易科罰金執行完畢；另因施用毒品案件，經臺灣新竹地方法院於90年7月27日以90年度毒聲字第1198號裁定送觀察、勒戒，因無繼續施用毒品傾向，於91年1月25日執行完畢釋放出所，且由臺灣新竹地方法院檢察署檢察官於同日以91年度毒偵緝字第6號為不起訴處分在案。詎其仍未悔改，復於上開觀察、勒戒執行完畢釋放後5年內，基於施用第一級毒品海洛因之概括犯意，自94年4月21日上午7時許起至94年9月初某日某時止，在其桃園縣桃園市○○路322巷26號3樓、桃園縣桃園市○○路296巷24號住處內，以將第一級毒品海洛因置入香菸內點燃吸食之方式，連續施用第一級毒品海洛因多次，平均每2日即施用1次。嗣分別於94年4月22日晚間10時40分許、94年6月6日上午11時30分許，在桃園縣桃園市○○街與文化街口、桃園縣桃園市○○路與中正路口，為警查獲，94年4月22日被查獲時，並在其身上扣得第一級毒品海洛因8包（合計驗餘淨重3.08公克，含極微量海洛因殘渣之外包裝8個合計重1.79公克）。二、證據：(一)被告甲○○於警詢及本院審理時之自白。(二)臺北市政府警察局中正第一分局94年4月移送煙毒麻醉藥品人犯尿液檢體對照表（尿液檢體編號：011084）、臺灣檢驗科技股份有限公司濫用藥物尿液檢驗報告（尿液檢體編號：011084）；臺灣尖端先進生技醫藥股份有限公司濫用藥物檢驗報告（尿液檢體編號：C7-276）。(三)扣案之第一級毒品海洛因8包（合計驗餘淨重3.08公克，含極微量海洛因殘渣之外包裝8個合計重1.79公克）。(四)法務部調查局94年6月17日調科壹字第080009415號鑑定通知書。(五)臺灣高等法院被告全國前案紀錄表。三、被告就上開犯罪事實已認罪，經本院指定公設辯護人協助其進行協商，當事人雙方於審判外達成如主文所示科刑之合意。經查，被告之自白，有上開證據足認屬實，並與本院認定之事實相符，審酌被告之犯罪行為主要係戕害自身，並未直接積極損害他人之利益，且犯後坦承犯行，態度尚稱良好，暨其施用毒品之動機、目的、手段、施用毒品之次數及其素行等情狀，上開協商內容尚無不當之處，本案復查無刑事訴訟法第455條之4第1項各款所列情形，檢察官聲請改依協商程序而為判決，本院爰不經言詞辯論，於協商合意範圍內為協商判決。四、應適用之法條：刑事訴訟法第273條之1第1項、第455條之2第1項、第455條之4第2項、第455條之8、第454條第2項，毒品危害防制條例第10條第1項、第18條第1項前段，刑法第11條、第56條、第47條。五、本判決除有刑事訴訟法第455條之4第1項第1款、第2款、第4款、第6款、第7款所定情形之一，或違反同條第2項規定者外，不得上訴。六、如有前述例外得上訴之情形，又不服本件判決，得自收受判決送達之日起10日內，向本院提出上訴書狀，上訴於第二審法院。中華民國94年11月15日刑事第十庭法官許炎灶以上正本證明與原本無異。書記官文巧雲中華民國94年11月17日附錄本案論罪科刑法條：毒品危害防制條例第10條第1項。施用第一級毒品者，處6月以上5年以下有期徒刑。",
  "characters": {
    "judges": [
      "許炎灶"
    ],
    "prosecutors": [

    ],
    "lawyers": [

    ],
    "clerks": [
      "文巧雲"
    ],
    "plaintiffs": [

    ],
    "defendants": [
      "甲○○"
    ],
    "prosecutor_office": [
      "臺灣桃園地方法院檢察署檢察官"
    ],
    "creditors": [

    ],
    "debtors": [

    ],
    "judicial_associate_officer": [

    ]
  },
  "adjudged_at": "2005-11-15",
  "created_at": "2016-02-06 23:10:10",
  "updated_at": "2016-02-06 23:10:10"
}