{
  "identify": "TYD-94-交訴-128-20051115-3",
  "court": {
    "name": "臺灣桃園地方法院",
    "code": "TYD"
  },
  "division": {
    "name": "刑事",
    "code": "M"
  },
  "year": 94,
  "word": "交訴",
  "number": "128",
  "jcheck": "3",
  "reason": "肇事遺棄罪等",
  "content": "臺灣桃園地方法院刑事判決             94年度交訴字第128號\n公  訴  人  台灣桃園地方法院檢察署檢察官\n被      告  甲○○\n上列被告因肇事遺棄罪等案件，經檢察官提起公訴（94年度偵字\n第13294 號），本院判決如下：\n    主  文\n被告甲○○被訴過失傷害部分公訴不受理。\n    理  由\n一、本件公訴意旨略以：被告甲○○於民國九十四年六月十五日\n    上午某時許，駕駛其所有之車牌號碼三Ｌ—八八五八號自小\n    客車（下稱系爭汽車），沿桃園縣八德市○○○街行駛，俟\n    其行經永福西街與福國北街交岔路口，欲沿永福西街右轉福\n    國北街之際，本應注意汽車行駛時，駕駛人應注意車前狀況\n    ，並隨時採取必要之安全措施，而依當時天候陰、光線為日\n    間自然光、路面乾燥、無缺陷、無障礙物、視距良好等一切\n    情狀，其並無不能注意之情形，竟疏未注意行人即告訴人鄭\n    乙○○正欲橫越永福西街，被告竟仍貿然右轉，因而撞及步\n    行中之告訴人，告訴人遭撞及後先彈起碰撞到系爭汽車之引\n    擎蓋後，摔落在地，並因此受有第十二胸椎壓迫性骨折之傷\n    害。詎被告明知已駕車肇事致人受傷，竟漠視該情未加援助\n    ，另起肇事逃逸之犯意，駕駛系爭汽車離開現場（其所涉肇\n    事逃逸罪嫌由本院另行審結），適經目擊前述車禍意外發生\n    之自小客車駕駛杜更新，記下被告所駕系爭汽車之車牌號碼\n    後報警處理，經警打電話至被告家中，告知被告駕車肇事情\n    事，要其出面說明後，被告始於九十四年六月十八日上午十\n    一時十分許，前往桃園縣政府警察局八德分局自白案情。案\n    經桃園縣政府警察局八德分局報請臺灣桃園地方法院檢察署\n    檢察官偵查起訴。\n二、按告訴乃論之罪，告訴人於第一審辯論終結前得撤回其告訴\n    ；又告訴經撤回者，法院應諭知不受理之判決，刑事訴訟法\n    第二百三十八條第一項、第三百零三條第三款定有明文。查\n    本件被告所涉刑法第二百八十四條第一項前段過失傷害罪嫌\n    ，依同法第二百八十七條前段之規定，須告訴乃論。嗣經告\n    訴人鄭乙○○於本院審理中具狀撤回告訴，有刑事撤回告訴\n    狀在卷可稽，並經本院電詢告訴人確認無誤，依照首開規定\n    ，本院就被告此部分之犯行，不經言詞辯論，逕行諭知不受\n    理之判決。\n三、據上論斷，應依刑事訴訟法第三百零三條第三款、第三百零\n    七條，判決如主文。\n中    華    民    國    94    年    11    月    15    日\n                  刑事第九庭  審判長法  官  林明洲\n                                    法  官  何燕蓉\n                                    法  官  胡芷瑜\n上正本證明與原本無異。\n如不服本判決，應於判決送達後10日內向本院提出上訴狀（應附\n繕本），上訴於臺灣高等法院。\n                                    書記官  李珈慧\n中    華    民    國    94    年    11    月    24    日\n",
  "structure": {
    "main": "被告甲○○被訴過失傷害部分公訴不受理。",
    "reason": "一、本件公訴意旨略以：被告甲○○於民國九十四年六月十五日\n    上午某時許，駕駛其所有之車牌號碼三Ｌ—八八五八號自小\n    客車（下稱系爭汽車），沿桃園縣八德市○○○街行駛，俟\n    其行經永福西街與福國北街交岔路口，欲沿永福西街右轉福\n    國北街之際，本應注意汽車行駛時，駕駛人應注意車前狀況\n    ，並隨時採取必要之安全措施，而依當時天候陰、光線為日\n    間自然光、路面乾燥、無缺陷、無障礙物、視距良好等一切\n    情狀，其並無不能注意之情形，竟疏未注意行人即告訴人鄭\n    乙○○正欲橫越永福西街，被告竟仍貿然右轉，因而撞及步\n    行中之告訴人，告訴人遭撞及後先彈起碰撞到系爭汽車之引\n    擎蓋後，摔落在地，並因此受有第十二胸椎壓迫性骨折之傷\n    害。詎被告明知已駕車肇事致人受傷，竟漠視該情未加援助\n    ，另起肇事逃逸之犯意，駕駛系爭汽車離開現場（其所涉肇\n    事逃逸罪嫌由本院另行審結），適經目擊前述車禍意外發生\n    之自小客車駕駛杜更新，記下被告所駕系爭汽車之車牌號碼\n    後報警處理，經警打電話至被告家中，告知被告駕車肇事情\n    事，要其出面說明後，被告始於九十四年六月十八日上午十\n    一時十分許，前往桃園縣政府警察局八德分局自白案情。案\n    經桃園縣政府警察局八德分局報請臺灣桃園地方法院檢察署\n    檢察官偵查起訴。\n二、按告訴乃論之罪，告訴人於第一審辯論終結前得撤回其告訴\n    ；又告訴經撤回者，法院應諭知不受理之判決，刑事訴訟法\n    第二百三十八條第一項、第三百零三條第三款定有明文。查\n    本件被告所涉刑法第二百八十四條第一項前段過失傷害罪嫌\n    ，依同法第二百八十七條前段之規定，須告訴乃論。嗣經告\n    訴人鄭乙○○於本院審理中具狀撤回告訴，有刑事撤回告訴\n    狀在卷可稽，並經本院電詢告訴人確認無誤，依照首開規定\n    ，本院就被告此部分之犯行，不經言詞辯論，逕行諭知不受\n    理之判決。\n三、據上論斷，應依刑事訴訟法第三百零三條第三款、第三百零\n    七條，判決如主文。"
  },
  "search": "臺灣桃園地方法院刑事判決94年度交訴字第128號公訴人台灣桃園地方法院檢察署檢察官被告甲○○上列被告因肇事遺棄罪等案件，經檢察官提起公訴（94年度偵字第13294號），本院判決如下：主文被告甲○○被訴過失傷害部分公訴不受理。理由一、本件公訴意旨略以：被告甲○○於民國九十四年六月十五日上午某時許，駕駛其所有之車牌號碼三Ｌ—八八五八號自小客車（下稱系爭汽車），沿桃園縣八德市○○○街行駛，俟其行經永福西街與福國北街交岔路口，欲沿永福西街右轉福國北街之際，本應注意汽車行駛時，駕駛人應注意車前狀況，並隨時採取必要之安全措施，而依當時天候陰、光線為日間自然光、路面乾燥、無缺陷、無障礙物、視距良好等一切情狀，其並無不能注意之情形，竟疏未注意行人即告訴人鄭乙○○正欲橫越永福西街，被告竟仍貿然右轉，因而撞及步行中之告訴人，告訴人遭撞及後先彈起碰撞到系爭汽車之引擎蓋後，摔落在地，並因此受有第十二胸椎壓迫性骨折之傷害。詎被告明知已駕車肇事致人受傷，竟漠視該情未加援助，另起肇事逃逸之犯意，駕駛系爭汽車離開現場（其所涉肇事逃逸罪嫌由本院另行審結），適經目擊前述車禍意外發生之自小客車駕駛杜更新，記下被告所駕系爭汽車之車牌號碼後報警處理，經警打電話至被告家中，告知被告駕車肇事情事，要其出面說明後，被告始於九十四年六月十八日上午十一時十分許，前往桃園縣政府警察局八德分局自白案情。案經桃園縣政府警察局八德分局報請臺灣桃園地方法院檢察署檢察官偵查起訴。二、按告訴乃論之罪，告訴人於第一審辯論終結前得撤回其告訴；又告訴經撤回者，法院應諭知不受理之判決，刑事訴訟法第二百三十八條第一項、第三百零三條第三款定有明文。查本件被告所涉刑法第二百八十四條第一項前段過失傷害罪嫌，依同法第二百八十七條前段之規定，須告訴乃論。嗣經告訴人鄭乙○○於本院審理中具狀撤回告訴，有刑事撤回告訴狀在卷可稽，並經本院電詢告訴人確認無誤，依照首開規定，本院就被告此部分之犯行，不經言詞辯論，逕行諭知不受理之判決。三、據上論斷，應依刑事訴訟法第三百零三條第三款、第三百零七條，判決如主文。中華民國94年11月15日刑事第九庭審判長法官林明洲法官何燕蓉法官胡芷瑜上正本證明與原本無異。如不服本判決，應於判決送達後10日內向本院提出上訴狀（應附繕本），上訴於臺灣高等法院。書記官李珈慧中華民國94年11月24日",
  "characters": {
    "judges": [
      "林明洲",
      "何燕蓉",
      "胡芷瑜"
    ],
    "prosecutors": [

    ],
    "lawyers": [

    ],
    "clerks": [
      "李珈慧"
    ],
    "plaintiffs": [

    ],
    "defendants": [
      "甲○○"
    ],
    "prosecutor_office": [
      "台灣桃園地方法院檢察署檢察官"
    ],
    "creditors": [

    ],
    "debtors": [

    ],
    "judicial_associate_officer": [

    ]
  },
  "adjudged_at": "2005-11-15",
  "created_at": "2016-02-06 23:14:58",
  "updated_at": "2016-02-06 23:14:58"
}