{
  "identify": "TYD-94-訴-1345-20051115-2",
  "court": {
    "name": "臺灣桃園地方法院",
    "code": "TYD"
  },
  "division": {
    "name": "民事",
    "code": "V"
  },
  "year": 94,
  "word": "訴",
  "number": "1345",
  "jcheck": "2",
  "reason": "清償債務",
  "content": "臺灣桃園地方法院民事裁定              94年度訴字第1345號\n原      告  第一商業銀行股份有限公司\n法定代理人  趙元旗\n訴訟代理人  郭秀琪\n被      告  甲○○\n上列當事人間請求清償債務事件，本院裁定如下：\n    主  文\n原告之訴駁回。\n訴訟費用由原告負擔。\n    理  由\n一、按提起民事訴訟應依民事訴訟法第77條之13、第77條之14第\n    1項規定繳納裁判費，此為必須具備之程式。\n二、本件原告起訴，未據繳納全部裁判費，經本院於民國94年10\n    月6 日裁定命原告於5 日內補正裁判費新臺幣11,088元，該\n    裁定已於94年10月14日送達原告，有送達證書在卷可稽。原\n    告逾期迄未補正，其訴不能認為合法，應予駁回。\n三、依民事訴訟法第249條第1項第6款、第95條、第78條，裁定\n    如主文。\n中    華    民    國    94    年    11    月    15    日\n                  民事第三庭  法  官  林望民\n上列正本證明與原本無異\n如不服本裁定應於裁定送達後10日內向本院提出抗告狀，並應繳\n納抗告裁判費新臺幣1,000元。\n中    華    民    國    94    年    11    月    15    日\n                              書記官  曾建中\n",
  "structure": {
    "main": "原告之訴駁回。\n訴訟費用由原告負擔。",
    "reason": "一、按提起民事訴訟應依民事訴訟法第77條之13、第77條之14第\n    1項規定繳納裁判費，此為必須具備之程式。\n二、本件原告起訴，未據繳納全部裁判費，經本院於民國94年10\n    月6 日裁定命原告於5 日內補正裁判費新臺幣11,088元，該\n    裁定已於94年10月14日送達原告，有送達證書在卷可稽。原\n    告逾期迄未補正，其訴不能認為合法，應予駁回。\n三、依民事訴訟法第249條第1項第6款、第95條、第78條，裁定\n    如主文。"
  },
  "search": "臺灣桃園地方法院民事裁定94年度訴字第1345號原告第一商業銀行股份有限公司法定代理人趙元旗訴訟代理人郭秀琪被告甲○○上列當事人間請求清償債務事件，本院裁定如下：主文原告之訴駁回。訴訟費用由原告負擔。理由一、按提起民事訴訟應依民事訴訟法第77條之13、第77條之14第1項規定繳納裁判費，此為必須具備之程式。二、本件原告起訴，未據繳納全部裁判費，經本院於民國94年10月6日裁定命原告於5日內補正裁判費新臺幣11,088元，該裁定已於94年10月14日送達原告，有送達證書在卷可稽。原告逾期迄未補正，其訴不能認為合法，應予駁回。三、依民事訴訟法第249條第1項第6款、第95條、第78條，裁定如主文。中華民國94年11月15日民事第三庭法官林望民上列正本證明與原本無異如不服本裁定應於裁定送達後10日內向本院提出抗告狀，並應繳納抗告裁判費新臺幣1,000元。中華民國94年11月15日書記官曾建中",
  "characters": {
    "judges": [
      "林望民"
    ],
    "prosecutors": [

    ],
    "lawyers": [

    ],
    "clerks": [
      "曾建中"
    ],
    "plaintiffs": [
      "第一商業銀行股份有限公司"
    ],
    "defendants": [
      "甲○○"
    ],
    "prosecutor_office": [

    ],
    "creditors": [

    ],
    "debtors": [

    ],
    "judicial_associate_officer": [

    ]
  },
  "adjudged_at": "2005-11-15",
  "created_at": "2016-02-06 23:15:20",
  "updated_at": "2016-02-06 23:15:20"
}