{
  "identify": "KSD-94-訴-869-20050531-1",
  "court": {
    "name": "臺灣高雄地方法院",
    "code": "KSD"
  },
  "division": {
    "name": "民事",
    "code": "V"
  },
  "year": 94,
  "word": "訴",
  "number": "869",
  "jcheck": "1",
  "reason": "清償借款",
  "content": "臺灣高雄地方法院民事判決               94年度訴字第869號\n原      告  中央信託局股份有限公司北高雄分公司\n法定代理人  戊○○\n代  理  人  甲○○\n代  理  人  丙○○\n被      告  乙○○\n被      告  丁○○\n當事人間清償借款事件，本院民國94年5月26日言詞辯論終結，\n判決如下：\n  主  文\n被告應連帶給付原告新臺幣柒拾柒萬貳仟壹佰貳拾伍元，及自民\n國九十三年十二月十四日起至清償日止，按年息百分之七點零七\n九計算之利息，暨自民國九十四年一月十五日起至清償日止，逾\n期在六個月以內者，按上開利率百分之十，逾期超過六個月者，\n按上開利率百分之二十計算之違約金。\n訴訟費用由被告連帶負擔。\n  事實及理由\n一、按當事人得以合意定第一審管轄法院，民事訴訟法第24條第\n    1 項前段定有明文。經查：本件原告係依消費借貸及連帶保\n    證之法律關係，訴請被告清償借款，而依兩造所簽訂之消費\n    性借款契約第8 條約定：「‧‧‧如違背本契約規定之各條\n    款經貴局提起訴訟時，由貴局所在地法院審理‧‧‧」，有\n    該契約一紙在卷可稽，又原告營業處所在高雄市左營區○○\n    ○路106 號1 、2F，亦有高雄市政府營利事業登記證一紙附\n    卷可參，足見兩造就本件之涉訟業已合意以本院為第一審管\n    轄法院。另本件訴訟非屬專屬管轄之訴訟，兩造上開合意管\n    轄之約定自不受影響。是本院依前揭法條規定，對本件自有\n    管轄權，合先敘明。\n二、本件被告均經合法通知，均未於言詞辯論期日到場，核無民\n    事訴訟法第386 條各款所列情形，爰依原告聲請，由其一造\n    辯論而為判決。\n三、原告起訴主張：被告乙○○於民國92年3 月14日，邀同被告\n    丁○○為連帶保證人，向原告借款新台幣（下同）100 萬元\n    ，約定到期日迄99年3 月14日止，利息則按原告基準放款年\n    利率加年息0.275 ﹪計算，惟若未依期限清償本息時，利息\n    則按逾期當時原告基準放款年利率加年息4 ﹪計算，（系爭\n    借款逾期清償時，原告基準放款利率為3. 079﹪，加計4 ﹪\n    ，主張本件利率應為7.079 ﹪），且自借款日起，按月攤還\n    本息，如不依約清償，全部債務視為到期，並自遲延日起6\n    個月以內者，按上開利率10﹪，逾期超過6 個月部分，按上\n    開約定利率20﹪計付違約金。詎被告乙○○攤還本息至94年\n    1 月4 日起即未履行債務（實際利息收至93年12月13日），\n    依約已喪失期限利益，全部債務視同到期，經核算結果，尚\n    有如主文所示之本金、利息及違約金未清償，而被告丁○○\n    為系爭債務之連帶保證人，依法應負連帶清償之責，爰本於\n    消費借貸、連帶保證法律關係，提起本訴，並聲明求為判決\n    ：如主文所示。\n四、按被告均未於言詞辯論期日到場爭執，亦未提出書狀作何聲\n    明或陳述。\n五、按稱消費借貸者，謂當事人約定，一方移轉金錢或其他代替\n    物之所有權於他方，而他方以種類、品質、數量相同之物返\n    還之契約。借用人應於約定期限內，返還與借用物種類、品\n    質、數量相同之物。遲延之債務，以支付金錢為標的者，債\n    權人得請求依法定利率計算之遲延利息。但約定利率較高者\n    ，仍從其約定利率。當事人得約定債務人不履行債務時，應\n    支付違約金。民法第474 條、第478 條、第233 條第1 項、\n    第250 條第1 項分別定有明文。又稱保證者，謂當事人約定\n    ，一方於他方之債務人不履行債務時，由其代負履行責任之\n    契約。保證債務，除契約另有訂定外，包含主債務之利息、\n    違約金、損害賠償及其他從屬於主債務之負擔，民法第739\n    條、第740 條亦分別定有明文。本件原告主張被告乙○○邀\n    同被告丁○○為連帶保證人，向原告借款100 萬元，後未依\n    約履行債務，全部債務視為到期，尚有如主文所示之本金、\n    利息及違約金未清償之事實，已據其提出借款契約、貸款清\n    償查詢表、放款帳卡明細列印表、基準放款利率變動表各一\n    份為證，本院依上開證據所載清償期限、方式、利息並受償\n    數額為調查之結果，與原告所述之事實相符，而被告經合法\n    通知，均未到庭爭執，亦未提出書狀作何聲明或陳述，依民\n    事訴訟法第280 條第3 項、第1 項規定，視同自認，則原告\n    主張之事實，可堪信為真實，則原告本於消費借貸及連帶保\n    證之法律關係，請求被告連帶給付如主文所示之本金及利息\n    、違約金，即屬正當，應予准許。\n六、結論：本件原告之訴為有理由，依民事訴訟法第385 條第1\n    項前段、第85條第2項，判決如主文。\n中    華    民    國    94    年    5     月    31    日\n                  民事第二庭法  官  黃宗揚\n正本係照原本作成。\n如不服本判決，應於送達後20日內，向本院提出上訴狀並表明上\n訴理由，如於本判決宣示後送達前提起上訴者，應於判決送達後\n10日內補提上訴理由書（須附繕本）。\n中    華    民    國    94    年    5     月    31    日\n                            書記官  陳玉娥\n",
  "structure": {
    "main": "被告應連帶給付原告新臺幣柒拾柒萬貳仟壹佰貳拾伍元，及自民\n國九十三年十二月十四日起至清償日止，按年息百分之七點零七\n九計算之利息，暨自民國九十四年一月十五日起至清償日止，逾\n期在六個月以內者，按上開利率百分之十，逾期超過六個月者，\n按上開利率百分之二十計算之違約金。\n訴訟費用由被告連帶負擔。",
    "fact": "一、按當事人得以合意定第一審管轄法院，民事訴訟法第24條第\n    1 項前段定有明文。經查：本件原告係依消費借貸及連帶保\n    證之法律關係，訴請被告清償借款，而依兩造所簽訂之消費\n    性借款契約第8 條約定：「‧‧‧如違背本契約規定之各條\n    款經貴局提起訴訟時，由貴局所在地法院審理‧‧‧」，有\n    該契約一紙在卷可稽，又原告營業處所在高雄市左營區○○\n    ○路106 號1 、2F，亦有高雄市政府營利事業登記證一紙附\n    卷可參，足見兩造就本件之涉訟業已合意以本院為第一審管\n    轄法院。另本件訴訟非屬專屬管轄之訴訟，兩造上開合意管\n    轄之約定自不受影響。是本院依前揭法條規定，對本件自有\n    管轄權，合先敘明。\n二、本件被告均經合法通知，均未於言詞辯論期日到場，核無民\n    事訴訟法第386 條各款所列情形，爰依原告聲請，由其一造\n    辯論而為判決。\n三、原告起訴主張：被告乙○○於民國92年3 月14日，邀同被告\n    丁○○為連帶保證人，向原告借款新台幣（下同）100 萬元\n    ，約定到期日迄99年3 月14日止，利息則按原告基準放款年\n    利率加年息0.275 ﹪計算，惟若未依期限清償本息時，利息\n    則按逾期當時原告基準放款年利率加年息4 ﹪計算，（系爭\n    借款逾期清償時，原告基準放款利率為3. 079﹪，加計4 ﹪\n    ，主張本件利率應為7.079 ﹪），且自借款日起，按月攤還\n    本息，如不依約清償，全部債務視為到期，並自遲延日起6\n    個月以內者，按上開利率10﹪，逾期超過6 個月部分，按上\n    開約定利率20﹪計付違約金。詎被告乙○○攤還本息至94年\n    1 月4 日起即未履行債務（實際利息收至93年12月13日），\n    依約已喪失期限利益，全部債務視同到期，經核算結果，尚\n    有如主文所示之本金、利息及違約金未清償，而被告丁○○\n    為系爭債務之連帶保證人，依法應負連帶清償之責，爰本於\n    消費借貸、連帶保證法律關係，提起本訴，並聲明求為判決\n    ：如主文所示。\n四、按被告均未於言詞辯論期日到場爭執，亦未提出書狀作何聲\n    明或陳述。\n五、按稱消費借貸者，謂當事人約定，一方移轉金錢或其他代替\n    物之所有權於他方，而他方以種類、品質、數量相同之物返\n    還之契約。借用人應於約定期限內，返還與借用物種類、品\n    質、數量相同之物。遲延之債務，以支付金錢為標的者，債\n    權人得請求依法定利率計算之遲延利息。但約定利率較高者\n    ，仍從其約定利率。當事人得約定債務人不履行債務時，應\n    支付違約金。民法第474 條、第478 條、第233 條第1 項、\n    第250 條第1 項分別定有明文。又稱保證者，謂當事人約定\n    ，一方於他方之債務人不履行債務時，由其代負履行責任之\n    契約。保證債務，除契約另有訂定外，包含主債務之利息、\n    違約金、損害賠償及其他從屬於主債務之負擔，民法第739\n    條、第740 條亦分別定有明文。本件原告主張被告乙○○邀\n    同被告丁○○為連帶保證人，向原告借款100 萬元，後未依\n    約履行債務，全部債務視為到期，尚有如主文所示之本金、\n    利息及違約金未清償之事實，已據其提出借款契約、貸款清\n    償查詢表、放款帳卡明細列印表、基準放款利率變動表各一\n    份為證，本院依上開證據所載清償期限、方式、利息並受償\n    數額為調查之結果，與原告所述之事實相符，而被告經合法\n    通知，均未到庭爭執，亦未提出書狀作何聲明或陳述，依民\n    事訴訟法第280 條第3 項、第1 項規定，視同自認，則原告\n    主張之事實，可堪信為真實，則原告本於消費借貸及連帶保\n    證之法律關係，請求被告連帶給付如主文所示之本金及利息\n    、違約金，即屬正當，應予准許。\n六、結論：本件原告之訴為有理由，依民事訴訟法第385 條第1\n    項前段、第85條第2項，判決如主文。",
    "reason": "一、按當事人得以合意定第一審管轄法院，民事訴訟法第24條第\n    1 項前段定有明文。經查：本件原告係依消費借貸及連帶保\n    證之法律關係，訴請被告清償借款，而依兩造所簽訂之消費\n    性借款契約第8 條約定：「‧‧‧如違背本契約規定之各條\n    款經貴局提起訴訟時，由貴局所在地法院審理‧‧‧」，有\n    該契約一紙在卷可稽，又原告營業處所在高雄市左營區○○\n    ○路106 號1 、2F，亦有高雄市政府營利事業登記證一紙附\n    卷可參，足見兩造就本件之涉訟業已合意以本院為第一審管\n    轄法院。另本件訴訟非屬專屬管轄之訴訟，兩造上開合意管\n    轄之約定自不受影響。是本院依前揭法條規定，對本件自有\n    管轄權，合先敘明。\n二、本件被告均經合法通知，均未於言詞辯論期日到場，核無民\n    事訴訟法第386 條各款所列情形，爰依原告聲請，由其一造\n    辯論而為判決。\n三、原告起訴主張：被告乙○○於民國92年3 月14日，邀同被告\n    丁○○為連帶保證人，向原告借款新台幣（下同）100 萬元\n    ，約定到期日迄99年3 月14日止，利息則按原告基準放款年\n    利率加年息0.275 ﹪計算，惟若未依期限清償本息時，利息\n    則按逾期當時原告基準放款年利率加年息4 ﹪計算，（系爭\n    借款逾期清償時，原告基準放款利率為3. 079﹪，加計4 ﹪\n    ，主張本件利率應為7.079 ﹪），且自借款日起，按月攤還\n    本息，如不依約清償，全部債務視為到期，並自遲延日起6\n    個月以內者，按上開利率10﹪，逾期超過6 個月部分，按上\n    開約定利率20﹪計付違約金。詎被告乙○○攤還本息至94年\n    1 月4 日起即未履行債務（實際利息收至93年12月13日），\n    依約已喪失期限利益，全部債務視同到期，經核算結果，尚\n    有如主文所示之本金、利息及違約金未清償，而被告丁○○\n    為系爭債務之連帶保證人，依法應負連帶清償之責，爰本於\n    消費借貸、連帶保證法律關係，提起本訴，並聲明求為判決\n    ：如主文所示。\n四、按被告均未於言詞辯論期日到場爭執，亦未提出書狀作何聲\n    明或陳述。\n五、按稱消費借貸者，謂當事人約定，一方移轉金錢或其他代替\n    物之所有權於他方，而他方以種類、品質、數量相同之物返\n    還之契約。借用人應於約定期限內，返還與借用物種類、品\n    質、數量相同之物。遲延之債務，以支付金錢為標的者，債\n    權人得請求依法定利率計算之遲延利息。但約定利率較高者\n    ，仍從其約定利率。當事人得約定債務人不履行債務時，應\n    支付違約金。民法第474 條、第478 條、第233 條第1 項、\n    第250 條第1 項分別定有明文。又稱保證者，謂當事人約定\n    ，一方於他方之債務人不履行債務時，由其代負履行責任之\n    契約。保證債務，除契約另有訂定外，包含主債務之利息、\n    違約金、損害賠償及其他從屬於主債務之負擔，民法第739\n    條、第740 條亦分別定有明文。本件原告主張被告乙○○邀\n    同被告丁○○為連帶保證人，向原告借款100 萬元，後未依\n    約履行債務，全部債務視為到期，尚有如主文所示之本金、\n    利息及違約金未清償之事實，已據其提出借款契約、貸款清\n    償查詢表、放款帳卡明細列印表、基準放款利率變動表各一\n    份為證，本院依上開證據所載清償期限、方式、利息並受償\n    數額為調查之結果，與原告所述之事實相符，而被告經合法\n    通知，均未到庭爭執，亦未提出書狀作何聲明或陳述，依民\n    事訴訟法第280 條第3 項、第1 項規定，視同自認，則原告\n    主張之事實，可堪信為真實，則原告本於消費借貸及連帶保\n    證之法律關係，請求被告連帶給付如主文所示之本金及利息\n    、違約金，即屬正當，應予准許。\n六、結論：本件原告之訴為有理由，依民事訴訟法第385 條第1\n    項前段、第85條第2項，判決如主文。"
  },
  "search": "臺灣高雄地方法院民事判決94年度訴字第869號原告中央信託局股份有限公司北高雄分公司法定代理人戊○○代理人甲○○代理人丙○○被告乙○○被告丁○○當事人間清償借款事件，本院民國94年5月26日言詞辯論終結，判決如下：主文被告應連帶給付原告新臺幣柒拾柒萬貳仟壹佰貳拾伍元，及自民國九十三年十二月十四日起至清償日止，按年息百分之七點零七九計算之利息，暨自民國九十四年一月十五日起至清償日止，逾期在六個月以內者，按上開利率百分之十，逾期超過六個月者，按上開利率百分之二十計算之違約金。訴訟費用由被告連帶負擔。事實及理由一、按當事人得以合意定第一審管轄法院，民事訴訟法第24條第1項前段定有明文。經查：本件原告係依消費借貸及連帶保證之法律關係，訴請被告清償借款，而依兩造所簽訂之消費性借款契約第8條約定：「‧‧‧如違背本契約規定之各條款經貴局提起訴訟時，由貴局所在地法院審理‧‧‧」，有該契約一紙在卷可稽，又原告營業處所在高雄市左營區○○○路106號1、2F，亦有高雄市政府營利事業登記證一紙附卷可參，足見兩造就本件之涉訟業已合意以本院為第一審管轄法院。另本件訴訟非屬專屬管轄之訴訟，兩造上開合意管轄之約定自不受影響。是本院依前揭法條規定，對本件自有管轄權，合先敘明。二、本件被告均經合法通知，均未於言詞辯論期日到場，核無民事訴訟法第386條各款所列情形，爰依原告聲請，由其一造辯論而為判決。三、原告起訴主張：被告乙○○於民國92年3月14日，邀同被告丁○○為連帶保證人，向原告借款新台幣（下同）100萬元，約定到期日迄99年3月14日止，利息則按原告基準放款年利率加年息0.275﹪計算，惟若未依期限清償本息時，利息則按逾期當時原告基準放款年利率加年息4﹪計算，（系爭借款逾期清償時，原告基準放款利率為3.079﹪，加計4﹪，主張本件利率應為7.079﹪），且自借款日起，按月攤還本息，如不依約清償，全部債務視為到期，並自遲延日起6個月以內者，按上開利率10﹪，逾期超過6個月部分，按上開約定利率20﹪計付違約金。詎被告乙○○攤還本息至94年1月4日起即未履行債務（實際利息收至93年12月13日），依約已喪失期限利益，全部債務視同到期，經核算結果，尚有如主文所示之本金、利息及違約金未清償，而被告丁○○為系爭債務之連帶保證人，依法應負連帶清償之責，爰本於消費借貸、連帶保證法律關係，提起本訴，並聲明求為判決：如主文所示。四、按被告均未於言詞辯論期日到場爭執，亦未提出書狀作何聲明或陳述。五、按稱消費借貸者，謂當事人約定，一方移轉金錢或其他代替物之所有權於他方，而他方以種類、品質、數量相同之物返還之契約。借用人應於約定期限內，返還與借用物種類、品質、數量相同之物。遲延之債務，以支付金錢為標的者，債權人得請求依法定利率計算之遲延利息。但約定利率較高者，仍從其約定利率。當事人得約定債務人不履行債務時，應支付違約金。民法第474條、第478條、第233條第1項、第250條第1項分別定有明文。又稱保證者，謂當事人約定，一方於他方之債務人不履行債務時，由其代負履行責任之契約。保證債務，除契約另有訂定外，包含主債務之利息、違約金、損害賠償及其他從屬於主債務之負擔，民法第739條、第740條亦分別定有明文。本件原告主張被告乙○○邀同被告丁○○為連帶保證人，向原告借款100萬元，後未依約履行債務，全部債務視為到期，尚有如主文所示之本金、利息及違約金未清償之事實，已據其提出借款契約、貸款清償查詢表、放款帳卡明細列印表、基準放款利率變動表各一份為證，本院依上開證據所載清償期限、方式、利息並受償數額為調查之結果，與原告所述之事實相符，而被告經合法通知，均未到庭爭執，亦未提出書狀作何聲明或陳述，依民事訴訟法第280條第3項、第1項規定，視同自認，則原告主張之事實，可堪信為真實，則原告本於消費借貸及連帶保證之法律關係，請求被告連帶給付如主文所示之本金及利息、違約金，即屬正當，應予准許。六、結論：本件原告之訴為有理由，依民事訴訟法第385條第1項前段、第85條第2項，判決如主文。中華民國94年5月31日民事第二庭法官黃宗揚正本係照原本作成。如不服本判決，應於送達後20日內，向本院提出上訴狀並表明上訴理由，如於本判決宣示後送達前提起上訴者，應於判決送達後10日內補提上訴理由書（須附繕本）。中華民國94年5月31日書記官陳玉娥",
  "characters": {
    "judges": [
      "黃宗揚"
    ],
    "prosecutors": [

    ],
    "lawyers": [

    ],
    "clerks": [
      "陳玉娥"
    ],
    "plaintiffs": [
      "中央信託局股份有限公司北高雄分公司"
    ],
    "defendants": [
      "乙○○",
      "被      告  丁○○",
      "當事人間清償借款事件，本院民國94年5月26日言詞辯論終結，",
      "判決如下："
    ],
    "prosecutor_office": [

    ],
    "creditors": [

    ],
    "debtors": [

    ],
    "judicial_associate_officer": [

    ]
  },
  "adjudged_at": "2005-05-31",
  "created_at": "2016-02-06 15:33:06",
  "updated_at": "2016-02-06 15:33:06"
}