{
  "identify": "KSH-94-上訴-419-20050531-1",
  "court": {
    "name": "臺灣高等法院",
    "code": "KSH"
  },
  "division": {
    "name": "刑事",
    "code": "M"
  },
  "year": 94,
  "word": "上訴",
  "number": "419",
  "jcheck": "1",
  "reason": "違反毒品危害防制條例",
  "content": "臺灣高等法院高雄分院刑事判決         94年度上訴字第419號\n上  訴  人\n即  被  告  甲○○\n上列上訴人因違反毒品危害防制條例案件，不服臺灣屏東地方法\n院94年度訴字第34號中華民國94年2 月16日第一審判決（起訴案\n號：臺灣屏東地方法院檢察署93年度毒偵字第2218號），提起上\n訴，本院判決如下：\n     主  文\n上訴駁回。\n     事實及理由\n一、本案經本院審理結果，認第一審判決認事用法及量刑均無不\n    當，應予維持，並引用第一審判決書記載之事實、證據及理\n    由。\n二、被告上訴意旨略以，伊獨負家庭生計，此次科刑，請暫緩執\n    行，嗣家庭生計安排妥當後再執行云云；經查，有關執行問\n    題，係本案判決確定後，由檢察官審酌事項，非本院審判時\n    應調查事項，是本案上訴無理由，應予駁回。\n據上論結，應依刑事訴訟法第368條、第373條，判決如主文。\n本案經檢察官周章欽到庭執行職務。\n中    華    民    國    94    年    5     月    31    日\n                  刑事第一庭    審判長法  官  郭雅美\n                                      法  官  邱永貴\n                                      法  官  江泰章\n以上正本證明與原本無異。\n施用第一級毒品部分如不服本判決應於收受本判決後10日內向本\n院提出上訴書狀，其未敘述上訴理由者，並得於提起上訴後10日\n內向本院補提理由書狀（均須按他造當事人之人數附繕本）「切\n勿逕送上級法院」。\n其他不得上訴。\n中    華    民    國    94    年    6     月    1     日\n                                      書記官  陳金卿\n                                                      Q\n附件：\n臺灣屏東地方法院刑事判決                            九十四年度訴字第三四號\n    公  訴  人  臺灣屏東地方法院檢察署檢察官\n    被      告  甲○○  男  五十歲（民國○○○年○○月○○日生）\n                        身分證統一編號：Ｚ000000000號\n                        住屏東縣萬丹鄉○○村○○街四巷十二號\n右列被告因違反毒品危害防制條例案件，經檢察官提起公訴（九十三年度毒偵字第二\n二一八號），本院裁定改依簡式審判程序審理，判決如左：\n     主     文\n甲○○連續施用第一級毒品，累犯，處有期徒刑拾月。扣案之海洛因貳包（淨重零點\n貳伍公克，空包裝重零點肆伍公克），沒收銷燬之。又連續施用第二級毒品，累犯，\n處有期徒刑陸月。應執行有期徒刑壹年貳月。扣案之海洛因貳包（淨重零點貳伍公克\n，空包裝重零點肆伍公克），沒收銷燬之。\n    事實及理由\n一、本院認定之犯罪事實及證據，除(一)、有關「安非他命」均更正為「甲基安非他命\n    」。(二)、犯罪事實欄第一行補充「甲○○曾於民國八十年間因恐嚇等案件，經臺\n    灣高雄地方法院八十二年度訴緝字第九號判處應執行有期徒刑一年十一月確定，\n    於八十三年六月十五日縮短刑期假釋出監，復於八十三年間因煙毒等案件，經臺\n    灣臺中地方法院八十三年度訴字第四０六一號判處應執行有期徒刑三年四月確定\n    ，再於八十四年間因煙毒案件，經臺灣高雄地方法院八十四年度訴字第一六二三\n    號判處有期徒刑三年四月，上開假釋並經撤銷執行殘刑有期徒刑五月五日，前述\n    三有期徒刑接續執行，於八十八年四月九日縮短刑期假釋出監後，又於八十九年\n    間因施用毒品案件，經撤銷假釋執行殘刑有期徒刑二年十一月二十四日，嗣於九\n    十三年四月六日縮刑期滿執行完畢」。(三)、犯罪事實欄第七行「連續施用海洛因\n    ，平均一天施用一次」更正為「以每天施用一次之頻率，將海洛因摻在香菸內以\n    口鼻吸食方式，連續施用第一級毒品海洛因多次」。(四)、犯罪事實欄第八行「同\n    上開期間，在上址，連續施用安非他命多次」更正為「自九十三年八月中旬某日\n    起至九十三年十月三十日止，以一星期施用一次之頻率，連續在其位於屏東縣萬\n    丹鄉○○路八０五巷十三號住處，以燒烤甲基安非他命產生煙氣以口鼻吸食方式\n    ，施用第二級毒品甲基安非他命多次」外，餘均與檢察官起訴書之記載相同，茲\n    引用之（如附件）。\n二、查海洛因及甲基安非他命分屬毒品危害防制條例第二條第二項第一款、第二款所\n    稱之第一級、第二級毒品，均不得持有、施用，被告竟持以施用，核其所為，係\n    犯同條例第十條第一項之施用第一級毒品罪及同條第二項施用第二級毒品罪。被\n    告施用前持有海洛因及甲基安非他命之低度行為，應為施用之高度行為所吸收，\n    均不另論罪。其先後多次施用海洛因、甲基安非他命之行為，均時間緊接，觸犯\n    構成要件相同之罪名，顯係基於概括犯意為之，為連續犯，均應以一罪論，並均\n    加重其刑。又被告曾於八十年間因恐嚇等案件，經臺灣高雄地方法院八十二年度\n    訴緝字第九號判處應執行有期徒刑一年十一月確定，於八十三年六月十五日縮短\n    刑期假釋出監，復於八十三年間因煙毒等案件，經臺灣臺中地方法院八十三年度\n    訴字第四０六一號判處應執行有期徒刑三年四月確定，再於八十四年間因煙毒案\n    件，經臺灣高雄地方法院八十四年度訴字第一六二三號判處有期徒刑三年四月，\n    上開假釋並經撤銷執行殘刑有期徒刑五月五日，前述三有期徒刑接續執行，於八\n    十八年四月九日縮短刑期假釋出監後，又於八十九年間因施用毒品案件，經撤銷\n    假釋執行殘刑有期徒刑二年十一月二十四日，嗣於九十三年四月六日縮刑期滿執\n    行完畢，有臺灣屏東地方法院檢察署刑案資料查註紀錄表、全國施用毒品案件紀\n    錄表及臺灣高等法院被告全國前案紀錄表在卷可按，其受有期徒刑之執行完畢後\n    ，五年之內再犯有期徒刑以上刑之上述二罪，皆為累犯，應依法加重其刑，其有\n    二種刑之加重事由，應均遞加重之。被告所犯上述二罪，犯意各別，行為互異，\n    應予分別論罪，合併處罰。爰審酌被告素行非佳，且經強制戒治後，仍未戒除毒\n    癮，再犯本案施用毒品罪，顯見其無戒毒悔改之意，惟念其施用毒品乃自戕行為\n    ，及其施用毒品之期間、次數、犯罪後坦承犯行、態度尚稱良好等一切情狀，分\n    別量處如主文所示之刑並定其應執行刑。扣案之海洛因二包（淨重零點二五公克\n    、空包裝重零點四五公克），應依毒品危害防制條例第十八條第一項前段之規定\n    沒收銷燬之。\n據上論斷，應依刑事訴訟法第二百七十三條之一第一項、第二百九十九條第一項前段\n、第三百十條之二、第四百五十四條第二項，毒品危害防制條例第十條第一項、第二\n項、第十八條第一項前段，刑法第十一條、第五十六條、第四十七條、第五十一條第\n五款，判決如主文。\n本案經檢察官黃莉琄到庭執行職務。\n中      華      民      國    九十四    年      二      月     十六     日\n                                      臺灣屏東地方法院刑事第二庭\n                                           法    官   蘇碧珠\n右正本證明與原本無異。\n如不服本判決應於收受本判決送達後十日內向本院提出上訴書狀，其未敘述上訴理由\n者，並得於提起上訴後十日內向本院補提理由書狀（均須按他造當事人之人數附繕本\n ）「切勿逕送上級法院」\n                                              書記官   王秋淑\n中      華      民      國    九十四    年      二      月     十七     日\n附錄本案論罪科刑法條全文：\n毒品危害防制條例第十條第一項\n施用第一級毒品者，處六月以上五年以下有期徒刑。\n施用第二級毒品者，處三年以下有期徒刑。\n",
  "structure": {
    "main": "上訴駁回。\n     事實及理由\n一、本案經本院審理結果，認第一審判決認事用法及量刑均無不\n    當，應予維持，並引用第一審判決書記載之事實、證據及理\n    由。\n二、被告上訴意旨略以，伊獨負家庭生計，此次科刑，請暫緩執\n    行，嗣家庭生計安排妥當後再執行云云；經查，有關執行問\n    題，係本案判決確定後，由檢察官審酌事項，非本院審判時\n    應調查事項，是本案上訴無理由，應予駁回。\n據上論結，應依刑事訴訟法第368條、第373條，判決如主文。\n本案經檢察官周章欽到庭執行職務。\n中    華    民    國    94    年    5     月    31    日\n                  刑事第一庭    審判長法  官  郭雅美\n                                      法  官  邱永貴\n                                      法  官  江泰章\n以上正本證明與原本無異。\n施用第一級毒品部分如不服本判決應於收受本判決後10日內向本\n院提出上訴書狀，其未敘述上訴理由者，並得於提起上訴後10日\n內向本院補提理由書狀（均須按他造當事人之人數附繕本）「切\n勿逕送上級法院」。\n其他不得上訴。\n中    華    民    國    94    年    6     月    1     日\n                                      書記官  陳金卿\n                                                      Q\n附件：\n臺灣屏東地方法院刑事判決                            九十四年度訴字第三四號\n    公  訴  人  臺灣屏東地方法院檢察署檢察官\n    被      告  甲○○  男  五十歲（民國○○○年○○月○○日生）\n                        身分證統一編號：Ｚ000000000號\n                        住屏東縣萬丹鄉○○村○○街四巷十二號\n右列被告因違反毒品危害防制條例案件，經檢察官提起公訴（九十三年度毒偵字第二\n二一八號），本院裁定改依簡式審判程序審理，判決如左：\n     主     文\n甲○○連續施用第一級毒品，累犯，處有期徒刑拾月。扣案之海洛因貳包（淨重零點\n貳伍公克，空包裝重零點肆伍公克），沒收銷燬之。又連續施用第二級毒品，累犯，\n處有期徒刑陸月。應執行有期徒刑壹年貳月。扣案之海洛因貳包（淨重零點貳伍公克\n，空包裝重零點肆伍公克），沒收銷燬之。",
    "fact": "一、本案經本院審理結果，認第一審判決認事用法及量刑均無不\n    當，應予維持，並引用第一審判決書記載之事實、證據及理\n    由。\n二、被告上訴意旨略以，伊獨負家庭生計，此次科刑，請暫緩執\n    行，嗣家庭生計安排妥當後再執行云云；經查，有關執行問\n    題，係本案判決確定後，由檢察官審酌事項，非本院審判時\n    應調查事項，是本案上訴無理由，應予駁回。\n據上論結，應依刑事訴訟法第368條、第373條，判決如主文。\n本案經檢察官周章欽到庭執行職務。",
    "reason": "一、本案經本院審理結果，認第一審判決認事用法及量刑均無不\n    當，應予維持，並引用第一審判決書記載之事實、證據及理\n    由。\n二、被告上訴意旨略以，伊獨負家庭生計，此次科刑，請暫緩執\n    行，嗣家庭生計安排妥當後再執行云云；經查，有關執行問\n    題，係本案判決確定後，由檢察官審酌事項，非本院審判時\n    應調查事項，是本案上訴無理由，應予駁回。\n據上論結，應依刑事訴訟法第368條、第373條，判決如主文。\n本案經檢察官周章欽到庭執行職務。"
  },
  "search": "臺灣高等法院高雄分院刑事判決94年度上訴字第419號上訴人即被告甲○○上列上訴人因違反毒品危害防制條例案件，不服臺灣屏東地方法院94年度訴字第34號中華民國94年2月16日第一審判決（起訴案號：臺灣屏東地方法院檢察署93年度毒偵字第2218號），提起上訴，本院判決如下：主文上訴駁回。事實及理由一、本案經本院審理結果，認第一審判決認事用法及量刑均無不當，應予維持，並引用第一審判決書記載之事實、證據及理由。二、被告上訴意旨略以，伊獨負家庭生計，此次科刑，請暫緩執行，嗣家庭生計安排妥當後再執行云云；經查，有關執行問題，係本案判決確定後，由檢察官審酌事項，非本院審判時應調查事項，是本案上訴無理由，應予駁回。據上論結，應依刑事訴訟法第368條、第373條，判決如主文。本案經檢察官周章欽到庭執行職務。中華民國94年5月31日刑事第一庭審判長法官郭雅美法官邱永貴法官江泰章以上正本證明與原本無異。施用第一級毒品部分如不服本判決應於收受本判決後10日內向本院提出上訴書狀，其未敘述上訴理由者，並得於提起上訴後10日內向本院補提理由書狀（均須按他造當事人之人數附繕本）「切勿逕送上級法院」。其他不得上訴。中華民國94年6月1日書記官陳金卿Q附件：臺灣屏東地方法院刑事判決九十四年度訴字第三四號公訴人臺灣屏東地方法院檢察署檢察官被告甲○○男五十歲（民國○○○年○○月○○日生）身分證統一編號：Ｚ000000000號住屏東縣萬丹鄉○○村○○街四巷十二號右列被告因違反毒品危害防制條例案件，經檢察官提起公訴（九十三年度毒偵字第二二一八號），本院裁定改依簡式審判程序審理，判決如左：主文甲○○連續施用第一級毒品，累犯，處有期徒刑拾月。扣案之海洛因貳包（淨重零點貳伍公克，空包裝重零點肆伍公克），沒收銷燬之。又連續施用第二級毒品，累犯，處有期徒刑陸月。應執行有期徒刑壹年貳月。扣案之海洛因貳包（淨重零點貳伍公克，空包裝重零點肆伍公克），沒收銷燬之。事實及理由一、本院認定之犯罪事實及證據，除(一)、有關「安非他命」均更正為「甲基安非他命」。(二)、犯罪事實欄第一行補充「甲○○曾於民國八十年間因恐嚇等案件，經臺灣高雄地方法院八十二年度訴緝字第九號判處應執行有期徒刑一年十一月確定，於八十三年六月十五日縮短刑期假釋出監，復於八十三年間因煙毒等案件，經臺灣臺中地方法院八十三年度訴字第四０六一號判處應執行有期徒刑三年四月確定，再於八十四年間因煙毒案件，經臺灣高雄地方法院八十四年度訴字第一六二三號判處有期徒刑三年四月，上開假釋並經撤銷執行殘刑有期徒刑五月五日，前述三有期徒刑接續執行，於八十八年四月九日縮短刑期假釋出監後，又於八十九年間因施用毒品案件，經撤銷假釋執行殘刑有期徒刑二年十一月二十四日，嗣於九十三年四月六日縮刑期滿執行完畢」。(三)、犯罪事實欄第七行「連續施用海洛因，平均一天施用一次」更正為「以每天施用一次之頻率，將海洛因摻在香菸內以口鼻吸食方式，連續施用第一級毒品海洛因多次」。(四)、犯罪事實欄第八行「同上開期間，在上址，連續施用安非他命多次」更正為「自九十三年八月中旬某日起至九十三年十月三十日止，以一星期施用一次之頻率，連續在其位於屏東縣萬丹鄉○○路八０五巷十三號住處，以燒烤甲基安非他命產生煙氣以口鼻吸食方式，施用第二級毒品甲基安非他命多次」外，餘均與檢察官起訴書之記載相同，茲引用之（如附件）。二、查海洛因及甲基安非他命分屬毒品危害防制條例第二條第二項第一款、第二款所稱之第一級、第二級毒品，均不得持有、施用，被告竟持以施用，核其所為，係犯同條例第十條第一項之施用第一級毒品罪及同條第二項施用第二級毒品罪。被告施用前持有海洛因及甲基安非他命之低度行為，應為施用之高度行為所吸收，均不另論罪。其先後多次施用海洛因、甲基安非他命之行為，均時間緊接，觸犯構成要件相同之罪名，顯係基於概括犯意為之，為連續犯，均應以一罪論，並均加重其刑。又被告曾於八十年間因恐嚇等案件，經臺灣高雄地方法院八十二年度訴緝字第九號判處應執行有期徒刑一年十一月確定，於八十三年六月十五日縮短刑期假釋出監，復於八十三年間因煙毒等案件，經臺灣臺中地方法院八十三年度訴字第四０六一號判處應執行有期徒刑三年四月確定，再於八十四年間因煙毒案件，經臺灣高雄地方法院八十四年度訴字第一六二三號判處有期徒刑三年四月，上開假釋並經撤銷執行殘刑有期徒刑五月五日，前述三有期徒刑接續執行，於八十八年四月九日縮短刑期假釋出監後，又於八十九年間因施用毒品案件，經撤銷假釋執行殘刑有期徒刑二年十一月二十四日，嗣於九十三年四月六日縮刑期滿執行完畢，有臺灣屏東地方法院檢察署刑案資料查註紀錄表、全國施用毒品案件紀錄表及臺灣高等法院被告全國前案紀錄表在卷可按，其受有期徒刑之執行完畢後，五年之內再犯有期徒刑以上刑之上述二罪，皆為累犯，應依法加重其刑，其有二種刑之加重事由，應均遞加重之。被告所犯上述二罪，犯意各別，行為互異，應予分別論罪，合併處罰。爰審酌被告素行非佳，且經強制戒治後，仍未戒除毒癮，再犯本案施用毒品罪，顯見其無戒毒悔改之意，惟念其施用毒品乃自戕行為，及其施用毒品之期間、次數、犯罪後坦承犯行、態度尚稱良好等一切情狀，分別量處如主文所示之刑並定其應執行刑。扣案之海洛因二包（淨重零點二五公克、空包裝重零點四五公克），應依毒品危害防制條例第十八條第一項前段之規定沒收銷燬之。據上論斷，應依刑事訴訟法第二百七十三條之一第一項、第二百九十九條第一項前段、第三百十條之二、第四百五十四條第二項，毒品危害防制條例第十條第一項、第二項、第十八條第一項前段，刑法第十一條、第五十六條、第四十七條、第五十一條第五款，判決如主文。本案經檢察官黃莉琄到庭執行職務。中華民國九十四年二月十六日臺灣屏東地方法院刑事第二庭法官蘇碧珠右正本證明與原本無異。如不服本判決應於收受本判決送達後十日內向本院提出上訴書狀，其未敘述上訴理由者，並得於提起上訴後十日內向本院補提理由書狀（均須按他造當事人之人數附繕本）「切勿逕送上級法院」書記官王秋淑中華民國九十四年二月十七日附錄本案論罪科刑法條全文：毒品危害防制條例第十條第一項施用第一級毒品者，處六月以上五年以下有期徒刑。施用第二級毒品者，處三年以下有期徒刑。",
  "characters": {
    "judges": [
      "郭雅美",
      "邱永貴",
      "江泰章",
      "蘇碧珠"
    ],
    "prosecutors": [
      "周章欽",
      "黃莉琄"
    ],
    "lawyers": [

    ],
    "clerks": [
      "陳金卿",
      "王秋淑"
    ],
    "plaintiffs": [

    ],
    "defendants": [
      "甲○○  男  五十歲（民國○○○年○○月○○日生）"
    ],
    "prosecutor_office": [
      "臺灣屏東地方法院檢察署檢察官"
    ],
    "creditors": [

    ],
    "debtors": [

    ],
    "judicial_associate_officer": [

    ]
  },
  "adjudged_at": "2005-05-31",
  "created_at": "2016-02-06 15:46:59",
  "updated_at": "2016-02-06 15:46:59"
}