{
  "identify": "PTD-94-訴-76-20050531-1",
  "court": {
    "name": "臺灣屏東地方法院",
    "code": "PTD"
  },
  "division": {
    "name": "刑事",
    "code": "M"
  },
  "year": 94,
  "word": "訴",
  "number": "76",
  "jcheck": "1",
  "reason": "違反毒品危害防制條例",
  "content": "臺灣屏東地方法院刑事裁定                94年度訴字第76號\n公  訴  人  臺灣屏東地方法院檢察署檢察官\n被      告  甲○○  男  26歲.\n                      (\n上列被告因違反毒品危害防制條例案件，本院裁定如下：\n    主  文\n本件由受命法官獨任進行簡式審判程序。\n    理  由\n一、本件被告甲○○所犯係死刑、無期徒刑、最輕本刑為三年以\n    上有期徒刑以外之罪，其於準備程序中就被訴事實為有罪之\n    陳述，經法官告知簡式審判程序之旨，並聽取公訴人及被告\n    之意見後，本院認為適宜由受命法官獨任進行簡式審判程序\n    。\n二、依刑事訴訟法第273條之1第1項，裁定如主文。\n中    華    民    國    94    年    5     月    31    日\n                  刑事第二庭    審判長法  官  黃國永\n                                      法  官  林柏泓\n                                      法  官  余德正\n不得抗告\n以上正本係照原本作成\n                                      書記官  潘美碧\n中    華    民    國    94    年    5     月    31    日\n",
  "structure": {
    "main": "本件由受命法官獨任進行簡式審判程序。",
    "reason": "一、本件被告甲○○所犯係死刑、無期徒刑、最輕本刑為三年以\n    上有期徒刑以外之罪，其於準備程序中就被訴事實為有罪之\n    陳述，經法官告知簡式審判程序之旨，並聽取公訴人及被告\n    之意見後，本院認為適宜由受命法官獨任進行簡式審判程序\n    。\n二、依刑事訴訟法第273條之1第1項，裁定如主文。"
  },
  "search": "臺灣屏東地方法院刑事裁定94年度訴字第76號公訴人臺灣屏東地方法院檢察署檢察官被告甲○○男26歲.(上列被告因違反毒品危害防制條例案件，本院裁定如下：主文本件由受命法官獨任進行簡式審判程序。理由一、本件被告甲○○所犯係死刑、無期徒刑、最輕本刑為三年以上有期徒刑以外之罪，其於準備程序中就被訴事實為有罪之陳述，經法官告知簡式審判程序之旨，並聽取公訴人及被告之意見後，本院認為適宜由受命法官獨任進行簡式審判程序。二、依刑事訴訟法第273條之1第1項，裁定如主文。中華民國94年5月31日刑事第二庭審判長法官黃國永法官林柏泓法官余德正不得抗告以上正本係照原本作成書記官潘美碧中華民國94年5月31日",
  "characters": {
    "judges": [
      "黃國永",
      "林柏泓",
      "余德正"
    ],
    "prosecutors": [

    ],
    "lawyers": [

    ],
    "clerks": [
      "潘美碧"
    ],
    "plaintiffs": [

    ],
    "defendants": [
      "甲○○  男  26歲."
    ],
    "prosecutor_office": [
      "臺灣屏東地方法院檢察署檢察官"
    ],
    "creditors": [

    ],
    "debtors": [

    ],
    "judicial_associate_officer": [

    ]
  },
  "adjudged_at": "2005-05-31",
  "created_at": "2016-02-06 15:33:39",
  "updated_at": "2016-02-06 15:33:39"
}