{
  "identify": "TPD-93-建-327-20050531-1",
  "court": {
    "name": "臺灣臺北地方法院",
    "code": "TPD"
  },
  "division": {
    "name": "民事",
    "code": "V"
  },
  "year": 93,
  "word": "建",
  "number": "327",
  "jcheck": "1",
  "reason": "給付工程款",
  "content": "臺灣臺北地方法院民事判決               93年度建字第327號\n原      告  堯詳石材實業有限公司\n法定代理人  甲○○\n訴訟代理人  王信雄律師\n被      告  大室內裝修工程股份有限公司\n法定代理人  乙○○\n訴訟代理人  謝協昌律師\n上列當事人間請求給付工程款事件，本院於中華民國九十四年五\n月二十日言詞辯論終結，判決如下：\n    主      文\n被告應給付原告新臺幣貳拾伍萬參仟肆佰參拾伍元及自民國九十\n三年十二月十四日起至清償日止，按年息百分之五計算之利息。\n原告其餘之訴駁回。\n訴訟費用由被告負擔百分之四十三，餘由原告負擔。\n本判決原告勝訴部分，得假執行；但被告如以新臺幣貳拾伍萬參\n仟肆佰參拾伍元供擔保，得免為假執行。\n原告其餘假執行之聲請駁回。\n    事實與理由\n壹、程序方面：被告法定代理人於起訴前即已由楊祺松變更乙○\n    ○，有原告提出之公司變更登記事項卡可證，嗣原告於民國\n    93年12月7日更正被告法定代理人，應准許之，先予敘明。\n貳、原告起訴主張：\n一、原告於92年12月2日承包被告亮碧思SPA生活館裝修工程之石\n    材工程，其工程尾款尚積欠新臺幣（下同）593,444元，前\n    經原告多次催討，被告均藉詞拖延，為此提起本訴。\n二、兩造簽訂工程前後分為兩期，第一期工程款（含稅）為1,84\n    7,292元，第二期追加工程款（含稅）為397,071元，合計2,\n    244,363元，扣除被告已支付之第一期工程款1,650,919 元\n    ，尚未給付之工程款為593,444元。被告主張之總工程款有\n    誤。\n三、依兩造簽訂之分包工程、材料訂購合約書，就被告之報價單\n    列表項次第四項「八角柱」僅註記使用石材為「路易石」，\n    契約並無特別約定為原告剖開刨空或石板黏合之方式製作。\n    系爭四根石柱單價為每根80,000元，原告依約完工並經被告\n    驗收，業主已在營業，並支付被告全部承攬之工程款，原告\n    自得請求工程尾款。\n四、鈞院去函臺北市石材製品商業同業公會及臺灣區石礦製品工\n    業同業公會所得之回文函復，結果相差甚大，前者以伯爵石\n    為評估基礎，後者則以西班牙玫瑰紅為例，兩者價差過鉅，\n    輕率作出石柱製作方式及價格計算之意見，與事實顯有差距\n    ，要難做為爭訟事項判斷依據。\n五、訴之聲明：\n（一）被告應給付原告593,444元，及自起訴狀繕本送達翌日起\n      至清償日止，按年息5%計算之利息。\n（二）原告願供擔保，請准宣告假執行。\n參、被告則以下列辯詞置辯：\n一、被告與原告確於92年底簽訂工程合約，由被告將坐落於臺北\n    市○○○路○段15之1號20樓之「亮碧思SPA生活館」裝修工\n    程之石材工程，交由原告承攬施作。然原告施作期間，關於\n    八角柱之施工部分，雙方約定應於圖面確認後12天即92年12\n    月初，原告即應進行石柱施作，原告卻拖延至93年1月1日及\n    93 年1月19日方分批進場施作。雙方原來約定石柱應以原石\n    剖開後再加工刨成八角形之方式為之，原告於93年1月1日所\n    進場施作之四根石柱並無問題，然93年1月19日施作之石柱\n    ，竟以石板黏合之方式拼裝而成，經被告多次要求拆除重作\n    ，原告仍以石板黏合之石柱製作，被告拒絕驗收，原告卻表\n    示因購入之原石剖開後內部材質問題，無法滿足八根柱子均\n    以原石製作需求，因此其中四根僅能另以石板黏合方式為之\n    ，強令被告接受，並表示若拒絕接受，將全面癱瘓其他工程\n    進行。由於被告與業主所約定完工期限已至，而原告前已作\n    輟無常，工期嚴重延宕，被告將面臨無法完工及業主鉅額違\n    約罰款責任，只得無奈接受此一嚴重瑕疵，並向原告表示嗣\n    後再行會算扣款事宜。\n二、今系爭工程已完工，總工程款為2,170,353元，扣除已支付\n    之1,650,918元，被告尚未支付之款項為519,435元，並非原\n    告聲稱之593,444元。此外原告對石柱施工之瑕疵經被告催\n    告修補仍未修補，依民法第493條、第494條規定，被告自得\n    請求減少報酬。一般而言，石板黏合之石柱價值僅有石材刨\n    空之石柱價值之10%至20%，由於契約約定單價為每根80,000\n    元，四根共320,000元，以20%計算，此四根石板黏合之石柱\n    價值僅有64,000元，就差額256,000元部分，被告自得請求\n    減少報酬。\n三、又原告曾就檯面石材開孔之木作打版部分請求被告代為施作\n    ，並請被告代為施作矽膠填縫收邊之工程，經雙方同意前開\n    代為施作之工程款10,000元於尾款中扣除，因此被告亦得主\n    張扣除10,000元。綜上所述，被告僅需支付253,435元，前\n    原告雖同意減少報酬，卻不同意減少比例而未能達成共識，\n    因此原告方提出本件訴訟。然依前開說明，原告請求逾253,\n    435元之部分屬無理由。\n四、依臺灣區石礦製品工業同業公會回函意旨指出，二片接之價\n    格約為八片接之六倍，依此原告本得以16%價格請求減少報\n    酬，今以20%計算請求減少報酬，尚且有利於原告。\n五、訴之聲明：\n（一）原告請求逾新臺幣253,435元之金額部分駁回。\n（二）如受不利判決，願供擔保請准宣告免為假執行。\n肆、兩造不爭執之事實：\n一、兩造於92年12月2日簽訂工程合約，由被告將坐落於臺北市\n    ○○○路一段15之1號20樓之「亮碧思SPA生活館」裝修工程\n    之石材工程，交由原告承攬施作，該工程已完工，業主已開\n    始營業。\n二、原告曾就檯面石材開孔之木作打版部分請求被告代為施作，\n    並請被告代為施作矽膠填縫收邊之工程，經雙方同意前開代\n    為施作之工程款10,000元於尾款中扣除。\n伍、得心證之理由：\n一、原告主張兩造簽訂工程前後分為兩期，第一期工程款（含稅\n    ）為1,847,292元，第二期追加工程款（含稅）為397,071元\n    ，合計2,244,363元，扣除被告已支付之第一期工程款1,650\n    ,919 元，尚未給付之工程款為593,444元等情，被告則以上\n    開辯詞資為抗辯。故本件爭執點在於本件工程款總金額及已\n    支付金額各為何？原契約約定之石柱施作方式得否以原石剖\n    開刨空方式製作？原石剖開刨空與石板黏合方式之價格是否\n    不同？\n二、經查原告主張工程款總金額為2,244,363元，被告已支付之\n    第一期工程款1,650,919元等情，被告則以總工程款應為2,1\n    70,353元，扣除已支付之1,650,918元等語資為抗辯，原告\n    並未舉證證明工程款總金額為2,244,363元，應以被告自認\n    之金額2,170,353元範圍為真，又原告主張被告已支付1,650\n    ,919 元部分，比被告辯稱已支付1,650,918元還多1元，以\n    已支付1,650,918元對原告有利，並經被告自認，故應認被\n    告已支付1,650,918元，故扣除已支付金額1,650,918元，被\n    告尚未支付金額應為519,435元（2,170,353－1,650,918＝5\n    19,435）。\n三、又查依被告提出且為原告不爭執真正之契約圖說（見卷 (一\n    )第33項）觀之，在該圖說內已明白記載「柱內挖空」，顯\n    然兩造就系爭石柱已約定須以柱內挖空之方式製作，原告主\n    張報價單未註明以何方式製作云云，即不足採，雖原告復主\n    張那麼長石柱不可能挖空云云，台北市石材公會並函覆持相\n    同意見，惟查被告辯稱系爭石柱共八支，其中四支係以原石\n    剖開挖空方式製作等情，為原告所不爭執，且台北市石材公\n    會係屬石材買賣性質之公會，對石柱製作之資訊可能較為貧\n    乏，故經被告聲請本院向製作石材較為專業之台灣區石礦製\n    品工業同業工會函詢有關以上開契約圖說所示石柱，就同一\n    規格、同一樣式、同一石材（伯爵石）之石柱，以「完整原\n    石剖開挖空製作」與「以石板黏合製作」方式，所需石材價\n    格有無差別，價格各為多少？又同尺寸究有無可能以「剖開\n    挖空」方式製作之結果，該公會以「一、石柱製作方式依工\n    廠機械設備不同可區分為：（１）一體成型．．．原石挖空\n    （２）二片接．．．原石對剖挖空組合」（３）八片接．．\n    ．三公分石板組合。二、依附圖所示其價格分別計算如下：\n    （１）一體成型：25,000元／ｍｘ2. 3＝57,500元（２）二\n    片接：20,500元／ｍｘ2.3＝47,150（３）八片接：3,500元\n    ／ｍｘ2.3＝8,050元。三、前述價格僅計算製品價（不含施\n    工費用），因各家報價不一，價格僅供參考。」函覆，此有\n    台灣區石礦製品工業同業公會94年3月28日、94年4月28日（\n    94）台石製公字第94063、94088號函在卷可稽（見卷 (一)7\n    3頁、卷 (二)第17頁），可見系爭石柱仍得以剖開挖空之方\n    式製作，且在價格上，八片接方式僅為一體成型、二片接方\n    式之百分之十四、百分之十七而已，故原告主張那麼長石柱\n    不可能挖空云云，即不足採，而製作方式不同，價格即有差\n    別，則系爭石柱既係以八片接方式製作，被告主張以比上開\n    函覆比例更高之百分之二十計算系爭石柱價值，應為可採。\n四、按工作有瑕疵者，定作人得定相當期限，請求承攬人修補之\n    。又按承攬人不於前條第 1 項所定期限內修補瑕疵，或依\n    前條第3項之規定拒絕修補或其瑕疵不能修補者，定作人得\n    解除契約或請求減少報酬。民法第493條第1項、第494條第1\n    項分別定有明文。故原告既認系爭石柱以石板黏合非瑕疵而\n    未能修補，被告自得請求減少報酬。從而以約定單價為每根\n    80,000元，四根共320,000元，20%計算，此四根石板黏合之\n    石柱價值為64 ,000 元（320,000ｘ20％＝64,000），則就\n    差額256,000元部分（320,000－64,000＝256,000），被告\n    自得請求減少報酬。\n五、綜上所述，被告未付工程款為519,435元，扣除減少報酬256\n    ,000 元及代為施作之工程款10,000元，被告公司應僅支付\n    253,435元，被告並為認諾。從而原告依承攬契約法律關係\n    ，請求被告給付在253,435元及自起訴狀繕本送達被告翌日\n    即93年12月14日起算之法定遲延利息之範圍內，為有理由，\n    應予准許，逾此部分，則無理由，應予駁回。\n六、兩造陳明願供擔保，聲請宣告假執行或免為假執行，經核原\n    告勝訴部分，業經被告認諾，依民事訴訟法第389條第1項第\n    1款規定，本院應就此部分，依職權宣告假執行，另被告聲\n    請免為假執行部分，亦合於法律規定，爰酌定相當之擔保金\n    額宣告之；原告其餘假執行之聲請，因訴之駁回而失所依據\n    ，不予准許。\n七、因本案事證已臻明確，兩造其餘主張陳述及所提之證據，經\n    本院審酌後，認與判決之結果無影響，爰不一一論駁，附此\n    敘明。\n陸、訴訟費用之裁判依據：民事訴訟法第79條。\n中    華    民    國    94    年    5     月    31    日\n                  民事第二庭    法  官  黃雯惠\n以上正本係照原本作成。\n如對本判決上訴，須於判決送達後20日內向本院提出上訴狀。\n中    華    民    國    94    年    5     月    31    日\n                                書記官  林玗倩\n",
  "structure": {
  },
  "search": "臺灣臺北地方法院民事判決93年度建字第327號原告堯詳石材實業有限公司法定代理人甲○○訴訟代理人王信雄律師被告大室內裝修工程股份有限公司法定代理人乙○○訴訟代理人謝協昌律師上列當事人間請求給付工程款事件，本院於中華民國九十四年五月二十日言詞辯論終結，判決如下：主文被告應給付原告新臺幣貳拾伍萬參仟肆佰參拾伍元及自民國九十三年十二月十四日起至清償日止，按年息百分之五計算之利息。原告其餘之訴駁回。訴訟費用由被告負擔百分之四十三，餘由原告負擔。本判決原告勝訴部分，得假執行；但被告如以新臺幣貳拾伍萬參仟肆佰參拾伍元供擔保，得免為假執行。原告其餘假執行之聲請駁回。事實與理由壹、程序方面：被告法定代理人於起訴前即已由楊祺松變更乙○○，有原告提出之公司變更登記事項卡可證，嗣原告於民國93年12月7日更正被告法定代理人，應准許之，先予敘明。貳、原告起訴主張：一、原告於92年12月2日承包被告亮碧思SPA生活館裝修工程之石材工程，其工程尾款尚積欠新臺幣（下同）593,444元，前經原告多次催討，被告均藉詞拖延，為此提起本訴。二、兩造簽訂工程前後分為兩期，第一期工程款（含稅）為1,847,292元，第二期追加工程款（含稅）為397,071元，合計2,244,363元，扣除被告已支付之第一期工程款1,650,919元，尚未給付之工程款為593,444元。被告主張之總工程款有誤。三、依兩造簽訂之分包工程、材料訂購合約書，就被告之報價單列表項次第四項「八角柱」僅註記使用石材為「路易石」，契約並無特別約定為原告剖開刨空或石板黏合之方式製作。系爭四根石柱單價為每根80,000元，原告依約完工並經被告驗收，業主已在營業，並支付被告全部承攬之工程款，原告自得請求工程尾款。四、鈞院去函臺北市石材製品商業同業公會及臺灣區石礦製品工業同業公會所得之回文函復，結果相差甚大，前者以伯爵石為評估基礎，後者則以西班牙玫瑰紅為例，兩者價差過鉅，輕率作出石柱製作方式及價格計算之意見，與事實顯有差距，要難做為爭訟事項判斷依據。五、訴之聲明：（一）被告應給付原告593,444元，及自起訴狀繕本送達翌日起至清償日止，按年息5%計算之利息。（二）原告願供擔保，請准宣告假執行。參、被告則以下列辯詞置辯：一、被告與原告確於92年底簽訂工程合約，由被告將坐落於臺北市○○○路○段15之1號20樓之「亮碧思SPA生活館」裝修工程之石材工程，交由原告承攬施作。然原告施作期間，關於八角柱之施工部分，雙方約定應於圖面確認後12天即92年12月初，原告即應進行石柱施作，原告卻拖延至93年1月1日及93年1月19日方分批進場施作。雙方原來約定石柱應以原石剖開後再加工刨成八角形之方式為之，原告於93年1月1日所進場施作之四根石柱並無問題，然93年1月19日施作之石柱，竟以石板黏合之方式拼裝而成，經被告多次要求拆除重作，原告仍以石板黏合之石柱製作，被告拒絕驗收，原告卻表示因購入之原石剖開後內部材質問題，無法滿足八根柱子均以原石製作需求，因此其中四根僅能另以石板黏合方式為之，強令被告接受，並表示若拒絕接受，將全面癱瘓其他工程進行。由於被告與業主所約定完工期限已至，而原告前已作輟無常，工期嚴重延宕，被告將面臨無法完工及業主鉅額違約罰款責任，只得無奈接受此一嚴重瑕疵，並向原告表示嗣後再行會算扣款事宜。二、今系爭工程已完工，總工程款為2,170,353元，扣除已支付之1,650,918元，被告尚未支付之款項為519,435元，並非原告聲稱之593,444元。此外原告對石柱施工之瑕疵經被告催告修補仍未修補，依民法第493條、第494條規定，被告自得請求減少報酬。一般而言，石板黏合之石柱價值僅有石材刨空之石柱價值之10%至20%，由於契約約定單價為每根80,000元，四根共320,000元，以20%計算，此四根石板黏合之石柱價值僅有64,000元，就差額256,000元部分，被告自得請求減少報酬。三、又原告曾就檯面石材開孔之木作打版部分請求被告代為施作，並請被告代為施作矽膠填縫收邊之工程，經雙方同意前開代為施作之工程款10,000元於尾款中扣除，因此被告亦得主張扣除10,000元。綜上所述，被告僅需支付253,435元，前原告雖同意減少報酬，卻不同意減少比例而未能達成共識，因此原告方提出本件訴訟。然依前開說明，原告請求逾253,435元之部分屬無理由。四、依臺灣區石礦製品工業同業公會回函意旨指出，二片接之價格約為八片接之六倍，依此原告本得以16%價格請求減少報酬，今以20%計算請求減少報酬，尚且有利於原告。五、訴之聲明：（一）原告請求逾新臺幣253,435元之金額部分駁回。（二）如受不利判決，願供擔保請准宣告免為假執行。肆、兩造不爭執之事實：一、兩造於92年12月2日簽訂工程合約，由被告將坐落於臺北市○○○路一段15之1號20樓之「亮碧思SPA生活館」裝修工程之石材工程，交由原告承攬施作，該工程已完工，業主已開始營業。二、原告曾就檯面石材開孔之木作打版部分請求被告代為施作，並請被告代為施作矽膠填縫收邊之工程，經雙方同意前開代為施作之工程款10,000元於尾款中扣除。伍、得心證之理由：一、原告主張兩造簽訂工程前後分為兩期，第一期工程款（含稅）為1,847,292元，第二期追加工程款（含稅）為397,071元，合計2,244,363元，扣除被告已支付之第一期工程款1,650,919元，尚未給付之工程款為593,444元等情，被告則以上開辯詞資為抗辯。故本件爭執點在於本件工程款總金額及已支付金額各為何？原契約約定之石柱施作方式得否以原石剖開刨空方式製作？原石剖開刨空與石板黏合方式之價格是否不同？二、經查原告主張工程款總金額為2,244,363元，被告已支付之第一期工程款1,650,919元等情，被告則以總工程款應為2,170,353元，扣除已支付之1,650,918元等語資為抗辯，原告並未舉證證明工程款總金額為2,244,363元，應以被告自認之金額2,170,353元範圍為真，又原告主張被告已支付1,650,919元部分，比被告辯稱已支付1,650,918元還多1元，以已支付1,650,918元對原告有利，並經被告自認，故應認被告已支付1,650,918元，故扣除已支付金額1,650,918元，被告尚未支付金額應為519,435元（2,170,353－1,650,918＝519,435）。三、又查依被告提出且為原告不爭執真正之契約圖說（見卷(一)第33項）觀之，在該圖說內已明白記載「柱內挖空」，顯然兩造就系爭石柱已約定須以柱內挖空之方式製作，原告主張報價單未註明以何方式製作云云，即不足採，雖原告復主張那麼長石柱不可能挖空云云，台北市石材公會並函覆持相同意見，惟查被告辯稱系爭石柱共八支，其中四支係以原石剖開挖空方式製作等情，為原告所不爭執，且台北市石材公會係屬石材買賣性質之公會，對石柱製作之資訊可能較為貧乏，故經被告聲請本院向製作石材較為專業之台灣區石礦製品工業同業工會函詢有關以上開契約圖說所示石柱，就同一規格、同一樣式、同一石材（伯爵石）之石柱，以「完整原石剖開挖空製作」與「以石板黏合製作」方式，所需石材價格有無差別，價格各為多少？又同尺寸究有無可能以「剖開挖空」方式製作之結果，該公會以「一、石柱製作方式依工廠機械設備不同可區分為：（１）一體成型．．．原石挖空（２）二片接．．．原石對剖挖空組合」（３）八片接．．．三公分石板組合。二、依附圖所示其價格分別計算如下：（１）一體成型：25,000元／ｍｘ2.3＝57,500元（２）二片接：20,500元／ｍｘ2.3＝47,150（３）八片接：3,500元／ｍｘ2.3＝8,050元。三、前述價格僅計算製品價（不含施工費用），因各家報價不一，價格僅供參考。」函覆，此有台灣區石礦製品工業同業公會94年3月28日、94年4月28日（94）台石製公字第94063、94088號函在卷可稽（見卷(一)73頁、卷(二)第17頁），可見系爭石柱仍得以剖開挖空之方式製作，且在價格上，八片接方式僅為一體成型、二片接方式之百分之十四、百分之十七而已，故原告主張那麼長石柱不可能挖空云云，即不足採，而製作方式不同，價格即有差別，則系爭石柱既係以八片接方式製作，被告主張以比上開函覆比例更高之百分之二十計算系爭石柱價值，應為可採。四、按工作有瑕疵者，定作人得定相當期限，請求承攬人修補之。又按承攬人不於前條第1項所定期限內修補瑕疵，或依前條第3項之規定拒絕修補或其瑕疵不能修補者，定作人得解除契約或請求減少報酬。民法第493條第1項、第494條第1項分別定有明文。故原告既認系爭石柱以石板黏合非瑕疵而未能修補，被告自得請求減少報酬。從而以約定單價為每根80,000元，四根共320,000元，20%計算，此四根石板黏合之石柱價值為64,000元（320,000ｘ20％＝64,000），則就差額256,000元部分（320,000－64,000＝256,000），被告自得請求減少報酬。五、綜上所述，被告未付工程款為519,435元，扣除減少報酬256,000元及代為施作之工程款10,000元，被告公司應僅支付253,435元，被告並為認諾。從而原告依承攬契約法律關係，請求被告給付在253,435元及自起訴狀繕本送達被告翌日即93年12月14日起算之法定遲延利息之範圍內，為有理由，應予准許，逾此部分，則無理由，應予駁回。六、兩造陳明願供擔保，聲請宣告假執行或免為假執行，經核原告勝訴部分，業經被告認諾，依民事訴訟法第389條第1項第1款規定，本院應就此部分，依職權宣告假執行，另被告聲請免為假執行部分，亦合於法律規定，爰酌定相當之擔保金額宣告之；原告其餘假執行之聲請，因訴之駁回而失所依據，不予准許。七、因本案事證已臻明確，兩造其餘主張陳述及所提之證據，經本院審酌後，認與判決之結果無影響，爰不一一論駁，附此敘明。陸、訴訟費用之裁判依據：民事訴訟法第79條。中華民國94年5月31日民事第二庭法官黃雯惠以上正本係照原本作成。如對本判決上訴，須於判決送達後20日內向本院提出上訴狀。中華民國94年5月31日書記官林玗倩",
  "characters": {
    "judges": [
      "黃雯惠"
    ],
    "prosecutors": [

    ],
    "lawyers": [
      "王信雄",
      "謝協昌"
    ],
    "clerks": [
      "林玗倩"
    ],
    "plaintiffs": [
      "堯詳石材實業有限公司"
    ],
    "defendants": [
      "大室內裝修工程股份有限公司"
    ],
    "prosecutor_office": [

    ],
    "creditors": [

    ],
    "debtors": [

    ],
    "judicial_associate_officer": [

    ]
  },
  "adjudged_at": "2005-05-31",
  "created_at": "2016-02-06 15:45:36",
  "updated_at": "2016-02-06 15:45:36"
}