{
  "identify": "TND-93-易-955-20051028-1",
  "court": {
    "name": "臺灣臺南地方法院",
    "code": "TND"
  },
  "division": {
    "name": "刑事",
    "code": "M"
  },
  "year": 93,
  "word": "易",
  "number": "955",
  "jcheck": "1",
  "reason": "違反毒品危害防制條例",
  "content": "臺灣臺南地方法院刑事判決               93年度易字第955號\n公  訴  人  臺灣台南地方法院檢察署檢察官\n被      告  甲○○\n上列被告因違反毒品危害防制條例案件，經檢察官提起公訴（93\n年度毒偵字第1923號），被告於準備程序期日就被訴事實為有罪\n之陳述，本院合議庭裁定由受命法官獨任行簡式審判程序，並判\n決如下：\n    主  文\n甲○○施用第二級毒品，累犯，處有期徒刑肆月，如易科罰金，\n以銀元參佰元即新臺幣玖佰元折算壹日。\n    事  實\n一、甲○○於民國87年間，因妨害自由案件，經臺灣高等法院臺\n    南分院八十八年上訴字第五○七號判處有期徒刑六月，經最\n    高法院以九十年台上字五九四七號駁回上訴確定，並於九十\n    一年三月六日易科罰金執行完畢。\n二、甲○○復因施用毒品案件，經本院以九十年毒聲字第四二四\n    號裁定送觀察勒戒後，認有繼續施用傾向，復經本院以九十\n    年毒聲字第六三八號裁定令入戒治處所強制戒治，後經本院\n    九十年毒聲字第二二八四號裁定停止戒治，所餘期間付保護\n    管束，九十年十二月十三日停止處分，並於九十一年三月二\n    十日期滿，未經撤銷，以執行完畢論，經臺灣臺南地方法院\n    檢察署檢察官於九十一年四月二日以九十一年度戒毒偵字第\n    一五五號不起訴處分。\n三、詎甲○○仍不知悔改，於前開有期徒刑執行完畢後五年內，\n    竟基於施用第二級毒品安非他命之犯意（起訴書誤繕為概括\n    之犯意），於九十三年三月六日，在臺南縣永康市○○路一\n    ○一巷十四號住處，以將安非他命置放在燈泡裡以火燒烤吸\n    食所產生煙霧之方式，施用第二級毒品安非他命一次。嗣於\n    九十三年三月七日凌晨二時四十四許，由警經同意對其採集\n    尿液送驗，其尿液呈甲基安非他命陽性反應而查獲。\n四、案經臺南市警察局第一分局報請臺灣台南地方法院檢察署檢\n    察官偵查起訴。\n    理  由\n一、本件被告甲○○所犯係死刑、無期徒刑、最輕本刑為三年以\n    上有期徒刑以外之罪，其於準備程序中就被訴事實為有罪之\n    陳述，經法官告知簡式審判程序之旨，並聽取公訴人及被告\n    之意見後，認為適宜由受命法官獨任進行簡式審判程序，依\n    刑事訴訟法第二百七十三條之一第一項規定，裁定由受命法\n    官獨任進行簡式審判程序，合先敘明。\n二、前揭事實，業據被告甲○○於本院審理時坦承不諱，且被告\n    經警查獲之時所採集之尿液，經送請台灣檢驗科技股份有限\n    公司檢驗之結果，確呈甲基安非他命之陽性反應，有該公司\n    九十三年三月十七日濫用藥物檢驗報告及列管毒品人口尿液\n    檢體採集送驗紀錄表各一紙附卷可稽；是被告之自白核與事\n    實相符，堪信為真實。復被告前因施用毒品案件，經本院以\n    九十年毒聲字第四二四號裁定送觀察勒戒後，認有繼續施用\n    傾向，復經本院以九十年毒聲字第六三八號裁定令入戒治處\n    所強制戒治，後經本院九十年毒聲字第二二八四號裁定停止\n    戒治，所餘期間付保護管束，九十年十二月十三日停止處分\n    ，並於九十一年三月二十日期滿，未經撤銷，以執行完畢論\n    ，經臺灣臺南地方法院檢察署檢察官於九十一年四月二日以\n    九十一年度戒毒偵字第一五五號不起訴處分確定，有台灣高\n    等法院被告前案紀錄表可按。其於強制戒治完畢後五年內再\n    犯毒品危害防制條例第十條之罪，應無疑義。從而，本件事\n    證明確，被告犯行應堪認定。\n三、按安非他命係屬第二級毒品，毒品危害防制條例第二條第二\n    項規定甚明。核被告所為，係犯同條例第十條第二項之施用\n    第二級毒品罪。其持有安非他命後，進而施用，其持有行為\n    應被其施用之行為所吸收，不另論罪。又被告前因妨害自由\n    案件，經法院判處有期徒刑六月確定，於九十一年三月六日\n    易科罰金執行完畢，有台灣高等法院被告前案紀錄表可按，\n    其於有期徒刑執行完畢後五年以內再犯有期徒刑以上之罪，\n    為累犯，依法加重其刑。爰審酌被告前因施用毒品案件，經\n    強制戒治後，竟再繼續施用毒品，顯見意志不堅，惟其犯罪\n    係戕害自身，尚未害及他人，且次數僅為一次，所犯情節，\n    及犯後坦認犯行等一切情狀，量處如主文所示之刑，並諭知\n    如易科罰金之標準，以資懲儆。\n據上論斷，應依刑事訴訟法第二百七十三條之一第一項、第二百\n九十九條第一項前段，毒品危害防制條例第十條第二項，刑法第\n十一條前段、第四十七、第四十一條前段，罰金罰鍰提高標準條\n例第二條，現行法規所定貨幣單位折算新臺幣條例第二條，判決\n如主文。\n中    華    民    國    94    年    10    月    28    日\n                  刑事第八庭    法  官  洪士傑\n以上正本證明與原本無異。\n如不服本判決，應於判決送達後10日內，向本院提出上訴狀（應\n附繕本）。\n                                書記官  李佩珊\n中    華    民    國    94    年    10    月    31    日\n附錄法條：\n毒品危害防制條例第10條\n施用第一級毒品者，處 6 月以上 5 年以下有期徒刑。\n施用第二級毒品者，處 3 年以下有期徒刑。\n",
  "structure": {
    "main": "甲○○施用第二級毒品，累犯，處有期徒刑肆月，如易科罰金，\n以銀元參佰元即新臺幣玖佰元折算壹日。",
    "fact": "一、甲○○於民國87年間，因妨害自由案件，經臺灣高等法院臺\n    南分院八十八年上訴字第五○七號判處有期徒刑六月，經最\n    高法院以九十年台上字五九四七號駁回上訴確定，並於九十\n    一年三月六日易科罰金執行完畢。\n二、甲○○復因施用毒品案件，經本院以九十年毒聲字第四二四\n    號裁定送觀察勒戒後，認有繼續施用傾向，復經本院以九十\n    年毒聲字第六三八號裁定令入戒治處所強制戒治，後經本院\n    九十年毒聲字第二二八四號裁定停止戒治，所餘期間付保護\n    管束，九十年十二月十三日停止處分，並於九十一年三月二\n    十日期滿，未經撤銷，以執行完畢論，經臺灣臺南地方法院\n    檢察署檢察官於九十一年四月二日以九十一年度戒毒偵字第\n    一五五號不起訴處分。\n三、詎甲○○仍不知悔改，於前開有期徒刑執行完畢後五年內，\n    竟基於施用第二級毒品安非他命之犯意（起訴書誤繕為概括\n    之犯意），於九十三年三月六日，在臺南縣永康市○○路一\n    ○一巷十四號住處，以將安非他命置放在燈泡裡以火燒烤吸\n    食所產生煙霧之方式，施用第二級毒品安非他命一次。嗣於\n    九十三年三月七日凌晨二時四十四許，由警經同意對其採集\n    尿液送驗，其尿液呈甲基安非他命陽性反應而查獲。\n四、案經臺南市警察局第一分局報請臺灣台南地方法院檢察署檢\n    察官偵查起訴。",
    "reason": "一、本件被告甲○○所犯係死刑、無期徒刑、最輕本刑為三年以\n    上有期徒刑以外之罪，其於準備程序中就被訴事實為有罪之\n    陳述，經法官告知簡式審判程序之旨，並聽取公訴人及被告\n    之意見後，認為適宜由受命法官獨任進行簡式審判程序，依\n    刑事訴訟法第二百七十三條之一第一項規定，裁定由受命法\n    官獨任進行簡式審判程序，合先敘明。\n二、前揭事實，業據被告甲○○於本院審理時坦承不諱，且被告\n    經警查獲之時所採集之尿液，經送請台灣檢驗科技股份有限\n    公司檢驗之結果，確呈甲基安非他命之陽性反應，有該公司\n    九十三年三月十七日濫用藥物檢驗報告及列管毒品人口尿液\n    檢體採集送驗紀錄表各一紙附卷可稽；是被告之自白核與事\n    實相符，堪信為真實。復被告前因施用毒品案件，經本院以\n    九十年毒聲字第四二四號裁定送觀察勒戒後，認有繼續施用\n    傾向，復經本院以九十年毒聲字第六三八號裁定令入戒治處\n    所強制戒治，後經本院九十年毒聲字第二二八四號裁定停止\n    戒治，所餘期間付保護管束，九十年十二月十三日停止處分\n    ，並於九十一年三月二十日期滿，未經撤銷，以執行完畢論\n    ，經臺灣臺南地方法院檢察署檢察官於九十一年四月二日以\n    九十一年度戒毒偵字第一五五號不起訴處分確定，有台灣高\n    等法院被告前案紀錄表可按。其於強制戒治完畢後五年內再\n    犯毒品危害防制條例第十條之罪，應無疑義。從而，本件事\n    證明確，被告犯行應堪認定。\n三、按安非他命係屬第二級毒品，毒品危害防制條例第二條第二\n    項規定甚明。核被告所為，係犯同條例第十條第二項之施用\n    第二級毒品罪。其持有安非他命後，進而施用，其持有行為\n    應被其施用之行為所吸收，不另論罪。又被告前因妨害自由\n    案件，經法院判處有期徒刑六月確定，於九十一年三月六日\n    易科罰金執行完畢，有台灣高等法院被告前案紀錄表可按，\n    其於有期徒刑執行完畢後五年以內再犯有期徒刑以上之罪，\n    為累犯，依法加重其刑。爰審酌被告前因施用毒品案件，經\n    強制戒治後，竟再繼續施用毒品，顯見意志不堅，惟其犯罪\n    係戕害自身，尚未害及他人，且次數僅為一次，所犯情節，\n    及犯後坦認犯行等一切情狀，量處如主文所示之刑，並諭知\n    如易科罰金之標準，以資懲儆。\n據上論斷，應依刑事訴訟法第二百七十三條之一第一項、第二百\n九十九條第一項前段，毒品危害防制條例第十條第二項，刑法第\n十一條前段、第四十七、第四十一條前段，罰金罰鍰提高標準條\n例第二條，現行法規所定貨幣單位折算新臺幣條例第二條，判決\n如主文。\n中    華    民    國    94    年    10    月    28    日\n                  刑事第八庭    法  官  洪士傑\n以上正本證明與原本無異。\n如不服本判決，應於判決送達後10日內，向本院提出上訴狀（應\n附繕本）。\n                                書記官  李佩珊"
  },
  "search": "臺灣臺南地方法院刑事判決93年度易字第955號公訴人臺灣台南地方法院檢察署檢察官被告甲○○上列被告因違反毒品危害防制條例案件，經檢察官提起公訴（93年度毒偵字第1923號），被告於準備程序期日就被訴事實為有罪之陳述，本院合議庭裁定由受命法官獨任行簡式審判程序，並判決如下：主文甲○○施用第二級毒品，累犯，處有期徒刑肆月，如易科罰金，以銀元參佰元即新臺幣玖佰元折算壹日。事實一、甲○○於民國87年間，因妨害自由案件，經臺灣高等法院臺南分院八十八年上訴字第五○七號判處有期徒刑六月，經最高法院以九十年台上字五九四七號駁回上訴確定，並於九十一年三月六日易科罰金執行完畢。二、甲○○復因施用毒品案件，經本院以九十年毒聲字第四二四號裁定送觀察勒戒後，認有繼續施用傾向，復經本院以九十年毒聲字第六三八號裁定令入戒治處所強制戒治，後經本院九十年毒聲字第二二八四號裁定停止戒治，所餘期間付保護管束，九十年十二月十三日停止處分，並於九十一年三月二十日期滿，未經撤銷，以執行完畢論，經臺灣臺南地方法院檢察署檢察官於九十一年四月二日以九十一年度戒毒偵字第一五五號不起訴處分。三、詎甲○○仍不知悔改，於前開有期徒刑執行完畢後五年內，竟基於施用第二級毒品安非他命之犯意（起訴書誤繕為概括之犯意），於九十三年三月六日，在臺南縣永康市○○路一○一巷十四號住處，以將安非他命置放在燈泡裡以火燒烤吸食所產生煙霧之方式，施用第二級毒品安非他命一次。嗣於九十三年三月七日凌晨二時四十四許，由警經同意對其採集尿液送驗，其尿液呈甲基安非他命陽性反應而查獲。四、案經臺南市警察局第一分局報請臺灣台南地方法院檢察署檢察官偵查起訴。理由一、本件被告甲○○所犯係死刑、無期徒刑、最輕本刑為三年以上有期徒刑以外之罪，其於準備程序中就被訴事實為有罪之陳述，經法官告知簡式審判程序之旨，並聽取公訴人及被告之意見後，認為適宜由受命法官獨任進行簡式審判程序，依刑事訴訟法第二百七十三條之一第一項規定，裁定由受命法官獨任進行簡式審判程序，合先敘明。二、前揭事實，業據被告甲○○於本院審理時坦承不諱，且被告經警查獲之時所採集之尿液，經送請台灣檢驗科技股份有限公司檢驗之結果，確呈甲基安非他命之陽性反應，有該公司九十三年三月十七日濫用藥物檢驗報告及列管毒品人口尿液檢體採集送驗紀錄表各一紙附卷可稽；是被告之自白核與事實相符，堪信為真實。復被告前因施用毒品案件，經本院以九十年毒聲字第四二四號裁定送觀察勒戒後，認有繼續施用傾向，復經本院以九十年毒聲字第六三八號裁定令入戒治處所強制戒治，後經本院九十年毒聲字第二二八四號裁定停止戒治，所餘期間付保護管束，九十年十二月十三日停止處分，並於九十一年三月二十日期滿，未經撤銷，以執行完畢論，經臺灣臺南地方法院檢察署檢察官於九十一年四月二日以九十一年度戒毒偵字第一五五號不起訴處分確定，有台灣高等法院被告前案紀錄表可按。其於強制戒治完畢後五年內再犯毒品危害防制條例第十條之罪，應無疑義。從而，本件事證明確，被告犯行應堪認定。三、按安非他命係屬第二級毒品，毒品危害防制條例第二條第二項規定甚明。核被告所為，係犯同條例第十條第二項之施用第二級毒品罪。其持有安非他命後，進而施用，其持有行為應被其施用之行為所吸收，不另論罪。又被告前因妨害自由案件，經法院判處有期徒刑六月確定，於九十一年三月六日易科罰金執行完畢，有台灣高等法院被告前案紀錄表可按，其於有期徒刑執行完畢後五年以內再犯有期徒刑以上之罪，為累犯，依法加重其刑。爰審酌被告前因施用毒品案件，經強制戒治後，竟再繼續施用毒品，顯見意志不堅，惟其犯罪係戕害自身，尚未害及他人，且次數僅為一次，所犯情節，及犯後坦認犯行等一切情狀，量處如主文所示之刑，並諭知如易科罰金之標準，以資懲儆。據上論斷，應依刑事訴訟法第二百七十三條之一第一項、第二百九十九條第一項前段，毒品危害防制條例第十條第二項，刑法第十一條前段、第四十七、第四十一條前段，罰金罰鍰提高標準條例第二條，現行法規所定貨幣單位折算新臺幣條例第二條，判決如主文。中華民國94年10月28日刑事第八庭法官洪士傑以上正本證明與原本無異。如不服本判決，應於判決送達後10日內，向本院提出上訴狀（應附繕本）。書記官李佩珊中華民國94年10月31日附錄法條：毒品危害防制條例第10條施用第一級毒品者，處6月以上5年以下有期徒刑。施用第二級毒品者，處3年以下有期徒刑。",
  "characters": {
    "judges": [
      "洪士傑"
    ],
    "prosecutors": [

    ],
    "lawyers": [

    ],
    "clerks": [
      "李佩珊"
    ],
    "plaintiffs": [

    ],
    "defendants": [
      "甲○○"
    ],
    "prosecutor_office": [
      "臺灣台南地方法院檢察署檢察官"
    ],
    "creditors": [

    ],
    "debtors": [

    ],
    "judicial_associate_officer": [

    ]
  },
  "adjudged_at": "2005-10-28",
  "created_at": "2016-02-07 10:34:21",
  "updated_at": "2016-02-07 10:34:21"
}