{
  "identify": "TYD-93-重訴緝-4-20050111-1",
  "court": {
    "name": "臺灣桃園地方法院",
    "code": "TYD"
  },
  "division": {
    "name": "刑事",
    "code": "M"
  },
  "year": 93,
  "word": "重訴緝",
  "number": "4",
  "jcheck": "1",
  "reason": "毒品危害防制條例",
  "content": "臺灣桃園地方法院刑事裁定             93年度重訴緝字第4號\n公  訴  人  臺灣桃園地方法院檢察署檢察官\n被      告  甲○○  男  33歲.\n                    （\n上列被告因毒品危害防制條例案件，經檢察官提起公訴，本院裁\n定如下：\n    主  文\n甲○○自民國94年1月12日起延長羈押2 月。\n    理  由\n本件被告因毒品危害防制條例案件，經本院認有刑事訴訟法第10\n1 條第1 、2 款之情形而有羈押必要，於民國93年10月12日執行\n羈押，茲本院以前項原因依然存在，仍有繼續羈押之必要，應自\n民國94年1月12日起延長羈押2 月。爰依刑事訴訟法第108 條第\n1項 裁定如主文。\n中    華    民    國    94    年    1     月    11    日\n                        刑事第四庭\n                        審判長法  官  陳世宗\n                              法  官  蘇昭蓉\n                              法  官  李昆南\n以上正本証明與原本無異\n如不服本裁定應於送達後5 日內，向本院提出抗告狀。\n中    華    民    國    94    年    1     月    11    日\n                              書記官  郭中明\n",
  "structure": {
    "main": "甲○○自民國94年1月12日起延長羈押2 月。",
    "reason": "本件被告因毒品危害防制條例案件，經本院認有刑事訴訟法第10\n1 條第1 、2 款之情形而有羈押必要，於民國93年10月12日執行\n羈押，茲本院以前項原因依然存在，仍有繼續羈押之必要，應自\n民國94年1月12日起延長羈押2 月。爰依刑事訴訟法第108 條第\n1項 裁定如主文。"
  },
  "search": "臺灣桃園地方法院刑事裁定93年度重訴緝字第4號公訴人臺灣桃園地方法院檢察署檢察官被告甲○○男33歲.（上列被告因毒品危害防制條例案件，經檢察官提起公訴，本院裁定如下：主文甲○○自民國94年1月12日起延長羈押2月。理由本件被告因毒品危害防制條例案件，經本院認有刑事訴訟法第101條第1、2款之情形而有羈押必要，於民國93年10月12日執行羈押，茲本院以前項原因依然存在，仍有繼續羈押之必要，應自民國94年1月12日起延長羈押2月。爰依刑事訴訟法第108條第1項裁定如主文。中華民國94年1月11日刑事第四庭審判長法官陳世宗法官蘇昭蓉法官李昆南以上正本証明與原本無異如不服本裁定應於送達後5日內，向本院提出抗告狀。中華民國94年1月11日書記官郭中明",
  "characters": {
    "judges": [
      "陳世宗",
      "蘇昭蓉",
      "李昆南"
    ],
    "prosecutors": [

    ],
    "lawyers": [

    ],
    "clerks": [
      "郭中明"
    ],
    "plaintiffs": [

    ],
    "defendants": [
      "甲○○  男  33歲."
    ],
    "prosecutor_office": [
      "臺灣桃園地方法院檢察署檢察官"
    ],
    "creditors": [

    ],
    "debtors": [

    ],
    "judicial_associate_officer": [

    ]
  },
  "adjudged_at": "2005-01-11",
  "created_at": "2016-02-07 01:55:46",
  "updated_at": "2016-02-07 01:55:46"
}