{
  "identify": "SCD-91-重訴-211-20020903-1",
  "court": {
    "name": "臺灣新竹地方法院",
    "code": "SCD"
  },
  "division": {
    "name": "民事",
    "code": "V"
  },
  "year": 91,
  "word": "重訴",
  "number": "211",
  "jcheck": "1",
  "reason": "返還消費借貸款",
  "content": "臺灣新竹地方法院民事裁定  九十一年度重訴字第二一一號\n    原      告  台灣土地銀行\n    法定代理人  林彭郎\n    訴訟代理人  陳玉齡\n    被      告  甲○○\n右當事人間返還消費借貸款事件，本院裁定如左：\n    主      文\n原告之訴及假執行之聲請均駁回。\n訴訟費用由原告負擔。\n    理      由\n一、按提起民事訴訟，應依民事訴訟費用法規定繳納裁判費，為必須具備之程式。\n二、本件原告起訴僅繳納部分裁判費，經本院於民國九十一年七月二十三日裁定命原\n    告於收受該裁定送達時起五日內補正。該項裁定已於民國九十一年七月二十六日\n    送達原告，有送達證書附卷可憑。\n三、原告逾期迄今仍未補正，其訴不能認為合法，應予駁回。\n四、依民事訴訟法第二百四十九條第一項第六款、第九十五條、第七十八條，裁定如\n    主文。\n中      華      民      國    九十一    年      九      月      三      日\n                                  臺灣新竹地方法院民事第一庭\n~B法      官  鄭子俊\n右正本證明與原本無異。\n如不服本裁定應於送達後十日內向本院提出抗告狀。\n~B法院書記官  林美足\n中      華      民      國    九十一    年      九      月      三      日\n",
  "structure": {
    "main": "原告之訴及假執行之聲請均駁回。\n訴訟費用由原告負擔。",
    "reason": "一、按提起民事訴訟，應依民事訴訟費用法規定繳納裁判費，為必須具備之程式。\n二、本件原告起訴僅繳納部分裁判費，經本院於民國九十一年七月二十三日裁定命原\n    告於收受該裁定送達時起五日內補正。該項裁定已於民國九十一年七月二十六日\n    送達原告，有送達證書附卷可憑。\n三、原告逾期迄今仍未補正，其訴不能認為合法，應予駁回。\n四、依民事訴訟法第二百四十九條第一項第六款、第九十五條、第七十八條，裁定如\n    主文。"
  },
  "search": "臺灣新竹地方法院民事裁定九十一年度重訴字第二一一號原告台灣土地銀行法定代理人林彭郎訴訟代理人陳玉齡被告甲○○右當事人間返還消費借貸款事件，本院裁定如左：主文原告之訴及假執行之聲請均駁回。訴訟費用由原告負擔。理由一、按提起民事訴訟，應依民事訴訟費用法規定繳納裁判費，為必須具備之程式。二、本件原告起訴僅繳納部分裁判費，經本院於民國九十一年七月二十三日裁定命原告於收受該裁定送達時起五日內補正。該項裁定已於民國九十一年七月二十六日送達原告，有送達證書附卷可憑。三、原告逾期迄今仍未補正，其訴不能認為合法，應予駁回。四、依民事訴訟法第二百四十九條第一項第六款、第九十五條、第七十八條，裁定如主文。中華民國九十一年九月三日臺灣新竹地方法院民事第一庭~B法官鄭子俊右正本證明與原本無異。如不服本裁定應於送達後十日內向本院提出抗告狀。~B法院書記官林美足中華民國九十一年九月三日",
  "characters": {
    "judges": [
      "鄭子俊"
    ],
    "prosecutors": [

    ],
    "lawyers": [

    ],
    "clerks": [

    ],
    "plaintiffs": [
      "台灣土地銀行"
    ],
    "defendants": [
      "甲○○",
      "右當事人間返還消費借貸款事件，本院裁定如左："
    ],
    "prosecutor_office": [

    ],
    "creditors": [

    ],
    "debtors": [

    ],
    "judicial_associate_officer": [

    ]
  },
  "adjudged_at": "2002-09-03",
  "created_at": "2016-02-04 17:18:46",
  "updated_at": "2016-02-04 17:18:46"
}