{
  "identify": "KSD-93-訴-1924-20041130-1",
  "court": {
    "name": "臺灣高雄地方法院",
    "code": "KSD"
  },
  "division": {
    "name": "刑事",
    "code": "M"
  },
  "year": 93,
  "word": "訴",
  "number": "1924",
  "jcheck": "1",
  "reason": "強盜",
  "content": "臺灣高雄地方法院刑事判決                        九十三年度訴字第一九二四號\n    公  訴  人  臺灣高雄地方法院檢察署檢察官\n    被      告  丙○○\n    指定辯護人  本院公設辯護人  乙○○\n右列被告因強盜案件，經檢察官提起公訴（九十三年度偵字第一０五二八號），本院\n判決如左：\n    主  文\n丙○○意圖為自己不法之所有，而搶奪他人之動產，處有期徒刑壹年。\n    事  實\n一、丙○○於民國九十三年五月二十二日十二時四十分許，行經高雄市○○區○○路\n    之「順盛市場」時，見甲○○攤位上之鐵盒內置有當日營業所得新臺幣（下同）\n    三千元之現金，竟意圖為自己不法之所有，趁甲○○不及防備之際，走近攤位徒\n    手搶奪該三千元握於手中，甲○○見狀即出手拉扯丙○○之手腕，惟丙○○仍掙\n    脫逃逸而得手，嗣於同日十四時許，為警在高雄市○○區○○路四六０號前循線\n    查獲。\n二、案經高雄市政府警察局三民第二分局報告臺灣高雄地方法院檢察署檢察官偵查起\n    訴。\n    理  由\n壹、程序部分：按被告以外之人於審判外之言詞或書面陳述，除法律有規定者外，不\n    得作為證據。又被告以外之人於檢察事務官、司法警察官或司法警察調查中所為\n    之陳述，與審判中不符時，其先前之陳述具有較可信之特別情況，且為證明犯罪\n    事實存否所必要者，得為證據，刑事訴訟法第一百五十九條第一項及同條之二分\n    別定有明文。依前揭規定之立法形式以觀，該條第一項為原則規定，同條之二則\n    為該條所謂「除法律有規定者」之例外規定，易言之，凡被告以外之人於審判外\n    之陳述，性質上均屬傳聞證據，故明文規定該等證據原則上不具證據能力，惟如\n    被告以外之人於審判外之陳述與其於審判中之證述不符，而先前之陳述具有較可\n    信之特別情況，且為證明犯罪事實存否所必要者，始例外賦予證據能力。是如被\n    告以外之人於審判外之陳述不符合例外規定之要件時，自應適用原則規定而認為\n    不具證據能力。經查，本件被害人甲○○於警詢時之陳述，與其於本院審判中之\n    證詞相符，且其就被告之犯行已於審判中證述明確，則先前之陳述即非證明本件\n    犯罪事實存否所必要，顯與前揭例外規定得為證據之要件不符，依法自不得作為\n    認定被告犯行之證據。\n貳、實體部分：\n一、右揭犯罪事實，迭據被告於警詢、偵訊及本院審理時坦承不諱，核與證人甲○○\n    於本院審理時證述之情節相符，復有高雄市政府警察局三民第二分局扣押筆錄、\n    扣押物品目錄表及照片五張附卷可稽，足見被告之自白與事實相符，堪予採信。\n    其確有前揭搶奪犯行，洵堪認定，本件事證明確，應依法論科。\n二、核被告所為，係犯刑法第三百二十五條第一項之普通搶奪罪。公訴意旨固認被告\n    係犯同法第三百二十九條之準強盜罪，惟被告於行搶時，並未當場施以任何強暴\n    或脅迫之行為，此業據證人甲○○證述綦詳，自不得遽以準強盜罪論，然其基本\n    事實同一，本院自應予審理，又公訴人已於本院審理時變更起訴法條為普通搶奪\n    罪，本院即無再予變更起訴法條之必要，附此敘明。爰審酌被告正值年輕力壯，\n    不思以己力賺取生活所需，竟出手奪取他人財物，影響社會治安甚鉅，惟念其犯\n    後坦承犯行，頗具悔意，且所搶得之金額甚微等一切情狀，量處如主文所示之刑\n    ，以資懲儆。公訴人具體求刑有期徒刑一年六月，固非無見，惟被告自警詢、偵\n    訊及本院審理時始終坦承犯行，態度良好，且所搶得之金額僅三千元，其犯罪情\n    節及所造成之損害均非鉅大，本院因認前揭求刑尚嫌過重，附此敘明。\n據上論斷，應依刑事訴訟法第二百九十九條第一項前段，刑法第三百二十五條第一項\n，判決如主文。\n本案經檢察官丁○○到庭執行職務。\n中      華      民      國    九十三    年     十一     月     三十     日\n                                    臺灣高雄地方法院刑事第十一庭\n                                        審判長法  官    徐美麗\n                                              法  官    高增泓\n                                              法  官    鄭詠仁\n右正本證明與原本無異。\n如不服本判決，應於判決送達後十日內，向本院提出上訴狀。\n                                              書記官    蔡妮君\n中      華      民      國    九十三    年     十一     月     三十     日\n附錄法條：\n刑法第三百二十五條\n意圖為自己或第三人不法之所有，而搶奪他人之動產者，處六月以上五年以下有期徒\n刑。\n因而致人於死者，處無期徒刑或七年以上有期徒刑，致重傷者，處三年以上十年以下\n有期徒刑。\n第一項之未遂犯罰之。\n",
  "structure": {
    "main": "丙○○意圖為自己不法之所有，而搶奪他人之動產，處有期徒刑壹年。",
    "fact": "一、丙○○於民國九十三年五月二十二日十二時四十分許，行經高雄市○○區○○路\n    之「順盛市場」時，見甲○○攤位上之鐵盒內置有當日營業所得新臺幣（下同）\n    三千元之現金，竟意圖為自己不法之所有，趁甲○○不及防備之際，走近攤位徒\n    手搶奪該三千元握於手中，甲○○見狀即出手拉扯丙○○之手腕，惟丙○○仍掙\n    脫逃逸而得手，嗣於同日十四時許，為警在高雄市○○區○○路四六０號前循線\n    查獲。\n二、案經高雄市政府警察局三民第二分局報告臺灣高雄地方法院檢察署檢察官偵查起\n    訴。",
    "reason": "壹、程序部分：按被告以外之人於審判外之言詞或書面陳述，除法律有規定者外，不\n    得作為證據。又被告以外之人於檢察事務官、司法警察官或司法警察調查中所為\n    之陳述，與審判中不符時，其先前之陳述具有較可信之特別情況，且為證明犯罪\n    事實存否所必要者，得為證據，刑事訴訟法第一百五十九條第一項及同條之二分\n    別定有明文。依前揭規定之立法形式以觀，該條第一項為原則規定，同條之二則\n    為該條所謂「除法律有規定者」之例外規定，易言之，凡被告以外之人於審判外\n    之陳述，性質上均屬傳聞證據，故明文規定該等證據原則上不具證據能力，惟如\n    被告以外之人於審判外之陳述與其於審判中之證述不符，而先前之陳述具有較可\n    信之特別情況，且為證明犯罪事實存否所必要者，始例外賦予證據能力。是如被\n    告以外之人於審判外之陳述不符合例外規定之要件時，自應適用原則規定而認為\n    不具證據能力。經查，本件被害人甲○○於警詢時之陳述，與其於本院審判中之\n    證詞相符，且其就被告之犯行已於審判中證述明確，則先前之陳述即非證明本件\n    犯罪事實存否所必要，顯與前揭例外規定得為證據之要件不符，依法自不得作為\n    認定被告犯行之證據。\n貳、實體部分：\n一、右揭犯罪事實，迭據被告於警詢、偵訊及本院審理時坦承不諱，核與證人甲○○\n    於本院審理時證述之情節相符，復有高雄市政府警察局三民第二分局扣押筆錄、\n    扣押物品目錄表及照片五張附卷可稽，足見被告之自白與事實相符，堪予採信。\n    其確有前揭搶奪犯行，洵堪認定，本件事證明確，應依法論科。\n二、核被告所為，係犯刑法第三百二十五條第一項之普通搶奪罪。公訴意旨固認被告\n    係犯同法第三百二十九條之準強盜罪，惟被告於行搶時，並未當場施以任何強暴\n    或脅迫之行為，此業據證人甲○○證述綦詳，自不得遽以準強盜罪論，然其基本\n    事實同一，本院自應予審理，又公訴人已於本院審理時變更起訴法條為普通搶奪\n    罪，本院即無再予變更起訴法條之必要，附此敘明。爰審酌被告正值年輕力壯，\n    不思以己力賺取生活所需，竟出手奪取他人財物，影響社會治安甚鉅，惟念其犯\n    後坦承犯行，頗具悔意，且所搶得之金額甚微等一切情狀，量處如主文所示之刑\n    ，以資懲儆。公訴人具體求刑有期徒刑一年六月，固非無見，惟被告自警詢、偵\n    訊及本院審理時始終坦承犯行，態度良好，且所搶得之金額僅三千元，其犯罪情\n    節及所造成之損害均非鉅大，本院因認前揭求刑尚嫌過重，附此敘明。\n據上論斷，應依刑事訴訟法第二百九十九條第一項前段，刑法第三百二十五條第一項\n，判決如主文。\n本案經檢察官丁○○到庭執行職務。\n中      華      民      國    九十三    年     十一     月     三十     日\n                                    臺灣高雄地方法院刑事第十一庭\n                                        審判長法  官    徐美麗\n                                              法  官    高增泓\n                                              法  官    鄭詠仁\n右正本證明與原本無異。\n如不服本判決，應於判決送達後十日內，向本院提出上訴狀。\n                                              書記官    蔡妮君"
  },
  "search": "臺灣高雄地方法院刑事判決九十三年度訴字第一九二四號公訴人臺灣高雄地方法院檢察署檢察官被告丙○○指定辯護人本院公設辯護人乙○○右列被告因強盜案件，經檢察官提起公訴（九十三年度偵字第一０五二八號），本院判決如左：主文丙○○意圖為自己不法之所有，而搶奪他人之動產，處有期徒刑壹年。事實一、丙○○於民國九十三年五月二十二日十二時四十分許，行經高雄市○○區○○路之「順盛市場」時，見甲○○攤位上之鐵盒內置有當日營業所得新臺幣（下同）三千元之現金，竟意圖為自己不法之所有，趁甲○○不及防備之際，走近攤位徒手搶奪該三千元握於手中，甲○○見狀即出手拉扯丙○○之手腕，惟丙○○仍掙脫逃逸而得手，嗣於同日十四時許，為警在高雄市○○區○○路四六０號前循線查獲。二、案經高雄市政府警察局三民第二分局報告臺灣高雄地方法院檢察署檢察官偵查起訴。理由壹、程序部分：按被告以外之人於審判外之言詞或書面陳述，除法律有規定者外，不得作為證據。又被告以外之人於檢察事務官、司法警察官或司法警察調查中所為之陳述，與審判中不符時，其先前之陳述具有較可信之特別情況，且為證明犯罪事實存否所必要者，得為證據，刑事訴訟法第一百五十九條第一項及同條之二分別定有明文。依前揭規定之立法形式以觀，該條第一項為原則規定，同條之二則為該條所謂「除法律有規定者」之例外規定，易言之，凡被告以外之人於審判外之陳述，性質上均屬傳聞證據，故明文規定該等證據原則上不具證據能力，惟如被告以外之人於審判外之陳述與其於審判中之證述不符，而先前之陳述具有較可信之特別情況，且為證明犯罪事實存否所必要者，始例外賦予證據能力。是如被告以外之人於審判外之陳述不符合例外規定之要件時，自應適用原則規定而認為不具證據能力。經查，本件被害人甲○○於警詢時之陳述，與其於本院審判中之證詞相符，且其就被告之犯行已於審判中證述明確，則先前之陳述即非證明本件犯罪事實存否所必要，顯與前揭例外規定得為證據之要件不符，依法自不得作為認定被告犯行之證據。貳、實體部分：一、右揭犯罪事實，迭據被告於警詢、偵訊及本院審理時坦承不諱，核與證人甲○○於本院審理時證述之情節相符，復有高雄市政府警察局三民第二分局扣押筆錄、扣押物品目錄表及照片五張附卷可稽，足見被告之自白與事實相符，堪予採信。其確有前揭搶奪犯行，洵堪認定，本件事證明確，應依法論科。二、核被告所為，係犯刑法第三百二十五條第一項之普通搶奪罪。公訴意旨固認被告係犯同法第三百二十九條之準強盜罪，惟被告於行搶時，並未當場施以任何強暴或脅迫之行為，此業據證人甲○○證述綦詳，自不得遽以準強盜罪論，然其基本事實同一，本院自應予審理，又公訴人已於本院審理時變更起訴法條為普通搶奪罪，本院即無再予變更起訴法條之必要，附此敘明。爰審酌被告正值年輕力壯，不思以己力賺取生活所需，竟出手奪取他人財物，影響社會治安甚鉅，惟念其犯後坦承犯行，頗具悔意，且所搶得之金額甚微等一切情狀，量處如主文所示之刑，以資懲儆。公訴人具體求刑有期徒刑一年六月，固非無見，惟被告自警詢、偵訊及本院審理時始終坦承犯行，態度良好，且所搶得之金額僅三千元，其犯罪情節及所造成之損害均非鉅大，本院因認前揭求刑尚嫌過重，附此敘明。據上論斷，應依刑事訴訟法第二百九十九條第一項前段，刑法第三百二十五條第一項，判決如主文。本案經檢察官丁○○到庭執行職務。中華民國九十三年十一月三十日臺灣高雄地方法院刑事第十一庭審判長法官徐美麗法官高增泓法官鄭詠仁右正本證明與原本無異。如不服本判決，應於判決送達後十日內，向本院提出上訴狀。書記官蔡妮君中華民國九十三年十一月三十日附錄法條：刑法第三百二十五條意圖為自己或第三人不法之所有，而搶奪他人之動產者，處六月以上五年以下有期徒刑。因而致人於死者，處無期徒刑或七年以上有期徒刑，致重傷者，處三年以上十年以下有期徒刑。第一項之未遂犯罰之。",
  "characters": {
    "judges": [
      "徐美麗",
      "高增泓",
      "鄭詠仁"
    ],
    "prosecutors": [

    ],
    "lawyers": [

    ],
    "clerks": [
      "蔡妮君"
    ],
    "plaintiffs": [

    ],
    "defendants": [
      "丙○○"
    ],
    "prosecutor_office": [
      "臺灣高雄地方法院檢察署檢察官"
    ],
    "creditors": [

    ],
    "debtors": [

    ],
    "judicial_associate_officer": [

    ]
  },
  "adjudged_at": "2004-11-30",
  "created_at": "2016-02-06 04:32:14",
  "updated_at": "2016-02-06 04:32:14"
}