{
  "identify": "TCD-93-訴-2584-20041130-1",
  "court": {
    "name": "臺灣臺中地方法院",
    "code": "TCD"
  },
  "division": {
    "name": "刑事",
    "code": "M"
  },
  "year": 93,
  "word": "訴",
  "number": "2584",
  "jcheck": "1",
  "reason": "毒品危害防制條例",
  "content": "臺灣臺中地方法院宣示判決筆錄                    九十三年度訴字第二五八四號\n    公  訴  人  臺灣臺中地方法院檢察署檢察官\n    被      告  甲○○\n    選任辯護人  曾耀聰律師\n右列被告因常業詐欺案件，於中華民國九十三年十一月三十日下午四時，在本院第六\n法庭宣示判決，出席職員如左：\n法官起立朗讀判決主文、犯罪事實要旨、處罰條文、附記事項，及告以上訴限制、期\n間並提出上訴狀之法院，且諭知記載其內容：\n一、主  文：\n甲○○共同持有第壹級毒品，處有期徒刑陸月，如易科罰金，以佰元折算壹日。扣\n案之第壹級毒品海洛因大包及壹小包（合計淨重佰伍拾壹點捌公克，純質淨重\n壹佰陸拾點伍公克，包裝重陸點玖公克）均沒收銷燬之。\n二、犯罪事實要旨：甲○○（原名曾惠玉）與林漢原係男女朋友，其二人自民國（下\n    同）八十七年間起即有施用毒品之不良犯行。緣林漢原、張明娟、賴煥松（以上\n    三人均另經檢察官另案起訴）於九十一年六月間，各出資新臺幣（下同）二十萬\n    元（共六十萬元），擬共同販入大量第一級毒品海洛因，賴煥松遂於九十一年六\n    月二十日下午，獨自駕車至臺南縣新營市某處，向不詳年籍姓名綽號「董仔」之\n    成年男子購入毒品海洛因三包（合計淨重三五一點八三公克，純質淨重一六三．\n    三五公克，包裝重六點九三公克）。賴煥松購得毒品後，即與林漢原約定在彰化\n    縣員林鎮○○○○○道路入口處會合交付上開毒品，林漢原即邀約其女友甲○○\n    一同前往，同日晚上九、十時許，林漢原與甲○○在上開快速道路入口處一起上\n    賴煥松所駕駛之自用小客車後，賴煥松即交付上開以報紙包裝之三包海洛因給林\n    漢原，甲○○即基於與林漢原共同持有毒品之犯意聯絡，將其所攜帶之空手提包\n    ，提供給林漢原裝上開海洛因。其二人並由賴煥松載至臺中市○○路之朝馬車站\n    ，於同日晚間十一時許，共同持有攜帶該三包海洛因，搭乘巴士行駛中山高速公\n    路前往新竹縣，並在事前約定之新竹縣湖口交流道下車，與張明娟會合，張明娟\n    則搭乘由郭錦泳（另案偵辦中）駕駛之車牌號碼二Ｍ─三九九七號自用小客車前\n    往等候，林漢原與甲○○抵達後，隨即上車，郭錦泳依張明娟指示駕車前往新竹\n    縣新豐鄉○○路一七六號之春城汽車旅館。抵達後，張明娟即分裝一小包海洛因\n    （毛重四點四四公克）充作樣品，與林漢原一同下車，欲進入該汽車旅館，旋於\n    翌日即同年六月二十一日凌晨一時許，經據報在場埋伏之員警查獲，並扣得張明\n    娟持有之前述海洛因一包，又在該汽車旅館附近即新竹縣新豐鄉○○路七之三號\n    前，查獲停車在該處等候之郭錦泳與甲○○，並在車上扣得甲○○持有之前述海\n    洛因三包。\n三、處罰條文：\n毒品危害防制條例第十一條第一項、第十八條第一項前段，刑法第十一條、第二十八\n條、第四十一條第一項前段，罰金罰鍰提高標準條例第二條。\n四、協商判決除有刑事訴訟法第四百五十四條之四第一項第一款於本訊問程序終結前\n    ，被告撤銷協商合意或檢察官撤回協商聲請者；第二款被告協商之意思非出於自\n    由意志者；第四款被告所犯之罪非第四百五十五條之二第一項所定得以協商判決\n    者；第六款被告有其他較重之裁判上一罪之犯罪事實者；第七款法院認應諭知免\n    刑或免訴、不受理者情形之一，及違反同條第二項「法院應於協商合意範圍內為\n    判決；法院為協商判決所科之刑，以宣告緩刑或二年以下有期徒刑、拘役或罰金\n    為限」之規定者外，不得上訴。\n六、如不服本件判決，且符合前述得上訴之特別規定者，得自收受判決送達之日起十\n    日內，向本院提出上訴書狀，上訴於第二審法院。\n中      華      民      國    九十三    年     十一     月     三十     日\n                                      臺灣臺中地方法院刑事第六庭\n                                                        書記官  謝明倫\n                                                        法  官  林念祖\n右正本證明與原本無異。\n                                                        書記官\n中      華      民      國    九十三    年     十一     月     三十     日\n",
  "structure": {
  },
  "search": "臺灣臺中地方法院宣示判決筆錄九十三年度訴字第二五八四號公訴人臺灣臺中地方法院檢察署檢察官被告甲○○選任辯護人曾耀聰律師右列被告因常業詐欺案件，於中華民國九十三年十一月三十日下午四時，在本院第六法庭宣示判決，出席職員如左：法官起立朗讀判決主文、犯罪事實要旨、處罰條文、附記事項，及告以上訴限制、期間並提出上訴狀之法院，且諭知記載其內容：一、主文：甲○○共同持有第壹級毒品，處有期徒刑陸月，如易科罰金，以佰元折算壹日。扣案之第壹級毒品海洛因大包及壹小包（合計淨重佰伍拾壹點捌公克，純質淨重壹佰陸拾點伍公克，包裝重陸點玖公克）均沒收銷燬之。二、犯罪事實要旨：甲○○（原名曾惠玉）與林漢原係男女朋友，其二人自民國（下同）八十七年間起即有施用毒品之不良犯行。緣林漢原、張明娟、賴煥松（以上三人均另經檢察官另案起訴）於九十一年六月間，各出資新臺幣（下同）二十萬元（共六十萬元），擬共同販入大量第一級毒品海洛因，賴煥松遂於九十一年六月二十日下午，獨自駕車至臺南縣新營市某處，向不詳年籍姓名綽號「董仔」之成年男子購入毒品海洛因三包（合計淨重三五一點八三公克，純質淨重一六三．三五公克，包裝重六點九三公克）。賴煥松購得毒品後，即與林漢原約定在彰化縣員林鎮○○○○○道路入口處會合交付上開毒品，林漢原即邀約其女友甲○○一同前往，同日晚上九、十時許，林漢原與甲○○在上開快速道路入口處一起上賴煥松所駕駛之自用小客車後，賴煥松即交付上開以報紙包裝之三包海洛因給林漢原，甲○○即基於與林漢原共同持有毒品之犯意聯絡，將其所攜帶之空手提包，提供給林漢原裝上開海洛因。其二人並由賴煥松載至臺中市○○路之朝馬車站，於同日晚間十一時許，共同持有攜帶該三包海洛因，搭乘巴士行駛中山高速公路前往新竹縣，並在事前約定之新竹縣湖口交流道下車，與張明娟會合，張明娟則搭乘由郭錦泳（另案偵辦中）駕駛之車牌號碼二Ｍ─三九九七號自用小客車前往等候，林漢原與甲○○抵達後，隨即上車，郭錦泳依張明娟指示駕車前往新竹縣新豐鄉○○路一七六號之春城汽車旅館。抵達後，張明娟即分裝一小包海洛因（毛重四點四四公克）充作樣品，與林漢原一同下車，欲進入該汽車旅館，旋於翌日即同年六月二十一日凌晨一時許，經據報在場埋伏之員警查獲，並扣得張明娟持有之前述海洛因一包，又在該汽車旅館附近即新竹縣新豐鄉○○路七之三號前，查獲停車在該處等候之郭錦泳與甲○○，並在車上扣得甲○○持有之前述海洛因三包。三、處罰條文：毒品危害防制條例第十一條第一項、第十八條第一項前段，刑法第十一條、第二十八條、第四十一條第一項前段，罰金罰鍰提高標準條例第二條。四、協商判決除有刑事訴訟法第四百五十四條之四第一項第一款於本訊問程序終結前，被告撤銷協商合意或檢察官撤回協商聲請者；第二款被告協商之意思非出於自由意志者；第四款被告所犯之罪非第四百五十五條之二第一項所定得以協商判決者；第六款被告有其他較重之裁判上一罪之犯罪事實者；第七款法院認應諭知免刑或免訴、不受理者情形之一，及違反同條第二項「法院應於協商合意範圍內為判決；法院為協商判決所科之刑，以宣告緩刑或二年以下有期徒刑、拘役或罰金為限」之規定者外，不得上訴。六、如不服本件判決，且符合前述得上訴之特別規定者，得自收受判決送達之日起十日內，向本院提出上訴書狀，上訴於第二審法院。中華民國九十三年十一月三十日臺灣臺中地方法院刑事第六庭書記官謝明倫法官林念祖右正本證明與原本無異。書記官中華民國九十三年十一月三十日",
  "characters": {
    "judges": [
      "林念祖"
    ],
    "prosecutors": [

    ],
    "lawyers": [
      "曾耀聰"
    ],
    "clerks": [
      "謝明倫",
      "中華民國九十三年十一月三十日"
    ],
    "plaintiffs": [

    ],
    "defendants": [
      "甲○○"
    ],
    "prosecutor_office": [
      "臺灣臺中地方法院檢察署檢察官"
    ],
    "creditors": [

    ],
    "debtors": [

    ],
    "judicial_associate_officer": [

    ]
  },
  "adjudged_at": "2004-11-30",
  "created_at": "2016-02-06 04:33:27",
  "updated_at": "2016-02-06 04:33:27"
}