{
  "identify": "TYD-93-交易-303-20041130-1",
  "court": {
    "name": "臺灣桃園地方法院",
    "code": "TYD"
  },
  "division": {
    "name": "刑事",
    "code": "M"
  },
  "year": 93,
  "word": "交易",
  "number": "303",
  "jcheck": "1",
  "reason": "過失傷害",
  "content": "臺灣桃園地方法院刑事判決                        九十三年度交易字第三０三號\n    聲  請  人  台灣桃園地方法院檢察署檢察官\n    被      告  乙○○  男  三.\n右被告因過失傷害案件，經檢察官聲請簡易判決處刑（九十三年度偵字第八七六五號\n），本院簡易庭認為不宜以簡易判決處刑，改依通常程序審理，茲判決如左：\n    主  文\n本件公訴不受理。\n    理  由\n一、聲請簡易判決處刑意旨略以：被告乙○○於民國九十三年五月十九日下午十三時\n    三十分許，在桃園縣中壢市便利商店購買啤酒飲畢後，已達不能安全駕駛動力交\n    通工具之程度，竟仍駕駛車牌號碼ＨＬ─四六七八號自用小客車，於同日下午二\n    時二十分許，行經桃園縣中壢市龍岡圓環旁，倒車欲進入車道時，本應注意有無\n    車輛經過，並應隨時採取必要之安全措施，而依當時情形，並無不能注意之情事\n    ，竟疏未注意，自後擦撞同向由告訴人甲○○所騎乘車號ＩＱＩ─○五六之重機\n    車，致甲○○人車倒地，受有右側小指及右小腿擦挫傷等傷害。嗣經警方前往處\n    理，經對乙○○施以呼氣酒精濃度檢測，測得其呼氣酒精濃度高達每公升零點八\n    五毫克（涉犯公共危險罪嫌部分，業據本院於九十三年十月十四日以九十三年度\n    壢交簡字第一二一五號判處拘役二十日），因認被告涉犯刑法第二百八十四條第\n    一項前段過失傷害罪嫌云云。\n二、按告訴乃論之罪，告訴人於第一審辯論終結前得撤回其告訴，而告訴經撤回者，\n    應諭知不受理之判決，刑事訴訟法第二百三十八條第一項、第三百零三條第三款\n    定有明文。又刑事事件於偵查中或第一審言詞辯論終結前，調解成立，經法院核\n    定，並經當事人同意撤回者，視為於調解成立時撤回告訴或自訴，鄉鎮市調解條\n    例第二十五條第二項亦定有明文。\n三、查本件告訴人告訴被告於右述時、地駕車不慎與告訴人騎駛之機車擦撞致告訴人\n    倒地受傷之過失傷害案件，經檢察官聲請簡易判決處刑，認係犯刑法第二百八十\n    四條第一項前段之罪，依同法第二百八十七條前段之規定，須告訴乃論。茲據告\n    訴人與被告間已於九十三年七月二十八日經由桃園縣中壢市調解委員會調解成立\n    ，亦於九十三年八月二十三日經本院核定，有桃園縣中壢市調解委員會調解書影\n    本一份在卷可稽，並經本院依職權調閱本院九十三年度壢核字第一０五四號卷查\n    閱屬實，依前述規定，本件於調解成立時即九十三年七月二十八日視為撤回告訴\n    ，依照首開說明，爰不經言詞辯論，逕為不受理之論知。\n四、據上論斷，應依刑事訴訟法第四百五十二條、第三百零三條第三款、第三百零七\n    條，判決如主文。\n中      華      民      國    九十三    年     十一     月     三十     日\n                              臺灣桃園地方法院刑事第一庭\n                                  審判長法  官 曾淑華\n                                        法  官 黃梅淑\n                                        法  官 朱美璘\n右正本證明與原本無異。\n如不服本判決，應於送達後十日內，向本院提出上訴狀。\n                                        書記官 楊鳳滿\n中      華      民      國    九十三    年     十二     月      三      日\n",
  "structure": {
    "main": "本件公訴不受理。",
    "reason": "一、聲請簡易判決處刑意旨略以：被告乙○○於民國九十三年五月十九日下午十三時\n    三十分許，在桃園縣中壢市便利商店購買啤酒飲畢後，已達不能安全駕駛動力交\n    通工具之程度，竟仍駕駛車牌號碼ＨＬ─四六七八號自用小客車，於同日下午二\n    時二十分許，行經桃園縣中壢市龍岡圓環旁，倒車欲進入車道時，本應注意有無\n    車輛經過，並應隨時採取必要之安全措施，而依當時情形，並無不能注意之情事\n    ，竟疏未注意，自後擦撞同向由告訴人甲○○所騎乘車號ＩＱＩ─○五六之重機\n    車，致甲○○人車倒地，受有右側小指及右小腿擦挫傷等傷害。嗣經警方前往處\n    理，經對乙○○施以呼氣酒精濃度檢測，測得其呼氣酒精濃度高達每公升零點八\n    五毫克（涉犯公共危險罪嫌部分，業據本院於九十三年十月十四日以九十三年度\n    壢交簡字第一二一五號判處拘役二十日），因認被告涉犯刑法第二百八十四條第\n    一項前段過失傷害罪嫌云云。\n二、按告訴乃論之罪，告訴人於第一審辯論終結前得撤回其告訴，而告訴經撤回者，\n    應諭知不受理之判決，刑事訴訟法第二百三十八條第一項、第三百零三條第三款\n    定有明文。又刑事事件於偵查中或第一審言詞辯論終結前，調解成立，經法院核\n    定，並經當事人同意撤回者，視為於調解成立時撤回告訴或自訴，鄉鎮市調解條\n    例第二十五條第二項亦定有明文。\n三、查本件告訴人告訴被告於右述時、地駕車不慎與告訴人騎駛之機車擦撞致告訴人\n    倒地受傷之過失傷害案件，經檢察官聲請簡易判決處刑，認係犯刑法第二百八十\n    四條第一項前段之罪，依同法第二百八十七條前段之規定，須告訴乃論。茲據告\n    訴人與被告間已於九十三年七月二十八日經由桃園縣中壢市調解委員會調解成立\n    ，亦於九十三年八月二十三日經本院核定，有桃園縣中壢市調解委員會調解書影\n    本一份在卷可稽，並經本院依職權調閱本院九十三年度壢核字第一０五四號卷查\n    閱屬實，依前述規定，本件於調解成立時即九十三年七月二十八日視為撤回告訴\n    ，依照首開說明，爰不經言詞辯論，逕為不受理之論知。\n四、據上論斷，應依刑事訴訟法第四百五十二條、第三百零三條第三款、第三百零七\n    條，判決如主文。"
  },
  "search": "臺灣桃園地方法院刑事判決九十三年度交易字第三０三號聲請人台灣桃園地方法院檢察署檢察官被告乙○○男三.右被告因過失傷害案件，經檢察官聲請簡易判決處刑（九十三年度偵字第八七六五號），本院簡易庭認為不宜以簡易判決處刑，改依通常程序審理，茲判決如左：主文本件公訴不受理。理由一、聲請簡易判決處刑意旨略以：被告乙○○於民國九十三年五月十九日下午十三時三十分許，在桃園縣中壢市便利商店購買啤酒飲畢後，已達不能安全駕駛動力交通工具之程度，竟仍駕駛車牌號碼ＨＬ─四六七八號自用小客車，於同日下午二時二十分許，行經桃園縣中壢市龍岡圓環旁，倒車欲進入車道時，本應注意有無車輛經過，並應隨時採取必要之安全措施，而依當時情形，並無不能注意之情事，竟疏未注意，自後擦撞同向由告訴人甲○○所騎乘車號ＩＱＩ─○五六之重機車，致甲○○人車倒地，受有右側小指及右小腿擦挫傷等傷害。嗣經警方前往處理，經對乙○○施以呼氣酒精濃度檢測，測得其呼氣酒精濃度高達每公升零點八五毫克（涉犯公共危險罪嫌部分，業據本院於九十三年十月十四日以九十三年度壢交簡字第一二一五號判處拘役二十日），因認被告涉犯刑法第二百八十四條第一項前段過失傷害罪嫌云云。二、按告訴乃論之罪，告訴人於第一審辯論終結前得撤回其告訴，而告訴經撤回者，應諭知不受理之判決，刑事訴訟法第二百三十八條第一項、第三百零三條第三款定有明文。又刑事事件於偵查中或第一審言詞辯論終結前，調解成立，經法院核定，並經當事人同意撤回者，視為於調解成立時撤回告訴或自訴，鄉鎮市調解條例第二十五條第二項亦定有明文。三、查本件告訴人告訴被告於右述時、地駕車不慎與告訴人騎駛之機車擦撞致告訴人倒地受傷之過失傷害案件，經檢察官聲請簡易判決處刑，認係犯刑法第二百八十四條第一項前段之罪，依同法第二百八十七條前段之規定，須告訴乃論。茲據告訴人與被告間已於九十三年七月二十八日經由桃園縣中壢市調解委員會調解成立，亦於九十三年八月二十三日經本院核定，有桃園縣中壢市調解委員會調解書影本一份在卷可稽，並經本院依職權調閱本院九十三年度壢核字第一０五四號卷查閱屬實，依前述規定，本件於調解成立時即九十三年七月二十八日視為撤回告訴，依照首開說明，爰不經言詞辯論，逕為不受理之論知。四、據上論斷，應依刑事訴訟法第四百五十二條、第三百零三條第三款、第三百零七條，判決如主文。中華民國九十三年十一月三十日臺灣桃園地方法院刑事第一庭審判長法官曾淑華法官黃梅淑法官朱美璘右正本證明與原本無異。如不服本判決，應於送達後十日內，向本院提出上訴狀。書記官楊鳳滿中華民國九十三年十二月三日",
  "characters": {
    "judges": [
      "曾淑華",
      "黃梅淑",
      "朱美璘"
    ],
    "prosecutors": [

    ],
    "lawyers": [

    ],
    "clerks": [
      "楊鳳滿"
    ],
    "plaintiffs": [

    ],
    "defendants": [
      "乙○○  男  三.",
      "右被告因過失傷害案件，經檢察官聲請簡易判決處刑（九十三年度偵字第八七六五號",
      "），本院簡易庭認為不宜以簡易判決處刑，改依通常程序審理，茲判決如左："
    ],
    "prosecutor_office": [
      "台灣桃園地方法院檢察署檢察官"
    ],
    "creditors": [

    ],
    "debtors": [

    ],
    "judicial_associate_officer": [

    ]
  },
  "adjudged_at": "2004-11-30",
  "created_at": "2016-02-06 04:38:56",
  "updated_at": "2016-02-06 04:38:56"
}