{
  "identify": "KLD-100-基交簡-332-20110601-1",
  "court": {
    "name": "臺灣基隆地方法院",
    "code": "KLD"
  },
  "division": {
    "name": "刑事",
    "code": "M"
  },
  "year": 100,
  "word": "基交簡",
  "number": "332",
  "jcheck": "1",
  "reason": "公共危險",
  "content": "臺灣基隆地方法院刑事簡易判決      100年度基交簡字第332號\n聲  請  人  臺灣基隆地方法院檢察署檢察官\n被      告  吳松津\n上列被告因公共危險案件，經檢察官聲請以簡易判決處刑（100\n年度速偵字第232號），本院判決如下：\n    主  文\n吳松津犯不能安全駕駛動力交通工具罪，處罰金新臺幣壹拾萬元\n，如易服勞役，以新臺幣壹仟元折算壹日。\n    事實及理由\n一、本件犯罪事實、證據，均引用檢察官聲請簡易判決處刑書之\n    記載（如附件）。\n二、核被告吳松津所為，係犯刑法第185條之3不能安全駕駛動力\n    交通工具之公共危險罪。玆審酌被告於上揭時地飲酒，陷己\n    於不能安全駕駛動力交通工具之程度，仍於上開時地騎乘機\n    車，欲返回家中，因酒醉致駕車不慎摔倒等情狀，足認其完\n    全不會自我節制飲酒習性，執意酒後仍駕駛上開自用小客車\n    ，顯然嚴重漠視人己行車安全，並對用路大眾及自己之生命\n    、身體及財產造成危險，其亦欠深刻反性及考量家人擔心，\n    並考量被告素行、犯罪並考量被告素行、犯罪動機、手段、\n    對社會所生危害及犯後態度，並斟酌被告國小畢業，職業為\n    司機，家中經濟狀況不富，且無任何犯罪紀錄，有臺灣高等\n    法院被告前案紀錄表在卷可稽等情，亦有被告100 年5月2日\n    警詢筆錄在卷可佐，爰量處如主文所示之罰金刑，並諭知易\n    服勞役之折算標準，避免被告再犯，用啟自新。\n三、爰依刑事訴訟法第449條第1項前段、第3項、第454條第2 項\n    ，刑法第185條之3、第42條第3項前段，刑法施行法第1條之\n    1第1項、第2項後段，逕以簡易判決處如主文所示之刑。\n四、如不服本判決，應於收受本件簡易判決書之日起10日內，向\n    本院提出上訴書狀，敘述上訴理由，上訴於本院合議庭「切\n    勿逕送上級法院」。告訴人或被害人如本判決不服者，應具\n    備理由請求檢察官上訴，其上訴期間之計算係以檢察官收受\n    判決正本之日期為準。\n中    華    民    國    100    年     6    月    1    日\n                  基隆簡易庭法  官  施添寶\n以上正本證明與原本無異。\n如不服本判決，應於判決送達後10日內，向本院提出上訴書狀，\n敘述上訴理由，上訴於本院合議庭，並按他造當事人之人數附具\n繕本。\n中    華    民    國    100    年     6    月    1    日\n                            書記官  施鴻均\n附錄論罪科刑法條：\n中華民國刑法第一百八十五條之三\n服用毒品、麻醉藥品、酒類或其他相類之物，不能安全駕駛動力\n交通工具而駕駛者，處一年以下有期徒刑、拘役或科或併科十五\n萬元以下罰金。\n附件：\n臺灣基隆地方法院檢察署檢察官聲請簡易判決處刑書\n                                    100年度速偵字第232號\n    被      告  吳松津  男  59歲（民國○○年○月○日生）\n                        住基隆市中山區○○○路113巷2弄61\n                        號\n                        國民身分證統一編號：Ｚ000000000號\n上列被告因公共危險案件，業經偵查終結，認為宜聲請以簡易判\n決處刑，茲將犯罪事實及證據並所犯法條分敘如下：\n        犯罪事實\n一、吳松津於民國100年5月2日下午1時許，在基隆市中山區海聖\n    宮飲用2 杯藥酒後，已達不能安全駕駛動力交通工具之程度\n    ，猶於當日騎乘車牌號碼POS-787 號普通重型機車，自上開\n    處所出發，欲返回其位在基隆市中山區○○○路113巷2弄61\n    號住所。惟於當日下午2 時31分許，在行經基隆市中山區○\n    ○○路52巷底，因酒後注意力及操控力欠佳，不慎摔倒，因\n    而受有右臉擦傷之傷害。經警據報前往處理，並對其實施吐\n    氣酒精濃度測試，測得值達1.04MG/L，始查知上情。\n二、案經基隆市警察局第四分局報告偵辦。\n        證據並所犯法條\n一、訊之被告吳松津，除對於其酒後騎乘機車之事實自白不諱外\n    ，餘均矢口否認，辯稱：飲酒並不影響其駕車安全云云。經\n    查，本件被告吳松津經警對其實施吐氣酒精濃度測試，得值\n    為1.04MG/L，且又酒後不勝酒力摔倒受傷等情，此均有吐氣\n    酒精濃度測試單、刑法第185條之3案件測試觀察紀錄表、汽\n    機車駕駛人酒後生理協調平衡檢測紀錄表各1 份在卷可稽。\n    按刑法第185條之3規定之所謂「不能安全駕駛」，係抽象危\n    險犯，並不以發生具體危險為必要。而依醫學實驗證明所得\n    經驗法則，對於吐氣酒精濃度達0.25MG/L以上時，將使駕駛\n    人產生複雜之技巧障礙、駕駛能力變壞之行為表現，肇事比\n    率比一般未飲酒時高出2倍，而吐氣酒精濃度達每公升0.5MG\n    /L以上時，將使駕駛人產生平衡感與判斷力障礙升高，肇事\n    比率比一般未飲酒時高出10倍，甚而如吐氣酒精濃度達0.75\n    MG/L時，駕駛人將產生明顯酒醉、步履蹣跚之行為狀態，其\n    肇事比率比一般高25倍，達吐氣酒精濃度達每1.0MG/ L時，\n    將造成中度中毒，有步態不穩、噁心、嘔吐、精神混惑不清\n    狀態（參見蔡志中著，對飲酒不能安全駕駛之執法研究，司\n    法院第46期業務研究會講義）。本件被告吐氣酒精濃度既已\n    達1.04MG/L，依上開說明顯已達不能安全駕駛之程度，是被\n    告上開辯詞，顯係推諉卸責之詞，委無可採，被告涉犯公共\n    危險罪嫌，洵堪認定。\n二、核被告所為，係犯刑法第185條之3之公共危險罪嫌，請依法\n    論科。\n三、依刑事訴訟法第451條第1項聲請逕以簡易判決處刑。\n    此致\n臺灣基隆地方法院基隆簡易庭\n中    華    民    國   100    年    5     月    5     日\n                              檢察官  林  秋  田\n本件正本證明與原本無異\n中    華    民    國   100    年    5     月    17    日\n                              書記官  魯  婷  芳\n附錄參考法條\n中華民國刑法第185條之3\n服用毒品、麻醉藥品、酒類或其他相類之物，不能安全駕駛動力\n交通工具而駕駛者，處1年以下有期徒刑、拘役或3萬元以下罰金\n。\n本件係依刑事訴訟法簡易程序辦理，法院簡易庭得不傳喚被告、\n輔佐人、告訴人、告發人等出庭即以簡易判決處刑；被告、被害\n人、告訴人等對告訴乃論案件如已達成民事和解而要撤回告訴或\n對非告訴乃論案件認有受傳喚到庭陳述意見之必要時，請即另以\n書狀向簡易法庭陳述或請求傳訊。",
  "structure": {
    "main": "吳松津犯不能安全駕駛動力交通工具罪，處罰金新臺幣壹拾萬元\n，如易服勞役，以新臺幣壹仟元折算壹日。",
    "fact": "一、本件犯罪事實、證據，均引用檢察官聲請簡易判決處刑書之\n    記載（如附件）。\n二、核被告吳松津所為，係犯刑法第185條之3不能安全駕駛動力\n    交通工具之公共危險罪。玆審酌被告於上揭時地飲酒，陷己\n    於不能安全駕駛動力交通工具之程度，仍於上開時地騎乘機\n    車，欲返回家中，因酒醉致駕車不慎摔倒等情狀，足認其完\n    全不會自我節制飲酒習性，執意酒後仍駕駛上開自用小客車\n    ，顯然嚴重漠視人己行車安全，並對用路大眾及自己之生命\n    、身體及財產造成危險，其亦欠深刻反性及考量家人擔心，\n    並考量被告素行、犯罪並考量被告素行、犯罪動機、手段、\n    對社會所生危害及犯後態度，並斟酌被告國小畢業，職業為\n    司機，家中經濟狀況不富，且無任何犯罪紀錄，有臺灣高等\n    法院被告前案紀錄表在卷可稽等情，亦有被告100 年5月2日\n    警詢筆錄在卷可佐，爰量處如主文所示之罰金刑，並諭知易\n    服勞役之折算標準，避免被告再犯，用啟自新。\n三、爰依刑事訴訟法第449條第1項前段、第3項、第454條第2 項\n    ，刑法第185條之3、第42條第3項前段，刑法施行法第1條之\n    1第1項、第2項後段，逕以簡易判決處如主文所示之刑。\n四、如不服本判決，應於收受本件簡易判決書之日起10日內，向\n    本院提出上訴書狀，敘述上訴理由，上訴於本院合議庭「切\n    勿逕送上級法院」。告訴人或被害人如本判決不服者，應具\n    備理由請求檢察官上訴，其上訴期間之計算係以檢察官收受\n    判決正本之日期為準。",
    "reason": "一、本件犯罪事實、證據，均引用檢察官聲請簡易判決處刑書之\n    記載（如附件）。\n二、核被告吳松津所為，係犯刑法第185條之3不能安全駕駛動力\n    交通工具之公共危險罪。玆審酌被告於上揭時地飲酒，陷己\n    於不能安全駕駛動力交通工具之程度，仍於上開時地騎乘機\n    車，欲返回家中，因酒醉致駕車不慎摔倒等情狀，足認其完\n    全不會自我節制飲酒習性，執意酒後仍駕駛上開自用小客車\n    ，顯然嚴重漠視人己行車安全，並對用路大眾及自己之生命\n    、身體及財產造成危險，其亦欠深刻反性及考量家人擔心，\n    並考量被告素行、犯罪並考量被告素行、犯罪動機、手段、\n    對社會所生危害及犯後態度，並斟酌被告國小畢業，職業為\n    司機，家中經濟狀況不富，且無任何犯罪紀錄，有臺灣高等\n    法院被告前案紀錄表在卷可稽等情，亦有被告100 年5月2日\n    警詢筆錄在卷可佐，爰量處如主文所示之罰金刑，並諭知易\n    服勞役之折算標準，避免被告再犯，用啟自新。\n三、爰依刑事訴訟法第449條第1項前段、第3項、第454條第2 項\n    ，刑法第185條之3、第42條第3項前段，刑法施行法第1條之\n    1第1項、第2項後段，逕以簡易判決處如主文所示之刑。\n四、如不服本判決，應於收受本件簡易判決書之日起10日內，向\n    本院提出上訴書狀，敘述上訴理由，上訴於本院合議庭「切\n    勿逕送上級法院」。告訴人或被害人如本判決不服者，應具\n    備理由請求檢察官上訴，其上訴期間之計算係以檢察官收受\n    判決正本之日期為準。"
  },
  "search": "臺灣基隆地方法院刑事簡易判決100年度基交簡字第332號聲請人臺灣基隆地方法院檢察署檢察官被告吳松津上列被告因公共危險案件，經檢察官聲請以簡易判決處刑（100年度速偵字第232號），本院判決如下：主文吳松津犯不能安全駕駛動力交通工具罪，處罰金新臺幣壹拾萬元，如易服勞役，以新臺幣壹仟元折算壹日。事實及理由一、本件犯罪事實、證據，均引用檢察官聲請簡易判決處刑書之記載（如附件）。二、核被告吳松津所為，係犯刑法第185條之3不能安全駕駛動力交通工具之公共危險罪。玆審酌被告於上揭時地飲酒，陷己於不能安全駕駛動力交通工具之程度，仍於上開時地騎乘機車，欲返回家中，因酒醉致駕車不慎摔倒等情狀，足認其完全不會自我節制飲酒習性，執意酒後仍駕駛上開自用小客車，顯然嚴重漠視人己行車安全，並對用路大眾及自己之生命、身體及財產造成危險，其亦欠深刻反性及考量家人擔心，並考量被告素行、犯罪並考量被告素行、犯罪動機、手段、對社會所生危害及犯後態度，並斟酌被告國小畢業，職業為司機，家中經濟狀況不富，且無任何犯罪紀錄，有臺灣高等法院被告前案紀錄表在卷可稽等情，亦有被告100年5月2日警詢筆錄在卷可佐，爰量處如主文所示之罰金刑，並諭知易服勞役之折算標準，避免被告再犯，用啟自新。三、爰依刑事訴訟法第449條第1項前段、第3項、第454條第2項，刑法第185條之3、第42條第3項前段，刑法施行法第1條之1第1項、第2項後段，逕以簡易判決處如主文所示之刑。四、如不服本判決，應於收受本件簡易判決書之日起10日內，向本院提出上訴書狀，敘述上訴理由，上訴於本院合議庭「切勿逕送上級法院」。告訴人或被害人如本判決不服者，應具備理由請求檢察官上訴，其上訴期間之計算係以檢察官收受判決正本之日期為準。中華民國100年6月1日基隆簡易庭法官施添寶以上正本證明與原本無異。如不服本判決，應於判決送達後10日內，向本院提出上訴書狀，敘述上訴理由，上訴於本院合議庭，並按他造當事人之人數附具繕本。中華民國100年6月1日書記官施鴻均附錄論罪科刑法條：中華民國刑法第一百八十五條之三服用毒品、麻醉藥品、酒類或其他相類之物，不能安全駕駛動力交通工具而駕駛者，處一年以下有期徒刑、拘役或科或併科十五萬元以下罰金。附件：臺灣基隆地方法院檢察署檢察官聲請簡易判決處刑書100年度速偵字第232號被告吳松津男59歲（民國○○年○月○日生）住基隆市中山區○○○路113巷2弄61號國民身分證統一編號：Ｚ000000000號上列被告因公共危險案件，業經偵查終結，認為宜聲請以簡易判決處刑，茲將犯罪事實及證據並所犯法條分敘如下：犯罪事實一、吳松津於民國100年5月2日下午1時許，在基隆市中山區海聖宮飲用2杯藥酒後，已達不能安全駕駛動力交通工具之程度，猶於當日騎乘車牌號碼POS-787號普通重型機車，自上開處所出發，欲返回其位在基隆市中山區○○○路113巷2弄61號住所。惟於當日下午2時31分許，在行經基隆市中山區○○○路52巷底，因酒後注意力及操控力欠佳，不慎摔倒，因而受有右臉擦傷之傷害。經警據報前往處理，並對其實施吐氣酒精濃度測試，測得值達1.04MG/L，始查知上情。二、案經基隆市警察局第四分局報告偵辦。證據並所犯法條一、訊之被告吳松津，除對於其酒後騎乘機車之事實自白不諱外，餘均矢口否認，辯稱：飲酒並不影響其駕車安全云云。經查，本件被告吳松津經警對其實施吐氣酒精濃度測試，得值為1.04MG/L，且又酒後不勝酒力摔倒受傷等情，此均有吐氣酒精濃度測試單、刑法第185條之3案件測試觀察紀錄表、汽機車駕駛人酒後生理協調平衡檢測紀錄表各1份在卷可稽。按刑法第185條之3規定之所謂「不能安全駕駛」，係抽象危險犯，並不以發生具體危險為必要。而依醫學實驗證明所得經驗法則，對於吐氣酒精濃度達0.25MG/L以上時，將使駕駛人產生複雜之技巧障礙、駕駛能力變壞之行為表現，肇事比率比一般未飲酒時高出2倍，而吐氣酒精濃度達每公升0.5MG/L以上時，將使駕駛人產生平衡感與判斷力障礙升高，肇事比率比一般未飲酒時高出10倍，甚而如吐氣酒精濃度達0.75MG/L時，駕駛人將產生明顯酒醉、步履蹣跚之行為狀態，其肇事比率比一般高25倍，達吐氣酒精濃度達每1.0MG/L時，將造成中度中毒，有步態不穩、噁心、嘔吐、精神混惑不清狀態（參見蔡志中著，對飲酒不能安全駕駛之執法研究，司法院第46期業務研究會講義）。本件被告吐氣酒精濃度既已達1.04MG/L，依上開說明顯已達不能安全駕駛之程度，是被告上開辯詞，顯係推諉卸責之詞，委無可採，被告涉犯公共危險罪嫌，洵堪認定。二、核被告所為，係犯刑法第185條之3之公共危險罪嫌，請依法論科。三、依刑事訴訟法第451條第1項聲請逕以簡易判決處刑。此致臺灣基隆地方法院基隆簡易庭中華民國100年5月5日檢察官林秋田本件正本證明與原本無異中華民國100年5月17日書記官魯婷芳附錄參考法條中華民國刑法第185條之3服用毒品、麻醉藥品、酒類或其他相類之物，不能安全駕駛動力交通工具而駕駛者，處1年以下有期徒刑、拘役或3萬元以下罰金。本件係依刑事訴訟法簡易程序辦理，法院簡易庭得不傳喚被告、輔佐人、告訴人、告發人等出庭即以簡易判決處刑；被告、被害人、告訴人等對告訴乃論案件如已達成民事和解而要撤回告訴或對非告訴乃論案件認有受傳喚到庭陳述意見之必要時，請即另以書狀向簡易法庭陳述或請求傳訊。",
  "characters": {
    "judges": [
      "施添寶"
    ],
    "prosecutors": [

    ],
    "lawyers": [

    ],
    "clerks": [
      "施鴻均",
      "魯婷芳"
    ],
    "plaintiffs": [

    ],
    "defendants": [
      "吳松津",
      "吳松津  男  59歲（民國○○年○月○日生）"
    ],
    "prosecutor_office": [
      "臺灣基隆地方法院檢察署檢察官"
    ],
    "creditors": [

    ],
    "debtors": [

    ],
    "judicial_associate_officer": [

    ]
  },
  "adjudged_at": "2011-06-01",
  "created_at": "2016-02-12 01:25:02",
  "updated_at": "2016-02-12 01:25:02"
}