{
  "identify": "KSD-100-交簡-2291-20110531-1",
  "court": {
    "name": "臺灣高雄地方法院",
    "code": "KSD"
  },
  "division": {
    "name": "刑事",
    "code": "M"
  },
  "year": 100,
  "word": "交簡",
  "number": "2291",
  "jcheck": "1",
  "reason": "公共危險",
  "content": "臺灣高雄地方法院刑事簡易判決       100年度交簡字第2291號\n聲  請  人  臺灣高雄地方法院檢察署檢察官\n被      告  洪誠駿\n上列被告因公共危險案件，經檢察官聲請簡易判決處刑（100 年\n度偵字第12536 號），本院判決如下：\n    主  文\n洪誠駿犯不能安全駕駛動力交通工具罪，處有期徒刑月，如易\n科罰金，以新臺幣壹仟元折算壹日。\n    事實及理由\n一、本件犯罪事實及證據，除證據並所犯法條欄一、「被告洪誠\n    駿警詢及偵查中之供述」應更正為「被告洪誠駿於警詢及偵\n    查中之自白」外，餘均引用檢察官聲請簡易判決處刑書之記\n    載（如附件）。\n二、核被告洪誠駿所為，係犯刑法第185 條之3 之不能安全駕駛\n    動力交通工具罪。爰審酌被告於飲酒後，已無法安全駕駛之\n    情形下，貿然騎乘機車上路並自摔，而被告經醫院抽取血液\n    檢驗，測得其血液中酒精濃度為172.24mg/dl ，換算為呼氣\n    所含酒精濃度達每公升0.86毫克，本已屬不該，雖犯後坦承\n    犯行，惟其於民國99年間，即曾因不能安全駕駛案件，經本\n    院判處拘役59日確定，有臺灣高等法院被告前案紀錄表1 份\n    在卷可憑，竟不知悔改警惕，此次再犯，足見其無視於其他\n    參與道路交通之不特定人生命、身體及財產安全，所為非是\n    ，暨其犯罪動機、目的及造成之危險等一切情狀，量處如主\n    文所示之刑，並諭知易科罰金之折算標準。\n三、應依刑事訴訟法第449 條第1 項前段、第3 項、第454 條第\n    2 項，刑法第185 條之3 、第41條第1 項前段，刑法施行法\n    第1條 之1 第1 項，逕以簡易判決處如主文所示之刑。\n四、如不服本判決，得自收受送達之日起10日內，向本院提起上\n    訴。\n中    華    民    國   100    年     5    月    31    日\n                  高雄簡易庭    法  官  王榆富\n以上正本，係照原本作成，證明與原本無異。\n如不服本判決，應於判決送達之日起10日內向本院提出上訴書狀\n。\n中    華    民    國  100     年    5     月    31    日\n                                書記官  鄭裕一\n附錄本判決論罪之法條：\n刑法第185條之3\n服用毒品、麻醉藥品、酒類或其他相類之物，不能安全駕駛動力\n交通工具而駕駛者，處1年以下有期徒刑、拘役或科或併科15 萬\n元以下罰金。\n附件：\n臺灣高雄地方法院檢察署檢察官聲請簡易判決處刑書\n                                    100年度偵字第12536號\n    被      告  洪誠駿  男  37歲（民國○○年○月○○日生）\n                        住高雄市路○區○○街132巷22號\n                        國民身分證統一編號：Ｚ000000000號\n上被告因公共危險案件，已經偵查終結，認為宜以簡易判決處刑\n，茲將犯罪事實及證據並所犯法條分述如下：\n        犯罪事實\n一、洪誠駿曾因酒後駕車觸犯公共危險，經臺灣高雄地方法院以\n    98年度審交簡字第5479號判處拘役59日確定（尚未執行完畢\n    ）。詎其不知悔改，明知酒後駕車易生危險，於民國99年8\n    月3日飲用高粱酒，已達不能安全駕駛動力交通工具之程度\n    後，仍於同日18時15分之前某時許，騎乘車號GH8-075號機\n    車，自高雄市岡山區空軍官校附近某處起駛，途經岡山區○\n    ○路580號前，因酒後注意力及操控車輛之能力顯然減弱，\n    不慎摔倒在地，經警到場處理本件交通事故，將其送醫救治\n    ，並委託劉光雄醫院抽血測得其血液中酒精濃度為每100毫\n    升血液含172.24毫克酒精，換算為呼氣酒精濃度達每公升\n    0.86毫克。\n二、案經高雄市政府警察局岡山分局報告偵辦。\n        證據並所犯法條\n一、證據清單：\n  (1)被告洪誠駿警詢及偵查中之供述。\n  (2)高雄縣（現以改制為高雄市）政府警察局交通警察隊岡山分\n    隊委託醫院實施血液中酒精濃度檢驗報告1紙。\n  (3)刑法第一百八十五條之三案件觀察紀錄表1紙。\n  (4)道路交通事故現場圖1紙。\n  (5)道路交通事故調查報告表(一)、(二)各1紙。\n  (6)現場採證照片11張。\n  (7)高雄縣（現已改制為高雄市）政府警察局舉發違反道路交通\n    管理事件通知單影本1紙。\n二、核被告所為，係犯刑法第185條之3之公共危險罪嫌。\n三、依刑事訴訟法第451條第1項聲請逕以簡易判決處刑。\n    此  致\n臺灣高雄地方法院\n中    華    民    國   100    年    5     月    4     日\n                              檢  察  官   游淑玟\n上正本證明與原本無異\n中    華    民    國   100    年    5     月    11    日\n                              書  記  官   楊文玲\n所犯法條：\n中華民國刑法第185條之3\n服用毒品、麻醉藥品、酒類或其他相類之物，不能安全駕駛動力\n交通工具而駕駛者，處 1 年以下有期徒刑、拘役或科或併科 15\n萬元以下罰金。",
  "structure": {
    "main": "洪誠駿犯不能安全駕駛動力交通工具罪，處有期徒刑月，如易\n科罰金，以新臺幣壹仟元折算壹日。",
    "fact": "一、本件犯罪事實及證據，除證據並所犯法條欄一、「被告洪誠\n    駿警詢及偵查中之供述」應更正為「被告洪誠駿於警詢及偵\n    查中之自白」外，餘均引用檢察官聲請簡易判決處刑書之記\n    載（如附件）。\n二、核被告洪誠駿所為，係犯刑法第185 條之3 之不能安全駕駛\n    動力交通工具罪。爰審酌被告於飲酒後，已無法安全駕駛之\n    情形下，貿然騎乘機車上路並自摔，而被告經醫院抽取血液\n    檢驗，測得其血液中酒精濃度為172.24mg/dl ，換算為呼氣\n    所含酒精濃度達每公升0.86毫克，本已屬不該，雖犯後坦承\n    犯行，惟其於民國99年間，即曾因不能安全駕駛案件，經本\n    院判處拘役59日確定，有臺灣高等法院被告前案紀錄表1 份\n    在卷可憑，竟不知悔改警惕，此次再犯，足見其無視於其他\n    參與道路交通之不特定人生命、身體及財產安全，所為非是\n    ，暨其犯罪動機、目的及造成之危險等一切情狀，量處如主\n    文所示之刑，並諭知易科罰金之折算標準。\n三、應依刑事訴訟法第449 條第1 項前段、第3 項、第454 條第\n    2 項，刑法第185 條之3 、第41條第1 項前段，刑法施行法\n    第1條 之1 第1 項，逕以簡易判決處如主文所示之刑。\n四、如不服本判決，得自收受送達之日起10日內，向本院提起上\n    訴。",
    "reason": "一、本件犯罪事實及證據，除證據並所犯法條欄一、「被告洪誠\n    駿警詢及偵查中之供述」應更正為「被告洪誠駿於警詢及偵\n    查中之自白」外，餘均引用檢察官聲請簡易判決處刑書之記\n    載（如附件）。\n二、核被告洪誠駿所為，係犯刑法第185 條之3 之不能安全駕駛\n    動力交通工具罪。爰審酌被告於飲酒後，已無法安全駕駛之\n    情形下，貿然騎乘機車上路並自摔，而被告經醫院抽取血液\n    檢驗，測得其血液中酒精濃度為172.24mg/dl ，換算為呼氣\n    所含酒精濃度達每公升0.86毫克，本已屬不該，雖犯後坦承\n    犯行，惟其於民國99年間，即曾因不能安全駕駛案件，經本\n    院判處拘役59日確定，有臺灣高等法院被告前案紀錄表1 份\n    在卷可憑，竟不知悔改警惕，此次再犯，足見其無視於其他\n    參與道路交通之不特定人生命、身體及財產安全，所為非是\n    ，暨其犯罪動機、目的及造成之危險等一切情狀，量處如主\n    文所示之刑，並諭知易科罰金之折算標準。\n三、應依刑事訴訟法第449 條第1 項前段、第3 項、第454 條第\n    2 項，刑法第185 條之3 、第41條第1 項前段，刑法施行法\n    第1條 之1 第1 項，逕以簡易判決處如主文所示之刑。\n四、如不服本判決，得自收受送達之日起10日內，向本院提起上\n    訴。"
  },
  "search": "臺灣高雄地方法院刑事簡易判決100年度交簡字第2291號聲請人臺灣高雄地方法院檢察署檢察官被告洪誠駿上列被告因公共危險案件，經檢察官聲請簡易判決處刑（100年度偵字第12536號），本院判決如下：主文洪誠駿犯不能安全駕駛動力交通工具罪，處有期徒刑月，如易科罰金，以新臺幣壹仟元折算壹日。事實及理由一、本件犯罪事實及證據，除證據並所犯法條欄一、「被告洪誠駿警詢及偵查中之供述」應更正為「被告洪誠駿於警詢及偵查中之自白」外，餘均引用檢察官聲請簡易判決處刑書之記載（如附件）。二、核被告洪誠駿所為，係犯刑法第185條之3之不能安全駕駛動力交通工具罪。爰審酌被告於飲酒後，已無法安全駕駛之情形下，貿然騎乘機車上路並自摔，而被告經醫院抽取血液檢驗，測得其血液中酒精濃度為172.24mg/dl，換算為呼氣所含酒精濃度達每公升0.86毫克，本已屬不該，雖犯後坦承犯行，惟其於民國99年間，即曾因不能安全駕駛案件，經本院判處拘役59日確定，有臺灣高等法院被告前案紀錄表1份在卷可憑，竟不知悔改警惕，此次再犯，足見其無視於其他參與道路交通之不特定人生命、身體及財產安全，所為非是，暨其犯罪動機、目的及造成之危險等一切情狀，量處如主文所示之刑，並諭知易科罰金之折算標準。三、應依刑事訴訟法第449條第1項前段、第3項、第454條第2項，刑法第185條之3、第41條第1項前段，刑法施行法第1條之1第1項，逕以簡易判決處如主文所示之刑。四、如不服本判決，得自收受送達之日起10日內，向本院提起上訴。中華民國100年5月31日高雄簡易庭法官王榆富以上正本，係照原本作成，證明與原本無異。如不服本判決，應於判決送達之日起10日內向本院提出上訴書狀。中華民國100年5月31日書記官鄭裕一附錄本判決論罪之法條：刑法第185條之3服用毒品、麻醉藥品、酒類或其他相類之物，不能安全駕駛動力交通工具而駕駛者，處1年以下有期徒刑、拘役或科或併科15萬元以下罰金。附件：臺灣高雄地方法院檢察署檢察官聲請簡易判決處刑書100年度偵字第12536號被告洪誠駿男37歲（民國○○年○月○○日生）住高雄市路○區○○街132巷22號國民身分證統一編號：Ｚ000000000號上被告因公共危險案件，已經偵查終結，認為宜以簡易判決處刑，茲將犯罪事實及證據並所犯法條分述如下：犯罪事實一、洪誠駿曾因酒後駕車觸犯公共危險，經臺灣高雄地方法院以98年度審交簡字第5479號判處拘役59日確定（尚未執行完畢）。詎其不知悔改，明知酒後駕車易生危險，於民國99年8月3日飲用高粱酒，已達不能安全駕駛動力交通工具之程度後，仍於同日18時15分之前某時許，騎乘車號GH8-075號機車，自高雄市岡山區空軍官校附近某處起駛，途經岡山區○○路580號前，因酒後注意力及操控車輛之能力顯然減弱，不慎摔倒在地，經警到場處理本件交通事故，將其送醫救治，並委託劉光雄醫院抽血測得其血液中酒精濃度為每100毫升血液含172.24毫克酒精，換算為呼氣酒精濃度達每公升0.86毫克。二、案經高雄市政府警察局岡山分局報告偵辦。證據並所犯法條一、證據清單：(1)被告洪誠駿警詢及偵查中之供述。(2)高雄縣（現以改制為高雄市）政府警察局交通警察隊岡山分隊委託醫院實施血液中酒精濃度檢驗報告1紙。(3)刑法第一百八十五條之三案件觀察紀錄表1紙。(4)道路交通事故現場圖1紙。(5)道路交通事故調查報告表(一)、(二)各1紙。(6)現場採證照片11張。(7)高雄縣（現已改制為高雄市）政府警察局舉發違反道路交通管理事件通知單影本1紙。二、核被告所為，係犯刑法第185條之3之公共危險罪嫌。三、依刑事訴訟法第451條第1項聲請逕以簡易判決處刑。此致臺灣高雄地方法院中華民國100年5月4日檢察官游淑玟上正本證明與原本無異中華民國100年5月11日書記官楊文玲所犯法條：中華民國刑法第185條之3服用毒品、麻醉藥品、酒類或其他相類之物，不能安全駕駛動力交通工具而駕駛者，處1年以下有期徒刑、拘役或科或併科15萬元以下罰金。",
  "characters": {
    "judges": [
      "王榆富"
    ],
    "prosecutors": [

    ],
    "lawyers": [

    ],
    "clerks": [
      "鄭裕一"
    ],
    "plaintiffs": [

    ],
    "defendants": [
      "洪誠駿",
      "洪誠駿  男  37歲（民國○○年○月○○日生）"
    ],
    "prosecutor_office": [
      "臺灣高雄地方法院檢察署檢察官"
    ],
    "creditors": [

    ],
    "debtors": [

    ],
    "judicial_associate_officer": [

    ]
  },
  "adjudged_at": "2011-05-31",
  "created_at": "2016-02-12 01:16:17",
  "updated_at": "2016-02-12 01:16:17"
}