{
  "identify": "KSD-100-選訴-29-20110531-1",
  "court": {
    "name": "臺灣高雄地方法院",
    "code": "KSD"
  },
  "division": {
    "name": "刑事",
    "code": "M"
  },
  "year": 100,
  "word": "選訴",
  "number": "29",
  "jcheck": "1",
  "reason": "違反公職人員選舉罷免法",
  "content": "臺灣高雄地方法院刑事判決             100年度選訴字第29號\n公  訴  人  臺灣高雄地方法院檢察署檢察官\n被      告  李珈璜\n選任辯護人  鄭國安律師\n            吳麗珠律師\n            郭宗塘律師\n上列被告因違反公職人員選舉罷免法案件，經檢察官提起公訴（\n99年度選偵字第130號、第374號、第46號），本院判決如下：\n    主  文\n李珈璜犯公職人員選舉罷免法第九十九條第一項之行求賄賂罪，\n處有期徒刑肆年，併科罰金新臺幣壹佰萬元，罰金如易服勞役，\n以新臺幣仟元折算壹日。褫奪公權肆年。交付之賄賂現金新臺\n幣捌仟元，未扣案用以行求賄賂之現金新臺幣捌仟元均沒收。\n    事  實\n一、李珈璜為使不知情之高雄縣市合併後第1 屆高雄市新興區浩\n    然里里長候選人即其妻李許美曄（另為不起訴處分）與所支\n    持之第1 屆第8 選區市議員候選人即不知情之許崑源均能順\n    利當選，竟基於對有投票權人行求、交付賄賂而約其投票權\n    為一定行使之犯意，欲以每票新臺幣（下同）1000元之對價\n    買受有投票權人之選票，要求受賄人之投票權為投票給李許\n    美曄、許崑源之一定行使，而接續為下列行為：\n（一）於民國99年9 月底某日下午5 、6 時許，到設籍在浩然里\n      有投票權之A2住處（真實姓名、年籍、地址均詳密封卷）\n      行求賄賂，並問明可支持許崑源之票數後，要求A2於99年\n      11月27日該屆市議員選舉，投票給許崑源。嗣於行求後欲\n      交付1000元賄款給A2時，遭A2拒絕。\n（二）於99年9 月底某日上午9 時許，在高雄市新興區國民市○\n      ○○路口紅綠燈處，向設籍在浩然里有投票權之A3（真實\n      姓名、年籍、地址均詳密封卷）行求賄賂，並問明可支持\n      李許美曄之票數後，要求A3於99年11月27日該屆里長選舉\n      ，投票給李許美曄。嗣於行求後欲交付2000元賄款給A2時\n      ，遭A2拒絕。\n（三）於99年10月中旬某日中午12時許，到設籍在浩然里有投票\n      權之A6所經營之麵店（真實姓名、年籍、地址、店名均詳\n      密封卷）對A6說「拜託一下」後，趁A6忙於店務無暇之際\n      ，放置5000元在該店櫃臺上，以此方式行求賄賂A6於99年\n      11月27日該屆里長選舉，投票給李許美曄。後A6不願受賄\n      而將該5000元退還給李珈璜。\n（四）於99年10月份某日接近中午某時許，到設籍在浩然里有投\n      票權之A7住處（真實姓名、年籍、地址均詳密封卷）行求\n      賄賂，並問明可支持李許美曄之票數後，要求A7於99年11\n      月27日該屆里長選舉，投票給李許美曄，嗣於行求後交付\n      1000元賄款給A7，另將1000元託付A7，約定由其轉達該款\n      項暨上揭投票行賄之旨予戶內另1 名有投票權家人。A7（\n      業經檢察官為不起訴處分確定）明知李珈璜所交付之現金\n      係賄選之對價，仍基於有投票權人，而許以其投票權為一\n      定行使之犯意，當場收下（賄款2000元業經扣案）。\n（五）於99年8 、9 月份某日中午某時許，到設籍在浩然里有投\n      票權之洪陳滿鄭住處行求賄賂，並問明可支持李許美曄之\n      票數後，要求洪陳滿鄭於99年11月27日該屆里長選舉，投\n      票給李許美曄，嗣於行求後交付1000元賄款給洪陳滿鄭，\n      另將5000元託付洪陳滿鄭，約定由其轉達該款項暨上揭投\n      票行賄之旨予戶內另5 名有投票權家人。洪陳滿鄭（業經\n      檢察官為不起訴處分確定）明知李珈璜所交付之現金係賄\n      選之對價，仍基於有投票權人，而許以其投票權為一定行\n      使之犯意，當場收下（賄款6000元業經扣案）。\n    嗣A7、洪陳滿鄭尚未轉告及將款項轉交其2 人具有投票權之\n    家人前，即經警接獲情資循線查獲，並分別扣得洪陳滿鄭、\n    A7所收受之賄款6000元、2000元。\n二、案經高雄市政府警察局苓雅分局移送臺灣高雄地方法院檢察\n    署檢察官偵查起訴。\n    理  由\n一、證據能力：\n（一）按被告以外之人於審判外之言詞或書面陳述，除法律有規\n      定外，不得作為證據；被告以外之人於檢察事務官、司法\n      警察官或司法警察調查中所為之陳述，與審判中不符時，\n      其先前之陳述具有較可信之特別情況，且為證明犯罪事實\n      存否所必要，得為證據，刑事訴訟法第159 條第1 項、第\n      159 條之2 分別定有明文。是被告以外之人於審判外之言\n      詞或書面，即屬傳聞證據，因有悖法院直接審理及言詞審\n      理之精神，妨礙當事人之反對詰問權，影響程序正義之實\n      現，除法律別有規定外，原則上不具證據能力，必符合上\n      開例外規定時，始具有證據能力。刑事訴訟法第159 條之\n      2 所謂「前後陳述不符」之要件，應就前後階段之陳述進\n      行整體判斷，以決定其間是否具有實質性差異，而所謂「\n      較可信之特別情況」，亦應就前後陳述時之各種外部情況\n      進行比較，以資決定何者外部情況具有可信性，若陳述係\n      在特別可信之情況下所為，則虛偽陳述之危險性不高，雖\n      係審判外陳述，或未經被告反對詰問，仍得承認其有證據\n      能力。就外部情況之認定，例如時間之間隔、是否為有意\n      識之迴避、有無受外力干擾或事後串謀、以及警詢所作時\n      之筆錄記載是否完整、是否出於自由意識陳述等情。法院\n      應斟酌上列因素綜合判斷，細究陳述人問答態度、表情與\n      舉動之變化，以查是否具較可信之特別情況。經查，證人\n      A2、A3、A6、A7、洪陳滿鄭於警詢時之陳述，就被告李珈\n      璜交付金錢之目的，是否曾經行求賄賂其等投票給李許美\n      曄、許崑源等與案情有重要關係之事項，明顯與其等在本\n      院審理時之陳述情節有異（見警卷第23-24 、32-34 、42\n      -47 頁、本院卷第42-60 、103-117 、130-137 頁）。而\n      證人A2等人於接受員警詢問時，詢問筆錄之記載採取一問\n      一答之方式，於本院審理中到庭作證時，未曾反映其警詢\n      筆錄係遭受不正方法訊問而為陳述，堪認員警製作證人A2\n      等人之警詢筆錄時，係依法定程序為之，並無違法取供之\n      情事，其等陳述之信用性已受保障。再衡諸證人A2等人於\n      警詢時之陳述較接近案發時點，並於陳述當時未直接面對\n      被告，心情較為篤定，壓力較小，較有可能為任意陳述，\n      憑信性甚高，經考量其等於審判外及審判中陳述之外部附\n      隨環境及條件，應認其等先前之陳述具有較可信之特別情\n      況，且與本件待證事實間具有相當之關聯性及必要性，符\n      合刑事訴訟法第159 條之2 規定，自有證據能力。\n（二）按被告以外之人於偵查中向檢察官所為之陳述，除顯有不\n      可信之情況者外，得為證據，刑事訴訟法第159 條之1 第\n      2 項亦有明文。而所謂「顯有不可信性」係指陳述是否出\n      於供述者之真意、有無違法取供情事之信用性而言，故應\n      就偵查筆錄製作之原因、過程及其功能等項加以綜合觀察\n      ，據以判斷該傳聞證據是否「非顯不可信」，倘可據以認\n      定其任意性暨信用性俱無疑慮者，即可例外賦予「證據能\n      力」，俾其成為法院審判時之適格證據資料而言。再按刑\n      事訴訟法第166 條以下規定之交互詰問，屬人證調查證據\n      程序之一環，與證據能力係指符合法律規定之證據適格，\n      亦即得成為證明犯罪事實存否之證據適格，其性質及在證\n      據法則之層次並非相同，而被告、辯護人詰問權之行使與\n      否，係有權處分，如欲行使，則證人於審判中，應依法定\n      程序到庭具結陳述，並接受被告或辯護人等之詰問，其陳\n      述始得作為認定被告犯罪事判斷之依據（參照司法院釋字\n      第582 號解釋），否則如未進行交互詰問之調查證據程序\n      ，讓被告或辯護人行使詰問權，則該有證據能力之證人陳\n      述，即不得作為判斷之依據，惟其原有之證據能力並不因\n      而喪失（最高法院97年度臺上字第603 號判決可資參酌）\n      。經查，證人A2等人於偵查中所為之陳述，對被告而言，\n      固均屬被告以外之人於審判外之言詞陳述，然證人A2等人\n      於偵查中所為之陳述，均為親身經歷事項，又係經檢察官\n      告以拒絕證言權、具結之義務及偽證罪之處罰後，再命其\n      等朗讀結文並具結後所為之陳述，有上開證人之結文在卷\n      可稽。核其等製作筆錄過程，並無違法取供或證明力明顯\n      過低之瑕疵，復有全程錄音錄影可資憑信，所為陳述蓋係\n      出於供述者之真意，皆具信用性，揆諸上開說明，本屬有\n      證據能力之證人陳述。且於本院審理時，已依人證調查程\n      序，傳喚證人A2等人到場，命其等立於證人之地位經檢察\n      官、被告及渠辯護人當庭交互詰問，並使被告有與之對質\n      及詰問之機會，而證人A2等人偵訊之證言亦使被告、辯護\n      人加以辯論，認均已完足為合法調查之證據，自得採為判\n      決之基礎。綜上，以上開證人A2等人於偵查中經具結後所\n      為陳述作為證據，並無任何不當，依同法第159 條之1第2\n      項之規定，認具有證據能力。\n（三）本判決後開所引用之其他被告以外之人於審判外之陳述（\n      包括書面陳述），雖均屬傳聞證據，惟業經被告、辯護人\n      及檢察官於審理期日時均表示無意見而不予爭執，且迄至\n      言詞辯論終結前亦均未聲明異議，本院審酌上開證據資料\n      製作時之情況，尚查無違法不當之瑕疵，亦認為以之作為\n      證據應屬適當，故逕依刑事訴訟法第159 條之5 規定，認\n      上揭證據資料均例外有證據能力。\n二、訊據被告矢口否認為本件犯行，辯稱：本件是選舉恩怨，伊\n    未行求、交付賄款給證人A2、A3、A6、A7、洪陳滿鄭等人云\n    云，經查：\n（一）被告之妻李許美曄為高雄市新興區第1 屆里長候選人；許\n      崑源則為高雄市第1 屆第8 選區市議員選舉候選人（投票\n      日均為99年11月27日），被告於該次選舉分別為李許美曄\n      拉票及支持許崑源；又被告、證人A2、A3、A6、A7、洪陳\n      滿鄭等人於上開選舉期間內，均設籍於浩然里，係該屆浩\n      然里里長及第8 選區市議員選舉之有投票權人；另被告曾\n      任浩然里里長，證人A2、A3、A6、A7、洪陳滿鄭等人係該\n      里里民，彼此間均相識等情，業據證人李許美曄、A2、A3\n      、A6、A7、洪陳滿鄭等人陳述在卷（見警卷第23-24 、32\n      -34 、42-47 頁，偵卷一第25-27 、30-32 、43-45 、53\n      -55 頁，偵卷二第71-73 頁），且為被告所不爭（見本院\n      卷第13頁），並有高雄市選舉委員會100 年3 月29日高市\n      選一字第1000000584號函暨所附99年直轄市里長選舉候選\n      人登記冊（一）、高雄市新興區第1 屆里長選舉候選人登\n      記冊（當日）、領表名冊、高雄市第1 屆議員選舉第8 選\n      舉區候選人登記申請調查表、請領登記表明冊（見本院卷\n      第69 -74頁）、真實姓名與代號對照表、戶籍查詢資料（\n      見密封卷）在卷可憑，並經本院調取高雄市第1 屆市長、\n      議員暨里長選舉之選舉人名冊核閱無誤，是此部分事實，\n      均可認定。\n（二）1.證人A2於警詢及偵訊時稱：「於99年9 月底某日下午5\n      、6 時許，被告至我家聊天、拜票，向我說他支持許崑源\n      ，問我家裡有幾個人，我說只有我自己可以支持他，其他\n      人的票不是我能作主。他聽完後就從他褲子的口袋要拿出\n      1000元塞給我，但是我沒有收他的錢，因為我心裡知道這\n      1000元是他要向我買票的錢，所以我不敢收，後來李珈璜\n      看我不收他的錢後，他就把1000元拿回去，然後說他還有\n      事情要處理就先走了。被告拿錢給我應該是要我投票給許\n      崑源。被告也曾拿許崑源的競選文宣來我家，跟我表明他\n      是支持許崑源的。」等語（見警卷第42-43 頁，偵卷一第\n      25 -27頁）；2.證人A3於警詢、偵訊及審理時稱：「於99\n      年9 月底某日上午9 時許，在高雄市新興區國民市○○○\n      路口紅綠燈處，我剛好遇上被告，他手裡拿出1 張競選文\n      宣，要我支持他老婆參選里長，然後就拿出2000元要給我\n      ，說我家有2 票（我1 票，我兒子1 票）。我當時對李珈\n      璜說我會投給李許美曄啦，我不要收你的錢，然後我就趕\n      快離開了。被告拿2000元就是要向我買票，不然要做什麼\n      。」等語（見警卷第44頁、第44頁反面，偵卷一第30-32\n      頁，本院卷第130-132 、136-137 頁）；3.證人A6於警詢\n      及偵訊時稱：「我家裡有5 位投票權人設籍在浩然里。於\n      99年10月中旬某日中午12時許，被告至我店裡吃完東西之\n      後，來到我身邊跟我說話，但是因為當時店裡很吵，所以\n      我沒有聽清楚他講了什麼，我只聽到他跟我說『拜託一下\n      』，然後他將5 張1000元的鈔票放在我店的櫃檯上後，就\n      走出去了。因為當時店裡還有其他客人在，也不方便跟他\n      說什麼，所以想說等比較沒有人的時候再去找他，將錢還\n      給他。之後我於同日下午1 時許，去他成立在五福二路上\n      的社區發展協會找他，將5000元還他，我跟他說『都是鄰\n      居，我不會跟你收這個』，他說『這是他的一點心意而已\n      』，之後我就回去店裡做生意了。他當時拿錢給我時，有\n      跟我說『拜託一下』，我知道李許美曄有參選里長，所以\n      應該是要我支持他太太李許美曄，因為他不可能幫對手買\n      票。」等語（見警卷第45-47 頁，偵卷一第53-55 頁）；\n      4.證人A7於警詢及偵訊時稱：「我於99年10月份某日接近\n      中午某時許，在我家門前遇到被告。被告說來找我聊天，\n      之後說要給我選舉的錢，因我家有2 票就給我2000元。我\n      知道李許美曄本次有出來選里長，被告也有跟我說」等語\n      （見警卷第23-24 頁，偵卷一第43-45 頁）；5.證人洪陳\n      滿鄭於警詢及偵訊時稱：「被告於99年8 、9 月份某日中\n      午某時許至我家，因我家有6 張選票，所以被告拿6000元\n      給我向我買票，要我投票給李許美曄」等語（見警卷第32\n      -34 頁，偵卷二第71-73 頁），觀諸其等於警詢及偵訊時\n      所述均一致，無明顯矛盾之處。又證人A6、A7、洪陳滿鄭\n      於警詢時均指認被告無誤（見警卷第25、35、48頁），且\n      證人A2等5 人於偵訊時均經具結，應足以擔保證言可信性\n      。再者，證人A3、A6、A7、洪陳滿鄭等人與被告並無仇怨\n      ，也無必要故意誣陷被告，並自陷己受偽證罪追訴處罰之\n      風險，甚至證人A2、A3於警詢時；證人A3於審理時均表示\n      希望其等上揭所述不要讓被告知道（見警卷第43頁、第44\n      頁反面，本院卷第135 頁），亦核與一般民眾若與被告居\n      住同里，彼此間又認識之反應相符，更添其等證言可信度\n      。而證人A2雖於審理時證稱：約4 年前曾因浩然里之公共\n      建設興建問題與被告有過不愉快等語（見本院卷第103-10\n      4 、108-109 頁），但相較於偽證罪之刑責，要難認證人\n      A2會為了此一陳年舊事而故意設詞陷害被告，堪認其上開\n      所述並無不實，被告辯稱與證人A2有糾紛，證人A2是故意\n      要陷害他，自難採信。甚且，證人A7、洪陳滿鄭除為上開\n      不利被告之陳述外，更坦承己受賄之犯行（見偵卷一第43\n      -45 頁，偵卷二第71-73 頁），並經臺灣高雄地方法院檢\n      察署檢察官以99年度選偵字第103 號為職權不起訴處分確\n      定（見偵卷二第80頁），倘若無受賄之事，證人A7、洪陳\n      滿鄭怎有可能陳稱上情，至己受刑事追訴？何況其2 人均\n      主動交出被告所給之賄款2000元及6000元，有扣押筆錄、\n      扣押物品目錄表、扣案現金照片、高雄市政府警察局苓雅\n      分局扣押物品清單、臺灣高雄地方法院檢察署贓證物款收\n      據存卷可考（見警卷第27-31 、36-41 、106-107 頁），\n      苟非該些款項確屬賄款，證人A7、洪陳滿鄭有何必要交由\n      警方扣案？從而，證人A2、A3、A6、A7、洪陳滿鄭等人上\n      開證述被告以金錢向其等行求賄選，要求其等對於上開里\n      長及市議員選舉之投票權為一定行使，且證人A7、洪陳滿\n      鄭均有受賄之意而收下上述賄賂款項等情，應屬真實，而\n      可採信。另被告留給證人A6之5000元，乃趁證人A6無暇之\n      際所留，後證人A6亦表示不願收受而退回，應認證人A6並\n      無受賄之意甚明。\n（三）證人A2、A3、A6、A7、洪陳滿鄭等人既均陳述被告有前揭\n      行求、交付賄賂之犯行如前，而證人A7、洪陳滿鄭更於警\n      詢及偵訊時均稱：「我收了李珈璜給我的買票錢後，我就\n      會投票給李許美曄」等語明確（見警卷第24、34頁，偵卷\n      一第44頁，偵卷二第72頁），益證被告係以「交付金錢」\n      利誘證人A2、A3、A6、A7、洪陳滿鄭等人之方式，希望證\n      人A2、A3、A6、A7、洪陳滿鄭等人能配合為投票權一定之\n      行使，亦即里長投給李許美曄、市議員投給許崑源之行求\n      賄選目的，至為灼然。又被告明確表示要求證人A2、A3、\n      A6 、A7 、洪陳滿鄭等人投給其指定之里長或市議員候選\n      人之行為，與其表示要給與證人A2、A3、A6、A7、洪陳滿\n      鄭等人金錢之行求賄賂，二者之間具有原因目的之對應關\n      係，具有對價關係至明。\n（四）另被告雖否認行賄犯行，但參以證人A2等5 人於警詢及偵\n      訊所述，已足認被告係以每票1000元之對價行賄。是被告\n      交付多餘之1000元給證人A7、多餘5000元給證人洪陳滿鄭\n      ，顯然是約定由證人A7、洪陳滿鄭轉達該些款項暨前揭投\n      票行賄之旨予戶內其他有投票權家人。惟證人A7、洪陳滿\n      鄭於警詢及偵查中均未曾證述已將除自己該票之對價1000\n      元以外其餘金錢轉交暨轉達被告前揭投票行賄之旨予戶內\n      其他有投票權家人，檢察官也未舉證證明與證人A7、洪陳\n      滿鄭設於同籍有投票權家人已獲得被告行賄之款項，則被\n      告對與證人A7、洪陳滿鄭設於同籍有投票權家人等人行賄\n      ，均僅止於預備階段，亦可認定。\n（五）至於審理中，證人A2改稱：「被告當天是到我店裡，並沒\n      有拿1000元給我，而是要從手提小袋子中拿許崑源的廣告\n      單給我，要我支持許崑源」云云（見本院卷第105 頁）；\n      證人A3雖稱：「被告說要我投票給誰我忘記了，也不記得\n      被告手上有無拿宣傳單」云云（見本院卷第132 頁）；證\n      人A6改稱：「我認為被告說『拜託一下』是要我支持許崑\n      源，與李許美曄參選里長無關」云云（見本院卷第55-56\n      頁）；證人A7則稱：「被告是看我身體不舒服，給我2 次\n      1000元，要我拿去看醫生及當生活費用。被告拿錢給我的\n      時間已經很久了，並非選舉期間，也沒有要我支持某個候\n      選人。我的警詢、偵訊筆錄均記載錯誤」云云（見本院卷\n      第111 、114 頁）；而證人洪陳滿鄭改口稱：「被告拿60\n      00元是給我生活用的，因他看我年紀大，家庭比較困難，\n      並非用以買票」云云（見本院卷第43-48 頁），然：\n    1.比對證人A2於警詢、偵訊及審理時所述之情節顯然不同，\n      倘若證人A2未經歷如事實欄一、（一）之事項，為何要虛\n      構此情節誣陷被告？又其為智識正常之成年人，對證人結\n      文及具結作證之意，當無不知之理，為何仍甘冒偽證罪之\n      刑責，於偵查中指證被告有前揭行求賄賂犯行？甚且，其\n      於審理時尚能陳述如此清晰，若所述屬實，為何不於偵查\n      中即向檢察官說明？再者，於本院審理中，經提示證人A2\n      之偵訊筆錄後，證人A2復改口稱：「被告當時確有從口袋\n      中拿錢的動作，也有問我家有幾票」等語明確（見本院卷\n      第106 頁），堪認證人A2上開對被告有利之證言，無非有\n      所保留，不能遽信。\n    2.考量人之記憶本隨時間而有衰退之跡象，證人A3雖於審理\n      中對被告拿錢給彼當時有無要求彼支持李許美曄，及有無\n      拿李許美曄之競選文宣給彼等節均不復記憶（見本院卷第\n      132 頁），但此為正常之現象，尚與常情無違。而對於被\n      告確有在事實欄一、（二）所載時地要拿2000元給彼之事\n      實仍為與彼先前於警詢、偵訊時所述一致，自不能以此瑕\n      疵，即認證人A3所述不實。\n    3.證人A6嗣經檢察官詰問，又改口坦承：「被告確有留5000\n      元給我，並說『拜託一下』，後來我有將錢還給被告，被\n      告說是一點心意，因當時李許美曄在參選，要拜託我選李\n      許美曄」等語（見本院卷第58頁），且被告與證人A6非親\n      非故，豈有無故留下5000元給證人A6之理，足見證人A6上\n      開有利被告之陳述，僅為避重就輕之詞，尚難採信。\n    4.同上論理，遍觀全卷，查無證人A7有任何陷害被告之動機\n      ，而一般人均知買票賄選是違法行為，若證人A7所述被告\n      有前載之行求賄賂犯行非真，當不可能為如此清晰之陳述\n      ，是其於審理時所述，要難憑採。\n    5.證人洪陳滿鄭於審理時明確證稱：「被告與我認識10年了\n      。除本次被告給我6000元外，未曾到我家慰問我喪夫，或\n      拿錢、生活用品貼補我。我的日子不好過」等語（見本院\n      卷第42、49頁），若其上揭所述為真，為何要將對其應屬\n      重要之生活費交由警方扣案？又為何從未過問其生活之被\n      告，卻於選前敏感時刻送錢給其？故其於審理時所述，自\n      甚可疑。\n    6.此外，審酌證人A2、A3、A6、A7、洪陳滿鄭等人均與被告\n      相識，平日作息皆有相遇之可能，且審理時被告又在庭，\n      難免因此情而難據實陳述，故考量上開證人於警詢及偵訊\n      中之陳述當時未直接面對被告，心情較為篤定，壓力較小\n      ，較有可能為任意陳述，憑信性甚高之外部附隨環境及條\n      件，應認其等先前於警詢及偵訊時之陳述較可信。\n    7.基此，證人A2、A6、A7、洪陳滿鄭等人於審理中所述有利\n      被告之證言，均係意在坦護被告，自不足作對被告有利之\n      認定。而證人A3於審理記憶不清之部分，也未悖於常理，\n      仍可信其於警詢及偵訊時所述為真。\n（六）綜上所述，被告前開辯詞顯和事實不合，純為卸責之詞。\n      本件事證已明，被告犯行堪以認定，應依法論科。\n三、論罪科刑：\n（一）按投票行賄罪之處罰分別規定於刑法第144 條及公職人員\n      選舉罷免法第99條第1 項，而公職人員選舉罷免法第99條\n      第1 項為刑法第144 條之特別法，依特別法優於普通法之\n      規定，應優先適用公職人員選舉罷免法。\n（二）按公職人員選舉罷免法第99條第1 項之賄選罪，係以對於\n      有投票權之人行求、期約或交付賄賂或其他不正利益，而\n      約其不行使投票權或為一定之行使為構成要件，亦即須視\n      行為人主觀上是否具有行賄之犯意，而約使有投票權人為\n      投票權一定之行使或不行使；客觀上行為人所行求期約或\n      交付之賄賂或不正利益是否可認係約使投票權人為投票權\n      之一定行使或不行使之對價；以及所行求、期約、交付之\n      對象是否為有投票權人而定。上開對價關係，在於行賄者\n      之一方，係認知其所行求、期約或交付之意思表示，乃為\n      約使有投票權人為投票權一定之行使或不行使；在受賄者\n      之一方，亦應認知行賄者對其所行求、期約或交付之意思\n      表示，乃為約使其為投票權一定之行使或不行使。且對有\n      投票權人交付之財物或不正利益，並不以金錢之多寡為絕\n      對標準，而應綜合社會價值觀念、授受雙方之認知及其他\n      客觀情事而為判斷（最高法院92年臺上字第893 號判例意\n      旨參照）。另該條所稱行求、期約、交付行為，係屬階段\n      行為，其行求賄選階段，係指行賄人自行向對方提出賄賂\n      或不正利益，以備交付，只以行賄者一方之意思表示為已\n      足，不以受賄者之允諾為必要，而交付賄賂階段，除行賄\n      者有實施交付賄賂行為外，因對收受賄賂者，刑法第143\n      條有投票受賄罪之處罰規定，二者乃必要共犯中之對向犯\n      ，以2 個以上之行為者，彼此相互對立之意思經合致而成\n      立犯罪，雖不以收受者確已承諾，或進而為一定投票權之\n      行使為必要，仍須於行賄人交付賄賂或其他不正利益時，\n      受交付之相對人對其交付之目的已然認識而予收受，其交\n      付賄賂或其他不正利益之犯行始克成立，行賄者方得論以\n      交付賄賂罪。\n（三）查本件被告於前述里長及市議員之選舉期間，為求李許美\n      曄、許崑源均順利當選該屆里長及市議員，而以給付一定\n      金錢為條件，對於有投票權之證人A2、A3、A6、A7、洪陳\n      滿鄭等人行求賄選並約其投票權為一定之行使，其主觀上\n      顯具有行賄之犯意，客觀上所行求之賄賂（金錢）可認係\n      約使有投票權人即證人A2、A3、A6、A7、洪陳滿鄭等人為\n      投票權之一定行使之對價，且被告於行賄當時明知其行求\n      之意思表示，乃為使有投票權人之證人A2、A3、A6、A7、\n      洪陳滿鄭等人為投票權一定之行使，且就上開證人A2等人\n      而言，亦認知被告對其等所行求之意思表示，乃為使其等\n      為投票權一定之行使，亦即里長投給候選人李許美曄，市\n      議員投票給許崑源，雖被告行求後，欲進一步交付賄賂遭\n      證人A2、A3、A6所拒，然被告既以交付金錢為對價約定證\n      人A2、A3、A6投票權為一定之行使，以行求當時之選舉氛\n      圍、社會價值觀念、授受雙方認知等情綜合判斷，已可認\n      定被告係對有投票權之證人A2、A3、A6行求賄賂，且就被\n      告之主觀犯意、行為時之客觀情事，衡以社會常情及經驗\n      法則等，堪認被告上開所為，已均對選舉人秘密投票暨國\n      家正當選舉程序法益有侵害之危險，而均違反公職人員選\n      舉罷免法第99條第1 項之對於有投票權人行求賄賂罪，不\n      因證人A2、A3、A6未承諾受賄而有不同。另證人A7、洪陳\n      滿鄭依上開情狀判斷，既已收下被告所交付之金錢，並均\n      證稱會因而投票給李許美曄業如前載，顯然於被告交付賄\n      賂時，其2 人對被告交付之目的已然認識而方收受，被告\n      此部分行為自得均論以同條第1 項之交付賄賂罪。故核被\n      告就事實欄一、（一）、（二）、（三）所為，均係犯公\n      職人員選舉罷免法第99條第1 項之行求賄賂罪；就事實欄\n      一、（四）、（五）所為則均係犯同條項之交付賄賂罪。\n（四）被告對具有投票權之證人A7、洪陳滿鄭等2 人行求賄賂之\n      低度行為，應為交付賄賂之高度行為所吸收，不另論罪。\n（五）按公職人員選舉罷免法之投票行賄罪係侵害國家法益之罪\n      ，以一行為同時對多數有投票權之人交付賄賂，約其不行\n      使投票權或為一定之行使，祇侵害一個國家法益，應僅成\n      立一投票行賄罪。而該罪之預備犯，僅止於該罪著手實行\n      前之準備階段，嗣若進而實行行賄之行為，即為行賄所吸\n      收，不另論罪。則以一行為同時對多數有投票權人行賄，\n      尚且論以一罪，其以一行為同時對多數有投票權之人部分\n      賄選，部分尚在預備賄選階段，亦僅能論以行賄一罪。本\n      件被告對證人A7、洪陳滿鄭行賄之同時，併委託其轉達行\n      賄之意思及轉交賄款予與證人A7、洪陳滿鄭設籍同址之其\n      他有投票權人，而同時對證人A7、洪陳滿鄭本人行賄及預\n      備對該2 址內多人行賄，應均係以一行為同時實行賄選及\n      預備賄選，自應論以一投票行賄罪。檢察官雖未對此多加\n      論述，然起訴書犯罪事實欄已載明被告每票行賄金額及交\n      付證人A7、洪陳滿鄭之賄賂數額，應認被告此部分預備犯\n      行均在起訴範圍內，本院自得依法審判。\n（六）按「刑法於民國94年2 月2 日修正公布（95年7 月1 日施\n      行）刪除連續犯規定之同時，對於合乎接續犯或包括的一\n      罪之情形，為避免刑罰之過度評價，已於立法理由說明委\n      由實務以補充解釋之方式，發展接續犯之概念，以限縮數\n      罪併罰之範圍。而多次投票行賄行為，在刑法刪除連續犯\n      規定之前，通說係論以連續犯。鑑於公職人員選舉，其前\n      、後屆及不同公職之間，均相區隔，選舉區亦已特定，以\n      候選人實行賄選為例，通常係以該次選舉當選為目的。是\n      於刪除連續犯規定後，苟行為人主觀上基於單一之犯意，\n      以數個舉動接續進行，而侵害同一法益，在時間、空間上\n      有密切關係，依一般社會健全觀念，難以強行分開，在刑\n      法評價上，以視為數個舉動之接續實行，合為包括之一行\n      為予以評價，較為合理，於此情形，即得依接續犯論以包\n      括之一罪。否則，如係分別起意，則仍依數罪併合處罰，\n      方符立法本旨。」最高法院99年度第5 次刑事庭會議決議\n      意旨可資參照，本件被告行求、交付賄賂證人A2、A3、A6\n      、A7、洪陳滿鄭等人之時間均在99年8 月至10月間，其5\n      次犯行時間、空間密接，顯係基於行求賄賂之單一犯意，\n      依一般社會健全觀念，難以強行分開，在刑法評價上，雖\n      行為階段不同，惟侵害同一選舉公正之法益，以視為數個\n      舉動之接續實行，合為包括之一行為予以評價，較為合理\n      ，應依接續犯論以情節較重的交付賄賂罪一罪。\n（七）爰審酌選舉乃民主政治之重要表徵，選民能否依據候選人\n      之品行、學識、才能、政見等資料而選賢與能，攸關一國\n      政治之良窳甚鉅，而賄選足以破壞候選人間之公平競爭，\n      更為敗壞選風之主要根源，故世界各民主法治國家莫不懸\n      為厲禁，全力遏止賄選犯行。被告為使李許美曄及許崑源\n      均能順利當選，不思以合法方式從事輔選、助選行為，竟\n      以給付金錢之方式，從事行求、交付賄選行為，企圖影響\n      選舉之公平，已嚴重侵蝕民主政治之機能，危害選舉制度\n      之公正性，並參酌其犯罪動機、手段、生活情狀、知識程\n      度及否認犯行之犯後態度等一切情狀，量處有期徒刑4 年\n      ，併科罰金新臺幣100 萬元，並諭知罰金易服勞役之折算\n      標準，且依公職人員選舉罷免法第113 條第3 項之規定宣\n      告褫奪公權4 年，以資警懲。\n（八）按公職人員選舉罷免法第99條第3 項規定：預備或用以行\n      求期約或交付之賄賂，不問屬於犯人與否，沒收之。此項\n      沒收為刑法第38條之特別規定，採絕對義務沒收主義，祇\n      要係預備或用以行求期約或交付之賄賂，不論是否屬於被\n      告所有或已否扣案，均應依法諭知沒收，法院並無自由裁\n      量之餘地。但如其賄賂已交付予有投票權之人收受，因收\n      受者係犯刑法第143 條第1 項之投票受賄罪，其所收受之\n      賄賂應依同法條第2 項規定沒收之，如全部或一部不能沒\n      收時，追徵其價額。故犯投票行賄罪者，其已交付之賄賂\n      ，苟該收受賄賂之有投票權人，復經檢察官依法起訴，法\n      院為有罪判決時，固應依刑法第143 條第2 項之規定，於\n      其對向共犯所犯投票受賄罪之從刑宣告沒收、追徵，而毋\n      庸再依上開規定重複宣告沒收；惟若對向共犯（即收受賄\n      賂者）所犯投票受賄罪嫌業經檢察官依刑事訴訟法第253\n      條規定為不起訴處分，或依同法第253 條之1 為緩起訴處\n      分確定者，則收受賄賂之對向共犯既毋庸經法院審判，其\n      所收受之賄賂即無從由法院依刑法第143 條第1 項之規定\n      宣告沒收、追徵。若檢察官未依刑事訴訟法第259 條之1\n      規定單獨聲請法院宣告沒收，則法院自仍應依公職人員選\n      舉罷免法第99條第3 項之規定，將犯投票行賄罪者所交付\n      之賄賂，於投票行賄罪之本案予以宣告沒收，始符立法本\n      旨（參最高法院100 年臺上字第214 號判決之發回意旨）\n      。查證人A7、洪陳滿鄭所犯刑法第143 條第1 項之有投票\n      權人收受賄路罪，雖經臺灣高雄地方法院檢察署檢察官以\n      99年度選偵字第103 號為不起訴處分確定，然並未就被告\n      所交付之賄款各2000元、6000元另案聲請單獨宣告沒收（\n      參證人洪陳滿鄭之前科紀錄表及本院公務電話紀錄），自\n      應依公職人員選舉罷免法第99條第3 項規定，均宣告沒收\n      。再按，倘該應沒收之物係屬金錢時，因金錢為代替物，\n      重在兌換價值，而不在原物，不以仍由被告持有、管理、\n      支配原物為限，是苟經確認係被告所用以行求之賄款時，\n      不問有無扣案，均應依公職人員選舉罷免法第99條第3 項\n      規定宣告沒收。查被告就事實欄一、（一）、（二）、（\n      三）所載渠所有用以行求賄賂之1000元、2000元、5000元\n      ，雖遭A2、A3拒收，及遭A6退回而未扣案，惟依上揭說明\n      ，仍應均宣告沒收之。另扣案之名冊1 張、旅遊行程表1\n      張，並無證據證明與本件有關，爰不予宣告沒收。\n據上論斷，應依刑事訴訟法第299 條第1 項前段，公職人員選舉\n罷免法第99條第1 項、第3 項，第113 條第3 項，刑法第11條、\n第37條第2 項、第42條第3 項，判決如主文。\n本件經檢察官陳俊宏到庭執行職務。\n中    華    民    國   100    年    5     月    31    日\n              刑事第十七庭  審判長法  官  陳培維\n                                  法  官  陳君杰\n                                  法  官  余銘軒\n以上正本證明與原本無異。\n如不服本判決應於收受送達後10日內向本院提出上訴書狀，並應\n敘述具體理由；如未敘述上訴理由者，應於上訴期間屆滿後20日\n內向本院補提理由書（均須按他造當事人之人數附繕本）「切勿\n逕送上級法院」。\n中    華    民    國   100    年    6     月    2     日\n                                  書記官  吳書逸\n附錄論罪科刑法條\n公職人員選舉罷免法第99條\n對於有投票權之人，行求期約或交付賄賂或其他不正利益，而約\n其不行使投票權或為一定之行使者，處 3 年以上 10 年以下有\n期徒刑，得併科新臺幣1 百萬元以上 1 千萬元以下罰金。\n預備犯前項之罪者，處 1 年以下有期徒刑。\n預備或用以行求期約或交付之賄賂，不問屬於犯人與否，沒收之\n。\n犯第 1 項或第 2 項之罪，於犯罪後六個月內自首者，減輕或免\n除其刑；因而查獲候選人為正犯或共犯者，免除其刑。\n犯第 1 項或第 2 項之罪，在偵查中自白者，減輕其刑；因而查\n獲候選人為正犯或共犯者，減輕或免除其刑。",
  "structure": {
    "main": "李珈璜犯公職人員選舉罷免法第九十九條第一項之行求賄賂罪，\n處有期徒刑肆年，併科罰金新臺幣壹佰萬元，罰金如易服勞役，\n以新臺幣仟元折算壹日。褫奪公權肆年。交付之賄賂現金新臺\n幣捌仟元，未扣案用以行求賄賂之現金新臺幣捌仟元均沒收。",
    "fact": "一、李珈璜為使不知情之高雄縣市合併後第1 屆高雄市新興區浩\n    然里里長候選人即其妻李許美曄（另為不起訴處分）與所支\n    持之第1 屆第8 選區市議員候選人即不知情之許崑源均能順\n    利當選，竟基於對有投票權人行求、交付賄賂而約其投票權\n    為一定行使之犯意，欲以每票新臺幣（下同）1000元之對價\n    買受有投票權人之選票，要求受賄人之投票權為投票給李許\n    美曄、許崑源之一定行使，而接續為下列行為：\n（一）於民國99年9 月底某日下午5 、6 時許，到設籍在浩然里\n      有投票權之A2住處（真實姓名、年籍、地址均詳密封卷）\n      行求賄賂，並問明可支持許崑源之票數後，要求A2於99年\n      11月27日該屆市議員選舉，投票給許崑源。嗣於行求後欲\n      交付1000元賄款給A2時，遭A2拒絕。\n（二）於99年9 月底某日上午9 時許，在高雄市新興區國民市○\n      ○○路口紅綠燈處，向設籍在浩然里有投票權之A3（真實\n      姓名、年籍、地址均詳密封卷）行求賄賂，並問明可支持\n      李許美曄之票數後，要求A3於99年11月27日該屆里長選舉\n      ，投票給李許美曄。嗣於行求後欲交付2000元賄款給A2時\n      ，遭A2拒絕。\n（三）於99年10月中旬某日中午12時許，到設籍在浩然里有投票\n      權之A6所經營之麵店（真實姓名、年籍、地址、店名均詳\n      密封卷）對A6說「拜託一下」後，趁A6忙於店務無暇之際\n      ，放置5000元在該店櫃臺上，以此方式行求賄賂A6於99年\n      11月27日該屆里長選舉，投票給李許美曄。後A6不願受賄\n      而將該5000元退還給李珈璜。\n（四）於99年10月份某日接近中午某時許，到設籍在浩然里有投\n      票權之A7住處（真實姓名、年籍、地址均詳密封卷）行求\n      賄賂，並問明可支持李許美曄之票數後，要求A7於99年11\n      月27日該屆里長選舉，投票給李許美曄，嗣於行求後交付\n      1000元賄款給A7，另將1000元託付A7，約定由其轉達該款\n      項暨上揭投票行賄之旨予戶內另1 名有投票權家人。A7（\n      業經檢察官為不起訴處分確定）明知李珈璜所交付之現金\n      係賄選之對價，仍基於有投票權人，而許以其投票權為一\n      定行使之犯意，當場收下（賄款2000元業經扣案）。\n（五）於99年8 、9 月份某日中午某時許，到設籍在浩然里有投\n      票權之洪陳滿鄭住處行求賄賂，並問明可支持李許美曄之\n      票數後，要求洪陳滿鄭於99年11月27日該屆里長選舉，投\n      票給李許美曄，嗣於行求後交付1000元賄款給洪陳滿鄭，\n      另將5000元託付洪陳滿鄭，約定由其轉達該款項暨上揭投\n      票行賄之旨予戶內另5 名有投票權家人。洪陳滿鄭（業經\n      檢察官為不起訴處分確定）明知李珈璜所交付之現金係賄\n      選之對價，仍基於有投票權人，而許以其投票權為一定行\n      使之犯意，當場收下（賄款6000元業經扣案）。\n    嗣A7、洪陳滿鄭尚未轉告及將款項轉交其2 人具有投票權之\n    家人前，即經警接獲情資循線查獲，並分別扣得洪陳滿鄭、\n    A7所收受之賄款6000元、2000元。\n二、案經高雄市政府警察局苓雅分局移送臺灣高雄地方法院檢察\n    署檢察官偵查起訴。",
    "reason": "一、證據能力：\n（一）按被告以外之人於審判外之言詞或書面陳述，除法律有規\n      定外，不得作為證據；被告以外之人於檢察事務官、司法\n      警察官或司法警察調查中所為之陳述，與審判中不符時，\n      其先前之陳述具有較可信之特別情況，且為證明犯罪事實\n      存否所必要，得為證據，刑事訴訟法第159 條第1 項、第\n      159 條之2 分別定有明文。是被告以外之人於審判外之言\n      詞或書面，即屬傳聞證據，因有悖法院直接審理及言詞審\n      理之精神，妨礙當事人之反對詰問權，影響程序正義之實\n      現，除法律別有規定外，原則上不具證據能力，必符合上\n      開例外規定時，始具有證據能力。刑事訴訟法第159 條之\n      2 所謂「前後陳述不符」之要件，應就前後階段之陳述進\n      行整體判斷，以決定其間是否具有實質性差異，而所謂「\n      較可信之特別情況」，亦應就前後陳述時之各種外部情況\n      進行比較，以資決定何者外部情況具有可信性，若陳述係\n      在特別可信之情況下所為，則虛偽陳述之危險性不高，雖\n      係審判外陳述，或未經被告反對詰問，仍得承認其有證據\n      能力。就外部情況之認定，例如時間之間隔、是否為有意\n      識之迴避、有無受外力干擾或事後串謀、以及警詢所作時\n      之筆錄記載是否完整、是否出於自由意識陳述等情。法院\n      應斟酌上列因素綜合判斷，細究陳述人問答態度、表情與\n      舉動之變化，以查是否具較可信之特別情況。經查，證人\n      A2、A3、A6、A7、洪陳滿鄭於警詢時之陳述，就被告李珈\n      璜交付金錢之目的，是否曾經行求賄賂其等投票給李許美\n      曄、許崑源等與案情有重要關係之事項，明顯與其等在本\n      院審理時之陳述情節有異（見警卷第23-24 、32-34 、42\n      -47 頁、本院卷第42-60 、103-117 、130-137 頁）。而\n      證人A2等人於接受員警詢問時，詢問筆錄之記載採取一問\n      一答之方式，於本院審理中到庭作證時，未曾反映其警詢\n      筆錄係遭受不正方法訊問而為陳述，堪認員警製作證人A2\n      等人之警詢筆錄時，係依法定程序為之，並無違法取供之\n      情事，其等陳述之信用性已受保障。再衡諸證人A2等人於\n      警詢時之陳述較接近案發時點，並於陳述當時未直接面對\n      被告，心情較為篤定，壓力較小，較有可能為任意陳述，\n      憑信性甚高，經考量其等於審判外及審判中陳述之外部附\n      隨環境及條件，應認其等先前之陳述具有較可信之特別情\n      況，且與本件待證事實間具有相當之關聯性及必要性，符\n      合刑事訴訟法第159 條之2 規定，自有證據能力。\n（二）按被告以外之人於偵查中向檢察官所為之陳述，除顯有不\n      可信之情況者外，得為證據，刑事訴訟法第159 條之1 第\n      2 項亦有明文。而所謂「顯有不可信性」係指陳述是否出\n      於供述者之真意、有無違法取供情事之信用性而言，故應\n      就偵查筆錄製作之原因、過程及其功能等項加以綜合觀察\n      ，據以判斷該傳聞證據是否「非顯不可信」，倘可據以認\n      定其任意性暨信用性俱無疑慮者，即可例外賦予「證據能\n      力」，俾其成為法院審判時之適格證據資料而言。再按刑\n      事訴訟法第166 條以下規定之交互詰問，屬人證調查證據\n      程序之一環，與證據能力係指符合法律規定之證據適格，\n      亦即得成為證明犯罪事實存否之證據適格，其性質及在證\n      據法則之層次並非相同，而被告、辯護人詰問權之行使與\n      否，係有權處分，如欲行使，則證人於審判中，應依法定\n      程序到庭具結陳述，並接受被告或辯護人等之詰問，其陳\n      述始得作為認定被告犯罪事判斷之依據（參照司法院釋字\n      第582 號解釋），否則如未進行交互詰問之調查證據程序\n      ，讓被告或辯護人行使詰問權，則該有證據能力之證人陳\n      述，即不得作為判斷之依據，惟其原有之證據能力並不因\n      而喪失（最高法院97年度臺上字第603 號判決可資參酌）\n      。經查，證人A2等人於偵查中所為之陳述，對被告而言，\n      固均屬被告以外之人於審判外之言詞陳述，然證人A2等人\n      於偵查中所為之陳述，均為親身經歷事項，又係經檢察官\n      告以拒絕證言權、具結之義務及偽證罪之處罰後，再命其\n      等朗讀結文並具結後所為之陳述，有上開證人之結文在卷\n      可稽。核其等製作筆錄過程，並無違法取供或證明力明顯\n      過低之瑕疵，復有全程錄音錄影可資憑信，所為陳述蓋係\n      出於供述者之真意，皆具信用性，揆諸上開說明，本屬有\n      證據能力之證人陳述。且於本院審理時，已依人證調查程\n      序，傳喚證人A2等人到場，命其等立於證人之地位經檢察\n      官、被告及渠辯護人當庭交互詰問，並使被告有與之對質\n      及詰問之機會，而證人A2等人偵訊之證言亦使被告、辯護\n      人加以辯論，認均已完足為合法調查之證據，自得採為判\n      決之基礎。綜上，以上開證人A2等人於偵查中經具結後所\n      為陳述作為證據，並無任何不當，依同法第159 條之1第2\n      項之規定，認具有證據能力。\n（三）本判決後開所引用之其他被告以外之人於審判外之陳述（\n      包括書面陳述），雖均屬傳聞證據，惟業經被告、辯護人\n      及檢察官於審理期日時均表示無意見而不予爭執，且迄至\n      言詞辯論終結前亦均未聲明異議，本院審酌上開證據資料\n      製作時之情況，尚查無違法不當之瑕疵，亦認為以之作為\n      證據應屬適當，故逕依刑事訴訟法第159 條之5 規定，認\n      上揭證據資料均例外有證據能力。\n二、訊據被告矢口否認為本件犯行，辯稱：本件是選舉恩怨，伊\n    未行求、交付賄款給證人A2、A3、A6、A7、洪陳滿鄭等人云\n    云，經查：\n（一）被告之妻李許美曄為高雄市新興區第1 屆里長候選人；許\n      崑源則為高雄市第1 屆第8 選區市議員選舉候選人（投票\n      日均為99年11月27日），被告於該次選舉分別為李許美曄\n      拉票及支持許崑源；又被告、證人A2、A3、A6、A7、洪陳\n      滿鄭等人於上開選舉期間內，均設籍於浩然里，係該屆浩\n      然里里長及第8 選區市議員選舉之有投票權人；另被告曾\n      任浩然里里長，證人A2、A3、A6、A7、洪陳滿鄭等人係該\n      里里民，彼此間均相識等情，業據證人李許美曄、A2、A3\n      、A6、A7、洪陳滿鄭等人陳述在卷（見警卷第23-24 、32\n      -34 、42-47 頁，偵卷一第25-27 、30-32 、43-45 、53\n      -55 頁，偵卷二第71-73 頁），且為被告所不爭（見本院\n      卷第13頁），並有高雄市選舉委員會100 年3 月29日高市\n      選一字第1000000584號函暨所附99年直轄市里長選舉候選\n      人登記冊（一）、高雄市新興區第1 屆里長選舉候選人登\n      記冊（當日）、領表名冊、高雄市第1 屆議員選舉第8 選\n      舉區候選人登記申請調查表、請領登記表明冊（見本院卷\n      第69 -74頁）、真實姓名與代號對照表、戶籍查詢資料（\n      見密封卷）在卷可憑，並經本院調取高雄市第1 屆市長、\n      議員暨里長選舉之選舉人名冊核閱無誤，是此部分事實，\n      均可認定。\n（二）1.證人A2於警詢及偵訊時稱：「於99年9 月底某日下午5\n      、6 時許，被告至我家聊天、拜票，向我說他支持許崑源\n      ，問我家裡有幾個人，我說只有我自己可以支持他，其他\n      人的票不是我能作主。他聽完後就從他褲子的口袋要拿出\n      1000元塞給我，但是我沒有收他的錢，因為我心裡知道這\n      1000元是他要向我買票的錢，所以我不敢收，後來李珈璜\n      看我不收他的錢後，他就把1000元拿回去，然後說他還有\n      事情要處理就先走了。被告拿錢給我應該是要我投票給許\n      崑源。被告也曾拿許崑源的競選文宣來我家，跟我表明他\n      是支持許崑源的。」等語（見警卷第42-43 頁，偵卷一第\n      25 -27頁）；2.證人A3於警詢、偵訊及審理時稱：「於99\n      年9 月底某日上午9 時許，在高雄市新興區國民市○○○\n      路口紅綠燈處，我剛好遇上被告，他手裡拿出1 張競選文\n      宣，要我支持他老婆參選里長，然後就拿出2000元要給我\n      ，說我家有2 票（我1 票，我兒子1 票）。我當時對李珈\n      璜說我會投給李許美曄啦，我不要收你的錢，然後我就趕\n      快離開了。被告拿2000元就是要向我買票，不然要做什麼\n      。」等語（見警卷第44頁、第44頁反面，偵卷一第30-32\n      頁，本院卷第130-132 、136-137 頁）；3.證人A6於警詢\n      及偵訊時稱：「我家裡有5 位投票權人設籍在浩然里。於\n      99年10月中旬某日中午12時許，被告至我店裡吃完東西之\n      後，來到我身邊跟我說話，但是因為當時店裡很吵，所以\n      我沒有聽清楚他講了什麼，我只聽到他跟我說『拜託一下\n      』，然後他將5 張1000元的鈔票放在我店的櫃檯上後，就\n      走出去了。因為當時店裡還有其他客人在，也不方便跟他\n      說什麼，所以想說等比較沒有人的時候再去找他，將錢還\n      給他。之後我於同日下午1 時許，去他成立在五福二路上\n      的社區發展協會找他，將5000元還他，我跟他說『都是鄰\n      居，我不會跟你收這個』，他說『這是他的一點心意而已\n      』，之後我就回去店裡做生意了。他當時拿錢給我時，有\n      跟我說『拜託一下』，我知道李許美曄有參選里長，所以\n      應該是要我支持他太太李許美曄，因為他不可能幫對手買\n      票。」等語（見警卷第45-47 頁，偵卷一第53-55 頁）；\n      4.證人A7於警詢及偵訊時稱：「我於99年10月份某日接近\n      中午某時許，在我家門前遇到被告。被告說來找我聊天，\n      之後說要給我選舉的錢，因我家有2 票就給我2000元。我\n      知道李許美曄本次有出來選里長，被告也有跟我說」等語\n      （見警卷第23-24 頁，偵卷一第43-45 頁）；5.證人洪陳\n      滿鄭於警詢及偵訊時稱：「被告於99年8 、9 月份某日中\n      午某時許至我家，因我家有6 張選票，所以被告拿6000元\n      給我向我買票，要我投票給李許美曄」等語（見警卷第32\n      -34 頁，偵卷二第71-73 頁），觀諸其等於警詢及偵訊時\n      所述均一致，無明顯矛盾之處。又證人A6、A7、洪陳滿鄭\n      於警詢時均指認被告無誤（見警卷第25、35、48頁），且\n      證人A2等5 人於偵訊時均經具結，應足以擔保證言可信性\n      。再者，證人A3、A6、A7、洪陳滿鄭等人與被告並無仇怨\n      ，也無必要故意誣陷被告，並自陷己受偽證罪追訴處罰之\n      風險，甚至證人A2、A3於警詢時；證人A3於審理時均表示\n      希望其等上揭所述不要讓被告知道（見警卷第43頁、第44\n      頁反面，本院卷第135 頁），亦核與一般民眾若與被告居\n      住同里，彼此間又認識之反應相符，更添其等證言可信度\n      。而證人A2雖於審理時證稱：約4 年前曾因浩然里之公共\n      建設興建問題與被告有過不愉快等語（見本院卷第103-10\n      4 、108-109 頁），但相較於偽證罪之刑責，要難認證人\n      A2會為了此一陳年舊事而故意設詞陷害被告，堪認其上開\n      所述並無不實，被告辯稱與證人A2有糾紛，證人A2是故意\n      要陷害他，自難採信。甚且，證人A7、洪陳滿鄭除為上開\n      不利被告之陳述外，更坦承己受賄之犯行（見偵卷一第43\n      -45 頁，偵卷二第71-73 頁），並經臺灣高雄地方法院檢\n      察署檢察官以99年度選偵字第103 號為職權不起訴處分確\n      定（見偵卷二第80頁），倘若無受賄之事，證人A7、洪陳\n      滿鄭怎有可能陳稱上情，至己受刑事追訴？何況其2 人均\n      主動交出被告所給之賄款2000元及6000元，有扣押筆錄、\n      扣押物品目錄表、扣案現金照片、高雄市政府警察局苓雅\n      分局扣押物品清單、臺灣高雄地方法院檢察署贓證物款收\n      據存卷可考（見警卷第27-31 、36-41 、106-107 頁），\n      苟非該些款項確屬賄款，證人A7、洪陳滿鄭有何必要交由\n      警方扣案？從而，證人A2、A3、A6、A7、洪陳滿鄭等人上\n      開證述被告以金錢向其等行求賄選，要求其等對於上開里\n      長及市議員選舉之投票權為一定行使，且證人A7、洪陳滿\n      鄭均有受賄之意而收下上述賄賂款項等情，應屬真實，而\n      可採信。另被告留給證人A6之5000元，乃趁證人A6無暇之\n      際所留，後證人A6亦表示不願收受而退回，應認證人A6並\n      無受賄之意甚明。\n（三）證人A2、A3、A6、A7、洪陳滿鄭等人既均陳述被告有前揭\n      行求、交付賄賂之犯行如前，而證人A7、洪陳滿鄭更於警\n      詢及偵訊時均稱：「我收了李珈璜給我的買票錢後，我就\n      會投票給李許美曄」等語明確（見警卷第24、34頁，偵卷\n      一第44頁，偵卷二第72頁），益證被告係以「交付金錢」\n      利誘證人A2、A3、A6、A7、洪陳滿鄭等人之方式，希望證\n      人A2、A3、A6、A7、洪陳滿鄭等人能配合為投票權一定之\n      行使，亦即里長投給李許美曄、市議員投給許崑源之行求\n      賄選目的，至為灼然。又被告明確表示要求證人A2、A3、\n      A6 、A7 、洪陳滿鄭等人投給其指定之里長或市議員候選\n      人之行為，與其表示要給與證人A2、A3、A6、A7、洪陳滿\n      鄭等人金錢之行求賄賂，二者之間具有原因目的之對應關\n      係，具有對價關係至明。\n（四）另被告雖否認行賄犯行，但參以證人A2等5 人於警詢及偵\n      訊所述，已足認被告係以每票1000元之對價行賄。是被告\n      交付多餘之1000元給證人A7、多餘5000元給證人洪陳滿鄭\n      ，顯然是約定由證人A7、洪陳滿鄭轉達該些款項暨前揭投\n      票行賄之旨予戶內其他有投票權家人。惟證人A7、洪陳滿\n      鄭於警詢及偵查中均未曾證述已將除自己該票之對價1000\n      元以外其餘金錢轉交暨轉達被告前揭投票行賄之旨予戶內\n      其他有投票權家人，檢察官也未舉證證明與證人A7、洪陳\n      滿鄭設於同籍有投票權家人已獲得被告行賄之款項，則被\n      告對與證人A7、洪陳滿鄭設於同籍有投票權家人等人行賄\n      ，均僅止於預備階段，亦可認定。\n（五）至於審理中，證人A2改稱：「被告當天是到我店裡，並沒\n      有拿1000元給我，而是要從手提小袋子中拿許崑源的廣告\n      單給我，要我支持許崑源」云云（見本院卷第105 頁）；\n      證人A3雖稱：「被告說要我投票給誰我忘記了，也不記得\n      被告手上有無拿宣傳單」云云（見本院卷第132 頁）；證\n      人A6改稱：「我認為被告說『拜託一下』是要我支持許崑\n      源，與李許美曄參選里長無關」云云（見本院卷第55-56\n      頁）；證人A7則稱：「被告是看我身體不舒服，給我2 次\n      1000元，要我拿去看醫生及當生活費用。被告拿錢給我的\n      時間已經很久了，並非選舉期間，也沒有要我支持某個候\n      選人。我的警詢、偵訊筆錄均記載錯誤」云云（見本院卷\n      第111 、114 頁）；而證人洪陳滿鄭改口稱：「被告拿60\n      00元是給我生活用的，因他看我年紀大，家庭比較困難，\n      並非用以買票」云云（見本院卷第43-48 頁），然：\n    1.比對證人A2於警詢、偵訊及審理時所述之情節顯然不同，\n      倘若證人A2未經歷如事實欄一、（一）之事項，為何要虛\n      構此情節誣陷被告？又其為智識正常之成年人，對證人結\n      文及具結作證之意，當無不知之理，為何仍甘冒偽證罪之\n      刑責，於偵查中指證被告有前揭行求賄賂犯行？甚且，其\n      於審理時尚能陳述如此清晰，若所述屬實，為何不於偵查\n      中即向檢察官說明？再者，於本院審理中，經提示證人A2\n      之偵訊筆錄後，證人A2復改口稱：「被告當時確有從口袋\n      中拿錢的動作，也有問我家有幾票」等語明確（見本院卷\n      第106 頁），堪認證人A2上開對被告有利之證言，無非有\n      所保留，不能遽信。\n    2.考量人之記憶本隨時間而有衰退之跡象，證人A3雖於審理\n      中對被告拿錢給彼當時有無要求彼支持李許美曄，及有無\n      拿李許美曄之競選文宣給彼等節均不復記憶（見本院卷第\n      132 頁），但此為正常之現象，尚與常情無違。而對於被\n      告確有在事實欄一、（二）所載時地要拿2000元給彼之事\n      實仍為與彼先前於警詢、偵訊時所述一致，自不能以此瑕\n      疵，即認證人A3所述不實。\n    3.證人A6嗣經檢察官詰問，又改口坦承：「被告確有留5000\n      元給我，並說『拜託一下』，後來我有將錢還給被告，被\n      告說是一點心意，因當時李許美曄在參選，要拜託我選李\n      許美曄」等語（見本院卷第58頁），且被告與證人A6非親\n      非故，豈有無故留下5000元給證人A6之理，足見證人A6上\n      開有利被告之陳述，僅為避重就輕之詞，尚難採信。\n    4.同上論理，遍觀全卷，查無證人A7有任何陷害被告之動機\n      ，而一般人均知買票賄選是違法行為，若證人A7所述被告\n      有前載之行求賄賂犯行非真，當不可能為如此清晰之陳述\n      ，是其於審理時所述，要難憑採。\n    5.證人洪陳滿鄭於審理時明確證稱：「被告與我認識10年了\n      。除本次被告給我6000元外，未曾到我家慰問我喪夫，或\n      拿錢、生活用品貼補我。我的日子不好過」等語（見本院\n      卷第42、49頁），若其上揭所述為真，為何要將對其應屬\n      重要之生活費交由警方扣案？又為何從未過問其生活之被\n      告，卻於選前敏感時刻送錢給其？故其於審理時所述，自\n      甚可疑。\n    6.此外，審酌證人A2、A3、A6、A7、洪陳滿鄭等人均與被告\n      相識，平日作息皆有相遇之可能，且審理時被告又在庭，\n      難免因此情而難據實陳述，故考量上開證人於警詢及偵訊\n      中之陳述當時未直接面對被告，心情較為篤定，壓力較小\n      ，較有可能為任意陳述，憑信性甚高之外部附隨環境及條\n      件，應認其等先前於警詢及偵訊時之陳述較可信。\n    7.基此，證人A2、A6、A7、洪陳滿鄭等人於審理中所述有利\n      被告之證言，均係意在坦護被告，自不足作對被告有利之\n      認定。而證人A3於審理記憶不清之部分，也未悖於常理，\n      仍可信其於警詢及偵訊時所述為真。\n（六）綜上所述，被告前開辯詞顯和事實不合，純為卸責之詞。\n      本件事證已明，被告犯行堪以認定，應依法論科。\n三、論罪科刑：\n（一）按投票行賄罪之處罰分別規定於刑法第144 條及公職人員\n      選舉罷免法第99條第1 項，而公職人員選舉罷免法第99條\n      第1 項為刑法第144 條之特別法，依特別法優於普通法之\n      規定，應優先適用公職人員選舉罷免法。\n（二）按公職人員選舉罷免法第99條第1 項之賄選罪，係以對於\n      有投票權之人行求、期約或交付賄賂或其他不正利益，而\n      約其不行使投票權或為一定之行使為構成要件，亦即須視\n      行為人主觀上是否具有行賄之犯意，而約使有投票權人為\n      投票權一定之行使或不行使；客觀上行為人所行求期約或\n      交付之賄賂或不正利益是否可認係約使投票權人為投票權\n      之一定行使或不行使之對價；以及所行求、期約、交付之\n      對象是否為有投票權人而定。上開對價關係，在於行賄者\n      之一方，係認知其所行求、期約或交付之意思表示，乃為\n      約使有投票權人為投票權一定之行使或不行使；在受賄者\n      之一方，亦應認知行賄者對其所行求、期約或交付之意思\n      表示，乃為約使其為投票權一定之行使或不行使。且對有\n      投票權人交付之財物或不正利益，並不以金錢之多寡為絕\n      對標準，而應綜合社會價值觀念、授受雙方之認知及其他\n      客觀情事而為判斷（最高法院92年臺上字第893 號判例意\n      旨參照）。另該條所稱行求、期約、交付行為，係屬階段\n      行為，其行求賄選階段，係指行賄人自行向對方提出賄賂\n      或不正利益，以備交付，只以行賄者一方之意思表示為已\n      足，不以受賄者之允諾為必要，而交付賄賂階段，除行賄\n      者有實施交付賄賂行為外，因對收受賄賂者，刑法第143\n      條有投票受賄罪之處罰規定，二者乃必要共犯中之對向犯\n      ，以2 個以上之行為者，彼此相互對立之意思經合致而成\n      立犯罪，雖不以收受者確已承諾，或進而為一定投票權之\n      行使為必要，仍須於行賄人交付賄賂或其他不正利益時，\n      受交付之相對人對其交付之目的已然認識而予收受，其交\n      付賄賂或其他不正利益之犯行始克成立，行賄者方得論以\n      交付賄賂罪。\n（三）查本件被告於前述里長及市議員之選舉期間，為求李許美\n      曄、許崑源均順利當選該屆里長及市議員，而以給付一定\n      金錢為條件，對於有投票權之證人A2、A3、A6、A7、洪陳\n      滿鄭等人行求賄選並約其投票權為一定之行使，其主觀上\n      顯具有行賄之犯意，客觀上所行求之賄賂（金錢）可認係\n      約使有投票權人即證人A2、A3、A6、A7、洪陳滿鄭等人為\n      投票權之一定行使之對價，且被告於行賄當時明知其行求\n      之意思表示，乃為使有投票權人之證人A2、A3、A6、A7、\n      洪陳滿鄭等人為投票權一定之行使，且就上開證人A2等人\n      而言，亦認知被告對其等所行求之意思表示，乃為使其等\n      為投票權一定之行使，亦即里長投給候選人李許美曄，市\n      議員投票給許崑源，雖被告行求後，欲進一步交付賄賂遭\n      證人A2、A3、A6所拒，然被告既以交付金錢為對價約定證\n      人A2、A3、A6投票權為一定之行使，以行求當時之選舉氛\n      圍、社會價值觀念、授受雙方認知等情綜合判斷，已可認\n      定被告係對有投票權之證人A2、A3、A6行求賄賂，且就被\n      告之主觀犯意、行為時之客觀情事，衡以社會常情及經驗\n      法則等，堪認被告上開所為，已均對選舉人秘密投票暨國\n      家正當選舉程序法益有侵害之危險，而均違反公職人員選\n      舉罷免法第99條第1 項之對於有投票權人行求賄賂罪，不\n      因證人A2、A3、A6未承諾受賄而有不同。另證人A7、洪陳\n      滿鄭依上開情狀判斷，既已收下被告所交付之金錢，並均\n      證稱會因而投票給李許美曄業如前載，顯然於被告交付賄\n      賂時，其2 人對被告交付之目的已然認識而方收受，被告\n      此部分行為自得均論以同條第1 項之交付賄賂罪。故核被\n      告就事實欄一、（一）、（二）、（三）所為，均係犯公\n      職人員選舉罷免法第99條第1 項之行求賄賂罪；就事實欄\n      一、（四）、（五）所為則均係犯同條項之交付賄賂罪。\n（四）被告對具有投票權之證人A7、洪陳滿鄭等2 人行求賄賂之\n      低度行為，應為交付賄賂之高度行為所吸收，不另論罪。\n（五）按公職人員選舉罷免法之投票行賄罪係侵害國家法益之罪\n      ，以一行為同時對多數有投票權之人交付賄賂，約其不行\n      使投票權或為一定之行使，祇侵害一個國家法益，應僅成\n      立一投票行賄罪。而該罪之預備犯，僅止於該罪著手實行\n      前之準備階段，嗣若進而實行行賄之行為，即為行賄所吸\n      收，不另論罪。則以一行為同時對多數有投票權人行賄，\n      尚且論以一罪，其以一行為同時對多數有投票權之人部分\n      賄選，部分尚在預備賄選階段，亦僅能論以行賄一罪。本\n      件被告對證人A7、洪陳滿鄭行賄之同時，併委託其轉達行\n      賄之意思及轉交賄款予與證人A7、洪陳滿鄭設籍同址之其\n      他有投票權人，而同時對證人A7、洪陳滿鄭本人行賄及預\n      備對該2 址內多人行賄，應均係以一行為同時實行賄選及\n      預備賄選，自應論以一投票行賄罪。檢察官雖未對此多加\n      論述，然起訴書犯罪事實欄已載明被告每票行賄金額及交\n      付證人A7、洪陳滿鄭之賄賂數額，應認被告此部分預備犯\n      行均在起訴範圍內，本院自得依法審判。\n（六）按「刑法於民國94年2 月2 日修正公布（95年7 月1 日施\n      行）刪除連續犯規定之同時，對於合乎接續犯或包括的一\n      罪之情形，為避免刑罰之過度評價，已於立法理由說明委\n      由實務以補充解釋之方式，發展接續犯之概念，以限縮數\n      罪併罰之範圍。而多次投票行賄行為，在刑法刪除連續犯\n      規定之前，通說係論以連續犯。鑑於公職人員選舉，其前\n      、後屆及不同公職之間，均相區隔，選舉區亦已特定，以\n      候選人實行賄選為例，通常係以該次選舉當選為目的。是\n      於刪除連續犯規定後，苟行為人主觀上基於單一之犯意，\n      以數個舉動接續進行，而侵害同一法益，在時間、空間上\n      有密切關係，依一般社會健全觀念，難以強行分開，在刑\n      法評價上，以視為數個舉動之接續實行，合為包括之一行\n      為予以評價，較為合理，於此情形，即得依接續犯論以包\n      括之一罪。否則，如係分別起意，則仍依數罪併合處罰，\n      方符立法本旨。」最高法院99年度第5 次刑事庭會議決議\n      意旨可資參照，本件被告行求、交付賄賂證人A2、A3、A6\n      、A7、洪陳滿鄭等人之時間均在99年8 月至10月間，其5\n      次犯行時間、空間密接，顯係基於行求賄賂之單一犯意，\n      依一般社會健全觀念，難以強行分開，在刑法評價上，雖\n      行為階段不同，惟侵害同一選舉公正之法益，以視為數個\n      舉動之接續實行，合為包括之一行為予以評價，較為合理\n      ，應依接續犯論以情節較重的交付賄賂罪一罪。\n（七）爰審酌選舉乃民主政治之重要表徵，選民能否依據候選人\n      之品行、學識、才能、政見等資料而選賢與能，攸關一國\n      政治之良窳甚鉅，而賄選足以破壞候選人間之公平競爭，\n      更為敗壞選風之主要根源，故世界各民主法治國家莫不懸\n      為厲禁，全力遏止賄選犯行。被告為使李許美曄及許崑源\n      均能順利當選，不思以合法方式從事輔選、助選行為，竟\n      以給付金錢之方式，從事行求、交付賄選行為，企圖影響\n      選舉之公平，已嚴重侵蝕民主政治之機能，危害選舉制度\n      之公正性，並參酌其犯罪動機、手段、生活情狀、知識程\n      度及否認犯行之犯後態度等一切情狀，量處有期徒刑4 年\n      ，併科罰金新臺幣100 萬元，並諭知罰金易服勞役之折算\n      標準，且依公職人員選舉罷免法第113 條第3 項之規定宣\n      告褫奪公權4 年，以資警懲。\n（八）按公職人員選舉罷免法第99條第3 項規定：預備或用以行\n      求期約或交付之賄賂，不問屬於犯人與否，沒收之。此項\n      沒收為刑法第38條之特別規定，採絕對義務沒收主義，祇\n      要係預備或用以行求期約或交付之賄賂，不論是否屬於被\n      告所有或已否扣案，均應依法諭知沒收，法院並無自由裁\n      量之餘地。但如其賄賂已交付予有投票權之人收受，因收\n      受者係犯刑法第143 條第1 項之投票受賄罪，其所收受之\n      賄賂應依同法條第2 項規定沒收之，如全部或一部不能沒\n      收時，追徵其價額。故犯投票行賄罪者，其已交付之賄賂\n      ，苟該收受賄賂之有投票權人，復經檢察官依法起訴，法\n      院為有罪判決時，固應依刑法第143 條第2 項之規定，於\n      其對向共犯所犯投票受賄罪之從刑宣告沒收、追徵，而毋\n      庸再依上開規定重複宣告沒收；惟若對向共犯（即收受賄\n      賂者）所犯投票受賄罪嫌業經檢察官依刑事訴訟法第253\n      條規定為不起訴處分，或依同法第253 條之1 為緩起訴處\n      分確定者，則收受賄賂之對向共犯既毋庸經法院審判，其\n      所收受之賄賂即無從由法院依刑法第143 條第1 項之規定\n      宣告沒收、追徵。若檢察官未依刑事訴訟法第259 條之1\n      規定單獨聲請法院宣告沒收，則法院自仍應依公職人員選\n      舉罷免法第99條第3 項之規定，將犯投票行賄罪者所交付\n      之賄賂，於投票行賄罪之本案予以宣告沒收，始符立法本\n      旨（參最高法院100 年臺上字第214 號判決之發回意旨）\n      。查證人A7、洪陳滿鄭所犯刑法第143 條第1 項之有投票\n      權人收受賄路罪，雖經臺灣高雄地方法院檢察署檢察官以\n      99年度選偵字第103 號為不起訴處分確定，然並未就被告\n      所交付之賄款各2000元、6000元另案聲請單獨宣告沒收（\n      參證人洪陳滿鄭之前科紀錄表及本院公務電話紀錄），自\n      應依公職人員選舉罷免法第99條第3 項規定，均宣告沒收\n      。再按，倘該應沒收之物係屬金錢時，因金錢為代替物，\n      重在兌換價值，而不在原物，不以仍由被告持有、管理、\n      支配原物為限，是苟經確認係被告所用以行求之賄款時，\n      不問有無扣案，均應依公職人員選舉罷免法第99條第3 項\n      規定宣告沒收。查被告就事實欄一、（一）、（二）、（\n      三）所載渠所有用以行求賄賂之1000元、2000元、5000元\n      ，雖遭A2、A3拒收，及遭A6退回而未扣案，惟依上揭說明\n      ，仍應均宣告沒收之。另扣案之名冊1 張、旅遊行程表1\n      張，並無證據證明與本件有關，爰不予宣告沒收。\n據上論斷，應依刑事訴訟法第299 條第1 項前段，公職人員選舉\n罷免法第99條第1 項、第3 項，第113 條第3 項，刑法第11條、\n第37條第2 項、第42條第3 項，判決如主文。\n本件經檢察官陳俊宏到庭執行職務。\n中    華    民    國   100    年    5     月    31    日\n              刑事第十七庭  審判長法  官  陳培維\n                                  法  官  陳君杰\n                                  法  官  余銘軒\n以上正本證明與原本無異。\n如不服本判決應於收受送達後10日內向本院提出上訴書狀，並應\n敘述具體理由；如未敘述上訴理由者，應於上訴期間屆滿後20日\n內向本院補提理由書（均須按他造當事人之人數附繕本）「切勿\n逕送上級法院」。"
  },
  "search": "臺灣高雄地方法院刑事判決100年度選訴字第29號公訴人臺灣高雄地方法院檢察署檢察官被告李珈璜選任辯護人鄭國安律師吳麗珠律師郭宗塘律師上列被告因違反公職人員選舉罷免法案件，經檢察官提起公訴（99年度選偵字第130號、第374號、第46號），本院判決如下：主文李珈璜犯公職人員選舉罷免法第九十九條第一項之行求賄賂罪，處有期徒刑肆年，併科罰金新臺幣壹佰萬元，罰金如易服勞役，以新臺幣仟元折算壹日。褫奪公權肆年。交付之賄賂現金新臺幣捌仟元，未扣案用以行求賄賂之現金新臺幣捌仟元均沒收。事實一、李珈璜為使不知情之高雄縣市合併後第1屆高雄市新興區浩然里里長候選人即其妻李許美曄（另為不起訴處分）與所支持之第1屆第8選區市議員候選人即不知情之許崑源均能順利當選，竟基於對有投票權人行求、交付賄賂而約其投票權為一定行使之犯意，欲以每票新臺幣（下同）1000元之對價買受有投票權人之選票，要求受賄人之投票權為投票給李許美曄、許崑源之一定行使，而接續為下列行為：（一）於民國99年9月底某日下午5、6時許，到設籍在浩然里有投票權之A2住處（真實姓名、年籍、地址均詳密封卷）行求賄賂，並問明可支持許崑源之票數後，要求A2於99年11月27日該屆市議員選舉，投票給許崑源。嗣於行求後欲交付1000元賄款給A2時，遭A2拒絕。（二）於99年9月底某日上午9時許，在高雄市新興區國民市○○○路口紅綠燈處，向設籍在浩然里有投票權之A3（真實姓名、年籍、地址均詳密封卷）行求賄賂，並問明可支持李許美曄之票數後，要求A3於99年11月27日該屆里長選舉，投票給李許美曄。嗣於行求後欲交付2000元賄款給A2時，遭A2拒絕。（三）於99年10月中旬某日中午12時許，到設籍在浩然里有投票權之A6所經營之麵店（真實姓名、年籍、地址、店名均詳密封卷）對A6說「拜託一下」後，趁A6忙於店務無暇之際，放置5000元在該店櫃臺上，以此方式行求賄賂A6於99年11月27日該屆里長選舉，投票給李許美曄。後A6不願受賄而將該5000元退還給李珈璜。（四）於99年10月份某日接近中午某時許，到設籍在浩然里有投票權之A7住處（真實姓名、年籍、地址均詳密封卷）行求賄賂，並問明可支持李許美曄之票數後，要求A7於99年11月27日該屆里長選舉，投票給李許美曄，嗣於行求後交付1000元賄款給A7，另將1000元託付A7，約定由其轉達該款項暨上揭投票行賄之旨予戶內另1名有投票權家人。A7（業經檢察官為不起訴處分確定）明知李珈璜所交付之現金係賄選之對價，仍基於有投票權人，而許以其投票權為一定行使之犯意，當場收下（賄款2000元業經扣案）。（五）於99年8、9月份某日中午某時許，到設籍在浩然里有投票權之洪陳滿鄭住處行求賄賂，並問明可支持李許美曄之票數後，要求洪陳滿鄭於99年11月27日該屆里長選舉，投票給李許美曄，嗣於行求後交付1000元賄款給洪陳滿鄭，另將5000元託付洪陳滿鄭，約定由其轉達該款項暨上揭投票行賄之旨予戶內另5名有投票權家人。洪陳滿鄭（業經檢察官為不起訴處分確定）明知李珈璜所交付之現金係賄選之對價，仍基於有投票權人，而許以其投票權為一定行使之犯意，當場收下（賄款6000元業經扣案）。嗣A7、洪陳滿鄭尚未轉告及將款項轉交其2人具有投票權之家人前，即經警接獲情資循線查獲，並分別扣得洪陳滿鄭、A7所收受之賄款6000元、2000元。二、案經高雄市政府警察局苓雅分局移送臺灣高雄地方法院檢察署檢察官偵查起訴。理由一、證據能力：（一）按被告以外之人於審判外之言詞或書面陳述，除法律有規定外，不得作為證據；被告以外之人於檢察事務官、司法警察官或司法警察調查中所為之陳述，與審判中不符時，其先前之陳述具有較可信之特別情況，且為證明犯罪事實存否所必要，得為證據，刑事訴訟法第159條第1項、第159條之2分別定有明文。是被告以外之人於審判外之言詞或書面，即屬傳聞證據，因有悖法院直接審理及言詞審理之精神，妨礙當事人之反對詰問權，影響程序正義之實現，除法律別有規定外，原則上不具證據能力，必符合上開例外規定時，始具有證據能力。刑事訴訟法第159條之2所謂「前後陳述不符」之要件，應就前後階段之陳述進行整體判斷，以決定其間是否具有實質性差異，而所謂「較可信之特別情況」，亦應就前後陳述時之各種外部情況進行比較，以資決定何者外部情況具有可信性，若陳述係在特別可信之情況下所為，則虛偽陳述之危險性不高，雖係審判外陳述，或未經被告反對詰問，仍得承認其有證據能力。就外部情況之認定，例如時間之間隔、是否為有意識之迴避、有無受外力干擾或事後串謀、以及警詢所作時之筆錄記載是否完整、是否出於自由意識陳述等情。法院應斟酌上列因素綜合判斷，細究陳述人問答態度、表情與舉動之變化，以查是否具較可信之特別情況。經查，證人A2、A3、A6、A7、洪陳滿鄭於警詢時之陳述，就被告李珈璜交付金錢之目的，是否曾經行求賄賂其等投票給李許美曄、許崑源等與案情有重要關係之事項，明顯與其等在本院審理時之陳述情節有異（見警卷第23-24、32-34、42-47頁、本院卷第42-60、103-117、130-137頁）。而證人A2等人於接受員警詢問時，詢問筆錄之記載採取一問一答之方式，於本院審理中到庭作證時，未曾反映其警詢筆錄係遭受不正方法訊問而為陳述，堪認員警製作證人A2等人之警詢筆錄時，係依法定程序為之，並無違法取供之情事，其等陳述之信用性已受保障。再衡諸證人A2等人於警詢時之陳述較接近案發時點，並於陳述當時未直接面對被告，心情較為篤定，壓力較小，較有可能為任意陳述，憑信性甚高，經考量其等於審判外及審判中陳述之外部附隨環境及條件，應認其等先前之陳述具有較可信之特別情況，且與本件待證事實間具有相當之關聯性及必要性，符合刑事訴訟法第159條之2規定，自有證據能力。（二）按被告以外之人於偵查中向檢察官所為之陳述，除顯有不可信之情況者外，得為證據，刑事訴訟法第159條之1第2項亦有明文。而所謂「顯有不可信性」係指陳述是否出於供述者之真意、有無違法取供情事之信用性而言，故應就偵查筆錄製作之原因、過程及其功能等項加以綜合觀察，據以判斷該傳聞證據是否「非顯不可信」，倘可據以認定其任意性暨信用性俱無疑慮者，即可例外賦予「證據能力」，俾其成為法院審判時之適格證據資料而言。再按刑事訴訟法第166條以下規定之交互詰問，屬人證調查證據程序之一環，與證據能力係指符合法律規定之證據適格，亦即得成為證明犯罪事實存否之證據適格，其性質及在證據法則之層次並非相同，而被告、辯護人詰問權之行使與否，係有權處分，如欲行使，則證人於審判中，應依法定程序到庭具結陳述，並接受被告或辯護人等之詰問，其陳述始得作為認定被告犯罪事判斷之依據（參照司法院釋字第582號解釋），否則如未進行交互詰問之調查證據程序，讓被告或辯護人行使詰問權，則該有證據能力之證人陳述，即不得作為判斷之依據，惟其原有之證據能力並不因而喪失（最高法院97年度臺上字第603號判決可資參酌）。經查，證人A2等人於偵查中所為之陳述，對被告而言，固均屬被告以外之人於審判外之言詞陳述，然證人A2等人於偵查中所為之陳述，均為親身經歷事項，又係經檢察官告以拒絕證言權、具結之義務及偽證罪之處罰後，再命其等朗讀結文並具結後所為之陳述，有上開證人之結文在卷可稽。核其等製作筆錄過程，並無違法取供或證明力明顯過低之瑕疵，復有全程錄音錄影可資憑信，所為陳述蓋係出於供述者之真意，皆具信用性，揆諸上開說明，本屬有證據能力之證人陳述。且於本院審理時，已依人證調查程序，傳喚證人A2等人到場，命其等立於證人之地位經檢察官、被告及渠辯護人當庭交互詰問，並使被告有與之對質及詰問之機會，而證人A2等人偵訊之證言亦使被告、辯護人加以辯論，認均已完足為合法調查之證據，自得採為判決之基礎。綜上，以上開證人A2等人於偵查中經具結後所為陳述作為證據，並無任何不當，依同法第159條之1第2項之規定，認具有證據能力。（三）本判決後開所引用之其他被告以外之人於審判外之陳述（包括書面陳述），雖均屬傳聞證據，惟業經被告、辯護人及檢察官於審理期日時均表示無意見而不予爭執，且迄至言詞辯論終結前亦均未聲明異議，本院審酌上開證據資料製作時之情況，尚查無違法不當之瑕疵，亦認為以之作為證據應屬適當，故逕依刑事訴訟法第159條之5規定，認上揭證據資料均例外有證據能力。二、訊據被告矢口否認為本件犯行，辯稱：本件是選舉恩怨，伊未行求、交付賄款給證人A2、A3、A6、A7、洪陳滿鄭等人云云，經查：（一）被告之妻李許美曄為高雄市新興區第1屆里長候選人；許崑源則為高雄市第1屆第8選區市議員選舉候選人（投票日均為99年11月27日），被告於該次選舉分別為李許美曄拉票及支持許崑源；又被告、證人A2、A3、A6、A7、洪陳滿鄭等人於上開選舉期間內，均設籍於浩然里，係該屆浩然里里長及第8選區市議員選舉之有投票權人；另被告曾任浩然里里長，證人A2、A3、A6、A7、洪陳滿鄭等人係該里里民，彼此間均相識等情，業據證人李許美曄、A2、A3、A6、A7、洪陳滿鄭等人陳述在卷（見警卷第23-24、32-34、42-47頁，偵卷一第25-27、30-32、43-45、53-55頁，偵卷二第71-73頁），且為被告所不爭（見本院卷第13頁），並有高雄市選舉委員會100年3月29日高市選一字第1000000584號函暨所附99年直轄市里長選舉候選人登記冊（一）、高雄市新興區第1屆里長選舉候選人登記冊（當日）、領表名冊、高雄市第1屆議員選舉第8選舉區候選人登記申請調查表、請領登記表明冊（見本院卷第69-74頁）、真實姓名與代號對照表、戶籍查詢資料（見密封卷）在卷可憑，並經本院調取高雄市第1屆市長、議員暨里長選舉之選舉人名冊核閱無誤，是此部分事實，均可認定。（二）1.證人A2於警詢及偵訊時稱：「於99年9月底某日下午5、6時許，被告至我家聊天、拜票，向我說他支持許崑源，問我家裡有幾個人，我說只有我自己可以支持他，其他人的票不是我能作主。他聽完後就從他褲子的口袋要拿出1000元塞給我，但是我沒有收他的錢，因為我心裡知道這1000元是他要向我買票的錢，所以我不敢收，後來李珈璜看我不收他的錢後，他就把1000元拿回去，然後說他還有事情要處理就先走了。被告拿錢給我應該是要我投票給許崑源。被告也曾拿許崑源的競選文宣來我家，跟我表明他是支持許崑源的。」等語（見警卷第42-43頁，偵卷一第25-27頁）；2.證人A3於警詢、偵訊及審理時稱：「於99年9月底某日上午9時許，在高雄市新興區國民市○○○路口紅綠燈處，我剛好遇上被告，他手裡拿出1張競選文宣，要我支持他老婆參選里長，然後就拿出2000元要給我，說我家有2票（我1票，我兒子1票）。我當時對李珈璜說我會投給李許美曄啦，我不要收你的錢，然後我就趕快離開了。被告拿2000元就是要向我買票，不然要做什麼。」等語（見警卷第44頁、第44頁反面，偵卷一第30-32頁，本院卷第130-132、136-137頁）；3.證人A6於警詢及偵訊時稱：「我家裡有5位投票權人設籍在浩然里。於99年10月中旬某日中午12時許，被告至我店裡吃完東西之後，來到我身邊跟我說話，但是因為當時店裡很吵，所以我沒有聽清楚他講了什麼，我只聽到他跟我說『拜託一下』，然後他將5張1000元的鈔票放在我店的櫃檯上後，就走出去了。因為當時店裡還有其他客人在，也不方便跟他說什麼，所以想說等比較沒有人的時候再去找他，將錢還給他。之後我於同日下午1時許，去他成立在五福二路上的社區發展協會找他，將5000元還他，我跟他說『都是鄰居，我不會跟你收這個』，他說『這是他的一點心意而已』，之後我就回去店裡做生意了。他當時拿錢給我時，有跟我說『拜託一下』，我知道李許美曄有參選里長，所以應該是要我支持他太太李許美曄，因為他不可能幫對手買票。」等語（見警卷第45-47頁，偵卷一第53-55頁）；4.證人A7於警詢及偵訊時稱：「我於99年10月份某日接近中午某時許，在我家門前遇到被告。被告說來找我聊天，之後說要給我選舉的錢，因我家有2票就給我2000元。我知道李許美曄本次有出來選里長，被告也有跟我說」等語（見警卷第23-24頁，偵卷一第43-45頁）；5.證人洪陳滿鄭於警詢及偵訊時稱：「被告於99年8、9月份某日中午某時許至我家，因我家有6張選票，所以被告拿6000元給我向我買票，要我投票給李許美曄」等語（見警卷第32-34頁，偵卷二第71-73頁），觀諸其等於警詢及偵訊時所述均一致，無明顯矛盾之處。又證人A6、A7、洪陳滿鄭於警詢時均指認被告無誤（見警卷第25、35、48頁），且證人A2等5人於偵訊時均經具結，應足以擔保證言可信性。再者，證人A3、A6、A7、洪陳滿鄭等人與被告並無仇怨，也無必要故意誣陷被告，並自陷己受偽證罪追訴處罰之風險，甚至證人A2、A3於警詢時；證人A3於審理時均表示希望其等上揭所述不要讓被告知道（見警卷第43頁、第44頁反面，本院卷第135頁），亦核與一般民眾若與被告居住同里，彼此間又認識之反應相符，更添其等證言可信度。而證人A2雖於審理時證稱：約4年前曾因浩然里之公共建設興建問題與被告有過不愉快等語（見本院卷第103-104、108-109頁），但相較於偽證罪之刑責，要難認證人A2會為了此一陳年舊事而故意設詞陷害被告，堪認其上開所述並無不實，被告辯稱與證人A2有糾紛，證人A2是故意要陷害他，自難採信。甚且，證人A7、洪陳滿鄭除為上開不利被告之陳述外，更坦承己受賄之犯行（見偵卷一第43-45頁，偵卷二第71-73頁），並經臺灣高雄地方法院檢察署檢察官以99年度選偵字第103號為職權不起訴處分確定（見偵卷二第80頁），倘若無受賄之事，證人A7、洪陳滿鄭怎有可能陳稱上情，至己受刑事追訴？何況其2人均主動交出被告所給之賄款2000元及6000元，有扣押筆錄、扣押物品目錄表、扣案現金照片、高雄市政府警察局苓雅分局扣押物品清單、臺灣高雄地方法院檢察署贓證物款收據存卷可考（見警卷第27-31、36-41、106-107頁），苟非該些款項確屬賄款，證人A7、洪陳滿鄭有何必要交由警方扣案？從而，證人A2、A3、A6、A7、洪陳滿鄭等人上開證述被告以金錢向其等行求賄選，要求其等對於上開里長及市議員選舉之投票權為一定行使，且證人A7、洪陳滿鄭均有受賄之意而收下上述賄賂款項等情，應屬真實，而可採信。另被告留給證人A6之5000元，乃趁證人A6無暇之際所留，後證人A6亦表示不願收受而退回，應認證人A6並無受賄之意甚明。（三）證人A2、A3、A6、A7、洪陳滿鄭等人既均陳述被告有前揭行求、交付賄賂之犯行如前，而證人A7、洪陳滿鄭更於警詢及偵訊時均稱：「我收了李珈璜給我的買票錢後，我就會投票給李許美曄」等語明確（見警卷第24、34頁，偵卷一第44頁，偵卷二第72頁），益證被告係以「交付金錢」利誘證人A2、A3、A6、A7、洪陳滿鄭等人之方式，希望證人A2、A3、A6、A7、洪陳滿鄭等人能配合為投票權一定之行使，亦即里長投給李許美曄、市議員投給許崑源之行求賄選目的，至為灼然。又被告明確表示要求證人A2、A3、A6、A7、洪陳滿鄭等人投給其指定之里長或市議員候選人之行為，與其表示要給與證人A2、A3、A6、A7、洪陳滿鄭等人金錢之行求賄賂，二者之間具有原因目的之對應關係，具有對價關係至明。（四）另被告雖否認行賄犯行，但參以證人A2等5人於警詢及偵訊所述，已足認被告係以每票1000元之對價行賄。是被告交付多餘之1000元給證人A7、多餘5000元給證人洪陳滿鄭，顯然是約定由證人A7、洪陳滿鄭轉達該些款項暨前揭投票行賄之旨予戶內其他有投票權家人。惟證人A7、洪陳滿鄭於警詢及偵查中均未曾證述已將除自己該票之對價1000元以外其餘金錢轉交暨轉達被告前揭投票行賄之旨予戶內其他有投票權家人，檢察官也未舉證證明與證人A7、洪陳滿鄭設於同籍有投票權家人已獲得被告行賄之款項，則被告對與證人A7、洪陳滿鄭設於同籍有投票權家人等人行賄，均僅止於預備階段，亦可認定。（五）至於審理中，證人A2改稱：「被告當天是到我店裡，並沒有拿1000元給我，而是要從手提小袋子中拿許崑源的廣告單給我，要我支持許崑源」云云（見本院卷第105頁）；證人A3雖稱：「被告說要我投票給誰我忘記了，也不記得被告手上有無拿宣傳單」云云（見本院卷第132頁）；證人A6改稱：「我認為被告說『拜託一下』是要我支持許崑源，與李許美曄參選里長無關」云云（見本院卷第55-56頁）；證人A7則稱：「被告是看我身體不舒服，給我2次1000元，要我拿去看醫生及當生活費用。被告拿錢給我的時間已經很久了，並非選舉期間，也沒有要我支持某個候選人。我的警詢、偵訊筆錄均記載錯誤」云云（見本院卷第111、114頁）；而證人洪陳滿鄭改口稱：「被告拿6000元是給我生活用的，因他看我年紀大，家庭比較困難，並非用以買票」云云（見本院卷第43-48頁），然：1.比對證人A2於警詢、偵訊及審理時所述之情節顯然不同，倘若證人A2未經歷如事實欄一、（一）之事項，為何要虛構此情節誣陷被告？又其為智識正常之成年人，對證人結文及具結作證之意，當無不知之理，為何仍甘冒偽證罪之刑責，於偵查中指證被告有前揭行求賄賂犯行？甚且，其於審理時尚能陳述如此清晰，若所述屬實，為何不於偵查中即向檢察官說明？再者，於本院審理中，經提示證人A2之偵訊筆錄後，證人A2復改口稱：「被告當時確有從口袋中拿錢的動作，也有問我家有幾票」等語明確（見本院卷第106頁），堪認證人A2上開對被告有利之證言，無非有所保留，不能遽信。2.考量人之記憶本隨時間而有衰退之跡象，證人A3雖於審理中對被告拿錢給彼當時有無要求彼支持李許美曄，及有無拿李許美曄之競選文宣給彼等節均不復記憶（見本院卷第132頁），但此為正常之現象，尚與常情無違。而對於被告確有在事實欄一、（二）所載時地要拿2000元給彼之事實仍為與彼先前於警詢、偵訊時所述一致，自不能以此瑕疵，即認證人A3所述不實。3.證人A6嗣經檢察官詰問，又改口坦承：「被告確有留5000元給我，並說『拜託一下』，後來我有將錢還給被告，被告說是一點心意，因當時李許美曄在參選，要拜託我選李許美曄」等語（見本院卷第58頁），且被告與證人A6非親非故，豈有無故留下5000元給證人A6之理，足見證人A6上開有利被告之陳述，僅為避重就輕之詞，尚難採信。4.同上論理，遍觀全卷，查無證人A7有任何陷害被告之動機，而一般人均知買票賄選是違法行為，若證人A7所述被告有前載之行求賄賂犯行非真，當不可能為如此清晰之陳述，是其於審理時所述，要難憑採。5.證人洪陳滿鄭於審理時明確證稱：「被告與我認識10年了。除本次被告給我6000元外，未曾到我家慰問我喪夫，或拿錢、生活用品貼補我。我的日子不好過」等語（見本院卷第42、49頁），若其上揭所述為真，為何要將對其應屬重要之生活費交由警方扣案？又為何從未過問其生活之被告，卻於選前敏感時刻送錢給其？故其於審理時所述，自甚可疑。6.此外，審酌證人A2、A3、A6、A7、洪陳滿鄭等人均與被告相識，平日作息皆有相遇之可能，且審理時被告又在庭，難免因此情而難據實陳述，故考量上開證人於警詢及偵訊中之陳述當時未直接面對被告，心情較為篤定，壓力較小，較有可能為任意陳述，憑信性甚高之外部附隨環境及條件，應認其等先前於警詢及偵訊時之陳述較可信。7.基此，證人A2、A6、A7、洪陳滿鄭等人於審理中所述有利被告之證言，均係意在坦護被告，自不足作對被告有利之認定。而證人A3於審理記憶不清之部分，也未悖於常理，仍可信其於警詢及偵訊時所述為真。（六）綜上所述，被告前開辯詞顯和事實不合，純為卸責之詞。本件事證已明，被告犯行堪以認定，應依法論科。三、論罪科刑：（一）按投票行賄罪之處罰分別規定於刑法第144條及公職人員選舉罷免法第99條第1項，而公職人員選舉罷免法第99條第1項為刑法第144條之特別法，依特別法優於普通法之規定，應優先適用公職人員選舉罷免法。（二）按公職人員選舉罷免法第99條第1項之賄選罪，係以對於有投票權之人行求、期約或交付賄賂或其他不正利益，而約其不行使投票權或為一定之行使為構成要件，亦即須視行為人主觀上是否具有行賄之犯意，而約使有投票權人為投票權一定之行使或不行使；客觀上行為人所行求期約或交付之賄賂或不正利益是否可認係約使投票權人為投票權之一定行使或不行使之對價；以及所行求、期約、交付之對象是否為有投票權人而定。上開對價關係，在於行賄者之一方，係認知其所行求、期約或交付之意思表示，乃為約使有投票權人為投票權一定之行使或不行使；在受賄者之一方，亦應認知行賄者對其所行求、期約或交付之意思表示，乃為約使其為投票權一定之行使或不行使。且對有投票權人交付之財物或不正利益，並不以金錢之多寡為絕對標準，而應綜合社會價值觀念、授受雙方之認知及其他客觀情事而為判斷（最高法院92年臺上字第893號判例意旨參照）。另該條所稱行求、期約、交付行為，係屬階段行為，其行求賄選階段，係指行賄人自行向對方提出賄賂或不正利益，以備交付，只以行賄者一方之意思表示為已足，不以受賄者之允諾為必要，而交付賄賂階段，除行賄者有實施交付賄賂行為外，因對收受賄賂者，刑法第143條有投票受賄罪之處罰規定，二者乃必要共犯中之對向犯，以2個以上之行為者，彼此相互對立之意思經合致而成立犯罪，雖不以收受者確已承諾，或進而為一定投票權之行使為必要，仍須於行賄人交付賄賂或其他不正利益時，受交付之相對人對其交付之目的已然認識而予收受，其交付賄賂或其他不正利益之犯行始克成立，行賄者方得論以交付賄賂罪。（三）查本件被告於前述里長及市議員之選舉期間，為求李許美曄、許崑源均順利當選該屆里長及市議員，而以給付一定金錢為條件，對於有投票權之證人A2、A3、A6、A7、洪陳滿鄭等人行求賄選並約其投票權為一定之行使，其主觀上顯具有行賄之犯意，客觀上所行求之賄賂（金錢）可認係約使有投票權人即證人A2、A3、A6、A7、洪陳滿鄭等人為投票權之一定行使之對價，且被告於行賄當時明知其行求之意思表示，乃為使有投票權人之證人A2、A3、A6、A7、洪陳滿鄭等人為投票權一定之行使，且就上開證人A2等人而言，亦認知被告對其等所行求之意思表示，乃為使其等為投票權一定之行使，亦即里長投給候選人李許美曄，市議員投票給許崑源，雖被告行求後，欲進一步交付賄賂遭證人A2、A3、A6所拒，然被告既以交付金錢為對價約定證人A2、A3、A6投票權為一定之行使，以行求當時之選舉氛圍、社會價值觀念、授受雙方認知等情綜合判斷，已可認定被告係對有投票權之證人A2、A3、A6行求賄賂，且就被告之主觀犯意、行為時之客觀情事，衡以社會常情及經驗法則等，堪認被告上開所為，已均對選舉人秘密投票暨國家正當選舉程序法益有侵害之危險，而均違反公職人員選舉罷免法第99條第1項之對於有投票權人行求賄賂罪，不因證人A2、A3、A6未承諾受賄而有不同。另證人A7、洪陳滿鄭依上開情狀判斷，既已收下被告所交付之金錢，並均證稱會因而投票給李許美曄業如前載，顯然於被告交付賄賂時，其2人對被告交付之目的已然認識而方收受，被告此部分行為自得均論以同條第1項之交付賄賂罪。故核被告就事實欄一、（一）、（二）、（三）所為，均係犯公職人員選舉罷免法第99條第1項之行求賄賂罪；就事實欄一、（四）、（五）所為則均係犯同條項之交付賄賂罪。（四）被告對具有投票權之證人A7、洪陳滿鄭等2人行求賄賂之低度行為，應為交付賄賂之高度行為所吸收，不另論罪。（五）按公職人員選舉罷免法之投票行賄罪係侵害國家法益之罪，以一行為同時對多數有投票權之人交付賄賂，約其不行使投票權或為一定之行使，祇侵害一個國家法益，應僅成立一投票行賄罪。而該罪之預備犯，僅止於該罪著手實行前之準備階段，嗣若進而實行行賄之行為，即為行賄所吸收，不另論罪。則以一行為同時對多數有投票權人行賄，尚且論以一罪，其以一行為同時對多數有投票權之人部分賄選，部分尚在預備賄選階段，亦僅能論以行賄一罪。本件被告對證人A7、洪陳滿鄭行賄之同時，併委託其轉達行賄之意思及轉交賄款予與證人A7、洪陳滿鄭設籍同址之其他有投票權人，而同時對證人A7、洪陳滿鄭本人行賄及預備對該2址內多人行賄，應均係以一行為同時實行賄選及預備賄選，自應論以一投票行賄罪。檢察官雖未對此多加論述，然起訴書犯罪事實欄已載明被告每票行賄金額及交付證人A7、洪陳滿鄭之賄賂數額，應認被告此部分預備犯行均在起訴範圍內，本院自得依法審判。（六）按「刑法於民國94年2月2日修正公布（95年7月1日施行）刪除連續犯規定之同時，對於合乎接續犯或包括的一罪之情形，為避免刑罰之過度評價，已於立法理由說明委由實務以補充解釋之方式，發展接續犯之概念，以限縮數罪併罰之範圍。而多次投票行賄行為，在刑法刪除連續犯規定之前，通說係論以連續犯。鑑於公職人員選舉，其前、後屆及不同公職之間，均相區隔，選舉區亦已特定，以候選人實行賄選為例，通常係以該次選舉當選為目的。是於刪除連續犯規定後，苟行為人主觀上基於單一之犯意，以數個舉動接續進行，而侵害同一法益，在時間、空間上有密切關係，依一般社會健全觀念，難以強行分開，在刑法評價上，以視為數個舉動之接續實行，合為包括之一行為予以評價，較為合理，於此情形，即得依接續犯論以包括之一罪。否則，如係分別起意，則仍依數罪併合處罰，方符立法本旨。」最高法院99年度第5次刑事庭會議決議意旨可資參照，本件被告行求、交付賄賂證人A2、A3、A6、A7、洪陳滿鄭等人之時間均在99年8月至10月間，其5次犯行時間、空間密接，顯係基於行求賄賂之單一犯意，依一般社會健全觀念，難以強行分開，在刑法評價上，雖行為階段不同，惟侵害同一選舉公正之法益，以視為數個舉動之接續實行，合為包括之一行為予以評價，較為合理，應依接續犯論以情節較重的交付賄賂罪一罪。（七）爰審酌選舉乃民主政治之重要表徵，選民能否依據候選人之品行、學識、才能、政見等資料而選賢與能，攸關一國政治之良窳甚鉅，而賄選足以破壞候選人間之公平競爭，更為敗壞選風之主要根源，故世界各民主法治國家莫不懸為厲禁，全力遏止賄選犯行。被告為使李許美曄及許崑源均能順利當選，不思以合法方式從事輔選、助選行為，竟以給付金錢之方式，從事行求、交付賄選行為，企圖影響選舉之公平，已嚴重侵蝕民主政治之機能，危害選舉制度之公正性，並參酌其犯罪動機、手段、生活情狀、知識程度及否認犯行之犯後態度等一切情狀，量處有期徒刑4年，併科罰金新臺幣100萬元，並諭知罰金易服勞役之折算標準，且依公職人員選舉罷免法第113條第3項之規定宣告褫奪公權4年，以資警懲。（八）按公職人員選舉罷免法第99條第3項規定：預備或用以行求期約或交付之賄賂，不問屬於犯人與否，沒收之。此項沒收為刑法第38條之特別規定，採絕對義務沒收主義，祇要係預備或用以行求期約或交付之賄賂，不論是否屬於被告所有或已否扣案，均應依法諭知沒收，法院並無自由裁量之餘地。但如其賄賂已交付予有投票權之人收受，因收受者係犯刑法第143條第1項之投票受賄罪，其所收受之賄賂應依同法條第2項規定沒收之，如全部或一部不能沒收時，追徵其價額。故犯投票行賄罪者，其已交付之賄賂，苟該收受賄賂之有投票權人，復經檢察官依法起訴，法院為有罪判決時，固應依刑法第143條第2項之規定，於其對向共犯所犯投票受賄罪之從刑宣告沒收、追徵，而毋庸再依上開規定重複宣告沒收；惟若對向共犯（即收受賄賂者）所犯投票受賄罪嫌業經檢察官依刑事訴訟法第253條規定為不起訴處分，或依同法第253條之1為緩起訴處分確定者，則收受賄賂之對向共犯既毋庸經法院審判，其所收受之賄賂即無從由法院依刑法第143條第1項之規定宣告沒收、追徵。若檢察官未依刑事訴訟法第259條之1規定單獨聲請法院宣告沒收，則法院自仍應依公職人員選舉罷免法第99條第3項之規定，將犯投票行賄罪者所交付之賄賂，於投票行賄罪之本案予以宣告沒收，始符立法本旨（參最高法院100年臺上字第214號判決之發回意旨）。查證人A7、洪陳滿鄭所犯刑法第143條第1項之有投票權人收受賄路罪，雖經臺灣高雄地方法院檢察署檢察官以99年度選偵字第103號為不起訴處分確定，然並未就被告所交付之賄款各2000元、6000元另案聲請單獨宣告沒收（參證人洪陳滿鄭之前科紀錄表及本院公務電話紀錄），自應依公職人員選舉罷免法第99條第3項規定，均宣告沒收。再按，倘該應沒收之物係屬金錢時，因金錢為代替物，重在兌換價值，而不在原物，不以仍由被告持有、管理、支配原物為限，是苟經確認係被告所用以行求之賄款時，不問有無扣案，均應依公職人員選舉罷免法第99條第3項規定宣告沒收。查被告就事實欄一、（一）、（二）、（三）所載渠所有用以行求賄賂之1000元、2000元、5000元，雖遭A2、A3拒收，及遭A6退回而未扣案，惟依上揭說明，仍應均宣告沒收之。另扣案之名冊1張、旅遊行程表1張，並無證據證明與本件有關，爰不予宣告沒收。據上論斷，應依刑事訴訟法第299條第1項前段，公職人員選舉罷免法第99條第1項、第3項，第113條第3項，刑法第11條、第37條第2項、第42條第3項，判決如主文。本件經檢察官陳俊宏到庭執行職務。中華民國100年5月31日刑事第十七庭審判長法官陳培維法官陳君杰法官余銘軒以上正本證明與原本無異。如不服本判決應於收受送達後10日內向本院提出上訴書狀，並應敘述具體理由；如未敘述上訴理由者，應於上訴期間屆滿後20日內向本院補提理由書（均須按他造當事人之人數附繕本）「切勿逕送上級法院」。中華民國100年6月2日書記官吳書逸附錄論罪科刑法條公職人員選舉罷免法第99條對於有投票權之人，行求期約或交付賄賂或其他不正利益，而約其不行使投票權或為一定之行使者，處3年以上10年以下有期徒刑，得併科新臺幣1百萬元以上1千萬元以下罰金。預備犯前項之罪者，處1年以下有期徒刑。預備或用以行求期約或交付之賄賂，不問屬於犯人與否，沒收之。犯第1項或第2項之罪，於犯罪後六個月內自首者，減輕或免除其刑；因而查獲候選人為正犯或共犯者，免除其刑。犯第1項或第2項之罪，在偵查中自白者，減輕其刑；因而查獲候選人為正犯或共犯者，減輕或免除其刑。",
  "characters": {
    "judges": [
      "陳培維",
      "陳君杰",
      "余銘軒"
    ],
    "prosecutors": [
      "陳俊宏"
    ],
    "lawyers": [
      "鄭國安",
      "吳麗珠",
      "郭宗塘"
    ],
    "clerks": [
      "吳書逸"
    ],
    "plaintiffs": [

    ],
    "defendants": [
      "李珈璜"
    ],
    "prosecutor_office": [
      "臺灣高雄地方法院檢察署檢察官"
    ],
    "creditors": [

    ],
    "debtors": [

    ],
    "judicial_associate_officer": [

    ]
  },
  "adjudged_at": "2011-05-31",
  "created_at": "2016-02-12 01:14:33",
  "updated_at": "2016-02-12 01:14:33"
}