{
  "identify": "MLD-100-易-23-20110531-1",
  "court": {
    "name": "臺灣苗栗地方法院",
    "code": "MLD"
  },
  "division": {
    "name": "刑事",
    "code": "M"
  },
  "year": 100,
  "word": "易",
  "number": "23",
  "jcheck": "1",
  "reason": "毒品危害防制條例",
  "content": "臺灣苗栗地方法院刑事判決               100年度易字第23號\n公  訴  人  臺灣苗栗地方法院檢察署檢察官\n被      告  周永忠\n上列被告因毒品危害防制條例案件，經檢察官提起公訴（100 年\n度毒偵字第1653號），本院以簡式審判程序審理，判決如下：\n    主  文\n周永忠施用第二級毒品，累犯，處有期徒刑伍月，如易科罰金，\n以新臺幣壹仟元折算壹日。\n    犯罪事實及理由\n一、犯罪事實：\n（一）周永忠前於：\n  民國95年間，因犯竊盜罪，經本院判處有期徒刑9月、9月，\n    應執行有期徒刑1年確定（95年度易字第159號）。\n  復於95年間，因犯竊盜罪，經本院判處有期徒刑7 月確定（\n    96年度易字第221號）。\n  復於95年間，因犯贓物、竊盜、偽造文書罪，分別經本院判\n    處有期徒刑10月、1年6月、6月、10月、6月，減為有期徒刑\n    5月、9月、3月、5月、3月，應執行有期徒刑2年確定（96年\n    度易字第1069號）。\n  上開、案，嗣因適用中華民國九十六年罪犯減刑條例，\n    經本院以96年聲減字第104號、97年聲字第945號裁定分別減\n    為3月、3月、3月15日、4月15日、4月15日、9月、5月、5月\n    ，應執行有期徒刑2年8月確定，並與前揭所示之有期徒刑\n    2年接續執行，甫於99年7月31日假釋付保護管束期滿執行完\n    畢。\n（二）周永忠前於：\n    95年間，因施用第二級毒品案件，經本院以96年度毒聲字第\n    172 號裁定送觀察、勒戒後，認有繼續施用毒品傾向，由本\n    院以96年度毒聲字第229 號裁定令入戒治處所，施以強制戒\n    治6 個月以上，最長不得逾1 年。周永忠於96年7 月17日入\n    臺灣臺中戒治所執行戒治後，於97年4 月18日停止戒治出所\n    ，並於97年4 月29日強制戒治期滿，復經臺灣苗栗地方法院\n    檢察署檢察官於97年5 月6 日以97年度毒偵字第24號不起訴\n    處分確定。\n（三）詎猶不知悔改，復基於施用第2級毒品之犯意，於99年9月\n      11日晚上，在不詳地點，施用毒品2級安非他命1次。嗣於\n      同年月12日下午6時40分許，在苗栗縣苗栗市新川里8鄰西\n      角坪20號前為警盤查，經周永忠同意採尿後，送驗呈安非\n      他命、甲基安非他命陽性反應。\n二、證據論述：\n    除增加被告於本院審理時之自白、臺灣高等法院被告前案紀\n    錄表1 份，及刪除起訴書證據並所犯法條欄內有關被告否認\n    犯行的陳述外，其餘均引用起訴書證據並所犯法條欄內所載\n    的證據（如附件）。\n三、論罪科刑：\n    核被告所為，係犯毒品危害防制條例第10條第2 項之施用第\n    二級毒品罪。又其持有第二級毒品後進而施用，持有之低度\n    行為，為施用之高度行為所吸收，均不另論罪。又其有事實\n    欄所載之前科素行，於民國99年7 月31日假釋付保護管束期\n    滿執行完畢，此有臺灣高等法院被告前案紀錄表1份在卷可\n    佐，是其於上述有期徒刑執行完畢後，5 年內故意再犯本件\n    上述有期徒刑以上的罪，為累犯，應依刑法第47條第1 項規\n    定，加重其刑。爰審酌被告曾因施用毒品而觸法，經觀察、\n    勒戒、強制戒治執行完畢釋放後，復因施用毒品案件經法院\n    判決確定執行完畢後，再次施用上述毒品，難認有悔悟之心\n    。復斟酌其施用毒品對個人身心戕害甚鉅，且未危害他人。\n    再衡酌其犯罪之動機、智識程度、所生危害、犯後坦承犯行\n    之態度等一切情狀，量處如主文所示之刑，並諭知易科罰金\n    之折算標準。至檢察官具體求處有期徒刑6 月，茲因被告於\n    審理時坦承犯行，節省有限的司法資源，犯後態度尚佳，因\n    認檢察官的求刑稍嫌過重，略予調減，附此敘明。\n四、應適用之法條：\n（一）刑事訴訟法第284條之1、第273條之1第1項、第299條第1\n      項前段、第310條之2、第454條第2項。\n（二）毒品危害防制條例第10條第2 項。\n（三）刑法第11條前段、第47條第1 項、第41條第1 項前段。\n本案經檢察官林文中到庭執行職務。\n中    華    民    國    100   年    5     月    31    日\n                  刑事第一庭  法  官  呂曾達\n以上正本證明與原本無異。\n如不服本判決應於收受判決後10日內向本院提出上訴書狀，並應\n敘述具體理由。其未敘述上訴理由者，應於上訴期間屆滿後20日\n內向本院補提理由書（均須按他造當事人之人數附繕本）「切勿\n逕送上級法院」。告訴人或被害人如對本判決不服者，應具備理\n由請求檢察官上訴，其上訴期間之計算係以檢察官收受判決正本\n之日期為準。\n                              書記官  劉容辰\n中    華    民    國   100    年    5     月    31    日\n附錄論罪科刑法條\n毒品危害防制條例第10條第2 項：\n施用第二級毒品者，處 3 年以下有期徒刑。",
  "structure": {
    "main": "周永忠施用第二級毒品，累犯，處有期徒刑伍月，如易科罰金，\n以新臺幣壹仟元折算壹日。",
    "fact": "一、犯罪事實：\n（一）周永忠前於：\n  民國95年間，因犯竊盜罪，經本院判處有期徒刑9月、9月，\n    應執行有期徒刑1年確定（95年度易字第159號）。\n  復於95年間，因犯竊盜罪，經本院判處有期徒刑7 月確定（\n    96年度易字第221號）。\n  復於95年間，因犯贓物、竊盜、偽造文書罪，分別經本院判\n    處有期徒刑10月、1年6月、6月、10月、6月，減為有期徒刑\n    5月、9月、3月、5月、3月，應執行有期徒刑2年確定（96年\n    度易字第1069號）。\n  上開、案，嗣因適用中華民國九十六年罪犯減刑條例，\n    經本院以96年聲減字第104號、97年聲字第945號裁定分別減\n    為3月、3月、3月15日、4月15日、4月15日、9月、5月、5月\n    ，應執行有期徒刑2年8月確定，並與前揭所示之有期徒刑\n    2年接續執行，甫於99年7月31日假釋付保護管束期滿執行完\n    畢。\n（二）周永忠前於：\n    95年間，因施用第二級毒品案件，經本院以96年度毒聲字第\n    172 號裁定送觀察、勒戒後，認有繼續施用毒品傾向，由本\n    院以96年度毒聲字第229 號裁定令入戒治處所，施以強制戒\n    治6 個月以上，最長不得逾1 年。周永忠於96年7 月17日入\n    臺灣臺中戒治所執行戒治後，於97年4 月18日停止戒治出所\n    ，並於97年4 月29日強制戒治期滿，復經臺灣苗栗地方法院\n    檢察署檢察官於97年5 月6 日以97年度毒偵字第24號不起訴\n    處分確定。\n（三）詎猶不知悔改，復基於施用第2級毒品之犯意，於99年9月\n      11日晚上，在不詳地點，施用毒品2級安非他命1次。嗣於\n      同年月12日下午6時40分許，在苗栗縣苗栗市新川里8鄰西\n      角坪20號前為警盤查，經周永忠同意採尿後，送驗呈安非\n      他命、甲基安非他命陽性反應。\n二、證據論述：\n    除增加被告於本院審理時之自白、臺灣高等法院被告前案紀\n    錄表1 份，及刪除起訴書證據並所犯法條欄內有關被告否認\n    犯行的陳述外，其餘均引用起訴書證據並所犯法條欄內所載\n    的證據（如附件）。\n三、論罪科刑：\n    核被告所為，係犯毒品危害防制條例第10條第2 項之施用第\n    二級毒品罪。又其持有第二級毒品後進而施用，持有之低度\n    行為，為施用之高度行為所吸收，均不另論罪。又其有事實\n    欄所載之前科素行，於民國99年7 月31日假釋付保護管束期\n    滿執行完畢，此有臺灣高等法院被告前案紀錄表1份在卷可\n    佐，是其於上述有期徒刑執行完畢後，5 年內故意再犯本件\n    上述有期徒刑以上的罪，為累犯，應依刑法第47條第1 項規\n    定，加重其刑。爰審酌被告曾因施用毒品而觸法，經觀察、\n    勒戒、強制戒治執行完畢釋放後，復因施用毒品案件經法院\n    判決確定執行完畢後，再次施用上述毒品，難認有悔悟之心\n    。復斟酌其施用毒品對個人身心戕害甚鉅，且未危害他人。\n    再衡酌其犯罪之動機、智識程度、所生危害、犯後坦承犯行\n    之態度等一切情狀，量處如主文所示之刑，並諭知易科罰金\n    之折算標準。至檢察官具體求處有期徒刑6 月，茲因被告於\n    審理時坦承犯行，節省有限的司法資源，犯後態度尚佳，因\n    認檢察官的求刑稍嫌過重，略予調減，附此敘明。\n四、應適用之法條：\n（一）刑事訴訟法第284條之1、第273條之1第1項、第299條第1\n      項前段、第310條之2、第454條第2項。\n（二）毒品危害防制條例第10條第2 項。\n（三）刑法第11條前段、第47條第1 項、第41條第1 項前段。\n本案經檢察官林文中到庭執行職務。",
    "reason": "一、犯罪事實：\n（一）周永忠前於：\n  民國95年間，因犯竊盜罪，經本院判處有期徒刑9月、9月，\n    應執行有期徒刑1年確定（95年度易字第159號）。\n  復於95年間，因犯竊盜罪，經本院判處有期徒刑7 月確定（\n    96年度易字第221號）。\n  復於95年間，因犯贓物、竊盜、偽造文書罪，分別經本院判\n    處有期徒刑10月、1年6月、6月、10月、6月，減為有期徒刑\n    5月、9月、3月、5月、3月，應執行有期徒刑2年確定（96年\n    度易字第1069號）。\n  上開、案，嗣因適用中華民國九十六年罪犯減刑條例，\n    經本院以96年聲減字第104號、97年聲字第945號裁定分別減\n    為3月、3月、3月15日、4月15日、4月15日、9月、5月、5月\n    ，應執行有期徒刑2年8月確定，並與前揭所示之有期徒刑\n    2年接續執行，甫於99年7月31日假釋付保護管束期滿執行完\n    畢。\n（二）周永忠前於：\n    95年間，因施用第二級毒品案件，經本院以96年度毒聲字第\n    172 號裁定送觀察、勒戒後，認有繼續施用毒品傾向，由本\n    院以96年度毒聲字第229 號裁定令入戒治處所，施以強制戒\n    治6 個月以上，最長不得逾1 年。周永忠於96年7 月17日入\n    臺灣臺中戒治所執行戒治後，於97年4 月18日停止戒治出所\n    ，並於97年4 月29日強制戒治期滿，復經臺灣苗栗地方法院\n    檢察署檢察官於97年5 月6 日以97年度毒偵字第24號不起訴\n    處分確定。\n（三）詎猶不知悔改，復基於施用第2級毒品之犯意，於99年9月\n      11日晚上，在不詳地點，施用毒品2級安非他命1次。嗣於\n      同年月12日下午6時40分許，在苗栗縣苗栗市新川里8鄰西\n      角坪20號前為警盤查，經周永忠同意採尿後，送驗呈安非\n      他命、甲基安非他命陽性反應。\n二、證據論述：\n    除增加被告於本院審理時之自白、臺灣高等法院被告前案紀\n    錄表1 份，及刪除起訴書證據並所犯法條欄內有關被告否認\n    犯行的陳述外，其餘均引用起訴書證據並所犯法條欄內所載\n    的證據（如附件）。\n三、論罪科刑：\n    核被告所為，係犯毒品危害防制條例第10條第2 項之施用第\n    二級毒品罪。又其持有第二級毒品後進而施用，持有之低度\n    行為，為施用之高度行為所吸收，均不另論罪。又其有事實\n    欄所載之前科素行，於民國99年7 月31日假釋付保護管束期\n    滿執行完畢，此有臺灣高等法院被告前案紀錄表1份在卷可\n    佐，是其於上述有期徒刑執行完畢後，5 年內故意再犯本件\n    上述有期徒刑以上的罪，為累犯，應依刑法第47條第1 項規\n    定，加重其刑。爰審酌被告曾因施用毒品而觸法，經觀察、\n    勒戒、強制戒治執行完畢釋放後，復因施用毒品案件經法院\n    判決確定執行完畢後，再次施用上述毒品，難認有悔悟之心\n    。復斟酌其施用毒品對個人身心戕害甚鉅，且未危害他人。\n    再衡酌其犯罪之動機、智識程度、所生危害、犯後坦承犯行\n    之態度等一切情狀，量處如主文所示之刑，並諭知易科罰金\n    之折算標準。至檢察官具體求處有期徒刑6 月，茲因被告於\n    審理時坦承犯行，節省有限的司法資源，犯後態度尚佳，因\n    認檢察官的求刑稍嫌過重，略予調減，附此敘明。\n四、應適用之法條：\n（一）刑事訴訟法第284條之1、第273條之1第1項、第299條第1\n      項前段、第310條之2、第454條第2項。\n（二）毒品危害防制條例第10條第2 項。\n（三）刑法第11條前段、第47條第1 項、第41條第1 項前段。\n本案經檢察官林文中到庭執行職務。"
  },
  "search": "臺灣苗栗地方法院刑事判決100年度易字第23號公訴人臺灣苗栗地方法院檢察署檢察官被告周永忠上列被告因毒品危害防制條例案件，經檢察官提起公訴（100年度毒偵字第1653號），本院以簡式審判程序審理，判決如下：主文周永忠施用第二級毒品，累犯，處有期徒刑伍月，如易科罰金，以新臺幣壹仟元折算壹日。犯罪事實及理由一、犯罪事實：（一）周永忠前於：民國95年間，因犯竊盜罪，經本院判處有期徒刑9月、9月，應執行有期徒刑1年確定（95年度易字第159號）。復於95年間，因犯竊盜罪，經本院判處有期徒刑7月確定（96年度易字第221號）。復於95年間，因犯贓物、竊盜、偽造文書罪，分別經本院判處有期徒刑10月、1年6月、6月、10月、6月，減為有期徒刑5月、9月、3月、5月、3月，應執行有期徒刑2年確定（96年度易字第1069號）。上開、案，嗣因適用中華民國九十六年罪犯減刑條例，經本院以96年聲減字第104號、97年聲字第945號裁定分別減為3月、3月、3月15日、4月15日、4月15日、9月、5月、5月，應執行有期徒刑2年8月確定，並與前揭所示之有期徒刑2年接續執行，甫於99年7月31日假釋付保護管束期滿執行完畢。（二）周永忠前於：95年間，因施用第二級毒品案件，經本院以96年度毒聲字第172號裁定送觀察、勒戒後，認有繼續施用毒品傾向，由本院以96年度毒聲字第229號裁定令入戒治處所，施以強制戒治6個月以上，最長不得逾1年。周永忠於96年7月17日入臺灣臺中戒治所執行戒治後，於97年4月18日停止戒治出所，並於97年4月29日強制戒治期滿，復經臺灣苗栗地方法院檢察署檢察官於97年5月6日以97年度毒偵字第24號不起訴處分確定。（三）詎猶不知悔改，復基於施用第2級毒品之犯意，於99年9月11日晚上，在不詳地點，施用毒品2級安非他命1次。嗣於同年月12日下午6時40分許，在苗栗縣苗栗市新川里8鄰西角坪20號前為警盤查，經周永忠同意採尿後，送驗呈安非他命、甲基安非他命陽性反應。二、證據論述：除增加被告於本院審理時之自白、臺灣高等法院被告前案紀錄表1份，及刪除起訴書證據並所犯法條欄內有關被告否認犯行的陳述外，其餘均引用起訴書證據並所犯法條欄內所載的證據（如附件）。三、論罪科刑：核被告所為，係犯毒品危害防制條例第10條第2項之施用第二級毒品罪。又其持有第二級毒品後進而施用，持有之低度行為，為施用之高度行為所吸收，均不另論罪。又其有事實欄所載之前科素行，於民國99年7月31日假釋付保護管束期滿執行完畢，此有臺灣高等法院被告前案紀錄表1份在卷可佐，是其於上述有期徒刑執行完畢後，5年內故意再犯本件上述有期徒刑以上的罪，為累犯，應依刑法第47條第1項規定，加重其刑。爰審酌被告曾因施用毒品而觸法，經觀察、勒戒、強制戒治執行完畢釋放後，復因施用毒品案件經法院判決確定執行完畢後，再次施用上述毒品，難認有悔悟之心。復斟酌其施用毒品對個人身心戕害甚鉅，且未危害他人。再衡酌其犯罪之動機、智識程度、所生危害、犯後坦承犯行之態度等一切情狀，量處如主文所示之刑，並諭知易科罰金之折算標準。至檢察官具體求處有期徒刑6月，茲因被告於審理時坦承犯行，節省有限的司法資源，犯後態度尚佳，因認檢察官的求刑稍嫌過重，略予調減，附此敘明。四、應適用之法條：（一）刑事訴訟法第284條之1、第273條之1第1項、第299條第1項前段、第310條之2、第454條第2項。（二）毒品危害防制條例第10條第2項。（三）刑法第11條前段、第47條第1項、第41條第1項前段。本案經檢察官林文中到庭執行職務。中華民國100年5月31日刑事第一庭法官呂曾達以上正本證明與原本無異。如不服本判決應於收受判決後10日內向本院提出上訴書狀，並應敘述具體理由。其未敘述上訴理由者，應於上訴期間屆滿後20日內向本院補提理由書（均須按他造當事人之人數附繕本）「切勿逕送上級法院」。告訴人或被害人如對本判決不服者，應具備理由請求檢察官上訴，其上訴期間之計算係以檢察官收受判決正本之日期為準。書記官劉容辰中華民國100年5月31日附錄論罪科刑法條毒品危害防制條例第10條第2項：施用第二級毒品者，處3年以下有期徒刑。",
  "characters": {
    "judges": [
      "呂曾達"
    ],
    "prosecutors": [
      "林文中"
    ],
    "lawyers": [

    ],
    "clerks": [
      "劉容辰"
    ],
    "plaintiffs": [

    ],
    "defendants": [
      "周永忠"
    ],
    "prosecutor_office": [
      "臺灣苗栗地方法院檢察署檢察官"
    ],
    "creditors": [

    ],
    "debtors": [

    ],
    "judicial_associate_officer": [

    ]
  },
  "adjudged_at": "2011-05-31",
  "created_at": "2016-02-12 01:21:16",
  "updated_at": "2016-02-12 01:21:16"
}