{
  "identify": "SLD-100-聲-832-20110531-1",
  "court": {
    "name": "臺灣士林地方法院",
    "code": "SLD"
  },
  "division": {
    "name": "刑事",
    "code": "M"
  },
  "year": 100,
  "word": "聲",
  "number": "832",
  "jcheck": "1",
  "reason": "宣告沒收",
  "content": "臺灣士林地方法院刑事裁定              100年度聲字第832號\n聲  請  人  臺灣士林地方法院檢察署檢察官\n受  刑  人  李培佳\n即  被  告\n            楊忠庚\n上列聲請人聲請宣告沒收案件（100 年度執聲字第529 號），本\n院裁定如下：\n    主  文\n扣案如附表所示仿冒商標之物均沒收。\n    理  由\n一、按違禁物或專科沒收之物得單獨宣告沒收，刑法第40條第2\n    項定有明文。次按商標法第83條規定，犯前2 條之罪所製造\n    、販賣、陳列、輸出或輸入之商品，或所提供於服務使用之\n    物品或文書，不問屬於犯人與否，沒收之。\n二、聲請意旨略以：本件被告李培佳、楊忠庚因違反商標法案件\n    ，業經臺灣士林地方法院檢察署檢察官以99年度偵字第1825\n    號聲請簡易判決處刑，經鈞院以100 年度士簡字第937 號判\n    處有期徒刑3 月，緩刑2 年，嗣經鈞院以100 年度審智簡上\n    字第1 號判決上訴駁回確定，扣案之購得仿冒品共9 件（99\n    年保管字第1191號），為被告所有供犯商標法第82條之罪所\n    用之物，爰依法聲請宣告沒收等語。\n三、查被告李培佳、楊忠庚因違反商標法案件，業經臺灣士林地\n    方法院檢察署檢察官以99年度偵字第1825 號 聲請簡易判決\n    處刑，經本院以100 年度士簡字第937 號判處有期徒刑3 月\n    ，緩刑2 年，嗣經本院以100 年度審智簡上字第1 號判決上\n    訴駁回確定，有上開聲請簡易判決處刑書、刑事簡易判決、\n    刑事判決各1 份在卷可稽。而扣案之「小熊維尼」筆、「米\n    老鼠」筆、「米妮」餐具、哆啦A 夢筷子及置物盒、哆啦A\n    夢輕觸式筆、HELLO KITTY 筷子及置物盒、小丸子書夾各1\n    件均係仿冒品等情，有鑑定報告書共4 份附卷可憑。揆諸上\n    開說明，聲請人聲請宣告沒收，核與上開規定相符，應予准\n    許，爰裁定如主文。至扣案之HELLO KITTY 筆、MY MELODY\n    筆各1 件，並非仿冒品等情，有侵權仿冒品鑑定報告在卷可\n    參（見99年度偵字第1825號卷第17頁至第20頁），爰不予宣\n    告沒收，附此說明。\n中    華    民    國   100    年    5     月    31    日\n                  刑事第八庭法  官  高雅敏\n以上正本證明與原本無異。\n如不服本裁定，應於送達後5日內，向本院提出抗告狀。\n                            書記官  陳映羽\n中    華    民    國   100    年    5     月    31    日\n附表：\n ┌──┬────────────────┬───┐\n │編號│扣案仿冒商標之物                │數量  │\n ├──┼────────────────┼───┤\n │ 一 │仿冒「小熊維尼」筆              │1 件  │\n ├──┼────────────────┼───┤\n │ 二 │仿冒「米老鼠」筆                │1 件  │\n ├──┼────────────────┼───┤\n │ 三 │仿冒「米妮」餐具                │1 件  │\n ├──┼────────────────┼───┤\n │ 四 │仿冒「哆啦A 夢」筷子及置物盒    │1 件  │\n ├──┼────────────────┼───┤\n │ 五 │仿冒「哆啦A夢」輕觸式筆         │1 件  │\n ├──┼────────────────┼───┤\n │ 六 │仿冒「HELLO KITTY 」筷子及置物盒│1 件  │\n ├──┼────────────────┼───┤\n │ 七 │仿冒「小丸子」書夾              │1 件  │\n └──┴────────────────┴───┘",
  "structure": {
    "main": "扣案如附表所示仿冒商標之物均沒收。",
    "reason": "一、按違禁物或專科沒收之物得單獨宣告沒收，刑法第40條第2\n    項定有明文。次按商標法第83條規定，犯前2 條之罪所製造\n    、販賣、陳列、輸出或輸入之商品，或所提供於服務使用之\n    物品或文書，不問屬於犯人與否，沒收之。\n二、聲請意旨略以：本件被告李培佳、楊忠庚因違反商標法案件\n    ，業經臺灣士林地方法院檢察署檢察官以99年度偵字第1825\n    號聲請簡易判決處刑，經鈞院以100 年度士簡字第937 號判\n    處有期徒刑3 月，緩刑2 年，嗣經鈞院以100 年度審智簡上\n    字第1 號判決上訴駁回確定，扣案之購得仿冒品共9 件（99\n    年保管字第1191號），為被告所有供犯商標法第82條之罪所\n    用之物，爰依法聲請宣告沒收等語。\n三、查被告李培佳、楊忠庚因違反商標法案件，業經臺灣士林地\n    方法院檢察署檢察官以99年度偵字第1825 號 聲請簡易判決\n    處刑，經本院以100 年度士簡字第937 號判處有期徒刑3 月\n    ，緩刑2 年，嗣經本院以100 年度審智簡上字第1 號判決上\n    訴駁回確定，有上開聲請簡易判決處刑書、刑事簡易判決、\n    刑事判決各1 份在卷可稽。而扣案之「小熊維尼」筆、「米\n    老鼠」筆、「米妮」餐具、哆啦A 夢筷子及置物盒、哆啦A\n    夢輕觸式筆、HELLO KITTY 筷子及置物盒、小丸子書夾各1\n    件均係仿冒品等情，有鑑定報告書共4 份附卷可憑。揆諸上\n    開說明，聲請人聲請宣告沒收，核與上開規定相符，應予准\n    許，爰裁定如主文。至扣案之HELLO KITTY 筆、MY MELODY\n    筆各1 件，並非仿冒品等情，有侵權仿冒品鑑定報告在卷可\n    參（見99年度偵字第1825號卷第17頁至第20頁），爰不予宣\n    告沒收，附此說明。"
  },
  "search": "臺灣士林地方法院刑事裁定100年度聲字第832號聲請人臺灣士林地方法院檢察署檢察官受刑人李培佳即被告楊忠庚上列聲請人聲請宣告沒收案件（100年度執聲字第529號），本院裁定如下：主文扣案如附表所示仿冒商標之物均沒收。理由一、按違禁物或專科沒收之物得單獨宣告沒收，刑法第40條第2項定有明文。次按商標法第83條規定，犯前2條之罪所製造、販賣、陳列、輸出或輸入之商品，或所提供於服務使用之物品或文書，不問屬於犯人與否，沒收之。二、聲請意旨略以：本件被告李培佳、楊忠庚因違反商標法案件，業經臺灣士林地方法院檢察署檢察官以99年度偵字第1825號聲請簡易判決處刑，經鈞院以100年度士簡字第937號判處有期徒刑3月，緩刑2年，嗣經鈞院以100年度審智簡上字第1號判決上訴駁回確定，扣案之購得仿冒品共9件（99年保管字第1191號），為被告所有供犯商標法第82條之罪所用之物，爰依法聲請宣告沒收等語。三、查被告李培佳、楊忠庚因違反商標法案件，業經臺灣士林地方法院檢察署檢察官以99年度偵字第1825號聲請簡易判決處刑，經本院以100年度士簡字第937號判處有期徒刑3月，緩刑2年，嗣經本院以100年度審智簡上字第1號判決上訴駁回確定，有上開聲請簡易判決處刑書、刑事簡易判決、刑事判決各1份在卷可稽。而扣案之「小熊維尼」筆、「米老鼠」筆、「米妮」餐具、哆啦A夢筷子及置物盒、哆啦A夢輕觸式筆、HELLOKITTY筷子及置物盒、小丸子書夾各1件均係仿冒品等情，有鑑定報告書共4份附卷可憑。揆諸上開說明，聲請人聲請宣告沒收，核與上開規定相符，應予准許，爰裁定如主文。至扣案之HELLOKITTY筆、MYMELODY筆各1件，並非仿冒品等情，有侵權仿冒品鑑定報告在卷可參（見99年度偵字第1825號卷第17頁至第20頁），爰不予宣告沒收，附此說明。中華民國100年5月31日刑事第八庭法官高雅敏以上正本證明與原本無異。如不服本裁定，應於送達後5日內，向本院提出抗告狀。書記官陳映羽中華民國100年5月31日附表：┌──┬────────────────┬───┐│編號│扣案仿冒商標之物│數量│├──┼────────────────┼───┤│一│仿冒「小熊維尼」筆│1件│├──┼────────────────┼───┤│二│仿冒「米老鼠」筆│1件│├──┼────────────────┼───┤│三│仿冒「米妮」餐具│1件│├──┼────────────────┼───┤│四│仿冒「哆啦A夢」筷子及置物盒│1件│├──┼────────────────┼───┤│五│仿冒「哆啦A夢」輕觸式筆│1件│├──┼────────────────┼───┤│六│仿冒「HELLOKITTY」筷子及置物盒│1件│├──┼────────────────┼───┤│七│仿冒「小丸子」書夾│1件│└──┴────────────────┴───┘",
  "characters": {
    "judges": [
      "高雅敏"
    ],
    "prosecutors": [

    ],
    "lawyers": [

    ],
    "clerks": [
      "陳映羽"
    ],
    "plaintiffs": [

    ],
    "defendants": [
      "楊忠庚"
    ],
    "prosecutor_office": [
      "臺灣士林地方法院檢察署檢察官"
    ],
    "creditors": [

    ],
    "debtors": [

    ],
    "judicial_associate_officer": [

    ]
  },
  "adjudged_at": "2011-05-31",
  "created_at": "2016-02-12 01:21:50",
  "updated_at": "2016-02-12 01:21:50"
}