{
  "identify": "PTD-93-訴-464-20040813-3",
  "court": {
    "name": "臺灣屏東地方法院",
    "code": "PTD"
  },
  "division": {
    "name": "刑事",
    "code": "M"
  },
  "year": 93,
  "word": "訴",
  "number": "464",
  "jcheck": "3",
  "reason": "違反毒品危害防制條例",
  "content": "臺灣屏東地方法院刑事判決                          九十三年度訴字第四六四號\n    公  訴  人  臺灣屏東地方法院檢察署檢察官\n    被      告  甲○○\n右列被告因違反毒品危害防制條例案件，經檢察官提起公訴（九十三年度毒偵字第九\n○七號），本院裁定以簡式審判程序審理，判決如左：\n     主  文\n甲○○施用第一級毒品，累犯，處有期徒刑捌月。又施用第二級毒品，累犯，處有期\n徒刑肆月。應執行有期徒刑拾月。\n     事  實\n一、甲○○曾於民國八十八年間因違反毒品危害防制條例案件，經本院潮州簡易庭於\n    八十八年六月二十二日，以八十八年潮簡字第一二九號判決判處有期徒刑六月，\n    如易科罰金，以三百元折算一日確定，於八十九年六月七日易科罰金執行完畢。\n    其於八十七年間且因施用毒品案件，經本院裁定觀察勒戒後，認無繼續施用毒品\n    傾向，由臺灣屏東地方法院檢察署檢察官於八十七年七月三十日，以八十七年偵\n    字第四六一九號不起訴處分確定。又於八十八年間因施用毒品案件，經本院裁定\n    觀察勒戒後，認有繼續施用毒品傾向，再經裁定令入戒治處所施以強制戒治，並\n    由本院潮州簡易庭於八十八年六月二十二日，以八十八年潮簡字第一二九號判決\n    判處有期徒刑六月，如易科罰金，以三百元折算一日確定，仍不知悔改，復基於\n    施用第一級毒品海洛因之犯意，於九十三年二月十三日十四時許，在其位於屏東\n    縣恆春鎮○○路一九四巷二五號住處，將香煙捲紙內部分煙草撥出，填入海洛因\n    粉末後，點燃香煙吸食之方式，施用海洛因一次。又另行起意，基於施用第二級\n    毒品安非他命之犯意，於九十三年二月十三日十六時許，在其友人位於高雄縣林\n    園鄉○○路四十巷六號住處，將安非他命置入玻璃管內，點火燒烤玻璃管，吸食\n    安非他命遇熱產生之煙氣之方式，施用安非他命一次。嗣警方於九十三年二月十\n    三日十七時許，在高雄縣林園鄉○○路四十巷六號查緝毒品案件時，因甲○○亦\n    在現場，經警方徵得其同意，於同日十九時三十分許採集其尿液送驗而查獲上情\n    。\n二、案經嘉義市警察局第一分局報請臺灣高雄地方法院檢察署呈由臺灣高等法院高雄\n    分院檢察署令轉臺灣屏東地方法院檢察署檢察官偵查起訴。\n     理  由\n一、上述事實，業經被告甲○○於本院審理時坦白承認，而被告於九十三年二月十三\n    日經警採尿送驗結果，呈嗎啡（即海洛因水解後之反應）及甲基安非他命陽性反\n    應，有嘉義市衛生局檢驗涉嫌毒品及管制藥品之尿液檢驗結果及長榮大學確認報\n    告各一紙在卷可佐，此為檢驗機關本於專業知識及以精密儀器測試所得之結論，\n    自可憑信，足見被告之自白與事實相符，可以採信，其於上述時地施用第一級毒\n    品海洛因及第二級毒品安非他命各一次之事實，應可認定。又被告曾於八十七年\n    間因施用毒品案件，經本院裁定觀察勒戒後，認無繼續施用毒品傾向，由臺灣屏\n    東地方法院檢察署檢察官於八十七年七月三十日，以八十七年偵字第四六一九號\n    不起訴處分確定。又於八十八年間因施用毒品案件，經本院裁定觀察勒戒後，認\n    有繼續施用毒品傾向，再經裁定令入戒治處所施以強制戒治，並由本院潮州簡易\n    庭於八十八年六月二十二日，以八十八年潮簡字第一二九號判決判處有期徒刑六\n    月，如易科罰金，以三百元折算一日確定等情，有臺灣屏東地方法院檢察署刑案\n    資料查註紀錄表及臺灣高等法院被告全國前案紀錄表各一紙在卷足憑，事證明確\n    ，被告犯行堪予認定。\n二、查海洛因、安非他命分別為毒品危害防制條例第二條第一項第一款、第二款所稱\n    之第一級、第二級毒品，被告甲○○竟持以施用，核其所為，係犯同條例第十條\n    第一項之施用第一級毒品罪及同條第二項之施用第二級毒品罪。其施用前持有第\n    一級毒品海洛因、第二級毒品安非他命之低度行為，應為施用之高度行為所吸收\n    ，均不另論罪。其所犯上述二罪，犯意各別，行為互異，應予分別論罪，合併處\n    罰。其曾於八十八年間因違反毒品危害防制條例案件，經本院潮州簡易庭於八十\n    八年六月二十二日，以八十八年潮簡字第一二九號判決判處有期徒刑六月，如易\n    科罰金，以三百元折算一日確定，於八十九年六月七日易科罰金執行完畢，有臺\n    灣高等法院被告全國前案紀錄表及臺灣屏東地方法院檢察署刑案資料查註紀錄表\n    各一紙在卷可供參考，其受有期徒刑之執行完畢後，五年之內再犯有期徒刑以上\n    刑之上述二罪，均為累犯，均應依法加重其刑。爰審酌被告曾有違反毒品危害防\n    制條例前科之素行、經執行觀察勒戒及強制戒治後仍未戒除毒癮、施用第一級毒\n    品海洛因與第二級毒品安非他命各一次、施用毒品嚴重危害其身心健康及犯罪後\n    坦認犯行，態度尚可等一切情狀，分別量處如主文所示之刑，並定其應執行之刑\n    。至被告持以施用毒品所用之點火工具及玻璃管等物均未扣案，亦無證據證明該\n    等物品係被告所有且現尚存在，均不併予宣告沒收。\n據上論斷，應依刑事訴訟法第二百七十三條之一、第二百九十九條第一項前段，毒品\n危害防制條例第十條第一項、第二項，刑法第十一條、第四十七條、第五十一條第五\n款，判決如主文。\n中      華      民      國      九十三      年    八    月    十三    日\n                                      臺灣屏東地方法院刑事第二庭\n                                          法  官  林昌義\n右正本證明與原本無異。\n如不服本判決應於收受本判決送達後十日內向本院提出上訴書狀，其未敘述上訴理由\n者，並得於提起上訴後十日內向本院補提理由書狀（均須按他造當事人之人數附繕本\n ）「切勿逕送上級法院」\n                                          書記官   潘美碧\n中      華      民      國      九十三      年    八    月    十三    日\n附錄論罪科刑法條全文\n毒品危害防制條例第十條\n施用第一級毒品者，處六月以上五年以下有期徒刑。\n施用第二級毒品者，處三年以下有期徒刑。\n",
  "structure": {
    "main": "甲○○施用第一級毒品，累犯，處有期徒刑捌月。又施用第二級毒品，累犯，處有期\n徒刑肆月。應執行有期徒刑拾月。",
    "fact": "一、甲○○曾於民國八十八年間因違反毒品危害防制條例案件，經本院潮州簡易庭於\n    八十八年六月二十二日，以八十八年潮簡字第一二九號判決判處有期徒刑六月，\n    如易科罰金，以三百元折算一日確定，於八十九年六月七日易科罰金執行完畢。\n    其於八十七年間且因施用毒品案件，經本院裁定觀察勒戒後，認無繼續施用毒品\n    傾向，由臺灣屏東地方法院檢察署檢察官於八十七年七月三十日，以八十七年偵\n    字第四六一九號不起訴處分確定。又於八十八年間因施用毒品案件，經本院裁定\n    觀察勒戒後，認有繼續施用毒品傾向，再經裁定令入戒治處所施以強制戒治，並\n    由本院潮州簡易庭於八十八年六月二十二日，以八十八年潮簡字第一二九號判決\n    判處有期徒刑六月，如易科罰金，以三百元折算一日確定，仍不知悔改，復基於\n    施用第一級毒品海洛因之犯意，於九十三年二月十三日十四時許，在其位於屏東\n    縣恆春鎮○○路一九四巷二五號住處，將香煙捲紙內部分煙草撥出，填入海洛因\n    粉末後，點燃香煙吸食之方式，施用海洛因一次。又另行起意，基於施用第二級\n    毒品安非他命之犯意，於九十三年二月十三日十六時許，在其友人位於高雄縣林\n    園鄉○○路四十巷六號住處，將安非他命置入玻璃管內，點火燒烤玻璃管，吸食\n    安非他命遇熱產生之煙氣之方式，施用安非他命一次。嗣警方於九十三年二月十\n    三日十七時許，在高雄縣林園鄉○○路四十巷六號查緝毒品案件時，因甲○○亦\n    在現場，經警方徵得其同意，於同日十九時三十分許採集其尿液送驗而查獲上情\n    。\n二、案經嘉義市警察局第一分局報請臺灣高雄地方法院檢察署呈由臺灣高等法院高雄\n    分院檢察署令轉臺灣屏東地方法院檢察署檢察官偵查起訴。",
    "reason": "一、上述事實，業經被告甲○○於本院審理時坦白承認，而被告於九十三年二月十三\n    日經警採尿送驗結果，呈嗎啡（即海洛因水解後之反應）及甲基安非他命陽性反\n    應，有嘉義市衛生局檢驗涉嫌毒品及管制藥品之尿液檢驗結果及長榮大學確認報\n    告各一紙在卷可佐，此為檢驗機關本於專業知識及以精密儀器測試所得之結論，\n    自可憑信，足見被告之自白與事實相符，可以採信，其於上述時地施用第一級毒\n    品海洛因及第二級毒品安非他命各一次之事實，應可認定。又被告曾於八十七年\n    間因施用毒品案件，經本院裁定觀察勒戒後，認無繼續施用毒品傾向，由臺灣屏\n    東地方法院檢察署檢察官於八十七年七月三十日，以八十七年偵字第四六一九號\n    不起訴處分確定。又於八十八年間因施用毒品案件，經本院裁定觀察勒戒後，認\n    有繼續施用毒品傾向，再經裁定令入戒治處所施以強制戒治，並由本院潮州簡易\n    庭於八十八年六月二十二日，以八十八年潮簡字第一二九號判決判處有期徒刑六\n    月，如易科罰金，以三百元折算一日確定等情，有臺灣屏東地方法院檢察署刑案\n    資料查註紀錄表及臺灣高等法院被告全國前案紀錄表各一紙在卷足憑，事證明確\n    ，被告犯行堪予認定。\n二、查海洛因、安非他命分別為毒品危害防制條例第二條第一項第一款、第二款所稱\n    之第一級、第二級毒品，被告甲○○竟持以施用，核其所為，係犯同條例第十條\n    第一項之施用第一級毒品罪及同條第二項之施用第二級毒品罪。其施用前持有第\n    一級毒品海洛因、第二級毒品安非他命之低度行為，應為施用之高度行為所吸收\n    ，均不另論罪。其所犯上述二罪，犯意各別，行為互異，應予分別論罪，合併處\n    罰。其曾於八十八年間因違反毒品危害防制條例案件，經本院潮州簡易庭於八十\n    八年六月二十二日，以八十八年潮簡字第一二九號判決判處有期徒刑六月，如易\n    科罰金，以三百元折算一日確定，於八十九年六月七日易科罰金執行完畢，有臺\n    灣高等法院被告全國前案紀錄表及臺灣屏東地方法院檢察署刑案資料查註紀錄表\n    各一紙在卷可供參考，其受有期徒刑之執行完畢後，五年之內再犯有期徒刑以上\n    刑之上述二罪，均為累犯，均應依法加重其刑。爰審酌被告曾有違反毒品危害防\n    制條例前科之素行、經執行觀察勒戒及強制戒治後仍未戒除毒癮、施用第一級毒\n    品海洛因與第二級毒品安非他命各一次、施用毒品嚴重危害其身心健康及犯罪後\n    坦認犯行，態度尚可等一切情狀，分別量處如主文所示之刑，並定其應執行之刑\n    。至被告持以施用毒品所用之點火工具及玻璃管等物均未扣案，亦無證據證明該\n    等物品係被告所有且現尚存在，均不併予宣告沒收。\n據上論斷，應依刑事訴訟法第二百七十三條之一、第二百九十九條第一項前段，毒品\n危害防制條例第十條第一項、第二項，刑法第十一條、第四十七條、第五十一條第五\n款，判決如主文。\n中      華      民      國      九十三      年    八    月    十三    日\n                                      臺灣屏東地方法院刑事第二庭\n                                          法  官  林昌義\n右正本證明與原本無異。\n如不服本判決應於收受本判決送達後十日內向本院提出上訴書狀，其未敘述上訴理由\n者，並得於提起上訴後十日內向本院補提理由書狀（均須按他造當事人之人數附繕本\n ）「切勿逕送上級法院」\n                                          書記官   潘美碧"
  },
  "search": "臺灣屏東地方法院刑事判決九十三年度訴字第四六四號公訴人臺灣屏東地方法院檢察署檢察官被告甲○○右列被告因違反毒品危害防制條例案件，經檢察官提起公訴（九十三年度毒偵字第九○七號），本院裁定以簡式審判程序審理，判決如左：主文甲○○施用第一級毒品，累犯，處有期徒刑捌月。又施用第二級毒品，累犯，處有期徒刑肆月。應執行有期徒刑拾月。事實一、甲○○曾於民國八十八年間因違反毒品危害防制條例案件，經本院潮州簡易庭於八十八年六月二十二日，以八十八年潮簡字第一二九號判決判處有期徒刑六月，如易科罰金，以三百元折算一日確定，於八十九年六月七日易科罰金執行完畢。其於八十七年間且因施用毒品案件，經本院裁定觀察勒戒後，認無繼續施用毒品傾向，由臺灣屏東地方法院檢察署檢察官於八十七年七月三十日，以八十七年偵字第四六一九號不起訴處分確定。又於八十八年間因施用毒品案件，經本院裁定觀察勒戒後，認有繼續施用毒品傾向，再經裁定令入戒治處所施以強制戒治，並由本院潮州簡易庭於八十八年六月二十二日，以八十八年潮簡字第一二九號判決判處有期徒刑六月，如易科罰金，以三百元折算一日確定，仍不知悔改，復基於施用第一級毒品海洛因之犯意，於九十三年二月十三日十四時許，在其位於屏東縣恆春鎮○○路一九四巷二五號住處，將香煙捲紙內部分煙草撥出，填入海洛因粉末後，點燃香煙吸食之方式，施用海洛因一次。又另行起意，基於施用第二級毒品安非他命之犯意，於九十三年二月十三日十六時許，在其友人位於高雄縣林園鄉○○路四十巷六號住處，將安非他命置入玻璃管內，點火燒烤玻璃管，吸食安非他命遇熱產生之煙氣之方式，施用安非他命一次。嗣警方於九十三年二月十三日十七時許，在高雄縣林園鄉○○路四十巷六號查緝毒品案件時，因甲○○亦在現場，經警方徵得其同意，於同日十九時三十分許採集其尿液送驗而查獲上情。二、案經嘉義市警察局第一分局報請臺灣高雄地方法院檢察署呈由臺灣高等法院高雄分院檢察署令轉臺灣屏東地方法院檢察署檢察官偵查起訴。理由一、上述事實，業經被告甲○○於本院審理時坦白承認，而被告於九十三年二月十三日經警採尿送驗結果，呈嗎啡（即海洛因水解後之反應）及甲基安非他命陽性反應，有嘉義市衛生局檢驗涉嫌毒品及管制藥品之尿液檢驗結果及長榮大學確認報告各一紙在卷可佐，此為檢驗機關本於專業知識及以精密儀器測試所得之結論，自可憑信，足見被告之自白與事實相符，可以採信，其於上述時地施用第一級毒品海洛因及第二級毒品安非他命各一次之事實，應可認定。又被告曾於八十七年間因施用毒品案件，經本院裁定觀察勒戒後，認無繼續施用毒品傾向，由臺灣屏東地方法院檢察署檢察官於八十七年七月三十日，以八十七年偵字第四六一九號不起訴處分確定。又於八十八年間因施用毒品案件，經本院裁定觀察勒戒後，認有繼續施用毒品傾向，再經裁定令入戒治處所施以強制戒治，並由本院潮州簡易庭於八十八年六月二十二日，以八十八年潮簡字第一二九號判決判處有期徒刑六月，如易科罰金，以三百元折算一日確定等情，有臺灣屏東地方法院檢察署刑案資料查註紀錄表及臺灣高等法院被告全國前案紀錄表各一紙在卷足憑，事證明確，被告犯行堪予認定。二、查海洛因、安非他命分別為毒品危害防制條例第二條第一項第一款、第二款所稱之第一級、第二級毒品，被告甲○○竟持以施用，核其所為，係犯同條例第十條第一項之施用第一級毒品罪及同條第二項之施用第二級毒品罪。其施用前持有第一級毒品海洛因、第二級毒品安非他命之低度行為，應為施用之高度行為所吸收，均不另論罪。其所犯上述二罪，犯意各別，行為互異，應予分別論罪，合併處罰。其曾於八十八年間因違反毒品危害防制條例案件，經本院潮州簡易庭於八十八年六月二十二日，以八十八年潮簡字第一二九號判決判處有期徒刑六月，如易科罰金，以三百元折算一日確定，於八十九年六月七日易科罰金執行完畢，有臺灣高等法院被告全國前案紀錄表及臺灣屏東地方法院檢察署刑案資料查註紀錄表各一紙在卷可供參考，其受有期徒刑之執行完畢後，五年之內再犯有期徒刑以上刑之上述二罪，均為累犯，均應依法加重其刑。爰審酌被告曾有違反毒品危害防制條例前科之素行、經執行觀察勒戒及強制戒治後仍未戒除毒癮、施用第一級毒品海洛因與第二級毒品安非他命各一次、施用毒品嚴重危害其身心健康及犯罪後坦認犯行，態度尚可等一切情狀，分別量處如主文所示之刑，並定其應執行之刑。至被告持以施用毒品所用之點火工具及玻璃管等物均未扣案，亦無證據證明該等物品係被告所有且現尚存在，均不併予宣告沒收。據上論斷，應依刑事訴訟法第二百七十三條之一、第二百九十九條第一項前段，毒品危害防制條例第十條第一項、第二項，刑法第十一條、第四十七條、第五十一條第五款，判決如主文。中華民國九十三年八月十三日臺灣屏東地方法院刑事第二庭法官林昌義右正本證明與原本無異。如不服本判決應於收受本判決送達後十日內向本院提出上訴書狀，其未敘述上訴理由者，並得於提起上訴後十日內向本院補提理由書狀（均須按他造當事人之人數附繕本）「切勿逕送上級法院」書記官潘美碧中華民國九十三年八月十三日附錄論罪科刑法條全文毒品危害防制條例第十條施用第一級毒品者，處六月以上五年以下有期徒刑。施用第二級毒品者，處三年以下有期徒刑。",
  "characters": {
    "judges": [
      "林昌義"
    ],
    "prosecutors": [

    ],
    "lawyers": [

    ],
    "clerks": [
      "潘美碧"
    ],
    "plaintiffs": [

    ],
    "defendants": [
      "甲○○",
      "右列被告因違反毒品危害防制條例案件，經檢察官提起公訴（九十三年度毒偵字第九",
      "○七號），本院裁定以簡式審判程序審理，判決如左："
    ],
    "prosecutor_office": [
      "臺灣屏東地方法院檢察署檢察官"
    ],
    "creditors": [

    ],
    "debtors": [

    ],
    "judicial_associate_officer": [

    ]
  },
  "adjudged_at": "2004-08-13",
  "created_at": "2016-02-06 02:25:36",
  "updated_at": "2016-02-06 02:25:36"
}