{
  "identify": "TND-100-簡-1952-20110905-1",
  "court": {
    "name": "臺灣臺南地方法院",
    "code": "TND"
  },
  "division": {
    "name": "刑事",
    "code": "M"
  },
  "year": 100,
  "word": "簡",
  "number": "1952",
  "jcheck": "1",
  "reason": "妨害名譽",
  "content": "臺灣臺南地方法院刑事簡易判決         100年度簡字第1952號\n聲  請  人  臺灣臺南地方法院檢察署檢察官\n被      告  葉建雄\n上列被告因妨害名譽案件，經檢察官聲請以簡易判決處刑（100\n年度偵字第9327號），本院判決如下：\n    主  文\n葉建雄犯公然侮辱罪，處罰金新臺幣參仟元，如易服勞役，以新\n臺幣壹仟元折算壹日。\n    事實及理由\n一、本件犯罪事實及證據均引用檢察官聲請簡易判決處刑書之記\n    載（如附件）。\n二、核被告葉建雄所為，係犯刑法第309條第1項之公然侮辱罪。\n    爰審酌被告因懷疑告訴人向其姪女表示被告所販賣的水果較\n    貴，竟不思自行檢討是否有此情形，反而罔顧彼此尊嚴，逞\n    一時言語之快而侮辱告訴人之犯罪動機，並考量告訴人因此\n    受有一定程度之損害，及被告犯後仍否認犯行，復未與告訴\n    人達成和解等一切情狀，量處如主文所示之刑，並諭知易服\n    勞役之折算標準。\n三、依刑事訴訟法第449條第1項前段、第454條第2項，刑法第30\n    9條第1項、第42條第3項，刑法施行法第1條之1，逕以簡易\n    判決處刑如主文。\n中    華    民    國   100    年    9     月    5     日\n                  刑事第一庭    法  官  鄭銘仁\n以上正本證明與原本無異。\n如不服本判決應於收受送達後10日內向本院提出上訴書狀（應附\n繕本）。\n                                書記官  郭勝華\n中    華    民    國   100    年    9     月    7     日\n附記：\n中華民國刑法第309條第1項\n公然侮辱人者，處拘役或 3 百元以下罰金。",
  "structure": {
    "main": "葉建雄犯公然侮辱罪，處罰金新臺幣參仟元，如易服勞役，以新\n臺幣壹仟元折算壹日。",
    "fact": "一、本件犯罪事實及證據均引用檢察官聲請簡易判決處刑書之記\n    載（如附件）。\n二、核被告葉建雄所為，係犯刑法第309條第1項之公然侮辱罪。\n    爰審酌被告因懷疑告訴人向其姪女表示被告所販賣的水果較\n    貴，竟不思自行檢討是否有此情形，反而罔顧彼此尊嚴，逞\n    一時言語之快而侮辱告訴人之犯罪動機，並考量告訴人因此\n    受有一定程度之損害，及被告犯後仍否認犯行，復未與告訴\n    人達成和解等一切情狀，量處如主文所示之刑，並諭知易服\n    勞役之折算標準。\n三、依刑事訴訟法第449條第1項前段、第454條第2項，刑法第30\n    9條第1項、第42條第3項，刑法施行法第1條之1，逕以簡易\n    判決處刑如主文。",
    "reason": "一、本件犯罪事實及證據均引用檢察官聲請簡易判決處刑書之記\n    載（如附件）。\n二、核被告葉建雄所為，係犯刑法第309條第1項之公然侮辱罪。\n    爰審酌被告因懷疑告訴人向其姪女表示被告所販賣的水果較\n    貴，竟不思自行檢討是否有此情形，反而罔顧彼此尊嚴，逞\n    一時言語之快而侮辱告訴人之犯罪動機，並考量告訴人因此\n    受有一定程度之損害，及被告犯後仍否認犯行，復未與告訴\n    人達成和解等一切情狀，量處如主文所示之刑，並諭知易服\n    勞役之折算標準。\n三、依刑事訴訟法第449條第1項前段、第454條第2項，刑法第30\n    9條第1項、第42條第3項，刑法施行法第1條之1，逕以簡易\n    判決處刑如主文。"
  },
  "search": "臺灣臺南地方法院刑事簡易判決100年度簡字第1952號聲請人臺灣臺南地方法院檢察署檢察官被告葉建雄上列被告因妨害名譽案件，經檢察官聲請以簡易判決處刑（100年度偵字第9327號），本院判決如下：主文葉建雄犯公然侮辱罪，處罰金新臺幣參仟元，如易服勞役，以新臺幣壹仟元折算壹日。事實及理由一、本件犯罪事實及證據均引用檢察官聲請簡易判決處刑書之記載（如附件）。二、核被告葉建雄所為，係犯刑法第309條第1項之公然侮辱罪。爰審酌被告因懷疑告訴人向其姪女表示被告所販賣的水果較貴，竟不思自行檢討是否有此情形，反而罔顧彼此尊嚴，逞一時言語之快而侮辱告訴人之犯罪動機，並考量告訴人因此受有一定程度之損害，及被告犯後仍否認犯行，復未與告訴人達成和解等一切情狀，量處如主文所示之刑，並諭知易服勞役之折算標準。三、依刑事訴訟法第449條第1項前段、第454條第2項，刑法第309條第1項、第42條第3項，刑法施行法第1條之1，逕以簡易判決處刑如主文。中華民國100年9月5日刑事第一庭法官鄭銘仁以上正本證明與原本無異。如不服本判決應於收受送達後10日內向本院提出上訴書狀（應附繕本）。書記官郭勝華中華民國100年9月7日附記：中華民國刑法第309條第1項公然侮辱人者，處拘役或3百元以下罰金。",
  "characters": {
    "judges": [
      "鄭銘仁"
    ],
    "prosecutors": [

    ],
    "lawyers": [

    ],
    "clerks": [
      "郭勝華"
    ],
    "plaintiffs": [

    ],
    "defendants": [
      "葉建雄"
    ],
    "prosecutor_office": [
      "臺灣臺南地方法院檢察署檢察官"
    ],
    "creditors": [

    ],
    "debtors": [

    ],
    "judicial_associate_officer": [

    ]
  },
  "adjudged_at": "2011-09-05",
  "created_at": "2016-02-12 13:00:49",
  "updated_at": "2016-02-12 13:00:49"
}