{
  "identify": "TYD-100-壢交簡-1396-20110905-1",
  "court": {
    "name": "臺灣桃園地方法院",
    "code": "TYD"
  },
  "division": {
    "name": "刑事",
    "code": "M"
  },
  "year": 100,
  "word": "壢交簡",
  "number": "1396",
  "jcheck": "1",
  "reason": "過失傷害",
  "content": "臺灣桃園地方法院刑事簡易判決     100年度壢交簡字第1396號\n聲  請  人  臺灣桃園地方法院檢察署檢察官\n被      告  鄺海威\n上列被告因過失傷害案件，經檢察官聲請簡易判決處刑(99年度\n偵字第22776號) ，本院判決如下:\n    主      文\n鄺海威因過失傷害人，處拘役伍拾日，如易科罰金，以新台幣壹\n仟元折算壹日。\n    事實及理由\n一、本件犯罪事實及證據，除檢察官聲請簡易判決處刑書犯罪事\n    實欄一第7 行補充告訴人與有過失部分為「詹國瑋駕駛上開\n    重型機車疏未注意車前狀況」、文末補充「鄺海威於肇事後\n    ，在未被有偵查犯罪職權之機關或公務員發覺其為犯人前，\n    即主動向到場處理警員表明為肇事者，進而接受裁判。」外\n    ，餘均引用檢察官聲請簡易判決處刑書之記載( 如附件) 。\n二、核被告所為，係犯刑法第284 條第1 項前段之過失傷害罪。\n    被告於警員到場處理尚不知孰為犯罪人時，主動向警員告知\n    其為肇事車輛之駕駛人，自首而受裁判，此有桃園縣政府警\n    察局道路交通事故肇事人自首情形紀錄表1 紙可按，係對於\n    尚未發覺之犯罪自首而受裁判，應依刑法第62條前段規定，\n    依法減輕其刑。爰審酌被告前無前科，此有臺灣高等法院被\n    告前案紀錄表在卷可按，素行尚可、犯後否認犯行，參以被\n    告及告訴人就本件車禍事故之過失程度，以被告之過失為肇\n    事主因，兼衡告訴人所受傷勢情形及被告犯後未與告訴人達\n    成和解等一切情狀，量處如主文所示之刑，並諭知易科罰金\n    之折算標準，以示警懲。\n三、依刑事訴訟法第449 條第1 項前段、第3 項、第454 條第2\n    項，刑法第284 條第1 項前段、第62條前段、第41條第1項\n    前段，刑法施行法第1 條之1 第1 項、第2 項前段，逕以簡\n    易判決處刑如主文。\n四、如不服本判決，得於判決書送達之翌日起10日內，以書狀敘\n    述理由（須附繕本），向本庭提出上訴。\n中    華    民    國   100    年    9     月    5     日\n                              交通法庭    法  官  李麗珍\n以上正本證明與原本無異。\n如不服本判決，得於判決書送達之翌日起10日內，以書狀敘述理\n由，向本庭提出上訴（應附繕本）。\n                                          書記官  李靜華\n中    華    民    國   100    年    9     月    6     日\n附錄法條:\n刑法第284條\n（過失傷害罪）\n因過失傷害人者，處 6 月以下有期徒刑、拘役或 5 百元以下罰\n金，致重傷者，處 1 年以下有期徒刑、拘役或 5 百元以下罰金\n。\n從事業務之人，因業務上之過失傷害人者，處 1 年以下有期徒\n刑、拘役或 1 千元以下罰金，致重傷者，處 3 年以下有期徒刑\n、拘役或 2 千元以下罰金。",
  "structure": {
    "main": "鄺海威因過失傷害人，處拘役伍拾日，如易科罰金，以新台幣壹\n仟元折算壹日。",
    "fact": "一、本件犯罪事實及證據，除檢察官聲請簡易判決處刑書犯罪事\n    實欄一第7 行補充告訴人與有過失部分為「詹國瑋駕駛上開\n    重型機車疏未注意車前狀況」、文末補充「鄺海威於肇事後\n    ，在未被有偵查犯罪職權之機關或公務員發覺其為犯人前，\n    即主動向到場處理警員表明為肇事者，進而接受裁判。」外\n    ，餘均引用檢察官聲請簡易判決處刑書之記載( 如附件) 。\n二、核被告所為，係犯刑法第284 條第1 項前段之過失傷害罪。\n    被告於警員到場處理尚不知孰為犯罪人時，主動向警員告知\n    其為肇事車輛之駕駛人，自首而受裁判，此有桃園縣政府警\n    察局道路交通事故肇事人自首情形紀錄表1 紙可按，係對於\n    尚未發覺之犯罪自首而受裁判，應依刑法第62條前段規定，\n    依法減輕其刑。爰審酌被告前無前科，此有臺灣高等法院被\n    告前案紀錄表在卷可按，素行尚可、犯後否認犯行，參以被\n    告及告訴人就本件車禍事故之過失程度，以被告之過失為肇\n    事主因，兼衡告訴人所受傷勢情形及被告犯後未與告訴人達\n    成和解等一切情狀，量處如主文所示之刑，並諭知易科罰金\n    之折算標準，以示警懲。\n三、依刑事訴訟法第449 條第1 項前段、第3 項、第454 條第2\n    項，刑法第284 條第1 項前段、第62條前段、第41條第1項\n    前段，刑法施行法第1 條之1 第1 項、第2 項前段，逕以簡\n    易判決處刑如主文。\n四、如不服本判決，得於判決書送達之翌日起10日內，以書狀敘\n    述理由（須附繕本），向本庭提出上訴。",
    "reason": "一、本件犯罪事實及證據，除檢察官聲請簡易判決處刑書犯罪事\n    實欄一第7 行補充告訴人與有過失部分為「詹國瑋駕駛上開\n    重型機車疏未注意車前狀況」、文末補充「鄺海威於肇事後\n    ，在未被有偵查犯罪職權之機關或公務員發覺其為犯人前，\n    即主動向到場處理警員表明為肇事者，進而接受裁判。」外\n    ，餘均引用檢察官聲請簡易判決處刑書之記載( 如附件) 。\n二、核被告所為，係犯刑法第284 條第1 項前段之過失傷害罪。\n    被告於警員到場處理尚不知孰為犯罪人時，主動向警員告知\n    其為肇事車輛之駕駛人，自首而受裁判，此有桃園縣政府警\n    察局道路交通事故肇事人自首情形紀錄表1 紙可按，係對於\n    尚未發覺之犯罪自首而受裁判，應依刑法第62條前段規定，\n    依法減輕其刑。爰審酌被告前無前科，此有臺灣高等法院被\n    告前案紀錄表在卷可按，素行尚可、犯後否認犯行，參以被\n    告及告訴人就本件車禍事故之過失程度，以被告之過失為肇\n    事主因，兼衡告訴人所受傷勢情形及被告犯後未與告訴人達\n    成和解等一切情狀，量處如主文所示之刑，並諭知易科罰金\n    之折算標準，以示警懲。\n三、依刑事訴訟法第449 條第1 項前段、第3 項、第454 條第2\n    項，刑法第284 條第1 項前段、第62條前段、第41條第1項\n    前段，刑法施行法第1 條之1 第1 項、第2 項前段，逕以簡\n    易判決處刑如主文。\n四、如不服本判決，得於判決書送達之翌日起10日內，以書狀敘\n    述理由（須附繕本），向本庭提出上訴。"
  },
  "search": "臺灣桃園地方法院刑事簡易判決100年度壢交簡字第1396號聲請人臺灣桃園地方法院檢察署檢察官被告鄺海威上列被告因過失傷害案件，經檢察官聲請簡易判決處刑(99年度偵字第22776號)，本院判決如下:主文鄺海威因過失傷害人，處拘役伍拾日，如易科罰金，以新台幣壹仟元折算壹日。事實及理由一、本件犯罪事實及證據，除檢察官聲請簡易判決處刑書犯罪事實欄一第7行補充告訴人與有過失部分為「詹國瑋駕駛上開重型機車疏未注意車前狀況」、文末補充「鄺海威於肇事後，在未被有偵查犯罪職權之機關或公務員發覺其為犯人前，即主動向到場處理警員表明為肇事者，進而接受裁判。」外，餘均引用檢察官聲請簡易判決處刑書之記載(如附件)。二、核被告所為，係犯刑法第284條第1項前段之過失傷害罪。被告於警員到場處理尚不知孰為犯罪人時，主動向警員告知其為肇事車輛之駕駛人，自首而受裁判，此有桃園縣政府警察局道路交通事故肇事人自首情形紀錄表1紙可按，係對於尚未發覺之犯罪自首而受裁判，應依刑法第62條前段規定，依法減輕其刑。爰審酌被告前無前科，此有臺灣高等法院被告前案紀錄表在卷可按，素行尚可、犯後否認犯行，參以被告及告訴人就本件車禍事故之過失程度，以被告之過失為肇事主因，兼衡告訴人所受傷勢情形及被告犯後未與告訴人達成和解等一切情狀，量處如主文所示之刑，並諭知易科罰金之折算標準，以示警懲。三、依刑事訴訟法第449條第1項前段、第3項、第454條第2項，刑法第284條第1項前段、第62條前段、第41條第1項前段，刑法施行法第1條之1第1項、第2項前段，逕以簡易判決處刑如主文。四、如不服本判決，得於判決書送達之翌日起10日內，以書狀敘述理由（須附繕本），向本庭提出上訴。中華民國100年9月5日交通法庭法官李麗珍以上正本證明與原本無異。如不服本判決，得於判決書送達之翌日起10日內，以書狀敘述理由，向本庭提出上訴（應附繕本）。書記官李靜華中華民國100年9月6日附錄法條:刑法第284條（過失傷害罪）因過失傷害人者，處6月以下有期徒刑、拘役或5百元以下罰金，致重傷者，處1年以下有期徒刑、拘役或5百元以下罰金。從事業務之人，因業務上之過失傷害人者，處1年以下有期徒刑、拘役或1千元以下罰金，致重傷者，處3年以下有期徒刑、拘役或2千元以下罰金。",
  "characters": {
    "judges": [
      "李麗珍"
    ],
    "prosecutors": [

    ],
    "lawyers": [

    ],
    "clerks": [
      "李靜華"
    ],
    "plaintiffs": [

    ],
    "defendants": [
      "鄺海威"
    ],
    "prosecutor_office": [
      "臺灣桃園地方法院檢察署檢察官"
    ],
    "creditors": [

    ],
    "debtors": [

    ],
    "judicial_associate_officer": [

    ]
  },
  "adjudged_at": "2011-09-05",
  "created_at": "2016-02-12 12:51:59",
  "updated_at": "2016-02-12 12:51:59"
}