{
  "identify": "SCD-93-竹簡-346-20040528-1",
  "court": {
    "name": "臺灣新竹地方法院",
    "code": "SCD"
  },
  "division": {
    "name": "刑事",
    "code": "M"
  },
  "year": 93,
  "word": "竹簡",
  "number": "346",
  "jcheck": "1",
  "reason": "違反勞動檢查法",
  "content": "臺灣新竹地方法院刑事簡易判決                    九十三年度竹簡字第三四六號\n    聲  請  人  臺灣新竹地方法院檢察署檢察官\n    被      告  彰億營造工程有限公司\n    兼  代表人  甲○\n    被      告  乙○○\n右列被告因違反勞動檢查法案件，經檢察官聲請以簡易判決處刑（九十二年度偵字第\n三三八二、九十三年度偵字第三一九號），本院判決如左：\n        主  文\n彰億營造工程有限公司其代表人、受僱人因執行業務違反中央主管機關會商目的事業\n主管機關指定之營造工程之危險性工作場所，非經勞動檢查機構審查或檢查合格，事\n業單位不得使勞工在該場所作業之規定，使勞工在未經審查或檢查合格之工作場所作\n業，科罰金新台幣壹拾萬元。\n甲○法人之代表人共同因執行業務違反中央主管機關會商目的事業主管機關指定之營\n造工程之危險性工作場所，非經勞動檢查機構審查或檢查合格，事業單位不得使勞工\n在該場所作業之規定，使勞工在未經審查或檢查合格之工作場所作業，處罰金新台幣\n壹拾萬元，如易服勞役，以新台幣玖佰元即銀元參佰元折算壹日。\n乙○○法人之受僱人共同因執行業務違反中央主管機關會商目的事業主管機關指定之\n營造工程之危險性工作場所，非經勞動檢查機構審查或檢查合格，事業單位不得使勞\n工在該場所作業之規定，使勞工在未經審查或檢查合格之工作場所作業，處罰金新台\n幣伍萬元，如易服勞役，以新台幣玖佰元即銀元參佰元折算壹日。\n        事實及理由\n一、本件犯罪事實、證據及應適用法條均引用檢察官聲請簡易判決處刑書之記載（如\n    附件）。\n二、依刑事訴訟法第四百四十九條第一項，第四百五十四條第二項，勞動檢查法第二\n    十六條第一項第六款、第三十四條第一項第一款、第二項，刑法第十一條前段、\n    第二十八條、第四十二條第二項，罰金罰鍰提高標準條例第二條，判決如主文。\n三、如不服本判決，得自收受送達之日起十日內，向本院提起上訴。\n中      華      民      國    九十三    年      五    月    二十八    日\n                              臺灣新竹地方法院新竹簡易庭\n                                    法  官   魏瑞紅\n右正本證明與原本無異。\n                                    書記官   陳凰榆\n中      華      民      國    九十三    年      五      月    二十八    日\n附錄法條：\n勞動檢查法第三十四條\n有左列情形之一者，處三年以下有期徒刑、拘役或科或併科新台幣十五萬\n元以下罰金：\n一  違反第二十六條規定，使勞工在未經審查或檢查合格之工作場所作業\n    者。\n二  違反第二十七條至第二十九條停工通知者。\n法人之代表人、法人或自然人之代理人、受僱人或其他從業人員，因執行\n業務犯前項之罪者，除處罰其行為人外，對該法人或自然人亦科以前項之\n罰金。\n勞動檢查法第二十六條\n左列危險性工作場所，非經勞動檢查機構審查或檢查合格，事業單位不得\n使勞工在該場所作業：\n一  從事石油裂解之石化工業之工作場所。\n二  農藥製造工作場所。\n三  爆竹煙火工廠及火藥類製造工作場所。\n四  設置高壓氣體類壓力容器或蒸汽鍋爐，其壓力或容量達中央主管機關\n    規定者之工作場所。\n五  製造、處置、使用危險物、有害物之數量達中央主管機關規定數量之\n    工作場所。\n六  中央主管機關會商目的事業主管機關指定之營造工程之工作場所。\n七  其他中央主管機關指定之工作場所。\n前項工作場所應審查或檢查之事項，由中央主管機關定之。\n",
  "structure": {
    "main": "彰億營造工程有限公司其代表人、受僱人因執行業務違反中央主管機關會商目的事業\n主管機關指定之營造工程之危險性工作場所，非經勞動檢查機構審查或檢查合格，事\n業單位不得使勞工在該場所作業之規定，使勞工在未經審查或檢查合格之工作場所作\n業，科罰金新台幣壹拾萬元。\n甲○法人之代表人共同因執行業務違反中央主管機關會商目的事業主管機關指定之營\n造工程之危險性工作場所，非經勞動檢查機構審查或檢查合格，事業單位不得使勞工\n在該場所作業之規定，使勞工在未經審查或檢查合格之工作場所作業，處罰金新台幣\n壹拾萬元，如易服勞役，以新台幣玖佰元即銀元參佰元折算壹日。\n乙○○法人之受僱人共同因執行業務違反中央主管機關會商目的事業主管機關指定之\n營造工程之危險性工作場所，非經勞動檢查機構審查或檢查合格，事業單位不得使勞\n工在該場所作業之規定，使勞工在未經審查或檢查合格之工作場所作業，處罰金新台\n幣伍萬元，如易服勞役，以新台幣玖佰元即銀元參佰元折算壹日。",
    "fact": "一、本件犯罪事實、證據及應適用法條均引用檢察官聲請簡易判決處刑書之記載（如\n    附件）。\n二、依刑事訴訟法第四百四十九條第一項，第四百五十四條第二項，勞動檢查法第二\n    十六條第一項第六款、第三十四條第一項第一款、第二項，刑法第十一條前段、\n    第二十八條、第四十二條第二項，罰金罰鍰提高標準條例第二條，判決如主文。\n三、如不服本判決，得自收受送達之日起十日內，向本院提起上訴。",
    "reason": "一、本件犯罪事實、證據及應適用法條均引用檢察官聲請簡易判決處刑書之記載（如\n    附件）。\n二、依刑事訴訟法第四百四十九條第一項，第四百五十四條第二項，勞動檢查法第二\n    十六條第一項第六款、第三十四條第一項第一款、第二項，刑法第十一條前段、\n    第二十八條、第四十二條第二項，罰金罰鍰提高標準條例第二條，判決如主文。\n三、如不服本判決，得自收受送達之日起十日內，向本院提起上訴。"
  },
  "search": "臺灣新竹地方法院刑事簡易判決九十三年度竹簡字第三四六號聲請人臺灣新竹地方法院檢察署檢察官被告彰億營造工程有限公司兼代表人甲○被告乙○○右列被告因違反勞動檢查法案件，經檢察官聲請以簡易判決處刑（九十二年度偵字第三三八二、九十三年度偵字第三一九號），本院判決如左：主文彰億營造工程有限公司其代表人、受僱人因執行業務違反中央主管機關會商目的事業主管機關指定之營造工程之危險性工作場所，非經勞動檢查機構審查或檢查合格，事業單位不得使勞工在該場所作業之規定，使勞工在未經審查或檢查合格之工作場所作業，科罰金新台幣壹拾萬元。甲○法人之代表人共同因執行業務違反中央主管機關會商目的事業主管機關指定之營造工程之危險性工作場所，非經勞動檢查機構審查或檢查合格，事業單位不得使勞工在該場所作業之規定，使勞工在未經審查或檢查合格之工作場所作業，處罰金新台幣壹拾萬元，如易服勞役，以新台幣玖佰元即銀元參佰元折算壹日。乙○○法人之受僱人共同因執行業務違反中央主管機關會商目的事業主管機關指定之營造工程之危險性工作場所，非經勞動檢查機構審查或檢查合格，事業單位不得使勞工在該場所作業之規定，使勞工在未經審查或檢查合格之工作場所作業，處罰金新台幣伍萬元，如易服勞役，以新台幣玖佰元即銀元參佰元折算壹日。事實及理由一、本件犯罪事實、證據及應適用法條均引用檢察官聲請簡易判決處刑書之記載（如附件）。二、依刑事訴訟法第四百四十九條第一項，第四百五十四條第二項，勞動檢查法第二十六條第一項第六款、第三十四條第一項第一款、第二項，刑法第十一條前段、第二十八條、第四十二條第二項，罰金罰鍰提高標準條例第二條，判決如主文。三、如不服本判決，得自收受送達之日起十日內，向本院提起上訴。中華民國九十三年五月二十八日臺灣新竹地方法院新竹簡易庭法官魏瑞紅右正本證明與原本無異。書記官陳凰榆中華民國九十三年五月二十八日附錄法條：勞動檢查法第三十四條有左列情形之一者，處三年以下有期徒刑、拘役或科或併科新台幣十五萬元以下罰金：一違反第二十六條規定，使勞工在未經審查或檢查合格之工作場所作業者。二違反第二十七條至第二十九條停工通知者。法人之代表人、法人或自然人之代理人、受僱人或其他從業人員，因執行業務犯前項之罪者，除處罰其行為人外，對該法人或自然人亦科以前項之罰金。勞動檢查法第二十六條左列危險性工作場所，非經勞動檢查機構審查或檢查合格，事業單位不得使勞工在該場所作業：一從事石油裂解之石化工業之工作場所。二農藥製造工作場所。三爆竹煙火工廠及火藥類製造工作場所。四設置高壓氣體類壓力容器或蒸汽鍋爐，其壓力或容量達中央主管機關規定者之工作場所。五製造、處置、使用危險物、有害物之數量達中央主管機關規定數量之工作場所。六中央主管機關會商目的事業主管機關指定之營造工程之工作場所。七其他中央主管機關指定之工作場所。前項工作場所應審查或檢查之事項，由中央主管機關定之。",
  "characters": {
    "judges": [
      "魏瑞紅"
    ],
    "prosecutors": [

    ],
    "lawyers": [

    ],
    "clerks": [
      "陳凰榆"
    ],
    "plaintiffs": [

    ],
    "defendants": [
      "彰億營造工程有限公司",
      "乙○○",
      "右列被告因違反勞動檢查法案件，經檢察官聲請以簡易判決處刑（九十二年度偵字第",
      "三三八二、九十三年度偵字第三一九號），本院判決如左："
    ],
    "prosecutor_office": [
      "臺灣新竹地方法院檢察署檢察官"
    ],
    "creditors": [

    ],
    "debtors": [

    ],
    "judicial_associate_officer": [

    ]
  },
  "adjudged_at": "2004-05-28",
  "created_at": "2016-02-05 20:04:03",
  "updated_at": "2016-02-05 20:04:03"
}