{
  "identify": "SLD-93-重訴-270-20041028-1",
  "court": {
    "name": "臺灣士林地方法院",
    "code": "SLD"
  },
  "division": {
    "name": "民事",
    "code": "V"
  },
  "year": 93,
  "word": "重訴",
  "number": "270",
  "jcheck": "1",
  "reason": "確認所有權等",
  "content": "臺灣士林地方法院民事裁定  九十三年度重訴字第二七０號\n    原      告  行政院環境保護署\n    法定代理人  張祖恩\n    被      告  開立工程股份有限公司\n    法定代理人  唐啟賢\n    被      告  甲○○○\n當事人間確認所有權等事件，本院裁定如下：\n    主      文\n本件移送臺灣臺南地方法院。\n    理      由\n一、按共同訴訟之被告數人，其住所不在一法院管轄區域內者，各該住所在地之法院\n    俱有管轄權。但依第四條至前條規定有共同管轄法院者，由該法院管轄。民事訴\n    訴法第二十條定有明文。而依同法第十五條第一項之規定，因侵權行為涉訟者，\n    得由行為地之法院管轄。次按訴訟之全部或一部，法院認為無管轄權者，依原告\n    聲請或依職權以裁定移送於其管轄法院，民事訴訟法第二十八條第一項規定甚明\n    。\n二、本件原告係本於民法第七百六十七條、第九百六十二條關於所有權及占有之規定\n    、同法第一百八十四條侵權行為之規定及同法第一百七十九條不當得利之規定有\n    所確認及請求而涉訟，被告開立工程股份有限公司之事務所及被告甲○○○之住\n    所所在地分別位在臺北縣汐止市及臺南縣永康市，原告所指之侵權行為地及系爭\n    財物所在地均則位於臺南縣永康市，且相關之強制執行及假處分執行事件亦均已\n    由臺灣臺南地方法院受理中，是無論調查證據、調閱相關卷宗或勘驗系爭財物均\n    以由臺灣臺南地方法院管轄較為便捷及經濟，故依民事訴訟法第十五條第一項及\n    第二十條但書之規定，自應由共同管轄法院臺灣臺南地方法院管轄。茲原告向無\n    管轄權之本院起訴，顯係違誤，爰依職權將本件移送於該管轄法院。\n三、依首開法條裁定如主文。\n中      華      民      國    九十三    年      十      月    二十八    日\n                                        臺灣士林地方法院民事第二庭\n                                            法      官  張國勳\n右為正本係照原本作成。\n如對本裁定抗告須於裁定送達後十日內向本院提出抗告狀。\n中      華      民      國    九十三    年      十一    月      一      日\n                                            法院書記官  秦慧綺\n",
  "structure": {
    "main": "本件移送臺灣臺南地方法院。",
    "reason": "一、按共同訴訟之被告數人，其住所不在一法院管轄區域內者，各該住所在地之法院\n    俱有管轄權。但依第四條至前條規定有共同管轄法院者，由該法院管轄。民事訴\n    訴法第二十條定有明文。而依同法第十五條第一項之規定，因侵權行為涉訟者，\n    得由行為地之法院管轄。次按訴訟之全部或一部，法院認為無管轄權者，依原告\n    聲請或依職權以裁定移送於其管轄法院，民事訴訟法第二十八條第一項規定甚明\n    。\n二、本件原告係本於民法第七百六十七條、第九百六十二條關於所有權及占有之規定\n    、同法第一百八十四條侵權行為之規定及同法第一百七十九條不當得利之規定有\n    所確認及請求而涉訟，被告開立工程股份有限公司之事務所及被告甲○○○之住\n    所所在地分別位在臺北縣汐止市及臺南縣永康市，原告所指之侵權行為地及系爭\n    財物所在地均則位於臺南縣永康市，且相關之強制執行及假處分執行事件亦均已\n    由臺灣臺南地方法院受理中，是無論調查證據、調閱相關卷宗或勘驗系爭財物均\n    以由臺灣臺南地方法院管轄較為便捷及經濟，故依民事訴訟法第十五條第一項及\n    第二十條但書之規定，自應由共同管轄法院臺灣臺南地方法院管轄。茲原告向無\n    管轄權之本院起訴，顯係違誤，爰依職權將本件移送於該管轄法院。\n三、依首開法條裁定如主文。"
  },
  "search": "臺灣士林地方法院民事裁定九十三年度重訴字第二七０號原告行政院環境保護署法定代理人張祖恩被告開立工程股份有限公司法定代理人唐啟賢被告甲○○○當事人間確認所有權等事件，本院裁定如下：主文本件移送臺灣臺南地方法院。理由一、按共同訴訟之被告數人，其住所不在一法院管轄區域內者，各該住所在地之法院俱有管轄權。但依第四條至前條規定有共同管轄法院者，由該法院管轄。民事訴訴法第二十條定有明文。而依同法第十五條第一項之規定，因侵權行為涉訟者，得由行為地之法院管轄。次按訴訟之全部或一部，法院認為無管轄權者，依原告聲請或依職權以裁定移送於其管轄法院，民事訴訟法第二十八條第一項規定甚明。二、本件原告係本於民法第七百六十七條、第九百六十二條關於所有權及占有之規定、同法第一百八十四條侵權行為之規定及同法第一百七十九條不當得利之規定有所確認及請求而涉訟，被告開立工程股份有限公司之事務所及被告甲○○○之住所所在地分別位在臺北縣汐止市及臺南縣永康市，原告所指之侵權行為地及系爭財物所在地均則位於臺南縣永康市，且相關之強制執行及假處分執行事件亦均已由臺灣臺南地方法院受理中，是無論調查證據、調閱相關卷宗或勘驗系爭財物均以由臺灣臺南地方法院管轄較為便捷及經濟，故依民事訴訟法第十五條第一項及第二十條但書之規定，自應由共同管轄法院臺灣臺南地方法院管轄。茲原告向無管轄權之本院起訴，顯係違誤，爰依職權將本件移送於該管轄法院。三、依首開法條裁定如主文。中華民國九十三年十月二十八日臺灣士林地方法院民事第二庭法官張國勳右為正本係照原本作成。如對本裁定抗告須於裁定送達後十日內向本院提出抗告狀。中華民國九十三年十一月一日法院書記官秦慧綺",
  "characters": {
    "judges": [
      "張國勳"
    ],
    "prosecutors": [

    ],
    "lawyers": [

    ],
    "clerks": [
      "法院"
    ],
    "plaintiffs": [
      "行政院環境保護署"
    ],
    "defendants": [
      "開立工程股份有限公司",
      "甲○○○",
      "當事人間確認所有權等事件，本院裁定如下："
    ],
    "prosecutor_office": [

    ],
    "creditors": [

    ],
    "debtors": [

    ],
    "judicial_associate_officer": [

    ]
  },
  "adjudged_at": "2004-10-28",
  "created_at": "2016-02-06 13:47:30",
  "updated_at": "2016-02-06 13:47:30"
}