{
  "identify": "KSH-100-上更(一)-94-20111201-2",
  "court": {
    "name": "臺灣高等法院",
    "code": "KSH"
  },
  "division": {
    "name": "刑事",
    "code": "M"
  },
  "year": 100,
  "word": "上更(一)",
  "number": "94",
  "jcheck": "2",
  "reason": "毒品危害防制條例等",
  "content": "臺灣高等法院高雄分院刑事判決     100年度上更(一)字第94號\n上  訴  人\n即  被  告  房國輝\n選任辯護人  洪國欽律師\n上列上訴人因毒品危害防制條例等案件，不服臺灣高雄地方法院\n98年度重訴字第50號中華民國99年12月9 日第一審判決（起訴案\n號：臺灣高雄地方法院檢察署98年度偵字第16214 號），提起上\n訴，經判決後，由最高法院發回更審，本院判決如下：\n     主  文\n原判決關於房國輝部分撤銷。\n房國輝共同犯運輸第一級毒品罪，處有期徒刑貳拾年。扣案之海\n洛因拾塊（合計淨重3612.27公克，純度78.98%，純質淨重2852.\n97公克）均沒收銷燬之。\n     事  實\n一、葉榮富為高雄市「盈萊有限公司」（下稱盈萊公司）負責人\n    ，平日經營水產養殖及買賣，房國輝則係在越南從事水產買\n    賣業務，2 人均明知海洛因係毒品危害防制條例所列之第一\n    級毒品及管制進出口物品，竟共同謀議以盈萊公司名義進口\n    魚漿、魚片貨櫃，在魚漿夾藏毒品之方式，自越南走私海洛\n    因進口入台灣地區，雙方並約定均以行動電話簡訊方式連絡\n    運輸毒品事宜，於民國（以下同）98年4 月底，葉榮富先行\n    透過地下通匯匯款美金9 萬5 千元至越南，並指示房國輝負\n    責在越南自不詳人士處取得第一級毒品海洛因10塊後，再由\n    房國輝將上開毒品夾藏於欲進口之魚漿塊，而裝入編號WHLU\n    0000000 號貨櫃內，由葉榮富藉由「盈萊公司」進口水產之\n    名義，自越南進口上開貨櫃進入台灣。嗣於98年5 月27日該\n    貨櫃抵達高雄港第63號碼頭後，經法務部調查局南部地區機\n    動工作組、財政部高雄關稅局、台南縣警察局少年警察隊、\n    高雄港務警察局、高雄市新興分局、海巡署台東查緝隊、基\n    隆憲兵隊組成之專案小組查知葉榮富、房國輝業已走私海洛\n    因入境，並於同日上午抵達高雄小港機場欲出境，乃由檢察\n    官指揮專案小組成員前往高雄小港機場，拘提葉榮富、房國\n    輝2 人到案，並扣得2 人使用之行動電話3 支，復帶同前往\n    高雄港第63號碼頭查驗區，會同高雄關稅局人員開櫃查驗時\n    ，當場查獲夾藏於魚漿內之海洛因10塊（合計淨重3612.27\n    公克，純度78.98 ％，純質淨重2852.97 公克，起訴書誤載\n    為8 塊）。\n二、案經法務部調查局南部地區機動工作組移送台灣高雄地方法\n    院檢察署檢察官偵查起訴。\n    理  由\n壹、證據能力部分：\n一、按被告以外之人於偵查中向檢察官所為之陳述，除顯有不可\n    信之情況者外，得為證據，此為刑事訴訟法第159 條之1 第\n    2 項所明定。經查本件證人即同案被告葉榮富於偵查中就同\n    案被告房國輝部分所為之陳述，業經具結以擔保陳述之可信\n    性，且查無何顯不可信之情形，核之上開說明，自有證據能\n    力得作為本件認定犯罪事實之依據。\n二、按「法院或檢察官得囑託醫院、學校或其他相當之機關、團\n    體為鑑定，或審查他人之鑑定，並準用第203 條至第206 條\n    之1 之規定」、「鑑定之經過及其結果，應命鑑定人以言詞\n    或書面報告」，亦分別為刑事訴訟法第208 條第1 項前段、\n    第206 條第1 項定明定。是經法院或檢察官囑託相當之機關\n    為鑑定後，經鑑定人以書面報告其鑑定之結果者，即屬同法\n    第159 條第1 項所謂之「法律有規定者」，不受該條項規定\n    「不得作為證據」之限制。且同法第208 條第1 項前段對於\n    法院或檢察官囑託相當之機關為鑑定之情形，僅規定：「準\n    用第203 條至第206 條之1 之規定」，至於同法第202 條有\n    關「鑑定人應於鑑定前具結」之規定，則不在準用之列。故\n    於法院或檢察官囑託相當之機關為鑑定，而該受囑託機關以\n    書面報告鑑定結果之情形，既非屬依法應具結者。是同法第\n    158 條之3 有關「證人、鑑定人依法應具結而未具結者，其\n    證言或鑑定意見，不得作為證據」之規定，於此時即無適用\n    之餘地。經查，本件法務部調查局關於扣案塊狀物是否屬於\n    第一級毒品海洛因所為鑑定而出具之鑑定書，係臺灣高雄地\n    方法院檢察署以事前概括選任方式指揮法務部調查局南部地\n    區機動工作組逕行送請法務部調查局所為之鑑定，依上揭說\n    明，上開鑑定書亦有證據能力。\n貳、實體部分：\n一、上開夾藏走私海洛因磚進口之事實，業據共同被告葉榮富於\n    偵查、原審及本院前審中坦承不諱，並有上開塊狀物品10塊\n    扣案可資佐証，且該10塊塊狀物品經檢驗結果確含海洛因成\n    份（合計淨重3612.27 公克，含海洛因之純度78.98 ％，純\n    質淨重2852.97 公克），有法務部調查局98年7 月16日調科\n    壹字第09823019820 號鑑定書在卷可稽（見偵卷第103 頁）\n    。又該海洛因磚10塊是在高雄港第63號碼頭查驗區，由警方\n    會同高雄關稅局人員開櫃查驗時，當場查獲夾藏於魚漿內，\n    足見共同被告葉榮富之自白核與事實相符，事證明確，共同\n    被告葉榮富走私毒品海洛因犯行已堪以認定。\n二、訊之上訴人房國輝固不否認上開接受共同被告葉榮富之託，\n    由葉榮富在越南之友人將水產樣品，託之轉交給天龍水產有\n    限公司辦理出口，惟否認共同走私海洛因磚，辯稱：伊不知\n    道魚漿內夾藏有海洛因，伊未參與云云。惟查：\n（一）上訴人房國輝於偵查中已坦承：「（問：你的工作？）答\n      ：在越南經商」「（問：南機組今日在高雄港第63號碼頭\n      查獲一只WHLU0000000 號內夾藏有十塊海洛因磚貨櫃是否\n      你進口？）答：是，是我幫葉榮富處理帶進來的」「（問\n      ：你如何幫他處理？）答：葉榮富知道我的經濟情況不好\n      ，他問是否願意幫他帶四號毒品進口，一塊的價格是5 至\n      6 萬元」「（問：你是否在越南幫他處理？）答：是葉榮\n      富請人在越南將毒品交給我，我負責幫他把毒品裝進貨櫃\n      內」「（問：夾藏的方式？）答：放在魚漿內，辨識的方\n      式是魚漿的紙箱外面日期不同」「（問：有無其他意見陳\n      述？）答：我今天在現場有配合檢調查案，供出夾藏毒品\n      魚漿的位置，讓檢調能順利的偵案此案，請求從輕處理」\n      等語不諱（見98年5 月27日偵查筆錄，即偵查卷第47頁）\n      ；本院前審審理時上訴人房國輝辯稱：偵查筆錄是紀錄，\n      不是筆錄云云，自非可採。又本院並未引用上訴人房國輝\n      在調查局之詢問筆錄，辯護人質疑房國輝在調查局之詢問\n      筆錄，即無庸審酌，附此敘明。又證人即同案被告葉榮富\n      於偵查中亦陳稱：「（問：你是否有在98年5 月7 日以盈\n      萊公司名義進口櫃號為WHLU0000000 號貨櫃，申報進口貨\n      物為魚片及魚漿？）答：是」「（問：你是否透過貨櫃夾\n      藏十塊海洛因磚來台？）答：是」「（問：海洛因來源？\n      ）答：這部分是房國輝負責，我是負責在台灣接貨」「（\n      問：整個毒品購買及裝運過程由何人負責？）答：房國輝\n      」「（問：這批毒品如果成功走私可分得多少酬榮？）答\n      ：房國輝可分得60多萬元，我的部分大概是120 萬元」「\n      （問：走私的模式？）答：是用盈萊公司名義進口櫃，將\n      海洛因磚夾藏在貨櫃的魚漿內，載到冷凍庫」等語（見98\n      年5 月27日偵查筆錄，即偵查卷第45頁），上訴人葉榮富\n      、房國輝2 人就房國輝於本件海洛因順利進口後可得之利\n      益約60萬元一節，所述內容大致相符（房國輝於偵查中稱\n      幫葉榮富帶四號毒品進口一塊的價格是5 至6 萬元），又\n      一般得合法進口之物品何需夾藏於合法進口之魚漿中，且\n      如非海洛因等價格貴重且被查獲後須負擔嚴重刑責之高度\n      風險違禁物品，豈有僅係負責接貨裝櫃即可獲得60萬元之\n      高報酬之理，又上訴人房國輝係在越南從事商務多年之人\n      ，社會經歷豐富，對此應甚為瞭解，其於審理中翻異辯稱\n      不知幫忙接貨裝櫃之物係海洛因云云，顯係事後卸責之詞\n      ，不足採信。\n（二）雖證人即同案被告葉榮富於原審審理中另證稱：本件被查\n      獲之海洛因在越南裝櫃出來前，並未告知房國輝係海洛因\n      等語，惟亦稱：房國輝有跟他們（指在越南之人士）接觸\n      ，應該知道（是海洛因）等語（見原審卷第357 頁），依\n      其證述僅謂未明確告知房國輝夾藏之物係海洛因，惟又謂\n      房國輝應知情，其內容模擬兩可，不如上開其於偵查中所\n      證述之內容明確，顯有迴護共同被告房國輝之嫌，自難作\n      為有利被告房國輝之認定。又該證人即同案被告葉榮富本\n      院前審審理時已肯定陳稱：「（問：你有無轉達給房國輝\n      ，說這是什麼東西？）答：我有跟他提過，這個可能是違\n      禁物品，你自己決定，是否要運送」「（問：他有無問你\n      是何違禁物品，或是你講他聽了就算了？）答：他有問我\n      是什麼東西，我有跟他講說是毒品」「（問：毒品用一塊\n      來做夾帶，是否這樣跟他講，他就知道是海洛因？）答：\n      應該是這樣」等語（見100 年5 月3 日本院前審審判筆錄\n      ，即本院上訴審卷第180 頁），葉榮富已明確陳稱房國輝\n      知道是夾藏海洛因，仍不能為上訴人房國輝有利之証明，\n      且上訴人房國輝知悉夾藏物品辨識的方式是魚漿的紙箱外\n      面日期不同（見98年5 月27日偵查筆錄），嗣後上訴人房\n      國輝在小港機場大廳被捕，並押往第63號碼頭檢查其進口\n      之貨櫃時，果在該貨櫃內之不同製造日期之魚漿內，啟出\n      該10塊海洛因磚，並有上開10塊海洛因磚扣案可資佐証，\n      且該10塊塊狀物品經調查局鑑驗結果確含海洛因成份，已\n      如前述，足見上訴人房國輝確有參與本件10塊海洛因磚之\n      走私進口。\n    綜上所述，因上訴人房國輝在偵查中已坦承：「是葉榮富請\n    人在越南將毒品交給我，我負責幫他把毒品裝進貨櫃內」「\n    放在魚漿內，辨識的方式是魚漿的紙箱外面日期不同」等語\n    ，又房國輝在小港機場大廳被捕，並押往第63號碼頭檢查其\n    進口之貨櫃時，果在該貨櫃內之不同製造日期之魚漿內，啟\n    出該10 塊 海洛因磚，事証明確，其於審理中翻異前供，辯\n    稱：不知幫忙接貨裝櫃之物係海洛因云云，係事後翻異卸責\n    之詞，不足採信，其犯行已堪認定。\n（三）被告之辯護人於本院審理時，聲請勘驗夾藏海洛因毒品之\n      魚漿樣本紙箱外觀，待證事項：證明紙箱外面標示之日期\n      是否有不同？有無另作記號？經本院於100 年11月17日勘\n      驗結果，該夾藏海洛因毒品之魚漿標本紙箱外面標示之生\n      產日期為2009年3 月1 日，又「Expiry date」後面的冒號\n      「：」被刮除，有勘驗筆錄可佐（見本院卷第100 頁反面\n      、第101 頁）。\n    查本案於98年5 月27日案發時，只扣押夾藏海洛因之魚漿外\n    包裝紙箱1 個，而未夾藏海洛因之魚漿外包裝紙箱則未扣押\n    （見偵卷第15頁）。故兩者紙箱外面標示之日期是否有不同\n    ，則無法比較。又另從偵查卷第30頁至第41頁所附之照片觀\n    之，亦看不出兩者紙箱外面標示之日期有何不同。但從上訴\n    人房國輝在偵查中坦承：「放在魚漿內，辨識的方式是魚漿\n    的紙箱外面日期不同」，及房國輝在小港機場大廳被捕，並\n    押往第63號碼頭檢查其進口之貨櫃時，果在該貨櫃內之不同\n    製造日期之魚漿內，啟出該10塊海洛因等情節已如前述，則\n    就上訴人房國輝知情啟出之海洛因確係藏放該貨櫃內之不同\n    製造日期之魚漿內一節，應可採信。\n三、按海洛因為毒品危害防制條例第2 條第1 項第1 款所定之第\n    一級毒品，且屬行政院依懲治走私條例第2 條第4 項授權公\n    告之「管制物品項目及數額」所列甲項第4 款之管制進口物\n    品，依法不得持有、運輸或私運進口。核上訴人葉榮富、房\n    國輝2 人所為，均係犯毒品危害防制條例第4 條第1 項之運\n    輸第一級毒品罪、懲治走私條例第2 條第1 項之私運管制物\n    品進口罪。上訴人葉榮富、房國輝2 人持有第一級毒品海洛\n    因之低度行為，已為運輸毒品之高度行為所吸收，不另論其\n    持有毒品罪。上訴人葉榮富、房國輝2 人間，就上開走私毒\n    品海洛因犯行，互有犯意聯絡及行為分擔，均應論以共同正\n    犯。上訴人葉榮富、房國輝2 人係以一行為同時觸犯運輸第\n    一級毒品罪及私運管制物品進口罪，為想像競合犯，應依刑\n    法第55條規定從較重之運輸第一級毒品罪處斷。又運輸第一\n    級毒品係法定刑為「死刑、無期徒刑」之罪，罪刑至為嚴峻\n    ，被告房國輝固有上開運輸海洛因之行為，然參之被告房國\n    輝係一時受誘而在越南交付海洛因予出口公司裝櫃運往國內\n    ，其並非主導本件運輸海洛因之人，且運輸之毒品尚未流入\n    市面造成實際危害，其亦未實際獲取龐大利益，其犯罪情節\n    若遽處以販賣毒品罪之法定本刑，除無從藉由量刑顯示、區\n    分行為人之惡性及犯罪情節輕重外，亦誠屬情輕法重，過於\n    嚴苛，其犯罪情狀在客觀上足以引起一般同情，堪予憫恕，\n    縱使科以法定最低刑度，猶為過重，爰就其所犯運輸第一級\n    毒品罪，依刑法第59條之規定酌減其刑。\n四、原審據以論處被告房國輝共同犯運輸第一級毒品罪，固非無\n    見。惟查無期徒刑減輕者，為二十年以下十五年以上有期徒\n    刑，刑法第65條第2 項定有明文。原判決理由欄對被告房國\n    輝有述減輕其刑，卻量處被告房國輝有期徒刑22年，超過\n    法定刑，顯有違誤。被告房國輝上訴，否認犯罪，雖無理由\n    ，但原判決關於被告房國輝部分既有可議之處，仍應就此部\n    分撤銷改判。審酌被告運輸之海洛因數量非少，對於國人健\n    康及社會治安之潛在危害甚大，惟甫入境即為警查獲，尚未\n    對國人造成具體毒害，被告房國輝未能坦承犯行，態度不佳\n    及其他等一切情狀，量處有期徒刑20年。扣案之海洛因10塊\n    （合計淨重3612.27 公克，純度78.98 ％，純質淨重2852.9\n    7 公克），係屬第一級毒品，不問屬於犯人與否，應依毒品\n    危害防制條例第18條第1 項前段規定沒收銷燬之。另扣得之\n    行動電話3 支（門號為0000000000號、0000000000、000000\n    0000000 ）尚無證據證明與本件運輸海洛因之犯行有關，爰\n    不予宣告沒收。\n五、共同被告葉榮富部分，業經原審判處罪刑確定，併此明。\n據上論結，應依刑事訴訟法第369 條第1 項前段、第364 條、第\n299 條第1 項前段，毒品危害防制條例第4 條第1 項、第18條第\n1 項前段，懲治走私條例第2 條第1 項、第11條前段，刑法第11\n條、第28條、第55條，判決如主文。\n本案經檢察官蔡國禎到庭執行職務。\n中    華    民    國  100     年    12    月    1     日\n                  刑事第二庭    審判長法  官 林正雄\n                                      法  官 黃壽燕\n                                      法  官 邱明弘\n以上正本證明與原本無異。\n如不服本判決應於收受本判決後10日內向本院提出上訴書狀，其\n未敘述上訴理由者，並得於提起上訴後10日內向本院補提理由書\n狀（均須按他造當事人之人數附繕本）「切勿逕送上級法院」。\n中    華    民    國  100     年    12    月    2     日\n                                      書記官 林淑敏\n附錄本判決論罪科刑法條：\n毒品危害防制條例第4條第1項\n製造、運輸、販賣第一級毒品者，處死刑或無期徒刑；處無期徒\n刑者，得併科新臺幣2 千萬元以下罰金。",
  "structure": {
    "main": "原判決關於房國輝部分撤銷。\n房國輝共同犯運輸第一級毒品罪，處有期徒刑貳拾年。扣案之海\n洛因拾塊（合計淨重3612.27公克，純度78.98%，純質淨重2852.\n97公克）均沒收銷燬之。",
    "fact": "一、葉榮富為高雄市「盈萊有限公司」（下稱盈萊公司）負責人\n    ，平日經營水產養殖及買賣，房國輝則係在越南從事水產買\n    賣業務，2 人均明知海洛因係毒品危害防制條例所列之第一\n    級毒品及管制進出口物品，竟共同謀議以盈萊公司名義進口\n    魚漿、魚片貨櫃，在魚漿夾藏毒品之方式，自越南走私海洛\n    因進口入台灣地區，雙方並約定均以行動電話簡訊方式連絡\n    運輸毒品事宜，於民國（以下同）98年4 月底，葉榮富先行\n    透過地下通匯匯款美金9 萬5 千元至越南，並指示房國輝負\n    責在越南自不詳人士處取得第一級毒品海洛因10塊後，再由\n    房國輝將上開毒品夾藏於欲進口之魚漿塊，而裝入編號WHLU\n    0000000 號貨櫃內，由葉榮富藉由「盈萊公司」進口水產之\n    名義，自越南進口上開貨櫃進入台灣。嗣於98年5 月27日該\n    貨櫃抵達高雄港第63號碼頭後，經法務部調查局南部地區機\n    動工作組、財政部高雄關稅局、台南縣警察局少年警察隊、\n    高雄港務警察局、高雄市新興分局、海巡署台東查緝隊、基\n    隆憲兵隊組成之專案小組查知葉榮富、房國輝業已走私海洛\n    因入境，並於同日上午抵達高雄小港機場欲出境，乃由檢察\n    官指揮專案小組成員前往高雄小港機場，拘提葉榮富、房國\n    輝2 人到案，並扣得2 人使用之行動電話3 支，復帶同前往\n    高雄港第63號碼頭查驗區，會同高雄關稅局人員開櫃查驗時\n    ，當場查獲夾藏於魚漿內之海洛因10塊（合計淨重3612.27\n    公克，純度78.98 ％，純質淨重2852.97 公克，起訴書誤載\n    為8 塊）。\n二、案經法務部調查局南部地區機動工作組移送台灣高雄地方法\n    院檢察署檢察官偵查起訴。",
    "reason": "壹、證據能力部分：\n一、按被告以外之人於偵查中向檢察官所為之陳述，除顯有不可\n    信之情況者外，得為證據，此為刑事訴訟法第159 條之1 第\n    2 項所明定。經查本件證人即同案被告葉榮富於偵查中就同\n    案被告房國輝部分所為之陳述，業經具結以擔保陳述之可信\n    性，且查無何顯不可信之情形，核之上開說明，自有證據能\n    力得作為本件認定犯罪事實之依據。\n二、按「法院或檢察官得囑託醫院、學校或其他相當之機關、團\n    體為鑑定，或審查他人之鑑定，並準用第203 條至第206 條\n    之1 之規定」、「鑑定之經過及其結果，應命鑑定人以言詞\n    或書面報告」，亦分別為刑事訴訟法第208 條第1 項前段、\n    第206 條第1 項定明定。是經法院或檢察官囑託相當之機關\n    為鑑定後，經鑑定人以書面報告其鑑定之結果者，即屬同法\n    第159 條第1 項所謂之「法律有規定者」，不受該條項規定\n    「不得作為證據」之限制。且同法第208 條第1 項前段對於\n    法院或檢察官囑託相當之機關為鑑定之情形，僅規定：「準\n    用第203 條至第206 條之1 之規定」，至於同法第202 條有\n    關「鑑定人應於鑑定前具結」之規定，則不在準用之列。故\n    於法院或檢察官囑託相當之機關為鑑定，而該受囑託機關以\n    書面報告鑑定結果之情形，既非屬依法應具結者。是同法第\n    158 條之3 有關「證人、鑑定人依法應具結而未具結者，其\n    證言或鑑定意見，不得作為證據」之規定，於此時即無適用\n    之餘地。經查，本件法務部調查局關於扣案塊狀物是否屬於\n    第一級毒品海洛因所為鑑定而出具之鑑定書，係臺灣高雄地\n    方法院檢察署以事前概括選任方式指揮法務部調查局南部地\n    區機動工作組逕行送請法務部調查局所為之鑑定，依上揭說\n    明，上開鑑定書亦有證據能力。\n貳、實體部分：\n一、上開夾藏走私海洛因磚進口之事實，業據共同被告葉榮富於\n    偵查、原審及本院前審中坦承不諱，並有上開塊狀物品10塊\n    扣案可資佐証，且該10塊塊狀物品經檢驗結果確含海洛因成\n    份（合計淨重3612.27 公克，含海洛因之純度78.98 ％，純\n    質淨重2852.97 公克），有法務部調查局98年7 月16日調科\n    壹字第09823019820 號鑑定書在卷可稽（見偵卷第103 頁）\n    。又該海洛因磚10塊是在高雄港第63號碼頭查驗區，由警方\n    會同高雄關稅局人員開櫃查驗時，當場查獲夾藏於魚漿內，\n    足見共同被告葉榮富之自白核與事實相符，事證明確，共同\n    被告葉榮富走私毒品海洛因犯行已堪以認定。\n二、訊之上訴人房國輝固不否認上開接受共同被告葉榮富之託，\n    由葉榮富在越南之友人將水產樣品，託之轉交給天龍水產有\n    限公司辦理出口，惟否認共同走私海洛因磚，辯稱：伊不知\n    道魚漿內夾藏有海洛因，伊未參與云云。惟查：\n（一）上訴人房國輝於偵查中已坦承：「（問：你的工作？）答\n      ：在越南經商」「（問：南機組今日在高雄港第63號碼頭\n      查獲一只WHLU0000000 號內夾藏有十塊海洛因磚貨櫃是否\n      你進口？）答：是，是我幫葉榮富處理帶進來的」「（問\n      ：你如何幫他處理？）答：葉榮富知道我的經濟情況不好\n      ，他問是否願意幫他帶四號毒品進口，一塊的價格是5 至\n      6 萬元」「（問：你是否在越南幫他處理？）答：是葉榮\n      富請人在越南將毒品交給我，我負責幫他把毒品裝進貨櫃\n      內」「（問：夾藏的方式？）答：放在魚漿內，辨識的方\n      式是魚漿的紙箱外面日期不同」「（問：有無其他意見陳\n      述？）答：我今天在現場有配合檢調查案，供出夾藏毒品\n      魚漿的位置，讓檢調能順利的偵案此案，請求從輕處理」\n      等語不諱（見98年5 月27日偵查筆錄，即偵查卷第47頁）\n      ；本院前審審理時上訴人房國輝辯稱：偵查筆錄是紀錄，\n      不是筆錄云云，自非可採。又本院並未引用上訴人房國輝\n      在調查局之詢問筆錄，辯護人質疑房國輝在調查局之詢問\n      筆錄，即無庸審酌，附此敘明。又證人即同案被告葉榮富\n      於偵查中亦陳稱：「（問：你是否有在98年5 月7 日以盈\n      萊公司名義進口櫃號為WHLU0000000 號貨櫃，申報進口貨\n      物為魚片及魚漿？）答：是」「（問：你是否透過貨櫃夾\n      藏十塊海洛因磚來台？）答：是」「（問：海洛因來源？\n      ）答：這部分是房國輝負責，我是負責在台灣接貨」「（\n      問：整個毒品購買及裝運過程由何人負責？）答：房國輝\n      」「（問：這批毒品如果成功走私可分得多少酬榮？）答\n      ：房國輝可分得60多萬元，我的部分大概是120 萬元」「\n      （問：走私的模式？）答：是用盈萊公司名義進口櫃，將\n      海洛因磚夾藏在貨櫃的魚漿內，載到冷凍庫」等語（見98\n      年5 月27日偵查筆錄，即偵查卷第45頁），上訴人葉榮富\n      、房國輝2 人就房國輝於本件海洛因順利進口後可得之利\n      益約60萬元一節，所述內容大致相符（房國輝於偵查中稱\n      幫葉榮富帶四號毒品進口一塊的價格是5 至6 萬元），又\n      一般得合法進口之物品何需夾藏於合法進口之魚漿中，且\n      如非海洛因等價格貴重且被查獲後須負擔嚴重刑責之高度\n      風險違禁物品，豈有僅係負責接貨裝櫃即可獲得60萬元之\n      高報酬之理，又上訴人房國輝係在越南從事商務多年之人\n      ，社會經歷豐富，對此應甚為瞭解，其於審理中翻異辯稱\n      不知幫忙接貨裝櫃之物係海洛因云云，顯係事後卸責之詞\n      ，不足採信。\n（二）雖證人即同案被告葉榮富於原審審理中另證稱：本件被查\n      獲之海洛因在越南裝櫃出來前，並未告知房國輝係海洛因\n      等語，惟亦稱：房國輝有跟他們（指在越南之人士）接觸\n      ，應該知道（是海洛因）等語（見原審卷第357 頁），依\n      其證述僅謂未明確告知房國輝夾藏之物係海洛因，惟又謂\n      房國輝應知情，其內容模擬兩可，不如上開其於偵查中所\n      證述之內容明確，顯有迴護共同被告房國輝之嫌，自難作\n      為有利被告房國輝之認定。又該證人即同案被告葉榮富本\n      院前審審理時已肯定陳稱：「（問：你有無轉達給房國輝\n      ，說這是什麼東西？）答：我有跟他提過，這個可能是違\n      禁物品，你自己決定，是否要運送」「（問：他有無問你\n      是何違禁物品，或是你講他聽了就算了？）答：他有問我\n      是什麼東西，我有跟他講說是毒品」「（問：毒品用一塊\n      來做夾帶，是否這樣跟他講，他就知道是海洛因？）答：\n      應該是這樣」等語（見100 年5 月3 日本院前審審判筆錄\n      ，即本院上訴審卷第180 頁），葉榮富已明確陳稱房國輝\n      知道是夾藏海洛因，仍不能為上訴人房國輝有利之証明，\n      且上訴人房國輝知悉夾藏物品辨識的方式是魚漿的紙箱外\n      面日期不同（見98年5 月27日偵查筆錄），嗣後上訴人房\n      國輝在小港機場大廳被捕，並押往第63號碼頭檢查其進口\n      之貨櫃時，果在該貨櫃內之不同製造日期之魚漿內，啟出\n      該10塊海洛因磚，並有上開10塊海洛因磚扣案可資佐証，\n      且該10塊塊狀物品經調查局鑑驗結果確含海洛因成份，已\n      如前述，足見上訴人房國輝確有參與本件10塊海洛因磚之\n      走私進口。\n    綜上所述，因上訴人房國輝在偵查中已坦承：「是葉榮富請\n    人在越南將毒品交給我，我負責幫他把毒品裝進貨櫃內」「\n    放在魚漿內，辨識的方式是魚漿的紙箱外面日期不同」等語\n    ，又房國輝在小港機場大廳被捕，並押往第63號碼頭檢查其\n    進口之貨櫃時，果在該貨櫃內之不同製造日期之魚漿內，啟\n    出該10 塊 海洛因磚，事証明確，其於審理中翻異前供，辯\n    稱：不知幫忙接貨裝櫃之物係海洛因云云，係事後翻異卸責\n    之詞，不足採信，其犯行已堪認定。\n（三）被告之辯護人於本院審理時，聲請勘驗夾藏海洛因毒品之\n      魚漿樣本紙箱外觀，待證事項：證明紙箱外面標示之日期\n      是否有不同？有無另作記號？經本院於100 年11月17日勘\n      驗結果，該夾藏海洛因毒品之魚漿標本紙箱外面標示之生\n      產日期為2009年3 月1 日，又「Expiry date」後面的冒號\n      「：」被刮除，有勘驗筆錄可佐（見本院卷第100 頁反面\n      、第101 頁）。\n    查本案於98年5 月27日案發時，只扣押夾藏海洛因之魚漿外\n    包裝紙箱1 個，而未夾藏海洛因之魚漿外包裝紙箱則未扣押\n    （見偵卷第15頁）。故兩者紙箱外面標示之日期是否有不同\n    ，則無法比較。又另從偵查卷第30頁至第41頁所附之照片觀\n    之，亦看不出兩者紙箱外面標示之日期有何不同。但從上訴\n    人房國輝在偵查中坦承：「放在魚漿內，辨識的方式是魚漿\n    的紙箱外面日期不同」，及房國輝在小港機場大廳被捕，並\n    押往第63號碼頭檢查其進口之貨櫃時，果在該貨櫃內之不同\n    製造日期之魚漿內，啟出該10塊海洛因等情節已如前述，則\n    就上訴人房國輝知情啟出之海洛因確係藏放該貨櫃內之不同\n    製造日期之魚漿內一節，應可採信。\n三、按海洛因為毒品危害防制條例第2 條第1 項第1 款所定之第\n    一級毒品，且屬行政院依懲治走私條例第2 條第4 項授權公\n    告之「管制物品項目及數額」所列甲項第4 款之管制進口物\n    品，依法不得持有、運輸或私運進口。核上訴人葉榮富、房\n    國輝2 人所為，均係犯毒品危害防制條例第4 條第1 項之運\n    輸第一級毒品罪、懲治走私條例第2 條第1 項之私運管制物\n    品進口罪。上訴人葉榮富、房國輝2 人持有第一級毒品海洛\n    因之低度行為，已為運輸毒品之高度行為所吸收，不另論其\n    持有毒品罪。上訴人葉榮富、房國輝2 人間，就上開走私毒\n    品海洛因犯行，互有犯意聯絡及行為分擔，均應論以共同正\n    犯。上訴人葉榮富、房國輝2 人係以一行為同時觸犯運輸第\n    一級毒品罪及私運管制物品進口罪，為想像競合犯，應依刑\n    法第55條規定從較重之運輸第一級毒品罪處斷。又運輸第一\n    級毒品係法定刑為「死刑、無期徒刑」之罪，罪刑至為嚴峻\n    ，被告房國輝固有上開運輸海洛因之行為，然參之被告房國\n    輝係一時受誘而在越南交付海洛因予出口公司裝櫃運往國內\n    ，其並非主導本件運輸海洛因之人，且運輸之毒品尚未流入\n    市面造成實際危害，其亦未實際獲取龐大利益，其犯罪情節\n    若遽處以販賣毒品罪之法定本刑，除無從藉由量刑顯示、區\n    分行為人之惡性及犯罪情節輕重外，亦誠屬情輕法重，過於\n    嚴苛，其犯罪情狀在客觀上足以引起一般同情，堪予憫恕，\n    縱使科以法定最低刑度，猶為過重，爰就其所犯運輸第一級\n    毒品罪，依刑法第59條之規定酌減其刑。\n四、原審據以論處被告房國輝共同犯運輸第一級毒品罪，固非無\n    見。惟查無期徒刑減輕者，為二十年以下十五年以上有期徒\n    刑，刑法第65條第2 項定有明文。原判決理由欄對被告房國\n    輝有述減輕其刑，卻量處被告房國輝有期徒刑22年，超過\n    法定刑，顯有違誤。被告房國輝上訴，否認犯罪，雖無理由\n    ，但原判決關於被告房國輝部分既有可議之處，仍應就此部\n    分撤銷改判。審酌被告運輸之海洛因數量非少，對於國人健\n    康及社會治安之潛在危害甚大，惟甫入境即為警查獲，尚未\n    對國人造成具體毒害，被告房國輝未能坦承犯行，態度不佳\n    及其他等一切情狀，量處有期徒刑20年。扣案之海洛因10塊\n    （合計淨重3612.27 公克，純度78.98 ％，純質淨重2852.9\n    7 公克），係屬第一級毒品，不問屬於犯人與否，應依毒品\n    危害防制條例第18條第1 項前段規定沒收銷燬之。另扣得之\n    行動電話3 支（門號為0000000000號、0000000000、000000\n    0000000 ）尚無證據證明與本件運輸海洛因之犯行有關，爰\n    不予宣告沒收。\n五、共同被告葉榮富部分，業經原審判處罪刑確定，併此明。\n據上論結，應依刑事訴訟法第369 條第1 項前段、第364 條、第\n299 條第1 項前段，毒品危害防制條例第4 條第1 項、第18條第\n1 項前段，懲治走私條例第2 條第1 項、第11條前段，刑法第11\n條、第28條、第55條，判決如主文。\n本案經檢察官蔡國禎到庭執行職務。\n中    華    民    國  100     年    12    月    1     日\n                  刑事第二庭    審判長法  官 林正雄\n                                      法  官 黃壽燕\n                                      法  官 邱明弘\n以上正本證明與原本無異。\n如不服本判決應於收受本判決後10日內向本院提出上訴書狀，其\n未敘述上訴理由者，並得於提起上訴後10日內向本院補提理由書\n狀（均須按他造當事人之人數附繕本）「切勿逕送上級法院」。"
  },
  "search": "臺灣高等法院高雄分院刑事判決100年度上更(一)字第94號上訴人即被告房國輝選任辯護人洪國欽律師上列上訴人因毒品危害防制條例等案件，不服臺灣高雄地方法院98年度重訴字第50號中華民國99年12月9日第一審判決（起訴案號：臺灣高雄地方法院檢察署98年度偵字第16214號），提起上訴，經判決後，由最高法院發回更審，本院判決如下：主文原判決關於房國輝部分撤銷。房國輝共同犯運輸第一級毒品罪，處有期徒刑貳拾年。扣案之海洛因拾塊（合計淨重3612.27公克，純度78.98%，純質淨重2852.97公克）均沒收銷燬之。事實一、葉榮富為高雄市「盈萊有限公司」（下稱盈萊公司）負責人，平日經營水產養殖及買賣，房國輝則係在越南從事水產買賣業務，2人均明知海洛因係毒品危害防制條例所列之第一級毒品及管制進出口物品，竟共同謀議以盈萊公司名義進口魚漿、魚片貨櫃，在魚漿夾藏毒品之方式，自越南走私海洛因進口入台灣地區，雙方並約定均以行動電話簡訊方式連絡運輸毒品事宜，於民國（以下同）98年4月底，葉榮富先行透過地下通匯匯款美金9萬5千元至越南，並指示房國輝負責在越南自不詳人士處取得第一級毒品海洛因10塊後，再由房國輝將上開毒品夾藏於欲進口之魚漿塊，而裝入編號WHLU0000000號貨櫃內，由葉榮富藉由「盈萊公司」進口水產之名義，自越南進口上開貨櫃進入台灣。嗣於98年5月27日該貨櫃抵達高雄港第63號碼頭後，經法務部調查局南部地區機動工作組、財政部高雄關稅局、台南縣警察局少年警察隊、高雄港務警察局、高雄市新興分局、海巡署台東查緝隊、基隆憲兵隊組成之專案小組查知葉榮富、房國輝業已走私海洛因入境，並於同日上午抵達高雄小港機場欲出境，乃由檢察官指揮專案小組成員前往高雄小港機場，拘提葉榮富、房國輝2人到案，並扣得2人使用之行動電話3支，復帶同前往高雄港第63號碼頭查驗區，會同高雄關稅局人員開櫃查驗時，當場查獲夾藏於魚漿內之海洛因10塊（合計淨重3612.27公克，純度78.98％，純質淨重2852.97公克，起訴書誤載為8塊）。二、案經法務部調查局南部地區機動工作組移送台灣高雄地方法院檢察署檢察官偵查起訴。理由壹、證據能力部分：一、按被告以外之人於偵查中向檢察官所為之陳述，除顯有不可信之情況者外，得為證據，此為刑事訴訟法第159條之1第2項所明定。經查本件證人即同案被告葉榮富於偵查中就同案被告房國輝部分所為之陳述，業經具結以擔保陳述之可信性，且查無何顯不可信之情形，核之上開說明，自有證據能力得作為本件認定犯罪事實之依據。二、按「法院或檢察官得囑託醫院、學校或其他相當之機關、團體為鑑定，或審查他人之鑑定，並準用第203條至第206條之1之規定」、「鑑定之經過及其結果，應命鑑定人以言詞或書面報告」，亦分別為刑事訴訟法第208條第1項前段、第206條第1項定明定。是經法院或檢察官囑託相當之機關為鑑定後，經鑑定人以書面報告其鑑定之結果者，即屬同法第159條第1項所謂之「法律有規定者」，不受該條項規定「不得作為證據」之限制。且同法第208條第1項前段對於法院或檢察官囑託相當之機關為鑑定之情形，僅規定：「準用第203條至第206條之1之規定」，至於同法第202條有關「鑑定人應於鑑定前具結」之規定，則不在準用之列。故於法院或檢察官囑託相當之機關為鑑定，而該受囑託機關以書面報告鑑定結果之情形，既非屬依法應具結者。是同法第158條之3有關「證人、鑑定人依法應具結而未具結者，其證言或鑑定意見，不得作為證據」之規定，於此時即無適用之餘地。經查，本件法務部調查局關於扣案塊狀物是否屬於第一級毒品海洛因所為鑑定而出具之鑑定書，係臺灣高雄地方法院檢察署以事前概括選任方式指揮法務部調查局南部地區機動工作組逕行送請法務部調查局所為之鑑定，依上揭說明，上開鑑定書亦有證據能力。貳、實體部分：一、上開夾藏走私海洛因磚進口之事實，業據共同被告葉榮富於偵查、原審及本院前審中坦承不諱，並有上開塊狀物品10塊扣案可資佐証，且該10塊塊狀物品經檢驗結果確含海洛因成份（合計淨重3612.27公克，含海洛因之純度78.98％，純質淨重2852.97公克），有法務部調查局98年7月16日調科壹字第09823019820號鑑定書在卷可稽（見偵卷第103頁）。又該海洛因磚10塊是在高雄港第63號碼頭查驗區，由警方會同高雄關稅局人員開櫃查驗時，當場查獲夾藏於魚漿內，足見共同被告葉榮富之自白核與事實相符，事證明確，共同被告葉榮富走私毒品海洛因犯行已堪以認定。二、訊之上訴人房國輝固不否認上開接受共同被告葉榮富之託，由葉榮富在越南之友人將水產樣品，託之轉交給天龍水產有限公司辦理出口，惟否認共同走私海洛因磚，辯稱：伊不知道魚漿內夾藏有海洛因，伊未參與云云。惟查：（一）上訴人房國輝於偵查中已坦承：「（問：你的工作？）答：在越南經商」「（問：南機組今日在高雄港第63號碼頭查獲一只WHLU0000000號內夾藏有十塊海洛因磚貨櫃是否你進口？）答：是，是我幫葉榮富處理帶進來的」「（問：你如何幫他處理？）答：葉榮富知道我的經濟情況不好，他問是否願意幫他帶四號毒品進口，一塊的價格是5至6萬元」「（問：你是否在越南幫他處理？）答：是葉榮富請人在越南將毒品交給我，我負責幫他把毒品裝進貨櫃內」「（問：夾藏的方式？）答：放在魚漿內，辨識的方式是魚漿的紙箱外面日期不同」「（問：有無其他意見陳述？）答：我今天在現場有配合檢調查案，供出夾藏毒品魚漿的位置，讓檢調能順利的偵案此案，請求從輕處理」等語不諱（見98年5月27日偵查筆錄，即偵查卷第47頁）；本院前審審理時上訴人房國輝辯稱：偵查筆錄是紀錄，不是筆錄云云，自非可採。又本院並未引用上訴人房國輝在調查局之詢問筆錄，辯護人質疑房國輝在調查局之詢問筆錄，即無庸審酌，附此敘明。又證人即同案被告葉榮富於偵查中亦陳稱：「（問：你是否有在98年5月7日以盈萊公司名義進口櫃號為WHLU0000000號貨櫃，申報進口貨物為魚片及魚漿？）答：是」「（問：你是否透過貨櫃夾藏十塊海洛因磚來台？）答：是」「（問：海洛因來源？）答：這部分是房國輝負責，我是負責在台灣接貨」「（問：整個毒品購買及裝運過程由何人負責？）答：房國輝」「（問：這批毒品如果成功走私可分得多少酬榮？）答：房國輝可分得60多萬元，我的部分大概是120萬元」「（問：走私的模式？）答：是用盈萊公司名義進口櫃，將海洛因磚夾藏在貨櫃的魚漿內，載到冷凍庫」等語（見98年5月27日偵查筆錄，即偵查卷第45頁），上訴人葉榮富、房國輝2人就房國輝於本件海洛因順利進口後可得之利益約60萬元一節，所述內容大致相符（房國輝於偵查中稱幫葉榮富帶四號毒品進口一塊的價格是5至6萬元），又一般得合法進口之物品何需夾藏於合法進口之魚漿中，且如非海洛因等價格貴重且被查獲後須負擔嚴重刑責之高度風險違禁物品，豈有僅係負責接貨裝櫃即可獲得60萬元之高報酬之理，又上訴人房國輝係在越南從事商務多年之人，社會經歷豐富，對此應甚為瞭解，其於審理中翻異辯稱不知幫忙接貨裝櫃之物係海洛因云云，顯係事後卸責之詞，不足採信。（二）雖證人即同案被告葉榮富於原審審理中另證稱：本件被查獲之海洛因在越南裝櫃出來前，並未告知房國輝係海洛因等語，惟亦稱：房國輝有跟他們（指在越南之人士）接觸，應該知道（是海洛因）等語（見原審卷第357頁），依其證述僅謂未明確告知房國輝夾藏之物係海洛因，惟又謂房國輝應知情，其內容模擬兩可，不如上開其於偵查中所證述之內容明確，顯有迴護共同被告房國輝之嫌，自難作為有利被告房國輝之認定。又該證人即同案被告葉榮富本院前審審理時已肯定陳稱：「（問：你有無轉達給房國輝，說這是什麼東西？）答：我有跟他提過，這個可能是違禁物品，你自己決定，是否要運送」「（問：他有無問你是何違禁物品，或是你講他聽了就算了？）答：他有問我是什麼東西，我有跟他講說是毒品」「（問：毒品用一塊來做夾帶，是否這樣跟他講，他就知道是海洛因？）答：應該是這樣」等語（見100年5月3日本院前審審判筆錄，即本院上訴審卷第180頁），葉榮富已明確陳稱房國輝知道是夾藏海洛因，仍不能為上訴人房國輝有利之証明，且上訴人房國輝知悉夾藏物品辨識的方式是魚漿的紙箱外面日期不同（見98年5月27日偵查筆錄），嗣後上訴人房國輝在小港機場大廳被捕，並押往第63號碼頭檢查其進口之貨櫃時，果在該貨櫃內之不同製造日期之魚漿內，啟出該10塊海洛因磚，並有上開10塊海洛因磚扣案可資佐証，且該10塊塊狀物品經調查局鑑驗結果確含海洛因成份，已如前述，足見上訴人房國輝確有參與本件10塊海洛因磚之走私進口。綜上所述，因上訴人房國輝在偵查中已坦承：「是葉榮富請人在越南將毒品交給我，我負責幫他把毒品裝進貨櫃內」「放在魚漿內，辨識的方式是魚漿的紙箱外面日期不同」等語，又房國輝在小港機場大廳被捕，並押往第63號碼頭檢查其進口之貨櫃時，果在該貨櫃內之不同製造日期之魚漿內，啟出該10塊海洛因磚，事証明確，其於審理中翻異前供，辯稱：不知幫忙接貨裝櫃之物係海洛因云云，係事後翻異卸責之詞，不足採信，其犯行已堪認定。（三）被告之辯護人於本院審理時，聲請勘驗夾藏海洛因毒品之魚漿樣本紙箱外觀，待證事項：證明紙箱外面標示之日期是否有不同？有無另作記號？經本院於100年11月17日勘驗結果，該夾藏海洛因毒品之魚漿標本紙箱外面標示之生產日期為2009年3月1日，又「Expirydate」後面的冒號「：」被刮除，有勘驗筆錄可佐（見本院卷第100頁反面、第101頁）。查本案於98年5月27日案發時，只扣押夾藏海洛因之魚漿外包裝紙箱1個，而未夾藏海洛因之魚漿外包裝紙箱則未扣押（見偵卷第15頁）。故兩者紙箱外面標示之日期是否有不同，則無法比較。又另從偵查卷第30頁至第41頁所附之照片觀之，亦看不出兩者紙箱外面標示之日期有何不同。但從上訴人房國輝在偵查中坦承：「放在魚漿內，辨識的方式是魚漿的紙箱外面日期不同」，及房國輝在小港機場大廳被捕，並押往第63號碼頭檢查其進口之貨櫃時，果在該貨櫃內之不同製造日期之魚漿內，啟出該10塊海洛因等情節已如前述，則就上訴人房國輝知情啟出之海洛因確係藏放該貨櫃內之不同製造日期之魚漿內一節，應可採信。三、按海洛因為毒品危害防制條例第2條第1項第1款所定之第一級毒品，且屬行政院依懲治走私條例第2條第4項授權公告之「管制物品項目及數額」所列甲項第4款之管制進口物品，依法不得持有、運輸或私運進口。核上訴人葉榮富、房國輝2人所為，均係犯毒品危害防制條例第4條第1項之運輸第一級毒品罪、懲治走私條例第2條第1項之私運管制物品進口罪。上訴人葉榮富、房國輝2人持有第一級毒品海洛因之低度行為，已為運輸毒品之高度行為所吸收，不另論其持有毒品罪。上訴人葉榮富、房國輝2人間，就上開走私毒品海洛因犯行，互有犯意聯絡及行為分擔，均應論以共同正犯。上訴人葉榮富、房國輝2人係以一行為同時觸犯運輸第一級毒品罪及私運管制物品進口罪，為想像競合犯，應依刑法第55條規定從較重之運輸第一級毒品罪處斷。又運輸第一級毒品係法定刑為「死刑、無期徒刑」之罪，罪刑至為嚴峻，被告房國輝固有上開運輸海洛因之行為，然參之被告房國輝係一時受誘而在越南交付海洛因予出口公司裝櫃運往國內，其並非主導本件運輸海洛因之人，且運輸之毒品尚未流入市面造成實際危害，其亦未實際獲取龐大利益，其犯罪情節若遽處以販賣毒品罪之法定本刑，除無從藉由量刑顯示、區分行為人之惡性及犯罪情節輕重外，亦誠屬情輕法重，過於嚴苛，其犯罪情狀在客觀上足以引起一般同情，堪予憫恕，縱使科以法定最低刑度，猶為過重，爰就其所犯運輸第一級毒品罪，依刑法第59條之規定酌減其刑。四、原審據以論處被告房國輝共同犯運輸第一級毒品罪，固非無見。惟查無期徒刑減輕者，為二十年以下十五年以上有期徒刑，刑法第65條第2項定有明文。原判決理由欄對被告房國輝有述減輕其刑，卻量處被告房國輝有期徒刑22年，超過法定刑，顯有違誤。被告房國輝上訴，否認犯罪，雖無理由，但原判決關於被告房國輝部分既有可議之處，仍應就此部分撤銷改判。審酌被告運輸之海洛因數量非少，對於國人健康及社會治安之潛在危害甚大，惟甫入境即為警查獲，尚未對國人造成具體毒害，被告房國輝未能坦承犯行，態度不佳及其他等一切情狀，量處有期徒刑20年。扣案之海洛因10塊（合計淨重3612.27公克，純度78.98％，純質淨重2852.97公克），係屬第一級毒品，不問屬於犯人與否，應依毒品危害防制條例第18條第1項前段規定沒收銷燬之。另扣得之行動電話3支（門號為0000000000號、0000000000、0000000000000）尚無證據證明與本件運輸海洛因之犯行有關，爰不予宣告沒收。五、共同被告葉榮富部分，業經原審判處罪刑確定，併此明。據上論結，應依刑事訴訟法第369條第1項前段、第364條、第299條第1項前段，毒品危害防制條例第4條第1項、第18條第1項前段，懲治走私條例第2條第1項、第11條前段，刑法第11條、第28條、第55條，判決如主文。本案經檢察官蔡國禎到庭執行職務。中華民國100年12月1日刑事第二庭審判長法官林正雄法官黃壽燕法官邱明弘以上正本證明與原本無異。如不服本判決應於收受本判決後10日內向本院提出上訴書狀，其未敘述上訴理由者，並得於提起上訴後10日內向本院補提理由書狀（均須按他造當事人之人數附繕本）「切勿逕送上級法院」。中華民國100年12月2日書記官林淑敏附錄本判決論罪科刑法條：毒品危害防制條例第4條第1項製造、運輸、販賣第一級毒品者，處死刑或無期徒刑；處無期徒刑者，得併科新臺幣2千萬元以下罰金。",
  "characters": {
    "judges": [
      "林正雄",
      "黃壽燕",
      "邱明弘"
    ],
    "prosecutors": [
      "蔡國禎"
    ],
    "lawyers": [
      "洪國欽"
    ],
    "clerks": [
      "林淑敏"
    ],
    "plaintiffs": [

    ],
    "defendants": [
      "房國輝"
    ],
    "prosecutor_office": [

    ],
    "creditors": [

    ],
    "debtors": [

    ],
    "judicial_associate_officer": [

    ]
  },
  "adjudged_at": "2011-12-01",
  "created_at": "2016-02-13 12:29:24",
  "updated_at": "2016-02-13 12:29:24"
}