{
  "identify": "PCD-100-簡-8092-20111202-1",
  "court": {
    "name": "臺灣新北地方法院",
    "code": "PCD"
  },
  "division": {
    "name": "刑事",
    "code": "M"
  },
  "year": 100,
  "word": "簡",
  "number": "8092",
  "jcheck": "1",
  "reason": "毒品危害防制條例",
  "content": "臺灣板橋地方法院刑事簡易判決         100年度簡字第8092號\n聲  請  人  臺灣板橋地方法院檢察署檢察官\n被      告  蔡淑惠\n上列被告因違反毒品危害防制條例案件，經檢察官聲請以簡易判\n決處刑（100 年度偵字第21857 號），本院判決如下：\n    主  文\n蔡淑惠持有第一級毒品，處拘役拾日，如易科罰金，以新臺幣\n壹仟元折算壹日。扣案之第一級毒品海洛因壹包（驗餘淨重零點\n零伍零公克）沒收銷燬。\n    事實及理由\n一、本件犯罪事實及證據，除檢察官聲請簡易判決處刑書中所載\n    「海洛因1 包（毛重0.2940公克、驗後餘重0.0530公克）」\n    均補充更正為「海洛因1 包（淨重0.0540公克，取樣0.0010\n    公克鑑驗用罄，驗餘淨重0.0530公克）」，及證據並所犯法\n    條欄一「交通部民用航空局航空醫務中心毒品鑑定書」補充\n    更正為「交通部民用航空局航空醫務中心100 年9 月20日航\n    藥鑑字第1004744 號毒品鑑定書」，並補充「新北市政府警\n    察局蘆洲分局搜索扣押筆錄及扣押物品目錄表各1 份」、「\n    照片2 張」外，其餘均引用如附件檢察官聲請簡易判決處刑\n    書之記載。\n二、核被告蔡淑惠所為，係犯毒品危害防制條例第11條第1 項之\n    持有第一級毒品罪。爰審酌被告無視於政府所推動之禁毒政\n    策，未經許可無故持有第一級毒品，所為實屬不當，惟念其\n    犯罪後坦承犯行、態度良好，又所持有之第一級毒品數量非\n    鉅，兼衡其犯罪之動機、目的、手段、平日素行及其教育程\n    度為高職畢業、家庭經濟狀況勉持等一切情狀，量處如主文\n    所示之刑，併諭知易科罰金之折算標準。另扣案之毒品海洛\n    因1包（淨重0.0540公克，取樣0.0010公克鑑驗用罄，驗餘\n    淨重0.0530公克），為本案查獲之第一級毒品，應依毒品危\n    害防制條例第18條第1 項前段規定宣告沒收銷燬。\n三、依刑事訴訟法第449 條第1 項前段、第3 項、第454 條第2\n    項、第450 條第1 項，毒品危害防制條例第11條第1 項、第\n    18條第1 項前段，刑法第11條、第41條第1 項前段，逕以簡\n    易判決處刑如主文。\n四、如不服本判決，得自收受送達之日起十日內向本院提出上訴\n    狀，上訴於本院第二審合議庭（須附繕本）。\n中    華    民    國   100    年    12    月    2     日\n                  刑事第二十三庭  法  官  詹蕙嘉\n上列正本證明與原本無異。\n                                  書記官  陳語嫣\n中    華    民    國   100    年    12    月    6     日\n附錄本案論罪科刑法條全文：\n毒品危害防制條例第11條\n持有第一級毒品者，處 3 年以下有期徒刑、拘役或新臺幣 5 萬\n元以下罰金。\n持有第二級毒品者，處 2 年以下有期徒刑、拘役或新臺幣 3 萬\n元以下罰金。\n持有第一級毒品純質淨重十公克以上者，處 1 年以上 7 年以下\n有期徒刑，得併科新臺幣 1 百萬元以下罰金。\n持有第二級毒品純質淨重二十公克以上者，處 6 月以上 5 年以\n下有期徒刑，得併科新臺幣 70 萬元以下罰金。\n持有第三級毒品純質淨重二十公克以上者，處 3 年以下有期徒\n刑，得併科新臺幣 30 萬元以下罰金。\n持有第四級毒品純質淨重二十公克以上者，處 1 年以下有期徒\n刑，得併科新臺幣 10 萬元以下罰金。\n持有專供製造或施用第一級、第二級毒品之器具者，處 1 年以\n下有期徒刑、拘役或新臺幣 1 萬元以下罰金。\n附件：\n臺灣板橋地方法院檢察署檢察官聲請簡易判決處刑書\n                                    100年度偵字第21857號\n    被      告  蔡淑惠  女  31歲（民國○○年○月○○日生）\n                        住新北市○○區○○路172號2樓\n                        國民身分證統一編號：Ｚ000000000號\n上列被告因違反毒品危害防制條例案件，業經偵查終結，認為宜\n以簡易判決處刑，茲將犯罪事實及證據並所犯法條分敘如下：\n         犯罪事實\n一、蔡淑惠明知海洛因係毒品危害防制條例所列管之第一級毒品\n    ，不得非法持有，竟基於持有第一級毒品海洛因之犯意，於\n    民國100年8月2日中午12時許，自真實姓名年籍不詳之成年\n    人取得海洛因1包而持有之。嗣於100年8月11日上午9時40分\n    許，在新北市○○區○○路174號前，因行蹤可疑，為警當\n    場查獲其身上持有海洛因1包（毛重0.2940公克、驗後餘重\n    0.0530公克），始查悉上情。\n二、案經新北市政府警察局蘆洲分局移送偵辦。\n          證據並所犯法條\n一、上揭犯罪事實，業據被告蔡淑惠於警詢及偵查中坦承不諱，\n    ，並有第一級毒品海洛因1包扣案可資佐證；又扣案毒品含\n    有第一級毒品海洛因成分，有交通部民用航空局航空醫務中\n    心毒品鑑定書附卷可佐，被告之自白核與事實相符，其犯行\n    洵足認定。\n二、核被告所為，係犯毒品危害防制條例第11條第1項之持有第\n    一級毒品海洛因罪嫌。至扣案之第一級毒品海洛因1包（毛\n    重0.294 0公克、驗後餘重0.0530公克），請依同條例第18\n    條第1項前段規定宣告沒收並銷燬之。\n三、依刑事訴訟法第451條第1項聲請逕以簡易判決處刑。\n    此    致\n臺灣板橋地方法院\n中    華    民    國   100    年    10    月    31    日\n                              檢  察  官  姜麗君\n本件正本證明與原本無異\n中    華    民    國   100    年    11    月    4     日\n                              書  記  官\n附錄本案所犯法條全文\n毒品危害防制條例第11條\n持有第一級毒品者，處 3 年以下有期徒刑、拘役或新臺幣 5 萬\n元以下罰金。\n持有第二級毒品者，處 2 年以下有期徒刑、拘役或新臺幣 3 萬\n元以下罰金。\n持有專供製造或施用第一、二級毒品之器具者，處 1 年以下有期\n徒刑、拘役或新臺幣 1 萬元以下罰金。\n持有毒品達一定數量者，加重其刑至二分之一，其標準由行政院\n定之。\n本件係依刑事訴訟法簡易程序辦理，法院簡易庭得不傳喚被告、\n輔佐人、告訴人、告發人等出庭即以簡易判決處刑；被告、被害\n人、告訴人等對於告訴乃論案件如已達成民事和解而要撤回告訴\n或對非告訴乃論案件認有受傳喚到庭陳述意見之必要時，請即另\n以書狀向簡易法庭陳述或請求傳訊。",
  "structure": {
    "main": "蔡淑惠持有第一級毒品，處拘役拾日，如易科罰金，以新臺幣\n壹仟元折算壹日。扣案之第一級毒品海洛因壹包（驗餘淨重零點\n零伍零公克）沒收銷燬。",
    "fact": "一、本件犯罪事實及證據，除檢察官聲請簡易判決處刑書中所載\n    「海洛因1 包（毛重0.2940公克、驗後餘重0.0530公克）」\n    均補充更正為「海洛因1 包（淨重0.0540公克，取樣0.0010\n    公克鑑驗用罄，驗餘淨重0.0530公克）」，及證據並所犯法\n    條欄一「交通部民用航空局航空醫務中心毒品鑑定書」補充\n    更正為「交通部民用航空局航空醫務中心100 年9 月20日航\n    藥鑑字第1004744 號毒品鑑定書」，並補充「新北市政府警\n    察局蘆洲分局搜索扣押筆錄及扣押物品目錄表各1 份」、「\n    照片2 張」外，其餘均引用如附件檢察官聲請簡易判決處刑\n    書之記載。\n二、核被告蔡淑惠所為，係犯毒品危害防制條例第11條第1 項之\n    持有第一級毒品罪。爰審酌被告無視於政府所推動之禁毒政\n    策，未經許可無故持有第一級毒品，所為實屬不當，惟念其\n    犯罪後坦承犯行、態度良好，又所持有之第一級毒品數量非\n    鉅，兼衡其犯罪之動機、目的、手段、平日素行及其教育程\n    度為高職畢業、家庭經濟狀況勉持等一切情狀，量處如主文\n    所示之刑，併諭知易科罰金之折算標準。另扣案之毒品海洛\n    因1包（淨重0.0540公克，取樣0.0010公克鑑驗用罄，驗餘\n    淨重0.0530公克），為本案查獲之第一級毒品，應依毒品危\n    害防制條例第18條第1 項前段規定宣告沒收銷燬。\n三、依刑事訴訟法第449 條第1 項前段、第3 項、第454 條第2\n    項、第450 條第1 項，毒品危害防制條例第11條第1 項、第\n    18條第1 項前段，刑法第11條、第41條第1 項前段，逕以簡\n    易判決處刑如主文。\n四、如不服本判決，得自收受送達之日起十日內向本院提出上訴\n    狀，上訴於本院第二審合議庭（須附繕本）。",
    "reason": "一、本件犯罪事實及證據，除檢察官聲請簡易判決處刑書中所載\n    「海洛因1 包（毛重0.2940公克、驗後餘重0.0530公克）」\n    均補充更正為「海洛因1 包（淨重0.0540公克，取樣0.0010\n    公克鑑驗用罄，驗餘淨重0.0530公克）」，及證據並所犯法\n    條欄一「交通部民用航空局航空醫務中心毒品鑑定書」補充\n    更正為「交通部民用航空局航空醫務中心100 年9 月20日航\n    藥鑑字第1004744 號毒品鑑定書」，並補充「新北市政府警\n    察局蘆洲分局搜索扣押筆錄及扣押物品目錄表各1 份」、「\n    照片2 張」外，其餘均引用如附件檢察官聲請簡易判決處刑\n    書之記載。\n二、核被告蔡淑惠所為，係犯毒品危害防制條例第11條第1 項之\n    持有第一級毒品罪。爰審酌被告無視於政府所推動之禁毒政\n    策，未經許可無故持有第一級毒品，所為實屬不當，惟念其\n    犯罪後坦承犯行、態度良好，又所持有之第一級毒品數量非\n    鉅，兼衡其犯罪之動機、目的、手段、平日素行及其教育程\n    度為高職畢業、家庭經濟狀況勉持等一切情狀，量處如主文\n    所示之刑，併諭知易科罰金之折算標準。另扣案之毒品海洛\n    因1包（淨重0.0540公克，取樣0.0010公克鑑驗用罄，驗餘\n    淨重0.0530公克），為本案查獲之第一級毒品，應依毒品危\n    害防制條例第18條第1 項前段規定宣告沒收銷燬。\n三、依刑事訴訟法第449 條第1 項前段、第3 項、第454 條第2\n    項、第450 條第1 項，毒品危害防制條例第11條第1 項、第\n    18條第1 項前段，刑法第11條、第41條第1 項前段，逕以簡\n    易判決處刑如主文。\n四、如不服本判決，得自收受送達之日起十日內向本院提出上訴\n    狀，上訴於本院第二審合議庭（須附繕本）。"
  },
  "search": "臺灣板橋地方法院刑事簡易判決100年度簡字第8092號聲請人臺灣板橋地方法院檢察署檢察官被告蔡淑惠上列被告因違反毒品危害防制條例案件，經檢察官聲請以簡易判決處刑（100年度偵字第21857號），本院判決如下：主文蔡淑惠持有第一級毒品，處拘役拾日，如易科罰金，以新臺幣壹仟元折算壹日。扣案之第一級毒品海洛因壹包（驗餘淨重零點零伍零公克）沒收銷燬。事實及理由一、本件犯罪事實及證據，除檢察官聲請簡易判決處刑書中所載「海洛因1包（毛重0.2940公克、驗後餘重0.0530公克）」均補充更正為「海洛因1包（淨重0.0540公克，取樣0.0010公克鑑驗用罄，驗餘淨重0.0530公克）」，及證據並所犯法條欄一「交通部民用航空局航空醫務中心毒品鑑定書」補充更正為「交通部民用航空局航空醫務中心100年9月20日航藥鑑字第1004744號毒品鑑定書」，並補充「新北市政府警察局蘆洲分局搜索扣押筆錄及扣押物品目錄表各1份」、「照片2張」外，其餘均引用如附件檢察官聲請簡易判決處刑書之記載。二、核被告蔡淑惠所為，係犯毒品危害防制條例第11條第1項之持有第一級毒品罪。爰審酌被告無視於政府所推動之禁毒政策，未經許可無故持有第一級毒品，所為實屬不當，惟念其犯罪後坦承犯行、態度良好，又所持有之第一級毒品數量非鉅，兼衡其犯罪之動機、目的、手段、平日素行及其教育程度為高職畢業、家庭經濟狀況勉持等一切情狀，量處如主文所示之刑，併諭知易科罰金之折算標準。另扣案之毒品海洛因1包（淨重0.0540公克，取樣0.0010公克鑑驗用罄，驗餘淨重0.0530公克），為本案查獲之第一級毒品，應依毒品危害防制條例第18條第1項前段規定宣告沒收銷燬。三、依刑事訴訟法第449條第1項前段、第3項、第454條第2項、第450條第1項，毒品危害防制條例第11條第1項、第18條第1項前段，刑法第11條、第41條第1項前段，逕以簡易判決處刑如主文。四、如不服本判決，得自收受送達之日起十日內向本院提出上訴狀，上訴於本院第二審合議庭（須附繕本）。中華民國100年12月2日刑事第二十三庭法官詹蕙嘉上列正本證明與原本無異。書記官陳語嫣中華民國100年12月6日附錄本案論罪科刑法條全文：毒品危害防制條例第11條持有第一級毒品者，處3年以下有期徒刑、拘役或新臺幣5萬元以下罰金。持有第二級毒品者，處2年以下有期徒刑、拘役或新臺幣3萬元以下罰金。持有第一級毒品純質淨重十公克以上者，處1年以上7年以下有期徒刑，得併科新臺幣1百萬元以下罰金。持有第二級毒品純質淨重二十公克以上者，處6月以上5年以下有期徒刑，得併科新臺幣70萬元以下罰金。持有第三級毒品純質淨重二十公克以上者，處3年以下有期徒刑，得併科新臺幣30萬元以下罰金。持有第四級毒品純質淨重二十公克以上者，處1年以下有期徒刑，得併科新臺幣10萬元以下罰金。持有專供製造或施用第一級、第二級毒品之器具者，處1年以下有期徒刑、拘役或新臺幣1萬元以下罰金。附件：臺灣板橋地方法院檢察署檢察官聲請簡易判決處刑書100年度偵字第21857號被告蔡淑惠女31歲（民國○○年○月○○日生）住新北市○○區○○路172號2樓國民身分證統一編號：Ｚ000000000號上列被告因違反毒品危害防制條例案件，業經偵查終結，認為宜以簡易判決處刑，茲將犯罪事實及證據並所犯法條分敘如下：犯罪事實一、蔡淑惠明知海洛因係毒品危害防制條例所列管之第一級毒品，不得非法持有，竟基於持有第一級毒品海洛因之犯意，於民國100年8月2日中午12時許，自真實姓名年籍不詳之成年人取得海洛因1包而持有之。嗣於100年8月11日上午9時40分許，在新北市○○區○○路174號前，因行蹤可疑，為警當場查獲其身上持有海洛因1包（毛重0.2940公克、驗後餘重0.0530公克），始查悉上情。二、案經新北市政府警察局蘆洲分局移送偵辦。證據並所犯法條一、上揭犯罪事實，業據被告蔡淑惠於警詢及偵查中坦承不諱，，並有第一級毒品海洛因1包扣案可資佐證；又扣案毒品含有第一級毒品海洛因成分，有交通部民用航空局航空醫務中心毒品鑑定書附卷可佐，被告之自白核與事實相符，其犯行洵足認定。二、核被告所為，係犯毒品危害防制條例第11條第1項之持有第一級毒品海洛因罪嫌。至扣案之第一級毒品海洛因1包（毛重0.2940公克、驗後餘重0.0530公克），請依同條例第18條第1項前段規定宣告沒收並銷燬之。三、依刑事訴訟法第451條第1項聲請逕以簡易判決處刑。此致臺灣板橋地方法院中華民國100年10月31日檢察官姜麗君本件正本證明與原本無異中華民國100年11月4日書記官附錄本案所犯法條全文毒品危害防制條例第11條持有第一級毒品者，處3年以下有期徒刑、拘役或新臺幣5萬元以下罰金。持有第二級毒品者，處2年以下有期徒刑、拘役或新臺幣3萬元以下罰金。持有專供製造或施用第一、二級毒品之器具者，處1年以下有期徒刑、拘役或新臺幣1萬元以下罰金。持有毒品達一定數量者，加重其刑至二分之一，其標準由行政院定之。本件係依刑事訴訟法簡易程序辦理，法院簡易庭得不傳喚被告、輔佐人、告訴人、告發人等出庭即以簡易判決處刑；被告、被害人、告訴人等對於告訴乃論案件如已達成民事和解而要撤回告訴或對非告訴乃論案件認有受傳喚到庭陳述意見之必要時，請即另以書狀向簡易法庭陳述或請求傳訊。",
  "characters": {
    "judges": [
      "詹蕙嘉"
    ],
    "prosecutors": [

    ],
    "lawyers": [

    ],
    "clerks": [
      "陳語嫣"
    ],
    "plaintiffs": [

    ],
    "defendants": [
      "蔡淑惠",
      "蔡淑惠  女  31歲（民國○○年○月○○日生）"
    ],
    "prosecutor_office": [
      "臺灣板橋地方法院檢察署檢察官"
    ],
    "creditors": [

    ],
    "debtors": [

    ],
    "judicial_associate_officer": [

    ]
  },
  "adjudged_at": "2011-12-02",
  "created_at": "2016-02-13 12:28:27",
  "updated_at": "2016-02-13 12:28:27"
}