{
  "identify": "KSD-100-審訴-1137-20110630-1",
  "court": {
    "name": "臺灣高雄地方法院",
    "code": "KSD"
  },
  "division": {
    "name": "刑事",
    "code": "M"
  },
  "year": 100,
  "word": "審訴",
  "number": "1137",
  "jcheck": "1",
  "reason": "偽證",
  "content": "臺灣高雄地方法院刑事判決           100年度審訴字第1137號\n公  訴  人  臺灣高雄地方法院檢察署檢察官\n被      告  穆春佑\n上列被告因偽證案件，經檢察官提起公訴（100年度偵字第5651\n號），嗣本院訊問被告後，因被告就其被訴事實為有罪之陳述，\n經詢問被告及檢察官之意見後，合議庭裁定由受命法官依簡式審\n判程序獨任審理，並判決如下：\n    主  文\n穆春佑犯偽證罪，處有期徒刑肆月。\n    事實及理由\n一、本件被告穆春佑所犯為死刑、無期徒刑、最輕本刑為3年以\n    上有期徒刑以外之罪，其於審判程序中就被訴事實為有罪之\n    陳述，經本院告知簡式審判程序之旨，並聽取當事人意見後\n    ，認宜進行簡式審判程序，爰依刑事訴訟法第273條之1第1\n    項規定，裁定進行簡式審判程序，合先敘明。又簡式審判程\n    序之證據調查，依刑事訴訟法第273條之2規定，不受同法第\n    159條第1項審判外陳述排除之限制，再被告對於卷內之各項\n    證據亦不爭執證據能力（本院卷第42頁背面、第43頁），故\n    卷內所列之各項證據，自得作為證據，先予敘明。\n二、本件犯罪事實及證據，除證據部分補充「被告於本院審理中\n    之自白」外，餘均引用附件檢察官起訴書所載。\n三、按刑法第168 條規定證人依法作證時，必須對於案情有重要\n    關係之事項，為虛偽之陳述，始負偽證罪責，所謂與案情有\n    重要關係之事項，係指該事項之有無，足以影響於裁判之結\n    果者而言，必證人就此種事項為虛偽之陳述，有使裁判陷於\n    錯誤之危險，始科以偽證刑責，最高法院71年度台上字第53\n    號著有判例。而在上開本院99年度訴字第580 、581 號鄭秋\n    香妨害風化案件中（業於99年9 月23日判決確定），被告是\n    否為「榮泰旅社」實際負責人之事實，自屬對於案情有重要\n    關係之事項，被告就此種事項為虛偽之陳述，自有使裁判陷\n    於錯誤之危險，故核其所為，係犯刑法第168 條之偽證罪。\n    又本件被告雖於100 年6 月10日本院審理中自白犯行，惟查\n    本院99年訴字581 號妨害風化罪乙案業於99年9 月21日判決\n    確定．並已於100 年4 月12日執行完畢在案，有鄭秋香之臺\n    灣高等法院被告前案紀錄表1 份在卷可參，故本案無刑法第\n    172 條減輕或免除其刑規定之適用，併予說明。爰審酌被告\n    人在本院上開案件審理時，於具結後就案情有重要關係之事\n    項，為虛偽之陳述，企圖誤導法院審判之正確性，惡性非輕\n    ，然念其犯後終能查坦承犯行，態度尚稱良好等一切情狀，\n    酌情量處如主文所示之刑，以示儆懲。又本院審酌上情，認\n    被告以量處如主文所示之刑，已足以達罰當其罪之目的，並\n    令被告心生警惕之效果，檢察官求處有期徒刑5 月等語，尚\n    嫌過重，併此敘明。\n據上論斷，應依刑事訴訟法第273條之1第1項、第299條第1項前\n段、第310條之2、第454條第2項，刑法第168條，判決如主文。\n本案經檢察官王清海到庭執行職務。\n中    華    民    國    100     年    6   月    30    日\n                  刑事第十庭   法  官  張  震\n以上正本證明與原本無異。\n如不服本判決應於收受判決後10日內向本院提出上訴書狀，並應\n敘述具體理由。其未敘述上訴理由者，應於上訴期間屆滿後20日\n內向本院補提理由書(均須按他造當事人之人數附繕本)「切勿逕\n送上級法院」。\n中    華    民    國    100     年    6   月    30    日\n                               書記官  邱家銘\n附錄本判決論罪科刑之法條：\n中華民國刑法第168條\n於執行審判職務之公署審判時或於檢查官偵查時，證人、鑑定人\n、通譯於案情有重要關係之事項，供前或供後具結，而為虛偽陳\n述者，處七年以下有期徒刑。\n附件：\n臺灣高雄地方法院檢察署檢察官起訴書\n                                     100年度偵字第5651號\n    被      告  穆春佑  男  27歲（民國○○年○月○○日生）\n                        籍設高雄市○○區○○街64號\n                        現住高雄市○○區○○路9巷32號10\n                        樓\n                        國民身分證統一編號：Ｚ000000000號\n上列被告因偽證案件，業經偵查終結，認應該提起公訴，茲將犯\n罪事實及證據並所犯法條分敘如下：\n        犯罪事實\n一、穆春佑受雇於鄭秋香，在鄭秋擔任實際負責人之「榮泰旅社\n    」（址設高雄市○○區○○路1段125號）擔任現場櫃檯管理\n    人員。鄭秋香與穆春佑共同基於意圖使女子與他人為性交行\n    為，而容留以營利之犯意聯絡，於民國98年3月16日容留鄭\n    秋香所僱用之女服務生黃日艷在上址3樓房間內，為男客蔡\n    勝吉進行俗稱「全套」之性交易，嗣於同日下午10時許，黃\n    日艷與蔡勝吉在上址3樓房間內甫沐浴完畢，正準備為性交\n    行為時，為警當場查獲，並扣得計時器4個、保險套6個，而\n    循線查悉上情。穆春佑明知鄭秋香係「榮泰旅社」之實際負\n    責人，為脫免鄭秋香所涉之妨害風化罪責，竟於99年7月29\n    日上午10時20分許，在臺灣高雄地方法院以99年度訴字第58\n    0號審理鄭秋香涉嫌妨害風化案件中，以證人身分應訊時，\n    竟基於偽證之故意，就審判長訊問鄭秋香是否為「榮泰旅社\n    」之實際負責人之案情有重要關係事項，供前具結為不實之\n    證言證稱：老闆娘不是鄭秋香，是另一個阿姨，鄭秋香沒什\n    麼在那邊出現過，…伊只知道鄭秋香是「榮泰旅社」名義負\n    責人，除此之外，鄭秋香跟「榮泰旅社」沒有關聯，…伊不\n    知道鄭秋香在榮泰旅社做什麼事情云云，而為虛偽陳述。\n二、案經臺灣高雄地方法院函送本署偵辦。\n        證據並所犯法條\n一、證據清單及待證事實\n┌──┬─────────────┬─────────────┐\n│編號│ 證據方法                 │待證事實                  │\n├──┼─────────────┼─────────────┤\n│1   │臺灣高雄地方法院99年度訴字│被告穆春佑於該案件審理時，│\n│    │第580號案件，99年7月29日之│以證人身分應訊，供前具結為│\n│    │審判筆錄影本1份           │不實之證述。              │\n├──┼─────────────┼─────────────┤\n│2   │另案被告鄭秋香於警詢、本署│鄭秋香於該案審理中時坦承係│\n│    │98年度偵字第9042號偵查中、│「榮泰旅社」之實際負責人。│\n│    │臺灣高雄地方法院99年度訴字│                          │\n│    │第580號案件審理中之供述。 │                          │\n├──┼─────────────┼─────────────┤\n│3   │被告穆春佑於臺灣高雄地方法│被告穆春佑為法律上具結行為│\n│    │院99年度訴字第580 號案件審│。                        │\n│    │理時所簽具書立之證人結文1 │                          │\n│    │紙。                      │                          │\n├──┼─────────────┼─────────────┤\n│4   │臺灣高雄地方法院99年度訴字│被告穆春佑經具結後，證述如│\n│    │第580號判決書1份。        │犯罪事實所載與案情有重大關│\n│    │                          │係之虛偽陳述情事。        │\n└──┴─────────────┴─────────────┘\n二、核被告穆春佑所為，係犯刑法第168條之偽證罪。\n三、依刑事訴訟法第251條第1項提起公訴。\n    此  致\n臺灣高雄地方法院\n中    華    民    國   100    年    3     月    25    日\n                              檢察官  黃雯麗\n上正本證明與原本無異\n中    華    民    國   100    年    4     月    11    日\n                              書記官  李元正\n所犯法條：\n中華民國刑法第168條\n（偽證罪）\n於執行審判職務之公署審判時或於檢察官偵查時，證人、鑑定人\n、通譯於案情有重要關係之事項，供前或供後具結，而為虛偽陳\n述者，處7年以下有期徒刑。",
  "structure": {
    "main": "穆春佑犯偽證罪，處有期徒刑肆月。",
    "fact": "一、本件被告穆春佑所犯為死刑、無期徒刑、最輕本刑為3年以\n    上有期徒刑以外之罪，其於審判程序中就被訴事實為有罪之\n    陳述，經本院告知簡式審判程序之旨，並聽取當事人意見後\n    ，認宜進行簡式審判程序，爰依刑事訴訟法第273條之1第1\n    項規定，裁定進行簡式審判程序，合先敘明。又簡式審判程\n    序之證據調查，依刑事訴訟法第273條之2規定，不受同法第\n    159條第1項審判外陳述排除之限制，再被告對於卷內之各項\n    證據亦不爭執證據能力（本院卷第42頁背面、第43頁），故\n    卷內所列之各項證據，自得作為證據，先予敘明。\n二、本件犯罪事實及證據，除證據部分補充「被告於本院審理中\n    之自白」外，餘均引用附件檢察官起訴書所載。\n三、按刑法第168 條規定證人依法作證時，必須對於案情有重要\n    關係之事項，為虛偽之陳述，始負偽證罪責，所謂與案情有\n    重要關係之事項，係指該事項之有無，足以影響於裁判之結\n    果者而言，必證人就此種事項為虛偽之陳述，有使裁判陷於\n    錯誤之危險，始科以偽證刑責，最高法院71年度台上字第53\n    號著有判例。而在上開本院99年度訴字第580 、581 號鄭秋\n    香妨害風化案件中（業於99年9 月23日判決確定），被告是\n    否為「榮泰旅社」實際負責人之事實，自屬對於案情有重要\n    關係之事項，被告就此種事項為虛偽之陳述，自有使裁判陷\n    於錯誤之危險，故核其所為，係犯刑法第168 條之偽證罪。\n    又本件被告雖於100 年6 月10日本院審理中自白犯行，惟查\n    本院99年訴字581 號妨害風化罪乙案業於99年9 月21日判決\n    確定．並已於100 年4 月12日執行完畢在案，有鄭秋香之臺\n    灣高等法院被告前案紀錄表1 份在卷可參，故本案無刑法第\n    172 條減輕或免除其刑規定之適用，併予說明。爰審酌被告\n    人在本院上開案件審理時，於具結後就案情有重要關係之事\n    項，為虛偽之陳述，企圖誤導法院審判之正確性，惡性非輕\n    ，然念其犯後終能查坦承犯行，態度尚稱良好等一切情狀，\n    酌情量處如主文所示之刑，以示儆懲。又本院審酌上情，認\n    被告以量處如主文所示之刑，已足以達罰當其罪之目的，並\n    令被告心生警惕之效果，檢察官求處有期徒刑5 月等語，尚\n    嫌過重，併此敘明。\n據上論斷，應依刑事訴訟法第273條之1第1項、第299條第1項前\n段、第310條之2、第454條第2項，刑法第168條，判決如主文。\n本案經檢察官王清海到庭執行職務。",
    "reason": "一、本件被告穆春佑所犯為死刑、無期徒刑、最輕本刑為3年以\n    上有期徒刑以外之罪，其於審判程序中就被訴事實為有罪之\n    陳述，經本院告知簡式審判程序之旨，並聽取當事人意見後\n    ，認宜進行簡式審判程序，爰依刑事訴訟法第273條之1第1\n    項規定，裁定進行簡式審判程序，合先敘明。又簡式審判程\n    序之證據調查，依刑事訴訟法第273條之2規定，不受同法第\n    159條第1項審判外陳述排除之限制，再被告對於卷內之各項\n    證據亦不爭執證據能力（本院卷第42頁背面、第43頁），故\n    卷內所列之各項證據，自得作為證據，先予敘明。\n二、本件犯罪事實及證據，除證據部分補充「被告於本院審理中\n    之自白」外，餘均引用附件檢察官起訴書所載。\n三、按刑法第168 條規定證人依法作證時，必須對於案情有重要\n    關係之事項，為虛偽之陳述，始負偽證罪責，所謂與案情有\n    重要關係之事項，係指該事項之有無，足以影響於裁判之結\n    果者而言，必證人就此種事項為虛偽之陳述，有使裁判陷於\n    錯誤之危險，始科以偽證刑責，最高法院71年度台上字第53\n    號著有判例。而在上開本院99年度訴字第580 、581 號鄭秋\n    香妨害風化案件中（業於99年9 月23日判決確定），被告是\n    否為「榮泰旅社」實際負責人之事實，自屬對於案情有重要\n    關係之事項，被告就此種事項為虛偽之陳述，自有使裁判陷\n    於錯誤之危險，故核其所為，係犯刑法第168 條之偽證罪。\n    又本件被告雖於100 年6 月10日本院審理中自白犯行，惟查\n    本院99年訴字581 號妨害風化罪乙案業於99年9 月21日判決\n    確定．並已於100 年4 月12日執行完畢在案，有鄭秋香之臺\n    灣高等法院被告前案紀錄表1 份在卷可參，故本案無刑法第\n    172 條減輕或免除其刑規定之適用，併予說明。爰審酌被告\n    人在本院上開案件審理時，於具結後就案情有重要關係之事\n    項，為虛偽之陳述，企圖誤導法院審判之正確性，惡性非輕\n    ，然念其犯後終能查坦承犯行，態度尚稱良好等一切情狀，\n    酌情量處如主文所示之刑，以示儆懲。又本院審酌上情，認\n    被告以量處如主文所示之刑，已足以達罰當其罪之目的，並\n    令被告心生警惕之效果，檢察官求處有期徒刑5 月等語，尚\n    嫌過重，併此敘明。\n據上論斷，應依刑事訴訟法第273條之1第1項、第299條第1項前\n段、第310條之2、第454條第2項，刑法第168條，判決如主文。\n本案經檢察官王清海到庭執行職務。"
  },
  "search": "臺灣高雄地方法院刑事判決100年度審訴字第1137號公訴人臺灣高雄地方法院檢察署檢察官被告穆春佑上列被告因偽證案件，經檢察官提起公訴（100年度偵字第5651號），嗣本院訊問被告後，因被告就其被訴事實為有罪之陳述，經詢問被告及檢察官之意見後，合議庭裁定由受命法官依簡式審判程序獨任審理，並判決如下：主文穆春佑犯偽證罪，處有期徒刑肆月。事實及理由一、本件被告穆春佑所犯為死刑、無期徒刑、最輕本刑為3年以上有期徒刑以外之罪，其於審判程序中就被訴事實為有罪之陳述，經本院告知簡式審判程序之旨，並聽取當事人意見後，認宜進行簡式審判程序，爰依刑事訴訟法第273條之1第1項規定，裁定進行簡式審判程序，合先敘明。又簡式審判程序之證據調查，依刑事訴訟法第273條之2規定，不受同法第159條第1項審判外陳述排除之限制，再被告對於卷內之各項證據亦不爭執證據能力（本院卷第42頁背面、第43頁），故卷內所列之各項證據，自得作為證據，先予敘明。二、本件犯罪事實及證據，除證據部分補充「被告於本院審理中之自白」外，餘均引用附件檢察官起訴書所載。三、按刑法第168條規定證人依法作證時，必須對於案情有重要關係之事項，為虛偽之陳述，始負偽證罪責，所謂與案情有重要關係之事項，係指該事項之有無，足以影響於裁判之結果者而言，必證人就此種事項為虛偽之陳述，有使裁判陷於錯誤之危險，始科以偽證刑責，最高法院71年度台上字第53號著有判例。而在上開本院99年度訴字第580、581號鄭秋香妨害風化案件中（業於99年9月23日判決確定），被告是否為「榮泰旅社」實際負責人之事實，自屬對於案情有重要關係之事項，被告就此種事項為虛偽之陳述，自有使裁判陷於錯誤之危險，故核其所為，係犯刑法第168條之偽證罪。又本件被告雖於100年6月10日本院審理中自白犯行，惟查本院99年訴字581號妨害風化罪乙案業於99年9月21日判決確定．並已於100年4月12日執行完畢在案，有鄭秋香之臺灣高等法院被告前案紀錄表1份在卷可參，故本案無刑法第172條減輕或免除其刑規定之適用，併予說明。爰審酌被告人在本院上開案件審理時，於具結後就案情有重要關係之事項，為虛偽之陳述，企圖誤導法院審判之正確性，惡性非輕，然念其犯後終能查坦承犯行，態度尚稱良好等一切情狀，酌情量處如主文所示之刑，以示儆懲。又本院審酌上情，認被告以量處如主文所示之刑，已足以達罰當其罪之目的，並令被告心生警惕之效果，檢察官求處有期徒刑5月等語，尚嫌過重，併此敘明。據上論斷，應依刑事訴訟法第273條之1第1項、第299條第1項前段、第310條之2、第454條第2項，刑法第168條，判決如主文。本案經檢察官王清海到庭執行職務。中華民國100年6月30日刑事第十庭法官張震以上正本證明與原本無異。如不服本判決應於收受判決後10日內向本院提出上訴書狀，並應敘述具體理由。其未敘述上訴理由者，應於上訴期間屆滿後20日內向本院補提理由書(均須按他造當事人之人數附繕本)「切勿逕送上級法院」。中華民國100年6月30日書記官邱家銘附錄本判決論罪科刑之法條：中華民國刑法第168條於執行審判職務之公署審判時或於檢查官偵查時，證人、鑑定人、通譯於案情有重要關係之事項，供前或供後具結，而為虛偽陳述者，處七年以下有期徒刑。附件：臺灣高雄地方法院檢察署檢察官起訴書100年度偵字第5651號被告穆春佑男27歲（民國○○年○月○○日生）籍設高雄市○○區○○街64號現住高雄市○○區○○路9巷32號10樓國民身分證統一編號：Ｚ000000000號上列被告因偽證案件，業經偵查終結，認應該提起公訴，茲將犯罪事實及證據並所犯法條分敘如下：犯罪事實一、穆春佑受雇於鄭秋香，在鄭秋擔任實際負責人之「榮泰旅社」（址設高雄市○○區○○路1段125號）擔任現場櫃檯管理人員。鄭秋香與穆春佑共同基於意圖使女子與他人為性交行為，而容留以營利之犯意聯絡，於民國98年3月16日容留鄭秋香所僱用之女服務生黃日艷在上址3樓房間內，為男客蔡勝吉進行俗稱「全套」之性交易，嗣於同日下午10時許，黃日艷與蔡勝吉在上址3樓房間內甫沐浴完畢，正準備為性交行為時，為警當場查獲，並扣得計時器4個、保險套6個，而循線查悉上情。穆春佑明知鄭秋香係「榮泰旅社」之實際負責人，為脫免鄭秋香所涉之妨害風化罪責，竟於99年7月29日上午10時20分許，在臺灣高雄地方法院以99年度訴字第580號審理鄭秋香涉嫌妨害風化案件中，以證人身分應訊時，竟基於偽證之故意，就審判長訊問鄭秋香是否為「榮泰旅社」之實際負責人之案情有重要關係事項，供前具結為不實之證言證稱：老闆娘不是鄭秋香，是另一個阿姨，鄭秋香沒什麼在那邊出現過，…伊只知道鄭秋香是「榮泰旅社」名義負責人，除此之外，鄭秋香跟「榮泰旅社」沒有關聯，…伊不知道鄭秋香在榮泰旅社做什麼事情云云，而為虛偽陳述。二、案經臺灣高雄地方法院函送本署偵辦。證據並所犯法條一、證據清單及待證事實┌──┬─────────────┬─────────────┐│編號│證據方法│待證事實│├──┼─────────────┼─────────────┤│1│臺灣高雄地方法院99年度訴字│被告穆春佑於該案件審理時，│││第580號案件，99年7月29日之│以證人身分應訊，供前具結為│││審判筆錄影本1份│不實之證述。│├──┼─────────────┼─────────────┤│2│另案被告鄭秋香於警詢、本署│鄭秋香於該案審理中時坦承係│││98年度偵字第9042號偵查中、│「榮泰旅社」之實際負責人。│││臺灣高雄地方法院99年度訴字││││第580號案件審理中之供述。││├──┼─────────────┼─────────────┤│3│被告穆春佑於臺灣高雄地方法│被告穆春佑為法律上具結行為│││院99年度訴字第580號案件審│。│││理時所簽具書立之證人結文1││││紙。││├──┼─────────────┼─────────────┤│4│臺灣高雄地方法院99年度訴字│被告穆春佑經具結後，證述如│││第580號判決書1份。│犯罪事實所載與案情有重大關││││係之虛偽陳述情事。│└──┴─────────────┴─────────────┘二、核被告穆春佑所為，係犯刑法第168條之偽證罪。三、依刑事訴訟法第251條第1項提起公訴。此致臺灣高雄地方法院中華民國100年3月25日檢察官黃雯麗上正本證明與原本無異中華民國100年4月11日書記官李元正所犯法條：中華民國刑法第168條（偽證罪）於執行審判職務之公署審判時或於檢察官偵查時，證人、鑑定人、通譯於案情有重要關係之事項，供前或供後具結，而為虛偽陳述者，處7年以下有期徒刑。",
  "characters": {
    "judges": [
      "張震"
    ],
    "prosecutors": [
      "王清海"
    ],
    "lawyers": [

    ],
    "clerks": [
      "邱家銘",
      "李元正"
    ],
    "plaintiffs": [

    ],
    "defendants": [
      "穆春佑",
      "穆春佑  男  27歲（民國○○年○月○○日生）"
    ],
    "prosecutor_office": [
      "臺灣高雄地方法院檢察署檢察官"
    ],
    "creditors": [

    ],
    "debtors": [

    ],
    "judicial_associate_officer": [

    ]
  },
  "adjudged_at": "2011-06-30",
  "created_at": "2016-02-13 18:42:08",
  "updated_at": "2016-02-13 18:42:08"
}