{
  "identify": "PCD-100-交訴-127-20110630-1",
  "court": {
    "name": "臺灣新北地方法院",
    "code": "PCD"
  },
  "division": {
    "name": "刑事",
    "code": "M"
  },
  "year": 100,
  "word": "交訴",
  "number": "127",
  "jcheck": "1",
  "reason": "公共危險",
  "content": "臺灣板橋地方法院刑事判決            100年度交訴字第127號\n公  訴  人  臺灣板橋地方法院檢察署檢察官\n被      告  陳宥廷\n上列被告因公共危險案件，經檢察官提起公訴（100 年度偵字第\n9797號），本院合議庭裁定依簡式審判程序，判決如下：\n    主  文\n陳宥廷犯肇事致人傷害逃逸罪，處有期徒刑陸月，如易科罰金，\n以新臺幣壹仟元折算壹日。緩刑貳年。\n    事  實\n一、陳宥廷於民國100 年3 月9 日11時40分許前之某時許，駕駛\n    友人蔡秀錢所有車牌號碼CZ-0635 號自用小客車沿土城往新\n    莊方向行駛，行經新北市○○區○○路上時，原應注意駕駛\n    人駕駛汽車應注意車前狀況及兩車併行之間隔，並隨時採取\n    必要之安全措施，而依當時情形天氣晴、日間自然光線、柏\n    油路面乾燥、無缺陷、無障礙物、視距良好，並無不能注意\n    之情事，竟疏未注意及此，因前方車輛緊急煞車而緊急往右\n    行駛，嗣謝瑩蓉騎乘車牌號碼CUF-296 號重型機車行駛於陳\n    宥廷所駕駛車輛右側（起訴書誤載為左側）時，因陳宥廷貿\n    然右轉而謝瑩蓉見狀閃避不及因而發生碰撞，致謝瑩蓉受有\n    左上臂挫傷、左大腿挫傷、左背挫傷等傷害（過失傷害部分\n    ，未據告訴）。詎陳宥廷肇事後停車察看，見謝瑩蓉受傷，\n    仍未予以處理或停留現場等候警方處理，便逕行駕駛上開車\n    輛逃逸，嗣因謝瑩蓉記下車號報警，始為警循線查獲上情。\n二、案經新北市政府警察局海山分局移送臺灣板橋地方法院檢察\n    署檢察官偵查起訴。\n    理  由\n一、程序方面：\n    本件被告陳宥廷所犯係死刑、無期徒刑、最輕本刑為3 年以\n    上有期徒刑以外之罪，其於本院準備程序中就被訴事實為有\n    罪之陳述，經告知簡式審判程序之旨，並聽取公訴人、被告\n    之意見後，合議庭裁定由受命法官獨任進行簡式審判程序。\n二、實體部分：\n１、上開事實，業據被告於本院審理中自白在案，核與證人蔡秀\n    錢於警詢時、證人即被害人謝瑩蓉於警詢及偵查之證述情節\n    相符，並有道路交通事故現場圖、道路交通事故調查報告表\n    （一）（二），及被害人謝瑩蓉之診斷證明書1 紙在卷可稽\n    。足見被告之自白核與事實相符，堪信為真實。綜上，本案\n    事證明確，被告犯行堪予認定，應予依法論科。\n２、核被告所為，係犯刑法第185 條之4 之駕駛動力交通工具肇\n    事，致人受傷而逃逸罪。爰審酌被告駕車發生事故，卻未對\n    受傷之被害人予以救助而逕行逃逸，致增加被害人無法獲得\n    即時救治，所受傷勢可能轉趨嚴重之風險；惟念及被告業於\n    本院審理中皆坦承犯行，且已與被害人謝瑩蓉達成和解，犯\n    後態度良好；又被害人於本院審理中亦表明不再訴究被告過\n    失傷害刑責，並就本件肇事逃逸部分同意給予緩刑等一切情\n    狀，爰量處如主文所示之刑。另考量被告自承有二位小孩就\n    讀大學，尚待扶養，經濟狀況勉持等情（見本院審判筆錄）\n    ，並諭知以新臺幣1 千元折算1 日之易科罰金折算標準，以\n    示懲儆。又查被告前因故意犯罪受有期徒刑以上刑之宣告，\n    執行完畢或赦免後，五年以內未曾因故意犯罪受有期徒刑以\n    上刑之宣告，有臺灣高等法院被告前案紀錄表在卷可憑，茲\n    念其一時失慮，再犯本案，經此偵查及科刑程序，應知警惕\n    ，信無再犯之虞，本院因認前開所宣告之刑以暫不執行為適\n    當，併予諭知緩刑貳年，以啟自新。\n三、據上論斷，應依刑事訴訟法第284 條之1 、第273 條之1 第\n    1 項、第299 條第1 項前段，刑法第185 條之4 、第41條第\n    1 項前段、第74條第1 項第2 款，刑法施行法第1 條之1 ，\n    判決如主文。\n本案經檢察官張瑞玲到庭執行職務。\n中    華    民    國   100    年    6     月    30    日\n                  交通法庭  法  官  蘇揚旭\n上列正本證明與原本無異。\n如不服本判決，應於判決送達後10日內敘明上訴理由，向本院提\n出上訴狀 (應附繕本) ，上訴於臺灣高等法院。其未敘述上訴理\n由者，應於上訴期間屆滿後20日內向本院補提理由書「切勿逕送\n上級法院」。\n                            書記官  李郁禎\n中    華    民    國   100    年    6     月    30    日\n附錄論罪科刑法條\n刑法第185條之4\n駕駛動力交通工具肇事，致人死傷而逃逸者，處 6 月以上 5 年\n以下有期徒刑。",
  "structure": {
    "main": "陳宥廷犯肇事致人傷害逃逸罪，處有期徒刑陸月，如易科罰金，\n以新臺幣壹仟元折算壹日。緩刑貳年。",
    "fact": "一、陳宥廷於民國100 年3 月9 日11時40分許前之某時許，駕駛\n    友人蔡秀錢所有車牌號碼CZ-0635 號自用小客車沿土城往新\n    莊方向行駛，行經新北市○○區○○路上時，原應注意駕駛\n    人駕駛汽車應注意車前狀況及兩車併行之間隔，並隨時採取\n    必要之安全措施，而依當時情形天氣晴、日間自然光線、柏\n    油路面乾燥、無缺陷、無障礙物、視距良好，並無不能注意\n    之情事，竟疏未注意及此，因前方車輛緊急煞車而緊急往右\n    行駛，嗣謝瑩蓉騎乘車牌號碼CUF-296 號重型機車行駛於陳\n    宥廷所駕駛車輛右側（起訴書誤載為左側）時，因陳宥廷貿\n    然右轉而謝瑩蓉見狀閃避不及因而發生碰撞，致謝瑩蓉受有\n    左上臂挫傷、左大腿挫傷、左背挫傷等傷害（過失傷害部分\n    ，未據告訴）。詎陳宥廷肇事後停車察看，見謝瑩蓉受傷，\n    仍未予以處理或停留現場等候警方處理，便逕行駕駛上開車\n    輛逃逸，嗣因謝瑩蓉記下車號報警，始為警循線查獲上情。\n二、案經新北市政府警察局海山分局移送臺灣板橋地方法院檢察\n    署檢察官偵查起訴。",
    "reason": "一、程序方面：\n    本件被告陳宥廷所犯係死刑、無期徒刑、最輕本刑為3 年以\n    上有期徒刑以外之罪，其於本院準備程序中就被訴事實為有\n    罪之陳述，經告知簡式審判程序之旨，並聽取公訴人、被告\n    之意見後，合議庭裁定由受命法官獨任進行簡式審判程序。\n二、實體部分：\n１、上開事實，業據被告於本院審理中自白在案，核與證人蔡秀\n    錢於警詢時、證人即被害人謝瑩蓉於警詢及偵查之證述情節\n    相符，並有道路交通事故現場圖、道路交通事故調查報告表\n    （一）（二），及被害人謝瑩蓉之診斷證明書1 紙在卷可稽\n    。足見被告之自白核與事實相符，堪信為真實。綜上，本案\n    事證明確，被告犯行堪予認定，應予依法論科。\n２、核被告所為，係犯刑法第185 條之4 之駕駛動力交通工具肇\n    事，致人受傷而逃逸罪。爰審酌被告駕車發生事故，卻未對\n    受傷之被害人予以救助而逕行逃逸，致增加被害人無法獲得\n    即時救治，所受傷勢可能轉趨嚴重之風險；惟念及被告業於\n    本院審理中皆坦承犯行，且已與被害人謝瑩蓉達成和解，犯\n    後態度良好；又被害人於本院審理中亦表明不再訴究被告過\n    失傷害刑責，並就本件肇事逃逸部分同意給予緩刑等一切情\n    狀，爰量處如主文所示之刑。另考量被告自承有二位小孩就\n    讀大學，尚待扶養，經濟狀況勉持等情（見本院審判筆錄）\n    ，並諭知以新臺幣1 千元折算1 日之易科罰金折算標準，以\n    示懲儆。又查被告前因故意犯罪受有期徒刑以上刑之宣告，\n    執行完畢或赦免後，五年以內未曾因故意犯罪受有期徒刑以\n    上刑之宣告，有臺灣高等法院被告前案紀錄表在卷可憑，茲\n    念其一時失慮，再犯本案，經此偵查及科刑程序，應知警惕\n    ，信無再犯之虞，本院因認前開所宣告之刑以暫不執行為適\n    當，併予諭知緩刑貳年，以啟自新。\n三、據上論斷，應依刑事訴訟法第284 條之1 、第273 條之1 第\n    1 項、第299 條第1 項前段，刑法第185 條之4 、第41條第\n    1 項前段、第74條第1 項第2 款，刑法施行法第1 條之1 ，\n    判決如主文。\n本案經檢察官張瑞玲到庭執行職務。\n中    華    民    國   100    年    6     月    30    日\n                  交通法庭  法  官  蘇揚旭\n上列正本證明與原本無異。\n如不服本判決，應於判決送達後10日內敘明上訴理由，向本院提\n出上訴狀 (應附繕本) ，上訴於臺灣高等法院。其未敘述上訴理\n由者，應於上訴期間屆滿後20日內向本院補提理由書「切勿逕送\n上級法院」。\n                            書記官  李郁禎"
  },
  "search": "臺灣板橋地方法院刑事判決100年度交訴字第127號公訴人臺灣板橋地方法院檢察署檢察官被告陳宥廷上列被告因公共危險案件，經檢察官提起公訴（100年度偵字第9797號），本院合議庭裁定依簡式審判程序，判決如下：主文陳宥廷犯肇事致人傷害逃逸罪，處有期徒刑陸月，如易科罰金，以新臺幣壹仟元折算壹日。緩刑貳年。事實一、陳宥廷於民國100年3月9日11時40分許前之某時許，駕駛友人蔡秀錢所有車牌號碼CZ-0635號自用小客車沿土城往新莊方向行駛，行經新北市○○區○○路上時，原應注意駕駛人駕駛汽車應注意車前狀況及兩車併行之間隔，並隨時採取必要之安全措施，而依當時情形天氣晴、日間自然光線、柏油路面乾燥、無缺陷、無障礙物、視距良好，並無不能注意之情事，竟疏未注意及此，因前方車輛緊急煞車而緊急往右行駛，嗣謝瑩蓉騎乘車牌號碼CUF-296號重型機車行駛於陳宥廷所駕駛車輛右側（起訴書誤載為左側）時，因陳宥廷貿然右轉而謝瑩蓉見狀閃避不及因而發生碰撞，致謝瑩蓉受有左上臂挫傷、左大腿挫傷、左背挫傷等傷害（過失傷害部分，未據告訴）。詎陳宥廷肇事後停車察看，見謝瑩蓉受傷，仍未予以處理或停留現場等候警方處理，便逕行駕駛上開車輛逃逸，嗣因謝瑩蓉記下車號報警，始為警循線查獲上情。二、案經新北市政府警察局海山分局移送臺灣板橋地方法院檢察署檢察官偵查起訴。理由一、程序方面：本件被告陳宥廷所犯係死刑、無期徒刑、最輕本刑為3年以上有期徒刑以外之罪，其於本院準備程序中就被訴事實為有罪之陳述，經告知簡式審判程序之旨，並聽取公訴人、被告之意見後，合議庭裁定由受命法官獨任進行簡式審判程序。二、實體部分：１、上開事實，業據被告於本院審理中自白在案，核與證人蔡秀錢於警詢時、證人即被害人謝瑩蓉於警詢及偵查之證述情節相符，並有道路交通事故現場圖、道路交通事故調查報告表（一）（二），及被害人謝瑩蓉之診斷證明書1紙在卷可稽。足見被告之自白核與事實相符，堪信為真實。綜上，本案事證明確，被告犯行堪予認定，應予依法論科。２、核被告所為，係犯刑法第185條之4之駕駛動力交通工具肇事，致人受傷而逃逸罪。爰審酌被告駕車發生事故，卻未對受傷之被害人予以救助而逕行逃逸，致增加被害人無法獲得即時救治，所受傷勢可能轉趨嚴重之風險；惟念及被告業於本院審理中皆坦承犯行，且已與被害人謝瑩蓉達成和解，犯後態度良好；又被害人於本院審理中亦表明不再訴究被告過失傷害刑責，並就本件肇事逃逸部分同意給予緩刑等一切情狀，爰量處如主文所示之刑。另考量被告自承有二位小孩就讀大學，尚待扶養，經濟狀況勉持等情（見本院審判筆錄），並諭知以新臺幣1千元折算1日之易科罰金折算標準，以示懲儆。又查被告前因故意犯罪受有期徒刑以上刑之宣告，執行完畢或赦免後，五年以內未曾因故意犯罪受有期徒刑以上刑之宣告，有臺灣高等法院被告前案紀錄表在卷可憑，茲念其一時失慮，再犯本案，經此偵查及科刑程序，應知警惕，信無再犯之虞，本院因認前開所宣告之刑以暫不執行為適當，併予諭知緩刑貳年，以啟自新。三、據上論斷，應依刑事訴訟法第284條之1、第273條之1第1項、第299條第1項前段，刑法第185條之4、第41條第1項前段、第74條第1項第2款，刑法施行法第1條之1，判決如主文。本案經檢察官張瑞玲到庭執行職務。中華民國100年6月30日交通法庭法官蘇揚旭上列正本證明與原本無異。如不服本判決，應於判決送達後10日內敘明上訴理由，向本院提出上訴狀(應附繕本)，上訴於臺灣高等法院。其未敘述上訴理由者，應於上訴期間屆滿後20日內向本院補提理由書「切勿逕送上級法院」。書記官李郁禎中華民國100年6月30日附錄論罪科刑法條刑法第185條之4駕駛動力交通工具肇事，致人死傷而逃逸者，處6月以上5年以下有期徒刑。",
  "characters": {
    "judges": [
      "蘇揚旭"
    ],
    "prosecutors": [
      "張瑞玲"
    ],
    "lawyers": [

    ],
    "clerks": [
      "李郁禎"
    ],
    "plaintiffs": [

    ],
    "defendants": [
      "陳宥廷"
    ],
    "prosecutor_office": [
      "臺灣板橋地方法院檢察署檢察官"
    ],
    "creditors": [

    ],
    "debtors": [

    ],
    "judicial_associate_officer": [

    ]
  },
  "adjudged_at": "2011-06-30",
  "created_at": "2016-02-13 18:40:58",
  "updated_at": "2016-02-13 18:40:58"
}