{
  "identify": "SLD-100-審交易-58-20110630-1",
  "court": {
    "name": "臺灣士林地方法院",
    "code": "SLD"
  },
  "division": {
    "name": "刑事",
    "code": "M"
  },
  "year": 100,
  "word": "審交易",
  "number": "58",
  "jcheck": "1",
  "reason": "過失致死",
  "content": "臺灣士林地方法院刑事判決           100年度審交易字第58號\n    公  訴  人  臺灣士林地方法院檢察署檢察官\n    被      告  李文\n上列被告因過失致死案件，經檢察官提起公訴（99年度偵字第13\n243 號、100年度偵字第1266號），本院判決如下：\n    主  文\n本件公訴不受理。\n    理  由\n一、公訴意旨如起訴書所載（如附件）\n二、按被告死亡者，應諭知不受理之判決，並得不經言詞辯論為\n    之，刑事訴訟法第303 條第5 款、第307 條分別定有明文。\n三、查本件被告李文業於民國100 年4 月21日死亡，此有個人\n    基本資料查詢結果1 紙附卷可稽。依照上開說明，爰不經言\n    詞辯論，逕為不受理之判決。\n據上論斷，應依刑事訴訟法第303 條第5 款、第307 條判決如主\n文。\n中    華    民    國   100    年    6     月    30    日\n                  刑事第一庭法  官  李育仁\n以上正本與原本無異。\n如不服本判決應於收受送達後 10 日內向本院提出上訴書狀，並\n應敘述具體理由。其未敘述上訴理由者，應於上訴期間屆滿後\n20 日內向本院補提理由書 (均須按他造當事人之人數附繕本 )\n「切勿逕送上級法院」。\n                            書記官  張竣閔\n中    華    民    國   100    年    6     月    30    日",
  "structure": {
    "main": "本件公訴不受理。",
    "reason": "一、公訴意旨如起訴書所載（如附件）\n二、按被告死亡者，應諭知不受理之判決，並得不經言詞辯論為\n    之，刑事訴訟法第303 條第5 款、第307 條分別定有明文。\n三、查本件被告李文業於民國100 年4 月21日死亡，此有個人\n    基本資料查詢結果1 紙附卷可稽。依照上開說明，爰不經言\n    詞辯論，逕為不受理之判決。\n據上論斷，應依刑事訴訟法第303 條第5 款、第307 條判決如主\n文。"
  },
  "search": "臺灣士林地方法院刑事判決100年度審交易字第58號公訴人臺灣士林地方法院檢察署檢察官被告李文上列被告因過失致死案件，經檢察官提起公訴（99年度偵字第13243號、100年度偵字第1266號），本院判決如下：主文本件公訴不受理。理由一、公訴意旨如起訴書所載（如附件）二、按被告死亡者，應諭知不受理之判決，並得不經言詞辯論為之，刑事訴訟法第303條第5款、第307條分別定有明文。三、查本件被告李文業於民國100年4月21日死亡，此有個人基本資料查詢結果1紙附卷可稽。依照上開說明，爰不經言詞辯論，逕為不受理之判決。據上論斷，應依刑事訴訟法第303條第5款、第307條判決如主文。中華民國100年6月30日刑事第一庭法官李育仁以上正本與原本無異。如不服本判決應於收受送達後10日內向本院提出上訴書狀，並應敘述具體理由。其未敘述上訴理由者，應於上訴期間屆滿後20日內向本院補提理由書(均須按他造當事人之人數附繕本)「切勿逕送上級法院」。書記官張竣閔中華民國100年6月30日",
  "characters": {
    "judges": [
      "李育仁"
    ],
    "prosecutors": [

    ],
    "lawyers": [

    ],
    "clerks": [
      "張竣閔"
    ],
    "plaintiffs": [

    ],
    "defendants": [
      "李文"
    ],
    "prosecutor_office": [
      "臺灣士林地方法院檢察署檢察官"
    ],
    "creditors": [

    ],
    "debtors": [

    ],
    "judicial_associate_officer": [

    ]
  },
  "adjudged_at": "2011-06-30",
  "created_at": "2016-02-13 18:34:01",
  "updated_at": "2016-02-13 18:34:01"
}