{
  "identify": "SCD-94-竹交簡-964-20051226-1",
  "court": {
    "name": "臺灣新竹地方法院",
    "code": "SCD"
  },
  "division": {
    "name": "刑事",
    "code": "M"
  },
  "year": 94,
  "word": "竹交簡",
  "number": "964",
  "jcheck": "1",
  "reason": "公共危險",
  "content": "臺灣新竹地方法院刑事簡易判決       94年度竹交簡字第964號\n聲  請  人  臺灣新竹地方法院檢察署檢察官\n被      告  甲○○\n上列被告因公共危險案件，經檢察官聲請以簡易判決處刑（九十\n四年度速偵字第一七九二號），本院判決如下：\n    主  文\n甲○○服用酒類，不能安全駕駛動力交通工具而駕駛，處罰金壹\n萬捌仟元，如易服勞役，以佰元折算壹日。\n    事實及理由\n一、本件犯罪事實及證據，除犯罪事實欄一、第五行「復於翌（\n    二十八）日凌晨三時許駕駛ＬＨ─九六八九號自用小客車前\n    往桃園」應予更正外，餘均引用檢察官聲請簡易判決處刑書\n    所載（如附件）。\n二、依刑事訴訟法第四百四十九條第一項前段、第四百五十四條\n    第二項，刑法第一百八十五條之三、第四十二條第二項，罰\n    金罰鍰提高標準條例第二條，逕以簡易判決處刑如主文。\n三、如不服本件判決，得自收受送達之日起十日內，向本院提起\n    上訴。\n中    華    民    國    94    年    12    月    26    日\n                  新竹簡易庭    法  官  楊麗文\n以上正本證明與原本無異。\n中    華    民    國    94    年    12    月    26    日\n                                書記官  賴寶合\n附錄本案論罪科刑法條：\n刑法第一百八十五條之三\n服用毒品、麻醉藥品、酒類或其他相類之物，不能安全駕駛動力\n交通工具而駕駛者，處一年以下有期徒刑、拘役或三萬元以下罰\n金。\n（附件）\n",
  "structure": {
    "main": "甲○○服用酒類，不能安全駕駛動力交通工具而駕駛，處罰金壹\n萬捌仟元，如易服勞役，以佰元折算壹日。",
    "fact": "一、本件犯罪事實及證據，除犯罪事實欄一、第五行「復於翌（\n    二十八）日凌晨三時許駕駛ＬＨ─九六八九號自用小客車前\n    往桃園」應予更正外，餘均引用檢察官聲請簡易判決處刑書\n    所載（如附件）。\n二、依刑事訴訟法第四百四十九條第一項前段、第四百五十四條\n    第二項，刑法第一百八十五條之三、第四十二條第二項，罰\n    金罰鍰提高標準條例第二條，逕以簡易判決處刑如主文。\n三、如不服本件判決，得自收受送達之日起十日內，向本院提起\n    上訴。",
    "reason": "一、本件犯罪事實及證據，除犯罪事實欄一、第五行「復於翌（\n    二十八）日凌晨三時許駕駛ＬＨ─九六八九號自用小客車前\n    往桃園」應予更正外，餘均引用檢察官聲請簡易判決處刑書\n    所載（如附件）。\n二、依刑事訴訟法第四百四十九條第一項前段、第四百五十四條\n    第二項，刑法第一百八十五條之三、第四十二條第二項，罰\n    金罰鍰提高標準條例第二條，逕以簡易判決處刑如主文。\n三、如不服本件判決，得自收受送達之日起十日內，向本院提起\n    上訴。"
  },
  "search": "臺灣新竹地方法院刑事簡易判決94年度竹交簡字第964號聲請人臺灣新竹地方法院檢察署檢察官被告甲○○上列被告因公共危險案件，經檢察官聲請以簡易判決處刑（九十四年度速偵字第一七九二號），本院判決如下：主文甲○○服用酒類，不能安全駕駛動力交通工具而駕駛，處罰金壹萬捌仟元，如易服勞役，以佰元折算壹日。事實及理由一、本件犯罪事實及證據，除犯罪事實欄一、第五行「復於翌（二十八）日凌晨三時許駕駛ＬＨ─九六八九號自用小客車前往桃園」應予更正外，餘均引用檢察官聲請簡易判決處刑書所載（如附件）。二、依刑事訴訟法第四百四十九條第一項前段、第四百五十四條第二項，刑法第一百八十五條之三、第四十二條第二項，罰金罰鍰提高標準條例第二條，逕以簡易判決處刑如主文。三、如不服本件判決，得自收受送達之日起十日內，向本院提起上訴。中華民國94年12月26日新竹簡易庭法官楊麗文以上正本證明與原本無異。中華民國94年12月26日書記官賴寶合附錄本案論罪科刑法條：刑法第一百八十五條之三服用毒品、麻醉藥品、酒類或其他相類之物，不能安全駕駛動力交通工具而駕駛者，處一年以下有期徒刑、拘役或三萬元以下罰金。（附件）",
  "characters": {
    "judges": [
      "楊麗文"
    ],
    "prosecutors": [

    ],
    "lawyers": [

    ],
    "clerks": [
      "賴寶合"
    ],
    "plaintiffs": [

    ],
    "defendants": [
      "甲○○"
    ],
    "prosecutor_office": [
      "臺灣新竹地方法院檢察署檢察官"
    ],
    "creditors": [

    ],
    "debtors": [

    ],
    "judicial_associate_officer": [

    ]
  },
  "adjudged_at": "2005-12-26",
  "created_at": "2016-02-07 03:47:24",
  "updated_at": "2016-02-07 03:47:24"
}