{
  "identify": "PTD-94-易-459-20050826-1",
  "court": {
    "name": "臺灣屏東地方法院",
    "code": "PTD"
  },
  "division": {
    "name": "刑事",
    "code": "M"
  },
  "year": 94,
  "word": "易",
  "number": "459",
  "jcheck": "1",
  "reason": "傷害",
  "content": "臺灣屏東地方法院刑事判決               94年度易字第459號\n公  訴  人  臺灣屏東地方法院檢察署檢察官\n被      告  甲○○\n被      告  乙○○\n上列被告等因傷害案件，經檢察官聲請簡易判決處刑（94年度偵\n字第3003號），因本院認不宜以簡易判決處刑，改依通常程序進\n行，經判決如下：\n    主  文\n本件公訴不受理。\n    理  由\n一、聲請意旨如檢察官聲請簡易判決處刑書所載（如附件）。\n二、按告訴乃論之罪，告訴人於第一審辯論終結前，得撤回其告\n    訴；又告訴經撤回者，法院應諭知不受理之判決，並得不經\n    言詞辯論為之，刑事訴訟法第238 條第1 項、第303 條第3\n    款及第307條分別定有明文。\n三、本件被告甲○○、乙○○因傷害案件，經檢察官聲請簡易判\n    決處刑，認被告二人均係犯刑法第277 條第1 項之傷害罪。\n    依同法第287 條前段之規定，須告訴乃論。茲據告訴人陳誌\n    彬於本院審理中，具狀聲請撤回其告訴，揆諸前開說明，爰\n    不經言詞辯論，逕為諭知不受理之判決。\n四、據上論斷，應依刑事訴訟法第303條第3款、第307條，判決\n    如主文。\n中    華    民    國    94    年    8     月    26    日\n                  刑事第一庭    審判長法  官  潘正屏\n                                      法  官  曾吉雄\n                                      法  官  黃聖涵\n以上正本證明與原本無異。\n如不服本判決應於收受本判決送達後十日內向本院提出上訴書狀\n，其未敘述上訴理由者，並得於提起上訴後十日內向本院補提理\n由書狀（均須按他造當事人之人數附繕本）「切勿逕送上級法院\n 」\n中    華    民    國    94    年    8     月    26    日\n                                      書記官  蘇雅慧\n",
  "structure": {
    "main": "本件公訴不受理。",
    "reason": "一、聲請意旨如檢察官聲請簡易判決處刑書所載（如附件）。\n二、按告訴乃論之罪，告訴人於第一審辯論終結前，得撤回其告\n    訴；又告訴經撤回者，法院應諭知不受理之判決，並得不經\n    言詞辯論為之，刑事訴訟法第238 條第1 項、第303 條第3\n    款及第307條分別定有明文。\n三、本件被告甲○○、乙○○因傷害案件，經檢察官聲請簡易判\n    決處刑，認被告二人均係犯刑法第277 條第1 項之傷害罪。\n    依同法第287 條前段之規定，須告訴乃論。茲據告訴人陳誌\n    彬於本院審理中，具狀聲請撤回其告訴，揆諸前開說明，爰\n    不經言詞辯論，逕為諭知不受理之判決。\n四、據上論斷，應依刑事訴訟法第303條第3款、第307條，判決\n    如主文。"
  },
  "search": "臺灣屏東地方法院刑事判決94年度易字第459號公訴人臺灣屏東地方法院檢察署檢察官被告甲○○被告乙○○上列被告等因傷害案件，經檢察官聲請簡易判決處刑（94年度偵字第3003號），因本院認不宜以簡易判決處刑，改依通常程序進行，經判決如下：主文本件公訴不受理。理由一、聲請意旨如檢察官聲請簡易判決處刑書所載（如附件）。二、按告訴乃論之罪，告訴人於第一審辯論終結前，得撤回其告訴；又告訴經撤回者，法院應諭知不受理之判決，並得不經言詞辯論為之，刑事訴訟法第238條第1項、第303條第3款及第307條分別定有明文。三、本件被告甲○○、乙○○因傷害案件，經檢察官聲請簡易判決處刑，認被告二人均係犯刑法第277條第1項之傷害罪。依同法第287條前段之規定，須告訴乃論。茲據告訴人陳誌彬於本院審理中，具狀聲請撤回其告訴，揆諸前開說明，爰不經言詞辯論，逕為諭知不受理之判決。四、據上論斷，應依刑事訴訟法第303條第3款、第307條，判決如主文。中華民國94年8月26日刑事第一庭審判長法官潘正屏法官曾吉雄法官黃聖涵以上正本證明與原本無異。如不服本判決應於收受本判決送達後十日內向本院提出上訴書狀，其未敘述上訴理由者，並得於提起上訴後十日內向本院補提理由書狀（均須按他造當事人之人數附繕本）「切勿逕送上級法院」中華民國94年8月26日書記官蘇雅慧",
  "characters": {
    "judges": [
      "潘正屏",
      "曾吉雄",
      "黃聖涵"
    ],
    "prosecutors": [

    ],
    "lawyers": [

    ],
    "clerks": [
      "蘇雅慧"
    ],
    "plaintiffs": [

    ],
    "defendants": [
      "甲○○",
      "被      告  乙○○"
    ],
    "prosecutor_office": [
      "臺灣屏東地方法院檢察署檢察官"
    ],
    "creditors": [

    ],
    "debtors": [

    ],
    "judicial_associate_officer": [

    ]
  },
  "adjudged_at": "2005-08-26",
  "created_at": "2016-02-06 22:16:12",
  "updated_at": "2016-02-06 22:16:12"
}