{
  "identify": "TYD-94-交簡上-74-20050825-1",
  "court": {
    "name": "臺灣桃園地方法院",
    "code": "TYD"
  },
  "division": {
    "name": "刑事",
    "code": "M"
  },
  "year": 94,
  "word": "交簡上",
  "number": "74",
  "jcheck": "1",
  "reason": "過失傷害",
  "content": "臺灣桃園地方法院刑事判決            94年度交簡上字第74號\n上  訴  人  臺灣桃園地方法院檢察署檢察官\n上  訴  人\n即  被  告  甲○○\n上列上訴人因被告過失傷害案件，不服本院民國九十四年四月二\n十五日九十三年度桃交簡字第一七三五號第一審刑事簡易判決（\n聲請簡易判決處刑案號：九十三年度調偵字第四六一號），提起\n上訴，本院管轄之第二審合議庭判決如下：\n    主  文\n上訴駁回。\n甲○○緩刑貳年。\n    事實及理由\n一、本案經本院管轄第二審之合議庭審理結果，認原審以被告甲\n    ○○犯刑法第二百八十四條第一項前段之過失傷害罪，判處\n    有期徒刑二月，如易科罰金，以三百元折算一日，經核其認\n    事用法及量刑均無不當，應予維持。並引用原審判決書記載\n    之事實、證據及理由。\n二、檢察官循告訴人請求，提起本件上訴意旨略以：被告雖與告\n    訴人達成和解，惟遲未履行，不負責任，原審量刑顯然過輕\n    云云。被告提起本件上訴意旨則以：原審判決後，與告訴人\n    業經調解成立，並已全額給付賠償金額，請求從輕量刑云云\n    。經查：被告於原審判決後，確於民國九十四年六月二十日\n    與告訴人調解成立，當日並給付賠償金額新臺幣八萬七千元\n    現金予告訴人，告訴人願意不再追究被告本件刑事責任等情\n    ，有桃園縣桃園市調解委員會調解書及刑事撤回告訴狀各一\n    件在卷可稽（撤回告訴部分詳見後述），被告顯無拒絕賠償\n    或避不見面之情形，檢察官所執上訴理由尚非可採，原審認\n    事、用法及量刑並無不當，檢察官及被告提起上訴均無理由\n    ，應予駁回。然被告既與告訴人成立調解，賠償告訴人損失\n    ，獲得告訴人之諒解，並對於犯罪事實坦承不諱，足認惡性\n    並非重大，且深具悔意，經此偵查審理程序，應無再犯之虞\n    ，又被告前未曾受有期徒刑以上刑之宣告，有臺灣高等法院\n    被告前案紀錄表一件附卷可查，本院因認對於被告宣告之刑\n    ，以暫不執行為適當，爰宣告緩刑二年，以啟自新。至告訴\n    人具狀撤回告訴部分，因撤回告訴須於第一審辯論終結前為\n    之，刑事訴訟法第二百三十八條第一項定有明文，告訴人尚\n    不得於本院審理之第二審程序中撤回本件告訴，併此敘明。\n據上論斷，應依刑事訴訟法第四百五十五條之一第一項、第三項\n、第三百六十八條、第三百七十三條，刑法第七十四條第一款，\n判決如主文。\n本案經檢察官徐則賢到庭執行職務。\n中    華    民    國    94    年    8     月    25    日\n                  刑事第八庭    審判長法  官  曾家貽\n                                      法  官  吳為平\n                                      法  官  袁雪華\n以上正本證明與原本無異。\n不得上訴。\n                                      書記官  邱仲騏\n中    華    民    國    94    年    8     月    25    日\n",
  "structure": {
    "main": "上訴駁回。\n甲○○緩刑貳年。",
    "fact": "一、本案經本院管轄第二審之合議庭審理結果，認原審以被告甲\n    ○○犯刑法第二百八十四條第一項前段之過失傷害罪，判處\n    有期徒刑二月，如易科罰金，以三百元折算一日，經核其認\n    事用法及量刑均無不當，應予維持。並引用原審判決書記載\n    之事實、證據及理由。\n二、檢察官循告訴人請求，提起本件上訴意旨略以：被告雖與告\n    訴人達成和解，惟遲未履行，不負責任，原審量刑顯然過輕\n    云云。被告提起本件上訴意旨則以：原審判決後，與告訴人\n    業經調解成立，並已全額給付賠償金額，請求從輕量刑云云\n    。經查：被告於原審判決後，確於民國九十四年六月二十日\n    與告訴人調解成立，當日並給付賠償金額新臺幣八萬七千元\n    現金予告訴人，告訴人願意不再追究被告本件刑事責任等情\n    ，有桃園縣桃園市調解委員會調解書及刑事撤回告訴狀各一\n    件在卷可稽（撤回告訴部分詳見後述），被告顯無拒絕賠償\n    或避不見面之情形，檢察官所執上訴理由尚非可採，原審認\n    事、用法及量刑並無不當，檢察官及被告提起上訴均無理由\n    ，應予駁回。然被告既與告訴人成立調解，賠償告訴人損失\n    ，獲得告訴人之諒解，並對於犯罪事實坦承不諱，足認惡性\n    並非重大，且深具悔意，經此偵查審理程序，應無再犯之虞\n    ，又被告前未曾受有期徒刑以上刑之宣告，有臺灣高等法院\n    被告前案紀錄表一件附卷可查，本院因認對於被告宣告之刑\n    ，以暫不執行為適當，爰宣告緩刑二年，以啟自新。至告訴\n    人具狀撤回告訴部分，因撤回告訴須於第一審辯論終結前為\n    之，刑事訴訟法第二百三十八條第一項定有明文，告訴人尚\n    不得於本院審理之第二審程序中撤回本件告訴，併此敘明。\n據上論斷，應依刑事訴訟法第四百五十五條之一第一項、第三項\n、第三百六十八條、第三百七十三條，刑法第七十四條第一款，\n判決如主文。\n本案經檢察官徐則賢到庭執行職務。",
    "reason": "一、本案經本院管轄第二審之合議庭審理結果，認原審以被告甲\n    ○○犯刑法第二百八十四條第一項前段之過失傷害罪，判處\n    有期徒刑二月，如易科罰金，以三百元折算一日，經核其認\n    事用法及量刑均無不當，應予維持。並引用原審判決書記載\n    之事實、證據及理由。\n二、檢察官循告訴人請求，提起本件上訴意旨略以：被告雖與告\n    訴人達成和解，惟遲未履行，不負責任，原審量刑顯然過輕\n    云云。被告提起本件上訴意旨則以：原審判決後，與告訴人\n    業經調解成立，並已全額給付賠償金額，請求從輕量刑云云\n    。經查：被告於原審判決後，確於民國九十四年六月二十日\n    與告訴人調解成立，當日並給付賠償金額新臺幣八萬七千元\n    現金予告訴人，告訴人願意不再追究被告本件刑事責任等情\n    ，有桃園縣桃園市調解委員會調解書及刑事撤回告訴狀各一\n    件在卷可稽（撤回告訴部分詳見後述），被告顯無拒絕賠償\n    或避不見面之情形，檢察官所執上訴理由尚非可採，原審認\n    事、用法及量刑並無不當，檢察官及被告提起上訴均無理由\n    ，應予駁回。然被告既與告訴人成立調解，賠償告訴人損失\n    ，獲得告訴人之諒解，並對於犯罪事實坦承不諱，足認惡性\n    並非重大，且深具悔意，經此偵查審理程序，應無再犯之虞\n    ，又被告前未曾受有期徒刑以上刑之宣告，有臺灣高等法院\n    被告前案紀錄表一件附卷可查，本院因認對於被告宣告之刑\n    ，以暫不執行為適當，爰宣告緩刑二年，以啟自新。至告訴\n    人具狀撤回告訴部分，因撤回告訴須於第一審辯論終結前為\n    之，刑事訴訟法第二百三十八條第一項定有明文，告訴人尚\n    不得於本院審理之第二審程序中撤回本件告訴，併此敘明。\n據上論斷，應依刑事訴訟法第四百五十五條之一第一項、第三項\n、第三百六十八條、第三百七十三條，刑法第七十四條第一款，\n判決如主文。\n本案經檢察官徐則賢到庭執行職務。"
  },
  "search": "臺灣桃園地方法院刑事判決94年度交簡上字第74號上訴人臺灣桃園地方法院檢察署檢察官上訴人即被告甲○○上列上訴人因被告過失傷害案件，不服本院民國九十四年四月二十五日九十三年度桃交簡字第一七三五號第一審刑事簡易判決（聲請簡易判決處刑案號：九十三年度調偵字第四六一號），提起上訴，本院管轄之第二審合議庭判決如下：主文上訴駁回。甲○○緩刑貳年。事實及理由一、本案經本院管轄第二審之合議庭審理結果，認原審以被告甲○○犯刑法第二百八十四條第一項前段之過失傷害罪，判處有期徒刑二月，如易科罰金，以三百元折算一日，經核其認事用法及量刑均無不當，應予維持。並引用原審判決書記載之事實、證據及理由。二、檢察官循告訴人請求，提起本件上訴意旨略以：被告雖與告訴人達成和解，惟遲未履行，不負責任，原審量刑顯然過輕云云。被告提起本件上訴意旨則以：原審判決後，與告訴人業經調解成立，並已全額給付賠償金額，請求從輕量刑云云。經查：被告於原審判決後，確於民國九十四年六月二十日與告訴人調解成立，當日並給付賠償金額新臺幣八萬七千元現金予告訴人，告訴人願意不再追究被告本件刑事責任等情，有桃園縣桃園市調解委員會調解書及刑事撤回告訴狀各一件在卷可稽（撤回告訴部分詳見後述），被告顯無拒絕賠償或避不見面之情形，檢察官所執上訴理由尚非可採，原審認事、用法及量刑並無不當，檢察官及被告提起上訴均無理由，應予駁回。然被告既與告訴人成立調解，賠償告訴人損失，獲得告訴人之諒解，並對於犯罪事實坦承不諱，足認惡性並非重大，且深具悔意，經此偵查審理程序，應無再犯之虞，又被告前未曾受有期徒刑以上刑之宣告，有臺灣高等法院被告前案紀錄表一件附卷可查，本院因認對於被告宣告之刑，以暫不執行為適當，爰宣告緩刑二年，以啟自新。至告訴人具狀撤回告訴部分，因撤回告訴須於第一審辯論終結前為之，刑事訴訟法第二百三十八條第一項定有明文，告訴人尚不得於本院審理之第二審程序中撤回本件告訴，併此敘明。據上論斷，應依刑事訴訟法第四百五十五條之一第一項、第三項、第三百六十八條、第三百七十三條，刑法第七十四條第一款，判決如主文。本案經檢察官徐則賢到庭執行職務。中華民國94年8月25日刑事第八庭審判長法官曾家貽法官吳為平法官袁雪華以上正本證明與原本無異。不得上訴。書記官邱仲騏中華民國94年8月25日",
  "characters": {
    "judges": [
      "曾家貽",
      "吳為平",
      "袁雪華"
    ],
    "prosecutors": [
      "徐則賢"
    ],
    "lawyers": [

    ],
    "clerks": [
      "邱仲騏"
    ],
    "plaintiffs": [

    ],
    "defendants": [
      "甲"
    ],
    "prosecutor_office": [

    ],
    "creditors": [

    ],
    "debtors": [

    ],
    "judicial_associate_officer": [

    ]
  },
  "adjudged_at": "2005-08-25",
  "created_at": "2016-02-06 22:16:51",
  "updated_at": "2016-02-06 22:16:51"
}