{
  "identify": "KMD-93-聲-47-20040927-1",
  "court": {
    "name": "福建金門地方法院",
    "code": "KMD"
  },
  "division": {
    "name": "民事",
    "code": "V"
  },
  "year": 93,
  "word": "聲",
  "number": "47",
  "jcheck": "1",
  "reason": "確定訴訟費用額",
  "content": "福建金門地方法院民事裁定                            九十三年度聲字第四七號\n    聲  請  人  財政部國有財產局台灣北區辨事處金馬分處\n    法定代理人  乙○○\n    相  對  人  甲○○\n右當事人間請求確認土地登記請求權不存在事件，聲請人聲請確定訴訟費用額，本院\n裁定如左：\n    主      文\n相對人應負擔之訴訟費用額確定為新台幣壹萬伍仟陸佰貳拾伍元。\n    理      由\n一、聲請人與相對人間請求確認土地登記請求權不存在事件，經本院金城簡易庭以九\n    十一年度城簡字第五一號及本院九十三年度簡上字第一號判決確定，其訴訟費用\n    應由相對人負擔。\n二、經本院調卷審查，相對人應負擔之訴訟費用額，依後附計算書確定為如主文所示\n    金額。\n三、依民事訴訟法第九十一條第一項、第九十五條、第七十八條裁定如主文。\n中      華      民      國    九十三    年      九      月    二十七    日\n                                  福建金門地方法院民事庭\n                                      法  官  林鈺琅\n右為正本係照原本作成\n如對本裁定抗告，應於收受裁定正本送達後十日內向本院提出抗告狀，並繳納抗告裁\n判費新台幣四十五元。\n中      華      民      國    九十三    年      九      月    二十七    日\n                                            書記官  董培祥\n┌───────┬─────────┬───────────────────┐\n│項          目│金  額（新臺幣元）│  備                              註  │\n├───────┼─────────┼───────────────────┤\n│第一審裁判費  │        二、九三○│                                      │\n├───────┼─────────┼───────────────────┤\n│第一審送達郵資│            三九○│                                      │\n├───────┼─────────┼───────────────────┤\n│第一審測量費  │        八、○○○│                                      │\n├───────┼─────────┼───────────────────┤\n│第二審裁判費  │        四、三○五│                                      │\n├───────┼─────────┼───────────────────┤\n│合          計│      一五、六二五│                                      │\n└───────┴─────────┴───────────────────┘\n",
  "structure": {
    "main": "相對人應負擔之訴訟費用額確定為新台幣壹萬伍仟陸佰貳拾伍元。",
    "reason": "一、聲請人與相對人間請求確認土地登記請求權不存在事件，經本院金城簡易庭以九\n    十一年度城簡字第五一號及本院九十三年度簡上字第一號判決確定，其訴訟費用\n    應由相對人負擔。\n二、經本院調卷審查，相對人應負擔之訴訟費用額，依後附計算書確定為如主文所示\n    金額。\n三、依民事訴訟法第九十一條第一項、第九十五條、第七十八條裁定如主文。"
  },
  "search": "福建金門地方法院民事裁定九十三年度聲字第四七號聲請人財政部國有財產局台灣北區辨事處金馬分處法定代理人乙○○相對人甲○○右當事人間請求確認土地登記請求權不存在事件，聲請人聲請確定訴訟費用額，本院裁定如左：主文相對人應負擔之訴訟費用額確定為新台幣壹萬伍仟陸佰貳拾伍元。理由一、聲請人與相對人間請求確認土地登記請求權不存在事件，經本院金城簡易庭以九十一年度城簡字第五一號及本院九十三年度簡上字第一號判決確定，其訴訟費用應由相對人負擔。二、經本院調卷審查，相對人應負擔之訴訟費用額，依後附計算書確定為如主文所示金額。三、依民事訴訟法第九十一條第一項、第九十五條、第七十八條裁定如主文。中華民國九十三年九月二十七日福建金門地方法院民事庭法官林鈺琅右為正本係照原本作成如對本裁定抗告，應於收受裁定正本送達後十日內向本院提出抗告狀，並繳納抗告裁判費新台幣四十五元。中華民國九十三年九月二十七日書記官董培祥┌───────┬─────────┬───────────────────┐│項目│金額（新臺幣元）│備註│├───────┼─────────┼───────────────────┤│第一審裁判費│二、九三○││├───────┼─────────┼───────────────────┤│第一審送達郵資│三九○││├───────┼─────────┼───────────────────┤│第一審測量費│八、○○○││├───────┼─────────┼───────────────────┤│第二審裁判費│四、三○五││├───────┼─────────┼───────────────────┤│合計│一五、六二五││└───────┴─────────┴───────────────────┘",
  "characters": {
    "judges": [
      "林鈺琅"
    ],
    "prosecutors": [

    ],
    "lawyers": [

    ],
    "clerks": [
      "董培祥"
    ],
    "plaintiffs": [

    ],
    "defendants": [

    ],
    "prosecutor_office": [
      "財政部國有財產局台灣北區辨事處金馬分處"
    ],
    "creditors": [

    ],
    "debtors": [

    ],
    "judicial_associate_officer": [

    ]
  },
  "adjudged_at": "2004-09-27",
  "created_at": "2016-02-06 00:42:09",
  "updated_at": "2016-02-06 00:42:09"
}