{
  "identify": "TPD-93-簡-1708-20040727-1",
  "court": {
    "name": "臺灣臺北地方法院",
    "code": "TPD"
  },
  "division": {
    "name": "刑事",
    "code": "M"
  },
  "year": 93,
  "word": "簡",
  "number": "1708",
  "jcheck": "1",
  "reason": "偽造文書",
  "content": "臺灣臺北地方法院刑事簡易判決                    九十三年度簡字第一七０八號\n    聲  請  人  臺灣臺北地方法院檢察署檢察官\n    被      告  甲○○\n右列被告因偽造文書案件，經檢察官聲請以簡易判決處刑（九十三年度偵字第九五一\n八號），本院判決如左：\n    主  文\n甲○○行使偽造私文書，足以生損害於公眾及他人，處有期徒刑參月，如易科罰金，\n以參佰元折算壹日。內政部警政署國道公路警察局舉發違反道路交通管理事件通知單\n（公警局交字第Ｚ00000000、Ｚ00000000號）移送聯上偽造之「黃\n宜宏」簽名及指印各貳枚，與酒精濃度測試紙上偽造之「黃宜宏」簽名及指印各貳枚\n均沒收。\n    事實及理由\n一、本件犯罪事實、證據及應適用之法條，均引用檢察官聲請簡易判決處刑書（如附\n    件）之記載。\n二、依刑事訴訟法第四百四十九條第一項前段、第三項、第四百五十條第一項、第四\n    百五十四條第二項，刑法第二百十六條、第二百十條、第六十二條前段、第四十\n    一條第一項前段、第二百十九條，罰金罰鍰提高標準條例第二條，逕以簡易判決\n    處刑如主文。\n如不服本判決，應於判決送達後十日內向本院提出上訴狀（應抄附繕本）。告訴人或\n被害人如對於本判決不服者，應具備理由請求檢察官上訴，上訴於本院第二審合議庭\n，其上訴期間之計算係以檢察官收受判決正本之日期為準。\n中      華      民      國    九十三    年      七      月    二十七    日\n                                    臺灣臺北地方法院刑事第七庭\n                                        法  官  蕭清清\n右正本證明與原本無異。\n                                        書記官  劉麗英\n中      華      民      國    九十三    年      七      月    二十九    日\n附錄本案論罪科刑法條全文：\n刑法第二百十六條\n行使第二百十條至第二百十五條之文書者，依偽造、變造文書或登載不實事項或使登\n載不實事項之規定處斷。\n刑法第二百十條\n偽造、變造私文書，足以生損害於公眾或他人者，處五年以下有期徒刑。\n",
  "structure": {
    "main": "甲○○行使偽造私文書，足以生損害於公眾及他人，處有期徒刑參月，如易科罰金，\n以參佰元折算壹日。內政部警政署國道公路警察局舉發違反道路交通管理事件通知單\n（公警局交字第Ｚ00000000、Ｚ00000000號）移送聯上偽造之「黃\n宜宏」簽名及指印各貳枚，與酒精濃度測試紙上偽造之「黃宜宏」簽名及指印各貳枚\n均沒收。",
    "fact": "一、本件犯罪事實、證據及應適用之法條，均引用檢察官聲請簡易判決處刑書（如附\n    件）之記載。\n二、依刑事訴訟法第四百四十九條第一項前段、第三項、第四百五十條第一項、第四\n    百五十四條第二項，刑法第二百十六條、第二百十條、第六十二條前段、第四十\n    一條第一項前段、第二百十九條，罰金罰鍰提高標準條例第二條，逕以簡易判決\n    處刑如主文。\n如不服本判決，應於判決送達後十日內向本院提出上訴狀（應抄附繕本）。告訴人或\n被害人如對於本判決不服者，應具備理由請求檢察官上訴，上訴於本院第二審合議庭\n，其上訴期間之計算係以檢察官收受判決正本之日期為準。",
    "reason": "一、本件犯罪事實、證據及應適用之法條，均引用檢察官聲請簡易判決處刑書（如附\n    件）之記載。\n二、依刑事訴訟法第四百四十九條第一項前段、第三項、第四百五十條第一項、第四\n    百五十四條第二項，刑法第二百十六條、第二百十條、第六十二條前段、第四十\n    一條第一項前段、第二百十九條，罰金罰鍰提高標準條例第二條，逕以簡易判決\n    處刑如主文。\n如不服本判決，應於判決送達後十日內向本院提出上訴狀（應抄附繕本）。告訴人或\n被害人如對於本判決不服者，應具備理由請求檢察官上訴，上訴於本院第二審合議庭\n，其上訴期間之計算係以檢察官收受判決正本之日期為準。"
  },
  "search": "臺灣臺北地方法院刑事簡易判決九十三年度簡字第一七０八號聲請人臺灣臺北地方法院檢察署檢察官被告甲○○右列被告因偽造文書案件，經檢察官聲請以簡易判決處刑（九十三年度偵字第九五一八號），本院判決如左：主文甲○○行使偽造私文書，足以生損害於公眾及他人，處有期徒刑參月，如易科罰金，以參佰元折算壹日。內政部警政署國道公路警察局舉發違反道路交通管理事件通知單（公警局交字第Ｚ00000000、Ｚ00000000號）移送聯上偽造之「黃宜宏」簽名及指印各貳枚，與酒精濃度測試紙上偽造之「黃宜宏」簽名及指印各貳枚均沒收。事實及理由一、本件犯罪事實、證據及應適用之法條，均引用檢察官聲請簡易判決處刑書（如附件）之記載。二、依刑事訴訟法第四百四十九條第一項前段、第三項、第四百五十條第一項、第四百五十四條第二項，刑法第二百十六條、第二百十條、第六十二條前段、第四十一條第一項前段、第二百十九條，罰金罰鍰提高標準條例第二條，逕以簡易判決處刑如主文。如不服本判決，應於判決送達後十日內向本院提出上訴狀（應抄附繕本）。告訴人或被害人如對於本判決不服者，應具備理由請求檢察官上訴，上訴於本院第二審合議庭，其上訴期間之計算係以檢察官收受判決正本之日期為準。中華民國九十三年七月二十七日臺灣臺北地方法院刑事第七庭法官蕭清清右正本證明與原本無異。書記官劉麗英中華民國九十三年七月二十九日附錄本案論罪科刑法條全文：刑法第二百十六條行使第二百十條至第二百十五條之文書者，依偽造、變造文書或登載不實事項或使登載不實事項之規定處斷。刑法第二百十條偽造、變造私文書，足以生損害於公眾或他人者，處五年以下有期徒刑。",
  "characters": {
    "judges": [
      "蕭清清"
    ],
    "prosecutors": [

    ],
    "lawyers": [

    ],
    "clerks": [
      "劉麗英"
    ],
    "plaintiffs": [

    ],
    "defendants": [
      "甲○○",
      "右列被告因偽造文書案件，經檢察官聲請以簡易判決處刑（九十三年度偵字第九五一",
      "八號），本院判決如左："
    ],
    "prosecutor_office": [
      "臺灣臺北地方法院檢察署檢察官"
    ],
    "creditors": [

    ],
    "debtors": [

    ],
    "judicial_associate_officer": [

    ]
  },
  "adjudged_at": "2004-07-27",
  "created_at": "2016-02-06 12:03:04",
  "updated_at": "2016-02-06 12:03:04"
}