{
  "identify": "TYD-93-壢簡-878-20040727-1",
  "court": {
    "name": "臺灣桃園地方法院",
    "code": "TYD"
  },
  "division": {
    "name": "刑事",
    "code": "M"
  },
  "year": 93,
  "word": "壢簡",
  "number": "878",
  "jcheck": "1",
  "reason": "賭博",
  "content": "臺灣桃園地方法院刑事簡易判決                    九十三年度壢簡字第八七八號\n    聲  請  人  臺灣桃園地方法院檢察署檢察官\n    被      告  甲○○\n右列被告因賭博案件，經檢察官聲請以簡易判決處刑（九十三年度偵字第六九五九號\n），本院判決如左：\n    主  文\n甲○○連續意圖營利聚眾賭博，處有期徒刑陸月，如易科罰金，以佰元折算壹日。\n如附件附表所示之物，均沒收之。\n    事實及理由\n一、本件犯罪事實、證據及應適用之法條，均引用檢察官聲請簡易判決處刑書之記載\n    （如附件）。\n二、依刑事訴訟法第四百四十九條第一項前段、第四百五十條第一項、第四百五十四\n    條第二項，刑法第五十六條、第二百六十八條、第二百六十六條第一項、第五十\n    五條、第三十八條第一項第二款、第四十一條第一項前段，罰金罰鍰提高標準條\n    例第一條前段、第二條，逕以簡易判決處如主文所示之刑。\n如不服本判決，得於判決書送達之翌日起十日內，以書狀敘述理由向本院提出上訴。\n中      華      民      國      九十三      年    七    月    二十七    日\n                                  臺灣桃園地方法院刑事第七庭\n                                      法  官  孫惠琳\n右正本證明與原本無異。\n                                      書記官  黃泰能\n中      華      民      國      九十三      年    七    月    二十八    日\n本案論罪科刑主要法條：\n中華民國刑法第二百六十八條\n(圖利供給賭場或聚眾賭博罪)\n意圖營利，供給賭博場所或聚眾賭博者，處三年以下有期徒刑，得併科三千元以下罰\n金。\n中華民國刑法第二百六十六條\n(普通賭博罪與沒收物)\n在公共場所或公眾得出入之場所賭博財物者，處一千元以下罰金。但以供人暫時娛樂\n之物為賭者，不在此限。\n當場賭博之器具與在賭檯或兌換籌碼處之財物，不問屬於犯人與否，沒收之。\n",
  "structure": {
    "main": "甲○○連續意圖營利聚眾賭博，處有期徒刑陸月，如易科罰金，以佰元折算壹日。\n如附件附表所示之物，均沒收之。",
    "fact": "一、本件犯罪事實、證據及應適用之法條，均引用檢察官聲請簡易判決處刑書之記載\n    （如附件）。\n二、依刑事訴訟法第四百四十九條第一項前段、第四百五十條第一項、第四百五十四\n    條第二項，刑法第五十六條、第二百六十八條、第二百六十六條第一項、第五十\n    五條、第三十八條第一項第二款、第四十一條第一項前段，罰金罰鍰提高標準條\n    例第一條前段、第二條，逕以簡易判決處如主文所示之刑。\n如不服本判決，得於判決書送達之翌日起十日內，以書狀敘述理由向本院提出上訴。",
    "reason": "一、本件犯罪事實、證據及應適用之法條，均引用檢察官聲請簡易判決處刑書之記載\n    （如附件）。\n二、依刑事訴訟法第四百四十九條第一項前段、第四百五十條第一項、第四百五十四\n    條第二項，刑法第五十六條、第二百六十八條、第二百六十六條第一項、第五十\n    五條、第三十八條第一項第二款、第四十一條第一項前段，罰金罰鍰提高標準條\n    例第一條前段、第二條，逕以簡易判決處如主文所示之刑。\n如不服本判決，得於判決書送達之翌日起十日內，以書狀敘述理由向本院提出上訴。"
  },
  "search": "臺灣桃園地方法院刑事簡易判決九十三年度壢簡字第八七八號聲請人臺灣桃園地方法院檢察署檢察官被告甲○○右列被告因賭博案件，經檢察官聲請以簡易判決處刑（九十三年度偵字第六九五九號），本院判決如左：主文甲○○連續意圖營利聚眾賭博，處有期徒刑陸月，如易科罰金，以佰元折算壹日。如附件附表所示之物，均沒收之。事實及理由一、本件犯罪事實、證據及應適用之法條，均引用檢察官聲請簡易判決處刑書之記載（如附件）。二、依刑事訴訟法第四百四十九條第一項前段、第四百五十條第一項、第四百五十四條第二項，刑法第五十六條、第二百六十八條、第二百六十六條第一項、第五十五條、第三十八條第一項第二款、第四十一條第一項前段，罰金罰鍰提高標準條例第一條前段、第二條，逕以簡易判決處如主文所示之刑。如不服本判決，得於判決書送達之翌日起十日內，以書狀敘述理由向本院提出上訴。中華民國九十三年七月二十七日臺灣桃園地方法院刑事第七庭法官孫惠琳右正本證明與原本無異。書記官黃泰能中華民國九十三年七月二十八日本案論罪科刑主要法條：中華民國刑法第二百六十八條(圖利供給賭場或聚眾賭博罪)意圖營利，供給賭博場所或聚眾賭博者，處三年以下有期徒刑，得併科三千元以下罰金。中華民國刑法第二百六十六條(普通賭博罪與沒收物)在公共場所或公眾得出入之場所賭博財物者，處一千元以下罰金。但以供人暫時娛樂之物為賭者，不在此限。當場賭博之器具與在賭檯或兌換籌碼處之財物，不問屬於犯人與否，沒收之。",
  "characters": {
    "judges": [
      "孫惠琳"
    ],
    "prosecutors": [

    ],
    "lawyers": [

    ],
    "clerks": [
      "黃泰能"
    ],
    "plaintiffs": [

    ],
    "defendants": [
      "甲○○",
      "右列被告因賭博案件，經檢察官聲請以簡易判決處刑（九十三年度偵字第六九五九號",
      "），本院判決如左："
    ],
    "prosecutor_office": [
      "臺灣桃園地方法院檢察署檢察官"
    ],
    "creditors": [

    ],
    "debtors": [

    ],
    "judicial_associate_officer": [

    ]
  },
  "adjudged_at": "2004-07-27",
  "created_at": "2016-02-06 12:04:24",
  "updated_at": "2016-02-06 12:04:24"
}