{
  "identify": "KSD-94-簡-5856-20051014-1",
  "court": {
    "name": "臺灣高雄地方法院",
    "code": "KSD"
  },
  "division": {
    "name": "刑事",
    "code": "M"
  },
  "year": 94,
  "word": "簡",
  "number": "5856",
  "jcheck": "1",
  "reason": "毒品危害防制條例",
  "content": "臺灣高雄地方法院刑事簡易判決          94年度簡字第5856號\n聲  請  人  臺灣高雄地方法院檢察署檢察官\n被      告  甲○○\n                      號\n上列被告因毒品危害防制條例案件，經檢察官聲請以簡易判決處\n刑（94年度毒偵字第2661號），本院判決如下：\n    主  文\n甲○○持有第一級毒品，處有期徒刑參月，如易科罰金，以參佰\n元折算壹日。扣案第一級毒品海洛因壹包（驗後淨重零點零伍公\n克，空包裝重零點壹陸公克）沒收銷燬之。\n    事實及理由\n一、本件犯罪事實及證據，均引用檢察官聲請簡易判決處刑書之\n    記載（如附件），並補充事實欄：被告購入第一級毒品後，\n    準備吸食而非法持有之。\n二、核被告所為，係犯毒品危害條例第11條第1 項之持有第一級\n    毒品罪。爰審酌被告意圖供自己施用而持有第一級毒品海洛\n    因，戕害自己身體健康，所為固不足取，惟其為警查獲持有\n    海洛因之數量甚少，及購入毒品僅為供己施用，所生危害尚\n    輕等一切情狀，量處如主文所示之刑，並諭知易科罰金之折\n    算標準。又扣案之海洛因1 包（驗後淨重0.05公克、空包裝\n    總重0.16公克），屬第一級毒品，應依毒品危害防制條例第\n    18條第1 項前段規定，不問屬於犯人與否，沒收銷燬之。（\n    包裝袋因與其內之毒品業已無法析離，應將之同視為第一級\n    毒品，從而不問屬於犯人與否，依上開規定宣告，應予沒收\n    銷燬；至鑑驗所耗損之毒品，既已滅失，自無庸宣告沒收銷\n    燬）\n三、依刑事訴訟法第449 條第1 項前段、第3 項、第450 條第1\n    項、第454 條第2 項，毒品危害防制條例第11條第1 項、第\n    18 條 第1 項前段，刑法第11條、第41條第1 項前段，罰金\n    罰鍰提高標準條例第2 條，逕以簡易判決處刑如主文。\n四、如不服本判決，得自收受送達之日起10日內，向本院提起上\n    訴。\n中    華    民    國    94    年    10    月    14    日\n                    高雄簡易庭  法  官  林瑋桓\n以上正本，係照原本作成，證明與原本無異。\n中    華    民    國    94    年    10    月    14    日\n                                書記官  謝群育\n附錄本判決論罪之法條：\n毒品危害防制條例第11條第1項：\n持有第1 級毒品者，處3 年以下有期徒刑、拘役或新臺幣5 萬元\n以下罰金。\n",
  "structure": {
    "main": "甲○○持有第一級毒品，處有期徒刑參月，如易科罰金，以參佰\n元折算壹日。扣案第一級毒品海洛因壹包（驗後淨重零點零伍公\n克，空包裝重零點壹陸公克）沒收銷燬之。",
    "fact": "一、本件犯罪事實及證據，均引用檢察官聲請簡易判決處刑書之\n    記載（如附件），並補充事實欄：被告購入第一級毒品後，\n    準備吸食而非法持有之。\n二、核被告所為，係犯毒品危害條例第11條第1 項之持有第一級\n    毒品罪。爰審酌被告意圖供自己施用而持有第一級毒品海洛\n    因，戕害自己身體健康，所為固不足取，惟其為警查獲持有\n    海洛因之數量甚少，及購入毒品僅為供己施用，所生危害尚\n    輕等一切情狀，量處如主文所示之刑，並諭知易科罰金之折\n    算標準。又扣案之海洛因1 包（驗後淨重0.05公克、空包裝\n    總重0.16公克），屬第一級毒品，應依毒品危害防制條例第\n    18條第1 項前段規定，不問屬於犯人與否，沒收銷燬之。（\n    包裝袋因與其內之毒品業已無法析離，應將之同視為第一級\n    毒品，從而不問屬於犯人與否，依上開規定宣告，應予沒收\n    銷燬；至鑑驗所耗損之毒品，既已滅失，自無庸宣告沒收銷\n    燬）\n三、依刑事訴訟法第449 條第1 項前段、第3 項、第450 條第1\n    項、第454 條第2 項，毒品危害防制條例第11條第1 項、第\n    18 條 第1 項前段，刑法第11條、第41條第1 項前段，罰金\n    罰鍰提高標準條例第2 條，逕以簡易判決處刑如主文。\n四、如不服本判決，得自收受送達之日起10日內，向本院提起上\n    訴。",
    "reason": "一、本件犯罪事實及證據，均引用檢察官聲請簡易判決處刑書之\n    記載（如附件），並補充事實欄：被告購入第一級毒品後，\n    準備吸食而非法持有之。\n二、核被告所為，係犯毒品危害條例第11條第1 項之持有第一級\n    毒品罪。爰審酌被告意圖供自己施用而持有第一級毒品海洛\n    因，戕害自己身體健康，所為固不足取，惟其為警查獲持有\n    海洛因之數量甚少，及購入毒品僅為供己施用，所生危害尚\n    輕等一切情狀，量處如主文所示之刑，並諭知易科罰金之折\n    算標準。又扣案之海洛因1 包（驗後淨重0.05公克、空包裝\n    總重0.16公克），屬第一級毒品，應依毒品危害防制條例第\n    18條第1 項前段規定，不問屬於犯人與否，沒收銷燬之。（\n    包裝袋因與其內之毒品業已無法析離，應將之同視為第一級\n    毒品，從而不問屬於犯人與否，依上開規定宣告，應予沒收\n    銷燬；至鑑驗所耗損之毒品，既已滅失，自無庸宣告沒收銷\n    燬）\n三、依刑事訴訟法第449 條第1 項前段、第3 項、第450 條第1\n    項、第454 條第2 項，毒品危害防制條例第11條第1 項、第\n    18 條 第1 項前段，刑法第11條、第41條第1 項前段，罰金\n    罰鍰提高標準條例第2 條，逕以簡易判決處刑如主文。\n四、如不服本判決，得自收受送達之日起10日內，向本院提起上\n    訴。"
  },
  "search": "臺灣高雄地方法院刑事簡易判決94年度簡字第5856號聲請人臺灣高雄地方法院檢察署檢察官被告甲○○號上列被告因毒品危害防制條例案件，經檢察官聲請以簡易判決處刑（94年度毒偵字第2661號），本院判決如下：主文甲○○持有第一級毒品，處有期徒刑參月，如易科罰金，以參佰元折算壹日。扣案第一級毒品海洛因壹包（驗後淨重零點零伍公克，空包裝重零點壹陸公克）沒收銷燬之。事實及理由一、本件犯罪事實及證據，均引用檢察官聲請簡易判決處刑書之記載（如附件），並補充事實欄：被告購入第一級毒品後，準備吸食而非法持有之。二、核被告所為，係犯毒品危害條例第11條第1項之持有第一級毒品罪。爰審酌被告意圖供自己施用而持有第一級毒品海洛因，戕害自己身體健康，所為固不足取，惟其為警查獲持有海洛因之數量甚少，及購入毒品僅為供己施用，所生危害尚輕等一切情狀，量處如主文所示之刑，並諭知易科罰金之折算標準。又扣案之海洛因1包（驗後淨重0.05公克、空包裝總重0.16公克），屬第一級毒品，應依毒品危害防制條例第18條第1項前段規定，不問屬於犯人與否，沒收銷燬之。（包裝袋因與其內之毒品業已無法析離，應將之同視為第一級毒品，從而不問屬於犯人與否，依上開規定宣告，應予沒收銷燬；至鑑驗所耗損之毒品，既已滅失，自無庸宣告沒收銷燬）三、依刑事訴訟法第449條第1項前段、第3項、第450條第1項、第454條第2項，毒品危害防制條例第11條第1項、第18條第1項前段，刑法第11條、第41條第1項前段，罰金罰鍰提高標準條例第2條，逕以簡易判決處刑如主文。四、如不服本判決，得自收受送達之日起10日內，向本院提起上訴。中華民國94年10月14日高雄簡易庭法官林瑋桓以上正本，係照原本作成，證明與原本無異。中華民國94年10月14日書記官謝群育附錄本判決論罪之法條：毒品危害防制條例第11條第1項：持有第1級毒品者，處3年以下有期徒刑、拘役或新臺幣5萬元以下罰金。",
  "characters": {
    "judges": [
      "林瑋桓"
    ],
    "prosecutors": [

    ],
    "lawyers": [

    ],
    "clerks": [
      "謝群育"
    ],
    "plaintiffs": [

    ],
    "defendants": [
      "甲○○"
    ],
    "prosecutor_office": [
      "臺灣高雄地方法院檢察署檢察官"
    ],
    "creditors": [

    ],
    "debtors": [

    ],
    "judicial_associate_officer": [

    ]
  },
  "adjudged_at": "2005-10-14",
  "created_at": "2016-02-07 10:04:22",
  "updated_at": "2016-02-07 10:04:22"
}