{
  "identify": "KSD-91-訴-1612-20020918-1",
  "court": {
    "name": "臺灣高雄地方法院",
    "code": "KSD"
  },
  "division": {
    "name": "刑事",
    "code": "M"
  },
  "year": 91,
  "word": "訴",
  "number": "1612",
  "jcheck": "1",
  "reason": "偽造文書等",
  "content": "臺灣高雄地方法院刑事判決                        九十一年度訴字第一六一二號\n    公  訴  人  臺灣高雄地方法院檢察署檢察官\n    被      告  甲○○\n    選任辯護人  吳建勛律師\n                游雪莉律師\n                陳慧錚律師\n右列被告因偽造文書等案件，經檢察官提起公訴（九十年度偵字第一０二三二號），\n本院判決如左：\n    主  文\n甲○○連續行使偽造私文書，足以生損害他人，處有期徒刑陸月，如易科罰金，以參\n佰元折算壹日。緩刑貳年。\n    事  實\n一、甲○○係設於高雄縣鳥松鄉○○路二五之二八號Ｄ棟立笠鋼鐵企業有限公司（下\n    稱立笠公司）之實際負責人，因公司財務發生危機，急需借款應急，向柯聰發借\n    用發票人為柯聰發，付款人為彰化銀行東高雄分行，發票日期分別為民國八十九\n    年十二月二十五日及九十年一月十日，票面金額分別為新臺幣（下同）五十五萬\n    二千七百八十元、二十萬元之支票二紙，並由立笠公司於該支票二紙背面背書，\n    惟因銀行要求須另有他公司背書以增加信用度，甲○○為能順利以該支票二紙向\n    銀行票貼借款，竟基於意圖為自己不法所有、行使偽造私文書之概括犯意，明知\n    未經長浚企業有限公司（下稱長浚公司）之同意，於八十九年底，在立笠公司，\n    持長浚公司留存於立笠公司作為承攬工程報價之用之「長浚企業有限公司」及該\n    公司名義負責人「宋靜」之印章（即俗稱大小章）各一枚，於該支票二紙背面背\n    書欄內盜蓋「長浚企業有限公司」、「宋靜」之印文各二枚背書於上，並先後於\n    不詳時間持該支票二紙向中國信託商業銀行股份有限公司（下稱中國信託商業銀\n    行）票貼借款而行使之，使中國信託商業銀行不疑有他，陷於錯誤而先後於八十\n    九年十月十二日、同年月十六日交付四十七萬三千三百三十元、十五萬九千八百\n    九十元，共計六十三萬三千二百二十元，足以生損害於長浚公司、宋靜及中國信\n    託商業銀行。嗣經中國信託商業銀行屆期提示遭以存款不足為由退票，中國信託\n    商業銀行乃向本院聲請支付命令，長浚公司於法定期間內聲明異議，始知上情。\n二、案經長浚企業有限公司訴由臺灣高雄地方法院檢察署檢察官偵查起訴。\n    理  由\n一、右揭犯罪事實，業據被告甲○○坦承不諱，核與告訴代表人宋靜指述之情節相符\n    ，並有中國信託公司民事號支付命令聲請狀、臺灣高雄地方法院九十年促字第五\n    一三六號支付命令、錄音帶譯文各一份附卷足憑，是被告自白與事實相符，本件\n    事證明確，被告犯行洵堪認定。\n二、核被告所為，係犯刑法第三百三十九條第一項之詐欺取財罪、第二百十六條、第\n    二百十條之行使偽造私文書罪。其盜用印章之行為為偽造私文書行為之階段行為\n    ；偽造私文書之低度行為又為行使偽造私文書之高度行為吸收，均不另論擬。被\n    告先後多次犯行，時間緊接，所犯構成要件相同，顯係基於概括犯意為之，為連\n    續犯，應依刑法第五十六條論以一罪，並加重其刑。被告所犯上開兩罪間，有方\n    法結果之牽連關係，為牽連犯，應從一重行使偽造私文書罪處斷。爰審酌被告犯\n    罪之動機、目的、手段、犯罪所生之損害，及犯後坦承犯行等一切情狀，量處如\n    主文所示之刑。按刑法第四十一條，已於九十年一月十日修正公布，並於同月十\n    二日施行，其第一項前段規定為「犯最重本刑為五年以下有期徒刑之罪，而受六\n    月以下有期徒刑或拘役之宣告，因身體、教育、職業或家庭之關係或因其他正當\n    事由，執行顯有困難者，得以一元以上三元以下折算一日，易科罰金。」，本件\n    被告犯罪後，上開犯行，已變更屬得易科罰金之罪，依最高法院二十四年七月刑\n    庭總會決議，易科罰金之事項，應依刑法第二條第一項之規定，適用修正後之刑\n    法第四十一條之新法，本件爰諭知易科罰金之折算標準，以資懲儆。又被告前未\n    曾受有期徒刑以上刑之宣告，此有臺灣高雄地方法院檢察署刑案資料查註記錄表\n    附卷可稽，因一時失慮，偶罹刑典，事後已坦承犯行，深具悔意，經此刑之宣告\n    後，應知警惕而無再犯之虞，本院因認暫不執行其刑為當，予以宣告緩刑二年，\n    用啟自新。\n據上論斷，應依刑事訴訟法第二百九十九條第一項前段，刑法第二條第一項前段、第\n五十六條、第二百十六條、第二百十條、第三百三十九條第一項、第五十五條、第四\n十一條第一項、第七十四條第一款，罰金罰鍰提高標準條例第一條前段、第二條，判\n決如主文。\n本案經檢察官劉昀到庭執行職務。\n中    華    民    國      九十一      年      九      月      十八      日\n                                  臺灣高雄地方法院刑事庭\n                                      法  官  何悅芳\n右正本證明與原本無異。\n如不服本判決，應於判決送達後十日內，向本院提出上訴狀。\n                                      書記官  顏宗貝\n中    華    民    國      九十一      年      九      月      十八      日\n附錄本判決論罪之法條：\n刑法第二百十六條：\n  行使第二百十條至第二百十五條之文書者，依偽造、變造文書或登載不實事項或使\n  登載不實事項之規定處斷。\n刑法第二百十條：\n  偽造、變造私文書，足以生損害於公眾或他人者，處五年以下有期徒刑。\n刑法第三百三十九條第一項：\n  意圖為自己或第三人不法之所有，以詐術使人將本人或第三人之物交付者，處五年\n  以下有期徒刑、拘役或科或併科一千元以下罰金。\n",
  "structure": {
    "main": "甲○○連續行使偽造私文書，足以生損害他人，處有期徒刑陸月，如易科罰金，以參\n佰元折算壹日。緩刑貳年。",
    "fact": "一、甲○○係設於高雄縣鳥松鄉○○路二五之二八號Ｄ棟立笠鋼鐵企業有限公司（下\n    稱立笠公司）之實際負責人，因公司財務發生危機，急需借款應急，向柯聰發借\n    用發票人為柯聰發，付款人為彰化銀行東高雄分行，發票日期分別為民國八十九\n    年十二月二十五日及九十年一月十日，票面金額分別為新臺幣（下同）五十五萬\n    二千七百八十元、二十萬元之支票二紙，並由立笠公司於該支票二紙背面背書，\n    惟因銀行要求須另有他公司背書以增加信用度，甲○○為能順利以該支票二紙向\n    銀行票貼借款，竟基於意圖為自己不法所有、行使偽造私文書之概括犯意，明知\n    未經長浚企業有限公司（下稱長浚公司）之同意，於八十九年底，在立笠公司，\n    持長浚公司留存於立笠公司作為承攬工程報價之用之「長浚企業有限公司」及該\n    公司名義負責人「宋靜」之印章（即俗稱大小章）各一枚，於該支票二紙背面背\n    書欄內盜蓋「長浚企業有限公司」、「宋靜」之印文各二枚背書於上，並先後於\n    不詳時間持該支票二紙向中國信託商業銀行股份有限公司（下稱中國信託商業銀\n    行）票貼借款而行使之，使中國信託商業銀行不疑有他，陷於錯誤而先後於八十\n    九年十月十二日、同年月十六日交付四十七萬三千三百三十元、十五萬九千八百\n    九十元，共計六十三萬三千二百二十元，足以生損害於長浚公司、宋靜及中國信\n    託商業銀行。嗣經中國信託商業銀行屆期提示遭以存款不足為由退票，中國信託\n    商業銀行乃向本院聲請支付命令，長浚公司於法定期間內聲明異議，始知上情。\n二、案經長浚企業有限公司訴由臺灣高雄地方法院檢察署檢察官偵查起訴。",
    "reason": "一、右揭犯罪事實，業據被告甲○○坦承不諱，核與告訴代表人宋靜指述之情節相符\n    ，並有中國信託公司民事號支付命令聲請狀、臺灣高雄地方法院九十年促字第五\n    一三六號支付命令、錄音帶譯文各一份附卷足憑，是被告自白與事實相符，本件\n    事證明確，被告犯行洵堪認定。\n二、核被告所為，係犯刑法第三百三十九條第一項之詐欺取財罪、第二百十六條、第\n    二百十條之行使偽造私文書罪。其盜用印章之行為為偽造私文書行為之階段行為\n    ；偽造私文書之低度行為又為行使偽造私文書之高度行為吸收，均不另論擬。被\n    告先後多次犯行，時間緊接，所犯構成要件相同，顯係基於概括犯意為之，為連\n    續犯，應依刑法第五十六條論以一罪，並加重其刑。被告所犯上開兩罪間，有方\n    法結果之牽連關係，為牽連犯，應從一重行使偽造私文書罪處斷。爰審酌被告犯\n    罪之動機、目的、手段、犯罪所生之損害，及犯後坦承犯行等一切情狀，量處如\n    主文所示之刑。按刑法第四十一條，已於九十年一月十日修正公布，並於同月十\n    二日施行，其第一項前段規定為「犯最重本刑為五年以下有期徒刑之罪，而受六\n    月以下有期徒刑或拘役之宣告，因身體、教育、職業或家庭之關係或因其他正當\n    事由，執行顯有困難者，得以一元以上三元以下折算一日，易科罰金。」，本件\n    被告犯罪後，上開犯行，已變更屬得易科罰金之罪，依最高法院二十四年七月刑\n    庭總會決議，易科罰金之事項，應依刑法第二條第一項之規定，適用修正後之刑\n    法第四十一條之新法，本件爰諭知易科罰金之折算標準，以資懲儆。又被告前未\n    曾受有期徒刑以上刑之宣告，此有臺灣高雄地方法院檢察署刑案資料查註記錄表\n    附卷可稽，因一時失慮，偶罹刑典，事後已坦承犯行，深具悔意，經此刑之宣告\n    後，應知警惕而無再犯之虞，本院因認暫不執行其刑為當，予以宣告緩刑二年，\n    用啟自新。\n據上論斷，應依刑事訴訟法第二百九十九條第一項前段，刑法第二條第一項前段、第\n五十六條、第二百十六條、第二百十條、第三百三十九條第一項、第五十五條、第四\n十一條第一項、第七十四條第一款，罰金罰鍰提高標準條例第一條前段、第二條，判\n決如主文。\n本案經檢察官劉昀到庭執行職務。\n中    華    民    國      九十一      年      九      月      十八      日\n                                  臺灣高雄地方法院刑事庭\n                                      法  官  何悅芳\n右正本證明與原本無異。\n如不服本判決，應於判決送達後十日內，向本院提出上訴狀。\n                                      書記官  顏宗貝"
  },
  "search": "臺灣高雄地方法院刑事判決九十一年度訴字第一六一二號公訴人臺灣高雄地方法院檢察署檢察官被告甲○○選任辯護人吳建勛律師游雪莉律師陳慧錚律師右列被告因偽造文書等案件，經檢察官提起公訴（九十年度偵字第一０二三二號），本院判決如左：主文甲○○連續行使偽造私文書，足以生損害他人，處有期徒刑陸月，如易科罰金，以參佰元折算壹日。緩刑貳年。事實一、甲○○係設於高雄縣鳥松鄉○○路二五之二八號Ｄ棟立笠鋼鐵企業有限公司（下稱立笠公司）之實際負責人，因公司財務發生危機，急需借款應急，向柯聰發借用發票人為柯聰發，付款人為彰化銀行東高雄分行，發票日期分別為民國八十九年十二月二十五日及九十年一月十日，票面金額分別為新臺幣（下同）五十五萬二千七百八十元、二十萬元之支票二紙，並由立笠公司於該支票二紙背面背書，惟因銀行要求須另有他公司背書以增加信用度，甲○○為能順利以該支票二紙向銀行票貼借款，竟基於意圖為自己不法所有、行使偽造私文書之概括犯意，明知未經長浚企業有限公司（下稱長浚公司）之同意，於八十九年底，在立笠公司，持長浚公司留存於立笠公司作為承攬工程報價之用之「長浚企業有限公司」及該公司名義負責人「宋靜」之印章（即俗稱大小章）各一枚，於該支票二紙背面背書欄內盜蓋「長浚企業有限公司」、「宋靜」之印文各二枚背書於上，並先後於不詳時間持該支票二紙向中國信託商業銀行股份有限公司（下稱中國信託商業銀行）票貼借款而行使之，使中國信託商業銀行不疑有他，陷於錯誤而先後於八十九年十月十二日、同年月十六日交付四十七萬三千三百三十元、十五萬九千八百九十元，共計六十三萬三千二百二十元，足以生損害於長浚公司、宋靜及中國信託商業銀行。嗣經中國信託商業銀行屆期提示遭以存款不足為由退票，中國信託商業銀行乃向本院聲請支付命令，長浚公司於法定期間內聲明異議，始知上情。二、案經長浚企業有限公司訴由臺灣高雄地方法院檢察署檢察官偵查起訴。理由一、右揭犯罪事實，業據被告甲○○坦承不諱，核與告訴代表人宋靜指述之情節相符，並有中國信託公司民事號支付命令聲請狀、臺灣高雄地方法院九十年促字第五一三六號支付命令、錄音帶譯文各一份附卷足憑，是被告自白與事實相符，本件事證明確，被告犯行洵堪認定。二、核被告所為，係犯刑法第三百三十九條第一項之詐欺取財罪、第二百十六條、第二百十條之行使偽造私文書罪。其盜用印章之行為為偽造私文書行為之階段行為；偽造私文書之低度行為又為行使偽造私文書之高度行為吸收，均不另論擬。被告先後多次犯行，時間緊接，所犯構成要件相同，顯係基於概括犯意為之，為連續犯，應依刑法第五十六條論以一罪，並加重其刑。被告所犯上開兩罪間，有方法結果之牽連關係，為牽連犯，應從一重行使偽造私文書罪處斷。爰審酌被告犯罪之動機、目的、手段、犯罪所生之損害，及犯後坦承犯行等一切情狀，量處如主文所示之刑。按刑法第四十一條，已於九十年一月十日修正公布，並於同月十二日施行，其第一項前段規定為「犯最重本刑為五年以下有期徒刑之罪，而受六月以下有期徒刑或拘役之宣告，因身體、教育、職業或家庭之關係或因其他正當事由，執行顯有困難者，得以一元以上三元以下折算一日，易科罰金。」，本件被告犯罪後，上開犯行，已變更屬得易科罰金之罪，依最高法院二十四年七月刑庭總會決議，易科罰金之事項，應依刑法第二條第一項之規定，適用修正後之刑法第四十一條之新法，本件爰諭知易科罰金之折算標準，以資懲儆。又被告前未曾受有期徒刑以上刑之宣告，此有臺灣高雄地方法院檢察署刑案資料查註記錄表附卷可稽，因一時失慮，偶罹刑典，事後已坦承犯行，深具悔意，經此刑之宣告後，應知警惕而無再犯之虞，本院因認暫不執行其刑為當，予以宣告緩刑二年，用啟自新。據上論斷，應依刑事訴訟法第二百九十九條第一項前段，刑法第二條第一項前段、第五十六條、第二百十六條、第二百十條、第三百三十九條第一項、第五十五條、第四十一條第一項、第七十四條第一款，罰金罰鍰提高標準條例第一條前段、第二條，判決如主文。本案經檢察官劉昀到庭執行職務。中華民國九十一年九月十八日臺灣高雄地方法院刑事庭法官何悅芳右正本證明與原本無異。如不服本判決，應於判決送達後十日內，向本院提出上訴狀。書記官顏宗貝中華民國九十一年九月十八日附錄本判決論罪之法條：刑法第二百十六條：行使第二百十條至第二百十五條之文書者，依偽造、變造文書或登載不實事項或使登載不實事項之規定處斷。刑法第二百十條：偽造、變造私文書，足以生損害於公眾或他人者，處五年以下有期徒刑。刑法第三百三十九條第一項：意圖為自己或第三人不法之所有，以詐術使人將本人或第三人之物交付者，處五年以下有期徒刑、拘役或科或併科一千元以下罰金。",
  "characters": {
    "judges": [
      "何悅芳"
    ],
    "prosecutors": [
      "劉昀"
    ],
    "lawyers": [
      "吳建勛",
      "游雪莉",
      "陳慧錚"
    ],
    "clerks": [
      "顏宗貝"
    ],
    "plaintiffs": [

    ],
    "defendants": [
      "甲○○"
    ],
    "prosecutor_office": [
      "臺灣高雄地方法院檢察署檢察官"
    ],
    "creditors": [

    ],
    "debtors": [

    ],
    "judicial_associate_officer": [

    ]
  },
  "adjudged_at": "2002-09-18",
  "created_at": "2016-02-04 17:03:14",
  "updated_at": "2016-02-04 17:03:14"
}