{
  "identify": "MLD-100-苗簡-258-20111011-1",
  "court": {
    "name": "臺灣苗栗地方法院",
    "code": "MLD"
  },
  "division": {
    "name": "民事",
    "code": "V"
  },
  "year": 100,
  "word": "苗簡",
  "number": "258",
  "jcheck": "1",
  "reason": "清償借款",
  "content": "臺灣苗栗地方法院民事簡易判決        100年度苗簡字第258號\n原      告  黎維全\n訴訟代理人  蕭秀源\n被      告  譚騰祥\n上列當事人間請求清償借款事件，本院於民國100 年9 月27日言\n詞辯論終結，判決如下：\n    主  文\n被告應給付原告新臺幣參萬壹仟元，及自民國一００年四月七日\n起至清償日止，按年息百分之五計算之利息。\n原告其餘之訴駁回。\n訴訟費用新臺幣參佰壹拾柒元由被告負擔，其餘由原告負擔。\n本判決第一項得假執行。\n    事實及理由\n一、原告起訴主張：被告分別於民國91年8 月27日、91年9 月20\n    日、91年9 月30日向原告借款新臺幣（下同）40,000元、20\n    ,000元及35,000元，共計95,000元，上開借款金額原告均自\n    原告所有兆豐國際商業銀行（原中國國際商業銀行）頭份分\n    行活期儲蓄存款帳戶提領現金交予被告，被告則於91年12月\n    25日簽發如卷第32頁所示，票號為TH0000000 號，票面金額\n    為100,000 元，到期日為92年4 月5 日並免除作成拒絕證書\n    之本票一紙（以下簡稱系爭本票）交付被告，以擔保上開借\n    款及5,000 元利息之清償；嗣因被告無法清償上開借款，另\n    於92年4 月7 日簽發臺灣中小企業銀行頭份分行，票號為AY\n    0000000 號，票面金額100,000 元之支票（以下簡稱系爭支\n    票）予原告，詎該支票屆期提示亦未獲兌現。又被告經由原\n    告介紹，另向訴外人黃郁梓借款31,000元，並簽發票號為AY\n    0000000 號，發票日為92年5 月15日，票面金額為31,000元\n    之支票以為擔保，詎上開支票屆期提示亦遭退票，訴外人黃\n    郁梓嗣將其對被告之債權移轉與原告，並以100 年8 月9 日\n    之民事補充理由狀繕本送達被告作為債權讓與通知之意思表\n    示。被告迄今均未清償上開借款，雖經原告屢次催討，未獲\n    置理。為此，爰依消費借貸及債權讓與之法律關係，訴請被\n    告給付等語。並聲明：被告應給付原告131,000 元，及自92\n    年5 月7 日起至清償日止，按年息百分之5 計算之利息。\n二、被告則以：確實曾向訴外人黃郁梓借款31,000元，並簽發票\n    號為AY0000000 號之支票以為擔保，該支票已遭退票。另其\n    簽發系爭本票係為擔保上開向黃郁梓借款之清償，被告實際\n    僅收受訴外人黃郁梓交付之31,000元借款金額，並未收到原\n    告交付之其他金額。原告所執系爭支票雖亦係被告所簽發，\n    惟簽發系爭支票係用以向原告調現，原告並未將調借之100,\n    000 元交付被告，亦未將系爭支票返還被告。原告應提出其\n    於何時、何地交付該100,000 元予被告之證據，又系爭本票\n    與支票之票據請求權均已罹於時效，原告之請求為無理由等\n    語置辯。並聲明：原告之訴駁回。\n三、本件原告所執系爭本票及系爭支票均為被告所簽發。又被告\n    經由原告介紹，曾向訴外人黃郁梓借款31,000元，並簽發票\n    號為AY0000000 號，發票日為92年5 月15日，票面金額為31\n    ,000元之支票以為擔保，上開支票屆期提示遭退票，被告迄\n    今未清償上開借款，而訴外人黃郁梓嗣將其對被告之債權移\n    轉與原告，並經原告於100 年8 月9 日以民事補充理由狀繕\n    本送達被告作為債權讓與通知之意思表示等情，為兩造所不\n    爭執，並有原告提出之債權讓與契約書及退票理由單（詳卷\n    第30、34頁）等件附卷可憑，自堪信為真實。\n四、按票據為無因證券，票據債權人就其取得票據之原因，固不\n    負證明之責任，惟執票人如主張票據係發票人向其借款而簽\n    發交付，而發票人抗辯未收受借款，消費借貸並未成立，則\n    就借款已交付之事實，自應由執票人負舉證責任，最高法院\n    著有89年度台上字第85號裁判意旨可參。故主張消費借貸關\n    係存在者，自應就業已踐行前揭要物行為乙節，即就借款交\n    付之事實，負舉證證明之責。本件原告主張被告分別於91年\n    8 月27日、91年9 月20日及91 年9月30日向原告借款40,000\n    元、20,000元及35,000元，共計95,000元，而被告則於91年\n    12月25日簽發系爭本票交付被告，以擔保上開借款及5,000\n    元利息之清償之事實，固據提出兆豐國際商業銀行活期儲蓄\n    存款存摺、系爭本票及票貼憑據（詳卷第31至33頁）等件為\n    證，惟被告既以其未收受該100,000 元等語置辯，則依前開\n    說明，原告自應就其分別於91年8 月27日、91年9 月20日及\n    91年9 月30日，分別交付借款金額40,000元、20,000 元 及\n    35,000元予被告之事實，負舉證證明之責。經查，原告就其\n    於上開日期分別交付被告前開借款金額之事實，雖據提出兆\n    豐國際商業銀行活期儲蓄存款存摺為證，惟據該活期儲蓄存\n    款存摺紀錄僅能證明原告分別於91年8 月27日、91年9 月20\n    日及91年9 月30日自該活期儲蓄帳戶提款40,000元、20,000\n    元及35,000元之事實，尚難僅憑該提款記錄，即謂原告於上\n    開日期曾分別交付前開借款金額予被告。另依原告訴訟代理\n    人蕭秀源到庭所稱原告曾持被告簽發之系爭支票向伊調借現\n    金10萬元，後來系爭支票經其提示遭退票未獲付款，由原告\n    給付伊10萬元換回系爭支票等語（詳本院卷第40、41頁），\n    亦僅能證明原告有向蕭秀源調借現金之事實，不足以證明原\n    告曾交付系爭支票所示借款金額10萬元予被告之事實。此外\n    ，原告又迄未能就此另舉證以實其說，則原告主張被告向其\n    借款共計95, 000 元云云，即無足採。\n五、次按稱消費借貸者，謂當事人一方移轉金錢或其他代替物之\n    所有權於他方，而約定他方以種類、品質、數量相同之物返\n    還之契約，民法第474 條第1 項定有明文。另按「債權之讓\n    與，依民法第297 條規定，非經讓與人或受讓人通知債務人\n    不生效力，此項通知不過觀念通知，使債務人知有債權移轉\n    之事實，免誤向原債權人清償而已」、「債權之讓與，依民\n    法第297 條第1 項之規定，雖須經讓與人或受讓人通知債務\n    人始生效力，但不以債務人之承諾為必要，而讓與之通知，\n    為通知債權讓與事實之行為，原得以言詞或文書為之，不需\n    何等之方式，故讓與人與受讓人間成立債權讓與契約時，債\n    權即移轉於受讓人，除法律另有規定外，如經讓與人或受讓\n    人通知債務人，即生債權移轉之效力」，最高法院39年台上\n    字第448 號判例、42年台上字第626 號判例意旨可資參照。\n    查訴外人黃郁梓將系爭31,000元借款返還請求權讓與原告後\n    ，訴外人黃郁梓或原告固未立即通知被告，惟原告對被告提\n    起本件訴訟時，於民事補充理由狀內既已對被告表明受讓上\n    開借款債權之事實，則足使被告知有債權讓與情事，應認兼\n    有通知效力，揆諸前開判例意旨，系爭借款債權讓與於原告\n    通知被告後，不待被告同意即生效力，被告對原告即負有返\n    還系爭31,000元借款之義務。\n六、末按給付有確定期限者，債務人自期限屆滿時起，負遲延責\n    任；給付無確定期限者，債務人於債權人得請求給付時，經\n    其催告而未為給付，自受催告時起，負遲延責任。其經債權\n    人起訴而送達訴狀，或依督促程序送達支付命令，或為其他\n    相類之行為者，與催告有同一之效力；前項催告定有期限者\n    ，債務人自期限屆滿時起負遲延責任，民法第229 條訂有明\n    文。又遲延之債務，以支付金錢為標的者，債權人得請求依\n    法定利率計算之遲延利息；而應付利息之債務，其利率未經\n    約定，亦無法律可據者，週年利率為百分之5 ，亦為同法第\n    233 條第1 項本文及第203 條所明定。經查，本件被告自訴\n    外人黃郁梓將系爭31,000元借款返還請求權讓與原告後，對\n    原告即負有返還上開借款之義務，已如前述。而本件兩造就\n    31,000元之借款並無約定確定清償期限，是被告對原告之給\n    付義務，應自原告向本院聲請對被告核發支付命令，該支付\n    命令送達翌日即100 年4 月7 日起負遲延責任。\n七、從而，原告本於消費借貸及債權讓與之法律關係，請求被告\n    應給付原告31,000元，及自100 年4 月7 日起至清償日止，\n    按年息百分之5 計算之利息，為有理由，應予准許。原告逾\n    此範圍之請求，則屬無據，不應准許。\n八、本件係依民事訴訟法第427 條第1 項規定適用簡易程序所為\n    被告部分敗訴之判決，應依同法第389 條第1 項第3 款規定\n    ，依職權宣告原告勝訴部分得假執行。\n九、因本案事證已臻明確，兩造其餘主張陳述及所提之證據，均\n    毋庸再予審酌，附此敘明。\n十、訴訟費用負擔之依據：民事訴訟法第79條。\n中    華    民    國  100     年    10    月    11    日\n              苗栗簡易庭法  官  王萬金\n以上正本係照原本作成\n如對本判決上訴，須於判決送達後20日內向本院提出上訴狀。\n如委任律師提起上訴者，應一併繳納上訴審裁判費。\n                        書記官  劉麗美\n中    華    民    國  100     年    10    月    11    日",
  "structure": {
    "main": "被告應給付原告新臺幣參萬壹仟元，及自民國一００年四月七日\n起至清償日止，按年息百分之五計算之利息。\n原告其餘之訴駁回。\n訴訟費用新臺幣參佰壹拾柒元由被告負擔，其餘由原告負擔。\n本判決第一項得假執行。",
    "fact": "一、原告起訴主張：被告分別於民國91年8 月27日、91年9 月20\n    日、91年9 月30日向原告借款新臺幣（下同）40,000元、20\n    ,000元及35,000元，共計95,000元，上開借款金額原告均自\n    原告所有兆豐國際商業銀行（原中國國際商業銀行）頭份分\n    行活期儲蓄存款帳戶提領現金交予被告，被告則於91年12月\n    25日簽發如卷第32頁所示，票號為TH0000000 號，票面金額\n    為100,000 元，到期日為92年4 月5 日並免除作成拒絕證書\n    之本票一紙（以下簡稱系爭本票）交付被告，以擔保上開借\n    款及5,000 元利息之清償；嗣因被告無法清償上開借款，另\n    於92年4 月7 日簽發臺灣中小企業銀行頭份分行，票號為AY\n    0000000 號，票面金額100,000 元之支票（以下簡稱系爭支\n    票）予原告，詎該支票屆期提示亦未獲兌現。又被告經由原\n    告介紹，另向訴外人黃郁梓借款31,000元，並簽發票號為AY\n    0000000 號，發票日為92年5 月15日，票面金額為31,000元\n    之支票以為擔保，詎上開支票屆期提示亦遭退票，訴外人黃\n    郁梓嗣將其對被告之債權移轉與原告，並以100 年8 月9 日\n    之民事補充理由狀繕本送達被告作為債權讓與通知之意思表\n    示。被告迄今均未清償上開借款，雖經原告屢次催討，未獲\n    置理。為此，爰依消費借貸及債權讓與之法律關係，訴請被\n    告給付等語。並聲明：被告應給付原告131,000 元，及自92\n    年5 月7 日起至清償日止，按年息百分之5 計算之利息。\n二、被告則以：確實曾向訴外人黃郁梓借款31,000元，並簽發票\n    號為AY0000000 號之支票以為擔保，該支票已遭退票。另其\n    簽發系爭本票係為擔保上開向黃郁梓借款之清償，被告實際\n    僅收受訴外人黃郁梓交付之31,000元借款金額，並未收到原\n    告交付之其他金額。原告所執系爭支票雖亦係被告所簽發，\n    惟簽發系爭支票係用以向原告調現，原告並未將調借之100,\n    000 元交付被告，亦未將系爭支票返還被告。原告應提出其\n    於何時、何地交付該100,000 元予被告之證據，又系爭本票\n    與支票之票據請求權均已罹於時效，原告之請求為無理由等\n    語置辯。並聲明：原告之訴駁回。\n三、本件原告所執系爭本票及系爭支票均為被告所簽發。又被告\n    經由原告介紹，曾向訴外人黃郁梓借款31,000元，並簽發票\n    號為AY0000000 號，發票日為92年5 月15日，票面金額為31\n    ,000元之支票以為擔保，上開支票屆期提示遭退票，被告迄\n    今未清償上開借款，而訴外人黃郁梓嗣將其對被告之債權移\n    轉與原告，並經原告於100 年8 月9 日以民事補充理由狀繕\n    本送達被告作為債權讓與通知之意思表示等情，為兩造所不\n    爭執，並有原告提出之債權讓與契約書及退票理由單（詳卷\n    第30、34頁）等件附卷可憑，自堪信為真實。\n四、按票據為無因證券，票據債權人就其取得票據之原因，固不\n    負證明之責任，惟執票人如主張票據係發票人向其借款而簽\n    發交付，而發票人抗辯未收受借款，消費借貸並未成立，則\n    就借款已交付之事實，自應由執票人負舉證責任，最高法院\n    著有89年度台上字第85號裁判意旨可參。故主張消費借貸關\n    係存在者，自應就業已踐行前揭要物行為乙節，即就借款交\n    付之事實，負舉證證明之責。本件原告主張被告分別於91年\n    8 月27日、91年9 月20日及91 年9月30日向原告借款40,000\n    元、20,000元及35,000元，共計95,000元，而被告則於91年\n    12月25日簽發系爭本票交付被告，以擔保上開借款及5,000\n    元利息之清償之事實，固據提出兆豐國際商業銀行活期儲蓄\n    存款存摺、系爭本票及票貼憑據（詳卷第31至33頁）等件為\n    證，惟被告既以其未收受該100,000 元等語置辯，則依前開\n    說明，原告自應就其分別於91年8 月27日、91年9 月20日及\n    91年9 月30日，分別交付借款金額40,000元、20,000 元 及\n    35,000元予被告之事實，負舉證證明之責。經查，原告就其\n    於上開日期分別交付被告前開借款金額之事實，雖據提出兆\n    豐國際商業銀行活期儲蓄存款存摺為證，惟據該活期儲蓄存\n    款存摺紀錄僅能證明原告分別於91年8 月27日、91年9 月20\n    日及91年9 月30日自該活期儲蓄帳戶提款40,000元、20,000\n    元及35,000元之事實，尚難僅憑該提款記錄，即謂原告於上\n    開日期曾分別交付前開借款金額予被告。另依原告訴訟代理\n    人蕭秀源到庭所稱原告曾持被告簽發之系爭支票向伊調借現\n    金10萬元，後來系爭支票經其提示遭退票未獲付款，由原告\n    給付伊10萬元換回系爭支票等語（詳本院卷第40、41頁），\n    亦僅能證明原告有向蕭秀源調借現金之事實，不足以證明原\n    告曾交付系爭支票所示借款金額10萬元予被告之事實。此外\n    ，原告又迄未能就此另舉證以實其說，則原告主張被告向其\n    借款共計95, 000 元云云，即無足採。\n五、次按稱消費借貸者，謂當事人一方移轉金錢或其他代替物之\n    所有權於他方，而約定他方以種類、品質、數量相同之物返\n    還之契約，民法第474 條第1 項定有明文。另按「債權之讓\n    與，依民法第297 條規定，非經讓與人或受讓人通知債務人\n    不生效力，此項通知不過觀念通知，使債務人知有債權移轉\n    之事實，免誤向原債權人清償而已」、「債權之讓與，依民\n    法第297 條第1 項之規定，雖須經讓與人或受讓人通知債務\n    人始生效力，但不以債務人之承諾為必要，而讓與之通知，\n    為通知債權讓與事實之行為，原得以言詞或文書為之，不需\n    何等之方式，故讓與人與受讓人間成立債權讓與契約時，債\n    權即移轉於受讓人，除法律另有規定外，如經讓與人或受讓\n    人通知債務人，即生債權移轉之效力」，最高法院39年台上\n    字第448 號判例、42年台上字第626 號判例意旨可資參照。\n    查訴外人黃郁梓將系爭31,000元借款返還請求權讓與原告後\n    ，訴外人黃郁梓或原告固未立即通知被告，惟原告對被告提\n    起本件訴訟時，於民事補充理由狀內既已對被告表明受讓上\n    開借款債權之事實，則足使被告知有債權讓與情事，應認兼\n    有通知效力，揆諸前開判例意旨，系爭借款債權讓與於原告\n    通知被告後，不待被告同意即生效力，被告對原告即負有返\n    還系爭31,000元借款之義務。\n六、末按給付有確定期限者，債務人自期限屆滿時起，負遲延責\n    任；給付無確定期限者，債務人於債權人得請求給付時，經\n    其催告而未為給付，自受催告時起，負遲延責任。其經債權\n    人起訴而送達訴狀，或依督促程序送達支付命令，或為其他\n    相類之行為者，與催告有同一之效力；前項催告定有期限者\n    ，債務人自期限屆滿時起負遲延責任，民法第229 條訂有明\n    文。又遲延之債務，以支付金錢為標的者，債權人得請求依\n    法定利率計算之遲延利息；而應付利息之債務，其利率未經\n    約定，亦無法律可據者，週年利率為百分之5 ，亦為同法第\n    233 條第1 項本文及第203 條所明定。經查，本件被告自訴\n    外人黃郁梓將系爭31,000元借款返還請求權讓與原告後，對\n    原告即負有返還上開借款之義務，已如前述。而本件兩造就\n    31,000元之借款並無約定確定清償期限，是被告對原告之給\n    付義務，應自原告向本院聲請對被告核發支付命令，該支付\n    命令送達翌日即100 年4 月7 日起負遲延責任。\n七、從而，原告本於消費借貸及債權讓與之法律關係，請求被告\n    應給付原告31,000元，及自100 年4 月7 日起至清償日止，\n    按年息百分之5 計算之利息，為有理由，應予准許。原告逾\n    此範圍之請求，則屬無據，不應准許。\n八、本件係依民事訴訟法第427 條第1 項規定適用簡易程序所為\n    被告部分敗訴之判決，應依同法第389 條第1 項第3 款規定\n    ，依職權宣告原告勝訴部分得假執行。\n九、因本案事證已臻明確，兩造其餘主張陳述及所提之證據，均\n    毋庸再予審酌，附此敘明。\n十、訴訟費用負擔之依據：民事訴訟法第79條。",
    "reason": "一、原告起訴主張：被告分別於民國91年8 月27日、91年9 月20\n    日、91年9 月30日向原告借款新臺幣（下同）40,000元、20\n    ,000元及35,000元，共計95,000元，上開借款金額原告均自\n    原告所有兆豐國際商業銀行（原中國國際商業銀行）頭份分\n    行活期儲蓄存款帳戶提領現金交予被告，被告則於91年12月\n    25日簽發如卷第32頁所示，票號為TH0000000 號，票面金額\n    為100,000 元，到期日為92年4 月5 日並免除作成拒絕證書\n    之本票一紙（以下簡稱系爭本票）交付被告，以擔保上開借\n    款及5,000 元利息之清償；嗣因被告無法清償上開借款，另\n    於92年4 月7 日簽發臺灣中小企業銀行頭份分行，票號為AY\n    0000000 號，票面金額100,000 元之支票（以下簡稱系爭支\n    票）予原告，詎該支票屆期提示亦未獲兌現。又被告經由原\n    告介紹，另向訴外人黃郁梓借款31,000元，並簽發票號為AY\n    0000000 號，發票日為92年5 月15日，票面金額為31,000元\n    之支票以為擔保，詎上開支票屆期提示亦遭退票，訴外人黃\n    郁梓嗣將其對被告之債權移轉與原告，並以100 年8 月9 日\n    之民事補充理由狀繕本送達被告作為債權讓與通知之意思表\n    示。被告迄今均未清償上開借款，雖經原告屢次催討，未獲\n    置理。為此，爰依消費借貸及債權讓與之法律關係，訴請被\n    告給付等語。並聲明：被告應給付原告131,000 元，及自92\n    年5 月7 日起至清償日止，按年息百分之5 計算之利息。\n二、被告則以：確實曾向訴外人黃郁梓借款31,000元，並簽發票\n    號為AY0000000 號之支票以為擔保，該支票已遭退票。另其\n    簽發系爭本票係為擔保上開向黃郁梓借款之清償，被告實際\n    僅收受訴外人黃郁梓交付之31,000元借款金額，並未收到原\n    告交付之其他金額。原告所執系爭支票雖亦係被告所簽發，\n    惟簽發系爭支票係用以向原告調現，原告並未將調借之100,\n    000 元交付被告，亦未將系爭支票返還被告。原告應提出其\n    於何時、何地交付該100,000 元予被告之證據，又系爭本票\n    與支票之票據請求權均已罹於時效，原告之請求為無理由等\n    語置辯。並聲明：原告之訴駁回。\n三、本件原告所執系爭本票及系爭支票均為被告所簽發。又被告\n    經由原告介紹，曾向訴外人黃郁梓借款31,000元，並簽發票\n    號為AY0000000 號，發票日為92年5 月15日，票面金額為31\n    ,000元之支票以為擔保，上開支票屆期提示遭退票，被告迄\n    今未清償上開借款，而訴外人黃郁梓嗣將其對被告之債權移\n    轉與原告，並經原告於100 年8 月9 日以民事補充理由狀繕\n    本送達被告作為債權讓與通知之意思表示等情，為兩造所不\n    爭執，並有原告提出之債權讓與契約書及退票理由單（詳卷\n    第30、34頁）等件附卷可憑，自堪信為真實。\n四、按票據為無因證券，票據債權人就其取得票據之原因，固不\n    負證明之責任，惟執票人如主張票據係發票人向其借款而簽\n    發交付，而發票人抗辯未收受借款，消費借貸並未成立，則\n    就借款已交付之事實，自應由執票人負舉證責任，最高法院\n    著有89年度台上字第85號裁判意旨可參。故主張消費借貸關\n    係存在者，自應就業已踐行前揭要物行為乙節，即就借款交\n    付之事實，負舉證證明之責。本件原告主張被告分別於91年\n    8 月27日、91年9 月20日及91 年9月30日向原告借款40,000\n    元、20,000元及35,000元，共計95,000元，而被告則於91年\n    12月25日簽發系爭本票交付被告，以擔保上開借款及5,000\n    元利息之清償之事實，固據提出兆豐國際商業銀行活期儲蓄\n    存款存摺、系爭本票及票貼憑據（詳卷第31至33頁）等件為\n    證，惟被告既以其未收受該100,000 元等語置辯，則依前開\n    說明，原告自應就其分別於91年8 月27日、91年9 月20日及\n    91年9 月30日，分別交付借款金額40,000元、20,000 元 及\n    35,000元予被告之事實，負舉證證明之責。經查，原告就其\n    於上開日期分別交付被告前開借款金額之事實，雖據提出兆\n    豐國際商業銀行活期儲蓄存款存摺為證，惟據該活期儲蓄存\n    款存摺紀錄僅能證明原告分別於91年8 月27日、91年9 月20\n    日及91年9 月30日自該活期儲蓄帳戶提款40,000元、20,000\n    元及35,000元之事實，尚難僅憑該提款記錄，即謂原告於上\n    開日期曾分別交付前開借款金額予被告。另依原告訴訟代理\n    人蕭秀源到庭所稱原告曾持被告簽發之系爭支票向伊調借現\n    金10萬元，後來系爭支票經其提示遭退票未獲付款，由原告\n    給付伊10萬元換回系爭支票等語（詳本院卷第40、41頁），\n    亦僅能證明原告有向蕭秀源調借現金之事實，不足以證明原\n    告曾交付系爭支票所示借款金額10萬元予被告之事實。此外\n    ，原告又迄未能就此另舉證以實其說，則原告主張被告向其\n    借款共計95, 000 元云云，即無足採。\n五、次按稱消費借貸者，謂當事人一方移轉金錢或其他代替物之\n    所有權於他方，而約定他方以種類、品質、數量相同之物返\n    還之契約，民法第474 條第1 項定有明文。另按「債權之讓\n    與，依民法第297 條規定，非經讓與人或受讓人通知債務人\n    不生效力，此項通知不過觀念通知，使債務人知有債權移轉\n    之事實，免誤向原債權人清償而已」、「債權之讓與，依民\n    法第297 條第1 項之規定，雖須經讓與人或受讓人通知債務\n    人始生效力，但不以債務人之承諾為必要，而讓與之通知，\n    為通知債權讓與事實之行為，原得以言詞或文書為之，不需\n    何等之方式，故讓與人與受讓人間成立債權讓與契約時，債\n    權即移轉於受讓人，除法律另有規定外，如經讓與人或受讓\n    人通知債務人，即生債權移轉之效力」，最高法院39年台上\n    字第448 號判例、42年台上字第626 號判例意旨可資參照。\n    查訴外人黃郁梓將系爭31,000元借款返還請求權讓與原告後\n    ，訴外人黃郁梓或原告固未立即通知被告，惟原告對被告提\n    起本件訴訟時，於民事補充理由狀內既已對被告表明受讓上\n    開借款債權之事實，則足使被告知有債權讓與情事，應認兼\n    有通知效力，揆諸前開判例意旨，系爭借款債權讓與於原告\n    通知被告後，不待被告同意即生效力，被告對原告即負有返\n    還系爭31,000元借款之義務。\n六、末按給付有確定期限者，債務人自期限屆滿時起，負遲延責\n    任；給付無確定期限者，債務人於債權人得請求給付時，經\n    其催告而未為給付，自受催告時起，負遲延責任。其經債權\n    人起訴而送達訴狀，或依督促程序送達支付命令，或為其他\n    相類之行為者，與催告有同一之效力；前項催告定有期限者\n    ，債務人自期限屆滿時起負遲延責任，民法第229 條訂有明\n    文。又遲延之債務，以支付金錢為標的者，債權人得請求依\n    法定利率計算之遲延利息；而應付利息之債務，其利率未經\n    約定，亦無法律可據者，週年利率為百分之5 ，亦為同法第\n    233 條第1 項本文及第203 條所明定。經查，本件被告自訴\n    外人黃郁梓將系爭31,000元借款返還請求權讓與原告後，對\n    原告即負有返還上開借款之義務，已如前述。而本件兩造就\n    31,000元之借款並無約定確定清償期限，是被告對原告之給\n    付義務，應自原告向本院聲請對被告核發支付命令，該支付\n    命令送達翌日即100 年4 月7 日起負遲延責任。\n七、從而，原告本於消費借貸及債權讓與之法律關係，請求被告\n    應給付原告31,000元，及自100 年4 月7 日起至清償日止，\n    按年息百分之5 計算之利息，為有理由，應予准許。原告逾\n    此範圍之請求，則屬無據，不應准許。\n八、本件係依民事訴訟法第427 條第1 項規定適用簡易程序所為\n    被告部分敗訴之判決，應依同法第389 條第1 項第3 款規定\n    ，依職權宣告原告勝訴部分得假執行。\n九、因本案事證已臻明確，兩造其餘主張陳述及所提之證據，均\n    毋庸再予審酌，附此敘明。\n十、訴訟費用負擔之依據：民事訴訟法第79條。"
  },
  "search": "臺灣苗栗地方法院民事簡易判決100年度苗簡字第258號原告黎維全訴訟代理人蕭秀源被告譚騰祥上列當事人間請求清償借款事件，本院於民國100年9月27日言詞辯論終結，判決如下：主文被告應給付原告新臺幣參萬壹仟元，及自民國一００年四月七日起至清償日止，按年息百分之五計算之利息。原告其餘之訴駁回。訴訟費用新臺幣參佰壹拾柒元由被告負擔，其餘由原告負擔。本判決第一項得假執行。事實及理由一、原告起訴主張：被告分別於民國91年8月27日、91年9月20日、91年9月30日向原告借款新臺幣（下同）40,000元、20,000元及35,000元，共計95,000元，上開借款金額原告均自原告所有兆豐國際商業銀行（原中國國際商業銀行）頭份分行活期儲蓄存款帳戶提領現金交予被告，被告則於91年12月25日簽發如卷第32頁所示，票號為TH0000000號，票面金額為100,000元，到期日為92年4月5日並免除作成拒絕證書之本票一紙（以下簡稱系爭本票）交付被告，以擔保上開借款及5,000元利息之清償；嗣因被告無法清償上開借款，另於92年4月7日簽發臺灣中小企業銀行頭份分行，票號為AY0000000號，票面金額100,000元之支票（以下簡稱系爭支票）予原告，詎該支票屆期提示亦未獲兌現。又被告經由原告介紹，另向訴外人黃郁梓借款31,000元，並簽發票號為AY0000000號，發票日為92年5月15日，票面金額為31,000元之支票以為擔保，詎上開支票屆期提示亦遭退票，訴外人黃郁梓嗣將其對被告之債權移轉與原告，並以100年8月9日之民事補充理由狀繕本送達被告作為債權讓與通知之意思表示。被告迄今均未清償上開借款，雖經原告屢次催討，未獲置理。為此，爰依消費借貸及債權讓與之法律關係，訴請被告給付等語。並聲明：被告應給付原告131,000元，及自92年5月7日起至清償日止，按年息百分之5計算之利息。二、被告則以：確實曾向訴外人黃郁梓借款31,000元，並簽發票號為AY0000000號之支票以為擔保，該支票已遭退票。另其簽發系爭本票係為擔保上開向黃郁梓借款之清償，被告實際僅收受訴外人黃郁梓交付之31,000元借款金額，並未收到原告交付之其他金額。原告所執系爭支票雖亦係被告所簽發，惟簽發系爭支票係用以向原告調現，原告並未將調借之100,000元交付被告，亦未將系爭支票返還被告。原告應提出其於何時、何地交付該100,000元予被告之證據，又系爭本票與支票之票據請求權均已罹於時效，原告之請求為無理由等語置辯。並聲明：原告之訴駁回。三、本件原告所執系爭本票及系爭支票均為被告所簽發。又被告經由原告介紹，曾向訴外人黃郁梓借款31,000元，並簽發票號為AY0000000號，發票日為92年5月15日，票面金額為31,000元之支票以為擔保，上開支票屆期提示遭退票，被告迄今未清償上開借款，而訴外人黃郁梓嗣將其對被告之債權移轉與原告，並經原告於100年8月9日以民事補充理由狀繕本送達被告作為債權讓與通知之意思表示等情，為兩造所不爭執，並有原告提出之債權讓與契約書及退票理由單（詳卷第30、34頁）等件附卷可憑，自堪信為真實。四、按票據為無因證券，票據債權人就其取得票據之原因，固不負證明之責任，惟執票人如主張票據係發票人向其借款而簽發交付，而發票人抗辯未收受借款，消費借貸並未成立，則就借款已交付之事實，自應由執票人負舉證責任，最高法院著有89年度台上字第85號裁判意旨可參。故主張消費借貸關係存在者，自應就業已踐行前揭要物行為乙節，即就借款交付之事實，負舉證證明之責。本件原告主張被告分別於91年8月27日、91年9月20日及91年9月30日向原告借款40,000元、20,000元及35,000元，共計95,000元，而被告則於91年12月25日簽發系爭本票交付被告，以擔保上開借款及5,000元利息之清償之事實，固據提出兆豐國際商業銀行活期儲蓄存款存摺、系爭本票及票貼憑據（詳卷第31至33頁）等件為證，惟被告既以其未收受該100,000元等語置辯，則依前開說明，原告自應就其分別於91年8月27日、91年9月20日及91年9月30日，分別交付借款金額40,000元、20,000元及35,000元予被告之事實，負舉證證明之責。經查，原告就其於上開日期分別交付被告前開借款金額之事實，雖據提出兆豐國際商業銀行活期儲蓄存款存摺為證，惟據該活期儲蓄存款存摺紀錄僅能證明原告分別於91年8月27日、91年9月20日及91年9月30日自該活期儲蓄帳戶提款40,000元、20,000元及35,000元之事實，尚難僅憑該提款記錄，即謂原告於上開日期曾分別交付前開借款金額予被告。另依原告訴訟代理人蕭秀源到庭所稱原告曾持被告簽發之系爭支票向伊調借現金10萬元，後來系爭支票經其提示遭退票未獲付款，由原告給付伊10萬元換回系爭支票等語（詳本院卷第40、41頁），亦僅能證明原告有向蕭秀源調借現金之事實，不足以證明原告曾交付系爭支票所示借款金額10萬元予被告之事實。此外，原告又迄未能就此另舉證以實其說，則原告主張被告向其借款共計95,000元云云，即無足採。五、次按稱消費借貸者，謂當事人一方移轉金錢或其他代替物之所有權於他方，而約定他方以種類、品質、數量相同之物返還之契約，民法第474條第1項定有明文。另按「債權之讓與，依民法第297條規定，非經讓與人或受讓人通知債務人不生效力，此項通知不過觀念通知，使債務人知有債權移轉之事實，免誤向原債權人清償而已」、「債權之讓與，依民法第297條第1項之規定，雖須經讓與人或受讓人通知債務人始生效力，但不以債務人之承諾為必要，而讓與之通知，為通知債權讓與事實之行為，原得以言詞或文書為之，不需何等之方式，故讓與人與受讓人間成立債權讓與契約時，債權即移轉於受讓人，除法律另有規定外，如經讓與人或受讓人通知債務人，即生債權移轉之效力」，最高法院39年台上字第448號判例、42年台上字第626號判例意旨可資參照。查訴外人黃郁梓將系爭31,000元借款返還請求權讓與原告後，訴外人黃郁梓或原告固未立即通知被告，惟原告對被告提起本件訴訟時，於民事補充理由狀內既已對被告表明受讓上開借款債權之事實，則足使被告知有債權讓與情事，應認兼有通知效力，揆諸前開判例意旨，系爭借款債權讓與於原告通知被告後，不待被告同意即生效力，被告對原告即負有返還系爭31,000元借款之義務。六、末按給付有確定期限者，債務人自期限屆滿時起，負遲延責任；給付無確定期限者，債務人於債權人得請求給付時，經其催告而未為給付，自受催告時起，負遲延責任。其經債權人起訴而送達訴狀，或依督促程序送達支付命令，或為其他相類之行為者，與催告有同一之效力；前項催告定有期限者，債務人自期限屆滿時起負遲延責任，民法第229條訂有明文。又遲延之債務，以支付金錢為標的者，債權人得請求依法定利率計算之遲延利息；而應付利息之債務，其利率未經約定，亦無法律可據者，週年利率為百分之5，亦為同法第233條第1項本文及第203條所明定。經查，本件被告自訴外人黃郁梓將系爭31,000元借款返還請求權讓與原告後，對原告即負有返還上開借款之義務，已如前述。而本件兩造就31,000元之借款並無約定確定清償期限，是被告對原告之給付義務，應自原告向本院聲請對被告核發支付命令，該支付命令送達翌日即100年4月7日起負遲延責任。七、從而，原告本於消費借貸及債權讓與之法律關係，請求被告應給付原告31,000元，及自100年4月7日起至清償日止，按年息百分之5計算之利息，為有理由，應予准許。原告逾此範圍之請求，則屬無據，不應准許。八、本件係依民事訴訟法第427條第1項規定適用簡易程序所為被告部分敗訴之判決，應依同法第389條第1項第3款規定，依職權宣告原告勝訴部分得假執行。九、因本案事證已臻明確，兩造其餘主張陳述及所提之證據，均毋庸再予審酌，附此敘明。十、訴訟費用負擔之依據：民事訴訟法第79條。中華民國100年10月11日苗栗簡易庭法官王萬金以上正本係照原本作成如對本判決上訴，須於判決送達後20日內向本院提出上訴狀。如委任律師提起上訴者，應一併繳納上訴審裁判費。書記官劉麗美中華民國100年10月11日",
  "characters": {
    "judges": [
      "王萬金"
    ],
    "prosecutors": [

    ],
    "lawyers": [
      "如委任"
    ],
    "clerks": [
      "劉麗美"
    ],
    "plaintiffs": [
      "黎維全"
    ],
    "defendants": [
      "譚騰祥"
    ],
    "prosecutor_office": [

    ],
    "creditors": [

    ],
    "debtors": [

    ],
    "judicial_associate_officer": [

    ]
  },
  "adjudged_at": "2011-10-11",
  "created_at": "2016-02-14 08:03:26",
  "updated_at": "2016-02-14 08:03:26"
}