{
  "identify": "TPB-90-訴-6650-20021016-1",
  "court": {
    "name": "臺北高等行政法院",
    "code": "TPB"
  },
  "division": {
    "name": "行政",
    "code": "A"
  },
  "year": 90,
  "word": "訴",
  "number": "6650",
  "jcheck": "1",
  "reason": "商標註冊",
  "content": "臺北高等行政法院裁定                              九十年度訴字第六六五○號\n    原      告  國本製藥工業股份有限公司\n    代  表  人  甲○○\n    訴訟代理人  乙○○\n右原告因商標註冊事件，不服經濟部中華民國九十年九月二十七日經（九０）訴字第\n０九００六三二三六三０號訴願決定，提起行政訴訟，本院裁定如左：\n    主  文\n原告之訴駁回。\n訴訟費用由原告負擔。\n    理  由\n一、起訴，應以訴狀表明當事人、起訴之聲明、訴訟標的及其原因事實，行政訴訟法\n    第一百零五條第一項定有明文。又當事人書狀，除別有規定外，應記載事實上及\n    法律上之陳述。同法第五十一條第五款亦有明文。\n二、本件原告不服訴願決定提起行政訴訟，核其訴狀未表明起訴之聲明，亦未記載原\n    因事實或為事實上或法律上之陳述，經本院審判長以九十年度訴字第六六五０號\n    裁定命其依法於七日內補正，該裁定已於九十一年三月七日送達原告收受，有送\n    達證書可稽，原告迄未補正，其起訴程式即屬於法不合，應予駁回。\n三、依行政訴訟法第一百零七條第一項第十款、第一百零四條、民事訴訟法第九十五\n    條、第七十八條，裁定如主文。\n中      華      民      國    九十一    年      十      月     十六     日\n                        臺 北 高 等 行 政 法 院   第 三 庭\n                                           審 判 長 法  官  姜素娥\n                                                    法  官  林文舟\n                                                    法  官  陳國成\n右為正本係照原本作成。\n如不服本裁定，應於送達後十日內向本院提出抗告狀（須按他造人數附繕本）。\n中      華      民      國    九十一    年      十      月     十七     日\n                                                    書記官  王英傑\n",
  "structure": {
    "main": "原告之訴駁回。\n訴訟費用由原告負擔。",
    "reason": "一、起訴，應以訴狀表明當事人、起訴之聲明、訴訟標的及其原因事實，行政訴訟法\n    第一百零五條第一項定有明文。又當事人書狀，除別有規定外，應記載事實上及\n    法律上之陳述。同法第五十一條第五款亦有明文。\n二、本件原告不服訴願決定提起行政訴訟，核其訴狀未表明起訴之聲明，亦未記載原\n    因事實或為事實上或法律上之陳述，經本院審判長以九十年度訴字第六六五０號\n    裁定命其依法於七日內補正，該裁定已於九十一年三月七日送達原告收受，有送\n    達證書可稽，原告迄未補正，其起訴程式即屬於法不合，應予駁回。\n三、依行政訴訟法第一百零七條第一項第十款、第一百零四條、民事訴訟法第九十五\n    條、第七十八條，裁定如主文。"
  },
  "search": "臺北高等行政法院裁定九十年度訴字第六六五○號原告國本製藥工業股份有限公司代表人甲○○訴訟代理人乙○○右原告因商標註冊事件，不服經濟部中華民國九十年九月二十七日經（九０）訴字第０九００六三二三六三０號訴願決定，提起行政訴訟，本院裁定如左：主文原告之訴駁回。訴訟費用由原告負擔。理由一、起訴，應以訴狀表明當事人、起訴之聲明、訴訟標的及其原因事實，行政訴訟法第一百零五條第一項定有明文。又當事人書狀，除別有規定外，應記載事實上及法律上之陳述。同法第五十一條第五款亦有明文。二、本件原告不服訴願決定提起行政訴訟，核其訴狀未表明起訴之聲明，亦未記載原因事實或為事實上或法律上之陳述，經本院審判長以九十年度訴字第六六五０號裁定命其依法於七日內補正，該裁定已於九十一年三月七日送達原告收受，有送達證書可稽，原告迄未補正，其起訴程式即屬於法不合，應予駁回。三、依行政訴訟法第一百零七條第一項第十款、第一百零四條、民事訴訟法第九十五條、第七十八條，裁定如主文。中華民國九十一年十月十六日臺北高等行政法院第三庭審判長法官姜素娥法官林文舟法官陳國成右為正本係照原本作成。如不服本裁定，應於送達後十日內向本院提出抗告狀（須按他造人數附繕本）。中華民國九十一年十月十七日書記官王英傑",
  "characters": {
    "judges": [
      "姜素娥",
      "林文舟",
      "陳國成"
    ],
    "prosecutors": [

    ],
    "lawyers": [

    ],
    "clerks": [
      "王英傑"
    ],
    "plaintiffs": [
      "國本製藥工業股份有限公司"
    ],
    "defendants": [

    ],
    "prosecutor_office": [

    ],
    "creditors": [

    ],
    "debtors": [

    ],
    "judicial_associate_officer": [

    ]
  },
  "adjudged_at": "2002-10-16",
  "created_at": "2016-02-05 19:27:43",
  "updated_at": "2016-02-05 19:27:43"
}