{
  "identify": "TPD-94-簡-1104-20050722-1",
  "court": {
    "name": "臺灣臺北地方法院",
    "code": "TPD"
  },
  "division": {
    "name": "刑事",
    "code": "M"
  },
  "year": 94,
  "word": "簡",
  "number": "1104",
  "jcheck": "1",
  "reason": "偽造文書",
  "content": "臺灣臺北地方法院刑事簡易判決          94年度簡字第1104號\n聲  請  人  臺灣臺北地方法院檢察署檢察官\n被      告  甲○○\n                    （另案在臺灣台北監獄執行中）\n上列被告因偽造文書案件，經檢察官聲請以簡易判決處刑（93年\n度偵字第2260號），本院判決如下：\n    主      文\n甲○○行使偽造私文書，足以生損害於公眾及他人，處有期徒刑\n參月，如易科罰金，以參佰元折算壹日。如附表所示偽造之「武\n富華」署押壹拾貳枚均沒收。\n    事實及理由\n一、甲○○與蘇振義（已經公訴人移送臺灣板橋地方法院併辦）\n    共同意圖供行使之用，而基於偽造國幣鈔券之概括犯意聯絡\n    ，先約定由甲○○租用臺北縣新店市○○街66巷1弄7號6 樓\n    作為偽造國幣鈔券之場所。嗣於民國92年11月12日下午5 時\n    45分許，甲○○搭乘不知情之友人所駕車號HU-515自小客車\n    返回前揭租屋處樓下時，經法務部調查局南部地區機動工作\n    組、台北縣調查站及台南縣政府警察局少年隊人員當場逮捕\n    ，並隨即逕行搜索甲○○前揭租屋處（該搜索行為已經本院\n    92年11月21日以北院錦刑正92急搜九字第25033 號函准予備\n    查在案）時，扣得偽造千元券、五百元券及道林紙等物（甲\n    ○○涉犯妨害國幣懲治條例之犯行部分，已經本院93年訴字\n    第1128號判處有期徒刑5年6月確定在案）。詎甲○○因另有\n    殺人未遂之執行案件曾經聲請人發布通緝在案，為掩飾其真\n    實身分，竟基於偽造署押、偽造私文書及行使偽造私文書之\n    犯意，於上揭租屋處冒用其弟「武富華」名義，並持其弟武\n    富華之國民身份證向調查局人員行使，表示其為武富華，而\n    接續於法務部調查局南部地區機動工作組搜索扣押筆錄2 紙\n    、扣押物品目錄表5 紙上偽造「武富華」之署押計12枚（詳\n    如附表所示），表示扣案物係武富華所有或持有之意思而偽\n    造私文書後，將前開文書出示行使交還予調查局人員，使武\n    富華涉有犯罪嫌疑，足生損害於武富華及調查機關偵查案件\n    之正確性。\n二、下列證據足以證明被告甲○○前述犯罪行為：\n  (一)被告於警詢及偵查中之自白。\n  (二)扣案之武富華身分證。\n  (三)搜索扣押筆錄2紙、扣押物品目錄表5紙在卷可資佐證。\n  (四)綜此，本件事證明確，依被告於警詢、偵查中之自白及現存\n    之其他證據，已足認定其確有偽造署押之犯行，本院爰不經\n    通常審判程序，逕以簡易判決處刑。\n三、按刑法上之偽造署押罪，係指單純偽造簽名、畫押而言，若\n    在制式之書類上偽造他人簽名，已為一定意思表示，具有申\n    請書或收據等類性質者，則係犯偽造文書罪，至該偽造署押\n    為偽造文書之部分行為，不另論罪，最高法院85年度台非字\n    第146 號判決意旨可資參照。本件被告在制式之搜索扣押筆\n    錄、扣押物品目錄表上偽造「武富華」之署押，表示扣案物\n    係武富華所有或持有之意思而偽造私文書後，再持以交回員\n    警處理而加以行使，顯然對上開文書之內容有所主張，足生\n    損害於武富華及調查機關偵查案件之正確性。核被告所為，\n    係犯刑法第216條、第210條之行使偽造私文書罪，其偽造署\n    押之行為，係偽造私文書之部分行為，偽造私文書後復持以\n    行使，偽造之低度行為應為行使之高度行為所吸收，均不另\n    論罪。又被告在同一警方偵辦程序中接續在搜索扣押筆錄、\n    扣押筆錄目錄表上偽造「武富華」署押、指印後行使之行為\n    ，時間緊接，行為無從分割，且侵害同一法益，應屬接續犯\n    而應以一行使偽造私文書罪論。聲請意旨認被告之行為係構\n    成刑法第217 條之偽造署押罪而聲請簡易判決處刑，尚有未\n    洽，在本院已依刑事訴訟法第95條第1 款後段之規定，於94\n    年7 月15日調查庭告知被告變更法條之意旨，使其得行使訴\n    訟上防禦權之情形下，應變更起訴法條。爰審酌被告為圖卸\n    責，冒用他人名義應訊，勢將誤導檢警單位之偵查方向，並\n    損及犯罪偵查之正確性，以及讓被害人受有刑事追訴之危險\n    ，惟念及被告犯後於偵訊過程中隨即坦承犯行，尚有悔意之\n    態度等一切情狀，量處如主文所示之刑，並諭知易科罰金之\n    折算標準。被告於如附表所示搜索扣押筆錄、扣押物品目錄\n    表上偽造「武富華」之署押計12枚，均應依刑法第219 條宣\n    告沒收。\n四、依刑事訴訟法第449條第1項前段、第3項、第450條第1 項、\n    第300條，刑法第216條、第210條、第41條第1項前段、第21\n    9條，罰金罰鍰提高標準條例第1條前段、第2 條，逕以簡易\n    判決處刑如主文所示之刑。\n五、如不服本判決，得自收受送達之日起10日內，向本院提出上\n    訴狀。\n中    華    民    國    94    年    7     月    22    日\n                        刑事第七庭    法  官  林孟皇\n以上正本證明與原本無異。\n                                      書記官  蔡宏志\n中    華    民    國    94    年    7     月    22    日\n附錄本案論罪科刑法條全文：\n中華民國刑法第217條（偽造盜用印章印文或署押罪）\n偽造印章、印文或署押，足以生損害於公眾或他人者，處三年以\n下有期徒刑。\n盜用印章、印文或署押，足以生損害於公眾或他人者，亦同。\n附表：\n一、（車號HU-515自小客車之搜索扣押筆錄1紙）：\n      偽造「武富華」署押2枚（指印、簽名各1枚）\n二、（上揭租屋處之搜索扣押筆錄1紙）：\n      偽造「武富華」署押2枚（指印、簽名各1枚）\n三、（車號HU-515自小客車之扣押物品目錄表1紙）：\n      偽造「武富華」署押2枚（指印、簽名各1枚）\n四、（上揭租屋處之之扣押物品目錄表4紙）：\n      偽造「武富華」署押6枚（指印、簽名各3枚）\n",
  "structure": {
    "main": "甲○○行使偽造私文書，足以生損害於公眾及他人，處有期徒刑\n參月，如易科罰金，以參佰元折算壹日。如附表所示偽造之「武\n富華」署押壹拾貳枚均沒收。",
    "fact": "一、甲○○與蘇振義（已經公訴人移送臺灣板橋地方法院併辦）\n    共同意圖供行使之用，而基於偽造國幣鈔券之概括犯意聯絡\n    ，先約定由甲○○租用臺北縣新店市○○街66巷1弄7號6 樓\n    作為偽造國幣鈔券之場所。嗣於民國92年11月12日下午5 時\n    45分許，甲○○搭乘不知情之友人所駕車號HU-515自小客車\n    返回前揭租屋處樓下時，經法務部調查局南部地區機動工作\n    組、台北縣調查站及台南縣政府警察局少年隊人員當場逮捕\n    ，並隨即逕行搜索甲○○前揭租屋處（該搜索行為已經本院\n    92年11月21日以北院錦刑正92急搜九字第25033 號函准予備\n    查在案）時，扣得偽造千元券、五百元券及道林紙等物（甲\n    ○○涉犯妨害國幣懲治條例之犯行部分，已經本院93年訴字\n    第1128號判處有期徒刑5年6月確定在案）。詎甲○○因另有\n    殺人未遂之執行案件曾經聲請人發布通緝在案，為掩飾其真\n    實身分，竟基於偽造署押、偽造私文書及行使偽造私文書之\n    犯意，於上揭租屋處冒用其弟「武富華」名義，並持其弟武\n    富華之國民身份證向調查局人員行使，表示其為武富華，而\n    接續於法務部調查局南部地區機動工作組搜索扣押筆錄2 紙\n    、扣押物品目錄表5 紙上偽造「武富華」之署押計12枚（詳\n    如附表所示），表示扣案物係武富華所有或持有之意思而偽\n    造私文書後，將前開文書出示行使交還予調查局人員，使武\n    富華涉有犯罪嫌疑，足生損害於武富華及調查機關偵查案件\n    之正確性。\n二、下列證據足以證明被告甲○○前述犯罪行為：\n  (一)被告於警詢及偵查中之自白。\n  (二)扣案之武富華身分證。\n  (三)搜索扣押筆錄2紙、扣押物品目錄表5紙在卷可資佐證。\n  (四)綜此，本件事證明確，依被告於警詢、偵查中之自白及現存\n    之其他證據，已足認定其確有偽造署押之犯行，本院爰不經\n    通常審判程序，逕以簡易判決處刑。\n三、按刑法上之偽造署押罪，係指單純偽造簽名、畫押而言，若\n    在制式之書類上偽造他人簽名，已為一定意思表示，具有申\n    請書或收據等類性質者，則係犯偽造文書罪，至該偽造署押\n    為偽造文書之部分行為，不另論罪，最高法院85年度台非字\n    第146 號判決意旨可資參照。本件被告在制式之搜索扣押筆\n    錄、扣押物品目錄表上偽造「武富華」之署押，表示扣案物\n    係武富華所有或持有之意思而偽造私文書後，再持以交回員\n    警處理而加以行使，顯然對上開文書之內容有所主張，足生\n    損害於武富華及調查機關偵查案件之正確性。核被告所為，\n    係犯刑法第216條、第210條之行使偽造私文書罪，其偽造署\n    押之行為，係偽造私文書之部分行為，偽造私文書後復持以\n    行使，偽造之低度行為應為行使之高度行為所吸收，均不另\n    論罪。又被告在同一警方偵辦程序中接續在搜索扣押筆錄、\n    扣押筆錄目錄表上偽造「武富華」署押、指印後行使之行為\n    ，時間緊接，行為無從分割，且侵害同一法益，應屬接續犯\n    而應以一行使偽造私文書罪論。聲請意旨認被告之行為係構\n    成刑法第217 條之偽造署押罪而聲請簡易判決處刑，尚有未\n    洽，在本院已依刑事訴訟法第95條第1 款後段之規定，於94\n    年7 月15日調查庭告知被告變更法條之意旨，使其得行使訴\n    訟上防禦權之情形下，應變更起訴法條。爰審酌被告為圖卸\n    責，冒用他人名義應訊，勢將誤導檢警單位之偵查方向，並\n    損及犯罪偵查之正確性，以及讓被害人受有刑事追訴之危險\n    ，惟念及被告犯後於偵訊過程中隨即坦承犯行，尚有悔意之\n    態度等一切情狀，量處如主文所示之刑，並諭知易科罰金之\n    折算標準。被告於如附表所示搜索扣押筆錄、扣押物品目錄\n    表上偽造「武富華」之署押計12枚，均應依刑法第219 條宣\n    告沒收。\n四、依刑事訴訟法第449條第1項前段、第3項、第450條第1 項、\n    第300條，刑法第216條、第210條、第41條第1項前段、第21\n    9條，罰金罰鍰提高標準條例第1條前段、第2 條，逕以簡易\n    判決處刑如主文所示之刑。\n五、如不服本判決，得自收受送達之日起10日內，向本院提出上\n    訴狀。",
    "reason": "一、甲○○與蘇振義（已經公訴人移送臺灣板橋地方法院併辦）\n    共同意圖供行使之用，而基於偽造國幣鈔券之概括犯意聯絡\n    ，先約定由甲○○租用臺北縣新店市○○街66巷1弄7號6 樓\n    作為偽造國幣鈔券之場所。嗣於民國92年11月12日下午5 時\n    45分許，甲○○搭乘不知情之友人所駕車號HU-515自小客車\n    返回前揭租屋處樓下時，經法務部調查局南部地區機動工作\n    組、台北縣調查站及台南縣政府警察局少年隊人員當場逮捕\n    ，並隨即逕行搜索甲○○前揭租屋處（該搜索行為已經本院\n    92年11月21日以北院錦刑正92急搜九字第25033 號函准予備\n    查在案）時，扣得偽造千元券、五百元券及道林紙等物（甲\n    ○○涉犯妨害國幣懲治條例之犯行部分，已經本院93年訴字\n    第1128號判處有期徒刑5年6月確定在案）。詎甲○○因另有\n    殺人未遂之執行案件曾經聲請人發布通緝在案，為掩飾其真\n    實身分，竟基於偽造署押、偽造私文書及行使偽造私文書之\n    犯意，於上揭租屋處冒用其弟「武富華」名義，並持其弟武\n    富華之國民身份證向調查局人員行使，表示其為武富華，而\n    接續於法務部調查局南部地區機動工作組搜索扣押筆錄2 紙\n    、扣押物品目錄表5 紙上偽造「武富華」之署押計12枚（詳\n    如附表所示），表示扣案物係武富華所有或持有之意思而偽\n    造私文書後，將前開文書出示行使交還予調查局人員，使武\n    富華涉有犯罪嫌疑，足生損害於武富華及調查機關偵查案件\n    之正確性。\n二、下列證據足以證明被告甲○○前述犯罪行為：\n  (一)被告於警詢及偵查中之自白。\n  (二)扣案之武富華身分證。\n  (三)搜索扣押筆錄2紙、扣押物品目錄表5紙在卷可資佐證。\n  (四)綜此，本件事證明確，依被告於警詢、偵查中之自白及現存\n    之其他證據，已足認定其確有偽造署押之犯行，本院爰不經\n    通常審判程序，逕以簡易判決處刑。\n三、按刑法上之偽造署押罪，係指單純偽造簽名、畫押而言，若\n    在制式之書類上偽造他人簽名，已為一定意思表示，具有申\n    請書或收據等類性質者，則係犯偽造文書罪，至該偽造署押\n    為偽造文書之部分行為，不另論罪，最高法院85年度台非字\n    第146 號判決意旨可資參照。本件被告在制式之搜索扣押筆\n    錄、扣押物品目錄表上偽造「武富華」之署押，表示扣案物\n    係武富華所有或持有之意思而偽造私文書後，再持以交回員\n    警處理而加以行使，顯然對上開文書之內容有所主張，足生\n    損害於武富華及調查機關偵查案件之正確性。核被告所為，\n    係犯刑法第216條、第210條之行使偽造私文書罪，其偽造署\n    押之行為，係偽造私文書之部分行為，偽造私文書後復持以\n    行使，偽造之低度行為應為行使之高度行為所吸收，均不另\n    論罪。又被告在同一警方偵辦程序中接續在搜索扣押筆錄、\n    扣押筆錄目錄表上偽造「武富華」署押、指印後行使之行為\n    ，時間緊接，行為無從分割，且侵害同一法益，應屬接續犯\n    而應以一行使偽造私文書罪論。聲請意旨認被告之行為係構\n    成刑法第217 條之偽造署押罪而聲請簡易判決處刑，尚有未\n    洽，在本院已依刑事訴訟法第95條第1 款後段之規定，於94\n    年7 月15日調查庭告知被告變更法條之意旨，使其得行使訴\n    訟上防禦權之情形下，應變更起訴法條。爰審酌被告為圖卸\n    責，冒用他人名義應訊，勢將誤導檢警單位之偵查方向，並\n    損及犯罪偵查之正確性，以及讓被害人受有刑事追訴之危險\n    ，惟念及被告犯後於偵訊過程中隨即坦承犯行，尚有悔意之\n    態度等一切情狀，量處如主文所示之刑，並諭知易科罰金之\n    折算標準。被告於如附表所示搜索扣押筆錄、扣押物品目錄\n    表上偽造「武富華」之署押計12枚，均應依刑法第219 條宣\n    告沒收。\n四、依刑事訴訟法第449條第1項前段、第3項、第450條第1 項、\n    第300條，刑法第216條、第210條、第41條第1項前段、第21\n    9條，罰金罰鍰提高標準條例第1條前段、第2 條，逕以簡易\n    判決處刑如主文所示之刑。\n五、如不服本判決，得自收受送達之日起10日內，向本院提出上\n    訴狀。"
  },
  "search": "臺灣臺北地方法院刑事簡易判決94年度簡字第1104號聲請人臺灣臺北地方法院檢察署檢察官被告甲○○（另案在臺灣台北監獄執行中）上列被告因偽造文書案件，經檢察官聲請以簡易判決處刑（93年度偵字第2260號），本院判決如下：主文甲○○行使偽造私文書，足以生損害於公眾及他人，處有期徒刑參月，如易科罰金，以參佰元折算壹日。如附表所示偽造之「武富華」署押壹拾貳枚均沒收。事實及理由一、甲○○與蘇振義（已經公訴人移送臺灣板橋地方法院併辦）共同意圖供行使之用，而基於偽造國幣鈔券之概括犯意聯絡，先約定由甲○○租用臺北縣新店市○○街66巷1弄7號6樓作為偽造國幣鈔券之場所。嗣於民國92年11月12日下午5時45分許，甲○○搭乘不知情之友人所駕車號HU-515自小客車返回前揭租屋處樓下時，經法務部調查局南部地區機動工作組、台北縣調查站及台南縣政府警察局少年隊人員當場逮捕，並隨即逕行搜索甲○○前揭租屋處（該搜索行為已經本院92年11月21日以北院錦刑正92急搜九字第25033號函准予備查在案）時，扣得偽造千元券、五百元券及道林紙等物（甲○○涉犯妨害國幣懲治條例之犯行部分，已經本院93年訴字第1128號判處有期徒刑5年6月確定在案）。詎甲○○因另有殺人未遂之執行案件曾經聲請人發布通緝在案，為掩飾其真實身分，竟基於偽造署押、偽造私文書及行使偽造私文書之犯意，於上揭租屋處冒用其弟「武富華」名義，並持其弟武富華之國民身份證向調查局人員行使，表示其為武富華，而接續於法務部調查局南部地區機動工作組搜索扣押筆錄2紙、扣押物品目錄表5紙上偽造「武富華」之署押計12枚（詳如附表所示），表示扣案物係武富華所有或持有之意思而偽造私文書後，將前開文書出示行使交還予調查局人員，使武富華涉有犯罪嫌疑，足生損害於武富華及調查機關偵查案件之正確性。二、下列證據足以證明被告甲○○前述犯罪行為：(一)被告於警詢及偵查中之自白。(二)扣案之武富華身分證。(三)搜索扣押筆錄2紙、扣押物品目錄表5紙在卷可資佐證。(四)綜此，本件事證明確，依被告於警詢、偵查中之自白及現存之其他證據，已足認定其確有偽造署押之犯行，本院爰不經通常審判程序，逕以簡易判決處刑。三、按刑法上之偽造署押罪，係指單純偽造簽名、畫押而言，若在制式之書類上偽造他人簽名，已為一定意思表示，具有申請書或收據等類性質者，則係犯偽造文書罪，至該偽造署押為偽造文書之部分行為，不另論罪，最高法院85年度台非字第146號判決意旨可資參照。本件被告在制式之搜索扣押筆錄、扣押物品目錄表上偽造「武富華」之署押，表示扣案物係武富華所有或持有之意思而偽造私文書後，再持以交回員警處理而加以行使，顯然對上開文書之內容有所主張，足生損害於武富華及調查機關偵查案件之正確性。核被告所為，係犯刑法第216條、第210條之行使偽造私文書罪，其偽造署押之行為，係偽造私文書之部分行為，偽造私文書後復持以行使，偽造之低度行為應為行使之高度行為所吸收，均不另論罪。又被告在同一警方偵辦程序中接續在搜索扣押筆錄、扣押筆錄目錄表上偽造「武富華」署押、指印後行使之行為，時間緊接，行為無從分割，且侵害同一法益，應屬接續犯而應以一行使偽造私文書罪論。聲請意旨認被告之行為係構成刑法第217條之偽造署押罪而聲請簡易判決處刑，尚有未洽，在本院已依刑事訴訟法第95條第1款後段之規定，於94年7月15日調查庭告知被告變更法條之意旨，使其得行使訴訟上防禦權之情形下，應變更起訴法條。爰審酌被告為圖卸責，冒用他人名義應訊，勢將誤導檢警單位之偵查方向，並損及犯罪偵查之正確性，以及讓被害人受有刑事追訴之危險，惟念及被告犯後於偵訊過程中隨即坦承犯行，尚有悔意之態度等一切情狀，量處如主文所示之刑，並諭知易科罰金之折算標準。被告於如附表所示搜索扣押筆錄、扣押物品目錄表上偽造「武富華」之署押計12枚，均應依刑法第219條宣告沒收。四、依刑事訴訟法第449條第1項前段、第3項、第450條第1項、第300條，刑法第216條、第210條、第41條第1項前段、第219條，罰金罰鍰提高標準條例第1條前段、第2條，逕以簡易判決處刑如主文所示之刑。五、如不服本判決，得自收受送達之日起10日內，向本院提出上訴狀。中華民國94年7月22日刑事第七庭法官林孟皇以上正本證明與原本無異。書記官蔡宏志中華民國94年7月22日附錄本案論罪科刑法條全文：中華民國刑法第217條（偽造盜用印章印文或署押罪）偽造印章、印文或署押，足以生損害於公眾或他人者，處三年以下有期徒刑。盜用印章、印文或署押，足以生損害於公眾或他人者，亦同。附表：一、（車號HU-515自小客車之搜索扣押筆錄1紙）：偽造「武富華」署押2枚（指印、簽名各1枚）二、（上揭租屋處之搜索扣押筆錄1紙）：偽造「武富華」署押2枚（指印、簽名各1枚）三、（車號HU-515自小客車之扣押物品目錄表1紙）：偽造「武富華」署押2枚（指印、簽名各1枚）四、（上揭租屋處之之扣押物品目錄表4紙）：偽造「武富華」署押6枚（指印、簽名各3枚）",
  "characters": {
    "judges": [
      "林孟皇"
    ],
    "prosecutors": [

    ],
    "lawyers": [

    ],
    "clerks": [
      "蔡宏志"
    ],
    "plaintiffs": [

    ],
    "defendants": [
      "甲○○"
    ],
    "prosecutor_office": [
      "臺灣臺北地方法院檢察署檢察官"
    ],
    "creditors": [

    ],
    "debtors": [

    ],
    "judicial_associate_officer": [

    ]
  },
  "adjudged_at": "2005-07-22",
  "created_at": "2016-02-07 09:49:39",
  "updated_at": "2016-02-07 09:49:39"
}