{
  "identify": "KSD-100-簡-5048-20110928-1",
  "court": {
    "name": "臺灣高雄地方法院",
    "code": "KSD"
  },
  "division": {
    "name": "刑事",
    "code": "M"
  },
  "year": 100,
  "word": "簡",
  "number": "5048",
  "jcheck": "1",
  "reason": "毒品危害防制條例",
  "content": "臺灣高雄地方法院刑事簡易判決         100年度簡字第5048號\n公  訴  人  臺灣高雄地方法院檢察署檢察官\n被      告  焦德明\n上列被告因毒品危害防制條例案件，經檢察官提起公訴（100 年\n度毒偵字第3189號），被告自白犯罪，本院認宜以簡易判決處刑\n（原案號：100年度審易字第2507 號），爰不經通常審理程序，\n裁定逕以簡易判決處刑如下：\n    主  文\n焦德明施用第二級毒品，累犯，處有期徒刑伍月，如易科罰金，\n以新臺幣壹仟元折算壹日。\n    事實及理由\n一、本件犯罪事實及證據，除證據部分補充：「被告焦德明於本\n    院調查程序中之自白」外，其餘均引用檢察官起訴書（如附\n    件）之記載。\n二、核被告所為，係犯毒品危害防制條例第10條第2 項之施用第\n    二級毒品罪。被告為施用而持有第二級毒品之低度行為，為\n    施用第二級毒品之高度行為所吸收，不另論罪。又被告有如\n    起訴書犯罪事實欄所記載論罪科刑執行完畢之紀錄，有臺灣\n    高等法院被告前案紀錄表1 份附卷可考，其於有期徒刑執行\n    完畢後，5 年內故意再犯本件有期徒刑以上之罪，為累犯，\n    應依刑法第47條第1 項規定，加重其刑。本院審酌被告前因\n    施用毒品案件，經觀察、勒戒、強制戒治及法院科刑判決後\n    ，竟再為本件犯行，足見其惡習非淺，且戒絕毒癮之意志不\n    堅，未能體悟施用毒品對自己、家人造成之傷害及社會之負\n    擔，自屬可議；參以被告犯後坦承犯行，且施用毒品本質上\n    係屬戕害自身健康之行為，尚未直接危害他人，反社會性程\n    度應屬較低，及其施用毒品之前科紀錄，智識程度為國中畢\n    業，從工，每日收入約新臺幣1,200 元等一切情狀，量處如\n    主文所示之刑，並諭知易科罰金之折算標準，以資懲儆。\n三、依刑事訴訟法第449 條第2 項、第3 項、第454 條第2 項，\n    毒品危害防制條例第10條第2 項，刑法第11條前段、第47條\n    第1項、第41條第1 項前段，逕以簡易判決處刑如主文。\n四、如不服本判決，應於判決送達之日起10日內，向本院提出上\n    訴狀。\n中    華    民    國    100    年    9    月    28    日\n                  高雄簡易庭    法  官  林裕凱\n以上正本證明與原本無異。\n如不服本判決，應於判決送達之日起10日內向本院提出上訴書狀\n。\n中    華    民    國    100    年    9    月    28    日\n                                書記官  黃振祐\n\n附錄本案論罪科刑法條：\n毒品危害防制條例第10條\n施用第一級毒品者，處 6 月以上 5 年以下有期徒刑。\n施用第二級毒品者，處 3 年以下有期徒刑。\n附件\n臺灣高雄地方法院檢察署檢察官起訴書\n                                   100年度毒偵字第3189號\n    被      告  焦德明  男  41歲（民國○○年○○月○○日生）\n                        住高雄市○○區○○里○○街142號\n                        國民身分證統一編號：Ｚ000000000號\n上列被告因違反毒品危害防制條例案件，業經偵查終結，認應提\n起公訴，茲敘述犯罪事實及證據並所犯法條如下：\n            犯罪事實\n一、焦德明前因施用毒品案件，經送強制戒治後，於民國92年2\n    月18日停止執行釋放付保護管束，於92年5月27日保護管束\n    期滿，停止執行之處分未經撤銷視為執行完畢，並經臺灣高\n    雄地方法院以91年度雄簡字第892號判處有期徒刑3月確定，\n    於92年9月26日期滿執行完畢，復因毒品危害防制條例案件\n    ，經同院以95年度簡上字第635號判處有期徒刑6月確定，於\n    96年2月13日縮刑期滿執行完畢。再於98年間，因施用毒品\n    案件，經同院以98年度審易字第1244號判處有期徒刑4月，\n    甫於99年2月22日縮刑期滿執行完畢。詎猶未戒斷毒癮，基\n    於施用第二級毒品之犯意，於100年4月18日12時許，在其位\n    於高雄市○○區○○街142號住處，以將燒烤玻璃球吸食煙\n    霧之方式，施用第二級毒品甲基安非他命1次。嗣於100年4\n    月19日7時47分許，經警通知前往警局驗尿，檢驗結果呈安\n    非他命、甲基安非他命陽性反應，始悉上情。\n二、案經高雄市政府警察局小港分局移送偵辦。\n            證據並所犯法條\n一、證據清單\n     ┌──┬───────────┬────────────┐\n     │編號│證據名稱              │待證事實                │\n     ├──┼───────────┼────────────┤\n     │ 1. │被告焦德明於警詢時之供│坦承有於上開時地施用第二│\n     │    │述。                  │級毒品甲基安非他命之事實│\n     │    │                      │。                      │\n     ├──┼───────────┼────────────┤\n     │ 2. │臺灣檢驗科技股份有限公│被告為警採集之尿液送驗結│\n     │    │司濫用藥物檢驗報告(V30│果呈甲基安非他命、安非他│\n     │    │0000000000)。         │命陽性反應，佐證被告有於│\n     │    │高雄市政府警察局小港分│上開時地施用第二級毒品甲│\n     │    │局毒品案嫌疑人尿液代碼│基安非他命之事實。      │\n     │    │與姓名對照表(         │                        │\n     │    │Ｚ000000000000)。      │                        │\n     └──┴───────────┴────────────┘\n二、核被告所為，係犯毒品危害防制條例第10條第2項之施用第\n    二級毒品甲基安非他命罪嫌。又其於有期徒刑執行完畢後，\n    5年內故意再犯本件有期徒刑以上之罪，為累犯，請依刑法\n    第47條第1項規定加重其刑。\n三、依毒品危害防制條例第23條2項、刑事訴訟法第251條第1項\n    提起公訴。\n    此  致\n臺灣高雄地方法院\n中    華    民    國   100    年    7     月    11    日\n                               檢  察  官  陳文哲\n上正本證明與原本無異\n中    華    民    國   100    年    7     月    12    日\n                               書  記  官\n參考法條：毒品危害防制條例第10條\n施用第一級毒品者，處 6 月以上 5 年以下有期徒刑。\n施用第二級毒品者，處 3 年以下有期徒刑。",
  "structure": {
    "main": "焦德明施用第二級毒品，累犯，處有期徒刑伍月，如易科罰金，\n以新臺幣壹仟元折算壹日。",
    "fact": "一、本件犯罪事實及證據，除證據部分補充：「被告焦德明於本\n    院調查程序中之自白」外，其餘均引用檢察官起訴書（如附\n    件）之記載。\n二、核被告所為，係犯毒品危害防制條例第10條第2 項之施用第\n    二級毒品罪。被告為施用而持有第二級毒品之低度行為，為\n    施用第二級毒品之高度行為所吸收，不另論罪。又被告有如\n    起訴書犯罪事實欄所記載論罪科刑執行完畢之紀錄，有臺灣\n    高等法院被告前案紀錄表1 份附卷可考，其於有期徒刑執行\n    完畢後，5 年內故意再犯本件有期徒刑以上之罪，為累犯，\n    應依刑法第47條第1 項規定，加重其刑。本院審酌被告前因\n    施用毒品案件，經觀察、勒戒、強制戒治及法院科刑判決後\n    ，竟再為本件犯行，足見其惡習非淺，且戒絕毒癮之意志不\n    堅，未能體悟施用毒品對自己、家人造成之傷害及社會之負\n    擔，自屬可議；參以被告犯後坦承犯行，且施用毒品本質上\n    係屬戕害自身健康之行為，尚未直接危害他人，反社會性程\n    度應屬較低，及其施用毒品之前科紀錄，智識程度為國中畢\n    業，從工，每日收入約新臺幣1,200 元等一切情狀，量處如\n    主文所示之刑，並諭知易科罰金之折算標準，以資懲儆。\n三、依刑事訴訟法第449 條第2 項、第3 項、第454 條第2 項，\n    毒品危害防制條例第10條第2 項，刑法第11條前段、第47條\n    第1項、第41條第1 項前段，逕以簡易判決處刑如主文。\n四、如不服本判決，應於判決送達之日起10日內，向本院提出上\n    訴狀。",
    "reason": "一、本件犯罪事實及證據，除證據部分補充：「被告焦德明於本\n    院調查程序中之自白」外，其餘均引用檢察官起訴書（如附\n    件）之記載。\n二、核被告所為，係犯毒品危害防制條例第10條第2 項之施用第\n    二級毒品罪。被告為施用而持有第二級毒品之低度行為，為\n    施用第二級毒品之高度行為所吸收，不另論罪。又被告有如\n    起訴書犯罪事實欄所記載論罪科刑執行完畢之紀錄，有臺灣\n    高等法院被告前案紀錄表1 份附卷可考，其於有期徒刑執行\n    完畢後，5 年內故意再犯本件有期徒刑以上之罪，為累犯，\n    應依刑法第47條第1 項規定，加重其刑。本院審酌被告前因\n    施用毒品案件，經觀察、勒戒、強制戒治及法院科刑判決後\n    ，竟再為本件犯行，足見其惡習非淺，且戒絕毒癮之意志不\n    堅，未能體悟施用毒品對自己、家人造成之傷害及社會之負\n    擔，自屬可議；參以被告犯後坦承犯行，且施用毒品本質上\n    係屬戕害自身健康之行為，尚未直接危害他人，反社會性程\n    度應屬較低，及其施用毒品之前科紀錄，智識程度為國中畢\n    業，從工，每日收入約新臺幣1,200 元等一切情狀，量處如\n    主文所示之刑，並諭知易科罰金之折算標準，以資懲儆。\n三、依刑事訴訟法第449 條第2 項、第3 項、第454 條第2 項，\n    毒品危害防制條例第10條第2 項，刑法第11條前段、第47條\n    第1項、第41條第1 項前段，逕以簡易判決處刑如主文。\n四、如不服本判決，應於判決送達之日起10日內，向本院提出上\n    訴狀。"
  },
  "search": "臺灣高雄地方法院刑事簡易判決100年度簡字第5048號公訴人臺灣高雄地方法院檢察署檢察官被告焦德明上列被告因毒品危害防制條例案件，經檢察官提起公訴（100年度毒偵字第3189號），被告自白犯罪，本院認宜以簡易判決處刑（原案號：100年度審易字第2507號），爰不經通常審理程序，裁定逕以簡易判決處刑如下：主文焦德明施用第二級毒品，累犯，處有期徒刑伍月，如易科罰金，以新臺幣壹仟元折算壹日。事實及理由一、本件犯罪事實及證據，除證據部分補充：「被告焦德明於本院調查程序中之自白」外，其餘均引用檢察官起訴書（如附件）之記載。二、核被告所為，係犯毒品危害防制條例第10條第2項之施用第二級毒品罪。被告為施用而持有第二級毒品之低度行為，為施用第二級毒品之高度行為所吸收，不另論罪。又被告有如起訴書犯罪事實欄所記載論罪科刑執行完畢之紀錄，有臺灣高等法院被告前案紀錄表1份附卷可考，其於有期徒刑執行完畢後，5年內故意再犯本件有期徒刑以上之罪，為累犯，應依刑法第47條第1項規定，加重其刑。本院審酌被告前因施用毒品案件，經觀察、勒戒、強制戒治及法院科刑判決後，竟再為本件犯行，足見其惡習非淺，且戒絕毒癮之意志不堅，未能體悟施用毒品對自己、家人造成之傷害及社會之負擔，自屬可議；參以被告犯後坦承犯行，且施用毒品本質上係屬戕害自身健康之行為，尚未直接危害他人，反社會性程度應屬較低，及其施用毒品之前科紀錄，智識程度為國中畢業，從工，每日收入約新臺幣1,200元等一切情狀，量處如主文所示之刑，並諭知易科罰金之折算標準，以資懲儆。三、依刑事訴訟法第449條第2項、第3項、第454條第2項，毒品危害防制條例第10條第2項，刑法第11條前段、第47條第1項、第41條第1項前段，逕以簡易判決處刑如主文。四、如不服本判決，應於判決送達之日起10日內，向本院提出上訴狀。中華民國100年9月28日高雄簡易庭法官林裕凱以上正本證明與原本無異。如不服本判決，應於判決送達之日起10日內向本院提出上訴書狀。中華民國100年9月28日書記官黃振祐附錄本案論罪科刑法條：毒品危害防制條例第10條施用第一級毒品者，處6月以上5年以下有期徒刑。施用第二級毒品者，處3年以下有期徒刑。附件臺灣高雄地方法院檢察署檢察官起訴書100年度毒偵字第3189號被告焦德明男41歲（民國○○年○○月○○日生）住高雄市○○區○○里○○街142號國民身分證統一編號：Ｚ000000000號上列被告因違反毒品危害防制條例案件，業經偵查終結，認應提起公訴，茲敘述犯罪事實及證據並所犯法條如下：犯罪事實一、焦德明前因施用毒品案件，經送強制戒治後，於民國92年2月18日停止執行釋放付保護管束，於92年5月27日保護管束期滿，停止執行之處分未經撤銷視為執行完畢，並經臺灣高雄地方法院以91年度雄簡字第892號判處有期徒刑3月確定，於92年9月26日期滿執行完畢，復因毒品危害防制條例案件，經同院以95年度簡上字第635號判處有期徒刑6月確定，於96年2月13日縮刑期滿執行完畢。再於98年間，因施用毒品案件，經同院以98年度審易字第1244號判處有期徒刑4月，甫於99年2月22日縮刑期滿執行完畢。詎猶未戒斷毒癮，基於施用第二級毒品之犯意，於100年4月18日12時許，在其位於高雄市○○區○○街142號住處，以將燒烤玻璃球吸食煙霧之方式，施用第二級毒品甲基安非他命1次。嗣於100年4月19日7時47分許，經警通知前往警局驗尿，檢驗結果呈安非他命、甲基安非他命陽性反應，始悉上情。二、案經高雄市政府警察局小港分局移送偵辦。證據並所犯法條一、證據清單┌──┬───────────┬────────────┐│編號│證據名稱│待證事實│├──┼───────────┼────────────┤│1.│被告焦德明於警詢時之供│坦承有於上開時地施用第二│││述。│級毒品甲基安非他命之事實││││。│├──┼───────────┼────────────┤│2.│臺灣檢驗科技股份有限公│被告為警採集之尿液送驗結│││司濫用藥物檢驗報告(V30│果呈甲基安非他命、安非他│││0000000000)。│命陽性反應，佐證被告有於│││高雄市政府警察局小港分│上開時地施用第二級毒品甲│││局毒品案嫌疑人尿液代碼│基安非他命之事實。│││與姓名對照表(││││Ｚ000000000000)。││└──┴───────────┴────────────┘二、核被告所為，係犯毒品危害防制條例第10條第2項之施用第二級毒品甲基安非他命罪嫌。又其於有期徒刑執行完畢後，5年內故意再犯本件有期徒刑以上之罪，為累犯，請依刑法第47條第1項規定加重其刑。三、依毒品危害防制條例第23條2項、刑事訴訟法第251條第1項提起公訴。此致臺灣高雄地方法院中華民國100年7月11日檢察官陳文哲上正本證明與原本無異中華民國100年7月12日書記官參考法條：毒品危害防制條例第10條施用第一級毒品者，處6月以上5年以下有期徒刑。施用第二級毒品者，處3年以下有期徒刑。",
  "characters": {
    "judges": [
      "林裕凱"
    ],
    "prosecutors": [

    ],
    "lawyers": [

    ],
    "clerks": [
      "黃振祐"
    ],
    "plaintiffs": [

    ],
    "defendants": [
      "焦德明",
      "焦德明  男  41歲（民國○○年○○月○○日生）"
    ],
    "prosecutor_office": [
      "臺灣高雄地方法院檢察署檢察官"
    ],
    "creditors": [

    ],
    "debtors": [

    ],
    "judicial_associate_officer": [

    ]
  },
  "adjudged_at": "2011-09-28",
  "created_at": "2016-02-12 13:37:38",
  "updated_at": "2016-02-12 13:37:38"
}