{
  "identify": "PCD-100-重訴-181-20110929-1",
  "court": {
    "name": "臺灣新北地方法院",
    "code": "PCD"
  },
  "division": {
    "name": "民事",
    "code": "V"
  },
  "year": 100,
  "word": "重訴",
  "number": "181",
  "jcheck": "1",
  "reason": "確認債務額",
  "content": "臺灣板橋地方法院民事判決            100年度重訴字第181號\n原      告  吳宛玉\n訴訟代理人  邱六郎律師\n被      告  謝劉碧霞\n訴訟代理人  陳明暉律師\n複  代理人  郭令立律師\n上列當事人間請求確認債務額事件，經本院於民國100 年9 月8\n日言詞辯論終結，判決如下：\n    主  文\n原告之訴駁回。\n訴訟費用由原告負擔。\n    事實及理由\n一、原告起訴主張：\n（一）原告於民國82年10月間向訴外人李金利、陳抱、陳尾、王\n      簡阿玉、金陳寶英等人分別購買如附表二所示坐落臺北市\n      中正區○○段○ ○段第315 及315 之1 至9 地號等10筆土\n      地（下稱系爭土地）。83年3 月間，訴外人簡金燦得知原\n      告購買系爭土地，即向原告佯稱有款項可借原告並以系爭\n      土地為擔保，原告徵得系爭土地之所有人即訴外人李金利\n      陳抱、陳尾、王簡阿玉、金陳寶英等人之同意，即將土地\n      所有權狀、印鑑證明書及印章交給簡金燦辦理貸款，並交\n      由委任之代書辦理設定最高限額抵押權；惟簡金燦實際係\n      向本件被告借款，並擅自將系爭土地完成本金最高限額新\n      臺幣（下同）7500萬元之最高限額抵押權登記予被告，並\n      將借得款項分別以被告簽發之九信支票給付與訴外人李金\n      利、陳抱、陳尾、王簡阿玉、金陳寶英等人，核算渠等收\n      受之支票總金額為2482萬5000元，加計原告陸續向被告借\n      得142 萬5000元之借款，合計為2625萬元。\n（二）簡金燦辦理前揭抵押權設定，設定期限一年，即自83 年3\n      月25日至84年3 月24日止，並將數十張系爭土地所有權狀\n      正本、印鑑章等交予被告保管，嗣被告為防止土地登記所\n      有權人李金利等人再設定次順位抵押權，影響其貸款之回\n      收，竟拒絕返還上開土地所有權狀正本、印鑑章，致原告\n      與李金利等人間之契約無法履行，無法將系爭土地移轉登\n      記予原告，終使貸款之清償發生遲延，此應歸責於被告之\n      事由所致。多年前原告即多次要求被告協調清償前開欠款\n      ，但被告堅持李金利、陳抱、陳尾、王簡阿玉、金陳寶英\n      等人所設定之抵押權本金為5125萬元，並於鈞院96年度執\n      字第25774 號聲請拍賣抵押物強制執行中，要求清償本息\n      達9000萬元以上，其請求顯非合理。\n（三）另案陳抱、陳尾之繼承人陳文忠、陳以諾，曾就被告所提\n      執行之異議之訴程序中，表示被告配偶謝英明所簽發領用\n      北市九信之支票30張，分別交與李金利、陳尾、王簡阿玉\n      、陳抱、金陳寶英，而總金額為7500萬元，有最高法院99\n      年度台上字第485 號裁定書之記載足資引據。據此即可證\n      明，被告主張貸借予原告等之本金總額，與原告事實上所\n      受之金額實有鉅額之差距，雙方就該債權額既有爭執，如\n      不予確定顯有侵害及原告權益之虞，應認原告有確認之利\n      益。蓋被告在拍賣抵押物強制執行程序中，除主張約定之\n      665 萬4375元違約金外，另又主張1848萬4375元之遲延利\n      息，此項請求顯與民法第250 條第1 項及第2 項前段之規\n      定不符，爰一併請求確認以保原告之權益。\n（四）再被告雖主張曾簽發30張總金額6500萬元之支票，作為交\n      付原告數額之證明，惟原告僅僅收到如原告100 年6 月8\n      日民事準備（一）狀附表所示之10張支票，總計僅2742萬\n      5000元，是其餘20張支票被告究竟交予何人？由何人兌領\n      ？請求依民事訴訟法第277 條第1 項規定，命被告舉證以\n      實其說。另本件借貸緣由實原告向李金利等人購買系爭土\n      地後，資金不足，徵得各地主同意提供各人所有土地，由\n      原告向簡金燦醫師借貸，作為原告購買土地之部分價金，\n      分別給付與各地主。期間一切手續向來經原告與簡金燦接\n      洽，故始終認定簡金燦為金主，且所有貸款支票亦概由簡\n      金燦交予原告。基此，究竟被告交予簡金燦幾紙支票？總\n      金額為何？均於被告對系爭土地強制執行時，原告閱卷後\n      始知，其餘20張支票乃被告與簡金燦間另一債權債務問題\n      ，至請斟酌。\n（五）被證一被告向北市九信合作社調取之27張支票影本，除未\n      註明具領票款人之姓名，且因支票雖經背書，多無法辨認\n      ，故請求被告作成表格分別載明具領人姓名、住址等，供\n      作確認。被證二切結書，則僅記載原告、李金利等人為債\n      務人兼設定抵押權之義務，以及同意提供土地為擔保，向\n      被告借貸之事實，毫未載明本件所列李金利等五人，實際\n      借款若干之事實，顯然該切結書與本件之爭點無涉。又因\n      該切結書所簽發之支票計9 張，每張支票影本上雖均經原\n      告、地主5 人及另一連帶債務人陳永明蓋章，然此係簡金\n      燦前此辦理抵押權設定登記持有原告等7 人之印鑑，逕行\n      蓋用於其上，非原告所蓋用。此外，該9 張支票最後一紙\n      支票下方附註欄，註有：「借款新台幣貳仟萬元，在於之\n      前於民國83年3 月24日，經借款人及連帶債務人，當面點\n      收現金」等詞，並非真正，是請被告舉證究於何時、何地\n      、在哪些人在場之下，又將此鉅款交於何人收受，此所謂\n      2000萬元現款，是否以被告所指共簽發30張支票交於借款\n      人收受，其中3 張以現金換回未經兌領云云，究竟為哪3\n      張支票？被證三切結書雖由原告與陳永明具名，表示願以\n      金陳寶英之土地持份及地上物為擔保，請求被告給予貸款\n      ，但並未表示「已」向被告「借到」1500萬元。又該切結\n      書所檢具之支票有8 張，在支票與支票間之騎縫上，蓋章\n      者有原告及陳永明二人，惟其中沒有一張經原告收受兌領\n      。原告曾收受兌領之支票，僅被告所稱發交於簡金燦鈞院\n      卷第185 頁編號12、13面額分別為120 萬、140 萬元之支\n      票2 紙。另被證四切結書檢具之支票6 張，於支票影本邊\n      蓋章者，雖為原告、陳永明、王簡阿玉三人，但其中僅支\n      票號碼CEO531977 ，面額245 萬元之支票，由王簡阿玉收\n      受兌領外，其餘5 張則不知被告或簡金燦交付何人。另被\n      證五之言詞辯論筆錄，並不能否認原告所指五人貸款金額\n      僅2742萬5000元之事實，故被告應具體提出證明事項。\n（六）被告自稱共簽發30張支票之票號、金額、到期日，以及依\n      被告所提兌現銀行供兌領人之背書，表列如附件3 （見本\n      院卷第113 頁）惟其中兌領人與原告或地主毫無關係者，\n      列舉如下：\n   1、編號2，面額200萬元，兌領人呂清朗。\n   2、編號8，面額270萬元，兌領人郭秀端。\n   3、編號14、15、16、19，面額依序分別為90萬元、180 萬元\n      、120 萬元、45萬元，兌領人完全空白，不知係由何人兌\n      領。\n   4、編號17、18、20，面額依序為530 萬元、60萬元、20萬元\n      ，均係由呂月香兌領。\n   5、編號27，面額67萬5000元，兌領者不詳。\n   6、編號28，面額30萬元，兌領者呂月香。\n   7、編號30，面額15萬元，兌領者不詳。\n（七）原告委由簡金燦代為辦理抵押借款時，曾再三言明按照原\n      證1 至原證5 之買賣契約書約定之價款，扣除原告已支付\n      之定金外金額，委由其定抵押貸款，貸得款項直接交於各\n      地主，是以原告確未經手，此項情節除請參酌台北地院檢\n      察署89年度偵字第22990 號不起訴處分書第一項簡金燦證\n      詞可證。被告稱2000萬元現金為支票簽收單所載編號1 至\n      7 之七張支票（見本卷卷第113 頁），由原告等人兌領，\n      惟其中編號1 為李金利、編號3 為陳尾、編號6 為塗銷陳\n      抱抵押權登記代償於王文芬之支票，上開三張支票既為票\n      據，並分別交由上開個人兌領，豈能又指為「當面點收現\n      金新台幣貳仟萬元」，據此，益足證被告所指交付2000萬\n      元云云，並非事實。\n（八）綜上所述，原告於本件有確認之利益。為此，依民事訴訟\n      法第247 條第1 項前段、最高法院42年度台上字第1031號\n      、52 年 度台上字第1237號之判例意旨，聲明：(一)請求確\n      認原告與附表一第2 項各土地所有權人為連帶債務人，就\n      同附表第3項 所載土地，於83年4 月1 日以被告為債權人\n      所設定本金最高限額7500萬元之抵押權設定為擔保實借金\n      額為2625萬元。(二)請求確認前項所載本金，自85年10月21\n      日至99年11月20日止，約定違約金為665 萬4375元，被告\n      另主張遲延利息1848萬4375元之請求權不存在等語。\n二、被告答辯則以：\n（一）原告是否向訴外人李金利等人購買系爭坐落臺北市○○區\n      ○○段三小段第315 號等10筆土地，被告並不知情，亦無\n      法判斷原告所述情節是否真正，況無論原告所述之買賣是\n      否屬實，均與被告無涉，與本訴訟無關。\n（二）原告與訴外人陳永明、李金利、王志銘、陳尾、陳抱、吳\n      陳玉英、金陳寶英、王簡阿玉等，經由簡金燦分別於83年\n      4 、5 月間向被告借款4000萬元、1500萬元、1000萬元，\n      並分別約定違約金每月每萬15元、15元、20元，借款到期\n      日則皆為85年10月20日，並有以下文件可證：\n   1、原告與陳永明、李金利、王志銘、陳尾、陳抱、吳陳玉英\n      等人，以李金利等人之不動產為擔保，向被告借款4000萬\n      元所共同簽具之切結書及支票簽收單（包括現金2000萬元\n      及支票9 張面額合計2000萬元）。\n   2、原告與陳永明持金陳寶英不動產為擔保，向被告借款所簽\n      具之切結書及支票簽收單（包括支票8 張面額合計1500萬\n      元）。\n   3、原告與陳永明持王簡阿玉不動產為擔保，向被告借款簽具\n      之切結書及支票簽收單（包括支票6 張面額合計1000萬元\n      ）。\n   4、準此，原告不否認其於上開切結書上之簽名，而其既共同\n      簽收上開現金及支票並負連帶責任，則其以原證1 至原證\n      5 之土地買賣契約書所載付款紀錄，證明其僅負債2625萬\n      元云云，顯無理由。\n（三）原告主張因被告保管土地所有權狀正本，致其無法辦理系\n      爭土地所有權移轉登記，認原告與李金利等人之契約無法\n      履行，終使貸款之清償發生遲延，應屬可歸責於被告之事\n      由所致云云，與事實不符，蓋被告保管土地所有權狀僅係\n      保全債權之方式，與原告對於系爭借貸能否清償無關，更\n      何況自借貸迄被告前揭聲請執行已逾十餘年，其間原告又\n      何曾提出款項表示清償？至於原告另主張被告請求給付違\n      約金、遲延利息與民法第250 條第1 項、第2 項前段規定\n      不符云云，惟被告請求給付違約金係基於抵押權設定契約\n      書，請求給付遲延利息則係依民法第233 條之規定，兩者\n      並無衝突。此外，按確認之訴，依民事訴訟法第247 條規\n      定，除確認證書真偽或為法律關係基礎事實存否之訴外，\n      以確認法律關係始得提起，原告起訴請求確認債務額，於\n      法不合，其訴之聲明亦不明確。\n（四）被證一至被證四中有關原告吳宛玉之簽名及印文均為一致\n      ，支票背面都有原告之背書，背書之印文也完全相同，然\n      原告僅承認被證二、三、四上之簽名及印文為真正，執詞\n      否認其他文件之真實，顯無理由而不可採信。另臺灣臺北\n      地方法院96年度訴字第7399號債務人異議之訴乙案，就被\n      告確實有給付借款之事實，及被證一27張支票交予原告吳\n      宛玉等人簽收兌現等情，均已認定明確，此有臺灣臺北地\n      方法院96年度訴字第7399號民事判決、臺灣高等法院97年\n      度重上字第621 號民事判決、最高法院99年度台上字第48\n      5 號民事裁定可稽，原告執詞否認支票簽收印文真正，係\n      屬臨訟卸責不可採信。\n（五）被證五臺北地方法院100 年2 月15日言詞辯論筆錄第6 頁\n      第15行所提示之「被證1 支票簽收單」即為本件被證四第\n      2 頁之「支票簽收單」，筆錄中原告除出庭證稱支票上「\n      吳宛玉」之簽名為其本人所簽之外，又再接續問到：「上\n      開簽收單上也有王簡阿玉的指印，是否她本人所為？」證\n      人即原告證稱：「是王簡阿玉的夫妻在一起，是王簡阿玉\n      本人或她先生蓋指印，我不清楚」、「就王簡阿玉夫妻在\n      場，誰簽名、蓋指印，我也沒有仔細看。」從而被告提出\n      之被證二、被證三、被證四所檢附之切結書及支票簽收單\n      ，均有原告之簽名蓋章作為簽收憑據，原告在上開言詞辯\n      論筆錄也承認「支票簽收單」上「吳宛玉」簽名為其本人\n      所為，已足證明原告分別與其他債務人共同簽收取得該支\n      票，原告以事前不知又未經手等語置辯，顯然不實。再縱\n      如原告所稱乃簡金燦事後要求原告補簽乙節屬實，而原告\n      既已簽署，自屬認同其相關內容，不影響其相關責任之判\n      斷。\n（六）被證三之切結書及支票簽收單既經原告簽名蓋章，即足以\n      證明原告向被告借款1500萬，並收取被告用以交付借款之\n      支票；至原告簽收支票後，又將支票交給何人，已與被告\n      無涉，被告亦無權干預，是原告已非其兌領云云，完全無\n      視於支票簽收單上所記載之「茲收到上項第九信用合作社\n      營業部支票捌張面額合計新台幣壹仟伍佰萬元正，業已辦\n      妥抵押權設定登記在案，確實無誤。收款人：吳宛玉」此\n      外，王簡阿玉是否收受被證四切結書編號21號支票，被告\n      不得而知，惟王簡阿玉與原告既共同收受該支票簽收單上\n      所列之支票6 張，則渠等於共同簽收該6 張支票後，如何\n      分配取得支票，與被告無關，被告也無權過問，原告以其\n      他5 張不知被告或簡金燦交給何人云云，顯有誤解，被告\n      沒有舉證之義務。另原告指稱未曾收受2000萬元部分，有\n      鈞院卷第220 頁附表二編號1-7 之支票，該7 紙支票面額\n      合計即2000萬元，前經原告、陳永明、陳抱、陳尾、李金\n      利、吳陳玉英等人於83年4 月6 日共同簽收，並分別於其\n      後數日內兌現，有支票簽收單可證（被證七），足證原告\n      及陳永明等人確已共同取得2000萬元款項，因該金額已經\n      包括其後簽署之被證二支票簽收單所載「總款項新臺幣肆\n      仟萬元整」之內，所以在執行程序，被告即未再就該支票\n      簽收單提出作為債權憑證。原告在其99年6 月4 日寄予被\n      告之台北光武郵局第499 號存證信函，自承「民國83年間\n      與本人向台端所借之款項... 需還款新台幣陸仟伍佰萬元\n      正... 」可見原告其實也自己承認該6500萬元債務之存在\n      。\n（七）臺灣臺北地方法院99年度重訴字第995 號債務人異議之訴\n      事件之爭點為抵押權設定登記是否有效存在，而本件原告\n      則請求確認兩造間債務總額，二件似無牽涉。原告於上開\n      案件中作證，證詞亦與本件無關；惟訴外人王信狀於99年\n      12月17日親自出庭陳稱：「簽定這個契約時，吳宛玉叫謝\n      劉碧霞拿支票給我們，支票金額多少我忘記了，交了幾張\n      支票我也忘了，需要看契約才會知道」。對問：「吳宛玉\n      跟你媽媽買土地，前後共付多少錢給你媽媽？」答：「一\n      仟多萬，價金已付清了」可證被告在完成抵押權設定登記\n      後，係直接按原告與各業主間之買賣契約所約定，直接將\n      支票交給各業主，代替原告之給付。易言之，被告對系爭\n      土地各業主之貸款，係由被告之代理人簡金燦直接交予各\n      業主，原告確無經手之事實。且被告曾於上開案件中，自\n      認證明被告所簽發之30張支票，均交於其代理人簡金燦，\n      然後分交於系爭土地各業主。\n（八）李金利於100 年8 月17日經傳訊到庭，雖就相關借款過程\n      大多以不復記憶或「沒有」來回應，惟其亦不否認有取得\n      600 萬元之事實。再審視證人當庭於證人結文上之簽名筆\n      跡與被證二切結書上之簽名筆跡，其形式、筆劃亦極為相\n      似，再加上其自承當時亦取得部分款項，自可推認被證二\n      之文件確為其簽署。\n（九）為此，聲明請駁回原告之訴。\n三、兩造不爭執之事實：\n（一）原告與訴外人李金利、陳尾、陳抱、王簡阿玉、金陳寶英\n      簽訂不動產買賣契約，約定各出賣其所有如附表二所示坐\n      落臺北市○○區○○段3 小段第315 及315 之1 至9 地號\n      等10筆土地予原告。（見台灣台北地方法院100 年度重訴\n      字第239 號卷第11頁至20頁）。\n（二）上開10筆土地之登記簿謄本之他項權利部記載：訴外人李\n      金利、陳尾、陳抱、王簡阿玉、金陳寶英各以其所有之上\n      開土地之應有部分，分別為被告設定2000萬、1100萬、11\n      00萬、1300萬、2000萬，共計7500萬元之本金最高限額抵\n      押權，以擔保李金利、陳尾、陳抱、吳宛玉、陳永明等人\n      在抵押權範圍內之一切債務，並辦妥抵押權登記在案。各\n      該抵押權約定存續期間分別自83年3 月25日起至84年3 月\n      24日止、自83年3 月25日起至84年3 月24日止、自83年4\n      月6 日起至84年4 月10日止、自83年4 月29日起至84年5\n      月1 日止、自83年5 月23日起至84年5 月22日止，清償日\n      期除金陳寶英所提供擔保之土地為84年5 月22日外，其餘\n      清償日期均依各個契約約定，並有臺北市土地登記第二類\n      謄本附卷可稽（見本院卷第23頁至111 頁）。\n（三）被告持上開最高限額抵押權執行名義，曾於96年間以臺灣\n      臺北地方法院96年度執字第25774 號聲請拍賣抵押物強制\n      執行。\n（四）原告曾收受兌領由謝英明簽發，被告交付之貸款支票，支\n      票號碼為CE0000000 、CE0000000 ，發票日期83年4 月12\n      日，票面金額分別為120 萬元、140 萬元。\n（五）如附表一第二項所示之陳以諾為陳尾之繼承人；陳以忠、\n      陳三郎、林玉葉、林兩傳、林治郎、陳榮生、陳振賢、倪\n      陳淑珍為陳抱之繼承人；王信雄、王信壯、王金鳳、王阿\n      足則為王簡阿玉之繼承人。\n四、本件爭點與本院判斷：\n    原告主張伊與訴外人李金利等人訂立系爭土地買賣契約，並\n    以系爭土地為向被告借款之擔保，設定本金最高限額7500萬\n    元抵押權予被告，惟原告與李金利等人僅收受被告所簽發之\n    支票金額共計2482萬5000元，加計原告陸續向被告借得142\n    萬5000元之借款，合計為2625萬元等情，為被告所否認，並\n    以上開情詞置辯，經查：本件原告於82年10月30日、12月4\n    日、83年4 月19日、4 月30日分別與訴外人陳抱、陳尾、李\n    金利、王簡阿玉、金陳寶英簽訂不動產買賣契約，約定各出\n    賣陳抱等人所有如附表二所示坐落臺北市○○區○○段3 小\n    段第315 及315 之1 至9 地號等10筆土地之應有部分。訴外\n    人李金利、陳尾、陳抱、王簡阿玉、金陳寶英分別於83年4\n    月1 日、4 月11日、5 月4 日、5 月25日以其所有上開土地\n    應有部分，擔保李金利陳尾、陳抱分別與原告及訴外人陳永\n    明共同向被告借款，分別為被告設定2000萬元、1100萬元、\n    1100萬元、1300萬元、2000萬元，共計7,500 萬元之本金最\n    高限額抵押權，以擔保李金利、陳尾、陳抱、吳宛玉、陳永\n    明等人在抵押權範圍內之一切債務，並辦妥抵押權登記在案\n    。各該抵押權約定存續期間分別自83年3 月25日起至84年3\n    月24日止、自83年3 月25日起至84年3 月24日止、自83年4\n    月6 日起至84年4 月10日止、自83年4 月29日起至84年5 月\n    1 日止、自83年5 月23日起至84年5 月22日止，清償日期除\n    金陳寶英所提供擔保之土地為84年5 月22日外，其餘清償日\n    期均依各個契約約定。又如附表一第一項所示之陳以諾為陳\n    尾之繼承人；陳以忠、陳三郎、林玉葉、林兩傳、林治郎、\n    陳榮生、陳振賢、倪陳淑珍為陳抱之繼承人；王信雄、王信\n    壯、王金鳳、王阿足則為王簡阿玉之繼承人等事實，為兩造\n    所不爭執，並有臺北市土地登記第二類謄本附卷可稽（見本\n    院卷第23頁至111 頁），堪信為真。\n    本件應審究之爭點厥為：（一）上開抵押權所擔保之債權是\n    否存在？原告與訴外人李金利等人分別共同向被告借貸之金\n    額總共為多少？被告是否已交付由原告等人簽收？（二）原\n    告與訴外人李金利等人分別共同向被告所借得之款項，應否\n    負連帶清償責任？（三）被告向原告等人除得請求約定之違\n    約金外，是否仍得請求遲延利息1848萬4375元？本院之判斷\n    如下：\n（一）上開抵押權所擔保之債權是否存在？原告等人分別共同向\n      被告借貸之金額總共為多少？被告是否已交付由原告等人\n      簽收？\n    1.系爭抵押權為最高限額抵押，所謂最高限額之抵押契約，\n      係指所有人提供抵押物，與債權人訂立在一定金額之限度\n      內，擔保現在已發生及將來可能發生之債權之抵押權設定\n      契約而言。此種抵押權所擔保之債權，除定約時已發生之\n      債權外，即將來發生之債權，在約定限額之範圍內，亦為\n      抵押權效力所及。雖抵押權存續期間內已發生之債權，因\n      清償或其他事由而減少或消滅，原訂立之抵押契約依然有\n      效，嗣後在存續期間內陸續發生之債權，債權人仍得對抵\n      押物行使權利（最高法院66年臺上字第1097號判例參照）\n      。又按抵押權所擔保之債權，其種類及範圍，屬於抵押權\n      之內容，依法應經登記，始生物權之效力，但如因內容過\n      於冗長，登記簿所列各欄篇幅不能容納記載，可以附件記\n      載，作為登記簿之一部分。因此關於最高限額抵押權所擔\n      保之債權，雖未記載於土地登記簿，然於聲請登記時提出\n      之最高限額抵押權設定契約書，有該項債權之記載者，此\n      契約書既作為登記簿之附件，自為抵押權效力所及（最高\n      法院84年臺上字第1967號判例參照）。\n   2、本件系爭最高限額抵押權係擔保原告及訴外人李金利、陳\n      尾、陳抱、陳永明之債務，原告與訴外人陳永明為連帶債\n      務人，此有被告所提原告與陳永明、李金利、陳尾等人分\n      別所書立之切結書3 紙及系爭土地登記第二類謄本土地他\n      項權利部債務人及債務額比例欄所載在卷可佐（見本院卷\n      第23頁至112 頁、第168 頁至171 頁、第175 頁及178 頁\n      ），並為原告所不爭（見本院100 年6 月29日及9 月8 日\n      言詞辯論筆錄），又依原告等人所書立之切結書載明約定\n      擔保債權包括：「將來所負之借據、票據、保證、損害賠\n      償等及其他一切債務」，是兩造係明定以借款、票據、保\n      證、違約金債務等債權債務關係，作為系爭最高限額抵押\n      權從屬之基礎法律關係。\n   3、本件原告主張僅向被告借得2625萬元云云，被告則抗辯已\n      交付台北市第九信用合作社支票30張予原告等人簽收，金\n      額共計6500萬元，並已全部兌領等語，兩造所爭執之借貸\n      關係乃發生於83年間，此有兩造所不爭之上開切結書所載\n      日期可按，依實體從舊原則，兩造有關借款爭執部分，自\n      應適用修正前民法關於消費借貸之規定。而稱消費借貸者\n      ，謂當事人一方移轉金錢或其他代替物之所有權於他方，\n      而約定他方以種類、品質、數量相同之物返還之契約，民\n      法第474 條第1 項定有明文。又金錢借貸契約固屬要物契\n      約，應由貸與人就交付金錢之事實負舉證之責，但若貸與\n      人提出之借用證內，經載明借款額，當日親收足訖無訛者\n      ，應解為貸與人就要物性之具備，已盡舉證責任，最高法\n      院69年台上字第3546號判號例意旨可資參照，雖該判例嗣\n      因民法第474 條文字之修正而經該院決議刪除，然係顧慮\n      原條文用語易遭誤會消費借貸契約係諾成契約而予修正，\n      前開根據修正前法條所作成之判例因而隨之刪除，惟無論\n      修法前後對借貸契約既均採要物契約見解（最高法院90年\n      第4 次民事庭會議決議參照）。則上開判例有關要物性舉\n      證責任之歸屬之闡釋於法理上既無瑕疵，自仍得資為本件\n      參酌之依據，故就已交付金錢之事實，應由被告負舉證責\n      任。經查：\n    被告抗辯原告與訴外人陳永明、李金利、陳尾、陳抱、金\n      陳寶英、王簡阿玉等人，經由簡金燦分別於83年4 、5 月\n      間向被告借款4000萬元、1500萬元、1000萬元，並分別約\n      定違約金每月每萬15元、15元、20元，借款到期日則皆為\n      85年10月20日，由被告之夫謝英明為發票人，以台北市第\n      九信用合作社為付款人，簽發如附表三所示之支票30張交\n      付原告等人簽收，除其中附表編號15、19及27嗣後由被告\n      以現金換回外，其餘均已兌現之事實，已據被告提出原告\n      等人所簽具之切結書3 紙及借款證明（支票簽收單）4 紙\n      及支票30張影本、台北市第九信用合作社97年3 月12日北\n      市九信社業字第0383號函影本1 份為證（本院卷第168 頁\n      至179 頁、第226 頁、第131 頁至167 頁），而觀之該切\n      結書及依借款證明上均有原告之簽名及蓋章，原告雖否認\n      借款證明（支票簽收單）上之簽名為其所簽，惟查：原告\n      於台灣台北地方法院99年度重訴字第995 號債務人異議之\n      訴事件作證時，證稱：「（被告訴訟代理人問：（請提示\n      被證1 支票簽收單）上面的吳宛玉簽名是否是你本人所簽\n      ？）答：是我簽的：：：」等語（該院卷第130 頁背面）\n      ，經核與其他3 紙借款證明（支票簽收單）之吳宛玉簽名\n      ，其筆勢、筆順經目視尚難看出有何相異之處，且原告對\n      於切結書上之簽名亦不爭執為其所親簽，再徵之原告於99\n      年6 月4 日所寄給被告之存證信函，亦自承：「於民國83\n      年間（李金利等人）與本人間向台端所借之款項，約半年\n      前我們雙方已達共識，需還款陸仟伍佰萬元正」等語（本\n      院卷第227 頁），被告主張該4 紙借款證明（支票簽收單\n      ）係原告所簽之事實，堪信為真。\n    又依借款證明（支票簽收單），其上分別載明：「（就如\n      附表三編號1 至7 所示支票號碼CE0000000 號至CE000000\n      0 號等7 張支票部分）茲借款人（承買人）吳宛玉、提供\n      擔保義務人兼債務人陳抱、陳尾、李金利、吳陳玉英於民\n      國83年4 月6 日向債權人謝劉碧霞借款新台幣貳仟萬元，\n      ……經借款人與義務人兼債務人及連帶債務人當面點收現\n      金事實無誤……簽收1.吳宛玉、陳永明。2.陳抱。3.陳尾\n      、李金利。」、「（就如附表三編號8 至16所示支票號碼\n      CE0000000 號至CE0000000 號等9 張支票部分）本件前順\n      位私人（民間）借貸（代還前胎）清償向債權人謝劉碧霞\n      借款新台幣貳仟萬元整，在於之前於民國83年3 月24日經\n      借款人及連帶債務人當面點收現金新台幣貳仟萬元整，計\n      總款額新台幣肆仟萬元整事實無誤……簽收李金利、王志\n      銘、吳陳玉英、陳抱、陳永明、吳宛玉、陳尾」等文字（\n      見本院卷第226 頁、第174 頁），另附表三編號17至22號\n      之支票6 張，金額合計1000萬元，由原告及訴外人陳永明\n      、王簡阿玉等3 人簽收；附表三編號23至30所示8 張支票\n      ，金額合計1500萬元，由原告吳宛玉、陳永明等2 人簽收\n      ，此部分亦有原告吳宛玉所簽具之借款證明（支票簽收單\n      ）2 紙及支票影本在卷可憑（本院卷第176 至177 頁、第\n      179 頁），除編號15、19及27嗣後由被告以現金換回外，\n      其餘均已兌現，亦有台北市第九信用合作社97年3 月12日\n      函附於本院依職權調取之台灣台北地方法院96年度訴字第\n      7399號卷可按（該院卷第204 至243 頁，另本院卷131 頁\n      至167 頁亦附有影本）；稽之上開支票背面分別有訴外人\n      李金利、陳抱、陳尾、陳永明、吳宛玉等人蓋章背書，顯\n      見原告等人已分別簽收如附表三所示之系爭支票30張，其\n      中編號15、19及27，則由被告以現金換回，其餘則均已兌\n      現，堪以認定。從而，被告所辯其交付原告等人簽收之支\n      票業經提示且已兌現，其有交付款項之事實，堪予採信。\n   4、原告與訴外人李金利等人分別共同向被告借款，被告並已\n      交付如附表三所示之支票，除其中編號15、19及27嗣後由\n      被告以現金換回外，其餘均已兌現，已如前述，並參酌原\n      告於99年6 月4 日所寄給被告之存證信函，自承需還款新\n      臺幣陸仟伍佰萬元正等語，被告抗辯原告等人係向其借款\n      6500萬元等語，堪信為真。被告所辯僅向被告借得2625萬\n      元云云，則不足採信。\n（二）原告與訴外人李金利等人分別共同向被告所借得之款項，\n      應否負連帶清償責任？\n   1、按「數人負同一債務，明示對於債權人各負全部給付之責\n      任者，為連帶債務。」「連帶債務之債權人，得對於債務\n      人中之一人或數人或其全體，同時或先後請求全部或一部\n      之給付。連帶債務未全部履行前，全體債務人仍負連帶責\n      任。」民法第272條第1項、第273條分別定有明文。\n   2、本件原告就其與訴外人陳永明、李金利等人分別共同向被\n      告借款，共計6500萬元，而為借款債務人，及與訴外人陳\n      永明、李金利、陳尾、陳抱為連帶債務人，此有上開原告\n      簽名之切結書、借款證明（支票簽收單）及土地建築改良\n      物抵押權設定約定書1 份（見台灣台北地方法院100 年度\n      重訴字第239 號卷第29頁至36頁）可證，且為原告所自承\n      （見本院100 年9 月8 日言詞辯論筆錄），依民法第272\n      條第1 項規定，原告與陳永明、李金利、陳尾、陳抱等人\n      就各別共同之系爭債務，對被告各負全部給付之責任；又\n      系爭抵押權係擔保原告及陳永明、李金利、陳尾、陳抱等\n      人對被告之債務，有土地登記第二類謄本可稽，則原告與\n      訴外人陳永明等人間之其中任一人對被告之債務均為系爭\n      抵押權擔保範圍，其內部如何分配或處分系爭借款，非被\n      告所得過問，原告縱未現實受領款項，基於其連帶債務人\n      地位，仍不能因此免責，即訴外人李金利等人對被告之債\n      務亦屬系爭抵押權擔保範圍；而系爭支票均經原告之簽收\n      簽名蓋章，並均有原告與訴外人陳永明之背書，已如前述\n      ，則原告以其未實際收受支票款項為由，主張其對被告所\n      負之債務僅2625萬元云云，不足酌採。\n（三）被告向原告等人除得請求約定之違約金外，是否仍得請求\n      遲延利息1848萬4375元？\n      原告主張被告在台灣台北地方法院96年度執進字第25774\n      號拍賣抵押物強制執行程序中，除主張約定之665 萬4375\n      元違約金外，另又主張1848萬4375元之遲延利息，此項請\n      求顯與民法第250 條第1 項及第2 項前段之規定不符，爰\n      一併請求確認以保原告之權益等語，惟為被告所否認，辯\n      稱：被告請求給付違約金係基於抵押權設定契約書，請求\n      給付遲延利息則係依民法第233 條之規定，兩者並無衝突\n      等語。按「違約金，有屬於懲罰之性質者，有屬於損害賠\n      償約定之性質者，本件違約金如為懲罰之性質，於上訴人\n      履行遲延時，被上訴人除請求違約金外，固得依民法第二\n      百三十三條規定，請求給付遲延利息及賠償其他之損害，\n      如為損害賠償約定之性質，則應視為就因遲延所生之損害\n      ，業已依契約預定其賠償，不得更請求遲延利息賠償損害\n      。」最高法院62年台上字第1394號著有判例可資參照。經\n      查：本件原告於上揭日期分別與訴外人陳抱、陳尾、李金\n      利、王簡阿玉、金陳寶英簽訂不動產買賣契約，約定各出\n      賣陳抱等人所有坐落臺北市○○區○○段3 小段第315 及\n      315 之1 至9 地號等10筆土地之應有部分。訴外人李金利\n      、陳尾、陳抱、王簡阿玉、金陳寶英分別於83年4 月1 日\n      、4 月11日、5 月4 日、5 月25日以其所有上開土地應有\n      部分，擔保李金利陳尾、陳抱分別與原告及訴外人陳永明\n      共同向被告借款，分別為被告設定2000萬元、1100萬元、\n      1100萬元、1300萬元、2000萬元，共計7,500 萬元之本金\n      最高限額抵押權，以擔保李金利、陳尾、陳抱、吳宛玉、\n      陳永明等人在抵押權範圍內之一切債務，並辦妥抵押權登\n      記在案等情，已如前述，而觀之抵押權設定契約書，固僅\n      記載違約金，而無遲延利息之記載，有該抵押權設定契約\n      書1 份附卷可按（見台灣台北地方法院100 年度重訴字第\n      239 號卷第29頁至36頁），惟此部分係有關抵押權效力所\n      及之約定，亦即抵押權之效力及於本金及違約金。而依上\n      開抵押權設定契約書所約定之違約金，係依每百元日息一\n      角五分計算，即每月每萬元15元，核其性質應屬懲罰違約\n      金，並非損害賠償約定之性質。依上開最高法院判例意旨\n      ，被告於原告等人履行遲延時，被告除請求違約金外，固\n      得依民法第233 條規定，請求給付遲延利息及賠償其他之\n      損害。又原告等人向被告借款之清償期，均為85年10月20\n      日，為兩造所不爭，則被告請求原告與李金利、陳尾、陳\n      抱等人分別共同向被告借款之部分，本金尚欠2625萬元，\n      違約金自85年10月21日起至99年11月20日止，每月每萬元\n      15元計算，共計665 萬4375元；遲延利息自85年10月21日\n      起至99年11月20日止，按年息百分之5 計算之利息，共計\n      1848萬4375元，有原告所提借款本金、遲延利息及約定違\n      約金計算表可佐（見台灣台北地方法院100 年度重訴字第\n      239 號卷第21頁），尚非無據，原告主張被告之遲延利息\n      1848萬4375元請求權不存在云云，並不足採。\n五、綜上，原告請求確認(一)請求確認原告與附表一第二項各土地\n    所有權人為連帶債務人，就同附表第三項所載土地，於83年\n    4 月1 日以被告為債權人所設定本金最高限額7500萬元之抵\n    押權設定為擔保實借金額為2625萬元。(二)請求確認前項所載\n    本金，自85年10月21日至99年11月20日止，約定違約金為66\n    5 萬4375元，被告另主張遲延利息1848萬4375元之請求權不\n    存在，為無理由，應予駁回。\n六、本件事證已臻明確，兩造其餘攻擊防禦方法暨舉證，經核與\n    判決結果不生影響，爰不一一論列，併此敘明。\n七、結論：原告之訴為無理由，依民事訴訟法第78條，判決如主\n    文。\n中    華    民    國   100    年    9     月    29    日\n                  民事第三庭  法  官  林錫凱\n以上正本係照原本作成\n如對本判決上訴，須於判決送達後20日內向本院提出上訴狀。如\n委任律師提起上訴者，應一併繳納上訴審裁判費。\n中    華    民    國   100    年    9     月    29    日\n                              書記官  王小芬",
  "structure": {
    "main": "原告之訴駁回。\n訴訟費用由原告負擔。",
    "fact": "一、原告起訴主張：\n（一）原告於民國82年10月間向訴外人李金利、陳抱、陳尾、王\n      簡阿玉、金陳寶英等人分別購買如附表二所示坐落臺北市\n      中正區○○段○ ○段第315 及315 之1 至9 地號等10筆土\n      地（下稱系爭土地）。83年3 月間，訴外人簡金燦得知原\n      告購買系爭土地，即向原告佯稱有款項可借原告並以系爭\n      土地為擔保，原告徵得系爭土地之所有人即訴外人李金利\n      陳抱、陳尾、王簡阿玉、金陳寶英等人之同意，即將土地\n      所有權狀、印鑑證明書及印章交給簡金燦辦理貸款，並交\n      由委任之代書辦理設定最高限額抵押權；惟簡金燦實際係\n      向本件被告借款，並擅自將系爭土地完成本金最高限額新\n      臺幣（下同）7500萬元之最高限額抵押權登記予被告，並\n      將借得款項分別以被告簽發之九信支票給付與訴外人李金\n      利、陳抱、陳尾、王簡阿玉、金陳寶英等人，核算渠等收\n      受之支票總金額為2482萬5000元，加計原告陸續向被告借\n      得142 萬5000元之借款，合計為2625萬元。\n（二）簡金燦辦理前揭抵押權設定，設定期限一年，即自83 年3\n      月25日至84年3 月24日止，並將數十張系爭土地所有權狀\n      正本、印鑑章等交予被告保管，嗣被告為防止土地登記所\n      有權人李金利等人再設定次順位抵押權，影響其貸款之回\n      收，竟拒絕返還上開土地所有權狀正本、印鑑章，致原告\n      與李金利等人間之契約無法履行，無法將系爭土地移轉登\n      記予原告，終使貸款之清償發生遲延，此應歸責於被告之\n      事由所致。多年前原告即多次要求被告協調清償前開欠款\n      ，但被告堅持李金利、陳抱、陳尾、王簡阿玉、金陳寶英\n      等人所設定之抵押權本金為5125萬元，並於鈞院96年度執\n      字第25774 號聲請拍賣抵押物強制執行中，要求清償本息\n      達9000萬元以上，其請求顯非合理。\n（三）另案陳抱、陳尾之繼承人陳文忠、陳以諾，曾就被告所提\n      執行之異議之訴程序中，表示被告配偶謝英明所簽發領用\n      北市九信之支票30張，分別交與李金利、陳尾、王簡阿玉\n      、陳抱、金陳寶英，而總金額為7500萬元，有最高法院99\n      年度台上字第485 號裁定書之記載足資引據。據此即可證\n      明，被告主張貸借予原告等之本金總額，與原告事實上所\n      受之金額實有鉅額之差距，雙方就該債權額既有爭執，如\n      不予確定顯有侵害及原告權益之虞，應認原告有確認之利\n      益。蓋被告在拍賣抵押物強制執行程序中，除主張約定之\n      665 萬4375元違約金外，另又主張1848萬4375元之遲延利\n      息，此項請求顯與民法第250 條第1 項及第2 項前段之規\n      定不符，爰一併請求確認以保原告之權益。\n（四）再被告雖主張曾簽發30張總金額6500萬元之支票，作為交\n      付原告數額之證明，惟原告僅僅收到如原告100 年6 月8\n      日民事準備（一）狀附表所示之10張支票，總計僅2742萬\n      5000元，是其餘20張支票被告究竟交予何人？由何人兌領\n      ？請求依民事訴訟法第277 條第1 項規定，命被告舉證以\n      實其說。另本件借貸緣由實原告向李金利等人購買系爭土\n      地後，資金不足，徵得各地主同意提供各人所有土地，由\n      原告向簡金燦醫師借貸，作為原告購買土地之部分價金，\n      分別給付與各地主。期間一切手續向來經原告與簡金燦接\n      洽，故始終認定簡金燦為金主，且所有貸款支票亦概由簡\n      金燦交予原告。基此，究竟被告交予簡金燦幾紙支票？總\n      金額為何？均於被告對系爭土地強制執行時，原告閱卷後\n      始知，其餘20張支票乃被告與簡金燦間另一債權債務問題\n      ，至請斟酌。\n（五）被證一被告向北市九信合作社調取之27張支票影本，除未\n      註明具領票款人之姓名，且因支票雖經背書，多無法辨認\n      ，故請求被告作成表格分別載明具領人姓名、住址等，供\n      作確認。被證二切結書，則僅記載原告、李金利等人為債\n      務人兼設定抵押權之義務，以及同意提供土地為擔保，向\n      被告借貸之事實，毫未載明本件所列李金利等五人，實際\n      借款若干之事實，顯然該切結書與本件之爭點無涉。又因\n      該切結書所簽發之支票計9 張，每張支票影本上雖均經原\n      告、地主5 人及另一連帶債務人陳永明蓋章，然此係簡金\n      燦前此辦理抵押權設定登記持有原告等7 人之印鑑，逕行\n      蓋用於其上，非原告所蓋用。此外，該9 張支票最後一紙\n      支票下方附註欄，註有：「借款新台幣貳仟萬元，在於之\n      前於民國83年3 月24日，經借款人及連帶債務人，當面點\n      收現金」等詞，並非真正，是請被告舉證究於何時、何地\n      、在哪些人在場之下，又將此鉅款交於何人收受，此所謂\n      2000萬元現款，是否以被告所指共簽發30張支票交於借款\n      人收受，其中3 張以現金換回未經兌領云云，究竟為哪3\n      張支票？被證三切結書雖由原告與陳永明具名，表示願以\n      金陳寶英之土地持份及地上物為擔保，請求被告給予貸款\n      ，但並未表示「已」向被告「借到」1500萬元。又該切結\n      書所檢具之支票有8 張，在支票與支票間之騎縫上，蓋章\n      者有原告及陳永明二人，惟其中沒有一張經原告收受兌領\n      。原告曾收受兌領之支票，僅被告所稱發交於簡金燦鈞院\n      卷第185 頁編號12、13面額分別為120 萬、140 萬元之支\n      票2 紙。另被證四切結書檢具之支票6 張，於支票影本邊\n      蓋章者，雖為原告、陳永明、王簡阿玉三人，但其中僅支\n      票號碼CEO531977 ，面額245 萬元之支票，由王簡阿玉收\n      受兌領外，其餘5 張則不知被告或簡金燦交付何人。另被\n      證五之言詞辯論筆錄，並不能否認原告所指五人貸款金額\n      僅2742萬5000元之事實，故被告應具體提出證明事項。\n（六）被告自稱共簽發30張支票之票號、金額、到期日，以及依\n      被告所提兌現銀行供兌領人之背書，表列如附件3 （見本\n      院卷第113 頁）惟其中兌領人與原告或地主毫無關係者，\n      列舉如下：\n   1、編號2，面額200萬元，兌領人呂清朗。\n   2、編號8，面額270萬元，兌領人郭秀端。\n   3、編號14、15、16、19，面額依序分別為90萬元、180 萬元\n      、120 萬元、45萬元，兌領人完全空白，不知係由何人兌\n      領。\n   4、編號17、18、20，面額依序為530 萬元、60萬元、20萬元\n      ，均係由呂月香兌領。\n   5、編號27，面額67萬5000元，兌領者不詳。\n   6、編號28，面額30萬元，兌領者呂月香。\n   7、編號30，面額15萬元，兌領者不詳。\n（七）原告委由簡金燦代為辦理抵押借款時，曾再三言明按照原\n      證1 至原證5 之買賣契約書約定之價款，扣除原告已支付\n      之定金外金額，委由其定抵押貸款，貸得款項直接交於各\n      地主，是以原告確未經手，此項情節除請參酌台北地院檢\n      察署89年度偵字第22990 號不起訴處分書第一項簡金燦證\n      詞可證。被告稱2000萬元現金為支票簽收單所載編號1 至\n      7 之七張支票（見本卷卷第113 頁），由原告等人兌領，\n      惟其中編號1 為李金利、編號3 為陳尾、編號6 為塗銷陳\n      抱抵押權登記代償於王文芬之支票，上開三張支票既為票\n      據，並分別交由上開個人兌領，豈能又指為「當面點收現\n      金新台幣貳仟萬元」，據此，益足證被告所指交付2000萬\n      元云云，並非事實。\n（八）綜上所述，原告於本件有確認之利益。為此，依民事訴訟\n      法第247 條第1 項前段、最高法院42年度台上字第1031號\n      、52 年 度台上字第1237號之判例意旨，聲明：(一)請求確\n      認原告與附表一第2 項各土地所有權人為連帶債務人，就\n      同附表第3項 所載土地，於83年4 月1 日以被告為債權人\n      所設定本金最高限額7500萬元之抵押權設定為擔保實借金\n      額為2625萬元。(二)請求確認前項所載本金，自85年10月21\n      日至99年11月20日止，約定違約金為665 萬4375元，被告\n      另主張遲延利息1848萬4375元之請求權不存在等語。\n二、被告答辯則以：\n（一）原告是否向訴外人李金利等人購買系爭坐落臺北市○○區\n      ○○段三小段第315 號等10筆土地，被告並不知情，亦無\n      法判斷原告所述情節是否真正，況無論原告所述之買賣是\n      否屬實，均與被告無涉，與本訴訟無關。\n（二）原告與訴外人陳永明、李金利、王志銘、陳尾、陳抱、吳\n      陳玉英、金陳寶英、王簡阿玉等，經由簡金燦分別於83年\n      4 、5 月間向被告借款4000萬元、1500萬元、1000萬元，\n      並分別約定違約金每月每萬15元、15元、20元，借款到期\n      日則皆為85年10月20日，並有以下文件可證：\n   1、原告與陳永明、李金利、王志銘、陳尾、陳抱、吳陳玉英\n      等人，以李金利等人之不動產為擔保，向被告借款4000萬\n      元所共同簽具之切結書及支票簽收單（包括現金2000萬元\n      及支票9 張面額合計2000萬元）。\n   2、原告與陳永明持金陳寶英不動產為擔保，向被告借款所簽\n      具之切結書及支票簽收單（包括支票8 張面額合計1500萬\n      元）。\n   3、原告與陳永明持王簡阿玉不動產為擔保，向被告借款簽具\n      之切結書及支票簽收單（包括支票6 張面額合計1000萬元\n      ）。\n   4、準此，原告不否認其於上開切結書上之簽名，而其既共同\n      簽收上開現金及支票並負連帶責任，則其以原證1 至原證\n      5 之土地買賣契約書所載付款紀錄，證明其僅負債2625萬\n      元云云，顯無理由。\n（三）原告主張因被告保管土地所有權狀正本，致其無法辦理系\n      爭土地所有權移轉登記，認原告與李金利等人之契約無法\n      履行，終使貸款之清償發生遲延，應屬可歸責於被告之事\n      由所致云云，與事實不符，蓋被告保管土地所有權狀僅係\n      保全債權之方式，與原告對於系爭借貸能否清償無關，更\n      何況自借貸迄被告前揭聲請執行已逾十餘年，其間原告又\n      何曾提出款項表示清償？至於原告另主張被告請求給付違\n      約金、遲延利息與民法第250 條第1 項、第2 項前段規定\n      不符云云，惟被告請求給付違約金係基於抵押權設定契約\n      書，請求給付遲延利息則係依民法第233 條之規定，兩者\n      並無衝突。此外，按確認之訴，依民事訴訟法第247 條規\n      定，除確認證書真偽或為法律關係基礎事實存否之訴外，\n      以確認法律關係始得提起，原告起訴請求確認債務額，於\n      法不合，其訴之聲明亦不明確。\n（四）被證一至被證四中有關原告吳宛玉之簽名及印文均為一致\n      ，支票背面都有原告之背書，背書之印文也完全相同，然\n      原告僅承認被證二、三、四上之簽名及印文為真正，執詞\n      否認其他文件之真實，顯無理由而不可採信。另臺灣臺北\n      地方法院96年度訴字第7399號債務人異議之訴乙案，就被\n      告確實有給付借款之事實，及被證一27張支票交予原告吳\n      宛玉等人簽收兌現等情，均已認定明確，此有臺灣臺北地\n      方法院96年度訴字第7399號民事判決、臺灣高等法院97年\n      度重上字第621 號民事判決、最高法院99年度台上字第48\n      5 號民事裁定可稽，原告執詞否認支票簽收印文真正，係\n      屬臨訟卸責不可採信。\n（五）被證五臺北地方法院100 年2 月15日言詞辯論筆錄第6 頁\n      第15行所提示之「被證1 支票簽收單」即為本件被證四第\n      2 頁之「支票簽收單」，筆錄中原告除出庭證稱支票上「\n      吳宛玉」之簽名為其本人所簽之外，又再接續問到：「上\n      開簽收單上也有王簡阿玉的指印，是否她本人所為？」證\n      人即原告證稱：「是王簡阿玉的夫妻在一起，是王簡阿玉\n      本人或她先生蓋指印，我不清楚」、「就王簡阿玉夫妻在\n      場，誰簽名、蓋指印，我也沒有仔細看。」從而被告提出\n      之被證二、被證三、被證四所檢附之切結書及支票簽收單\n      ，均有原告之簽名蓋章作為簽收憑據，原告在上開言詞辯\n      論筆錄也承認「支票簽收單」上「吳宛玉」簽名為其本人\n      所為，已足證明原告分別與其他債務人共同簽收取得該支\n      票，原告以事前不知又未經手等語置辯，顯然不實。再縱\n      如原告所稱乃簡金燦事後要求原告補簽乙節屬實，而原告\n      既已簽署，自屬認同其相關內容，不影響其相關責任之判\n      斷。\n（六）被證三之切結書及支票簽收單既經原告簽名蓋章，即足以\n      證明原告向被告借款1500萬，並收取被告用以交付借款之\n      支票；至原告簽收支票後，又將支票交給何人，已與被告\n      無涉，被告亦無權干預，是原告已非其兌領云云，完全無\n      視於支票簽收單上所記載之「茲收到上項第九信用合作社\n      營業部支票捌張面額合計新台幣壹仟伍佰萬元正，業已辦\n      妥抵押權設定登記在案，確實無誤。收款人：吳宛玉」此\n      外，王簡阿玉是否收受被證四切結書編號21號支票，被告\n      不得而知，惟王簡阿玉與原告既共同收受該支票簽收單上\n      所列之支票6 張，則渠等於共同簽收該6 張支票後，如何\n      分配取得支票，與被告無關，被告也無權過問，原告以其\n      他5 張不知被告或簡金燦交給何人云云，顯有誤解，被告\n      沒有舉證之義務。另原告指稱未曾收受2000萬元部分，有\n      鈞院卷第220 頁附表二編號1-7 之支票，該7 紙支票面額\n      合計即2000萬元，前經原告、陳永明、陳抱、陳尾、李金\n      利、吳陳玉英等人於83年4 月6 日共同簽收，並分別於其\n      後數日內兌現，有支票簽收單可證（被證七），足證原告\n      及陳永明等人確已共同取得2000萬元款項，因該金額已經\n      包括其後簽署之被證二支票簽收單所載「總款項新臺幣肆\n      仟萬元整」之內，所以在執行程序，被告即未再就該支票\n      簽收單提出作為債權憑證。原告在其99年6 月4 日寄予被\n      告之台北光武郵局第499 號存證信函，自承「民國83年間\n      與本人向台端所借之款項... 需還款新台幣陸仟伍佰萬元\n      正... 」可見原告其實也自己承認該6500萬元債務之存在\n      。\n（七）臺灣臺北地方法院99年度重訴字第995 號債務人異議之訴\n      事件之爭點為抵押權設定登記是否有效存在，而本件原告\n      則請求確認兩造間債務總額，二件似無牽涉。原告於上開\n      案件中作證，證詞亦與本件無關；惟訴外人王信狀於99年\n      12月17日親自出庭陳稱：「簽定這個契約時，吳宛玉叫謝\n      劉碧霞拿支票給我們，支票金額多少我忘記了，交了幾張\n      支票我也忘了，需要看契約才會知道」。對問：「吳宛玉\n      跟你媽媽買土地，前後共付多少錢給你媽媽？」答：「一\n      仟多萬，價金已付清了」可證被告在完成抵押權設定登記\n      後，係直接按原告與各業主間之買賣契約所約定，直接將\n      支票交給各業主，代替原告之給付。易言之，被告對系爭\n      土地各業主之貸款，係由被告之代理人簡金燦直接交予各\n      業主，原告確無經手之事實。且被告曾於上開案件中，自\n      認證明被告所簽發之30張支票，均交於其代理人簡金燦，\n      然後分交於系爭土地各業主。\n（八）李金利於100 年8 月17日經傳訊到庭，雖就相關借款過程\n      大多以不復記憶或「沒有」來回應，惟其亦不否認有取得\n      600 萬元之事實。再審視證人當庭於證人結文上之簽名筆\n      跡與被證二切結書上之簽名筆跡，其形式、筆劃亦極為相\n      似，再加上其自承當時亦取得部分款項，自可推認被證二\n      之文件確為其簽署。\n（九）為此，聲明請駁回原告之訴。\n三、兩造不爭執之事實：\n（一）原告與訴外人李金利、陳尾、陳抱、王簡阿玉、金陳寶英\n      簽訂不動產買賣契約，約定各出賣其所有如附表二所示坐\n      落臺北市○○區○○段3 小段第315 及315 之1 至9 地號\n      等10筆土地予原告。（見台灣台北地方法院100 年度重訴\n      字第239 號卷第11頁至20頁）。\n（二）上開10筆土地之登記簿謄本之他項權利部記載：訴外人李\n      金利、陳尾、陳抱、王簡阿玉、金陳寶英各以其所有之上\n      開土地之應有部分，分別為被告設定2000萬、1100萬、11\n      00萬、1300萬、2000萬，共計7500萬元之本金最高限額抵\n      押權，以擔保李金利、陳尾、陳抱、吳宛玉、陳永明等人\n      在抵押權範圍內之一切債務，並辦妥抵押權登記在案。各\n      該抵押權約定存續期間分別自83年3 月25日起至84年3 月\n      24日止、自83年3 月25日起至84年3 月24日止、自83年4\n      月6 日起至84年4 月10日止、自83年4 月29日起至84年5\n      月1 日止、自83年5 月23日起至84年5 月22日止，清償日\n      期除金陳寶英所提供擔保之土地為84年5 月22日外，其餘\n      清償日期均依各個契約約定，並有臺北市土地登記第二類\n      謄本附卷可稽（見本院卷第23頁至111 頁）。\n（三）被告持上開最高限額抵押權執行名義，曾於96年間以臺灣\n      臺北地方法院96年度執字第25774 號聲請拍賣抵押物強制\n      執行。\n（四）原告曾收受兌領由謝英明簽發，被告交付之貸款支票，支\n      票號碼為CE0000000 、CE0000000 ，發票日期83年4 月12\n      日，票面金額分別為120 萬元、140 萬元。\n（五）如附表一第二項所示之陳以諾為陳尾之繼承人；陳以忠、\n      陳三郎、林玉葉、林兩傳、林治郎、陳榮生、陳振賢、倪\n      陳淑珍為陳抱之繼承人；王信雄、王信壯、王金鳳、王阿\n      足則為王簡阿玉之繼承人。\n四、本件爭點與本院判斷：\n    原告主張伊與訴外人李金利等人訂立系爭土地買賣契約，並\n    以系爭土地為向被告借款之擔保，設定本金最高限額7500萬\n    元抵押權予被告，惟原告與李金利等人僅收受被告所簽發之\n    支票金額共計2482萬5000元，加計原告陸續向被告借得142\n    萬5000元之借款，合計為2625萬元等情，為被告所否認，並\n    以上開情詞置辯，經查：本件原告於82年10月30日、12月4\n    日、83年4 月19日、4 月30日分別與訴外人陳抱、陳尾、李\n    金利、王簡阿玉、金陳寶英簽訂不動產買賣契約，約定各出\n    賣陳抱等人所有如附表二所示坐落臺北市○○區○○段3 小\n    段第315 及315 之1 至9 地號等10筆土地之應有部分。訴外\n    人李金利、陳尾、陳抱、王簡阿玉、金陳寶英分別於83年4\n    月1 日、4 月11日、5 月4 日、5 月25日以其所有上開土地\n    應有部分，擔保李金利陳尾、陳抱分別與原告及訴外人陳永\n    明共同向被告借款，分別為被告設定2000萬元、1100萬元、\n    1100萬元、1300萬元、2000萬元，共計7,500 萬元之本金最\n    高限額抵押權，以擔保李金利、陳尾、陳抱、吳宛玉、陳永\n    明等人在抵押權範圍內之一切債務，並辦妥抵押權登記在案\n    。各該抵押權約定存續期間分別自83年3 月25日起至84年3\n    月24日止、自83年3 月25日起至84年3 月24日止、自83年4\n    月6 日起至84年4 月10日止、自83年4 月29日起至84年5 月\n    1 日止、自83年5 月23日起至84年5 月22日止，清償日期除\n    金陳寶英所提供擔保之土地為84年5 月22日外，其餘清償日\n    期均依各個契約約定。又如附表一第一項所示之陳以諾為陳\n    尾之繼承人；陳以忠、陳三郎、林玉葉、林兩傳、林治郎、\n    陳榮生、陳振賢、倪陳淑珍為陳抱之繼承人；王信雄、王信\n    壯、王金鳳、王阿足則為王簡阿玉之繼承人等事實，為兩造\n    所不爭執，並有臺北市土地登記第二類謄本附卷可稽（見本\n    院卷第23頁至111 頁），堪信為真。\n    本件應審究之爭點厥為：（一）上開抵押權所擔保之債權是\n    否存在？原告與訴外人李金利等人分別共同向被告借貸之金\n    額總共為多少？被告是否已交付由原告等人簽收？（二）原\n    告與訴外人李金利等人分別共同向被告所借得之款項，應否\n    負連帶清償責任？（三）被告向原告等人除得請求約定之違\n    約金外，是否仍得請求遲延利息1848萬4375元？本院之判斷\n    如下：\n（一）上開抵押權所擔保之債權是否存在？原告等人分別共同向\n      被告借貸之金額總共為多少？被告是否已交付由原告等人\n      簽收？\n    1.系爭抵押權為最高限額抵押，所謂最高限額之抵押契約，\n      係指所有人提供抵押物，與債權人訂立在一定金額之限度\n      內，擔保現在已發生及將來可能發生之債權之抵押權設定\n      契約而言。此種抵押權所擔保之債權，除定約時已發生之\n      債權外，即將來發生之債權，在約定限額之範圍內，亦為\n      抵押權效力所及。雖抵押權存續期間內已發生之債權，因\n      清償或其他事由而減少或消滅，原訂立之抵押契約依然有\n      效，嗣後在存續期間內陸續發生之債權，債權人仍得對抵\n      押物行使權利（最高法院66年臺上字第1097號判例參照）\n      。又按抵押權所擔保之債權，其種類及範圍，屬於抵押權\n      之內容，依法應經登記，始生物權之效力，但如因內容過\n      於冗長，登記簿所列各欄篇幅不能容納記載，可以附件記\n      載，作為登記簿之一部分。因此關於最高限額抵押權所擔\n      保之債權，雖未記載於土地登記簿，然於聲請登記時提出\n      之最高限額抵押權設定契約書，有該項債權之記載者，此\n      契約書既作為登記簿之附件，自為抵押權效力所及（最高\n      法院84年臺上字第1967號判例參照）。\n   2、本件系爭最高限額抵押權係擔保原告及訴外人李金利、陳\n      尾、陳抱、陳永明之債務，原告與訴外人陳永明為連帶債\n      務人，此有被告所提原告與陳永明、李金利、陳尾等人分\n      別所書立之切結書3 紙及系爭土地登記第二類謄本土地他\n      項權利部債務人及債務額比例欄所載在卷可佐（見本院卷\n      第23頁至112 頁、第168 頁至171 頁、第175 頁及178 頁\n      ），並為原告所不爭（見本院100 年6 月29日及9 月8 日\n      言詞辯論筆錄），又依原告等人所書立之切結書載明約定\n      擔保債權包括：「將來所負之借據、票據、保證、損害賠\n      償等及其他一切債務」，是兩造係明定以借款、票據、保\n      證、違約金債務等債權債務關係，作為系爭最高限額抵押\n      權從屬之基礎法律關係。\n   3、本件原告主張僅向被告借得2625萬元云云，被告則抗辯已\n      交付台北市第九信用合作社支票30張予原告等人簽收，金\n      額共計6500萬元，並已全部兌領等語，兩造所爭執之借貸\n      關係乃發生於83年間，此有兩造所不爭之上開切結書所載\n      日期可按，依實體從舊原則，兩造有關借款爭執部分，自\n      應適用修正前民法關於消費借貸之規定。而稱消費借貸者\n      ，謂當事人一方移轉金錢或其他代替物之所有權於他方，\n      而約定他方以種類、品質、數量相同之物返還之契約，民\n      法第474 條第1 項定有明文。又金錢借貸契約固屬要物契\n      約，應由貸與人就交付金錢之事實負舉證之責，但若貸與\n      人提出之借用證內，經載明借款額，當日親收足訖無訛者\n      ，應解為貸與人就要物性之具備，已盡舉證責任，最高法\n      院69年台上字第3546號判號例意旨可資參照，雖該判例嗣\n      因民法第474 條文字之修正而經該院決議刪除，然係顧慮\n      原條文用語易遭誤會消費借貸契約係諾成契約而予修正，\n      前開根據修正前法條所作成之判例因而隨之刪除，惟無論\n      修法前後對借貸契約既均採要物契約見解（最高法院90年\n      第4 次民事庭會議決議參照）。則上開判例有關要物性舉\n      證責任之歸屬之闡釋於法理上既無瑕疵，自仍得資為本件\n      參酌之依據，故就已交付金錢之事實，應由被告負舉證責\n      任。經查：\n    被告抗辯原告與訴外人陳永明、李金利、陳尾、陳抱、金\n      陳寶英、王簡阿玉等人，經由簡金燦分別於83年4 、5 月\n      間向被告借款4000萬元、1500萬元、1000萬元，並分別約\n      定違約金每月每萬15元、15元、20元，借款到期日則皆為\n      85年10月20日，由被告之夫謝英明為發票人，以台北市第\n      九信用合作社為付款人，簽發如附表三所示之支票30張交\n      付原告等人簽收，除其中附表編號15、19及27嗣後由被告\n      以現金換回外，其餘均已兌現之事實，已據被告提出原告\n      等人所簽具之切結書3 紙及借款證明（支票簽收單）4 紙\n      及支票30張影本、台北市第九信用合作社97年3 月12日北\n      市九信社業字第0383號函影本1 份為證（本院卷第168 頁\n      至179 頁、第226 頁、第131 頁至167 頁），而觀之該切\n      結書及依借款證明上均有原告之簽名及蓋章，原告雖否認\n      借款證明（支票簽收單）上之簽名為其所簽，惟查：原告\n      於台灣台北地方法院99年度重訴字第995 號債務人異議之\n      訴事件作證時，證稱：「（被告訴訟代理人問：（請提示\n      被證1 支票簽收單）上面的吳宛玉簽名是否是你本人所簽\n      ？）答：是我簽的：：：」等語（該院卷第130 頁背面）\n      ，經核與其他3 紙借款證明（支票簽收單）之吳宛玉簽名\n      ，其筆勢、筆順經目視尚難看出有何相異之處，且原告對\n      於切結書上之簽名亦不爭執為其所親簽，再徵之原告於99\n      年6 月4 日所寄給被告之存證信函，亦自承：「於民國83\n      年間（李金利等人）與本人間向台端所借之款項，約半年\n      前我們雙方已達共識，需還款陸仟伍佰萬元正」等語（本\n      院卷第227 頁），被告主張該4 紙借款證明（支票簽收單\n      ）係原告所簽之事實，堪信為真。\n    又依借款證明（支票簽收單），其上分別載明：「（就如\n      附表三編號1 至7 所示支票號碼CE0000000 號至CE000000\n      0 號等7 張支票部分）茲借款人（承買人）吳宛玉、提供\n      擔保義務人兼債務人陳抱、陳尾、李金利、吳陳玉英於民\n      國83年4 月6 日向債權人謝劉碧霞借款新台幣貳仟萬元，\n      ……經借款人與義務人兼債務人及連帶債務人當面點收現\n      金事實無誤……簽收1.吳宛玉、陳永明。2.陳抱。3.陳尾\n      、李金利。」、「（就如附表三編號8 至16所示支票號碼\n      CE0000000 號至CE0000000 號等9 張支票部分）本件前順\n      位私人（民間）借貸（代還前胎）清償向債權人謝劉碧霞\n      借款新台幣貳仟萬元整，在於之前於民國83年3 月24日經\n      借款人及連帶債務人當面點收現金新台幣貳仟萬元整，計\n      總款額新台幣肆仟萬元整事實無誤……簽收李金利、王志\n      銘、吳陳玉英、陳抱、陳永明、吳宛玉、陳尾」等文字（\n      見本院卷第226 頁、第174 頁），另附表三編號17至22號\n      之支票6 張，金額合計1000萬元，由原告及訴外人陳永明\n      、王簡阿玉等3 人簽收；附表三編號23至30所示8 張支票\n      ，金額合計1500萬元，由原告吳宛玉、陳永明等2 人簽收\n      ，此部分亦有原告吳宛玉所簽具之借款證明（支票簽收單\n      ）2 紙及支票影本在卷可憑（本院卷第176 至177 頁、第\n      179 頁），除編號15、19及27嗣後由被告以現金換回外，\n      其餘均已兌現，亦有台北市第九信用合作社97年3 月12日\n      函附於本院依職權調取之台灣台北地方法院96年度訴字第\n      7399號卷可按（該院卷第204 至243 頁，另本院卷131 頁\n      至167 頁亦附有影本）；稽之上開支票背面分別有訴外人\n      李金利、陳抱、陳尾、陳永明、吳宛玉等人蓋章背書，顯\n      見原告等人已分別簽收如附表三所示之系爭支票30張，其\n      中編號15、19及27，則由被告以現金換回，其餘則均已兌\n      現，堪以認定。從而，被告所辯其交付原告等人簽收之支\n      票業經提示且已兌現，其有交付款項之事實，堪予採信。\n   4、原告與訴外人李金利等人分別共同向被告借款，被告並已\n      交付如附表三所示之支票，除其中編號15、19及27嗣後由\n      被告以現金換回外，其餘均已兌現，已如前述，並參酌原\n      告於99年6 月4 日所寄給被告之存證信函，自承需還款新\n      臺幣陸仟伍佰萬元正等語，被告抗辯原告等人係向其借款\n      6500萬元等語，堪信為真。被告所辯僅向被告借得2625萬\n      元云云，則不足採信。\n（二）原告與訴外人李金利等人分別共同向被告所借得之款項，\n      應否負連帶清償責任？\n   1、按「數人負同一債務，明示對於債權人各負全部給付之責\n      任者，為連帶債務。」「連帶債務之債權人，得對於債務\n      人中之一人或數人或其全體，同時或先後請求全部或一部\n      之給付。連帶債務未全部履行前，全體債務人仍負連帶責\n      任。」民法第272條第1項、第273條分別定有明文。\n   2、本件原告就其與訴外人陳永明、李金利等人分別共同向被\n      告借款，共計6500萬元，而為借款債務人，及與訴外人陳\n      永明、李金利、陳尾、陳抱為連帶債務人，此有上開原告\n      簽名之切結書、借款證明（支票簽收單）及土地建築改良\n      物抵押權設定約定書1 份（見台灣台北地方法院100 年度\n      重訴字第239 號卷第29頁至36頁）可證，且為原告所自承\n      （見本院100 年9 月8 日言詞辯論筆錄），依民法第272\n      條第1 項規定，原告與陳永明、李金利、陳尾、陳抱等人\n      就各別共同之系爭債務，對被告各負全部給付之責任；又\n      系爭抵押權係擔保原告及陳永明、李金利、陳尾、陳抱等\n      人對被告之債務，有土地登記第二類謄本可稽，則原告與\n      訴外人陳永明等人間之其中任一人對被告之債務均為系爭\n      抵押權擔保範圍，其內部如何分配或處分系爭借款，非被\n      告所得過問，原告縱未現實受領款項，基於其連帶債務人\n      地位，仍不能因此免責，即訴外人李金利等人對被告之債\n      務亦屬系爭抵押權擔保範圍；而系爭支票均經原告之簽收\n      簽名蓋章，並均有原告與訴外人陳永明之背書，已如前述\n      ，則原告以其未實際收受支票款項為由，主張其對被告所\n      負之債務僅2625萬元云云，不足酌採。\n（三）被告向原告等人除得請求約定之違約金外，是否仍得請求\n      遲延利息1848萬4375元？\n      原告主張被告在台灣台北地方法院96年度執進字第25774\n      號拍賣抵押物強制執行程序中，除主張約定之665 萬4375\n      元違約金外，另又主張1848萬4375元之遲延利息，此項請\n      求顯與民法第250 條第1 項及第2 項前段之規定不符，爰\n      一併請求確認以保原告之權益等語，惟為被告所否認，辯\n      稱：被告請求給付違約金係基於抵押權設定契約書，請求\n      給付遲延利息則係依民法第233 條之規定，兩者並無衝突\n      等語。按「違約金，有屬於懲罰之性質者，有屬於損害賠\n      償約定之性質者，本件違約金如為懲罰之性質，於上訴人\n      履行遲延時，被上訴人除請求違約金外，固得依民法第二\n      百三十三條規定，請求給付遲延利息及賠償其他之損害，\n      如為損害賠償約定之性質，則應視為就因遲延所生之損害\n      ，業已依契約預定其賠償，不得更請求遲延利息賠償損害\n      。」最高法院62年台上字第1394號著有判例可資參照。經\n      查：本件原告於上揭日期分別與訴外人陳抱、陳尾、李金\n      利、王簡阿玉、金陳寶英簽訂不動產買賣契約，約定各出\n      賣陳抱等人所有坐落臺北市○○區○○段3 小段第315 及\n      315 之1 至9 地號等10筆土地之應有部分。訴外人李金利\n      、陳尾、陳抱、王簡阿玉、金陳寶英分別於83年4 月1 日\n      、4 月11日、5 月4 日、5 月25日以其所有上開土地應有\n      部分，擔保李金利陳尾、陳抱分別與原告及訴外人陳永明\n      共同向被告借款，分別為被告設定2000萬元、1100萬元、\n      1100萬元、1300萬元、2000萬元，共計7,500 萬元之本金\n      最高限額抵押權，以擔保李金利、陳尾、陳抱、吳宛玉、\n      陳永明等人在抵押權範圍內之一切債務，並辦妥抵押權登\n      記在案等情，已如前述，而觀之抵押權設定契約書，固僅\n      記載違約金，而無遲延利息之記載，有該抵押權設定契約\n      書1 份附卷可按（見台灣台北地方法院100 年度重訴字第\n      239 號卷第29頁至36頁），惟此部分係有關抵押權效力所\n      及之約定，亦即抵押權之效力及於本金及違約金。而依上\n      開抵押權設定契約書所約定之違約金，係依每百元日息一\n      角五分計算，即每月每萬元15元，核其性質應屬懲罰違約\n      金，並非損害賠償約定之性質。依上開最高法院判例意旨\n      ，被告於原告等人履行遲延時，被告除請求違約金外，固\n      得依民法第233 條規定，請求給付遲延利息及賠償其他之\n      損害。又原告等人向被告借款之清償期，均為85年10月20\n      日，為兩造所不爭，則被告請求原告與李金利、陳尾、陳\n      抱等人分別共同向被告借款之部分，本金尚欠2625萬元，\n      違約金自85年10月21日起至99年11月20日止，每月每萬元\n      15元計算，共計665 萬4375元；遲延利息自85年10月21日\n      起至99年11月20日止，按年息百分之5 計算之利息，共計\n      1848萬4375元，有原告所提借款本金、遲延利息及約定違\n      約金計算表可佐（見台灣台北地方法院100 年度重訴字第\n      239 號卷第21頁），尚非無據，原告主張被告之遲延利息\n      1848萬4375元請求權不存在云云，並不足採。\n五、綜上，原告請求確認(一)請求確認原告與附表一第二項各土地\n    所有權人為連帶債務人，就同附表第三項所載土地，於83年\n    4 月1 日以被告為債權人所設定本金最高限額7500萬元之抵\n    押權設定為擔保實借金額為2625萬元。(二)請求確認前項所載\n    本金，自85年10月21日至99年11月20日止，約定違約金為66\n    5 萬4375元，被告另主張遲延利息1848萬4375元之請求權不\n    存在，為無理由，應予駁回。\n六、本件事證已臻明確，兩造其餘攻擊防禦方法暨舉證，經核與\n    判決結果不生影響，爰不一一論列，併此敘明。\n七、結論：原告之訴為無理由，依民事訴訟法第78條，判決如主\n    文。",
    "reason": "一、原告起訴主張：\n（一）原告於民國82年10月間向訴外人李金利、陳抱、陳尾、王\n      簡阿玉、金陳寶英等人分別購買如附表二所示坐落臺北市\n      中正區○○段○ ○段第315 及315 之1 至9 地號等10筆土\n      地（下稱系爭土地）。83年3 月間，訴外人簡金燦得知原\n      告購買系爭土地，即向原告佯稱有款項可借原告並以系爭\n      土地為擔保，原告徵得系爭土地之所有人即訴外人李金利\n      陳抱、陳尾、王簡阿玉、金陳寶英等人之同意，即將土地\n      所有權狀、印鑑證明書及印章交給簡金燦辦理貸款，並交\n      由委任之代書辦理設定最高限額抵押權；惟簡金燦實際係\n      向本件被告借款，並擅自將系爭土地完成本金最高限額新\n      臺幣（下同）7500萬元之最高限額抵押權登記予被告，並\n      將借得款項分別以被告簽發之九信支票給付與訴外人李金\n      利、陳抱、陳尾、王簡阿玉、金陳寶英等人，核算渠等收\n      受之支票總金額為2482萬5000元，加計原告陸續向被告借\n      得142 萬5000元之借款，合計為2625萬元。\n（二）簡金燦辦理前揭抵押權設定，設定期限一年，即自83 年3\n      月25日至84年3 月24日止，並將數十張系爭土地所有權狀\n      正本、印鑑章等交予被告保管，嗣被告為防止土地登記所\n      有權人李金利等人再設定次順位抵押權，影響其貸款之回\n      收，竟拒絕返還上開土地所有權狀正本、印鑑章，致原告\n      與李金利等人間之契約無法履行，無法將系爭土地移轉登\n      記予原告，終使貸款之清償發生遲延，此應歸責於被告之\n      事由所致。多年前原告即多次要求被告協調清償前開欠款\n      ，但被告堅持李金利、陳抱、陳尾、王簡阿玉、金陳寶英\n      等人所設定之抵押權本金為5125萬元，並於鈞院96年度執\n      字第25774 號聲請拍賣抵押物強制執行中，要求清償本息\n      達9000萬元以上，其請求顯非合理。\n（三）另案陳抱、陳尾之繼承人陳文忠、陳以諾，曾就被告所提\n      執行之異議之訴程序中，表示被告配偶謝英明所簽發領用\n      北市九信之支票30張，分別交與李金利、陳尾、王簡阿玉\n      、陳抱、金陳寶英，而總金額為7500萬元，有最高法院99\n      年度台上字第485 號裁定書之記載足資引據。據此即可證\n      明，被告主張貸借予原告等之本金總額，與原告事實上所\n      受之金額實有鉅額之差距，雙方就該債權額既有爭執，如\n      不予確定顯有侵害及原告權益之虞，應認原告有確認之利\n      益。蓋被告在拍賣抵押物強制執行程序中，除主張約定之\n      665 萬4375元違約金外，另又主張1848萬4375元之遲延利\n      息，此項請求顯與民法第250 條第1 項及第2 項前段之規\n      定不符，爰一併請求確認以保原告之權益。\n（四）再被告雖主張曾簽發30張總金額6500萬元之支票，作為交\n      付原告數額之證明，惟原告僅僅收到如原告100 年6 月8\n      日民事準備（一）狀附表所示之10張支票，總計僅2742萬\n      5000元，是其餘20張支票被告究竟交予何人？由何人兌領\n      ？請求依民事訴訟法第277 條第1 項規定，命被告舉證以\n      實其說。另本件借貸緣由實原告向李金利等人購買系爭土\n      地後，資金不足，徵得各地主同意提供各人所有土地，由\n      原告向簡金燦醫師借貸，作為原告購買土地之部分價金，\n      分別給付與各地主。期間一切手續向來經原告與簡金燦接\n      洽，故始終認定簡金燦為金主，且所有貸款支票亦概由簡\n      金燦交予原告。基此，究竟被告交予簡金燦幾紙支票？總\n      金額為何？均於被告對系爭土地強制執行時，原告閱卷後\n      始知，其餘20張支票乃被告與簡金燦間另一債權債務問題\n      ，至請斟酌。\n（五）被證一被告向北市九信合作社調取之27張支票影本，除未\n      註明具領票款人之姓名，且因支票雖經背書，多無法辨認\n      ，故請求被告作成表格分別載明具領人姓名、住址等，供\n      作確認。被證二切結書，則僅記載原告、李金利等人為債\n      務人兼設定抵押權之義務，以及同意提供土地為擔保，向\n      被告借貸之事實，毫未載明本件所列李金利等五人，實際\n      借款若干之事實，顯然該切結書與本件之爭點無涉。又因\n      該切結書所簽發之支票計9 張，每張支票影本上雖均經原\n      告、地主5 人及另一連帶債務人陳永明蓋章，然此係簡金\n      燦前此辦理抵押權設定登記持有原告等7 人之印鑑，逕行\n      蓋用於其上，非原告所蓋用。此外，該9 張支票最後一紙\n      支票下方附註欄，註有：「借款新台幣貳仟萬元，在於之\n      前於民國83年3 月24日，經借款人及連帶債務人，當面點\n      收現金」等詞，並非真正，是請被告舉證究於何時、何地\n      、在哪些人在場之下，又將此鉅款交於何人收受，此所謂\n      2000萬元現款，是否以被告所指共簽發30張支票交於借款\n      人收受，其中3 張以現金換回未經兌領云云，究竟為哪3\n      張支票？被證三切結書雖由原告與陳永明具名，表示願以\n      金陳寶英之土地持份及地上物為擔保，請求被告給予貸款\n      ，但並未表示「已」向被告「借到」1500萬元。又該切結\n      書所檢具之支票有8 張，在支票與支票間之騎縫上，蓋章\n      者有原告及陳永明二人，惟其中沒有一張經原告收受兌領\n      。原告曾收受兌領之支票，僅被告所稱發交於簡金燦鈞院\n      卷第185 頁編號12、13面額分別為120 萬、140 萬元之支\n      票2 紙。另被證四切結書檢具之支票6 張，於支票影本邊\n      蓋章者，雖為原告、陳永明、王簡阿玉三人，但其中僅支\n      票號碼CEO531977 ，面額245 萬元之支票，由王簡阿玉收\n      受兌領外，其餘5 張則不知被告或簡金燦交付何人。另被\n      證五之言詞辯論筆錄，並不能否認原告所指五人貸款金額\n      僅2742萬5000元之事實，故被告應具體提出證明事項。\n（六）被告自稱共簽發30張支票之票號、金額、到期日，以及依\n      被告所提兌現銀行供兌領人之背書，表列如附件3 （見本\n      院卷第113 頁）惟其中兌領人與原告或地主毫無關係者，\n      列舉如下：\n   1、編號2，面額200萬元，兌領人呂清朗。\n   2、編號8，面額270萬元，兌領人郭秀端。\n   3、編號14、15、16、19，面額依序分別為90萬元、180 萬元\n      、120 萬元、45萬元，兌領人完全空白，不知係由何人兌\n      領。\n   4、編號17、18、20，面額依序為530 萬元、60萬元、20萬元\n      ，均係由呂月香兌領。\n   5、編號27，面額67萬5000元，兌領者不詳。\n   6、編號28，面額30萬元，兌領者呂月香。\n   7、編號30，面額15萬元，兌領者不詳。\n（七）原告委由簡金燦代為辦理抵押借款時，曾再三言明按照原\n      證1 至原證5 之買賣契約書約定之價款，扣除原告已支付\n      之定金外金額，委由其定抵押貸款，貸得款項直接交於各\n      地主，是以原告確未經手，此項情節除請參酌台北地院檢\n      察署89年度偵字第22990 號不起訴處分書第一項簡金燦證\n      詞可證。被告稱2000萬元現金為支票簽收單所載編號1 至\n      7 之七張支票（見本卷卷第113 頁），由原告等人兌領，\n      惟其中編號1 為李金利、編號3 為陳尾、編號6 為塗銷陳\n      抱抵押權登記代償於王文芬之支票，上開三張支票既為票\n      據，並分別交由上開個人兌領，豈能又指為「當面點收現\n      金新台幣貳仟萬元」，據此，益足證被告所指交付2000萬\n      元云云，並非事實。\n（八）綜上所述，原告於本件有確認之利益。為此，依民事訴訟\n      法第247 條第1 項前段、最高法院42年度台上字第1031號\n      、52 年 度台上字第1237號之判例意旨，聲明：(一)請求確\n      認原告與附表一第2 項各土地所有權人為連帶債務人，就\n      同附表第3項 所載土地，於83年4 月1 日以被告為債權人\n      所設定本金最高限額7500萬元之抵押權設定為擔保實借金\n      額為2625萬元。(二)請求確認前項所載本金，自85年10月21\n      日至99年11月20日止，約定違約金為665 萬4375元，被告\n      另主張遲延利息1848萬4375元之請求權不存在等語。\n二、被告答辯則以：\n（一）原告是否向訴外人李金利等人購買系爭坐落臺北市○○區\n      ○○段三小段第315 號等10筆土地，被告並不知情，亦無\n      法判斷原告所述情節是否真正，況無論原告所述之買賣是\n      否屬實，均與被告無涉，與本訴訟無關。\n（二）原告與訴外人陳永明、李金利、王志銘、陳尾、陳抱、吳\n      陳玉英、金陳寶英、王簡阿玉等，經由簡金燦分別於83年\n      4 、5 月間向被告借款4000萬元、1500萬元、1000萬元，\n      並分別約定違約金每月每萬15元、15元、20元，借款到期\n      日則皆為85年10月20日，並有以下文件可證：\n   1、原告與陳永明、李金利、王志銘、陳尾、陳抱、吳陳玉英\n      等人，以李金利等人之不動產為擔保，向被告借款4000萬\n      元所共同簽具之切結書及支票簽收單（包括現金2000萬元\n      及支票9 張面額合計2000萬元）。\n   2、原告與陳永明持金陳寶英不動產為擔保，向被告借款所簽\n      具之切結書及支票簽收單（包括支票8 張面額合計1500萬\n      元）。\n   3、原告與陳永明持王簡阿玉不動產為擔保，向被告借款簽具\n      之切結書及支票簽收單（包括支票6 張面額合計1000萬元\n      ）。\n   4、準此，原告不否認其於上開切結書上之簽名，而其既共同\n      簽收上開現金及支票並負連帶責任，則其以原證1 至原證\n      5 之土地買賣契約書所載付款紀錄，證明其僅負債2625萬\n      元云云，顯無理由。\n（三）原告主張因被告保管土地所有權狀正本，致其無法辦理系\n      爭土地所有權移轉登記，認原告與李金利等人之契約無法\n      履行，終使貸款之清償發生遲延，應屬可歸責於被告之事\n      由所致云云，與事實不符，蓋被告保管土地所有權狀僅係\n      保全債權之方式，與原告對於系爭借貸能否清償無關，更\n      何況自借貸迄被告前揭聲請執行已逾十餘年，其間原告又\n      何曾提出款項表示清償？至於原告另主張被告請求給付違\n      約金、遲延利息與民法第250 條第1 項、第2 項前段規定\n      不符云云，惟被告請求給付違約金係基於抵押權設定契約\n      書，請求給付遲延利息則係依民法第233 條之規定，兩者\n      並無衝突。此外，按確認之訴，依民事訴訟法第247 條規\n      定，除確認證書真偽或為法律關係基礎事實存否之訴外，\n      以確認法律關係始得提起，原告起訴請求確認債務額，於\n      法不合，其訴之聲明亦不明確。\n（四）被證一至被證四中有關原告吳宛玉之簽名及印文均為一致\n      ，支票背面都有原告之背書，背書之印文也完全相同，然\n      原告僅承認被證二、三、四上之簽名及印文為真正，執詞\n      否認其他文件之真實，顯無理由而不可採信。另臺灣臺北\n      地方法院96年度訴字第7399號債務人異議之訴乙案，就被\n      告確實有給付借款之事實，及被證一27張支票交予原告吳\n      宛玉等人簽收兌現等情，均已認定明確，此有臺灣臺北地\n      方法院96年度訴字第7399號民事判決、臺灣高等法院97年\n      度重上字第621 號民事判決、最高法院99年度台上字第48\n      5 號民事裁定可稽，原告執詞否認支票簽收印文真正，係\n      屬臨訟卸責不可採信。\n（五）被證五臺北地方法院100 年2 月15日言詞辯論筆錄第6 頁\n      第15行所提示之「被證1 支票簽收單」即為本件被證四第\n      2 頁之「支票簽收單」，筆錄中原告除出庭證稱支票上「\n      吳宛玉」之簽名為其本人所簽之外，又再接續問到：「上\n      開簽收單上也有王簡阿玉的指印，是否她本人所為？」證\n      人即原告證稱：「是王簡阿玉的夫妻在一起，是王簡阿玉\n      本人或她先生蓋指印，我不清楚」、「就王簡阿玉夫妻在\n      場，誰簽名、蓋指印，我也沒有仔細看。」從而被告提出\n      之被證二、被證三、被證四所檢附之切結書及支票簽收單\n      ，均有原告之簽名蓋章作為簽收憑據，原告在上開言詞辯\n      論筆錄也承認「支票簽收單」上「吳宛玉」簽名為其本人\n      所為，已足證明原告分別與其他債務人共同簽收取得該支\n      票，原告以事前不知又未經手等語置辯，顯然不實。再縱\n      如原告所稱乃簡金燦事後要求原告補簽乙節屬實，而原告\n      既已簽署，自屬認同其相關內容，不影響其相關責任之判\n      斷。\n（六）被證三之切結書及支票簽收單既經原告簽名蓋章，即足以\n      證明原告向被告借款1500萬，並收取被告用以交付借款之\n      支票；至原告簽收支票後，又將支票交給何人，已與被告\n      無涉，被告亦無權干預，是原告已非其兌領云云，完全無\n      視於支票簽收單上所記載之「茲收到上項第九信用合作社\n      營業部支票捌張面額合計新台幣壹仟伍佰萬元正，業已辦\n      妥抵押權設定登記在案，確實無誤。收款人：吳宛玉」此\n      外，王簡阿玉是否收受被證四切結書編號21號支票，被告\n      不得而知，惟王簡阿玉與原告既共同收受該支票簽收單上\n      所列之支票6 張，則渠等於共同簽收該6 張支票後，如何\n      分配取得支票，與被告無關，被告也無權過問，原告以其\n      他5 張不知被告或簡金燦交給何人云云，顯有誤解，被告\n      沒有舉證之義務。另原告指稱未曾收受2000萬元部分，有\n      鈞院卷第220 頁附表二編號1-7 之支票，該7 紙支票面額\n      合計即2000萬元，前經原告、陳永明、陳抱、陳尾、李金\n      利、吳陳玉英等人於83年4 月6 日共同簽收，並分別於其\n      後數日內兌現，有支票簽收單可證（被證七），足證原告\n      及陳永明等人確已共同取得2000萬元款項，因該金額已經\n      包括其後簽署之被證二支票簽收單所載「總款項新臺幣肆\n      仟萬元整」之內，所以在執行程序，被告即未再就該支票\n      簽收單提出作為債權憑證。原告在其99年6 月4 日寄予被\n      告之台北光武郵局第499 號存證信函，自承「民國83年間\n      與本人向台端所借之款項... 需還款新台幣陸仟伍佰萬元\n      正... 」可見原告其實也自己承認該6500萬元債務之存在\n      。\n（七）臺灣臺北地方法院99年度重訴字第995 號債務人異議之訴\n      事件之爭點為抵押權設定登記是否有效存在，而本件原告\n      則請求確認兩造間債務總額，二件似無牽涉。原告於上開\n      案件中作證，證詞亦與本件無關；惟訴外人王信狀於99年\n      12月17日親自出庭陳稱：「簽定這個契約時，吳宛玉叫謝\n      劉碧霞拿支票給我們，支票金額多少我忘記了，交了幾張\n      支票我也忘了，需要看契約才會知道」。對問：「吳宛玉\n      跟你媽媽買土地，前後共付多少錢給你媽媽？」答：「一\n      仟多萬，價金已付清了」可證被告在完成抵押權設定登記\n      後，係直接按原告與各業主間之買賣契約所約定，直接將\n      支票交給各業主，代替原告之給付。易言之，被告對系爭\n      土地各業主之貸款，係由被告之代理人簡金燦直接交予各\n      業主，原告確無經手之事實。且被告曾於上開案件中，自\n      認證明被告所簽發之30張支票，均交於其代理人簡金燦，\n      然後分交於系爭土地各業主。\n（八）李金利於100 年8 月17日經傳訊到庭，雖就相關借款過程\n      大多以不復記憶或「沒有」來回應，惟其亦不否認有取得\n      600 萬元之事實。再審視證人當庭於證人結文上之簽名筆\n      跡與被證二切結書上之簽名筆跡，其形式、筆劃亦極為相\n      似，再加上其自承當時亦取得部分款項，自可推認被證二\n      之文件確為其簽署。\n（九）為此，聲明請駁回原告之訴。\n三、兩造不爭執之事實：\n（一）原告與訴外人李金利、陳尾、陳抱、王簡阿玉、金陳寶英\n      簽訂不動產買賣契約，約定各出賣其所有如附表二所示坐\n      落臺北市○○區○○段3 小段第315 及315 之1 至9 地號\n      等10筆土地予原告。（見台灣台北地方法院100 年度重訴\n      字第239 號卷第11頁至20頁）。\n（二）上開10筆土地之登記簿謄本之他項權利部記載：訴外人李\n      金利、陳尾、陳抱、王簡阿玉、金陳寶英各以其所有之上\n      開土地之應有部分，分別為被告設定2000萬、1100萬、11\n      00萬、1300萬、2000萬，共計7500萬元之本金最高限額抵\n      押權，以擔保李金利、陳尾、陳抱、吳宛玉、陳永明等人\n      在抵押權範圍內之一切債務，並辦妥抵押權登記在案。各\n      該抵押權約定存續期間分別自83年3 月25日起至84年3 月\n      24日止、自83年3 月25日起至84年3 月24日止、自83年4\n      月6 日起至84年4 月10日止、自83年4 月29日起至84年5\n      月1 日止、自83年5 月23日起至84年5 月22日止，清償日\n      期除金陳寶英所提供擔保之土地為84年5 月22日外，其餘\n      清償日期均依各個契約約定，並有臺北市土地登記第二類\n      謄本附卷可稽（見本院卷第23頁至111 頁）。\n（三）被告持上開最高限額抵押權執行名義，曾於96年間以臺灣\n      臺北地方法院96年度執字第25774 號聲請拍賣抵押物強制\n      執行。\n（四）原告曾收受兌領由謝英明簽發，被告交付之貸款支票，支\n      票號碼為CE0000000 、CE0000000 ，發票日期83年4 月12\n      日，票面金額分別為120 萬元、140 萬元。\n（五）如附表一第二項所示之陳以諾為陳尾之繼承人；陳以忠、\n      陳三郎、林玉葉、林兩傳、林治郎、陳榮生、陳振賢、倪\n      陳淑珍為陳抱之繼承人；王信雄、王信壯、王金鳳、王阿\n      足則為王簡阿玉之繼承人。\n四、本件爭點與本院判斷：\n    原告主張伊與訴外人李金利等人訂立系爭土地買賣契約，並\n    以系爭土地為向被告借款之擔保，設定本金最高限額7500萬\n    元抵押權予被告，惟原告與李金利等人僅收受被告所簽發之\n    支票金額共計2482萬5000元，加計原告陸續向被告借得142\n    萬5000元之借款，合計為2625萬元等情，為被告所否認，並\n    以上開情詞置辯，經查：本件原告於82年10月30日、12月4\n    日、83年4 月19日、4 月30日分別與訴外人陳抱、陳尾、李\n    金利、王簡阿玉、金陳寶英簽訂不動產買賣契約，約定各出\n    賣陳抱等人所有如附表二所示坐落臺北市○○區○○段3 小\n    段第315 及315 之1 至9 地號等10筆土地之應有部分。訴外\n    人李金利、陳尾、陳抱、王簡阿玉、金陳寶英分別於83年4\n    月1 日、4 月11日、5 月4 日、5 月25日以其所有上開土地\n    應有部分，擔保李金利陳尾、陳抱分別與原告及訴外人陳永\n    明共同向被告借款，分別為被告設定2000萬元、1100萬元、\n    1100萬元、1300萬元、2000萬元，共計7,500 萬元之本金最\n    高限額抵押權，以擔保李金利、陳尾、陳抱、吳宛玉、陳永\n    明等人在抵押權範圍內之一切債務，並辦妥抵押權登記在案\n    。各該抵押權約定存續期間分別自83年3 月25日起至84年3\n    月24日止、自83年3 月25日起至84年3 月24日止、自83年4\n    月6 日起至84年4 月10日止、自83年4 月29日起至84年5 月\n    1 日止、自83年5 月23日起至84年5 月22日止，清償日期除\n    金陳寶英所提供擔保之土地為84年5 月22日外，其餘清償日\n    期均依各個契約約定。又如附表一第一項所示之陳以諾為陳\n    尾之繼承人；陳以忠、陳三郎、林玉葉、林兩傳、林治郎、\n    陳榮生、陳振賢、倪陳淑珍為陳抱之繼承人；王信雄、王信\n    壯、王金鳳、王阿足則為王簡阿玉之繼承人等事實，為兩造\n    所不爭執，並有臺北市土地登記第二類謄本附卷可稽（見本\n    院卷第23頁至111 頁），堪信為真。\n    本件應審究之爭點厥為：（一）上開抵押權所擔保之債權是\n    否存在？原告與訴外人李金利等人分別共同向被告借貸之金\n    額總共為多少？被告是否已交付由原告等人簽收？（二）原\n    告與訴外人李金利等人分別共同向被告所借得之款項，應否\n    負連帶清償責任？（三）被告向原告等人除得請求約定之違\n    約金外，是否仍得請求遲延利息1848萬4375元？本院之判斷\n    如下：\n（一）上開抵押權所擔保之債權是否存在？原告等人分別共同向\n      被告借貸之金額總共為多少？被告是否已交付由原告等人\n      簽收？\n    1.系爭抵押權為最高限額抵押，所謂最高限額之抵押契約，\n      係指所有人提供抵押物，與債權人訂立在一定金額之限度\n      內，擔保現在已發生及將來可能發生之債權之抵押權設定\n      契約而言。此種抵押權所擔保之債權，除定約時已發生之\n      債權外，即將來發生之債權，在約定限額之範圍內，亦為\n      抵押權效力所及。雖抵押權存續期間內已發生之債權，因\n      清償或其他事由而減少或消滅，原訂立之抵押契約依然有\n      效，嗣後在存續期間內陸續發生之債權，債權人仍得對抵\n      押物行使權利（最高法院66年臺上字第1097號判例參照）\n      。又按抵押權所擔保之債權，其種類及範圍，屬於抵押權\n      之內容，依法應經登記，始生物權之效力，但如因內容過\n      於冗長，登記簿所列各欄篇幅不能容納記載，可以附件記\n      載，作為登記簿之一部分。因此關於最高限額抵押權所擔\n      保之債權，雖未記載於土地登記簿，然於聲請登記時提出\n      之最高限額抵押權設定契約書，有該項債權之記載者，此\n      契約書既作為登記簿之附件，自為抵押權效力所及（最高\n      法院84年臺上字第1967號判例參照）。\n   2、本件系爭最高限額抵押權係擔保原告及訴外人李金利、陳\n      尾、陳抱、陳永明之債務，原告與訴外人陳永明為連帶債\n      務人，此有被告所提原告與陳永明、李金利、陳尾等人分\n      別所書立之切結書3 紙及系爭土地登記第二類謄本土地他\n      項權利部債務人及債務額比例欄所載在卷可佐（見本院卷\n      第23頁至112 頁、第168 頁至171 頁、第175 頁及178 頁\n      ），並為原告所不爭（見本院100 年6 月29日及9 月8 日\n      言詞辯論筆錄），又依原告等人所書立之切結書載明約定\n      擔保債權包括：「將來所負之借據、票據、保證、損害賠\n      償等及其他一切債務」，是兩造係明定以借款、票據、保\n      證、違約金債務等債權債務關係，作為系爭最高限額抵押\n      權從屬之基礎法律關係。\n   3、本件原告主張僅向被告借得2625萬元云云，被告則抗辯已\n      交付台北市第九信用合作社支票30張予原告等人簽收，金\n      額共計6500萬元，並已全部兌領等語，兩造所爭執之借貸\n      關係乃發生於83年間，此有兩造所不爭之上開切結書所載\n      日期可按，依實體從舊原則，兩造有關借款爭執部分，自\n      應適用修正前民法關於消費借貸之規定。而稱消費借貸者\n      ，謂當事人一方移轉金錢或其他代替物之所有權於他方，\n      而約定他方以種類、品質、數量相同之物返還之契約，民\n      法第474 條第1 項定有明文。又金錢借貸契約固屬要物契\n      約，應由貸與人就交付金錢之事實負舉證之責，但若貸與\n      人提出之借用證內，經載明借款額，當日親收足訖無訛者\n      ，應解為貸與人就要物性之具備，已盡舉證責任，最高法\n      院69年台上字第3546號判號例意旨可資參照，雖該判例嗣\n      因民法第474 條文字之修正而經該院決議刪除，然係顧慮\n      原條文用語易遭誤會消費借貸契約係諾成契約而予修正，\n      前開根據修正前法條所作成之判例因而隨之刪除，惟無論\n      修法前後對借貸契約既均採要物契約見解（最高法院90年\n      第4 次民事庭會議決議參照）。則上開判例有關要物性舉\n      證責任之歸屬之闡釋於法理上既無瑕疵，自仍得資為本件\n      參酌之依據，故就已交付金錢之事實，應由被告負舉證責\n      任。經查：\n    被告抗辯原告與訴外人陳永明、李金利、陳尾、陳抱、金\n      陳寶英、王簡阿玉等人，經由簡金燦分別於83年4 、5 月\n      間向被告借款4000萬元、1500萬元、1000萬元，並分別約\n      定違約金每月每萬15元、15元、20元，借款到期日則皆為\n      85年10月20日，由被告之夫謝英明為發票人，以台北市第\n      九信用合作社為付款人，簽發如附表三所示之支票30張交\n      付原告等人簽收，除其中附表編號15、19及27嗣後由被告\n      以現金換回外，其餘均已兌現之事實，已據被告提出原告\n      等人所簽具之切結書3 紙及借款證明（支票簽收單）4 紙\n      及支票30張影本、台北市第九信用合作社97年3 月12日北\n      市九信社業字第0383號函影本1 份為證（本院卷第168 頁\n      至179 頁、第226 頁、第131 頁至167 頁），而觀之該切\n      結書及依借款證明上均有原告之簽名及蓋章，原告雖否認\n      借款證明（支票簽收單）上之簽名為其所簽，惟查：原告\n      於台灣台北地方法院99年度重訴字第995 號債務人異議之\n      訴事件作證時，證稱：「（被告訴訟代理人問：（請提示\n      被證1 支票簽收單）上面的吳宛玉簽名是否是你本人所簽\n      ？）答：是我簽的：：：」等語（該院卷第130 頁背面）\n      ，經核與其他3 紙借款證明（支票簽收單）之吳宛玉簽名\n      ，其筆勢、筆順經目視尚難看出有何相異之處，且原告對\n      於切結書上之簽名亦不爭執為其所親簽，再徵之原告於99\n      年6 月4 日所寄給被告之存證信函，亦自承：「於民國83\n      年間（李金利等人）與本人間向台端所借之款項，約半年\n      前我們雙方已達共識，需還款陸仟伍佰萬元正」等語（本\n      院卷第227 頁），被告主張該4 紙借款證明（支票簽收單\n      ）係原告所簽之事實，堪信為真。\n    又依借款證明（支票簽收單），其上分別載明：「（就如\n      附表三編號1 至7 所示支票號碼CE0000000 號至CE000000\n      0 號等7 張支票部分）茲借款人（承買人）吳宛玉、提供\n      擔保義務人兼債務人陳抱、陳尾、李金利、吳陳玉英於民\n      國83年4 月6 日向債權人謝劉碧霞借款新台幣貳仟萬元，\n      ……經借款人與義務人兼債務人及連帶債務人當面點收現\n      金事實無誤……簽收1.吳宛玉、陳永明。2.陳抱。3.陳尾\n      、李金利。」、「（就如附表三編號8 至16所示支票號碼\n      CE0000000 號至CE0000000 號等9 張支票部分）本件前順\n      位私人（民間）借貸（代還前胎）清償向債權人謝劉碧霞\n      借款新台幣貳仟萬元整，在於之前於民國83年3 月24日經\n      借款人及連帶債務人當面點收現金新台幣貳仟萬元整，計\n      總款額新台幣肆仟萬元整事實無誤……簽收李金利、王志\n      銘、吳陳玉英、陳抱、陳永明、吳宛玉、陳尾」等文字（\n      見本院卷第226 頁、第174 頁），另附表三編號17至22號\n      之支票6 張，金額合計1000萬元，由原告及訴外人陳永明\n      、王簡阿玉等3 人簽收；附表三編號23至30所示8 張支票\n      ，金額合計1500萬元，由原告吳宛玉、陳永明等2 人簽收\n      ，此部分亦有原告吳宛玉所簽具之借款證明（支票簽收單\n      ）2 紙及支票影本在卷可憑（本院卷第176 至177 頁、第\n      179 頁），除編號15、19及27嗣後由被告以現金換回外，\n      其餘均已兌現，亦有台北市第九信用合作社97年3 月12日\n      函附於本院依職權調取之台灣台北地方法院96年度訴字第\n      7399號卷可按（該院卷第204 至243 頁，另本院卷131 頁\n      至167 頁亦附有影本）；稽之上開支票背面分別有訴外人\n      李金利、陳抱、陳尾、陳永明、吳宛玉等人蓋章背書，顯\n      見原告等人已分別簽收如附表三所示之系爭支票30張，其\n      中編號15、19及27，則由被告以現金換回，其餘則均已兌\n      現，堪以認定。從而，被告所辯其交付原告等人簽收之支\n      票業經提示且已兌現，其有交付款項之事實，堪予採信。\n   4、原告與訴外人李金利等人分別共同向被告借款，被告並已\n      交付如附表三所示之支票，除其中編號15、19及27嗣後由\n      被告以現金換回外，其餘均已兌現，已如前述，並參酌原\n      告於99年6 月4 日所寄給被告之存證信函，自承需還款新\n      臺幣陸仟伍佰萬元正等語，被告抗辯原告等人係向其借款\n      6500萬元等語，堪信為真。被告所辯僅向被告借得2625萬\n      元云云，則不足採信。\n（二）原告與訴外人李金利等人分別共同向被告所借得之款項，\n      應否負連帶清償責任？\n   1、按「數人負同一債務，明示對於債權人各負全部給付之責\n      任者，為連帶債務。」「連帶債務之債權人，得對於債務\n      人中之一人或數人或其全體，同時或先後請求全部或一部\n      之給付。連帶債務未全部履行前，全體債務人仍負連帶責\n      任。」民法第272條第1項、第273條分別定有明文。\n   2、本件原告就其與訴外人陳永明、李金利等人分別共同向被\n      告借款，共計6500萬元，而為借款債務人，及與訴外人陳\n      永明、李金利、陳尾、陳抱為連帶債務人，此有上開原告\n      簽名之切結書、借款證明（支票簽收單）及土地建築改良\n      物抵押權設定約定書1 份（見台灣台北地方法院100 年度\n      重訴字第239 號卷第29頁至36頁）可證，且為原告所自承\n      （見本院100 年9 月8 日言詞辯論筆錄），依民法第272\n      條第1 項規定，原告與陳永明、李金利、陳尾、陳抱等人\n      就各別共同之系爭債務，對被告各負全部給付之責任；又\n      系爭抵押權係擔保原告及陳永明、李金利、陳尾、陳抱等\n      人對被告之債務，有土地登記第二類謄本可稽，則原告與\n      訴外人陳永明等人間之其中任一人對被告之債務均為系爭\n      抵押權擔保範圍，其內部如何分配或處分系爭借款，非被\n      告所得過問，原告縱未現實受領款項，基於其連帶債務人\n      地位，仍不能因此免責，即訴外人李金利等人對被告之債\n      務亦屬系爭抵押權擔保範圍；而系爭支票均經原告之簽收\n      簽名蓋章，並均有原告與訴外人陳永明之背書，已如前述\n      ，則原告以其未實際收受支票款項為由，主張其對被告所\n      負之債務僅2625萬元云云，不足酌採。\n（三）被告向原告等人除得請求約定之違約金外，是否仍得請求\n      遲延利息1848萬4375元？\n      原告主張被告在台灣台北地方法院96年度執進字第25774\n      號拍賣抵押物強制執行程序中，除主張約定之665 萬4375\n      元違約金外，另又主張1848萬4375元之遲延利息，此項請\n      求顯與民法第250 條第1 項及第2 項前段之規定不符，爰\n      一併請求確認以保原告之權益等語，惟為被告所否認，辯\n      稱：被告請求給付違約金係基於抵押權設定契約書，請求\n      給付遲延利息則係依民法第233 條之規定，兩者並無衝突\n      等語。按「違約金，有屬於懲罰之性質者，有屬於損害賠\n      償約定之性質者，本件違約金如為懲罰之性質，於上訴人\n      履行遲延時，被上訴人除請求違約金外，固得依民法第二\n      百三十三條規定，請求給付遲延利息及賠償其他之損害，\n      如為損害賠償約定之性質，則應視為就因遲延所生之損害\n      ，業已依契約預定其賠償，不得更請求遲延利息賠償損害\n      。」最高法院62年台上字第1394號著有判例可資參照。經\n      查：本件原告於上揭日期分別與訴外人陳抱、陳尾、李金\n      利、王簡阿玉、金陳寶英簽訂不動產買賣契約，約定各出\n      賣陳抱等人所有坐落臺北市○○區○○段3 小段第315 及\n      315 之1 至9 地號等10筆土地之應有部分。訴外人李金利\n      、陳尾、陳抱、王簡阿玉、金陳寶英分別於83年4 月1 日\n      、4 月11日、5 月4 日、5 月25日以其所有上開土地應有\n      部分，擔保李金利陳尾、陳抱分別與原告及訴外人陳永明\n      共同向被告借款，分別為被告設定2000萬元、1100萬元、\n      1100萬元、1300萬元、2000萬元，共計7,500 萬元之本金\n      最高限額抵押權，以擔保李金利、陳尾、陳抱、吳宛玉、\n      陳永明等人在抵押權範圍內之一切債務，並辦妥抵押權登\n      記在案等情，已如前述，而觀之抵押權設定契約書，固僅\n      記載違約金，而無遲延利息之記載，有該抵押權設定契約\n      書1 份附卷可按（見台灣台北地方法院100 年度重訴字第\n      239 號卷第29頁至36頁），惟此部分係有關抵押權效力所\n      及之約定，亦即抵押權之效力及於本金及違約金。而依上\n      開抵押權設定契約書所約定之違約金，係依每百元日息一\n      角五分計算，即每月每萬元15元，核其性質應屬懲罰違約\n      金，並非損害賠償約定之性質。依上開最高法院判例意旨\n      ，被告於原告等人履行遲延時，被告除請求違約金外，固\n      得依民法第233 條規定，請求給付遲延利息及賠償其他之\n      損害。又原告等人向被告借款之清償期，均為85年10月20\n      日，為兩造所不爭，則被告請求原告與李金利、陳尾、陳\n      抱等人分別共同向被告借款之部分，本金尚欠2625萬元，\n      違約金自85年10月21日起至99年11月20日止，每月每萬元\n      15元計算，共計665 萬4375元；遲延利息自85年10月21日\n      起至99年11月20日止，按年息百分之5 計算之利息，共計\n      1848萬4375元，有原告所提借款本金、遲延利息及約定違\n      約金計算表可佐（見台灣台北地方法院100 年度重訴字第\n      239 號卷第21頁），尚非無據，原告主張被告之遲延利息\n      1848萬4375元請求權不存在云云，並不足採。\n五、綜上，原告請求確認(一)請求確認原告與附表一第二項各土地\n    所有權人為連帶債務人，就同附表第三項所載土地，於83年\n    4 月1 日以被告為債權人所設定本金最高限額7500萬元之抵\n    押權設定為擔保實借金額為2625萬元。(二)請求確認前項所載\n    本金，自85年10月21日至99年11月20日止，約定違約金為66\n    5 萬4375元，被告另主張遲延利息1848萬4375元之請求權不\n    存在，為無理由，應予駁回。\n六、本件事證已臻明確，兩造其餘攻擊防禦方法暨舉證，經核與\n    判決結果不生影響，爰不一一論列，併此敘明。\n七、結論：原告之訴為無理由，依民事訴訟法第78條，判決如主\n    文。"
  },
  "search": "臺灣板橋地方法院民事判決100年度重訴字第181號原告吳宛玉訴訟代理人邱六郎律師被告謝劉碧霞訴訟代理人陳明暉律師複代理人郭令立律師上列當事人間請求確認債務額事件，經本院於民國100年9月8日言詞辯論終結，判決如下：主文原告之訴駁回。訴訟費用由原告負擔。事實及理由一、原告起訴主張：（一）原告於民國82年10月間向訴外人李金利、陳抱、陳尾、王簡阿玉、金陳寶英等人分別購買如附表二所示坐落臺北市中正區○○段○○段第315及315之1至9地號等10筆土地（下稱系爭土地）。83年3月間，訴外人簡金燦得知原告購買系爭土地，即向原告佯稱有款項可借原告並以系爭土地為擔保，原告徵得系爭土地之所有人即訴外人李金利陳抱、陳尾、王簡阿玉、金陳寶英等人之同意，即將土地所有權狀、印鑑證明書及印章交給簡金燦辦理貸款，並交由委任之代書辦理設定最高限額抵押權；惟簡金燦實際係向本件被告借款，並擅自將系爭土地完成本金最高限額新臺幣（下同）7500萬元之最高限額抵押權登記予被告，並將借得款項分別以被告簽發之九信支票給付與訴外人李金利、陳抱、陳尾、王簡阿玉、金陳寶英等人，核算渠等收受之支票總金額為2482萬5000元，加計原告陸續向被告借得142萬5000元之借款，合計為2625萬元。（二）簡金燦辦理前揭抵押權設定，設定期限一年，即自83年3月25日至84年3月24日止，並將數十張系爭土地所有權狀正本、印鑑章等交予被告保管，嗣被告為防止土地登記所有權人李金利等人再設定次順位抵押權，影響其貸款之回收，竟拒絕返還上開土地所有權狀正本、印鑑章，致原告與李金利等人間之契約無法履行，無法將系爭土地移轉登記予原告，終使貸款之清償發生遲延，此應歸責於被告之事由所致。多年前原告即多次要求被告協調清償前開欠款，但被告堅持李金利、陳抱、陳尾、王簡阿玉、金陳寶英等人所設定之抵押權本金為5125萬元，並於鈞院96年度執字第25774號聲請拍賣抵押物強制執行中，要求清償本息達9000萬元以上，其請求顯非合理。（三）另案陳抱、陳尾之繼承人陳文忠、陳以諾，曾就被告所提執行之異議之訴程序中，表示被告配偶謝英明所簽發領用北市九信之支票30張，分別交與李金利、陳尾、王簡阿玉、陳抱、金陳寶英，而總金額為7500萬元，有最高法院99年度台上字第485號裁定書之記載足資引據。據此即可證明，被告主張貸借予原告等之本金總額，與原告事實上所受之金額實有鉅額之差距，雙方就該債權額既有爭執，如不予確定顯有侵害及原告權益之虞，應認原告有確認之利益。蓋被告在拍賣抵押物強制執行程序中，除主張約定之665萬4375元違約金外，另又主張1848萬4375元之遲延利息，此項請求顯與民法第250條第1項及第2項前段之規定不符，爰一併請求確認以保原告之權益。（四）再被告雖主張曾簽發30張總金額6500萬元之支票，作為交付原告數額之證明，惟原告僅僅收到如原告100年6月8日民事準備（一）狀附表所示之10張支票，總計僅2742萬5000元，是其餘20張支票被告究竟交予何人？由何人兌領？請求依民事訴訟法第277條第1項規定，命被告舉證以實其說。另本件借貸緣由實原告向李金利等人購買系爭土地後，資金不足，徵得各地主同意提供各人所有土地，由原告向簡金燦醫師借貸，作為原告購買土地之部分價金，分別給付與各地主。期間一切手續向來經原告與簡金燦接洽，故始終認定簡金燦為金主，且所有貸款支票亦概由簡金燦交予原告。基此，究竟被告交予簡金燦幾紙支票？總金額為何？均於被告對系爭土地強制執行時，原告閱卷後始知，其餘20張支票乃被告與簡金燦間另一債權債務問題，至請斟酌。（五）被證一被告向北市九信合作社調取之27張支票影本，除未註明具領票款人之姓名，且因支票雖經背書，多無法辨認，故請求被告作成表格分別載明具領人姓名、住址等，供作確認。被證二切結書，則僅記載原告、李金利等人為債務人兼設定抵押權之義務，以及同意提供土地為擔保，向被告借貸之事實，毫未載明本件所列李金利等五人，實際借款若干之事實，顯然該切結書與本件之爭點無涉。又因該切結書所簽發之支票計9張，每張支票影本上雖均經原告、地主5人及另一連帶債務人陳永明蓋章，然此係簡金燦前此辦理抵押權設定登記持有原告等7人之印鑑，逕行蓋用於其上，非原告所蓋用。此外，該9張支票最後一紙支票下方附註欄，註有：「借款新台幣貳仟萬元，在於之前於民國83年3月24日，經借款人及連帶債務人，當面點收現金」等詞，並非真正，是請被告舉證究於何時、何地、在哪些人在場之下，又將此鉅款交於何人收受，此所謂2000萬元現款，是否以被告所指共簽發30張支票交於借款人收受，其中3張以現金換回未經兌領云云，究竟為哪3張支票？被證三切結書雖由原告與陳永明具名，表示願以金陳寶英之土地持份及地上物為擔保，請求被告給予貸款，但並未表示「已」向被告「借到」1500萬元。又該切結書所檢具之支票有8張，在支票與支票間之騎縫上，蓋章者有原告及陳永明二人，惟其中沒有一張經原告收受兌領。原告曾收受兌領之支票，僅被告所稱發交於簡金燦鈞院卷第185頁編號12、13面額分別為120萬、140萬元之支票2紙。另被證四切結書檢具之支票6張，於支票影本邊蓋章者，雖為原告、陳永明、王簡阿玉三人，但其中僅支票號碼CEO531977，面額245萬元之支票，由王簡阿玉收受兌領外，其餘5張則不知被告或簡金燦交付何人。另被證五之言詞辯論筆錄，並不能否認原告所指五人貸款金額僅2742萬5000元之事實，故被告應具體提出證明事項。（六）被告自稱共簽發30張支票之票號、金額、到期日，以及依被告所提兌現銀行供兌領人之背書，表列如附件3（見本院卷第113頁）惟其中兌領人與原告或地主毫無關係者，列舉如下：1、編號2，面額200萬元，兌領人呂清朗。2、編號8，面額270萬元，兌領人郭秀端。3、編號14、15、16、19，面額依序分別為90萬元、180萬元、120萬元、45萬元，兌領人完全空白，不知係由何人兌領。4、編號17、18、20，面額依序為530萬元、60萬元、20萬元，均係由呂月香兌領。5、編號27，面額67萬5000元，兌領者不詳。6、編號28，面額30萬元，兌領者呂月香。7、編號30，面額15萬元，兌領者不詳。（七）原告委由簡金燦代為辦理抵押借款時，曾再三言明按照原證1至原證5之買賣契約書約定之價款，扣除原告已支付之定金外金額，委由其定抵押貸款，貸得款項直接交於各地主，是以原告確未經手，此項情節除請參酌台北地院檢察署89年度偵字第22990號不起訴處分書第一項簡金燦證詞可證。被告稱2000萬元現金為支票簽收單所載編號1至7之七張支票（見本卷卷第113頁），由原告等人兌領，惟其中編號1為李金利、編號3為陳尾、編號6為塗銷陳抱抵押權登記代償於王文芬之支票，上開三張支票既為票據，並分別交由上開個人兌領，豈能又指為「當面點收現金新台幣貳仟萬元」，據此，益足證被告所指交付2000萬元云云，並非事實。（八）綜上所述，原告於本件有確認之利益。為此，依民事訴訟法第247條第1項前段、最高法院42年度台上字第1031號、52年度台上字第1237號之判例意旨，聲明：(一)請求確認原告與附表一第2項各土地所有權人為連帶債務人，就同附表第3項所載土地，於83年4月1日以被告為債權人所設定本金最高限額7500萬元之抵押權設定為擔保實借金額為2625萬元。(二)請求確認前項所載本金，自85年10月21日至99年11月20日止，約定違約金為665萬4375元，被告另主張遲延利息1848萬4375元之請求權不存在等語。二、被告答辯則以：（一）原告是否向訴外人李金利等人購買系爭坐落臺北市○○區○○段三小段第315號等10筆土地，被告並不知情，亦無法判斷原告所述情節是否真正，況無論原告所述之買賣是否屬實，均與被告無涉，與本訴訟無關。（二）原告與訴外人陳永明、李金利、王志銘、陳尾、陳抱、吳陳玉英、金陳寶英、王簡阿玉等，經由簡金燦分別於83年4、5月間向被告借款4000萬元、1500萬元、1000萬元，並分別約定違約金每月每萬15元、15元、20元，借款到期日則皆為85年10月20日，並有以下文件可證：1、原告與陳永明、李金利、王志銘、陳尾、陳抱、吳陳玉英等人，以李金利等人之不動產為擔保，向被告借款4000萬元所共同簽具之切結書及支票簽收單（包括現金2000萬元及支票9張面額合計2000萬元）。2、原告與陳永明持金陳寶英不動產為擔保，向被告借款所簽具之切結書及支票簽收單（包括支票8張面額合計1500萬元）。3、原告與陳永明持王簡阿玉不動產為擔保，向被告借款簽具之切結書及支票簽收單（包括支票6張面額合計1000萬元）。4、準此，原告不否認其於上開切結書上之簽名，而其既共同簽收上開現金及支票並負連帶責任，則其以原證1至原證5之土地買賣契約書所載付款紀錄，證明其僅負債2625萬元云云，顯無理由。（三）原告主張因被告保管土地所有權狀正本，致其無法辦理系爭土地所有權移轉登記，認原告與李金利等人之契約無法履行，終使貸款之清償發生遲延，應屬可歸責於被告之事由所致云云，與事實不符，蓋被告保管土地所有權狀僅係保全債權之方式，與原告對於系爭借貸能否清償無關，更何況自借貸迄被告前揭聲請執行已逾十餘年，其間原告又何曾提出款項表示清償？至於原告另主張被告請求給付違約金、遲延利息與民法第250條第1項、第2項前段規定不符云云，惟被告請求給付違約金係基於抵押權設定契約書，請求給付遲延利息則係依民法第233條之規定，兩者並無衝突。此外，按確認之訴，依民事訴訟法第247條規定，除確認證書真偽或為法律關係基礎事實存否之訴外，以確認法律關係始得提起，原告起訴請求確認債務額，於法不合，其訴之聲明亦不明確。（四）被證一至被證四中有關原告吳宛玉之簽名及印文均為一致，支票背面都有原告之背書，背書之印文也完全相同，然原告僅承認被證二、三、四上之簽名及印文為真正，執詞否認其他文件之真實，顯無理由而不可採信。另臺灣臺北地方法院96年度訴字第7399號債務人異議之訴乙案，就被告確實有給付借款之事實，及被證一27張支票交予原告吳宛玉等人簽收兌現等情，均已認定明確，此有臺灣臺北地方法院96年度訴字第7399號民事判決、臺灣高等法院97年度重上字第621號民事判決、最高法院99年度台上字第485號民事裁定可稽，原告執詞否認支票簽收印文真正，係屬臨訟卸責不可採信。（五）被證五臺北地方法院100年2月15日言詞辯論筆錄第6頁第15行所提示之「被證1支票簽收單」即為本件被證四第2頁之「支票簽收單」，筆錄中原告除出庭證稱支票上「吳宛玉」之簽名為其本人所簽之外，又再接續問到：「上開簽收單上也有王簡阿玉的指印，是否她本人所為？」證人即原告證稱：「是王簡阿玉的夫妻在一起，是王簡阿玉本人或她先生蓋指印，我不清楚」、「就王簡阿玉夫妻在場，誰簽名、蓋指印，我也沒有仔細看。」從而被告提出之被證二、被證三、被證四所檢附之切結書及支票簽收單，均有原告之簽名蓋章作為簽收憑據，原告在上開言詞辯論筆錄也承認「支票簽收單」上「吳宛玉」簽名為其本人所為，已足證明原告分別與其他債務人共同簽收取得該支票，原告以事前不知又未經手等語置辯，顯然不實。再縱如原告所稱乃簡金燦事後要求原告補簽乙節屬實，而原告既已簽署，自屬認同其相關內容，不影響其相關責任之判斷。（六）被證三之切結書及支票簽收單既經原告簽名蓋章，即足以證明原告向被告借款1500萬，並收取被告用以交付借款之支票；至原告簽收支票後，又將支票交給何人，已與被告無涉，被告亦無權干預，是原告已非其兌領云云，完全無視於支票簽收單上所記載之「茲收到上項第九信用合作社營業部支票捌張面額合計新台幣壹仟伍佰萬元正，業已辦妥抵押權設定登記在案，確實無誤。收款人：吳宛玉」此外，王簡阿玉是否收受被證四切結書編號21號支票，被告不得而知，惟王簡阿玉與原告既共同收受該支票簽收單上所列之支票6張，則渠等於共同簽收該6張支票後，如何分配取得支票，與被告無關，被告也無權過問，原告以其他5張不知被告或簡金燦交給何人云云，顯有誤解，被告沒有舉證之義務。另原告指稱未曾收受2000萬元部分，有鈞院卷第220頁附表二編號1-7之支票，該7紙支票面額合計即2000萬元，前經原告、陳永明、陳抱、陳尾、李金利、吳陳玉英等人於83年4月6日共同簽收，並分別於其後數日內兌現，有支票簽收單可證（被證七），足證原告及陳永明等人確已共同取得2000萬元款項，因該金額已經包括其後簽署之被證二支票簽收單所載「總款項新臺幣肆仟萬元整」之內，所以在執行程序，被告即未再就該支票簽收單提出作為債權憑證。原告在其99年6月4日寄予被告之台北光武郵局第499號存證信函，自承「民國83年間與本人向台端所借之款項...需還款新台幣陸仟伍佰萬元正...」可見原告其實也自己承認該6500萬元債務之存在。（七）臺灣臺北地方法院99年度重訴字第995號債務人異議之訴事件之爭點為抵押權設定登記是否有效存在，而本件原告則請求確認兩造間債務總額，二件似無牽涉。原告於上開案件中作證，證詞亦與本件無關；惟訴外人王信狀於99年12月17日親自出庭陳稱：「簽定這個契約時，吳宛玉叫謝劉碧霞拿支票給我們，支票金額多少我忘記了，交了幾張支票我也忘了，需要看契約才會知道」。對問：「吳宛玉跟你媽媽買土地，前後共付多少錢給你媽媽？」答：「一仟多萬，價金已付清了」可證被告在完成抵押權設定登記後，係直接按原告與各業主間之買賣契約所約定，直接將支票交給各業主，代替原告之給付。易言之，被告對系爭土地各業主之貸款，係由被告之代理人簡金燦直接交予各業主，原告確無經手之事實。且被告曾於上開案件中，自認證明被告所簽發之30張支票，均交於其代理人簡金燦，然後分交於系爭土地各業主。（八）李金利於100年8月17日經傳訊到庭，雖就相關借款過程大多以不復記憶或「沒有」來回應，惟其亦不否認有取得600萬元之事實。再審視證人當庭於證人結文上之簽名筆跡與被證二切結書上之簽名筆跡，其形式、筆劃亦極為相似，再加上其自承當時亦取得部分款項，自可推認被證二之文件確為其簽署。（九）為此，聲明請駁回原告之訴。三、兩造不爭執之事實：（一）原告與訴外人李金利、陳尾、陳抱、王簡阿玉、金陳寶英簽訂不動產買賣契約，約定各出賣其所有如附表二所示坐落臺北市○○區○○段3小段第315及315之1至9地號等10筆土地予原告。（見台灣台北地方法院100年度重訴字第239號卷第11頁至20頁）。（二）上開10筆土地之登記簿謄本之他項權利部記載：訴外人李金利、陳尾、陳抱、王簡阿玉、金陳寶英各以其所有之上開土地之應有部分，分別為被告設定2000萬、1100萬、1100萬、1300萬、2000萬，共計7500萬元之本金最高限額抵押權，以擔保李金利、陳尾、陳抱、吳宛玉、陳永明等人在抵押權範圍內之一切債務，並辦妥抵押權登記在案。各該抵押權約定存續期間分別自83年3月25日起至84年3月24日止、自83年3月25日起至84年3月24日止、自83年4月6日起至84年4月10日止、自83年4月29日起至84年5月1日止、自83年5月23日起至84年5月22日止，清償日期除金陳寶英所提供擔保之土地為84年5月22日外，其餘清償日期均依各個契約約定，並有臺北市土地登記第二類謄本附卷可稽（見本院卷第23頁至111頁）。（三）被告持上開最高限額抵押權執行名義，曾於96年間以臺灣臺北地方法院96年度執字第25774號聲請拍賣抵押物強制執行。（四）原告曾收受兌領由謝英明簽發，被告交付之貸款支票，支票號碼為CE0000000、CE0000000，發票日期83年4月12日，票面金額分別為120萬元、140萬元。（五）如附表一第二項所示之陳以諾為陳尾之繼承人；陳以忠、陳三郎、林玉葉、林兩傳、林治郎、陳榮生、陳振賢、倪陳淑珍為陳抱之繼承人；王信雄、王信壯、王金鳳、王阿足則為王簡阿玉之繼承人。四、本件爭點與本院判斷：原告主張伊與訴外人李金利等人訂立系爭土地買賣契約，並以系爭土地為向被告借款之擔保，設定本金最高限額7500萬元抵押權予被告，惟原告與李金利等人僅收受被告所簽發之支票金額共計2482萬5000元，加計原告陸續向被告借得142萬5000元之借款，合計為2625萬元等情，為被告所否認，並以上開情詞置辯，經查：本件原告於82年10月30日、12月4日、83年4月19日、4月30日分別與訴外人陳抱、陳尾、李金利、王簡阿玉、金陳寶英簽訂不動產買賣契約，約定各出賣陳抱等人所有如附表二所示坐落臺北市○○區○○段3小段第315及315之1至9地號等10筆土地之應有部分。訴外人李金利、陳尾、陳抱、王簡阿玉、金陳寶英分別於83年4月1日、4月11日、5月4日、5月25日以其所有上開土地應有部分，擔保李金利陳尾、陳抱分別與原告及訴外人陳永明共同向被告借款，分別為被告設定2000萬元、1100萬元、1100萬元、1300萬元、2000萬元，共計7,500萬元之本金最高限額抵押權，以擔保李金利、陳尾、陳抱、吳宛玉、陳永明等人在抵押權範圍內之一切債務，並辦妥抵押權登記在案。各該抵押權約定存續期間分別自83年3月25日起至84年3月24日止、自83年3月25日起至84年3月24日止、自83年4月6日起至84年4月10日止、自83年4月29日起至84年5月1日止、自83年5月23日起至84年5月22日止，清償日期除金陳寶英所提供擔保之土地為84年5月22日外，其餘清償日期均依各個契約約定。又如附表一第一項所示之陳以諾為陳尾之繼承人；陳以忠、陳三郎、林玉葉、林兩傳、林治郎、陳榮生、陳振賢、倪陳淑珍為陳抱之繼承人；王信雄、王信壯、王金鳳、王阿足則為王簡阿玉之繼承人等事實，為兩造所不爭執，並有臺北市土地登記第二類謄本附卷可稽（見本院卷第23頁至111頁），堪信為真。本件應審究之爭點厥為：（一）上開抵押權所擔保之債權是否存在？原告與訴外人李金利等人分別共同向被告借貸之金額總共為多少？被告是否已交付由原告等人簽收？（二）原告與訴外人李金利等人分別共同向被告所借得之款項，應否負連帶清償責任？（三）被告向原告等人除得請求約定之違約金外，是否仍得請求遲延利息1848萬4375元？本院之判斷如下：（一）上開抵押權所擔保之債權是否存在？原告等人分別共同向被告借貸之金額總共為多少？被告是否已交付由原告等人簽收？1.系爭抵押權為最高限額抵押，所謂最高限額之抵押契約，係指所有人提供抵押物，與債權人訂立在一定金額之限度內，擔保現在已發生及將來可能發生之債權之抵押權設定契約而言。此種抵押權所擔保之債權，除定約時已發生之債權外，即將來發生之債權，在約定限額之範圍內，亦為抵押權效力所及。雖抵押權存續期間內已發生之債權，因清償或其他事由而減少或消滅，原訂立之抵押契約依然有效，嗣後在存續期間內陸續發生之債權，債權人仍得對抵押物行使權利（最高法院66年臺上字第1097號判例參照）。又按抵押權所擔保之債權，其種類及範圍，屬於抵押權之內容，依法應經登記，始生物權之效力，但如因內容過於冗長，登記簿所列各欄篇幅不能容納記載，可以附件記載，作為登記簿之一部分。因此關於最高限額抵押權所擔保之債權，雖未記載於土地登記簿，然於聲請登記時提出之最高限額抵押權設定契約書，有該項債權之記載者，此契約書既作為登記簿之附件，自為抵押權效力所及（最高法院84年臺上字第1967號判例參照）。2、本件系爭最高限額抵押權係擔保原告及訴外人李金利、陳尾、陳抱、陳永明之債務，原告與訴外人陳永明為連帶債務人，此有被告所提原告與陳永明、李金利、陳尾等人分別所書立之切結書3紙及系爭土地登記第二類謄本土地他項權利部債務人及債務額比例欄所載在卷可佐（見本院卷第23頁至112頁、第168頁至171頁、第175頁及178頁），並為原告所不爭（見本院100年6月29日及9月8日言詞辯論筆錄），又依原告等人所書立之切結書載明約定擔保債權包括：「將來所負之借據、票據、保證、損害賠償等及其他一切債務」，是兩造係明定以借款、票據、保證、違約金債務等債權債務關係，作為系爭最高限額抵押權從屬之基礎法律關係。3、本件原告主張僅向被告借得2625萬元云云，被告則抗辯已交付台北市第九信用合作社支票30張予原告等人簽收，金額共計6500萬元，並已全部兌領等語，兩造所爭執之借貸關係乃發生於83年間，此有兩造所不爭之上開切結書所載日期可按，依實體從舊原則，兩造有關借款爭執部分，自應適用修正前民法關於消費借貸之規定。而稱消費借貸者，謂當事人一方移轉金錢或其他代替物之所有權於他方，而約定他方以種類、品質、數量相同之物返還之契約，民法第474條第1項定有明文。又金錢借貸契約固屬要物契約，應由貸與人就交付金錢之事實負舉證之責，但若貸與人提出之借用證內，經載明借款額，當日親收足訖無訛者，應解為貸與人就要物性之具備，已盡舉證責任，最高法院69年台上字第3546號判號例意旨可資參照，雖該判例嗣因民法第474條文字之修正而經該院決議刪除，然係顧慮原條文用語易遭誤會消費借貸契約係諾成契約而予修正，前開根據修正前法條所作成之判例因而隨之刪除，惟無論修法前後對借貸契約既均採要物契約見解（最高法院90年第4次民事庭會議決議參照）。則上開判例有關要物性舉證責任之歸屬之闡釋於法理上既無瑕疵，自仍得資為本件參酌之依據，故就已交付金錢之事實，應由被告負舉證責任。經查：被告抗辯原告與訴外人陳永明、李金利、陳尾、陳抱、金陳寶英、王簡阿玉等人，經由簡金燦分別於83年4、5月間向被告借款4000萬元、1500萬元、1000萬元，並分別約定違約金每月每萬15元、15元、20元，借款到期日則皆為85年10月20日，由被告之夫謝英明為發票人，以台北市第九信用合作社為付款人，簽發如附表三所示之支票30張交付原告等人簽收，除其中附表編號15、19及27嗣後由被告以現金換回外，其餘均已兌現之事實，已據被告提出原告等人所簽具之切結書3紙及借款證明（支票簽收單）4紙及支票30張影本、台北市第九信用合作社97年3月12日北市九信社業字第0383號函影本1份為證（本院卷第168頁至179頁、第226頁、第131頁至167頁），而觀之該切結書及依借款證明上均有原告之簽名及蓋章，原告雖否認借款證明（支票簽收單）上之簽名為其所簽，惟查：原告於台灣台北地方法院99年度重訴字第995號債務人異議之訴事件作證時，證稱：「（被告訴訟代理人問：（請提示被證1支票簽收單）上面的吳宛玉簽名是否是你本人所簽？）答：是我簽的：：：」等語（該院卷第130頁背面），經核與其他3紙借款證明（支票簽收單）之吳宛玉簽名，其筆勢、筆順經目視尚難看出有何相異之處，且原告對於切結書上之簽名亦不爭執為其所親簽，再徵之原告於99年6月4日所寄給被告之存證信函，亦自承：「於民國83年間（李金利等人）與本人間向台端所借之款項，約半年前我們雙方已達共識，需還款陸仟伍佰萬元正」等語（本院卷第227頁），被告主張該4紙借款證明（支票簽收單）係原告所簽之事實，堪信為真。又依借款證明（支票簽收單），其上分別載明：「（就如附表三編號1至7所示支票號碼CE0000000號至CE0000000號等7張支票部分）茲借款人（承買人）吳宛玉、提供擔保義務人兼債務人陳抱、陳尾、李金利、吳陳玉英於民國83年4月6日向債權人謝劉碧霞借款新台幣貳仟萬元，……經借款人與義務人兼債務人及連帶債務人當面點收現金事實無誤……簽收1.吳宛玉、陳永明。2.陳抱。3.陳尾、李金利。」、「（就如附表三編號8至16所示支票號碼CE0000000號至CE0000000號等9張支票部分）本件前順位私人（民間）借貸（代還前胎）清償向債權人謝劉碧霞借款新台幣貳仟萬元整，在於之前於民國83年3月24日經借款人及連帶債務人當面點收現金新台幣貳仟萬元整，計總款額新台幣肆仟萬元整事實無誤……簽收李金利、王志銘、吳陳玉英、陳抱、陳永明、吳宛玉、陳尾」等文字（見本院卷第226頁、第174頁），另附表三編號17至22號之支票6張，金額合計1000萬元，由原告及訴外人陳永明、王簡阿玉等3人簽收；附表三編號23至30所示8張支票，金額合計1500萬元，由原告吳宛玉、陳永明等2人簽收，此部分亦有原告吳宛玉所簽具之借款證明（支票簽收單）2紙及支票影本在卷可憑（本院卷第176至177頁、第179頁），除編號15、19及27嗣後由被告以現金換回外，其餘均已兌現，亦有台北市第九信用合作社97年3月12日函附於本院依職權調取之台灣台北地方法院96年度訴字第7399號卷可按（該院卷第204至243頁，另本院卷131頁至167頁亦附有影本）；稽之上開支票背面分別有訴外人李金利、陳抱、陳尾、陳永明、吳宛玉等人蓋章背書，顯見原告等人已分別簽收如附表三所示之系爭支票30張，其中編號15、19及27，則由被告以現金換回，其餘則均已兌現，堪以認定。從而，被告所辯其交付原告等人簽收之支票業經提示且已兌現，其有交付款項之事實，堪予採信。4、原告與訴外人李金利等人分別共同向被告借款，被告並已交付如附表三所示之支票，除其中編號15、19及27嗣後由被告以現金換回外，其餘均已兌現，已如前述，並參酌原告於99年6月4日所寄給被告之存證信函，自承需還款新臺幣陸仟伍佰萬元正等語，被告抗辯原告等人係向其借款6500萬元等語，堪信為真。被告所辯僅向被告借得2625萬元云云，則不足採信。（二）原告與訴外人李金利等人分別共同向被告所借得之款項，應否負連帶清償責任？1、按「數人負同一債務，明示對於債權人各負全部給付之責任者，為連帶債務。」「連帶債務之債權人，得對於債務人中之一人或數人或其全體，同時或先後請求全部或一部之給付。連帶債務未全部履行前，全體債務人仍負連帶責任。」民法第272條第1項、第273條分別定有明文。2、本件原告就其與訴外人陳永明、李金利等人分別共同向被告借款，共計6500萬元，而為借款債務人，及與訴外人陳永明、李金利、陳尾、陳抱為連帶債務人，此有上開原告簽名之切結書、借款證明（支票簽收單）及土地建築改良物抵押權設定約定書1份（見台灣台北地方法院100年度重訴字第239號卷第29頁至36頁）可證，且為原告所自承（見本院100年9月8日言詞辯論筆錄），依民法第272條第1項規定，原告與陳永明、李金利、陳尾、陳抱等人就各別共同之系爭債務，對被告各負全部給付之責任；又系爭抵押權係擔保原告及陳永明、李金利、陳尾、陳抱等人對被告之債務，有土地登記第二類謄本可稽，則原告與訴外人陳永明等人間之其中任一人對被告之債務均為系爭抵押權擔保範圍，其內部如何分配或處分系爭借款，非被告所得過問，原告縱未現實受領款項，基於其連帶債務人地位，仍不能因此免責，即訴外人李金利等人對被告之債務亦屬系爭抵押權擔保範圍；而系爭支票均經原告之簽收簽名蓋章，並均有原告與訴外人陳永明之背書，已如前述，則原告以其未實際收受支票款項為由，主張其對被告所負之債務僅2625萬元云云，不足酌採。（三）被告向原告等人除得請求約定之違約金外，是否仍得請求遲延利息1848萬4375元？原告主張被告在台灣台北地方法院96年度執進字第25774號拍賣抵押物強制執行程序中，除主張約定之665萬4375元違約金外，另又主張1848萬4375元之遲延利息，此項請求顯與民法第250條第1項及第2項前段之規定不符，爰一併請求確認以保原告之權益等語，惟為被告所否認，辯稱：被告請求給付違約金係基於抵押權設定契約書，請求給付遲延利息則係依民法第233條之規定，兩者並無衝突等語。按「違約金，有屬於懲罰之性質者，有屬於損害賠償約定之性質者，本件違約金如為懲罰之性質，於上訴人履行遲延時，被上訴人除請求違約金外，固得依民法第二百三十三條規定，請求給付遲延利息及賠償其他之損害，如為損害賠償約定之性質，則應視為就因遲延所生之損害，業已依契約預定其賠償，不得更請求遲延利息賠償損害。」最高法院62年台上字第1394號著有判例可資參照。經查：本件原告於上揭日期分別與訴外人陳抱、陳尾、李金利、王簡阿玉、金陳寶英簽訂不動產買賣契約，約定各出賣陳抱等人所有坐落臺北市○○區○○段3小段第315及315之1至9地號等10筆土地之應有部分。訴外人李金利、陳尾、陳抱、王簡阿玉、金陳寶英分別於83年4月1日、4月11日、5月4日、5月25日以其所有上開土地應有部分，擔保李金利陳尾、陳抱分別與原告及訴外人陳永明共同向被告借款，分別為被告設定2000萬元、1100萬元、1100萬元、1300萬元、2000萬元，共計7,500萬元之本金最高限額抵押權，以擔保李金利、陳尾、陳抱、吳宛玉、陳永明等人在抵押權範圍內之一切債務，並辦妥抵押權登記在案等情，已如前述，而觀之抵押權設定契約書，固僅記載違約金，而無遲延利息之記載，有該抵押權設定契約書1份附卷可按（見台灣台北地方法院100年度重訴字第239號卷第29頁至36頁），惟此部分係有關抵押權效力所及之約定，亦即抵押權之效力及於本金及違約金。而依上開抵押權設定契約書所約定之違約金，係依每百元日息一角五分計算，即每月每萬元15元，核其性質應屬懲罰違約金，並非損害賠償約定之性質。依上開最高法院判例意旨，被告於原告等人履行遲延時，被告除請求違約金外，固得依民法第233條規定，請求給付遲延利息及賠償其他之損害。又原告等人向被告借款之清償期，均為85年10月20日，為兩造所不爭，則被告請求原告與李金利、陳尾、陳抱等人分別共同向被告借款之部分，本金尚欠2625萬元，違約金自85年10月21日起至99年11月20日止，每月每萬元15元計算，共計665萬4375元；遲延利息自85年10月21日起至99年11月20日止，按年息百分之5計算之利息，共計1848萬4375元，有原告所提借款本金、遲延利息及約定違約金計算表可佐（見台灣台北地方法院100年度重訴字第239號卷第21頁），尚非無據，原告主張被告之遲延利息1848萬4375元請求權不存在云云，並不足採。五、綜上，原告請求確認(一)請求確認原告與附表一第二項各土地所有權人為連帶債務人，就同附表第三項所載土地，於83年4月1日以被告為債權人所設定本金最高限額7500萬元之抵押權設定為擔保實借金額為2625萬元。(二)請求確認前項所載本金，自85年10月21日至99年11月20日止，約定違約金為665萬4375元，被告另主張遲延利息1848萬4375元之請求權不存在，為無理由，應予駁回。六、本件事證已臻明確，兩造其餘攻擊防禦方法暨舉證，經核與判決結果不生影響，爰不一一論列，併此敘明。七、結論：原告之訴為無理由，依民事訴訟法第78條，判決如主文。中華民國100年9月29日民事第三庭法官林錫凱以上正本係照原本作成如對本判決上訴，須於判決送達後20日內向本院提出上訴狀。如委任律師提起上訴者，應一併繳納上訴審裁判費。中華民國100年9月29日書記官王小芬",
  "characters": {
    "judges": [
      "林錫凱"
    ],
    "prosecutors": [

    ],
    "lawyers": [
      "邱六郎",
      "陳明暉",
      "郭令立",
      "委任"
    ],
    "clerks": [

    ],
    "plaintiffs": [
      "吳宛玉"
    ],
    "defendants": [
      "謝劉碧霞"
    ],
    "prosecutor_office": [

    ],
    "creditors": [

    ],
    "debtors": [

    ],
    "judicial_associate_officer": [

    ]
  },
  "adjudged_at": "2011-09-29",
  "created_at": "2016-02-12 13:45:35",
  "updated_at": "2016-02-12 13:45:35"
}