{
  "identify": "SCD-100-竹簡-374-20110929-1",
  "court": {
    "name": "臺灣新竹地方法院",
    "code": "SCD"
  },
  "division": {
    "name": "刑事",
    "code": "M"
  },
  "year": 100,
  "word": "竹簡",
  "number": "374",
  "jcheck": "1",
  "reason": "違反槍砲彈藥刀械管制條例",
  "content": "臺灣新竹地方法院刑事簡易判決        100年度竹簡字第374號\n聲  請  人  臺灣新竹地方法院檢察署檢察官\n被      告  鄭程瑋\n上列被告因違反槍砲彈藥刀械管制條例案件，經檢察官聲請以簡\n易判決處刑（99年度偵字第9402號），本院判決如下:\n    主  文\n鄭程瑋犯非法持有子彈罪，累犯，處有期徒刑陸月，併科罰金新\n臺幣萬元，有期徒刑如易科罰金，罰金如易服勞役，均以新臺\n幣壹仟元折算壹日。\n    事實及理由\n一、本件犯罪事實：\n（一）、鄭程瑋前曾於民國89年間因犯傷害致死及妨害自由等\n        案件，經臺灣高等法院於92年11月25日以92年度上更一\n        字第37號判決分別判處有期徒刑7 年6 月，褫奪公權4\n        年及有期徒刑8 月，並定應執行有期徒刑8 年，褫奪公\n        權4 年，而經最高法院於93年11月4 日以93年度臺上字\n        第5769號判決上訴駁回因而確定；其又於91年間因違\n        反槍砲彈藥刀械管制條例及妨害自由等案件，經本院於\n        91年8 月15日以91年度訴字第364 號分別判處有期徒刑\n        1 年6 月，併科罰金新臺幣（下同）150000元、1 年2\n        月、1 年，應執行有期徒刑3 年4 月，併科罰金150000\n        元，又經臺灣高等法院於91年10月30日以91年度上訴字\n        第2890號撤銷原判決關於妨害自由二罪及執行刑部分，\n        改判處有期徒刑1 年2 月、1 年，並與駁回上訴之違反\n        槍砲彈藥刀械管制條例部分定應執行刑有期徒刑3 年4\n        月，併科罰金150000元，嗣並確定；嗣上開及案件\n        復經臺灣高等法院於96年7 月16日以96年度聲減字第70\n        8 號裁定減刑並定應執行刑有期徒刑9 年4 月，併科罰\n        金75000 元，褫奪公權4 年。其於91年12月20日入監執\n        行，於97年5 月8 日縮短刑期假釋付保護管束出監，並\n        於99年8 月3 日保護管束期滿，假釋未經撤銷視為執行\n        完畢。\n（二）、詎鄭程瑋仍不知悔改，明知具有殺傷力之子彈為槍砲彈\n        藥刀械管制條例所管制之物品，非經主管機關許可，不\n        得擅自持有，竟於99年11月27日中午12時30分許，在位\n        於新竹市○○路○ 段20巷166 號小林海釣場對面之產業\n        道路上，見口徑12GAUGE 具有殺傷力之制式霰彈7 顆遺\n        留在該處，竟基於非法持有具有殺傷力之子彈之犯意，\n        撿拾其中3 顆子彈藏放於長褲左側口袋內，而自斯時起\n        非法持有之。嗣於同日中午12時50分許，在新竹市○區\n        ○○路2 段678 號新竹國泰醫院急診室，為警當場查獲\n        ，並於其長褲左側口袋扣得前揭具有殺傷力之子彈3 顆\n        。\n（三）、案經新竹市警察局第三分局報請臺灣新竹地方法院檢察\n        署檢察官偵查並聲請簡易判決處刑。\n二、證據及理由：\n（一）、被告鄭程瑋於警詢及偵查中之供述。\n（二）、新竹市警察局第三分局自願受搜索同意書、搜索、扣押\n        筆錄、扣押物品目錄表、扣押物品收據、勘察報告各1\n        份、警員覃陽民出具之偵查報告1 份、警員李智瑋出具\n        之偵查報告2 份及警員張永昇出具之職務報告1 份在卷\n        可證。\n（三）、上開子彈經送內政部警政署刑事警察局鑑驗，鑑定情形\n        如下：送鑑子彈7 顆，認均係口徑12GAUGE 制式霰彈，\n        採樣2 顆試射，可擊發，認均具殺傷力；又經臺灣新竹\n        地方法院檢察署院將未試射子彈送內政部警政署刑事警\n        察局鑑定結果：未試射子彈5 顆，均經試射，可擊發，\n        認均具殺傷力等情，有99年12月15日刑鑑字第09901711\n        25號鑑定書1 份及內政部警政署刑事警察局100 年1 月\n        3 日刑鑑字第0990180654 號函1 份在卷足稽。\n（四）、查被告鄭程瑋於警詢及偵訊時固坦承有於上開時、地，\n        於地上撿拾三顆子彈，並置放於褲子左邊口袋內，為警\n        查獲等情，惟矢口否認涉嫌持有該子彈，辯稱：該三顆\n        子彈不是我的，是在現場的，但是誰的我也不清楚，因\n        為子彈是現場的證據，子彈上面有對方的指紋，所以我\n        把它放進我口袋內，我知道我身上有子彈，但我不知道\n        是誰的云云。經查：依本件子彈照片係藏放在被告所有\n        褲子左邊口袋內，（見臺灣新竹地方法院檢察署99年度\n        偵字第9402號卷第13頁）等情以觀，衡之常理，一般人\n        看到子彈散落一地，應主動報警處理，而被告不主動報\n        警，反將三顆子彈置放於其長褲左邊口袋內，並以此方\n        式對子彈有事實上之管領力無疑。況縱如被告所言，該\n        子彈均係他人所有，於被告明知上開子彈散落於現場之\n        情形，被告仍係基於為他人管理該子彈之意思而持有該\n        子彈，子彈為他人所有並無礙於被告與該子彈間之持有\n        關係成立。綜上，本件事證已臻明確，被告所辯顯係事\n        後卸責之詞，顯不足採，從而，該子彈確係查獲當時，\n        係被告所持有乙情，應可認定。\n三、論罪及科刑：\n    按槍砲彈藥刀械管制條例第4 條所列之槍砲、彈藥，依同條\n    例第5 條規定，非經中央主管機關許可，不得製造、販賣、\n    運輸、轉讓、出租、出借、持有、寄藏或陳列。核被告鄭程\n    瑋所為，係違反槍砲彈藥刀械管制條例第12條第4 項未經許\n    可持有子彈罪。又被告前曾於89年間因犯傷害致死及妨害\n    自由等案件，經臺灣高等法院於92年11月25日以92年度上更\n    一字第37號判決分別判處有期徒刑7 年6 月，褫奪公權4 年\n    及有期徒刑8 月，並定應執行有期徒刑8 年，褫奪公權4 年\n    ，而經最高法院於93年11月4 日以93年度臺上字第5769號判\n    決上訴駁回因而確定；其又於91年間因違反槍砲彈藥刀械\n    管制條例及妨害自由等案件，經本院於91年8 月15日以91年\n    度訴字第364 號分別判處有期徒刑1 年6 月，併科罰金1500\n    00元、1 年2 月、1 年，應執行有期徒刑3 年4 月，併科罰\n    金150000元，又經臺灣高等法院於91年10月30日以91 年 度\n    上訴字第2890號撤銷原判決關於妨害自由二罪及執行刑部分\n    ，改判處有期徒刑1 年2 月、1 年，並與駁回上訴之違反槍\n    砲彈藥刀械管制條例部分定應執行刑有期徒刑3 年4 月，併\n    科罰金150000元，嗣並確定；嗣上開及案件復經臺灣高\n    等法院於96年7 月16日以96年度聲減字第708 號裁定減刑並\n    定應執行刑有期徒刑9 年4 月，併科罰金75000 元，褫奪公\n    權4 年。其於91年12月20日入監執行，於97年5 月8 日縮短\n    刑期假釋付保護管束出監，並於99年8 月3 日保護管束期滿\n    ，假釋未經撤銷視為執行完畢等情，有臺灣新竹地方法院檢\n    察署刑案資料查註紀錄表及臺灣高等法院被告前案紀錄表各\n    1 份在卷足按，其於5 年以內再犯本件有期徒刑以上之罪，\n    為累犯，應依刑法第47條第1 項規定加重其刑。爰審酌被告\n    前有違反槍砲彈藥刀械管制條例及傷害致死案件之前科紀錄\n    ，素行非佳，又其非法持有具有殺傷力制式子彈3 顆，所為\n    對社會有潛在危險性，威脅社會秩序及人民之生命、身體安\n    全，影響社會治安，且被告飾詞狡辯，否認犯行，顯難認有\n    悔意，兼衡其生活狀況、智識程度、犯罪之動機、手段、持\n    有時間長短、持有子彈之數量為3 顆、所生危害程度等一切\n    情狀，量處如主文所示之刑，並分別就有期徒刑部分諭知如\n    易科罰金，及罰金部分諭知如易服勞役之折算標準，以資懲\n    儆。\n四、扣案之口徑12GAUGE 制式子彈7 顆（3 顆於被告長褲左邊口\n    袋搜出，4 顆於案發現場查獲），雖均具有殺傷力，惟經內\n    政部警政署刑事警察局鑑驗時試射擊發，試射後所餘之彈頭\n    、彈殼已喪失子彈效用，非屬違禁物，爰不予宣告沒收，附\n    此敘明。\n五、依刑事訴訟法第449 條第1 項前段、第454 條第1 項，槍砲\n    彈藥刀械管制條例第12條第4 項，刑法第11條前段、第47條\n    、第41條第1 項前段、第42條第3 項前段，逕以簡易判決處\n    刑如主文。\n六、如不服本判決，得自收受送達之日起10日內，向本院提起上\n    訴。\n中    華    民    國   100    年    9     月    29    日\n                  新竹簡易庭    法  官  王銘勇\n以上正本證明與原本無異。\n中    華    民    國   100    年    9     月    29    日\n                                書記官  許弘杰\n附錄本院論罪科刑法條：\n槍砲彈藥刀械管制條例第12條：\n未經許可，製造、販賣或運輸子彈者，處一年以上七年以下有期\n徒刑，併科新臺幣五百萬元以下罰金。\n未經許可，轉讓、出租或出借子彈者，處六月以上五年以下有期\n徒刑，併科新臺幣三百萬元以下罰金。\n意圖供自己或他人犯罪之用，而犯前二項之罪者，處三年以上十\n年以下有期徒刑，併科新臺幣七百萬元以下罰金。\n未經許可，持有、寄藏或意圖販賣而陳列子彈者，處五年以下有\n期徒刑，併科新臺幣三百萬元以下罰金。\n第一項至第三項之未遂犯罰之。",
  "structure": {
    "main": "鄭程瑋犯非法持有子彈罪，累犯，處有期徒刑陸月，併科罰金新\n臺幣萬元，有期徒刑如易科罰金，罰金如易服勞役，均以新臺\n幣壹仟元折算壹日。",
    "fact": "一、本件犯罪事實：\n（一）、鄭程瑋前曾於民國89年間因犯傷害致死及妨害自由等\n        案件，經臺灣高等法院於92年11月25日以92年度上更一\n        字第37號判決分別判處有期徒刑7 年6 月，褫奪公權4\n        年及有期徒刑8 月，並定應執行有期徒刑8 年，褫奪公\n        權4 年，而經最高法院於93年11月4 日以93年度臺上字\n        第5769號判決上訴駁回因而確定；其又於91年間因違\n        反槍砲彈藥刀械管制條例及妨害自由等案件，經本院於\n        91年8 月15日以91年度訴字第364 號分別判處有期徒刑\n        1 年6 月，併科罰金新臺幣（下同）150000元、1 年2\n        月、1 年，應執行有期徒刑3 年4 月，併科罰金150000\n        元，又經臺灣高等法院於91年10月30日以91年度上訴字\n        第2890號撤銷原判決關於妨害自由二罪及執行刑部分，\n        改判處有期徒刑1 年2 月、1 年，並與駁回上訴之違反\n        槍砲彈藥刀械管制條例部分定應執行刑有期徒刑3 年4\n        月，併科罰金150000元，嗣並確定；嗣上開及案件\n        復經臺灣高等法院於96年7 月16日以96年度聲減字第70\n        8 號裁定減刑並定應執行刑有期徒刑9 年4 月，併科罰\n        金75000 元，褫奪公權4 年。其於91年12月20日入監執\n        行，於97年5 月8 日縮短刑期假釋付保護管束出監，並\n        於99年8 月3 日保護管束期滿，假釋未經撤銷視為執行\n        完畢。\n（二）、詎鄭程瑋仍不知悔改，明知具有殺傷力之子彈為槍砲彈\n        藥刀械管制條例所管制之物品，非經主管機關許可，不\n        得擅自持有，竟於99年11月27日中午12時30分許，在位\n        於新竹市○○路○ 段20巷166 號小林海釣場對面之產業\n        道路上，見口徑12GAUGE 具有殺傷力之制式霰彈7 顆遺\n        留在該處，竟基於非法持有具有殺傷力之子彈之犯意，\n        撿拾其中3 顆子彈藏放於長褲左側口袋內，而自斯時起\n        非法持有之。嗣於同日中午12時50分許，在新竹市○區\n        ○○路2 段678 號新竹國泰醫院急診室，為警當場查獲\n        ，並於其長褲左側口袋扣得前揭具有殺傷力之子彈3 顆\n        。\n（三）、案經新竹市警察局第三分局報請臺灣新竹地方法院檢察\n        署檢察官偵查並聲請簡易判決處刑。\n二、證據及理由：\n（一）、被告鄭程瑋於警詢及偵查中之供述。\n（二）、新竹市警察局第三分局自願受搜索同意書、搜索、扣押\n        筆錄、扣押物品目錄表、扣押物品收據、勘察報告各1\n        份、警員覃陽民出具之偵查報告1 份、警員李智瑋出具\n        之偵查報告2 份及警員張永昇出具之職務報告1 份在卷\n        可證。\n（三）、上開子彈經送內政部警政署刑事警察局鑑驗，鑑定情形\n        如下：送鑑子彈7 顆，認均係口徑12GAUGE 制式霰彈，\n        採樣2 顆試射，可擊發，認均具殺傷力；又經臺灣新竹\n        地方法院檢察署院將未試射子彈送內政部警政署刑事警\n        察局鑑定結果：未試射子彈5 顆，均經試射，可擊發，\n        認均具殺傷力等情，有99年12月15日刑鑑字第09901711\n        25號鑑定書1 份及內政部警政署刑事警察局100 年1 月\n        3 日刑鑑字第0990180654 號函1 份在卷足稽。\n（四）、查被告鄭程瑋於警詢及偵訊時固坦承有於上開時、地，\n        於地上撿拾三顆子彈，並置放於褲子左邊口袋內，為警\n        查獲等情，惟矢口否認涉嫌持有該子彈，辯稱：該三顆\n        子彈不是我的，是在現場的，但是誰的我也不清楚，因\n        為子彈是現場的證據，子彈上面有對方的指紋，所以我\n        把它放進我口袋內，我知道我身上有子彈，但我不知道\n        是誰的云云。經查：依本件子彈照片係藏放在被告所有\n        褲子左邊口袋內，（見臺灣新竹地方法院檢察署99年度\n        偵字第9402號卷第13頁）等情以觀，衡之常理，一般人\n        看到子彈散落一地，應主動報警處理，而被告不主動報\n        警，反將三顆子彈置放於其長褲左邊口袋內，並以此方\n        式對子彈有事實上之管領力無疑。況縱如被告所言，該\n        子彈均係他人所有，於被告明知上開子彈散落於現場之\n        情形，被告仍係基於為他人管理該子彈之意思而持有該\n        子彈，子彈為他人所有並無礙於被告與該子彈間之持有\n        關係成立。綜上，本件事證已臻明確，被告所辯顯係事\n        後卸責之詞，顯不足採，從而，該子彈確係查獲當時，\n        係被告所持有乙情，應可認定。\n三、論罪及科刑：\n    按槍砲彈藥刀械管制條例第4 條所列之槍砲、彈藥，依同條\n    例第5 條規定，非經中央主管機關許可，不得製造、販賣、\n    運輸、轉讓、出租、出借、持有、寄藏或陳列。核被告鄭程\n    瑋所為，係違反槍砲彈藥刀械管制條例第12條第4 項未經許\n    可持有子彈罪。又被告前曾於89年間因犯傷害致死及妨害\n    自由等案件，經臺灣高等法院於92年11月25日以92年度上更\n    一字第37號判決分別判處有期徒刑7 年6 月，褫奪公權4 年\n    及有期徒刑8 月，並定應執行有期徒刑8 年，褫奪公權4 年\n    ，而經最高法院於93年11月4 日以93年度臺上字第5769號判\n    決上訴駁回因而確定；其又於91年間因違反槍砲彈藥刀械\n    管制條例及妨害自由等案件，經本院於91年8 月15日以91年\n    度訴字第364 號分別判處有期徒刑1 年6 月，併科罰金1500\n    00元、1 年2 月、1 年，應執行有期徒刑3 年4 月，併科罰\n    金150000元，又經臺灣高等法院於91年10月30日以91 年 度\n    上訴字第2890號撤銷原判決關於妨害自由二罪及執行刑部分\n    ，改判處有期徒刑1 年2 月、1 年，並與駁回上訴之違反槍\n    砲彈藥刀械管制條例部分定應執行刑有期徒刑3 年4 月，併\n    科罰金150000元，嗣並確定；嗣上開及案件復經臺灣高\n    等法院於96年7 月16日以96年度聲減字第708 號裁定減刑並\n    定應執行刑有期徒刑9 年4 月，併科罰金75000 元，褫奪公\n    權4 年。其於91年12月20日入監執行，於97年5 月8 日縮短\n    刑期假釋付保護管束出監，並於99年8 月3 日保護管束期滿\n    ，假釋未經撤銷視為執行完畢等情，有臺灣新竹地方法院檢\n    察署刑案資料查註紀錄表及臺灣高等法院被告前案紀錄表各\n    1 份在卷足按，其於5 年以內再犯本件有期徒刑以上之罪，\n    為累犯，應依刑法第47條第1 項規定加重其刑。爰審酌被告\n    前有違反槍砲彈藥刀械管制條例及傷害致死案件之前科紀錄\n    ，素行非佳，又其非法持有具有殺傷力制式子彈3 顆，所為\n    對社會有潛在危險性，威脅社會秩序及人民之生命、身體安\n    全，影響社會治安，且被告飾詞狡辯，否認犯行，顯難認有\n    悔意，兼衡其生活狀況、智識程度、犯罪之動機、手段、持\n    有時間長短、持有子彈之數量為3 顆、所生危害程度等一切\n    情狀，量處如主文所示之刑，並分別就有期徒刑部分諭知如\n    易科罰金，及罰金部分諭知如易服勞役之折算標準，以資懲\n    儆。\n四、扣案之口徑12GAUGE 制式子彈7 顆（3 顆於被告長褲左邊口\n    袋搜出，4 顆於案發現場查獲），雖均具有殺傷力，惟經內\n    政部警政署刑事警察局鑑驗時試射擊發，試射後所餘之彈頭\n    、彈殼已喪失子彈效用，非屬違禁物，爰不予宣告沒收，附\n    此敘明。\n五、依刑事訴訟法第449 條第1 項前段、第454 條第1 項，槍砲\n    彈藥刀械管制條例第12條第4 項，刑法第11條前段、第47條\n    、第41條第1 項前段、第42條第3 項前段，逕以簡易判決處\n    刑如主文。\n六、如不服本判決，得自收受送達之日起10日內，向本院提起上\n    訴。",
    "reason": "一、本件犯罪事實：\n（一）、鄭程瑋前曾於民國89年間因犯傷害致死及妨害自由等\n        案件，經臺灣高等法院於92年11月25日以92年度上更一\n        字第37號判決分別判處有期徒刑7 年6 月，褫奪公權4\n        年及有期徒刑8 月，並定應執行有期徒刑8 年，褫奪公\n        權4 年，而經最高法院於93年11月4 日以93年度臺上字\n        第5769號判決上訴駁回因而確定；其又於91年間因違\n        反槍砲彈藥刀械管制條例及妨害自由等案件，經本院於\n        91年8 月15日以91年度訴字第364 號分別判處有期徒刑\n        1 年6 月，併科罰金新臺幣（下同）150000元、1 年2\n        月、1 年，應執行有期徒刑3 年4 月，併科罰金150000\n        元，又經臺灣高等法院於91年10月30日以91年度上訴字\n        第2890號撤銷原判決關於妨害自由二罪及執行刑部分，\n        改判處有期徒刑1 年2 月、1 年，並與駁回上訴之違反\n        槍砲彈藥刀械管制條例部分定應執行刑有期徒刑3 年4\n        月，併科罰金150000元，嗣並確定；嗣上開及案件\n        復經臺灣高等法院於96年7 月16日以96年度聲減字第70\n        8 號裁定減刑並定應執行刑有期徒刑9 年4 月，併科罰\n        金75000 元，褫奪公權4 年。其於91年12月20日入監執\n        行，於97年5 月8 日縮短刑期假釋付保護管束出監，並\n        於99年8 月3 日保護管束期滿，假釋未經撤銷視為執行\n        完畢。\n（二）、詎鄭程瑋仍不知悔改，明知具有殺傷力之子彈為槍砲彈\n        藥刀械管制條例所管制之物品，非經主管機關許可，不\n        得擅自持有，竟於99年11月27日中午12時30分許，在位\n        於新竹市○○路○ 段20巷166 號小林海釣場對面之產業\n        道路上，見口徑12GAUGE 具有殺傷力之制式霰彈7 顆遺\n        留在該處，竟基於非法持有具有殺傷力之子彈之犯意，\n        撿拾其中3 顆子彈藏放於長褲左側口袋內，而自斯時起\n        非法持有之。嗣於同日中午12時50分許，在新竹市○區\n        ○○路2 段678 號新竹國泰醫院急診室，為警當場查獲\n        ，並於其長褲左側口袋扣得前揭具有殺傷力之子彈3 顆\n        。\n（三）、案經新竹市警察局第三分局報請臺灣新竹地方法院檢察\n        署檢察官偵查並聲請簡易判決處刑。\n二、證據及理由：\n（一）、被告鄭程瑋於警詢及偵查中之供述。\n（二）、新竹市警察局第三分局自願受搜索同意書、搜索、扣押\n        筆錄、扣押物品目錄表、扣押物品收據、勘察報告各1\n        份、警員覃陽民出具之偵查報告1 份、警員李智瑋出具\n        之偵查報告2 份及警員張永昇出具之職務報告1 份在卷\n        可證。\n（三）、上開子彈經送內政部警政署刑事警察局鑑驗，鑑定情形\n        如下：送鑑子彈7 顆，認均係口徑12GAUGE 制式霰彈，\n        採樣2 顆試射，可擊發，認均具殺傷力；又經臺灣新竹\n        地方法院檢察署院將未試射子彈送內政部警政署刑事警\n        察局鑑定結果：未試射子彈5 顆，均經試射，可擊發，\n        認均具殺傷力等情，有99年12月15日刑鑑字第09901711\n        25號鑑定書1 份及內政部警政署刑事警察局100 年1 月\n        3 日刑鑑字第0990180654 號函1 份在卷足稽。\n（四）、查被告鄭程瑋於警詢及偵訊時固坦承有於上開時、地，\n        於地上撿拾三顆子彈，並置放於褲子左邊口袋內，為警\n        查獲等情，惟矢口否認涉嫌持有該子彈，辯稱：該三顆\n        子彈不是我的，是在現場的，但是誰的我也不清楚，因\n        為子彈是現場的證據，子彈上面有對方的指紋，所以我\n        把它放進我口袋內，我知道我身上有子彈，但我不知道\n        是誰的云云。經查：依本件子彈照片係藏放在被告所有\n        褲子左邊口袋內，（見臺灣新竹地方法院檢察署99年度\n        偵字第9402號卷第13頁）等情以觀，衡之常理，一般人\n        看到子彈散落一地，應主動報警處理，而被告不主動報\n        警，反將三顆子彈置放於其長褲左邊口袋內，並以此方\n        式對子彈有事實上之管領力無疑。況縱如被告所言，該\n        子彈均係他人所有，於被告明知上開子彈散落於現場之\n        情形，被告仍係基於為他人管理該子彈之意思而持有該\n        子彈，子彈為他人所有並無礙於被告與該子彈間之持有\n        關係成立。綜上，本件事證已臻明確，被告所辯顯係事\n        後卸責之詞，顯不足採，從而，該子彈確係查獲當時，\n        係被告所持有乙情，應可認定。\n三、論罪及科刑：\n    按槍砲彈藥刀械管制條例第4 條所列之槍砲、彈藥，依同條\n    例第5 條規定，非經中央主管機關許可，不得製造、販賣、\n    運輸、轉讓、出租、出借、持有、寄藏或陳列。核被告鄭程\n    瑋所為，係違反槍砲彈藥刀械管制條例第12條第4 項未經許\n    可持有子彈罪。又被告前曾於89年間因犯傷害致死及妨害\n    自由等案件，經臺灣高等法院於92年11月25日以92年度上更\n    一字第37號判決分別判處有期徒刑7 年6 月，褫奪公權4 年\n    及有期徒刑8 月，並定應執行有期徒刑8 年，褫奪公權4 年\n    ，而經最高法院於93年11月4 日以93年度臺上字第5769號判\n    決上訴駁回因而確定；其又於91年間因違反槍砲彈藥刀械\n    管制條例及妨害自由等案件，經本院於91年8 月15日以91年\n    度訴字第364 號分別判處有期徒刑1 年6 月，併科罰金1500\n    00元、1 年2 月、1 年，應執行有期徒刑3 年4 月，併科罰\n    金150000元，又經臺灣高等法院於91年10月30日以91 年 度\n    上訴字第2890號撤銷原判決關於妨害自由二罪及執行刑部分\n    ，改判處有期徒刑1 年2 月、1 年，並與駁回上訴之違反槍\n    砲彈藥刀械管制條例部分定應執行刑有期徒刑3 年4 月，併\n    科罰金150000元，嗣並確定；嗣上開及案件復經臺灣高\n    等法院於96年7 月16日以96年度聲減字第708 號裁定減刑並\n    定應執行刑有期徒刑9 年4 月，併科罰金75000 元，褫奪公\n    權4 年。其於91年12月20日入監執行，於97年5 月8 日縮短\n    刑期假釋付保護管束出監，並於99年8 月3 日保護管束期滿\n    ，假釋未經撤銷視為執行完畢等情，有臺灣新竹地方法院檢\n    察署刑案資料查註紀錄表及臺灣高等法院被告前案紀錄表各\n    1 份在卷足按，其於5 年以內再犯本件有期徒刑以上之罪，\n    為累犯，應依刑法第47條第1 項規定加重其刑。爰審酌被告\n    前有違反槍砲彈藥刀械管制條例及傷害致死案件之前科紀錄\n    ，素行非佳，又其非法持有具有殺傷力制式子彈3 顆，所為\n    對社會有潛在危險性，威脅社會秩序及人民之生命、身體安\n    全，影響社會治安，且被告飾詞狡辯，否認犯行，顯難認有\n    悔意，兼衡其生活狀況、智識程度、犯罪之動機、手段、持\n    有時間長短、持有子彈之數量為3 顆、所生危害程度等一切\n    情狀，量處如主文所示之刑，並分別就有期徒刑部分諭知如\n    易科罰金，及罰金部分諭知如易服勞役之折算標準，以資懲\n    儆。\n四、扣案之口徑12GAUGE 制式子彈7 顆（3 顆於被告長褲左邊口\n    袋搜出，4 顆於案發現場查獲），雖均具有殺傷力，惟經內\n    政部警政署刑事警察局鑑驗時試射擊發，試射後所餘之彈頭\n    、彈殼已喪失子彈效用，非屬違禁物，爰不予宣告沒收，附\n    此敘明。\n五、依刑事訴訟法第449 條第1 項前段、第454 條第1 項，槍砲\n    彈藥刀械管制條例第12條第4 項，刑法第11條前段、第47條\n    、第41條第1 項前段、第42條第3 項前段，逕以簡易判決處\n    刑如主文。\n六、如不服本判決，得自收受送達之日起10日內，向本院提起上\n    訴。"
  },
  "search": "臺灣新竹地方法院刑事簡易判決100年度竹簡字第374號聲請人臺灣新竹地方法院檢察署檢察官被告鄭程瑋上列被告因違反槍砲彈藥刀械管制條例案件，經檢察官聲請以簡易判決處刑（99年度偵字第9402號），本院判決如下:主文鄭程瑋犯非法持有子彈罪，累犯，處有期徒刑陸月，併科罰金新臺幣萬元，有期徒刑如易科罰金，罰金如易服勞役，均以新臺幣壹仟元折算壹日。事實及理由一、本件犯罪事實：（一）、鄭程瑋前曾於民國89年間因犯傷害致死及妨害自由等案件，經臺灣高等法院於92年11月25日以92年度上更一字第37號判決分別判處有期徒刑7年6月，褫奪公權4年及有期徒刑8月，並定應執行有期徒刑8年，褫奪公權4年，而經最高法院於93年11月4日以93年度臺上字第5769號判決上訴駁回因而確定；其又於91年間因違反槍砲彈藥刀械管制條例及妨害自由等案件，經本院於91年8月15日以91年度訴字第364號分別判處有期徒刑1年6月，併科罰金新臺幣（下同）150000元、1年2月、1年，應執行有期徒刑3年4月，併科罰金150000元，又經臺灣高等法院於91年10月30日以91年度上訴字第2890號撤銷原判決關於妨害自由二罪及執行刑部分，改判處有期徒刑1年2月、1年，並與駁回上訴之違反槍砲彈藥刀械管制條例部分定應執行刑有期徒刑3年4月，併科罰金150000元，嗣並確定；嗣上開及案件復經臺灣高等法院於96年7月16日以96年度聲減字第708號裁定減刑並定應執行刑有期徒刑9年4月，併科罰金75000元，褫奪公權4年。其於91年12月20日入監執行，於97年5月8日縮短刑期假釋付保護管束出監，並於99年8月3日保護管束期滿，假釋未經撤銷視為執行完畢。（二）、詎鄭程瑋仍不知悔改，明知具有殺傷力之子彈為槍砲彈藥刀械管制條例所管制之物品，非經主管機關許可，不得擅自持有，竟於99年11月27日中午12時30分許，在位於新竹市○○路○段20巷166號小林海釣場對面之產業道路上，見口徑12GAUGE具有殺傷力之制式霰彈7顆遺留在該處，竟基於非法持有具有殺傷力之子彈之犯意，撿拾其中3顆子彈藏放於長褲左側口袋內，而自斯時起非法持有之。嗣於同日中午12時50分許，在新竹市○區○○路2段678號新竹國泰醫院急診室，為警當場查獲，並於其長褲左側口袋扣得前揭具有殺傷力之子彈3顆。（三）、案經新竹市警察局第三分局報請臺灣新竹地方法院檢察署檢察官偵查並聲請簡易判決處刑。二、證據及理由：（一）、被告鄭程瑋於警詢及偵查中之供述。（二）、新竹市警察局第三分局自願受搜索同意書、搜索、扣押筆錄、扣押物品目錄表、扣押物品收據、勘察報告各1份、警員覃陽民出具之偵查報告1份、警員李智瑋出具之偵查報告2份及警員張永昇出具之職務報告1份在卷可證。（三）、上開子彈經送內政部警政署刑事警察局鑑驗，鑑定情形如下：送鑑子彈7顆，認均係口徑12GAUGE制式霰彈，採樣2顆試射，可擊發，認均具殺傷力；又經臺灣新竹地方法院檢察署院將未試射子彈送內政部警政署刑事警察局鑑定結果：未試射子彈5顆，均經試射，可擊發，認均具殺傷力等情，有99年12月15日刑鑑字第0990171125號鑑定書1份及內政部警政署刑事警察局100年1月3日刑鑑字第0990180654號函1份在卷足稽。（四）、查被告鄭程瑋於警詢及偵訊時固坦承有於上開時、地，於地上撿拾三顆子彈，並置放於褲子左邊口袋內，為警查獲等情，惟矢口否認涉嫌持有該子彈，辯稱：該三顆子彈不是我的，是在現場的，但是誰的我也不清楚，因為子彈是現場的證據，子彈上面有對方的指紋，所以我把它放進我口袋內，我知道我身上有子彈，但我不知道是誰的云云。經查：依本件子彈照片係藏放在被告所有褲子左邊口袋內，（見臺灣新竹地方法院檢察署99年度偵字第9402號卷第13頁）等情以觀，衡之常理，一般人看到子彈散落一地，應主動報警處理，而被告不主動報警，反將三顆子彈置放於其長褲左邊口袋內，並以此方式對子彈有事實上之管領力無疑。況縱如被告所言，該子彈均係他人所有，於被告明知上開子彈散落於現場之情形，被告仍係基於為他人管理該子彈之意思而持有該子彈，子彈為他人所有並無礙於被告與該子彈間之持有關係成立。綜上，本件事證已臻明確，被告所辯顯係事後卸責之詞，顯不足採，從而，該子彈確係查獲當時，係被告所持有乙情，應可認定。三、論罪及科刑：按槍砲彈藥刀械管制條例第4條所列之槍砲、彈藥，依同條例第5條規定，非經中央主管機關許可，不得製造、販賣、運輸、轉讓、出租、出借、持有、寄藏或陳列。核被告鄭程瑋所為，係違反槍砲彈藥刀械管制條例第12條第4項未經許可持有子彈罪。又被告前曾於89年間因犯傷害致死及妨害自由等案件，經臺灣高等法院於92年11月25日以92年度上更一字第37號判決分別判處有期徒刑7年6月，褫奪公權4年及有期徒刑8月，並定應執行有期徒刑8年，褫奪公權4年，而經最高法院於93年11月4日以93年度臺上字第5769號判決上訴駁回因而確定；其又於91年間因違反槍砲彈藥刀械管制條例及妨害自由等案件，經本院於91年8月15日以91年度訴字第364號分別判處有期徒刑1年6月，併科罰金150000元、1年2月、1年，應執行有期徒刑3年4月，併科罰金150000元，又經臺灣高等法院於91年10月30日以91年度上訴字第2890號撤銷原判決關於妨害自由二罪及執行刑部分，改判處有期徒刑1年2月、1年，並與駁回上訴之違反槍砲彈藥刀械管制條例部分定應執行刑有期徒刑3年4月，併科罰金150000元，嗣並確定；嗣上開及案件復經臺灣高等法院於96年7月16日以96年度聲減字第708號裁定減刑並定應執行刑有期徒刑9年4月，併科罰金75000元，褫奪公權4年。其於91年12月20日入監執行，於97年5月8日縮短刑期假釋付保護管束出監，並於99年8月3日保護管束期滿，假釋未經撤銷視為執行完畢等情，有臺灣新竹地方法院檢察署刑案資料查註紀錄表及臺灣高等法院被告前案紀錄表各1份在卷足按，其於5年以內再犯本件有期徒刑以上之罪，為累犯，應依刑法第47條第1項規定加重其刑。爰審酌被告前有違反槍砲彈藥刀械管制條例及傷害致死案件之前科紀錄，素行非佳，又其非法持有具有殺傷力制式子彈3顆，所為對社會有潛在危險性，威脅社會秩序及人民之生命、身體安全，影響社會治安，且被告飾詞狡辯，否認犯行，顯難認有悔意，兼衡其生活狀況、智識程度、犯罪之動機、手段、持有時間長短、持有子彈之數量為3顆、所生危害程度等一切情狀，量處如主文所示之刑，並分別就有期徒刑部分諭知如易科罰金，及罰金部分諭知如易服勞役之折算標準，以資懲儆。四、扣案之口徑12GAUGE制式子彈7顆（3顆於被告長褲左邊口袋搜出，4顆於案發現場查獲），雖均具有殺傷力，惟經內政部警政署刑事警察局鑑驗時試射擊發，試射後所餘之彈頭、彈殼已喪失子彈效用，非屬違禁物，爰不予宣告沒收，附此敘明。五、依刑事訴訟法第449條第1項前段、第454條第1項，槍砲彈藥刀械管制條例第12條第4項，刑法第11條前段、第47條、第41條第1項前段、第42條第3項前段，逕以簡易判決處刑如主文。六、如不服本判決，得自收受送達之日起10日內，向本院提起上訴。中華民國100年9月29日新竹簡易庭法官王銘勇以上正本證明與原本無異。中華民國100年9月29日書記官許弘杰附錄本院論罪科刑法條：槍砲彈藥刀械管制條例第12條：未經許可，製造、販賣或運輸子彈者，處一年以上七年以下有期徒刑，併科新臺幣五百萬元以下罰金。未經許可，轉讓、出租或出借子彈者，處六月以上五年以下有期徒刑，併科新臺幣三百萬元以下罰金。意圖供自己或他人犯罪之用，而犯前二項之罪者，處三年以上十年以下有期徒刑，併科新臺幣七百萬元以下罰金。未經許可，持有、寄藏或意圖販賣而陳列子彈者，處五年以下有期徒刑，併科新臺幣三百萬元以下罰金。第一項至第三項之未遂犯罰之。",
  "characters": {
    "judges": [
      "王銘勇"
    ],
    "prosecutors": [

    ],
    "lawyers": [

    ],
    "clerks": [
      "許弘杰"
    ],
    "plaintiffs": [

    ],
    "defendants": [
      "鄭程瑋"
    ],
    "prosecutor_office": [
      "臺灣新竹地方法院檢察署檢察官"
    ],
    "creditors": [

    ],
    "debtors": [

    ],
    "judicial_associate_officer": [

    ]
  },
  "adjudged_at": "2011-09-29",
  "created_at": "2016-02-12 13:51:18",
  "updated_at": "2016-02-12 13:51:18"
}