{
  "identify": "SCD-100-司執消債更-2-20110928-2",
  "court": {
    "name": "臺灣新竹地方法院",
    "code": "SCD"
  },
  "division": {
    "name": "民事",
    "code": "V"
  },
  "year": 100,
  "word": "司執消債更",
  "number": "2",
  "jcheck": "2",
  "reason": "更生事件",
  "content": "臺灣新竹地方法院民事裁定        100年度司執消債更字第2號\n聲  請  人  林英哲\n代  理  人  余瑞華\n債  權  人  安泰商業銀行股份有限公司\n法定代理人  齊百邁\n債  權  人  台北富邦商業銀行股份有限公司\n法定代理人  韓蔚廷\n樓債  權  人  國泰世華銀行股份有限公司\n法定代理人  汪國華\n債  權  人  花旗（台灣）商業銀行股份有限公司\n法定代理人  管國霖\n債  權  人  台新國際商業銀行股份有限公司\n法定代理人  蔡榮棟\n債  權  人  台灣新光商業銀行股份有限公司\n法定代理人  李增昌\n債  權  人  聯邦商業銀行股份有限公司\n法定代理人  李憲章\n債  權  人  萬泰商業銀行股份有限公司\n法定代理人  盧正昕\n債  權  人  日盛國際商業銀行股份有限公司\n法定代理人  黃錦瑭\n代  理  人  張美芝\n債  權  人  台中商業銀行股份有限公司\n法定代理人  蘇金豐\n債  權  人  玉山商業銀行股份有限公司\n法定代理人  曾國烈\n代  理  人  洪瑞霞\n債  權  人  何月梅\n債  權  人  楊淑蘭\n債  權  人  宇炫明\n債  權  人  余瑞梅\n上列當事人聲請消費者債務清理事件，本院裁定如下：\n    主  文\n債務人所提如附件一所示之更生方案應予認可。\n債務人在未依更生條件全部履行完畢前，應受如附件二之生活限\n制。\n    理  由\n一、按「債務人有薪資、執行業務所得或其他固定收入，法院認\n    更生方案之條件公允者，得不經債權人會議可決，逕依債務\n    人之聲請或依職權以裁定認可更生方案。」且「法院為認可\n    之裁定時，因更生方案履行之必要，對於債務人在未依更生\n    條件全部履行完畢前之生活程度，得為相當之限制。」消費\n    者債務清理條例（以下簡稱本條例）第64條第1項、第62條\n    第2項定有明文。\n二、查本件債務人聲請更生，前經本院99年度消債更字第22號裁\n    定開始更生程序在案，有上開裁定一份在卷可參，而債務人\n    於100年7月5日所提之更生方案，經通知15位債權人以書面\n    對更生方案表示意見，僅債權人台新國際商業銀行股份有限\n    公司、何月梅、楊淑蘭、宇炫明、余瑞梅同意債務人所提更\n    生方案，其餘10位債權人均書面否決，其所表達之意見為：\n    債務人年僅35歲，距勞動基準法所定強制退休年齡65歲，尚\n    得工作30年，足認其具備相當之工作能力，而得以其未來之\n    勞務清償債務、債務人清償債務成數僅44.49%，清償成數過\n    低，債務人應縮減支出，提高還款金額等語。\n三、惟債務人任職於國立暨南國際大學附屬高級中學，確有薪資\n    、執行業務所得或其他固定收入等情，有債務人提出之100\n    年1月至7月薪資所得通知單在卷足憑。經查：\n（一）債務人每月薪資新台幣（下同）53,595元，扣除應繳納之\n      公保費711元、健保費2,920元、退撫金2,388元，實領\n      47,576元，另債務人為增加收入在學校兼課，因鐘點費係\n      按實際授課計費，故非固定收入，依債務人提出之100年1\n      月至5月鐘點費收入計算平均月入4,240元，二項相加，債\n      務人每月實際收入約51,816元，年終獎金為1.5個月薪水\n      ，考績獎金0.5至1個月薪水。\n（二）債務人陳報其每月支出為房租5,000元（債務人目前與配\n      偶分居中，獨自租屋居住）、伙食費4,500元、交通費\n      1,000元、水、電、瓦斯、電話費及日常用品2,060元，二\n      個小孩扶養費10,244元（女兒目前由配偶照顧，小孩扶養\n      費依行政院主計處公告之100年度臺灣省平均每人每月最\n      低生活費用10,244元計算，由債務人與配偶平均負擔），\n      所得稅17,218元，有房屋租賃契約、加油發票、幼稚園繳\n      費單、購物發票、99年綜合所得稅結算申報資料（以上均\n      影本）等附卷可稽，債務人之支出尚屬合理。\n（三）債務人有一個讀幼稚園之女兒及一個將於本年10月出生之\n      幼兒（有二位扶養義務人）須扶養，觀諸債務人所提如附\n      件一所示之更生方案，於每月所得51,816元中提出30,000\n      元清償債務，每年二月再清償80,000元，每年清償金額\n      440,000元。債務人將其每年所得扣除其支出後餘額均用\n      於清償債務，且債務人所提更生方案之清償期為8年，足\n      認其有履行更生方案之誠意。另聲請人聲請債權人為金融\n      機構部分由最大債權金融機構統一辦理更生方案之收款及\n      撥付款項之作業，併此敘明。\n四、綜上所述，債務人所提之更生方案債務人清償金額高於聲請\n    前二年間可處分所得扣除自己及依法應受其其扶養者所必要\n    生活費用之數額，本院認其更生條件核屬公允、適當、可行\n    ，且本件無同條例第63條所定不應認可之消極事由存在，故\n    不經債權人會議可決，予以認可該更生方案，另依同條例第\n    62條第2項規定，就債務人在未依更生條件全部履行完畢前\n    生活程度，裁定相當之限制，爰裁定如主文。\n五、如不服本裁定，應於裁定送達後10日內，以書狀向司法事務\n    官提出異議。\n中    華    民    國   100    年    9     月    28    日\n                          民事庭司法事務官  張倩影",
  "structure": {
    "main": "債務人所提如附件一所示之更生方案應予認可。\n債務人在未依更生條件全部履行完畢前，應受如附件二之生活限\n制。",
    "reason": "一、按「債務人有薪資、執行業務所得或其他固定收入，法院認\n    更生方案之條件公允者，得不經債權人會議可決，逕依債務\n    人之聲請或依職權以裁定認可更生方案。」且「法院為認可\n    之裁定時，因更生方案履行之必要，對於債務人在未依更生\n    條件全部履行完畢前之生活程度，得為相當之限制。」消費\n    者債務清理條例（以下簡稱本條例）第64條第1項、第62條\n    第2項定有明文。\n二、查本件債務人聲請更生，前經本院99年度消債更字第22號裁\n    定開始更生程序在案，有上開裁定一份在卷可參，而債務人\n    於100年7月5日所提之更生方案，經通知15位債權人以書面\n    對更生方案表示意見，僅債權人台新國際商業銀行股份有限\n    公司、何月梅、楊淑蘭、宇炫明、余瑞梅同意債務人所提更\n    生方案，其餘10位債權人均書面否決，其所表達之意見為：\n    債務人年僅35歲，距勞動基準法所定強制退休年齡65歲，尚\n    得工作30年，足認其具備相當之工作能力，而得以其未來之\n    勞務清償債務、債務人清償債務成數僅44.49%，清償成數過\n    低，債務人應縮減支出，提高還款金額等語。\n三、惟債務人任職於國立暨南國際大學附屬高級中學，確有薪資\n    、執行業務所得或其他固定收入等情，有債務人提出之100\n    年1月至7月薪資所得通知單在卷足憑。經查：\n（一）債務人每月薪資新台幣（下同）53,595元，扣除應繳納之\n      公保費711元、健保費2,920元、退撫金2,388元，實領\n      47,576元，另債務人為增加收入在學校兼課，因鐘點費係\n      按實際授課計費，故非固定收入，依債務人提出之100年1\n      月至5月鐘點費收入計算平均月入4,240元，二項相加，債\n      務人每月實際收入約51,816元，年終獎金為1.5個月薪水\n      ，考績獎金0.5至1個月薪水。\n（二）債務人陳報其每月支出為房租5,000元（債務人目前與配\n      偶分居中，獨自租屋居住）、伙食費4,500元、交通費\n      1,000元、水、電、瓦斯、電話費及日常用品2,060元，二\n      個小孩扶養費10,244元（女兒目前由配偶照顧，小孩扶養\n      費依行政院主計處公告之100年度臺灣省平均每人每月最\n      低生活費用10,244元計算，由債務人與配偶平均負擔），\n      所得稅17,218元，有房屋租賃契約、加油發票、幼稚園繳\n      費單、購物發票、99年綜合所得稅結算申報資料（以上均\n      影本）等附卷可稽，債務人之支出尚屬合理。\n（三）債務人有一個讀幼稚園之女兒及一個將於本年10月出生之\n      幼兒（有二位扶養義務人）須扶養，觀諸債務人所提如附\n      件一所示之更生方案，於每月所得51,816元中提出30,000\n      元清償債務，每年二月再清償80,000元，每年清償金額\n      440,000元。債務人將其每年所得扣除其支出後餘額均用\n      於清償債務，且債務人所提更生方案之清償期為8年，足\n      認其有履行更生方案之誠意。另聲請人聲請債權人為金融\n      機構部分由最大債權金融機構統一辦理更生方案之收款及\n      撥付款項之作業，併此敘明。\n四、綜上所述，債務人所提之更生方案債務人清償金額高於聲請\n    前二年間可處分所得扣除自己及依法應受其其扶養者所必要\n    生活費用之數額，本院認其更生條件核屬公允、適當、可行\n    ，且本件無同條例第63條所定不應認可之消極事由存在，故\n    不經債權人會議可決，予以認可該更生方案，另依同條例第\n    62條第2項規定，就債務人在未依更生條件全部履行完畢前\n    生活程度，裁定相當之限制，爰裁定如主文。\n五、如不服本裁定，應於裁定送達後10日內，以書狀向司法事務\n    官提出異議。"
  },
  "search": "臺灣新竹地方法院民事裁定100年度司執消債更字第2號聲請人林英哲代理人余瑞華債權人安泰商業銀行股份有限公司法定代理人齊百邁債權人台北富邦商業銀行股份有限公司法定代理人韓蔚廷樓債權人國泰世華銀行股份有限公司法定代理人汪國華債權人花旗（台灣）商業銀行股份有限公司法定代理人管國霖債權人台新國際商業銀行股份有限公司法定代理人蔡榮棟債權人台灣新光商業銀行股份有限公司法定代理人李增昌債權人聯邦商業銀行股份有限公司法定代理人李憲章債權人萬泰商業銀行股份有限公司法定代理人盧正昕債權人日盛國際商業銀行股份有限公司法定代理人黃錦瑭代理人張美芝債權人台中商業銀行股份有限公司法定代理人蘇金豐債權人玉山商業銀行股份有限公司法定代理人曾國烈代理人洪瑞霞債權人何月梅債權人楊淑蘭債權人宇炫明債權人余瑞梅上列當事人聲請消費者債務清理事件，本院裁定如下：主文債務人所提如附件一所示之更生方案應予認可。債務人在未依更生條件全部履行完畢前，應受如附件二之生活限制。理由一、按「債務人有薪資、執行業務所得或其他固定收入，法院認更生方案之條件公允者，得不經債權人會議可決，逕依債務人之聲請或依職權以裁定認可更生方案。」且「法院為認可之裁定時，因更生方案履行之必要，對於債務人在未依更生條件全部履行完畢前之生活程度，得為相當之限制。」消費者債務清理條例（以下簡稱本條例）第64條第1項、第62條第2項定有明文。二、查本件債務人聲請更生，前經本院99年度消債更字第22號裁定開始更生程序在案，有上開裁定一份在卷可參，而債務人於100年7月5日所提之更生方案，經通知15位債權人以書面對更生方案表示意見，僅債權人台新國際商業銀行股份有限公司、何月梅、楊淑蘭、宇炫明、余瑞梅同意債務人所提更生方案，其餘10位債權人均書面否決，其所表達之意見為：債務人年僅35歲，距勞動基準法所定強制退休年齡65歲，尚得工作30年，足認其具備相當之工作能力，而得以其未來之勞務清償債務、債務人清償債務成數僅44.49%，清償成數過低，債務人應縮減支出，提高還款金額等語。三、惟債務人任職於國立暨南國際大學附屬高級中學，確有薪資、執行業務所得或其他固定收入等情，有債務人提出之100年1月至7月薪資所得通知單在卷足憑。經查：（一）債務人每月薪資新台幣（下同）53,595元，扣除應繳納之公保費711元、健保費2,920元、退撫金2,388元，實領47,576元，另債務人為增加收入在學校兼課，因鐘點費係按實際授課計費，故非固定收入，依債務人提出之100年1月至5月鐘點費收入計算平均月入4,240元，二項相加，債務人每月實際收入約51,816元，年終獎金為1.5個月薪水，考績獎金0.5至1個月薪水。（二）債務人陳報其每月支出為房租5,000元（債務人目前與配偶分居中，獨自租屋居住）、伙食費4,500元、交通費1,000元、水、電、瓦斯、電話費及日常用品2,060元，二個小孩扶養費10,244元（女兒目前由配偶照顧，小孩扶養費依行政院主計處公告之100年度臺灣省平均每人每月最低生活費用10,244元計算，由債務人與配偶平均負擔），所得稅17,218元，有房屋租賃契約、加油發票、幼稚園繳費單、購物發票、99年綜合所得稅結算申報資料（以上均影本）等附卷可稽，債務人之支出尚屬合理。（三）債務人有一個讀幼稚園之女兒及一個將於本年10月出生之幼兒（有二位扶養義務人）須扶養，觀諸債務人所提如附件一所示之更生方案，於每月所得51,816元中提出30,000元清償債務，每年二月再清償80,000元，每年清償金額440,000元。債務人將其每年所得扣除其支出後餘額均用於清償債務，且債務人所提更生方案之清償期為8年，足認其有履行更生方案之誠意。另聲請人聲請債權人為金融機構部分由最大債權金融機構統一辦理更生方案之收款及撥付款項之作業，併此敘明。四、綜上所述，債務人所提之更生方案債務人清償金額高於聲請前二年間可處分所得扣除自己及依法應受其其扶養者所必要生活費用之數額，本院認其更生條件核屬公允、適當、可行，且本件無同條例第63條所定不應認可之消極事由存在，故不經債權人會議可決，予以認可該更生方案，另依同條例第62條第2項規定，就債務人在未依更生條件全部履行完畢前生活程度，裁定相當之限制，爰裁定如主文。五、如不服本裁定，應於裁定送達後10日內，以書狀向司法事務官提出異議。中華民國100年9月28日民事庭司法事務官張倩影",
  "characters": {
    "judges": [

    ],
    "prosecutors": [

    ],
    "lawyers": [

    ],
    "clerks": [

    ],
    "plaintiffs": [

    ],
    "defendants": [

    ],
    "prosecutor_office": [
      "林英哲"
    ],
    "creditors": [
      "安泰商業銀行股份有限公司",
      "台北富邦商業銀行股份有限公司",
      "花旗",
      "台新國際商業銀行股份有限公司",
      "台灣新光商業銀行股份有限公司",
      "聯邦商業銀行股份有限公司",
      "萬泰商業銀行股份有限公司",
      "日盛國際商業銀行股份有限公司",
      "台中商業銀行股份有限公司",
      "玉山商業銀行股份有限公司",
      "何月梅",
      "楊淑蘭",
      "宇炫明",
      "余瑞梅"
    ],
    "debtors": [

    ],
    "judicial_associate_officer": [
      "張倩影"
    ]
  },
  "adjudged_at": "2011-09-28",
  "created_at": "2016-02-12 13:39:36",
  "updated_at": "2016-02-12 13:39:36"
}