{
  "identify": "SLD-100-自-17-20110929-1",
  "court": {
    "name": "臺灣士林地方法院",
    "code": "SLD"
  },
  "division": {
    "name": "刑事",
    "code": "M"
  },
  "year": 100,
  "word": "自",
  "number": "17",
  "jcheck": "1",
  "reason": "詐欺",
  "content": "臺灣士林地方法院刑事裁定               100年度自字第17號\n自  訴  人  卓玉麗\n自訴代理人  林鳳秋律師\n被      告  林軼鵲\n選任辯護人  魏君婷律師\n上列被告因詐欺案件，對於證據能力之有無，本院裁定如下：\n    主  文\n本案各項證據之證據能力之認定，詳如附表之「本院認定有無證\n據能力」欄所載。\n    理  由\n一、各項證據之證據能力認定之理由，詳如附表之「本院認定之\n    理由」欄所載。\n二、依刑事訴訟法第220條，裁定如主文。\n中    華    民    國   100    年    9     月    29    日\n                刑事第八庭      審判長法  官  楊秀枝\n                                      法  官  黃怡瑜\n                                      法  官  黃翰義\n以上正本證明與原本無異。\n不得上訴。\n                                      書記官  謝文傑\n中    華    民    國   100    年    9     月    30    日\n附表\n註：卷宗代號一覽表\n臺灣士林地方法院100年度審自字第26號卷宗以「審查庭卷」\n  表示\n臺灣士林地方法院100年度自字第17號偵查卷宗以「本院卷」\n  表示\n┌──┬───────┬─────┬─────────┬───┬───┬───────┐\n│編號│證據資料      │頁次      │   待 證 事 項    │被告之│本院認│本院認定之理由│\n│    │              │          │                  │主張  │定有無│【刑事訴訟法（│\n│    │              │          │                  │      │證據能│下稱刑訴法）】│\n│    │              │          │                  │      │力    │              │\n├──┼───────┼─────┼─────────┼───┼───┼───────┤\n│一  │卓玉麗皮膚專科│審查庭卷  │自訴人與98年5月5日│無意見│有    │依刑訴法第159 │\n│    │診所98年5月5日│p6-8      │與被告簽訂合約，聘│      │      │條之4第3款，其│\n│    │與被告簽訂之聘│          │僱日期自98年6月1日│      │      │他於可信之特別│\n│    │書            │          │至100年5月31日，其│      │      │情形下所製作之│\n│    │              │          │中約定服務未滿二年│      │      │文書，有證據能│\n│    │              │          │離職，須賠償自訴人│      │      │力。          │\n│    │              │          │新臺幣96萬元之違約│      │      │              │\n│    │              │          │金。              │      │      │              │\n├──┼───────┼─────┼─────────┼───┼───┼───────┤\n│二  │當事人間98年7 │審查庭卷  │被告因故無法於自訴│無意見│有    │依刑訴法第159 │\n│    │月20日協議書  │p9        │人約聘間履行合約，│      │      │條之4第3款，其│\n│    │              │          │當事人協議調低違約│      │      │他於可信之特別│\n│    │              │          │金，以被告98年7月 │      │      │情形下所製作之│\n│    │              │          │於自訴人處之薪資作│      │      │文書，有證據能│\n│    │              │          │為違約金賠償。    │      │      │力。          │\n├──┼───────┼─────┼─────────┼───┼───┼───────┤\n│三  │被告於國家網路│審查庭卷  │被告自告訴人處離職│無意見│有    │依刑訴法第159 │\n│    │醫院之網頁資料│p10       │後，馬上到和安皮膚│      │      │條之4第3款，其│\n│    │              │          │科任職。          │      │      │他於可信之特別│\n│    │              │          │                  │      │      │情形下所製作之│\n│    │              │          │                  │      │      │文書，有證據能│\n│    │              │          │                  │      │      │力。          │\n├──┼───────┼─────┼─────────┼───┼───┼───────┤\n│四  │淨美皮膚科診所│審查庭卷  │淨美皮膚科診所為被│未表示│有    │依刑訴法第159 │\n│    │網頁          │p49-50    │告所自行經營。    │意見  │      │條之4第3款，其│\n│    │              │          │                  │      │      │他於可信之特別│\n│    │              │          │                  │      │      │情形下所製作之│\n│    │              │          │                  │      │      │文書，有證據能│\n│    │              │          │                  │      │      │力。          │\n├──┼───────┼─────┼─────────┼───┼───┼───────┤\n│五  │新北市政府衛生│審查庭卷  │被告自98年7月31日 │未表示│有    │依刑訴法第159 │\n│    │局100年8月1日 │p52       │至98年12月23日執業│意見  │      │條之4第1款規定│\n│    │北衛醫字第    │          │登記於和安耳鼻喉科│      │      │，為公務員職務│\n│    │1000101961號函│          │診所。            │      │      │上所製作證明文│\n│    │              │          │                  │      │      │書，得為證據。│\n├──┼───────┼─────┼─────────┼───┼───┼───────┤\n│六  │行政院衛生署中│本院卷    │檢送98年間自訴人、│未表示│有    │依刑訴法第159 │\n│    │央健康保險局  │p16-19    │被告於自訴人處及和│意見  │      │條之4第1款規定│\n│    │100年9月19日健│          │安診所健保申報資料│      │      │，為公務員職務│\n│    │保北字第      │          │。被告係身體不堪自│      │      │上所製作證明文│\n│    │1001621557號函│          │訴人診所之門診量而│      │      │書，得為證據。│\n│    │及附件        │          │離職。            │      │      │              │\n└──┴───────┴─────┴─────────┴───┴───┴───────┘",
  "structure": {
    "main": "本案各項證據之證據能力之認定，詳如附表之「本院認定有無證\n據能力」欄所載。",
    "reason": "一、各項證據之證據能力認定之理由，詳如附表之「本院認定之\n    理由」欄所載。\n二、依刑事訴訟法第220條，裁定如主文。"
  },
  "search": "臺灣士林地方法院刑事裁定100年度自字第17號自訴人卓玉麗自訴代理人林鳳秋律師被告林軼鵲選任辯護人魏君婷律師上列被告因詐欺案件，對於證據能力之有無，本院裁定如下：主文本案各項證據之證據能力之認定，詳如附表之「本院認定有無證據能力」欄所載。理由一、各項證據之證據能力認定之理由，詳如附表之「本院認定之理由」欄所載。二、依刑事訴訟法第220條，裁定如主文。中華民國100年9月29日刑事第八庭審判長法官楊秀枝法官黃怡瑜法官黃翰義以上正本證明與原本無異。不得上訴。書記官謝文傑中華民國100年9月30日附表註：卷宗代號一覽表臺灣士林地方法院100年度審自字第26號卷宗以「審查庭卷」表示臺灣士林地方法院100年度自字第17號偵查卷宗以「本院卷」表示┌──┬───────┬─────┬─────────┬───┬───┬───────┐│編號│證據資料│頁次│待證事項│被告之│本院認│本院認定之理由││││││主張│定有無│【刑事訴訟法（│││││││證據能│下稱刑訴法）】│││││││力││├──┼───────┼─────┼─────────┼───┼───┼───────┤│一│卓玉麗皮膚專科│審查庭卷│自訴人與98年5月5日│無意見│有│依刑訴法第159│││診所98年5月5日│p6-8│與被告簽訂合約，聘│││條之4第3款，其│││與被告簽訂之聘││僱日期自98年6月1日│││他於可信之特別│││書││至100年5月31日，其│││情形下所製作之│││││中約定服務未滿二年│││文書，有證據能│││││離職，須賠償自訴人│││力。│││││新臺幣96萬元之違約││││││││金。││││├──┼───────┼─────┼─────────┼───┼───┼───────┤│二│當事人間98年7│審查庭卷│被告因故無法於自訴│無意見│有│依刑訴法第159│││月20日協議書│p9│人約聘間履行合約，│││條之4第3款，其│││││當事人協議調低違約│││他於可信之特別│││││金，以被告98年7月│││情形下所製作之│││││於自訴人處之薪資作│││文書，有證據能│││││為違約金賠償。│││力。│├──┼───────┼─────┼─────────┼───┼───┼───────┤│三│被告於國家網路│審查庭卷│被告自告訴人處離職│無意見│有│依刑訴法第159│││醫院之網頁資料│p10│後，馬上到和安皮膚│││條之4第3款，其│││││科任職。│││他於可信之特別││││││││情形下所製作之││││││││文書，有證據能││││││││力。│├──┼───────┼─────┼─────────┼───┼───┼───────┤│四│淨美皮膚科診所│審查庭卷│淨美皮膚科診所為被│未表示│有│依刑訴法第159│││網頁│p49-50│告所自行經營。│意見││條之4第3款，其││││││││他於可信之特別││││││││情形下所製作之││││││││文書，有證據能││││││││力。│├──┼───────┼─────┼─────────┼───┼───┼───────┤│五│新北市政府衛生│審查庭卷│被告自98年7月31日│未表示│有│依刑訴法第159│││局100年8月1日│p52│至98年12月23日執業│意見││條之4第1款規定│││北衛醫字第││登記於和安耳鼻喉科│││，為公務員職務│││1000101961號函││診所。│││上所製作證明文││││││││書，得為證據。│├──┼───────┼─────┼─────────┼───┼───┼───────┤│六│行政院衛生署中│本院卷│檢送98年間自訴人、│未表示│有│依刑訴法第159│││央健康保險局│p16-19│被告於自訴人處及和│意見││條之4第1款規定│││100年9月19日健││安診所健保申報資料│││，為公務員職務│││保北字第││。被告係身體不堪自│││上所製作證明文│││1001621557號函││訴人診所之門診量而│││書，得為證據。│││及附件││離職。││││└──┴───────┴─────┴─────────┴───┴───┴───────┘",
  "characters": {
    "judges": [
      "楊秀枝",
      "黃怡瑜",
      "黃翰義"
    ],
    "prosecutors": [

    ],
    "lawyers": [
      "林鳳秋",
      "魏君婷"
    ],
    "clerks": [
      "謝文傑"
    ],
    "plaintiffs": [

    ],
    "defendants": [
      "林軼鵲"
    ],
    "prosecutor_office": [

    ],
    "creditors": [

    ],
    "debtors": [

    ],
    "judicial_associate_officer": [

    ]
  },
  "adjudged_at": "2011-09-29",
  "created_at": "2016-02-12 13:33:11",
  "updated_at": "2016-02-12 13:33:11"
}