{
  "identify": "TPD-100-審自-2-20110929-2",
  "court": {
    "name": "臺灣臺北地方法院",
    "code": "TPD"
  },
  "division": {
    "name": "刑事",
    "code": "M"
  },
  "year": 100,
  "word": "審自",
  "number": "2",
  "jcheck": "2",
  "reason": "詐欺",
  "content": "臺灣臺北地方法院刑事判決              100年度審自字第2號\n自  訴  人  方慧淑\n被      告  黃位賢\n上列自訴人自訴被告詐欺案件，本院判決如下：\n    主  文\n本件自訴不受理。\n    理  由\n一、自訴意旨如附件刑事自訴狀所示。\n二、按自訴之提起，應委任律師行之；自訴人未委任代理人者，\n    法院應定期間以裁定命其委任代理人，逾期仍不委任者，應\n    諭知不受理之判決；不受理之判決，得不經言詞辯論為之，\n    此亦為自訴程序所準用，刑事訴訟法第319條第2項、第329\n    條第2項、第343條及第307條分別定有明文。經查：自訴人\n    於民國100年9月14日向本院提出本件自訴，並未委任律師為\n    其代理人，經本院以裁定命自訴人於裁定送達後5日內補正\n    委任律師為自訴代理人，而將補正裁定於100年9月22日送達\n    於自訴人自訴狀上所記載之郵政信箱，自訴人並親自收受上\n    開裁定，此有送達證書1紙在卷可證。惟自訴人逾期未為補\n    正，從而本件自訴之起訴程式即有未備，爰不經言詞辯論，\n    逕為不受理判決之諭知。\n據上論結，應依刑事訴訟法第329條第2項、第343條、第307條，\n判決如主文。\n中    華    民    國   100    年    9     月    29    日\n               刑事第二十一庭 審判長法  官  劉素如\n                                    法  官  林勇如\n                                    法  官  徐淑芬\n上正本證明與原本無異。\n如不服本判決，應於判決送達後10日內向本院提出上訴狀（應抄\n附繕本）。\n                                    書記官  陳育君\n中    華    民    國   100    年    9     月    29    日",
  "structure": {
    "main": "本件自訴不受理。",
    "reason": "一、自訴意旨如附件刑事自訴狀所示。\n二、按自訴之提起，應委任律師行之；自訴人未委任代理人者，\n    法院應定期間以裁定命其委任代理人，逾期仍不委任者，應\n    諭知不受理之判決；不受理之判決，得不經言詞辯論為之，\n    此亦為自訴程序所準用，刑事訴訟法第319條第2項、第329\n    條第2項、第343條及第307條分別定有明文。經查：自訴人\n    於民國100年9月14日向本院提出本件自訴，並未委任律師為\n    其代理人，經本院以裁定命自訴人於裁定送達後5日內補正\n    委任律師為自訴代理人，而將補正裁定於100年9月22日送達\n    於自訴人自訴狀上所記載之郵政信箱，自訴人並親自收受上\n    開裁定，此有送達證書1紙在卷可證。惟自訴人逾期未為補\n    正，從而本件自訴之起訴程式即有未備，爰不經言詞辯論，\n    逕為不受理判決之諭知。\n據上論結，應依刑事訴訟法第329條第2項、第343條、第307條，\n判決如主文。"
  },
  "search": "臺灣臺北地方法院刑事判決100年度審自字第2號自訴人方慧淑被告黃位賢上列自訴人自訴被告詐欺案件，本院判決如下：主文本件自訴不受理。理由一、自訴意旨如附件刑事自訴狀所示。二、按自訴之提起，應委任律師行之；自訴人未委任代理人者，法院應定期間以裁定命其委任代理人，逾期仍不委任者，應諭知不受理之判決；不受理之判決，得不經言詞辯論為之，此亦為自訴程序所準用，刑事訴訟法第319條第2項、第329條第2項、第343條及第307條分別定有明文。經查：自訴人於民國100年9月14日向本院提出本件自訴，並未委任律師為其代理人，經本院以裁定命自訴人於裁定送達後5日內補正委任律師為自訴代理人，而將補正裁定於100年9月22日送達於自訴人自訴狀上所記載之郵政信箱，自訴人並親自收受上開裁定，此有送達證書1紙在卷可證。惟自訴人逾期未為補正，從而本件自訴之起訴程式即有未備，爰不經言詞辯論，逕為不受理判決之諭知。據上論結，應依刑事訴訟法第329條第2項、第343條、第307條，判決如主文。中華民國100年9月29日刑事第二十一庭審判長法官劉素如法官林勇如法官徐淑芬上正本證明與原本無異。如不服本判決，應於判決送達後10日內向本院提出上訴狀（應抄附繕本）。書記官陳育君中華民國100年9月29日",
  "characters": {
    "judges": [
      "劉素如",
      "林勇如",
      "徐淑芬"
    ],
    "prosecutors": [

    ],
    "lawyers": [
      "委任"
    ],
    "clerks": [
      "陳育君"
    ],
    "plaintiffs": [

    ],
    "defendants": [
      "黃位賢"
    ],
    "prosecutor_office": [

    ],
    "creditors": [

    ],
    "debtors": [

    ],
    "judicial_associate_officer": [

    ]
  },
  "adjudged_at": "2011-09-29",
  "created_at": "2016-02-12 13:32:28",
  "updated_at": "2016-02-12 13:32:28"
}