{
  "identify": "TCD-94-簡-130-20051216-1",
  "court": {
    "name": "臺灣臺中地方法院",
    "code": "TCD"
  },
  "division": {
    "name": "刑事",
    "code": "M"
  },
  "year": 94,
  "word": "簡",
  "number": "130",
  "jcheck": "1",
  "reason": "傷害等",
  "content": "臺灣臺中地方法院刑事簡易判決  94年度簡字第130號\n公  訴  人  臺灣臺中地方法院檢察署檢察官\n被      告  乙○○\n上列被告因傷害等案件，經檢察官提起公訴（九十四年度偵字第\n四一一一號），被告於本院訊問時自白犯罪，本院合議庭裁定由\n受命法官獨任以簡易判決處刑，判決如下：\n    主    文\n乙○○傷害人之身體，處有期徒刑月，如易科罰金，以佰元\n折算壹日。\n    事實及理由\n一、本件犯罪事實及證據均引用檢察官起訴書之記載（如附件）\n    。\n二、告訴人甲○○雖陳稱：被告以數拳打在伊之太陽穴上，造成\n    嚴重腦震盪，導致伊之左眼於九十四年九月十九日發生嚴重\n    後遺症，跡近失明，請求改依重傷害罪判決云云。惟查告訴\n    人甲○○於九十二年四月二十四日自臺灣宜蘭監獄移入臺灣\n    臺中監獄時，即已患有視網膜剝離，曾分別於九十二年五月\n    八日、五月十九日、六月十一日、六月十七日、八月七日、\n    八月十二日致函予案外人林瑞福、陳得福、親民黨主席宋楚\n    瑜、陳田錨、慈濟醫學院、陸延奇牧師等人請求為其出資治\n    療眼疾，有臺灣臺中監獄主任管理員九十三年七月六日報告\n    書附於九十三年度他字第一六六五號卷第三○頁可稽。而被\n    告毆打告訴人之日期係九十三年四月六日，告訴人左眼之後\n    遺症既於九十四年九月十九日始發生，距離遭被告毆打已有\n    一年又五個月餘之久，難以認定為遭被告毆打所導致，故本\n    件並無變更起訴法條之必要，併此敘明。\n三、依刑事訴訟法第四百四十九條第二項、第四百五十四條第二\n    項，刑法第二百七十七條第一項、第三百五十四條、第五十\n    五條、第四十一條第一項前段，罰金罰鍰提高標準條例第一\n    條前段、第二條，逕以簡易判決處如主文所示之刑。\n四、檢察官及被告如不服本案判決，得自收受送達之日起十日內\n    向本院提出上訴狀；告訴人如不服本案判決，須具狀書明理\n    由，向檢察官請求上訴（均須附繕本）。\n中    華    民    國    94    年    12    月    16    日\n                  刑事第六庭    法  官  林念祖\n以上正本證明與原本無異。\n                                書記官  謝明倫\n中    華    民    國    94    年    12    月    16    日\n附錄本案論罪科刑法條全文\n中華民國刑法第二百七十七條第一項\n傷害人之身體或健康者，處三年以下有期徒刑、拘役或一千元以\n下罰金。\n中華民國刑法第三百五十四條\n 毀棄、損壞前二條以外之他人之物或致令不堪用，足以生損害於\n公眾或他人者，處二年以下有期徒刑、拘役或五百元以下罰金。\n",
  "structure": {
    "main": "乙○○傷害人之身體，處有期徒刑月，如易科罰金，以佰元\n折算壹日。",
    "fact": "一、本件犯罪事實及證據均引用檢察官起訴書之記載（如附件）\n    。\n二、告訴人甲○○雖陳稱：被告以數拳打在伊之太陽穴上，造成\n    嚴重腦震盪，導致伊之左眼於九十四年九月十九日發生嚴重\n    後遺症，跡近失明，請求改依重傷害罪判決云云。惟查告訴\n    人甲○○於九十二年四月二十四日自臺灣宜蘭監獄移入臺灣\n    臺中監獄時，即已患有視網膜剝離，曾分別於九十二年五月\n    八日、五月十九日、六月十一日、六月十七日、八月七日、\n    八月十二日致函予案外人林瑞福、陳得福、親民黨主席宋楚\n    瑜、陳田錨、慈濟醫學院、陸延奇牧師等人請求為其出資治\n    療眼疾，有臺灣臺中監獄主任管理員九十三年七月六日報告\n    書附於九十三年度他字第一六六五號卷第三○頁可稽。而被\n    告毆打告訴人之日期係九十三年四月六日，告訴人左眼之後\n    遺症既於九十四年九月十九日始發生，距離遭被告毆打已有\n    一年又五個月餘之久，難以認定為遭被告毆打所導致，故本\n    件並無變更起訴法條之必要，併此敘明。\n三、依刑事訴訟法第四百四十九條第二項、第四百五十四條第二\n    項，刑法第二百七十七條第一項、第三百五十四條、第五十\n    五條、第四十一條第一項前段，罰金罰鍰提高標準條例第一\n    條前段、第二條，逕以簡易判決處如主文所示之刑。\n四、檢察官及被告如不服本案判決，得自收受送達之日起十日內\n    向本院提出上訴狀；告訴人如不服本案判決，須具狀書明理\n    由，向檢察官請求上訴（均須附繕本）。",
    "reason": "一、本件犯罪事實及證據均引用檢察官起訴書之記載（如附件）\n    。\n二、告訴人甲○○雖陳稱：被告以數拳打在伊之太陽穴上，造成\n    嚴重腦震盪，導致伊之左眼於九十四年九月十九日發生嚴重\n    後遺症，跡近失明，請求改依重傷害罪判決云云。惟查告訴\n    人甲○○於九十二年四月二十四日自臺灣宜蘭監獄移入臺灣\n    臺中監獄時，即已患有視網膜剝離，曾分別於九十二年五月\n    八日、五月十九日、六月十一日、六月十七日、八月七日、\n    八月十二日致函予案外人林瑞福、陳得福、親民黨主席宋楚\n    瑜、陳田錨、慈濟醫學院、陸延奇牧師等人請求為其出資治\n    療眼疾，有臺灣臺中監獄主任管理員九十三年七月六日報告\n    書附於九十三年度他字第一六六五號卷第三○頁可稽。而被\n    告毆打告訴人之日期係九十三年四月六日，告訴人左眼之後\n    遺症既於九十四年九月十九日始發生，距離遭被告毆打已有\n    一年又五個月餘之久，難以認定為遭被告毆打所導致，故本\n    件並無變更起訴法條之必要，併此敘明。\n三、依刑事訴訟法第四百四十九條第二項、第四百五十四條第二\n    項，刑法第二百七十七條第一項、第三百五十四條、第五十\n    五條、第四十一條第一項前段，罰金罰鍰提高標準條例第一\n    條前段、第二條，逕以簡易判決處如主文所示之刑。\n四、檢察官及被告如不服本案判決，得自收受送達之日起十日內\n    向本院提出上訴狀；告訴人如不服本案判決，須具狀書明理\n    由，向檢察官請求上訴（均須附繕本）。"
  },
  "search": "臺灣臺中地方法院刑事簡易判決94年度簡字第130號公訴人臺灣臺中地方法院檢察署檢察官被告乙○○上列被告因傷害等案件，經檢察官提起公訴（九十四年度偵字第四一一一號），被告於本院訊問時自白犯罪，本院合議庭裁定由受命法官獨任以簡易判決處刑，判決如下：主文乙○○傷害人之身體，處有期徒刑月，如易科罰金，以佰元折算壹日。事實及理由一、本件犯罪事實及證據均引用檢察官起訴書之記載（如附件）。二、告訴人甲○○雖陳稱：被告以數拳打在伊之太陽穴上，造成嚴重腦震盪，導致伊之左眼於九十四年九月十九日發生嚴重後遺症，跡近失明，請求改依重傷害罪判決云云。惟查告訴人甲○○於九十二年四月二十四日自臺灣宜蘭監獄移入臺灣臺中監獄時，即已患有視網膜剝離，曾分別於九十二年五月八日、五月十九日、六月十一日、六月十七日、八月七日、八月十二日致函予案外人林瑞福、陳得福、親民黨主席宋楚瑜、陳田錨、慈濟醫學院、陸延奇牧師等人請求為其出資治療眼疾，有臺灣臺中監獄主任管理員九十三年七月六日報告書附於九十三年度他字第一六六五號卷第三○頁可稽。而被告毆打告訴人之日期係九十三年四月六日，告訴人左眼之後遺症既於九十四年九月十九日始發生，距離遭被告毆打已有一年又五個月餘之久，難以認定為遭被告毆打所導致，故本件並無變更起訴法條之必要，併此敘明。三、依刑事訴訟法第四百四十九條第二項、第四百五十四條第二項，刑法第二百七十七條第一項、第三百五十四條、第五十五條、第四十一條第一項前段，罰金罰鍰提高標準條例第一條前段、第二條，逕以簡易判決處如主文所示之刑。四、檢察官及被告如不服本案判決，得自收受送達之日起十日內向本院提出上訴狀；告訴人如不服本案判決，須具狀書明理由，向檢察官請求上訴（均須附繕本）。中華民國94年12月16日刑事第六庭法官林念祖以上正本證明與原本無異。書記官謝明倫中華民國94年12月16日附錄本案論罪科刑法條全文中華民國刑法第二百七十七條第一項傷害人之身體或健康者，處三年以下有期徒刑、拘役或一千元以下罰金。中華民國刑法第三百五十四條毀棄、損壞前二條以外之他人之物或致令不堪用，足以生損害於公眾或他人者，處二年以下有期徒刑、拘役或五百元以下罰金。",
  "characters": {
    "judges": [
      "林念祖"
    ],
    "prosecutors": [

    ],
    "lawyers": [

    ],
    "clerks": [
      "謝明倫"
    ],
    "plaintiffs": [

    ],
    "defendants": [
      "乙○○"
    ],
    "prosecutor_office": [
      "臺灣臺中地方法院檢察署檢察官"
    ],
    "creditors": [

    ],
    "debtors": [

    ],
    "judicial_associate_officer": [

    ]
  },
  "adjudged_at": "2005-12-16",
  "created_at": "2016-02-07 02:56:20",
  "updated_at": "2016-02-07 02:56:20"
}