{
  "identify": "TPB-94-訴-785-20051215-1",
  "court": {
    "name": "臺北高等行政法院",
    "code": "TPB"
  },
  "division": {
    "name": "行政",
    "code": "A"
  },
  "year": 94,
  "word": "訴",
  "number": "785",
  "jcheck": "1",
  "reason": "勞保",
  "content": "臺北高等行政法院裁定\n                                     94年度訴字第00785號\n                              .\n原      告  甲○○\n被      告  勞工保險局\n代  表  人  乙○（總經理）\n訴訟代理人  丙○○\n            丁○○\n            戊○○\n上列當事人間因勞保事件，原告不服行政院勞工委員會中華民國\n94年2月1日勞訴字第0930054698號訴願決定，提起行政訴訟。就\n原告訴請：(1)撤銷訴願決定、審議審定及原處分關於被告91年10\n月1日「勞工保險給付申請書（兼給付收據）、核定通知書」部\n分；(2)判命被告作成核付原告自91年7月3日起至92年3月19日止\n職業傷害傷病給付之處分部分；(3)判命被告作成核付原告勞工保\n險殘廢給付標準表第133障害項目第3等級殘廢給付之處分部分，\n本院裁定如下：\n    主  文\n原告之訴駁回。\n訴訟費用由原告負擔。\n    理  由\n一、有關原告訴請：(1)撤銷訴願決定、審議審定及原處分關於被\n    告91年10月1日「勞工保險給付申請書（兼給付收據）、核\n    定通知書」部分；(2)判命被告作成核付原告勞工保險殘廢給\n    付標準表第133障害項目第3等級殘廢給付之處分部分：\n１、按「勞工保險爭議事項審議辦法，由中央主管機關擬訂，報\n    請行政院核定之。」、「本辦法依勞工保險條例第5條第3項\n    規定訂定之。」、「投保單位、被保險人、受益人或全民健\n    康保險醫事服務機構（以下均稱申請人）對勞工保險局（以\n    下簡稱勞保局）下列事項之核定發生爭議時，得依本辦法規\n    定申請審議：一、有關被保險人、受益人資格及投保事項。\n    二、有關被保險人投保薪資或年資事項。三、有關保險費或\n    滯納金事項。四、有關保險給付事項。五、有關職業傷病事\n    項。六、有關殘廢等級事項。七、有關職業災害診療費用事\n    項。八、其他有關保險權益事項。」、「申請人依前條規定\n    申請審議時，應於接到勞保局核定通知文件之翌日起60日內\n    ，填具勞工保險爭議事項審議申請書（以下簡稱審議申請書\n    ），並檢附有關證件經由勞保局向勞工保險監理委員會（以\n    下簡稱監理會）申請審議。其因不可歸責於己之事由致遲誤\n    期間者，申請人應自其事由消滅之翌日起30日內，以書面敘\n    明遲誤原因申請審議。」、「審議之申請，以收受審議申請\n    書之日期為準，以郵遞方式申請者，以原寄郵局之郵戳為憑\n    。」勞工保險條例第5條第3項、勞工保險爭議事項審議辦法\n    第1條、第2條、第3條第1項及第2項分別定有明文。又按「\n    原告之訴，有左列各款情形之一者，行政法院應以裁定駁回\n    之。但其情形可以補正者，審判長應定期間先命補正：．．\n    十、起訴不合程式或不備其他要件者。」行政訴訟法第107\n    條第1項第10款亦有明文。\n２、查勞工保險條例第5條第3項已明定：「勞工保險爭議事項審\n    議辦法，由中央主管機關擬訂，報請行政院核定之。」，而\n    勞工保險爭議事項審議辦法第1條亦表明：「本辦法依勞工\n    保險條例第5條第3項規定訂定之。」，參照司法院釋字第53\n    8號解釋及釋字第394號解釋意旨，此項授權條款雖未就授權\n    之內容與範圍為規定，惟依勞工保險條例之法律整體解釋，\n    應可推知立法者有意授權主管機關，就有關勞工保險給付爭\n    議事項之審查程序、申請審議所需備置之文書表件、審查機\n    構之組織等事項，依其行政專業之考量，訂定法規命令，以\n    資規範，就授權明確性而言尚無違背，是以，勞工保險爭議\n    事項審議辦法第3條第1項有關60天申請審議期間之規定，仍\n    屬於前述勞工保險給付爭議審查之程序事項，並未逾越勞工\n    保險條例之授權範圍，自得作為本件審理之依據（最高行政\n    法院92年度裁字第1554號裁定意旨參照）。\n３、本件原告係由鏵塑股份有限公司申報參加勞工保險之被保險\n    人，以於民國（下同）91年2月8日在工廠搬運貨物時遭壓傷\n    致殘，於91年7月15日（被告收文日期）向被告申請職業傷\n    害殘廢給付，經被告於91年10月1日以「勞工保險給付申請\n    書（兼給付收據）、核定通知書」核定依勞工保險殘廢給付\n    標準表第8項第7等級，發給普通傷病殘廢給付440日，計新\n    台幣281,600元。經查，本件業據原告自承其係於91年10月\n    中旬左右收到被告91年10月1日上開「勞工保險給付申請書\n    （兼給付收據）、核定通知書」，經記明於本院94年11月23\n    日準備程序筆錄在卷可按，並有被告94年12月8日庭呈勞保\n    殘廢給付詳細資料查詢表（殘廢給付核付日期：91年10月1\n    日）為憑，則原告遲至93年7月15日始申請審議（被告收文\n    日期：93年7月5日，有勞工保險爭議事項審議申請書附於爭\n    議審議案卷可稽），顯已逾越首揭規定之申請審議60日期間\n    。審議審定及訴願決定未從程序上不受理原告之審議申請及\n    訴願，而誤從實體駁回，固屬未洽，惟駁回結果並無二致，\n    仍應予維持。原告復對之提起行政訴訟，而其情形又不可以\n    補正，其訴顯非合法，應予駁回。\n４、次按，提起撤銷訴訟及課予義務訴訟，須以經過合法之訴願\n    前置程序及訴願程序，為其前提要件，其未經合法之訴願前\n    置程序及訴願程序，遽行提起撤銷訴訟及課予義務訴訟，自\n    非法之所許，此就行政訴訟法第4條第1項及第5條第2項規定\n    觀之甚明。本件原告就被告所為殘廢給付之核定【即被告91\n    年10月1日「勞工保險給付申請書（兼給付收據）、核定通\n    知書」】不服，惟其申請審議，已逾越法定60日期間，業如\n    前述，則原告訴請：「(1)撤銷訴願決定、審議審定及原處分\n    關於被告91年10月1日「勞工保險給付申請書（兼給付收據\n    ）、核定通知書」；(2)判命被告作成核付原告勞工保險殘廢\n    給付標準表第133障害項目第3等級殘廢給付之處分」部分，\n    自亦難認為合法，應予駁回。\n二、有關原告訴請判命被告作成核付原告自91年7月3日起至92年\n    3月19日止職業傷害傷病給付之處分部分：\n１、按「人民因中央或地方機關對其依法申請之案件，於法令所\n    定期間內應作為而不作為，認為其權利或法律上利益受損害\n    者，經依訴願程序後，得向高等行政法院提起請求該機關應\n    為行政處分或應為特定內容之行政處分之訴訟。」「人民因\n    中央或地方機關對其依法申請之案件，予以駁回，認為其權\n    利或法律上利益受違法損害者，經依訴願程序後，得向高等\n    行政法院提起請求該機關應為行政處分或應為特定內容之行\n    政處分之訴訟。」行政訴訟法第5條第1項及第2項定有明文\n    。因此人民提起行政訴訟法第5條第1項或第2項之課予義務\n    訴訟，須存在有人民依法申請之案件為其起訴要件，否則，\n    依行政訴訟法第107條第1項第10款：「原告之訴，有左列各\n    款情形之一者，行政法院應以裁定駁回之。但其情形可以補\n    正者，審判長應定期間先命補正：．．十、起訴不合程式或\n    不備其他要件者。」之規定，行政法院亦應以裁定駁回之。\n２、經查，本件原告係分別於91年4月23日、91年6月4日、91年\n    7月5日（被告收文日期），向被告申請91年3月19日至同年4\n    月12日期間職業傷害傷病給付、91年2月25日至同年5月31日\n    期間職業傷害傷病給付、91年2月9日至同年7月2日期間職業\n    傷害傷病給付，此有原處分卷所附3份勞工保險給付申請書\n    （兼給付收據）、核定通知書影本可稽，且為兩造所不爭執\n    ，經記明於94年11月23日準備程序筆錄及94年12月8日言詞\n    辯論筆錄在卷可按。則本件原告訴請判命被告作成核付原告\n    自91年7月3日起至92年3月19日止職業傷害傷病給付之處分\n    部分，並未據原告向被告提出申請，亦未經原告申請審議及\n    提起訴願，揆諸前揭規定及說明，原告逕向本院起訴請求，\n    自非法之所許，應予駁回。\n三、本件原告訴請：「(1)撤銷訴願決定、審議審定及原處分關於\n    被告91年10月1日『勞工保險給付申請書（兼給付收據）、\n    核定通知書』；(2)判命被告作成核付原告自91年7月3日起至\n    92 年3月19日止職業傷害傷病給付之處分；(3)判命被告作成\n    核付原告勞工保險殘廢給付標準表第133障害項目第3等級殘\n    廢給付之處分」部分，既均不合法而應予駁回，其實體上之\n    主張及陳述，已無審究之必要，併此敘明。\n四、依行政訴訟法第107條第1項第10款、第104條，民事訴訟法\n    第95條、第78條，裁定如主文。\n中    華    民    國    94    年     12   月    15    日\n                        第六庭審判長法  官  林樹埔\n                                    法  官  陳鴻斌\n                                    法  官  曹瑞卿\n上為正本係照原本作成。\n如不服本裁定，應於送達後10日內向本院提出抗告狀（須按他造\n人數附繕本）。\n中    華    民    國    94    年     12   月    15    日\n                                    書記官  方偉皓\n",
  "structure": {
    "main": "原告之訴駁回。\n訴訟費用由原告負擔。",
    "reason": "一、有關原告訴請：(1)撤銷訴願決定、審議審定及原處分關於被\n    告91年10月1日「勞工保險給付申請書（兼給付收據）、核\n    定通知書」部分；(2)判命被告作成核付原告勞工保險殘廢給\n    付標準表第133障害項目第3等級殘廢給付之處分部分：\n１、按「勞工保險爭議事項審議辦法，由中央主管機關擬訂，報\n    請行政院核定之。」、「本辦法依勞工保險條例第5條第3項\n    規定訂定之。」、「投保單位、被保險人、受益人或全民健\n    康保險醫事服務機構（以下均稱申請人）對勞工保險局（以\n    下簡稱勞保局）下列事項之核定發生爭議時，得依本辦法規\n    定申請審議：一、有關被保險人、受益人資格及投保事項。\n    二、有關被保險人投保薪資或年資事項。三、有關保險費或\n    滯納金事項。四、有關保險給付事項。五、有關職業傷病事\n    項。六、有關殘廢等級事項。七、有關職業災害診療費用事\n    項。八、其他有關保險權益事項。」、「申請人依前條規定\n    申請審議時，應於接到勞保局核定通知文件之翌日起60日內\n    ，填具勞工保險爭議事項審議申請書（以下簡稱審議申請書\n    ），並檢附有關證件經由勞保局向勞工保險監理委員會（以\n    下簡稱監理會）申請審議。其因不可歸責於己之事由致遲誤\n    期間者，申請人應自其事由消滅之翌日起30日內，以書面敘\n    明遲誤原因申請審議。」、「審議之申請，以收受審議申請\n    書之日期為準，以郵遞方式申請者，以原寄郵局之郵戳為憑\n    。」勞工保險條例第5條第3項、勞工保險爭議事項審議辦法\n    第1條、第2條、第3條第1項及第2項分別定有明文。又按「\n    原告之訴，有左列各款情形之一者，行政法院應以裁定駁回\n    之。但其情形可以補正者，審判長應定期間先命補正：．．\n    十、起訴不合程式或不備其他要件者。」行政訴訟法第107\n    條第1項第10款亦有明文。\n２、查勞工保險條例第5條第3項已明定：「勞工保險爭議事項審\n    議辦法，由中央主管機關擬訂，報請行政院核定之。」，而\n    勞工保險爭議事項審議辦法第1條亦表明：「本辦法依勞工\n    保險條例第5條第3項規定訂定之。」，參照司法院釋字第53\n    8號解釋及釋字第394號解釋意旨，此項授權條款雖未就授權\n    之內容與範圍為規定，惟依勞工保險條例之法律整體解釋，\n    應可推知立法者有意授權主管機關，就有關勞工保險給付爭\n    議事項之審查程序、申請審議所需備置之文書表件、審查機\n    構之組織等事項，依其行政專業之考量，訂定法規命令，以\n    資規範，就授權明確性而言尚無違背，是以，勞工保險爭議\n    事項審議辦法第3條第1項有關60天申請審議期間之規定，仍\n    屬於前述勞工保險給付爭議審查之程序事項，並未逾越勞工\n    保險條例之授權範圍，自得作為本件審理之依據（最高行政\n    法院92年度裁字第1554號裁定意旨參照）。\n３、本件原告係由鏵塑股份有限公司申報參加勞工保險之被保險\n    人，以於民國（下同）91年2月8日在工廠搬運貨物時遭壓傷\n    致殘，於91年7月15日（被告收文日期）向被告申請職業傷\n    害殘廢給付，經被告於91年10月1日以「勞工保險給付申請\n    書（兼給付收據）、核定通知書」核定依勞工保險殘廢給付\n    標準表第8項第7等級，發給普通傷病殘廢給付440日，計新\n    台幣281,600元。經查，本件業據原告自承其係於91年10月\n    中旬左右收到被告91年10月1日上開「勞工保險給付申請書\n    （兼給付收據）、核定通知書」，經記明於本院94年11月23\n    日準備程序筆錄在卷可按，並有被告94年12月8日庭呈勞保\n    殘廢給付詳細資料查詢表（殘廢給付核付日期：91年10月1\n    日）為憑，則原告遲至93年7月15日始申請審議（被告收文\n    日期：93年7月5日，有勞工保險爭議事項審議申請書附於爭\n    議審議案卷可稽），顯已逾越首揭規定之申請審議60日期間\n    。審議審定及訴願決定未從程序上不受理原告之審議申請及\n    訴願，而誤從實體駁回，固屬未洽，惟駁回結果並無二致，\n    仍應予維持。原告復對之提起行政訴訟，而其情形又不可以\n    補正，其訴顯非合法，應予駁回。\n４、次按，提起撤銷訴訟及課予義務訴訟，須以經過合法之訴願\n    前置程序及訴願程序，為其前提要件，其未經合法之訴願前\n    置程序及訴願程序，遽行提起撤銷訴訟及課予義務訴訟，自\n    非法之所許，此就行政訴訟法第4條第1項及第5條第2項規定\n    觀之甚明。本件原告就被告所為殘廢給付之核定【即被告91\n    年10月1日「勞工保險給付申請書（兼給付收據）、核定通\n    知書」】不服，惟其申請審議，已逾越法定60日期間，業如\n    前述，則原告訴請：「(1)撤銷訴願決定、審議審定及原處分\n    關於被告91年10月1日「勞工保險給付申請書（兼給付收據\n    ）、核定通知書」；(2)判命被告作成核付原告勞工保險殘廢\n    給付標準表第133障害項目第3等級殘廢給付之處分」部分，\n    自亦難認為合法，應予駁回。\n二、有關原告訴請判命被告作成核付原告自91年7月3日起至92年\n    3月19日止職業傷害傷病給付之處分部分：\n１、按「人民因中央或地方機關對其依法申請之案件，於法令所\n    定期間內應作為而不作為，認為其權利或法律上利益受損害\n    者，經依訴願程序後，得向高等行政法院提起請求該機關應\n    為行政處分或應為特定內容之行政處分之訴訟。」「人民因\n    中央或地方機關對其依法申請之案件，予以駁回，認為其權\n    利或法律上利益受違法損害者，經依訴願程序後，得向高等\n    行政法院提起請求該機關應為行政處分或應為特定內容之行\n    政處分之訴訟。」行政訴訟法第5條第1項及第2項定有明文\n    。因此人民提起行政訴訟法第5條第1項或第2項之課予義務\n    訴訟，須存在有人民依法申請之案件為其起訴要件，否則，\n    依行政訴訟法第107條第1項第10款：「原告之訴，有左列各\n    款情形之一者，行政法院應以裁定駁回之。但其情形可以補\n    正者，審判長應定期間先命補正：．．十、起訴不合程式或\n    不備其他要件者。」之規定，行政法院亦應以裁定駁回之。\n２、經查，本件原告係分別於91年4月23日、91年6月4日、91年\n    7月5日（被告收文日期），向被告申請91年3月19日至同年4\n    月12日期間職業傷害傷病給付、91年2月25日至同年5月31日\n    期間職業傷害傷病給付、91年2月9日至同年7月2日期間職業\n    傷害傷病給付，此有原處分卷所附3份勞工保險給付申請書\n    （兼給付收據）、核定通知書影本可稽，且為兩造所不爭執\n    ，經記明於94年11月23日準備程序筆錄及94年12月8日言詞\n    辯論筆錄在卷可按。則本件原告訴請判命被告作成核付原告\n    自91年7月3日起至92年3月19日止職業傷害傷病給付之處分\n    部分，並未據原告向被告提出申請，亦未經原告申請審議及\n    提起訴願，揆諸前揭規定及說明，原告逕向本院起訴請求，\n    自非法之所許，應予駁回。\n三、本件原告訴請：「(1)撤銷訴願決定、審議審定及原處分關於\n    被告91年10月1日『勞工保險給付申請書（兼給付收據）、\n    核定通知書』；(2)判命被告作成核付原告自91年7月3日起至\n    92 年3月19日止職業傷害傷病給付之處分；(3)判命被告作成\n    核付原告勞工保險殘廢給付標準表第133障害項目第3等級殘\n    廢給付之處分」部分，既均不合法而應予駁回，其實體上之\n    主張及陳述，已無審究之必要，併此敘明。\n四、依行政訴訟法第107條第1項第10款、第104條，民事訴訟法\n    第95條、第78條，裁定如主文。"
  },
  "search": "臺北高等行政法院裁定94年度訴字第00785號.原告甲○○被告勞工保險局代表人乙○（總經理）訴訟代理人丙○○丁○○戊○○上列當事人間因勞保事件，原告不服行政院勞工委員會中華民國94年2月1日勞訴字第0930054698號訴願決定，提起行政訴訟。就原告訴請：(1)撤銷訴願決定、審議審定及原處分關於被告91年10月1日「勞工保險給付申請書（兼給付收據）、核定通知書」部分；(2)判命被告作成核付原告自91年7月3日起至92年3月19日止職業傷害傷病給付之處分部分；(3)判命被告作成核付原告勞工保險殘廢給付標準表第133障害項目第3等級殘廢給付之處分部分，本院裁定如下：主文原告之訴駁回。訴訟費用由原告負擔。理由一、有關原告訴請：(1)撤銷訴願決定、審議審定及原處分關於被告91年10月1日「勞工保險給付申請書（兼給付收據）、核定通知書」部分；(2)判命被告作成核付原告勞工保險殘廢給付標準表第133障害項目第3等級殘廢給付之處分部分：１、按「勞工保險爭議事項審議辦法，由中央主管機關擬訂，報請行政院核定之。」、「本辦法依勞工保險條例第5條第3項規定訂定之。」、「投保單位、被保險人、受益人或全民健康保險醫事服務機構（以下均稱申請人）對勞工保險局（以下簡稱勞保局）下列事項之核定發生爭議時，得依本辦法規定申請審議：一、有關被保險人、受益人資格及投保事項。二、有關被保險人投保薪資或年資事項。三、有關保險費或滯納金事項。四、有關保險給付事項。五、有關職業傷病事項。六、有關殘廢等級事項。七、有關職業災害診療費用事項。八、其他有關保險權益事項。」、「申請人依前條規定申請審議時，應於接到勞保局核定通知文件之翌日起60日內，填具勞工保險爭議事項審議申請書（以下簡稱審議申請書），並檢附有關證件經由勞保局向勞工保險監理委員會（以下簡稱監理會）申請審議。其因不可歸責於己之事由致遲誤期間者，申請人應自其事由消滅之翌日起30日內，以書面敘明遲誤原因申請審議。」、「審議之申請，以收受審議申請書之日期為準，以郵遞方式申請者，以原寄郵局之郵戳為憑。」勞工保險條例第5條第3項、勞工保險爭議事項審議辦法第1條、第2條、第3條第1項及第2項分別定有明文。又按「原告之訴，有左列各款情形之一者，行政法院應以裁定駁回之。但其情形可以補正者，審判長應定期間先命補正：．．十、起訴不合程式或不備其他要件者。」行政訴訟法第107條第1項第10款亦有明文。２、查勞工保險條例第5條第3項已明定：「勞工保險爭議事項審議辦法，由中央主管機關擬訂，報請行政院核定之。」，而勞工保險爭議事項審議辦法第1條亦表明：「本辦法依勞工保險條例第5條第3項規定訂定之。」，參照司法院釋字第538號解釋及釋字第394號解釋意旨，此項授權條款雖未就授權之內容與範圍為規定，惟依勞工保險條例之法律整體解釋，應可推知立法者有意授權主管機關，就有關勞工保險給付爭議事項之審查程序、申請審議所需備置之文書表件、審查機構之組織等事項，依其行政專業之考量，訂定法規命令，以資規範，就授權明確性而言尚無違背，是以，勞工保險爭議事項審議辦法第3條第1項有關60天申請審議期間之規定，仍屬於前述勞工保險給付爭議審查之程序事項，並未逾越勞工保險條例之授權範圍，自得作為本件審理之依據（最高行政法院92年度裁字第1554號裁定意旨參照）。３、本件原告係由鏵塑股份有限公司申報參加勞工保險之被保險人，以於民國（下同）91年2月8日在工廠搬運貨物時遭壓傷致殘，於91年7月15日（被告收文日期）向被告申請職業傷害殘廢給付，經被告於91年10月1日以「勞工保險給付申請書（兼給付收據）、核定通知書」核定依勞工保險殘廢給付標準表第8項第7等級，發給普通傷病殘廢給付440日，計新台幣281,600元。經查，本件業據原告自承其係於91年10月中旬左右收到被告91年10月1日上開「勞工保險給付申請書（兼給付收據）、核定通知書」，經記明於本院94年11月23日準備程序筆錄在卷可按，並有被告94年12月8日庭呈勞保殘廢給付詳細資料查詢表（殘廢給付核付日期：91年10月1日）為憑，則原告遲至93年7月15日始申請審議（被告收文日期：93年7月5日，有勞工保險爭議事項審議申請書附於爭議審議案卷可稽），顯已逾越首揭規定之申請審議60日期間。審議審定及訴願決定未從程序上不受理原告之審議申請及訴願，而誤從實體駁回，固屬未洽，惟駁回結果並無二致，仍應予維持。原告復對之提起行政訴訟，而其情形又不可以補正，其訴顯非合法，應予駁回。４、次按，提起撤銷訴訟及課予義務訴訟，須以經過合法之訴願前置程序及訴願程序，為其前提要件，其未經合法之訴願前置程序及訴願程序，遽行提起撤銷訴訟及課予義務訴訟，自非法之所許，此就行政訴訟法第4條第1項及第5條第2項規定觀之甚明。本件原告就被告所為殘廢給付之核定【即被告91年10月1日「勞工保險給付申請書（兼給付收據）、核定通知書」】不服，惟其申請審議，已逾越法定60日期間，業如前述，則原告訴請：「(1)撤銷訴願決定、審議審定及原處分關於被告91年10月1日「勞工保險給付申請書（兼給付收據）、核定通知書」；(2)判命被告作成核付原告勞工保險殘廢給付標準表第133障害項目第3等級殘廢給付之處分」部分，自亦難認為合法，應予駁回。二、有關原告訴請判命被告作成核付原告自91年7月3日起至92年3月19日止職業傷害傷病給付之處分部分：１、按「人民因中央或地方機關對其依法申請之案件，於法令所定期間內應作為而不作為，認為其權利或法律上利益受損害者，經依訴願程序後，得向高等行政法院提起請求該機關應為行政處分或應為特定內容之行政處分之訴訟。」「人民因中央或地方機關對其依法申請之案件，予以駁回，認為其權利或法律上利益受違法損害者，經依訴願程序後，得向高等行政法院提起請求該機關應為行政處分或應為特定內容之行政處分之訴訟。」行政訴訟法第5條第1項及第2項定有明文。因此人民提起行政訴訟法第5條第1項或第2項之課予義務訴訟，須存在有人民依法申請之案件為其起訴要件，否則，依行政訴訟法第107條第1項第10款：「原告之訴，有左列各款情形之一者，行政法院應以裁定駁回之。但其情形可以補正者，審判長應定期間先命補正：．．十、起訴不合程式或不備其他要件者。」之規定，行政法院亦應以裁定駁回之。２、經查，本件原告係分別於91年4月23日、91年6月4日、91年7月5日（被告收文日期），向被告申請91年3月19日至同年4月12日期間職業傷害傷病給付、91年2月25日至同年5月31日期間職業傷害傷病給付、91年2月9日至同年7月2日期間職業傷害傷病給付，此有原處分卷所附3份勞工保險給付申請書（兼給付收據）、核定通知書影本可稽，且為兩造所不爭執，經記明於94年11月23日準備程序筆錄及94年12月8日言詞辯論筆錄在卷可按。則本件原告訴請判命被告作成核付原告自91年7月3日起至92年3月19日止職業傷害傷病給付之處分部分，並未據原告向被告提出申請，亦未經原告申請審議及提起訴願，揆諸前揭規定及說明，原告逕向本院起訴請求，自非法之所許，應予駁回。三、本件原告訴請：「(1)撤銷訴願決定、審議審定及原處分關於被告91年10月1日『勞工保險給付申請書（兼給付收據）、核定通知書』；(2)判命被告作成核付原告自91年7月3日起至92年3月19日止職業傷害傷病給付之處分；(3)判命被告作成核付原告勞工保險殘廢給付標準表第133障害項目第3等級殘廢給付之處分」部分，既均不合法而應予駁回，其實體上之主張及陳述，已無審究之必要，併此敘明。四、依行政訴訟法第107條第1項第10款、第104條，民事訴訟法第95條、第78條，裁定如主文。中華民國94年12月15日第六庭審判長法官林樹埔法官陳鴻斌法官曹瑞卿上為正本係照原本作成。如不服本裁定，應於送達後10日內向本院提出抗告狀（須按他造人數附繕本）。中華民國94年12月15日書記官方偉皓",
  "characters": {
    "judges": [
      "林樹埔",
      "陳鴻斌",
      "曹瑞卿"
    ],
    "prosecutors": [

    ],
    "lawyers": [

    ],
    "clerks": [
      "方偉皓"
    ],
    "plaintiffs": [
      "甲○○"
    ],
    "defendants": [
      "勞工保險局",
      "代  表  人  乙○（總經理）"
    ],
    "prosecutor_office": [

    ],
    "creditors": [

    ],
    "debtors": [

    ],
    "judicial_associate_officer": [

    ]
  },
  "adjudged_at": "2005-12-15",
  "created_at": "2016-02-07 02:52:31",
  "updated_at": "2016-02-07 02:52:31"
}