{
  "identify": "TYD-93-壢簡-1514-20041118-1",
  "court": {
    "name": "臺灣桃園地方法院",
    "code": "TYD"
  },
  "division": {
    "name": "刑事",
    "code": "M"
  },
  "year": 93,
  "word": "壢簡",
  "number": "1514",
  "jcheck": "1",
  "reason": "就業服務法",
  "content": "臺灣桃園地方法院刑事簡易判決                  九十三年度壢簡字第一五一四號\n    聲  請  人  臺灣桃園地方法院檢察署檢察官\n    被      告  甲○○  男  四.\n右被告因違反就業務服法案件，經檢察官聲請以簡易判決處刑（九十三年度偵字第一\n五一０六號），本院判決如左：\n    主  文\n甲○○五年內再違反雇主不得聘僱未經許可、許可失效或他人所申請聘僱之外國人之\n規定，聘僱許可失效之外國人，科罰金新臺幣貳萬元，如易服勞役，以罰金總額與陸\n個月之日數比例折算。\n    事實及理由\n一、本件犯罪事實及證據均用檢察官聲請簡易判決處刑書之記載（如附件）。\n二、被告甲○○於本院訊問時，表示願受新臺幣二萬元之刑度（見本院九十三年十一\n    月十五日訊問筆錄），依刑事訴訟法第四百五十五條之一第二項規定，被告對於\n    本件不得上訴，至聲請人如不服本判決，得於收受判決送達後十日內向本院提出\n    上訴狀。\n三、依刑事訴訟法第四百四十九條第一項前段、第三項、第四百五十四條第二項，就\n    業服務法第六十三條第一項，刑法第十一條前段、第四十二條第三項，逕以簡易\n    判決處刑如主文。\n中      華      民      國    九十三    年     十一     月     十八     日\n                                      臺灣桃園地方法院刑事第一庭\n                                          法  官  曾淑華\n右正本證明與原本無異。\n                                          書記官  林怡君\n中      華      民      國    九十三    年     十一     月     十九     日\n本案論罪科刑主要法條：\n就業服務法第六十三條\n違反第四十四條或第五十七條第一款、第二款規定者，處新臺幣十五萬元以上七十五\n萬元以下罰鍰。五年內再違反者，處三年以下有期徒刑、拘役或科或併科新臺幣一百\n二十萬元以下罰金。\n法人之代表人、法人或自然人之代理人、受僱人或其他從業人員，因執行業務違反第\n四十四條或第五十七條第一款、第二款規定者，除依前項規定處罰其行為人外，對該\n法人或自然人亦科處前項之罰鍰或罰金。\n",
  "structure": {
    "main": "甲○○五年內再違反雇主不得聘僱未經許可、許可失效或他人所申請聘僱之外國人之\n規定，聘僱許可失效之外國人，科罰金新臺幣貳萬元，如易服勞役，以罰金總額與陸\n個月之日數比例折算。",
    "fact": "一、本件犯罪事實及證據均用檢察官聲請簡易判決處刑書之記載（如附件）。\n二、被告甲○○於本院訊問時，表示願受新臺幣二萬元之刑度（見本院九十三年十一\n    月十五日訊問筆錄），依刑事訴訟法第四百五十五條之一第二項規定，被告對於\n    本件不得上訴，至聲請人如不服本判決，得於收受判決送達後十日內向本院提出\n    上訴狀。\n三、依刑事訴訟法第四百四十九條第一項前段、第三項、第四百五十四條第二項，就\n    業服務法第六十三條第一項，刑法第十一條前段、第四十二條第三項，逕以簡易\n    判決處刑如主文。",
    "reason": "一、本件犯罪事實及證據均用檢察官聲請簡易判決處刑書之記載（如附件）。\n二、被告甲○○於本院訊問時，表示願受新臺幣二萬元之刑度（見本院九十三年十一\n    月十五日訊問筆錄），依刑事訴訟法第四百五十五條之一第二項規定，被告對於\n    本件不得上訴，至聲請人如不服本判決，得於收受判決送達後十日內向本院提出\n    上訴狀。\n三、依刑事訴訟法第四百四十九條第一項前段、第三項、第四百五十四條第二項，就\n    業服務法第六十三條第一項，刑法第十一條前段、第四十二條第三項，逕以簡易\n    判決處刑如主文。"
  },
  "search": "臺灣桃園地方法院刑事簡易判決九十三年度壢簡字第一五一四號聲請人臺灣桃園地方法院檢察署檢察官被告甲○○男四.右被告因違反就業務服法案件，經檢察官聲請以簡易判決處刑（九十三年度偵字第一五一０六號），本院判決如左：主文甲○○五年內再違反雇主不得聘僱未經許可、許可失效或他人所申請聘僱之外國人之規定，聘僱許可失效之外國人，科罰金新臺幣貳萬元，如易服勞役，以罰金總額與陸個月之日數比例折算。事實及理由一、本件犯罪事實及證據均用檢察官聲請簡易判決處刑書之記載（如附件）。二、被告甲○○於本院訊問時，表示願受新臺幣二萬元之刑度（見本院九十三年十一月十五日訊問筆錄），依刑事訴訟法第四百五十五條之一第二項規定，被告對於本件不得上訴，至聲請人如不服本判決，得於收受判決送達後十日內向本院提出上訴狀。三、依刑事訴訟法第四百四十九條第一項前段、第三項、第四百五十四條第二項，就業服務法第六十三條第一項，刑法第十一條前段、第四十二條第三項，逕以簡易判決處刑如主文。中華民國九十三年十一月十八日臺灣桃園地方法院刑事第一庭法官曾淑華右正本證明與原本無異。書記官林怡君中華民國九十三年十一月十九日本案論罪科刑主要法條：就業服務法第六十三條違反第四十四條或第五十七條第一款、第二款規定者，處新臺幣十五萬元以上七十五萬元以下罰鍰。五年內再違反者，處三年以下有期徒刑、拘役或科或併科新臺幣一百二十萬元以下罰金。法人之代表人、法人或自然人之代理人、受僱人或其他從業人員，因執行業務違反第四十四條或第五十七條第一款、第二款規定者，除依前項規定處罰其行為人外，對該法人或自然人亦科處前項之罰鍰或罰金。",
  "characters": {
    "judges": [
      "曾淑華"
    ],
    "prosecutors": [

    ],
    "lawyers": [

    ],
    "clerks": [
      "林怡君"
    ],
    "plaintiffs": [

    ],
    "defendants": [
      "甲○○  男  四.",
      "右被告因違反就業務服法案件，經檢察官聲請以簡易判決處刑（九十三年度偵字第一",
      "五一０六號），本院判決如左："
    ],
    "prosecutor_office": [
      "臺灣桃園地方法院檢察署檢察官"
    ],
    "creditors": [

    ],
    "debtors": [

    ],
    "judicial_associate_officer": [

    ]
  },
  "adjudged_at": "2004-11-18",
  "created_at": "2016-02-06 03:24:54",
  "updated_at": "2016-02-06 03:24:54"
}