{
  "identify": "TPD-91-簡-1945-20020625-1",
  "court": {
    "name": "臺灣臺北地方法院",
    "code": "TPD"
  },
  "division": {
    "name": "刑事",
    "code": "M"
  },
  "year": 91,
  "word": "簡",
  "number": "1945",
  "jcheck": "1",
  "reason": "毒品危害防制條例",
  "content": "臺灣臺北地方法院刑事簡易判決                    九十一年度簡字第一九四五號\n    聲  請  人  臺灣臺北地方法院檢察署檢察官\n    被      告  甲○○\n右列被告因違反毒品危害防制條例案件，經檢察官聲請以簡易判決處刑（九十年度毒\n偵字第二四八八號），本院判決如左：\n    主  文\n甲○○持有第二級毒品，處有期徒刑參月，如易科罰金以參佰元折算壹日；扣案第二\n級毒品大麻煙貳支，毛重零點陸伍公克均沒收銷毀。\n    事實及理由\n一、甲○○明知不得持有第二級毒品大麻，仍於九十年九月二十七日凌晨一時許，在\n    臺北市○○區○○街與雙城街口之「Ｗ」舞廳，持有第二級毒品大麻煙，嗣於同\n    日凌晨一時十五分許，在臺北市○○區○○街與雙城街口遇警攔檢而查獲，並扣\n    得甲○○所有第二級毒品大麻煙二支毛重零點六五公克（聲請書誤載為淨重零點\n    六四公克）。\n二、證據：（一）本件被告甲○○於警訊時及檢察官偵查中坦承不諱，且有該扣案第\n    二級毒品係於被告持有中，在其香煙盒被警查獲等事實（見九十年度毒偵字第二\n    四八八號偵查卷宗第五、二十頁背面警詢、檢察官偵查筆錄），再佐以其他現存\n    之證據，已足認定其犯罪，檢察官既已聲請本院逕以簡易判決處刑，經核檢察官\n    之聲請合法，著以簡易判決處刑，合先敘明；（二）此外復有扣案之第二級毒品\n    大麻煙二支毛重零點六五公克，及臺北市政府警察局保安警察大隊第三中隊所出\n    具上載「檢出第二級毒品大麻煙反應」等語之檢驗報告書及法務部調查局所出具\n    鑑定通知書各一紙可稽（見同前偵查卷宗第九、二十七頁），被告之自白經核與\n    事實相符，本件事證明確，被告犯行堪以認定，應予依法論科；（三）按大麻煙\n    係屬毒品危害防制條例第二條第二項第二款所稱之第二級毒品，核被告所為係犯\n    毒品危害防制條例第十一條第二項之持有第二級毒品罪，爰審酌被告犯後已坦承\n    犯行，態度尚佳，經查亦無施用毒品犯行，所生之社會危險等一切情狀，量處如\n    主文所示之刑，並諭知易科罰金之折算標準，以示懲儆；（四）扣案被告所持有\n    第二級毒品大麻煙二支毛重零點六五公克，應依毒品危害防制條例第十八條第一\n    項前段規定沒收銷燬之。\n三、據上論斷，應依刑事訴訟法第第四百四十九條第一項前段、第三項、第四百五十\n    條第一項，毒品危害防制條例第十一條第二項、第十八條第一項前段，刑法第十\n    一條前段、第四十一條第一項前段，罰金罰鍰提高標準條例第二條，逕以簡易判\n    決處刑如主文。\n如不服本判決，得自收受送達之日起十日內，向本院提起上訴。\n中      華      民      國    九十一    年      六      月    二十五    日\n                                      臺灣臺北地方法院刑事第六庭\n                                          法  官  黃程暉\n右正本證明與原本無異\n          書記官  張華瓊\n中      華      民      國    九十一    年      七      月      三      日\n附錄本案論罪科刑法條全文\n毒品危害防制條例第十一條\n持有第一級毒品者，處三年以下有期徒刑、拘役或新臺幣五萬元以下罰金。\n持有第二級毒品者，處二年以下有期徒刑、拘役或新臺幣三萬元以下罰金。\n持有專供製造或施用毒品之器具者，處一年以下有期徒刑、拘役或新臺幣一萬元以下\n罰金。\n",
  "structure": {
    "main": "甲○○持有第二級毒品，處有期徒刑參月，如易科罰金以參佰元折算壹日；扣案第二\n級毒品大麻煙貳支，毛重零點陸伍公克均沒收銷毀。",
    "fact": "一、甲○○明知不得持有第二級毒品大麻，仍於九十年九月二十七日凌晨一時許，在\n    臺北市○○區○○街與雙城街口之「Ｗ」舞廳，持有第二級毒品大麻煙，嗣於同\n    日凌晨一時十五分許，在臺北市○○區○○街與雙城街口遇警攔檢而查獲，並扣\n    得甲○○所有第二級毒品大麻煙二支毛重零點六五公克（聲請書誤載為淨重零點\n    六四公克）。\n二、證據：（一）本件被告甲○○於警訊時及檢察官偵查中坦承不諱，且有該扣案第\n    二級毒品係於被告持有中，在其香煙盒被警查獲等事實（見九十年度毒偵字第二\n    四八八號偵查卷宗第五、二十頁背面警詢、檢察官偵查筆錄），再佐以其他現存\n    之證據，已足認定其犯罪，檢察官既已聲請本院逕以簡易判決處刑，經核檢察官\n    之聲請合法，著以簡易判決處刑，合先敘明；（二）此外復有扣案之第二級毒品\n    大麻煙二支毛重零點六五公克，及臺北市政府警察局保安警察大隊第三中隊所出\n    具上載「檢出第二級毒品大麻煙反應」等語之檢驗報告書及法務部調查局所出具\n    鑑定通知書各一紙可稽（見同前偵查卷宗第九、二十七頁），被告之自白經核與\n    事實相符，本件事證明確，被告犯行堪以認定，應予依法論科；（三）按大麻煙\n    係屬毒品危害防制條例第二條第二項第二款所稱之第二級毒品，核被告所為係犯\n    毒品危害防制條例第十一條第二項之持有第二級毒品罪，爰審酌被告犯後已坦承\n    犯行，態度尚佳，經查亦無施用毒品犯行，所生之社會危險等一切情狀，量處如\n    主文所示之刑，並諭知易科罰金之折算標準，以示懲儆；（四）扣案被告所持有\n    第二級毒品大麻煙二支毛重零點六五公克，應依毒品危害防制條例第十八條第一\n    項前段規定沒收銷燬之。\n三、據上論斷，應依刑事訴訟法第第四百四十九條第一項前段、第三項、第四百五十\n    條第一項，毒品危害防制條例第十一條第二項、第十八條第一項前段，刑法第十\n    一條前段、第四十一條第一項前段，罰金罰鍰提高標準條例第二條，逕以簡易判\n    決處刑如主文。\n如不服本判決，得自收受送達之日起十日內，向本院提起上訴。",
    "reason": "一、甲○○明知不得持有第二級毒品大麻，仍於九十年九月二十七日凌晨一時許，在\n    臺北市○○區○○街與雙城街口之「Ｗ」舞廳，持有第二級毒品大麻煙，嗣於同\n    日凌晨一時十五分許，在臺北市○○區○○街與雙城街口遇警攔檢而查獲，並扣\n    得甲○○所有第二級毒品大麻煙二支毛重零點六五公克（聲請書誤載為淨重零點\n    六四公克）。\n二、證據：（一）本件被告甲○○於警訊時及檢察官偵查中坦承不諱，且有該扣案第\n    二級毒品係於被告持有中，在其香煙盒被警查獲等事實（見九十年度毒偵字第二\n    四八八號偵查卷宗第五、二十頁背面警詢、檢察官偵查筆錄），再佐以其他現存\n    之證據，已足認定其犯罪，檢察官既已聲請本院逕以簡易判決處刑，經核檢察官\n    之聲請合法，著以簡易判決處刑，合先敘明；（二）此外復有扣案之第二級毒品\n    大麻煙二支毛重零點六五公克，及臺北市政府警察局保安警察大隊第三中隊所出\n    具上載「檢出第二級毒品大麻煙反應」等語之檢驗報告書及法務部調查局所出具\n    鑑定通知書各一紙可稽（見同前偵查卷宗第九、二十七頁），被告之自白經核與\n    事實相符，本件事證明確，被告犯行堪以認定，應予依法論科；（三）按大麻煙\n    係屬毒品危害防制條例第二條第二項第二款所稱之第二級毒品，核被告所為係犯\n    毒品危害防制條例第十一條第二項之持有第二級毒品罪，爰審酌被告犯後已坦承\n    犯行，態度尚佳，經查亦無施用毒品犯行，所生之社會危險等一切情狀，量處如\n    主文所示之刑，並諭知易科罰金之折算標準，以示懲儆；（四）扣案被告所持有\n    第二級毒品大麻煙二支毛重零點六五公克，應依毒品危害防制條例第十八條第一\n    項前段規定沒收銷燬之。\n三、據上論斷，應依刑事訴訟法第第四百四十九條第一項前段、第三項、第四百五十\n    條第一項，毒品危害防制條例第十一條第二項、第十八條第一項前段，刑法第十\n    一條前段、第四十一條第一項前段，罰金罰鍰提高標準條例第二條，逕以簡易判\n    決處刑如主文。\n如不服本判決，得自收受送達之日起十日內，向本院提起上訴。"
  },
  "search": "臺灣臺北地方法院刑事簡易判決九十一年度簡字第一九四五號聲請人臺灣臺北地方法院檢察署檢察官被告甲○○右列被告因違反毒品危害防制條例案件，經檢察官聲請以簡易判決處刑（九十年度毒偵字第二四八八號），本院判決如左：主文甲○○持有第二級毒品，處有期徒刑參月，如易科罰金以參佰元折算壹日；扣案第二級毒品大麻煙貳支，毛重零點陸伍公克均沒收銷毀。事實及理由一、甲○○明知不得持有第二級毒品大麻，仍於九十年九月二十七日凌晨一時許，在臺北市○○區○○街與雙城街口之「Ｗ」舞廳，持有第二級毒品大麻煙，嗣於同日凌晨一時十五分許，在臺北市○○區○○街與雙城街口遇警攔檢而查獲，並扣得甲○○所有第二級毒品大麻煙二支毛重零點六五公克（聲請書誤載為淨重零點六四公克）。二、證據：（一）本件被告甲○○於警訊時及檢察官偵查中坦承不諱，且有該扣案第二級毒品係於被告持有中，在其香煙盒被警查獲等事實（見九十年度毒偵字第二四八八號偵查卷宗第五、二十頁背面警詢、檢察官偵查筆錄），再佐以其他現存之證據，已足認定其犯罪，檢察官既已聲請本院逕以簡易判決處刑，經核檢察官之聲請合法，著以簡易判決處刑，合先敘明；（二）此外復有扣案之第二級毒品大麻煙二支毛重零點六五公克，及臺北市政府警察局保安警察大隊第三中隊所出具上載「檢出第二級毒品大麻煙反應」等語之檢驗報告書及法務部調查局所出具鑑定通知書各一紙可稽（見同前偵查卷宗第九、二十七頁），被告之自白經核與事實相符，本件事證明確，被告犯行堪以認定，應予依法論科；（三）按大麻煙係屬毒品危害防制條例第二條第二項第二款所稱之第二級毒品，核被告所為係犯毒品危害防制條例第十一條第二項之持有第二級毒品罪，爰審酌被告犯後已坦承犯行，態度尚佳，經查亦無施用毒品犯行，所生之社會危險等一切情狀，量處如主文所示之刑，並諭知易科罰金之折算標準，以示懲儆；（四）扣案被告所持有第二級毒品大麻煙二支毛重零點六五公克，應依毒品危害防制條例第十八條第一項前段規定沒收銷燬之。三、據上論斷，應依刑事訴訟法第第四百四十九條第一項前段、第三項、第四百五十條第一項，毒品危害防制條例第十一條第二項、第十八條第一項前段，刑法第十一條前段、第四十一條第一項前段，罰金罰鍰提高標準條例第二條，逕以簡易判決處刑如主文。如不服本判決，得自收受送達之日起十日內，向本院提起上訴。中華民國九十一年六月二十五日臺灣臺北地方法院刑事第六庭法官黃程暉右正本證明與原本無異書記官張華瓊中華民國九十一年七月三日附錄本案論罪科刑法條全文毒品危害防制條例第十一條持有第一級毒品者，處三年以下有期徒刑、拘役或新臺幣五萬元以下罰金。持有第二級毒品者，處二年以下有期徒刑、拘役或新臺幣三萬元以下罰金。持有專供製造或施用毒品之器具者，處一年以下有期徒刑、拘役或新臺幣一萬元以下罰金。",
  "characters": {
    "judges": [
      "黃程暉"
    ],
    "prosecutors": [

    ],
    "lawyers": [

    ],
    "clerks": [
      "張華瓊"
    ],
    "plaintiffs": [

    ],
    "defendants": [
      "甲○○",
      "右列被告因違反毒品危害防制條例案件，經檢察官聲請以簡易判決處刑（九十年度毒",
      "偵字第二四八八號），本院判決如左："
    ],
    "prosecutor_office": [
      "臺灣臺北地方法院檢察署檢察官"
    ],
    "creditors": [

    ],
    "debtors": [

    ],
    "judicial_associate_officer": [

    ]
  },
  "adjudged_at": "2002-06-25",
  "created_at": "2016-02-05 15:38:09",
  "updated_at": "2016-02-05 15:38:09"
}