{
  "identify": "TPD-100-除-563-20110316-1",
  "court": {
    "name": "臺灣臺北地方法院",
    "code": "TPD"
  },
  "division": {
    "name": "民事",
    "code": "V"
  },
  "year": 100,
  "word": "除",
  "number": "563",
  "jcheck": "1",
  "reason": "除權判決（票據）",
  "content": "臺灣臺北地方法院民事判決              100年度除字第563號\n聲  請  人  黃鴻恩\n代  理  人  陳姿蓁\n上列聲請人聲請除權判決事件，本院判決如下：\n    主  文\n如附表所示之證券無效。\n訴訟費用由聲請人負擔。\n    理  由\n一、上開證券，經本院以99年度司催字第2652號公示催告。\n二、所定申報權利期間，已於民國100年2月12日屆滿，迄今無人\n    申報權利。\n三、依民事訴訟法第564條第1項，判決如主文。\n中    華    民    國   100    年    3     月    16    日\n                  民事第三庭  審判長法  官  郭美杏\n                                    法  官  曾益盛\n                                    法  官  吳若萍\n以上正本係照原本作成。\n本判決不得上訴。\n中    華    民    國   100    年    3     月    16    日\n                                    書記官  劉英權\n┌────────────────────────────────┐\n│附表：                                        100年度除字第563號│\n├──┬────────┬──────┬──────┬──┬───┤\n│編號│發  行  公  司  │受益憑證名稱│受益憑證號碼│張數│單位數│\n├──┼────────┼──────┼──────┼──┼───┤\n│001 │豐中華證券投資│豐成功基金│00-0000000-0│1   │1000  │\n│    │信託股份有限公司│            │            │    │      │\n├──┼────────┼──────┼──────┼──┼───┤\n│002 │豐中華證券投資│豐成功基金│00-0000000-0│1   │1000  │\n│    │信託股份有限公司│            │            │    │      │\n├──┼────────┼──────┼──────┼──┼───┤\n│003 │豐中華證券投資│豐成功基金│00-0000000-0│1   │1000  │\n│    │信託股份有限公司│            │            │    │      │\n├──┼────────┼──────┼──────┼──┼───┤\n│004 │豐中華證券投資│豐成功基金│00-0000000-0│1   │1000  │\n│    │信託股份有限公司│            │            │    │      │\n├──┼────────┼──────┼──────┼──┼───┤\n│005 │豐中華證券投資│豐成功基金│00-0000000-0│1   │1000  │\n│    │信託股份有限公司│            │            │    │      │\n├──┼────────┼──────┼──────┼──┼───┤\n│006 │豐中華證券投資│豐成功基金│00-0000000-0│1   │1000  │\n│    │信託股份有限公司│            │            │    │      │\n├──┼────────┼──────┼──────┼──┼───┤\n│007 │豐中華證券投資│豐成功基金│00-0000000-0│1   │1000  │\n│    │信託股份有限公司│            │            │    │      │\n├──┼────────┼──────┼──────┼──┼───┤\n│008 │豐中華證券投資│豐成功基金│00-0000000-0│1   │1000  │\n│    │信託股份有限公司│            │            │    │      │\n├──┼────────┼──────┼──────┼──┼───┤\n│009 │豐中華證券投資│豐成功基金│00-0000000-0│1   │1000  │\n│    │信託股份有限公司│            │            │    │      │\n├──┼────────┼──────┼──────┼──┼───┤\n│010 │豐中華證券投資│豐成功基金│00-0000000-0│1   │1000  │\n│    │信託股份有限公司│            │            │    │      │\n└──┴────────┴──────┴──────┴──┴───┘",
  "structure": {
    "main": "如附表所示之證券無效。\n訴訟費用由聲請人負擔。",
    "reason": "一、上開證券，經本院以99年度司催字第2652號公示催告。\n二、所定申報權利期間，已於民國100年2月12日屆滿，迄今無人\n    申報權利。\n三、依民事訴訟法第564條第1項，判決如主文。"
  },
  "search": "臺灣臺北地方法院民事判決100年度除字第563號聲請人黃鴻恩代理人陳姿蓁上列聲請人聲請除權判決事件，本院判決如下：主文如附表所示之證券無效。訴訟費用由聲請人負擔。理由一、上開證券，經本院以99年度司催字第2652號公示催告。二、所定申報權利期間，已於民國100年2月12日屆滿，迄今無人申報權利。三、依民事訴訟法第564條第1項，判決如主文。中華民國100年3月16日民事第三庭審判長法官郭美杏法官曾益盛法官吳若萍以上正本係照原本作成。本判決不得上訴。中華民國100年3月16日書記官劉英權┌────────────────────────────────┐│附表：100年度除字第563號│├──┬────────┬──────┬──────┬──┬───┤│編號│發行公司│受益憑證名稱│受益憑證號碼│張數│單位數│├──┼────────┼──────┼──────┼──┼───┤│001│豐中華證券投資│豐成功基金│00-0000000-0│1│1000│││信託股份有限公司│││││├──┼────────┼──────┼──────┼──┼───┤│002│豐中華證券投資│豐成功基金│00-0000000-0│1│1000│││信託股份有限公司│││││├──┼────────┼──────┼──────┼──┼───┤│003│豐中華證券投資│豐成功基金│00-0000000-0│1│1000│││信託股份有限公司│││││├──┼────────┼──────┼──────┼──┼───┤│004│豐中華證券投資│豐成功基金│00-0000000-0│1│1000│││信託股份有限公司│││││├──┼────────┼──────┼──────┼──┼───┤│005│豐中華證券投資│豐成功基金│00-0000000-0│1│1000│││信託股份有限公司│││││├──┼────────┼──────┼──────┼──┼───┤│006│豐中華證券投資│豐成功基金│00-0000000-0│1│1000│││信託股份有限公司│││││├──┼────────┼──────┼──────┼──┼───┤│007│豐中華證券投資│豐成功基金│00-0000000-0│1│1000│││信託股份有限公司│││││├──┼────────┼──────┼──────┼──┼───┤│008│豐中華證券投資│豐成功基金│00-0000000-0│1│1000│││信託股份有限公司│││││├──┼────────┼──────┼──────┼──┼───┤│009│豐中華證券投資│豐成功基金│00-0000000-0│1│1000│││信託股份有限公司│││││├──┼────────┼──────┼──────┼──┼───┤│010│豐中華證券投資│豐成功基金│00-0000000-0│1│1000│││信託股份有限公司│││││└──┴────────┴──────┴──────┴──┴───┘",
  "characters": {
    "judges": [
      "郭美杏",
      "曾益盛",
      "吳若萍"
    ],
    "prosecutors": [

    ],
    "lawyers": [

    ],
    "clerks": [
      "劉英權"
    ],
    "plaintiffs": [

    ],
    "defendants": [

    ],
    "prosecutor_office": [
      "黃鴻恩"
    ],
    "creditors": [

    ],
    "debtors": [

    ],
    "judicial_associate_officer": [

    ]
  },
  "adjudged_at": "2011-03-16",
  "created_at": "2016-02-13 23:39:32",
  "updated_at": "2016-02-13 23:39:32"
}