{
  "identify": "TPD-100-除-447-20110316-1",
  "court": {
    "name": "臺灣臺北地方法院",
    "code": "TPD"
  },
  "division": {
    "name": "民事",
    "code": "V"
  },
  "year": 100,
  "word": "除",
  "number": "447",
  "jcheck": "1",
  "reason": "除權判決（票據）",
  "content": "臺灣臺北地方法院民事判決              100年度除字第447號\n聲  請  人  上海商業儲蓄銀行股份有限公司\n法定代理人  邱怡仁\n代  理  人  陳正志\n上列聲請人聲請除權判決（票據）事件，本院判決如下：\n    主  文\n如附表所示之證券無效。\n訴訟費用由聲請人負擔。\n    理  由\n一、上開證券，經本院以99年度司催字第2689號公示催告。\n二、所定申報權利期間，已於民國100年2月2日屆滿，迄今無人\n    申報權利。\n三、依民事訴訟法第564條第1項，判決如主文。\n中    華    民    國   100    年    3     月    16    日\n                  民事第三庭    法  官  郭美杏\n本判決不得上訴。\n以上正本證明係照原本作成。\n中    華    民    國   100    年    3     月    16    日\n                                書記官  周小玲\n┌─────────────────────────────────┐\n│附表：                                                            │\n├──┬─────────┬──────┬─────┬───────┤\n│編號│ 發    票    人   │發  票  日  │到  期  日│金額（新臺幣）│\n├──┼─────────┼──────┼─────┼───────┤\n│001 │志發企業股份有限公│86年2月17日 │未載      │8,800,000元   │\n│    │司  陳梅妹、陳梅妹│            │          │              │\n│    │、姜林茂森、姜林茂│            │          │              │\n│    │盛、姜林茂樹      │            │          │              │\n├──┼─────────┼──────┼─────┼───────┤\n│002 │志發企業股份有限公│86年2月17日 │未載      │6,000,000元   │\n│    │司  陳梅妹、陳梅妹│            │          │              │\n│    │、姜林茂森、姜林茂│            │          │              │\n│    │盛、姜林茂樹      │            │          │              │\n└──┴─────────┴──────┴─────┴───────┘",
  "structure": {
    "main": "如附表所示之證券無效。\n訴訟費用由聲請人負擔。",
    "reason": "一、上開證券，經本院以99年度司催字第2689號公示催告。\n二、所定申報權利期間，已於民國100年2月2日屆滿，迄今無人\n    申報權利。\n三、依民事訴訟法第564條第1項，判決如主文。"
  },
  "search": "臺灣臺北地方法院民事判決100年度除字第447號聲請人上海商業儲蓄銀行股份有限公司法定代理人邱怡仁代理人陳正志上列聲請人聲請除權判決（票據）事件，本院判決如下：主文如附表所示之證券無效。訴訟費用由聲請人負擔。理由一、上開證券，經本院以99年度司催字第2689號公示催告。二、所定申報權利期間，已於民國100年2月2日屆滿，迄今無人申報權利。三、依民事訴訟法第564條第1項，判決如主文。中華民國100年3月16日民事第三庭法官郭美杏本判決不得上訴。以上正本證明係照原本作成。中華民國100年3月16日書記官周小玲┌─────────────────────────────────┐│附表：│├──┬─────────┬──────┬─────┬───────┤│編號│發票人│發票日│到期日│金額（新臺幣）│├──┼─────────┼──────┼─────┼───────┤│001│志發企業股份有限公│86年2月17日│未載│8,800,000元│││司陳梅妹、陳梅妹││││││、姜林茂森、姜林茂││││││盛、姜林茂樹││││├──┼─────────┼──────┼─────┼───────┤│002│志發企業股份有限公│86年2月17日│未載│6,000,000元│││司陳梅妹、陳梅妹││││││、姜林茂森、姜林茂││││││盛、姜林茂樹││││└──┴─────────┴──────┴─────┴───────┘",
  "characters": {
    "judges": [
      "郭美杏"
    ],
    "prosecutors": [

    ],
    "lawyers": [

    ],
    "clerks": [
      "周小玲"
    ],
    "plaintiffs": [

    ],
    "defendants": [

    ],
    "prosecutor_office": [
      "上海商業儲蓄銀行股份有限公司"
    ],
    "creditors": [

    ],
    "debtors": [

    ],
    "judicial_associate_officer": [

    ]
  },
  "adjudged_at": "2011-03-16",
  "created_at": "2016-02-13 23:33:02",
  "updated_at": "2016-02-13 23:33:02"
}