{
  "identify": "TPD-94-重訴-147-20050128-1",
  "court": {
    "name": "臺灣臺北地方法院",
    "code": "TPD"
  },
  "division": {
    "name": "民事",
    "code": "V"
  },
  "year": 94,
  "word": "重訴",
  "number": "147",
  "jcheck": "1",
  "reason": "清償債務",
  "content": "臺灣臺北地方法院民事裁定             94年度重訴字第147號\n原      告  中炬實業有限公司\n法定代理人  鄭清華\n被      告  立達工業股份有限公司\n法定代理人  徐陳阿屘\n上列當事人間清償債務事件，本院裁定如下：\n    主  文\n原告之訴及假執行之聲請均駁回。\n訴訟費用由原告負擔。\n    理  由\n一、按提起民事訴訟應依民事訴訟法第77條之13規定繳納裁判費\n    ，此為必須具備之程式。\n二、本件原告起訴，未據繳納裁判費，經本院於民國94年1月3日\n    書面裁定命原告於5日內補繳新台幣302,400元，該項裁定業\n    於94年1月7日送達予原告，有送達回執附卷可參。\n三、原告逾期迄未補正，有本院繳費查詢單附卷可參，其訴顯難\n    認為合法，其假執行聲請亦乏依據，均應予駁回。\n四、依民事訴訟法第249條第1項第6款、第95條、第78條，裁定\n    如主文。\n中    華    民    國    94    年    1     月    28    日\n                  民事第一庭    法  官  呂淑玲\n以上正本係照原本作成\n如不服本裁定應於送達後10日內向本院提出抗告狀，並繳納抗告\n費新臺幣1,000元\n中    華    民    國    94    年    1     月    28    日\n                                書記官  方美雲\n",
  "structure": {
    "main": "原告之訴及假執行之聲請均駁回。\n訴訟費用由原告負擔。",
    "reason": "一、按提起民事訴訟應依民事訴訟法第77條之13規定繳納裁判費\n    ，此為必須具備之程式。\n二、本件原告起訴，未據繳納裁判費，經本院於民國94年1月3日\n    書面裁定命原告於5日內補繳新台幣302,400元，該項裁定業\n    於94年1月7日送達予原告，有送達回執附卷可參。\n三、原告逾期迄未補正，有本院繳費查詢單附卷可參，其訴顯難\n    認為合法，其假執行聲請亦乏依據，均應予駁回。\n四、依民事訴訟法第249條第1項第6款、第95條、第78條，裁定\n    如主文。"
  },
  "search": "臺灣臺北地方法院民事裁定94年度重訴字第147號原告中炬實業有限公司法定代理人鄭清華被告立達工業股份有限公司法定代理人徐陳阿屘上列當事人間清償債務事件，本院裁定如下：主文原告之訴及假執行之聲請均駁回。訴訟費用由原告負擔。理由一、按提起民事訴訟應依民事訴訟法第77條之13規定繳納裁判費，此為必須具備之程式。二、本件原告起訴，未據繳納裁判費，經本院於民國94年1月3日書面裁定命原告於5日內補繳新台幣302,400元，該項裁定業於94年1月7日送達予原告，有送達回執附卷可參。三、原告逾期迄未補正，有本院繳費查詢單附卷可參，其訴顯難認為合法，其假執行聲請亦乏依據，均應予駁回。四、依民事訴訟法第249條第1項第6款、第95條、第78條，裁定如主文。中華民國94年1月28日民事第一庭法官呂淑玲以上正本係照原本作成如不服本裁定應於送達後10日內向本院提出抗告狀，並繳納抗告費新臺幣1,000元中華民國94年1月28日書記官方美雲",
  "characters": {
    "judges": [
      "呂淑玲"
    ],
    "prosecutors": [

    ],
    "lawyers": [

    ],
    "clerks": [
      "方美雲"
    ],
    "plaintiffs": [
      "中炬實業有限公司"
    ],
    "defendants": [
      "立達工業股份有限公司"
    ],
    "prosecutor_office": [

    ],
    "creditors": [

    ],
    "debtors": [

    ],
    "judicial_associate_officer": [

    ]
  },
  "adjudged_at": "2005-01-28",
  "created_at": "2016-02-07 01:38:06",
  "updated_at": "2016-02-07 01:38:06"
}