{
  "identify": "TPD-94-簡-42-20050127-1",
  "court": {
    "name": "臺灣臺北地方法院",
    "code": "TPD"
  },
  "division": {
    "name": "刑事",
    "code": "M"
  },
  "year": 94,
  "word": "簡",
  "number": "42",
  "jcheck": "1",
  "reason": "竊盜",
  "content": "臺灣臺北地方法院刑事簡易判決            94年度簡字第42號\n聲  請  人  臺灣臺北地方法院檢察署檢察官\n被      告  阮氏蘭甲○○○○.\n                    現於外國人收容中心收容中\n上列被告因竊盜案件，經檢察官聲請以簡易判決處刑（93年度速\n偵字第593號），本院判決如下：\n    主  文\n阮氏蘭（甲○○○○○ ○○○ ○○○）竊盜，處有期徒刑伍月，如易科罰金\n，以參佰元折算壹日。\n    事實及理由\n一、本件犯罪事實、證據及所應適用之法條均引用檢察官聲請簡\n    易判決處刑書之記載。並補充犯罪事實部分：被告NGUYEN.T\n    HI.LAM前於民國93年11月20日20時30分許，在臺北市○○區\n    ○○街八十三號前，竊得趁曾瓊瑤背包內皮夾一只（內含新\n    台幣800 元、\n    森釧發現後上前逮捕，並報警查獲，經檢察官於同年11月23\n    日以93年度速偵字第527 號聲請簡易判決處刑，並經本院於\n    同年12月9 日以93年簡字2927號簡易判決判處拘役40日，詎\n    被告不知悔悟，另行起意。證據部分：被告之\n    出境紀錄附卷為憑。\n二、核被告甲○○○○○ ○○○ ○○○（即阮氏蘭）所為係犯刑法第320條\n    第一項之普通竊盜罪。爰審酌被告素行不佳（前有本院於93\n    年12月9日以93年簡字2927號簡易判決依普通竊盜罪判處拘\n    役40天），有臺灣高等法院被告全國前案紀錄表在卷可參，\n    渠以外國人身分假借觀光名義入境我國行竊，得手後揚長而\n    去之手段極其惡劣、經起訴判決後仍不知悛悔再行犯罪，犯\n    罪後坦認犯罪等一切情狀，量處如主文所示之刑，並諭知易\n    科罰金之折算標準，以示懲儆。\n四、應依刑事訴訟法第449條第1項前段、第3項、第454條第二項\n    ，刑法第320條第1項、第41條第1項前段，罰金罰鍰提高標\n    準條例第1條前段、第2條，逕以簡易判決處如主文所示之刑\n    。\n如不服本件判決，得自收受送達之日起十日內，向本院提起上訴。\n中    華    民    國    94    年    1     月     27     日\n                        刑事第四庭法  官  吳定亞\n以上正本證明與原本無異。\n如不服本判決，應於判決送達後十日內，向本院提出上訴狀。\n                                  書記官  張漪蕙\n中    華    民    國    94    年    1     月     27     日\n附錄本案論罪科刑法條全文\n中華民國刑法第320條第1項（普通竊盜罪）\n意圖為自己或第三人不法之所有，而竊取他人之動產者，為竊盜\n罪，處五年以下有期徒刑、拘役或五百元以下罰金。\n",
  "structure": {
    "main": "阮氏蘭（甲○○○○○ ○○○ ○○○）竊盜，處有期徒刑伍月，如易科罰金\n，以參佰元折算壹日。",
    "fact": "一、本件犯罪事實、證據及所應適用之法條均引用檢察官聲請簡\n    易判決處刑書之記載。並補充犯罪事實部分：被告NGUYEN.T\n    HI.LAM前於民國93年11月20日20時30分許，在臺北市○○區\n    ○○街八十三號前，竊得趁曾瓊瑤背包內皮夾一只（內含新\n    台幣800 元、\n    森釧發現後上前逮捕，並報警查獲，經檢察官於同年11月23\n    日以93年度速偵字第527 號聲請簡易判決處刑，並經本院於\n    同年12月9 日以93年簡字2927號簡易判決判處拘役40日，詎\n    被告不知悔悟，另行起意。證據部分：被告之\n    出境紀錄附卷為憑。\n二、核被告甲○○○○○ ○○○ ○○○（即阮氏蘭）所為係犯刑法第320條\n    第一項之普通竊盜罪。爰審酌被告素行不佳（前有本院於93\n    年12月9日以93年簡字2927號簡易判決依普通竊盜罪判處拘\n    役40天），有臺灣高等法院被告全國前案紀錄表在卷可參，\n    渠以外國人身分假借觀光名義入境我國行竊，得手後揚長而\n    去之手段極其惡劣、經起訴判決後仍不知悛悔再行犯罪，犯\n    罪後坦認犯罪等一切情狀，量處如主文所示之刑，並諭知易\n    科罰金之折算標準，以示懲儆。\n四、應依刑事訴訟法第449條第1項前段、第3項、第454條第二項\n    ，刑法第320條第1項、第41條第1項前段，罰金罰鍰提高標\n    準條例第1條前段、第2條，逕以簡易判決處如主文所示之刑\n    。\n如不服本件判決，得自收受送達之日起十日內，向本院提起上訴。",
    "reason": "一、本件犯罪事實、證據及所應適用之法條均引用檢察官聲請簡\n    易判決處刑書之記載。並補充犯罪事實部分：被告NGUYEN.T\n    HI.LAM前於民國93年11月20日20時30分許，在臺北市○○區\n    ○○街八十三號前，竊得趁曾瓊瑤背包內皮夾一只（內含新\n    台幣800 元、\n    森釧發現後上前逮捕，並報警查獲，經檢察官於同年11月23\n    日以93年度速偵字第527 號聲請簡易判決處刑，並經本院於\n    同年12月9 日以93年簡字2927號簡易判決判處拘役40日，詎\n    被告不知悔悟，另行起意。證據部分：被告之\n    出境紀錄附卷為憑。\n二、核被告甲○○○○○ ○○○ ○○○（即阮氏蘭）所為係犯刑法第320條\n    第一項之普通竊盜罪。爰審酌被告素行不佳（前有本院於93\n    年12月9日以93年簡字2927號簡易判決依普通竊盜罪判處拘\n    役40天），有臺灣高等法院被告全國前案紀錄表在卷可參，\n    渠以外國人身分假借觀光名義入境我國行竊，得手後揚長而\n    去之手段極其惡劣、經起訴判決後仍不知悛悔再行犯罪，犯\n    罪後坦認犯罪等一切情狀，量處如主文所示之刑，並諭知易\n    科罰金之折算標準，以示懲儆。\n四、應依刑事訴訟法第449條第1項前段、第3項、第454條第二項\n    ，刑法第320條第1項、第41條第1項前段，罰金罰鍰提高標\n    準條例第1條前段、第2條，逕以簡易判決處如主文所示之刑\n    。\n如不服本件判決，得自收受送達之日起十日內，向本院提起上訴。"
  },
  "search": "臺灣臺北地方法院刑事簡易判決94年度簡字第42號聲請人臺灣臺北地方法院檢察署檢察官被告阮氏蘭甲○○○○.現於外國人收容中心收容中上列被告因竊盜案件，經檢察官聲請以簡易判決處刑（93年度速偵字第593號），本院判決如下：主文阮氏蘭（甲○○○○○○○○○○○）竊盜，處有期徒刑伍月，如易科罰金，以參佰元折算壹日。事實及理由一、本件犯罪事實、證據及所應適用之法條均引用檢察官聲請簡易判決處刑書之記載。並補充犯罪事實部分：被告NGUYEN.THI.LAM前於民國93年11月20日20時30分許，在臺北市○○區○○街八十三號前，竊得趁曾瓊瑤背包內皮夾一只（內含新台幣800元、森釧發現後上前逮捕，並報警查獲，經檢察官於同年11月23日以93年度速偵字第527號聲請簡易判決處刑，並經本院於同年12月9日以93年簡字2927號簡易判決判處拘役40日，詎被告不知悔悟，另行起意。證據部分：被告之出境紀錄附卷為憑。二、核被告甲○○○○○○○○○○○（即阮氏蘭）所為係犯刑法第320條第一項之普通竊盜罪。爰審酌被告素行不佳（前有本院於93年12月9日以93年簡字2927號簡易判決依普通竊盜罪判處拘役40天），有臺灣高等法院被告全國前案紀錄表在卷可參，渠以外國人身分假借觀光名義入境我國行竊，得手後揚長而去之手段極其惡劣、經起訴判決後仍不知悛悔再行犯罪，犯罪後坦認犯罪等一切情狀，量處如主文所示之刑，並諭知易科罰金之折算標準，以示懲儆。四、應依刑事訴訟法第449條第1項前段、第3項、第454條第二項，刑法第320條第1項、第41條第1項前段，罰金罰鍰提高標準條例第1條前段、第2條，逕以簡易判決處如主文所示之刑。如不服本件判決，得自收受送達之日起十日內，向本院提起上訴。中華民國94年1月27日刑事第四庭法官吳定亞以上正本證明與原本無異。如不服本判決，應於判決送達後十日內，向本院提出上訴狀。書記官張漪蕙中華民國94年1月27日附錄本案論罪科刑法條全文中華民國刑法第320條第1項（普通竊盜罪）意圖為自己或第三人不法之所有，而竊取他人之動產者，為竊盜罪，處五年以下有期徒刑、拘役或五百元以下罰金。",
  "characters": {
    "judges": [
      "吳定亞"
    ],
    "prosecutors": [

    ],
    "lawyers": [

    ],
    "clerks": [
      "張漪蕙"
    ],
    "plaintiffs": [

    ],
    "defendants": [
      "阮氏蘭甲○○○○."
    ],
    "prosecutor_office": [
      "臺灣臺北地方法院檢察署檢察官"
    ],
    "creditors": [

    ],
    "debtors": [

    ],
    "judicial_associate_officer": [

    ]
  },
  "adjudged_at": "2005-01-27",
  "created_at": "2016-02-07 01:45:09",
  "updated_at": "2016-02-07 01:45:09"
}