{
  "identify": "TPD-100-簡-3878-20111028-1",
  "court": {
    "name": "臺灣臺北地方法院",
    "code": "TPD"
  },
  "division": {
    "name": "刑事",
    "code": "M"
  },
  "year": 100,
  "word": "簡",
  "number": "3878",
  "jcheck": "1",
  "reason": "賭博",
  "content": "臺灣臺北地方法院刑事簡易判決         100年度簡字第3878號\n聲  請  人  臺灣臺北地方法院檢察署檢察官\n被      告  溫玉枝\n上列被告因賭博案件，經檢察官聲請以簡易判決處刑（100 年度\n速偵字第221 號），本院判決如下：\n    主      文\n溫玉枝意圖營利，聚眾賭博，處有期徒刑月，如易科罰金，以\n新臺幣壹仟元折算壹日。扣案如附表所示之物，均沒收。\n    事實及理由\n一、本件除於聲請簡易判決處刑書犯罪事實欄除補充、更正被告\n    溫玉枝之犯罪時間係「自民國100 年9 月15日起，至100 年\n    9 月22日下午4 時20分許為警查獲時止」，另更正被告意圖\n    營利供給賭博之場所為「臺北市萬華區○○○路36號7 樓之\n    11 」 外。其餘犯罪事實、證據及應適用之法條，均引用檢\n    察官聲請簡易判決處刑書之記載（如附件）。\n二、核被告溫玉枝所為，係犯刑法第268 條前段之意圖營利供給\n    賭博場所及同條後段之意圖營利聚眾賭博罪。按刑事法若干\n    犯罪行為態樣，本質上原具有反覆、延續實行之特徵，立法\n    時既予特別歸類，定為犯罪構成要件之行為要素，則行為人\n    基於概括之犯意，在密切接近之一定時、地持續實行之複次\n    行為，倘依社會通念，於客觀上認為符合一個反覆、延續性\n    之行為觀念者，於刑法評價上，即應僅成立一罪。學理上所\n    稱「集合犯」之職業性、營業性或收集性等具有重複特質之\n    犯罪均屬之，例如經營、從事業務、收集、販賣、製造、散\n    布等行為概念者（最高法院95年度台上字第1079號、95年度\n    台上字第3937號、95年度台上字第4686號判決意旨參照）。\n    被告自100 年9 月15日起至100 年9 月22日下午4 時20分許\n    為警查獲止，反覆提供同一賭博場所供人賭博，且其利用在\n    場不特定賭客賭局偶然之輸贏情形予以抽頭牟利，其顯具有\n    營利之意圖，此種犯罪形態及刑法條文構成要件之內涵，在\n    本質上即具有反覆、延續性行為之特質，揆諸前開說明及社\n    會通念，屬具有預定多數同種類之行為將反覆實行特質之集\n    合犯，應為包括一罪。被告所犯前開二罪，係以一行為而觸\n    犯數罪名，應依刑法第55條前段想像競合犯之規定，依情節\n    較重之刑法第268 條後段之意圖營利，聚眾賭博罪處斷。茲\n    審酌被告為圖己利，而為本件賭博犯行，助長社會不良風氣\n    ，所為非是，惟念及被告犯後坦承犯行，已見悔意，並兼衡\n    被告之品行、智識程度、生活狀況等一切情狀，量處如主文\n    所示之刑，並諭知易科罰金之折算標準。扣案如附表編號1\n    至3 所示之物，均屬被告所有，均係供其犯本件賭博犯罪所\n    用之物，業據被告供承在卷（各見臺灣臺北地方法院檢察署\n    100 年度速偵字第221 號卷第11頁、第60頁），爰依刑法第\n    38條第1 項第2 款之規定宣告沒收；另扣案如附表編號4 所\n    示之物，亦屬被告所有，且為其因本件賭博犯罪所得之物，\n    爰依刑法第38條第1 項第3 款之規定宣告沒收。\n三、據上論斷，應依刑事訴訟法第449 條第2 項、第3 項、第45\n    0 條第1 項、第454 條第2 項，刑法第268 條、第55條前段\n    、第41條第1 項前段、第38條第1 項第2 款、第3 款，刑法\n    施行法第1 條之1 第1 項、第2 項前段，逕以簡易判決處刑\n    如主文。\n四、如不服本判決，應於判決送達後10日內，向本院提出上訴狀\n    （應附繕本），上訴於本院合議庭。\n中    華    民    國   100    年    10    月    28    日\n                  刑事第三庭  法  官  蔡羽玄\n上正本證明與原本無異。\n如不服本判決應於收受送達後10日內向本院提出上訴書狀，並應\n敘述具體理由；其未敘述上訴理由者，應於上訴期間屆滿後20日\n內向本院補提理由書（均須按他造當事人之人數附繕本）「切勿\n逕送上級法院」。\n                              書記官  許博為\n中    華    民    國   100    年    10    月    28    日\n附表：\n┌──┬─────┬──────┐\n│編號│ 扣案物品 │   數量     │\n├──┼─────┼──────┤\n│ 1  │麻將      │1副         │\n├──┼─────┼──────┤\n│ 2  │骰子      │4只         │\n├──┼─────┼──────┤\n│ 3  │牌尺      │4只         │\n├──┼─────┼──────┤\n│ 4  │抽頭金    │新臺幣100 元│\n└──┴─────┴──────┘\n附錄論罪科刑法條：\n刑法第268條\n意圖營利，供給賭博場所或聚眾賭博者，處 3 年以下有期徒刑\n，得併科 3 千元以下罰金。",
  "structure": {
    "main": "溫玉枝意圖營利，聚眾賭博，處有期徒刑月，如易科罰金，以\n新臺幣壹仟元折算壹日。扣案如附表所示之物，均沒收。",
    "fact": "一、本件除於聲請簡易判決處刑書犯罪事實欄除補充、更正被告\n    溫玉枝之犯罪時間係「自民國100 年9 月15日起，至100 年\n    9 月22日下午4 時20分許為警查獲時止」，另更正被告意圖\n    營利供給賭博之場所為「臺北市萬華區○○○路36號7 樓之\n    11 」 外。其餘犯罪事實、證據及應適用之法條，均引用檢\n    察官聲請簡易判決處刑書之記載（如附件）。\n二、核被告溫玉枝所為，係犯刑法第268 條前段之意圖營利供給\n    賭博場所及同條後段之意圖營利聚眾賭博罪。按刑事法若干\n    犯罪行為態樣，本質上原具有反覆、延續實行之特徵，立法\n    時既予特別歸類，定為犯罪構成要件之行為要素，則行為人\n    基於概括之犯意，在密切接近之一定時、地持續實行之複次\n    行為，倘依社會通念，於客觀上認為符合一個反覆、延續性\n    之行為觀念者，於刑法評價上，即應僅成立一罪。學理上所\n    稱「集合犯」之職業性、營業性或收集性等具有重複特質之\n    犯罪均屬之，例如經營、從事業務、收集、販賣、製造、散\n    布等行為概念者（最高法院95年度台上字第1079號、95年度\n    台上字第3937號、95年度台上字第4686號判決意旨參照）。\n    被告自100 年9 月15日起至100 年9 月22日下午4 時20分許\n    為警查獲止，反覆提供同一賭博場所供人賭博，且其利用在\n    場不特定賭客賭局偶然之輸贏情形予以抽頭牟利，其顯具有\n    營利之意圖，此種犯罪形態及刑法條文構成要件之內涵，在\n    本質上即具有反覆、延續性行為之特質，揆諸前開說明及社\n    會通念，屬具有預定多數同種類之行為將反覆實行特質之集\n    合犯，應為包括一罪。被告所犯前開二罪，係以一行為而觸\n    犯數罪名，應依刑法第55條前段想像競合犯之規定，依情節\n    較重之刑法第268 條後段之意圖營利，聚眾賭博罪處斷。茲\n    審酌被告為圖己利，而為本件賭博犯行，助長社會不良風氣\n    ，所為非是，惟念及被告犯後坦承犯行，已見悔意，並兼衡\n    被告之品行、智識程度、生活狀況等一切情狀，量處如主文\n    所示之刑，並諭知易科罰金之折算標準。扣案如附表編號1\n    至3 所示之物，均屬被告所有，均係供其犯本件賭博犯罪所\n    用之物，業據被告供承在卷（各見臺灣臺北地方法院檢察署\n    100 年度速偵字第221 號卷第11頁、第60頁），爰依刑法第\n    38條第1 項第2 款之規定宣告沒收；另扣案如附表編號4 所\n    示之物，亦屬被告所有，且為其因本件賭博犯罪所得之物，\n    爰依刑法第38條第1 項第3 款之規定宣告沒收。\n三、據上論斷，應依刑事訴訟法第449 條第2 項、第3 項、第45\n    0 條第1 項、第454 條第2 項，刑法第268 條、第55條前段\n    、第41條第1 項前段、第38條第1 項第2 款、第3 款，刑法\n    施行法第1 條之1 第1 項、第2 項前段，逕以簡易判決處刑\n    如主文。\n四、如不服本判決，應於判決送達後10日內，向本院提出上訴狀\n    （應附繕本），上訴於本院合議庭。",
    "reason": "一、本件除於聲請簡易判決處刑書犯罪事實欄除補充、更正被告\n    溫玉枝之犯罪時間係「自民國100 年9 月15日起，至100 年\n    9 月22日下午4 時20分許為警查獲時止」，另更正被告意圖\n    營利供給賭博之場所為「臺北市萬華區○○○路36號7 樓之\n    11 」 外。其餘犯罪事實、證據及應適用之法條，均引用檢\n    察官聲請簡易判決處刑書之記載（如附件）。\n二、核被告溫玉枝所為，係犯刑法第268 條前段之意圖營利供給\n    賭博場所及同條後段之意圖營利聚眾賭博罪。按刑事法若干\n    犯罪行為態樣，本質上原具有反覆、延續實行之特徵，立法\n    時既予特別歸類，定為犯罪構成要件之行為要素，則行為人\n    基於概括之犯意，在密切接近之一定時、地持續實行之複次\n    行為，倘依社會通念，於客觀上認為符合一個反覆、延續性\n    之行為觀念者，於刑法評價上，即應僅成立一罪。學理上所\n    稱「集合犯」之職業性、營業性或收集性等具有重複特質之\n    犯罪均屬之，例如經營、從事業務、收集、販賣、製造、散\n    布等行為概念者（最高法院95年度台上字第1079號、95年度\n    台上字第3937號、95年度台上字第4686號判決意旨參照）。\n    被告自100 年9 月15日起至100 年9 月22日下午4 時20分許\n    為警查獲止，反覆提供同一賭博場所供人賭博，且其利用在\n    場不特定賭客賭局偶然之輸贏情形予以抽頭牟利，其顯具有\n    營利之意圖，此種犯罪形態及刑法條文構成要件之內涵，在\n    本質上即具有反覆、延續性行為之特質，揆諸前開說明及社\n    會通念，屬具有預定多數同種類之行為將反覆實行特質之集\n    合犯，應為包括一罪。被告所犯前開二罪，係以一行為而觸\n    犯數罪名，應依刑法第55條前段想像競合犯之規定，依情節\n    較重之刑法第268 條後段之意圖營利，聚眾賭博罪處斷。茲\n    審酌被告為圖己利，而為本件賭博犯行，助長社會不良風氣\n    ，所為非是，惟念及被告犯後坦承犯行，已見悔意，並兼衡\n    被告之品行、智識程度、生活狀況等一切情狀，量處如主文\n    所示之刑，並諭知易科罰金之折算標準。扣案如附表編號1\n    至3 所示之物，均屬被告所有，均係供其犯本件賭博犯罪所\n    用之物，業據被告供承在卷（各見臺灣臺北地方法院檢察署\n    100 年度速偵字第221 號卷第11頁、第60頁），爰依刑法第\n    38條第1 項第2 款之規定宣告沒收；另扣案如附表編號4 所\n    示之物，亦屬被告所有，且為其因本件賭博犯罪所得之物，\n    爰依刑法第38條第1 項第3 款之規定宣告沒收。\n三、據上論斷，應依刑事訴訟法第449 條第2 項、第3 項、第45\n    0 條第1 項、第454 條第2 項，刑法第268 條、第55條前段\n    、第41條第1 項前段、第38條第1 項第2 款、第3 款，刑法\n    施行法第1 條之1 第1 項、第2 項前段，逕以簡易判決處刑\n    如主文。\n四、如不服本判決，應於判決送達後10日內，向本院提出上訴狀\n    （應附繕本），上訴於本院合議庭。"
  },
  "search": "臺灣臺北地方法院刑事簡易判決100年度簡字第3878號聲請人臺灣臺北地方法院檢察署檢察官被告溫玉枝上列被告因賭博案件，經檢察官聲請以簡易判決處刑（100年度速偵字第221號），本院判決如下：主文溫玉枝意圖營利，聚眾賭博，處有期徒刑月，如易科罰金，以新臺幣壹仟元折算壹日。扣案如附表所示之物，均沒收。事實及理由一、本件除於聲請簡易判決處刑書犯罪事實欄除補充、更正被告溫玉枝之犯罪時間係「自民國100年9月15日起，至100年9月22日下午4時20分許為警查獲時止」，另更正被告意圖營利供給賭博之場所為「臺北市萬華區○○○路36號7樓之11」外。其餘犯罪事實、證據及應適用之法條，均引用檢察官聲請簡易判決處刑書之記載（如附件）。二、核被告溫玉枝所為，係犯刑法第268條前段之意圖營利供給賭博場所及同條後段之意圖營利聚眾賭博罪。按刑事法若干犯罪行為態樣，本質上原具有反覆、延續實行之特徵，立法時既予特別歸類，定為犯罪構成要件之行為要素，則行為人基於概括之犯意，在密切接近之一定時、地持續實行之複次行為，倘依社會通念，於客觀上認為符合一個反覆、延續性之行為觀念者，於刑法評價上，即應僅成立一罪。學理上所稱「集合犯」之職業性、營業性或收集性等具有重複特質之犯罪均屬之，例如經營、從事業務、收集、販賣、製造、散布等行為概念者（最高法院95年度台上字第1079號、95年度台上字第3937號、95年度台上字第4686號判決意旨參照）。被告自100年9月15日起至100年9月22日下午4時20分許為警查獲止，反覆提供同一賭博場所供人賭博，且其利用在場不特定賭客賭局偶然之輸贏情形予以抽頭牟利，其顯具有營利之意圖，此種犯罪形態及刑法條文構成要件之內涵，在本質上即具有反覆、延續性行為之特質，揆諸前開說明及社會通念，屬具有預定多數同種類之行為將反覆實行特質之集合犯，應為包括一罪。被告所犯前開二罪，係以一行為而觸犯數罪名，應依刑法第55條前段想像競合犯之規定，依情節較重之刑法第268條後段之意圖營利，聚眾賭博罪處斷。茲審酌被告為圖己利，而為本件賭博犯行，助長社會不良風氣，所為非是，惟念及被告犯後坦承犯行，已見悔意，並兼衡被告之品行、智識程度、生活狀況等一切情狀，量處如主文所示之刑，並諭知易科罰金之折算標準。扣案如附表編號1至3所示之物，均屬被告所有，均係供其犯本件賭博犯罪所用之物，業據被告供承在卷（各見臺灣臺北地方法院檢察署100年度速偵字第221號卷第11頁、第60頁），爰依刑法第38條第1項第2款之規定宣告沒收；另扣案如附表編號4所示之物，亦屬被告所有，且為其因本件賭博犯罪所得之物，爰依刑法第38條第1項第3款之規定宣告沒收。三、據上論斷，應依刑事訴訟法第449條第2項、第3項、第450條第1項、第454條第2項，刑法第268條、第55條前段、第41條第1項前段、第38條第1項第2款、第3款，刑法施行法第1條之1第1項、第2項前段，逕以簡易判決處刑如主文。四、如不服本判決，應於判決送達後10日內，向本院提出上訴狀（應附繕本），上訴於本院合議庭。中華民國100年10月28日刑事第三庭法官蔡羽玄上正本證明與原本無異。如不服本判決應於收受送達後10日內向本院提出上訴書狀，並應敘述具體理由；其未敘述上訴理由者，應於上訴期間屆滿後20日內向本院補提理由書（均須按他造當事人之人數附繕本）「切勿逕送上級法院」。書記官許博為中華民國100年10月28日附表：┌──┬─────┬──────┐│編號│扣案物品│數量│├──┼─────┼──────┤│1│麻將│1副│├──┼─────┼──────┤│2│骰子│4只│├──┼─────┼──────┤│3│牌尺│4只│├──┼─────┼──────┤│4│抽頭金│新臺幣100元│└──┴─────┴──────┘附錄論罪科刑法條：刑法第268條意圖營利，供給賭博場所或聚眾賭博者，處3年以下有期徒刑，得併科3千元以下罰金。",
  "characters": {
    "judges": [
      "蔡羽玄"
    ],
    "prosecutors": [

    ],
    "lawyers": [

    ],
    "clerks": [
      "許博為"
    ],
    "plaintiffs": [

    ],
    "defendants": [
      "溫玉枝"
    ],
    "prosecutor_office": [
      "臺灣臺北地方法院檢察署檢察官"
    ],
    "creditors": [

    ],
    "debtors": [

    ],
    "judicial_associate_officer": [

    ]
  },
  "adjudged_at": "2011-10-28",
  "created_at": "2016-02-14 06:03:46",
  "updated_at": "2016-02-14 06:03:46"
}