{
  "identify": "KLD-100-訴-159-20110426-1",
  "court": {
    "name": "臺灣基隆地方法院",
    "code": "KLD"
  },
  "division": {
    "name": "刑事",
    "code": "M"
  },
  "year": 100,
  "word": "訴",
  "number": "159",
  "jcheck": "1",
  "reason": "毒品危害防制條例",
  "content": "臺灣基隆地方法院刑事判決              100年度訴字第159號\n公  訴  人  臺灣基隆地方法院檢察署檢察官\n被      告  梁淑卿\n上列被告因毒品危害防制條例案件，經檢察官提起公訴（100 年\n度毒偵字第110 號），被告於準備程序進行中，就被訴事實為有\n罪之陳述，經本院合議庭裁定由受命法官獨任進行簡式審判程序\n，判決如下：\n    主  文\n梁淑卿施用第一級毒品，處有期徒刑陸月，如易科罰金，以新台\n幣壹仟元折算壹日。\n    事  實\n一、梁淑卿前因施用第二級毒品甲基安非他命案件，經觀察、勒\n    戒後，認無繼續施用毒品之傾向，於民國99年4 月13日釋放\n    ，並由臺灣士林地方法院檢察署檢察官於99年4 月13日，以\n    99年度毒偵字第138 號為不起訴處分確定。詎猶不知悔改，\n    於上開觀察勒戒釋放後5 年內，復基於施用第一級毒品海洛\n    因之犯意，於99年10月11日中午，在其位於新北市○○區○\n    ○村○○路195 號住處將之前捲摻有海洛因的香煙，點燃吸\n    食之方式，非法施用第一級毒品海洛因1 次。嗣因其係毒品\n    列管人口，經警於上開時間採驗尿液，結果呈嗎啡陽性反應\n    ，始悉上情。\n二、案經新北市政府警察局金山分局報告臺灣基隆地方法院檢察\n    署檢察官偵查起訴。\n    理  由\n一、本件被告所犯者非為死刑、無期徒刑、最輕本刑為3 年以上\n    有期徒刑之罪或高等法院管轄第一審案件，其於準備程序進\n    行中，先就被訴事實為有罪之陳述，經告知其簡式審判程序\n    之旨，並聽取公訴人及被告之意見後，本院依刑事訴訟法第\n    273 條之1 第1 項之規定，裁定由受命法官獨任進行簡式審\n    判程序，且依同法第273 條之2 規定，簡式審判程序之證據\n    調查，不受第159 條第1 項、第161 條之2 、第161 條之3\n    、第163 條之1 及第164 條至第170 條規定之限制，合先敘\n    明。\n二、上開事實，業據被告於本院準備程序及審理時坦承在卷，而\n    被告於上述所示時間、地點為警查獲後採集尿液，呈嗎啡之\n    陽性反應，此有台灣檢驗科技股份有限公司濫用藥物尿液檢\n    驗報告1 份附卷可稽。又其前因施用第二級毒品甲基安非他\n    命案件，經觀察、勒戒後，認無繼續施用毒品之傾向，於民\n    國99年4 月13日釋放，並由臺灣士林地方法院檢察署檢察官\n    於99年4 月13日，以99年度毒偵字第138 號為不起訴處分確\n    定等情，亦有臺灣高等法院被告前案紀錄表附卷足佐。綜上\n    所陳，被告於前次初犯觀察、勒戒於99年4 月13日執行完畢\n    ，5 年內再犯本案施用第一級毒品海洛因，罪證明確，犯行\n    洵堪認定，自應依法論科。\n三、論罪科刑：\n  (一)查海洛因係毒品危害防制條例第2 條第2 項第1 款所定之第\n    一級，核被告所為係犯毒品危害防制條例第10條第1 項之施\n    用第一級毒品罪。被告持有第一級毒品海洛因之低度行為，\n    應為施用第一級毒品之高度行為所吸收，不另論罪。\n  (二)爰審酌被告犯罪之動機、曾有施用毒品之前科仍不知戒除，\n    惟犯罪後坦承犯行，且所犯之施用毒品犯行乃戕害自己身心\n    健康，並未危及他人等一切情狀，量處如主文所示之刑，併\n    諭知易科罰金之折算標準。\n據上論斷，應依刑事訴訟法第273 條之1 第1 項、第299 條第1\n項前段，毒品危害防制條例第10條第1 項、第23條第2 項，刑法\n第11條前段、第41條第1 項前段，判決如主文。\n本案經檢察官翁春鈴到庭執行職務。\n中    華    民    國   100    年    4     月    26    日\n                  刑事第四庭法  官  黃永定\n以上正本證明與原本無異。\n如不服本判決應於收受送達後10日內向本院提出上訴書狀，並應\n敘述具體理由；其未敘述上訴理由者，應於上訴期間屆滿後20日\n內向本院補提理由書（均須按他造當事人之人數附繕本）「切勿\n逕送上級法院」。\n中    華    民    國   100    年    4     月    26    日\n                            書記官  劉珍珍\n附錄本案所犯法條：\n毒品危害防制條例第10條：\n施用第一級毒品者，處 6 月以上 5 年以下有期徒刑。",
  "structure": {
    "main": "梁淑卿施用第一級毒品，處有期徒刑陸月，如易科罰金，以新台\n幣壹仟元折算壹日。",
    "fact": "一、梁淑卿前因施用第二級毒品甲基安非他命案件，經觀察、勒\n    戒後，認無繼續施用毒品之傾向，於民國99年4 月13日釋放\n    ，並由臺灣士林地方法院檢察署檢察官於99年4 月13日，以\n    99年度毒偵字第138 號為不起訴處分確定。詎猶不知悔改，\n    於上開觀察勒戒釋放後5 年內，復基於施用第一級毒品海洛\n    因之犯意，於99年10月11日中午，在其位於新北市○○區○\n    ○村○○路195 號住處將之前捲摻有海洛因的香煙，點燃吸\n    食之方式，非法施用第一級毒品海洛因1 次。嗣因其係毒品\n    列管人口，經警於上開時間採驗尿液，結果呈嗎啡陽性反應\n    ，始悉上情。\n二、案經新北市政府警察局金山分局報告臺灣基隆地方法院檢察\n    署檢察官偵查起訴。",
    "reason": "一、本件被告所犯者非為死刑、無期徒刑、最輕本刑為3 年以上\n    有期徒刑之罪或高等法院管轄第一審案件，其於準備程序進\n    行中，先就被訴事實為有罪之陳述，經告知其簡式審判程序\n    之旨，並聽取公訴人及被告之意見後，本院依刑事訴訟法第\n    273 條之1 第1 項之規定，裁定由受命法官獨任進行簡式審\n    判程序，且依同法第273 條之2 規定，簡式審判程序之證據\n    調查，不受第159 條第1 項、第161 條之2 、第161 條之3\n    、第163 條之1 及第164 條至第170 條規定之限制，合先敘\n    明。\n二、上開事實，業據被告於本院準備程序及審理時坦承在卷，而\n    被告於上述所示時間、地點為警查獲後採集尿液，呈嗎啡之\n    陽性反應，此有台灣檢驗科技股份有限公司濫用藥物尿液檢\n    驗報告1 份附卷可稽。又其前因施用第二級毒品甲基安非他\n    命案件，經觀察、勒戒後，認無繼續施用毒品之傾向，於民\n    國99年4 月13日釋放，並由臺灣士林地方法院檢察署檢察官\n    於99年4 月13日，以99年度毒偵字第138 號為不起訴處分確\n    定等情，亦有臺灣高等法院被告前案紀錄表附卷足佐。綜上\n    所陳，被告於前次初犯觀察、勒戒於99年4 月13日執行完畢\n    ，5 年內再犯本案施用第一級毒品海洛因，罪證明確，犯行\n    洵堪認定，自應依法論科。\n三、論罪科刑：\n  (一)查海洛因係毒品危害防制條例第2 條第2 項第1 款所定之第\n    一級，核被告所為係犯毒品危害防制條例第10條第1 項之施\n    用第一級毒品罪。被告持有第一級毒品海洛因之低度行為，\n    應為施用第一級毒品之高度行為所吸收，不另論罪。\n  (二)爰審酌被告犯罪之動機、曾有施用毒品之前科仍不知戒除，\n    惟犯罪後坦承犯行，且所犯之施用毒品犯行乃戕害自己身心\n    健康，並未危及他人等一切情狀，量處如主文所示之刑，併\n    諭知易科罰金之折算標準。\n據上論斷，應依刑事訴訟法第273 條之1 第1 項、第299 條第1\n項前段，毒品危害防制條例第10條第1 項、第23條第2 項，刑法\n第11條前段、第41條第1 項前段，判決如主文。\n本案經檢察官翁春鈴到庭執行職務。\n中    華    民    國   100    年    4     月    26    日\n                  刑事第四庭法  官  黃永定\n以上正本證明與原本無異。\n如不服本判決應於收受送達後10日內向本院提出上訴書狀，並應\n敘述具體理由；其未敘述上訴理由者，應於上訴期間屆滿後20日\n內向本院補提理由書（均須按他造當事人之人數附繕本）「切勿\n逕送上級法院」。"
  },
  "search": "臺灣基隆地方法院刑事判決100年度訴字第159號公訴人臺灣基隆地方法院檢察署檢察官被告梁淑卿上列被告因毒品危害防制條例案件，經檢察官提起公訴（100年度毒偵字第110號），被告於準備程序進行中，就被訴事實為有罪之陳述，經本院合議庭裁定由受命法官獨任進行簡式審判程序，判決如下：主文梁淑卿施用第一級毒品，處有期徒刑陸月，如易科罰金，以新台幣壹仟元折算壹日。事實一、梁淑卿前因施用第二級毒品甲基安非他命案件，經觀察、勒戒後，認無繼續施用毒品之傾向，於民國99年4月13日釋放，並由臺灣士林地方法院檢察署檢察官於99年4月13日，以99年度毒偵字第138號為不起訴處分確定。詎猶不知悔改，於上開觀察勒戒釋放後5年內，復基於施用第一級毒品海洛因之犯意，於99年10月11日中午，在其位於新北市○○區○○村○○路195號住處將之前捲摻有海洛因的香煙，點燃吸食之方式，非法施用第一級毒品海洛因1次。嗣因其係毒品列管人口，經警於上開時間採驗尿液，結果呈嗎啡陽性反應，始悉上情。二、案經新北市政府警察局金山分局報告臺灣基隆地方法院檢察署檢察官偵查起訴。理由一、本件被告所犯者非為死刑、無期徒刑、最輕本刑為3年以上有期徒刑之罪或高等法院管轄第一審案件，其於準備程序進行中，先就被訴事實為有罪之陳述，經告知其簡式審判程序之旨，並聽取公訴人及被告之意見後，本院依刑事訴訟法第273條之1第1項之規定，裁定由受命法官獨任進行簡式審判程序，且依同法第273條之2規定，簡式審判程序之證據調查，不受第159條第1項、第161條之2、第161條之3、第163條之1及第164條至第170條規定之限制，合先敘明。二、上開事實，業據被告於本院準備程序及審理時坦承在卷，而被告於上述所示時間、地點為警查獲後採集尿液，呈嗎啡之陽性反應，此有台灣檢驗科技股份有限公司濫用藥物尿液檢驗報告1份附卷可稽。又其前因施用第二級毒品甲基安非他命案件，經觀察、勒戒後，認無繼續施用毒品之傾向，於民國99年4月13日釋放，並由臺灣士林地方法院檢察署檢察官於99年4月13日，以99年度毒偵字第138號為不起訴處分確定等情，亦有臺灣高等法院被告前案紀錄表附卷足佐。綜上所陳，被告於前次初犯觀察、勒戒於99年4月13日執行完畢，5年內再犯本案施用第一級毒品海洛因，罪證明確，犯行洵堪認定，自應依法論科。三、論罪科刑：(一)查海洛因係毒品危害防制條例第2條第2項第1款所定之第一級，核被告所為係犯毒品危害防制條例第10條第1項之施用第一級毒品罪。被告持有第一級毒品海洛因之低度行為，應為施用第一級毒品之高度行為所吸收，不另論罪。(二)爰審酌被告犯罪之動機、曾有施用毒品之前科仍不知戒除，惟犯罪後坦承犯行，且所犯之施用毒品犯行乃戕害自己身心健康，並未危及他人等一切情狀，量處如主文所示之刑，併諭知易科罰金之折算標準。據上論斷，應依刑事訴訟法第273條之1第1項、第299條第1項前段，毒品危害防制條例第10條第1項、第23條第2項，刑法第11條前段、第41條第1項前段，判決如主文。本案經檢察官翁春鈴到庭執行職務。中華民國100年4月26日刑事第四庭法官黃永定以上正本證明與原本無異。如不服本判決應於收受送達後10日內向本院提出上訴書狀，並應敘述具體理由；其未敘述上訴理由者，應於上訴期間屆滿後20日內向本院補提理由書（均須按他造當事人之人數附繕本）「切勿逕送上級法院」。中華民國100年4月26日書記官劉珍珍附錄本案所犯法條：毒品危害防制條例第10條：施用第一級毒品者，處6月以上5年以下有期徒刑。",
  "characters": {
    "judges": [
      "黃永定"
    ],
    "prosecutors": [
      "翁春鈴"
    ],
    "lawyers": [

    ],
    "clerks": [
      "劉珍珍"
    ],
    "plaintiffs": [

    ],
    "defendants": [
      "梁淑卿"
    ],
    "prosecutor_office": [
      "臺灣基隆地方法院檢察署檢察官"
    ],
    "creditors": [

    ],
    "debtors": [

    ],
    "judicial_associate_officer": [

    ]
  },
  "adjudged_at": "2011-04-26",
  "created_at": "2016-02-12 10:06:51",
  "updated_at": "2016-02-12 10:06:51"
}