{
  "identify": "PCD-100-易-1220-20110425-1",
  "court": {
    "name": "臺灣新北地方法院",
    "code": "PCD"
  },
  "division": {
    "name": "刑事",
    "code": "M"
  },
  "year": 100,
  "word": "易",
  "number": "1220",
  "jcheck": "1",
  "reason": "妨害名譽",
  "content": "臺灣板橋地方法院刑事判決             100年度易字第1220號\n公  訴  人  臺灣板橋地方法院檢察署檢察官\n被      告  黃義芳\n上列被告因妨害名譽案件，經檢察官聲請以簡易判決處刑（99年\n度偵字第31644 號），本院認不得以簡易判決處刑（原案號：10\n0 年度簡字第2010號），改依通常程序判決如下：\n    主  文\n本件公訴不受理。\n    理  由\n一、聲請簡易判決處刑意旨略稱：被告黃義芳係告訴人黃月昭之\n    小叔，因不滿告訴人之子黃永騰檢舉其臺北縣三峽鎮（現改\n    制為新北市三峽區○○○街223 號住處之鐵皮屋係違章建築\n    ，竟意圖散布於眾，基於妨害名譽之犯意，於民國99年11月\n    15日8 時許，將載有「黃永騰的媽媽月昭四嫂…你兒子要報\n    你三伯我們沒話說，但大嫂以前為你夫妻作保你才能取得一\n    千萬元，你錢收到手，以此方法對大嫂對嗎？…還有你小妹\n    一直看精神科看不好，不是我解結（應為「決」之誤）的嗎\n    ？」等語之宣傳單，散發予告訴人所居住，位於臺北縣板橋\n    市（現改制為新北市板橋區）自強新村82號2 樓社區之1 、\n    3 、4 樓鄰居，足以毀損告訴人名譽。因認被告涉犯刑法第\n    310 條第2 項之加重誹謗罪嫌等語。\n二、按告訴乃論之罪，告訴人於第一審辯論終結前得撤回其告訴\n    ；又告訴經撤回者，應諭知不受理之判決，且該判決得不經\n    言詞辯論，刑事訴訟法第238 條第1 項、第303 條第3 款及\n    第307條分別定有明文。\n三、本件被告黃義芳被訴妨害名譽案件，聲請簡易判決處刑書認\n    被告係觸犯刑法第310 條第2 項之加重誹謗罪嫌，而依同法\n    第314 條之規定，須告訴乃論。茲據告訴人黃月昭具狀撤回\n    告訴乙節，此有聲請撤回刑事告訴狀1 紙在卷可證，揆諸上\n    開法條及說明，爰不經言詞辯論，逕為不受理判決之諭知。\n據上論斷，應依刑事訴訟法第452 條、第303 條第3 款、第307\n條，判決如主文。\n中    華    民    國    100   年    4     月    25    日\n            刑事第二十二庭  審判長法  官  潘長生\n                                  法  官  許映鈞\n                                  法  官  陳苑文\n上列正本證明與原本無異。\n如不服本判決，應於判決送達後10日內敘明上訴理由，向本院提\n出上訴狀 (應附繕本) ，上訴於臺灣高等法院。其未敘述上訴理\n由者，應於上訴期間屆滿後20日內向本院補提理由書「切勿逕送\n上級法院」。\n                                  書記官  張玫玲\n中    華    民    國    100   年    4     月    25    日",
  "structure": {
    "main": "本件公訴不受理。",
    "reason": "一、聲請簡易判決處刑意旨略稱：被告黃義芳係告訴人黃月昭之\n    小叔，因不滿告訴人之子黃永騰檢舉其臺北縣三峽鎮（現改\n    制為新北市三峽區○○○街223 號住處之鐵皮屋係違章建築\n    ，竟意圖散布於眾，基於妨害名譽之犯意，於民國99年11月\n    15日8 時許，將載有「黃永騰的媽媽月昭四嫂…你兒子要報\n    你三伯我們沒話說，但大嫂以前為你夫妻作保你才能取得一\n    千萬元，你錢收到手，以此方法對大嫂對嗎？…還有你小妹\n    一直看精神科看不好，不是我解結（應為「決」之誤）的嗎\n    ？」等語之宣傳單，散發予告訴人所居住，位於臺北縣板橋\n    市（現改制為新北市板橋區）自強新村82號2 樓社區之1 、\n    3 、4 樓鄰居，足以毀損告訴人名譽。因認被告涉犯刑法第\n    310 條第2 項之加重誹謗罪嫌等語。\n二、按告訴乃論之罪，告訴人於第一審辯論終結前得撤回其告訴\n    ；又告訴經撤回者，應諭知不受理之判決，且該判決得不經\n    言詞辯論，刑事訴訟法第238 條第1 項、第303 條第3 款及\n    第307條分別定有明文。\n三、本件被告黃義芳被訴妨害名譽案件，聲請簡易判決處刑書認\n    被告係觸犯刑法第310 條第2 項之加重誹謗罪嫌，而依同法\n    第314 條之規定，須告訴乃論。茲據告訴人黃月昭具狀撤回\n    告訴乙節，此有聲請撤回刑事告訴狀1 紙在卷可證，揆諸上\n    開法條及說明，爰不經言詞辯論，逕為不受理判決之諭知。\n據上論斷，應依刑事訴訟法第452 條、第303 條第3 款、第307\n條，判決如主文。"
  },
  "search": "臺灣板橋地方法院刑事判決100年度易字第1220號公訴人臺灣板橋地方法院檢察署檢察官被告黃義芳上列被告因妨害名譽案件，經檢察官聲請以簡易判決處刑（99年度偵字第31644號），本院認不得以簡易判決處刑（原案號：100年度簡字第2010號），改依通常程序判決如下：主文本件公訴不受理。理由一、聲請簡易判決處刑意旨略稱：被告黃義芳係告訴人黃月昭之小叔，因不滿告訴人之子黃永騰檢舉其臺北縣三峽鎮（現改制為新北市三峽區○○○街223號住處之鐵皮屋係違章建築，竟意圖散布於眾，基於妨害名譽之犯意，於民國99年11月15日8時許，將載有「黃永騰的媽媽月昭四嫂…你兒子要報你三伯我們沒話說，但大嫂以前為你夫妻作保你才能取得一千萬元，你錢收到手，以此方法對大嫂對嗎？…還有你小妹一直看精神科看不好，不是我解結（應為「決」之誤）的嗎？」等語之宣傳單，散發予告訴人所居住，位於臺北縣板橋市（現改制為新北市板橋區）自強新村82號2樓社區之1、3、4樓鄰居，足以毀損告訴人名譽。因認被告涉犯刑法第310條第2項之加重誹謗罪嫌等語。二、按告訴乃論之罪，告訴人於第一審辯論終結前得撤回其告訴；又告訴經撤回者，應諭知不受理之判決，且該判決得不經言詞辯論，刑事訴訟法第238條第1項、第303條第3款及第307條分別定有明文。三、本件被告黃義芳被訴妨害名譽案件，聲請簡易判決處刑書認被告係觸犯刑法第310條第2項之加重誹謗罪嫌，而依同法第314條之規定，須告訴乃論。茲據告訴人黃月昭具狀撤回告訴乙節，此有聲請撤回刑事告訴狀1紙在卷可證，揆諸上開法條及說明，爰不經言詞辯論，逕為不受理判決之諭知。據上論斷，應依刑事訴訟法第452條、第303條第3款、第307條，判決如主文。中華民國100年4月25日刑事第二十二庭審判長法官潘長生法官許映鈞法官陳苑文上列正本證明與原本無異。如不服本判決，應於判決送達後10日內敘明上訴理由，向本院提出上訴狀(應附繕本)，上訴於臺灣高等法院。其未敘述上訴理由者，應於上訴期間屆滿後20日內向本院補提理由書「切勿逕送上級法院」。書記官張玫玲中華民國100年4月25日",
  "characters": {
    "judges": [
      "潘長生",
      "許映鈞",
      "陳苑文"
    ],
    "prosecutors": [

    ],
    "lawyers": [

    ],
    "clerks": [
      "張玫玲"
    ],
    "plaintiffs": [

    ],
    "defendants": [
      "黃義芳"
    ],
    "prosecutor_office": [
      "臺灣板橋地方法院檢察署檢察官"
    ],
    "creditors": [

    ],
    "debtors": [

    ],
    "judicial_associate_officer": [

    ]
  },
  "adjudged_at": "2011-04-25",
  "created_at": "2016-02-12 10:21:54",
  "updated_at": "2016-02-12 10:21:54"
}