{
  "identify": "SCD-100-審易緝-2-20110426-1",
  "court": {
    "name": "臺灣新竹地方法院",
    "code": "SCD"
  },
  "division": {
    "name": "刑事",
    "code": "M"
  },
  "year": 100,
  "word": "審易緝",
  "number": "2",
  "jcheck": "1",
  "reason": "違反毒品危害防制條例",
  "content": "臺灣新竹地方法院刑事宣示判決筆錄    100年度審易緝字第2號\n公  訴  人  臺灣新竹地方法院檢察署檢察官\n被      告  楊芷畇\n上列被告因違反毒品危害防制條例案件，檢察官提起公訴（99年\n度毒偵字第1172號）後，聲請改依協商程序而為判決，本院於中\n華民國100 年4 月26日下午4 時，在本院刑事第十一法庭宣示判\n決，出席職員如下：\n                審判長法  官  劉兆菊\n                      書記官  林兆嘉\n                      通  譯  邱立杰\n法官起立朗讀判決主文、犯罪事實要旨、處罰條文，及告以上訴\n限制、期間並提出上訴狀之法院，且諭知記載其內容：\n一、主  文：\n    楊芷畇施用第二級毒品，累犯，處有期徒刑陸月；如易科罰\n    金，以新臺幣壹仟元折算壹日。\n二、犯罪事實要旨：\n（一）楊芷畇前於民國94年間，因施用第二級毒品案件，經本院\n      於94年10月17日以94年度毒聲字第421 號裁定送觀察、勒\n      戒後，認無繼續施用毒品之傾向，於94年12月12日執行完\n      畢釋放出所，並經臺灣新竹地方法院檢察署檢察官於95年\n      2 月14日以94年度核退毒偵字第54號為不起訴處分確定；\n      又於96年間，因施用第二級毒品案件，經本院於96年10月\n      25日以96年度竹簡字第1244號判決判處有期徒刑3 月，減\n      為有期徒刑1 月又15日確定，於97年1 月2 日易科罰金執\n      行完畢；另於97年間，因施用第二級毒品案件，經本院於\n      97年8 月8 日以97年度竹簡字第974 號判決判處有期徒刑\n      3 月，於98年1月8日易科罰金執行完畢。\n（二）詎楊芷畇仍不知悔改，於前開觀察、勒戒執行完畢釋放後\n      5 年內，復基於施用第二級毒品甲基安非他命之犯意，於\n      99年5 月29日晚間某不詳時間，在新竹市○○路○段105\n      號今彩釣蝦場之廁所內，以將第二級毒品甲基安非他命置\n      於玻璃球吸食器（未扣案）內燒烤後吸取煙霧之方式，非\n      法施用第二級毒品甲基安非他命1 次。嗣於同日早上9 時\n      42分許，為警在上址內查獲；復經楊芷畇同意採集其尿液\n      送驗，結果呈安非他命、甲基安非他命之類陽性反應，始\n      悉上情。\n（三）案經新竹市警察局第一分局報告臺灣新竹地方法院檢察署\n      檢察官偵查起訴後，經檢察官聲請認罪協商判決。\n三、處罰條文：\n    毒品危害防制條例第10條第2項，刑法第11條前段、第47條\n    第1項、第41條第1項前段、第2項。\n四、協商判決除有刑事訴訟法第455條之4第1項第1款於本訊問程\n    序終結前，被告撤銷協商合意或檢察官撤回協商聲請者；第\n    2款被告協商之意思非出於自由意志者；第4款被告所犯之罪\n    非第455條之2第1項所定得以協商判決者；第6款被告有其他\n    較重之裁判上一罪之犯罪事實者；第7 款法院認應諭知免刑\n    或免訴、不受理者情形之一，及違反同條第2 項「法院應於\n    協商合意範圍內為判決；法院為協商判決所科之刑，以宣告\n    緩刑或2 年以下有期徒刑、拘役或罰金為限」之規定者外，\n    檢察官與被告均不得上訴。\n五、如有前項得上訴之情形，得自收受宣示判決筆錄送達之日起\n    10日內，向本院提出上訴書狀，上訴於第二審法院。\n本案經檢察官洪期榮到庭執行職務。\n中    華    民    國    100    年    4    月     26   日\n                  刑事第九庭    書  記  官  林兆嘉\n                                審判長法官  劉兆菊\n以上筆錄正本係照原本作成。\n中    華    民    國    100    年    4    月     26   日\n                                書  記  官  廖宜君\n附錄本案論罪科刑法條全文：\n毒品危害防制條例第10條\n施用第一級毒品者，處6月以上5年以下有期徒刑。\n施用第二級毒品者，處3年以下有期徒刑。",
  "structure": {
  },
  "search": "臺灣新竹地方法院刑事宣示判決筆錄100年度審易緝字第2號公訴人臺灣新竹地方法院檢察署檢察官被告楊芷畇上列被告因違反毒品危害防制條例案件，檢察官提起公訴（99年度毒偵字第1172號）後，聲請改依協商程序而為判決，本院於中華民國100年4月26日下午4時，在本院刑事第十一法庭宣示判決，出席職員如下：審判長法官劉兆菊書記官林兆嘉通譯邱立杰法官起立朗讀判決主文、犯罪事實要旨、處罰條文，及告以上訴限制、期間並提出上訴狀之法院，且諭知記載其內容：一、主文：楊芷畇施用第二級毒品，累犯，處有期徒刑陸月；如易科罰金，以新臺幣壹仟元折算壹日。二、犯罪事實要旨：（一）楊芷畇前於民國94年間，因施用第二級毒品案件，經本院於94年10月17日以94年度毒聲字第421號裁定送觀察、勒戒後，認無繼續施用毒品之傾向，於94年12月12日執行完畢釋放出所，並經臺灣新竹地方法院檢察署檢察官於95年2月14日以94年度核退毒偵字第54號為不起訴處分確定；又於96年間，因施用第二級毒品案件，經本院於96年10月25日以96年度竹簡字第1244號判決判處有期徒刑3月，減為有期徒刑1月又15日確定，於97年1月2日易科罰金執行完畢；另於97年間，因施用第二級毒品案件，經本院於97年8月8日以97年度竹簡字第974號判決判處有期徒刑3月，於98年1月8日易科罰金執行完畢。（二）詎楊芷畇仍不知悔改，於前開觀察、勒戒執行完畢釋放後5年內，復基於施用第二級毒品甲基安非他命之犯意，於99年5月29日晚間某不詳時間，在新竹市○○路○段105號今彩釣蝦場之廁所內，以將第二級毒品甲基安非他命置於玻璃球吸食器（未扣案）內燒烤後吸取煙霧之方式，非法施用第二級毒品甲基安非他命1次。嗣於同日早上9時42分許，為警在上址內查獲；復經楊芷畇同意採集其尿液送驗，結果呈安非他命、甲基安非他命之類陽性反應，始悉上情。（三）案經新竹市警察局第一分局報告臺灣新竹地方法院檢察署檢察官偵查起訴後，經檢察官聲請認罪協商判決。三、處罰條文：毒品危害防制條例第10條第2項，刑法第11條前段、第47條第1項、第41條第1項前段、第2項。四、協商判決除有刑事訴訟法第455條之4第1項第1款於本訊問程序終結前，被告撤銷協商合意或檢察官撤回協商聲請者；第2款被告協商之意思非出於自由意志者；第4款被告所犯之罪非第455條之2第1項所定得以協商判決者；第6款被告有其他較重之裁判上一罪之犯罪事實者；第7款法院認應諭知免刑或免訴、不受理者情形之一，及違反同條第2項「法院應於協商合意範圍內為判決；法院為協商判決所科之刑，以宣告緩刑或2年以下有期徒刑、拘役或罰金為限」之規定者外，檢察官與被告均不得上訴。五、如有前項得上訴之情形，得自收受宣示判決筆錄送達之日起10日內，向本院提出上訴書狀，上訴於第二審法院。本案經檢察官洪期榮到庭執行職務。中華民國100年4月26日刑事第九庭書記官林兆嘉審判長法官劉兆菊以上筆錄正本係照原本作成。中華民國100年4月26日書記官廖宜君附錄本案論罪科刑法條全文：毒品危害防制條例第10條施用第一級毒品者，處6月以上5年以下有期徒刑。施用第二級毒品者，處3年以下有期徒刑。",
  "characters": {
    "judges": [
      "劉兆菊"
    ],
    "prosecutors": [
      "洪期榮"
    ],
    "lawyers": [

    ],
    "clerks": [
      "林兆嘉"
    ],
    "plaintiffs": [

    ],
    "defendants": [
      "楊芷畇"
    ],
    "prosecutor_office": [
      "臺灣新竹地方法院檢察署檢察官"
    ],
    "creditors": [

    ],
    "debtors": [

    ],
    "judicial_associate_officer": [

    ]
  },
  "adjudged_at": "2011-04-26",
  "created_at": "2016-02-12 10:19:17",
  "updated_at": "2016-02-12 10:19:17"
}