{
  "identify": "KSD-91-簡-207-20020927-1",
  "court": {
    "name": "臺灣高雄地方法院",
    "code": "KSD"
  },
  "division": {
    "name": "刑事",
    "code": "M"
  },
  "year": 91,
  "word": "簡",
  "number": "207",
  "jcheck": "1",
  "reason": "詐欺",
  "content": "臺灣高雄地方法院刑事簡易判決                      九十一年度簡字第二七號\n    聲  請  人  臺灣高雄地方法院檢察署檢察官\n    被      告  甲○○\n右列被告因詐欺案件，經檢察官聲請以簡易判決處刑（九十一年度偵字一六六二八號\n），本院判決如左：\n    主  文\n甲○○意圖為自己不法之所有，以詐術使人將本人之物交付，處有期徒刑月，如易\n科罰金以佰元折算壹日，緩刑貳年。\n    事實及理由\n一、本件犯罪事實及證據均引用檢察官聲請簡易判決處刑書之記載（如附件）。\n二、爰審酌被告於偵查中業已返還詐欺所得之溢領金額新台幣二萬七千五百元，有勞\n    工保險局回函在卷可按，顯見被告於犯後知悉所犯，深具悔意，參以其詐騙金額\n    非詎等一切情狀，量處如主文所示之刑。又刑法第四十一條業已於九十年一月十\n    日修正公布，並於同年月十二日生效，其第一項前段規定為「犯最重本刑為五年\n    以下有期徒刑以下之刑之罪，而受六個月以下有期徒刑或拘役之宣告，因身體、\n    教育、職業、家庭之關係或其他正當事由，執行顯有困難者，得以一元以上三元\n    以下折算一日，易科罰金。」本件被告犯罪時間雖在上開條文修正生效前，然依\n    刑法第二條第一項前段規定，行為後法律有變更者，應適用裁判時之法律，故依\n    前開之規定，就被告所宣告之刑，併依修正後刑法第四十一條第一項前段諭知易\n    科罰金之折算標準。末查被告未曾受有期徒刑以上刑之宣告，有臺灣高等法院被\n    告全國全國前案紀錄表一紙在卷可查，被告因一時貪圖小利，致罹刑典，犯罪情\n    節亦屬輕微，經此偵審程序及科刑之宣告，當知所警惕，信無再犯之虞，本院因\n    認所宣告之刑以暫不執行為適當，爰併諭知緩刑二年，以啟自新。\n三、依刑事訴訟法第四百四十九條第一項前段、第四百五十四條第二項，刑法第二條\n    第一項前段、第三百三十九條第一項、第四十一條第一項、第七十四條第一款，\n    罰金罰鍰提高標準條例第一條前段、第二條，逕以簡易判決處如主文所示之刑。\n中      華      民      國      九十一      年      九    月    二十七  日\n                                  臺灣高雄地方法院高雄簡易庭\n                                      法  官    官信成\n右正本證明與原本無異。\n如不服本判決，得於判決書送達之翌日起十日內，以書狀敘述理由，向本庭提出上訴\n。\n                                      書記官    黃意雯\n中    華    民    國      九十一      年      十       月      一       日\n附錄本判決論罪之法條：\n刑法第三百三十九條第一項：\n意圖為自己或第三人不法之所有，以詐術使人將本人或第三人之物交付者，處五年以\n下有期徒刑、拘役或科或併科一千元以下罰金。\n",
  "structure": {
    "main": "甲○○意圖為自己不法之所有，以詐術使人將本人之物交付，處有期徒刑月，如易\n科罰金以佰元折算壹日，緩刑貳年。",
    "fact": "一、本件犯罪事實及證據均引用檢察官聲請簡易判決處刑書之記載（如附件）。\n二、爰審酌被告於偵查中業已返還詐欺所得之溢領金額新台幣二萬七千五百元，有勞\n    工保險局回函在卷可按，顯見被告於犯後知悉所犯，深具悔意，參以其詐騙金額\n    非詎等一切情狀，量處如主文所示之刑。又刑法第四十一條業已於九十年一月十\n    日修正公布，並於同年月十二日生效，其第一項前段規定為「犯最重本刑為五年\n    以下有期徒刑以下之刑之罪，而受六個月以下有期徒刑或拘役之宣告，因身體、\n    教育、職業、家庭之關係或其他正當事由，執行顯有困難者，得以一元以上三元\n    以下折算一日，易科罰金。」本件被告犯罪時間雖在上開條文修正生效前，然依\n    刑法第二條第一項前段規定，行為後法律有變更者，應適用裁判時之法律，故依\n    前開之規定，就被告所宣告之刑，併依修正後刑法第四十一條第一項前段諭知易\n    科罰金之折算標準。末查被告未曾受有期徒刑以上刑之宣告，有臺灣高等法院被\n    告全國全國前案紀錄表一紙在卷可查，被告因一時貪圖小利，致罹刑典，犯罪情\n    節亦屬輕微，經此偵審程序及科刑之宣告，當知所警惕，信無再犯之虞，本院因\n    認所宣告之刑以暫不執行為適當，爰併諭知緩刑二年，以啟自新。\n三、依刑事訴訟法第四百四十九條第一項前段、第四百五十四條第二項，刑法第二條\n    第一項前段、第三百三十九條第一項、第四十一條第一項、第七十四條第一款，\n    罰金罰鍰提高標準條例第一條前段、第二條，逕以簡易判決處如主文所示之刑。",
    "reason": "一、本件犯罪事實及證據均引用檢察官聲請簡易判決處刑書之記載（如附件）。\n二、爰審酌被告於偵查中業已返還詐欺所得之溢領金額新台幣二萬七千五百元，有勞\n    工保險局回函在卷可按，顯見被告於犯後知悉所犯，深具悔意，參以其詐騙金額\n    非詎等一切情狀，量處如主文所示之刑。又刑法第四十一條業已於九十年一月十\n    日修正公布，並於同年月十二日生效，其第一項前段規定為「犯最重本刑為五年\n    以下有期徒刑以下之刑之罪，而受六個月以下有期徒刑或拘役之宣告，因身體、\n    教育、職業、家庭之關係或其他正當事由，執行顯有困難者，得以一元以上三元\n    以下折算一日，易科罰金。」本件被告犯罪時間雖在上開條文修正生效前，然依\n    刑法第二條第一項前段規定，行為後法律有變更者，應適用裁判時之法律，故依\n    前開之規定，就被告所宣告之刑，併依修正後刑法第四十一條第一項前段諭知易\n    科罰金之折算標準。末查被告未曾受有期徒刑以上刑之宣告，有臺灣高等法院被\n    告全國全國前案紀錄表一紙在卷可查，被告因一時貪圖小利，致罹刑典，犯罪情\n    節亦屬輕微，經此偵審程序及科刑之宣告，當知所警惕，信無再犯之虞，本院因\n    認所宣告之刑以暫不執行為適當，爰併諭知緩刑二年，以啟自新。\n三、依刑事訴訟法第四百四十九條第一項前段、第四百五十四條第二項，刑法第二條\n    第一項前段、第三百三十九條第一項、第四十一條第一項、第七十四條第一款，\n    罰金罰鍰提高標準條例第一條前段、第二條，逕以簡易判決處如主文所示之刑。"
  },
  "search": "臺灣高雄地方法院刑事簡易判決九十一年度簡字第二七號聲請人臺灣高雄地方法院檢察署檢察官被告甲○○右列被告因詐欺案件，經檢察官聲請以簡易判決處刑（九十一年度偵字一六六二八號），本院判決如左：主文甲○○意圖為自己不法之所有，以詐術使人將本人之物交付，處有期徒刑月，如易科罰金以佰元折算壹日，緩刑貳年。事實及理由一、本件犯罪事實及證據均引用檢察官聲請簡易判決處刑書之記載（如附件）。二、爰審酌被告於偵查中業已返還詐欺所得之溢領金額新台幣二萬七千五百元，有勞工保險局回函在卷可按，顯見被告於犯後知悉所犯，深具悔意，參以其詐騙金額非詎等一切情狀，量處如主文所示之刑。又刑法第四十一條業已於九十年一月十日修正公布，並於同年月十二日生效，其第一項前段規定為「犯最重本刑為五年以下有期徒刑以下之刑之罪，而受六個月以下有期徒刑或拘役之宣告，因身體、教育、職業、家庭之關係或其他正當事由，執行顯有困難者，得以一元以上三元以下折算一日，易科罰金。」本件被告犯罪時間雖在上開條文修正生效前，然依刑法第二條第一項前段規定，行為後法律有變更者，應適用裁判時之法律，故依前開之規定，就被告所宣告之刑，併依修正後刑法第四十一條第一項前段諭知易科罰金之折算標準。末查被告未曾受有期徒刑以上刑之宣告，有臺灣高等法院被告全國全國前案紀錄表一紙在卷可查，被告因一時貪圖小利，致罹刑典，犯罪情節亦屬輕微，經此偵審程序及科刑之宣告，當知所警惕，信無再犯之虞，本院因認所宣告之刑以暫不執行為適當，爰併諭知緩刑二年，以啟自新。三、依刑事訴訟法第四百四十九條第一項前段、第四百五十四條第二項，刑法第二條第一項前段、第三百三十九條第一項、第四十一條第一項、第七十四條第一款，罰金罰鍰提高標準條例第一條前段、第二條，逕以簡易判決處如主文所示之刑。中華民國九十一年九月二十七日臺灣高雄地方法院高雄簡易庭法官官信成右正本證明與原本無異。如不服本判決，得於判決書送達之翌日起十日內，以書狀敘述理由，向本庭提出上訴。書記官黃意雯中華民國九十一年十月一日附錄本判決論罪之法條：刑法第三百三十九條第一項：意圖為自己或第三人不法之所有，以詐術使人將本人或第三人之物交付者，處五年以下有期徒刑、拘役或科或併科一千元以下罰金。",
  "characters": {
    "judges": [
      "官信成"
    ],
    "prosecutors": [

    ],
    "lawyers": [

    ],
    "clerks": [
      "黃意雯"
    ],
    "plaintiffs": [

    ],
    "defendants": [
      "甲○○",
      "右列被告因詐欺案件，經檢察官聲請以簡易判決處刑（九十一年度偵字一六六二八號",
      "），本院判決如左："
    ],
    "prosecutor_office": [
      "臺灣高雄地方法院檢察署檢察官"
    ],
    "creditors": [

    ],
    "debtors": [

    ],
    "judicial_associate_officer": [

    ]
  },
  "adjudged_at": "2002-09-27",
  "created_at": "2016-02-04 17:16:58",
  "updated_at": "2016-02-04 17:16:58"
}