{
  "identify": "KSD-100-簡-4687-20110922-1",
  "court": {
    "name": "臺灣高雄地方法院",
    "code": "KSD"
  },
  "division": {
    "name": "刑事",
    "code": "M"
  },
  "year": 100,
  "word": "簡",
  "number": "4687",
  "jcheck": "1",
  "reason": "竊盜",
  "content": "臺灣高雄地方法院刑事簡易判決         100年度簡字第4687號\n聲  請  人  臺灣高雄地方法院檢察署檢察官\n被      告  蘇進財\n上列被告因竊盜案件，經檢察官聲請依簡易判決處刑（100年度\n偵字第19588號），本院判決如下：\n    主      文\n蘇進財犯竊盜罪，處有期徒刑貳月，如易科罰金，以新臺幣壹仟\n元折算壹日。\n    事實及理由\n一、本件犯罪事實及證據，除犯罪事實欄一、第1行補充「蘇進\n    財係瘖啞人」；證據並所犯法條欄一、第2行「被害人陳永\n    順於警詢中所述其有遭竊大西瓜一情相符」補充為「證人即\n    被害人陳永順於警詢中所示其有遭竊大西瓜一情相符」，證\n    據部分並補充「高雄市旗津區公所99年7月23日高市旗區社\n    福字第0990005601號函暨函附之身心障礙人口基本資料表、\n    中華民國身心障礙手冊影本各1紙」外，餘均引用附件檢察\n    官聲請簡易判決處刑書之記載。\n二、核被告蘇進財所為，係犯刑法第320 條第1 項之普通竊盜罪\n    。再按瘖啞人之行為，得減輕其刑，刑法第20條定有明文。\n    經查，被告於警詢及檢察官詢問程序中，均須透過通譯人員\n    以手語方式傳達詢問及訊問內容及代為表達其回答，有警詢\n    筆錄（見警卷第2頁、第5頁）及臺灣高雄地方法院檢察署檢\n    察官100年6月28日訊問筆錄(見偵卷第7、8頁)各1 份附卷可\n    憑，又被告於民國79年12月4日經鑑定為中度聽障乙情，經\n    本院調閱99年度審簡字第2260號卷查核屬實，並有卷附中華\n    民國身心障礙手冊1紙以及高雄市旗津區公所99年7月23日高\n    市旗區社福字第0990005601號函暨函附之身心障礙人口基本\n    資料表各1份可憑，依前開說明，足認被告為自幼瘖啞之瘖\n    啞人無疑，爰依刑法第20條之規定，減輕其刑。爰審酌被告\n    不思以正當途徑賺取所需，率爾竊取他人財物，侵害他人之\n    財產權，所為實屬不該，惟念其犯後坦承犯行，且所竊之物\n    價值尚非鉅大，並已由被害人領回，有贓物認領保管單在卷\n    可稽（警卷第15頁），被害人所受損害已有減輕，兼衡其犯\n    罪動機、目的、情節、品行、生活狀況、智識程度等一切情\n    狀，量處如主文所示之刑，並諭知易科罰金之折算標準，以\n    資懲儆。\n三、依刑事訴訟法第449 條第1 項前段、第3 項、第454 條第2\n    項，刑法第320 條第1 項、第20條、第41條第1 項前段，刑\n    法施行法第1 條之1 第1 項、第2 項前段，逕以簡易判決處\n    刑如主文。\n四、如不服本判決，得自收受送達之日起10日內，向本院提起上\n    訴。\n中    華    民    國  100    年    9    月    22    日\n                  高雄簡易庭    法  官  陳奕帆\n以上正本證明與原本無異。\n如不服本判決，應於判決送達之日起10日內向本院提出上訴書狀\n。\n中    華    民    國  100    年    9    月    22    日\n                                書記官  張義龍\n附錄本判決論罪之法條：\n中華民國刑法第320條\n（普通竊盜罪、竊佔罪）\n意圖為自己或第三人不法之所有，而竊取他人之動產者，為竊盜\n罪，處 5 年以下有期徒刑、拘役或 5 百元以下罰金。\n意圖為自己或第三人不法之利益，而竊佔他人之不動產者，依前\n項之規定處斷。\n前二項之未遂犯罰之。\n附件：\n臺灣高雄地方法院檢察署檢察官聲請簡易判決處刑書\n                                    100年度偵字第19588號\n    被      告  蘇進財  男  50歲（民國○○年○月○○日生）\n                        住高雄市旗津區○○○路513巷2號\n                        國民身分證統一編號：Ｚ000000000號\n上列被告因竊盜案件，業經偵查終結，認為宜聲請以簡易判決處\n刑，茲將犯罪事實及證據並所犯法條分敘如下：\n            犯罪事實\n一、蘇進財於民國100年6月27日4時6分許，騎乘腳踏車行經高雄\n    市○○區○○路70號前時，見陳永順所經營之水果攤位旁之\n    塑膠箱內置有大西瓜，因其無錢購買，又欲讓家人有大西瓜\n    可食用，竟意圖為自己不法之所有，基於竊盜之犯意，徒手\n    自該塑膠箱內竊取大西瓜1顆（售價約新臺幣400元），放在\n    所騎腳踏車後方之塑膠籃子裡，再騎腳踏車將該顆大西瓜載\n    回其位於高雄市旗津區○○○路513巷2號，以此方式竊取陳\n    永順所有之大西瓜1顆得逞。嗣陳永順於當日上午前往上開\n    水果攤準備營業時，發現塑膠箱內之大西瓜遭竊，遂報警處\n    理，經原警調閱設置在附近之監視器所錄得之影像始循線查\n    悉上情，並在蘇進財上開住處內扣得尚未食用之大西瓜1顆\n    。\n二、案經高雄市政府警察局鼓山分局報告偵辦。\n            證據並所犯法條\n一、上揭犯罪事實業據被告蘇進財於警詢及偵查中坦承不諱，核\n    與被害人陳永順於警詢中所述其有遭竊大西瓜一情相符，此\n    外，復有高雄市政府警察局鼓山分局扣押筆錄、扣押物品目\n    錄表、扣押現場照片、監視器錄得畫面列印照片及贓物認領\n    保管單等在卷可稽，被告犯行堪以認定。\n二、核被告所為，係犯刑法第320條第1項之竊盜罪嫌。至於報告\n    意旨雖認被告係竊得2顆大西瓜云云，然被告辯稱僅竊得1顆\n    ，且員警於當日上午10時50分前往被告住處查緝時，僅在屋\n    內查獲大西瓜1顆，又依監視器錄得影像印列照片所示，被\n    告所騎腳踏車後方之塑膠籃僅載有1顆大西瓜而已，故被害\n    人報案時雖指稱係遭竊2顆大西瓜，然恐係被害人清點錯誤\n    或另遭他人竊取，難認係被告所為，併此敘明。\n三、依刑事訴訟法第451條第1項聲請逕以簡易判決處刑。\n      此    致\n臺灣高雄地方法院\n中    華    民    國   100    年    7     月    25    日\n                          檢  察  官    李  廷  輝\n參考法條：\n中華民國刑法第320條（普通竊盜罪、竊佔罪）\n意圖為自己或第三人不法之所有，而竊取他人之動產者，為竊盜\n罪，處5年以下有期徒刑、拘役或5百元以下罰金。\n意圖為自己或第三人不法之利益，而竊佔他人之不動產者，依前\n項之規定處斷。\n前二項之未遂犯罰之。",
  "structure": {
    "main": "蘇進財犯竊盜罪，處有期徒刑貳月，如易科罰金，以新臺幣壹仟\n元折算壹日。",
    "fact": "一、本件犯罪事實及證據，除犯罪事實欄一、第1行補充「蘇進\n    財係瘖啞人」；證據並所犯法條欄一、第2行「被害人陳永\n    順於警詢中所述其有遭竊大西瓜一情相符」補充為「證人即\n    被害人陳永順於警詢中所示其有遭竊大西瓜一情相符」，證\n    據部分並補充「高雄市旗津區公所99年7月23日高市旗區社\n    福字第0990005601號函暨函附之身心障礙人口基本資料表、\n    中華民國身心障礙手冊影本各1紙」外，餘均引用附件檢察\n    官聲請簡易判決處刑書之記載。\n二、核被告蘇進財所為，係犯刑法第320 條第1 項之普通竊盜罪\n    。再按瘖啞人之行為，得減輕其刑，刑法第20條定有明文。\n    經查，被告於警詢及檢察官詢問程序中，均須透過通譯人員\n    以手語方式傳達詢問及訊問內容及代為表達其回答，有警詢\n    筆錄（見警卷第2頁、第5頁）及臺灣高雄地方法院檢察署檢\n    察官100年6月28日訊問筆錄(見偵卷第7、8頁)各1 份附卷可\n    憑，又被告於民國79年12月4日經鑑定為中度聽障乙情，經\n    本院調閱99年度審簡字第2260號卷查核屬實，並有卷附中華\n    民國身心障礙手冊1紙以及高雄市旗津區公所99年7月23日高\n    市旗區社福字第0990005601號函暨函附之身心障礙人口基本\n    資料表各1份可憑，依前開說明，足認被告為自幼瘖啞之瘖\n    啞人無疑，爰依刑法第20條之規定，減輕其刑。爰審酌被告\n    不思以正當途徑賺取所需，率爾竊取他人財物，侵害他人之\n    財產權，所為實屬不該，惟念其犯後坦承犯行，且所竊之物\n    價值尚非鉅大，並已由被害人領回，有贓物認領保管單在卷\n    可稽（警卷第15頁），被害人所受損害已有減輕，兼衡其犯\n    罪動機、目的、情節、品行、生活狀況、智識程度等一切情\n    狀，量處如主文所示之刑，並諭知易科罰金之折算標準，以\n    資懲儆。\n三、依刑事訴訟法第449 條第1 項前段、第3 項、第454 條第2\n    項，刑法第320 條第1 項、第20條、第41條第1 項前段，刑\n    法施行法第1 條之1 第1 項、第2 項前段，逕以簡易判決處\n    刑如主文。\n四、如不服本判決，得自收受送達之日起10日內，向本院提起上\n    訴。",
    "reason": "一、本件犯罪事實及證據，除犯罪事實欄一、第1行補充「蘇進\n    財係瘖啞人」；證據並所犯法條欄一、第2行「被害人陳永\n    順於警詢中所述其有遭竊大西瓜一情相符」補充為「證人即\n    被害人陳永順於警詢中所示其有遭竊大西瓜一情相符」，證\n    據部分並補充「高雄市旗津區公所99年7月23日高市旗區社\n    福字第0990005601號函暨函附之身心障礙人口基本資料表、\n    中華民國身心障礙手冊影本各1紙」外，餘均引用附件檢察\n    官聲請簡易判決處刑書之記載。\n二、核被告蘇進財所為，係犯刑法第320 條第1 項之普通竊盜罪\n    。再按瘖啞人之行為，得減輕其刑，刑法第20條定有明文。\n    經查，被告於警詢及檢察官詢問程序中，均須透過通譯人員\n    以手語方式傳達詢問及訊問內容及代為表達其回答，有警詢\n    筆錄（見警卷第2頁、第5頁）及臺灣高雄地方法院檢察署檢\n    察官100年6月28日訊問筆錄(見偵卷第7、8頁)各1 份附卷可\n    憑，又被告於民國79年12月4日經鑑定為中度聽障乙情，經\n    本院調閱99年度審簡字第2260號卷查核屬實，並有卷附中華\n    民國身心障礙手冊1紙以及高雄市旗津區公所99年7月23日高\n    市旗區社福字第0990005601號函暨函附之身心障礙人口基本\n    資料表各1份可憑，依前開說明，足認被告為自幼瘖啞之瘖\n    啞人無疑，爰依刑法第20條之規定，減輕其刑。爰審酌被告\n    不思以正當途徑賺取所需，率爾竊取他人財物，侵害他人之\n    財產權，所為實屬不該，惟念其犯後坦承犯行，且所竊之物\n    價值尚非鉅大，並已由被害人領回，有贓物認領保管單在卷\n    可稽（警卷第15頁），被害人所受損害已有減輕，兼衡其犯\n    罪動機、目的、情節、品行、生活狀況、智識程度等一切情\n    狀，量處如主文所示之刑，並諭知易科罰金之折算標準，以\n    資懲儆。\n三、依刑事訴訟法第449 條第1 項前段、第3 項、第454 條第2\n    項，刑法第320 條第1 項、第20條、第41條第1 項前段，刑\n    法施行法第1 條之1 第1 項、第2 項前段，逕以簡易判決處\n    刑如主文。\n四、如不服本判決，得自收受送達之日起10日內，向本院提起上\n    訴。"
  },
  "search": "臺灣高雄地方法院刑事簡易判決100年度簡字第4687號聲請人臺灣高雄地方法院檢察署檢察官被告蘇進財上列被告因竊盜案件，經檢察官聲請依簡易判決處刑（100年度偵字第19588號），本院判決如下：主文蘇進財犯竊盜罪，處有期徒刑貳月，如易科罰金，以新臺幣壹仟元折算壹日。事實及理由一、本件犯罪事實及證據，除犯罪事實欄一、第1行補充「蘇進財係瘖啞人」；證據並所犯法條欄一、第2行「被害人陳永順於警詢中所述其有遭竊大西瓜一情相符」補充為「證人即被害人陳永順於警詢中所示其有遭竊大西瓜一情相符」，證據部分並補充「高雄市旗津區公所99年7月23日高市旗區社福字第0990005601號函暨函附之身心障礙人口基本資料表、中華民國身心障礙手冊影本各1紙」外，餘均引用附件檢察官聲請簡易判決處刑書之記載。二、核被告蘇進財所為，係犯刑法第320條第1項之普通竊盜罪。再按瘖啞人之行為，得減輕其刑，刑法第20條定有明文。經查，被告於警詢及檢察官詢問程序中，均須透過通譯人員以手語方式傳達詢問及訊問內容及代為表達其回答，有警詢筆錄（見警卷第2頁、第5頁）及臺灣高雄地方法院檢察署檢察官100年6月28日訊問筆錄(見偵卷第7、8頁)各1份附卷可憑，又被告於民國79年12月4日經鑑定為中度聽障乙情，經本院調閱99年度審簡字第2260號卷查核屬實，並有卷附中華民國身心障礙手冊1紙以及高雄市旗津區公所99年7月23日高市旗區社福字第0990005601號函暨函附之身心障礙人口基本資料表各1份可憑，依前開說明，足認被告為自幼瘖啞之瘖啞人無疑，爰依刑法第20條之規定，減輕其刑。爰審酌被告不思以正當途徑賺取所需，率爾竊取他人財物，侵害他人之財產權，所為實屬不該，惟念其犯後坦承犯行，且所竊之物價值尚非鉅大，並已由被害人領回，有贓物認領保管單在卷可稽（警卷第15頁），被害人所受損害已有減輕，兼衡其犯罪動機、目的、情節、品行、生活狀況、智識程度等一切情狀，量處如主文所示之刑，並諭知易科罰金之折算標準，以資懲儆。三、依刑事訴訟法第449條第1項前段、第3項、第454條第2項，刑法第320條第1項、第20條、第41條第1項前段，刑法施行法第1條之1第1項、第2項前段，逕以簡易判決處刑如主文。四、如不服本判決，得自收受送達之日起10日內，向本院提起上訴。中華民國100年9月22日高雄簡易庭法官陳奕帆以上正本證明與原本無異。如不服本判決，應於判決送達之日起10日內向本院提出上訴書狀。中華民國100年9月22日書記官張義龍附錄本判決論罪之法條：中華民國刑法第320條（普通竊盜罪、竊佔罪）意圖為自己或第三人不法之所有，而竊取他人之動產者，為竊盜罪，處5年以下有期徒刑、拘役或5百元以下罰金。意圖為自己或第三人不法之利益，而竊佔他人之不動產者，依前項之規定處斷。前二項之未遂犯罰之。附件：臺灣高雄地方法院檢察署檢察官聲請簡易判決處刑書100年度偵字第19588號被告蘇進財男50歲（民國○○年○月○○日生）住高雄市旗津區○○○路513巷2號國民身分證統一編號：Ｚ000000000號上列被告因竊盜案件，業經偵查終結，認為宜聲請以簡易判決處刑，茲將犯罪事實及證據並所犯法條分敘如下：犯罪事實一、蘇進財於民國100年6月27日4時6分許，騎乘腳踏車行經高雄市○○區○○路70號前時，見陳永順所經營之水果攤位旁之塑膠箱內置有大西瓜，因其無錢購買，又欲讓家人有大西瓜可食用，竟意圖為自己不法之所有，基於竊盜之犯意，徒手自該塑膠箱內竊取大西瓜1顆（售價約新臺幣400元），放在所騎腳踏車後方之塑膠籃子裡，再騎腳踏車將該顆大西瓜載回其位於高雄市旗津區○○○路513巷2號，以此方式竊取陳永順所有之大西瓜1顆得逞。嗣陳永順於當日上午前往上開水果攤準備營業時，發現塑膠箱內之大西瓜遭竊，遂報警處理，經原警調閱設置在附近之監視器所錄得之影像始循線查悉上情，並在蘇進財上開住處內扣得尚未食用之大西瓜1顆。二、案經高雄市政府警察局鼓山分局報告偵辦。證據並所犯法條一、上揭犯罪事實業據被告蘇進財於警詢及偵查中坦承不諱，核與被害人陳永順於警詢中所述其有遭竊大西瓜一情相符，此外，復有高雄市政府警察局鼓山分局扣押筆錄、扣押物品目錄表、扣押現場照片、監視器錄得畫面列印照片及贓物認領保管單等在卷可稽，被告犯行堪以認定。二、核被告所為，係犯刑法第320條第1項之竊盜罪嫌。至於報告意旨雖認被告係竊得2顆大西瓜云云，然被告辯稱僅竊得1顆，且員警於當日上午10時50分前往被告住處查緝時，僅在屋內查獲大西瓜1顆，又依監視器錄得影像印列照片所示，被告所騎腳踏車後方之塑膠籃僅載有1顆大西瓜而已，故被害人報案時雖指稱係遭竊2顆大西瓜，然恐係被害人清點錯誤或另遭他人竊取，難認係被告所為，併此敘明。三、依刑事訴訟法第451條第1項聲請逕以簡易判決處刑。此致臺灣高雄地方法院中華民國100年7月25日檢察官李廷輝參考法條：中華民國刑法第320條（普通竊盜罪、竊佔罪）意圖為自己或第三人不法之所有，而竊取他人之動產者，為竊盜罪，處5年以下有期徒刑、拘役或5百元以下罰金。意圖為自己或第三人不法之利益，而竊佔他人之不動產者，依前項之規定處斷。前二項之未遂犯罰之。",
  "characters": {
    "judges": [
      "陳奕帆"
    ],
    "prosecutors": [

    ],
    "lawyers": [

    ],
    "clerks": [
      "張義龍"
    ],
    "plaintiffs": [

    ],
    "defendants": [
      "蘇進財",
      "蘇進財  男  50歲（民國○○年○月○○日生）"
    ],
    "prosecutor_office": [
      "臺灣高雄地方法院檢察署檢察官"
    ],
    "creditors": [

    ],
    "debtors": [

    ],
    "judicial_associate_officer": [

    ]
  },
  "adjudged_at": "2011-09-22",
  "created_at": "2016-02-12 15:11:00",
  "updated_at": "2016-02-12 15:11:00"
}