{
  "identify": "TPD-93-簡-2199-20041012-1",
  "court": {
    "name": "臺灣臺北地方法院",
    "code": "TPD"
  },
  "division": {
    "name": "刑事",
    "code": "M"
  },
  "year": 93,
  "word": "簡",
  "number": "2199",
  "jcheck": "1",
  "reason": "竊盜",
  "content": "臺灣臺北地方法院刑事簡易判決                九十三年度簡字第二一九九號\n    聲  請  人  臺灣臺北地方法院檢察署檢察官\n    被      告  乙○○\n右列被告因竊盜案件，經檢察官聲請以簡易判決處刑（九十三年度速偵字第三一○號\n），本院判決如左：\n    主      文\n乙○○竊盜，處罰金壹仟元，如易服勞役，以參佰元折算壹日。\n    事實及理由\n一、乙○○無犯罪前科。乙○○於民國九十三年八月十二日下午，進入台北市○○區\n    ○○路九號新光百貨三館地下二樓內遊逛，於當日下午三時許，竟意圖為自己不\n    法之所有，竊取「法雅客股份有限公司」所屬專櫃店內貨架陳列擺售之「拉普人\n    之歌─瑪麗．波依娜演唱」音樂ＣＤ一片（販售價格新台幣三百九十九元），並\n    將竊盜得手之音樂ＣＤ藏放在所攜帶之側背包內，而於當日下午三時十二分許乙\n    ○○企圖避開防盜偵測器而步出賣場時，因乙○○上開行逕已為「法雅客股份有\n    限公司」駐現場員工甲○○發覺，見乙○○未至櫃台結帳乃上前攔下乙○○並通\n    知台北市政府警察局信義分局三張犁派出所警員到場處理，到場處理警員自乙○\n    ○側背包內搜出「拉普人之歌─瑪麗．波依娜演唱」音樂ＣＤ一片，遂將乙○○\n    帶回三張犁派出所處理。案經台北市政府警察局信義分局報請台灣台北地方法院\n    檢察署檢察官偵查後聲請簡易判決處刑。\n二、右揭犯罪事實，業據被告乙○○於警方調查及檢察官偵查時坦承不諱，核與證人\n    即「法雅客股份有限公司」店員甲○○於警詢中證述之情節相符，並有贓物認領\n    保管單一紙及贓證照片四張在卷可稽。綜上所述，本件事證明確，被告犯行堪以\n    認定，應予依法論科。\n三、核被告所為係犯刑法第三百二十條第一項之竊盜罪。爰審酌被告無犯罪前科，素\n    行良好（有台灣台北地方法院檢察署刑案資料查註記錄表、台灣高等法院被告全\n    國前案紀錄表足稽）、惟正值壯年，卻不思以己力正當謀生，竟為貪圖不法利益\n    ，竊取他人財物、所竊取之物品價值尚非甚高，犯後態度等一切情狀，量處如主\n    文所示之刑，並諭知易服勞役之折算標準。\n四、依刑事訴訟法第四百四十九條第一項前段、第三項，刑法第三百二十條第一項、\n    第四十二條第二項，罰金罰鍰提高標準條例第一條前段、第二條，逕以簡易判決\n    處刑如主文。\n五、如不服本判決，應於判決送達後十日內，向本院提出上訴狀。\n中      華      民      國    九十三    年      十      月     十二     日\n                                  臺灣臺北地方法院刑事第一庭\n                                      法  官  林婷立\n右正本證明與原本無異。\n                                      書記官  葉志昭\n中      華      民      國    九十三    年      十      月     十二     日\n附錄論罪科刑法條\n刑法第三百二十條\n意圖為自己或第三人不法之所有，而竊取他人之動產者，為竊盜罪，處五年以下有期\n徒刑、拘役或五百元以下罰金。\n意圖為自己或第三人不法之利益，而竊佔他人之不動產者，依前項之規定處斷。\n前二項之未遂犯罰之。\n",
  "structure": {
    "main": "乙○○竊盜，處罰金壹仟元，如易服勞役，以參佰元折算壹日。",
    "fact": "一、乙○○無犯罪前科。乙○○於民國九十三年八月十二日下午，進入台北市○○區\n    ○○路九號新光百貨三館地下二樓內遊逛，於當日下午三時許，竟意圖為自己不\n    法之所有，竊取「法雅客股份有限公司」所屬專櫃店內貨架陳列擺售之「拉普人\n    之歌─瑪麗．波依娜演唱」音樂ＣＤ一片（販售價格新台幣三百九十九元），並\n    將竊盜得手之音樂ＣＤ藏放在所攜帶之側背包內，而於當日下午三時十二分許乙\n    ○○企圖避開防盜偵測器而步出賣場時，因乙○○上開行逕已為「法雅客股份有\n    限公司」駐現場員工甲○○發覺，見乙○○未至櫃台結帳乃上前攔下乙○○並通\n    知台北市政府警察局信義分局三張犁派出所警員到場處理，到場處理警員自乙○\n    ○側背包內搜出「拉普人之歌─瑪麗．波依娜演唱」音樂ＣＤ一片，遂將乙○○\n    帶回三張犁派出所處理。案經台北市政府警察局信義分局報請台灣台北地方法院\n    檢察署檢察官偵查後聲請簡易判決處刑。\n二、右揭犯罪事實，業據被告乙○○於警方調查及檢察官偵查時坦承不諱，核與證人\n    即「法雅客股份有限公司」店員甲○○於警詢中證述之情節相符，並有贓物認領\n    保管單一紙及贓證照片四張在卷可稽。綜上所述，本件事證明確，被告犯行堪以\n    認定，應予依法論科。\n三、核被告所為係犯刑法第三百二十條第一項之竊盜罪。爰審酌被告無犯罪前科，素\n    行良好（有台灣台北地方法院檢察署刑案資料查註記錄表、台灣高等法院被告全\n    國前案紀錄表足稽）、惟正值壯年，卻不思以己力正當謀生，竟為貪圖不法利益\n    ，竊取他人財物、所竊取之物品價值尚非甚高，犯後態度等一切情狀，量處如主\n    文所示之刑，並諭知易服勞役之折算標準。\n四、依刑事訴訟法第四百四十九條第一項前段、第三項，刑法第三百二十條第一項、\n    第四十二條第二項，罰金罰鍰提高標準條例第一條前段、第二條，逕以簡易判決\n    處刑如主文。\n五、如不服本判決，應於判決送達後十日內，向本院提出上訴狀。",
    "reason": "一、乙○○無犯罪前科。乙○○於民國九十三年八月十二日下午，進入台北市○○區\n    ○○路九號新光百貨三館地下二樓內遊逛，於當日下午三時許，竟意圖為自己不\n    法之所有，竊取「法雅客股份有限公司」所屬專櫃店內貨架陳列擺售之「拉普人\n    之歌─瑪麗．波依娜演唱」音樂ＣＤ一片（販售價格新台幣三百九十九元），並\n    將竊盜得手之音樂ＣＤ藏放在所攜帶之側背包內，而於當日下午三時十二分許乙\n    ○○企圖避開防盜偵測器而步出賣場時，因乙○○上開行逕已為「法雅客股份有\n    限公司」駐現場員工甲○○發覺，見乙○○未至櫃台結帳乃上前攔下乙○○並通\n    知台北市政府警察局信義分局三張犁派出所警員到場處理，到場處理警員自乙○\n    ○側背包內搜出「拉普人之歌─瑪麗．波依娜演唱」音樂ＣＤ一片，遂將乙○○\n    帶回三張犁派出所處理。案經台北市政府警察局信義分局報請台灣台北地方法院\n    檢察署檢察官偵查後聲請簡易判決處刑。\n二、右揭犯罪事實，業據被告乙○○於警方調查及檢察官偵查時坦承不諱，核與證人\n    即「法雅客股份有限公司」店員甲○○於警詢中證述之情節相符，並有贓物認領\n    保管單一紙及贓證照片四張在卷可稽。綜上所述，本件事證明確，被告犯行堪以\n    認定，應予依法論科。\n三、核被告所為係犯刑法第三百二十條第一項之竊盜罪。爰審酌被告無犯罪前科，素\n    行良好（有台灣台北地方法院檢察署刑案資料查註記錄表、台灣高等法院被告全\n    國前案紀錄表足稽）、惟正值壯年，卻不思以己力正當謀生，竟為貪圖不法利益\n    ，竊取他人財物、所竊取之物品價值尚非甚高，犯後態度等一切情狀，量處如主\n    文所示之刑，並諭知易服勞役之折算標準。\n四、依刑事訴訟法第四百四十九條第一項前段、第三項，刑法第三百二十條第一項、\n    第四十二條第二項，罰金罰鍰提高標準條例第一條前段、第二條，逕以簡易判決\n    處刑如主文。\n五、如不服本判決，應於判決送達後十日內，向本院提出上訴狀。"
  },
  "search": "臺灣臺北地方法院刑事簡易判決九十三年度簡字第二一九九號聲請人臺灣臺北地方法院檢察署檢察官被告乙○○右列被告因竊盜案件，經檢察官聲請以簡易判決處刑（九十三年度速偵字第三一○號），本院判決如左：主文乙○○竊盜，處罰金壹仟元，如易服勞役，以參佰元折算壹日。事實及理由一、乙○○無犯罪前科。乙○○於民國九十三年八月十二日下午，進入台北市○○區○○路九號新光百貨三館地下二樓內遊逛，於當日下午三時許，竟意圖為自己不法之所有，竊取「法雅客股份有限公司」所屬專櫃店內貨架陳列擺售之「拉普人之歌─瑪麗．波依娜演唱」音樂ＣＤ一片（販售價格新台幣三百九十九元），並將竊盜得手之音樂ＣＤ藏放在所攜帶之側背包內，而於當日下午三時十二分許乙○○企圖避開防盜偵測器而步出賣場時，因乙○○上開行逕已為「法雅客股份有限公司」駐現場員工甲○○發覺，見乙○○未至櫃台結帳乃上前攔下乙○○並通知台北市政府警察局信義分局三張犁派出所警員到場處理，到場處理警員自乙○○側背包內搜出「拉普人之歌─瑪麗．波依娜演唱」音樂ＣＤ一片，遂將乙○○帶回三張犁派出所處理。案經台北市政府警察局信義分局報請台灣台北地方法院檢察署檢察官偵查後聲請簡易判決處刑。二、右揭犯罪事實，業據被告乙○○於警方調查及檢察官偵查時坦承不諱，核與證人即「法雅客股份有限公司」店員甲○○於警詢中證述之情節相符，並有贓物認領保管單一紙及贓證照片四張在卷可稽。綜上所述，本件事證明確，被告犯行堪以認定，應予依法論科。三、核被告所為係犯刑法第三百二十條第一項之竊盜罪。爰審酌被告無犯罪前科，素行良好（有台灣台北地方法院檢察署刑案資料查註記錄表、台灣高等法院被告全國前案紀錄表足稽）、惟正值壯年，卻不思以己力正當謀生，竟為貪圖不法利益，竊取他人財物、所竊取之物品價值尚非甚高，犯後態度等一切情狀，量處如主文所示之刑，並諭知易服勞役之折算標準。四、依刑事訴訟法第四百四十九條第一項前段、第三項，刑法第三百二十條第一項、第四十二條第二項，罰金罰鍰提高標準條例第一條前段、第二條，逕以簡易判決處刑如主文。五、如不服本判決，應於判決送達後十日內，向本院提出上訴狀。中華民國九十三年十月十二日臺灣臺北地方法院刑事第一庭法官林婷立右正本證明與原本無異。書記官葉志昭中華民國九十三年十月十二日附錄論罪科刑法條刑法第三百二十條意圖為自己或第三人不法之所有，而竊取他人之動產者，為竊盜罪，處五年以下有期徒刑、拘役或五百元以下罰金。意圖為自己或第三人不法之利益，而竊佔他人之不動產者，依前項之規定處斷。前二項之未遂犯罰之。",
  "characters": {
    "judges": [
      "林婷立"
    ],
    "prosecutors": [

    ],
    "lawyers": [

    ],
    "clerks": [
      "葉志昭"
    ],
    "plaintiffs": [

    ],
    "defendants": [
      "乙○○",
      "右列被告因竊盜案件，經檢察官聲請以簡易判決處刑（九十三年度速偵字第三一○號",
      "），本院判決如左："
    ],
    "prosecutor_office": [
      "臺灣臺北地方法院檢察署檢察官"
    ],
    "creditors": [

    ],
    "debtors": [

    ],
    "judicial_associate_officer": [

    ]
  },
  "adjudged_at": "2004-10-12",
  "created_at": "2016-02-06 13:51:21",
  "updated_at": "2016-02-06 13:51:21"
}