{
  "identify": "SLD-94-簡-458-20051209-1",
  "court": {
    "name": "臺灣士林地方法院",
    "code": "SLD"
  },
  "division": {
    "name": "刑事",
    "code": "M"
  },
  "year": 94,
  "word": "簡",
  "number": "458",
  "jcheck": "1",
  "reason": "賭博",
  "content": "臺灣士林地方法院刑事簡易判決           94年度簡字第458號\n聲  請  人  臺灣士林地方法院檢察署檢察官\n被      告  甲○○\n上列被告因賭博案件，經檢察官聲請以簡易判決處刑（94年度偵\n字第7841號），本院士林簡易庭認為不宜以簡易判決處刑，改由\n本院依通常程序審理，而被告於準備程序中自白犯罪，經合議庭\n裁定由受命法官獨任逕以簡易判決處刑，並判決如下：\n        主  文\n甲○○在公眾得出入之場所賭博財物，處罰金貳佰元，如易服勞\n役，以佰元折算壹日。當場賭博之器具電子遊戲機肆臺（野蠻\n遊戲機及金歡禧景品販賣機各貳臺，內含扣案之IC板陸塊）及賭\n資新臺幣伍仟壹佰壹拾元，均沒收。\n        事實及理由\n一、本件犯罪事實、證據及應適用之法條，除犯罪事實補充：「\n    被告甲○○所把玩之賭博機具為金歡禧販賣機彈珠臺，所得\n    積分可兌換洗衣精、洗潔精、飲料及香煙等日常生活用品及\n    布娃娃」，及補充以「被告於本院訊問時之自白」為證據外\n    ，其餘均引用檢察官聲請簡易判決處刑書之記載（如附件）\n    。\n二、被告甲○○於本院訊問時，表示願受科刑之範圍為罰金200\n    元，聲請人實行公訴時同意依被告之表示求刑，本院審酌被\n    告甲○○之生活狀況、品行、智識程度、犯罪所生之危害及\n    犯罪動機、目的、犯罪後坦承犯罪等一切情狀，認聲請人之\n    求刑尚屬允洽，爰於前開範圍內，依法量處如主文所示之刑\n    ，並諭知易服勞役之折算標準。另當場賭博之器具電子遊戲\n    機4 臺（野蠻遊戲機及金歡禧景品販賣機各2 台，內含電子\n    IC板6 塊）及賭資新臺幣5,110 元，不問屬於被告甲○○所\n    有，均應依刑法第266 條第2 項規定，宣告沒收。\n三、依刑事訴訟法第449 條第1 項、第3 項、第450 條第1 項、\n    第454 條第2 項、第455 條之1 第2 項，刑法第266 條第1\n    項前段、第2 項、第42條第2 項，罰金罰鍰提高標準條例第\n    1 條前段、第2 條，逕以簡易判決處刑如主文。\n四、本件判決不得上訴。\n中    華    民    國    94    年    12    月    9     日\n                  刑事第三庭法  官  周群翔\n以上正本證明與原本無異。\n                            書記官  劉育君\n中    華    民    國    94    年    12    月    9     日\n刑法第266條第1項前段:\n在公共場所或公眾得出入之場所賭博財物者，處1,000 元以下罰\n金。\n",
  "structure": {
    "main": "甲○○在公眾得出入之場所賭博財物，處罰金貳佰元，如易服勞\n役，以佰元折算壹日。當場賭博之器具電子遊戲機肆臺（野蠻\n遊戲機及金歡禧景品販賣機各貳臺，內含扣案之IC板陸塊）及賭\n資新臺幣伍仟壹佰壹拾元，均沒收。",
    "fact": "一、本件犯罪事實、證據及應適用之法條，除犯罪事實補充：「\n    被告甲○○所把玩之賭博機具為金歡禧販賣機彈珠臺，所得\n    積分可兌換洗衣精、洗潔精、飲料及香煙等日常生活用品及\n    布娃娃」，及補充以「被告於本院訊問時之自白」為證據外\n    ，其餘均引用檢察官聲請簡易判決處刑書之記載（如附件）\n    。\n二、被告甲○○於本院訊問時，表示願受科刑之範圍為罰金200\n    元，聲請人實行公訴時同意依被告之表示求刑，本院審酌被\n    告甲○○之生活狀況、品行、智識程度、犯罪所生之危害及\n    犯罪動機、目的、犯罪後坦承犯罪等一切情狀，認聲請人之\n    求刑尚屬允洽，爰於前開範圍內，依法量處如主文所示之刑\n    ，並諭知易服勞役之折算標準。另當場賭博之器具電子遊戲\n    機4 臺（野蠻遊戲機及金歡禧景品販賣機各2 台，內含電子\n    IC板6 塊）及賭資新臺幣5,110 元，不問屬於被告甲○○所\n    有，均應依刑法第266 條第2 項規定，宣告沒收。\n三、依刑事訴訟法第449 條第1 項、第3 項、第450 條第1 項、\n    第454 條第2 項、第455 條之1 第2 項，刑法第266 條第1\n    項前段、第2 項、第42條第2 項，罰金罰鍰提高標準條例第\n    1 條前段、第2 條，逕以簡易判決處刑如主文。\n四、本件判決不得上訴。",
    "reason": "一、本件犯罪事實、證據及應適用之法條，除犯罪事實補充：「\n    被告甲○○所把玩之賭博機具為金歡禧販賣機彈珠臺，所得\n    積分可兌換洗衣精、洗潔精、飲料及香煙等日常生活用品及\n    布娃娃」，及補充以「被告於本院訊問時之自白」為證據外\n    ，其餘均引用檢察官聲請簡易判決處刑書之記載（如附件）\n    。\n二、被告甲○○於本院訊問時，表示願受科刑之範圍為罰金200\n    元，聲請人實行公訴時同意依被告之表示求刑，本院審酌被\n    告甲○○之生活狀況、品行、智識程度、犯罪所生之危害及\n    犯罪動機、目的、犯罪後坦承犯罪等一切情狀，認聲請人之\n    求刑尚屬允洽，爰於前開範圍內，依法量處如主文所示之刑\n    ，並諭知易服勞役之折算標準。另當場賭博之器具電子遊戲\n    機4 臺（野蠻遊戲機及金歡禧景品販賣機各2 台，內含電子\n    IC板6 塊）及賭資新臺幣5,110 元，不問屬於被告甲○○所\n    有，均應依刑法第266 條第2 項規定，宣告沒收。\n三、依刑事訴訟法第449 條第1 項、第3 項、第450 條第1 項、\n    第454 條第2 項、第455 條之1 第2 項，刑法第266 條第1\n    項前段、第2 項、第42條第2 項，罰金罰鍰提高標準條例第\n    1 條前段、第2 條，逕以簡易判決處刑如主文。\n四、本件判決不得上訴。"
  },
  "search": "臺灣士林地方法院刑事簡易判決94年度簡字第458號聲請人臺灣士林地方法院檢察署檢察官被告甲○○上列被告因賭博案件，經檢察官聲請以簡易判決處刑（94年度偵字第7841號），本院士林簡易庭認為不宜以簡易判決處刑，改由本院依通常程序審理，而被告於準備程序中自白犯罪，經合議庭裁定由受命法官獨任逕以簡易判決處刑，並判決如下：主文甲○○在公眾得出入之場所賭博財物，處罰金貳佰元，如易服勞役，以佰元折算壹日。當場賭博之器具電子遊戲機肆臺（野蠻遊戲機及金歡禧景品販賣機各貳臺，內含扣案之IC板陸塊）及賭資新臺幣伍仟壹佰壹拾元，均沒收。事實及理由一、本件犯罪事實、證據及應適用之法條，除犯罪事實補充：「被告甲○○所把玩之賭博機具為金歡禧販賣機彈珠臺，所得積分可兌換洗衣精、洗潔精、飲料及香煙等日常生活用品及布娃娃」，及補充以「被告於本院訊問時之自白」為證據外，其餘均引用檢察官聲請簡易判決處刑書之記載（如附件）。二、被告甲○○於本院訊問時，表示願受科刑之範圍為罰金200元，聲請人實行公訴時同意依被告之表示求刑，本院審酌被告甲○○之生活狀況、品行、智識程度、犯罪所生之危害及犯罪動機、目的、犯罪後坦承犯罪等一切情狀，認聲請人之求刑尚屬允洽，爰於前開範圍內，依法量處如主文所示之刑，並諭知易服勞役之折算標準。另當場賭博之器具電子遊戲機4臺（野蠻遊戲機及金歡禧景品販賣機各2台，內含電子IC板6塊）及賭資新臺幣5,110元，不問屬於被告甲○○所有，均應依刑法第266條第2項規定，宣告沒收。三、依刑事訴訟法第449條第1項、第3項、第450條第1項、第454條第2項、第455條之1第2項，刑法第266條第1項前段、第2項、第42條第2項，罰金罰鍰提高標準條例第1條前段、第2條，逕以簡易判決處刑如主文。四、本件判決不得上訴。中華民國94年12月9日刑事第三庭法官周群翔以上正本證明與原本無異。書記官劉育君中華民國94年12月9日刑法第266條第1項前段:在公共場所或公眾得出入之場所賭博財物者，處1,000元以下罰金。",
  "characters": {
    "judges": [
      "周群翔"
    ],
    "prosecutors": [

    ],
    "lawyers": [

    ],
    "clerks": [
      "劉育君"
    ],
    "plaintiffs": [

    ],
    "defendants": [
      "甲○○"
    ],
    "prosecutor_office": [
      "臺灣士林地方法院檢察署檢察官"
    ],
    "creditors": [

    ],
    "debtors": [

    ],
    "judicial_associate_officer": [

    ]
  },
  "adjudged_at": "2005-12-09",
  "created_at": "2016-02-07 03:31:14",
  "updated_at": "2016-02-07 03:31:14"
}