{
  "identify": "KSD-93-易-461-20040504-1",
  "court": {
    "name": "臺灣高雄地方法院",
    "code": "KSD"
  },
  "division": {
    "name": "刑事",
    "code": "M"
  },
  "year": 93,
  "word": "易",
  "number": "461",
  "jcheck": "1",
  "reason": "竊盜",
  "content": "臺灣高雄地方法院刑事判決                          九十三年度易字第四六一號\n    公  訴  人  臺灣高雄地方法院檢察署檢察官\n    被      告  丙○○\n右列被告因竊盜案件，經檢察官提起公訴（九十三年度偵字第三六七四號、第六五五\n五號），本院判決如左：\n    主  文\n丙○○共同攜帶兇器於夜間侵入住宅竊盜，累犯，處有期徒刑壹年拾月。\n扣案之扳手鉗、開鎖鑽頭各壹支、螺絲起子貳支，均沒收。\n    事  實\n一、丙○○前曾因民國八十七年、八十九年間因竊盜案件，分別經法院判處有期徒刑\n    七月及有期徒刑一年確定，並分別於八十九年三月八日及九十一年七月三十一日\n    執行完畢；復不知悔改，與林清添（俟到案後另行審理）共同意圖為自己不法之\n    所有，於九十三年二月十三日二十一時許，由甲○○攜帶其所有客觀上對人之生\n    命、身體具有危險性可供做為兇器使用之扳手鉗、開鎖鑽頭各一支及螺絲起子二\n    支，至高雄縣阿蓮鄉民族二三八巷三十二號乙○○住處，二人以上開扳手鉗、開\n    鎖鑽頭及螺絲起子等撬開門鎖後（未毀損），無故侵入屋內下手竊取乙○○所有\n    之舊式新台幣百元鈔六張、舊式新台幣二十元幣一個、舊式新台幣十元幣六個、\n    ＭＯＴＯＲＬＡ牌手機一支、各式皮包八只、手錶二只、乙○○郵局存摺一本、\n    乙○○合作金庫存摺一本、乙○○農會存摺一本及洪慶琳所有之農會存摺一本等\n    物，得手後甫欲離去之際，適為乙○○返家聽聞前開住處二樓有異聲傳出，事覺\n    有異，便大喊捉賊，丙○○與甲○○二人聞訊後倉皇，由該處二樓陽台跳下逃逸\n    ；嗣經乙○○報警於同日二十一時二十八分許，當場在高雄縣阿蓮鄉○○路三五\n    七號前查獲因跳樓而受傷之丙○○，並追回乙○○所有之舊式新台幣百元鈔六張\n    、舊式新台幣二十元幣一個、舊式新台幣十元幣六個、ＭＯＴＯＲＬＡ牌手機一\n    支、各式皮包八只、手錶二只、乙○○郵局存摺一本、乙○○合作金庫存摺一本\n    、乙○○農會存摺一本等物及洪慶琳所有之農會存摺一本，並扣得甲○○所有供\n    行竊所用之扳手鉗、開鎖鑽頭各一支及螺絲起子二支。\n二、案經高雄縣政府警察局湖內分局移送台灣高雄地方法院檢察署檢察官偵查起訴。\n    理  由\n一、上開事實業據被告丙○○於本院審理中坦承不諱，且經證人即被害人乙○○於警\n    訊及偵查中證述無誤，復有贓物領據一紙附卷可查，並有同案被告甲○○所有上\n    開供行竊所用之扳手鉗、開鎖鑽頭各一支及螺絲起子二支扣案可憑，罪證明確，\n    被告犯行堪以認定。\n二、核被告所為，係犯刑法第三百二十一條第一項第一款、第三款之加重竊盜罪。被\n    告與同案被告甲○○二人就上開犯行，彼此間有犯意之聯絡及行為之分擔，應論\n    以共同正犯。又被告曾受上開如事實欄所示之有期徒刑以上刑之執行，有其之台\n    灣高等法院被告全國前案紀錄表各一份附卷可稽，其於執行完畢後五年內，再犯\n    本件有期徒刑以上之罪，為累犯，應依刑法第四十七條之規定加重其刑。審酌被\n    告年輕力壯，竟不思努力工作以獲取正當之報酬，反貪圖不法之利益而夥同他人\n    竊取財物，惟本件所竊之財物價值尚非鉅大，且已當場追回減低被害人之損失，\n    且被告犯後坦承犯行亦深表悔悟之意，犯後態度尚稱良好等一切情狀，量處如主\n    文所示之刑。扣案之扳手鉗、開鎖鑽頭各一支及螺絲起子二支，同案被告甲○○\n    所有，供本件竊盜犯罪所用之物，應依刑法第三十八條第一項第二款之規定宣告\n    沒收。\n三、又本件被告所犯係死刑、無期徒刑、最輕本刑為三年以上有期徒刑以外之罪，其\n    於準備程序中就被訴事實為有罪之陳述，經法官告知簡式審判程序之旨，並聽取\n    公訴人、被告之意見後，本院認為適宜由受命法官獨任進行簡式審判程序，附予\n    敘明。\n據上論斷，應依刑事訴訟法第二百七十三條之一第一項、第二百九十九條第一項前段\n，刑法第二十八條、刑法第三百二十一條第一項第一款、第三款、第四十七條、第三\n十八條第一項第二款，判決如主文。\n中      華      民      國      九十三      年      五      月    四    日\n                                  臺灣高雄地方法院刑事第十四庭\n                                      法  官   林俊寬\n右正本證明與原本無異。\n如不服本判決，應於判決送達後十日內，向本院提出上訴狀。\n                                      書記官   蔡淑貞\n中      華      民      國      九十三      年      五      月    四    日\n",
  "structure": {
    "main": "丙○○共同攜帶兇器於夜間侵入住宅竊盜，累犯，處有期徒刑壹年拾月。\n扣案之扳手鉗、開鎖鑽頭各壹支、螺絲起子貳支，均沒收。",
    "fact": "一、丙○○前曾因民國八十七年、八十九年間因竊盜案件，分別經法院判處有期徒刑\n    七月及有期徒刑一年確定，並分別於八十九年三月八日及九十一年七月三十一日\n    執行完畢；復不知悔改，與林清添（俟到案後另行審理）共同意圖為自己不法之\n    所有，於九十三年二月十三日二十一時許，由甲○○攜帶其所有客觀上對人之生\n    命、身體具有危險性可供做為兇器使用之扳手鉗、開鎖鑽頭各一支及螺絲起子二\n    支，至高雄縣阿蓮鄉民族二三八巷三十二號乙○○住處，二人以上開扳手鉗、開\n    鎖鑽頭及螺絲起子等撬開門鎖後（未毀損），無故侵入屋內下手竊取乙○○所有\n    之舊式新台幣百元鈔六張、舊式新台幣二十元幣一個、舊式新台幣十元幣六個、\n    ＭＯＴＯＲＬＡ牌手機一支、各式皮包八只、手錶二只、乙○○郵局存摺一本、\n    乙○○合作金庫存摺一本、乙○○農會存摺一本及洪慶琳所有之農會存摺一本等\n    物，得手後甫欲離去之際，適為乙○○返家聽聞前開住處二樓有異聲傳出，事覺\n    有異，便大喊捉賊，丙○○與甲○○二人聞訊後倉皇，由該處二樓陽台跳下逃逸\n    ；嗣經乙○○報警於同日二十一時二十八分許，當場在高雄縣阿蓮鄉○○路三五\n    七號前查獲因跳樓而受傷之丙○○，並追回乙○○所有之舊式新台幣百元鈔六張\n    、舊式新台幣二十元幣一個、舊式新台幣十元幣六個、ＭＯＴＯＲＬＡ牌手機一\n    支、各式皮包八只、手錶二只、乙○○郵局存摺一本、乙○○合作金庫存摺一本\n    、乙○○農會存摺一本等物及洪慶琳所有之農會存摺一本，並扣得甲○○所有供\n    行竊所用之扳手鉗、開鎖鑽頭各一支及螺絲起子二支。\n二、案經高雄縣政府警察局湖內分局移送台灣高雄地方法院檢察署檢察官偵查起訴。",
    "reason": "一、上開事實業據被告丙○○於本院審理中坦承不諱，且經證人即被害人乙○○於警\n    訊及偵查中證述無誤，復有贓物領據一紙附卷可查，並有同案被告甲○○所有上\n    開供行竊所用之扳手鉗、開鎖鑽頭各一支及螺絲起子二支扣案可憑，罪證明確，\n    被告犯行堪以認定。\n二、核被告所為，係犯刑法第三百二十一條第一項第一款、第三款之加重竊盜罪。被\n    告與同案被告甲○○二人就上開犯行，彼此間有犯意之聯絡及行為之分擔，應論\n    以共同正犯。又被告曾受上開如事實欄所示之有期徒刑以上刑之執行，有其之台\n    灣高等法院被告全國前案紀錄表各一份附卷可稽，其於執行完畢後五年內，再犯\n    本件有期徒刑以上之罪，為累犯，應依刑法第四十七條之規定加重其刑。審酌被\n    告年輕力壯，竟不思努力工作以獲取正當之報酬，反貪圖不法之利益而夥同他人\n    竊取財物，惟本件所竊之財物價值尚非鉅大，且已當場追回減低被害人之損失，\n    且被告犯後坦承犯行亦深表悔悟之意，犯後態度尚稱良好等一切情狀，量處如主\n    文所示之刑。扣案之扳手鉗、開鎖鑽頭各一支及螺絲起子二支，同案被告甲○○\n    所有，供本件竊盜犯罪所用之物，應依刑法第三十八條第一項第二款之規定宣告\n    沒收。\n三、又本件被告所犯係死刑、無期徒刑、最輕本刑為三年以上有期徒刑以外之罪，其\n    於準備程序中就被訴事實為有罪之陳述，經法官告知簡式審判程序之旨，並聽取\n    公訴人、被告之意見後，本院認為適宜由受命法官獨任進行簡式審判程序，附予\n    敘明。\n據上論斷，應依刑事訴訟法第二百七十三條之一第一項、第二百九十九條第一項前段\n，刑法第二十八條、刑法第三百二十一條第一項第一款、第三款、第四十七條、第三\n十八條第一項第二款，判決如主文。\n中      華      民      國      九十三      年      五      月    四    日\n                                  臺灣高雄地方法院刑事第十四庭\n                                      法  官   林俊寬\n右正本證明與原本無異。\n如不服本判決，應於判決送達後十日內，向本院提出上訴狀。\n                                      書記官   蔡淑貞"
  },
  "search": "臺灣高雄地方法院刑事判決九十三年度易字第四六一號公訴人臺灣高雄地方法院檢察署檢察官被告丙○○右列被告因竊盜案件，經檢察官提起公訴（九十三年度偵字第三六七四號、第六五五五號），本院判決如左：主文丙○○共同攜帶兇器於夜間侵入住宅竊盜，累犯，處有期徒刑壹年拾月。扣案之扳手鉗、開鎖鑽頭各壹支、螺絲起子貳支，均沒收。事實一、丙○○前曾因民國八十七年、八十九年間因竊盜案件，分別經法院判處有期徒刑七月及有期徒刑一年確定，並分別於八十九年三月八日及九十一年七月三十一日執行完畢；復不知悔改，與林清添（俟到案後另行審理）共同意圖為自己不法之所有，於九十三年二月十三日二十一時許，由甲○○攜帶其所有客觀上對人之生命、身體具有危險性可供做為兇器使用之扳手鉗、開鎖鑽頭各一支及螺絲起子二支，至高雄縣阿蓮鄉民族二三八巷三十二號乙○○住處，二人以上開扳手鉗、開鎖鑽頭及螺絲起子等撬開門鎖後（未毀損），無故侵入屋內下手竊取乙○○所有之舊式新台幣百元鈔六張、舊式新台幣二十元幣一個、舊式新台幣十元幣六個、ＭＯＴＯＲＬＡ牌手機一支、各式皮包八只、手錶二只、乙○○郵局存摺一本、乙○○合作金庫存摺一本、乙○○農會存摺一本及洪慶琳所有之農會存摺一本等物，得手後甫欲離去之際，適為乙○○返家聽聞前開住處二樓有異聲傳出，事覺有異，便大喊捉賊，丙○○與甲○○二人聞訊後倉皇，由該處二樓陽台跳下逃逸；嗣經乙○○報警於同日二十一時二十八分許，當場在高雄縣阿蓮鄉○○路三五七號前查獲因跳樓而受傷之丙○○，並追回乙○○所有之舊式新台幣百元鈔六張、舊式新台幣二十元幣一個、舊式新台幣十元幣六個、ＭＯＴＯＲＬＡ牌手機一支、各式皮包八只、手錶二只、乙○○郵局存摺一本、乙○○合作金庫存摺一本、乙○○農會存摺一本等物及洪慶琳所有之農會存摺一本，並扣得甲○○所有供行竊所用之扳手鉗、開鎖鑽頭各一支及螺絲起子二支。二、案經高雄縣政府警察局湖內分局移送台灣高雄地方法院檢察署檢察官偵查起訴。理由一、上開事實業據被告丙○○於本院審理中坦承不諱，且經證人即被害人乙○○於警訊及偵查中證述無誤，復有贓物領據一紙附卷可查，並有同案被告甲○○所有上開供行竊所用之扳手鉗、開鎖鑽頭各一支及螺絲起子二支扣案可憑，罪證明確，被告犯行堪以認定。二、核被告所為，係犯刑法第三百二十一條第一項第一款、第三款之加重竊盜罪。被告與同案被告甲○○二人就上開犯行，彼此間有犯意之聯絡及行為之分擔，應論以共同正犯。又被告曾受上開如事實欄所示之有期徒刑以上刑之執行，有其之台灣高等法院被告全國前案紀錄表各一份附卷可稽，其於執行完畢後五年內，再犯本件有期徒刑以上之罪，為累犯，應依刑法第四十七條之規定加重其刑。審酌被告年輕力壯，竟不思努力工作以獲取正當之報酬，反貪圖不法之利益而夥同他人竊取財物，惟本件所竊之財物價值尚非鉅大，且已當場追回減低被害人之損失，且被告犯後坦承犯行亦深表悔悟之意，犯後態度尚稱良好等一切情狀，量處如主文所示之刑。扣案之扳手鉗、開鎖鑽頭各一支及螺絲起子二支，同案被告甲○○所有，供本件竊盜犯罪所用之物，應依刑法第三十八條第一項第二款之規定宣告沒收。三、又本件被告所犯係死刑、無期徒刑、最輕本刑為三年以上有期徒刑以外之罪，其於準備程序中就被訴事實為有罪之陳述，經法官告知簡式審判程序之旨，並聽取公訴人、被告之意見後，本院認為適宜由受命法官獨任進行簡式審判程序，附予敘明。據上論斷，應依刑事訴訟法第二百七十三條之一第一項、第二百九十九條第一項前段，刑法第二十八條、刑法第三百二十一條第一項第一款、第三款、第四十七條、第三十八條第一項第二款，判決如主文。中華民國九十三年五月四日臺灣高雄地方法院刑事第十四庭法官林俊寬右正本證明與原本無異。如不服本判決，應於判決送達後十日內，向本院提出上訴狀。書記官蔡淑貞中華民國九十三年五月四日",
  "characters": {
    "judges": [
      "林俊寬"
    ],
    "prosecutors": [

    ],
    "lawyers": [

    ],
    "clerks": [
      "蔡淑貞"
    ],
    "plaintiffs": [

    ],
    "defendants": [
      "丙○○",
      "右列被告因竊盜案件，經檢察官提起公訴（九十三年度偵字第三六七四號、第六五五",
      "五號），本院判決如左："
    ],
    "prosecutor_office": [
      "臺灣高雄地方法院檢察署檢察官"
    ],
    "creditors": [

    ],
    "debtors": [

    ],
    "judicial_associate_officer": [

    ]
  },
  "adjudged_at": "2004-05-04",
  "created_at": "2016-02-05 19:56:11",
  "updated_at": "2016-02-05 19:56:11"
}