{
  "identify": "TPD-94-簡-504-20050322-1",
  "court": {
    "name": "臺灣臺北地方法院",
    "code": "TPD"
  },
  "division": {
    "name": "刑事",
    "code": "M"
  },
  "year": 94,
  "word": "簡",
  "number": "504",
  "jcheck": "1",
  "reason": "竊盜",
  "content": "臺灣臺北地方法院刑事簡易判決           94年度簡字第504號\n聲  請  人  臺灣臺北地方法院檢察署檢察官\n被      告  甲○○\n                      號2樓\n上列被告因竊盜案件，經檢察官聲請以簡易判決處刑（94年度速\n偵字第60號），本院判決如下：\n    主  文\n甲○○連續竊盜，累犯，處有期徒刑陸月，如易科罰金，以參佰\n元折算壹日。\n    事實及理由\n一、本件除犯罪事實部分應補充及更正：甲○○前因竊盜罪，經\n    本院93年度簡字第1413號判決判處有期徒刑3月確定，並於\n    民國93年8月20日（聲請簡易判決處刑書誤載為93年7月26日\n    ）易科罰金執行完畢外，其餘犯罪事實、證據及應適用之法\n    條均引用檢察官聲請簡易判決處刑書（如附件）之記載，並\n    適用刑法第56條、第47條、第41條第1項前段，罰金罰鍰提\n    高標準條例第1條前段、第2條之規定。\n二、依刑事訴訟法第449條第1項前段、第3項、第454條第2項，\n    逕以簡易判決處如主文所示之刑，並諭知易科罰金之折算標\n    準。\n三、如不服本判決，應於送達後10日內，向本院提出上訴狀。\n中    華    民    國    94    年    3     月    22    日\n                  刑事第十二庭  法  官  張永宏\n以上正本證明與原本無異。\n                                書記官  楊灥\n中    華    民    國    94    年    3     月    22    日\n附錄本件論罪科刑法條全文\n中華民國刑法第320條\n (普通竊盜罪、竊佔罪)\n意圖為自己或第 3 人不法之所有，而竊取他人之動產者，為竊盜\n罪，處五年以下有期徒刑、拘役或五百元以下罰金。\n意圖為自己或第 3 人不法之利益，而竊佔他人之不動產者，依前\n項之規定處斷。\n前二項之未遂犯罰之。\n",
  "structure": {
    "main": "甲○○連續竊盜，累犯，處有期徒刑陸月，如易科罰金，以參佰\n元折算壹日。",
    "fact": "一、本件除犯罪事實部分應補充及更正：甲○○前因竊盜罪，經\n    本院93年度簡字第1413號判決判處有期徒刑3月確定，並於\n    民國93年8月20日（聲請簡易判決處刑書誤載為93年7月26日\n    ）易科罰金執行完畢外，其餘犯罪事實、證據及應適用之法\n    條均引用檢察官聲請簡易判決處刑書（如附件）之記載，並\n    適用刑法第56條、第47條、第41條第1項前段，罰金罰鍰提\n    高標準條例第1條前段、第2條之規定。\n二、依刑事訴訟法第449條第1項前段、第3項、第454條第2項，\n    逕以簡易判決處如主文所示之刑，並諭知易科罰金之折算標\n    準。\n三、如不服本判決，應於送達後10日內，向本院提出上訴狀。",
    "reason": "一、本件除犯罪事實部分應補充及更正：甲○○前因竊盜罪，經\n    本院93年度簡字第1413號判決判處有期徒刑3月確定，並於\n    民國93年8月20日（聲請簡易判決處刑書誤載為93年7月26日\n    ）易科罰金執行完畢外，其餘犯罪事實、證據及應適用之法\n    條均引用檢察官聲請簡易判決處刑書（如附件）之記載，並\n    適用刑法第56條、第47條、第41條第1項前段，罰金罰鍰提\n    高標準條例第1條前段、第2條之規定。\n二、依刑事訴訟法第449條第1項前段、第3項、第454條第2項，\n    逕以簡易判決處如主文所示之刑，並諭知易科罰金之折算標\n    準。\n三、如不服本判決，應於送達後10日內，向本院提出上訴狀。"
  },
  "search": "臺灣臺北地方法院刑事簡易判決94年度簡字第504號聲請人臺灣臺北地方法院檢察署檢察官被告甲○○號2樓上列被告因竊盜案件，經檢察官聲請以簡易判決處刑（94年度速偵字第60號），本院判決如下：主文甲○○連續竊盜，累犯，處有期徒刑陸月，如易科罰金，以參佰元折算壹日。事實及理由一、本件除犯罪事實部分應補充及更正：甲○○前因竊盜罪，經本院93年度簡字第1413號判決判處有期徒刑3月確定，並於民國93年8月20日（聲請簡易判決處刑書誤載為93年7月26日）易科罰金執行完畢外，其餘犯罪事實、證據及應適用之法條均引用檢察官聲請簡易判決處刑書（如附件）之記載，並適用刑法第56條、第47條、第41條第1項前段，罰金罰鍰提高標準條例第1條前段、第2條之規定。二、依刑事訴訟法第449條第1項前段、第3項、第454條第2項，逕以簡易判決處如主文所示之刑，並諭知易科罰金之折算標準。三、如不服本判決，應於送達後10日內，向本院提出上訴狀。中華民國94年3月22日刑事第十二庭法官張永宏以上正本證明與原本無異。書記官楊灥中華民國94年3月22日附錄本件論罪科刑法條全文中華民國刑法第320條(普通竊盜罪、竊佔罪)意圖為自己或第3人不法之所有，而竊取他人之動產者，為竊盜罪，處五年以下有期徒刑、拘役或五百元以下罰金。意圖為自己或第3人不法之利益，而竊佔他人之不動產者，依前項之規定處斷。前二項之未遂犯罰之。",
  "characters": {
    "judges": [
      "張永宏"
    ],
    "prosecutors": [

    ],
    "lawyers": [

    ],
    "clerks": [
      "楊灥"
    ],
    "plaintiffs": [

    ],
    "defendants": [
      "甲○○"
    ],
    "prosecutor_office": [
      "臺灣臺北地方法院檢察署檢察官"
    ],
    "creditors": [

    ],
    "debtors": [

    ],
    "judicial_associate_officer": [

    ]
  },
  "adjudged_at": "2005-03-22",
  "created_at": "2016-02-07 07:46:06",
  "updated_at": "2016-02-07 07:46:06"
}