{
  "identify": "TND-94-簡-209-20050203-1",
  "court": {
    "name": "臺灣南投地方法院",
    "code": "TND"
  },
  "division": {
    "name": "刑事",
    "code": "M"
  },
  "year": 94,
  "word": "簡",
  "number": "209",
  "jcheck": "1",
  "reason": "妨害家庭",
  "content": "臺灣臺南地方法院刑事簡易判決                      九十四年度簡字第二九號\n    聲  請  人  臺灣台南地方法院檢察署檢察官\n    被      告  甲○○\n右列被告因妨害家庭案件，經檢察官聲請以簡易判決處刑（九十四年度偵字第五二號\n），本院判決如左：\n    主      文\n甲○○連續有配偶而與人通姦，處有期徒刑月，如易科罰金，以佰元折算壹日。\n    事實及理由\n一、本件犯罪事實及證據，均引用檢察官聲請簡易判決處刑書之記載（如附件）。\n二、依刑事訴訟法第四百四十九條第一項前段、第四百五十四條第二項，刑法第五十\n    六條、第二百三十九條前段、第四十一條第一項前段，罰金罰鍰提高標準條例第\n    二條，逕以簡易判決處如主文所示之刑。\n三、如不服本判決，得於判決書送達之翌日起十日內，以書狀敘述理由，向本院提出\n    上訴（應附繕本）。\n中      華      民      國    九十四    年      二      月      三      日\n                                  臺灣臺南地方法院刑事第五庭\n                                          法  官  張家瑛\n右正本證明與原本無異。\n                                          書記官  許悉愛\n中      華      民      國    九十四    年      二      月      四      日\n",
  "structure": {
    "main": "甲○○連續有配偶而與人通姦，處有期徒刑月，如易科罰金，以佰元折算壹日。",
    "fact": "一、本件犯罪事實及證據，均引用檢察官聲請簡易判決處刑書之記載（如附件）。\n二、依刑事訴訟法第四百四十九條第一項前段、第四百五十四條第二項，刑法第五十\n    六條、第二百三十九條前段、第四十一條第一項前段，罰金罰鍰提高標準條例第\n    二條，逕以簡易判決處如主文所示之刑。\n三、如不服本判決，得於判決書送達之翌日起十日內，以書狀敘述理由，向本院提出\n    上訴（應附繕本）。",
    "reason": "一、本件犯罪事實及證據，均引用檢察官聲請簡易判決處刑書之記載（如附件）。\n二、依刑事訴訟法第四百四十九條第一項前段、第四百五十四條第二項，刑法第五十\n    六條、第二百三十九條前段、第四十一條第一項前段，罰金罰鍰提高標準條例第\n    二條，逕以簡易判決處如主文所示之刑。\n三、如不服本判決，得於判決書送達之翌日起十日內，以書狀敘述理由，向本院提出\n    上訴（應附繕本）。"
  },
  "search": "臺灣臺南地方法院刑事簡易判決九十四年度簡字第二九號聲請人臺灣台南地方法院檢察署檢察官被告甲○○右列被告因妨害家庭案件，經檢察官聲請以簡易判決處刑（九十四年度偵字第五二號），本院判決如左：主文甲○○連續有配偶而與人通姦，處有期徒刑月，如易科罰金，以佰元折算壹日。事實及理由一、本件犯罪事實及證據，均引用檢察官聲請簡易判決處刑書之記載（如附件）。二、依刑事訴訟法第四百四十九條第一項前段、第四百五十四條第二項，刑法第五十六條、第二百三十九條前段、第四十一條第一項前段，罰金罰鍰提高標準條例第二條，逕以簡易判決處如主文所示之刑。三、如不服本判決，得於判決書送達之翌日起十日內，以書狀敘述理由，向本院提出上訴（應附繕本）。中華民國九十四年二月三日臺灣臺南地方法院刑事第五庭法官張家瑛右正本證明與原本無異。書記官許悉愛中華民國九十四年二月四日",
  "characters": {
    "judges": [
      "張家瑛"
    ],
    "prosecutors": [

    ],
    "lawyers": [

    ],
    "clerks": [
      "許悉愛"
    ],
    "plaintiffs": [

    ],
    "defendants": [
      "甲○○",
      "右列被告因妨害家庭案件，經檢察官聲請以簡易判決處刑（九十四年度偵字第五二號",
      "），本院判決如左："
    ],
    "prosecutor_office": [
      "臺灣台南地方法院檢察署檢察官"
    ],
    "creditors": [

    ],
    "debtors": [

    ],
    "judicial_associate_officer": [

    ]
  },
  "adjudged_at": "2005-02-03",
  "created_at": "2016-02-06 16:51:17",
  "updated_at": "2016-02-06 16:51:17"
}