{
  "identify": "KLD-100-訴-276-20110621-1",
  "court": {
    "name": "臺灣基隆地方法院",
    "code": "KLD"
  },
  "division": {
    "name": "刑事",
    "code": "M"
  },
  "year": 100,
  "word": "訴",
  "number": "276",
  "jcheck": "1",
  "reason": "毒品危害防制條例",
  "content": "臺灣基隆地方法院刑事判決              100年度訴字第276號\n公  訴  人  臺灣基隆地方法院檢察署檢察官\n被      告  彭國誠\n上列被告因違反毒品危害防制條例案件，經檢察官提起公訴（\n100 年度毒偵字第630 號），被告就被訴事實為有罪之陳述，本\n院合議庭裁定由受命法官獨任進行審判，經改依簡式審判程序審\n理後判決如下：\n    主  文\n彭國誠施用第一級毒品，累犯，處有期徒刑柒月。\n    事  實\n一、彭國誠前因施用第二級毒品案件，經本院裁定送觀察勒戒後\n    ，認無繼續施用毒品之傾向，於民國88年4 月9 日執行完畢\n    釋放出所，並由臺灣基隆地方法院檢察署檢察官以88年度偵\n    字第927 號為不起訴處分確定。又於上開觀察勒戒執行完畢\n    釋放後之5 年內，因施用第二級毒品案件，經本院再次裁定\n    送觀察勒戒，亦認無繼續施用毒品之傾向，於88年12月16日\n    執行完畢釋放出所，並由臺灣基隆地方法院檢察署檢察官以\n    88年度毒偵字第1121號為不起訴處分確定。再因施用第一級\n    、第二級毒品案件，經本院裁定送強制戒治（91年5 月21日\n    執行完畢），並以89年度訴字第784 號判決判處有期徒刑8\n    月、3 月，應執行有期徒刑10月確定（下稱甲案）。又因施\n    用第一級毒品案件，經本院以90年度訴字第658 號判決判處\n    有期徒刑8 月確定（下稱乙案）；因竊盜、搶奪案件，經本\n    院以90年度訴字第720 號判決判處有期徒刑8 月、2 年6 月\n    ，應執行有期徒刑3 年確定（下稱丙案）。其因乙丙案件所\n    處之刑，嗣經本院以91年度聲字第243 號裁定合併應執行有\n    期徒刑3 年7 月，並於91年5 月22日入監接續執行上開甲案\n    所處有期徒刑10月、乙丙案件所定應執行之有期徒刑3 年7\n    月，93年12月3 日假釋出監，並付保護管束（假釋嗣經撤銷\n    ，應執行殘刑1 年7 月9 日）。嗣其於假釋期間，又因施用\n    第一級毒品案件，經本院以94年度訴字第362 號判決判處有\n    期徒刑9 月確定（下稱丁案）；因施用第二級毒品案件，經\n    本院以94年度易字第301 號判決判處有期徒刑4 月確定（下\n    稱戊案）。其因丁戊案件所處之刑，嗣經本院以96年度聲減\n    字第735 號裁定減刑，並合併定應執行有期徒刑6 月確定。\n    其於94年10月13日入監接續執行上開應執行之殘刑1 年7 月\n    9 日及丁戊案件所應執行之有期徒刑6 月，於96年8 月31日\n    執行完畢（構成累犯）。再因施用第一級毒品案件，經本院\n    以97年度訴字第1204號判決判處有期徒刑7 月確定（下稱己\n    案）；因施用第一級、第二級毒品案件，經本院以97年度訴\n    字第1843號判決判處有期徒刑4 月（共5 罪）、2 月，應執\n    行有期徒刑6 月（下稱庚案），其因己庚案件所處之刑，嗣\n    經本院以98年度聲字第405 號裁定合併應執行有期徒刑8 月\n    確定。再因施用第一級、第二級毒品案件，經本院以98年度\n    訴字第57號判決判處有期徒刑7 月、3 月，應執行有期徒刑\n    9 月確定（下稱辛案）；因施用第一級毒品案件，經本院以\n    98年度訴字第588 號判決判處有期徒刑7 月確定（下稱壬案\n    ），其因辛壬案件所處之刑，嗣經本院以98年度聲字第904\n    號裁定合併應執行有期徒刑1 年3 月確定。其於98年2 月2\n    日入監接續上開應執行之有期徒刑8 月、1 年3 月，於99年\n    10月6 日假釋出監，並付保護管束，99年11月30日保護管束\n    期滿，所受假釋之宣告未經撤銷，未執行之刑以已執行論，\n    而執行完畢（構成累犯）。\n二、詎彭國誠猶未戒斷毒癮，復基於施用第一級毒品海洛因之犯\n    意，於100 年1 月12日上午8 、9 時許，在基隆市○○區○\n    ○街117 之3 號4 樓住處，以將第一級毒品海洛因摻水注入\n    注射針筒，再施打入身體之方式，施用第一級毒品海洛因1\n    次。嗣因其為列管之毒品調驗人口，為警通知於100 年1 月\n    13日下午6 時25分許到案採驗尿液，結果呈嗎啡陽性反應，\n    始悉上情。\n三、案經基隆市警察局第一分局報告臺灣基隆地方法院檢察署檢\n    察官偵查後起訴。\n    理  由\n壹、程序事項：\n    本件被告彭國誠所犯者非為死刑、無期徒刑、最輕本刑為3\n    年以上有期徒刑之罪或高等法院管轄第一審案件，其於準備\n    程序進行中，先就被訴事實為有罪之陳述，經告知其簡式審\n    判程序之旨，並聽取公訴人、被告之意見後，本院業已依刑\n    事訴訟法第273 條之1 第1 項之規定，裁定由受命法官獨任\n    以簡式審判程序進行本案之審理。\n貳、實體事項：\n一、認定犯罪事實所憑之證據及理由：\n    上開事實，業據被告於檢察官偵訊及本院審理時坦承在卷，\n    且其為警查獲時所採集之尿液送驗後，結果呈嗎啡之陽性反\n    應，有台灣檢驗科技股份有限公司濫用藥物檢驗報告及列管\n    毒品人口尿液檢體採集送驗紀錄表各1 紙附卷可稽，被告之\n    自白核與事實相符，可以採信。綜上，本案事證明確，被告\n    施用第一級毒品之犯行洵堪認定，應依法論科。\n二、論罪科刑：\n  (一)按毒品危害防制條例係於92年7 月9 日修正公布，自93年1\n    月9 日起施行，其中第20條、第23條將施用毒品之刑事處遇\n    程序，區分為「初犯」、「五年內再犯」、「五年後再犯」\n    。依其立法理由之說明：「初犯」，經觀察、勒戒或強制戒\n    治後，應為不起訴處分或不付審理之裁定；經觀察、勒戒或\n    強制戒治執行完畢釋放後，「五年內再犯者」，因其再犯率\n    甚高，原實施之觀察、勒戒及強制戒治既已無法收其實效，\n    爰依法追訴或裁定交付審理。至於經觀察、勒戒或強制戒治\n    執行完畢釋放後，「五年後再犯者」，前所實施之觀察、勒\n    戒或強制戒治已足以遮斷其施用毒品之毒癮，為其自新及協\n    助其斷除毒癮，仍適用「初犯」規定，先經觀察、勒戒或強\n    制戒治之程序。從而依修正後之規定，僅限於「初犯」及「\n    五年後再犯」二種情形，始應先經觀察、勒戒或強制戒治程\n    序。倘被告於5 年內已再犯，經依法追訴處罰，縱其第三次\n    （或第三次以上）再度施用毒品之時間，在初犯經觀察、勒\n    戒或強制戒治執行完畢釋放五年以後，已不合於「五年後再\n    犯」之規定，且因已於「五年內再犯」，顯見其再犯率甚高\n    ，原實施觀察、勒戒或強制戒治，已無法收其實效，即應依\n    該條例第10條處罰（最高法院95年度台非字第59號、第65號\n    判決意旨及最高法院95年第7 次刑事庭會議決議意旨參照）\n    。被告有如事實欄一所載，88年4 月9 日第一次觀察勒戒執\n    行完畢後之5 年內，再因施用毒品案件，經法院第二次裁定\n    觀察勒戒、第三次裁定送強制戒治，並判處徒刑等情，有臺\n    灣高等法院被告前案紀錄表在卷可稽。被告既曾於「五年內\n    再犯」，且經追訴處罰，竟又於如事實欄二所示之時間施用\n    第一級毒品，揆諸前揭說明，即非屬毒品危害防制條例第20\n    條第3 項所定「五年後再犯」之情形，故檢察官依法逕行起\n    訴，於法要無不合，合先敘明。\n  (二)查海洛因係毒品危害防制條例第2 條第2 項第1 款所定之第\n    一級毒品，被告如事實欄二所示非法施用第一級毒品海洛因\n    之行為，核係犯毒品危害防制條例第10條第1 項之施用第一\n    級毒品罪。被告因施用而持有第一級毒品海洛因之低度行為\n    ，應為其施用第一級毒品之高度行為所吸收，不另論罪。再\n    被告前曾受如事實欄所示有期徒刑之執行完畢，有臺灣高等\n    法院被告前案紀錄表在卷可憑，其於有期徒刑執行完畢釋放\n    後之5 年內，故意再犯本件有期徒刑以上之罪，合於累犯之\n    規定，爰依刑法第47 條 第1 項規定，加重其刑。爰審酌被\n    告犯罪之動機、曾有施用毒品之前科仍不知戒除，惟犯罪後\n    坦承犯行，且所犯施用毒品犯行乃戕害自己身心健康，並未\n    危及他人等一切情狀，量處如主文所示之刑。\n據上論斷，應依刑事訴訟法第273 條之1 第1 項、第299 條第1\n項前段，毒品危害防制條例第10條第1 項、第23條第2 項，刑法\n第11條前段、第47條第1 項，判決如主文。\n本案經檢察官李辛茹到庭執行職務。\n中    華    民    國   100    年    6     月    21    日\n                  刑事第二庭法  官  劉桂金\n以上正本證明與原本無異。\n如不服本判決應於收受送達後10日內向本院提出上訴書狀，並應\n敘述具體理由；其未敘述上訴理由者，應於上訴期間屆滿後20日\n內向本院補提理由書(均須按他造當事人之人數附繕本)「切勿逕\n送上級法院」。\n中    華    民    國   100    年    6     月    21    日\n                            書記官  劉如純\n附錄本案論罪法條：\n毒品危害防制條例第10條第1 項\n施用第一級毒品者，處6 月以上5 年以下有期徒刑。",
  "structure": {
    "main": "彭國誠施用第一級毒品，累犯，處有期徒刑柒月。",
    "fact": "一、彭國誠前因施用第二級毒品案件，經本院裁定送觀察勒戒後\n    ，認無繼續施用毒品之傾向，於民國88年4 月9 日執行完畢\n    釋放出所，並由臺灣基隆地方法院檢察署檢察官以88年度偵\n    字第927 號為不起訴處分確定。又於上開觀察勒戒執行完畢\n    釋放後之5 年內，因施用第二級毒品案件，經本院再次裁定\n    送觀察勒戒，亦認無繼續施用毒品之傾向，於88年12月16日\n    執行完畢釋放出所，並由臺灣基隆地方法院檢察署檢察官以\n    88年度毒偵字第1121號為不起訴處分確定。再因施用第一級\n    、第二級毒品案件，經本院裁定送強制戒治（91年5 月21日\n    執行完畢），並以89年度訴字第784 號判決判處有期徒刑8\n    月、3 月，應執行有期徒刑10月確定（下稱甲案）。又因施\n    用第一級毒品案件，經本院以90年度訴字第658 號判決判處\n    有期徒刑8 月確定（下稱乙案）；因竊盜、搶奪案件，經本\n    院以90年度訴字第720 號判決判處有期徒刑8 月、2 年6 月\n    ，應執行有期徒刑3 年確定（下稱丙案）。其因乙丙案件所\n    處之刑，嗣經本院以91年度聲字第243 號裁定合併應執行有\n    期徒刑3 年7 月，並於91年5 月22日入監接續執行上開甲案\n    所處有期徒刑10月、乙丙案件所定應執行之有期徒刑3 年7\n    月，93年12月3 日假釋出監，並付保護管束（假釋嗣經撤銷\n    ，應執行殘刑1 年7 月9 日）。嗣其於假釋期間，又因施用\n    第一級毒品案件，經本院以94年度訴字第362 號判決判處有\n    期徒刑9 月確定（下稱丁案）；因施用第二級毒品案件，經\n    本院以94年度易字第301 號判決判處有期徒刑4 月確定（下\n    稱戊案）。其因丁戊案件所處之刑，嗣經本院以96年度聲減\n    字第735 號裁定減刑，並合併定應執行有期徒刑6 月確定。\n    其於94年10月13日入監接續執行上開應執行之殘刑1 年7 月\n    9 日及丁戊案件所應執行之有期徒刑6 月，於96年8 月31日\n    執行完畢（構成累犯）。再因施用第一級毒品案件，經本院\n    以97年度訴字第1204號判決判處有期徒刑7 月確定（下稱己\n    案）；因施用第一級、第二級毒品案件，經本院以97年度訴\n    字第1843號判決判處有期徒刑4 月（共5 罪）、2 月，應執\n    行有期徒刑6 月（下稱庚案），其因己庚案件所處之刑，嗣\n    經本院以98年度聲字第405 號裁定合併應執行有期徒刑8 月\n    確定。再因施用第一級、第二級毒品案件，經本院以98年度\n    訴字第57號判決判處有期徒刑7 月、3 月，應執行有期徒刑\n    9 月確定（下稱辛案）；因施用第一級毒品案件，經本院以\n    98年度訴字第588 號判決判處有期徒刑7 月確定（下稱壬案\n    ），其因辛壬案件所處之刑，嗣經本院以98年度聲字第904\n    號裁定合併應執行有期徒刑1 年3 月確定。其於98年2 月2\n    日入監接續上開應執行之有期徒刑8 月、1 年3 月，於99年\n    10月6 日假釋出監，並付保護管束，99年11月30日保護管束\n    期滿，所受假釋之宣告未經撤銷，未執行之刑以已執行論，\n    而執行完畢（構成累犯）。\n二、詎彭國誠猶未戒斷毒癮，復基於施用第一級毒品海洛因之犯\n    意，於100 年1 月12日上午8 、9 時許，在基隆市○○區○\n    ○街117 之3 號4 樓住處，以將第一級毒品海洛因摻水注入\n    注射針筒，再施打入身體之方式，施用第一級毒品海洛因1\n    次。嗣因其為列管之毒品調驗人口，為警通知於100 年1 月\n    13日下午6 時25分許到案採驗尿液，結果呈嗎啡陽性反應，\n    始悉上情。\n三、案經基隆市警察局第一分局報告臺灣基隆地方法院檢察署檢\n    察官偵查後起訴。",
    "reason": "壹、程序事項：\n    本件被告彭國誠所犯者非為死刑、無期徒刑、最輕本刑為3\n    年以上有期徒刑之罪或高等法院管轄第一審案件，其於準備\n    程序進行中，先就被訴事實為有罪之陳述，經告知其簡式審\n    判程序之旨，並聽取公訴人、被告之意見後，本院業已依刑\n    事訴訟法第273 條之1 第1 項之規定，裁定由受命法官獨任\n    以簡式審判程序進行本案之審理。\n貳、實體事項：\n一、認定犯罪事實所憑之證據及理由：\n    上開事實，業據被告於檢察官偵訊及本院審理時坦承在卷，\n    且其為警查獲時所採集之尿液送驗後，結果呈嗎啡之陽性反\n    應，有台灣檢驗科技股份有限公司濫用藥物檢驗報告及列管\n    毒品人口尿液檢體採集送驗紀錄表各1 紙附卷可稽，被告之\n    自白核與事實相符，可以採信。綜上，本案事證明確，被告\n    施用第一級毒品之犯行洵堪認定，應依法論科。\n二、論罪科刑：\n  (一)按毒品危害防制條例係於92年7 月9 日修正公布，自93年1\n    月9 日起施行，其中第20條、第23條將施用毒品之刑事處遇\n    程序，區分為「初犯」、「五年內再犯」、「五年後再犯」\n    。依其立法理由之說明：「初犯」，經觀察、勒戒或強制戒\n    治後，應為不起訴處分或不付審理之裁定；經觀察、勒戒或\n    強制戒治執行完畢釋放後，「五年內再犯者」，因其再犯率\n    甚高，原實施之觀察、勒戒及強制戒治既已無法收其實效，\n    爰依法追訴或裁定交付審理。至於經觀察、勒戒或強制戒治\n    執行完畢釋放後，「五年後再犯者」，前所實施之觀察、勒\n    戒或強制戒治已足以遮斷其施用毒品之毒癮，為其自新及協\n    助其斷除毒癮，仍適用「初犯」規定，先經觀察、勒戒或強\n    制戒治之程序。從而依修正後之規定，僅限於「初犯」及「\n    五年後再犯」二種情形，始應先經觀察、勒戒或強制戒治程\n    序。倘被告於5 年內已再犯，經依法追訴處罰，縱其第三次\n    （或第三次以上）再度施用毒品之時間，在初犯經觀察、勒\n    戒或強制戒治執行完畢釋放五年以後，已不合於「五年後再\n    犯」之規定，且因已於「五年內再犯」，顯見其再犯率甚高\n    ，原實施觀察、勒戒或強制戒治，已無法收其實效，即應依\n    該條例第10條處罰（最高法院95年度台非字第59號、第65號\n    判決意旨及最高法院95年第7 次刑事庭會議決議意旨參照）\n    。被告有如事實欄一所載，88年4 月9 日第一次觀察勒戒執\n    行完畢後之5 年內，再因施用毒品案件，經法院第二次裁定\n    觀察勒戒、第三次裁定送強制戒治，並判處徒刑等情，有臺\n    灣高等法院被告前案紀錄表在卷可稽。被告既曾於「五年內\n    再犯」，且經追訴處罰，竟又於如事實欄二所示之時間施用\n    第一級毒品，揆諸前揭說明，即非屬毒品危害防制條例第20\n    條第3 項所定「五年後再犯」之情形，故檢察官依法逕行起\n    訴，於法要無不合，合先敘明。\n  (二)查海洛因係毒品危害防制條例第2 條第2 項第1 款所定之第\n    一級毒品，被告如事實欄二所示非法施用第一級毒品海洛因\n    之行為，核係犯毒品危害防制條例第10條第1 項之施用第一\n    級毒品罪。被告因施用而持有第一級毒品海洛因之低度行為\n    ，應為其施用第一級毒品之高度行為所吸收，不另論罪。再\n    被告前曾受如事實欄所示有期徒刑之執行完畢，有臺灣高等\n    法院被告前案紀錄表在卷可憑，其於有期徒刑執行完畢釋放\n    後之5 年內，故意再犯本件有期徒刑以上之罪，合於累犯之\n    規定，爰依刑法第47 條 第1 項規定，加重其刑。爰審酌被\n    告犯罪之動機、曾有施用毒品之前科仍不知戒除，惟犯罪後\n    坦承犯行，且所犯施用毒品犯行乃戕害自己身心健康，並未\n    危及他人等一切情狀，量處如主文所示之刑。\n據上論斷，應依刑事訴訟法第273 條之1 第1 項、第299 條第1\n項前段，毒品危害防制條例第10條第1 項、第23條第2 項，刑法\n第11條前段、第47條第1 項，判決如主文。\n本案經檢察官李辛茹到庭執行職務。\n中    華    民    國   100    年    6     月    21    日\n                  刑事第二庭法  官  劉桂金\n以上正本證明與原本無異。\n如不服本判決應於收受送達後10日內向本院提出上訴書狀，並應\n敘述具體理由；其未敘述上訴理由者，應於上訴期間屆滿後20日\n內向本院補提理由書(均須按他造當事人之人數附繕本)「切勿逕\n送上級法院」。"
  },
  "search": "臺灣基隆地方法院刑事判決100年度訴字第276號公訴人臺灣基隆地方法院檢察署檢察官被告彭國誠上列被告因違反毒品危害防制條例案件，經檢察官提起公訴（100年度毒偵字第630號），被告就被訴事實為有罪之陳述，本院合議庭裁定由受命法官獨任進行審判，經改依簡式審判程序審理後判決如下：主文彭國誠施用第一級毒品，累犯，處有期徒刑柒月。事實一、彭國誠前因施用第二級毒品案件，經本院裁定送觀察勒戒後，認無繼續施用毒品之傾向，於民國88年4月9日執行完畢釋放出所，並由臺灣基隆地方法院檢察署檢察官以88年度偵字第927號為不起訴處分確定。又於上開觀察勒戒執行完畢釋放後之5年內，因施用第二級毒品案件，經本院再次裁定送觀察勒戒，亦認無繼續施用毒品之傾向，於88年12月16日執行完畢釋放出所，並由臺灣基隆地方法院檢察署檢察官以88年度毒偵字第1121號為不起訴處分確定。再因施用第一級、第二級毒品案件，經本院裁定送強制戒治（91年5月21日執行完畢），並以89年度訴字第784號判決判處有期徒刑8月、3月，應執行有期徒刑10月確定（下稱甲案）。又因施用第一級毒品案件，經本院以90年度訴字第658號判決判處有期徒刑8月確定（下稱乙案）；因竊盜、搶奪案件，經本院以90年度訴字第720號判決判處有期徒刑8月、2年6月，應執行有期徒刑3年確定（下稱丙案）。其因乙丙案件所處之刑，嗣經本院以91年度聲字第243號裁定合併應執行有期徒刑3年7月，並於91年5月22日入監接續執行上開甲案所處有期徒刑10月、乙丙案件所定應執行之有期徒刑3年7月，93年12月3日假釋出監，並付保護管束（假釋嗣經撤銷，應執行殘刑1年7月9日）。嗣其於假釋期間，又因施用第一級毒品案件，經本院以94年度訴字第362號判決判處有期徒刑9月確定（下稱丁案）；因施用第二級毒品案件，經本院以94年度易字第301號判決判處有期徒刑4月確定（下稱戊案）。其因丁戊案件所處之刑，嗣經本院以96年度聲減字第735號裁定減刑，並合併定應執行有期徒刑6月確定。其於94年10月13日入監接續執行上開應執行之殘刑1年7月9日及丁戊案件所應執行之有期徒刑6月，於96年8月31日執行完畢（構成累犯）。再因施用第一級毒品案件，經本院以97年度訴字第1204號判決判處有期徒刑7月確定（下稱己案）；因施用第一級、第二級毒品案件，經本院以97年度訴字第1843號判決判處有期徒刑4月（共5罪）、2月，應執行有期徒刑6月（下稱庚案），其因己庚案件所處之刑，嗣經本院以98年度聲字第405號裁定合併應執行有期徒刑8月確定。再因施用第一級、第二級毒品案件，經本院以98年度訴字第57號判決判處有期徒刑7月、3月，應執行有期徒刑9月確定（下稱辛案）；因施用第一級毒品案件，經本院以98年度訴字第588號判決判處有期徒刑7月確定（下稱壬案），其因辛壬案件所處之刑，嗣經本院以98年度聲字第904號裁定合併應執行有期徒刑1年3月確定。其於98年2月2日入監接續上開應執行之有期徒刑8月、1年3月，於99年10月6日假釋出監，並付保護管束，99年11月30日保護管束期滿，所受假釋之宣告未經撤銷，未執行之刑以已執行論，而執行完畢（構成累犯）。二、詎彭國誠猶未戒斷毒癮，復基於施用第一級毒品海洛因之犯意，於100年1月12日上午8、9時許，在基隆市○○區○○街117之3號4樓住處，以將第一級毒品海洛因摻水注入注射針筒，再施打入身體之方式，施用第一級毒品海洛因1次。嗣因其為列管之毒品調驗人口，為警通知於100年1月13日下午6時25分許到案採驗尿液，結果呈嗎啡陽性反應，始悉上情。三、案經基隆市警察局第一分局報告臺灣基隆地方法院檢察署檢察官偵查後起訴。理由壹、程序事項：本件被告彭國誠所犯者非為死刑、無期徒刑、最輕本刑為3年以上有期徒刑之罪或高等法院管轄第一審案件，其於準備程序進行中，先就被訴事實為有罪之陳述，經告知其簡式審判程序之旨，並聽取公訴人、被告之意見後，本院業已依刑事訴訟法第273條之1第1項之規定，裁定由受命法官獨任以簡式審判程序進行本案之審理。貳、實體事項：一、認定犯罪事實所憑之證據及理由：上開事實，業據被告於檢察官偵訊及本院審理時坦承在卷，且其為警查獲時所採集之尿液送驗後，結果呈嗎啡之陽性反應，有台灣檢驗科技股份有限公司濫用藥物檢驗報告及列管毒品人口尿液檢體採集送驗紀錄表各1紙附卷可稽，被告之自白核與事實相符，可以採信。綜上，本案事證明確，被告施用第一級毒品之犯行洵堪認定，應依法論科。二、論罪科刑：(一)按毒品危害防制條例係於92年7月9日修正公布，自93年1月9日起施行，其中第20條、第23條將施用毒品之刑事處遇程序，區分為「初犯」、「五年內再犯」、「五年後再犯」。依其立法理由之說明：「初犯」，經觀察、勒戒或強制戒治後，應為不起訴處分或不付審理之裁定；經觀察、勒戒或強制戒治執行完畢釋放後，「五年內再犯者」，因其再犯率甚高，原實施之觀察、勒戒及強制戒治既已無法收其實效，爰依法追訴或裁定交付審理。至於經觀察、勒戒或強制戒治執行完畢釋放後，「五年後再犯者」，前所實施之觀察、勒戒或強制戒治已足以遮斷其施用毒品之毒癮，為其自新及協助其斷除毒癮，仍適用「初犯」規定，先經觀察、勒戒或強制戒治之程序。從而依修正後之規定，僅限於「初犯」及「五年後再犯」二種情形，始應先經觀察、勒戒或強制戒治程序。倘被告於5年內已再犯，經依法追訴處罰，縱其第三次（或第三次以上）再度施用毒品之時間，在初犯經觀察、勒戒或強制戒治執行完畢釋放五年以後，已不合於「五年後再犯」之規定，且因已於「五年內再犯」，顯見其再犯率甚高，原實施觀察、勒戒或強制戒治，已無法收其實效，即應依該條例第10條處罰（最高法院95年度台非字第59號、第65號判決意旨及最高法院95年第7次刑事庭會議決議意旨參照）。被告有如事實欄一所載，88年4月9日第一次觀察勒戒執行完畢後之5年內，再因施用毒品案件，經法院第二次裁定觀察勒戒、第三次裁定送強制戒治，並判處徒刑等情，有臺灣高等法院被告前案紀錄表在卷可稽。被告既曾於「五年內再犯」，且經追訴處罰，竟又於如事實欄二所示之時間施用第一級毒品，揆諸前揭說明，即非屬毒品危害防制條例第20條第3項所定「五年後再犯」之情形，故檢察官依法逕行起訴，於法要無不合，合先敘明。(二)查海洛因係毒品危害防制條例第2條第2項第1款所定之第一級毒品，被告如事實欄二所示非法施用第一級毒品海洛因之行為，核係犯毒品危害防制條例第10條第1項之施用第一級毒品罪。被告因施用而持有第一級毒品海洛因之低度行為，應為其施用第一級毒品之高度行為所吸收，不另論罪。再被告前曾受如事實欄所示有期徒刑之執行完畢，有臺灣高等法院被告前案紀錄表在卷可憑，其於有期徒刑執行完畢釋放後之5年內，故意再犯本件有期徒刑以上之罪，合於累犯之規定，爰依刑法第47條第1項規定，加重其刑。爰審酌被告犯罪之動機、曾有施用毒品之前科仍不知戒除，惟犯罪後坦承犯行，且所犯施用毒品犯行乃戕害自己身心健康，並未危及他人等一切情狀，量處如主文所示之刑。據上論斷，應依刑事訴訟法第273條之1第1項、第299條第1項前段，毒品危害防制條例第10條第1項、第23條第2項，刑法第11條前段、第47條第1項，判決如主文。本案經檢察官李辛茹到庭執行職務。中華民國100年6月21日刑事第二庭法官劉桂金以上正本證明與原本無異。如不服本判決應於收受送達後10日內向本院提出上訴書狀，並應敘述具體理由；其未敘述上訴理由者，應於上訴期間屆滿後20日內向本院補提理由書(均須按他造當事人之人數附繕本)「切勿逕送上級法院」。中華民國100年6月21日書記官劉如純附錄本案論罪法條：毒品危害防制條例第10條第1項施用第一級毒品者，處6月以上5年以下有期徒刑。",
  "characters": {
    "judges": [
      "劉桂金"
    ],
    "prosecutors": [
      "李辛茹"
    ],
    "lawyers": [

    ],
    "clerks": [
      "劉如純"
    ],
    "plaintiffs": [

    ],
    "defendants": [
      "彭國誠"
    ],
    "prosecutor_office": [
      "臺灣基隆地方法院檢察署檢察官"
    ],
    "creditors": [

    ],
    "debtors": [

    ],
    "judicial_associate_officer": [

    ]
  },
  "adjudged_at": "2011-06-21",
  "created_at": "2016-02-13 17:05:44",
  "updated_at": "2016-02-13 17:05:44"
}