{
  "identify": "KSD-94-聲-591-20050315-1",
  "court": {
    "name": "臺灣高雄地方法院",
    "code": "KSD"
  },
  "division": {
    "name": "刑事",
    "code": "M"
  },
  "year": 94,
  "word": "聲",
  "number": "591",
  "jcheck": "1",
  "reason": "聲請單獨宣告沒收違禁物",
  "content": "臺灣高雄地方法院刑事裁定                          九十四年度聲字第五九一號\n    聲  請  人  臺灣高雄地方法院檢察署檢察官\n    被      告  甲○○\n右聲請人因被告違反毒品危害防制條例案件，聲請單獨宣告沒收違禁物（九十四年聲\n沒字第二二九號），本院裁定如左：\n    主    文\n第一級毒品海洛因壹包（驗後淨重零點貳公克，包裝重零點壹玖公克）沒收銷燬之\n。\n    理   由\n一、按違禁物得單獨宣告沒收，刑法第四十條但書定有明文。次按海洛因屬第一級毒\n    品；又查獲之第一、二級毒品及專供製造或施用第一、二級毒品之器具，不問屬\n    於犯人與否，均沒收銷燬之，毒品危害防制條例第二條第二項第一款、第十八條\n    第一項前段分別定有明文。\n二、本件聲請意旨略以：高雄市政府警察局於民國九十年九月二十四日在高雄市三民\n    區○○○路與中山高速高路口，查獲被告甲○○施用第一級毒品海洛因，並扣得\n    白色粉末一包，係海洛因為違禁物，該案業經臺灣高雄地方法院檢察署檢察官以\n    被告強制戒治期滿而處分不起訴在案，爰就該扣案之海洛因聲請宣告沒收等語。\n    經查，上開扣案白粉一包，經送請法務部調查局鑑定結果，認含海洛因成分（淨\n    重零點二三公克，包裝重零點一九公克，包裝部分因難以剝離，一併沒收銷燬）\n    ，有該局九十年九月二十五日編號（電腦條碼）000000000號鑑定通知\n    書一紙附卷可稽，是該白粉確為第一級毒品海洛因無訛，自屬違禁物，應予宣告\n    沒收銷燬之。至送鑑耗損之海洛因粉末，既已滅失，尚無庸併予宣告沒收銷燬。\n三、本院認聲請為正當，爰依刑事訴訟法第二百二十條，毒品危害防制條例第十八條\n    第一項前段，刑法第四十條但書、第三十八條第一項第一款，裁定如主文。\n中      華      民      國    九十四    年      三      月     十五     日\n                                臺灣高雄地方法院刑事第十五庭\n                                    法  官   莊松泉\n右正本證明與原本無異。\n如不服本裁定，應於送達後五日內向本院提出抗告狀。\n                                    書記官   盧聰明\n中      華      民      國    九十四    年      三      月     十五     日\n",
  "structure": {
    "main": "第一級毒品海洛因壹包（驗後淨重零點貳公克，包裝重零點壹玖公克）沒收銷燬之\n。",
    "reason": "一、按違禁物得單獨宣告沒收，刑法第四十條但書定有明文。次按海洛因屬第一級毒\n    品；又查獲之第一、二級毒品及專供製造或施用第一、二級毒品之器具，不問屬\n    於犯人與否，均沒收銷燬之，毒品危害防制條例第二條第二項第一款、第十八條\n    第一項前段分別定有明文。\n二、本件聲請意旨略以：高雄市政府警察局於民國九十年九月二十四日在高雄市三民\n    區○○○路與中山高速高路口，查獲被告甲○○施用第一級毒品海洛因，並扣得\n    白色粉末一包，係海洛因為違禁物，該案業經臺灣高雄地方法院檢察署檢察官以\n    被告強制戒治期滿而處分不起訴在案，爰就該扣案之海洛因聲請宣告沒收等語。\n    經查，上開扣案白粉一包，經送請法務部調查局鑑定結果，認含海洛因成分（淨\n    重零點二三公克，包裝重零點一九公克，包裝部分因難以剝離，一併沒收銷燬）\n    ，有該局九十年九月二十五日編號（電腦條碼）000000000號鑑定通知\n    書一紙附卷可稽，是該白粉確為第一級毒品海洛因無訛，自屬違禁物，應予宣告\n    沒收銷燬之。至送鑑耗損之海洛因粉末，既已滅失，尚無庸併予宣告沒收銷燬。\n三、本院認聲請為正當，爰依刑事訴訟法第二百二十條，毒品危害防制條例第十八條\n    第一項前段，刑法第四十條但書、第三十八條第一項第一款，裁定如主文。"
  },
  "search": "臺灣高雄地方法院刑事裁定九十四年度聲字第五九一號聲請人臺灣高雄地方法院檢察署檢察官被告甲○○右聲請人因被告違反毒品危害防制條例案件，聲請單獨宣告沒收違禁物（九十四年聲沒字第二二九號），本院裁定如左：主文第一級毒品海洛因壹包（驗後淨重零點貳公克，包裝重零點壹玖公克）沒收銷燬之。理由一、按違禁物得單獨宣告沒收，刑法第四十條但書定有明文。次按海洛因屬第一級毒品；又查獲之第一、二級毒品及專供製造或施用第一、二級毒品之器具，不問屬於犯人與否，均沒收銷燬之，毒品危害防制條例第二條第二項第一款、第十八條第一項前段分別定有明文。二、本件聲請意旨略以：高雄市政府警察局於民國九十年九月二十四日在高雄市三民區○○○路與中山高速高路口，查獲被告甲○○施用第一級毒品海洛因，並扣得白色粉末一包，係海洛因為違禁物，該案業經臺灣高雄地方法院檢察署檢察官以被告強制戒治期滿而處分不起訴在案，爰就該扣案之海洛因聲請宣告沒收等語。經查，上開扣案白粉一包，經送請法務部調查局鑑定結果，認含海洛因成分（淨重零點二三公克，包裝重零點一九公克，包裝部分因難以剝離，一併沒收銷燬），有該局九十年九月二十五日編號（電腦條碼）000000000號鑑定通知書一紙附卷可稽，是該白粉確為第一級毒品海洛因無訛，自屬違禁物，應予宣告沒收銷燬之。至送鑑耗損之海洛因粉末，既已滅失，尚無庸併予宣告沒收銷燬。三、本院認聲請為正當，爰依刑事訴訟法第二百二十條，毒品危害防制條例第十八條第一項前段，刑法第四十條但書、第三十八條第一項第一款，裁定如主文。中華民國九十四年三月十五日臺灣高雄地方法院刑事第十五庭法官莊松泉右正本證明與原本無異。如不服本裁定，應於送達後五日內向本院提出抗告狀。書記官盧聰明中華民國九十四年三月十五日",
  "characters": {
    "judges": [
      "莊松泉"
    ],
    "prosecutors": [

    ],
    "lawyers": [

    ],
    "clerks": [
      "盧聰明"
    ],
    "plaintiffs": [

    ],
    "defendants": [
      "甲○○",
      "右聲請人因被告違反毒品危害防制條例案件，聲請單獨宣告沒收違禁物（九十四年聲",
      "沒字第二二九號），本院裁定如左："
    ],
    "prosecutor_office": [
      "臺灣高雄地方法院檢察署檢察官"
    ],
    "creditors": [

    ],
    "debtors": [

    ],
    "judicial_associate_officer": [

    ]
  },
  "adjudged_at": "2005-03-15",
  "created_at": "2016-02-07 06:47:39",
  "updated_at": "2016-02-07 06:47:39"
}