{
  "identify": "TPD-91-簡-1768-20020626-1",
  "court": {
    "name": "臺灣臺北地方法院",
    "code": "TPD"
  },
  "division": {
    "name": "刑事",
    "code": "M"
  },
  "year": 91,
  "word": "簡",
  "number": "1768",
  "jcheck": "1",
  "reason": "侵占遺失物",
  "content": "臺灣臺北地方法院刑事簡易判決                    九十一年度簡字第一七六八號\n    公  訴  人  臺灣臺北地方法院檢察署檢察官\n    被      告  乙○○\n右列被告因侵占遺失物案件，經檢察官聲請簡易判決處刑（九十一年度偵字第五八二\n四號），本院判決如左：\n    主  文\n乙○○意圖為自己不法之所有，而侵占離本人所持有之物，處罰金貳仟元。如易服勞\n役，以佰元折算壹日。\n    事實及理由\n一、本件除補充犯罪事實為被告乙○○於民國九十年六月下旬某日，在臺北市○○○\n    路國光客運股份有限公司臺北西站內垃圾桶旁拾獲甲○○所有於同年六月三十日\n    在臺北市國父紀念館失竊而離本人所持有之內有甲○○所有之身分證、車號ＱＵ\n    Ｃ三五二號機車行照各一張之男用皮包一只，竟意圖為自己不法之所有，將前揭\n    證件予以侵占入己外，其餘證據並所犯法條，均引用檢察官聲請簡易判決處刑書\n    （如附件）之記載。\n二、爰審酌被告並無前科記錄，素行良好，有台灣高等法院被告全國前案紀錄表在卷\n    可稽，於警訊及偵查中就前開犯罪事實供承不諱，犯後已知所悔悟態度良好，及\n    其因一時貪念臨時起意將前揭證件佔為己有之犯罪動機、目的、手段、所生危害\n    等一切情狀，量處如主文所示之刑，並諭知易服勞役之折算標準。\n三、據上論斷，依刑事訴訟法第四百四十九條第一項、第三項、第四百五十四條第二\n    項，刑法第三百三十七條、第四十二條第二項，罰金罰鍰提高標準條例第一條前\n    段，第二條，逕以簡易判決如主文所示之刑。\n如不服本判決，應於判決送達後十日內，向本院提出上訴狀。\n中      華      民      國      九十一    年      六    月    二十六    日\n                                  臺灣臺北地方法院刑事第五庭\n                                      審判長法官  廖紋妤\n                                            法官  朱夢蘋\n                                            法官  李家慧\n右正本證明與原本無異。\n                                          書記官  黃秀琴\n中      華      民      國      九十一    年      六    月    二十八    日\n附錄本案論罪科刑法條全文：\n刑法第三百三十七條：\n意圖為自己或第三人不法之所有，而侵占遺失物、漂流物或其他離本人所持有之物者\n，處五百元以下罰金。\n",
  "structure": {
    "main": "乙○○意圖為自己不法之所有，而侵占離本人所持有之物，處罰金貳仟元。如易服勞\n役，以佰元折算壹日。",
    "fact": "一、本件除補充犯罪事實為被告乙○○於民國九十年六月下旬某日，在臺北市○○○\n    路國光客運股份有限公司臺北西站內垃圾桶旁拾獲甲○○所有於同年六月三十日\n    在臺北市國父紀念館失竊而離本人所持有之內有甲○○所有之身分證、車號ＱＵ\n    Ｃ三五二號機車行照各一張之男用皮包一只，竟意圖為自己不法之所有，將前揭\n    證件予以侵占入己外，其餘證據並所犯法條，均引用檢察官聲請簡易判決處刑書\n    （如附件）之記載。\n二、爰審酌被告並無前科記錄，素行良好，有台灣高等法院被告全國前案紀錄表在卷\n    可稽，於警訊及偵查中就前開犯罪事實供承不諱，犯後已知所悔悟態度良好，及\n    其因一時貪念臨時起意將前揭證件佔為己有之犯罪動機、目的、手段、所生危害\n    等一切情狀，量處如主文所示之刑，並諭知易服勞役之折算標準。\n三、據上論斷，依刑事訴訟法第四百四十九條第一項、第三項、第四百五十四條第二\n    項，刑法第三百三十七條、第四十二條第二項，罰金罰鍰提高標準條例第一條前\n    段，第二條，逕以簡易判決如主文所示之刑。\n如不服本判決，應於判決送達後十日內，向本院提出上訴狀。",
    "reason": "一、本件除補充犯罪事實為被告乙○○於民國九十年六月下旬某日，在臺北市○○○\n    路國光客運股份有限公司臺北西站內垃圾桶旁拾獲甲○○所有於同年六月三十日\n    在臺北市國父紀念館失竊而離本人所持有之內有甲○○所有之身分證、車號ＱＵ\n    Ｃ三五二號機車行照各一張之男用皮包一只，竟意圖為自己不法之所有，將前揭\n    證件予以侵占入己外，其餘證據並所犯法條，均引用檢察官聲請簡易判決處刑書\n    （如附件）之記載。\n二、爰審酌被告並無前科記錄，素行良好，有台灣高等法院被告全國前案紀錄表在卷\n    可稽，於警訊及偵查中就前開犯罪事實供承不諱，犯後已知所悔悟態度良好，及\n    其因一時貪念臨時起意將前揭證件佔為己有之犯罪動機、目的、手段、所生危害\n    等一切情狀，量處如主文所示之刑，並諭知易服勞役之折算標準。\n三、據上論斷，依刑事訴訟法第四百四十九條第一項、第三項、第四百五十四條第二\n    項，刑法第三百三十七條、第四十二條第二項，罰金罰鍰提高標準條例第一條前\n    段，第二條，逕以簡易判決如主文所示之刑。\n如不服本判決，應於判決送達後十日內，向本院提出上訴狀。"
  },
  "search": "臺灣臺北地方法院刑事簡易判決九十一年度簡字第一七六八號公訴人臺灣臺北地方法院檢察署檢察官被告乙○○右列被告因侵占遺失物案件，經檢察官聲請簡易判決處刑（九十一年度偵字第五八二四號），本院判決如左：主文乙○○意圖為自己不法之所有，而侵占離本人所持有之物，處罰金貳仟元。如易服勞役，以佰元折算壹日。事實及理由一、本件除補充犯罪事實為被告乙○○於民國九十年六月下旬某日，在臺北市○○○路國光客運股份有限公司臺北西站內垃圾桶旁拾獲甲○○所有於同年六月三十日在臺北市國父紀念館失竊而離本人所持有之內有甲○○所有之身分證、車號ＱＵＣ三五二號機車行照各一張之男用皮包一只，竟意圖為自己不法之所有，將前揭證件予以侵占入己外，其餘證據並所犯法條，均引用檢察官聲請簡易判決處刑書（如附件）之記載。二、爰審酌被告並無前科記錄，素行良好，有台灣高等法院被告全國前案紀錄表在卷可稽，於警訊及偵查中就前開犯罪事實供承不諱，犯後已知所悔悟態度良好，及其因一時貪念臨時起意將前揭證件佔為己有之犯罪動機、目的、手段、所生危害等一切情狀，量處如主文所示之刑，並諭知易服勞役之折算標準。三、據上論斷，依刑事訴訟法第四百四十九條第一項、第三項、第四百五十四條第二項，刑法第三百三十七條、第四十二條第二項，罰金罰鍰提高標準條例第一條前段，第二條，逕以簡易判決如主文所示之刑。如不服本判決，應於判決送達後十日內，向本院提出上訴狀。中華民國九十一年六月二十六日臺灣臺北地方法院刑事第五庭審判長法官廖紋妤法官朱夢蘋法官李家慧右正本證明與原本無異。書記官黃秀琴中華民國九十一年六月二十八日附錄本案論罪科刑法條全文：刑法第三百三十七條：意圖為自己或第三人不法之所有，而侵占遺失物、漂流物或其他離本人所持有之物者，處五百元以下罰金。",
  "characters": {
    "judges": [

    ],
    "prosecutors": [

    ],
    "lawyers": [

    ],
    "clerks": [
      "黃秀琴"
    ],
    "plaintiffs": [

    ],
    "defendants": [
      "乙○○",
      "右列被告因侵占遺失物案件，經檢察官聲請簡易判決處刑（九十一年度偵字第五八二",
      "四號），本院判決如左："
    ],
    "prosecutor_office": [
      "臺灣臺北地方法院檢察署檢察官"
    ],
    "creditors": [

    ],
    "debtors": [

    ],
    "judicial_associate_officer": [

    ]
  },
  "adjudged_at": "2002-06-26",
  "created_at": "2016-02-05 15:05:11",
  "updated_at": "2016-02-05 15:05:11"
}