{
  "identify": "SLD-94-交簡-174-20051114-1",
  "court": {
    "name": "臺灣士林地方法院",
    "code": "SLD"
  },
  "division": {
    "name": "刑事",
    "code": "M"
  },
  "year": 94,
  "word": "交簡",
  "number": "174",
  "jcheck": "1",
  "reason": "公共危險",
  "content": "臺灣士林地方法院刑事簡易判決        94年度交簡字第174 號\n公  訴  人  臺灣士林地方法院檢察署檢察官\n被      告  甲○○\n上列被告因公共危險案件，經檢察官提起公訴（94年度偵字第87\n51號），本院訊問被告後（94年度交易字第256 號），經合議庭\n裁定認為宜由受命法官獨任逕以簡易判決處刑如下：\n    主  文\n甲○○服用酒類，不能安全駕駛動力交通工具而駕駛，處拘役伍\n拾日，如易科罰金以參佰元折算壹日。\n    事實及理由\n一、本件犯罪事實、證據及應適用之法條，除引用檢察官起訴書\n    之記載外，茲補充如下：本件被告甲○○因公共危險案件，\n    經檢察官依通常程序起訴，被告於檢察官偵查時未到庭應訊\n    ，惟其於警詢時所留年籍資料及自承有公共危險、賭博等前\n    科，各有警員調取之口卡片影本、前科表在卷供參，互核相\n    符；另因該口卡片上貼有被告之照片，於查獲當時，自經員\n    警核對確認人別無訛；又被告所駕駛之車號P36-003 號機車\n    ，係石素珠本人所有，該車主即係被告之配偶，亦有車籍作\n    業系統- 查詢認可資料、口卡片影本附卷可稽；本院傳訊被\n    告後，被告雖未到庭，然其家人接獲傳票後，已提出被告之\n    診斷證明書1 紙欲證明被告之健康狀況，準此，堪認被告之\n    人別無誤。而本院依被告在警詢中之自白及現存之證據，已\n    足認定其犯公共危險罪事證明確，應依法論科。\n二、依刑事訴訟法第449 條第2 項前段、第3 項、第454 條第2\n    項，刑法第185 條之3 、第41條第1 項，罰金罰鍰提高標準\n    條例第2 條，以簡易判決處刑如主文。\n三、如不服本判決，應於送達後10日內，向本院出上訴狀。\n中    華    民    國    94    年    11    月    14    日\n                  交通法庭法  官  黃潔茹\n以上正本證明與原本無異。\n如不服本判決應於判決送達後10日內向本院提出上訴狀。\n                          書記官  柳瑞宗\n中    華    民    國    94    年    11    月    14    日\n附錄本判決論罪科刑依據之法條：\n中華民國刑法第185條之3\n服用毒品、麻醉藥品、酒類或其他相類之物，不能安全駕駛動\n力交通工具而駕駛者，處一年以下有期徒刑、拘役或三萬元以下\n罰金。\n",
  "structure": {
    "main": "甲○○服用酒類，不能安全駕駛動力交通工具而駕駛，處拘役伍\n拾日，如易科罰金以參佰元折算壹日。",
    "fact": "一、本件犯罪事實、證據及應適用之法條，除引用檢察官起訴書\n    之記載外，茲補充如下：本件被告甲○○因公共危險案件，\n    經檢察官依通常程序起訴，被告於檢察官偵查時未到庭應訊\n    ，惟其於警詢時所留年籍資料及自承有公共危險、賭博等前\n    科，各有警員調取之口卡片影本、前科表在卷供參，互核相\n    符；另因該口卡片上貼有被告之照片，於查獲當時，自經員\n    警核對確認人別無訛；又被告所駕駛之車號P36-003 號機車\n    ，係石素珠本人所有，該車主即係被告之配偶，亦有車籍作\n    業系統- 查詢認可資料、口卡片影本附卷可稽；本院傳訊被\n    告後，被告雖未到庭，然其家人接獲傳票後，已提出被告之\n    診斷證明書1 紙欲證明被告之健康狀況，準此，堪認被告之\n    人別無誤。而本院依被告在警詢中之自白及現存之證據，已\n    足認定其犯公共危險罪事證明確，應依法論科。\n二、依刑事訴訟法第449 條第2 項前段、第3 項、第454 條第2\n    項，刑法第185 條之3 、第41條第1 項，罰金罰鍰提高標準\n    條例第2 條，以簡易判決處刑如主文。\n三、如不服本判決，應於送達後10日內，向本院出上訴狀。",
    "reason": "一、本件犯罪事實、證據及應適用之法條，除引用檢察官起訴書\n    之記載外，茲補充如下：本件被告甲○○因公共危險案件，\n    經檢察官依通常程序起訴，被告於檢察官偵查時未到庭應訊\n    ，惟其於警詢時所留年籍資料及自承有公共危險、賭博等前\n    科，各有警員調取之口卡片影本、前科表在卷供參，互核相\n    符；另因該口卡片上貼有被告之照片，於查獲當時，自經員\n    警核對確認人別無訛；又被告所駕駛之車號P36-003 號機車\n    ，係石素珠本人所有，該車主即係被告之配偶，亦有車籍作\n    業系統- 查詢認可資料、口卡片影本附卷可稽；本院傳訊被\n    告後，被告雖未到庭，然其家人接獲傳票後，已提出被告之\n    診斷證明書1 紙欲證明被告之健康狀況，準此，堪認被告之\n    人別無誤。而本院依被告在警詢中之自白及現存之證據，已\n    足認定其犯公共危險罪事證明確，應依法論科。\n二、依刑事訴訟法第449 條第2 項前段、第3 項、第454 條第2\n    項，刑法第185 條之3 、第41條第1 項，罰金罰鍰提高標準\n    條例第2 條，以簡易判決處刑如主文。\n三、如不服本判決，應於送達後10日內，向本院出上訴狀。"
  },
  "search": "臺灣士林地方法院刑事簡易判決94年度交簡字第174號公訴人臺灣士林地方法院檢察署檢察官被告甲○○上列被告因公共危險案件，經檢察官提起公訴（94年度偵字第8751號），本院訊問被告後（94年度交易字第256號），經合議庭裁定認為宜由受命法官獨任逕以簡易判決處刑如下：主文甲○○服用酒類，不能安全駕駛動力交通工具而駕駛，處拘役伍拾日，如易科罰金以參佰元折算壹日。事實及理由一、本件犯罪事實、證據及應適用之法條，除引用檢察官起訴書之記載外，茲補充如下：本件被告甲○○因公共危險案件，經檢察官依通常程序起訴，被告於檢察官偵查時未到庭應訊，惟其於警詢時所留年籍資料及自承有公共危險、賭博等前科，各有警員調取之口卡片影本、前科表在卷供參，互核相符；另因該口卡片上貼有被告之照片，於查獲當時，自經員警核對確認人別無訛；又被告所駕駛之車號P36-003號機車，係石素珠本人所有，該車主即係被告之配偶，亦有車籍作業系統-查詢認可資料、口卡片影本附卷可稽；本院傳訊被告後，被告雖未到庭，然其家人接獲傳票後，已提出被告之診斷證明書1紙欲證明被告之健康狀況，準此，堪認被告之人別無誤。而本院依被告在警詢中之自白及現存之證據，已足認定其犯公共危險罪事證明確，應依法論科。二、依刑事訴訟法第449條第2項前段、第3項、第454條第2項，刑法第185條之3、第41條第1項，罰金罰鍰提高標準條例第2條，以簡易判決處刑如主文。三、如不服本判決，應於送達後10日內，向本院出上訴狀。中華民國94年11月14日交通法庭法官黃潔茹以上正本證明與原本無異。如不服本判決應於判決送達後10日內向本院提出上訴狀。書記官柳瑞宗中華民國94年11月14日附錄本判決論罪科刑依據之法條：中華民國刑法第185條之3服用毒品、麻醉藥品、酒類或其他相類之物，不能安全駕駛動力交通工具而駕駛者，處一年以下有期徒刑、拘役或三萬元以下罰金。",
  "characters": {
    "judges": [
      "黃潔茹"
    ],
    "prosecutors": [

    ],
    "lawyers": [

    ],
    "clerks": [
      "柳瑞宗"
    ],
    "plaintiffs": [

    ],
    "defendants": [
      "甲○○"
    ],
    "prosecutor_office": [
      "臺灣士林地方法院檢察署檢察官"
    ],
    "creditors": [

    ],
    "debtors": [

    ],
    "judicial_associate_officer": [

    ]
  },
  "adjudged_at": "2005-11-14",
  "created_at": "2016-02-06 23:06:10",
  "updated_at": "2016-02-06 23:06:10"
}