{
  "identify": "SLD-94-簡-416-20051114-1",
  "court": {
    "name": "臺灣士林地方法院",
    "code": "SLD"
  },
  "division": {
    "name": "刑事",
    "code": "M"
  },
  "year": 94,
  "word": "簡",
  "number": "416",
  "jcheck": "1",
  "reason": "違反商標法",
  "content": "臺灣士林地方法院刑事簡易判決           94年度簡字第416號\n聲  請  人  臺灣士林地方法院檢察署檢察官\n被      告  甲○○\n選任辯護人  吳金棟    律師\n上列被告因違反商標法案件，經檢察官提起公訴（94年度偵字第\n294 號）後，被告自白犯罪，本院認為宜以簡易判決處刑，茲判\n決如下：\n    主      文\n甲○○連續明知為未得商標權人同意，於同一商品，使用相同之\n註冊商標商品而販賣，處拘役伍拾日，如易科罰金，以參佰元折\n算壹日，緩刑貳年。\n扣案如附表二所示之仿冒商品，均沒收。\n    事實及理由\n一、本案犯罪事實及證據除引用檢察官起訴書外，另補充或更正\n    ：(一)甲○○明知如附表一所示之商標圖樣，係法商克麗絲汀\n    迪奧高巧股份有限公司向經濟部智慧財產局申請註冊，而取\n    得於附表一所示之商標權期間內指定使用於附表一所示商品\n    之商標權。(二)詎竟基於意圖營利之概括犯意，自93年6 月間\n    某日起，將未得商標權人同意，於同一商品，使用相同之上\n    開註冊商標之項鍊、手鍊、手環等貴金屬珠寶商品，以每只\n    新臺幣（下同）100 元至200 元不等之價格，販售予不特定\n    之顧客牟利。(三)復有告訴代理人蔡立煇提出之查扣物估價表\n    及檢視書1 件附於偵查卷可參。(四)被告所販賣之仿冒項鍊、\n    手鍊、手環等貴金屬珠寶商品，均有相同如附表一所示之商\n    標圖樣，亦經本院當庭勘驗屬實，製有勘驗筆錄1 紙在本院\n    卷可考。\n二、核被告甲○○所為，係犯商標法第82條、第81條第1 款之明\n    知為未得商標權人同意，於同一商品，使用相同之註冊商標\n    商品而販賣罪。被告意圖販賣而陳列仿冒商標商品之低度行\n    為，為販賣仿冒商標商品之高度行為所吸收，不另論罪。被\n    告先後多次販賣仿冒商標商品之犯行，時間緊接，犯罪構成\n    要件相同，顯係基於概括犯意反覆為之，應依連續犯之規定\n    論以一罪，並依法加重其刑。\n三、扣案仿冒如附表二所示之貴金屬珠寶商品共計10件，係被告\n    犯商標法第82條之罪所販賣之物，不問屬於被告與否，均應\n    依商標法第83條之規定諭知沒收。\n四、被告前未曾受有期徒刑以上刑之宣告，有臺灣高等法院被告\n    全國前案紀錄表1 紙在卷可按，其因一時失慎，致罹刑章，\n    犯後坦承犯行，經此偵審程序並經科刑判決，當益知戒慎，\n    諒無再犯之虞，本院因認其所宣告之刑以暫不執行為適當，\n    爰併諭知緩刑二年，以勵自新，併觀後效。\n五、應依刑事訴訟法第451 條之1 第4 項第1 款、第449 條第2\n    項、第3 項、第454 條第2 項、第450 條第1 項，商標法第\n    82 條 、第81條第1 款、第83條，刑法第11條、第56條、第\n    41 條 第1 項、第74條第1 款，罰金罰鍰提高標準條例第2\n    條，逕以簡易判決量處如主文所示之刑。\n六、如不服本判決，得自收受送達之日起10日內，向本院提起上\n    訴。\n中    華    民    國    94    年    11    月    14    日\n                  刑事第五庭法  官  朱光仁\n以上正本證明與原本無異。\n                            書記官  陳佳伶\n中    華    民    國   941    年    11    月    15    日\n附錄本案論罪科刑法條：\n商標法第81條第1款\n未得商標權人或團體商標權人同意，有下列情形之一者，處三年\n以下有期徒刑、拘役或科或併科新臺幣20萬元以下罰金：\n  一、於同一商品或服務，使用相同之註冊商標或團體商標者。\n商標法第82條\n明知為前條商品而販賣、意圖販賣而陳列、輸出或輸入者，處一\n年以下有期徒刑、拘役或科或併科新臺幣5 萬元以下罰金。\n",
  "structure": {
    "main": "甲○○連續明知為未得商標權人同意，於同一商品，使用相同之\n註冊商標商品而販賣，處拘役伍拾日，如易科罰金，以參佰元折\n算壹日，緩刑貳年。\n扣案如附表二所示之仿冒商品，均沒收。",
    "fact": "一、本案犯罪事實及證據除引用檢察官起訴書外，另補充或更正\n    ：(一)甲○○明知如附表一所示之商標圖樣，係法商克麗絲汀\n    迪奧高巧股份有限公司向經濟部智慧財產局申請註冊，而取\n    得於附表一所示之商標權期間內指定使用於附表一所示商品\n    之商標權。(二)詎竟基於意圖營利之概括犯意，自93年6 月間\n    某日起，將未得商標權人同意，於同一商品，使用相同之上\n    開註冊商標之項鍊、手鍊、手環等貴金屬珠寶商品，以每只\n    新臺幣（下同）100 元至200 元不等之價格，販售予不特定\n    之顧客牟利。(三)復有告訴代理人蔡立煇提出之查扣物估價表\n    及檢視書1 件附於偵查卷可參。(四)被告所販賣之仿冒項鍊、\n    手鍊、手環等貴金屬珠寶商品，均有相同如附表一所示之商\n    標圖樣，亦經本院當庭勘驗屬實，製有勘驗筆錄1 紙在本院\n    卷可考。\n二、核被告甲○○所為，係犯商標法第82條、第81條第1 款之明\n    知為未得商標權人同意，於同一商品，使用相同之註冊商標\n    商品而販賣罪。被告意圖販賣而陳列仿冒商標商品之低度行\n    為，為販賣仿冒商標商品之高度行為所吸收，不另論罪。被\n    告先後多次販賣仿冒商標商品之犯行，時間緊接，犯罪構成\n    要件相同，顯係基於概括犯意反覆為之，應依連續犯之規定\n    論以一罪，並依法加重其刑。\n三、扣案仿冒如附表二所示之貴金屬珠寶商品共計10件，係被告\n    犯商標法第82條之罪所販賣之物，不問屬於被告與否，均應\n    依商標法第83條之規定諭知沒收。\n四、被告前未曾受有期徒刑以上刑之宣告，有臺灣高等法院被告\n    全國前案紀錄表1 紙在卷可按，其因一時失慎，致罹刑章，\n    犯後坦承犯行，經此偵審程序並經科刑判決，當益知戒慎，\n    諒無再犯之虞，本院因認其所宣告之刑以暫不執行為適當，\n    爰併諭知緩刑二年，以勵自新，併觀後效。\n五、應依刑事訴訟法第451 條之1 第4 項第1 款、第449 條第2\n    項、第3 項、第454 條第2 項、第450 條第1 項，商標法第\n    82 條 、第81條第1 款、第83條，刑法第11條、第56條、第\n    41 條 第1 項、第74條第1 款，罰金罰鍰提高標準條例第2\n    條，逕以簡易判決量處如主文所示之刑。\n六、如不服本判決，得自收受送達之日起10日內，向本院提起上\n    訴。",
    "reason": "一、本案犯罪事實及證據除引用檢察官起訴書外，另補充或更正\n    ：(一)甲○○明知如附表一所示之商標圖樣，係法商克麗絲汀\n    迪奧高巧股份有限公司向經濟部智慧財產局申請註冊，而取\n    得於附表一所示之商標權期間內指定使用於附表一所示商品\n    之商標權。(二)詎竟基於意圖營利之概括犯意，自93年6 月間\n    某日起，將未得商標權人同意，於同一商品，使用相同之上\n    開註冊商標之項鍊、手鍊、手環等貴金屬珠寶商品，以每只\n    新臺幣（下同）100 元至200 元不等之價格，販售予不特定\n    之顧客牟利。(三)復有告訴代理人蔡立煇提出之查扣物估價表\n    及檢視書1 件附於偵查卷可參。(四)被告所販賣之仿冒項鍊、\n    手鍊、手環等貴金屬珠寶商品，均有相同如附表一所示之商\n    標圖樣，亦經本院當庭勘驗屬實，製有勘驗筆錄1 紙在本院\n    卷可考。\n二、核被告甲○○所為，係犯商標法第82條、第81條第1 款之明\n    知為未得商標權人同意，於同一商品，使用相同之註冊商標\n    商品而販賣罪。被告意圖販賣而陳列仿冒商標商品之低度行\n    為，為販賣仿冒商標商品之高度行為所吸收，不另論罪。被\n    告先後多次販賣仿冒商標商品之犯行，時間緊接，犯罪構成\n    要件相同，顯係基於概括犯意反覆為之，應依連續犯之規定\n    論以一罪，並依法加重其刑。\n三、扣案仿冒如附表二所示之貴金屬珠寶商品共計10件，係被告\n    犯商標法第82條之罪所販賣之物，不問屬於被告與否，均應\n    依商標法第83條之規定諭知沒收。\n四、被告前未曾受有期徒刑以上刑之宣告，有臺灣高等法院被告\n    全國前案紀錄表1 紙在卷可按，其因一時失慎，致罹刑章，\n    犯後坦承犯行，經此偵審程序並經科刑判決，當益知戒慎，\n    諒無再犯之虞，本院因認其所宣告之刑以暫不執行為適當，\n    爰併諭知緩刑二年，以勵自新，併觀後效。\n五、應依刑事訴訟法第451 條之1 第4 項第1 款、第449 條第2\n    項、第3 項、第454 條第2 項、第450 條第1 項，商標法第\n    82 條 、第81條第1 款、第83條，刑法第11條、第56條、第\n    41 條 第1 項、第74條第1 款，罰金罰鍰提高標準條例第2\n    條，逕以簡易判決量處如主文所示之刑。\n六、如不服本判決，得自收受送達之日起10日內，向本院提起上\n    訴。"
  },
  "search": "臺灣士林地方法院刑事簡易判決94年度簡字第416號聲請人臺灣士林地方法院檢察署檢察官被告甲○○選任辯護人吳金棟律師上列被告因違反商標法案件，經檢察官提起公訴（94年度偵字第294號）後，被告自白犯罪，本院認為宜以簡易判決處刑，茲判決如下：主文甲○○連續明知為未得商標權人同意，於同一商品，使用相同之註冊商標商品而販賣，處拘役伍拾日，如易科罰金，以參佰元折算壹日，緩刑貳年。扣案如附表二所示之仿冒商品，均沒收。事實及理由一、本案犯罪事實及證據除引用檢察官起訴書外，另補充或更正：(一)甲○○明知如附表一所示之商標圖樣，係法商克麗絲汀迪奧高巧股份有限公司向經濟部智慧財產局申請註冊，而取得於附表一所示之商標權期間內指定使用於附表一所示商品之商標權。(二)詎竟基於意圖營利之概括犯意，自93年6月間某日起，將未得商標權人同意，於同一商品，使用相同之上開註冊商標之項鍊、手鍊、手環等貴金屬珠寶商品，以每只新臺幣（下同）100元至200元不等之價格，販售予不特定之顧客牟利。(三)復有告訴代理人蔡立煇提出之查扣物估價表及檢視書1件附於偵查卷可參。(四)被告所販賣之仿冒項鍊、手鍊、手環等貴金屬珠寶商品，均有相同如附表一所示之商標圖樣，亦經本院當庭勘驗屬實，製有勘驗筆錄1紙在本院卷可考。二、核被告甲○○所為，係犯商標法第82條、第81條第1款之明知為未得商標權人同意，於同一商品，使用相同之註冊商標商品而販賣罪。被告意圖販賣而陳列仿冒商標商品之低度行為，為販賣仿冒商標商品之高度行為所吸收，不另論罪。被告先後多次販賣仿冒商標商品之犯行，時間緊接，犯罪構成要件相同，顯係基於概括犯意反覆為之，應依連續犯之規定論以一罪，並依法加重其刑。三、扣案仿冒如附表二所示之貴金屬珠寶商品共計10件，係被告犯商標法第82條之罪所販賣之物，不問屬於被告與否，均應依商標法第83條之規定諭知沒收。四、被告前未曾受有期徒刑以上刑之宣告，有臺灣高等法院被告全國前案紀錄表1紙在卷可按，其因一時失慎，致罹刑章，犯後坦承犯行，經此偵審程序並經科刑判決，當益知戒慎，諒無再犯之虞，本院因認其所宣告之刑以暫不執行為適當，爰併諭知緩刑二年，以勵自新，併觀後效。五、應依刑事訴訟法第451條之1第4項第1款、第449條第2項、第3項、第454條第2項、第450條第1項，商標法第82條、第81條第1款、第83條，刑法第11條、第56條、第41條第1項、第74條第1款，罰金罰鍰提高標準條例第2條，逕以簡易判決量處如主文所示之刑。六、如不服本判決，得自收受送達之日起10日內，向本院提起上訴。中華民國94年11月14日刑事第五庭法官朱光仁以上正本證明與原本無異。書記官陳佳伶中華民國941年11月15日附錄本案論罪科刑法條：商標法第81條第1款未得商標權人或團體商標權人同意，有下列情形之一者，處三年以下有期徒刑、拘役或科或併科新臺幣20萬元以下罰金：一、於同一商品或服務，使用相同之註冊商標或團體商標者。商標法第82條明知為前條商品而販賣、意圖販賣而陳列、輸出或輸入者，處一年以下有期徒刑、拘役或科或併科新臺幣5萬元以下罰金。",
  "characters": {
    "judges": [
      "朱光仁"
    ],
    "prosecutors": [

    ],
    "lawyers": [

    ],
    "clerks": [
      "陳佳伶"
    ],
    "plaintiffs": [

    ],
    "defendants": [
      "甲○○"
    ],
    "prosecutor_office": [
      "臺灣士林地方法院檢察署檢察官"
    ],
    "creditors": [

    ],
    "debtors": [

    ],
    "judicial_associate_officer": [

    ]
  },
  "adjudged_at": "2005-11-14",
  "created_at": "2016-02-06 23:03:05",
  "updated_at": "2016-02-06 23:03:05"
}