{
  "identify": "TPB-92-訴-847-20040226-2",
  "court": {
    "name": "臺北高等行政法院",
    "code": "TPB"
  },
  "division": {
    "name": "行政",
    "code": "A"
  },
  "year": 92,
  "word": "訴",
  "number": "847",
  "jcheck": "2",
  "reason": "有關土地登記事務",
  "content": "臺北高等行政法院裁定                              九十二年度訴字第八四七號\n    原      告  甲○○○\n    訴訟代理人  乙○○\n    被      告  臺北市古亭地政事務所\n    代  表  人  沈永祥主任）.\n    訴訟代理人  丙○○\n右當事人間因有關土地登記事務事件，原告提起備位之訴。本院裁定如左：\n    主  文\n原告備位之訴駁回。\n訴訟費用由原告負擔。\n    理  由\n一、按訴訟種類應選擇正確，此為訴訟的實體裁判要件，不得以預備訴訟方式作為訴\n    訟種類之選擇，如逕提起之，應認其不備起訴要件，依行政訴訟法第一百零七條\n    第一項第十款後段規定裁定駁回之。\n二、本件原告備位聲明：「請求被告應賠償原告新臺幣陸佰捌拾萬元及自起訴狀繕本\n    送達翌日起至清償日止按年利率百分之五計算之利息。」理由略以：訴外人即詐\n    騙集團成員陸孝順就臺北市○○區○○段六小段五九九、五九九之一、五九九之\n    二、五九九之三地號土地及其上九九七建號建物，於九十年三月二十二日向被告\n    提出申請辦理所有權買賣移轉登記〔被告收件字號：中正(一)字第一八二八號〕，\n    被告於竟漏未審查該案之土地增值稅、契稅等根本未繳納，即率而辦理所有權移\n    轉予陸孝順及設定抵押權設定登記〔被告收件字號：中正(一)字第一九八八號〕，\n    嚴重損害原告之權益，惟系爭房地業經抵押權銀行聲請拍賣並拍定，被告有所疏\n    失，依土地法第六十八條規定應負賠償之責，為國家賠償性質，爰請求賠償新臺\n    幣六百八十萬元及利息云云。\n三、本件係課予義務訴訟為主訴（按：本院九十二年訴字第八四七號判決駁回之），\n    自不得單獨以國家賠償為備位請求，是本院認其備位之訴不合法，應予駁回。\n四、依行政訴訟法第一百零七條第一項第十款、第一百零四條，民事訴訟法第九十五\n    條、第七十八條，裁定如主文。\n中      華      民      國    九十三    年      二      月    二十六    日\n                 臺 北 高 等 行 政 法 院   第 六 庭\n                                    審 判 長 法  官  林樹埔\n                                             法  官  曹瑞卿\n                                             法  官  胡方新\n右為正本係照原本作成。\n如不服本裁定，應於送達後十日內向本院提出抗告狀（須按他造人數附繕本）。\n中      華      民      國    九十三    年      二      月    二十六    日\n                                             書記官  陳幸潔\n",
  "structure": {
    "main": "原告備位之訴駁回。\n訴訟費用由原告負擔。",
    "reason": "一、按訴訟種類應選擇正確，此為訴訟的實體裁判要件，不得以預備訴訟方式作為訴\n    訟種類之選擇，如逕提起之，應認其不備起訴要件，依行政訴訟法第一百零七條\n    第一項第十款後段規定裁定駁回之。\n二、本件原告備位聲明：「請求被告應賠償原告新臺幣陸佰捌拾萬元及自起訴狀繕本\n    送達翌日起至清償日止按年利率百分之五計算之利息。」理由略以：訴外人即詐\n    騙集團成員陸孝順就臺北市○○區○○段六小段五九九、五九九之一、五九九之\n    二、五九九之三地號土地及其上九九七建號建物，於九十年三月二十二日向被告\n    提出申請辦理所有權買賣移轉登記〔被告收件字號：中正(一)字第一八二八號〕，\n    被告於竟漏未審查該案之土地增值稅、契稅等根本未繳納，即率而辦理所有權移\n    轉予陸孝順及設定抵押權設定登記〔被告收件字號：中正(一)字第一九八八號〕，\n    嚴重損害原告之權益，惟系爭房地業經抵押權銀行聲請拍賣並拍定，被告有所疏\n    失，依土地法第六十八條規定應負賠償之責，為國家賠償性質，爰請求賠償新臺\n    幣六百八十萬元及利息云云。\n三、本件係課予義務訴訟為主訴（按：本院九十二年訴字第八四七號判決駁回之），\n    自不得單獨以國家賠償為備位請求，是本院認其備位之訴不合法，應予駁回。\n四、依行政訴訟法第一百零七條第一項第十款、第一百零四條，民事訴訟法第九十五\n    條、第七十八條，裁定如主文。"
  },
  "search": "臺北高等行政法院裁定九十二年度訴字第八四七號原告甲○○○訴訟代理人乙○○被告臺北市古亭地政事務所代表人沈永祥主任）.訴訟代理人丙○○右當事人間因有關土地登記事務事件，原告提起備位之訴。本院裁定如左：主文原告備位之訴駁回。訴訟費用由原告負擔。理由一、按訴訟種類應選擇正確，此為訴訟的實體裁判要件，不得以預備訴訟方式作為訴訟種類之選擇，如逕提起之，應認其不備起訴要件，依行政訴訟法第一百零七條第一項第十款後段規定裁定駁回之。二、本件原告備位聲明：「請求被告應賠償原告新臺幣陸佰捌拾萬元及自起訴狀繕本送達翌日起至清償日止按年利率百分之五計算之利息。」理由略以：訴外人即詐騙集團成員陸孝順就臺北市○○區○○段六小段五九九、五九九之一、五九九之二、五九九之三地號土地及其上九九七建號建物，於九十年三月二十二日向被告提出申請辦理所有權買賣移轉登記〔被告收件字號：中正(一)字第一八二八號〕，被告於竟漏未審查該案之土地增值稅、契稅等根本未繳納，即率而辦理所有權移轉予陸孝順及設定抵押權設定登記〔被告收件字號：中正(一)字第一九八八號〕，嚴重損害原告之權益，惟系爭房地業經抵押權銀行聲請拍賣並拍定，被告有所疏失，依土地法第六十八條規定應負賠償之責，為國家賠償性質，爰請求賠償新臺幣六百八十萬元及利息云云。三、本件係課予義務訴訟為主訴（按：本院九十二年訴字第八四七號判決駁回之），自不得單獨以國家賠償為備位請求，是本院認其備位之訴不合法，應予駁回。四、依行政訴訟法第一百零七條第一項第十款、第一百零四條，民事訴訟法第九十五條、第七十八條，裁定如主文。中華民國九十三年二月二十六日臺北高等行政法院第六庭審判長法官林樹埔法官曹瑞卿法官胡方新右為正本係照原本作成。如不服本裁定，應於送達後十日內向本院提出抗告狀（須按他造人數附繕本）。中華民國九十三年二月二十六日書記官陳幸潔",
  "characters": {
    "judges": [
      "林樹埔",
      "曹瑞卿",
      "胡方新"
    ],
    "prosecutors": [

    ],
    "lawyers": [

    ],
    "clerks": [
      "陳幸潔"
    ],
    "plaintiffs": [
      "甲"
    ],
    "defendants": [
      "臺北市古亭地政事務所"
    ],
    "prosecutor_office": [

    ],
    "creditors": [

    ],
    "debtors": [

    ],
    "judicial_associate_officer": [

    ]
  },
  "adjudged_at": "2004-02-26",
  "created_at": "2016-02-05 21:24:03",
  "updated_at": "2016-02-05 21:24:03"
}