{
  "identify": "KSD-92-附民-360-20040929-1",
  "court": {
    "name": "臺灣高雄地方法院",
    "code": "KSD"
  },
  "division": {
    "name": "刑事",
    "code": "M"
  },
  "year": 92,
  "word": "附民",
  "number": "360",
  "jcheck": "1",
  "reason": "誹謗",
  "content": "臺灣高雄地方法院刑事附帶民事訴訟判決            九十二年度附民字第三六號\n    原      告  甲○○\n    訴訟代理人  陳三兒律師\n    被      告  乙  ○\n    訴訟代理人  蘇吉雄律師\n                陳雅娟律師\n右列被告因九十二年度自字第二三九號誹謗案件，經原告提起附帶民事訴訟，請求損\n害賠償，本院判決如左：\n    主  文\n原告之訴及假執行之聲請均駁回。\n    事  實\n一、原告聲明及陳述：如附件刑事附帶民事起訴狀所載。\n二、被告聲明及陳述：原告之訴駁回，其餘引用刑事答辯狀所載。\n    理  由\n一、按刑事訴訟諭知無罪，免訴或不受理之判決者，對於附帶民事訴訟部份應以判決\n    駁回原告之訴，刑事訴訟法第五百零三條第一項前段定有明文。\n二、本件被告被訴誹謗一案，業經刑事判決諭知無罪在案，根據首揭規定，原告之訴\n    ，自應予以駁回，其假執行聲請，失所附麗，一併駁回。\n據上論斷，應依刑事訴訟法第五百零三條第一項前段，判決如主文。\n中      華      民      國    九十三    年      九      月    二十九    日\n                                臺灣高雄地方法院刑事第七庭\n                                  審判長法  官    曾逸誠\n                                        法  官    洪乙心\n                                        法  官    廖純卿\n右為正本，係照原本作成，證明與原本無異。\n如不服本判決，非對於刑事判決有上訴時，不得上訴，並應於送達後十日內，向本院\n提出上訴狀。\n                                        書記官    劉企萍\n中      華      民      國    九十三    年      十      月     四       日\n",
  "structure": {
    "main": "原告之訴及假執行之聲請均駁回。",
    "fact": "一、原告聲明及陳述：如附件刑事附帶民事起訴狀所載。\n二、被告聲明及陳述：原告之訴駁回，其餘引用刑事答辯狀所載。",
    "reason": "一、按刑事訴訟諭知無罪，免訴或不受理之判決者，對於附帶民事訴訟部份應以判決\n    駁回原告之訴，刑事訴訟法第五百零三條第一項前段定有明文。\n二、本件被告被訴誹謗一案，業經刑事判決諭知無罪在案，根據首揭規定，原告之訴\n    ，自應予以駁回，其假執行聲請，失所附麗，一併駁回。\n據上論斷，應依刑事訴訟法第五百零三條第一項前段，判決如主文。\n中      華      民      國    九十三    年      九      月    二十九    日\n                                臺灣高雄地方法院刑事第七庭\n                                  審判長法  官    曾逸誠\n                                        法  官    洪乙心\n                                        法  官    廖純卿\n右為正本，係照原本作成，證明與原本無異。\n如不服本判決，非對於刑事判決有上訴時，不得上訴，並應於送達後十日內，向本院\n提出上訴狀。\n                                        書記官    劉企萍"
  },
  "search": "臺灣高雄地方法院刑事附帶民事訴訟判決九十二年度附民字第三六號原告甲○○訴訟代理人陳三兒律師被告乙○訴訟代理人蘇吉雄律師陳雅娟律師右列被告因九十二年度自字第二三九號誹謗案件，經原告提起附帶民事訴訟，請求損害賠償，本院判決如左：主文原告之訴及假執行之聲請均駁回。事實一、原告聲明及陳述：如附件刑事附帶民事起訴狀所載。二、被告聲明及陳述：原告之訴駁回，其餘引用刑事答辯狀所載。理由一、按刑事訴訟諭知無罪，免訴或不受理之判決者，對於附帶民事訴訟部份應以判決駁回原告之訴，刑事訴訟法第五百零三條第一項前段定有明文。二、本件被告被訴誹謗一案，業經刑事判決諭知無罪在案，根據首揭規定，原告之訴，自應予以駁回，其假執行聲請，失所附麗，一併駁回。據上論斷，應依刑事訴訟法第五百零三條第一項前段，判決如主文。中華民國九十三年九月二十九日臺灣高雄地方法院刑事第七庭審判長法官曾逸誠法官洪乙心法官廖純卿右為正本，係照原本作成，證明與原本無異。如不服本判決，非對於刑事判決有上訴時，不得上訴，並應於送達後十日內，向本院提出上訴狀。書記官劉企萍中華民國九十三年十月四日",
  "characters": {
    "judges": [
      "曾逸誠",
      "洪乙心",
      "廖純卿"
    ],
    "prosecutors": [

    ],
    "lawyers": [
      "陳三兒",
      "蘇吉雄",
      "陳雅娟"
    ],
    "clerks": [
      "劉企萍"
    ],
    "plaintiffs": [
      "甲"
    ],
    "defendants": [
      "乙  ○"
    ],
    "prosecutor_office": [

    ],
    "creditors": [

    ],
    "debtors": [

    ],
    "judicial_associate_officer": [

    ]
  },
  "adjudged_at": "2004-09-29",
  "created_at": "2016-02-06 01:08:57",
  "updated_at": "2016-02-06 01:08:57"
}