{
  "identify": "TPB-93-訴更一-17-20040930-1",
  "court": {
    "name": "臺北高等行政法院",
    "code": "TPB"
  },
  "division": {
    "name": "行政",
    "code": "A"
  },
  "year": 93,
  "word": "訴更一",
  "number": "17",
  "jcheck": "1",
  "reason": "戒嚴時期不當叛亂暨匪諜審判案件補償金",
  "content": "臺北高等行政法院裁定                          九十三年度訴更一字第一七號\n    原      告     甲○\n    訴訟代理人     毛國樑律師\n    複 代 理人     孫志堅律師\n    被      告     行政院\n    代  表  人     游錫院.\n    參  加  人     乙○○\n    參  加  人     丙○○\n    參  加  人     丁○○\n右當事人間因戒嚴時期不當叛亂暨匪諜審判案件補償金事件，應命參加人獨立參加訴\n訟，本院裁定如左：\n    主  文\n乙○○、丙○○、丁○○應獨立參加本件被告之訴訟。\n    理  由\n一、按行政法院認為撤銷訴訟之結果，第三人之權利或法律上利益將受損害者，得依\n    職權命其獨立參加訴訟，行政訴訟法第四十二條第一項定有明文。\n二、本件乙○○及呂築妹於八十八年六月二十三日向財團法人戒嚴時期不當叛亂暨匪\n    諜審判案件補償基金會（以下簡稱補償基金會）申請戒嚴時期不當叛亂暨匪諜審\n    判案件補償金。經該會併同陳盛周八十八年五月四日申請案件審查，以八十九年\n    八月十九日（八九）基衡法寅字第六○二三號函復決議予以補償，補償範圍：執\n    行死刑，補償基數：六十個，金額新台幣（下同）六百萬元整，並依分配比例四\n    分之一（受裁判者陳盛妙之繼承人：乙○○、陳盛周、丙○○、甲○）核發一百\n    五十萬元整。乙○○以原告甲○出生後即由張亨收養，嗣因張亨死亡而由張來旺\n    收養，於陳盛妙死亡時，原告甲○並無法定繼承人資格，請取消甲○之補償金，\n    由受裁判人陳盛妙死後立嗣之子丁○○領取，或指定由陳盛周、丙○○及甲○三\n    人各提三分之一交予丁○○云云，提起訴願，經行政院決定將原處分撤銷，由補\n    償基金會於兩個月內另為適法之處分。原告不服，遂提起行政訴訟。本院認本件\n    訴訟之結果，將影響乙○○、丙○○、丁○○（陳盛周之繼承人）之法律上利益\n    ，有使渠等獨立參加訴訟之必要，爰依首揭法條規定，裁定如主文。\n中      華      民      國    九十三    年      九      月     三十     日\n                             臺 北 高 等 行 政 法 院   第 三 庭\n                                            審 判 長 法  官  鄭忠仁\n                                                     法  官  林育如\n                                                     法  官  侯東昇\n右為正本係照原本作成。\n不得抗告。\n中      華      民      國    九十三    年      九      月     三十     日\n                                                     書記官  蕭純純\n",
  "structure": {
    "main": "乙○○、丙○○、丁○○應獨立參加本件被告之訴訟。",
    "reason": "一、按行政法院認為撤銷訴訟之結果，第三人之權利或法律上利益將受損害者，得依\n    職權命其獨立參加訴訟，行政訴訟法第四十二條第一項定有明文。\n二、本件乙○○及呂築妹於八十八年六月二十三日向財團法人戒嚴時期不當叛亂暨匪\n    諜審判案件補償基金會（以下簡稱補償基金會）申請戒嚴時期不當叛亂暨匪諜審\n    判案件補償金。經該會併同陳盛周八十八年五月四日申請案件審查，以八十九年\n    八月十九日（八九）基衡法寅字第六○二三號函復決議予以補償，補償範圍：執\n    行死刑，補償基數：六十個，金額新台幣（下同）六百萬元整，並依分配比例四\n    分之一（受裁判者陳盛妙之繼承人：乙○○、陳盛周、丙○○、甲○）核發一百\n    五十萬元整。乙○○以原告甲○出生後即由張亨收養，嗣因張亨死亡而由張來旺\n    收養，於陳盛妙死亡時，原告甲○並無法定繼承人資格，請取消甲○之補償金，\n    由受裁判人陳盛妙死後立嗣之子丁○○領取，或指定由陳盛周、丙○○及甲○三\n    人各提三分之一交予丁○○云云，提起訴願，經行政院決定將原處分撤銷，由補\n    償基金會於兩個月內另為適法之處分。原告不服，遂提起行政訴訟。本院認本件\n    訴訟之結果，將影響乙○○、丙○○、丁○○（陳盛周之繼承人）之法律上利益\n    ，有使渠等獨立參加訴訟之必要，爰依首揭法條規定，裁定如主文。"
  },
  "search": "臺北高等行政法院裁定九十三年度訴更一字第一七號原告甲○訴訟代理人毛國樑律師複代理人孫志堅律師被告行政院代表人游錫院.參加人乙○○參加人丙○○參加人丁○○右當事人間因戒嚴時期不當叛亂暨匪諜審判案件補償金事件，應命參加人獨立參加訴訟，本院裁定如左：主文乙○○、丙○○、丁○○應獨立參加本件被告之訴訟。理由一、按行政法院認為撤銷訴訟之結果，第三人之權利或法律上利益將受損害者，得依職權命其獨立參加訴訟，行政訴訟法第四十二條第一項定有明文。二、本件乙○○及呂築妹於八十八年六月二十三日向財團法人戒嚴時期不當叛亂暨匪諜審判案件補償基金會（以下簡稱補償基金會）申請戒嚴時期不當叛亂暨匪諜審判案件補償金。經該會併同陳盛周八十八年五月四日申請案件審查，以八十九年八月十九日（八九）基衡法寅字第六○二三號函復決議予以補償，補償範圍：執行死刑，補償基數：六十個，金額新台幣（下同）六百萬元整，並依分配比例四分之一（受裁判者陳盛妙之繼承人：乙○○、陳盛周、丙○○、甲○）核發一百五十萬元整。乙○○以原告甲○出生後即由張亨收養，嗣因張亨死亡而由張來旺收養，於陳盛妙死亡時，原告甲○並無法定繼承人資格，請取消甲○之補償金，由受裁判人陳盛妙死後立嗣之子丁○○領取，或指定由陳盛周、丙○○及甲○三人各提三分之一交予丁○○云云，提起訴願，經行政院決定將原處分撤銷，由補償基金會於兩個月內另為適法之處分。原告不服，遂提起行政訴訟。本院認本件訴訟之結果，將影響乙○○、丙○○、丁○○（陳盛周之繼承人）之法律上利益，有使渠等獨立參加訴訟之必要，爰依首揭法條規定，裁定如主文。中華民國九十三年九月三十日臺北高等行政法院第三庭審判長法官鄭忠仁法官林育如法官侯東昇右為正本係照原本作成。不得抗告。中華民國九十三年九月三十日書記官蕭純純",
  "characters": {
    "judges": [
      "鄭忠仁",
      "林育如",
      "侯東昇"
    ],
    "prosecutors": [

    ],
    "lawyers": [
      "毛國樑",
      "孫志堅"
    ],
    "clerks": [
      "蕭純純"
    ],
    "plaintiffs": [
      "甲"
    ],
    "defendants": [
      "行政院"
    ],
    "prosecutor_office": [

    ],
    "creditors": [

    ],
    "debtors": [

    ],
    "judicial_associate_officer": [

    ]
  },
  "adjudged_at": "2004-09-30",
  "created_at": "2016-02-06 01:09:31",
  "updated_at": "2016-02-06 01:09:31"
}