{
  "identify": "TPD-93-交附民-80-20040929-1",
  "court": {
    "name": "臺灣臺北地方法院",
    "code": "TPD"
  },
  "division": {
    "name": "刑事",
    "code": "M"
  },
  "year": 93,
  "word": "交附民",
  "number": "80",
  "jcheck": "1",
  "reason": "因過失傷害案附帶民訴",
  "content": "臺灣臺北地方法院刑事附帶民事訴訟裁定            九十三年度交附民字第八○號\n    原      告  甲○○○\n    訴訟代理人  黃馨慧律師\n                孫櫻倩律師\n    被      告  乙○○\n右被告因本院九十三年度交簡字第一○三號過失傷害案件，經原告提起附帶民事訴訟\n。查其內容繁雜，非經長久之時日，不能終結其審判，爰依刑事訴訟法第五百零五條\n第一項、第五百零四條第一項前段，將本件附帶民事訴訟移送本院民事庭，特此裁定\n中      華      民      國    九十三    年      九      月    二十九    日\n                                     臺灣臺北地方法院交通法庭\n                                          審判長法  官 周祖民\n                                                法  官 鄧德倩\n                                                法  官 陳婷玉\n右正本證明與原本無異\n                                                書記官 陳弘文\n中      華      民      國    九十三    年      九      月    二十九    日\n",
  "structure": {
  },
  "search": "臺灣臺北地方法院刑事附帶民事訴訟裁定九十三年度交附民字第八○號原告甲○○○訴訟代理人黃馨慧律師孫櫻倩律師被告乙○○右被告因本院九十三年度交簡字第一○三號過失傷害案件，經原告提起附帶民事訴訟。查其內容繁雜，非經長久之時日，不能終結其審判，爰依刑事訴訟法第五百零五條第一項、第五百零四條第一項前段，將本件附帶民事訴訟移送本院民事庭，特此裁定中華民國九十三年九月二十九日臺灣臺北地方法院交通法庭審判長法官周祖民法官鄧德倩法官陳婷玉右正本證明與原本無異書記官陳弘文中華民國九十三年九月二十九日",
  "characters": {
    "judges": [
      "周祖民",
      "鄧德倩",
      "陳婷玉"
    ],
    "prosecutors": [

    ],
    "lawyers": [
      "黃馨慧",
      "孫櫻倩"
    ],
    "clerks": [
      "陳弘文"
    ],
    "plaintiffs": [
      "甲"
    ],
    "defendants": [
      "乙○○",
      "右被告因本院九十三年度交簡字第一○三號過失傷害案件，經原告提起附帶民事訴訟",
      "。查其內容繁雜，非經長久之時日，不能終結其審判，爰依刑事訴訟法第五百零五條",
      "第一項、第五百零四條第一項前段，將本件附帶民事訴訟移送本院民事庭，特此裁定",
      "中      華      民      國    九十三    年      九      月    二十九    日"
    ],
    "prosecutor_office": [

    ],
    "creditors": [

    ],
    "debtors": [

    ],
    "judicial_associate_officer": [

    ]
  },
  "adjudged_at": "2004-09-29",
  "created_at": "2016-02-06 01:21:41",
  "updated_at": "2016-02-06 01:21:41"
}