{
  "identify": "KSD-94-簡-156-20050117-1",
  "court": {
    "name": "臺灣高雄地方法院",
    "code": "KSD"
  },
  "division": {
    "name": "刑事",
    "code": "M"
  },
  "year": 94,
  "word": "簡",
  "number": "156",
  "jcheck": "1",
  "reason": "毒品危害防制條例",
  "content": "臺灣高雄地方法院刑事簡易判決                      九十四年度簡字第一五六號\n    聲  請  人  臺灣高雄地方法院檢察署檢察官\n    被      告  甲○○  男  三.\n右列被告因違反毒品危害防制條例案件，經檢察官聲請以簡易判決處刑（民國九十三\n年度毒偵字第五九九三號），本院判決如左：\n    主  文\n甲○○施用第二級毒品，處有期徒刑伍月，如易科罰金，以佰元折算壹日。扣案第\n二級毒品甲基安非他命壹包（驗前毛重零點伍公克，驗後毛重零點肆公克）沒收銷燬\n之。\n    事實及理由\n一、本件犯罪事實及證據均引用檢察官聲請簡易判決處刑書之記載（如附件）。\n二、按甲基安非他命係毒品危害防制條例第二條第二項所稱之第二級毒品，不得持有\n    、施用。次按犯毒品危害防制條例第十條施用第一級、第二級毒品之罪者，檢察\n    官應先將被告送勒戒處所觀察、勒戒，經觀察、勒戒後，認有繼續施用毒品傾向\n    者，應由檢察官聲請法院裁定令入戒治處所施以強制戒治，強制戒治期滿或交付\n    保護管束期滿，應由檢察官為不起訴之處分。依此為不起訴處分後，五年內再犯\n    第十條之罪，檢察官應依一般刑事訴訟程序予以起訴論罪科刑。此觀諸毒品危害\n    防制條例第二十條第一項、第二項、第二十三條規定自明。被告甲○○前既曾因\n    施用第二級毒品案件，經本院以八十九年度毒聲字第八七二五號裁定送觀察勒戒\n    ，經評定無繼續施用毒品傾向，而經台灣高雄地方法院檢察署於八十九年十一月\n    二十九日以八十九年度毒偵字第五七五一號不起訴處分確定在案，復因施用第二\n    級毒品案件，經本院九十二年度毒聲字第三一六八號裁定觀察勒戒，認有繼續施\n    用毒品傾向，經本院以九十二年度毒聲字第四七０七八號裁定強制戒治，並經本\n    院於九十二年九月二十四日，以九十二年度簡字第三四七五號判決判處有期徒刑\n    五月確定，此有臺灣高雄地方法院檢察署刑案資料查註紀錄表及臺灣高等法院被\n    告全國前案紀錄表附卷可稽，其於五年內再犯本件施用毒品案件，依前述規定應\n    予論罪科刑。核被告所為，係犯毒品危害防制條例第十條第二項之施用第二級毒\n    品罪，其持有第二級毒品甲基安非他命之低度行為，應為施用第二級毒品之高度\n    行為所吸收，不另論罪。爰審酌被告經觀察勒戒、強制戒治後，未戒絕毒品，再\n    施用第二級毒品安非他命，顯見其自制力不足，無法擺脫毒品，故應藉由刑罰之\n    執行，以收教化之功能，惟念及其犯罪後坦承犯行，態度尚可，並參以被告所犯\n    施用毒品乃自戕一己之身體健康，尚未害及他人等一切情狀，量處如主文所示之\n    刑，並諭知易科罰金之折算標準，以資懲儆。\n三、至被告於為警查獲時扣案之第二級毒品甲基安非他命一包（驗前毛重零點五公克\n    ，驗後毛重零點四公克），經送請高雄醫學大學附設中和紀念醫院鑑定，結果呈\n    甲基安非他命陽性反應，有該院九十三年十一月九日編號９３１１之９７號檢驗\n    報告書一紙附卷可參，是甲基安非他命一包係屬毒品危害防制條例所管制之毒品\n    ，且該包裝袋因與其內之毒品業已無法析離，應將之同視為第二級毒品無訛，從\n    而不問屬於犯人與否，爰均依毒品危害防制條例第十八條第一項前段之規定，沒\n    收銷燬之。\n四、依刑事訴訟法第四百四十九條第一項前段、第三項、第四百五十條第一項、第四\n    百五十四條第二項，毒品危害防制條例第十條第二項、第十八條第一項前段，刑\n    法第十一條、第四十一條第一項前段，罰金罰鍰提高標準條例第二條，逕以簡易\n    判決處如主文所示之刑。\n五、如不服本判決，得自收受送達之日起十日內，向本院提起上訴。\n中      華      民      國    九十四      年    一    月        十七    日\n                                臺灣高雄地方法院高雄簡易庭\n                                    法  官    林意芳\n右正本證明與原本無異。\n                                    書記官    曾秀鳳\n中      華      民      國    九十四      年    一    月        二十    日\n附錄本判決論罪之法條：\n毒品危害防制條例第十條\n施用第一級毒品者，處六月以上五年以下有期徒刑。\n施用第二級毒品者，處三年以下有期徒刑。\n",
  "structure": {
    "main": "甲○○施用第二級毒品，處有期徒刑伍月，如易科罰金，以佰元折算壹日。扣案第\n二級毒品甲基安非他命壹包（驗前毛重零點伍公克，驗後毛重零點肆公克）沒收銷燬\n之。",
    "fact": "一、本件犯罪事實及證據均引用檢察官聲請簡易判決處刑書之記載（如附件）。\n二、按甲基安非他命係毒品危害防制條例第二條第二項所稱之第二級毒品，不得持有\n    、施用。次按犯毒品危害防制條例第十條施用第一級、第二級毒品之罪者，檢察\n    官應先將被告送勒戒處所觀察、勒戒，經觀察、勒戒後，認有繼續施用毒品傾向\n    者，應由檢察官聲請法院裁定令入戒治處所施以強制戒治，強制戒治期滿或交付\n    保護管束期滿，應由檢察官為不起訴之處分。依此為不起訴處分後，五年內再犯\n    第十條之罪，檢察官應依一般刑事訴訟程序予以起訴論罪科刑。此觀諸毒品危害\n    防制條例第二十條第一項、第二項、第二十三條規定自明。被告甲○○前既曾因\n    施用第二級毒品案件，經本院以八十九年度毒聲字第八七二五號裁定送觀察勒戒\n    ，經評定無繼續施用毒品傾向，而經台灣高雄地方法院檢察署於八十九年十一月\n    二十九日以八十九年度毒偵字第五七五一號不起訴處分確定在案，復因施用第二\n    級毒品案件，經本院九十二年度毒聲字第三一六八號裁定觀察勒戒，認有繼續施\n    用毒品傾向，經本院以九十二年度毒聲字第四七０七八號裁定強制戒治，並經本\n    院於九十二年九月二十四日，以九十二年度簡字第三四七五號判決判處有期徒刑\n    五月確定，此有臺灣高雄地方法院檢察署刑案資料查註紀錄表及臺灣高等法院被\n    告全國前案紀錄表附卷可稽，其於五年內再犯本件施用毒品案件，依前述規定應\n    予論罪科刑。核被告所為，係犯毒品危害防制條例第十條第二項之施用第二級毒\n    品罪，其持有第二級毒品甲基安非他命之低度行為，應為施用第二級毒品之高度\n    行為所吸收，不另論罪。爰審酌被告經觀察勒戒、強制戒治後，未戒絕毒品，再\n    施用第二級毒品安非他命，顯見其自制力不足，無法擺脫毒品，故應藉由刑罰之\n    執行，以收教化之功能，惟念及其犯罪後坦承犯行，態度尚可，並參以被告所犯\n    施用毒品乃自戕一己之身體健康，尚未害及他人等一切情狀，量處如主文所示之\n    刑，並諭知易科罰金之折算標準，以資懲儆。\n三、至被告於為警查獲時扣案之第二級毒品甲基安非他命一包（驗前毛重零點五公克\n    ，驗後毛重零點四公克），經送請高雄醫學大學附設中和紀念醫院鑑定，結果呈\n    甲基安非他命陽性反應，有該院九十三年十一月九日編號９３１１之９７號檢驗\n    報告書一紙附卷可參，是甲基安非他命一包係屬毒品危害防制條例所管制之毒品\n    ，且該包裝袋因與其內之毒品業已無法析離，應將之同視為第二級毒品無訛，從\n    而不問屬於犯人與否，爰均依毒品危害防制條例第十八條第一項前段之規定，沒\n    收銷燬之。\n四、依刑事訴訟法第四百四十九條第一項前段、第三項、第四百五十條第一項、第四\n    百五十四條第二項，毒品危害防制條例第十條第二項、第十八條第一項前段，刑\n    法第十一條、第四十一條第一項前段，罰金罰鍰提高標準條例第二條，逕以簡易\n    判決處如主文所示之刑。\n五、如不服本判決，得自收受送達之日起十日內，向本院提起上訴。",
    "reason": "一、本件犯罪事實及證據均引用檢察官聲請簡易判決處刑書之記載（如附件）。\n二、按甲基安非他命係毒品危害防制條例第二條第二項所稱之第二級毒品，不得持有\n    、施用。次按犯毒品危害防制條例第十條施用第一級、第二級毒品之罪者，檢察\n    官應先將被告送勒戒處所觀察、勒戒，經觀察、勒戒後，認有繼續施用毒品傾向\n    者，應由檢察官聲請法院裁定令入戒治處所施以強制戒治，強制戒治期滿或交付\n    保護管束期滿，應由檢察官為不起訴之處分。依此為不起訴處分後，五年內再犯\n    第十條之罪，檢察官應依一般刑事訴訟程序予以起訴論罪科刑。此觀諸毒品危害\n    防制條例第二十條第一項、第二項、第二十三條規定自明。被告甲○○前既曾因\n    施用第二級毒品案件，經本院以八十九年度毒聲字第八七二五號裁定送觀察勒戒\n    ，經評定無繼續施用毒品傾向，而經台灣高雄地方法院檢察署於八十九年十一月\n    二十九日以八十九年度毒偵字第五七五一號不起訴處分確定在案，復因施用第二\n    級毒品案件，經本院九十二年度毒聲字第三一六八號裁定觀察勒戒，認有繼續施\n    用毒品傾向，經本院以九十二年度毒聲字第四七０七八號裁定強制戒治，並經本\n    院於九十二年九月二十四日，以九十二年度簡字第三四七五號判決判處有期徒刑\n    五月確定，此有臺灣高雄地方法院檢察署刑案資料查註紀錄表及臺灣高等法院被\n    告全國前案紀錄表附卷可稽，其於五年內再犯本件施用毒品案件，依前述規定應\n    予論罪科刑。核被告所為，係犯毒品危害防制條例第十條第二項之施用第二級毒\n    品罪，其持有第二級毒品甲基安非他命之低度行為，應為施用第二級毒品之高度\n    行為所吸收，不另論罪。爰審酌被告經觀察勒戒、強制戒治後，未戒絕毒品，再\n    施用第二級毒品安非他命，顯見其自制力不足，無法擺脫毒品，故應藉由刑罰之\n    執行，以收教化之功能，惟念及其犯罪後坦承犯行，態度尚可，並參以被告所犯\n    施用毒品乃自戕一己之身體健康，尚未害及他人等一切情狀，量處如主文所示之\n    刑，並諭知易科罰金之折算標準，以資懲儆。\n三、至被告於為警查獲時扣案之第二級毒品甲基安非他命一包（驗前毛重零點五公克\n    ，驗後毛重零點四公克），經送請高雄醫學大學附設中和紀念醫院鑑定，結果呈\n    甲基安非他命陽性反應，有該院九十三年十一月九日編號９３１１之９７號檢驗\n    報告書一紙附卷可參，是甲基安非他命一包係屬毒品危害防制條例所管制之毒品\n    ，且該包裝袋因與其內之毒品業已無法析離，應將之同視為第二級毒品無訛，從\n    而不問屬於犯人與否，爰均依毒品危害防制條例第十八條第一項前段之規定，沒\n    收銷燬之。\n四、依刑事訴訟法第四百四十九條第一項前段、第三項、第四百五十條第一項、第四\n    百五十四條第二項，毒品危害防制條例第十條第二項、第十八條第一項前段，刑\n    法第十一條、第四十一條第一項前段，罰金罰鍰提高標準條例第二條，逕以簡易\n    判決處如主文所示之刑。\n五、如不服本判決，得自收受送達之日起十日內，向本院提起上訴。"
  },
  "search": "臺灣高雄地方法院刑事簡易判決九十四年度簡字第一五六號聲請人臺灣高雄地方法院檢察署檢察官被告甲○○男三.右列被告因違反毒品危害防制條例案件，經檢察官聲請以簡易判決處刑（民國九十三年度毒偵字第五九九三號），本院判決如左：主文甲○○施用第二級毒品，處有期徒刑伍月，如易科罰金，以佰元折算壹日。扣案第二級毒品甲基安非他命壹包（驗前毛重零點伍公克，驗後毛重零點肆公克）沒收銷燬之。事實及理由一、本件犯罪事實及證據均引用檢察官聲請簡易判決處刑書之記載（如附件）。二、按甲基安非他命係毒品危害防制條例第二條第二項所稱之第二級毒品，不得持有、施用。次按犯毒品危害防制條例第十條施用第一級、第二級毒品之罪者，檢察官應先將被告送勒戒處所觀察、勒戒，經觀察、勒戒後，認有繼續施用毒品傾向者，應由檢察官聲請法院裁定令入戒治處所施以強制戒治，強制戒治期滿或交付保護管束期滿，應由檢察官為不起訴之處分。依此為不起訴處分後，五年內再犯第十條之罪，檢察官應依一般刑事訴訟程序予以起訴論罪科刑。此觀諸毒品危害防制條例第二十條第一項、第二項、第二十三條規定自明。被告甲○○前既曾因施用第二級毒品案件，經本院以八十九年度毒聲字第八七二五號裁定送觀察勒戒，經評定無繼續施用毒品傾向，而經台灣高雄地方法院檢察署於八十九年十一月二十九日以八十九年度毒偵字第五七五一號不起訴處分確定在案，復因施用第二級毒品案件，經本院九十二年度毒聲字第三一六八號裁定觀察勒戒，認有繼續施用毒品傾向，經本院以九十二年度毒聲字第四七０七八號裁定強制戒治，並經本院於九十二年九月二十四日，以九十二年度簡字第三四七五號判決判處有期徒刑五月確定，此有臺灣高雄地方法院檢察署刑案資料查註紀錄表及臺灣高等法院被告全國前案紀錄表附卷可稽，其於五年內再犯本件施用毒品案件，依前述規定應予論罪科刑。核被告所為，係犯毒品危害防制條例第十條第二項之施用第二級毒品罪，其持有第二級毒品甲基安非他命之低度行為，應為施用第二級毒品之高度行為所吸收，不另論罪。爰審酌被告經觀察勒戒、強制戒治後，未戒絕毒品，再施用第二級毒品安非他命，顯見其自制力不足，無法擺脫毒品，故應藉由刑罰之執行，以收教化之功能，惟念及其犯罪後坦承犯行，態度尚可，並參以被告所犯施用毒品乃自戕一己之身體健康，尚未害及他人等一切情狀，量處如主文所示之刑，並諭知易科罰金之折算標準，以資懲儆。三、至被告於為警查獲時扣案之第二級毒品甲基安非他命一包（驗前毛重零點五公克，驗後毛重零點四公克），經送請高雄醫學大學附設中和紀念醫院鑑定，結果呈甲基安非他命陽性反應，有該院九十三年十一月九日編號９３１１之９７號檢驗報告書一紙附卷可參，是甲基安非他命一包係屬毒品危害防制條例所管制之毒品，且該包裝袋因與其內之毒品業已無法析離，應將之同視為第二級毒品無訛，從而不問屬於犯人與否，爰均依毒品危害防制條例第十八條第一項前段之規定，沒收銷燬之。四、依刑事訴訟法第四百四十九條第一項前段、第三項、第四百五十條第一項、第四百五十四條第二項，毒品危害防制條例第十條第二項、第十八條第一項前段，刑法第十一條、第四十一條第一項前段，罰金罰鍰提高標準條例第二條，逕以簡易判決處如主文所示之刑。五、如不服本判決，得自收受送達之日起十日內，向本院提起上訴。中華民國九十四年一月十七日臺灣高雄地方法院高雄簡易庭法官林意芳右正本證明與原本無異。書記官曾秀鳳中華民國九十四年一月二十日附錄本判決論罪之法條：毒品危害防制條例第十條施用第一級毒品者，處六月以上五年以下有期徒刑。施用第二級毒品者，處三年以下有期徒刑。",
  "characters": {
    "judges": [
      "林意芳"
    ],
    "prosecutors": [

    ],
    "lawyers": [

    ],
    "clerks": [
      "曾秀鳳"
    ],
    "plaintiffs": [

    ],
    "defendants": [
      "甲○○  男  三.",
      "右列被告因違反毒品危害防制條例案件，經檢察官聲請以簡易判決處刑（民國九十三",
      "年度毒偵字第五九九三號），本院判決如左："
    ],
    "prosecutor_office": [
      "臺灣高雄地方法院檢察署檢察官"
    ],
    "creditors": [

    ],
    "debtors": [

    ],
    "judicial_associate_officer": [

    ]
  },
  "adjudged_at": "2005-01-17",
  "created_at": "2016-02-07 01:28:20",
  "updated_at": "2016-02-07 01:28:20"
}