{
  "identify": "KSD-100-聲-729-20110304-1",
  "court": {
    "name": "臺灣高雄地方法院",
    "code": "KSD"
  },
  "division": {
    "name": "刑事",
    "code": "M"
  },
  "year": 100,
  "word": "聲",
  "number": "729",
  "jcheck": "1",
  "reason": "聲請沒入保証金",
  "content": "臺灣高雄地方法院刑事裁定              100年度聲字第729號\n聲  請  人  臺灣高雄地方法院檢察署檢察官\n被      告  黃閎鑫\n(即受刑人)\n具  保  人  黃若綺\n上列具保人因受刑人違反槍砲彈藥刀械管制條例案件，經檢察官\n聲請沒入保證金（100年度執聲沒字第39 號），本院裁定如下：\n    主  文\n黃若綺繳納之保證金新臺幣參萬元，沒入之。\n    理  由\n一、聲請意旨略以：被告黃閎鑫因違反槍砲彈藥刀械管制條例案\n    件，經具保人黃若綺提出指定之保證金額新臺幣( 以下同)3\n    萬元後，經檢察官裁定許可釋放在案。茲因被告現已逃匿，\n    爰依刑事訴訟法第118 條第2 項、第1 項、第121 條第1 項\n    之規定，聲請沒入上開保證金等語。\n二、按具保之被告逃匿者，應命具保人繳納指定之保證金額，並\n    沒入之；保證金已繳納者，沒入之。前項規定，於檢察官依\n    第93條第3 項但書及第228 條第4 項命具保者，準用之。刑\n    事訴訟法第118 條定有明文。\n三、經查，被告黃閎鑫因違反槍砲彈藥刀械管制條例案件，經本\n    院以99年度重訴字第30號判處有期徒刑3 年4 月，併科罰金\n    新臺幣5 萬元，並經臺灣高等法院高雄分院以99年度上訴字\n    第1355號判決上訴駁回確定在案，此有上開刑事判決書2 份\n    、臺灣高等法院被告前案紀錄表1 份附卷可稽。茲因被告經\n    聲請人合法傳喚、拘提，無正當理由不到案，且具保人經通\n    知亦未遵期帶同被告到案，有執行傳票之送達證書1 紙、臺\n    灣高雄地方法院檢察署檢察官拘票1 紙、拘提報告書1 紙、\n    臺灣高雄地方法院檢察署刑事保證金收據、臺灣高雄地方法\n    院檢察署通知及追保函送達證書各1 紙附卷可稽。又被告現\n    未在監執行或受羈押，亦有臺灣高等法院在監在押全國紀錄\n    表1 份在卷可按，足見被告業已逃匿，揆諸上開規定，聲請\n    人之聲請自屬有據，應將具保人繳納之上開保證金沒入之。\n四、依刑事訴訟法第118 條第1 項、第2 項、第121 條第1 項規\n    定，裁定如主文。\n中    華    民    國    100    年    3     月    4    日\n                  刑事第三庭  法  官   李爭春\n以上正本證明與原本無異。\n如不服本裁定，應於收受送達後5 日內向本院提出抗告狀。\n中    華    民    國    100    年    3     月    4    日\n                              書記官   胡樂寧",
  "structure": {
    "main": "黃若綺繳納之保證金新臺幣參萬元，沒入之。",
    "reason": "一、聲請意旨略以：被告黃閎鑫因違反槍砲彈藥刀械管制條例案\n    件，經具保人黃若綺提出指定之保證金額新臺幣( 以下同)3\n    萬元後，經檢察官裁定許可釋放在案。茲因被告現已逃匿，\n    爰依刑事訴訟法第118 條第2 項、第1 項、第121 條第1 項\n    之規定，聲請沒入上開保證金等語。\n二、按具保之被告逃匿者，應命具保人繳納指定之保證金額，並\n    沒入之；保證金已繳納者，沒入之。前項規定，於檢察官依\n    第93條第3 項但書及第228 條第4 項命具保者，準用之。刑\n    事訴訟法第118 條定有明文。\n三、經查，被告黃閎鑫因違反槍砲彈藥刀械管制條例案件，經本\n    院以99年度重訴字第30號判處有期徒刑3 年4 月，併科罰金\n    新臺幣5 萬元，並經臺灣高等法院高雄分院以99年度上訴字\n    第1355號判決上訴駁回確定在案，此有上開刑事判決書2 份\n    、臺灣高等法院被告前案紀錄表1 份附卷可稽。茲因被告經\n    聲請人合法傳喚、拘提，無正當理由不到案，且具保人經通\n    知亦未遵期帶同被告到案，有執行傳票之送達證書1 紙、臺\n    灣高雄地方法院檢察署檢察官拘票1 紙、拘提報告書1 紙、\n    臺灣高雄地方法院檢察署刑事保證金收據、臺灣高雄地方法\n    院檢察署通知及追保函送達證書各1 紙附卷可稽。又被告現\n    未在監執行或受羈押，亦有臺灣高等法院在監在押全國紀錄\n    表1 份在卷可按，足見被告業已逃匿，揆諸上開規定，聲請\n    人之聲請自屬有據，應將具保人繳納之上開保證金沒入之。\n四、依刑事訴訟法第118 條第1 項、第2 項、第121 條第1 項規\n    定，裁定如主文。"
  },
  "search": "臺灣高雄地方法院刑事裁定100年度聲字第729號聲請人臺灣高雄地方法院檢察署檢察官被告黃閎鑫(即受刑人)具保人黃若綺上列具保人因受刑人違反槍砲彈藥刀械管制條例案件，經檢察官聲請沒入保證金（100年度執聲沒字第39號），本院裁定如下：主文黃若綺繳納之保證金新臺幣參萬元，沒入之。理由一、聲請意旨略以：被告黃閎鑫因違反槍砲彈藥刀械管制條例案件，經具保人黃若綺提出指定之保證金額新臺幣(以下同)3萬元後，經檢察官裁定許可釋放在案。茲因被告現已逃匿，爰依刑事訴訟法第118條第2項、第1項、第121條第1項之規定，聲請沒入上開保證金等語。二、按具保之被告逃匿者，應命具保人繳納指定之保證金額，並沒入之；保證金已繳納者，沒入之。前項規定，於檢察官依第93條第3項但書及第228條第4項命具保者，準用之。刑事訴訟法第118條定有明文。三、經查，被告黃閎鑫因違反槍砲彈藥刀械管制條例案件，經本院以99年度重訴字第30號判處有期徒刑3年4月，併科罰金新臺幣5萬元，並經臺灣高等法院高雄分院以99年度上訴字第1355號判決上訴駁回確定在案，此有上開刑事判決書2份、臺灣高等法院被告前案紀錄表1份附卷可稽。茲因被告經聲請人合法傳喚、拘提，無正當理由不到案，且具保人經通知亦未遵期帶同被告到案，有執行傳票之送達證書1紙、臺灣高雄地方法院檢察署檢察官拘票1紙、拘提報告書1紙、臺灣高雄地方法院檢察署刑事保證金收據、臺灣高雄地方法院檢察署通知及追保函送達證書各1紙附卷可稽。又被告現未在監執行或受羈押，亦有臺灣高等法院在監在押全國紀錄表1份在卷可按，足見被告業已逃匿，揆諸上開規定，聲請人之聲請自屬有據，應將具保人繳納之上開保證金沒入之。四、依刑事訴訟法第118條第1項、第2項、第121條第1項規定，裁定如主文。中華民國100年3月4日刑事第三庭法官李爭春以上正本證明與原本無異。如不服本裁定，應於收受送達後5日內向本院提出抗告狀。中華民國100年3月4日書記官胡樂寧",
  "characters": {
    "judges": [
      "李爭春"
    ],
    "prosecutors": [

    ],
    "lawyers": [

    ],
    "clerks": [

    ],
    "plaintiffs": [

    ],
    "defendants": [
      "黃閎鑫",
      "(即受刑人)",
      "具  保  人  黃若綺"
    ],
    "prosecutor_office": [
      "臺灣高雄地方法院檢察署檢察官"
    ],
    "creditors": [

    ],
    "debtors": [

    ],
    "judicial_associate_officer": [

    ]
  },
  "adjudged_at": "2011-03-04",
  "created_at": "2016-02-13 20:05:04",
  "updated_at": "2016-02-13 20:05:04"
}