{
  "identify": "TYD-100-桃簡-188-20110119-1",
  "court": {
    "name": "臺灣桃園地方法院",
    "code": "TYD"
  },
  "division": {
    "name": "刑事",
    "code": "M"
  },
  "year": 100,
  "word": "桃簡",
  "number": "188",
  "jcheck": "1",
  "reason": "毒品危害防制條例",
  "content": "臺灣桃園地方法院刑事簡易判決        100年度桃簡字第188號\n聲  請  人  臺灣桃園地方法院檢察署檢察官\n被      告  饒永廷\n上列被告因毒品危害防制條例案件，經檢察官聲請以簡易判決處\n刑（99年度毒偵字第6367號），本院判決如下：\n    主  文\n饒永廷施用第二級毒品，處有期徒刑參月，如易科罰金，以新臺\n幣壹仟元折算壹日。\n    事實及理由\n一、本件犯罪事實、證據及應適用之法條，除引用檢察官聲請簡\n    易判決處刑書（如附件）之記載外，並補充：按甲基安非他\n    命經口服投與後約百分之70於24小時內自尿中排出，約百分\n    之90於96小時內自尿中排出，由於目前國內尿液中甲基安非\n    他命之檢驗僅為鑑定其是否呈陽性反應尚未定其含量，且甲\n    基安非他命成分之檢出與其投與方式、投與量、個人體質、\n    採尿時間與檢測儀器之精密度等諸多因素有關，因此僅憑尿\n    液中呈甲基安非他命陽性反應，並無法確實推算吸食時間距\n    採集時間之長短，惟依上述資料推斷，最長可能不會超過4\n    日（按即96小時），業據行政院衛生署藥物食品檢驗局民國\n    81年2 月8 日（81）藥檢壹字第001156號函解釋在案，被告\n    饒永廷本件所採之尿液，經檢驗結果既有甲基安非他命陽性\n    反應，足證被告於99年10月10日上午10時30分許採尿時往前\n    回溯96小時內之某時，有施用第二級毒品甲基安非他命一次\n    之犯行無疑，事證明確，被告犯行堪以認定。被告施用第二\n    級毒品甲基安非他命前之持有第二級毒品甲基安非他命之低\n    度行為，應為施用之高度行為所吸收，不另論罪。\n二、依刑事訴訟法第449 條第1 項前段、第3 項、第454 條第2\n    項，毒品危害防制條例第10條第2 項，刑法第11條前段、第\n    41條第1 項前段，逕以簡易判決處如主文所示之刑。\n如不服本件判決，得自判決送達後10日內，向本院提起上訴。\n中    華    民    國   100    年    1     月    19    日\n                    刑事第一庭  法  官  曾家貽\n以上正本證明與原本無異。\n如不服本判決，應於判決送達後10日內向本院提出上訴狀（應附\n繕本）。\n                                書記官  洪明煥\n中    華    民    國   100    年    1     月    21    日\n附錄本判決論罪科刑依據之法條：\n毒品危害防制條例第10條\n施用第一級毒品者，處6 月以上5 年以下有期徒刑。\n施用第二級毒品者，處3 年以下有期徒刑。",
  "structure": {
    "main": "饒永廷施用第二級毒品，處有期徒刑參月，如易科罰金，以新臺\n幣壹仟元折算壹日。",
    "fact": "一、本件犯罪事實、證據及應適用之法條，除引用檢察官聲請簡\n    易判決處刑書（如附件）之記載外，並補充：按甲基安非他\n    命經口服投與後約百分之70於24小時內自尿中排出，約百分\n    之90於96小時內自尿中排出，由於目前國內尿液中甲基安非\n    他命之檢驗僅為鑑定其是否呈陽性反應尚未定其含量，且甲\n    基安非他命成分之檢出與其投與方式、投與量、個人體質、\n    採尿時間與檢測儀器之精密度等諸多因素有關，因此僅憑尿\n    液中呈甲基安非他命陽性反應，並無法確實推算吸食時間距\n    採集時間之長短，惟依上述資料推斷，最長可能不會超過4\n    日（按即96小時），業據行政院衛生署藥物食品檢驗局民國\n    81年2 月8 日（81）藥檢壹字第001156號函解釋在案，被告\n    饒永廷本件所採之尿液，經檢驗結果既有甲基安非他命陽性\n    反應，足證被告於99年10月10日上午10時30分許採尿時往前\n    回溯96小時內之某時，有施用第二級毒品甲基安非他命一次\n    之犯行無疑，事證明確，被告犯行堪以認定。被告施用第二\n    級毒品甲基安非他命前之持有第二級毒品甲基安非他命之低\n    度行為，應為施用之高度行為所吸收，不另論罪。\n二、依刑事訴訟法第449 條第1 項前段、第3 項、第454 條第2\n    項，毒品危害防制條例第10條第2 項，刑法第11條前段、第\n    41條第1 項前段，逕以簡易判決處如主文所示之刑。\n如不服本件判決，得自判決送達後10日內，向本院提起上訴。",
    "reason": "一、本件犯罪事實、證據及應適用之法條，除引用檢察官聲請簡\n    易判決處刑書（如附件）之記載外，並補充：按甲基安非他\n    命經口服投與後約百分之70於24小時內自尿中排出，約百分\n    之90於96小時內自尿中排出，由於目前國內尿液中甲基安非\n    他命之檢驗僅為鑑定其是否呈陽性反應尚未定其含量，且甲\n    基安非他命成分之檢出與其投與方式、投與量、個人體質、\n    採尿時間與檢測儀器之精密度等諸多因素有關，因此僅憑尿\n    液中呈甲基安非他命陽性反應，並無法確實推算吸食時間距\n    採集時間之長短，惟依上述資料推斷，最長可能不會超過4\n    日（按即96小時），業據行政院衛生署藥物食品檢驗局民國\n    81年2 月8 日（81）藥檢壹字第001156號函解釋在案，被告\n    饒永廷本件所採之尿液，經檢驗結果既有甲基安非他命陽性\n    反應，足證被告於99年10月10日上午10時30分許採尿時往前\n    回溯96小時內之某時，有施用第二級毒品甲基安非他命一次\n    之犯行無疑，事證明確，被告犯行堪以認定。被告施用第二\n    級毒品甲基安非他命前之持有第二級毒品甲基安非他命之低\n    度行為，應為施用之高度行為所吸收，不另論罪。\n二、依刑事訴訟法第449 條第1 項前段、第3 項、第454 條第2\n    項，毒品危害防制條例第10條第2 項，刑法第11條前段、第\n    41條第1 項前段，逕以簡易判決處如主文所示之刑。\n如不服本件判決，得自判決送達後10日內，向本院提起上訴。"
  },
  "search": "臺灣桃園地方法院刑事簡易判決100年度桃簡字第188號聲請人臺灣桃園地方法院檢察署檢察官被告饒永廷上列被告因毒品危害防制條例案件，經檢察官聲請以簡易判決處刑（99年度毒偵字第6367號），本院判決如下：主文饒永廷施用第二級毒品，處有期徒刑參月，如易科罰金，以新臺幣壹仟元折算壹日。事實及理由一、本件犯罪事實、證據及應適用之法條，除引用檢察官聲請簡易判決處刑書（如附件）之記載外，並補充：按甲基安非他命經口服投與後約百分之70於24小時內自尿中排出，約百分之90於96小時內自尿中排出，由於目前國內尿液中甲基安非他命之檢驗僅為鑑定其是否呈陽性反應尚未定其含量，且甲基安非他命成分之檢出與其投與方式、投與量、個人體質、採尿時間與檢測儀器之精密度等諸多因素有關，因此僅憑尿液中呈甲基安非他命陽性反應，並無法確實推算吸食時間距採集時間之長短，惟依上述資料推斷，最長可能不會超過4日（按即96小時），業據行政院衛生署藥物食品檢驗局民國81年2月8日（81）藥檢壹字第001156號函解釋在案，被告饒永廷本件所採之尿液，經檢驗結果既有甲基安非他命陽性反應，足證被告於99年10月10日上午10時30分許採尿時往前回溯96小時內之某時，有施用第二級毒品甲基安非他命一次之犯行無疑，事證明確，被告犯行堪以認定。被告施用第二級毒品甲基安非他命前之持有第二級毒品甲基安非他命之低度行為，應為施用之高度行為所吸收，不另論罪。二、依刑事訴訟法第449條第1項前段、第3項、第454條第2項，毒品危害防制條例第10條第2項，刑法第11條前段、第41條第1項前段，逕以簡易判決處如主文所示之刑。如不服本件判決，得自判決送達後10日內，向本院提起上訴。中華民國100年1月19日刑事第一庭法官曾家貽以上正本證明與原本無異。如不服本判決，應於判決送達後10日內向本院提出上訴狀（應附繕本）。書記官洪明煥中華民國100年1月21日附錄本判決論罪科刑依據之法條：毒品危害防制條例第10條施用第一級毒品者，處6月以上5年以下有期徒刑。施用第二級毒品者，處3年以下有期徒刑。",
  "characters": {
    "judges": [
      "曾家貽"
    ],
    "prosecutors": [

    ],
    "lawyers": [

    ],
    "clerks": [
      "洪明煥"
    ],
    "plaintiffs": [

    ],
    "defendants": [
      "饒永廷"
    ],
    "prosecutor_office": [
      "臺灣桃園地方法院檢察署檢察官"
    ],
    "creditors": [

    ],
    "debtors": [

    ],
    "judicial_associate_officer": [

    ]
  },
  "adjudged_at": "2011-01-19",
  "created_at": "2016-02-13 02:58:54",
  "updated_at": "2016-02-13 02:58:54"
}