{
  "identify": "CHD-100-交簡-1871-20110916-1",
  "court": {
    "name": "臺灣彰化地方法院",
    "code": "CHD"
  },
  "division": {
    "name": "刑事",
    "code": "M"
  },
  "year": 100,
  "word": "交簡",
  "number": "1871",
  "jcheck": "1",
  "reason": "公共危險",
  "content": "臺灣彰化地方法院刑事簡易判決       100年度交簡字第1871號\n聲  請  人  臺灣彰化地方法院檢察署檢察官\n被      告  謝其展\n上列被告因公共危險案件，經檢察官聲請以簡易判決處刑（100\n年度偵字第6948號），本院判決如下：\n    主  文\n謝其展服用酒類，不能安全駕駛動力交通工具而駕駛，處拘役伍\n拾日，如易科罰金，以新臺幣壹仟元折算壹日。\n    犯罪事實及理由\n一、本件犯罪事實及證據，均引用臺灣彰化地方法院檢察署檢察\n    官聲請簡易判決處刑書之記載（如附件）。\n二、核被告謝其展所為，係犯刑法第185 條之3 之公共危險罪。\n    。爰審酌被告本次酒後駕車行為確實有害於交通安全，對他\n    人生命、身體、財產造成莫大危險，暨其犯後坦承犯行之態\n    度、智識程度、生活狀況、騎乘機車酒測值達每公升0.56毫\n    克，併因此而肇事之犯罪情節等一切情狀，量處如主文所示\n    之刑，並諭知易科罰金之折算標準。\n三、依刑事訴訟法第449 條第1 項前段、第3 項、第454 條第2\n    項，刑法第185 條之3 、第41條第1 項前段，刑法施行法第\n    1 條之1 第1 項，逕以簡易判決處刑如主文。\n四、如不服本判決，應於判決書送達之翌日起10日內，向本院提\n    出上訴狀（應附繕本），上訴於本院合議庭。\n中    華    民    國   100    年    9     月    16    日\n                  刑事第五庭          法  官  陳德池\n以上正本證明與原本無異。\n如不服本件判決，得自收受送達之翌日起10日，表明上訴理由，\n向本院提起上訴狀（須附繕本）。\n中    華    民    國   100    年    9     月    16    日\n                                      書記官  黃國源\n附錄論罪科刑法條：\n中華民國刑法第185 條之3\n服用毒品、麻醉藥品、酒類或其他相類之物，不能安全駕駛動力\n交通工具而駕駛者，處1 年以下有期徒刑、拘役或科或併科15萬\n元以下罰金。\n附件：臺灣彰化地方法院檢察署檢察官100 年度偵字第6948號聲\n      請簡易判決處刑書1 份。",
  "structure": {
    "main": "謝其展服用酒類，不能安全駕駛動力交通工具而駕駛，處拘役伍\n拾日，如易科罰金，以新臺幣壹仟元折算壹日。",
    "fact": "一、本件犯罪事實及證據，均引用臺灣彰化地方法院檢察署檢察\n    官聲請簡易判決處刑書之記載（如附件）。\n二、核被告謝其展所為，係犯刑法第185 條之3 之公共危險罪。\n    。爰審酌被告本次酒後駕車行為確實有害於交通安全，對他\n    人生命、身體、財產造成莫大危險，暨其犯後坦承犯行之態\n    度、智識程度、生活狀況、騎乘機車酒測值達每公升0.56毫\n    克，併因此而肇事之犯罪情節等一切情狀，量處如主文所示\n    之刑，並諭知易科罰金之折算標準。\n三、依刑事訴訟法第449 條第1 項前段、第3 項、第454 條第2\n    項，刑法第185 條之3 、第41條第1 項前段，刑法施行法第\n    1 條之1 第1 項，逕以簡易判決處刑如主文。\n四、如不服本判決，應於判決書送達之翌日起10日內，向本院提\n    出上訴狀（應附繕本），上訴於本院合議庭。",
    "reason": "一、本件犯罪事實及證據，均引用臺灣彰化地方法院檢察署檢察\n    官聲請簡易判決處刑書之記載（如附件）。\n二、核被告謝其展所為，係犯刑法第185 條之3 之公共危險罪。\n    。爰審酌被告本次酒後駕車行為確實有害於交通安全，對他\n    人生命、身體、財產造成莫大危險，暨其犯後坦承犯行之態\n    度、智識程度、生活狀況、騎乘機車酒測值達每公升0.56毫\n    克，併因此而肇事之犯罪情節等一切情狀，量處如主文所示\n    之刑，並諭知易科罰金之折算標準。\n三、依刑事訴訟法第449 條第1 項前段、第3 項、第454 條第2\n    項，刑法第185 條之3 、第41條第1 項前段，刑法施行法第\n    1 條之1 第1 項，逕以簡易判決處刑如主文。\n四、如不服本判決，應於判決書送達之翌日起10日內，向本院提\n    出上訴狀（應附繕本），上訴於本院合議庭。"
  },
  "search": "臺灣彰化地方法院刑事簡易判決100年度交簡字第1871號聲請人臺灣彰化地方法院檢察署檢察官被告謝其展上列被告因公共危險案件，經檢察官聲請以簡易判決處刑（100年度偵字第6948號），本院判決如下：主文謝其展服用酒類，不能安全駕駛動力交通工具而駕駛，處拘役伍拾日，如易科罰金，以新臺幣壹仟元折算壹日。犯罪事實及理由一、本件犯罪事實及證據，均引用臺灣彰化地方法院檢察署檢察官聲請簡易判決處刑書之記載（如附件）。二、核被告謝其展所為，係犯刑法第185條之3之公共危險罪。。爰審酌被告本次酒後駕車行為確實有害於交通安全，對他人生命、身體、財產造成莫大危險，暨其犯後坦承犯行之態度、智識程度、生活狀況、騎乘機車酒測值達每公升0.56毫克，併因此而肇事之犯罪情節等一切情狀，量處如主文所示之刑，並諭知易科罰金之折算標準。三、依刑事訴訟法第449條第1項前段、第3項、第454條第2項，刑法第185條之3、第41條第1項前段，刑法施行法第1條之1第1項，逕以簡易判決處刑如主文。四、如不服本判決，應於判決書送達之翌日起10日內，向本院提出上訴狀（應附繕本），上訴於本院合議庭。中華民國100年9月16日刑事第五庭法官陳德池以上正本證明與原本無異。如不服本件判決，得自收受送達之翌日起10日，表明上訴理由，向本院提起上訴狀（須附繕本）。中華民國100年9月16日書記官黃國源附錄論罪科刑法條：中華民國刑法第185條之3服用毒品、麻醉藥品、酒類或其他相類之物，不能安全駕駛動力交通工具而駕駛者，處1年以下有期徒刑、拘役或科或併科15萬元以下罰金。附件：臺灣彰化地方法院檢察署檢察官100年度偵字第6948號聲請簡易判決處刑書1份。",
  "characters": {
    "judges": [
      "陳德池"
    ],
    "prosecutors": [

    ],
    "lawyers": [

    ],
    "clerks": [
      "黃國源"
    ],
    "plaintiffs": [

    ],
    "defendants": [
      "謝其展"
    ],
    "prosecutor_office": [
      "臺灣彰化地方法院檢察署檢察官"
    ],
    "creditors": [

    ],
    "debtors": [

    ],
    "judicial_associate_officer": [

    ]
  },
  "adjudged_at": "2011-09-16",
  "created_at": "2016-02-12 15:57:32",
  "updated_at": "2016-02-12 15:57:32"
}