{
  "identify": "TCD-100-中簡-2107-20110916-1",
  "court": {
    "name": "臺灣臺中地方法院",
    "code": "TCD"
  },
  "division": {
    "name": "刑事",
    "code": "M"
  },
  "year": 100,
  "word": "中簡",
  "number": "2107",
  "jcheck": "1",
  "reason": "妨害兵役",
  "content": "臺灣臺中地方法院刑事簡易判決       100年度中簡字第2107號\n聲  請  人  臺灣臺中地方法院檢察署檢察官\n被      告  楊宗霖\n上列被告因妨害兵役案件，經檢察官聲請以簡易判決處刑（100\n年度偵緝字第1278號），本院判決如下：\n    主    文\n楊宗霖後備軍人，意圖避免召集處理，居住處所遷移，無故不依\n規定申報，致使教育召集令無法送達，處有期徒刑貳月，如易科\n罰金，以新臺幣壹仟元折算壹日。緩刑貳年。\n    事實及理由\n一、本案犯罪事實及證據，均引用檢察官聲請簡易判決處刑書之\n    記載（如附件）。\n二、審酌被告係列管之後備軍人，依法有應教育召集之義務；且\n    其戶籍遷徒或居住地址變更時，依後備軍人管理規則第7 條\n    第2 款、第15條之規定，應依相關戶籍法規向主管單位申報\n    異動登記。茲被告居住處所遷移，竟無故不依規定向主管單\n    位申報，致使教育召集令無法送達，妨害國家後備軍人動員\n    之施行及兵役之有效管理，應予責難；另兼衡其犯後已坦承\n    犯行，態度尚佳；暨其犯罪之動機、目的、手段、國中畢業\n    之智識程度等一切情狀，量處如主文所示之刑，並諭知易科\n    罰金之折算標準。又被告前未曾因故意犯罪而受有期徒刑以\n    上刑之宣告，有臺灣高等法院被告前案紀錄表在卷可按，信\n    其經此科刑之教訓後，已能知所警惕，而無再犯之虞。本院\n    綜核各情，因認對被告所宣告之刑，以暫不執行為適當，爰\n    併予宣告緩刑2 年，以啟自新。\n三、依刑事訴訟法第449 條第1 項前段、第454 條第2 項，妨害\n    兵役治罪條例第10條第3 項、第1 項第3 款、第6 條第1 項\n    ，刑法第11條、第41條第1 項前段、第74條第1 項第1 款，\n    逕以簡易判決處刑如主文。\n四、如不服本判決，得於收受判決書送達後10日內，以書狀敘述\n    理由（須附繕本），向本院提出上訴狀，上訴於本院管轄第\n    二審之合議庭。\n中    華    民    國    100    年    9    月    16    日\n                  臺中簡易庭  法  官  黃佩韻\n上正本證明與原本無異。\n                              書記官  林柏名\n中    華    民    國    100    年    9    月    16    日\n附錄本案論罪科刑法條全文\n妨害兵役治罪條例第10條\n後備軍人意圖避免召集處理有下列行為之一者，處1 年以下有期\n徒刑、拘役或科新臺幣9 萬元以下罰金：\n一、離營歸鄉無故不依規定報到，或重複申報戶籍者。\n二、拒絕依規定調查，或體格檢查不到者。\n三、居住處所遷移，無故不依規定申報者。\n國民兵犯前項第三款之罪者，處6 月以下有期徒刑、拘役或科新\n臺幣3 萬元以下罰金。\n後備軍人犯第一項之罪或國民兵犯前項之罪，致使召集令無法送\n達者，以意圖避免召集論；分別依第五條或第六條科刑。\n妨害兵役治罪條例第6條\n意圖避免教育召集或勤務召集，而有下列行為之一者，處3 年以\n下有期徒刑：\n一、捏造免役、除役、轉役或免除召集原因者。\n二、毀傷身體者。\n三、拒絕接受召集令者。\n四、應受召集，無故逾應召期限二日者。\n五、使人頂替本人應召者。\n無故不參加點閱召集，或意圖避免點閱召集，而有前項第一款至\n第三款及第五款行為之一者，處1 年以下有期徒刑、拘役或科新\n臺幣9 萬元以下罰金。\n國民兵為避免應召集輔助軍事勤務犯第一項之罪者，處3 年以下\n有期徒刑。\n附件：",
  "structure": {
    "main": "楊宗霖後備軍人，意圖避免召集處理，居住處所遷移，無故不依\n規定申報，致使教育召集令無法送達，處有期徒刑貳月，如易科\n罰金，以新臺幣壹仟元折算壹日。緩刑貳年。",
    "fact": "一、本案犯罪事實及證據，均引用檢察官聲請簡易判決處刑書之\n    記載（如附件）。\n二、審酌被告係列管之後備軍人，依法有應教育召集之義務；且\n    其戶籍遷徒或居住地址變更時，依後備軍人管理規則第7 條\n    第2 款、第15條之規定，應依相關戶籍法規向主管單位申報\n    異動登記。茲被告居住處所遷移，竟無故不依規定向主管單\n    位申報，致使教育召集令無法送達，妨害國家後備軍人動員\n    之施行及兵役之有效管理，應予責難；另兼衡其犯後已坦承\n    犯行，態度尚佳；暨其犯罪之動機、目的、手段、國中畢業\n    之智識程度等一切情狀，量處如主文所示之刑，並諭知易科\n    罰金之折算標準。又被告前未曾因故意犯罪而受有期徒刑以\n    上刑之宣告，有臺灣高等法院被告前案紀錄表在卷可按，信\n    其經此科刑之教訓後，已能知所警惕，而無再犯之虞。本院\n    綜核各情，因認對被告所宣告之刑，以暫不執行為適當，爰\n    併予宣告緩刑2 年，以啟自新。\n三、依刑事訴訟法第449 條第1 項前段、第454 條第2 項，妨害\n    兵役治罪條例第10條第3 項、第1 項第3 款、第6 條第1 項\n    ，刑法第11條、第41條第1 項前段、第74條第1 項第1 款，\n    逕以簡易判決處刑如主文。\n四、如不服本判決，得於收受判決書送達後10日內，以書狀敘述\n    理由（須附繕本），向本院提出上訴狀，上訴於本院管轄第\n    二審之合議庭。",
    "reason": "一、本案犯罪事實及證據，均引用檢察官聲請簡易判決處刑書之\n    記載（如附件）。\n二、審酌被告係列管之後備軍人，依法有應教育召集之義務；且\n    其戶籍遷徒或居住地址變更時，依後備軍人管理規則第7 條\n    第2 款、第15條之規定，應依相關戶籍法規向主管單位申報\n    異動登記。茲被告居住處所遷移，竟無故不依規定向主管單\n    位申報，致使教育召集令無法送達，妨害國家後備軍人動員\n    之施行及兵役之有效管理，應予責難；另兼衡其犯後已坦承\n    犯行，態度尚佳；暨其犯罪之動機、目的、手段、國中畢業\n    之智識程度等一切情狀，量處如主文所示之刑，並諭知易科\n    罰金之折算標準。又被告前未曾因故意犯罪而受有期徒刑以\n    上刑之宣告，有臺灣高等法院被告前案紀錄表在卷可按，信\n    其經此科刑之教訓後，已能知所警惕，而無再犯之虞。本院\n    綜核各情，因認對被告所宣告之刑，以暫不執行為適當，爰\n    併予宣告緩刑2 年，以啟自新。\n三、依刑事訴訟法第449 條第1 項前段、第454 條第2 項，妨害\n    兵役治罪條例第10條第3 項、第1 項第3 款、第6 條第1 項\n    ，刑法第11條、第41條第1 項前段、第74條第1 項第1 款，\n    逕以簡易判決處刑如主文。\n四、如不服本判決，得於收受判決書送達後10日內，以書狀敘述\n    理由（須附繕本），向本院提出上訴狀，上訴於本院管轄第\n    二審之合議庭。"
  },
  "search": "臺灣臺中地方法院刑事簡易判決100年度中簡字第2107號聲請人臺灣臺中地方法院檢察署檢察官被告楊宗霖上列被告因妨害兵役案件，經檢察官聲請以簡易判決處刑（100年度偵緝字第1278號），本院判決如下：主文楊宗霖後備軍人，意圖避免召集處理，居住處所遷移，無故不依規定申報，致使教育召集令無法送達，處有期徒刑貳月，如易科罰金，以新臺幣壹仟元折算壹日。緩刑貳年。事實及理由一、本案犯罪事實及證據，均引用檢察官聲請簡易判決處刑書之記載（如附件）。二、審酌被告係列管之後備軍人，依法有應教育召集之義務；且其戶籍遷徒或居住地址變更時，依後備軍人管理規則第7條第2款、第15條之規定，應依相關戶籍法規向主管單位申報異動登記。茲被告居住處所遷移，竟無故不依規定向主管單位申報，致使教育召集令無法送達，妨害國家後備軍人動員之施行及兵役之有效管理，應予責難；另兼衡其犯後已坦承犯行，態度尚佳；暨其犯罪之動機、目的、手段、國中畢業之智識程度等一切情狀，量處如主文所示之刑，並諭知易科罰金之折算標準。又被告前未曾因故意犯罪而受有期徒刑以上刑之宣告，有臺灣高等法院被告前案紀錄表在卷可按，信其經此科刑之教訓後，已能知所警惕，而無再犯之虞。本院綜核各情，因認對被告所宣告之刑，以暫不執行為適當，爰併予宣告緩刑2年，以啟自新。三、依刑事訴訟法第449條第1項前段、第454條第2項，妨害兵役治罪條例第10條第3項、第1項第3款、第6條第1項，刑法第11條、第41條第1項前段、第74條第1項第1款，逕以簡易判決處刑如主文。四、如不服本判決，得於收受判決書送達後10日內，以書狀敘述理由（須附繕本），向本院提出上訴狀，上訴於本院管轄第二審之合議庭。中華民國100年9月16日臺中簡易庭法官黃佩韻上正本證明與原本無異。書記官林柏名中華民國100年9月16日附錄本案論罪科刑法條全文妨害兵役治罪條例第10條後備軍人意圖避免召集處理有下列行為之一者，處1年以下有期徒刑、拘役或科新臺幣9萬元以下罰金：一、離營歸鄉無故不依規定報到，或重複申報戶籍者。二、拒絕依規定調查，或體格檢查不到者。三、居住處所遷移，無故不依規定申報者。國民兵犯前項第三款之罪者，處6月以下有期徒刑、拘役或科新臺幣3萬元以下罰金。後備軍人犯第一項之罪或國民兵犯前項之罪，致使召集令無法送達者，以意圖避免召集論；分別依第五條或第六條科刑。妨害兵役治罪條例第6條意圖避免教育召集或勤務召集，而有下列行為之一者，處3年以下有期徒刑：一、捏造免役、除役、轉役或免除召集原因者。二、毀傷身體者。三、拒絕接受召集令者。四、應受召集，無故逾應召期限二日者。五、使人頂替本人應召者。無故不參加點閱召集，或意圖避免點閱召集，而有前項第一款至第三款及第五款行為之一者，處1年以下有期徒刑、拘役或科新臺幣9萬元以下罰金。國民兵為避免應召集輔助軍事勤務犯第一項之罪者，處3年以下有期徒刑。附件：",
  "characters": {
    "judges": [
      "黃佩韻"
    ],
    "prosecutors": [

    ],
    "lawyers": [

    ],
    "clerks": [
      "林柏名"
    ],
    "plaintiffs": [

    ],
    "defendants": [
      "楊宗霖"
    ],
    "prosecutor_office": [
      "臺灣臺中地方法院檢察署檢察官"
    ],
    "creditors": [

    ],
    "debtors": [

    ],
    "judicial_associate_officer": [

    ]
  },
  "adjudged_at": "2011-09-16",
  "created_at": "2016-02-12 15:57:43",
  "updated_at": "2016-02-12 15:57:43"
}