{
  "identify": "KSD-93-簡-576-20040210-1",
  "court": {
    "name": "臺灣高雄地方法院",
    "code": "KSD"
  },
  "division": {
    "name": "刑事",
    "code": "M"
  },
  "year": 93,
  "word": "簡",
  "number": "576",
  "jcheck": "1",
  "reason": "偽造文書等",
  "content": "臺灣高雄地方法院刑事簡易判決                      九十三年度簡字第五七六號\n    聲  請  人  臺灣高雄地方法院檢察署檢察官\n    被      告  甲○○\n右列被告因偽造文書等案件，經檢察官聲請以簡易判決處刑（九十三年度偵字第一四\n一八號），本院判決如左：\n    主  文\n甲○○行使變造私文書，足以生損害於他人，累犯，處有期徒刑肆月，如易科罰金，\n以參佰元折算壹日。變造之英達商行、中華民國九十二年十月二十五日、ＷＣ000\n00000號及友倫商行、中華民國九十二年九月二十二日、ＷＤ00000000\n號之統一發票各壹張，均沒收。\n    事實及理由\n一、本件犯罪事實及證據均引用檢察官聲請簡易判決處刑書之記載（如附件），並補\n    充記載犯罪事實如下：(1)甲○○前因違反毒品危害防制條例案件，經法院先後以\n    九十年度竹東簡字第六五三號、九十一年度訴字第一二六八號分別判處有期徒刑\n    六月、七月確定，嗣接續執行於九十二年八月七日縮刑期滿執行完畢，猶不知悔\n    改。(2)其於該變造之統一發票二張背面填寫自己之年籍資料，並持向臺灣銀行左\n    營分行之行員張秀芳兌獎而行使之，足以生損害於國家財政稅收及統一發票開獎\n    之公信性，惟遭該銀行行員張秀芳察覺識破，始未得逞」等語。\n二、按統一發票係營業人銷售貨物或勞務予買受人之憑證，應屬私文書，不因事後公\n    布中獎而得依給獎辦法兌領獎金之偶然事實，變易其私文書之性質；又統一發票\n    上之號碼僅係表彰營業人開立該憑證之部分內容，未中獎之發票，仍具憑證之功\n    能，是就統一發票之號碼擅自更改，應成立變造罪責而非屬偽造行為（最高法院\n    八十九年度台上字第五四二八號判決意旨參照）。是核被告甲○○上開持變造統\n    一發票行使兌獎詐財因遭識破而未得逞之所為，係犯刑法第二百十六條、第二百\n    十條行使變造私文書及刑法第三百三十九條第三項、第一項之詐欺取財未遂罪。\n    被告變造私文書後復持以行使，其變造之低度行為已為行使之高度行為所吸收，\n    不另論罪。又其行使變造私文書之行為，係為達詐欺取財之目的，所犯上開二罪\n    間，具有方法、目的之牽連關係，應依牽連犯之規定論以較重之行使變造私文書\n    罪。爰審酌被告前因違反毒品危害防制條例案件，經法院分別判處有期徒刑六月\n    、七月確定，嗣接續執行於九十二年八月七日縮刑期滿執行完畢之事實，有臺灣\n    高等法院被告全國前案紀錄表、臺灣高雄地方法院檢察署刑案資料查註紀錄表各\n    一份在卷可按，其於有期徒刑執行完畢後，五年內再犯本件有期徒刑以上之罪，\n    為累犯，應依刑法第四十七條之規定加重其刑。爰審酌被告貪圖小利，竟心存僥\n    倖，變造統一發票並持向銀行詐騙兌獎，危及國庫財政與統一發票對獎制度之公\n    信性，且犯後復未能坦承犯行，本不宜寬貸，惟念及其變造之統一發票所詐領之\n    金額不高等一切情狀，量處如主文所示之刑，並諭知易科罰金之折算標準，以示\n    懲儆。扣案變造之英達商行、中華民國九十二年十月二十五日、ＷＣ00000\n    000號及友倫商行、中華民國九十二年九月二十二日、ＷＤ00000000\n    號之統一發票各一張，均係被告所有供犯罪所用之物，應依刑法第三十八條第一\n    項第二款之規定，均併予宣告沒收。\n三、依刑事訴訟法第四百四十九條第一項前段、第三項、第四百五十條第一項、第四\n    百五十四條第二項，刑法第二百十六條、第二百十條、第三百三十九條第三項、\n    第一項、第五十五條、第四十一條第一項前段、第四十七條、第三十八條第一項\n    第二款，罰金罰鍰提高標準條例第一條前段、第二條，逕以簡易判決處如主文所\n    示之刑。\n中      華      民      國    九十三    年      二     月       十    日\n                                  臺灣高雄地方法院高雄簡易庭\n                                            法  官  吳俊龍\n右正本證明與原本無異。\n如不服本判決，得於判決書送達之日起十日內，以書狀敘述理由，向本庭提出上訴。\n                                            書記官  許麗珠\n中      華      民      國    九十三    年      二     月      十三    日\n附錄本判決論罪之法條】\n刑法第二百十六條\n行使第二百十條至第二百十五條之文書者，依偽造、變造文書或登載不實事項或使登\n載不實事項之規定處斷。\n刑法第二百十條\n偽造、變造私文書，足以生損害於公眾或他人者，處五年以下有期徒刑。\n刑法第三百三十九條第一項、第三項\n意圖為自己或第三人不法之所有，以詐術使人將本人或第三人之物交付者，處五年以\n下有期徒刑、拘役或科或併科一千元以下罰金。\n前二項之未遂犯罰之。\n",
  "structure": {
    "main": "甲○○行使變造私文書，足以生損害於他人，累犯，處有期徒刑肆月，如易科罰金，\n以參佰元折算壹日。變造之英達商行、中華民國九十二年十月二十五日、ＷＣ000\n00000號及友倫商行、中華民國九十二年九月二十二日、ＷＤ00000000\n號之統一發票各壹張，均沒收。",
    "fact": "一、本件犯罪事實及證據均引用檢察官聲請簡易判決處刑書之記載（如附件），並補\n    充記載犯罪事實如下：(1)甲○○前因違反毒品危害防制條例案件，經法院先後以\n    九十年度竹東簡字第六五三號、九十一年度訴字第一二六八號分別判處有期徒刑\n    六月、七月確定，嗣接續執行於九十二年八月七日縮刑期滿執行完畢，猶不知悔\n    改。(2)其於該變造之統一發票二張背面填寫自己之年籍資料，並持向臺灣銀行左\n    營分行之行員張秀芳兌獎而行使之，足以生損害於國家財政稅收及統一發票開獎\n    之公信性，惟遭該銀行行員張秀芳察覺識破，始未得逞」等語。\n二、按統一發票係營業人銷售貨物或勞務予買受人之憑證，應屬私文書，不因事後公\n    布中獎而得依給獎辦法兌領獎金之偶然事實，變易其私文書之性質；又統一發票\n    上之號碼僅係表彰營業人開立該憑證之部分內容，未中獎之發票，仍具憑證之功\n    能，是就統一發票之號碼擅自更改，應成立變造罪責而非屬偽造行為（最高法院\n    八十九年度台上字第五四二八號判決意旨參照）。是核被告甲○○上開持變造統\n    一發票行使兌獎詐財因遭識破而未得逞之所為，係犯刑法第二百十六條、第二百\n    十條行使變造私文書及刑法第三百三十九條第三項、第一項之詐欺取財未遂罪。\n    被告變造私文書後復持以行使，其變造之低度行為已為行使之高度行為所吸收，\n    不另論罪。又其行使變造私文書之行為，係為達詐欺取財之目的，所犯上開二罪\n    間，具有方法、目的之牽連關係，應依牽連犯之規定論以較重之行使變造私文書\n    罪。爰審酌被告前因違反毒品危害防制條例案件，經法院分別判處有期徒刑六月\n    、七月確定，嗣接續執行於九十二年八月七日縮刑期滿執行完畢之事實，有臺灣\n    高等法院被告全國前案紀錄表、臺灣高雄地方法院檢察署刑案資料查註紀錄表各\n    一份在卷可按，其於有期徒刑執行完畢後，五年內再犯本件有期徒刑以上之罪，\n    為累犯，應依刑法第四十七條之規定加重其刑。爰審酌被告貪圖小利，竟心存僥\n    倖，變造統一發票並持向銀行詐騙兌獎，危及國庫財政與統一發票對獎制度之公\n    信性，且犯後復未能坦承犯行，本不宜寬貸，惟念及其變造之統一發票所詐領之\n    金額不高等一切情狀，量處如主文所示之刑，並諭知易科罰金之折算標準，以示\n    懲儆。扣案變造之英達商行、中華民國九十二年十月二十五日、ＷＣ00000\n    000號及友倫商行、中華民國九十二年九月二十二日、ＷＤ00000000\n    號之統一發票各一張，均係被告所有供犯罪所用之物，應依刑法第三十八條第一\n    項第二款之規定，均併予宣告沒收。\n三、依刑事訴訟法第四百四十九條第一項前段、第三項、第四百五十條第一項、第四\n    百五十四條第二項，刑法第二百十六條、第二百十條、第三百三十九條第三項、\n    第一項、第五十五條、第四十一條第一項前段、第四十七條、第三十八條第一項\n    第二款，罰金罰鍰提高標準條例第一條前段、第二條，逕以簡易判決處如主文所\n    示之刑。",
    "reason": "一、本件犯罪事實及證據均引用檢察官聲請簡易判決處刑書之記載（如附件），並補\n    充記載犯罪事實如下：(1)甲○○前因違反毒品危害防制條例案件，經法院先後以\n    九十年度竹東簡字第六五三號、九十一年度訴字第一二六八號分別判處有期徒刑\n    六月、七月確定，嗣接續執行於九十二年八月七日縮刑期滿執行完畢，猶不知悔\n    改。(2)其於該變造之統一發票二張背面填寫自己之年籍資料，並持向臺灣銀行左\n    營分行之行員張秀芳兌獎而行使之，足以生損害於國家財政稅收及統一發票開獎\n    之公信性，惟遭該銀行行員張秀芳察覺識破，始未得逞」等語。\n二、按統一發票係營業人銷售貨物或勞務予買受人之憑證，應屬私文書，不因事後公\n    布中獎而得依給獎辦法兌領獎金之偶然事實，變易其私文書之性質；又統一發票\n    上之號碼僅係表彰營業人開立該憑證之部分內容，未中獎之發票，仍具憑證之功\n    能，是就統一發票之號碼擅自更改，應成立變造罪責而非屬偽造行為（最高法院\n    八十九年度台上字第五四二八號判決意旨參照）。是核被告甲○○上開持變造統\n    一發票行使兌獎詐財因遭識破而未得逞之所為，係犯刑法第二百十六條、第二百\n    十條行使變造私文書及刑法第三百三十九條第三項、第一項之詐欺取財未遂罪。\n    被告變造私文書後復持以行使，其變造之低度行為已為行使之高度行為所吸收，\n    不另論罪。又其行使變造私文書之行為，係為達詐欺取財之目的，所犯上開二罪\n    間，具有方法、目的之牽連關係，應依牽連犯之規定論以較重之行使變造私文書\n    罪。爰審酌被告前因違反毒品危害防制條例案件，經法院分別判處有期徒刑六月\n    、七月確定，嗣接續執行於九十二年八月七日縮刑期滿執行完畢之事實，有臺灣\n    高等法院被告全國前案紀錄表、臺灣高雄地方法院檢察署刑案資料查註紀錄表各\n    一份在卷可按，其於有期徒刑執行完畢後，五年內再犯本件有期徒刑以上之罪，\n    為累犯，應依刑法第四十七條之規定加重其刑。爰審酌被告貪圖小利，竟心存僥\n    倖，變造統一發票並持向銀行詐騙兌獎，危及國庫財政與統一發票對獎制度之公\n    信性，且犯後復未能坦承犯行，本不宜寬貸，惟念及其變造之統一發票所詐領之\n    金額不高等一切情狀，量處如主文所示之刑，並諭知易科罰金之折算標準，以示\n    懲儆。扣案變造之英達商行、中華民國九十二年十月二十五日、ＷＣ00000\n    000號及友倫商行、中華民國九十二年九月二十二日、ＷＤ00000000\n    號之統一發票各一張，均係被告所有供犯罪所用之物，應依刑法第三十八條第一\n    項第二款之規定，均併予宣告沒收。\n三、依刑事訴訟法第四百四十九條第一項前段、第三項、第四百五十條第一項、第四\n    百五十四條第二項，刑法第二百十六條、第二百十條、第三百三十九條第三項、\n    第一項、第五十五條、第四十一條第一項前段、第四十七條、第三十八條第一項\n    第二款，罰金罰鍰提高標準條例第一條前段、第二條，逕以簡易判決處如主文所\n    示之刑。"
  },
  "search": "臺灣高雄地方法院刑事簡易判決九十三年度簡字第五七六號聲請人臺灣高雄地方法院檢察署檢察官被告甲○○右列被告因偽造文書等案件，經檢察官聲請以簡易判決處刑（九十三年度偵字第一四一八號），本院判決如左：主文甲○○行使變造私文書，足以生損害於他人，累犯，處有期徒刑肆月，如易科罰金，以參佰元折算壹日。變造之英達商行、中華民國九十二年十月二十五日、ＷＣ00000000號及友倫商行、中華民國九十二年九月二十二日、ＷＤ00000000號之統一發票各壹張，均沒收。事實及理由一、本件犯罪事實及證據均引用檢察官聲請簡易判決處刑書之記載（如附件），並補充記載犯罪事實如下：(1)甲○○前因違反毒品危害防制條例案件，經法院先後以九十年度竹東簡字第六五三號、九十一年度訴字第一二六八號分別判處有期徒刑六月、七月確定，嗣接續執行於九十二年八月七日縮刑期滿執行完畢，猶不知悔改。(2)其於該變造之統一發票二張背面填寫自己之年籍資料，並持向臺灣銀行左營分行之行員張秀芳兌獎而行使之，足以生損害於國家財政稅收及統一發票開獎之公信性，惟遭該銀行行員張秀芳察覺識破，始未得逞」等語。二、按統一發票係營業人銷售貨物或勞務予買受人之憑證，應屬私文書，不因事後公布中獎而得依給獎辦法兌領獎金之偶然事實，變易其私文書之性質；又統一發票上之號碼僅係表彰營業人開立該憑證之部分內容，未中獎之發票，仍具憑證之功能，是就統一發票之號碼擅自更改，應成立變造罪責而非屬偽造行為（最高法院八十九年度台上字第五四二八號判決意旨參照）。是核被告甲○○上開持變造統一發票行使兌獎詐財因遭識破而未得逞之所為，係犯刑法第二百十六條、第二百十條行使變造私文書及刑法第三百三十九條第三項、第一項之詐欺取財未遂罪。被告變造私文書後復持以行使，其變造之低度行為已為行使之高度行為所吸收，不另論罪。又其行使變造私文書之行為，係為達詐欺取財之目的，所犯上開二罪間，具有方法、目的之牽連關係，應依牽連犯之規定論以較重之行使變造私文書罪。爰審酌被告前因違反毒品危害防制條例案件，經法院分別判處有期徒刑六月、七月確定，嗣接續執行於九十二年八月七日縮刑期滿執行完畢之事實，有臺灣高等法院被告全國前案紀錄表、臺灣高雄地方法院檢察署刑案資料查註紀錄表各一份在卷可按，其於有期徒刑執行完畢後，五年內再犯本件有期徒刑以上之罪，為累犯，應依刑法第四十七條之規定加重其刑。爰審酌被告貪圖小利，竟心存僥倖，變造統一發票並持向銀行詐騙兌獎，危及國庫財政與統一發票對獎制度之公信性，且犯後復未能坦承犯行，本不宜寬貸，惟念及其變造之統一發票所詐領之金額不高等一切情狀，量處如主文所示之刑，並諭知易科罰金之折算標準，以示懲儆。扣案變造之英達商行、中華民國九十二年十月二十五日、ＷＣ00000000號及友倫商行、中華民國九十二年九月二十二日、ＷＤ00000000號之統一發票各一張，均係被告所有供犯罪所用之物，應依刑法第三十八條第一項第二款之規定，均併予宣告沒收。三、依刑事訴訟法第四百四十九條第一項前段、第三項、第四百五十條第一項、第四百五十四條第二項，刑法第二百十六條、第二百十條、第三百三十九條第三項、第一項、第五十五條、第四十一條第一項前段、第四十七條、第三十八條第一項第二款，罰金罰鍰提高標準條例第一條前段、第二條，逕以簡易判決處如主文所示之刑。中華民國九十三年二月十日臺灣高雄地方法院高雄簡易庭法官吳俊龍右正本證明與原本無異。如不服本判決，得於判決書送達之日起十日內，以書狀敘述理由，向本庭提出上訴。書記官許麗珠中華民國九十三年二月十三日附錄本判決論罪之法條】刑法第二百十六條行使第二百十條至第二百十五條之文書者，依偽造、變造文書或登載不實事項或使登載不實事項之規定處斷。刑法第二百十條偽造、變造私文書，足以生損害於公眾或他人者，處五年以下有期徒刑。刑法第三百三十九條第一項、第三項意圖為自己或第三人不法之所有，以詐術使人將本人或第三人之物交付者，處五年以下有期徒刑、拘役或科或併科一千元以下罰金。前二項之未遂犯罰之。",
  "characters": {
    "judges": [
      "吳俊龍"
    ],
    "prosecutors": [

    ],
    "lawyers": [

    ],
    "clerks": [
      "許麗珠"
    ],
    "plaintiffs": [

    ],
    "defendants": [
      "甲○○",
      "右列被告因偽造文書等案件，經檢察官聲請以簡易判決處刑（九十三年度偵字第一四",
      "一八號），本院判決如左："
    ],
    "prosecutor_office": [
      "臺灣高雄地方法院檢察署檢察官"
    ],
    "creditors": [

    ],
    "debtors": [

    ],
    "judicial_associate_officer": [

    ]
  },
  "adjudged_at": "2004-02-10",
  "created_at": "2016-02-05 22:20:56",
  "updated_at": "2016-02-05 22:20:56"
}