{
  "identify": "TPD-93-訴-2330-20040910-1",
  "court": {
    "name": "臺灣臺北地方法院",
    "code": "TPD"
  },
  "division": {
    "name": "民事",
    "code": "V"
  },
  "year": 93,
  "word": "訴",
  "number": "2330",
  "jcheck": "1",
  "reason": "給付貨款",
  "content": "臺灣臺北地方法院民事判決                        九十三年度訴字第二三三０號\n    原      告    捷元股份有限公司\n    法定代理人    戊○○\n    訴訟代理人    甲○○\n    被      告    理凱企業股份有限公司\n    兼法定代理人  乙○○\n    被      告    丁○○\n                  丙○○\n當事人間請求給付貨款事件，本院於民國九十三年八月二十七日言詞辯論終結，判決\n如下：\n    主  文\n被告應連帶給付原告新台幣伍拾貳萬伍仟元，及自民國九十三年六月五日起至清償日\n止，按年息百分之五計算之利息。\n訴訟費用由被告連帶負擔。\n    事實及理由\n一程序方面：\n  (一)按當事人得以合意定第一審管轄法院，但以關於由一定法律關係而生之訴訟為限\n    ，前項合意，應以文書證之，民事訴訟法第二十四條定有明文。依經銷合約書第\n    十九條約定，兩造合意以本院為第一審管轄法院，故本院有管轄權。\n  (二)按訴狀送達後，原告不得將原訴變更或追加他訴。但擴張或減縮應受判決事項之\n    聲明者，不在此限，民事訴訟法第二百五十五條第一項第三款定有明文。本件原\n    告原起訴請求被告連帶給付新台幣（下同）七十八萬四千八百廿三元，嗣於訴訟\n    中減縮為請求被告連帶給付五十二萬五千元，依前揭規定，自應准許。\n  (三)被告丙○○未於最後言詞辯論期日到場，核無民事訴訟法第三百八十六條所列各\n    款情形，應依原告之聲請，由其一造辯論而為判決。\n二原告主張：被告理凱企業股份有限公司（以下簡稱為理凱公司）與原告簽訂經銷合\n  約書，並由被告丁○○、乙○○、丙○○擔任履約連帶保證人。被告理凱公司於九\n  十二年八月至十月間分別向原告買受電腦周邊設備，計七十八萬四千八百廿三元，\n  原告業已依約交付產品，嗣原告向被告理凱公司請求給付貨款，詎被告竟拒不履行\n  ，迄今尚有五十二萬五千元貨款未付，故被告對原告應連帶負責等語。並聲明被告\n  應連帶給付原告五十二萬五千元，及自起訴狀繕本送達之翌日起至清償日止，按年\n  息百分之五計算之利息。\n三被告理凱公司及被告乙○○則以：被告理凱公司因遭惡性倒帳致財物週轉不靈，惟\n  被告乙○○及被告理凱公司本於誠信原則已陸續還款，至九十二年八月止尚欠五十\n  二萬五千元，希望原告准予每月分期償還一萬元。至於被告丁○○及被告丙○○二\n  人早已自被告理凱公司離職，且皆已通知原告，並經雙方同意更換保證人，惟原告\n  遲未重新對保等語資為抗辯。\n  被告丁○○則以：被告丁○○雖曾為被告理凱公司股東並任職於該公司，惟早於八\n  十九年八月間離職並退股，之後被告理凱公司多次遷移及重組，且系爭貨款發生於\n  九十二年八月至十月間，與被告丁○○無關。依合約第十九條規定，合約期間自八\n  十八年十月十八日起至八十九年十月十七日止，合約期滿如雙方無重新議定另立新\n  約，視為自動延長一年，得延長無數次，已違反合約精神及公平交易原則。被告理\n  凱公司已償還部分貨款，原告未進行協商逕提起本件訴訟，亦違反合約第二十一條\n  規定等語資為抗辯，並請求駁回原告之訴。\n  被告丙○○則以：原告與被告理凱公司於簽約前，均告知被告丙○○將依合約第九\n  條第一項規定以現金、有價證券或不動產設定質權或抵押權，被告丙○○僅須負擔\n  臨時出貨超過抵押不動產之金額，惟原告及被告理凱公司卻未依該項規定進行設定\n  ，顯有故意欺騙被告丙○○之行為。原告在被告理凱公司未支付前一個月應收貨款\n  且未設定不動產抵押之情況下，竟仍於九十二年八至十月連續出貨達七十八萬四千\n  八百廿三元，顯係原告內部控管失當而造成本件糾紛，此部份不應要求被告丙○○\n  負擔。又被告丙○○雖曾為被告理凱公司股東並任職於該公司，惟早於八十九年十\n  一月間離職並退股，且已獲被告理凱公司法定代理人乙○○同意取消保證人身分，\n  之後被告理凱公司多次遷移及重組，系爭貨款發生於九十二年八月至十月間，自與\n  被告丙○○無關。被告丙○○並於九十三年二月六日以存證信函通知原告及被告理\n  凱公司，渠等均無回應，應認渠等對於被告丙○○取消保證人身分均無異議。依合\n  約第十三條規定，保證人於合約期滿六個月後申請退保，然原告卻置之不理，且未\n  催促被告理凱公司另覓保證人，已違反合約第十三條規定。依合約第十九條規定，\n  合約期滿後，得延長無數次，已違反合約精神及公平交易原則。被告理凱公司已償\n  還部分款項，原告未進行協商逕提起本件訴訟，亦違反合約第二十一條規定等語資\n  為抗辯，並請求駁回原告之訴。\n四兩造不爭之事項：\n  (一)被告理凱公司於八十八年十月十八日與原告簽訂經銷合約書，由被告丁○○、乙\n    ○○、丙○○擔任連帶保證人。\n  (二)被告理凱公司於九十二年八月至十月間向原告進貨七十八萬四千八百廿三元，原\n    告已依約交貨，惟被告迄今尚有五十二萬五千元貨款未付。\n  (三)被告丙○○於九十三年二月六日寄發存證信函予原告及被告理凱公司，內容為：\n    「茲本人丙○○（以下稱為甲方）擔任理凱企業股份有限公司（以下稱為乙方）\n    向捷元股份有限公司（以下稱為丙方）進貨貨款之保證人。經乙方負責人乙○○\n    請另覓他人。甲方特以此存證信函，寄給乙、丙雙方，作為日後依據。」\n五本件爭點為：被告丁○○、丙○○是否須就系爭五十二萬五千元貨款負連帶保證責\n  任？經查：\n  (一)系爭經銷合約書第十條「保證人之責任」約定：「甲方（即被告理凱公司）之連\n    帶保證人應與甲方連帶履行本合約各項規定，就甲方對乙方所負之一切債務及損\n    害賠償責任，．．．3.甲方於經銷期間內，應支付乙方之貨款．．．保證人均願\n    負連帶保證責任。．．．」第十九條「經銷期間」約定：「本合約自八十八年十\n    月十八日起至八十九年十月十七日止，合約期滿如雙方無重新議定另立新約，視\n    為自動延長壹年，得延長無數次。」則原告與被告理凱公司間係屬繼續性、未定\n    期間之經銷買賣關係，被告丁○○、丙○○係就連續發生之債務為保證而未定有\n    期間。\n  (二)民法第七百五十四條第一項規定：「就連續發生之債務為保證而未定有期間者，\n    保證人得隨時通知債權人終止保證契約。」第二項規定：「前項情形，保證人對\n    於通知到達債權人後所發生主債務人之債務，不負保證責任。」本件被告丙○○\n    於九十三年二月六日以存證信函通知原告終止保證契約，然被告丙○○對於保證\n    契約終止前之被告理凱公司九十二年八月至十月間貨款債務，仍應負保證之責。\n  (三)被告丁○○陳稱：「我在八十九年八月間離職，應該是由被告理凱公司去更換保\n    證人，並沒有想到要向原告表示終止保證契約。」（九十三年七月廿日筆錄第二\n    頁）。依系爭經銷合約書觀之，被告丁○○係以私人身份擔任被告理凱公司之連\n    帶保證人，其於八十九年八月離職，並不影響其與原告間之保證契約，亦即在系\n    爭保證契約經合法終止前，原告與被告丁○○間之保證契約仍屬存續，被告丁○\n    ○仍應依系爭契約負保證責任，換言之，由於保證為債權人與保證人間之契約，\n    被告丁○○為保證人，其於未定保證期間之保證，須終止保證契約始能終止保證\n    責任，被告丁○○既未向原告為終止保證契約之意思表示，則被告丁○○與原告\n    間之保證契約仍存續中，被告丁○○仍須就被告理凱公司之債務負保證責任。\n  (四)被告丙○○答辯部分：\n    1.被告丙○○辯稱：「我在八十九年的時候也已經離開被告理凱企業股份有限公\n      司了，這些債務都是八十九年之後的事，我們離開的時候，有向被告法定代理\n      人乙○○表示要更換保證人，被告法定代理人乙○○表示她有跟原告捷元股份\n      有限公司取消我連帶保證人的義務，可是原告沒有回應。」被告兼法定代理人\n      乙○○到場陳稱：「被告丁○○離職的時候有告訴我要更換保證人，我想公司\n      地址要變更，所以在公司變更地址之後才同時跟原告說被告丁○○、被告丙○\n      ○兩個保證人都要更換。我們在被告丙○○離職之後，我自己有打過一次電話\n      ，也有在原告公司的人員到被告公司的時候告訴過他一次，跟原告捷元股份有\n      限公司的通訊部門的業務聯繫，內容是我們要變更保證人的事，他說當初與我\n      們簽約的是資訊部門，所以會通知資訊部門過來跟我們換，但原告也都一直沒\n      有回應。」原告則表示：「原告除了收到被告丙○○於九十三年二月六日的存\n      證信函外，並沒有接到任何通知終止保證的書面資料，被告丙○○是他們內部\n      的事。否認有收到被告法定代理人乙○○申請換保證人的任何訊息。」（九十\n      三年七月廿日筆錄第三頁）由於被告丙○○陳稱其並非親自通知原告終止保證\n      契約，而係透被告過乙○○為之，被告乙○○未能指明其所告知更換保證人之\n      原告人員姓名，難認此部分所述為真實，縱被告乙○○所述為真，然被告乙○\n      ○僅係告知原告員工要更換保證人，並非告知係代被告丙○○終止與原告之保\n      證契約，尚難認為被告丙○○有終止與原告之保證契約。依系爭經銷合約書觀\n      之，被告丙○○係以私人身份擔任被告理凱公司之連帶保證人，其於八十九年\n      間離職，並不影響其與原告間之保證契約。被告丙○○於九十三年二月六日寄\n      發終止保證契約之存證信函予原告，應認被告丙○○與原告之保證契約於九十\n      三年二月六日終止，然被告丙○○對於保證契約終止前之被告理凱公司九十二\n      年八月至十月間貨款債務，仍應負保證之責，已如前述，而被告丙○○未能舉\n      證證明於系爭貨款債務發生之前已向原告為終止保證契約之意表示，故被告丙\n      ○○與原告間之保證契約於系爭貨款債務發生時（九十二年八月至十月間）應\n      屬存續中。\n    2.被告丙○○辯稱：原告與被告理凱公司於簽約前，均告知被告丙○○將依合約\n      第九條第一項規定以現金、有價證券或不動產設定質權或抵押權，被告丙○○\n      僅須負擔臨時出貨超過抵押不動產之金額，惟原告及被告理凱公司卻未依該項\n      規定進行設定，顯有故意欺騙被告丙○○之行為云云部分，惟被告丙○○並未\n      舉證證明其受欺騙而為保證，且縱使被告丙○○於八十八年十月十八日係受詐\n      欺而為保證之意思表示，在其依民法第九十二條第一項之規定撤銷意思表示之\n      前，該保證之意思表示仍為有效。\n    3.被告丙○○辯稱：伊於合約期滿六個月後申請退保，然原告卻置之不理，且未\n      催促被告理凱公司另覓保證人，已違反合約第十三條之約定云云部分，經查：\n      民法第七百五十四條第一項規定：「就連續發生之債務為保證而未定有期間者\n      ，保證人得隨時通知債權人終止保證契約。」而系爭合約第十三條約定：「保\n      證人如須退保時，可於合約期滿六個月，以書面請求退保，經乙方（即原告）\n      同意後生效。否則無論保證人在報紙上刊登退保啟事或其他任何退保表示，均\n      不生效力。」合約約定保證人須於合約期滿六個月以書面請求退保並經原告同\n      意後生效部分，與民法之前揭強制規定不合，該保證人須於合約期滿六個月以\n      書面請求退保並經原告同意後生效部分應屬無效，應認本件保證人得隨時通知\n      原告終止保證契約。被告丙○○得隨時通知原告終止保證契約，然被告丙○○\n      並未舉證證明於系爭貨款債務發生之前已向原告為終止保證契約之意表示，故\n      被告丙○○仍須就系爭貨款債務負保證之責。\n    4.被告丙○○所辯：依合約第十九條規定，合約期間自八十八年十月十八日起至\n      八十九年十月十七日止，合約期滿如雙方無重新議定另立新約，視為自動延長\n      一年，得延長無數次，已違反合約精神及公平交易原則云云部分，經查：被告\n      丙○○所擔保者為原告與被告理凱公司間之連續發生之債務而為保證，並未定\n      有期間，被告本得依民法第七百五十四條之規定，隨時通知上訴人終止保證契\n      約，難謂系爭保證書為無效。保證人通常雖係礙於職務從屬或情誼原因，而由\n      債務人覓為其與債權人間債務之連帶保證人，惟就保證契約之法律關係而言，\n      保證人既係擔保他人間之債務清償責任，並非經濟上之弱者，且未自保證契約\n      獲取任何利益，如認保證契約有違民法保護保證人之任意規定，自可不訂定保\n      證契約，並不會因未成為保證人而生不利益，或經濟生活受制於債權人不得不\n      為保證人之情形，併予敘明。\n    5.系爭合約第二十一條雖約定：「因本合約事項所生之爭執，甲乙雙方應本誠信\n      盡力協商解決紛爭，惟協商不成時，雙方同意以台灣台北地方法院為第一審管\n      轄法院。」惟並未約定未協商即不得提起訴訟，是以原告仍得提起本件訴訟請\n      求被告為給付。\n  (六)綜上，被告理凱公司積欠原告九十二年八月至十月間之貨款五十二萬五千元，斯\n    時被告丁○○、丙○○與原告間之保證契約仍存續中，被告丁○○、丙○○仍須\n    就系爭貨款負連帶保證責任。\n六被告理凱公司及被告乙○○有誠意還款，希請求每月分期償還一萬元部分，未經原\n  告同意，而本件所命令給付其性質非長期間不能履行，故未能依民事訴訟法第三百\n  九十六條第一項之規定命分期給付。\n七綜上所述，被告理凱公司與原告簽訂經銷合約書，並由被告丁○○、乙○○、丙○\n  ○擔任履約連帶保證人，被告理凱公司於九十二年八月至十月間分別向原告買受電\n  腦周邊設備，計七十八萬四千八百廿三元，原告業已依約交付產品，被告理凱公司\n  迄今尚欠五十二萬五千元貨款未付。從而，原告依給付貨款及連帶保證之法律關係\n  ，請求被告連帶給付原告五十二萬五千元，及自起訴狀繕本送達之翌日即九十三年\n  六月五日起至清償日止按年息百分之五計算之利息，為有理由，應予准許。又原告\n  陳明願供擔保，請求宣告假執行，核無不合，茲酌定擔保金額，予以准許。\n八本件事已臻明確，兩造所為之其他主張陳述並所提之證據，經審酌後，認均與本件\n  之結論無礙，不再一一論述，併予敘明\n九結論：本件原告之訴為有理由，依民事訴訟法第三百八十五條第一項前段、第七十\n  八條、第八十五條第二項、第三百九十條第二項，判決如主文。\n中      華      民      國    九十三    年      九      月      十      日\n                                民事第五庭  法  官    周美雲\n正本係照原本作成\n如對本判決上訴，須於判決送達後廿日內向本院提出上訴狀\n中      華      民      國    九十三    年      九      月      十      日\n                                            書記官    王宜玲\n",
  "structure": {
    "main": "被告應連帶給付原告新台幣伍拾貳萬伍仟元，及自民國九十三年六月五日起至清償日\n止，按年息百分之五計算之利息。\n訴訟費用由被告連帶負擔。",
    "fact": "一程序方面：\n  (一)按當事人得以合意定第一審管轄法院，但以關於由一定法律關係而生之訴訟為限\n    ，前項合意，應以文書證之，民事訴訟法第二十四條定有明文。依經銷合約書第\n    十九條約定，兩造合意以本院為第一審管轄法院，故本院有管轄權。\n  (二)按訴狀送達後，原告不得將原訴變更或追加他訴。但擴張或減縮應受判決事項之\n    聲明者，不在此限，民事訴訟法第二百五十五條第一項第三款定有明文。本件原\n    告原起訴請求被告連帶給付新台幣（下同）七十八萬四千八百廿三元，嗣於訴訟\n    中減縮為請求被告連帶給付五十二萬五千元，依前揭規定，自應准許。\n  (三)被告丙○○未於最後言詞辯論期日到場，核無民事訴訟法第三百八十六條所列各\n    款情形，應依原告之聲請，由其一造辯論而為判決。\n二原告主張：被告理凱企業股份有限公司（以下簡稱為理凱公司）與原告簽訂經銷合\n  約書，並由被告丁○○、乙○○、丙○○擔任履約連帶保證人。被告理凱公司於九\n  十二年八月至十月間分別向原告買受電腦周邊設備，計七十八萬四千八百廿三元，\n  原告業已依約交付產品，嗣原告向被告理凱公司請求給付貨款，詎被告竟拒不履行\n  ，迄今尚有五十二萬五千元貨款未付，故被告對原告應連帶負責等語。並聲明被告\n  應連帶給付原告五十二萬五千元，及自起訴狀繕本送達之翌日起至清償日止，按年\n  息百分之五計算之利息。\n三被告理凱公司及被告乙○○則以：被告理凱公司因遭惡性倒帳致財物週轉不靈，惟\n  被告乙○○及被告理凱公司本於誠信原則已陸續還款，至九十二年八月止尚欠五十\n  二萬五千元，希望原告准予每月分期償還一萬元。至於被告丁○○及被告丙○○二\n  人早已自被告理凱公司離職，且皆已通知原告，並經雙方同意更換保證人，惟原告\n  遲未重新對保等語資為抗辯。\n  被告丁○○則以：被告丁○○雖曾為被告理凱公司股東並任職於該公司，惟早於八\n  十九年八月間離職並退股，之後被告理凱公司多次遷移及重組，且系爭貨款發生於\n  九十二年八月至十月間，與被告丁○○無關。依合約第十九條規定，合約期間自八\n  十八年十月十八日起至八十九年十月十七日止，合約期滿如雙方無重新議定另立新\n  約，視為自動延長一年，得延長無數次，已違反合約精神及公平交易原則。被告理\n  凱公司已償還部分貨款，原告未進行協商逕提起本件訴訟，亦違反合約第二十一條\n  規定等語資為抗辯，並請求駁回原告之訴。\n  被告丙○○則以：原告與被告理凱公司於簽約前，均告知被告丙○○將依合約第九\n  條第一項規定以現金、有價證券或不動產設定質權或抵押權，被告丙○○僅須負擔\n  臨時出貨超過抵押不動產之金額，惟原告及被告理凱公司卻未依該項規定進行設定\n  ，顯有故意欺騙被告丙○○之行為。原告在被告理凱公司未支付前一個月應收貨款\n  且未設定不動產抵押之情況下，竟仍於九十二年八至十月連續出貨達七十八萬四千\n  八百廿三元，顯係原告內部控管失當而造成本件糾紛，此部份不應要求被告丙○○\n  負擔。又被告丙○○雖曾為被告理凱公司股東並任職於該公司，惟早於八十九年十\n  一月間離職並退股，且已獲被告理凱公司法定代理人乙○○同意取消保證人身分，\n  之後被告理凱公司多次遷移及重組，系爭貨款發生於九十二年八月至十月間，自與\n  被告丙○○無關。被告丙○○並於九十三年二月六日以存證信函通知原告及被告理\n  凱公司，渠等均無回應，應認渠等對於被告丙○○取消保證人身分均無異議。依合\n  約第十三條規定，保證人於合約期滿六個月後申請退保，然原告卻置之不理，且未\n  催促被告理凱公司另覓保證人，已違反合約第十三條規定。依合約第十九條規定，\n  合約期滿後，得延長無數次，已違反合約精神及公平交易原則。被告理凱公司已償\n  還部分款項，原告未進行協商逕提起本件訴訟，亦違反合約第二十一條規定等語資\n  為抗辯，並請求駁回原告之訴。\n四兩造不爭之事項：\n  (一)被告理凱公司於八十八年十月十八日與原告簽訂經銷合約書，由被告丁○○、乙\n    ○○、丙○○擔任連帶保證人。\n  (二)被告理凱公司於九十二年八月至十月間向原告進貨七十八萬四千八百廿三元，原\n    告已依約交貨，惟被告迄今尚有五十二萬五千元貨款未付。\n  (三)被告丙○○於九十三年二月六日寄發存證信函予原告及被告理凱公司，內容為：\n    「茲本人丙○○（以下稱為甲方）擔任理凱企業股份有限公司（以下稱為乙方）\n    向捷元股份有限公司（以下稱為丙方）進貨貨款之保證人。經乙方負責人乙○○\n    請另覓他人。甲方特以此存證信函，寄給乙、丙雙方，作為日後依據。」\n五本件爭點為：被告丁○○、丙○○是否須就系爭五十二萬五千元貨款負連帶保證責\n  任？經查：\n  (一)系爭經銷合約書第十條「保證人之責任」約定：「甲方（即被告理凱公司）之連\n    帶保證人應與甲方連帶履行本合約各項規定，就甲方對乙方所負之一切債務及損\n    害賠償責任，．．．3.甲方於經銷期間內，應支付乙方之貨款．．．保證人均願\n    負連帶保證責任。．．．」第十九條「經銷期間」約定：「本合約自八十八年十\n    月十八日起至八十九年十月十七日止，合約期滿如雙方無重新議定另立新約，視\n    為自動延長壹年，得延長無數次。」則原告與被告理凱公司間係屬繼續性、未定\n    期間之經銷買賣關係，被告丁○○、丙○○係就連續發生之債務為保證而未定有\n    期間。\n  (二)民法第七百五十四條第一項規定：「就連續發生之債務為保證而未定有期間者，\n    保證人得隨時通知債權人終止保證契約。」第二項規定：「前項情形，保證人對\n    於通知到達債權人後所發生主債務人之債務，不負保證責任。」本件被告丙○○\n    於九十三年二月六日以存證信函通知原告終止保證契約，然被告丙○○對於保證\n    契約終止前之被告理凱公司九十二年八月至十月間貨款債務，仍應負保證之責。\n  (三)被告丁○○陳稱：「我在八十九年八月間離職，應該是由被告理凱公司去更換保\n    證人，並沒有想到要向原告表示終止保證契約。」（九十三年七月廿日筆錄第二\n    頁）。依系爭經銷合約書觀之，被告丁○○係以私人身份擔任被告理凱公司之連\n    帶保證人，其於八十九年八月離職，並不影響其與原告間之保證契約，亦即在系\n    爭保證契約經合法終止前，原告與被告丁○○間之保證契約仍屬存續，被告丁○\n    ○仍應依系爭契約負保證責任，換言之，由於保證為債權人與保證人間之契約，\n    被告丁○○為保證人，其於未定保證期間之保證，須終止保證契約始能終止保證\n    責任，被告丁○○既未向原告為終止保證契約之意思表示，則被告丁○○與原告\n    間之保證契約仍存續中，被告丁○○仍須就被告理凱公司之債務負保證責任。\n  (四)被告丙○○答辯部分：\n    1.被告丙○○辯稱：「我在八十九年的時候也已經離開被告理凱企業股份有限公\n      司了，這些債務都是八十九年之後的事，我們離開的時候，有向被告法定代理\n      人乙○○表示要更換保證人，被告法定代理人乙○○表示她有跟原告捷元股份\n      有限公司取消我連帶保證人的義務，可是原告沒有回應。」被告兼法定代理人\n      乙○○到場陳稱：「被告丁○○離職的時候有告訴我要更換保證人，我想公司\n      地址要變更，所以在公司變更地址之後才同時跟原告說被告丁○○、被告丙○\n      ○兩個保證人都要更換。我們在被告丙○○離職之後，我自己有打過一次電話\n      ，也有在原告公司的人員到被告公司的時候告訴過他一次，跟原告捷元股份有\n      限公司的通訊部門的業務聯繫，內容是我們要變更保證人的事，他說當初與我\n      們簽約的是資訊部門，所以會通知資訊部門過來跟我們換，但原告也都一直沒\n      有回應。」原告則表示：「原告除了收到被告丙○○於九十三年二月六日的存\n      證信函外，並沒有接到任何通知終止保證的書面資料，被告丙○○是他們內部\n      的事。否認有收到被告法定代理人乙○○申請換保證人的任何訊息。」（九十\n      三年七月廿日筆錄第三頁）由於被告丙○○陳稱其並非親自通知原告終止保證\n      契約，而係透被告過乙○○為之，被告乙○○未能指明其所告知更換保證人之\n      原告人員姓名，難認此部分所述為真實，縱被告乙○○所述為真，然被告乙○\n      ○僅係告知原告員工要更換保證人，並非告知係代被告丙○○終止與原告之保\n      證契約，尚難認為被告丙○○有終止與原告之保證契約。依系爭經銷合約書觀\n      之，被告丙○○係以私人身份擔任被告理凱公司之連帶保證人，其於八十九年\n      間離職，並不影響其與原告間之保證契約。被告丙○○於九十三年二月六日寄\n      發終止保證契約之存證信函予原告，應認被告丙○○與原告之保證契約於九十\n      三年二月六日終止，然被告丙○○對於保證契約終止前之被告理凱公司九十二\n      年八月至十月間貨款債務，仍應負保證之責，已如前述，而被告丙○○未能舉\n      證證明於系爭貨款債務發生之前已向原告為終止保證契約之意表示，故被告丙\n      ○○與原告間之保證契約於系爭貨款債務發生時（九十二年八月至十月間）應\n      屬存續中。\n    2.被告丙○○辯稱：原告與被告理凱公司於簽約前，均告知被告丙○○將依合約\n      第九條第一項規定以現金、有價證券或不動產設定質權或抵押權，被告丙○○\n      僅須負擔臨時出貨超過抵押不動產之金額，惟原告及被告理凱公司卻未依該項\n      規定進行設定，顯有故意欺騙被告丙○○之行為云云部分，惟被告丙○○並未\n      舉證證明其受欺騙而為保證，且縱使被告丙○○於八十八年十月十八日係受詐\n      欺而為保證之意思表示，在其依民法第九十二條第一項之規定撤銷意思表示之\n      前，該保證之意思表示仍為有效。\n    3.被告丙○○辯稱：伊於合約期滿六個月後申請退保，然原告卻置之不理，且未\n      催促被告理凱公司另覓保證人，已違反合約第十三條之約定云云部分，經查：\n      民法第七百五十四條第一項規定：「就連續發生之債務為保證而未定有期間者\n      ，保證人得隨時通知債權人終止保證契約。」而系爭合約第十三條約定：「保\n      證人如須退保時，可於合約期滿六個月，以書面請求退保，經乙方（即原告）\n      同意後生效。否則無論保證人在報紙上刊登退保啟事或其他任何退保表示，均\n      不生效力。」合約約定保證人須於合約期滿六個月以書面請求退保並經原告同\n      意後生效部分，與民法之前揭強制規定不合，該保證人須於合約期滿六個月以\n      書面請求退保並經原告同意後生效部分應屬無效，應認本件保證人得隨時通知\n      原告終止保證契約。被告丙○○得隨時通知原告終止保證契約，然被告丙○○\n      並未舉證證明於系爭貨款債務發生之前已向原告為終止保證契約之意表示，故\n      被告丙○○仍須就系爭貨款債務負保證之責。\n    4.被告丙○○所辯：依合約第十九條規定，合約期間自八十八年十月十八日起至\n      八十九年十月十七日止，合約期滿如雙方無重新議定另立新約，視為自動延長\n      一年，得延長無數次，已違反合約精神及公平交易原則云云部分，經查：被告\n      丙○○所擔保者為原告與被告理凱公司間之連續發生之債務而為保證，並未定\n      有期間，被告本得依民法第七百五十四條之規定，隨時通知上訴人終止保證契\n      約，難謂系爭保證書為無效。保證人通常雖係礙於職務從屬或情誼原因，而由\n      債務人覓為其與債權人間債務之連帶保證人，惟就保證契約之法律關係而言，\n      保證人既係擔保他人間之債務清償責任，並非經濟上之弱者，且未自保證契約\n      獲取任何利益，如認保證契約有違民法保護保證人之任意規定，自可不訂定保\n      證契約，並不會因未成為保證人而生不利益，或經濟生活受制於債權人不得不\n      為保證人之情形，併予敘明。\n    5.系爭合約第二十一條雖約定：「因本合約事項所生之爭執，甲乙雙方應本誠信\n      盡力協商解決紛爭，惟協商不成時，雙方同意以台灣台北地方法院為第一審管\n      轄法院。」惟並未約定未協商即不得提起訴訟，是以原告仍得提起本件訴訟請\n      求被告為給付。\n  (六)綜上，被告理凱公司積欠原告九十二年八月至十月間之貨款五十二萬五千元，斯\n    時被告丁○○、丙○○與原告間之保證契約仍存續中，被告丁○○、丙○○仍須\n    就系爭貨款負連帶保證責任。\n六被告理凱公司及被告乙○○有誠意還款，希請求每月分期償還一萬元部分，未經原\n  告同意，而本件所命令給付其性質非長期間不能履行，故未能依民事訴訟法第三百\n  九十六條第一項之規定命分期給付。\n七綜上所述，被告理凱公司與原告簽訂經銷合約書，並由被告丁○○、乙○○、丙○\n  ○擔任履約連帶保證人，被告理凱公司於九十二年八月至十月間分別向原告買受電\n  腦周邊設備，計七十八萬四千八百廿三元，原告業已依約交付產品，被告理凱公司\n  迄今尚欠五十二萬五千元貨款未付。從而，原告依給付貨款及連帶保證之法律關係\n  ，請求被告連帶給付原告五十二萬五千元，及自起訴狀繕本送達之翌日即九十三年\n  六月五日起至清償日止按年息百分之五計算之利息，為有理由，應予准許。又原告\n  陳明願供擔保，請求宣告假執行，核無不合，茲酌定擔保金額，予以准許。\n八本件事已臻明確，兩造所為之其他主張陳述並所提之證據，經審酌後，認均與本件\n  之結論無礙，不再一一論述，併予敘明\n九結論：本件原告之訴為有理由，依民事訴訟法第三百八十五條第一項前段、第七十\n  八條、第八十五條第二項、第三百九十條第二項，判決如主文。",
    "reason": "一程序方面：\n  (一)按當事人得以合意定第一審管轄法院，但以關於由一定法律關係而生之訴訟為限\n    ，前項合意，應以文書證之，民事訴訟法第二十四條定有明文。依經銷合約書第\n    十九條約定，兩造合意以本院為第一審管轄法院，故本院有管轄權。\n  (二)按訴狀送達後，原告不得將原訴變更或追加他訴。但擴張或減縮應受判決事項之\n    聲明者，不在此限，民事訴訟法第二百五十五條第一項第三款定有明文。本件原\n    告原起訴請求被告連帶給付新台幣（下同）七十八萬四千八百廿三元，嗣於訴訟\n    中減縮為請求被告連帶給付五十二萬五千元，依前揭規定，自應准許。\n  (三)被告丙○○未於最後言詞辯論期日到場，核無民事訴訟法第三百八十六條所列各\n    款情形，應依原告之聲請，由其一造辯論而為判決。\n二原告主張：被告理凱企業股份有限公司（以下簡稱為理凱公司）與原告簽訂經銷合\n  約書，並由被告丁○○、乙○○、丙○○擔任履約連帶保證人。被告理凱公司於九\n  十二年八月至十月間分別向原告買受電腦周邊設備，計七十八萬四千八百廿三元，\n  原告業已依約交付產品，嗣原告向被告理凱公司請求給付貨款，詎被告竟拒不履行\n  ，迄今尚有五十二萬五千元貨款未付，故被告對原告應連帶負責等語。並聲明被告\n  應連帶給付原告五十二萬五千元，及自起訴狀繕本送達之翌日起至清償日止，按年\n  息百分之五計算之利息。\n三被告理凱公司及被告乙○○則以：被告理凱公司因遭惡性倒帳致財物週轉不靈，惟\n  被告乙○○及被告理凱公司本於誠信原則已陸續還款，至九十二年八月止尚欠五十\n  二萬五千元，希望原告准予每月分期償還一萬元。至於被告丁○○及被告丙○○二\n  人早已自被告理凱公司離職，且皆已通知原告，並經雙方同意更換保證人，惟原告\n  遲未重新對保等語資為抗辯。\n  被告丁○○則以：被告丁○○雖曾為被告理凱公司股東並任職於該公司，惟早於八\n  十九年八月間離職並退股，之後被告理凱公司多次遷移及重組，且系爭貨款發生於\n  九十二年八月至十月間，與被告丁○○無關。依合約第十九條規定，合約期間自八\n  十八年十月十八日起至八十九年十月十七日止，合約期滿如雙方無重新議定另立新\n  約，視為自動延長一年，得延長無數次，已違反合約精神及公平交易原則。被告理\n  凱公司已償還部分貨款，原告未進行協商逕提起本件訴訟，亦違反合約第二十一條\n  規定等語資為抗辯，並請求駁回原告之訴。\n  被告丙○○則以：原告與被告理凱公司於簽約前，均告知被告丙○○將依合約第九\n  條第一項規定以現金、有價證券或不動產設定質權或抵押權，被告丙○○僅須負擔\n  臨時出貨超過抵押不動產之金額，惟原告及被告理凱公司卻未依該項規定進行設定\n  ，顯有故意欺騙被告丙○○之行為。原告在被告理凱公司未支付前一個月應收貨款\n  且未設定不動產抵押之情況下，竟仍於九十二年八至十月連續出貨達七十八萬四千\n  八百廿三元，顯係原告內部控管失當而造成本件糾紛，此部份不應要求被告丙○○\n  負擔。又被告丙○○雖曾為被告理凱公司股東並任職於該公司，惟早於八十九年十\n  一月間離職並退股，且已獲被告理凱公司法定代理人乙○○同意取消保證人身分，\n  之後被告理凱公司多次遷移及重組，系爭貨款發生於九十二年八月至十月間，自與\n  被告丙○○無關。被告丙○○並於九十三年二月六日以存證信函通知原告及被告理\n  凱公司，渠等均無回應，應認渠等對於被告丙○○取消保證人身分均無異議。依合\n  約第十三條規定，保證人於合約期滿六個月後申請退保，然原告卻置之不理，且未\n  催促被告理凱公司另覓保證人，已違反合約第十三條規定。依合約第十九條規定，\n  合約期滿後，得延長無數次，已違反合約精神及公平交易原則。被告理凱公司已償\n  還部分款項，原告未進行協商逕提起本件訴訟，亦違反合約第二十一條規定等語資\n  為抗辯，並請求駁回原告之訴。\n四兩造不爭之事項：\n  (一)被告理凱公司於八十八年十月十八日與原告簽訂經銷合約書，由被告丁○○、乙\n    ○○、丙○○擔任連帶保證人。\n  (二)被告理凱公司於九十二年八月至十月間向原告進貨七十八萬四千八百廿三元，原\n    告已依約交貨，惟被告迄今尚有五十二萬五千元貨款未付。\n  (三)被告丙○○於九十三年二月六日寄發存證信函予原告及被告理凱公司，內容為：\n    「茲本人丙○○（以下稱為甲方）擔任理凱企業股份有限公司（以下稱為乙方）\n    向捷元股份有限公司（以下稱為丙方）進貨貨款之保證人。經乙方負責人乙○○\n    請另覓他人。甲方特以此存證信函，寄給乙、丙雙方，作為日後依據。」\n五本件爭點為：被告丁○○、丙○○是否須就系爭五十二萬五千元貨款負連帶保證責\n  任？經查：\n  (一)系爭經銷合約書第十條「保證人之責任」約定：「甲方（即被告理凱公司）之連\n    帶保證人應與甲方連帶履行本合約各項規定，就甲方對乙方所負之一切債務及損\n    害賠償責任，．．．3.甲方於經銷期間內，應支付乙方之貨款．．．保證人均願\n    負連帶保證責任。．．．」第十九條「經銷期間」約定：「本合約自八十八年十\n    月十八日起至八十九年十月十七日止，合約期滿如雙方無重新議定另立新約，視\n    為自動延長壹年，得延長無數次。」則原告與被告理凱公司間係屬繼續性、未定\n    期間之經銷買賣關係，被告丁○○、丙○○係就連續發生之債務為保證而未定有\n    期間。\n  (二)民法第七百五十四條第一項規定：「就連續發生之債務為保證而未定有期間者，\n    保證人得隨時通知債權人終止保證契約。」第二項規定：「前項情形，保證人對\n    於通知到達債權人後所發生主債務人之債務，不負保證責任。」本件被告丙○○\n    於九十三年二月六日以存證信函通知原告終止保證契約，然被告丙○○對於保證\n    契約終止前之被告理凱公司九十二年八月至十月間貨款債務，仍應負保證之責。\n  (三)被告丁○○陳稱：「我在八十九年八月間離職，應該是由被告理凱公司去更換保\n    證人，並沒有想到要向原告表示終止保證契約。」（九十三年七月廿日筆錄第二\n    頁）。依系爭經銷合約書觀之，被告丁○○係以私人身份擔任被告理凱公司之連\n    帶保證人，其於八十九年八月離職，並不影響其與原告間之保證契約，亦即在系\n    爭保證契約經合法終止前，原告與被告丁○○間之保證契約仍屬存續，被告丁○\n    ○仍應依系爭契約負保證責任，換言之，由於保證為債權人與保證人間之契約，\n    被告丁○○為保證人，其於未定保證期間之保證，須終止保證契約始能終止保證\n    責任，被告丁○○既未向原告為終止保證契約之意思表示，則被告丁○○與原告\n    間之保證契約仍存續中，被告丁○○仍須就被告理凱公司之債務負保證責任。\n  (四)被告丙○○答辯部分：\n    1.被告丙○○辯稱：「我在八十九年的時候也已經離開被告理凱企業股份有限公\n      司了，這些債務都是八十九年之後的事，我們離開的時候，有向被告法定代理\n      人乙○○表示要更換保證人，被告法定代理人乙○○表示她有跟原告捷元股份\n      有限公司取消我連帶保證人的義務，可是原告沒有回應。」被告兼法定代理人\n      乙○○到場陳稱：「被告丁○○離職的時候有告訴我要更換保證人，我想公司\n      地址要變更，所以在公司變更地址之後才同時跟原告說被告丁○○、被告丙○\n      ○兩個保證人都要更換。我們在被告丙○○離職之後，我自己有打過一次電話\n      ，也有在原告公司的人員到被告公司的時候告訴過他一次，跟原告捷元股份有\n      限公司的通訊部門的業務聯繫，內容是我們要變更保證人的事，他說當初與我\n      們簽約的是資訊部門，所以會通知資訊部門過來跟我們換，但原告也都一直沒\n      有回應。」原告則表示：「原告除了收到被告丙○○於九十三年二月六日的存\n      證信函外，並沒有接到任何通知終止保證的書面資料，被告丙○○是他們內部\n      的事。否認有收到被告法定代理人乙○○申請換保證人的任何訊息。」（九十\n      三年七月廿日筆錄第三頁）由於被告丙○○陳稱其並非親自通知原告終止保證\n      契約，而係透被告過乙○○為之，被告乙○○未能指明其所告知更換保證人之\n      原告人員姓名，難認此部分所述為真實，縱被告乙○○所述為真，然被告乙○\n      ○僅係告知原告員工要更換保證人，並非告知係代被告丙○○終止與原告之保\n      證契約，尚難認為被告丙○○有終止與原告之保證契約。依系爭經銷合約書觀\n      之，被告丙○○係以私人身份擔任被告理凱公司之連帶保證人，其於八十九年\n      間離職，並不影響其與原告間之保證契約。被告丙○○於九十三年二月六日寄\n      發終止保證契約之存證信函予原告，應認被告丙○○與原告之保證契約於九十\n      三年二月六日終止，然被告丙○○對於保證契約終止前之被告理凱公司九十二\n      年八月至十月間貨款債務，仍應負保證之責，已如前述，而被告丙○○未能舉\n      證證明於系爭貨款債務發生之前已向原告為終止保證契約之意表示，故被告丙\n      ○○與原告間之保證契約於系爭貨款債務發生時（九十二年八月至十月間）應\n      屬存續中。\n    2.被告丙○○辯稱：原告與被告理凱公司於簽約前，均告知被告丙○○將依合約\n      第九條第一項規定以現金、有價證券或不動產設定質權或抵押權，被告丙○○\n      僅須負擔臨時出貨超過抵押不動產之金額，惟原告及被告理凱公司卻未依該項\n      規定進行設定，顯有故意欺騙被告丙○○之行為云云部分，惟被告丙○○並未\n      舉證證明其受欺騙而為保證，且縱使被告丙○○於八十八年十月十八日係受詐\n      欺而為保證之意思表示，在其依民法第九十二條第一項之規定撤銷意思表示之\n      前，該保證之意思表示仍為有效。\n    3.被告丙○○辯稱：伊於合約期滿六個月後申請退保，然原告卻置之不理，且未\n      催促被告理凱公司另覓保證人，已違反合約第十三條之約定云云部分，經查：\n      民法第七百五十四條第一項規定：「就連續發生之債務為保證而未定有期間者\n      ，保證人得隨時通知債權人終止保證契約。」而系爭合約第十三條約定：「保\n      證人如須退保時，可於合約期滿六個月，以書面請求退保，經乙方（即原告）\n      同意後生效。否則無論保證人在報紙上刊登退保啟事或其他任何退保表示，均\n      不生效力。」合約約定保證人須於合約期滿六個月以書面請求退保並經原告同\n      意後生效部分，與民法之前揭強制規定不合，該保證人須於合約期滿六個月以\n      書面請求退保並經原告同意後生效部分應屬無效，應認本件保證人得隨時通知\n      原告終止保證契約。被告丙○○得隨時通知原告終止保證契約，然被告丙○○\n      並未舉證證明於系爭貨款債務發生之前已向原告為終止保證契約之意表示，故\n      被告丙○○仍須就系爭貨款債務負保證之責。\n    4.被告丙○○所辯：依合約第十九條規定，合約期間自八十八年十月十八日起至\n      八十九年十月十七日止，合約期滿如雙方無重新議定另立新約，視為自動延長\n      一年，得延長無數次，已違反合約精神及公平交易原則云云部分，經查：被告\n      丙○○所擔保者為原告與被告理凱公司間之連續發生之債務而為保證，並未定\n      有期間，被告本得依民法第七百五十四條之規定，隨時通知上訴人終止保證契\n      約，難謂系爭保證書為無效。保證人通常雖係礙於職務從屬或情誼原因，而由\n      債務人覓為其與債權人間債務之連帶保證人，惟就保證契約之法律關係而言，\n      保證人既係擔保他人間之債務清償責任，並非經濟上之弱者，且未自保證契約\n      獲取任何利益，如認保證契約有違民法保護保證人之任意規定，自可不訂定保\n      證契約，並不會因未成為保證人而生不利益，或經濟生活受制於債權人不得不\n      為保證人之情形，併予敘明。\n    5.系爭合約第二十一條雖約定：「因本合約事項所生之爭執，甲乙雙方應本誠信\n      盡力協商解決紛爭，惟協商不成時，雙方同意以台灣台北地方法院為第一審管\n      轄法院。」惟並未約定未協商即不得提起訴訟，是以原告仍得提起本件訴訟請\n      求被告為給付。\n  (六)綜上，被告理凱公司積欠原告九十二年八月至十月間之貨款五十二萬五千元，斯\n    時被告丁○○、丙○○與原告間之保證契約仍存續中，被告丁○○、丙○○仍須\n    就系爭貨款負連帶保證責任。\n六被告理凱公司及被告乙○○有誠意還款，希請求每月分期償還一萬元部分，未經原\n  告同意，而本件所命令給付其性質非長期間不能履行，故未能依民事訴訟法第三百\n  九十六條第一項之規定命分期給付。\n七綜上所述，被告理凱公司與原告簽訂經銷合約書，並由被告丁○○、乙○○、丙○\n  ○擔任履約連帶保證人，被告理凱公司於九十二年八月至十月間分別向原告買受電\n  腦周邊設備，計七十八萬四千八百廿三元，原告業已依約交付產品，被告理凱公司\n  迄今尚欠五十二萬五千元貨款未付。從而，原告依給付貨款及連帶保證之法律關係\n  ，請求被告連帶給付原告五十二萬五千元，及自起訴狀繕本送達之翌日即九十三年\n  六月五日起至清償日止按年息百分之五計算之利息，為有理由，應予准許。又原告\n  陳明願供擔保，請求宣告假執行，核無不合，茲酌定擔保金額，予以准許。\n八本件事已臻明確，兩造所為之其他主張陳述並所提之證據，經審酌後，認均與本件\n  之結論無礙，不再一一論述，併予敘明\n九結論：本件原告之訴為有理由，依民事訴訟法第三百八十五條第一項前段、第七十\n  八條、第八十五條第二項、第三百九十條第二項，判決如主文。"
  },
  "search": "臺灣臺北地方法院民事判決九十三年度訴字第二三三０號原告捷元股份有限公司法定代理人戊○○訴訟代理人甲○○被告理凱企業股份有限公司兼法定代理人乙○○被告丁○○丙○○當事人間請求給付貨款事件，本院於民國九十三年八月二十七日言詞辯論終結，判決如下：主文被告應連帶給付原告新台幣伍拾貳萬伍仟元，及自民國九十三年六月五日起至清償日止，按年息百分之五計算之利息。訴訟費用由被告連帶負擔。事實及理由一程序方面：(一)按當事人得以合意定第一審管轄法院，但以關於由一定法律關係而生之訴訟為限，前項合意，應以文書證之，民事訴訟法第二十四條定有明文。依經銷合約書第十九條約定，兩造合意以本院為第一審管轄法院，故本院有管轄權。(二)按訴狀送達後，原告不得將原訴變更或追加他訴。但擴張或減縮應受判決事項之聲明者，不在此限，民事訴訟法第二百五十五條第一項第三款定有明文。本件原告原起訴請求被告連帶給付新台幣（下同）七十八萬四千八百廿三元，嗣於訴訟中減縮為請求被告連帶給付五十二萬五千元，依前揭規定，自應准許。(三)被告丙○○未於最後言詞辯論期日到場，核無民事訴訟法第三百八十六條所列各款情形，應依原告之聲請，由其一造辯論而為判決。二原告主張：被告理凱企業股份有限公司（以下簡稱為理凱公司）與原告簽訂經銷合約書，並由被告丁○○、乙○○、丙○○擔任履約連帶保證人。被告理凱公司於九十二年八月至十月間分別向原告買受電腦周邊設備，計七十八萬四千八百廿三元，原告業已依約交付產品，嗣原告向被告理凱公司請求給付貨款，詎被告竟拒不履行，迄今尚有五十二萬五千元貨款未付，故被告對原告應連帶負責等語。並聲明被告應連帶給付原告五十二萬五千元，及自起訴狀繕本送達之翌日起至清償日止，按年息百分之五計算之利息。三被告理凱公司及被告乙○○則以：被告理凱公司因遭惡性倒帳致財物週轉不靈，惟被告乙○○及被告理凱公司本於誠信原則已陸續還款，至九十二年八月止尚欠五十二萬五千元，希望原告准予每月分期償還一萬元。至於被告丁○○及被告丙○○二人早已自被告理凱公司離職，且皆已通知原告，並經雙方同意更換保證人，惟原告遲未重新對保等語資為抗辯。被告丁○○則以：被告丁○○雖曾為被告理凱公司股東並任職於該公司，惟早於八十九年八月間離職並退股，之後被告理凱公司多次遷移及重組，且系爭貨款發生於九十二年八月至十月間，與被告丁○○無關。依合約第十九條規定，合約期間自八十八年十月十八日起至八十九年十月十七日止，合約期滿如雙方無重新議定另立新約，視為自動延長一年，得延長無數次，已違反合約精神及公平交易原則。被告理凱公司已償還部分貨款，原告未進行協商逕提起本件訴訟，亦違反合約第二十一條規定等語資為抗辯，並請求駁回原告之訴。被告丙○○則以：原告與被告理凱公司於簽約前，均告知被告丙○○將依合約第九條第一項規定以現金、有價證券或不動產設定質權或抵押權，被告丙○○僅須負擔臨時出貨超過抵押不動產之金額，惟原告及被告理凱公司卻未依該項規定進行設定，顯有故意欺騙被告丙○○之行為。原告在被告理凱公司未支付前一個月應收貨款且未設定不動產抵押之情況下，竟仍於九十二年八至十月連續出貨達七十八萬四千八百廿三元，顯係原告內部控管失當而造成本件糾紛，此部份不應要求被告丙○○負擔。又被告丙○○雖曾為被告理凱公司股東並任職於該公司，惟早於八十九年十一月間離職並退股，且已獲被告理凱公司法定代理人乙○○同意取消保證人身分，之後被告理凱公司多次遷移及重組，系爭貨款發生於九十二年八月至十月間，自與被告丙○○無關。被告丙○○並於九十三年二月六日以存證信函通知原告及被告理凱公司，渠等均無回應，應認渠等對於被告丙○○取消保證人身分均無異議。依合約第十三條規定，保證人於合約期滿六個月後申請退保，然原告卻置之不理，且未催促被告理凱公司另覓保證人，已違反合約第十三條規定。依合約第十九條規定，合約期滿後，得延長無數次，已違反合約精神及公平交易原則。被告理凱公司已償還部分款項，原告未進行協商逕提起本件訴訟，亦違反合約第二十一條規定等語資為抗辯，並請求駁回原告之訴。四兩造不爭之事項：(一)被告理凱公司於八十八年十月十八日與原告簽訂經銷合約書，由被告丁○○、乙○○、丙○○擔任連帶保證人。(二)被告理凱公司於九十二年八月至十月間向原告進貨七十八萬四千八百廿三元，原告已依約交貨，惟被告迄今尚有五十二萬五千元貨款未付。(三)被告丙○○於九十三年二月六日寄發存證信函予原告及被告理凱公司，內容為：「茲本人丙○○（以下稱為甲方）擔任理凱企業股份有限公司（以下稱為乙方）向捷元股份有限公司（以下稱為丙方）進貨貨款之保證人。經乙方負責人乙○○請另覓他人。甲方特以此存證信函，寄給乙、丙雙方，作為日後依據。」五本件爭點為：被告丁○○、丙○○是否須就系爭五十二萬五千元貨款負連帶保證責任？經查：(一)系爭經銷合約書第十條「保證人之責任」約定：「甲方（即被告理凱公司）之連帶保證人應與甲方連帶履行本合約各項規定，就甲方對乙方所負之一切債務及損害賠償責任，．．．3.甲方於經銷期間內，應支付乙方之貨款．．．保證人均願負連帶保證責任。．．．」第十九條「經銷期間」約定：「本合約自八十八年十月十八日起至八十九年十月十七日止，合約期滿如雙方無重新議定另立新約，視為自動延長壹年，得延長無數次。」則原告與被告理凱公司間係屬繼續性、未定期間之經銷買賣關係，被告丁○○、丙○○係就連續發生之債務為保證而未定有期間。(二)民法第七百五十四條第一項規定：「就連續發生之債務為保證而未定有期間者，保證人得隨時通知債權人終止保證契約。」第二項規定：「前項情形，保證人對於通知到達債權人後所發生主債務人之債務，不負保證責任。」本件被告丙○○於九十三年二月六日以存證信函通知原告終止保證契約，然被告丙○○對於保證契約終止前之被告理凱公司九十二年八月至十月間貨款債務，仍應負保證之責。(三)被告丁○○陳稱：「我在八十九年八月間離職，應該是由被告理凱公司去更換保證人，並沒有想到要向原告表示終止保證契約。」（九十三年七月廿日筆錄第二頁）。依系爭經銷合約書觀之，被告丁○○係以私人身份擔任被告理凱公司之連帶保證人，其於八十九年八月離職，並不影響其與原告間之保證契約，亦即在系爭保證契約經合法終止前，原告與被告丁○○間之保證契約仍屬存續，被告丁○○仍應依系爭契約負保證責任，換言之，由於保證為債權人與保證人間之契約，被告丁○○為保證人，其於未定保證期間之保證，須終止保證契約始能終止保證責任，被告丁○○既未向原告為終止保證契約之意思表示，則被告丁○○與原告間之保證契約仍存續中，被告丁○○仍須就被告理凱公司之債務負保證責任。(四)被告丙○○答辯部分：1.被告丙○○辯稱：「我在八十九年的時候也已經離開被告理凱企業股份有限公司了，這些債務都是八十九年之後的事，我們離開的時候，有向被告法定代理人乙○○表示要更換保證人，被告法定代理人乙○○表示她有跟原告捷元股份有限公司取消我連帶保證人的義務，可是原告沒有回應。」被告兼法定代理人乙○○到場陳稱：「被告丁○○離職的時候有告訴我要更換保證人，我想公司地址要變更，所以在公司變更地址之後才同時跟原告說被告丁○○、被告丙○○兩個保證人都要更換。我們在被告丙○○離職之後，我自己有打過一次電話，也有在原告公司的人員到被告公司的時候告訴過他一次，跟原告捷元股份有限公司的通訊部門的業務聯繫，內容是我們要變更保證人的事，他說當初與我們簽約的是資訊部門，所以會通知資訊部門過來跟我們換，但原告也都一直沒有回應。」原告則表示：「原告除了收到被告丙○○於九十三年二月六日的存證信函外，並沒有接到任何通知終止保證的書面資料，被告丙○○是他們內部的事。否認有收到被告法定代理人乙○○申請換保證人的任何訊息。」（九十三年七月廿日筆錄第三頁）由於被告丙○○陳稱其並非親自通知原告終止保證契約，而係透被告過乙○○為之，被告乙○○未能指明其所告知更換保證人之原告人員姓名，難認此部分所述為真實，縱被告乙○○所述為真，然被告乙○○僅係告知原告員工要更換保證人，並非告知係代被告丙○○終止與原告之保證契約，尚難認為被告丙○○有終止與原告之保證契約。依系爭經銷合約書觀之，被告丙○○係以私人身份擔任被告理凱公司之連帶保證人，其於八十九年間離職，並不影響其與原告間之保證契約。被告丙○○於九十三年二月六日寄發終止保證契約之存證信函予原告，應認被告丙○○與原告之保證契約於九十三年二月六日終止，然被告丙○○對於保證契約終止前之被告理凱公司九十二年八月至十月間貨款債務，仍應負保證之責，已如前述，而被告丙○○未能舉證證明於系爭貨款債務發生之前已向原告為終止保證契約之意表示，故被告丙○○與原告間之保證契約於系爭貨款債務發生時（九十二年八月至十月間）應屬存續中。2.被告丙○○辯稱：原告與被告理凱公司於簽約前，均告知被告丙○○將依合約第九條第一項規定以現金、有價證券或不動產設定質權或抵押權，被告丙○○僅須負擔臨時出貨超過抵押不動產之金額，惟原告及被告理凱公司卻未依該項規定進行設定，顯有故意欺騙被告丙○○之行為云云部分，惟被告丙○○並未舉證證明其受欺騙而為保證，且縱使被告丙○○於八十八年十月十八日係受詐欺而為保證之意思表示，在其依民法第九十二條第一項之規定撤銷意思表示之前，該保證之意思表示仍為有效。3.被告丙○○辯稱：伊於合約期滿六個月後申請退保，然原告卻置之不理，且未催促被告理凱公司另覓保證人，已違反合約第十三條之約定云云部分，經查：民法第七百五十四條第一項規定：「就連續發生之債務為保證而未定有期間者，保證人得隨時通知債權人終止保證契約。」而系爭合約第十三條約定：「保證人如須退保時，可於合約期滿六個月，以書面請求退保，經乙方（即原告）同意後生效。否則無論保證人在報紙上刊登退保啟事或其他任何退保表示，均不生效力。」合約約定保證人須於合約期滿六個月以書面請求退保並經原告同意後生效部分，與民法之前揭強制規定不合，該保證人須於合約期滿六個月以書面請求退保並經原告同意後生效部分應屬無效，應認本件保證人得隨時通知原告終止保證契約。被告丙○○得隨時通知原告終止保證契約，然被告丙○○並未舉證證明於系爭貨款債務發生之前已向原告為終止保證契約之意表示，故被告丙○○仍須就系爭貨款債務負保證之責。4.被告丙○○所辯：依合約第十九條規定，合約期間自八十八年十月十八日起至八十九年十月十七日止，合約期滿如雙方無重新議定另立新約，視為自動延長一年，得延長無數次，已違反合約精神及公平交易原則云云部分，經查：被告丙○○所擔保者為原告與被告理凱公司間之連續發生之債務而為保證，並未定有期間，被告本得依民法第七百五十四條之規定，隨時通知上訴人終止保證契約，難謂系爭保證書為無效。保證人通常雖係礙於職務從屬或情誼原因，而由債務人覓為其與債權人間債務之連帶保證人，惟就保證契約之法律關係而言，保證人既係擔保他人間之債務清償責任，並非經濟上之弱者，且未自保證契約獲取任何利益，如認保證契約有違民法保護保證人之任意規定，自可不訂定保證契約，並不會因未成為保證人而生不利益，或經濟生活受制於債權人不得不為保證人之情形，併予敘明。5.系爭合約第二十一條雖約定：「因本合約事項所生之爭執，甲乙雙方應本誠信盡力協商解決紛爭，惟協商不成時，雙方同意以台灣台北地方法院為第一審管轄法院。」惟並未約定未協商即不得提起訴訟，是以原告仍得提起本件訴訟請求被告為給付。(六)綜上，被告理凱公司積欠原告九十二年八月至十月間之貨款五十二萬五千元，斯時被告丁○○、丙○○與原告間之保證契約仍存續中，被告丁○○、丙○○仍須就系爭貨款負連帶保證責任。六被告理凱公司及被告乙○○有誠意還款，希請求每月分期償還一萬元部分，未經原告同意，而本件所命令給付其性質非長期間不能履行，故未能依民事訴訟法第三百九十六條第一項之規定命分期給付。七綜上所述，被告理凱公司與原告簽訂經銷合約書，並由被告丁○○、乙○○、丙○○擔任履約連帶保證人，被告理凱公司於九十二年八月至十月間分別向原告買受電腦周邊設備，計七十八萬四千八百廿三元，原告業已依約交付產品，被告理凱公司迄今尚欠五十二萬五千元貨款未付。從而，原告依給付貨款及連帶保證之法律關係，請求被告連帶給付原告五十二萬五千元，及自起訴狀繕本送達之翌日即九十三年六月五日起至清償日止按年息百分之五計算之利息，為有理由，應予准許。又原告陳明願供擔保，請求宣告假執行，核無不合，茲酌定擔保金額，予以准許。八本件事已臻明確，兩造所為之其他主張陳述並所提之證據，經審酌後，認均與本件之結論無礙，不再一一論述，併予敘明九結論：本件原告之訴為有理由，依民事訴訟法第三百八十五條第一項前段、第七十八條、第八十五條第二項、第三百九十條第二項，判決如主文。中華民國九十三年九月十日民事第五庭法官周美雲正本係照原本作成如對本判決上訴，須於判決送達後廿日內向本院提出上訴狀中華民國九十三年九月十日書記官王宜玲",
  "characters": {
    "judges": [
      "周美雲"
    ],
    "prosecutors": [

    ],
    "lawyers": [

    ],
    "clerks": [
      "王宜玲"
    ],
    "plaintiffs": [
      "捷元股份有限公司"
    ],
    "defendants": [
      "理凱企業股份有限公司",
      "丁○○"
    ],
    "prosecutor_office": [

    ],
    "creditors": [

    ],
    "debtors": [

    ],
    "judicial_associate_officer": [

    ]
  },
  "adjudged_at": "2004-09-10",
  "created_at": "2016-02-06 00:51:34",
  "updated_at": "2016-02-06 00:51:34"
}