{
  "identify": "TPD-93-簡-323-20040310-1",
  "court": {
    "name": "臺灣臺北地方法院",
    "code": "TPD"
  },
  "division": {
    "name": "刑事",
    "code": "M"
  },
  "year": 93,
  "word": "簡",
  "number": "323",
  "jcheck": "1",
  "reason": "竊盜",
  "content": "臺灣臺北地方法院刑事簡易判決                      九十三年度簡字第三二三號\n    聲  請  人  臺灣臺北地方法院檢察署檢察官\n    被      告  甲○○\n右列被告因竊盜案件，經檢察官聲請以簡易判決處刑（九十三年度偵字第一一三三號\n），本院判決如左：\n    主  文\n甲○○竊盜，科罰金貳仟元，如易服勞役，以佰元折算壹日。\n    事實及理由\n一、甲○○前曾因竊盜案件，經本院以九十二年度簡字第四一二五號判處罰金一千元\n    （不構成累犯），竟因曾與位於臺北市○○○路○段二五號「金超群商店」之店\n    員發生爭執而於民國九十二年十二月二十四日凌晨二時三十分許，復意圖為自己\n    不法所有之犯意，在上址「金超群商店」內，徒手竊取價值共新臺幣（下同）四\n    十五元之富士牌接著劑二條、如意牌竹牙籤一包，並即將前開竊得物品藏放於口\n    袋內，得手後欲離去之際，為該店店員林建成發覺並報警處理始查悉上情。\n二、上開犯罪事實，業據被告甲○○於警詢及本院調查中坦白承認，核與證人林建成\n    於警詢所述情節相符，並有臺北市政府警察局中山分局贓物認領保管收據一紙、\n    照片一張在卷可資佐證，被告自白與事實相符，本件事證已臻明確，被告犯行堪\n    以認定。\n三、核被告所為，係犯刑法第三百二十條第一項之竊盜罪。爰審酌被告雖前曾因竊盜\n    案件，經本院判處罰金一千元後，再次犯下本件犯行，然被告於警詢及本院調查\n    中均坦白承認犯行，並表示悔意，犯後態度尚佳，被告係以順手牽羊之方式竊取\n    他人財物，竊得之物品價值不大等情狀，量處如主文所示之刑，並諭知易服勞役\n    之折算標準。\n四、至於被告前於九十二年十一月七日因涉犯竊盜罪嫌而經本院以九十二年度簡字第\n    四一二五號判處罰金一千元之部分（下稱前案），被告於本院調查中到庭供稱：\n    伊於前案為警查獲後，有被送到地檢署，經檢察官飭回而離去，於斯時，伊並未\n    想到要再去竊盜，本案係因與金超群商店店員前有爭執而下手行竊等語，且前案\n    係於九十二年十二月一日經本院判決，並於九十二年十二月九日寄存送達於管轄\n    被告住處之派出所、且於同年十二月十五日送達於檢察官，此業經本院調閱前案\n    卷宗並影印附卷可參，足認被告顯係於前案經檢察官飭回後始另行起意犯下本案\n    ，本案並非前案起訴或既判力效力所及，併此敘明。\n五、依刑事訴訟法第四百四十九條第一項、第三項，刑法第三百二十條第一項、第四\n    十二條第二項，罰金罰鍰提高標準條例第一條前段、第二條，逕以簡易判決處刑\n    如主文。\n如不服本件判決，得自收受送達之日起十日內，向本院提起上訴。\n中      華      民      國    九十三    年      三      月      十      日\n                              臺灣臺北地方法院刑事第一庭\n                                        法  官    唐于智\n右正本證明與原本無異。\n                                        書記官    陳俐妙\n中      華      民      國    九十三    年      三      月      十      日\n附錄本案論罪法條\n刑法第三百二十條第一項\n意圖為自己或第三人不法之所有，而竊取他人之動產者，為竊盜罪，處五年以下有期\n徒刑、拘役或五百元以下罰金。\n",
  "structure": {
    "main": "甲○○竊盜，科罰金貳仟元，如易服勞役，以佰元折算壹日。",
    "fact": "一、甲○○前曾因竊盜案件，經本院以九十二年度簡字第四一二五號判處罰金一千元\n    （不構成累犯），竟因曾與位於臺北市○○○路○段二五號「金超群商店」之店\n    員發生爭執而於民國九十二年十二月二十四日凌晨二時三十分許，復意圖為自己\n    不法所有之犯意，在上址「金超群商店」內，徒手竊取價值共新臺幣（下同）四\n    十五元之富士牌接著劑二條、如意牌竹牙籤一包，並即將前開竊得物品藏放於口\n    袋內，得手後欲離去之際，為該店店員林建成發覺並報警處理始查悉上情。\n二、上開犯罪事實，業據被告甲○○於警詢及本院調查中坦白承認，核與證人林建成\n    於警詢所述情節相符，並有臺北市政府警察局中山分局贓物認領保管收據一紙、\n    照片一張在卷可資佐證，被告自白與事實相符，本件事證已臻明確，被告犯行堪\n    以認定。\n三、核被告所為，係犯刑法第三百二十條第一項之竊盜罪。爰審酌被告雖前曾因竊盜\n    案件，經本院判處罰金一千元後，再次犯下本件犯行，然被告於警詢及本院調查\n    中均坦白承認犯行，並表示悔意，犯後態度尚佳，被告係以順手牽羊之方式竊取\n    他人財物，竊得之物品價值不大等情狀，量處如主文所示之刑，並諭知易服勞役\n    之折算標準。\n四、至於被告前於九十二年十一月七日因涉犯竊盜罪嫌而經本院以九十二年度簡字第\n    四一二五號判處罰金一千元之部分（下稱前案），被告於本院調查中到庭供稱：\n    伊於前案為警查獲後，有被送到地檢署，經檢察官飭回而離去，於斯時，伊並未\n    想到要再去竊盜，本案係因與金超群商店店員前有爭執而下手行竊等語，且前案\n    係於九十二年十二月一日經本院判決，並於九十二年十二月九日寄存送達於管轄\n    被告住處之派出所、且於同年十二月十五日送達於檢察官，此業經本院調閱前案\n    卷宗並影印附卷可參，足認被告顯係於前案經檢察官飭回後始另行起意犯下本案\n    ，本案並非前案起訴或既判力效力所及，併此敘明。\n五、依刑事訴訟法第四百四十九條第一項、第三項，刑法第三百二十條第一項、第四\n    十二條第二項，罰金罰鍰提高標準條例第一條前段、第二條，逕以簡易判決處刑\n    如主文。\n如不服本件判決，得自收受送達之日起十日內，向本院提起上訴。",
    "reason": "一、甲○○前曾因竊盜案件，經本院以九十二年度簡字第四一二五號判處罰金一千元\n    （不構成累犯），竟因曾與位於臺北市○○○路○段二五號「金超群商店」之店\n    員發生爭執而於民國九十二年十二月二十四日凌晨二時三十分許，復意圖為自己\n    不法所有之犯意，在上址「金超群商店」內，徒手竊取價值共新臺幣（下同）四\n    十五元之富士牌接著劑二條、如意牌竹牙籤一包，並即將前開竊得物品藏放於口\n    袋內，得手後欲離去之際，為該店店員林建成發覺並報警處理始查悉上情。\n二、上開犯罪事實，業據被告甲○○於警詢及本院調查中坦白承認，核與證人林建成\n    於警詢所述情節相符，並有臺北市政府警察局中山分局贓物認領保管收據一紙、\n    照片一張在卷可資佐證，被告自白與事實相符，本件事證已臻明確，被告犯行堪\n    以認定。\n三、核被告所為，係犯刑法第三百二十條第一項之竊盜罪。爰審酌被告雖前曾因竊盜\n    案件，經本院判處罰金一千元後，再次犯下本件犯行，然被告於警詢及本院調查\n    中均坦白承認犯行，並表示悔意，犯後態度尚佳，被告係以順手牽羊之方式竊取\n    他人財物，竊得之物品價值不大等情狀，量處如主文所示之刑，並諭知易服勞役\n    之折算標準。\n四、至於被告前於九十二年十一月七日因涉犯竊盜罪嫌而經本院以九十二年度簡字第\n    四一二五號判處罰金一千元之部分（下稱前案），被告於本院調查中到庭供稱：\n    伊於前案為警查獲後，有被送到地檢署，經檢察官飭回而離去，於斯時，伊並未\n    想到要再去竊盜，本案係因與金超群商店店員前有爭執而下手行竊等語，且前案\n    係於九十二年十二月一日經本院判決，並於九十二年十二月九日寄存送達於管轄\n    被告住處之派出所、且於同年十二月十五日送達於檢察官，此業經本院調閱前案\n    卷宗並影印附卷可參，足認被告顯係於前案經檢察官飭回後始另行起意犯下本案\n    ，本案並非前案起訴或既判力效力所及，併此敘明。\n五、依刑事訴訟法第四百四十九條第一項、第三項，刑法第三百二十條第一項、第四\n    十二條第二項，罰金罰鍰提高標準條例第一條前段、第二條，逕以簡易判決處刑\n    如主文。\n如不服本件判決，得自收受送達之日起十日內，向本院提起上訴。"
  },
  "search": "臺灣臺北地方法院刑事簡易判決九十三年度簡字第三二三號聲請人臺灣臺北地方法院檢察署檢察官被告甲○○右列被告因竊盜案件，經檢察官聲請以簡易判決處刑（九十三年度偵字第一一三三號），本院判決如左：主文甲○○竊盜，科罰金貳仟元，如易服勞役，以佰元折算壹日。事實及理由一、甲○○前曾因竊盜案件，經本院以九十二年度簡字第四一二五號判處罰金一千元（不構成累犯），竟因曾與位於臺北市○○○路○段二五號「金超群商店」之店員發生爭執而於民國九十二年十二月二十四日凌晨二時三十分許，復意圖為自己不法所有之犯意，在上址「金超群商店」內，徒手竊取價值共新臺幣（下同）四十五元之富士牌接著劑二條、如意牌竹牙籤一包，並即將前開竊得物品藏放於口袋內，得手後欲離去之際，為該店店員林建成發覺並報警處理始查悉上情。二、上開犯罪事實，業據被告甲○○於警詢及本院調查中坦白承認，核與證人林建成於警詢所述情節相符，並有臺北市政府警察局中山分局贓物認領保管收據一紙、照片一張在卷可資佐證，被告自白與事實相符，本件事證已臻明確，被告犯行堪以認定。三、核被告所為，係犯刑法第三百二十條第一項之竊盜罪。爰審酌被告雖前曾因竊盜案件，經本院判處罰金一千元後，再次犯下本件犯行，然被告於警詢及本院調查中均坦白承認犯行，並表示悔意，犯後態度尚佳，被告係以順手牽羊之方式竊取他人財物，竊得之物品價值不大等情狀，量處如主文所示之刑，並諭知易服勞役之折算標準。四、至於被告前於九十二年十一月七日因涉犯竊盜罪嫌而經本院以九十二年度簡字第四一二五號判處罰金一千元之部分（下稱前案），被告於本院調查中到庭供稱：伊於前案為警查獲後，有被送到地檢署，經檢察官飭回而離去，於斯時，伊並未想到要再去竊盜，本案係因與金超群商店店員前有爭執而下手行竊等語，且前案係於九十二年十二月一日經本院判決，並於九十二年十二月九日寄存送達於管轄被告住處之派出所、且於同年十二月十五日送達於檢察官，此業經本院調閱前案卷宗並影印附卷可參，足認被告顯係於前案經檢察官飭回後始另行起意犯下本案，本案並非前案起訴或既判力效力所及，併此敘明。五、依刑事訴訟法第四百四十九條第一項、第三項，刑法第三百二十條第一項、第四十二條第二項，罰金罰鍰提高標準條例第一條前段、第二條，逕以簡易判決處刑如主文。如不服本件判決，得自收受送達之日起十日內，向本院提起上訴。中華民國九十三年三月十日臺灣臺北地方法院刑事第一庭法官唐于智右正本證明與原本無異。書記官陳俐妙中華民國九十三年三月十日附錄本案論罪法條刑法第三百二十條第一項意圖為自己或第三人不法之所有，而竊取他人之動產者，為竊盜罪，處五年以下有期徒刑、拘役或五百元以下罰金。",
  "characters": {
    "judges": [
      "唐于智"
    ],
    "prosecutors": [

    ],
    "lawyers": [

    ],
    "clerks": [
      "陳俐妙"
    ],
    "plaintiffs": [

    ],
    "defendants": [
      "甲○○",
      "右列被告因竊盜案件，經檢察官聲請以簡易判決處刑（九十三年度偵字第一一三三號",
      "），本院判決如左："
    ],
    "prosecutor_office": [
      "臺灣臺北地方法院檢察署檢察官"
    ],
    "creditors": [

    ],
    "debtors": [

    ],
    "judicial_associate_officer": [

    ]
  },
  "adjudged_at": "2004-03-10",
  "created_at": "2016-02-06 10:10:30",
  "updated_at": "2016-02-06 10:10:30"
}