{
  "identify": "TPD-93-簡-550-20040311-1",
  "court": {
    "name": "臺灣臺北地方法院",
    "code": "TPD"
  },
  "division": {
    "name": "刑事",
    "code": "M"
  },
  "year": 93,
  "word": "簡",
  "number": "550",
  "jcheck": "1",
  "reason": "贓物",
  "content": "臺灣臺北地方法院刑事簡易判決                      九十三年度簡字第五五○號\n      公  訴  人  臺灣臺北地方法院檢察署檢察官\n      被      告  甲○○\n右列被告因贓物案件，經檢察官提起公訴（九十二年度偵緝字第一五五一號），被告\n於本院準備程序中自白犯罪，本院合議庭認為宜以簡易判決處刑，判決如左：\n    主      文\n甲○○收受贓物，累犯，處拘役伍拾伍日，如易科罰金，以參佰元折算壹日。\n    事實及理由\n一、本件除犯罪事實應補充被告甲○○「前於民國九十年間因詐欺案件，經本院判處\n    有期徒刑三月確定，於九十一年五月二十八日易科罰金執行完畢」以及應將被告\n    所收受之贓車原車號「Ｋ四─一一九八號」更正為「ＢＩ─六七五八號」、增加\n    被告收受贓車之地點係在其住處臺北縣烏來鄉忠治村四八號、證據部分應補充被\n    告於本院訊問時坦承犯行以及贓車之行車執照、保險證（行車執照與保險證之車\n    主姓名不同）外，餘犯罪事實、證據及應適用之法條均引用檢察官聲請簡易判決\n    處刑書之記載（如附件）。\n二、被告前於九十年間因詐欺案件，經本院判處有期徒刑三月確定，於九十一年五月\n    二十八日易科罰金執行完畢，有臺灣高等法院被告全國前案紀錄表在卷可按，被\n    告五年以內再犯本件有期徒刑以上之罪，核屬累犯，應依刑法第四十七條規定加\n    重其刑。\n三、依刑事訴訟法第四百四十九條第二項、第三項、第四百五十四條第二項、刑法第\n    三百四十九條第一項、第四十七條、第四十一條第一項前段、罰金罰鍰提高標準\n    條例第一條前段、第二條，逕以簡易判決處如主文所示之刑。\n如不服本件判決，得自收受送達之日起十日內，向本院提起上訴。\n中      華      民      國    九十三    年      三      月    十一      日\n                                臺灣臺北地方法院刑事第十五庭\n                                          法  官 范智達\n右正本證明與原本無異。\n                                          書記官 田華仁\n中      華      民      國    九十三    年      三      月    十一      日\n附錄本案論罪科刑法條：\n刑法第三百四十九條\n收受贓物者，處三年以下有期徒刑、拘役或五百元以下罰金。\n搬運、寄藏、故買贓物或為牙保者，處五年以下有期徒刑、拘役或科或併科一千元以\n下罰金。\n因贓物變得之財物，以贓物論。\n",
  "structure": {
    "main": "甲○○收受贓物，累犯，處拘役伍拾伍日，如易科罰金，以參佰元折算壹日。",
    "fact": "一、本件除犯罪事實應補充被告甲○○「前於民國九十年間因詐欺案件，經本院判處\n    有期徒刑三月確定，於九十一年五月二十八日易科罰金執行完畢」以及應將被告\n    所收受之贓車原車號「Ｋ四─一一九八號」更正為「ＢＩ─六七五八號」、增加\n    被告收受贓車之地點係在其住處臺北縣烏來鄉忠治村四八號、證據部分應補充被\n    告於本院訊問時坦承犯行以及贓車之行車執照、保險證（行車執照與保險證之車\n    主姓名不同）外，餘犯罪事實、證據及應適用之法條均引用檢察官聲請簡易判決\n    處刑書之記載（如附件）。\n二、被告前於九十年間因詐欺案件，經本院判處有期徒刑三月確定，於九十一年五月\n    二十八日易科罰金執行完畢，有臺灣高等法院被告全國前案紀錄表在卷可按，被\n    告五年以內再犯本件有期徒刑以上之罪，核屬累犯，應依刑法第四十七條規定加\n    重其刑。\n三、依刑事訴訟法第四百四十九條第二項、第三項、第四百五十四條第二項、刑法第\n    三百四十九條第一項、第四十七條、第四十一條第一項前段、罰金罰鍰提高標準\n    條例第一條前段、第二條，逕以簡易判決處如主文所示之刑。\n如不服本件判決，得自收受送達之日起十日內，向本院提起上訴。",
    "reason": "一、本件除犯罪事實應補充被告甲○○「前於民國九十年間因詐欺案件，經本院判處\n    有期徒刑三月確定，於九十一年五月二十八日易科罰金執行完畢」以及應將被告\n    所收受之贓車原車號「Ｋ四─一一九八號」更正為「ＢＩ─六七五八號」、增加\n    被告收受贓車之地點係在其住處臺北縣烏來鄉忠治村四八號、證據部分應補充被\n    告於本院訊問時坦承犯行以及贓車之行車執照、保險證（行車執照與保險證之車\n    主姓名不同）外，餘犯罪事實、證據及應適用之法條均引用檢察官聲請簡易判決\n    處刑書之記載（如附件）。\n二、被告前於九十年間因詐欺案件，經本院判處有期徒刑三月確定，於九十一年五月\n    二十八日易科罰金執行完畢，有臺灣高等法院被告全國前案紀錄表在卷可按，被\n    告五年以內再犯本件有期徒刑以上之罪，核屬累犯，應依刑法第四十七條規定加\n    重其刑。\n三、依刑事訴訟法第四百四十九條第二項、第三項、第四百五十四條第二項、刑法第\n    三百四十九條第一項、第四十七條、第四十一條第一項前段、罰金罰鍰提高標準\n    條例第一條前段、第二條，逕以簡易判決處如主文所示之刑。\n如不服本件判決，得自收受送達之日起十日內，向本院提起上訴。"
  },
  "search": "臺灣臺北地方法院刑事簡易判決九十三年度簡字第五五○號公訴人臺灣臺北地方法院檢察署檢察官被告甲○○右列被告因贓物案件，經檢察官提起公訴（九十二年度偵緝字第一五五一號），被告於本院準備程序中自白犯罪，本院合議庭認為宜以簡易判決處刑，判決如左：主文甲○○收受贓物，累犯，處拘役伍拾伍日，如易科罰金，以參佰元折算壹日。事實及理由一、本件除犯罪事實應補充被告甲○○「前於民國九十年間因詐欺案件，經本院判處有期徒刑三月確定，於九十一年五月二十八日易科罰金執行完畢」以及應將被告所收受之贓車原車號「Ｋ四─一一九八號」更正為「ＢＩ─六七五八號」、增加被告收受贓車之地點係在其住處臺北縣烏來鄉忠治村四八號、證據部分應補充被告於本院訊問時坦承犯行以及贓車之行車執照、保險證（行車執照與保險證之車主姓名不同）外，餘犯罪事實、證據及應適用之法條均引用檢察官聲請簡易判決處刑書之記載（如附件）。二、被告前於九十年間因詐欺案件，經本院判處有期徒刑三月確定，於九十一年五月二十八日易科罰金執行完畢，有臺灣高等法院被告全國前案紀錄表在卷可按，被告五年以內再犯本件有期徒刑以上之罪，核屬累犯，應依刑法第四十七條規定加重其刑。三、依刑事訴訟法第四百四十九條第二項、第三項、第四百五十四條第二項、刑法第三百四十九條第一項、第四十七條、第四十一條第一項前段、罰金罰鍰提高標準條例第一條前段、第二條，逕以簡易判決處如主文所示之刑。如不服本件判決，得自收受送達之日起十日內，向本院提起上訴。中華民國九十三年三月十一日臺灣臺北地方法院刑事第十五庭法官范智達右正本證明與原本無異。書記官田華仁中華民國九十三年三月十一日附錄本案論罪科刑法條：刑法第三百四十九條收受贓物者，處三年以下有期徒刑、拘役或五百元以下罰金。搬運、寄藏、故買贓物或為牙保者，處五年以下有期徒刑、拘役或科或併科一千元以下罰金。因贓物變得之財物，以贓物論。",
  "characters": {
    "judges": [
      "范智達"
    ],
    "prosecutors": [

    ],
    "lawyers": [

    ],
    "clerks": [
      "田華仁"
    ],
    "plaintiffs": [

    ],
    "defendants": [
      "甲○○",
      "右列被告因贓物案件，經檢察官提起公訴（九十二年度偵緝字第一五五一號），被告",
      "於本院準備程序中自白犯罪，本院合議庭認為宜以簡易判決處刑，判決如左："
    ],
    "prosecutor_office": [
      "臺灣臺北地方法院檢察署檢察官"
    ],
    "creditors": [

    ],
    "debtors": [

    ],
    "judicial_associate_officer": [

    ]
  },
  "adjudged_at": "2004-03-11",
  "created_at": "2016-02-06 10:23:00",
  "updated_at": "2016-02-06 10:23:00"
}