{
  "identify": "KSD-100-簡-142-20110407-1",
  "court": {
    "name": "臺灣高雄地方法院",
    "code": "KSD"
  },
  "division": {
    "name": "刑事",
    "code": "M"
  },
  "year": 100,
  "word": "簡",
  "number": "142",
  "jcheck": "1",
  "reason": "妨害家庭",
  "content": "臺灣高雄地方法院刑事簡易判決          100年度簡字第142號\n聲  請  人  臺灣高雄地方法院檢察署檢察官\n被      告  方香懿\n上列被告因妨害婚姻案件，經檢察官聲請以簡易判決處刑（99年\n度偵字第29147 號），本院判決如下：\n    主  文\n方香懿犯相姦罪，處有期徒刑貳月，如易科罰金，以新臺幣壹仟\n元折算壹日。\n    事實及理由\n一、本件犯罪事實及證據名稱暨被告辯解不足以採信之理由，業\n    據檢察官於聲請簡易判決處刑書記載明確予以引用如附件。\n二、核被告方香懿所為，係犯刑法第239條後段之相姦罪。爰審\n    酌被告明知吳煌池為有配偶之人，竟仍與之發生性交行為，\n    影響告訴人婚姻生活之圓滿，迄今尚未與告訴人達成和解，\n    惟念其無前科，有臺灣高等法院被告前案紀錄表附卷可稽，\n    及其犯罪目的、生活狀況、智識程度等一切情狀，量處如主\n    文所示之刑，並諭知易科罰金之折算標準，以資懲儆。\n三、依刑事訴訟法第449條第1項前段、第3項、第454條第2項，\n    刑法第239條後段、第41條第1項前段，逕以簡易判決處刑如\n    主文。\n四、如不服本判決，應於判決送達後10日內，向本院提出上訴狀\n    。 \n中    華    民    國   100    年    4     月    7     日\n                  高雄簡易庭   法  官   李爭春\n以上正本證明與原本無異。\n如不服本判決，應於判決送達之日起10日內向本院提出上訴書狀\n。                          \n中    華    民    國   100    年    4     月    8     日\n                               書記官   胡淑芳\n附錄本件論罪科刑法條：\n刑法第239條：\n有配偶而與人通姦者，處1年以下有期徒刑。其相姦者亦同。",
  "structure": {
    "main": "方香懿犯相姦罪，處有期徒刑貳月，如易科罰金，以新臺幣壹仟\n元折算壹日。",
    "fact": "一、本件犯罪事實及證據名稱暨被告辯解不足以採信之理由，業\n    據檢察官於聲請簡易判決處刑書記載明確予以引用如附件。\n二、核被告方香懿所為，係犯刑法第239條後段之相姦罪。爰審\n    酌被告明知吳煌池為有配偶之人，竟仍與之發生性交行為，\n    影響告訴人婚姻生活之圓滿，迄今尚未與告訴人達成和解，\n    惟念其無前科，有臺灣高等法院被告前案紀錄表附卷可稽，\n    及其犯罪目的、生活狀況、智識程度等一切情狀，量處如主\n    文所示之刑，並諭知易科罰金之折算標準，以資懲儆。\n三、依刑事訴訟法第449條第1項前段、第3項、第454條第2項，\n    刑法第239條後段、第41條第1項前段，逕以簡易判決處刑如\n    主文。\n四、如不服本判決，應於判決送達後10日內，向本院提出上訴狀\n    。",
    "reason": "一、本件犯罪事實及證據名稱暨被告辯解不足以採信之理由，業\n    據檢察官於聲請簡易判決處刑書記載明確予以引用如附件。\n二、核被告方香懿所為，係犯刑法第239條後段之相姦罪。爰審\n    酌被告明知吳煌池為有配偶之人，竟仍與之發生性交行為，\n    影響告訴人婚姻生活之圓滿，迄今尚未與告訴人達成和解，\n    惟念其無前科，有臺灣高等法院被告前案紀錄表附卷可稽，\n    及其犯罪目的、生活狀況、智識程度等一切情狀，量處如主\n    文所示之刑，並諭知易科罰金之折算標準，以資懲儆。\n三、依刑事訴訟法第449條第1項前段、第3項、第454條第2項，\n    刑法第239條後段、第41條第1項前段，逕以簡易判決處刑如\n    主文。\n四、如不服本判決，應於判決送達後10日內，向本院提出上訴狀\n    。"
  },
  "search": "臺灣高雄地方法院刑事簡易判決100年度簡字第142號聲請人臺灣高雄地方法院檢察署檢察官被告方香懿上列被告因妨害婚姻案件，經檢察官聲請以簡易判決處刑（99年度偵字第29147號），本院判決如下：主文方香懿犯相姦罪，處有期徒刑貳月，如易科罰金，以新臺幣壹仟元折算壹日。事實及理由一、本件犯罪事實及證據名稱暨被告辯解不足以採信之理由，業據檢察官於聲請簡易判決處刑書記載明確予以引用如附件。二、核被告方香懿所為，係犯刑法第239條後段之相姦罪。爰審酌被告明知吳煌池為有配偶之人，竟仍與之發生性交行為，影響告訴人婚姻生活之圓滿，迄今尚未與告訴人達成和解，惟念其無前科，有臺灣高等法院被告前案紀錄表附卷可稽，及其犯罪目的、生活狀況、智識程度等一切情狀，量處如主文所示之刑，並諭知易科罰金之折算標準，以資懲儆。三、依刑事訴訟法第449條第1項前段、第3項、第454條第2項，刑法第239條後段、第41條第1項前段，逕以簡易判決處刑如主文。四、如不服本判決，應於判決送達後10日內，向本院提出上訴狀。中華民國100年4月7日高雄簡易庭法官李爭春以上正本證明與原本無異。如不服本判決，應於判決送達之日起10日內向本院提出上訴書狀。中華民國100年4月8日書記官胡淑芳附錄本件論罪科刑法條：刑法第239條：有配偶而與人通姦者，處1年以下有期徒刑。其相姦者亦同。",
  "characters": {
    "judges": [
      "李爭春"
    ],
    "prosecutors": [

    ],
    "lawyers": [

    ],
    "clerks": [
      "胡淑芳"
    ],
    "plaintiffs": [

    ],
    "defendants": [
      "方香懿"
    ],
    "prosecutor_office": [
      "臺灣高雄地方法院檢察署檢察官"
    ],
    "creditors": [

    ],
    "debtors": [

    ],
    "judicial_associate_officer": [

    ]
  },
  "adjudged_at": "2011-04-07",
  "created_at": "2016-02-12 10:41:26",
  "updated_at": "2016-02-12 10:41:26"
}