{
  "identify": "TCD-100-中簡-1502-20110616-1",
  "court": {
    "name": "臺灣臺中地方法院",
    "code": "TCD"
  },
  "division": {
    "name": "刑事",
    "code": "M"
  },
  "year": 100,
  "word": "中簡",
  "number": "1502",
  "jcheck": "1",
  "reason": "偽造文書等",
  "content": "臺灣臺中地方法院刑事簡易判決       100年度中簡字第1502號\n聲  請  人  臺灣臺中地方法院檢察署檢察官\n被      告  傅慶斌\n上列被告因偽造文書等案件，經檢察官聲請以簡易判決處刑（10\n0年度偵字第11013號），本院判決如下：\n    主  文\n傅慶斌犯侵占離本人持有物罪，處罰金新臺幣伍仟元，如易服勞\n役，以新臺幣壹仟元折算壹日。又犯行使變造特種文書罪，處有\n期徒刑貳月，如易科罰金，以新臺幣壹仟元折算壹日。\n    事實及理由\n一、本件犯罪事實欄第15行於「資料管理之正確性」後補充「及\n    林文雀本人」，證據欄(二)關於「被害人林文雀於本署偵查中\n    之陳述」更正為「被害人林文雀於警詢時之陳述」，其餘犯\n    罪事實及證據均引用檢察官聲請簡易判決處刑書之記載（如\n    附件所示）。\n二、依刑事訴訟法第449條第1項前段、第454條第2項，刑法第21\n    2條、第216條、第337條、第41條第1項前段、第42條 第3項\n    ，刑法施行法第1條之1第1項、第2項前段，逕以簡易判決處\n    刑如主文。\n如不服本判決，得於判決書送達之日起10日內，以書狀敘述理由\n，向本院提出上訴（須附繕本）。\n中    華    民    國   100    年    6     月    16    日\n                    臺中簡易庭  法  官  張靜琪\n上正本證明與原本無異。\n                                書記官  王嘉麒\n中    華    民    國   100    年    6     月    16    日\n【附錄本案論罪科刑法條】\n刑法第212條\n偽造、變造護照、旅券、免許證、特許證及關於品行、能力服務\n或其他相類之證書、介紹書，足以生損害於公眾或他人者，處 1\n年以下有期徒刑、拘役或3百元以下罰金。\n刑法第216條\n行使第210條至第215條之文書者，依偽造、變造文書或登載不實\n事項或使登載不實事項之規定處斷。\n刑法第337條\n意圖為自己或第三人不法之所有，而侵占遺失物、漂流物或其他\n離本人所持有之物者，處5百元以下罰金。",
  "structure": {
    "main": "傅慶斌犯侵占離本人持有物罪，處罰金新臺幣伍仟元，如易服勞\n役，以新臺幣壹仟元折算壹日。又犯行使變造特種文書罪，處有\n期徒刑貳月，如易科罰金，以新臺幣壹仟元折算壹日。",
    "fact": "一、本件犯罪事實欄第15行於「資料管理之正確性」後補充「及\n    林文雀本人」，證據欄(二)關於「被害人林文雀於本署偵查中\n    之陳述」更正為「被害人林文雀於警詢時之陳述」，其餘犯\n    罪事實及證據均引用檢察官聲請簡易判決處刑書之記載（如\n    附件所示）。\n二、依刑事訴訟法第449條第1項前段、第454條第2項，刑法第21\n    2條、第216條、第337條、第41條第1項前段、第42條 第3項\n    ，刑法施行法第1條之1第1項、第2項前段，逕以簡易判決處\n    刑如主文。\n如不服本判決，得於判決書送達之日起10日內，以書狀敘述理由\n，向本院提出上訴（須附繕本）。",
    "reason": "一、本件犯罪事實欄第15行於「資料管理之正確性」後補充「及\n    林文雀本人」，證據欄(二)關於「被害人林文雀於本署偵查中\n    之陳述」更正為「被害人林文雀於警詢時之陳述」，其餘犯\n    罪事實及證據均引用檢察官聲請簡易判決處刑書之記載（如\n    附件所示）。\n二、依刑事訴訟法第449條第1項前段、第454條第2項，刑法第21\n    2條、第216條、第337條、第41條第1項前段、第42條 第3項\n    ，刑法施行法第1條之1第1項、第2項前段，逕以簡易判決處\n    刑如主文。\n如不服本判決，得於判決書送達之日起10日內，以書狀敘述理由\n，向本院提出上訴（須附繕本）。"
  },
  "search": "臺灣臺中地方法院刑事簡易判決100年度中簡字第1502號聲請人臺灣臺中地方法院檢察署檢察官被告傅慶斌上列被告因偽造文書等案件，經檢察官聲請以簡易判決處刑（100年度偵字第11013號），本院判決如下：主文傅慶斌犯侵占離本人持有物罪，處罰金新臺幣伍仟元，如易服勞役，以新臺幣壹仟元折算壹日。又犯行使變造特種文書罪，處有期徒刑貳月，如易科罰金，以新臺幣壹仟元折算壹日。事實及理由一、本件犯罪事實欄第15行於「資料管理之正確性」後補充「及林文雀本人」，證據欄(二)關於「被害人林文雀於本署偵查中之陳述」更正為「被害人林文雀於警詢時之陳述」，其餘犯罪事實及證據均引用檢察官聲請簡易判決處刑書之記載（如附件所示）。二、依刑事訴訟法第449條第1項前段、第454條第2項，刑法第212條、第216條、第337條、第41條第1項前段、第42條第3項，刑法施行法第1條之1第1項、第2項前段，逕以簡易判決處刑如主文。如不服本判決，得於判決書送達之日起10日內，以書狀敘述理由，向本院提出上訴（須附繕本）。中華民國100年6月16日臺中簡易庭法官張靜琪上正本證明與原本無異。書記官王嘉麒中華民國100年6月16日【附錄本案論罪科刑法條】刑法第212條偽造、變造護照、旅券、免許證、特許證及關於品行、能力服務或其他相類之證書、介紹書，足以生損害於公眾或他人者，處1年以下有期徒刑、拘役或3百元以下罰金。刑法第216條行使第210條至第215條之文書者，依偽造、變造文書或登載不實事項或使登載不實事項之規定處斷。刑法第337條意圖為自己或第三人不法之所有，而侵占遺失物、漂流物或其他離本人所持有之物者，處5百元以下罰金。",
  "characters": {
    "judges": [
      "張靜琪"
    ],
    "prosecutors": [

    ],
    "lawyers": [

    ],
    "clerks": [
      "王嘉麒"
    ],
    "plaintiffs": [

    ],
    "defendants": [
      "傅慶斌"
    ],
    "prosecutor_office": [
      "臺灣臺中地方法院檢察署檢察官"
    ],
    "creditors": [

    ],
    "debtors": [

    ],
    "judicial_associate_officer": [

    ]
  },
  "adjudged_at": "2011-06-16",
  "created_at": "2016-02-13 19:04:46",
  "updated_at": "2016-02-13 19:04:46"
}