{
  "identify": "TPH-99-上更(一)-538-20110617-4",
  "court": {
    "name": "臺灣高等法院",
    "code": "TPH"
  },
  "division": {
    "name": "刑事",
    "code": "M"
  },
  "year": 99,
  "word": "上更(一)",
  "number": "538",
  "jcheck": "4",
  "reason": "殺人等",
  "content": "臺灣高等法院刑事裁定             99年度上更(一)字第538號\n上  訴  人\n即  被  告  蕭文凱\n選任辯護人  法律扶助王淑琍律師\n上列被告因殺人案件，本院裁定如下：\n    主  文\n蕭文凱之羈押期間，自民國壹佰年柒月壹日起，延長貳月。\n    理  由\n一、上訴人即被告蕭文凱前經本院認涉犯刑法第271條第1項之殺\n    人罪、同法第277條第2項之傷害致死罪，嫌疑重大，有刑事\n    訴訟法第101條第1項第1款、第3款情形，非予羈押，顯難進\n    行審判，於民國99年11月29日執行羈押，嗣經本院先後裁定\n    其羈押期間自100年3月1日、同年5月1日起延長二月，至100\n    年6月30日，其延長羈押期間即將屆滿。\n二、茲經本院於100年6月16日訊問後，認被告蕭文凱犯罪嫌疑重\n    大，所涉刑法第271條第1項之殺人罪，為最輕本刑五年以上\n    有期徒刑之罪，且被告蕭文凱經本院判處有期徒刑十三年之\n    重刑，有相當理由及事實足認有逃亡之虞，核與刑事訴訟法\n    第101條第1項第1款、第3款之羈押要件相符，羈押原因依然\n    存在，非予羈押，顯難進行審判或執行，仍有繼續羈押被告\n    蕭文凱之必要，被告蕭文凱應自100年7月1日起延長羈押二\n    月，爰依刑事訴訟法第108條第1項、第5項，裁定如主文。\n中    華    民    國   100    年    6     月    17    日\n                  刑事第二十庭  審判長法  官  周盈文\n                                      法  官  詹駿鴻\n                                      法  官  林海祥\n以上正本證明與原本無異。\n如不服本裁定，應於收受送達後五日內向本院提出抗告狀。\n                                      書記官  林敬傑\n中    華    民    國   100    年    6     月    17    日",
  "structure": {
    "main": "蕭文凱之羈押期間，自民國壹佰年柒月壹日起，延長貳月。",
    "reason": "一、上訴人即被告蕭文凱前經本院認涉犯刑法第271條第1項之殺\n    人罪、同法第277條第2項之傷害致死罪，嫌疑重大，有刑事\n    訴訟法第101條第1項第1款、第3款情形，非予羈押，顯難進\n    行審判，於民國99年11月29日執行羈押，嗣經本院先後裁定\n    其羈押期間自100年3月1日、同年5月1日起延長二月，至100\n    年6月30日，其延長羈押期間即將屆滿。\n二、茲經本院於100年6月16日訊問後，認被告蕭文凱犯罪嫌疑重\n    大，所涉刑法第271條第1項之殺人罪，為最輕本刑五年以上\n    有期徒刑之罪，且被告蕭文凱經本院判處有期徒刑十三年之\n    重刑，有相當理由及事實足認有逃亡之虞，核與刑事訴訟法\n    第101條第1項第1款、第3款之羈押要件相符，羈押原因依然\n    存在，非予羈押，顯難進行審判或執行，仍有繼續羈押被告\n    蕭文凱之必要，被告蕭文凱應自100年7月1日起延長羈押二\n    月，爰依刑事訴訟法第108條第1項、第5項，裁定如主文。"
  },
  "search": "臺灣高等法院刑事裁定99年度上更(一)字第538號上訴人即被告蕭文凱選任辯護人法律扶助王淑琍律師上列被告因殺人案件，本院裁定如下：主文蕭文凱之羈押期間，自民國壹佰年柒月壹日起，延長貳月。理由一、上訴人即被告蕭文凱前經本院認涉犯刑法第271條第1項之殺人罪、同法第277條第2項之傷害致死罪，嫌疑重大，有刑事訴訟法第101條第1項第1款、第3款情形，非予羈押，顯難進行審判，於民國99年11月29日執行羈押，嗣經本院先後裁定其羈押期間自100年3月1日、同年5月1日起延長二月，至100年6月30日，其延長羈押期間即將屆滿。二、茲經本院於100年6月16日訊問後，認被告蕭文凱犯罪嫌疑重大，所涉刑法第271條第1項之殺人罪，為最輕本刑五年以上有期徒刑之罪，且被告蕭文凱經本院判處有期徒刑十三年之重刑，有相當理由及事實足認有逃亡之虞，核與刑事訴訟法第101條第1項第1款、第3款之羈押要件相符，羈押原因依然存在，非予羈押，顯難進行審判或執行，仍有繼續羈押被告蕭文凱之必要，被告蕭文凱應自100年7月1日起延長羈押二月，爰依刑事訴訟法第108條第1項、第5項，裁定如主文。中華民國100年6月17日刑事第二十庭審判長法官周盈文法官詹駿鴻法官林海祥以上正本證明與原本無異。如不服本裁定，應於收受送達後五日內向本院提出抗告狀。書記官林敬傑中華民國100年6月17日",
  "characters": {
    "judges": [
      "周盈文",
      "詹駿鴻",
      "林海祥"
    ],
    "prosecutors": [

    ],
    "lawyers": [
      "法律扶助王淑琍"
    ],
    "clerks": [
      "林敬傑"
    ],
    "plaintiffs": [

    ],
    "defendants": [
      "蕭文凱"
    ],
    "prosecutor_office": [

    ],
    "creditors": [

    ],
    "debtors": [

    ],
    "judicial_associate_officer": [

    ]
  },
  "adjudged_at": "2011-06-17",
  "created_at": "2016-02-13 18:55:45",
  "updated_at": "2016-02-13 18:55:45"
}