{
  "identify": "TYD-100-桃簡-1221-20110617-1",
  "court": {
    "name": "臺灣桃園地方法院",
    "code": "TYD"
  },
  "division": {
    "name": "刑事",
    "code": "M"
  },
  "year": 100,
  "word": "桃簡",
  "number": "1221",
  "jcheck": "1",
  "reason": "竊盜",
  "content": "臺灣桃園地方法院刑事簡易判決       100年度桃簡字第1221號\n聲  請  人  臺灣桃園地方法院檢察署檢察官\n被      告  崔立學\n上列被告因竊盜案件，經檢察官聲請以簡易判決處刑（100 年度\n偵字第11192 號），本院判決如下：\n    主  文\n崔立學竊盜，未遂，累犯，處有期徒刑參月，如易科罰金，以新\n臺幣壹仟元折算壹日。扣案之鑰匙壹支沒收。\n    事實及理由\n一、本件犯罪事實、證據及所犯法條除引用檢察官聲請簡易判決\n    處刑書之記載（如附件）外，並補充如下：被告崔立學前因\n    竊盜案件，經本院以92年度易字第1024號刑事判決判處有期\n    徒刑2 年4 月確定，於民國96年8 月30日入監執行，至98年\n    5 月1 日假釋出獄，迄同年11月13日縮刑假釋期滿，假釋未\n    經撤銷，所餘刑期以已執行論而執行完畢，有臺灣高等法院\n    被告前案紀錄表可憑。其前受有期徒刑執行完畢，於5 年內\n    故意再犯本件有期徒刑以上之罪，為累犯，應依刑法第47條\n    第1 項之規定加重其刑。又被告雖已著手竊盜行為之實行，\n    惟並未竊得財物即為警查獲，其犯罪尚屬未遂，爰依刑法第\n    25條第2 項之規定，按既遂犯之刑度減輕其刑，並先加後減\n    。扣案之鑰匙1 支，為被告所有，且係供本件竊盜犯罪所用\n    之物，併依刑法第38條第1 項第2 款之規定宣告沒收。\n二、依刑事訴訟法第449 條第1 項前段、第450 條第1 項、第45\n    4 條第2 項，刑法第320 條第3 項、第1 項、第47條第1 項\n    、第25條第2 項、第41條第1 項前段、第38條第1 項第2 款\n    ，刑法施行法第1 條之1 第1 項、第2 項前段，逕以簡易判\n    決處如主文所示之刑。\n如不服本判決，得於判決書送達之翌日起10日內，以書狀敘述理\n由，向本庭提出上訴。\n中    華    民    國   100    年    6     月    17    日\n                  刑事第九庭  法  官  吳為平\n以上正本證明與原本無異。\n如不服本判決，應於判決送達後10日內向本院提出上訴狀（應附\n繕本）。\n                              書記官  常毓生\n中    華    民    國   100    年    6     月    20    日\n附錄論罪科刑法條：\n刑法第320條\n意圖為自己或第三人不法之所有，而竊取他人之動產者，為竊盜\n罪，處5  年以下有期徒刑、拘役或 5 百元以下罰金。\n意圖為自己或第三人不法之利益，而竊佔他人之不動產者，依前\n項之規定處斷。\n前二項之未遂犯罰之。",
  "structure": {
    "main": "崔立學竊盜，未遂，累犯，處有期徒刑參月，如易科罰金，以新\n臺幣壹仟元折算壹日。扣案之鑰匙壹支沒收。",
    "fact": "一、本件犯罪事實、證據及所犯法條除引用檢察官聲請簡易判決\n    處刑書之記載（如附件）外，並補充如下：被告崔立學前因\n    竊盜案件，經本院以92年度易字第1024號刑事判決判處有期\n    徒刑2 年4 月確定，於民國96年8 月30日入監執行，至98年\n    5 月1 日假釋出獄，迄同年11月13日縮刑假釋期滿，假釋未\n    經撤銷，所餘刑期以已執行論而執行完畢，有臺灣高等法院\n    被告前案紀錄表可憑。其前受有期徒刑執行完畢，於5 年內\n    故意再犯本件有期徒刑以上之罪，為累犯，應依刑法第47條\n    第1 項之規定加重其刑。又被告雖已著手竊盜行為之實行，\n    惟並未竊得財物即為警查獲，其犯罪尚屬未遂，爰依刑法第\n    25條第2 項之規定，按既遂犯之刑度減輕其刑，並先加後減\n    。扣案之鑰匙1 支，為被告所有，且係供本件竊盜犯罪所用\n    之物，併依刑法第38條第1 項第2 款之規定宣告沒收。\n二、依刑事訴訟法第449 條第1 項前段、第450 條第1 項、第45\n    4 條第2 項，刑法第320 條第3 項、第1 項、第47條第1 項\n    、第25條第2 項、第41條第1 項前段、第38條第1 項第2 款\n    ，刑法施行法第1 條之1 第1 項、第2 項前段，逕以簡易判\n    決處如主文所示之刑。\n如不服本判決，得於判決書送達之翌日起10日內，以書狀敘述理\n由，向本庭提出上訴。",
    "reason": "一、本件犯罪事實、證據及所犯法條除引用檢察官聲請簡易判決\n    處刑書之記載（如附件）外，並補充如下：被告崔立學前因\n    竊盜案件，經本院以92年度易字第1024號刑事判決判處有期\n    徒刑2 年4 月確定，於民國96年8 月30日入監執行，至98年\n    5 月1 日假釋出獄，迄同年11月13日縮刑假釋期滿，假釋未\n    經撤銷，所餘刑期以已執行論而執行完畢，有臺灣高等法院\n    被告前案紀錄表可憑。其前受有期徒刑執行完畢，於5 年內\n    故意再犯本件有期徒刑以上之罪，為累犯，應依刑法第47條\n    第1 項之規定加重其刑。又被告雖已著手竊盜行為之實行，\n    惟並未竊得財物即為警查獲，其犯罪尚屬未遂，爰依刑法第\n    25條第2 項之規定，按既遂犯之刑度減輕其刑，並先加後減\n    。扣案之鑰匙1 支，為被告所有，且係供本件竊盜犯罪所用\n    之物，併依刑法第38條第1 項第2 款之規定宣告沒收。\n二、依刑事訴訟法第449 條第1 項前段、第450 條第1 項、第45\n    4 條第2 項，刑法第320 條第3 項、第1 項、第47條第1 項\n    、第25條第2 項、第41條第1 項前段、第38條第1 項第2 款\n    ，刑法施行法第1 條之1 第1 項、第2 項前段，逕以簡易判\n    決處如主文所示之刑。\n如不服本判決，得於判決書送達之翌日起10日內，以書狀敘述理\n由，向本庭提出上訴。"
  },
  "search": "臺灣桃園地方法院刑事簡易判決100年度桃簡字第1221號聲請人臺灣桃園地方法院檢察署檢察官被告崔立學上列被告因竊盜案件，經檢察官聲請以簡易判決處刑（100年度偵字第11192號），本院判決如下：主文崔立學竊盜，未遂，累犯，處有期徒刑參月，如易科罰金，以新臺幣壹仟元折算壹日。扣案之鑰匙壹支沒收。事實及理由一、本件犯罪事實、證據及所犯法條除引用檢察官聲請簡易判決處刑書之記載（如附件）外，並補充如下：被告崔立學前因竊盜案件，經本院以92年度易字第1024號刑事判決判處有期徒刑2年4月確定，於民國96年8月30日入監執行，至98年5月1日假釋出獄，迄同年11月13日縮刑假釋期滿，假釋未經撤銷，所餘刑期以已執行論而執行完畢，有臺灣高等法院被告前案紀錄表可憑。其前受有期徒刑執行完畢，於5年內故意再犯本件有期徒刑以上之罪，為累犯，應依刑法第47條第1項之規定加重其刑。又被告雖已著手竊盜行為之實行，惟並未竊得財物即為警查獲，其犯罪尚屬未遂，爰依刑法第25條第2項之規定，按既遂犯之刑度減輕其刑，並先加後減。扣案之鑰匙1支，為被告所有，且係供本件竊盜犯罪所用之物，併依刑法第38條第1項第2款之規定宣告沒收。二、依刑事訴訟法第449條第1項前段、第450條第1項、第454條第2項，刑法第320條第3項、第1項、第47條第1項、第25條第2項、第41條第1項前段、第38條第1項第2款，刑法施行法第1條之1第1項、第2項前段，逕以簡易判決處如主文所示之刑。如不服本判決，得於判決書送達之翌日起10日內，以書狀敘述理由，向本庭提出上訴。中華民國100年6月17日刑事第九庭法官吳為平以上正本證明與原本無異。如不服本判決，應於判決送達後10日內向本院提出上訴狀（應附繕本）。書記官常毓生中華民國100年6月20日附錄論罪科刑法條：刑法第320條意圖為自己或第三人不法之所有，而竊取他人之動產者，為竊盜罪，處5年以下有期徒刑、拘役或5百元以下罰金。意圖為自己或第三人不法之利益，而竊佔他人之不動產者，依前項之規定處斷。前二項之未遂犯罰之。",
  "characters": {
    "judges": [
      "吳為平"
    ],
    "prosecutors": [

    ],
    "lawyers": [

    ],
    "clerks": [
      "常毓生"
    ],
    "plaintiffs": [

    ],
    "defendants": [
      "崔立學"
    ],
    "prosecutor_office": [
      "臺灣桃園地方法院檢察署檢察官"
    ],
    "creditors": [

    ],
    "debtors": [

    ],
    "judicial_associate_officer": [

    ]
  },
  "adjudged_at": "2011-06-17",
  "created_at": "2016-02-13 18:51:18",
  "updated_at": "2016-02-13 18:51:18"
}