{
  "identify": "TCD-100-訴-757-20110704-1",
  "court": {
    "name": "臺灣臺中地方法院",
    "code": "TCD"
  },
  "division": {
    "name": "民事",
    "code": "V"
  },
  "year": 100,
  "word": "訴",
  "number": "757",
  "jcheck": "1",
  "reason": "確認債權存在",
  "content": "臺灣臺地方法民事判決                  100年度訴字第757號\n原      告  和佶地磚有限公司\n法定代理人  石賜宗\n訴訟代理人  陳建勛律師\n被      告  義和營造工程股份有限公司\n法定代理人  陳奇男\n訴訟代理人  鄭順興\n被      告  內政部營建署\n法定代理人  葉世文\n訴訟代理人  蔡得謙律師\n複  代理人  侯志翔律師\n            何立斌律師\n上列當事人間確認債權存在事件，本院於民國100年6月20日言詞\n辯論終結，判決如下：\n    主      文\n確認被告義和營造工程股份有限公司對被告內政部營建署有新台\n幣壹佰貳拾陸萬柒仟壹佰肆拾肆元之工程款債權存在。\n訴訟費用由被告負擔。\n    事實及理由\n一、原告起訴主張：\n  (一)被告義和營造工程股份有限公司(下稱義和公司)於民國99年\n    8月23日將其向被告內政部營建署(下稱營建署)承攬之「國\n    立彰化高級商業職業學校教學行政大樓興建工程暨植栽工程\n    2項合併」工程(下稱系爭工程)中之地坪舖磨石子地磚工程\n    ，發包予原告施作，契約總價為新台幣(下同)132萬5630元\n    ，原告已施作完畢，依實作數量結算，被告義和公司應給付\n    原告138萬2206元。惟被告義和公司除給付12萬5119元外，\n    其餘125萬7087元之工程款尚未給付。\n  (二)嗣經原告聲請假扣押被告義和公司之財產，經鈞院以100年\n    度裁全字第224號裁定准原告供擔保後假扣押被告義和公司\n    之財產。原告乃提供擔保，聲請對被告義和公司對被告營建\n    署就上開系爭工程之工程款債權為假扣押，並由鈞院以100\n    年度司執全字第176號受理在案。詎料被告營建署具狀聲明\n    異議，略以：現在工程尚在施工中，債權金額尚未確定，而\n    否認被告義和公司對之有工程款債權存在。惟查，被告義和\n    公司向被告營建署所承攬之系爭工程，決標金額高達8816萬\n    8000元，縱使尚在施工，仍有履約保證金、各期估驗保留款\n    與工程尾款尚未給付予被告義和公司，被告營建署聲明異議\n    ，顯無理由。\n  (三)另鈞院所核發之假扣押執行命令，其範圍包括原告對被告義\n    和公司之工程款125萬7087元及假扣押執行費1萬0057元，金\n    額合計126萬7144元，爰依強制執行法第120條之規定，提起\n    本件確認債權之訴，並聲明：確認被告義和公司對被告營建\n    署有126萬7144元之工程款債權存在。\n二、被告部分：被告義和公司及被告營建署對於原告之上開主張\n    均不爭執。\n三、得心證之理由：\n  (一)按第三人於接獲扣押命令後，因對扣押債權之存否有所爭執\n    ，進而聲明異議者，執行債權人即得依民事訴訟法第247條\n    之規定提起確認之訴，以排除其私法上所處之不安定狀態（\n    最高法院89年度台上字第1477號、90年度台上字第415號判\n    決參照），是原告提起本件確認之訴，於法有據，合先敘明\n    。\n  (二)本件原告主張之事實，業據提出原告與被告義和公司之工程\n    合約書、發票、被告義和公司開立之支票、退票理由單、本\n    院100年度司裁全字第224號裁定、假扣押執行聲請狀、本院\n    100年司執全三字第176號執行命令、通知函、被告營建署提\n    出之聲明異議狀為證，並有被告義和公司與被告營建署之系\n    爭工程契約書為憑，且均為被告所不爭執，堪信屬實。從而\n    原告請求確認被告義和公司對被告營建署有126萬7144元之\n    工程款債權存在，為有理由。\n四、本件事證已臻明確，兩造其餘攻擊防禦方法及所舉證據，經\n    審酌結果，與本件判決結論均無影響，爰不一一論述，附此\n    敘明。\n五、結論：本件原告之訴為有理由，依民事訴訟法第78條、第85\n    條第1項前段，判決如主文。\n中    華    民    國    100    年    7    月     4    日\n                  民事第三庭    法  官  高英賓\n正本係照原本作成。\n如對本判決上訴，須於判決送達後20日內向本院提出上訴狀。如\n委任律師提起上訴者，應一併繳納上訴審裁判費。\n中    華    民    國    100    年    7    月     4    日\n                                書記官  廖碩薇",
  "structure": {
    "main": "確認被告義和營造工程股份有限公司對被告內政部營建署有新台\n幣壹佰貳拾陸萬柒仟壹佰肆拾肆元之工程款債權存在。\n訴訟費用由被告負擔。",
    "fact": "一、原告起訴主張：\n  (一)被告義和營造工程股份有限公司(下稱義和公司)於民國99年\n    8月23日將其向被告內政部營建署(下稱營建署)承攬之「國\n    立彰化高級商業職業學校教學行政大樓興建工程暨植栽工程\n    2項合併」工程(下稱系爭工程)中之地坪舖磨石子地磚工程\n    ，發包予原告施作，契約總價為新台幣(下同)132萬5630元\n    ，原告已施作完畢，依實作數量結算，被告義和公司應給付\n    原告138萬2206元。惟被告義和公司除給付12萬5119元外，\n    其餘125萬7087元之工程款尚未給付。\n  (二)嗣經原告聲請假扣押被告義和公司之財產，經鈞院以100年\n    度裁全字第224號裁定准原告供擔保後假扣押被告義和公司\n    之財產。原告乃提供擔保，聲請對被告義和公司對被告營建\n    署就上開系爭工程之工程款債權為假扣押，並由鈞院以100\n    年度司執全字第176號受理在案。詎料被告營建署具狀聲明\n    異議，略以：現在工程尚在施工中，債權金額尚未確定，而\n    否認被告義和公司對之有工程款債權存在。惟查，被告義和\n    公司向被告營建署所承攬之系爭工程，決標金額高達8816萬\n    8000元，縱使尚在施工，仍有履約保證金、各期估驗保留款\n    與工程尾款尚未給付予被告義和公司，被告營建署聲明異議\n    ，顯無理由。\n  (三)另鈞院所核發之假扣押執行命令，其範圍包括原告對被告義\n    和公司之工程款125萬7087元及假扣押執行費1萬0057元，金\n    額合計126萬7144元，爰依強制執行法第120條之規定，提起\n    本件確認債權之訴，並聲明：確認被告義和公司對被告營建\n    署有126萬7144元之工程款債權存在。\n二、被告部分：被告義和公司及被告營建署對於原告之上開主張\n    均不爭執。\n三、得心證之理由：\n  (一)按第三人於接獲扣押命令後，因對扣押債權之存否有所爭執\n    ，進而聲明異議者，執行債權人即得依民事訴訟法第247條\n    之規定提起確認之訴，以排除其私法上所處之不安定狀態（\n    最高法院89年度台上字第1477號、90年度台上字第415號判\n    決參照），是原告提起本件確認之訴，於法有據，合先敘明\n    。\n  (二)本件原告主張之事實，業據提出原告與被告義和公司之工程\n    合約書、發票、被告義和公司開立之支票、退票理由單、本\n    院100年度司裁全字第224號裁定、假扣押執行聲請狀、本院\n    100年司執全三字第176號執行命令、通知函、被告營建署提\n    出之聲明異議狀為證，並有被告義和公司與被告營建署之系\n    爭工程契約書為憑，且均為被告所不爭執，堪信屬實。從而\n    原告請求確認被告義和公司對被告營建署有126萬7144元之\n    工程款債權存在，為有理由。\n四、本件事證已臻明確，兩造其餘攻擊防禦方法及所舉證據，經\n    審酌結果，與本件判決結論均無影響，爰不一一論述，附此\n    敘明。\n五、結論：本件原告之訴為有理由，依民事訴訟法第78條、第85\n    條第1項前段，判決如主文。",
    "reason": "一、原告起訴主張：\n  (一)被告義和營造工程股份有限公司(下稱義和公司)於民國99年\n    8月23日將其向被告內政部營建署(下稱營建署)承攬之「國\n    立彰化高級商業職業學校教學行政大樓興建工程暨植栽工程\n    2項合併」工程(下稱系爭工程)中之地坪舖磨石子地磚工程\n    ，發包予原告施作，契約總價為新台幣(下同)132萬5630元\n    ，原告已施作完畢，依實作數量結算，被告義和公司應給付\n    原告138萬2206元。惟被告義和公司除給付12萬5119元外，\n    其餘125萬7087元之工程款尚未給付。\n  (二)嗣經原告聲請假扣押被告義和公司之財產，經鈞院以100年\n    度裁全字第224號裁定准原告供擔保後假扣押被告義和公司\n    之財產。原告乃提供擔保，聲請對被告義和公司對被告營建\n    署就上開系爭工程之工程款債權為假扣押，並由鈞院以100\n    年度司執全字第176號受理在案。詎料被告營建署具狀聲明\n    異議，略以：現在工程尚在施工中，債權金額尚未確定，而\n    否認被告義和公司對之有工程款債權存在。惟查，被告義和\n    公司向被告營建署所承攬之系爭工程，決標金額高達8816萬\n    8000元，縱使尚在施工，仍有履約保證金、各期估驗保留款\n    與工程尾款尚未給付予被告義和公司，被告營建署聲明異議\n    ，顯無理由。\n  (三)另鈞院所核發之假扣押執行命令，其範圍包括原告對被告義\n    和公司之工程款125萬7087元及假扣押執行費1萬0057元，金\n    額合計126萬7144元，爰依強制執行法第120條之規定，提起\n    本件確認債權之訴，並聲明：確認被告義和公司對被告營建\n    署有126萬7144元之工程款債權存在。\n二、被告部分：被告義和公司及被告營建署對於原告之上開主張\n    均不爭執。\n三、得心證之理由：\n  (一)按第三人於接獲扣押命令後，因對扣押債權之存否有所爭執\n    ，進而聲明異議者，執行債權人即得依民事訴訟法第247條\n    之規定提起確認之訴，以排除其私法上所處之不安定狀態（\n    最高法院89年度台上字第1477號、90年度台上字第415號判\n    決參照），是原告提起本件確認之訴，於法有據，合先敘明\n    。\n  (二)本件原告主張之事實，業據提出原告與被告義和公司之工程\n    合約書、發票、被告義和公司開立之支票、退票理由單、本\n    院100年度司裁全字第224號裁定、假扣押執行聲請狀、本院\n    100年司執全三字第176號執行命令、通知函、被告營建署提\n    出之聲明異議狀為證，並有被告義和公司與被告營建署之系\n    爭工程契約書為憑，且均為被告所不爭執，堪信屬實。從而\n    原告請求確認被告義和公司對被告營建署有126萬7144元之\n    工程款債權存在，為有理由。\n四、本件事證已臻明確，兩造其餘攻擊防禦方法及所舉證據，經\n    審酌結果，與本件判決結論均無影響，爰不一一論述，附此\n    敘明。\n五、結論：本件原告之訴為有理由，依民事訴訟法第78條、第85\n    條第1項前段，判決如主文。"
  },
  "search": "臺灣臺地方法民事判決100年度訴字第757號原告和佶地磚有限公司法定代理人石賜宗訴訟代理人陳建勛律師被告義和營造工程股份有限公司法定代理人陳奇男訴訟代理人鄭順興被告內政部營建署法定代理人葉世文訴訟代理人蔡得謙律師複代理人侯志翔律師何立斌律師上列當事人間確認債權存在事件，本院於民國100年6月20日言詞辯論終結，判決如下：主文確認被告義和營造工程股份有限公司對被告內政部營建署有新台幣壹佰貳拾陸萬柒仟壹佰肆拾肆元之工程款債權存在。訴訟費用由被告負擔。事實及理由一、原告起訴主張：(一)被告義和營造工程股份有限公司(下稱義和公司)於民國99年8月23日將其向被告內政部營建署(下稱營建署)承攬之「國立彰化高級商業職業學校教學行政大樓興建工程暨植栽工程2項合併」工程(下稱系爭工程)中之地坪舖磨石子地磚工程，發包予原告施作，契約總價為新台幣(下同)132萬5630元，原告已施作完畢，依實作數量結算，被告義和公司應給付原告138萬2206元。惟被告義和公司除給付12萬5119元外，其餘125萬7087元之工程款尚未給付。(二)嗣經原告聲請假扣押被告義和公司之財產，經鈞院以100年度裁全字第224號裁定准原告供擔保後假扣押被告義和公司之財產。原告乃提供擔保，聲請對被告義和公司對被告營建署就上開系爭工程之工程款債權為假扣押，並由鈞院以100年度司執全字第176號受理在案。詎料被告營建署具狀聲明異議，略以：現在工程尚在施工中，債權金額尚未確定，而否認被告義和公司對之有工程款債權存在。惟查，被告義和公司向被告營建署所承攬之系爭工程，決標金額高達8816萬8000元，縱使尚在施工，仍有履約保證金、各期估驗保留款與工程尾款尚未給付予被告義和公司，被告營建署聲明異議，顯無理由。(三)另鈞院所核發之假扣押執行命令，其範圍包括原告對被告義和公司之工程款125萬7087元及假扣押執行費1萬0057元，金額合計126萬7144元，爰依強制執行法第120條之規定，提起本件確認債權之訴，並聲明：確認被告義和公司對被告營建署有126萬7144元之工程款債權存在。二、被告部分：被告義和公司及被告營建署對於原告之上開主張均不爭執。三、得心證之理由：(一)按第三人於接獲扣押命令後，因對扣押債權之存否有所爭執，進而聲明異議者，執行債權人即得依民事訴訟法第247條之規定提起確認之訴，以排除其私法上所處之不安定狀態（最高法院89年度台上字第1477號、90年度台上字第415號判決參照），是原告提起本件確認之訴，於法有據，合先敘明。(二)本件原告主張之事實，業據提出原告與被告義和公司之工程合約書、發票、被告義和公司開立之支票、退票理由單、本院100年度司裁全字第224號裁定、假扣押執行聲請狀、本院100年司執全三字第176號執行命令、通知函、被告營建署提出之聲明異議狀為證，並有被告義和公司與被告營建署之系爭工程契約書為憑，且均為被告所不爭執，堪信屬實。從而原告請求確認被告義和公司對被告營建署有126萬7144元之工程款債權存在，為有理由。四、本件事證已臻明確，兩造其餘攻擊防禦方法及所舉證據，經審酌結果，與本件判決結論均無影響，爰不一一論述，附此敘明。五、結論：本件原告之訴為有理由，依民事訴訟法第78條、第85條第1項前段，判決如主文。中華民國100年7月4日民事第三庭法官高英賓正本係照原本作成。如對本判決上訴，須於判決送達後20日內向本院提出上訴狀。如委任律師提起上訴者，應一併繳納上訴審裁判費。中華民國100年7月4日書記官廖碩薇",
  "characters": {
    "judges": [
      "高英賓"
    ],
    "prosecutors": [

    ],
    "lawyers": [
      "陳建勛",
      "蔡得謙",
      "侯志翔",
      "何立斌",
      "委任"
    ],
    "clerks": [

    ],
    "plaintiffs": [
      "和佶地磚有限公司"
    ],
    "defendants": [
      "義和營造工程股份有限公司",
      "內政部營建署"
    ],
    "prosecutor_office": [

    ],
    "creditors": [

    ],
    "debtors": [

    ],
    "judicial_associate_officer": [

    ]
  },
  "adjudged_at": "2011-07-04",
  "created_at": "2016-02-14 01:15:57",
  "updated_at": "2016-02-14 01:15:57"
}