{
  "identify": "TND-100-易-633-20110704-2",
  "court": {
    "name": "臺灣臺南地方法院",
    "code": "TND"
  },
  "division": {
    "name": "刑事",
    "code": "M"
  },
  "year": 100,
  "word": "易",
  "number": "633",
  "jcheck": "2",
  "reason": "恐嚇等",
  "content": "臺灣臺南地方法院刑事判決              100年度易字第633號\n公  訴  人  臺灣臺南地方法院檢察署檢察官\n被      告  郭晉魁\n選任辯護人  許雅芬律師\n上列被告因公然侮辱案件，經檢察官聲請簡易判決處刑（聲請案\n號：100年度偵字第920號），本院認不宜以簡易判決處刑，改依\n通常程序審理並判決如下：\n    主  文\n本件公訴不受理。\n    理  由\n一、聲請簡易判決處刑意旨略以：被告郭晉魁與告訴人林鄭金英\n    係對面鄰居，因住家噪音等事件長期不睦，於民國99年3 月\n    13日下午2時許，因告訴人林鄭金英及林鄭金英之女林雅玲\n    懷疑被告郭晉魁在臺南縣永康市（現已改制為臺南市永康區\n    ○○○路376巷6號告訴人林鄭金英住處前潑灑魚類廢棄物，\n    雙方復起爭執，被告郭晉魁竟基於公然侮辱之犯意，在不特\n    定多數人得以共見共聞之告訴人林鄭金英上開住處前馬路，\n    以「幹你娘」等客觀上足以貶抑人格及社會評價之言詞，公\n    然辱罵告訴人林鄭金英、林雅玲，致生損害其等名譽。\n二、按告訴乃論之罪，告訴人於第一審辯論終結前得撤回其告訴\n    ，又告訴經撤回者，應諭知不受理之判決，刑事訴訟法第23\n    8條第1項、第303條第3款分別定有明文。\n三、查本件告訴人告訴被告公然侮辱案件，檢察官聲請簡易判決\n    處刑意旨認被告係觸犯刑法第309條第1項之公然侮辱罪嫌，\n    經本院審酌起訴書及全案卷證之結果亦同此認定，依同法第\n    314條前段之規定，即須告訴乃論。茲據告訴人林鄭金英、\n    林雅玲具狀撤回告訴，此有撤回告訴狀乙只附卷足參（見本\n    院100年度易字第633號卷第17頁）。依照首開說明，本件爰\n    不經言詞辯論，逕為諭知不受理之判決。\n四、本件被告涉犯恐嚇罪部分，另行審結。\n據上論斷，應依刑事訴訟法第452條、第303條第3款、第307條，\n判決如主文。\n中    華    民    國    100    年    7    月    4    日\n                  刑事第八庭    法  官  蔡奇秀\n以上正本證明與原本無異。\n如不服本判決應於收受本判決後10日內向本院提出上訴書狀，並\n應敘述具體理由。其未敘述上訴理由者，應於上訴期間屆滿後20\n日內向本院補提理由書狀（均須按他造當事人之人數附繕本）「\n切勿逕送上級法院」。\n                                書記官  蕭伊舒\n中    華    民    國   100    年    7     月    4     日",
  "structure": {
    "main": "本件公訴不受理。",
    "reason": "一、聲請簡易判決處刑意旨略以：被告郭晉魁與告訴人林鄭金英\n    係對面鄰居，因住家噪音等事件長期不睦，於民國99年3 月\n    13日下午2時許，因告訴人林鄭金英及林鄭金英之女林雅玲\n    懷疑被告郭晉魁在臺南縣永康市（現已改制為臺南市永康區\n    ○○○路376巷6號告訴人林鄭金英住處前潑灑魚類廢棄物，\n    雙方復起爭執，被告郭晉魁竟基於公然侮辱之犯意，在不特\n    定多數人得以共見共聞之告訴人林鄭金英上開住處前馬路，\n    以「幹你娘」等客觀上足以貶抑人格及社會評價之言詞，公\n    然辱罵告訴人林鄭金英、林雅玲，致生損害其等名譽。\n二、按告訴乃論之罪，告訴人於第一審辯論終結前得撤回其告訴\n    ，又告訴經撤回者，應諭知不受理之判決，刑事訴訟法第23\n    8條第1項、第303條第3款分別定有明文。\n三、查本件告訴人告訴被告公然侮辱案件，檢察官聲請簡易判決\n    處刑意旨認被告係觸犯刑法第309條第1項之公然侮辱罪嫌，\n    經本院審酌起訴書及全案卷證之結果亦同此認定，依同法第\n    314條前段之規定，即須告訴乃論。茲據告訴人林鄭金英、\n    林雅玲具狀撤回告訴，此有撤回告訴狀乙只附卷足參（見本\n    院100年度易字第633號卷第17頁）。依照首開說明，本件爰\n    不經言詞辯論，逕為諭知不受理之判決。\n四、本件被告涉犯恐嚇罪部分，另行審結。\n據上論斷，應依刑事訴訟法第452條、第303條第3款、第307條，\n判決如主文。"
  },
  "search": "臺灣臺南地方法院刑事判決100年度易字第633號公訴人臺灣臺南地方法院檢察署檢察官被告郭晉魁選任辯護人許雅芬律師上列被告因公然侮辱案件，經檢察官聲請簡易判決處刑（聲請案號：100年度偵字第920號），本院認不宜以簡易判決處刑，改依通常程序審理並判決如下：主文本件公訴不受理。理由一、聲請簡易判決處刑意旨略以：被告郭晉魁與告訴人林鄭金英係對面鄰居，因住家噪音等事件長期不睦，於民國99年3月13日下午2時許，因告訴人林鄭金英及林鄭金英之女林雅玲懷疑被告郭晉魁在臺南縣永康市（現已改制為臺南市永康區○○○路376巷6號告訴人林鄭金英住處前潑灑魚類廢棄物，雙方復起爭執，被告郭晉魁竟基於公然侮辱之犯意，在不特定多數人得以共見共聞之告訴人林鄭金英上開住處前馬路，以「幹你娘」等客觀上足以貶抑人格及社會評價之言詞，公然辱罵告訴人林鄭金英、林雅玲，致生損害其等名譽。二、按告訴乃論之罪，告訴人於第一審辯論終結前得撤回其告訴，又告訴經撤回者，應諭知不受理之判決，刑事訴訟法第238條第1項、第303條第3款分別定有明文。三、查本件告訴人告訴被告公然侮辱案件，檢察官聲請簡易判決處刑意旨認被告係觸犯刑法第309條第1項之公然侮辱罪嫌，經本院審酌起訴書及全案卷證之結果亦同此認定，依同法第314條前段之規定，即須告訴乃論。茲據告訴人林鄭金英、林雅玲具狀撤回告訴，此有撤回告訴狀乙只附卷足參（見本院100年度易字第633號卷第17頁）。依照首開說明，本件爰不經言詞辯論，逕為諭知不受理之判決。四、本件被告涉犯恐嚇罪部分，另行審結。據上論斷，應依刑事訴訟法第452條、第303條第3款、第307條，判決如主文。中華民國100年7月4日刑事第八庭法官蔡奇秀以上正本證明與原本無異。如不服本判決應於收受本判決後10日內向本院提出上訴書狀，並應敘述具體理由。其未敘述上訴理由者，應於上訴期間屆滿後20日內向本院補提理由書狀（均須按他造當事人之人數附繕本）「切勿逕送上級法院」。書記官蕭伊舒中華民國100年7月4日",
  "characters": {
    "judges": [
      "蔡奇秀"
    ],
    "prosecutors": [

    ],
    "lawyers": [
      "許雅芬"
    ],
    "clerks": [
      "蕭伊舒"
    ],
    "plaintiffs": [

    ],
    "defendants": [
      "郭晉魁"
    ],
    "prosecutor_office": [
      "臺灣臺南地方法院檢察署檢察官"
    ],
    "creditors": [

    ],
    "debtors": [

    ],
    "judicial_associate_officer": [

    ]
  },
  "adjudged_at": "2011-07-04",
  "created_at": "2016-02-14 01:22:16",
  "updated_at": "2016-02-14 01:22:16"
}