{
  "identify": "KSD-93-簡-2559-20040617-1",
  "court": {
    "name": "臺灣高雄地方法院",
    "code": "KSD"
  },
  "division": {
    "name": "刑事",
    "code": "M"
  },
  "year": 93,
  "word": "簡",
  "number": "2559",
  "jcheck": "1",
  "reason": "偽造文書",
  "content": "臺灣高雄地方法院刑事簡易判決                    九十三年度簡字第二五五九號\n    聲  請  人  臺灣高雄地方法院檢察署檢察官\n    被      告  甲○○\n右列被告因偽造文書案件，經檢察官聲請以簡易判決處刑（民國九十二年度偵字第一\n四００五號），本院判決如左：\n    主      文\n甲○○明知為不實之事項，而使公務員登載於職務上所掌公文書，足以生損害於公眾\n及他人，處拘役伍拾日，如易科罰金，以參佰元折算壹日。\n    事實及理由\n一、本件犯罪事實及證據均引用檢察官聲請簡易判決處刑書之記載（如附件）。\n二、依刑事訴訟法第四百四十九條第一項，刑法第二百十四條、第四十一條第一項前\n    段，罰金罰鍰提高標準條例第一條前段、第二條，逕以簡易判決處如主文所示之\n    刑。\n如不服本判決，得自收受送達之日起十日內，向本院提起上訴。\n中      華      民      國    九十三    年      六      月    十七      日\n                                臺灣高雄地方法院刑事第三庭\n                    法  官  高思大\n右為正本，係照原本作成，證明與原本無異。\n                                    書記官  蔡語珊\n中      華      民      國    九十三    年      六      月     十八     日\n附錄本判決論罪之法條：\n中華民國刑法第二百十四條：\n明知為不實之事項，而使公務員登載於職務上所掌之公文書，足以生損害於公眾或他\n人者，處三年以下有期徒刑、拘役或五百元以下罰金。\n",
  "structure": {
    "main": "甲○○明知為不實之事項，而使公務員登載於職務上所掌公文書，足以生損害於公眾\n及他人，處拘役伍拾日，如易科罰金，以參佰元折算壹日。",
    "fact": "一、本件犯罪事實及證據均引用檢察官聲請簡易判決處刑書之記載（如附件）。\n二、依刑事訴訟法第四百四十九條第一項，刑法第二百十四條、第四十一條第一項前\n    段，罰金罰鍰提高標準條例第一條前段、第二條，逕以簡易判決處如主文所示之\n    刑。\n如不服本判決，得自收受送達之日起十日內，向本院提起上訴。",
    "reason": "一、本件犯罪事實及證據均引用檢察官聲請簡易判決處刑書之記載（如附件）。\n二、依刑事訴訟法第四百四十九條第一項，刑法第二百十四條、第四十一條第一項前\n    段，罰金罰鍰提高標準條例第一條前段、第二條，逕以簡易判決處如主文所示之\n    刑。\n如不服本判決，得自收受送達之日起十日內，向本院提起上訴。"
  },
  "search": "臺灣高雄地方法院刑事簡易判決九十三年度簡字第二五五九號聲請人臺灣高雄地方法院檢察署檢察官被告甲○○右列被告因偽造文書案件，經檢察官聲請以簡易判決處刑（民國九十二年度偵字第一四００五號），本院判決如左：主文甲○○明知為不實之事項，而使公務員登載於職務上所掌公文書，足以生損害於公眾及他人，處拘役伍拾日，如易科罰金，以參佰元折算壹日。事實及理由一、本件犯罪事實及證據均引用檢察官聲請簡易判決處刑書之記載（如附件）。二、依刑事訴訟法第四百四十九條第一項，刑法第二百十四條、第四十一條第一項前段，罰金罰鍰提高標準條例第一條前段、第二條，逕以簡易判決處如主文所示之刑。如不服本判決，得自收受送達之日起十日內，向本院提起上訴。中華民國九十三年六月十七日臺灣高雄地方法院刑事第三庭法官高思大右為正本，係照原本作成，證明與原本無異。書記官蔡語珊中華民國九十三年六月十八日附錄本判決論罪之法條：中華民國刑法第二百十四條：明知為不實之事項，而使公務員登載於職務上所掌之公文書，足以生損害於公眾或他人者，處三年以下有期徒刑、拘役或五百元以下罰金。",
  "characters": {
    "judges": [
      "高思大"
    ],
    "prosecutors": [

    ],
    "lawyers": [

    ],
    "clerks": [
      "蔡語珊"
    ],
    "plaintiffs": [

    ],
    "defendants": [
      "甲○○",
      "右列被告因偽造文書案件，經檢察官聲請以簡易判決處刑（民國九十二年度偵字第一",
      "四００五號），本院判決如左："
    ],
    "prosecutor_office": [
      "臺灣高雄地方法院檢察署檢察官"
    ],
    "creditors": [

    ],
    "debtors": [

    ],
    "judicial_associate_officer": [

    ]
  },
  "adjudged_at": "2004-06-17",
  "created_at": "2016-02-06 08:31:58",
  "updated_at": "2016-02-06 08:31:58"
}