{
  "identify": "TPD-93-易-1365-20041203-1",
  "court": {
    "name": "臺灣臺北地方法院",
    "code": "TPD"
  },
  "division": {
    "name": "刑事",
    "code": "M"
  },
  "year": 93,
  "word": "易",
  "number": "1365",
  "jcheck": "1",
  "reason": "傷害",
  "content": "臺灣臺北地方法院刑事判決                        九十三年度易字第一三六五號\n    公  訴  人  臺灣臺北地方法院檢察署檢察官\n    被      告  甲○○\n                乙○○\n                丙○○\n                丁○○○\n    右四人共同\n    選任辯護人  黃安然  律師\n    被      告  戊○○\n                己○○\n                庚○○\n                辛○○\n                壬○○\n    右五人共同\n    選任辯護人  林詮勝  律師\n右列被告等因傷害案件，經檢察官提起公訴（九十三年度偵字第一五二二一號、第一\n六八二八號），本院判決如左：\n    主  文\n本件公訴不受理。\n    理  由\n一、本件公訴意旨略以：被告乙○○與被告己○○於九十三年五月廿九日十四時許在\n    臺北縣新店市○○路四二巷四七弄七號前，雙方因停車細故發生爭執，被告乙○\n    ○之親屬即被告丙○○、甲○○、丁○○○，以及被告己○○之親屬即被告庚○\n    ○、壬○○、戊○○、辛○○等人聞訊均趕至現場加入互罵口角，繼而雙方人馬\n    以徒手互相毆打，致被告乙○○臉部、頸部、上背部、雙肘等處挫、擦傷；被告\n    甲○○臉部、頸部、上腹、後背、右拇指挫傷；被告丙○○頭部外傷、頸部、胸\n    部、後背等處挫傷；被告丁○○○上唇、胸部挫傷；被告己○○面部左側頸部、\n    胸前等處瘀傷；被告庚○○左手前臂、頸部挫傷，辛○○左小腿、左足背擦、頸\n    部挫傷；被告壬○○右臉頰、右膝、左肘擦傷；被告戊○○面部、胸前、右手等\n    處挫傷。案經被告乙○○、甲○○、丙○○、丁○○○、己○○、庚○○、辛○\n    ○、壬○○、戊○○等訴由臺北縣政府警察局新店分局移送偵辦。因認被告等均\n    涉有刑法第二百七十七條第一項之傷害罪嫌。\n二、按告訴乃論之罪，告訴人於第一審辯論終結前得撤回其告訴，又告訴經撤回者，\n    應諭知不受理之判決，並得不經言詞辯論為之，刑事訴訟法第二百三十八條第一\n    項、第三百零三條第三款、第三百零七條分別定有明文。\n三、經查：本件告訴人即被告乙○○、甲○○、丙○○、丁○○○等人，以及告訴人\n    即被告己○○、庚○○、辛○○、壬○○、戊○○等人相互告訴在上開時、地因\n    停車糾紛互毆，致其等分別受有上開傷害，公訴人認均係觸犯刑法第二百七十七\n    條第一項之過失傷害罪嫌，依同法第二百八十七條前段之規定，須告訴乃論。茲\n    因被告等業已達成民事和解，於本院審理時當庭撤回告訴在案，此有本院九十三\n    年十二月二日審判筆錄一份在卷可稽，揆諸前揭規定，本件爰不經言詞辯論，逕\n    均為不受理判決之諭知。\n據上論斷，應依刑事訴訟法第三百零三條第三款、第三百零七條，判決如主文。\n中      華      民      國    九十三    年     十二     月      三      日\n                              臺灣臺北地方法院刑事第十五庭\n                                  審判長法  官  周祖民\n                                        法  官  邱蓮華\n                                        法  官  吳麗英\n右正本證明與原本無異\n如不服本判決應於送達後十日內向本院提出上訴狀\n                                        書記官  田華仁\n中      華      民      國    九十三    年     十二     月      九      日\n",
  "structure": {
    "main": "本件公訴不受理。",
    "reason": "一、本件公訴意旨略以：被告乙○○與被告己○○於九十三年五月廿九日十四時許在\n    臺北縣新店市○○路四二巷四七弄七號前，雙方因停車細故發生爭執，被告乙○\n    ○之親屬即被告丙○○、甲○○、丁○○○，以及被告己○○之親屬即被告庚○\n    ○、壬○○、戊○○、辛○○等人聞訊均趕至現場加入互罵口角，繼而雙方人馬\n    以徒手互相毆打，致被告乙○○臉部、頸部、上背部、雙肘等處挫、擦傷；被告\n    甲○○臉部、頸部、上腹、後背、右拇指挫傷；被告丙○○頭部外傷、頸部、胸\n    部、後背等處挫傷；被告丁○○○上唇、胸部挫傷；被告己○○面部左側頸部、\n    胸前等處瘀傷；被告庚○○左手前臂、頸部挫傷，辛○○左小腿、左足背擦、頸\n    部挫傷；被告壬○○右臉頰、右膝、左肘擦傷；被告戊○○面部、胸前、右手等\n    處挫傷。案經被告乙○○、甲○○、丙○○、丁○○○、己○○、庚○○、辛○\n    ○、壬○○、戊○○等訴由臺北縣政府警察局新店分局移送偵辦。因認被告等均\n    涉有刑法第二百七十七條第一項之傷害罪嫌。\n二、按告訴乃論之罪，告訴人於第一審辯論終結前得撤回其告訴，又告訴經撤回者，\n    應諭知不受理之判決，並得不經言詞辯論為之，刑事訴訟法第二百三十八條第一\n    項、第三百零三條第三款、第三百零七條分別定有明文。\n三、經查：本件告訴人即被告乙○○、甲○○、丙○○、丁○○○等人，以及告訴人\n    即被告己○○、庚○○、辛○○、壬○○、戊○○等人相互告訴在上開時、地因\n    停車糾紛互毆，致其等分別受有上開傷害，公訴人認均係觸犯刑法第二百七十七\n    條第一項之過失傷害罪嫌，依同法第二百八十七條前段之規定，須告訴乃論。茲\n    因被告等業已達成民事和解，於本院審理時當庭撤回告訴在案，此有本院九十三\n    年十二月二日審判筆錄一份在卷可稽，揆諸前揭規定，本件爰不經言詞辯論，逕\n    均為不受理判決之諭知。\n據上論斷，應依刑事訴訟法第三百零三條第三款、第三百零七條，判決如主文。"
  },
  "search": "臺灣臺北地方法院刑事判決九十三年度易字第一三六五號公訴人臺灣臺北地方法院檢察署檢察官被告甲○○乙○○丙○○丁○○○右四人共同選任辯護人黃安然律師被告戊○○己○○庚○○辛○○壬○○右五人共同選任辯護人林詮勝律師右列被告等因傷害案件，經檢察官提起公訴（九十三年度偵字第一五二二一號、第一六八二八號），本院判決如左：主文本件公訴不受理。理由一、本件公訴意旨略以：被告乙○○與被告己○○於九十三年五月廿九日十四時許在臺北縣新店市○○路四二巷四七弄七號前，雙方因停車細故發生爭執，被告乙○○之親屬即被告丙○○、甲○○、丁○○○，以及被告己○○之親屬即被告庚○○、壬○○、戊○○、辛○○等人聞訊均趕至現場加入互罵口角，繼而雙方人馬以徒手互相毆打，致被告乙○○臉部、頸部、上背部、雙肘等處挫、擦傷；被告甲○○臉部、頸部、上腹、後背、右拇指挫傷；被告丙○○頭部外傷、頸部、胸部、後背等處挫傷；被告丁○○○上唇、胸部挫傷；被告己○○面部左側頸部、胸前等處瘀傷；被告庚○○左手前臂、頸部挫傷，辛○○左小腿、左足背擦、頸部挫傷；被告壬○○右臉頰、右膝、左肘擦傷；被告戊○○面部、胸前、右手等處挫傷。案經被告乙○○、甲○○、丙○○、丁○○○、己○○、庚○○、辛○○、壬○○、戊○○等訴由臺北縣政府警察局新店分局移送偵辦。因認被告等均涉有刑法第二百七十七條第一項之傷害罪嫌。二、按告訴乃論之罪，告訴人於第一審辯論終結前得撤回其告訴，又告訴經撤回者，應諭知不受理之判決，並得不經言詞辯論為之，刑事訴訟法第二百三十八條第一項、第三百零三條第三款、第三百零七條分別定有明文。三、經查：本件告訴人即被告乙○○、甲○○、丙○○、丁○○○等人，以及告訴人即被告己○○、庚○○、辛○○、壬○○、戊○○等人相互告訴在上開時、地因停車糾紛互毆，致其等分別受有上開傷害，公訴人認均係觸犯刑法第二百七十七條第一項之過失傷害罪嫌，依同法第二百八十七條前段之規定，須告訴乃論。茲因被告等業已達成民事和解，於本院審理時當庭撤回告訴在案，此有本院九十三年十二月二日審判筆錄一份在卷可稽，揆諸前揭規定，本件爰不經言詞辯論，逕均為不受理判決之諭知。據上論斷，應依刑事訴訟法第三百零三條第三款、第三百零七條，判決如主文。中華民國九十三年十二月三日臺灣臺北地方法院刑事第十五庭審判長法官周祖民法官邱蓮華法官吳麗英右正本證明與原本無異如不服本判決應於送達後十日內向本院提出上訴狀書記官田華仁中華民國九十三年十二月九日",
  "characters": {
    "judges": [
      "周祖民",
      "邱蓮華",
      "吳麗英"
    ],
    "prosecutors": [

    ],
    "lawyers": [

    ],
    "clerks": [
      "田華仁"
    ],
    "plaintiffs": [

    ],
    "defendants": [
      "甲○○",
      "戊○○"
    ],
    "prosecutor_office": [
      "臺灣臺北地方法院檢察署檢察官"
    ],
    "creditors": [

    ],
    "debtors": [

    ],
    "judicial_associate_officer": [

    ]
  },
  "adjudged_at": "2004-12-03",
  "created_at": "2016-02-06 06:32:49",
  "updated_at": "2016-02-06 06:32:49"
}