{
  "identify": "SCD-100-竹東簡-119-20110829-1",
  "court": {
    "name": "臺灣新竹地方法院",
    "code": "SCD"
  },
  "division": {
    "name": "刑事",
    "code": "M"
  },
  "year": 100,
  "word": "竹東簡",
  "number": "119",
  "jcheck": "1",
  "reason": "違反電子遊戲場業管理條例",
  "content": "臺灣新竹地方法院刑事簡易判決      100年度竹東簡字第119號\n聲  請  人  臺灣新竹地方法院檢察署檢察官\n被      告  黃煥彩\n上列被告因違反電子遊戲場業管理條例案件，前經臺灣新竹地方\n法院檢察署檢察官為緩起訴處分（99年度偵字第5843號），被告\n於緩起訴期間內，故意更犯有期徒刑以上刑之罪，經檢察官依職\n權撤銷原處分（100年度撤緩字第35號）後，聲請簡易判決處刑\n（100年度撤緩偵字第67號），本院判決如下︰\n    主  文\n黃煥彩犯電子遊戲場業管理條例第二十二條之非法營業罪，處拘\n役伍拾日，如易科罰金，以新臺幣壹仟元折算壹日。扣案之電子\n遊戲機具「水果盤滿天星」臺（含IC板塊）、「麻將台滿貫\n大亨」貳臺（含IC板貳塊）及新臺幣伍拾元，均沒收之。\n    事實及證據\n一、本件犯罪事實及證據，均引用檢察官聲請簡易判決處刑書之\n    記載（如附件）。\n二、論罪及科刑：\n（一）論罪：\n  １、按電子遊戲場業管理條例第10條第1項前段規定：「經營\n      電子遊戲場業，應依公司法或商業登記法辦理公司或商業\n      登記」，第15條規定：「未依本條例規定辦理營利事業登\n      記者，不得經營電子遊戲場業」，第22條規定：「違反第\n      15條規定者，處行為人1年以下有期徒刑、拘役或科或併\n      科新臺幣50萬元以上250萬元以下罰金。」。所謂電子遊\n      戲場「業」，指「業務」而言，刑法上所謂業務，係以事\n      實上執行業務者為標準，指以反覆同種類之行為為目的之\n      社會的活動而言；執行此項業務，縱令欠缺形式上之條件\n      ，仍無礙於業務之性質，因此不論該事業是否「專營」電\n      子遊戲場業，亦不問經營是否需達「一定之規模」，即使\n      於原本所營事業外，兼營電子遊戲場業，或所經營之電子\n      遊戲場不具相當之規模，亦無礙於電子遊戲場業管理條例\n      相關規定之適用（此有最高法院90年台非字第276號判例\n      意旨可資參照）。易言之，未依電子遊戲場業管理條例規\n      定辦理營利事業登記，而擺放電玩經營電子遊戲場業者，\n      即有電子遊戲場業管理條例第22條處罰規定之適用，且經\n      營電子遊戲場業，僅需有反覆同種類之行為為目的之社會\n      的活動即為已足，至於其經營是否為「專營」、「達一定\n      之規模」，皆非所論。\n  ２、核被告黃煥彩所為，係犯違反電子遊戲場業管理條例第15\n      條之規定，應依同條例第22條規定處罰。\n  ３、包括一罪：被告所犯違反電子遊戲場業管理條例第22條之\n      罪，其性質本質上具有反覆性及延續性，其複次為從事電\n      子遊戲場業之經營，乃其業務本質所當然，應為包括一罪\n      。\n（二）科刑：\n  １、主刑：審酌被告無視法令之禁止，未依規定申請主管機關\n      許可，並辦理營利事業登記，即擅自經營電子遊戲場業，\n      ，兼衡擺放遊戲機臺之數量、侵害之法益，及被告之智識\n      程度、素行、所生危害及犯罪後態度等一切情狀，量處如\n      主文所示之刑，並諭知易科罰金之折算標準，以資懲儆。\n  ２、從刑（沒收）：扣案之電子遊戲機「水果盤滿天星」3臺\n      （含IC板3塊）、「麻將台滿貫大亨」2臺（含IC板2塊）\n      ，係被告所有供經營本件犯罪所用之物，另機具內硬幣50\n      元，係本件犯罪所得之物，已據被告供明在卷，爰均依刑\n      法第38條第1項第2、3款之規定，宣告沒收之。\n三、依刑事訴訟法第449條第1項前段、第450條第1項、第454條\n    第2項，電子遊戲場業管理條例第22條、刑法第11條前段、\n    第38條第1項第1款、第2款、第41條第1項前段，刑法施行法\n    第1條之1第1項、第2項前段，逕以簡易判決處刑如主文。\n四、如不服本件判決，得自收受送達之日起10日內，向本院提起\n    上訴。\n中    華    民    國   100    年    8     月    29    日\n                  竹東簡易庭法  官  謝永昌\n以上正本證明與原本無異。\n中    華    民    國   100    年    8     月    29    日\n                            書記官  張淑芬\n附錄本案論罪科刑實體法條全文：\n電子遊戲場業管理條例第22條：\n違反第15條規定者，處行為人1 年以下有期徒刑、拘役或科或併\n科新臺幣50萬元以上250 萬元以下罰金。\n【電子遊戲場業管理條例第15條：未依本條例規定辦理營利事業\n登記者，不得經營電子遊戲場業。】\n附件：\n臺灣新竹地方法院檢察署檢察官聲請簡易判決處刑書\n                                   100年度撤緩偵字第67號\n    被      告  黃煥彩  男  51歲（民國○○年○月○○日生）\n                        住新竹縣北埔鄉○○村○○街8號\n                        居新竹縣北埔鄉埔尾村26-1號\n                        國民身分證統一編號：Ｚ000000000號\n上列被告因電子遊戲場業管理條例案件，業經偵查終結，認宜以\n簡易判決處刑，茲將犯罪事實及證據並所犯法條分敘如下：\n        犯罪事實\n一、黃煥彩明知未依電子遊戲場業管理條例之規定辦理營利事業\n    登記者，不得經營電子遊戲場業，竟意圖營利，自不詳時間\n    起，在新竹縣北埔鄉埔尾村26之1號其所經營之阿彩釣魚池\n    內，擺設「水果盤滿天星」電子遊戲機3台、「麻將台滿貫\n    大亨」2台，供不特定人投幣把玩，而經營電子遊戲場業。\n    嗣於民國99年7月20日下午4時30分許，為警於上址查獲，並\n    扣得上開電子遊戲機5台（含IC板5片）及機臺內之現金新臺\n    幣（下同）50元。\n二、案經新竹縣政府警察局竹東分局報告偵辦。\n          證據並所犯法條\n一、訊據被告黃煥彩對前揭犯罪事實自白不諱，並有新竹縣政府\n    警察局竹東分局現場臨檢紀錄表及蒐證照片18張附卷足憑，\n    復有上開電子遊戲機5台（含IC板5片）及機臺內之現金50元\n    扣案可證，是被告犯嫌足堪認定。\n二、核被告所為，係違反電子遊戲場業管理條例第15條規定，而\n    犯同條例第22條之未依規定領有電子遊戲場業營業級別證經\n    營電子遊戲場業罪嫌。扣案如事實欄所示內含IC板5片之電\n    子遊戲機具，係被告所有以供經營電子遊戲場業所用之物，\n    另機具內硬幣50元，係犯罪所得之物，業據其供明在卷，請\n    依刑法第38條第1項第2款、第3款之規定併予宣告沒收。\n三、依刑事訴訟法第451條第1項聲請逕以簡易判決處刑。\n    此  致\n臺灣新竹地方法院\n中    華    民    國   100    年    5     月    25    日\n                       檢 察 官  黃士元\n                       檢 察 官  呂雅純\n本件證明與原本無異\n中    華    民    國   100    年    6     月    2     日\n                       書 記 官  王榆婷\n參考法條：\n電子遊戲場業管理條例第15條\n未依本條例規定辦理營利事業登記者，不得經營電子遊戲場業。\n電子遊戲場業管理條例第22條\n違反第15條規定者，處行為人1年以下有期徒刑、拘役或科或併\n科新台幣 50 萬元以上 250 萬元以下罰金。\n本件係依刑事訴訟法簡易程序辦理，法院簡易庭得不傳喚被告、\n輔佐人、告訴人、告發人等出庭即以簡易判決處刑；被告、被害\n人、告訴人等對告訴乃論案件如已達成民事和解而要撤回告訴或\n對非告訴乃論案件認有受傳喚到庭陳述意見之必要時，請即另以\n書狀向簡易法庭陳述或請求傳訊。",
  "structure": {
    "main": "黃煥彩犯電子遊戲場業管理條例第二十二條之非法營業罪，處拘\n役伍拾日，如易科罰金，以新臺幣壹仟元折算壹日。扣案之電子\n遊戲機具「水果盤滿天星」臺（含IC板塊）、「麻將台滿貫\n大亨」貳臺（含IC板貳塊）及新臺幣伍拾元，均沒收之。\n    事實及證據\n一、本件犯罪事實及證據，均引用檢察官聲請簡易判決處刑書之\n    記載（如附件）。\n二、論罪及科刑：\n（一）論罪：\n  １、按電子遊戲場業管理條例第10條第1項前段規定：「經營\n      電子遊戲場業，應依公司法或商業登記法辦理公司或商業\n      登記」，第15條規定：「未依本條例規定辦理營利事業登\n      記者，不得經營電子遊戲場業」，第22條規定：「違反第\n      15條規定者，處行為人1年以下有期徒刑、拘役或科或併\n      科新臺幣50萬元以上250萬元以下罰金。」。所謂電子遊\n      戲場「業」，指「業務」而言，刑法上所謂業務，係以事\n      實上執行業務者為標準，指以反覆同種類之行為為目的之\n      社會的活動而言；執行此項業務，縱令欠缺形式上之條件\n      ，仍無礙於業務之性質，因此不論該事業是否「專營」電\n      子遊戲場業，亦不問經營是否需達「一定之規模」，即使\n      於原本所營事業外，兼營電子遊戲場業，或所經營之電子\n      遊戲場不具相當之規模，亦無礙於電子遊戲場業管理條例\n      相關規定之適用（此有最高法院90年台非字第276號判例\n      意旨可資參照）。易言之，未依電子遊戲場業管理條例規\n      定辦理營利事業登記，而擺放電玩經營電子遊戲場業者，\n      即有電子遊戲場業管理條例第22條處罰規定之適用，且經\n      營電子遊戲場業，僅需有反覆同種類之行為為目的之社會\n      的活動即為已足，至於其經營是否為「專營」、「達一定\n      之規模」，皆非所論。\n  ２、核被告黃煥彩所為，係犯違反電子遊戲場業管理條例第15\n      條之規定，應依同條例第22條規定處罰。\n  ３、包括一罪：被告所犯違反電子遊戲場業管理條例第22條之\n      罪，其性質本質上具有反覆性及延續性，其複次為從事電\n      子遊戲場業之經營，乃其業務本質所當然，應為包括一罪\n      。\n（二）科刑：\n  １、主刑：審酌被告無視法令之禁止，未依規定申請主管機關\n      許可，並辦理營利事業登記，即擅自經營電子遊戲場業，\n      ，兼衡擺放遊戲機臺之數量、侵害之法益，及被告之智識\n      程度、素行、所生危害及犯罪後態度等一切情狀，量處如\n      主文所示之刑，並諭知易科罰金之折算標準，以資懲儆。\n  ２、從刑（沒收）：扣案之電子遊戲機「水果盤滿天星」3臺\n      （含IC板3塊）、「麻將台滿貫大亨」2臺（含IC板2塊）\n      ，係被告所有供經營本件犯罪所用之物，另機具內硬幣50\n      元，係本件犯罪所得之物，已據被告供明在卷，爰均依刑\n      法第38條第1項第2、3款之規定，宣告沒收之。\n三、依刑事訴訟法第449條第1項前段、第450條第1項、第454條\n    第2項，電子遊戲場業管理條例第22條、刑法第11條前段、\n    第38條第1項第1款、第2款、第41條第1項前段，刑法施行法\n    第1條之1第1項、第2項前段，逕以簡易判決處刑如主文。\n四、如不服本件判決，得自收受送達之日起10日內，向本院提起\n    上訴。\n中    華    民    國   100    年    8     月    29    日\n                  竹東簡易庭法  官  謝永昌\n以上正本證明與原本無異。\n中    華    民    國   100    年    8     月    29    日\n                            書記官  張淑芬\n附錄本案論罪科刑實體法條全文：\n電子遊戲場業管理條例第22條：\n違反第15條規定者，處行為人1 年以下有期徒刑、拘役或科或併\n科新臺幣50萬元以上250 萬元以下罰金。\n【電子遊戲場業管理條例第15條：未依本條例規定辦理營利事業\n登記者，不得經營電子遊戲場業。】\n附件：\n臺灣新竹地方法院檢察署檢察官聲請簡易判決處刑書\n                                   100年度撤緩偵字第67號\n    被      告  黃煥彩  男  51歲（民國○○年○月○○日生）\n                        住新竹縣北埔鄉○○村○○街8號\n                        居新竹縣北埔鄉埔尾村26-1號\n                        國民身分證統一編號：Ｚ000000000號\n上列被告因電子遊戲場業管理條例案件，業經偵查終結，認宜以\n簡易判決處刑，茲將犯罪事實及證據並所犯法條分敘如下：",
    "fact": "一、黃煥彩明知未依電子遊戲場業管理條例之規定辦理營利事業\n    登記者，不得經營電子遊戲場業，竟意圖營利，自不詳時間\n    起，在新竹縣北埔鄉埔尾村26之1號其所經營之阿彩釣魚池\n    內，擺設「水果盤滿天星」電子遊戲機3台、「麻將台滿貫\n    大亨」2台，供不特定人投幣把玩，而經營電子遊戲場業。\n    嗣於民國99年7月20日下午4時30分許，為警於上址查獲，並\n    扣得上開電子遊戲機5台（含IC板5片）及機臺內之現金新臺\n    幣（下同）50元。\n二、案經新竹縣政府警察局竹東分局報告偵辦。\n          證據並所犯法條\n一、訊據被告黃煥彩對前揭犯罪事實自白不諱，並有新竹縣政府\n    警察局竹東分局現場臨檢紀錄表及蒐證照片18張附卷足憑，\n    復有上開電子遊戲機5台（含IC板5片）及機臺內之現金50元\n    扣案可證，是被告犯嫌足堪認定。\n二、核被告所為，係違反電子遊戲場業管理條例第15條規定，而\n    犯同條例第22條之未依規定領有電子遊戲場業營業級別證經\n    營電子遊戲場業罪嫌。扣案如事實欄所示內含IC板5片之電\n    子遊戲機具，係被告所有以供經營電子遊戲場業所用之物，\n    另機具內硬幣50元，係犯罪所得之物，業據其供明在卷，請\n    依刑法第38條第1項第2款、第3款之規定併予宣告沒收。\n三、依刑事訴訟法第451條第1項聲請逕以簡易判決處刑。\n    此  致\n臺灣新竹地方法院"
  },
  "search": "臺灣新竹地方法院刑事簡易判決100年度竹東簡字第119號聲請人臺灣新竹地方法院檢察署檢察官被告黃煥彩上列被告因違反電子遊戲場業管理條例案件，前經臺灣新竹地方法院檢察署檢察官為緩起訴處分（99年度偵字第5843號），被告於緩起訴期間內，故意更犯有期徒刑以上刑之罪，經檢察官依職權撤銷原處分（100年度撤緩字第35號）後，聲請簡易判決處刑（100年度撤緩偵字第67號），本院判決如下︰主文黃煥彩犯電子遊戲場業管理條例第二十二條之非法營業罪，處拘役伍拾日，如易科罰金，以新臺幣壹仟元折算壹日。扣案之電子遊戲機具「水果盤滿天星」臺（含IC板塊）、「麻將台滿貫大亨」貳臺（含IC板貳塊）及新臺幣伍拾元，均沒收之。事實及證據一、本件犯罪事實及證據，均引用檢察官聲請簡易判決處刑書之記載（如附件）。二、論罪及科刑：（一）論罪：１、按電子遊戲場業管理條例第10條第1項前段規定：「經營電子遊戲場業，應依公司法或商業登記法辦理公司或商業登記」，第15條規定：「未依本條例規定辦理營利事業登記者，不得經營電子遊戲場業」，第22條規定：「違反第15條規定者，處行為人1年以下有期徒刑、拘役或科或併科新臺幣50萬元以上250萬元以下罰金。」。所謂電子遊戲場「業」，指「業務」而言，刑法上所謂業務，係以事實上執行業務者為標準，指以反覆同種類之行為為目的之社會的活動而言；執行此項業務，縱令欠缺形式上之條件，仍無礙於業務之性質，因此不論該事業是否「專營」電子遊戲場業，亦不問經營是否需達「一定之規模」，即使於原本所營事業外，兼營電子遊戲場業，或所經營之電子遊戲場不具相當之規模，亦無礙於電子遊戲場業管理條例相關規定之適用（此有最高法院90年台非字第276號判例意旨可資參照）。易言之，未依電子遊戲場業管理條例規定辦理營利事業登記，而擺放電玩經營電子遊戲場業者，即有電子遊戲場業管理條例第22條處罰規定之適用，且經營電子遊戲場業，僅需有反覆同種類之行為為目的之社會的活動即為已足，至於其經營是否為「專營」、「達一定之規模」，皆非所論。２、核被告黃煥彩所為，係犯違反電子遊戲場業管理條例第15條之規定，應依同條例第22條規定處罰。３、包括一罪：被告所犯違反電子遊戲場業管理條例第22條之罪，其性質本質上具有反覆性及延續性，其複次為從事電子遊戲場業之經營，乃其業務本質所當然，應為包括一罪。（二）科刑：１、主刑：審酌被告無視法令之禁止，未依規定申請主管機關許可，並辦理營利事業登記，即擅自經營電子遊戲場業，，兼衡擺放遊戲機臺之數量、侵害之法益，及被告之智識程度、素行、所生危害及犯罪後態度等一切情狀，量處如主文所示之刑，並諭知易科罰金之折算標準，以資懲儆。２、從刑（沒收）：扣案之電子遊戲機「水果盤滿天星」3臺（含IC板3塊）、「麻將台滿貫大亨」2臺（含IC板2塊），係被告所有供經營本件犯罪所用之物，另機具內硬幣50元，係本件犯罪所得之物，已據被告供明在卷，爰均依刑法第38條第1項第2、3款之規定，宣告沒收之。三、依刑事訴訟法第449條第1項前段、第450條第1項、第454條第2項，電子遊戲場業管理條例第22條、刑法第11條前段、第38條第1項第1款、第2款、第41條第1項前段，刑法施行法第1條之1第1項、第2項前段，逕以簡易判決處刑如主文。四、如不服本件判決，得自收受送達之日起10日內，向本院提起上訴。中華民國100年8月29日竹東簡易庭法官謝永昌以上正本證明與原本無異。中華民國100年8月29日書記官張淑芬附錄本案論罪科刑實體法條全文：電子遊戲場業管理條例第22條：違反第15條規定者，處行為人1年以下有期徒刑、拘役或科或併科新臺幣50萬元以上250萬元以下罰金。【電子遊戲場業管理條例第15條：未依本條例規定辦理營利事業登記者，不得經營電子遊戲場業。】附件：臺灣新竹地方法院檢察署檢察官聲請簡易判決處刑書100年度撤緩偵字第67號被告黃煥彩男51歲（民國○○年○月○○日生）住新竹縣北埔鄉○○村○○街8號居新竹縣北埔鄉埔尾村26-1號國民身分證統一編號：Ｚ000000000號上列被告因電子遊戲場業管理條例案件，業經偵查終結，認宜以簡易判決處刑，茲將犯罪事實及證據並所犯法條分敘如下：犯罪事實一、黃煥彩明知未依電子遊戲場業管理條例之規定辦理營利事業登記者，不得經營電子遊戲場業，竟意圖營利，自不詳時間起，在新竹縣北埔鄉埔尾村26之1號其所經營之阿彩釣魚池內，擺設「水果盤滿天星」電子遊戲機3台、「麻將台滿貫大亨」2台，供不特定人投幣把玩，而經營電子遊戲場業。嗣於民國99年7月20日下午4時30分許，為警於上址查獲，並扣得上開電子遊戲機5台（含IC板5片）及機臺內之現金新臺幣（下同）50元。二、案經新竹縣政府警察局竹東分局報告偵辦。證據並所犯法條一、訊據被告黃煥彩對前揭犯罪事實自白不諱，並有新竹縣政府警察局竹東分局現場臨檢紀錄表及蒐證照片18張附卷足憑，復有上開電子遊戲機5台（含IC板5片）及機臺內之現金50元扣案可證，是被告犯嫌足堪認定。二、核被告所為，係違反電子遊戲場業管理條例第15條規定，而犯同條例第22條之未依規定領有電子遊戲場業營業級別證經營電子遊戲場業罪嫌。扣案如事實欄所示內含IC板5片之電子遊戲機具，係被告所有以供經營電子遊戲場業所用之物，另機具內硬幣50元，係犯罪所得之物，業據其供明在卷，請依刑法第38條第1項第2款、第3款之規定併予宣告沒收。三、依刑事訴訟法第451條第1項聲請逕以簡易判決處刑。此致臺灣新竹地方法院中華民國100年5月25日檢察官黃士元檢察官呂雅純本件證明與原本無異中華民國100年6月2日書記官王榆婷參考法條：電子遊戲場業管理條例第15條未依本條例規定辦理營利事業登記者，不得經營電子遊戲場業。電子遊戲場業管理條例第22條違反第15條規定者，處行為人1年以下有期徒刑、拘役或科或併科新台幣50萬元以上250萬元以下罰金。本件係依刑事訴訟法簡易程序辦理，法院簡易庭得不傳喚被告、輔佐人、告訴人、告發人等出庭即以簡易判決處刑；被告、被害人、告訴人等對告訴乃論案件如已達成民事和解而要撤回告訴或對非告訴乃論案件認有受傳喚到庭陳述意見之必要時，請即另以書狀向簡易法庭陳述或請求傳訊。",
  "characters": {
    "judges": [
      "謝永昌"
    ],
    "prosecutors": [

    ],
    "lawyers": [

    ],
    "clerks": [
      "張淑芬"
    ],
    "plaintiffs": [

    ],
    "defendants": [
      "黃煥彩",
      "黃煥彩  男  51歲（民國○○年○月○○日生）"
    ],
    "prosecutor_office": [
      "臺灣新竹地方法院檢察署檢察官"
    ],
    "creditors": [

    ],
    "debtors": [

    ],
    "judicial_associate_officer": [

    ]
  },
  "adjudged_at": "2011-08-29",
  "created_at": "2016-02-12 20:07:08",
  "updated_at": "2016-02-12 20:07:08"
}