{
  "identify": "TPH-100-聲-3600-20111118-1",
  "court": {
    "name": "臺灣高等法院",
    "code": "TPH"
  },
  "division": {
    "name": "刑事",
    "code": "M"
  },
  "year": 100,
  "word": "聲",
  "number": "3600",
  "jcheck": "1",
  "reason": "保護管束",
  "content": "臺灣高等法院刑事裁定                 100年度聲字第3600號\n聲  請  人    臺灣高等法院檢察署檢察官\n受  刑  人    劉瀚聲\n              （現於法務部矯正署臺北監獄臺北分監執行中）\n上列受刑人因違反毒品危害防制條例案件，聲請人聲請保護管束\n（100年度執聲付字第1308號），本院裁定如下：\n    主  文\n劉瀚聲假釋中付保護管束。\n    理  由\n一、聲請意旨略以：受刑人劉瀚聲因違反毒品危害防制條例案件\n    ，經本院以99年度上易字第741號刑事判決判處有期徒刑8月\n    確定，另因違反毒品危害防制條例案件，經臺灣板橋地方法\n    院以99年度簡字第1597號刑事簡易判決處刑書判處有期徒刑\n    5月確定，嗣由臺灣板橋地方法院以99年度聲字第3511號裁\n    定定其應執行有期徒刑11月確定；另因違反毒品危害防制條\n    例案件，經臺灣板橋地方法院以99年度易字第2567號刑事判\n    決判處有期徒刑7月，上訴後，經本院以99年度上易字第266\n    1 號判決駁回上訴而告確定，並於民國（下同）99年7月7日\n    入監執行。嗣經法務部於100年11月11日核准假釋在案，依\n    刑法第93條第2項規定，假釋出獄者，在假釋中付保護管束\n    ，爰依刑事訴訟法第481條第1項規定聲請裁定等語。\n二、本院審核法務部矯正司100年11月11日法授矯字第100012714\n    81號函及所附交付保護管束名冊，認聲請人之聲請為正當，\n    爰裁定如主文所示。\n據上論斷，應依刑事訴訟法第481條第1項，刑法第96條但書、第\n93條第2項，裁定如主文。\n中    華    民    國   100    年    11    月    18    日\n                  刑事第二十五庭審判長法  官  黃瑞華\n                                      法  官  許文章\n                                      法  官  高玉舜\n以上正本證明與原本無異。\n如不服本裁定，應於收受送達後五日內向本院提出抗告狀。\n                                      書記官  許雅淩\n中    華    民    國   100    年    11    月    18    日",
  "structure": {
    "main": "劉瀚聲假釋中付保護管束。",
    "reason": "一、聲請意旨略以：受刑人劉瀚聲因違反毒品危害防制條例案件\n    ，經本院以99年度上易字第741號刑事判決判處有期徒刑8月\n    確定，另因違反毒品危害防制條例案件，經臺灣板橋地方法\n    院以99年度簡字第1597號刑事簡易判決處刑書判處有期徒刑\n    5月確定，嗣由臺灣板橋地方法院以99年度聲字第3511號裁\n    定定其應執行有期徒刑11月確定；另因違反毒品危害防制條\n    例案件，經臺灣板橋地方法院以99年度易字第2567號刑事判\n    決判處有期徒刑7月，上訴後，經本院以99年度上易字第266\n    1 號判決駁回上訴而告確定，並於民國（下同）99年7月7日\n    入監執行。嗣經法務部於100年11月11日核准假釋在案，依\n    刑法第93條第2項規定，假釋出獄者，在假釋中付保護管束\n    ，爰依刑事訴訟法第481條第1項規定聲請裁定等語。\n二、本院審核法務部矯正司100年11月11日法授矯字第100012714\n    81號函及所附交付保護管束名冊，認聲請人之聲請為正當，\n    爰裁定如主文所示。\n據上論斷，應依刑事訴訟法第481條第1項，刑法第96條但書、第\n93條第2項，裁定如主文。"
  },
  "search": "臺灣高等法院刑事裁定100年度聲字第3600號聲請人臺灣高等法院檢察署檢察官受刑人劉瀚聲（現於法務部矯正署臺北監獄臺北分監執行中）上列受刑人因違反毒品危害防制條例案件，聲請人聲請保護管束（100年度執聲付字第1308號），本院裁定如下：主文劉瀚聲假釋中付保護管束。理由一、聲請意旨略以：受刑人劉瀚聲因違反毒品危害防制條例案件，經本院以99年度上易字第741號刑事判決判處有期徒刑8月確定，另因違反毒品危害防制條例案件，經臺灣板橋地方法院以99年度簡字第1597號刑事簡易判決處刑書判處有期徒刑5月確定，嗣由臺灣板橋地方法院以99年度聲字第3511號裁定定其應執行有期徒刑11月確定；另因違反毒品危害防制條例案件，經臺灣板橋地方法院以99年度易字第2567號刑事判決判處有期徒刑7月，上訴後，經本院以99年度上易字第2661號判決駁回上訴而告確定，並於民國（下同）99年7月7日入監執行。嗣經法務部於100年11月11日核准假釋在案，依刑法第93條第2項規定，假釋出獄者，在假釋中付保護管束，爰依刑事訴訟法第481條第1項規定聲請裁定等語。二、本院審核法務部矯正司100年11月11日法授矯字第10001271481號函及所附交付保護管束名冊，認聲請人之聲請為正當，爰裁定如主文所示。據上論斷，應依刑事訴訟法第481條第1項，刑法第96條但書、第93條第2項，裁定如主文。中華民國100年11月18日刑事第二十五庭審判長法官黃瑞華法官許文章法官高玉舜以上正本證明與原本無異。如不服本裁定，應於收受送達後五日內向本院提出抗告狀。書記官許雅淩中華民國100年11月18日",
  "characters": {
    "judges": [
      "黃瑞華",
      "許文章",
      "高玉舜"
    ],
    "prosecutors": [

    ],
    "lawyers": [

    ],
    "clerks": [
      "許雅淩"
    ],
    "plaintiffs": [

    ],
    "defendants": [

    ],
    "prosecutor_office": [
      "臺灣高等法院檢察署檢察官"
    ],
    "creditors": [

    ],
    "debtors": [

    ],
    "judicial_associate_officer": [

    ]
  },
  "adjudged_at": "2011-11-18",
  "created_at": "2016-02-12 22:29:01",
  "updated_at": "2016-02-12 22:29:01"
}