{
  "identify": "TYD-100-壢交簡-3202-20111118-1",
  "court": {
    "name": "臺灣桃園地方法院",
    "code": "TYD"
  },
  "division": {
    "name": "刑事",
    "code": "M"
  },
  "year": 100,
  "word": "壢交簡",
  "number": "3202",
  "jcheck": "1",
  "reason": "公共危險",
  "content": "臺灣桃園地方法院刑事簡易判決     100年度壢交簡字第3202號\n聲  請  人  臺灣桃園地方法院檢察署檢察官\n被      告  楊煜涵\n上列被告因公共危險案件，經檢察官聲請以簡易判決處刑（100\n年度偵字第26918號），本院判決如下：\n    主      文\n楊煜涵犯不能安全駕駛動力交通工具罪，處拘役伍拾伍日，如易\n科罰金，以新臺幣壹仟元折算壹日。\n    事實及理由\n一、本件犯罪事實及證據，除於犯罪事實欄文首補充「楊煜涵前\n    於民國99年間因酒後駕車之公共危險案件，經臺灣桃園地方\n    法院檢察署檢察官以99年度速偵字第7939號緩起訴處分確定\n    」之外，其餘均引用檢察官聲請簡易判決處刑書所載（如附\n    件）。\n二、按刑法第185條之3所謂不能安全駕駛，係抽象危險犯，不以\n    發生具體危險為必要，且參考德國、美國之認定標準，對於\n    酒精濃度呼氣已達每公升0.55毫克或血液濃度達百分之0.11\n    以上，肇事率為一般正常人之10倍，認為已達「不能安全駕\n    駛」之標準，有法務部民國88年5 月18日法88檢字第001669\n    號函可參；復按人體呼氣中所含酒精成分濃度如為每公升0.\n    25毫克，即相當於血液中酒精濃度（ＢＡＣ）百分之0.05，\n    ＢＡＣ到達百分之0.08至百分之0.15時，對駕駛能力之影響\n    為：判斷力嚴重受到影響，體能與精神協調受損，駕駛之體\n    能困難增加。對心理行為之影響為：產生情緒異常現象，步\n    伐不平穩，言語不清，反應惡劣，記憶及判斷力受損，精神\n    處於錯亂狀態。有交通部運輸研究所民國90年9 月24日運安\n    字第900005854 號函暨所附該所79年「駕駛人行為反應之研\n    究─酒醉駕車對駕駛行為之分析研究」函釋綦詳。查被告酒\n    後駕車，其未依規定使用燈光、駕駛有蛇行，車身搖擺不定\n    ，轉彎半徑過大或過小、車輛行徑偏離常軌，時而加速，時\n    而突停，且為警查獲後之詢問及測試過程中，其有腳步不穩\n    、語無倫次、含糊不清、滿身酒味等情形，且其酒後生理協\n    調平衡檢測結果，5 項檢測有4 項不合格等情事，有刑法第\n    185 條之3 案件測試觀察紀錄表及汽車駕駛人酒後駕車生理\n    協調平衡檢測紀錄表各1 紙在卷可稽。佐以被告經警查獲後\n    所檢測之呼氣中所含酒精濃度高達每公升0.67毫克，相當於\n    ＢＡＣ百分之0.134 ，是被告飲酒後確實已達於不能安全駕\n    駛動力交通工具之程度，而仍駕車，應堪認定。\n三、核被告楊煜涵所為，係犯刑法第185條之3不能安全駕駛動力\n    交通工具罪。爰審酌被告明知酒後不能駕車及酒醉駕車之危\n    險性，竟於飲用酒類後，呼氣酒精濃度高達每公升0.67毫克\n    ，已處於不能安全駕駛動力交通工具之狀態下，猶騎乘機車\n    行駛於公眾往來道路，漠視自己安危，更罔顧法律禁止規範\n    與公眾道路通行之安全，惟念被告犯後坦承犯行及兼衡其自\n    述家庭經濟狀況小康、智識程度為高中畢業等一切情狀，量\n    處如主文所示之刑，並諭知易科罰金之折算標準，以示懲儆\n    。\n四、依刑事訴訟法第449 條第1 項前段、第3 項、第454 條第2\n    項，刑法第185 條之3 、第41條第1 項前段，刑法施行法第\n    1 條之1 第1 項，逕以簡易判決處刑如主文。\n五、如不服本判決，應於判決送達後10日內，向本院提起上訴狀\n    。\n中    華    民    國   100    年    11    月    18    日\n                  交通法庭  法  官  吳芙蓉\n以上正本證明與原本無異。\n如不服本判決，應於判決送達後10日內向本院提出上訴狀（應附\n繕本）。\n                            書記官  吳采蓉\n中    華    民    國   100    年    11    月    28    日\n附錄本案論罪科刑之法條：\n中華民國刑法第185 條之3\n服用毒品、麻醉藥品、酒類或其他相類之物，不能安全駕駛動力\n交通工具而駕駛者，處1年以下有期徒刑、拘役或科或併科15萬\n元以下罰金。",
  "structure": {
    "main": "楊煜涵犯不能安全駕駛動力交通工具罪，處拘役伍拾伍日，如易\n科罰金，以新臺幣壹仟元折算壹日。",
    "fact": "一、本件犯罪事實及證據，除於犯罪事實欄文首補充「楊煜涵前\n    於民國99年間因酒後駕車之公共危險案件，經臺灣桃園地方\n    法院檢察署檢察官以99年度速偵字第7939號緩起訴處分確定\n    」之外，其餘均引用檢察官聲請簡易判決處刑書所載（如附\n    件）。\n二、按刑法第185條之3所謂不能安全駕駛，係抽象危險犯，不以\n    發生具體危險為必要，且參考德國、美國之認定標準，對於\n    酒精濃度呼氣已達每公升0.55毫克或血液濃度達百分之0.11\n    以上，肇事率為一般正常人之10倍，認為已達「不能安全駕\n    駛」之標準，有法務部民國88年5 月18日法88檢字第001669\n    號函可參；復按人體呼氣中所含酒精成分濃度如為每公升0.\n    25毫克，即相當於血液中酒精濃度（ＢＡＣ）百分之0.05，\n    ＢＡＣ到達百分之0.08至百分之0.15時，對駕駛能力之影響\n    為：判斷力嚴重受到影響，體能與精神協調受損，駕駛之體\n    能困難增加。對心理行為之影響為：產生情緒異常現象，步\n    伐不平穩，言語不清，反應惡劣，記憶及判斷力受損，精神\n    處於錯亂狀態。有交通部運輸研究所民國90年9 月24日運安\n    字第900005854 號函暨所附該所79年「駕駛人行為反應之研\n    究─酒醉駕車對駕駛行為之分析研究」函釋綦詳。查被告酒\n    後駕車，其未依規定使用燈光、駕駛有蛇行，車身搖擺不定\n    ，轉彎半徑過大或過小、車輛行徑偏離常軌，時而加速，時\n    而突停，且為警查獲後之詢問及測試過程中，其有腳步不穩\n    、語無倫次、含糊不清、滿身酒味等情形，且其酒後生理協\n    調平衡檢測結果，5 項檢測有4 項不合格等情事，有刑法第\n    185 條之3 案件測試觀察紀錄表及汽車駕駛人酒後駕車生理\n    協調平衡檢測紀錄表各1 紙在卷可稽。佐以被告經警查獲後\n    所檢測之呼氣中所含酒精濃度高達每公升0.67毫克，相當於\n    ＢＡＣ百分之0.134 ，是被告飲酒後確實已達於不能安全駕\n    駛動力交通工具之程度，而仍駕車，應堪認定。\n三、核被告楊煜涵所為，係犯刑法第185條之3不能安全駕駛動力\n    交通工具罪。爰審酌被告明知酒後不能駕車及酒醉駕車之危\n    險性，竟於飲用酒類後，呼氣酒精濃度高達每公升0.67毫克\n    ，已處於不能安全駕駛動力交通工具之狀態下，猶騎乘機車\n    行駛於公眾往來道路，漠視自己安危，更罔顧法律禁止規範\n    與公眾道路通行之安全，惟念被告犯後坦承犯行及兼衡其自\n    述家庭經濟狀況小康、智識程度為高中畢業等一切情狀，量\n    處如主文所示之刑，並諭知易科罰金之折算標準，以示懲儆\n    。\n四、依刑事訴訟法第449 條第1 項前段、第3 項、第454 條第2\n    項，刑法第185 條之3 、第41條第1 項前段，刑法施行法第\n    1 條之1 第1 項，逕以簡易判決處刑如主文。\n五、如不服本判決，應於判決送達後10日內，向本院提起上訴狀\n    。",
    "reason": "一、本件犯罪事實及證據，除於犯罪事實欄文首補充「楊煜涵前\n    於民國99年間因酒後駕車之公共危險案件，經臺灣桃園地方\n    法院檢察署檢察官以99年度速偵字第7939號緩起訴處分確定\n    」之外，其餘均引用檢察官聲請簡易判決處刑書所載（如附\n    件）。\n二、按刑法第185條之3所謂不能安全駕駛，係抽象危險犯，不以\n    發生具體危險為必要，且參考德國、美國之認定標準，對於\n    酒精濃度呼氣已達每公升0.55毫克或血液濃度達百分之0.11\n    以上，肇事率為一般正常人之10倍，認為已達「不能安全駕\n    駛」之標準，有法務部民國88年5 月18日法88檢字第001669\n    號函可參；復按人體呼氣中所含酒精成分濃度如為每公升0.\n    25毫克，即相當於血液中酒精濃度（ＢＡＣ）百分之0.05，\n    ＢＡＣ到達百分之0.08至百分之0.15時，對駕駛能力之影響\n    為：判斷力嚴重受到影響，體能與精神協調受損，駕駛之體\n    能困難增加。對心理行為之影響為：產生情緒異常現象，步\n    伐不平穩，言語不清，反應惡劣，記憶及判斷力受損，精神\n    處於錯亂狀態。有交通部運輸研究所民國90年9 月24日運安\n    字第900005854 號函暨所附該所79年「駕駛人行為反應之研\n    究─酒醉駕車對駕駛行為之分析研究」函釋綦詳。查被告酒\n    後駕車，其未依規定使用燈光、駕駛有蛇行，車身搖擺不定\n    ，轉彎半徑過大或過小、車輛行徑偏離常軌，時而加速，時\n    而突停，且為警查獲後之詢問及測試過程中，其有腳步不穩\n    、語無倫次、含糊不清、滿身酒味等情形，且其酒後生理協\n    調平衡檢測結果，5 項檢測有4 項不合格等情事，有刑法第\n    185 條之3 案件測試觀察紀錄表及汽車駕駛人酒後駕車生理\n    協調平衡檢測紀錄表各1 紙在卷可稽。佐以被告經警查獲後\n    所檢測之呼氣中所含酒精濃度高達每公升0.67毫克，相當於\n    ＢＡＣ百分之0.134 ，是被告飲酒後確實已達於不能安全駕\n    駛動力交通工具之程度，而仍駕車，應堪認定。\n三、核被告楊煜涵所為，係犯刑法第185條之3不能安全駕駛動力\n    交通工具罪。爰審酌被告明知酒後不能駕車及酒醉駕車之危\n    險性，竟於飲用酒類後，呼氣酒精濃度高達每公升0.67毫克\n    ，已處於不能安全駕駛動力交通工具之狀態下，猶騎乘機車\n    行駛於公眾往來道路，漠視自己安危，更罔顧法律禁止規範\n    與公眾道路通行之安全，惟念被告犯後坦承犯行及兼衡其自\n    述家庭經濟狀況小康、智識程度為高中畢業等一切情狀，量\n    處如主文所示之刑，並諭知易科罰金之折算標準，以示懲儆\n    。\n四、依刑事訴訟法第449 條第1 項前段、第3 項、第454 條第2\n    項，刑法第185 條之3 、第41條第1 項前段，刑法施行法第\n    1 條之1 第1 項，逕以簡易判決處刑如主文。\n五、如不服本判決，應於判決送達後10日內，向本院提起上訴狀\n    。"
  },
  "search": "臺灣桃園地方法院刑事簡易判決100年度壢交簡字第3202號聲請人臺灣桃園地方法院檢察署檢察官被告楊煜涵上列被告因公共危險案件，經檢察官聲請以簡易判決處刑（100年度偵字第26918號），本院判決如下：主文楊煜涵犯不能安全駕駛動力交通工具罪，處拘役伍拾伍日，如易科罰金，以新臺幣壹仟元折算壹日。事實及理由一、本件犯罪事實及證據，除於犯罪事實欄文首補充「楊煜涵前於民國99年間因酒後駕車之公共危險案件，經臺灣桃園地方法院檢察署檢察官以99年度速偵字第7939號緩起訴處分確定」之外，其餘均引用檢察官聲請簡易判決處刑書所載（如附件）。二、按刑法第185條之3所謂不能安全駕駛，係抽象危險犯，不以發生具體危險為必要，且參考德國、美國之認定標準，對於酒精濃度呼氣已達每公升0.55毫克或血液濃度達百分之0.11以上，肇事率為一般正常人之10倍，認為已達「不能安全駕駛」之標準，有法務部民國88年5月18日法88檢字第001669號函可參；復按人體呼氣中所含酒精成分濃度如為每公升0.25毫克，即相當於血液中酒精濃度（ＢＡＣ）百分之0.05，ＢＡＣ到達百分之0.08至百分之0.15時，對駕駛能力之影響為：判斷力嚴重受到影響，體能與精神協調受損，駕駛之體能困難增加。對心理行為之影響為：產生情緒異常現象，步伐不平穩，言語不清，反應惡劣，記憶及判斷力受損，精神處於錯亂狀態。有交通部運輸研究所民國90年9月24日運安字第900005854號函暨所附該所79年「駕駛人行為反應之研究─酒醉駕車對駕駛行為之分析研究」函釋綦詳。查被告酒後駕車，其未依規定使用燈光、駕駛有蛇行，車身搖擺不定，轉彎半徑過大或過小、車輛行徑偏離常軌，時而加速，時而突停，且為警查獲後之詢問及測試過程中，其有腳步不穩、語無倫次、含糊不清、滿身酒味等情形，且其酒後生理協調平衡檢測結果，5項檢測有4項不合格等情事，有刑法第185條之3案件測試觀察紀錄表及汽車駕駛人酒後駕車生理協調平衡檢測紀錄表各1紙在卷可稽。佐以被告經警查獲後所檢測之呼氣中所含酒精濃度高達每公升0.67毫克，相當於ＢＡＣ百分之0.134，是被告飲酒後確實已達於不能安全駕駛動力交通工具之程度，而仍駕車，應堪認定。三、核被告楊煜涵所為，係犯刑法第185條之3不能安全駕駛動力交通工具罪。爰審酌被告明知酒後不能駕車及酒醉駕車之危險性，竟於飲用酒類後，呼氣酒精濃度高達每公升0.67毫克，已處於不能安全駕駛動力交通工具之狀態下，猶騎乘機車行駛於公眾往來道路，漠視自己安危，更罔顧法律禁止規範與公眾道路通行之安全，惟念被告犯後坦承犯行及兼衡其自述家庭經濟狀況小康、智識程度為高中畢業等一切情狀，量處如主文所示之刑，並諭知易科罰金之折算標準，以示懲儆。四、依刑事訴訟法第449條第1項前段、第3項、第454條第2項，刑法第185條之3、第41條第1項前段，刑法施行法第1條之1第1項，逕以簡易判決處刑如主文。五、如不服本判決，應於判決送達後10日內，向本院提起上訴狀。中華民國100年11月18日交通法庭法官吳芙蓉以上正本證明與原本無異。如不服本判決，應於判決送達後10日內向本院提出上訴狀（應附繕本）。書記官吳采蓉中華民國100年11月28日附錄本案論罪科刑之法條：中華民國刑法第185條之3服用毒品、麻醉藥品、酒類或其他相類之物，不能安全駕駛動力交通工具而駕駛者，處1年以下有期徒刑、拘役或科或併科15萬元以下罰金。",
  "characters": {
    "judges": [
      "吳芙蓉"
    ],
    "prosecutors": [

    ],
    "lawyers": [

    ],
    "clerks": [
      "吳采蓉"
    ],
    "plaintiffs": [

    ],
    "defendants": [
      "楊煜涵"
    ],
    "prosecutor_office": [
      "臺灣桃園地方法院檢察署檢察官"
    ],
    "creditors": [

    ],
    "debtors": [

    ],
    "judicial_associate_officer": [

    ]
  },
  "adjudged_at": "2011-11-18",
  "created_at": "2016-02-12 22:38:39",
  "updated_at": "2016-02-12 22:38:39"
}