{
  "identify": "ILD-100-訴更-1-20111111-1",
  "court": {
    "name": "臺灣宜蘭地方法院",
    "code": "ILD"
  },
  "division": {
    "name": "民事",
    "code": "V"
  },
  "year": 100,
  "word": "訴更",
  "number": "1",
  "jcheck": "1",
  "reason": "分配表異議之訴",
  "content": "臺灣宜蘭地方法院民事判決              100年度訴更字第1號\n原      告  游秋華\n訴訟代理人  林世超律師\n被      告  張智維\n被      告  吳宛柔\n共      同\n訴訟代理人  蔡坤鐘律師\n當事人間分配表異議之訴事件，本院於100年10月28日言詞辯論\n終結，判決如下：\n    主  文\n原告之訴駁回。\n訴訟費用由原告負擔。\n    事實及理由\n一、本件原告主張：被告張智維及吳宛柔，分執本院97年度訴字\n    第167號假執行判決為執行名義，聲請對原告所有坐落宜蘭\n    縣羅東鎮○○段1360地號土地及其上門牌號碼宜蘭縣羅東鎮\n    ○○路123號7樓建物（下簡稱系爭不動產）為強制執行（本\n    院民事執行處99年度司執字第1705號）及參與分配。經本院\n    民事執行處拍定後，於民國97年6月23日作成分配表，被告\n    張智維受有新臺幣（下同）1,624,395元之分配金額（包括\n    次序4執行費21,882元、次序7普通債權1,472,787元、次序7\n    利息129,726元），被告吳宛柔則受有219,216元之分配金額\n    （包括次序5執行費1,60 0元、次序6第一順位抵押債權200,\n    000元、次序6利息17,616元），並定於同年7月7日實行分配\n    。惟兩造前於本院97年移調字第15號土地所有權移轉登記事\n    件達成調解，調解筆錄第4項載明：「參加人張智維保證第\n    三人吳宛柔就相對人（即本件原告游秋華）所有坐落宜蘭縣\n    羅東鎮○○路123號7樓之房屋及坐落基地（即宜蘭縣羅東鎮\n    ○○段136地號及其上同段1963建號），設有價值360萬元之\n    第一順位抵押權，於相對人應於97年6月9日（以法院收狀日\n    為準）前，另對參加人張智維提起請求清償借款、傭金及代\n    墊款項等給付訴訟之民事事件之訴訟期間至確定為止，第三\n    人吳宛柔不會聲請拍賣前開抵押物（含聲請裁定及強制執行\n    ）。如第三人吳宛柔有前開行為，參加人同意對相對人因之\n    所受之一切損害負賠償責任」等語。是依前揭調解內容，被\n    告張智維尚且出面保證被告吳宛柔於原告對被告張智維提起\n    請求清償借款、傭金及代墊款項等給付訴訟之民事事件（即\n    系爭假執行之本案訴訟）確定前，不得拍賣該不動產，則舉\n    重以明輕，被告張智維更不能於系爭假執行之本案訴訟判決\n    確定前，聲請拍賣該不動產。被告張智維、吳宛柔違反前開\n    調解內容約定，分別聲請強制拍賣原告之系爭不動產及參與\n    分配，則依前揭調解筆錄約定，被告張智維須對原告所受一\n    切損害負賠償責任。原告之系爭不動產在判決確定前，提前\n    遭被告張智維聲請強制執行拍賣，並由第三人得標，拍賣金\n    額為2,377,000元，上開損害既係由假執行所造成，原告自\n    得主張以上開損害額來抵銷被告張智維、吳宛柔受分配之金\n    額。經此抵銷，被告張智維、吳宛柔依前開分配表所受之分\n    配金額，應予剔除。為此提起本件分配表異議之訴，聲明請\n    求剔除被告張智維、吳宛柔自前述分配表所受之各該分配金\n    額。\n二、被告則以：系爭假執行事件之本案訴訟，就原告本案訴訟之\n    請求及主張，經本院判決駁回後，迭經臺灣高等法院、最高\n    法院駁回原告上訴而告確定，甚至增加原告應給付被告張智\n    維之款項，在法律上殊無准許原告在本件訴訟重為主張之理\n    。是原告所提起本件訴訟，在法律上已屬顯無理由，而無權\n    利保護之必要。又，兩造雖曾於本院97年度移調字第15號所\n    有權移轉登記事件達成和解，並製有前揭內容之調解筆錄，\n    但前述調解內容僅對被告吳宛柔聲請拍賣系爭不動產之時間\n    作限制，而未限制被告張智維得自行聲請強制執行之權利。\n    且被告張智維係因其另行取得對原告之執行名義而聲請就系\n    爭不動產為強制執行，此與前揭調解內容所載被告張智維保\n    證被告吳宛柔於訴訟確定前不得對原告聲請強制執行之約定\n    ，明顯不同，被告張智維自無違反調解筆錄之約定。且假執\n    行係依判決而為之，並無不法侵害原告權利可言，被告自無\n    須負損害賠償之責任，原告即不得以其對被告另有損害賠償\n    債權主張抵銷等語，資為抗辯。並聲明求為駁回原告之訴。\n三、兩造不爭執事項：\n (一) 被告張智維於99年2月4日執本院97年度訴字第167號假執行\n    判決為執行名義，向本院民事執行處聲請就系爭不動產為假\n    執行，於99年5月25日由訴外人侯蓉以2,377,000元得標買受\n    ，本院民事執行處於99年6月23日製作分配表，定於99年7月\n    7 日實行分配。\n (二) 系爭假執行之本案訴訟，經本院97年度訴字第167號判決本\n    件原告應給付被告張智維1,472,787元及遲延利息、應給付\n    被告吳宛柔200,000元及遲延利息，兩造不服提起上訴，經\n    臺灣高等法院就上開原告應給付部分駁回原告之上訴，並經\n    最高法院裁定駁回上訴確定，而確認被告張智維、被告吳宛\n    柔分別對原告具有1,472,787元、200,000元（即分別如系爭\n    分配表次序7、次序6所示）之金錢債權存在。\n (三) 兩造前於本院97年移調字第15號土地所有權移轉登記事件達\n    成調解，調解內容記載：「參加人張智維保證第三人吳宛柔\n    就相對人（即本件原告游秋華）所有坐落宜蘭縣羅東鎮○○\n    路123號7樓之房屋及坐落基地（即宜蘭縣羅東鎮○○段136\n    地號及其上同段1963建號），設有價值360萬元之第一順位\n    抵押權，於相對人應於97年6月9日（以法院收狀日為準）前\n    ，另對參加人張智維提起請求清償借款、傭金及代墊款項等\n    給付訴訟之民事事件之訴訟期間至確定為止，第三人吳宛柔\n    不會聲請拍賣前開抵押物（含聲請裁定及強制執行）。如第\n    三人吳宛柔有前開行為，參加人同意對相對人因之所受之一\n    切損害負賠償責任」等語。\n四、經本院於言詞辯論期日使當事人整理並協議簡化爭點結果（\n    見本院卷第108至109頁），兩造之爭點為：(一)原告提起本件\n    訴訟是否有權利保護之必要？(二)被告張智維是否違反前開調\n    解內容而負賠償責任，及原告得否主張抵銷？茲就前開爭點\n    ，說明本院心證如下：\n (一) 原告提起本件訴訟是否無權利保護必要？\n    系爭假執行程序經本院民事執行處於99年6月23日製作分配\n    表之事實，為兩造所不爭執，已如前述。而依本院民事執行\n    處所製作之分配表內容（見本院99年度訴字第205號卷第24\n    頁），可知系爭不動產經法院拍賣且實施分配之結果，該不\n    動產拍賣所得金額合計2,377,000元，扣除應受分配之相關\n    稅捐（如分配表次序1至3所示）、執行費（如分配表次序4\n    、5 所示）、抵押權（如分配表次序6所示）、普通債權（\n    如分配表次序7所示）等應受分配之債權金額後，尚有餘款\n    435,013元可發還原告。而查，本件原告起訴主張被告違反\n    前揭調解內容之約定而負損害賠償之責，並主張以之抵銷被\n    告張智維、吳宛柔對於原告之債權，則倘原告所為前開抵銷\n    之抗辯確屬有據，自足以影響被告張智維、吳宛柔於前開分\n    配表上之債權金額，而進一步影響被告張智維、吳宛柔應受\n    分配之金額；被告張智維、吳宛柔應受分配之金額倘經扣減\n    或剔除，原告所受發還之餘款即可增加，足認原告提起本件\n    訴訟，非無權利保護之必要。被告抗辯：系爭假執行之本案\n    訴訟業已判決確定，被告張智維對原告確有系爭分配表所載\n    之金錢借貸債權存在，其債權甚至超過系爭分配表所列之債\n    權金額，故原告提起本件訴訟欠缺權利保護必要，不應准許\n    云云，並不足採。\n (二) 被告張智維是否違反前揭調解內容而負賠償責任，及原告得\n    否主張抵銷？\n    兩造前於本院97年移調字第15號土地所有權移轉登記事件達\n    成調解，調解筆錄第4項載明：「參加人張智維保證第三人\n    吳宛柔就相對人（即本件原告游秋華）所有坐落宜蘭縣羅東\n    鎮○○路123號7樓之房屋及坐落基地（即宜蘭縣羅東鎮○○\n    段136地號及其上同段1963建號），設有價值360萬元之第一\n    順位抵押權，於相對人應於97年6月9日（以法院收狀日為準\n    ）前，另對參加人張智維提起請求清償借款、傭金及代墊款\n    項等給付訴訟之民事事件之訴訟期間至確定為止，第三人吳\n    宛柔不會聲請拍賣前開抵押物（含聲請裁定及強制執行）。\n    如第三人吳宛柔有前開行為，參加人同意對相對人因之所受\n    之一切損害負賠償責任」等語，此為兩造所不爭執，已見前\n    述。原告雖稱：依前揭調解內容，被告張智維尚且出面保證\n    被告吳宛柔於系爭假執行之本案訴訟判決確定前，不得拍賣\n    系爭不動產，則舉重以明輕，被告張智維更不能於本案訴訟\n    之判決確定前聲請拍賣系爭不動產云云。然查：調解筆錄第\n    4項載明被告張智維係「保證被告吳宛柔於系爭假執行之本\n    案訴訟判決確定前，不會就系爭不動產聲請拍賣抵押」，其\n    文義內容僅係被告張智維願擔保被告吳宛柔不致在系爭假執\n    行之本案訴訟判決確定前聲請拍賣系爭不動產，並未限制被\n    告張智維自行聲請拍賣系爭不動產之權利。且本院97年度移\n    調字第15號所有權移轉登記事件，乃係本院97年度重訴字第\n    32號所有權移轉登記等事件中所為移付調解之事件，該案當\n    事人原告為吳宛柔、林宏明、林宏程，被告為游秋華、鄭福\n    來、鄭志成、李素鳳等人，至本件被告張智維則非該案之當\n    事人，僅於該民事事件移付調解程序中，以參加人之身分參\n    與調解，此業據本院調閱上開民事卷宗核閱明確，並為兩造\n    當事人所不爭執。本件被告張智維既僅於前述調解程序中基\n    於參加人地位參加和解，自難認其除前述調解內容載明應負\n    之責任外，尚願負擔其他責任。是依前述調解約定之內容及\n    調解作成情況，並無從解釋被告張智維本人願負有不得在系\n    爭假執行程序之本案訴訟確定前聲請強制執行之義務。原告\n    謂：舉重以明輕，被告張智維不能於本案訴訟之判決確定前\n    聲請拍賣系爭不動產云云，要屬無據。從而，被告張智維本\n    件聲請假執行系爭不動產，既未違反前述調解內容，自無須\n    依前述調解內容負損害賠償責任。原告對於被告張智維既無\n    其所指違反調解約定所生之損害賠償債權存在，其主張以該\n    債權作為抵銷云云，即非有據。\n五、綜上所述，原告所為抵銷之抗辯並無足採，其依強制執行法\n    第41條第1項規定提起本件分配表異議之訴，請求將系爭分\n    配表中被告張智維、吳宛柔應受分配之債權額予以剔除，並\n    無理由，不應准許。\n六、本件事證已臻明確，兩造其餘攻擊防禦及未經援用之證據，\n    於判決結果不生影響，爰不另一一論述，併此敘明。\n七、據上論結，原告之訴為無理由，依民事訴訟法第78條，判決\n    如主文。\n中    華    民    國   100    年    11    月    11    日\n正本係照原本作成。\n如不服本判決，應於收受送達後20日內向本院提出上訴狀（應附\n繕本）。\n中    華    民    國   100    年    11    月    11    日\n                              書記官  吳文雄",
  "structure": {
    "main": "原告之訴駁回。\n訴訟費用由原告負擔。",
    "fact": "一、本件原告主張：被告張智維及吳宛柔，分執本院97年度訴字\n    第167號假執行判決為執行名義，聲請對原告所有坐落宜蘭\n    縣羅東鎮○○段1360地號土地及其上門牌號碼宜蘭縣羅東鎮\n    ○○路123號7樓建物（下簡稱系爭不動產）為強制執行（本\n    院民事執行處99年度司執字第1705號）及參與分配。經本院\n    民事執行處拍定後，於民國97年6月23日作成分配表，被告\n    張智維受有新臺幣（下同）1,624,395元之分配金額（包括\n    次序4執行費21,882元、次序7普通債權1,472,787元、次序7\n    利息129,726元），被告吳宛柔則受有219,216元之分配金額\n    （包括次序5執行費1,60 0元、次序6第一順位抵押債權200,\n    000元、次序6利息17,616元），並定於同年7月7日實行分配\n    。惟兩造前於本院97年移調字第15號土地所有權移轉登記事\n    件達成調解，調解筆錄第4項載明：「參加人張智維保證第\n    三人吳宛柔就相對人（即本件原告游秋華）所有坐落宜蘭縣\n    羅東鎮○○路123號7樓之房屋及坐落基地（即宜蘭縣羅東鎮\n    ○○段136地號及其上同段1963建號），設有價值360萬元之\n    第一順位抵押權，於相對人應於97年6月9日（以法院收狀日\n    為準）前，另對參加人張智維提起請求清償借款、傭金及代\n    墊款項等給付訴訟之民事事件之訴訟期間至確定為止，第三\n    人吳宛柔不會聲請拍賣前開抵押物（含聲請裁定及強制執行\n    ）。如第三人吳宛柔有前開行為，參加人同意對相對人因之\n    所受之一切損害負賠償責任」等語。是依前揭調解內容，被\n    告張智維尚且出面保證被告吳宛柔於原告對被告張智維提起\n    請求清償借款、傭金及代墊款項等給付訴訟之民事事件（即\n    系爭假執行之本案訴訟）確定前，不得拍賣該不動產，則舉\n    重以明輕，被告張智維更不能於系爭假執行之本案訴訟判決\n    確定前，聲請拍賣該不動產。被告張智維、吳宛柔違反前開\n    調解內容約定，分別聲請強制拍賣原告之系爭不動產及參與\n    分配，則依前揭調解筆錄約定，被告張智維須對原告所受一\n    切損害負賠償責任。原告之系爭不動產在判決確定前，提前\n    遭被告張智維聲請強制執行拍賣，並由第三人得標，拍賣金\n    額為2,377,000元，上開損害既係由假執行所造成，原告自\n    得主張以上開損害額來抵銷被告張智維、吳宛柔受分配之金\n    額。經此抵銷，被告張智維、吳宛柔依前開分配表所受之分\n    配金額，應予剔除。為此提起本件分配表異議之訴，聲明請\n    求剔除被告張智維、吳宛柔自前述分配表所受之各該分配金\n    額。\n二、被告則以：系爭假執行事件之本案訴訟，就原告本案訴訟之\n    請求及主張，經本院判決駁回後，迭經臺灣高等法院、最高\n    法院駁回原告上訴而告確定，甚至增加原告應給付被告張智\n    維之款項，在法律上殊無准許原告在本件訴訟重為主張之理\n    。是原告所提起本件訴訟，在法律上已屬顯無理由，而無權\n    利保護之必要。又，兩造雖曾於本院97年度移調字第15號所\n    有權移轉登記事件達成和解，並製有前揭內容之調解筆錄，\n    但前述調解內容僅對被告吳宛柔聲請拍賣系爭不動產之時間\n    作限制，而未限制被告張智維得自行聲請強制執行之權利。\n    且被告張智維係因其另行取得對原告之執行名義而聲請就系\n    爭不動產為強制執行，此與前揭調解內容所載被告張智維保\n    證被告吳宛柔於訴訟確定前不得對原告聲請強制執行之約定\n    ，明顯不同，被告張智維自無違反調解筆錄之約定。且假執\n    行係依判決而為之，並無不法侵害原告權利可言，被告自無\n    須負損害賠償之責任，原告即不得以其對被告另有損害賠償\n    債權主張抵銷等語，資為抗辯。並聲明求為駁回原告之訴。\n三、兩造不爭執事項：\n (一) 被告張智維於99年2月4日執本院97年度訴字第167號假執行\n    判決為執行名義，向本院民事執行處聲請就系爭不動產為假\n    執行，於99年5月25日由訴外人侯蓉以2,377,000元得標買受\n    ，本院民事執行處於99年6月23日製作分配表，定於99年7月\n    7 日實行分配。\n (二) 系爭假執行之本案訴訟，經本院97年度訴字第167號判決本\n    件原告應給付被告張智維1,472,787元及遲延利息、應給付\n    被告吳宛柔200,000元及遲延利息，兩造不服提起上訴，經\n    臺灣高等法院就上開原告應給付部分駁回原告之上訴，並經\n    最高法院裁定駁回上訴確定，而確認被告張智維、被告吳宛\n    柔分別對原告具有1,472,787元、200,000元（即分別如系爭\n    分配表次序7、次序6所示）之金錢債權存在。\n (三) 兩造前於本院97年移調字第15號土地所有權移轉登記事件達\n    成調解，調解內容記載：「參加人張智維保證第三人吳宛柔\n    就相對人（即本件原告游秋華）所有坐落宜蘭縣羅東鎮○○\n    路123號7樓之房屋及坐落基地（即宜蘭縣羅東鎮○○段136\n    地號及其上同段1963建號），設有價值360萬元之第一順位\n    抵押權，於相對人應於97年6月9日（以法院收狀日為準）前\n    ，另對參加人張智維提起請求清償借款、傭金及代墊款項等\n    給付訴訟之民事事件之訴訟期間至確定為止，第三人吳宛柔\n    不會聲請拍賣前開抵押物（含聲請裁定及強制執行）。如第\n    三人吳宛柔有前開行為，參加人同意對相對人因之所受之一\n    切損害負賠償責任」等語。\n四、經本院於言詞辯論期日使當事人整理並協議簡化爭點結果（\n    見本院卷第108至109頁），兩造之爭點為：(一)原告提起本件\n    訴訟是否有權利保護之必要？(二)被告張智維是否違反前開調\n    解內容而負賠償責任，及原告得否主張抵銷？茲就前開爭點\n    ，說明本院心證如下：\n (一) 原告提起本件訴訟是否無權利保護必要？\n    系爭假執行程序經本院民事執行處於99年6月23日製作分配\n    表之事實，為兩造所不爭執，已如前述。而依本院民事執行\n    處所製作之分配表內容（見本院99年度訴字第205號卷第24\n    頁），可知系爭不動產經法院拍賣且實施分配之結果，該不\n    動產拍賣所得金額合計2,377,000元，扣除應受分配之相關\n    稅捐（如分配表次序1至3所示）、執行費（如分配表次序4\n    、5 所示）、抵押權（如分配表次序6所示）、普通債權（\n    如分配表次序7所示）等應受分配之債權金額後，尚有餘款\n    435,013元可發還原告。而查，本件原告起訴主張被告違反\n    前揭調解內容之約定而負損害賠償之責，並主張以之抵銷被\n    告張智維、吳宛柔對於原告之債權，則倘原告所為前開抵銷\n    之抗辯確屬有據，自足以影響被告張智維、吳宛柔於前開分\n    配表上之債權金額，而進一步影響被告張智維、吳宛柔應受\n    分配之金額；被告張智維、吳宛柔應受分配之金額倘經扣減\n    或剔除，原告所受發還之餘款即可增加，足認原告提起本件\n    訴訟，非無權利保護之必要。被告抗辯：系爭假執行之本案\n    訴訟業已判決確定，被告張智維對原告確有系爭分配表所載\n    之金錢借貸債權存在，其債權甚至超過系爭分配表所列之債\n    權金額，故原告提起本件訴訟欠缺權利保護必要，不應准許\n    云云，並不足採。\n (二) 被告張智維是否違反前揭調解內容而負賠償責任，及原告得\n    否主張抵銷？\n    兩造前於本院97年移調字第15號土地所有權移轉登記事件達\n    成調解，調解筆錄第4項載明：「參加人張智維保證第三人\n    吳宛柔就相對人（即本件原告游秋華）所有坐落宜蘭縣羅東\n    鎮○○路123號7樓之房屋及坐落基地（即宜蘭縣羅東鎮○○\n    段136地號及其上同段1963建號），設有價值360萬元之第一\n    順位抵押權，於相對人應於97年6月9日（以法院收狀日為準\n    ）前，另對參加人張智維提起請求清償借款、傭金及代墊款\n    項等給付訴訟之民事事件之訴訟期間至確定為止，第三人吳\n    宛柔不會聲請拍賣前開抵押物（含聲請裁定及強制執行）。\n    如第三人吳宛柔有前開行為，參加人同意對相對人因之所受\n    之一切損害負賠償責任」等語，此為兩造所不爭執，已見前\n    述。原告雖稱：依前揭調解內容，被告張智維尚且出面保證\n    被告吳宛柔於系爭假執行之本案訴訟判決確定前，不得拍賣\n    系爭不動產，則舉重以明輕，被告張智維更不能於本案訴訟\n    之判決確定前聲請拍賣系爭不動產云云。然查：調解筆錄第\n    4項載明被告張智維係「保證被告吳宛柔於系爭假執行之本\n    案訴訟判決確定前，不會就系爭不動產聲請拍賣抵押」，其\n    文義內容僅係被告張智維願擔保被告吳宛柔不致在系爭假執\n    行之本案訴訟判決確定前聲請拍賣系爭不動產，並未限制被\n    告張智維自行聲請拍賣系爭不動產之權利。且本院97年度移\n    調字第15號所有權移轉登記事件，乃係本院97年度重訴字第\n    32號所有權移轉登記等事件中所為移付調解之事件，該案當\n    事人原告為吳宛柔、林宏明、林宏程，被告為游秋華、鄭福\n    來、鄭志成、李素鳳等人，至本件被告張智維則非該案之當\n    事人，僅於該民事事件移付調解程序中，以參加人之身分參\n    與調解，此業據本院調閱上開民事卷宗核閱明確，並為兩造\n    當事人所不爭執。本件被告張智維既僅於前述調解程序中基\n    於參加人地位參加和解，自難認其除前述調解內容載明應負\n    之責任外，尚願負擔其他責任。是依前述調解約定之內容及\n    調解作成情況，並無從解釋被告張智維本人願負有不得在系\n    爭假執行程序之本案訴訟確定前聲請強制執行之義務。原告\n    謂：舉重以明輕，被告張智維不能於本案訴訟之判決確定前\n    聲請拍賣系爭不動產云云，要屬無據。從而，被告張智維本\n    件聲請假執行系爭不動產，既未違反前述調解內容，自無須\n    依前述調解內容負損害賠償責任。原告對於被告張智維既無\n    其所指違反調解約定所生之損害賠償債權存在，其主張以該\n    債權作為抵銷云云，即非有據。\n五、綜上所述，原告所為抵銷之抗辯並無足採，其依強制執行法\n    第41條第1項規定提起本件分配表異議之訴，請求將系爭分\n    配表中被告張智維、吳宛柔應受分配之債權額予以剔除，並\n    無理由，不應准許。\n六、本件事證已臻明確，兩造其餘攻擊防禦及未經援用之證據，\n    於判決結果不生影響，爰不另一一論述，併此敘明。\n七、據上論結，原告之訴為無理由，依民事訴訟法第78條，判決\n    如主文。",
    "reason": "一、本件原告主張：被告張智維及吳宛柔，分執本院97年度訴字\n    第167號假執行判決為執行名義，聲請對原告所有坐落宜蘭\n    縣羅東鎮○○段1360地號土地及其上門牌號碼宜蘭縣羅東鎮\n    ○○路123號7樓建物（下簡稱系爭不動產）為強制執行（本\n    院民事執行處99年度司執字第1705號）及參與分配。經本院\n    民事執行處拍定後，於民國97年6月23日作成分配表，被告\n    張智維受有新臺幣（下同）1,624,395元之分配金額（包括\n    次序4執行費21,882元、次序7普通債權1,472,787元、次序7\n    利息129,726元），被告吳宛柔則受有219,216元之分配金額\n    （包括次序5執行費1,60 0元、次序6第一順位抵押債權200,\n    000元、次序6利息17,616元），並定於同年7月7日實行分配\n    。惟兩造前於本院97年移調字第15號土地所有權移轉登記事\n    件達成調解，調解筆錄第4項載明：「參加人張智維保證第\n    三人吳宛柔就相對人（即本件原告游秋華）所有坐落宜蘭縣\n    羅東鎮○○路123號7樓之房屋及坐落基地（即宜蘭縣羅東鎮\n    ○○段136地號及其上同段1963建號），設有價值360萬元之\n    第一順位抵押權，於相對人應於97年6月9日（以法院收狀日\n    為準）前，另對參加人張智維提起請求清償借款、傭金及代\n    墊款項等給付訴訟之民事事件之訴訟期間至確定為止，第三\n    人吳宛柔不會聲請拍賣前開抵押物（含聲請裁定及強制執行\n    ）。如第三人吳宛柔有前開行為，參加人同意對相對人因之\n    所受之一切損害負賠償責任」等語。是依前揭調解內容，被\n    告張智維尚且出面保證被告吳宛柔於原告對被告張智維提起\n    請求清償借款、傭金及代墊款項等給付訴訟之民事事件（即\n    系爭假執行之本案訴訟）確定前，不得拍賣該不動產，則舉\n    重以明輕，被告張智維更不能於系爭假執行之本案訴訟判決\n    確定前，聲請拍賣該不動產。被告張智維、吳宛柔違反前開\n    調解內容約定，分別聲請強制拍賣原告之系爭不動產及參與\n    分配，則依前揭調解筆錄約定，被告張智維須對原告所受一\n    切損害負賠償責任。原告之系爭不動產在判決確定前，提前\n    遭被告張智維聲請強制執行拍賣，並由第三人得標，拍賣金\n    額為2,377,000元，上開損害既係由假執行所造成，原告自\n    得主張以上開損害額來抵銷被告張智維、吳宛柔受分配之金\n    額。經此抵銷，被告張智維、吳宛柔依前開分配表所受之分\n    配金額，應予剔除。為此提起本件分配表異議之訴，聲明請\n    求剔除被告張智維、吳宛柔自前述分配表所受之各該分配金\n    額。\n二、被告則以：系爭假執行事件之本案訴訟，就原告本案訴訟之\n    請求及主張，經本院判決駁回後，迭經臺灣高等法院、最高\n    法院駁回原告上訴而告確定，甚至增加原告應給付被告張智\n    維之款項，在法律上殊無准許原告在本件訴訟重為主張之理\n    。是原告所提起本件訴訟，在法律上已屬顯無理由，而無權\n    利保護之必要。又，兩造雖曾於本院97年度移調字第15號所\n    有權移轉登記事件達成和解，並製有前揭內容之調解筆錄，\n    但前述調解內容僅對被告吳宛柔聲請拍賣系爭不動產之時間\n    作限制，而未限制被告張智維得自行聲請強制執行之權利。\n    且被告張智維係因其另行取得對原告之執行名義而聲請就系\n    爭不動產為強制執行，此與前揭調解內容所載被告張智維保\n    證被告吳宛柔於訴訟確定前不得對原告聲請強制執行之約定\n    ，明顯不同，被告張智維自無違反調解筆錄之約定。且假執\n    行係依判決而為之，並無不法侵害原告權利可言，被告自無\n    須負損害賠償之責任，原告即不得以其對被告另有損害賠償\n    債權主張抵銷等語，資為抗辯。並聲明求為駁回原告之訴。\n三、兩造不爭執事項：\n (一) 被告張智維於99年2月4日執本院97年度訴字第167號假執行\n    判決為執行名義，向本院民事執行處聲請就系爭不動產為假\n    執行，於99年5月25日由訴外人侯蓉以2,377,000元得標買受\n    ，本院民事執行處於99年6月23日製作分配表，定於99年7月\n    7 日實行分配。\n (二) 系爭假執行之本案訴訟，經本院97年度訴字第167號判決本\n    件原告應給付被告張智維1,472,787元及遲延利息、應給付\n    被告吳宛柔200,000元及遲延利息，兩造不服提起上訴，經\n    臺灣高等法院就上開原告應給付部分駁回原告之上訴，並經\n    最高法院裁定駁回上訴確定，而確認被告張智維、被告吳宛\n    柔分別對原告具有1,472,787元、200,000元（即分別如系爭\n    分配表次序7、次序6所示）之金錢債權存在。\n (三) 兩造前於本院97年移調字第15號土地所有權移轉登記事件達\n    成調解，調解內容記載：「參加人張智維保證第三人吳宛柔\n    就相對人（即本件原告游秋華）所有坐落宜蘭縣羅東鎮○○\n    路123號7樓之房屋及坐落基地（即宜蘭縣羅東鎮○○段136\n    地號及其上同段1963建號），設有價值360萬元之第一順位\n    抵押權，於相對人應於97年6月9日（以法院收狀日為準）前\n    ，另對參加人張智維提起請求清償借款、傭金及代墊款項等\n    給付訴訟之民事事件之訴訟期間至確定為止，第三人吳宛柔\n    不會聲請拍賣前開抵押物（含聲請裁定及強制執行）。如第\n    三人吳宛柔有前開行為，參加人同意對相對人因之所受之一\n    切損害負賠償責任」等語。\n四、經本院於言詞辯論期日使當事人整理並協議簡化爭點結果（\n    見本院卷第108至109頁），兩造之爭點為：(一)原告提起本件\n    訴訟是否有權利保護之必要？(二)被告張智維是否違反前開調\n    解內容而負賠償責任，及原告得否主張抵銷？茲就前開爭點\n    ，說明本院心證如下：\n (一) 原告提起本件訴訟是否無權利保護必要？\n    系爭假執行程序經本院民事執行處於99年6月23日製作分配\n    表之事實，為兩造所不爭執，已如前述。而依本院民事執行\n    處所製作之分配表內容（見本院99年度訴字第205號卷第24\n    頁），可知系爭不動產經法院拍賣且實施分配之結果，該不\n    動產拍賣所得金額合計2,377,000元，扣除應受分配之相關\n    稅捐（如分配表次序1至3所示）、執行費（如分配表次序4\n    、5 所示）、抵押權（如分配表次序6所示）、普通債權（\n    如分配表次序7所示）等應受分配之債權金額後，尚有餘款\n    435,013元可發還原告。而查，本件原告起訴主張被告違反\n    前揭調解內容之約定而負損害賠償之責，並主張以之抵銷被\n    告張智維、吳宛柔對於原告之債權，則倘原告所為前開抵銷\n    之抗辯確屬有據，自足以影響被告張智維、吳宛柔於前開分\n    配表上之債權金額，而進一步影響被告張智維、吳宛柔應受\n    分配之金額；被告張智維、吳宛柔應受分配之金額倘經扣減\n    或剔除，原告所受發還之餘款即可增加，足認原告提起本件\n    訴訟，非無權利保護之必要。被告抗辯：系爭假執行之本案\n    訴訟業已判決確定，被告張智維對原告確有系爭分配表所載\n    之金錢借貸債權存在，其債權甚至超過系爭分配表所列之債\n    權金額，故原告提起本件訴訟欠缺權利保護必要，不應准許\n    云云，並不足採。\n (二) 被告張智維是否違反前揭調解內容而負賠償責任，及原告得\n    否主張抵銷？\n    兩造前於本院97年移調字第15號土地所有權移轉登記事件達\n    成調解，調解筆錄第4項載明：「參加人張智維保證第三人\n    吳宛柔就相對人（即本件原告游秋華）所有坐落宜蘭縣羅東\n    鎮○○路123號7樓之房屋及坐落基地（即宜蘭縣羅東鎮○○\n    段136地號及其上同段1963建號），設有價值360萬元之第一\n    順位抵押權，於相對人應於97年6月9日（以法院收狀日為準\n    ）前，另對參加人張智維提起請求清償借款、傭金及代墊款\n    項等給付訴訟之民事事件之訴訟期間至確定為止，第三人吳\n    宛柔不會聲請拍賣前開抵押物（含聲請裁定及強制執行）。\n    如第三人吳宛柔有前開行為，參加人同意對相對人因之所受\n    之一切損害負賠償責任」等語，此為兩造所不爭執，已見前\n    述。原告雖稱：依前揭調解內容，被告張智維尚且出面保證\n    被告吳宛柔於系爭假執行之本案訴訟判決確定前，不得拍賣\n    系爭不動產，則舉重以明輕，被告張智維更不能於本案訴訟\n    之判決確定前聲請拍賣系爭不動產云云。然查：調解筆錄第\n    4項載明被告張智維係「保證被告吳宛柔於系爭假執行之本\n    案訴訟判決確定前，不會就系爭不動產聲請拍賣抵押」，其\n    文義內容僅係被告張智維願擔保被告吳宛柔不致在系爭假執\n    行之本案訴訟判決確定前聲請拍賣系爭不動產，並未限制被\n    告張智維自行聲請拍賣系爭不動產之權利。且本院97年度移\n    調字第15號所有權移轉登記事件，乃係本院97年度重訴字第\n    32號所有權移轉登記等事件中所為移付調解之事件，該案當\n    事人原告為吳宛柔、林宏明、林宏程，被告為游秋華、鄭福\n    來、鄭志成、李素鳳等人，至本件被告張智維則非該案之當\n    事人，僅於該民事事件移付調解程序中，以參加人之身分參\n    與調解，此業據本院調閱上開民事卷宗核閱明確，並為兩造\n    當事人所不爭執。本件被告張智維既僅於前述調解程序中基\n    於參加人地位參加和解，自難認其除前述調解內容載明應負\n    之責任外，尚願負擔其他責任。是依前述調解約定之內容及\n    調解作成情況，並無從解釋被告張智維本人願負有不得在系\n    爭假執行程序之本案訴訟確定前聲請強制執行之義務。原告\n    謂：舉重以明輕，被告張智維不能於本案訴訟之判決確定前\n    聲請拍賣系爭不動產云云，要屬無據。從而，被告張智維本\n    件聲請假執行系爭不動產，既未違反前述調解內容，自無須\n    依前述調解內容負損害賠償責任。原告對於被告張智維既無\n    其所指違反調解約定所生之損害賠償債權存在，其主張以該\n    債權作為抵銷云云，即非有據。\n五、綜上所述，原告所為抵銷之抗辯並無足採，其依強制執行法\n    第41條第1項規定提起本件分配表異議之訴，請求將系爭分\n    配表中被告張智維、吳宛柔應受分配之債權額予以剔除，並\n    無理由，不應准許。\n六、本件事證已臻明確，兩造其餘攻擊防禦及未經援用之證據，\n    於判決結果不生影響，爰不另一一論述，併此敘明。\n七、據上論結，原告之訴為無理由，依民事訴訟法第78條，判決\n    如主文。"
  },
  "search": "臺灣宜蘭地方法院民事判決100年度訴更字第1號原告游秋華訴訟代理人林世超律師被告張智維被告吳宛柔共同訴訟代理人蔡坤鐘律師當事人間分配表異議之訴事件，本院於100年10月28日言詞辯論終結，判決如下：主文原告之訴駁回。訴訟費用由原告負擔。事實及理由一、本件原告主張：被告張智維及吳宛柔，分執本院97年度訴字第167號假執行判決為執行名義，聲請對原告所有坐落宜蘭縣羅東鎮○○段1360地號土地及其上門牌號碼宜蘭縣羅東鎮○○路123號7樓建物（下簡稱系爭不動產）為強制執行（本院民事執行處99年度司執字第1705號）及參與分配。經本院民事執行處拍定後，於民國97年6月23日作成分配表，被告張智維受有新臺幣（下同）1,624,395元之分配金額（包括次序4執行費21,882元、次序7普通債權1,472,787元、次序7利息129,726元），被告吳宛柔則受有219,216元之分配金額（包括次序5執行費1,600元、次序6第一順位抵押債權200,000元、次序6利息17,616元），並定於同年7月7日實行分配。惟兩造前於本院97年移調字第15號土地所有權移轉登記事件達成調解，調解筆錄第4項載明：「參加人張智維保證第三人吳宛柔就相對人（即本件原告游秋華）所有坐落宜蘭縣羅東鎮○○路123號7樓之房屋及坐落基地（即宜蘭縣羅東鎮○○段136地號及其上同段1963建號），設有價值360萬元之第一順位抵押權，於相對人應於97年6月9日（以法院收狀日為準）前，另對參加人張智維提起請求清償借款、傭金及代墊款項等給付訴訟之民事事件之訴訟期間至確定為止，第三人吳宛柔不會聲請拍賣前開抵押物（含聲請裁定及強制執行）。如第三人吳宛柔有前開行為，參加人同意對相對人因之所受之一切損害負賠償責任」等語。是依前揭調解內容，被告張智維尚且出面保證被告吳宛柔於原告對被告張智維提起請求清償借款、傭金及代墊款項等給付訴訟之民事事件（即系爭假執行之本案訴訟）確定前，不得拍賣該不動產，則舉重以明輕，被告張智維更不能於系爭假執行之本案訴訟判決確定前，聲請拍賣該不動產。被告張智維、吳宛柔違反前開調解內容約定，分別聲請強制拍賣原告之系爭不動產及參與分配，則依前揭調解筆錄約定，被告張智維須對原告所受一切損害負賠償責任。原告之系爭不動產在判決確定前，提前遭被告張智維聲請強制執行拍賣，並由第三人得標，拍賣金額為2,377,000元，上開損害既係由假執行所造成，原告自得主張以上開損害額來抵銷被告張智維、吳宛柔受分配之金額。經此抵銷，被告張智維、吳宛柔依前開分配表所受之分配金額，應予剔除。為此提起本件分配表異議之訴，聲明請求剔除被告張智維、吳宛柔自前述分配表所受之各該分配金額。二、被告則以：系爭假執行事件之本案訴訟，就原告本案訴訟之請求及主張，經本院判決駁回後，迭經臺灣高等法院、最高法院駁回原告上訴而告確定，甚至增加原告應給付被告張智維之款項，在法律上殊無准許原告在本件訴訟重為主張之理。是原告所提起本件訴訟，在法律上已屬顯無理由，而無權利保護之必要。又，兩造雖曾於本院97年度移調字第15號所有權移轉登記事件達成和解，並製有前揭內容之調解筆錄，但前述調解內容僅對被告吳宛柔聲請拍賣系爭不動產之時間作限制，而未限制被告張智維得自行聲請強制執行之權利。且被告張智維係因其另行取得對原告之執行名義而聲請就系爭不動產為強制執行，此與前揭調解內容所載被告張智維保證被告吳宛柔於訴訟確定前不得對原告聲請強制執行之約定，明顯不同，被告張智維自無違反調解筆錄之約定。且假執行係依判決而為之，並無不法侵害原告權利可言，被告自無須負損害賠償之責任，原告即不得以其對被告另有損害賠償債權主張抵銷等語，資為抗辯。並聲明求為駁回原告之訴。三、兩造不爭執事項：(一)被告張智維於99年2月4日執本院97年度訴字第167號假執行判決為執行名義，向本院民事執行處聲請就系爭不動產為假執行，於99年5月25日由訴外人侯蓉以2,377,000元得標買受，本院民事執行處於99年6月23日製作分配表，定於99年7月7日實行分配。(二)系爭假執行之本案訴訟，經本院97年度訴字第167號判決本件原告應給付被告張智維1,472,787元及遲延利息、應給付被告吳宛柔200,000元及遲延利息，兩造不服提起上訴，經臺灣高等法院就上開原告應給付部分駁回原告之上訴，並經最高法院裁定駁回上訴確定，而確認被告張智維、被告吳宛柔分別對原告具有1,472,787元、200,000元（即分別如系爭分配表次序7、次序6所示）之金錢債權存在。(三)兩造前於本院97年移調字第15號土地所有權移轉登記事件達成調解，調解內容記載：「參加人張智維保證第三人吳宛柔就相對人（即本件原告游秋華）所有坐落宜蘭縣羅東鎮○○路123號7樓之房屋及坐落基地（即宜蘭縣羅東鎮○○段136地號及其上同段1963建號），設有價值360萬元之第一順位抵押權，於相對人應於97年6月9日（以法院收狀日為準）前，另對參加人張智維提起請求清償借款、傭金及代墊款項等給付訴訟之民事事件之訴訟期間至確定為止，第三人吳宛柔不會聲請拍賣前開抵押物（含聲請裁定及強制執行）。如第三人吳宛柔有前開行為，參加人同意對相對人因之所受之一切損害負賠償責任」等語。四、經本院於言詞辯論期日使當事人整理並協議簡化爭點結果（見本院卷第108至109頁），兩造之爭點為：(一)原告提起本件訴訟是否有權利保護之必要？(二)被告張智維是否違反前開調解內容而負賠償責任，及原告得否主張抵銷？茲就前開爭點，說明本院心證如下：(一)原告提起本件訴訟是否無權利保護必要？系爭假執行程序經本院民事執行處於99年6月23日製作分配表之事實，為兩造所不爭執，已如前述。而依本院民事執行處所製作之分配表內容（見本院99年度訴字第205號卷第24頁），可知系爭不動產經法院拍賣且實施分配之結果，該不動產拍賣所得金額合計2,377,000元，扣除應受分配之相關稅捐（如分配表次序1至3所示）、執行費（如分配表次序4、5所示）、抵押權（如分配表次序6所示）、普通債權（如分配表次序7所示）等應受分配之債權金額後，尚有餘款435,013元可發還原告。而查，本件原告起訴主張被告違反前揭調解內容之約定而負損害賠償之責，並主張以之抵銷被告張智維、吳宛柔對於原告之債權，則倘原告所為前開抵銷之抗辯確屬有據，自足以影響被告張智維、吳宛柔於前開分配表上之債權金額，而進一步影響被告張智維、吳宛柔應受分配之金額；被告張智維、吳宛柔應受分配之金額倘經扣減或剔除，原告所受發還之餘款即可增加，足認原告提起本件訴訟，非無權利保護之必要。被告抗辯：系爭假執行之本案訴訟業已判決確定，被告張智維對原告確有系爭分配表所載之金錢借貸債權存在，其債權甚至超過系爭分配表所列之債權金額，故原告提起本件訴訟欠缺權利保護必要，不應准許云云，並不足採。(二)被告張智維是否違反前揭調解內容而負賠償責任，及原告得否主張抵銷？兩造前於本院97年移調字第15號土地所有權移轉登記事件達成調解，調解筆錄第4項載明：「參加人張智維保證第三人吳宛柔就相對人（即本件原告游秋華）所有坐落宜蘭縣羅東鎮○○路123號7樓之房屋及坐落基地（即宜蘭縣羅東鎮○○段136地號及其上同段1963建號），設有價值360萬元之第一順位抵押權，於相對人應於97年6月9日（以法院收狀日為準）前，另對參加人張智維提起請求清償借款、傭金及代墊款項等給付訴訟之民事事件之訴訟期間至確定為止，第三人吳宛柔不會聲請拍賣前開抵押物（含聲請裁定及強制執行）。如第三人吳宛柔有前開行為，參加人同意對相對人因之所受之一切損害負賠償責任」等語，此為兩造所不爭執，已見前述。原告雖稱：依前揭調解內容，被告張智維尚且出面保證被告吳宛柔於系爭假執行之本案訴訟判決確定前，不得拍賣系爭不動產，則舉重以明輕，被告張智維更不能於本案訴訟之判決確定前聲請拍賣系爭不動產云云。然查：調解筆錄第4項載明被告張智維係「保證被告吳宛柔於系爭假執行之本案訴訟判決確定前，不會就系爭不動產聲請拍賣抵押」，其文義內容僅係被告張智維願擔保被告吳宛柔不致在系爭假執行之本案訴訟判決確定前聲請拍賣系爭不動產，並未限制被告張智維自行聲請拍賣系爭不動產之權利。且本院97年度移調字第15號所有權移轉登記事件，乃係本院97年度重訴字第32號所有權移轉登記等事件中所為移付調解之事件，該案當事人原告為吳宛柔、林宏明、林宏程，被告為游秋華、鄭福來、鄭志成、李素鳳等人，至本件被告張智維則非該案之當事人，僅於該民事事件移付調解程序中，以參加人之身分參與調解，此業據本院調閱上開民事卷宗核閱明確，並為兩造當事人所不爭執。本件被告張智維既僅於前述調解程序中基於參加人地位參加和解，自難認其除前述調解內容載明應負之責任外，尚願負擔其他責任。是依前述調解約定之內容及調解作成情況，並無從解釋被告張智維本人願負有不得在系爭假執行程序之本案訴訟確定前聲請強制執行之義務。原告謂：舉重以明輕，被告張智維不能於本案訴訟之判決確定前聲請拍賣系爭不動產云云，要屬無據。從而，被告張智維本件聲請假執行系爭不動產，既未違反前述調解內容，自無須依前述調解內容負損害賠償責任。原告對於被告張智維既無其所指違反調解約定所生之損害賠償債權存在，其主張以該債權作為抵銷云云，即非有據。五、綜上所述，原告所為抵銷之抗辯並無足採，其依強制執行法第41條第1項規定提起本件分配表異議之訴，請求將系爭分配表中被告張智維、吳宛柔應受分配之債權額予以剔除，並無理由，不應准許。六、本件事證已臻明確，兩造其餘攻擊防禦及未經援用之證據，於判決結果不生影響，爰不另一一論述，併此敘明。七、據上論結，原告之訴為無理由，依民事訴訟法第78條，判決如主文。中華民國100年11月11日正本係照原本作成。如不服本判決，應於收受送達後20日內向本院提出上訴狀（應附繕本）。中華民國100年11月11日書記官吳文雄",
  "characters": {
    "judges": [

    ],
    "prosecutors": [

    ],
    "lawyers": [
      "林世超",
      "蔡坤鐘"
    ],
    "clerks": [

    ],
    "plaintiffs": [
      "游秋華"
    ],
    "defendants": [
      "張智維",
      "被      告  吳宛柔",
      "共      同"
    ],
    "prosecutor_office": [

    ],
    "creditors": [

    ],
    "debtors": [

    ],
    "judicial_associate_officer": [

    ]
  },
  "adjudged_at": "2011-11-11",
  "created_at": "2016-02-12 23:23:43",
  "updated_at": "2016-02-12 23:23:43"
}