{
  "identify": "PCD-100-易-3043-20111111-1",
  "court": {
    "name": "臺灣新北地方法院",
    "code": "PCD"
  },
  "division": {
    "name": "刑事",
    "code": "M"
  },
  "year": 100,
  "word": "易",
  "number": "3043",
  "jcheck": "1",
  "reason": "毀損等",
  "content": "臺灣板橋地方法院刑事判決             100年度易字第3043號\n聲  請  人  臺灣板橋地方法院檢察署檢察官\n被      告  陳詮濬\n上列被告因毀損等案件，經檢察官聲請以簡易判決處刑（100 年\n度偵字第6727號），本院認不得以簡易判決處刑，改依通常程序\n審理，判決如下：\n    主  文\n本件公訴不受理。\n    理  由\n一、聲請簡易判決處刑意旨略以：被告陳詮濬曾受張孝蓉委託，\n    就張孝蓉位於新北市○○區○○路96巷7 號3 樓住處進行室\n    內裝璜工程，雙方間產生工程款糾紛，陳詮濬因之夥同姓名\n    、年籍不詳之成年男子1 名，於民國100 年1 月24日上午某\n    時許，共同至上址欲向張孝蓉與其夫鄭清泉催討工程款，嗣\n    陳詮濬與該名男子到場後，先共同基於無故侵入住居之犯意\n    聯絡，於未得鄭清泉、張孝蓉同意或授權之情形下，由陳詮\n    濬持張孝蓉之姐張孝蘭（另為不起訴處分）所交付之上址大\n    樓鐵門鑰匙，開啟該處大樓鐵門，經由樓梯間至該處3 樓門\n    口按門鈴，適鄭清泉、張孝蓉外出而不在屋內，由渠等之子\n    鄭亦鈞開啟該屋內側鐵門，惟見陳詮濬並非渠等之親友，故\n    未開啟該屋之外側鐵門，陳詮濬因而心生不滿，竟自行基於\n    恐嚇危害安全之犯意，向鄭亦鈞恫稱：「…大人在不在…到\n    底在不在！叫大人快點出來！你們大人都不出來！叫小孩出\n    來應門！…再不開門我就要拆房子…再不開門我就要敲房子\n    …」等語，並指示該名男子，手持自備之大鐵鎚與鐵撬，敲\n    打該處門口外牆，致該處外牆有多處凹陷，鄭亦鈞因之心生\n    畏懼（所涉恐嚇危害安全罪嫌部分，由本院另案審理），隨\n    即撥打電話通知鄭清泉並報警處理，嗣員警到場後，陳詮濬\n    與該名男子始停手。因認被告涉有刑法第306 條第1 項之無\n    故侵入住居、第354 之毀損器物等罪嫌。\n二、按告訴乃論之罪，告訴人於第一審辯論終結前得撤回其告訴\n    ；又告訴乃論之罪，其告訴經撤回者，應諭知不受理之判決\n    ，並得不經言詞辯論為之；刑事訴訟法第238 條第1 項、第\n    303 條第3 款、第307 條分別定有明文。\n三、本件告訴人張孝蓉告訴被告陳詮濬侵入住居及毀損等案件，\n    聲請簡易判決處刑意旨認被告係觸犯刑法第306 條第1 項之\n    侵入住居及第354 條之毀損罪，依同法第308 條第1 項及第\n    357 條之規定，須告訴乃論。茲據告訴人張孝蓉具狀撤回其\n    告訴，有刑事撤回告訴狀1 紙在卷可稽，揆諸首開說明，爰\n    不經言詞辯論，諭知不受理之判決。\n四、據上論斷，應依刑事訴訟法第452 條、第303 條第3 款、第\n    307 條，判決如主文。\n中    華    民    國   100    年    11     月   11    日\n                刑事第二十三庭  審判長法  官  鄭水銓\n                                      法  官  薛嘉珩\n                                      法  官  周宛蘭\n上列正本證明與原本無異。\n如不服本判決，應於送達後10日內敘明上訴理由，向本院提出上\n訴狀，上訴於本院第二審合議庭 (應附繕本) 。其未敘述上訴理\n由者，應於上訴期間屆滿後20日內向本院補提理由書「切勿逕送\n上級法院」。\n                                      書記官  陳淑婷\n中    華    民    國   100    年    11    月    14    日",
  "structure": {
    "main": "本件公訴不受理。",
    "reason": "一、聲請簡易判決處刑意旨略以：被告陳詮濬曾受張孝蓉委託，\n    就張孝蓉位於新北市○○區○○路96巷7 號3 樓住處進行室\n    內裝璜工程，雙方間產生工程款糾紛，陳詮濬因之夥同姓名\n    、年籍不詳之成年男子1 名，於民國100 年1 月24日上午某\n    時許，共同至上址欲向張孝蓉與其夫鄭清泉催討工程款，嗣\n    陳詮濬與該名男子到場後，先共同基於無故侵入住居之犯意\n    聯絡，於未得鄭清泉、張孝蓉同意或授權之情形下，由陳詮\n    濬持張孝蓉之姐張孝蘭（另為不起訴處分）所交付之上址大\n    樓鐵門鑰匙，開啟該處大樓鐵門，經由樓梯間至該處3 樓門\n    口按門鈴，適鄭清泉、張孝蓉外出而不在屋內，由渠等之子\n    鄭亦鈞開啟該屋內側鐵門，惟見陳詮濬並非渠等之親友，故\n    未開啟該屋之外側鐵門，陳詮濬因而心生不滿，竟自行基於\n    恐嚇危害安全之犯意，向鄭亦鈞恫稱：「…大人在不在…到\n    底在不在！叫大人快點出來！你們大人都不出來！叫小孩出\n    來應門！…再不開門我就要拆房子…再不開門我就要敲房子\n    …」等語，並指示該名男子，手持自備之大鐵鎚與鐵撬，敲\n    打該處門口外牆，致該處外牆有多處凹陷，鄭亦鈞因之心生\n    畏懼（所涉恐嚇危害安全罪嫌部分，由本院另案審理），隨\n    即撥打電話通知鄭清泉並報警處理，嗣員警到場後，陳詮濬\n    與該名男子始停手。因認被告涉有刑法第306 條第1 項之無\n    故侵入住居、第354 之毀損器物等罪嫌。\n二、按告訴乃論之罪，告訴人於第一審辯論終結前得撤回其告訴\n    ；又告訴乃論之罪，其告訴經撤回者，應諭知不受理之判決\n    ，並得不經言詞辯論為之；刑事訴訟法第238 條第1 項、第\n    303 條第3 款、第307 條分別定有明文。\n三、本件告訴人張孝蓉告訴被告陳詮濬侵入住居及毀損等案件，\n    聲請簡易判決處刑意旨認被告係觸犯刑法第306 條第1 項之\n    侵入住居及第354 條之毀損罪，依同法第308 條第1 項及第\n    357 條之規定，須告訴乃論。茲據告訴人張孝蓉具狀撤回其\n    告訴，有刑事撤回告訴狀1 紙在卷可稽，揆諸首開說明，爰\n    不經言詞辯論，諭知不受理之判決。\n四、據上論斷，應依刑事訴訟法第452 條、第303 條第3 款、第\n    307 條，判決如主文。"
  },
  "search": "臺灣板橋地方法院刑事判決100年度易字第3043號聲請人臺灣板橋地方法院檢察署檢察官被告陳詮濬上列被告因毀損等案件，經檢察官聲請以簡易判決處刑（100年度偵字第6727號），本院認不得以簡易判決處刑，改依通常程序審理，判決如下：主文本件公訴不受理。理由一、聲請簡易判決處刑意旨略以：被告陳詮濬曾受張孝蓉委託，就張孝蓉位於新北市○○區○○路96巷7號3樓住處進行室內裝璜工程，雙方間產生工程款糾紛，陳詮濬因之夥同姓名、年籍不詳之成年男子1名，於民國100年1月24日上午某時許，共同至上址欲向張孝蓉與其夫鄭清泉催討工程款，嗣陳詮濬與該名男子到場後，先共同基於無故侵入住居之犯意聯絡，於未得鄭清泉、張孝蓉同意或授權之情形下，由陳詮濬持張孝蓉之姐張孝蘭（另為不起訴處分）所交付之上址大樓鐵門鑰匙，開啟該處大樓鐵門，經由樓梯間至該處3樓門口按門鈴，適鄭清泉、張孝蓉外出而不在屋內，由渠等之子鄭亦鈞開啟該屋內側鐵門，惟見陳詮濬並非渠等之親友，故未開啟該屋之外側鐵門，陳詮濬因而心生不滿，竟自行基於恐嚇危害安全之犯意，向鄭亦鈞恫稱：「…大人在不在…到底在不在！叫大人快點出來！你們大人都不出來！叫小孩出來應門！…再不開門我就要拆房子…再不開門我就要敲房子…」等語，並指示該名男子，手持自備之大鐵鎚與鐵撬，敲打該處門口外牆，致該處外牆有多處凹陷，鄭亦鈞因之心生畏懼（所涉恐嚇危害安全罪嫌部分，由本院另案審理），隨即撥打電話通知鄭清泉並報警處理，嗣員警到場後，陳詮濬與該名男子始停手。因認被告涉有刑法第306條第1項之無故侵入住居、第354之毀損器物等罪嫌。二、按告訴乃論之罪，告訴人於第一審辯論終結前得撤回其告訴；又告訴乃論之罪，其告訴經撤回者，應諭知不受理之判決，並得不經言詞辯論為之；刑事訴訟法第238條第1項、第303條第3款、第307條分別定有明文。三、本件告訴人張孝蓉告訴被告陳詮濬侵入住居及毀損等案件，聲請簡易判決處刑意旨認被告係觸犯刑法第306條第1項之侵入住居及第354條之毀損罪，依同法第308條第1項及第357條之規定，須告訴乃論。茲據告訴人張孝蓉具狀撤回其告訴，有刑事撤回告訴狀1紙在卷可稽，揆諸首開說明，爰不經言詞辯論，諭知不受理之判決。四、據上論斷，應依刑事訴訟法第452條、第303條第3款、第307條，判決如主文。中華民國100年11月11日刑事第二十三庭審判長法官鄭水銓法官薛嘉珩法官周宛蘭上列正本證明與原本無異。如不服本判決，應於送達後10日內敘明上訴理由，向本院提出上訴狀，上訴於本院第二審合議庭(應附繕本)。其未敘述上訴理由者，應於上訴期間屆滿後20日內向本院補提理由書「切勿逕送上級法院」。書記官陳淑婷中華民國100年11月14日",
  "characters": {
    "judges": [
      "鄭水銓",
      "薛嘉珩",
      "周宛蘭"
    ],
    "prosecutors": [

    ],
    "lawyers": [

    ],
    "clerks": [
      "陳淑婷"
    ],
    "plaintiffs": [

    ],
    "defendants": [
      "陳詮濬"
    ],
    "prosecutor_office": [
      "臺灣板橋地方法院檢察署檢察官"
    ],
    "creditors": [

    ],
    "debtors": [

    ],
    "judicial_associate_officer": [

    ]
  },
  "adjudged_at": "2011-11-11",
  "created_at": "2016-02-12 23:31:59",
  "updated_at": "2016-02-12 23:31:59"
}