{
  "identify": "KSD-91-聲-484-20020319-1",
  "court": {
    "name": "臺灣高雄地方法院",
    "code": "KSD"
  },
  "division": {
    "name": "刑事",
    "code": "M"
  },
  "year": 91,
  "word": "聲",
  "number": "484",
  "jcheck": "1",
  "reason": "聲請單獨宣告沒收違禁物",
  "content": "臺灣高雄地方法院刑事裁定                          九十一年度聲字第四八四號\n    聲  請  人  臺灣高雄地方法院檢察署檢察官\n    被      告  甲○○\n右聲請人因毒品危害防制條例案件，聲請單獨宣告沒收違禁物（九十一年度聲沒字第\n一六七號），本院裁定如左：\n    主  文\n第二級毒品安非他命壹包（驗前毛重零點陸公克，驗後毛重零點伍公克）沒收銷燬之\n。\n    理  由\n一、按違禁物得單獨宣告沒收，刑法第四十條但書定有明文。次按查獲之毒品及專供\n    製造或施用毒品之器具，不問屬於犯人與否，均沒收銷燬之，毒品危害防制條例\n    第十八條第一項前段分別定有明文。\n二、本件聲請意旨略以：高雄市政府警察局及其前鎮分局移送經扣案之第二級毒品安\n    非他命壹包（驗前毛重零點陸公克，驗後毛重零點伍公克），係毒品，依毒品危\n    害防制條例第十八條第一項前段之規定，係屬違禁物，爰請依法宣告沒收等情。\n    經查，聲請人前因承辦八十八年度毒偵字第二三四九號、九十年度毒偵字第六八\n    號被告甲○○違反毒品危害防制條例案件，就高雄市政府警察局及其前鎮移送扣\n    案之前開毒品，因被告甲○○經本院裁定送觀察勒戒後，認有繼續施用毒品之傾\n    向，並經裁定送戒治處所強制戒治一年，戒治期滿，而為不起訴處分後（九十一\n    年度戒毒偵字第二二號），扣案之第二級毒品安非他命壹包（驗前毛重零點陸公\n    克，驗後毛重零點伍公克）係毒品，依毒品危害防制條例第十八條第一項前段之\n    規定屬違禁物等情，有高雄醫學大學附設中和紀念醫院九十一年二月十三日編號\n    九一○二─七號檢驗報告單一紙在卷可佐，本院認其聲請為正當，爰依刑事訴訟\n    法第二百二十條、毒品危害防制條例第十八條第一項前段、刑法第四十條但書規\n    定，裁定如主文。\n中      華      民      國      九十一      年      三    月    十九    日\n                            臺灣高雄地方法院刑事庭\n                                法  官  涂裕洪\n右正本証明與原本無異\n如不服本裁定應於送達後五日內向本院提出抗告狀。\n                                書記官  賴佳慧\n中      華      民      國      九十一      年      三    月    十九    日\n",
  "structure": {
    "main": "第二級毒品安非他命壹包（驗前毛重零點陸公克，驗後毛重零點伍公克）沒收銷燬之\n。",
    "reason": "一、按違禁物得單獨宣告沒收，刑法第四十條但書定有明文。次按查獲之毒品及專供\n    製造或施用毒品之器具，不問屬於犯人與否，均沒收銷燬之，毒品危害防制條例\n    第十八條第一項前段分別定有明文。\n二、本件聲請意旨略以：高雄市政府警察局及其前鎮分局移送經扣案之第二級毒品安\n    非他命壹包（驗前毛重零點陸公克，驗後毛重零點伍公克），係毒品，依毒品危\n    害防制條例第十八條第一項前段之規定，係屬違禁物，爰請依法宣告沒收等情。\n    經查，聲請人前因承辦八十八年度毒偵字第二三四九號、九十年度毒偵字第六八\n    號被告甲○○違反毒品危害防制條例案件，就高雄市政府警察局及其前鎮移送扣\n    案之前開毒品，因被告甲○○經本院裁定送觀察勒戒後，認有繼續施用毒品之傾\n    向，並經裁定送戒治處所強制戒治一年，戒治期滿，而為不起訴處分後（九十一\n    年度戒毒偵字第二二號），扣案之第二級毒品安非他命壹包（驗前毛重零點陸公\n    克，驗後毛重零點伍公克）係毒品，依毒品危害防制條例第十八條第一項前段之\n    規定屬違禁物等情，有高雄醫學大學附設中和紀念醫院九十一年二月十三日編號\n    九一○二─七號檢驗報告單一紙在卷可佐，本院認其聲請為正當，爰依刑事訴訟\n    法第二百二十條、毒品危害防制條例第十八條第一項前段、刑法第四十條但書規\n    定，裁定如主文。"
  },
  "search": "臺灣高雄地方法院刑事裁定九十一年度聲字第四八四號聲請人臺灣高雄地方法院檢察署檢察官被告甲○○右聲請人因毒品危害防制條例案件，聲請單獨宣告沒收違禁物（九十一年度聲沒字第一六七號），本院裁定如左：主文第二級毒品安非他命壹包（驗前毛重零點陸公克，驗後毛重零點伍公克）沒收銷燬之。理由一、按違禁物得單獨宣告沒收，刑法第四十條但書定有明文。次按查獲之毒品及專供製造或施用毒品之器具，不問屬於犯人與否，均沒收銷燬之，毒品危害防制條例第十八條第一項前段分別定有明文。二、本件聲請意旨略以：高雄市政府警察局及其前鎮分局移送經扣案之第二級毒品安非他命壹包（驗前毛重零點陸公克，驗後毛重零點伍公克），係毒品，依毒品危害防制條例第十八條第一項前段之規定，係屬違禁物，爰請依法宣告沒收等情。經查，聲請人前因承辦八十八年度毒偵字第二三四九號、九十年度毒偵字第六八號被告甲○○違反毒品危害防制條例案件，就高雄市政府警察局及其前鎮移送扣案之前開毒品，因被告甲○○經本院裁定送觀察勒戒後，認有繼續施用毒品之傾向，並經裁定送戒治處所強制戒治一年，戒治期滿，而為不起訴處分後（九十一年度戒毒偵字第二二號），扣案之第二級毒品安非他命壹包（驗前毛重零點陸公克，驗後毛重零點伍公克）係毒品，依毒品危害防制條例第十八條第一項前段之規定屬違禁物等情，有高雄醫學大學附設中和紀念醫院九十一年二月十三日編號九一○二─七號檢驗報告單一紙在卷可佐，本院認其聲請為正當，爰依刑事訴訟法第二百二十條、毒品危害防制條例第十八條第一項前段、刑法第四十條但書規定，裁定如主文。中華民國九十一年三月十九日臺灣高雄地方法院刑事庭法官涂裕洪右正本証明與原本無異如不服本裁定應於送達後五日內向本院提出抗告狀。書記官賴佳慧中華民國九十一年三月十九日",
  "characters": {
    "judges": [
      "涂裕洪"
    ],
    "prosecutors": [

    ],
    "lawyers": [

    ],
    "clerks": [
      "賴佳慧"
    ],
    "plaintiffs": [

    ],
    "defendants": [
      "甲○○",
      "右聲請人因毒品危害防制條例案件，聲請單獨宣告沒收違禁物（九十一年度聲沒字第",
      "一六七號），本院裁定如左："
    ],
    "prosecutor_office": [
      "臺灣高雄地方法院檢察署檢察官"
    ],
    "creditors": [

    ],
    "debtors": [

    ],
    "judicial_associate_officer": [

    ]
  },
  "adjudged_at": "2002-03-19",
  "created_at": "2016-02-05 08:02:49",
  "updated_at": "2016-02-05 08:02:49"
}