{
  "identify": "KSH-91-附民-34-20020318-1",
  "court": {
    "name": "臺灣高等法院",
    "code": "KSH"
  },
  "division": {
    "name": "刑事",
    "code": "M"
  },
  "year": 91,
  "word": "附民",
  "number": "34",
  "jcheck": "1",
  "reason": "偽造文書等",
  "content": "臺灣高等法院高雄分院刑事附帶民事訴訟判決       九十一年度附民字第三四號\n    原      告  乙○○\n    被      告  甲○○\n右列被告因偽造文書等案件（本院九十年度上訴字第一八一三號），原告提起附帶民\n事訴訟，請求損害賠償，本院判決如左：\n    主  文\n原告之訴及假執行之聲請均駁回。\n    事  實\n一、原告聲明求為判決，被告應賠償原告新台幣（下同）一百四十五萬四千元，及自\n    起訴狀繕本送達被告之翌日起，至清償日止，按年息百分之五計算之利息。並願\n    供擔保，聲請宣告假執行。其事實上陳述略稱，被告與其母確有共同冒標會款之\n    事實，爰求為判決如訴之聲明；並援用刑事訴訟之證據。\n二、被告未提出書狀，亦未作何陳述，惟依其在刑事訴訟之陳述，不承認有何冒標會\n    款之侵權行為。\n    理  由\n一、按刑事訴訟諭知無罪、免訴或不受理之判決者，應以判決駁回原告之訴，刑事訴\n    訟法第五百零三條第一項前段定有明文。\n二、本件被告被訴偽造文書等案件，業經臺灣高雄地方法院諭知無罪，原告即自訴人\n    不服原判決提起上訴後，亦經本院判決上訴駁回在案。依照首開規定，自應駁回\n 原告附帶提起之民事訴訟，其假執行之聲請因亦無所依附，應併予駁回。\n三、據上論斷，應依刑事訴訟法第五百零三條第一項前段，判決如主文。\n中    華    民    國     九十一     年       三       月     十八   日\n                              臺灣高等法院高雄分院刑事第六庭\n                                  審判長法官  王憲義\n                                        法官  謝靜雯\n                                        法官  張意聰\n右正本證明與原本無異。\n如不服本判決應於收受本判決後十日內向本院提出上訴書狀，其未述上訴理由者，\n並得於提起上訴後十日內向本院補提理由書狀（均須按他造當事人之人數附繕本)「\n切勿逕送上級法院」。\n                                      書記官  王婉蓉\n中    華    民    國     九十一     年       三       月     二十   日\n                                                                 Ｊ\n",
  "structure": {
    "main": "原告之訴及假執行之聲請均駁回。",
    "fact": "一、原告聲明求為判決，被告應賠償原告新台幣（下同）一百四十五萬四千元，及自\n    起訴狀繕本送達被告之翌日起，至清償日止，按年息百分之五計算之利息。並願\n    供擔保，聲請宣告假執行。其事實上陳述略稱，被告與其母確有共同冒標會款之\n    事實，爰求為判決如訴之聲明；並援用刑事訴訟之證據。\n二、被告未提出書狀，亦未作何陳述，惟依其在刑事訴訟之陳述，不承認有何冒標會\n    款之侵權行為。",
    "reason": "一、按刑事訴訟諭知無罪、免訴或不受理之判決者，應以判決駁回原告之訴，刑事訴\n    訟法第五百零三條第一項前段定有明文。\n二、本件被告被訴偽造文書等案件，業經臺灣高雄地方法院諭知無罪，原告即自訴人\n    不服原判決提起上訴後，亦經本院判決上訴駁回在案。依照首開規定，自應駁回\n 原告附帶提起之民事訴訟，其假執行之聲請因亦無所依附，應併予駁回。\n三、據上論斷，應依刑事訴訟法第五百零三條第一項前段，判決如主文。\n中    華    民    國     九十一     年       三       月     十八   日\n                              臺灣高等法院高雄分院刑事第六庭\n                                  審判長法官  王憲義\n                                        法官  謝靜雯\n                                        法官  張意聰\n右正本證明與原本無異。\n如不服本判決應於收受本判決後十日內向本院提出上訴書狀，其未述上訴理由者，\n並得於提起上訴後十日內向本院補提理由書狀（均須按他造當事人之人數附繕本)「\n切勿逕送上級法院」。\n                                      書記官  王婉蓉"
  },
  "search": "臺灣高等法院高雄分院刑事附帶民事訴訟判決九十一年度附民字第三四號原告乙○○被告甲○○右列被告因偽造文書等案件（本院九十年度上訴字第一八一三號），原告提起附帶民事訴訟，請求損害賠償，本院判決如左：主文原告之訴及假執行之聲請均駁回。事實一、原告聲明求為判決，被告應賠償原告新台幣（下同）一百四十五萬四千元，及自起訴狀繕本送達被告之翌日起，至清償日止，按年息百分之五計算之利息。並願供擔保，聲請宣告假執行。其事實上陳述略稱，被告與其母確有共同冒標會款之事實，爰求為判決如訴之聲明；並援用刑事訴訟之證據。二、被告未提出書狀，亦未作何陳述，惟依其在刑事訴訟之陳述，不承認有何冒標會款之侵權行為。理由一、按刑事訴訟諭知無罪、免訴或不受理之判決者，應以判決駁回原告之訴，刑事訴訟法第五百零三條第一項前段定有明文。二、本件被告被訴偽造文書等案件，業經臺灣高雄地方法院諭知無罪，原告即自訴人不服原判決提起上訴後，亦經本院判決上訴駁回在案。依照首開規定，自應駁回原告附帶提起之民事訴訟，其假執行之聲請因亦無所依附，應併予駁回。三、據上論斷，應依刑事訴訟法第五百零三條第一項前段，判決如主文。中華民國九十一年三月十八日臺灣高等法院高雄分院刑事第六庭審判長法官王憲義法官謝靜雯法官張意聰右正本證明與原本無異。如不服本判決應於收受本判決後十日內向本院提出上訴書狀，其未述上訴理由者，並得於提起上訴後十日內向本院補提理由書狀（均須按他造當事人之人數附繕本)「切勿逕送上級法院」。書記官王婉蓉中華民國九十一年三月二十日Ｊ",
  "characters": {
    "judges": [

    ],
    "prosecutors": [

    ],
    "lawyers": [

    ],
    "clerks": [
      "王婉蓉"
    ],
    "plaintiffs": [
      "乙"
    ],
    "defendants": [
      "甲○○",
      "右列被告因偽造文書等案件（本院九十年度上訴字第一八一三號），原告提起附帶民",
      "事訴訟，請求損害賠償，本院判決如左："
    ],
    "prosecutor_office": [

    ],
    "creditors": [

    ],
    "debtors": [

    ],
    "judicial_associate_officer": [

    ]
  },
  "adjudged_at": "2002-03-18",
  "created_at": "2016-02-05 07:58:44",
  "updated_at": "2016-02-05 07:58:44"
}