{
  "identify": "KLD-94-訴-58-20050223-1",
  "court": {
    "name": "臺灣基隆地方法院",
    "code": "KLD"
  },
  "division": {
    "name": "刑事",
    "code": "M"
  },
  "year": 94,
  "word": "訴",
  "number": "58",
  "jcheck": "1",
  "reason": "毒品危害防制條例",
  "content": "臺灣基隆地方法院刑事裁定                94年度訴字第58號\n公  訴  人  臺灣基隆地方法院檢察署檢察官\n具  保  人  乙○○\n            甲○○\n被      告  丙○○  男  39歲.\n上列具保人因被告違反毒品危害防制條例案件，本院裁定如下：\n    主  文\n乙○○、甲○○繳納之保證金各新臺幣壹萬元，均沒入之。\n    理  由\n一、被告丙○○因違反毒品危害防制條例案件，前經臺灣基隆地\n    方法院檢察署檢察官分別於93年12月14日及12月22日各指定\n    保證金額新臺幣壹萬元（93年度毒偵字第2502號及94年度毒\n    偵字第45號），由具保人乙○○、甲○○繳納上開保證金後\n    ，已許可具保將被告釋放。\n二、茲該被告經合法傳喚，而無正當理由未到場，復經拘提未獲\n    ，顯已逃匿，自應將原繳納上開保證金沒入。\n三、依刑事訴訟法第118 條、第121條第1項，裁定如主文。\n中    華    民    國    94    年    2     月    23    日\n                  刑事第二庭審判長法  官  王福康\n                                  法  官  徐世禎\n                                  法  官  齊  潔\n以上正本證明與原本無異。\n對於本件裁定如有不服，應於送達後5日內， 向本院提出抗告書\n狀，敘述抗告之理由，抗告於臺灣高等法院。\n中    華    民    國    94    年    2     月    23    日\n                                  書記官  莊國南\n",
  "structure": {
    "main": "乙○○、甲○○繳納之保證金各新臺幣壹萬元，均沒入之。",
    "reason": "一、被告丙○○因違反毒品危害防制條例案件，前經臺灣基隆地\n    方法院檢察署檢察官分別於93年12月14日及12月22日各指定\n    保證金額新臺幣壹萬元（93年度毒偵字第2502號及94年度毒\n    偵字第45號），由具保人乙○○、甲○○繳納上開保證金後\n    ，已許可具保將被告釋放。\n二、茲該被告經合法傳喚，而無正當理由未到場，復經拘提未獲\n    ，顯已逃匿，自應將原繳納上開保證金沒入。\n三、依刑事訴訟法第118 條、第121條第1項，裁定如主文。"
  },
  "search": "臺灣基隆地方法院刑事裁定94年度訴字第58號公訴人臺灣基隆地方法院檢察署檢察官具保人乙○○甲○○被告丙○○男39歲.上列具保人因被告違反毒品危害防制條例案件，本院裁定如下：主文乙○○、甲○○繳納之保證金各新臺幣壹萬元，均沒入之。理由一、被告丙○○因違反毒品危害防制條例案件，前經臺灣基隆地方法院檢察署檢察官分別於93年12月14日及12月22日各指定保證金額新臺幣壹萬元（93年度毒偵字第2502號及94年度毒偵字第45號），由具保人乙○○、甲○○繳納上開保證金後，已許可具保將被告釋放。二、茲該被告經合法傳喚，而無正當理由未到場，復經拘提未獲，顯已逃匿，自應將原繳納上開保證金沒入。三、依刑事訴訟法第118條、第121條第1項，裁定如主文。中華民國94年2月23日刑事第二庭審判長法官王福康法官徐世禎法官齊潔以上正本證明與原本無異。對於本件裁定如有不服，應於送達後5日內，向本院提出抗告書狀，敘述抗告之理由，抗告於臺灣高等法院。中華民國94年2月23日書記官莊國南",
  "characters": {
    "judges": [
      "王福康",
      "徐世禎",
      "齊潔"
    ],
    "prosecutors": [

    ],
    "lawyers": [

    ],
    "clerks": [
      "莊國南"
    ],
    "plaintiffs": [

    ],
    "defendants": [
      "丙○○  男  39歲."
    ],
    "prosecutor_office": [
      "臺灣基隆地方法院檢察署檢察官"
    ],
    "creditors": [

    ],
    "debtors": [

    ],
    "judicial_associate_officer": [

    ]
  },
  "adjudged_at": "2005-02-23",
  "created_at": "2016-02-06 17:29:11",
  "updated_at": "2016-02-06 17:29:11"
}