{
  "identify": "CYD-99-重訴-93-20110105-1",
  "court": {
    "name": "臺灣嘉義地方法院",
    "code": "CYD"
  },
  "division": {
    "name": "民事",
    "code": "V"
  },
  "year": 99,
  "word": "重訴",
  "number": "93",
  "jcheck": "1",
  "reason": "異議之訴",
  "content": "臺灣嘉義地方法院民事裁定  99年度重訴字第93號\n原      告  蘇耿賦\n訴訟代理人  羅振宏律師\n被      告  臺灣中小企業銀行股份有限公司\n法定代理人  羅澤成\n被      告  台南縣善化鎮農會\n訴訟代理人  莊美貴律師\n法定代理人  蘇堂校\n被      告  荷商柯企資產管理股份有限公司台灣分公司\n法定代理人  楚柯西\n上列當事人間異議之訴事件，本院裁定如下：\n    主  文\n本件移送臺灣臺南地方法院。\n    理  由\n一、按訴訟之全部或一部，法院認為無管轄權者，依原告聲請或\n    依職權以裁定移送其管轄法院，民事訴訟法第28條第1項定\n    有明文。又按所謂專屬管轄，係指法律規定某類事件專屬一\n    定法院管轄之謂。凡法律規定某類事件僅得由一定法院管轄\n    者，縱未以法文明定「專屬管轄」字樣，仍不失其專屬管轄\n    之性質。又執行名義成立後，如有消滅或妨礙債權人請求之\n    事由發生，債務人得於強制執行程序終結前，向執行法院對\n    債權人提起異議之訴，強制執行法第14條第1項前段定有明\n    文。是以提起債務人異議之訴，應向執行法院為之，顯已由\n    該法明定此類事件應由執行法院管轄，性質上自屬專屬管轄\n    （最高法院98年度台抗字第38號裁定參照）。再強制執行法\n    第7條第4項規定之受囑託法院，解釋上縱亦得認係同法第14\n    條第1項規定之執行法院，惟債務人異議之繫屬時受囑託法\n    院執行程序業已終結者，因已終結之執行程序已無從撤銷，\n    囑託法院尚未終結之執行程序則非受託法院所得管轄之範圍\n    ，自應認受囑託法院於此情形並無管轄權，此時之「執行法\n    院」應專指囑託法院，受囑託法院則不與之。\n二、經查，本院98年度司執字第10891號強制執行事件，係受臺\n    灣臺南地方法院（下稱臺南地院）囑託執行，執行標的為原\n    告於本院轄區內之對第三人之薪資債權，惟上開執行標的之\n    原告薪資債權，業經本院民事執行處於民國99年5月5日核發\n    移轉命令，請第三人國立嘉義大學將扣得之薪資在新臺幣（\n    下同）20,225,900元之範圍內移轉於被告臺灣中小企業銀行\n    股份有限公司等情，業經原告提出本院執行命令在卷可佐。\n    是原告於99年12月15日提起本訴時，本院受託執行程序早已\n    終結，亦已無兩造尚在繫屬中之執行事件，依前揭說明，應\n    以囑託法院即臺南地院為執行法院，並專屬臺南地院管轄。\n    玆原告向無管轄權之本院起訴，顯係違誤，爰依職權裁定移\n    送管轄之臺南地院。\n三、依首開法條裁定如主文。\n中    華    民    國   100    年    1     月    5     日\n                  民事第二庭    法  官  黃仁勇\n以上正本係照原本作成。\n如對本裁定抗告須於裁定送達後10日內向本院提出抗告狀，並繳\n納抗告費新臺幣1,000元。\n中    華    民    國   100    年    1     月    5     日\n                                書記官  黃意雯",
  "structure": {
    "main": "本件移送臺灣臺南地方法院。",
    "reason": "一、按訴訟之全部或一部，法院認為無管轄權者，依原告聲請或\n    依職權以裁定移送其管轄法院，民事訴訟法第28條第1項定\n    有明文。又按所謂專屬管轄，係指法律規定某類事件專屬一\n    定法院管轄之謂。凡法律規定某類事件僅得由一定法院管轄\n    者，縱未以法文明定「專屬管轄」字樣，仍不失其專屬管轄\n    之性質。又執行名義成立後，如有消滅或妨礙債權人請求之\n    事由發生，債務人得於強制執行程序終結前，向執行法院對\n    債權人提起異議之訴，強制執行法第14條第1項前段定有明\n    文。是以提起債務人異議之訴，應向執行法院為之，顯已由\n    該法明定此類事件應由執行法院管轄，性質上自屬專屬管轄\n    （最高法院98年度台抗字第38號裁定參照）。再強制執行法\n    第7條第4項規定之受囑託法院，解釋上縱亦得認係同法第14\n    條第1項規定之執行法院，惟債務人異議之繫屬時受囑託法\n    院執行程序業已終結者，因已終結之執行程序已無從撤銷，\n    囑託法院尚未終結之執行程序則非受託法院所得管轄之範圍\n    ，自應認受囑託法院於此情形並無管轄權，此時之「執行法\n    院」應專指囑託法院，受囑託法院則不與之。\n二、經查，本院98年度司執字第10891號強制執行事件，係受臺\n    灣臺南地方法院（下稱臺南地院）囑託執行，執行標的為原\n    告於本院轄區內之對第三人之薪資債權，惟上開執行標的之\n    原告薪資債權，業經本院民事執行處於民國99年5月5日核發\n    移轉命令，請第三人國立嘉義大學將扣得之薪資在新臺幣（\n    下同）20,225,900元之範圍內移轉於被告臺灣中小企業銀行\n    股份有限公司等情，業經原告提出本院執行命令在卷可佐。\n    是原告於99年12月15日提起本訴時，本院受託執行程序早已\n    終結，亦已無兩造尚在繫屬中之執行事件，依前揭說明，應\n    以囑託法院即臺南地院為執行法院，並專屬臺南地院管轄。\n    玆原告向無管轄權之本院起訴，顯係違誤，爰依職權裁定移\n    送管轄之臺南地院。\n三、依首開法條裁定如主文。"
  },
  "search": "臺灣嘉義地方法院民事裁定99年度重訴字第93號原告蘇耿賦訴訟代理人羅振宏律師被告臺灣中小企業銀行股份有限公司法定代理人羅澤成被告台南縣善化鎮農會訴訟代理人莊美貴律師法定代理人蘇堂校被告荷商柯企資產管理股份有限公司台灣分公司法定代理人楚柯西上列當事人間異議之訴事件，本院裁定如下：主文本件移送臺灣臺南地方法院。理由一、按訴訟之全部或一部，法院認為無管轄權者，依原告聲請或依職權以裁定移送其管轄法院，民事訴訟法第28條第1項定有明文。又按所謂專屬管轄，係指法律規定某類事件專屬一定法院管轄之謂。凡法律規定某類事件僅得由一定法院管轄者，縱未以法文明定「專屬管轄」字樣，仍不失其專屬管轄之性質。又執行名義成立後，如有消滅或妨礙債權人請求之事由發生，債務人得於強制執行程序終結前，向執行法院對債權人提起異議之訴，強制執行法第14條第1項前段定有明文。是以提起債務人異議之訴，應向執行法院為之，顯已由該法明定此類事件應由執行法院管轄，性質上自屬專屬管轄（最高法院98年度台抗字第38號裁定參照）。再強制執行法第7條第4項規定之受囑託法院，解釋上縱亦得認係同法第14條第1項規定之執行法院，惟債務人異議之繫屬時受囑託法院執行程序業已終結者，因已終結之執行程序已無從撤銷，囑託法院尚未終結之執行程序則非受託法院所得管轄之範圍，自應認受囑託法院於此情形並無管轄權，此時之「執行法院」應專指囑託法院，受囑託法院則不與之。二、經查，本院98年度司執字第10891號強制執行事件，係受臺灣臺南地方法院（下稱臺南地院）囑託執行，執行標的為原告於本院轄區內之對第三人之薪資債權，惟上開執行標的之原告薪資債權，業經本院民事執行處於民國99年5月5日核發移轉命令，請第三人國立嘉義大學將扣得之薪資在新臺幣（下同）20,225,900元之範圍內移轉於被告臺灣中小企業銀行股份有限公司等情，業經原告提出本院執行命令在卷可佐。是原告於99年12月15日提起本訴時，本院受託執行程序早已終結，亦已無兩造尚在繫屬中之執行事件，依前揭說明，應以囑託法院即臺南地院為執行法院，並專屬臺南地院管轄。玆原告向無管轄權之本院起訴，顯係違誤，爰依職權裁定移送管轄之臺南地院。三、依首開法條裁定如主文。中華民國100年1月5日民事第二庭法官黃仁勇以上正本係照原本作成。如對本裁定抗告須於裁定送達後10日內向本院提出抗告狀，並繳納抗告費新臺幣1,000元。中華民國100年1月5日書記官黃意雯",
  "characters": {
    "judges": [
      "黃仁勇"
    ],
    "prosecutors": [

    ],
    "lawyers": [
      "羅振宏",
      "莊美貴"
    ],
    "clerks": [

    ],
    "plaintiffs": [
      "蘇耿賦"
    ],
    "defendants": [
      "臺灣中小企業銀行股份有限公司",
      "台南縣善化鎮農會",
      "荷商柯企資產管理股份有限公司台灣分公司"
    ],
    "prosecutor_office": [

    ],
    "creditors": [

    ],
    "debtors": [

    ],
    "judicial_associate_officer": [

    ]
  },
  "adjudged_at": "2011-01-05",
  "created_at": "2016-02-13 04:32:02",
  "updated_at": "2016-02-13 04:32:02"
}