{
  "identify": "TCH-100-聲-886-20110512-1",
  "court": {
    "name": "臺灣高等法院",
    "code": "TCH"
  },
  "division": {
    "name": "刑事",
    "code": "M"
  },
  "year": 100,
  "word": "聲",
  "number": "886",
  "jcheck": "1",
  "reason": "聲請假釋中付保護管束",
  "content": "臺灣高等法院臺中分院刑事裁定          100年度聲字第886號\n聲  請  人  臺灣高等法院臺中分院檢察署檢察官\n受  刑  人  蔡耀輝\n上列受刑人因強盜等案件，聲請人聲請付保護管束（100年度執\n聲付字第120號），本院裁定如下：\n    主    文\n蔡耀輝假釋中付保護管束。\n    理    由\n聲請意旨略稱：受刑人蔡耀輝前犯強盜等罪，經法院判處有期徒\n刑12年1月確定後，移送執行。 茲聲請人以受刑人業經法務部於\n民國100年5月4日以法授矯字第1000108477號函核准假釋， 而縮\n刑後刑期終結日為民國104年1月9日， 聲請於其假釋中付保護管\n束等情。本院審核有關文件，認聲請為正當。爰依刑事訴訟法第\n481 條第1項、刑法第93條第2項、第96條但書，裁定如主文。\n中    華    民    國   100    年    5     月    12    日\n                刑事第八庭    審判長法  官  羅得村\n                                    法  官  劉榮服\n                                    法  官  簡源希\n上列正本證明與原本無異。\n如不服本裁定，得於收受送達後五日內向本院提出抗告書狀（須\n附繕本）。\n                                    書記官  顏子良\n中    華    民    國   100    年    5     月    12    日",
  "structure": {
    "main": "蔡耀輝假釋中付保護管束。",
    "reason": "聲請意旨略稱：受刑人蔡耀輝前犯強盜等罪，經法院判處有期徒\n刑12年1月確定後，移送執行。 茲聲請人以受刑人業經法務部於\n民國100年5月4日以法授矯字第1000108477號函核准假釋， 而縮\n刑後刑期終結日為民國104年1月9日， 聲請於其假釋中付保護管\n束等情。本院審核有關文件，認聲請為正當。爰依刑事訴訟法第\n481 條第1項、刑法第93條第2項、第96條但書，裁定如主文。"
  },
  "search": "臺灣高等法院臺中分院刑事裁定100年度聲字第886號聲請人臺灣高等法院臺中分院檢察署檢察官受刑人蔡耀輝上列受刑人因強盜等案件，聲請人聲請付保護管束（100年度執聲付字第120號），本院裁定如下：主文蔡耀輝假釋中付保護管束。理由聲請意旨略稱：受刑人蔡耀輝前犯強盜等罪，經法院判處有期徒刑12年1月確定後，移送執行。茲聲請人以受刑人業經法務部於民國100年5月4日以法授矯字第1000108477號函核准假釋，而縮刑後刑期終結日為民國104年1月9日，聲請於其假釋中付保護管束等情。本院審核有關文件，認聲請為正當。爰依刑事訴訟法第481條第1項、刑法第93條第2項、第96條但書，裁定如主文。中華民國100年5月12日刑事第八庭審判長法官羅得村法官劉榮服法官簡源希上列正本證明與原本無異。如不服本裁定，得於收受送達後五日內向本院提出抗告書狀（須附繕本）。書記官顏子良中華民國100年5月12日",
  "characters": {
    "judges": [
      "羅得村",
      "劉榮服",
      "簡源希"
    ],
    "prosecutors": [

    ],
    "lawyers": [

    ],
    "clerks": [
      "顏子良"
    ],
    "plaintiffs": [

    ],
    "defendants": [

    ],
    "prosecutor_office": [
      "臺灣高等法院臺中分院檢察署檢察官"
    ],
    "creditors": [

    ],
    "debtors": [

    ],
    "judicial_associate_officer": [

    ]
  },
  "adjudged_at": "2011-05-12",
  "created_at": "2016-02-12 00:42:00",
  "updated_at": "2016-02-12 00:42:00"
}