{
  "identify": "KSD-100-交簡-934-20110302-1",
  "court": {
    "name": "臺灣高雄地方法院",
    "code": "KSD"
  },
  "division": {
    "name": "刑事",
    "code": "M"
  },
  "year": 100,
  "word": "交簡",
  "number": "934",
  "jcheck": "1",
  "reason": "公共危險",
  "content": "臺灣高雄地方法院刑事簡易判決        100年度交簡字第934號\n聲  請  人  臺灣高雄地方法院檢察署檢察官\n被      告  蔡進壽\n上列被告因公共危險案件，經檢察官聲請簡易判決處刑（100 年\n度偵字第4763號），本院判決如下：\n    主      文\n蔡進壽犯不能安全駕駛動力交通工具罪，科罰金新臺幣伍萬元，\n如易服勞役，以新臺幣壹仟元折算壹日。\n    事實及理由\n一、本件犯罪事實及證據，均引用檢察官聲請簡易判決處刑書之\n    記載（如附件）。\n二、核被告蔡進壽所為，係犯刑法第185 條之3 之不能安全駕駛\n    動力交通工具罪。爰審酌被告前無前科紀錄，此素行資料有\n    臺灣高等法院被告前案紀錄表1 紙在卷可參，其飲用酒類後\n    ，呼氣酒精濃度達每公升0.70毫克，實際已無法安全駕駛之\n    情形下，仍不顧行車安全，即率然騎乘機車上路，顯然其無\n    視於自己及其他參與道路交通之不特定人之生命、身體及財\n    產之安全，所為非是，兼衡其犯罪動機、目的、手段，而其\n    生活狀況勉持及智識程度為國中畢業，犯後坦承犯罪等一切\n    情狀，量處如主文所示之刑，併諭知易服勞役之折算標準，\n    以資警惕。\n三、應依刑事訴訟法第449條第1項前段、第3項、第454條第2 項\n    ，刑法第185 條之3 、第42條第3 項前段，刑法施行法第1\n    條之1第1項，逕以簡易判決處如主文所示之刑。\n四、如不服本判決，得自收受送達之日起10日內，向本院提起上\n    訴（須附繕本）。\n中    華    民    國   100    年    3     月    2     日\n                    高雄簡易庭  法  官  饒志民\n以上正本證明與原本無異。\n如不服本判決，得自收受送達之日起10日內，向本院提起上訴。\n中    華    民    國   100    年    3     月    2     日\n                                書記官  蕭永同\n附錄本判決論罪之法條：\n刑法第185條之3\n服用毒品、麻醉藥品、酒類或其他相類之物，不能安全駕駛動力\n交通工具而駕駛者，處1年以下有期徒刑、拘役或科或併科15 萬\n元以下罰金。\n附件\n臺灣高雄地方法院檢察署檢察官簡易判決處刑書\n                                     100年度偵字第4763號\n    被      告  蔡進壽  男  45歲（民國○○年○月○○日生）\n                        住高雄市○○區○○里○○街235號\n                        國民身分證統一編號：Ｚ000000000號\n上列被告因公共危險案件，業經偵查終結，認為宜聲請以簡易判\n決處刑，茲將犯罪事實及證據並所犯法條分敘如下：\n         犯罪事實\n一、蔡進壽明知服用酒類或其他相類之物過量，不能安全駕駛動\n    力交通工具者，不得駕駛動力交通工具，竟於民國100年1月\n    11日20時許，在高雄市鳥松區靠近澄清湖附近海產店與友人\n    飲用酒類，至同月12日2時許，已達不能安全駕駛動力交通\n    工具之程度，仍駕駛車牌號碼MOZ-403號重機車，行至高雄\n    市○○區○○路85─3號前，因不勝酒力，注意能力降低，\n    自行摔倒成傷，嗣警據報前往處理，並對其實施酒精濃度測\n    試，其吐氣所含酒精成份達每公升0.70毫克，始查獲上情。\n二、案經高雄市政府警察局鳳山分局報告偵辦。\n         證據並所犯法條\n一、上揭犯罪事實，業據被告坦承不諱，復有酒精濃度檢驗報告\n    、刑法第185條之3案件測試觀察紀錄表、高雄市政府警察局\n    舉發違反道路交通管理事件通知單、道路交通事故現場圖、\n    交通事故談話紀錄表及道路交通事故調查報告(一)、(二)各\n    1紙及現場照片24張、診斷証明書附卷可稽，足認被告之自\n    白與犯罪事實相符，堪以採信。按刑法第185條之3規定所謂\n    「不能安全駕駛」，乃抽象危險犯，並不以發生具體危險為\n    必要，參諸德國、美國之認定標準，對於呼氣酒精濃度達\n    0.55MG/L以上，因肇事率為一般人之10倍以上，均認為已達\n    「不能安全駕駛」之標準，即應依刑法第185條之3之規定處\n    罰，法務部88年5月18日法88檢字第001669號函意旨可資參\n    照。本件被告呼氣酒精濃度高達0.70MG/L，顯逾不能安全駕\n    駛呼氣酒精濃度0.55MG/L之標準值，且有發生交通事故等不\n    能正常駕駛之情事，足認已達不能安全駕駛之程度，甚為明\n    確，被告犯嫌應堪認定。\n二、核被告所為，係犯刑法第185條之3違背安全駕駛致交通危險\n    罪嫌。\n三、依刑事訴訟法第451條第1項聲請逕以簡易判決處刑。\n臺灣高雄地方法院\n中    華    民    國   100    年    2     月    9     日\n                          檢  察  官  蕭  博  文",
  "structure": {
    "main": "蔡進壽犯不能安全駕駛動力交通工具罪，科罰金新臺幣伍萬元，\n如易服勞役，以新臺幣壹仟元折算壹日。",
    "fact": "一、本件犯罪事實及證據，均引用檢察官聲請簡易判決處刑書之\n    記載（如附件）。\n二、核被告蔡進壽所為，係犯刑法第185 條之3 之不能安全駕駛\n    動力交通工具罪。爰審酌被告前無前科紀錄，此素行資料有\n    臺灣高等法院被告前案紀錄表1 紙在卷可參，其飲用酒類後\n    ，呼氣酒精濃度達每公升0.70毫克，實際已無法安全駕駛之\n    情形下，仍不顧行車安全，即率然騎乘機車上路，顯然其無\n    視於自己及其他參與道路交通之不特定人之生命、身體及財\n    產之安全，所為非是，兼衡其犯罪動機、目的、手段，而其\n    生活狀況勉持及智識程度為國中畢業，犯後坦承犯罪等一切\n    情狀，量處如主文所示之刑，併諭知易服勞役之折算標準，\n    以資警惕。\n三、應依刑事訴訟法第449條第1項前段、第3項、第454條第2 項\n    ，刑法第185 條之3 、第42條第3 項前段，刑法施行法第1\n    條之1第1項，逕以簡易判決處如主文所示之刑。\n四、如不服本判決，得自收受送達之日起10日內，向本院提起上\n    訴（須附繕本）。",
    "reason": "一、本件犯罪事實及證據，均引用檢察官聲請簡易判決處刑書之\n    記載（如附件）。\n二、核被告蔡進壽所為，係犯刑法第185 條之3 之不能安全駕駛\n    動力交通工具罪。爰審酌被告前無前科紀錄，此素行資料有\n    臺灣高等法院被告前案紀錄表1 紙在卷可參，其飲用酒類後\n    ，呼氣酒精濃度達每公升0.70毫克，實際已無法安全駕駛之\n    情形下，仍不顧行車安全，即率然騎乘機車上路，顯然其無\n    視於自己及其他參與道路交通之不特定人之生命、身體及財\n    產之安全，所為非是，兼衡其犯罪動機、目的、手段，而其\n    生活狀況勉持及智識程度為國中畢業，犯後坦承犯罪等一切\n    情狀，量處如主文所示之刑，併諭知易服勞役之折算標準，\n    以資警惕。\n三、應依刑事訴訟法第449條第1項前段、第3項、第454條第2 項\n    ，刑法第185 條之3 、第42條第3 項前段，刑法施行法第1\n    條之1第1項，逕以簡易判決處如主文所示之刑。\n四、如不服本判決，得自收受送達之日起10日內，向本院提起上\n    訴（須附繕本）。"
  },
  "search": "臺灣高雄地方法院刑事簡易判決100年度交簡字第934號聲請人臺灣高雄地方法院檢察署檢察官被告蔡進壽上列被告因公共危險案件，經檢察官聲請簡易判決處刑（100年度偵字第4763號），本院判決如下：主文蔡進壽犯不能安全駕駛動力交通工具罪，科罰金新臺幣伍萬元，如易服勞役，以新臺幣壹仟元折算壹日。事實及理由一、本件犯罪事實及證據，均引用檢察官聲請簡易判決處刑書之記載（如附件）。二、核被告蔡進壽所為，係犯刑法第185條之3之不能安全駕駛動力交通工具罪。爰審酌被告前無前科紀錄，此素行資料有臺灣高等法院被告前案紀錄表1紙在卷可參，其飲用酒類後，呼氣酒精濃度達每公升0.70毫克，實際已無法安全駕駛之情形下，仍不顧行車安全，即率然騎乘機車上路，顯然其無視於自己及其他參與道路交通之不特定人之生命、身體及財產之安全，所為非是，兼衡其犯罪動機、目的、手段，而其生活狀況勉持及智識程度為國中畢業，犯後坦承犯罪等一切情狀，量處如主文所示之刑，併諭知易服勞役之折算標準，以資警惕。三、應依刑事訴訟法第449條第1項前段、第3項、第454條第2項，刑法第185條之3、第42條第3項前段，刑法施行法第1條之1第1項，逕以簡易判決處如主文所示之刑。四、如不服本判決，得自收受送達之日起10日內，向本院提起上訴（須附繕本）。中華民國100年3月2日高雄簡易庭法官饒志民以上正本證明與原本無異。如不服本判決，得自收受送達之日起10日內，向本院提起上訴。中華民國100年3月2日書記官蕭永同附錄本判決論罪之法條：刑法第185條之3服用毒品、麻醉藥品、酒類或其他相類之物，不能安全駕駛動力交通工具而駕駛者，處1年以下有期徒刑、拘役或科或併科15萬元以下罰金。附件臺灣高雄地方法院檢察署檢察官簡易判決處刑書100年度偵字第4763號被告蔡進壽男45歲（民國○○年○月○○日生）住高雄市○○區○○里○○街235號國民身分證統一編號：Ｚ000000000號上列被告因公共危險案件，業經偵查終結，認為宜聲請以簡易判決處刑，茲將犯罪事實及證據並所犯法條分敘如下：犯罪事實一、蔡進壽明知服用酒類或其他相類之物過量，不能安全駕駛動力交通工具者，不得駕駛動力交通工具，竟於民國100年1月11日20時許，在高雄市鳥松區靠近澄清湖附近海產店與友人飲用酒類，至同月12日2時許，已達不能安全駕駛動力交通工具之程度，仍駕駛車牌號碼MOZ-403號重機車，行至高雄市○○區○○路85─3號前，因不勝酒力，注意能力降低，自行摔倒成傷，嗣警據報前往處理，並對其實施酒精濃度測試，其吐氣所含酒精成份達每公升0.70毫克，始查獲上情。二、案經高雄市政府警察局鳳山分局報告偵辦。證據並所犯法條一、上揭犯罪事實，業據被告坦承不諱，復有酒精濃度檢驗報告、刑法第185條之3案件測試觀察紀錄表、高雄市政府警察局舉發違反道路交通管理事件通知單、道路交通事故現場圖、交通事故談話紀錄表及道路交通事故調查報告(一)、(二)各1紙及現場照片24張、診斷証明書附卷可稽，足認被告之自白與犯罪事實相符，堪以採信。按刑法第185條之3規定所謂「不能安全駕駛」，乃抽象危險犯，並不以發生具體危險為必要，參諸德國、美國之認定標準，對於呼氣酒精濃度達0.55MG/L以上，因肇事率為一般人之10倍以上，均認為已達「不能安全駕駛」之標準，即應依刑法第185條之3之規定處罰，法務部88年5月18日法88檢字第001669號函意旨可資參照。本件被告呼氣酒精濃度高達0.70MG/L，顯逾不能安全駕駛呼氣酒精濃度0.55MG/L之標準值，且有發生交通事故等不能正常駕駛之情事，足認已達不能安全駕駛之程度，甚為明確，被告犯嫌應堪認定。二、核被告所為，係犯刑法第185條之3違背安全駕駛致交通危險罪嫌。三、依刑事訴訟法第451條第1項聲請逕以簡易判決處刑。臺灣高雄地方法院中華民國100年2月9日檢察官蕭博文",
  "characters": {
    "judges": [
      "饒志民"
    ],
    "prosecutors": [

    ],
    "lawyers": [

    ],
    "clerks": [
      "蕭永同"
    ],
    "plaintiffs": [

    ],
    "defendants": [
      "蔡進壽",
      "蔡進壽  男  45歲（民國○○年○月○○日生）"
    ],
    "prosecutor_office": [
      "臺灣高雄地方法院檢察署檢察官"
    ],
    "creditors": [

    ],
    "debtors": [

    ],
    "judicial_associate_officer": [

    ]
  },
  "adjudged_at": "2011-03-02",
  "created_at": "2016-02-13 19:53:18",
  "updated_at": "2016-02-13 19:53:18"
}