{
  "identify": "PCD-100-簡-679-20110302-1",
  "court": {
    "name": "臺灣新北地方法院",
    "code": "PCD"
  },
  "division": {
    "name": "刑事",
    "code": "M"
  },
  "year": 100,
  "word": "簡",
  "number": "679",
  "jcheck": "1",
  "reason": "偽造文書",
  "content": "臺灣板橋地方法院刑事簡易判決          100年度簡字第679號\n聲  請  人  臺灣板橋地方法院檢察署檢察官\n被      告  錢隸澤\n上列被告因偽造文書案件，經檢察官聲請以簡易判決處刑（99年\n度偵字第28575號），本院判決如下：\n    主  文\n錢隸澤行使偽造私文書，足以生損害於公眾及他人，處有期徒刑\n月，如易科罰金，以新臺幣壹仟元折算壹日。臺北縣政府警察\n局中華民國97年1月20日北縣警交字第C00000000號舉發違反道路\n交通管理事件通知單「移送聯」、「存根聯」上「收受通知聯者\n簽章欄」內偽造之「葉金龍」署押共枚（含簽名貳枚、指印壹\n枚）均沒收之。\n    事實及理由\n一、本件犯罪事實及證據，除下列事項應予更正或補充外，均引\n    用如附件檢察官聲請簡易判決處刑書之記載：\n（一）犯罪事實欄第一段第6-9行之文字應補充更正為：「在臺\n      北縣政府警察局中華民國97年1月20日北縣警交字第C0000\n      00 00號舉發違反道路交通管理事件通知單（下稱舉發通\n      知單）第二聯即『移送聯』之『收受通知聯者簽章欄』上\n      偽簽『葉金龍』之姓名，並複寫至該舉發通知單第三聯即\n      『存根聯』上，復捺己之指印於第二聯即『移送聯』之『\n      收受通知聯者簽章欄』上」。\n（二）證據並所犯法條第二段倒數第2行關於：「犯罪事實欄所\n      載之「葉金龍」署押2枚」之記載，應更正為「犯罪事實\n      欄所載之「葉金龍」署押共3枚（含簽名2枚、指印1枚）\n      」。\n二、按在舉發違反道路交通管理事件通知單移送聯上「收受通知\n    聯者簽章」欄內，偽簽他人姓名，自不待依據習慣或特約，\n    單從形式上觀察，即足以知悉係表示由他人名義出具領收通\n    知之證明，此與事先在印妥內容之收據上偽簽他人姓名之情\n    形，無分軒輊，當然屬於刑法第210 條所稱之私文書，而非\n    同法第220 條之準私文書，最高法院83年度台上字第6631號\n    判例意旨可資參照。本件被告於上開舉發通知單之移送聯上\n    「收受通知聯者簽章」欄內偽造「葉金龍」之署押後，復交\n    回舉發警員處理，顯係對於該文書之內容有所主張，自有行\n    使之意思。是核被告錢隸澤所為，係犯刑法第216條、第210\n    條之行使偽造私文書罪。又被告上開偽造署押係其偽造私文\n    書之部分行為；而於偽造私文書後復持以行使，其偽造之低\n    度行為，應為其行使偽造私文書之高度行為所吸收，均不另\n    論罪。爰審酌被告前於96年間即因偽造文書案件受刑之宣告\n    ，此次為規避交通違規之裁罰，竟鋌而走險，冒用葉金龍名\n    義接受稽查而偽造葉金龍之署押，足以生損害於交通監理機\n    關對道路交通管理之正確性及葉金龍之利益，足顯其心存僥\n    倖進而挑戰公權力，兼衡其犯罪動機、手段、品行、智識程\n    度，及被告犯罪後坦承犯行等一切情狀，量處如主文所示之\n    刑，並諭知易科罰金之折算標準，以資懲儆。至扣案舉發違\n    反道路交通管理事件通知單偽造署押（舉發通知單共有三聯\n    ，第一聯為「收執聯」（交違規人收執）、第二聯為「移送\n    聯」（移送監理機關）、第三聯為「存根聯」（舉發單位存\n    查），違規人於「移送聯」簽名後，並同時複寫該簽名於「\n    存根聯」，至「收執聯」因交給違規當事人故無須簽名；被\n    告並捺己之指印於第二聯即『移送聯』之『收受通知聯者簽\n    章欄』上）共3枚，不問是否屬於被告所有，均應依刑法第\n    219條之規定宣告沒收之。\n三、依刑事訴訟法第449條第1項前段、第3項、第454條第2項、\n    第450條第1項，刑法第216條、第210條、第219條、第41條\n    第1項前段，逕以簡易判決處刑如主文。\n四、如不服本判決，得自收受送達之日起10日內，向本院提出上\n    訴狀，上訴於本院第二審合議庭（須附繕本）。\n中    華    民    國   100    年    3     月    2     日\n                  刑事第二十二庭    法  官  徐子涵\n以上正本證明與原本無異。\n                                    書記官  藍淑芬\n中    華    民    國   100    年    3     月    2     日\n附錄本案論罪科刑法條全文：\n中華民國刑法第210條\n偽造、變造私文書，足以生損害於公眾或他人者，處5年以下有\n期徒刑。\n中華民國刑法第216條\n行使第210條至第215條之文書者，依偽造、變造文書或登載不實\n事項或使登載不實事項之規定處斷。",
  "structure": {
    "main": "錢隸澤行使偽造私文書，足以生損害於公眾及他人，處有期徒刑\n月，如易科罰金，以新臺幣壹仟元折算壹日。臺北縣政府警察\n局中華民國97年1月20日北縣警交字第C00000000號舉發違反道路\n交通管理事件通知單「移送聯」、「存根聯」上「收受通知聯者\n簽章欄」內偽造之「葉金龍」署押共枚（含簽名貳枚、指印壹\n枚）均沒收之。",
    "fact": "一、本件犯罪事實及證據，除下列事項應予更正或補充外，均引\n    用如附件檢察官聲請簡易判決處刑書之記載：\n（一）犯罪事實欄第一段第6-9行之文字應補充更正為：「在臺\n      北縣政府警察局中華民國97年1月20日北縣警交字第C0000\n      00 00號舉發違反道路交通管理事件通知單（下稱舉發通\n      知單）第二聯即『移送聯』之『收受通知聯者簽章欄』上\n      偽簽『葉金龍』之姓名，並複寫至該舉發通知單第三聯即\n      『存根聯』上，復捺己之指印於第二聯即『移送聯』之『\n      收受通知聯者簽章欄』上」。\n（二）證據並所犯法條第二段倒數第2行關於：「犯罪事實欄所\n      載之「葉金龍」署押2枚」之記載，應更正為「犯罪事實\n      欄所載之「葉金龍」署押共3枚（含簽名2枚、指印1枚）\n      」。\n二、按在舉發違反道路交通管理事件通知單移送聯上「收受通知\n    聯者簽章」欄內，偽簽他人姓名，自不待依據習慣或特約，\n    單從形式上觀察，即足以知悉係表示由他人名義出具領收通\n    知之證明，此與事先在印妥內容之收據上偽簽他人姓名之情\n    形，無分軒輊，當然屬於刑法第210 條所稱之私文書，而非\n    同法第220 條之準私文書，最高法院83年度台上字第6631號\n    判例意旨可資參照。本件被告於上開舉發通知單之移送聯上\n    「收受通知聯者簽章」欄內偽造「葉金龍」之署押後，復交\n    回舉發警員處理，顯係對於該文書之內容有所主張，自有行\n    使之意思。是核被告錢隸澤所為，係犯刑法第216條、第210\n    條之行使偽造私文書罪。又被告上開偽造署押係其偽造私文\n    書之部分行為；而於偽造私文書後復持以行使，其偽造之低\n    度行為，應為其行使偽造私文書之高度行為所吸收，均不另\n    論罪。爰審酌被告前於96年間即因偽造文書案件受刑之宣告\n    ，此次為規避交通違規之裁罰，竟鋌而走險，冒用葉金龍名\n    義接受稽查而偽造葉金龍之署押，足以生損害於交通監理機\n    關對道路交通管理之正確性及葉金龍之利益，足顯其心存僥\n    倖進而挑戰公權力，兼衡其犯罪動機、手段、品行、智識程\n    度，及被告犯罪後坦承犯行等一切情狀，量處如主文所示之\n    刑，並諭知易科罰金之折算標準，以資懲儆。至扣案舉發違\n    反道路交通管理事件通知單偽造署押（舉發通知單共有三聯\n    ，第一聯為「收執聯」（交違規人收執）、第二聯為「移送\n    聯」（移送監理機關）、第三聯為「存根聯」（舉發單位存\n    查），違規人於「移送聯」簽名後，並同時複寫該簽名於「\n    存根聯」，至「收執聯」因交給違規當事人故無須簽名；被\n    告並捺己之指印於第二聯即『移送聯』之『收受通知聯者簽\n    章欄』上）共3枚，不問是否屬於被告所有，均應依刑法第\n    219條之規定宣告沒收之。\n三、依刑事訴訟法第449條第1項前段、第3項、第454條第2項、\n    第450條第1項，刑法第216條、第210條、第219條、第41條\n    第1項前段，逕以簡易判決處刑如主文。\n四、如不服本判決，得自收受送達之日起10日內，向本院提出上\n    訴狀，上訴於本院第二審合議庭（須附繕本）。",
    "reason": "一、本件犯罪事實及證據，除下列事項應予更正或補充外，均引\n    用如附件檢察官聲請簡易判決處刑書之記載：\n（一）犯罪事實欄第一段第6-9行之文字應補充更正為：「在臺\n      北縣政府警察局中華民國97年1月20日北縣警交字第C0000\n      00 00號舉發違反道路交通管理事件通知單（下稱舉發通\n      知單）第二聯即『移送聯』之『收受通知聯者簽章欄』上\n      偽簽『葉金龍』之姓名，並複寫至該舉發通知單第三聯即\n      『存根聯』上，復捺己之指印於第二聯即『移送聯』之『\n      收受通知聯者簽章欄』上」。\n（二）證據並所犯法條第二段倒數第2行關於：「犯罪事實欄所\n      載之「葉金龍」署押2枚」之記載，應更正為「犯罪事實\n      欄所載之「葉金龍」署押共3枚（含簽名2枚、指印1枚）\n      」。\n二、按在舉發違反道路交通管理事件通知單移送聯上「收受通知\n    聯者簽章」欄內，偽簽他人姓名，自不待依據習慣或特約，\n    單從形式上觀察，即足以知悉係表示由他人名義出具領收通\n    知之證明，此與事先在印妥內容之收據上偽簽他人姓名之情\n    形，無分軒輊，當然屬於刑法第210 條所稱之私文書，而非\n    同法第220 條之準私文書，最高法院83年度台上字第6631號\n    判例意旨可資參照。本件被告於上開舉發通知單之移送聯上\n    「收受通知聯者簽章」欄內偽造「葉金龍」之署押後，復交\n    回舉發警員處理，顯係對於該文書之內容有所主張，自有行\n    使之意思。是核被告錢隸澤所為，係犯刑法第216條、第210\n    條之行使偽造私文書罪。又被告上開偽造署押係其偽造私文\n    書之部分行為；而於偽造私文書後復持以行使，其偽造之低\n    度行為，應為其行使偽造私文書之高度行為所吸收，均不另\n    論罪。爰審酌被告前於96年間即因偽造文書案件受刑之宣告\n    ，此次為規避交通違規之裁罰，竟鋌而走險，冒用葉金龍名\n    義接受稽查而偽造葉金龍之署押，足以生損害於交通監理機\n    關對道路交通管理之正確性及葉金龍之利益，足顯其心存僥\n    倖進而挑戰公權力，兼衡其犯罪動機、手段、品行、智識程\n    度，及被告犯罪後坦承犯行等一切情狀，量處如主文所示之\n    刑，並諭知易科罰金之折算標準，以資懲儆。至扣案舉發違\n    反道路交通管理事件通知單偽造署押（舉發通知單共有三聯\n    ，第一聯為「收執聯」（交違規人收執）、第二聯為「移送\n    聯」（移送監理機關）、第三聯為「存根聯」（舉發單位存\n    查），違規人於「移送聯」簽名後，並同時複寫該簽名於「\n    存根聯」，至「收執聯」因交給違規當事人故無須簽名；被\n    告並捺己之指印於第二聯即『移送聯』之『收受通知聯者簽\n    章欄』上）共3枚，不問是否屬於被告所有，均應依刑法第\n    219條之規定宣告沒收之。\n三、依刑事訴訟法第449條第1項前段、第3項、第454條第2項、\n    第450條第1項，刑法第216條、第210條、第219條、第41條\n    第1項前段，逕以簡易判決處刑如主文。\n四、如不服本判決，得自收受送達之日起10日內，向本院提出上\n    訴狀，上訴於本院第二審合議庭（須附繕本）。"
  },
  "search": "臺灣板橋地方法院刑事簡易判決100年度簡字第679號聲請人臺灣板橋地方法院檢察署檢察官被告錢隸澤上列被告因偽造文書案件，經檢察官聲請以簡易判決處刑（99年度偵字第28575號），本院判決如下：主文錢隸澤行使偽造私文書，足以生損害於公眾及他人，處有期徒刑月，如易科罰金，以新臺幣壹仟元折算壹日。臺北縣政府警察局中華民國97年1月20日北縣警交字第C00000000號舉發違反道路交通管理事件通知單「移送聯」、「存根聯」上「收受通知聯者簽章欄」內偽造之「葉金龍」署押共枚（含簽名貳枚、指印壹枚）均沒收之。事實及理由一、本件犯罪事實及證據，除下列事項應予更正或補充外，均引用如附件檢察官聲請簡易判決處刑書之記載：（一）犯罪事實欄第一段第6-9行之文字應補充更正為：「在臺北縣政府警察局中華民國97年1月20日北縣警交字第C00000000號舉發違反道路交通管理事件通知單（下稱舉發通知單）第二聯即『移送聯』之『收受通知聯者簽章欄』上偽簽『葉金龍』之姓名，並複寫至該舉發通知單第三聯即『存根聯』上，復捺己之指印於第二聯即『移送聯』之『收受通知聯者簽章欄』上」。（二）證據並所犯法條第二段倒數第2行關於：「犯罪事實欄所載之「葉金龍」署押2枚」之記載，應更正為「犯罪事實欄所載之「葉金龍」署押共3枚（含簽名2枚、指印1枚）」。二、按在舉發違反道路交通管理事件通知單移送聯上「收受通知聯者簽章」欄內，偽簽他人姓名，自不待依據習慣或特約，單從形式上觀察，即足以知悉係表示由他人名義出具領收通知之證明，此與事先在印妥內容之收據上偽簽他人姓名之情形，無分軒輊，當然屬於刑法第210條所稱之私文書，而非同法第220條之準私文書，最高法院83年度台上字第6631號判例意旨可資參照。本件被告於上開舉發通知單之移送聯上「收受通知聯者簽章」欄內偽造「葉金龍」之署押後，復交回舉發警員處理，顯係對於該文書之內容有所主張，自有行使之意思。是核被告錢隸澤所為，係犯刑法第216條、第210條之行使偽造私文書罪。又被告上開偽造署押係其偽造私文書之部分行為；而於偽造私文書後復持以行使，其偽造之低度行為，應為其行使偽造私文書之高度行為所吸收，均不另論罪。爰審酌被告前於96年間即因偽造文書案件受刑之宣告，此次為規避交通違規之裁罰，竟鋌而走險，冒用葉金龍名義接受稽查而偽造葉金龍之署押，足以生損害於交通監理機關對道路交通管理之正確性及葉金龍之利益，足顯其心存僥倖進而挑戰公權力，兼衡其犯罪動機、手段、品行、智識程度，及被告犯罪後坦承犯行等一切情狀，量處如主文所示之刑，並諭知易科罰金之折算標準，以資懲儆。至扣案舉發違反道路交通管理事件通知單偽造署押（舉發通知單共有三聯，第一聯為「收執聯」（交違規人收執）、第二聯為「移送聯」（移送監理機關）、第三聯為「存根聯」（舉發單位存查），違規人於「移送聯」簽名後，並同時複寫該簽名於「存根聯」，至「收執聯」因交給違規當事人故無須簽名；被告並捺己之指印於第二聯即『移送聯』之『收受通知聯者簽章欄』上）共3枚，不問是否屬於被告所有，均應依刑法第219條之規定宣告沒收之。三、依刑事訴訟法第449條第1項前段、第3項、第454條第2項、第450條第1項，刑法第216條、第210條、第219條、第41條第1項前段，逕以簡易判決處刑如主文。四、如不服本判決，得自收受送達之日起10日內，向本院提出上訴狀，上訴於本院第二審合議庭（須附繕本）。中華民國100年3月2日刑事第二十二庭法官徐子涵以上正本證明與原本無異。書記官藍淑芬中華民國100年3月2日附錄本案論罪科刑法條全文：中華民國刑法第210條偽造、變造私文書，足以生損害於公眾或他人者，處5年以下有期徒刑。中華民國刑法第216條行使第210條至第215條之文書者，依偽造、變造文書或登載不實事項或使登載不實事項之規定處斷。",
  "characters": {
    "judges": [
      "徐子涵"
    ],
    "prosecutors": [

    ],
    "lawyers": [

    ],
    "clerks": [
      "藍淑芬"
    ],
    "plaintiffs": [

    ],
    "defendants": [
      "錢隸澤"
    ],
    "prosecutor_office": [
      "臺灣板橋地方法院檢察署檢察官"
    ],
    "creditors": [

    ],
    "debtors": [

    ],
    "judicial_associate_officer": [

    ]
  },
  "adjudged_at": "2011-03-02",
  "created_at": "2016-02-13 19:43:06",
  "updated_at": "2016-02-13 19:43:06"
}