{
  "identify": "KLD-94-交簡上-32-20050928-1",
  "court": {
    "name": "臺灣基隆地方法院",
    "code": "KLD"
  },
  "division": {
    "name": "刑事",
    "code": "M"
  },
  "year": 94,
  "word": "交簡上",
  "number": "32",
  "jcheck": "1",
  "reason": "過失傷害",
  "content": "臺灣基隆地方法院刑事判決            94年度交簡上字第32號\n公  訴  人  臺灣基隆地方法院檢察署檢察官\n上  訴  人\n即  被  告  乙○○\n上列上訴人即被告因過失傷害案件，不服本院基隆簡易庭94年度\n基交簡字第251號，中華民國94年3月30日第一審簡易判決（聲請\n案號：94年度偵字第2065號）提起上訴，本院管轄之第二審合議\n庭判決如下：\n    主  文\n原判決撤銷。\n乙○○因過失傷害人，處拘役伍拾日，如易科罰金以佰元折算\n壹日。緩刑貳年。\n    事  實\n一、乙○○於民國（下同）94年3月8 日晚間7時許，駕駛車牌號\n    碼3C- 7701號自小客車，沿基隆市○○街由東向西方向行駛\n    ，行經基隆市○○街154 巷口欲左轉時，本應注意車前狀況\n    ，並隨時採取必要之安全措施，且依諸當時情形並無不能注\n    意之情形，竟疏未注意，適有丙○之妻潘宏亮欲穿越福二街\n    巷口，且未暫停讓行人先行通過及保持隨時可採取必要剎停\n    措施，致撞及潘宏亮倒地，致潘宏亮受有右肩關節脫臼、右\n    肱股大結節骨折、右膝挫傷合併內側副韌帶斷裂、右踝及右\n    腳挫傷及擦傷等傷害。\n二、案經丙○訴請臺灣基隆地方法院檢察署檢察官聲請簡易判決\n    處刑。\n    理  由\n一、上揭犯罪事實，業據被告乙○○於偵訊時坦承不諱，核與告\n    訴人丙○、被害人潘宏亮指訴之情節相符，並有診斷證明書\n    附卷可稽。按汽車行駛時，駕駛人應注意車前狀況，並隨時\n    採取必要之安全措施，道路交通安全規則第94條第3 項定有\n    明文，被告駕駛汽車自應注意上開規定，竟疏未注意，致肇\n    車禍，其有過失甚為顯然。被告之過失行為與被害人之傷害\n    結果間，有相當因果關係。被告自白與事實相符，事證明確\n    ，被告犯行堪以認定，應依法論科。\n二、核被告所為，係犯刑法第284條第1項前段之過失傷害罪。原\n    審以被告罪證明確，援引刑法第284條第1項前段、第41條第\n    1項前段、罰金罰鍰提高標準條例第1條前段、第2 條，量處\n    被告有期徒刑3 月，並諭知易科罰金之折算標準，固非無據\n    ，惟被告除本案外，並無其他犯罪紀錄，原審竟論以累犯，\n    顯有不當，被告提起上訴，指摘原審判決不當，雖無理由，\n    但原審判決既有可議之處，自應由本院管轄之第二審合議庭\n    將原審判決予以撤銷改判。爰審酌被告之品行，犯罪之動機\n    、目的、手段、犯罪所生之損害及犯罪後坦承犯行，並與告\n    訴人達成和解，告訴人並撤回告訴（詳本院卷94年8 月30日\n    訊問筆錄）等一切情狀，量處如主文所示之刑，並諭知易科\n    罰金之折算標準，以示儆懲。末查被告前未曾受有期徒刑以\n    上刑之宣告，有臺灣基隆地方法院檢察署刑案資料查註紀錄\n    表及臺灣高等法院被告全國前案紀錄表各1 份附卷可佐，被\n    告犯罪後已與告訴人達成和解，有本院訊問筆錄在卷可憑，\n    本院認其經此教訓後，當知警惕，應無再犯之虞，因認其所\n    宣告之刑，以暫不執行為適當，併予宣告緩刑2年，以勵來\n    茲而啟自新。\n三、末按被告經合法傳喚，無正當理由不到庭者，得不待其陳述\n    ，逕行判決，刑事訴訟法第371 條定有明文。查被告經合法\n    傳喚，無正當理由未於審判期日到庭，有傳票送達證書在卷\n    可查，爰依上開條文規定，不待其陳述逕行判決如主文所示\n    ，附此敘明。\n據上論斷，應依刑事訴訟法第455條之1第3 項、第369條第1項、\n第364條、第371條、第299條第1項前段，刑法第284條第1項前段\n、第41條第1項前段、第74條第1 款，罰金罰鍰提高標準條例第1\n條前段、第2條，判決如主文。\n本案經檢察官甲○○到庭執行職務\n中    華    民    國    94    年    9     月    28    日\n                  刑事第二庭審判長 法 官  王福康\n                                   法 官  王慧惠\n                                   法 官  齊  潔\n以上正本證明與原本無異。\n本件判決不得上訴。\n中    華    民    國    94    年    9     月    28    日\n                                   書記官 潘端典\n附錄論罪法條：\n中華民國刑法第284條第1項前段：\n(過失傷害罪)\n因過失傷害人者，處 6 月以下有期徒刑、拘役或 500 元以下罰\n金，致重傷者，處1年以下有期徒刑、拘役或500元以下罰金。\n",
  "structure": {
    "main": "原判決撤銷。\n乙○○因過失傷害人，處拘役伍拾日，如易科罰金以佰元折算\n壹日。緩刑貳年。",
    "fact": "一、乙○○於民國（下同）94年3月8 日晚間7時許，駕駛車牌號\n    碼3C- 7701號自小客車，沿基隆市○○街由東向西方向行駛\n    ，行經基隆市○○街154 巷口欲左轉時，本應注意車前狀況\n    ，並隨時採取必要之安全措施，且依諸當時情形並無不能注\n    意之情形，竟疏未注意，適有丙○之妻潘宏亮欲穿越福二街\n    巷口，且未暫停讓行人先行通過及保持隨時可採取必要剎停\n    措施，致撞及潘宏亮倒地，致潘宏亮受有右肩關節脫臼、右\n    肱股大結節骨折、右膝挫傷合併內側副韌帶斷裂、右踝及右\n    腳挫傷及擦傷等傷害。\n二、案經丙○訴請臺灣基隆地方法院檢察署檢察官聲請簡易判決\n    處刑。",
    "reason": "一、上揭犯罪事實，業據被告乙○○於偵訊時坦承不諱，核與告\n    訴人丙○、被害人潘宏亮指訴之情節相符，並有診斷證明書\n    附卷可稽。按汽車行駛時，駕駛人應注意車前狀況，並隨時\n    採取必要之安全措施，道路交通安全規則第94條第3 項定有\n    明文，被告駕駛汽車自應注意上開規定，竟疏未注意，致肇\n    車禍，其有過失甚為顯然。被告之過失行為與被害人之傷害\n    結果間，有相當因果關係。被告自白與事實相符，事證明確\n    ，被告犯行堪以認定，應依法論科。\n二、核被告所為，係犯刑法第284條第1項前段之過失傷害罪。原\n    審以被告罪證明確，援引刑法第284條第1項前段、第41條第\n    1項前段、罰金罰鍰提高標準條例第1條前段、第2 條，量處\n    被告有期徒刑3 月，並諭知易科罰金之折算標準，固非無據\n    ，惟被告除本案外，並無其他犯罪紀錄，原審竟論以累犯，\n    顯有不當，被告提起上訴，指摘原審判決不當，雖無理由，\n    但原審判決既有可議之處，自應由本院管轄之第二審合議庭\n    將原審判決予以撤銷改判。爰審酌被告之品行，犯罪之動機\n    、目的、手段、犯罪所生之損害及犯罪後坦承犯行，並與告\n    訴人達成和解，告訴人並撤回告訴（詳本院卷94年8 月30日\n    訊問筆錄）等一切情狀，量處如主文所示之刑，並諭知易科\n    罰金之折算標準，以示儆懲。末查被告前未曾受有期徒刑以\n    上刑之宣告，有臺灣基隆地方法院檢察署刑案資料查註紀錄\n    表及臺灣高等法院被告全國前案紀錄表各1 份附卷可佐，被\n    告犯罪後已與告訴人達成和解，有本院訊問筆錄在卷可憑，\n    本院認其經此教訓後，當知警惕，應無再犯之虞，因認其所\n    宣告之刑，以暫不執行為適當，併予宣告緩刑2年，以勵來\n    茲而啟自新。\n三、末按被告經合法傳喚，無正當理由不到庭者，得不待其陳述\n    ，逕行判決，刑事訴訟法第371 條定有明文。查被告經合法\n    傳喚，無正當理由未於審判期日到庭，有傳票送達證書在卷\n    可查，爰依上開條文規定，不待其陳述逕行判決如主文所示\n    ，附此敘明。\n據上論斷，應依刑事訴訟法第455條之1第3 項、第369條第1項、\n第364條、第371條、第299條第1項前段，刑法第284條第1項前段\n、第41條第1項前段、第74條第1 款，罰金罰鍰提高標準條例第1\n條前段、第2條，判決如主文。\n本案經檢察官甲○○到庭執行職務\n中    華    民    國    94    年    9     月    28    日\n                  刑事第二庭審判長 法 官  王福康\n                                   法 官  王慧惠\n                                   法 官  齊  潔\n以上正本證明與原本無異。\n本件判決不得上訴。"
  },
  "search": "臺灣基隆地方法院刑事判決94年度交簡上字第32號公訴人臺灣基隆地方法院檢察署檢察官上訴人即被告乙○○上列上訴人即被告因過失傷害案件，不服本院基隆簡易庭94年度基交簡字第251號，中華民國94年3月30日第一審簡易判決（聲請案號：94年度偵字第2065號）提起上訴，本院管轄之第二審合議庭判決如下：主文原判決撤銷。乙○○因過失傷害人，處拘役伍拾日，如易科罰金以佰元折算壹日。緩刑貳年。事實一、乙○○於民國（下同）94年3月8日晚間7時許，駕駛車牌號碼3C-7701號自小客車，沿基隆市○○街由東向西方向行駛，行經基隆市○○街154巷口欲左轉時，本應注意車前狀況，並隨時採取必要之安全措施，且依諸當時情形並無不能注意之情形，竟疏未注意，適有丙○之妻潘宏亮欲穿越福二街巷口，且未暫停讓行人先行通過及保持隨時可採取必要剎停措施，致撞及潘宏亮倒地，致潘宏亮受有右肩關節脫臼、右肱股大結節骨折、右膝挫傷合併內側副韌帶斷裂、右踝及右腳挫傷及擦傷等傷害。二、案經丙○訴請臺灣基隆地方法院檢察署檢察官聲請簡易判決處刑。理由一、上揭犯罪事實，業據被告乙○○於偵訊時坦承不諱，核與告訴人丙○、被害人潘宏亮指訴之情節相符，並有診斷證明書附卷可稽。按汽車行駛時，駕駛人應注意車前狀況，並隨時採取必要之安全措施，道路交通安全規則第94條第3項定有明文，被告駕駛汽車自應注意上開規定，竟疏未注意，致肇車禍，其有過失甚為顯然。被告之過失行為與被害人之傷害結果間，有相當因果關係。被告自白與事實相符，事證明確，被告犯行堪以認定，應依法論科。二、核被告所為，係犯刑法第284條第1項前段之過失傷害罪。原審以被告罪證明確，援引刑法第284條第1項前段、第41條第1項前段、罰金罰鍰提高標準條例第1條前段、第2條，量處被告有期徒刑3月，並諭知易科罰金之折算標準，固非無據，惟被告除本案外，並無其他犯罪紀錄，原審竟論以累犯，顯有不當，被告提起上訴，指摘原審判決不當，雖無理由，但原審判決既有可議之處，自應由本院管轄之第二審合議庭將原審判決予以撤銷改判。爰審酌被告之品行，犯罪之動機、目的、手段、犯罪所生之損害及犯罪後坦承犯行，並與告訴人達成和解，告訴人並撤回告訴（詳本院卷94年8月30日訊問筆錄）等一切情狀，量處如主文所示之刑，並諭知易科罰金之折算標準，以示儆懲。末查被告前未曾受有期徒刑以上刑之宣告，有臺灣基隆地方法院檢察署刑案資料查註紀錄表及臺灣高等法院被告全國前案紀錄表各1份附卷可佐，被告犯罪後已與告訴人達成和解，有本院訊問筆錄在卷可憑，本院認其經此教訓後，當知警惕，應無再犯之虞，因認其所宣告之刑，以暫不執行為適當，併予宣告緩刑2年，以勵來茲而啟自新。三、末按被告經合法傳喚，無正當理由不到庭者，得不待其陳述，逕行判決，刑事訴訟法第371條定有明文。查被告經合法傳喚，無正當理由未於審判期日到庭，有傳票送達證書在卷可查，爰依上開條文規定，不待其陳述逕行判決如主文所示，附此敘明。據上論斷，應依刑事訴訟法第455條之1第3項、第369條第1項、第364條、第371條、第299條第1項前段，刑法第284條第1項前段、第41條第1項前段、第74條第1款，罰金罰鍰提高標準條例第1條前段、第2條，判決如主文。本案經檢察官甲○○到庭執行職務中華民國94年9月28日刑事第二庭審判長法官王福康法官王慧惠法官齊潔以上正本證明與原本無異。本件判決不得上訴。中華民國94年9月28日書記官潘端典附錄論罪法條：中華民國刑法第284條第1項前段：(過失傷害罪)因過失傷害人者，處6月以下有期徒刑、拘役或500元以下罰金，致重傷者，處1年以下有期徒刑、拘役或500元以下罰金。",
  "characters": {
    "judges": [
      "王福康",
      "王慧惠",
      "齊潔"
    ],
    "prosecutors": [

    ],
    "lawyers": [

    ],
    "clerks": [
      "潘端典"
    ],
    "plaintiffs": [

    ],
    "defendants": [
      "乙"
    ],
    "prosecutor_office": [
      "臺灣基隆地方法院檢察署檢察官"
    ],
    "creditors": [

    ],
    "debtors": [

    ],
    "judicial_associate_officer": [

    ]
  },
  "adjudged_at": "2005-09-28",
  "created_at": "2016-02-06 20:06:34",
  "updated_at": "2016-02-06 20:06:34"
}