{
  "identify": "KSD-91-訴-2779-20021128-1",
  "court": {
    "name": "臺灣高雄地方法院",
    "code": "KSD"
  },
  "division": {
    "name": "刑事",
    "code": "M"
  },
  "year": 91,
  "word": "訴",
  "number": "2779",
  "jcheck": "1",
  "reason": "毒品危害防制條例",
  "content": "臺灣高雄地方法院刑事判決                        九十一年度訴字第二七七九號\n    公  訴  人  臺灣高雄地方法院檢察署檢察官\n    被      告  甲○○\n右列被告因違反毒品危害防制條例案件，經檢察官提起公訴（九十一年度毒偵字第四\n二一六號），本院判決如左：\n    主  文\n甲○○連續施用第一級毒品，累犯，處有期徒刑捌月。又連續施用第二級毒品，累犯\n，處有期徒刑肆月。應執行有期徒刑拾壹月。\n    事  實\n一、甲○○前因麻醉藥品管理條例、竊盜案件，分別經臺灣屏東地方法院分別判處有\n    期徒刑七月、九月，經接續執行，嗣為一部執行，交付保護管束，已於民國八十\n    六年十一月二十二日執行完畢，再因施用毒品案件，經強制戒治期滿，而由臺灣\n    屏東地方法院檢察署於九十年三月八日以九十年度戒毒偵字第三十八號為不起訴\n    處分確定後，仍不知悔改，於五年內復基於概括之犯意，自九十年十月間起至九\n    十一年六月十五日止，連續在不詳處所，施用第一級毒品海洛因及第二級毒品安\n    非他命，嗣復於九十一年六月二十五日十時二十五分許回溯二十四小時內之某時\n    （不含為警查獲後公權力拘束時間），在不詳處所，施用第一級毒品海洛因及第\n    二級毒品安非他命，為警於同日六時三十分許，在高雄縣鳳山市○○路六○五號\n    前查獲。\n二、案經高雄縣警察局鳳山分局報請臺灣高雄地方法院檢察署檢察官偵查起訴。\n    理  由\n一、訊據被告固對於其自九十年十月間起至九十一年六月十五日止，連續施用第一級\n    毒品海洛因及第二級毒品安非他命之犯罪事實，坦承不諱，惟矢口否認於九十一\n    年六月二十五日即經警查獲當日，有何施用第一、二級毒品之犯行，並辯稱其於\n    查獲前有服用安眠藥云云；然查，被告於九十一年六月二十五日為警查獲當日所\n    採尿液，經送請高雄縣政府衛生局檢驗結果確呈第一級毒品海洛因嗎啡之陽性反\n    應及第二級毒品甲基安非他命之陽性反應，有該局九十一年七月十二日九十一煙\n    檢字第一○一四號之煙毒尿液檢驗成績書一份附卷可稽，足見被告於九十一年六\n    月二十五日十時二十五分許回溯二十四小時內之某時，確有施用第一、二級毒品\n    ，是被告上開所辯顯不足採。再被告前因施用毒品案件，經強制戒治期滿後，業\n    經臺灣屏東地方法院檢察署檢察官於九十年三月八日以九十年度戒毒偵字第三十\n    八號不起訴處分確定，其於五年內復再犯毒品危害防制條例第十條之罪一節，亦\n    有不起訴處分書及刑案資料查註紀錄表附卷可稽。從而，本件事證明確，被告連\n    續施用第一、二級毒品之犯罪事實，洵堪認定。\n二、復按海洛因係屬毒品危害防制條例第二條第二項第一款所稱之第一級毒品，而安\n    非他命則為毒品危害防制條例第二條第二項第二款所稱之第二級毒品，是被告施\n    用海洛因、安非他命之行為，係犯該條例第十條第一項之施用第一級毒品罪、同\n    條例第十條第二項之施用第二級毒品罪。被告分別持有第一級毒品海洛因及第二\n    級毒品安非他命，嗣進而施用之，持有之低度行為應為施用之高度行為所吸收，\n    不另論罪。其前後多次施用第一級毒品及第二級毒品之行為時間密接、犯罪構成\n    要件相同，顯係基於概括犯意為之，應依連續犯規定分別論處，並分別加重其刑\n    。又被告所犯上開連續施用第一級毒品與連續施用第二級毒品二罪間，犯意各別\n    ，行為互殊，應予分論併罰。另被告曾因麻醉藥品管理條例、竊盜案件，分別經\n    臺灣屏東地方法院分別判處有期徒刑七月、九月，經接續執行，嗣為一部執行，\n    交付保護管束，已於八十六年十一月二十二日執行完畢後（此可參卷附之臺灣高\n    等法院被告全國前案紀錄表及被告刑案資料查註紀錄表），五年以內再犯本件有\n    期徒刑以上之罪，為累犯，依刑法第四十七條規定應加重其刑。被告同時有二種\n    刑之加重事由，應依刑法第七十條之規定，遞加其刑。又被告於九十一年六月二\n    十五日十時二十五分許回溯二十四小時內之某時（不含為警查獲後公權力拘束時\n    間），在不詳處所，施用第一級毒品海洛因及第二級毒品部分，雖未據起訴，惟\n    與已起訴部分之犯罪事實，既有裁判上一罪之連續犯關係，依審判不可分之法理\n    ，本院自得一併審究，併此敘明。爰審酌被告前已有施用毒品之前科，並經判刑\n    確定而入監服刑完畢，又因違反毒品危害防制條例案件，經強制戒治期滿，並由\n    檢察官為不起訴處分確定後，仍繼續施用毒品，已如上述，顯見其並無戒除毒害\n    之決心，及其所犯罪行乃自戕之行為，尚無害及他人，犯後坦承部分犯行，態度\n    良好等一切情狀，分別量處如主文所示之刑，並定其應執行刑，以資懲儆。\n據上論斷，應依刑事訴訟法第二百九十九條第一項前段，毒品危害防制條例第十條第\n一項、第二項，刑法第十一條、第五十六條、第四十七條、第五十一條第五款，判決\n如主文。\n本案經檢察官曾靖雅到庭執行職務\n中      華      民      國      九十一      年      十一  月    二十八  日\n                                      臺灣高雄地方法院刑事第三庭\n                                          法  官    林靜梅\n右正本證明與原本無異。\n如不服本判決，應於判決送達後十日內，向本院提出上訴狀。\n                                          書記官    洪生輝\n中    華    民    國      九十一      年      十一      月     二十九   日\n",
  "structure": {
    "main": "甲○○連續施用第一級毒品，累犯，處有期徒刑捌月。又連續施用第二級毒品，累犯\n，處有期徒刑肆月。應執行有期徒刑拾壹月。",
    "fact": "一、甲○○前因麻醉藥品管理條例、竊盜案件，分別經臺灣屏東地方法院分別判處有\n    期徒刑七月、九月，經接續執行，嗣為一部執行，交付保護管束，已於民國八十\n    六年十一月二十二日執行完畢，再因施用毒品案件，經強制戒治期滿，而由臺灣\n    屏東地方法院檢察署於九十年三月八日以九十年度戒毒偵字第三十八號為不起訴\n    處分確定後，仍不知悔改，於五年內復基於概括之犯意，自九十年十月間起至九\n    十一年六月十五日止，連續在不詳處所，施用第一級毒品海洛因及第二級毒品安\n    非他命，嗣復於九十一年六月二十五日十時二十五分許回溯二十四小時內之某時\n    （不含為警查獲後公權力拘束時間），在不詳處所，施用第一級毒品海洛因及第\n    二級毒品安非他命，為警於同日六時三十分許，在高雄縣鳳山市○○路六○五號\n    前查獲。\n二、案經高雄縣警察局鳳山分局報請臺灣高雄地方法院檢察署檢察官偵查起訴。",
    "reason": "一、訊據被告固對於其自九十年十月間起至九十一年六月十五日止，連續施用第一級\n    毒品海洛因及第二級毒品安非他命之犯罪事實，坦承不諱，惟矢口否認於九十一\n    年六月二十五日即經警查獲當日，有何施用第一、二級毒品之犯行，並辯稱其於\n    查獲前有服用安眠藥云云；然查，被告於九十一年六月二十五日為警查獲當日所\n    採尿液，經送請高雄縣政府衛生局檢驗結果確呈第一級毒品海洛因嗎啡之陽性反\n    應及第二級毒品甲基安非他命之陽性反應，有該局九十一年七月十二日九十一煙\n    檢字第一○一四號之煙毒尿液檢驗成績書一份附卷可稽，足見被告於九十一年六\n    月二十五日十時二十五分許回溯二十四小時內之某時，確有施用第一、二級毒品\n    ，是被告上開所辯顯不足採。再被告前因施用毒品案件，經強制戒治期滿後，業\n    經臺灣屏東地方法院檢察署檢察官於九十年三月八日以九十年度戒毒偵字第三十\n    八號不起訴處分確定，其於五年內復再犯毒品危害防制條例第十條之罪一節，亦\n    有不起訴處分書及刑案資料查註紀錄表附卷可稽。從而，本件事證明確，被告連\n    續施用第一、二級毒品之犯罪事實，洵堪認定。\n二、復按海洛因係屬毒品危害防制條例第二條第二項第一款所稱之第一級毒品，而安\n    非他命則為毒品危害防制條例第二條第二項第二款所稱之第二級毒品，是被告施\n    用海洛因、安非他命之行為，係犯該條例第十條第一項之施用第一級毒品罪、同\n    條例第十條第二項之施用第二級毒品罪。被告分別持有第一級毒品海洛因及第二\n    級毒品安非他命，嗣進而施用之，持有之低度行為應為施用之高度行為所吸收，\n    不另論罪。其前後多次施用第一級毒品及第二級毒品之行為時間密接、犯罪構成\n    要件相同，顯係基於概括犯意為之，應依連續犯規定分別論處，並分別加重其刑\n    。又被告所犯上開連續施用第一級毒品與連續施用第二級毒品二罪間，犯意各別\n    ，行為互殊，應予分論併罰。另被告曾因麻醉藥品管理條例、竊盜案件，分別經\n    臺灣屏東地方法院分別判處有期徒刑七月、九月，經接續執行，嗣為一部執行，\n    交付保護管束，已於八十六年十一月二十二日執行完畢後（此可參卷附之臺灣高\n    等法院被告全國前案紀錄表及被告刑案資料查註紀錄表），五年以內再犯本件有\n    期徒刑以上之罪，為累犯，依刑法第四十七條規定應加重其刑。被告同時有二種\n    刑之加重事由，應依刑法第七十條之規定，遞加其刑。又被告於九十一年六月二\n    十五日十時二十五分許回溯二十四小時內之某時（不含為警查獲後公權力拘束時\n    間），在不詳處所，施用第一級毒品海洛因及第二級毒品部分，雖未據起訴，惟\n    與已起訴部分之犯罪事實，既有裁判上一罪之連續犯關係，依審判不可分之法理\n    ，本院自得一併審究，併此敘明。爰審酌被告前已有施用毒品之前科，並經判刑\n    確定而入監服刑完畢，又因違反毒品危害防制條例案件，經強制戒治期滿，並由\n    檢察官為不起訴處分確定後，仍繼續施用毒品，已如上述，顯見其並無戒除毒害\n    之決心，及其所犯罪行乃自戕之行為，尚無害及他人，犯後坦承部分犯行，態度\n    良好等一切情狀，分別量處如主文所示之刑，並定其應執行刑，以資懲儆。\n據上論斷，應依刑事訴訟法第二百九十九條第一項前段，毒品危害防制條例第十條第\n一項、第二項，刑法第十一條、第五十六條、第四十七條、第五十一條第五款，判決\n如主文。\n本案經檢察官曾靖雅到庭執行職務\n中      華      民      國      九十一      年      十一  月    二十八  日\n                                      臺灣高雄地方法院刑事第三庭\n                                          法  官    林靜梅\n右正本證明與原本無異。\n如不服本判決，應於判決送達後十日內，向本院提出上訴狀。\n                                          書記官    洪生輝"
  },
  "search": "臺灣高雄地方法院刑事判決九十一年度訴字第二七七九號公訴人臺灣高雄地方法院檢察署檢察官被告甲○○右列被告因違反毒品危害防制條例案件，經檢察官提起公訴（九十一年度毒偵字第四二一六號），本院判決如左：主文甲○○連續施用第一級毒品，累犯，處有期徒刑捌月。又連續施用第二級毒品，累犯，處有期徒刑肆月。應執行有期徒刑拾壹月。事實一、甲○○前因麻醉藥品管理條例、竊盜案件，分別經臺灣屏東地方法院分別判處有期徒刑七月、九月，經接續執行，嗣為一部執行，交付保護管束，已於民國八十六年十一月二十二日執行完畢，再因施用毒品案件，經強制戒治期滿，而由臺灣屏東地方法院檢察署於九十年三月八日以九十年度戒毒偵字第三十八號為不起訴處分確定後，仍不知悔改，於五年內復基於概括之犯意，自九十年十月間起至九十一年六月十五日止，連續在不詳處所，施用第一級毒品海洛因及第二級毒品安非他命，嗣復於九十一年六月二十五日十時二十五分許回溯二十四小時內之某時（不含為警查獲後公權力拘束時間），在不詳處所，施用第一級毒品海洛因及第二級毒品安非他命，為警於同日六時三十分許，在高雄縣鳳山市○○路六○五號前查獲。二、案經高雄縣警察局鳳山分局報請臺灣高雄地方法院檢察署檢察官偵查起訴。理由一、訊據被告固對於其自九十年十月間起至九十一年六月十五日止，連續施用第一級毒品海洛因及第二級毒品安非他命之犯罪事實，坦承不諱，惟矢口否認於九十一年六月二十五日即經警查獲當日，有何施用第一、二級毒品之犯行，並辯稱其於查獲前有服用安眠藥云云；然查，被告於九十一年六月二十五日為警查獲當日所採尿液，經送請高雄縣政府衛生局檢驗結果確呈第一級毒品海洛因嗎啡之陽性反應及第二級毒品甲基安非他命之陽性反應，有該局九十一年七月十二日九十一煙檢字第一○一四號之煙毒尿液檢驗成績書一份附卷可稽，足見被告於九十一年六月二十五日十時二十五分許回溯二十四小時內之某時，確有施用第一、二級毒品，是被告上開所辯顯不足採。再被告前因施用毒品案件，經強制戒治期滿後，業經臺灣屏東地方法院檢察署檢察官於九十年三月八日以九十年度戒毒偵字第三十八號不起訴處分確定，其於五年內復再犯毒品危害防制條例第十條之罪一節，亦有不起訴處分書及刑案資料查註紀錄表附卷可稽。從而，本件事證明確，被告連續施用第一、二級毒品之犯罪事實，洵堪認定。二、復按海洛因係屬毒品危害防制條例第二條第二項第一款所稱之第一級毒品，而安非他命則為毒品危害防制條例第二條第二項第二款所稱之第二級毒品，是被告施用海洛因、安非他命之行為，係犯該條例第十條第一項之施用第一級毒品罪、同條例第十條第二項之施用第二級毒品罪。被告分別持有第一級毒品海洛因及第二級毒品安非他命，嗣進而施用之，持有之低度行為應為施用之高度行為所吸收，不另論罪。其前後多次施用第一級毒品及第二級毒品之行為時間密接、犯罪構成要件相同，顯係基於概括犯意為之，應依連續犯規定分別論處，並分別加重其刑。又被告所犯上開連續施用第一級毒品與連續施用第二級毒品二罪間，犯意各別，行為互殊，應予分論併罰。另被告曾因麻醉藥品管理條例、竊盜案件，分別經臺灣屏東地方法院分別判處有期徒刑七月、九月，經接續執行，嗣為一部執行，交付保護管束，已於八十六年十一月二十二日執行完畢後（此可參卷附之臺灣高等法院被告全國前案紀錄表及被告刑案資料查註紀錄表），五年以內再犯本件有期徒刑以上之罪，為累犯，依刑法第四十七條規定應加重其刑。被告同時有二種刑之加重事由，應依刑法第七十條之規定，遞加其刑。又被告於九十一年六月二十五日十時二十五分許回溯二十四小時內之某時（不含為警查獲後公權力拘束時間），在不詳處所，施用第一級毒品海洛因及第二級毒品部分，雖未據起訴，惟與已起訴部分之犯罪事實，既有裁判上一罪之連續犯關係，依審判不可分之法理，本院自得一併審究，併此敘明。爰審酌被告前已有施用毒品之前科，並經判刑確定而入監服刑完畢，又因違反毒品危害防制條例案件，經強制戒治期滿，並由檢察官為不起訴處分確定後，仍繼續施用毒品，已如上述，顯見其並無戒除毒害之決心，及其所犯罪行乃自戕之行為，尚無害及他人，犯後坦承部分犯行，態度良好等一切情狀，分別量處如主文所示之刑，並定其應執行刑，以資懲儆。據上論斷，應依刑事訴訟法第二百九十九條第一項前段，毒品危害防制條例第十條第一項、第二項，刑法第十一條、第五十六條、第四十七條、第五十一條第五款，判決如主文。本案經檢察官曾靖雅到庭執行職務中華民國九十一年十一月二十八日臺灣高雄地方法院刑事第三庭法官林靜梅右正本證明與原本無異。如不服本判決，應於判決送達後十日內，向本院提出上訴狀。書記官洪生輝中華民國九十一年十一月二十九日",
  "characters": {
    "judges": [
      "林靜梅"
    ],
    "prosecutors": [
      "曾靖雅"
    ],
    "lawyers": [

    ],
    "clerks": [
      "洪生輝"
    ],
    "plaintiffs": [

    ],
    "defendants": [
      "甲○○",
      "右列被告因違反毒品危害防制條例案件，經檢察官提起公訴（九十一年度毒偵字第四",
      "二一六號），本院判決如左："
    ],
    "prosecutor_office": [
      "臺灣高雄地方法院檢察署檢察官"
    ],
    "creditors": [

    ],
    "debtors": [

    ],
    "judicial_associate_officer": [

    ]
  },
  "adjudged_at": "2002-11-28",
  "created_at": "2016-02-05 02:06:31",
  "updated_at": "2016-02-05 02:06:31"
}