{
  "identify": "KLD-100-基簡-1446-20111223-1",
  "court": {
    "name": "臺灣基隆地方法院",
    "code": "KLD"
  },
  "division": {
    "name": "刑事",
    "code": "M"
  },
  "year": 100,
  "word": "基簡",
  "number": "1446",
  "jcheck": "1",
  "reason": "詐欺",
  "content": "臺灣基隆地方法院刑事簡易判決       100年度基簡字第1446號\n聲  請  人  臺灣基隆地方法院檢察署檢察官\n被      告  卓奕廷\n上列被告因詐欺案件，經檢察官聲請以簡易判決處刑（100 年度\n偵字第3115號），本院判決如下︰\n    主  文\n卓奕廷意圖為自己不法之所有，以詐術使人將本人之物交付，處\n有期徒刑月，如易科罰金，以新台幣壹仟元折算壹日。\n    事實及理由\n一、本案事實：\n    緣王健軒因無力負擔其母李淑華向遠傳電信股份有限公司（\n    下稱遠傳電信公司）所申辦行動電話門號「0000000000 」\n    （該門號實際使用人係王健軒；下稱系爭門號）之門號費率\n    ，乃於民國99年12月間某日，於奇摩拍賣網上刊登出售行動\n    電話（廠牌：易利信W995 )1 支（下稱系爭手機）及系爭門\n    號之廣告。卓奕廷閱覽出售系爭手機及門號之訊息後，認有\n    機可趁，乃意圖為自己不法之所有，明知自己無力負擔高額\n    之門號費率，且健保卡已遺失，無法辦理系爭門號之過戶手\n    續，仍主動與王健軒聯繫，並佯稱：其願承受系爭門號未到\n    期之合約，且同意負擔王健軒於99年2 月1 日至2 月15日使\n    用系爭門號通話之相關費用，作為購買系爭手機之代價，王\n    健軒聞言後，乃於100 年2 月15日晚間9 時許，與卓奕廷相\n    約至基隆市○○區○○路6 號「遠傳電信基隆仁五門市」營\n    業服務所辦理系爭門號之過戶手續，惟於辦理過戶之際，卓\n    奕廷佯藉忘記帶健保卡，無法辦理過戶之由，要求王健軒先\n    行交付系爭手機及系爭門號SIM 卡，並保證隔日即會將健保\n    卡資料傳真至上開營業服務所辦理後續過戶事宜，致王健軒\n    信以為真，陷於錯誤，將系爭手機及系爭門號SIM 卡交付與\n    卓奕廷。嗣因卓奕廷使用詐得之系爭門號SIM 卡撥打通話後\n    ，均未依約辦理系爭門號之過戶手續及繳納通話費，致上開\n    電信公司向門號申辦人李淑華催繳費用，王健軒發現受騙報\n    警處理後，始循線查悉上情。\n二、證據：\n(一)證人王健軒於警詢、偵查及本院調查時所為之證述。\n(二)證人李淑華於偵查中之證述。\n(三)被告於偵查中所為之供述。\n(四)行動電話付款人帳戶移轉申請書（一退一租）、遠傳電信股\n    份有限公司電信電信費用繳款（客戶收執聯）、卓奕廷身分\n    證影本、王健軒身分證影本、李淑華身分證影本、李淑華健\n    保卡影本各1 份、王健軒手機簡訊照片2 張、遠傳電信股份\n    有限公司100 年8 月13日遠傳(發)字第1001082697號函暨所\n    附系爭門號於100 年1 月之7 月間之帳單明細、行政院衛生\n    署中央健康保險局100 年8 月10日健保承字第1000035070號\n    函1 紙（100 年度偵字第3115號第6 頁至第9 頁、第46頁至\n    第47頁、第57頁、第67頁至第106 頁）、遠傳電信股份有限\n    公司100 年11月29日遠傳（發）字第10011102127 號函暨所\n    附系爭門號100 年2 月份帳單明細1份（本院卷）。\n三、論罪科刑：\n(一)核被告卓奕廷所為，係犯刑法第339 條第1 項之詐欺取財罪。\n(二)爰審酌被告詐騙被害人王健軒交付系爭手機及系爭門號SIM\n    卡供其使用，顯已侵害他人之財產法益，其行顯不可取，併\n    酌以被告迄今尚未與被害人達成和解，賠償被害人所受損害\n    ，及其犯罪後之態度等一切情狀，量處如主文所示之刑，並\n    諭知易科罰金之折算標準，以資儆懲。又聲請簡易判決處刑\n    書所載被害人王健軒交付系爭手機及系爭門號SIM 卡之時間\n    為「100 年2 月16日晚間9 時許」，惟經本院訊問證人即被\n    害人王健軒，其乃具結證稱係為「100 年2 月15日晚間9 時\n    許」，有訊問筆錄存卷可參，故聲請簡易判決處刑書關此部\n    分，應予更正，附此敘明。\n(三)本案被告自被害人王健軒處詐得系爭手機及系爭門號SIM 卡\n    後，其詐欺取財行為即已完成而既遂，其嗣後就系爭門號\n    SIM 卡予以使用而取得通話利益之行為，客觀及評價上均應\n    認係屬另一行為，而屬另涉犯刑法第339 條第2 項之詐欺得\n    利罪嫌之範疇，然此部分未經檢察官提起公訴，本院自不得\n    併予審理，該部分依法仍應由檢察官另行偵處，併予敘明。\n四、依刑事訴訟法第449 條第1 項前段，刑法第339 條第1 項、\n    第41條第1 項前段，刑法施行法第1 條之1 ，逕以簡易判決\n    處刑如主文。\n五、如不服本件判決，得自收受送達之日起10日內，向本院提出\n    上訴書狀，上訴於本院第二審合議庭。\n中    華    民    國   100    年    12    月    23    日\n                  基隆簡易庭法  官  周霙蘭\n以上正本證明與原本無異。\n如不服本判決，應於判決送達後10日內，向本院提出上訴書狀，\n敘述上訴理由，上訴於本院合議庭，並按他造當事人之人數附具\n繕本。\n中    華    民    國   100    年    12    月    23    日\n                            書記官  翁其良\n論罪法條：\n中華民國刑法第339條\n（普通詐欺罪）\n意圖為自己或第三人不法之所有，以詐術使人將本人或第三人之\n物交付者，處 5 年以下有期徒刑、拘役或科或併科 1 千元以下\n罰金。\n以前項方法得財產上不法之利益或使第三人得之者，亦同。\n前二項之未遂犯罰之。",
  "structure": {
    "main": "卓奕廷意圖為自己不法之所有，以詐術使人將本人之物交付，處\n有期徒刑月，如易科罰金，以新台幣壹仟元折算壹日。",
    "fact": "一、本案事實：\n    緣王健軒因無力負擔其母李淑華向遠傳電信股份有限公司（\n    下稱遠傳電信公司）所申辦行動電話門號「0000000000 」\n    （該門號實際使用人係王健軒；下稱系爭門號）之門號費率\n    ，乃於民國99年12月間某日，於奇摩拍賣網上刊登出售行動\n    電話（廠牌：易利信W995 )1 支（下稱系爭手機）及系爭門\n    號之廣告。卓奕廷閱覽出售系爭手機及門號之訊息後，認有\n    機可趁，乃意圖為自己不法之所有，明知自己無力負擔高額\n    之門號費率，且健保卡已遺失，無法辦理系爭門號之過戶手\n    續，仍主動與王健軒聯繫，並佯稱：其願承受系爭門號未到\n    期之合約，且同意負擔王健軒於99年2 月1 日至2 月15日使\n    用系爭門號通話之相關費用，作為購買系爭手機之代價，王\n    健軒聞言後，乃於100 年2 月15日晚間9 時許，與卓奕廷相\n    約至基隆市○○區○○路6 號「遠傳電信基隆仁五門市」營\n    業服務所辦理系爭門號之過戶手續，惟於辦理過戶之際，卓\n    奕廷佯藉忘記帶健保卡，無法辦理過戶之由，要求王健軒先\n    行交付系爭手機及系爭門號SIM 卡，並保證隔日即會將健保\n    卡資料傳真至上開營業服務所辦理後續過戶事宜，致王健軒\n    信以為真，陷於錯誤，將系爭手機及系爭門號SIM 卡交付與\n    卓奕廷。嗣因卓奕廷使用詐得之系爭門號SIM 卡撥打通話後\n    ，均未依約辦理系爭門號之過戶手續及繳納通話費，致上開\n    電信公司向門號申辦人李淑華催繳費用，王健軒發現受騙報\n    警處理後，始循線查悉上情。\n二、證據：\n(一)證人王健軒於警詢、偵查及本院調查時所為之證述。\n(二)證人李淑華於偵查中之證述。\n(三)被告於偵查中所為之供述。\n(四)行動電話付款人帳戶移轉申請書（一退一租）、遠傳電信股\n    份有限公司電信電信費用繳款（客戶收執聯）、卓奕廷身分\n    證影本、王健軒身分證影本、李淑華身分證影本、李淑華健\n    保卡影本各1 份、王健軒手機簡訊照片2 張、遠傳電信股份\n    有限公司100 年8 月13日遠傳(發)字第1001082697號函暨所\n    附系爭門號於100 年1 月之7 月間之帳單明細、行政院衛生\n    署中央健康保險局100 年8 月10日健保承字第1000035070號\n    函1 紙（100 年度偵字第3115號第6 頁至第9 頁、第46頁至\n    第47頁、第57頁、第67頁至第106 頁）、遠傳電信股份有限\n    公司100 年11月29日遠傳（發）字第10011102127 號函暨所\n    附系爭門號100 年2 月份帳單明細1份（本院卷）。\n三、論罪科刑：\n(一)核被告卓奕廷所為，係犯刑法第339 條第1 項之詐欺取財罪。\n(二)爰審酌被告詐騙被害人王健軒交付系爭手機及系爭門號SIM\n    卡供其使用，顯已侵害他人之財產法益，其行顯不可取，併\n    酌以被告迄今尚未與被害人達成和解，賠償被害人所受損害\n    ，及其犯罪後之態度等一切情狀，量處如主文所示之刑，並\n    諭知易科罰金之折算標準，以資儆懲。又聲請簡易判決處刑\n    書所載被害人王健軒交付系爭手機及系爭門號SIM 卡之時間\n    為「100 年2 月16日晚間9 時許」，惟經本院訊問證人即被\n    害人王健軒，其乃具結證稱係為「100 年2 月15日晚間9 時\n    許」，有訊問筆錄存卷可參，故聲請簡易判決處刑書關此部\n    分，應予更正，附此敘明。\n(三)本案被告自被害人王健軒處詐得系爭手機及系爭門號SIM 卡\n    後，其詐欺取財行為即已完成而既遂，其嗣後就系爭門號\n    SIM 卡予以使用而取得通話利益之行為，客觀及評價上均應\n    認係屬另一行為，而屬另涉犯刑法第339 條第2 項之詐欺得\n    利罪嫌之範疇，然此部分未經檢察官提起公訴，本院自不得\n    併予審理，該部分依法仍應由檢察官另行偵處，併予敘明。\n四、依刑事訴訟法第449 條第1 項前段，刑法第339 條第1 項、\n    第41條第1 項前段，刑法施行法第1 條之1 ，逕以簡易判決\n    處刑如主文。\n五、如不服本件判決，得自收受送達之日起10日內，向本院提出\n    上訴書狀，上訴於本院第二審合議庭。",
    "reason": "一、本案事實：\n    緣王健軒因無力負擔其母李淑華向遠傳電信股份有限公司（\n    下稱遠傳電信公司）所申辦行動電話門號「0000000000 」\n    （該門號實際使用人係王健軒；下稱系爭門號）之門號費率\n    ，乃於民國99年12月間某日，於奇摩拍賣網上刊登出售行動\n    電話（廠牌：易利信W995 )1 支（下稱系爭手機）及系爭門\n    號之廣告。卓奕廷閱覽出售系爭手機及門號之訊息後，認有\n    機可趁，乃意圖為自己不法之所有，明知自己無力負擔高額\n    之門號費率，且健保卡已遺失，無法辦理系爭門號之過戶手\n    續，仍主動與王健軒聯繫，並佯稱：其願承受系爭門號未到\n    期之合約，且同意負擔王健軒於99年2 月1 日至2 月15日使\n    用系爭門號通話之相關費用，作為購買系爭手機之代價，王\n    健軒聞言後，乃於100 年2 月15日晚間9 時許，與卓奕廷相\n    約至基隆市○○區○○路6 號「遠傳電信基隆仁五門市」營\n    業服務所辦理系爭門號之過戶手續，惟於辦理過戶之際，卓\n    奕廷佯藉忘記帶健保卡，無法辦理過戶之由，要求王健軒先\n    行交付系爭手機及系爭門號SIM 卡，並保證隔日即會將健保\n    卡資料傳真至上開營業服務所辦理後續過戶事宜，致王健軒\n    信以為真，陷於錯誤，將系爭手機及系爭門號SIM 卡交付與\n    卓奕廷。嗣因卓奕廷使用詐得之系爭門號SIM 卡撥打通話後\n    ，均未依約辦理系爭門號之過戶手續及繳納通話費，致上開\n    電信公司向門號申辦人李淑華催繳費用，王健軒發現受騙報\n    警處理後，始循線查悉上情。\n二、證據：\n(一)證人王健軒於警詢、偵查及本院調查時所為之證述。\n(二)證人李淑華於偵查中之證述。\n(三)被告於偵查中所為之供述。\n(四)行動電話付款人帳戶移轉申請書（一退一租）、遠傳電信股\n    份有限公司電信電信費用繳款（客戶收執聯）、卓奕廷身分\n    證影本、王健軒身分證影本、李淑華身分證影本、李淑華健\n    保卡影本各1 份、王健軒手機簡訊照片2 張、遠傳電信股份\n    有限公司100 年8 月13日遠傳(發)字第1001082697號函暨所\n    附系爭門號於100 年1 月之7 月間之帳單明細、行政院衛生\n    署中央健康保險局100 年8 月10日健保承字第1000035070號\n    函1 紙（100 年度偵字第3115號第6 頁至第9 頁、第46頁至\n    第47頁、第57頁、第67頁至第106 頁）、遠傳電信股份有限\n    公司100 年11月29日遠傳（發）字第10011102127 號函暨所\n    附系爭門號100 年2 月份帳單明細1份（本院卷）。\n三、論罪科刑：\n(一)核被告卓奕廷所為，係犯刑法第339 條第1 項之詐欺取財罪。\n(二)爰審酌被告詐騙被害人王健軒交付系爭手機及系爭門號SIM\n    卡供其使用，顯已侵害他人之財產法益，其行顯不可取，併\n    酌以被告迄今尚未與被害人達成和解，賠償被害人所受損害\n    ，及其犯罪後之態度等一切情狀，量處如主文所示之刑，並\n    諭知易科罰金之折算標準，以資儆懲。又聲請簡易判決處刑\n    書所載被害人王健軒交付系爭手機及系爭門號SIM 卡之時間\n    為「100 年2 月16日晚間9 時許」，惟經本院訊問證人即被\n    害人王健軒，其乃具結證稱係為「100 年2 月15日晚間9 時\n    許」，有訊問筆錄存卷可參，故聲請簡易判決處刑書關此部\n    分，應予更正，附此敘明。\n(三)本案被告自被害人王健軒處詐得系爭手機及系爭門號SIM 卡\n    後，其詐欺取財行為即已完成而既遂，其嗣後就系爭門號\n    SIM 卡予以使用而取得通話利益之行為，客觀及評價上均應\n    認係屬另一行為，而屬另涉犯刑法第339 條第2 項之詐欺得\n    利罪嫌之範疇，然此部分未經檢察官提起公訴，本院自不得\n    併予審理，該部分依法仍應由檢察官另行偵處，併予敘明。\n四、依刑事訴訟法第449 條第1 項前段，刑法第339 條第1 項、\n    第41條第1 項前段，刑法施行法第1 條之1 ，逕以簡易判決\n    處刑如主文。\n五、如不服本件判決，得自收受送達之日起10日內，向本院提出\n    上訴書狀，上訴於本院第二審合議庭。"
  },
  "search": "臺灣基隆地方法院刑事簡易判決100年度基簡字第1446號聲請人臺灣基隆地方法院檢察署檢察官被告卓奕廷上列被告因詐欺案件，經檢察官聲請以簡易判決處刑（100年度偵字第3115號），本院判決如下︰主文卓奕廷意圖為自己不法之所有，以詐術使人將本人之物交付，處有期徒刑月，如易科罰金，以新台幣壹仟元折算壹日。事實及理由一、本案事實：緣王健軒因無力負擔其母李淑華向遠傳電信股份有限公司（下稱遠傳電信公司）所申辦行動電話門號「0000000000」（該門號實際使用人係王健軒；下稱系爭門號）之門號費率，乃於民國99年12月間某日，於奇摩拍賣網上刊登出售行動電話（廠牌：易利信W995)1支（下稱系爭手機）及系爭門號之廣告。卓奕廷閱覽出售系爭手機及門號之訊息後，認有機可趁，乃意圖為自己不法之所有，明知自己無力負擔高額之門號費率，且健保卡已遺失，無法辦理系爭門號之過戶手續，仍主動與王健軒聯繫，並佯稱：其願承受系爭門號未到期之合約，且同意負擔王健軒於99年2月1日至2月15日使用系爭門號通話之相關費用，作為購買系爭手機之代價，王健軒聞言後，乃於100年2月15日晚間9時許，與卓奕廷相約至基隆市○○區○○路6號「遠傳電信基隆仁五門市」營業服務所辦理系爭門號之過戶手續，惟於辦理過戶之際，卓奕廷佯藉忘記帶健保卡，無法辦理過戶之由，要求王健軒先行交付系爭手機及系爭門號SIM卡，並保證隔日即會將健保卡資料傳真至上開營業服務所辦理後續過戶事宜，致王健軒信以為真，陷於錯誤，將系爭手機及系爭門號SIM卡交付與卓奕廷。嗣因卓奕廷使用詐得之系爭門號SIM卡撥打通話後，均未依約辦理系爭門號之過戶手續及繳納通話費，致上開電信公司向門號申辦人李淑華催繳費用，王健軒發現受騙報警處理後，始循線查悉上情。二、證據：(一)證人王健軒於警詢、偵查及本院調查時所為之證述。(二)證人李淑華於偵查中之證述。(三)被告於偵查中所為之供述。(四)行動電話付款人帳戶移轉申請書（一退一租）、遠傳電信股份有限公司電信電信費用繳款（客戶收執聯）、卓奕廷身分證影本、王健軒身分證影本、李淑華身分證影本、李淑華健保卡影本各1份、王健軒手機簡訊照片2張、遠傳電信股份有限公司100年8月13日遠傳(發)字第1001082697號函暨所附系爭門號於100年1月之7月間之帳單明細、行政院衛生署中央健康保險局100年8月10日健保承字第1000035070號函1紙（100年度偵字第3115號第6頁至第9頁、第46頁至第47頁、第57頁、第67頁至第106頁）、遠傳電信股份有限公司100年11月29日遠傳（發）字第10011102127號函暨所附系爭門號100年2月份帳單明細1份（本院卷）。三、論罪科刑：(一)核被告卓奕廷所為，係犯刑法第339條第1項之詐欺取財罪。(二)爰審酌被告詐騙被害人王健軒交付系爭手機及系爭門號SIM卡供其使用，顯已侵害他人之財產法益，其行顯不可取，併酌以被告迄今尚未與被害人達成和解，賠償被害人所受損害，及其犯罪後之態度等一切情狀，量處如主文所示之刑，並諭知易科罰金之折算標準，以資儆懲。又聲請簡易判決處刑書所載被害人王健軒交付系爭手機及系爭門號SIM卡之時間為「100年2月16日晚間9時許」，惟經本院訊問證人即被害人王健軒，其乃具結證稱係為「100年2月15日晚間9時許」，有訊問筆錄存卷可參，故聲請簡易判決處刑書關此部分，應予更正，附此敘明。(三)本案被告自被害人王健軒處詐得系爭手機及系爭門號SIM卡後，其詐欺取財行為即已完成而既遂，其嗣後就系爭門號SIM卡予以使用而取得通話利益之行為，客觀及評價上均應認係屬另一行為，而屬另涉犯刑法第339條第2項之詐欺得利罪嫌之範疇，然此部分未經檢察官提起公訴，本院自不得併予審理，該部分依法仍應由檢察官另行偵處，併予敘明。四、依刑事訴訟法第449條第1項前段，刑法第339條第1項、第41條第1項前段，刑法施行法第1條之1，逕以簡易判決處刑如主文。五、如不服本件判決，得自收受送達之日起10日內，向本院提出上訴書狀，上訴於本院第二審合議庭。中華民國100年12月23日基隆簡易庭法官周霙蘭以上正本證明與原本無異。如不服本判決，應於判決送達後10日內，向本院提出上訴書狀，敘述上訴理由，上訴於本院合議庭，並按他造當事人之人數附具繕本。中華民國100年12月23日書記官翁其良論罪法條：中華民國刑法第339條（普通詐欺罪）意圖為自己或第三人不法之所有，以詐術使人將本人或第三人之物交付者，處5年以下有期徒刑、拘役或科或併科1千元以下罰金。以前項方法得財產上不法之利益或使第三人得之者，亦同。前二項之未遂犯罰之。",
  "characters": {
    "judges": [
      "周霙蘭"
    ],
    "prosecutors": [

    ],
    "lawyers": [

    ],
    "clerks": [
      "翁其良"
    ],
    "plaintiffs": [

    ],
    "defendants": [
      "卓奕廷"
    ],
    "prosecutor_office": [
      "臺灣基隆地方法院檢察署檢察官"
    ],
    "creditors": [

    ],
    "debtors": [

    ],
    "judicial_associate_officer": [

    ]
  },
  "adjudged_at": "2011-12-23",
  "created_at": "2016-02-13 14:42:56",
  "updated_at": "2016-02-13 14:42:56"
}