{
  "identify": "SLD-100-審簡-1567-20111223-1",
  "court": {
    "name": "臺灣士林地方法院",
    "code": "SLD"
  },
  "division": {
    "name": "刑事",
    "code": "M"
  },
  "year": 100,
  "word": "審簡",
  "number": "1567",
  "jcheck": "1",
  "reason": "竊盜",
  "content": "臺灣士林地方法院刑事簡易判決       100年度審簡字第1567號\n公  訴  人  臺灣士林地方法院檢察署檢察官\n被      告  吳家瑋榮\n上列被告因竊盜案件，經檢察官提起公訴（100 年度偵字第1143\n1 號），本院受理後（100 年度審易字第2292號），認被告經本\n院傳喚固未到庭，惟於警詢、偵查中既已自白犯行，且依卷存證\n據亦足認定其犯罪，本院認宜以簡易判決處刑，經改分後逕以簡\n易判決處刑如下：\n    主  文\n吳家瑋榮攜帶兇器竊盜，處有期徒刑陸月，如易科罰金，以新臺\n幣壹仟元折算壹日。緩刑貳年，緩刑期間付保護管束，並應向執\n行檢察官指定之政府機關、政府機構、行政法人、社區或其他符\n合公益目的之機構或團體提供壹佰小時之義務勞務。扣案之十字\n螺絲起子貳支、一字螺絲起子壹支、尖嘴鉗壹支均沒收。\n    事實及理由\n一、本件犯罪事實及證據，除引用檢察官起訴書之記載（如附件\n    ）外，另更正並補充如下：起訴書證據並所犯法條欄一第5\n    行所載「電桿牌位置對照圖」應更正為「電桿牌位置對照表\n    」。\n二、按刑法第321 條第1 項第3 款之攜帶兇器竊盜罪，係以行為\n    人攜帶兇器竊盜為其加重條件，此所謂兇器，其種類並無限\n    制，凡客觀上足對人之生命、身體、安全構成威脅，具有危\n    險性之兇器均屬之，且只須行竊時攜帶此種具有危險性之兇\n    器為已足，並不以攜帶之初有行兇之意圖為必要（最高法院\n    79年台上字第5253號判例參照）。查本件被告為竊盜犯行時\n    所攜帶之十字螺絲起子2 支、一字螺絲起子1 支及尖嘴鉗1\n    支，均為金屬材質，既可將緊密固定於電線桿上之電桿牌拆\n    卸拔取，堪認係屬質地堅硬之器具，如持以行兇，依照一般\n    社會通念，足以對人之生命、身體產生危害，自屬兇器無訛\n    。\n三、核被告吳家瑋榮所為，係犯刑法第321 條第1 項第3 款之攜\n    帶兇器竊盜罪。爰審酌被告無前科紀錄，素行尚佳，本件係\n    一時輕率失慮，而為竊取他人財物犯行，衡其所為固無足取\n    ，惟念其犯後已知坦承犯行，態度良好，所竊財物均經被害\n    人依法領回，告訴代理人蔡邦熙並於本院民國100 年12月5\n    日準備程序中當庭表示：「法院怎麼判，我們都沒意見，但\n    是對電力公司來講，竊盜的部分還是要依法提出告訴，而且\n    本件電桿牌成本只有10元，被告偷了六塊，損失很小，警察\n    為何要移送，我們也不知道。」等語，可知被告所竊財物價\n    值甚微，被害人財產損失有限，兼衡被告犯罪之動機、目的\n    、手段、品行、智識程度、家庭經濟狀況等一切情狀，量處\n    如主文所示之刑，並諭知如易科罰金之折算標準，以資懲儆\n    。\n四、末查，被告前未曾因故意犯罪受有期徒刑以上刑之宣告，有\n    臺灣高等法院被告前案紀錄表1 份附卷可考，其因一時失慮\n    ，偶罹刑典，且犯後已坦承犯行，態度良好，所竊財物已經\n    被害人依法領回，業如前述，本院衡酌上情，因認被告經此\n    偵審程序及科刑教訓後，應當知所警惕，信無再犯之虞，前\n    開所宣告之刑以暫不執行為適當，爰依刑法第74條第1 項第\n    1 款之規定，併予宣告緩刑如主文所示之期間，以觀後效，\n    用啟自新。並諭知被告於緩刑期間應付保護管束，且應向執\n    行檢察官指定之政府機關、政府機構、行政法人、社區或其\n    他符合公益目的之機構或團體提供如主文所示之義務勞務時\n    數。以上為緩刑宣告附帶之條件，依刑法第75條之1 第1 項\n    第4 款規定，違反上開之負擔情節重大，足認原宣告之緩刑\n    難收其預期效果，而有執行刑罰之必要者，得撤銷緩刑之宣\n    告。\n五、至本件扣案之十字螺絲起子2 支、一字螺絲起子1 支、尖嘴\n    鉗1 支均為被告吳家瑋榮所有供本件犯罪所用之物，業據其\n    於警詢及偵查時供承明確，乃依刑法第38條第1 項第2 款、\n    第3 項規定均宣告沒收。\n六、依刑事訴訟法第449 條第2 項、第3 項、第450 條第1 項、\n    第454 條第2 項，刑法第321 條第1 項第3 款、第41條第1\n    項前段、第74條第1 項第1 款、第2 項第5 款、第93條第1\n    項第2 款、第38條第1 項第2 款、第3 項，刑法施行法第1\n    條之1 第1 項、第2 項前段，逕以簡易判決處如主文所示之\n    刑。\n本案經檢察官許梨雯到庭執行職務。\n中    華    民    國  100     年    12    月    23    日\n                  刑事第一庭法  官  徐文瑞\n以上正本證明與原本無異。\n如不服本判決，得於判決書送達之日起10日內，以書狀敘述理由\n，向本院提出上訴。\n                            書記官  張茹茵\n中    華    民    國   100    年    12    月    26    日\n附錄本案論罪科刑法條全文：\n刑法第321條\n（加重竊盜罪）\n犯竊盜罪而有下列情形之一者，處 6 月以上、5 年以下有期徒\n刑，得併科新臺幣 10 萬元以下罰金：\n一、侵入住宅或有人居住之建築物、船艦或隱匿其內而犯之者。\n二、毀越門扇、牆垣或其他安全設備而犯之者。\n三、攜帶兇器而犯之者。\n四、結夥三人以上而犯之者。\n五、乘火災、水災或其他災害之際而犯之者。\n六、在車站、埠頭、航空站或其他供水、陸、空公眾運輸之舟、\n    車、航空機內而犯之者。\n前項之未遂犯罰之。",
  "structure": {
    "main": "吳家瑋榮攜帶兇器竊盜，處有期徒刑陸月，如易科罰金，以新臺\n幣壹仟元折算壹日。緩刑貳年，緩刑期間付保護管束，並應向執\n行檢察官指定之政府機關、政府機構、行政法人、社區或其他符\n合公益目的之機構或團體提供壹佰小時之義務勞務。扣案之十字\n螺絲起子貳支、一字螺絲起子壹支、尖嘴鉗壹支均沒收。",
    "fact": "一、本件犯罪事實及證據，除引用檢察官起訴書之記載（如附件\n    ）外，另更正並補充如下：起訴書證據並所犯法條欄一第5\n    行所載「電桿牌位置對照圖」應更正為「電桿牌位置對照表\n    」。\n二、按刑法第321 條第1 項第3 款之攜帶兇器竊盜罪，係以行為\n    人攜帶兇器竊盜為其加重條件，此所謂兇器，其種類並無限\n    制，凡客觀上足對人之生命、身體、安全構成威脅，具有危\n    險性之兇器均屬之，且只須行竊時攜帶此種具有危險性之兇\n    器為已足，並不以攜帶之初有行兇之意圖為必要（最高法院\n    79年台上字第5253號判例參照）。查本件被告為竊盜犯行時\n    所攜帶之十字螺絲起子2 支、一字螺絲起子1 支及尖嘴鉗1\n    支，均為金屬材質，既可將緊密固定於電線桿上之電桿牌拆\n    卸拔取，堪認係屬質地堅硬之器具，如持以行兇，依照一般\n    社會通念，足以對人之生命、身體產生危害，自屬兇器無訛\n    。\n三、核被告吳家瑋榮所為，係犯刑法第321 條第1 項第3 款之攜\n    帶兇器竊盜罪。爰審酌被告無前科紀錄，素行尚佳，本件係\n    一時輕率失慮，而為竊取他人財物犯行，衡其所為固無足取\n    ，惟念其犯後已知坦承犯行，態度良好，所竊財物均經被害\n    人依法領回，告訴代理人蔡邦熙並於本院民國100 年12月5\n    日準備程序中當庭表示：「法院怎麼判，我們都沒意見，但\n    是對電力公司來講，竊盜的部分還是要依法提出告訴，而且\n    本件電桿牌成本只有10元，被告偷了六塊，損失很小，警察\n    為何要移送，我們也不知道。」等語，可知被告所竊財物價\n    值甚微，被害人財產損失有限，兼衡被告犯罪之動機、目的\n    、手段、品行、智識程度、家庭經濟狀況等一切情狀，量處\n    如主文所示之刑，並諭知如易科罰金之折算標準，以資懲儆\n    。\n四、末查，被告前未曾因故意犯罪受有期徒刑以上刑之宣告，有\n    臺灣高等法院被告前案紀錄表1 份附卷可考，其因一時失慮\n    ，偶罹刑典，且犯後已坦承犯行，態度良好，所竊財物已經\n    被害人依法領回，業如前述，本院衡酌上情，因認被告經此\n    偵審程序及科刑教訓後，應當知所警惕，信無再犯之虞，前\n    開所宣告之刑以暫不執行為適當，爰依刑法第74條第1 項第\n    1 款之規定，併予宣告緩刑如主文所示之期間，以觀後效，\n    用啟自新。並諭知被告於緩刑期間應付保護管束，且應向執\n    行檢察官指定之政府機關、政府機構、行政法人、社區或其\n    他符合公益目的之機構或團體提供如主文所示之義務勞務時\n    數。以上為緩刑宣告附帶之條件，依刑法第75條之1 第1 項\n    第4 款規定，違反上開之負擔情節重大，足認原宣告之緩刑\n    難收其預期效果，而有執行刑罰之必要者，得撤銷緩刑之宣\n    告。\n五、至本件扣案之十字螺絲起子2 支、一字螺絲起子1 支、尖嘴\n    鉗1 支均為被告吳家瑋榮所有供本件犯罪所用之物，業據其\n    於警詢及偵查時供承明確，乃依刑法第38條第1 項第2 款、\n    第3 項規定均宣告沒收。\n六、依刑事訴訟法第449 條第2 項、第3 項、第450 條第1 項、\n    第454 條第2 項，刑法第321 條第1 項第3 款、第41條第1\n    項前段、第74條第1 項第1 款、第2 項第5 款、第93條第1\n    項第2 款、第38條第1 項第2 款、第3 項，刑法施行法第1\n    條之1 第1 項、第2 項前段，逕以簡易判決處如主文所示之\n    刑。\n本案經檢察官許梨雯到庭執行職務。",
    "reason": "一、本件犯罪事實及證據，除引用檢察官起訴書之記載（如附件\n    ）外，另更正並補充如下：起訴書證據並所犯法條欄一第5\n    行所載「電桿牌位置對照圖」應更正為「電桿牌位置對照表\n    」。\n二、按刑法第321 條第1 項第3 款之攜帶兇器竊盜罪，係以行為\n    人攜帶兇器竊盜為其加重條件，此所謂兇器，其種類並無限\n    制，凡客觀上足對人之生命、身體、安全構成威脅，具有危\n    險性之兇器均屬之，且只須行竊時攜帶此種具有危險性之兇\n    器為已足，並不以攜帶之初有行兇之意圖為必要（最高法院\n    79年台上字第5253號判例參照）。查本件被告為竊盜犯行時\n    所攜帶之十字螺絲起子2 支、一字螺絲起子1 支及尖嘴鉗1\n    支，均為金屬材質，既可將緊密固定於電線桿上之電桿牌拆\n    卸拔取，堪認係屬質地堅硬之器具，如持以行兇，依照一般\n    社會通念，足以對人之生命、身體產生危害，自屬兇器無訛\n    。\n三、核被告吳家瑋榮所為，係犯刑法第321 條第1 項第3 款之攜\n    帶兇器竊盜罪。爰審酌被告無前科紀錄，素行尚佳，本件係\n    一時輕率失慮，而為竊取他人財物犯行，衡其所為固無足取\n    ，惟念其犯後已知坦承犯行，態度良好，所竊財物均經被害\n    人依法領回，告訴代理人蔡邦熙並於本院民國100 年12月5\n    日準備程序中當庭表示：「法院怎麼判，我們都沒意見，但\n    是對電力公司來講，竊盜的部分還是要依法提出告訴，而且\n    本件電桿牌成本只有10元，被告偷了六塊，損失很小，警察\n    為何要移送，我們也不知道。」等語，可知被告所竊財物價\n    值甚微，被害人財產損失有限，兼衡被告犯罪之動機、目的\n    、手段、品行、智識程度、家庭經濟狀況等一切情狀，量處\n    如主文所示之刑，並諭知如易科罰金之折算標準，以資懲儆\n    。\n四、末查，被告前未曾因故意犯罪受有期徒刑以上刑之宣告，有\n    臺灣高等法院被告前案紀錄表1 份附卷可考，其因一時失慮\n    ，偶罹刑典，且犯後已坦承犯行，態度良好，所竊財物已經\n    被害人依法領回，業如前述，本院衡酌上情，因認被告經此\n    偵審程序及科刑教訓後，應當知所警惕，信無再犯之虞，前\n    開所宣告之刑以暫不執行為適當，爰依刑法第74條第1 項第\n    1 款之規定，併予宣告緩刑如主文所示之期間，以觀後效，\n    用啟自新。並諭知被告於緩刑期間應付保護管束，且應向執\n    行檢察官指定之政府機關、政府機構、行政法人、社區或其\n    他符合公益目的之機構或團體提供如主文所示之義務勞務時\n    數。以上為緩刑宣告附帶之條件，依刑法第75條之1 第1 項\n    第4 款規定，違反上開之負擔情節重大，足認原宣告之緩刑\n    難收其預期效果，而有執行刑罰之必要者，得撤銷緩刑之宣\n    告。\n五、至本件扣案之十字螺絲起子2 支、一字螺絲起子1 支、尖嘴\n    鉗1 支均為被告吳家瑋榮所有供本件犯罪所用之物，業據其\n    於警詢及偵查時供承明確，乃依刑法第38條第1 項第2 款、\n    第3 項規定均宣告沒收。\n六、依刑事訴訟法第449 條第2 項、第3 項、第450 條第1 項、\n    第454 條第2 項，刑法第321 條第1 項第3 款、第41條第1\n    項前段、第74條第1 項第1 款、第2 項第5 款、第93條第1\n    項第2 款、第38條第1 項第2 款、第3 項，刑法施行法第1\n    條之1 第1 項、第2 項前段，逕以簡易判決處如主文所示之\n    刑。\n本案經檢察官許梨雯到庭執行職務。"
  },
  "search": "臺灣士林地方法院刑事簡易判決100年度審簡字第1567號公訴人臺灣士林地方法院檢察署檢察官被告吳家瑋榮上列被告因竊盜案件，經檢察官提起公訴（100年度偵字第11431號），本院受理後（100年度審易字第2292號），認被告經本院傳喚固未到庭，惟於警詢、偵查中既已自白犯行，且依卷存證據亦足認定其犯罪，本院認宜以簡易判決處刑，經改分後逕以簡易判決處刑如下：主文吳家瑋榮攜帶兇器竊盜，處有期徒刑陸月，如易科罰金，以新臺幣壹仟元折算壹日。緩刑貳年，緩刑期間付保護管束，並應向執行檢察官指定之政府機關、政府機構、行政法人、社區或其他符合公益目的之機構或團體提供壹佰小時之義務勞務。扣案之十字螺絲起子貳支、一字螺絲起子壹支、尖嘴鉗壹支均沒收。事實及理由一、本件犯罪事實及證據，除引用檢察官起訴書之記載（如附件）外，另更正並補充如下：起訴書證據並所犯法條欄一第5行所載「電桿牌位置對照圖」應更正為「電桿牌位置對照表」。二、按刑法第321條第1項第3款之攜帶兇器竊盜罪，係以行為人攜帶兇器竊盜為其加重條件，此所謂兇器，其種類並無限制，凡客觀上足對人之生命、身體、安全構成威脅，具有危險性之兇器均屬之，且只須行竊時攜帶此種具有危險性之兇器為已足，並不以攜帶之初有行兇之意圖為必要（最高法院79年台上字第5253號判例參照）。查本件被告為竊盜犯行時所攜帶之十字螺絲起子2支、一字螺絲起子1支及尖嘴鉗1支，均為金屬材質，既可將緊密固定於電線桿上之電桿牌拆卸拔取，堪認係屬質地堅硬之器具，如持以行兇，依照一般社會通念，足以對人之生命、身體產生危害，自屬兇器無訛。三、核被告吳家瑋榮所為，係犯刑法第321條第1項第3款之攜帶兇器竊盜罪。爰審酌被告無前科紀錄，素行尚佳，本件係一時輕率失慮，而為竊取他人財物犯行，衡其所為固無足取，惟念其犯後已知坦承犯行，態度良好，所竊財物均經被害人依法領回，告訴代理人蔡邦熙並於本院民國100年12月5日準備程序中當庭表示：「法院怎麼判，我們都沒意見，但是對電力公司來講，竊盜的部分還是要依法提出告訴，而且本件電桿牌成本只有10元，被告偷了六塊，損失很小，警察為何要移送，我們也不知道。」等語，可知被告所竊財物價值甚微，被害人財產損失有限，兼衡被告犯罪之動機、目的、手段、品行、智識程度、家庭經濟狀況等一切情狀，量處如主文所示之刑，並諭知如易科罰金之折算標準，以資懲儆。四、末查，被告前未曾因故意犯罪受有期徒刑以上刑之宣告，有臺灣高等法院被告前案紀錄表1份附卷可考，其因一時失慮，偶罹刑典，且犯後已坦承犯行，態度良好，所竊財物已經被害人依法領回，業如前述，本院衡酌上情，因認被告經此偵審程序及科刑教訓後，應當知所警惕，信無再犯之虞，前開所宣告之刑以暫不執行為適當，爰依刑法第74條第1項第1款之規定，併予宣告緩刑如主文所示之期間，以觀後效，用啟自新。並諭知被告於緩刑期間應付保護管束，且應向執行檢察官指定之政府機關、政府機構、行政法人、社區或其他符合公益目的之機構或團體提供如主文所示之義務勞務時數。以上為緩刑宣告附帶之條件，依刑法第75條之1第1項第4款規定，違反上開之負擔情節重大，足認原宣告之緩刑難收其預期效果，而有執行刑罰之必要者，得撤銷緩刑之宣告。五、至本件扣案之十字螺絲起子2支、一字螺絲起子1支、尖嘴鉗1支均為被告吳家瑋榮所有供本件犯罪所用之物，業據其於警詢及偵查時供承明確，乃依刑法第38條第1項第2款、第3項規定均宣告沒收。六、依刑事訴訟法第449條第2項、第3項、第450條第1項、第454條第2項，刑法第321條第1項第3款、第41條第1項前段、第74條第1項第1款、第2項第5款、第93條第1項第2款、第38條第1項第2款、第3項，刑法施行法第1條之1第1項、第2項前段，逕以簡易判決處如主文所示之刑。本案經檢察官許梨雯到庭執行職務。中華民國100年12月23日刑事第一庭法官徐文瑞以上正本證明與原本無異。如不服本判決，得於判決書送達之日起10日內，以書狀敘述理由，向本院提出上訴。書記官張茹茵中華民國100年12月26日附錄本案論罪科刑法條全文：刑法第321條（加重竊盜罪）犯竊盜罪而有下列情形之一者，處6月以上、5年以下有期徒刑，得併科新臺幣10萬元以下罰金：一、侵入住宅或有人居住之建築物、船艦或隱匿其內而犯之者。二、毀越門扇、牆垣或其他安全設備而犯之者。三、攜帶兇器而犯之者。四、結夥三人以上而犯之者。五、乘火災、水災或其他災害之際而犯之者。六、在車站、埠頭、航空站或其他供水、陸、空公眾運輸之舟、車、航空機內而犯之者。前項之未遂犯罰之。",
  "characters": {
    "judges": [
      "徐文瑞"
    ],
    "prosecutors": [
      "許梨雯"
    ],
    "lawyers": [

    ],
    "clerks": [
      "張茹茵"
    ],
    "plaintiffs": [

    ],
    "defendants": [
      "吳家瑋榮"
    ],
    "prosecutor_office": [
      "臺灣士林地方法院檢察署檢察官"
    ],
    "creditors": [

    ],
    "debtors": [

    ],
    "judicial_associate_officer": [

    ]
  },
  "adjudged_at": "2011-12-23",
  "created_at": "2016-02-13 14:43:08",
  "updated_at": "2016-02-13 14:43:08"
}