{
  "identify": "PCD-94-訴-652-20050923-3",
  "court": {
    "name": "臺灣新北地方法院",
    "code": "PCD"
  },
  "division": {
    "name": "刑事",
    "code": "M"
  },
  "year": 94,
  "word": "訴",
  "number": "652",
  "jcheck": "3",
  "reason": "毒品危害防制條例",
  "content": "臺灣板橋地方法院刑事判決               94年度訴字第652號\n公  訴  人  臺灣板橋地方法院檢察署檢察官\n被      告  甲○○\n                    （另案於臺灣桃園龍潭女子監獄執刑）\n上列被告因違反毒品危害防制條例案件，經檢察官提起公訴（九\n十四年度核退毒偵字第四七七號），被告於準備程序中對被訴之\n事實為有罪陳述，本院合議庭裁定由受命法官獨任行簡式審判程\n序，並判決如下：\n    主  文\n甲○○連續施用第一級毒品，處有期徒刑壹年，扣案第一級毒品\n海洛因驗餘淨重合計拾貳點捌玖公克、海洛因殘渣袋肆只內之海\n洛因殘渣（微量無法秤重）均沒收銷燬之；盛裝上開第一級毒品\n海洛因之包裝袋伍只（重參點壹壹公克）、留有上開海洛因殘渣\n之包裝（塑膠）袋肆只、塑膠剷管貳支、注射針筒拾肆支、空分\n裝袋貳拾貳只均沒收。\n    事  實\n一、甲○○前有違反肅清煙毒條例、麻醉藥品管理條例等案件之\n    犯罪科刑紀錄，執行完畢已逾五年。又於民國八十八年間因\n    施用毒品案件，經本院以八十八年度毒聲字第三０八０號裁\n    定送觀察、勒戒，因認有繼續施用毒品傾向，再經本院以八\n    十八年度毒聲字第三四二０號裁定令入戒治處所施以強制戒\n    治一年，因戒治成效經評估為良好，經本院以八十八年度毒\n    聲字第八００一號裁定停止戒治，所餘期間付保護管束，於\n    八十八年十二月二十八日自臺灣桃園女子戒治所出所，復於\n    保護管束期間，因違反保護管束情節重大，經臺灣板橋地方\n    法院檢察署檢察官聲請本院以八十九年度毒聲字第三二七八\n    裁定撤銷保護管束，令入戒治處所施以強制戒治後，因該裁\n    定送達確定時，已逾上開保護管束期間（八十九年六月一日\n    期滿），臺灣板橋地方法院檢察署檢察官以事實上已無從執\n    行，應視為保護管束期間屆滿，乃於八十九年八月三日以八\n    十九年度戒毒偵字第四九七號為不起訴處分確定。\n二、詎甲○○不知悔改，於上開強制戒治執行完畢釋放後五年內\n    ，其明知海洛因、甲基安非他命分別係毒品危害防制條例所\n    規定之第一級、第二級毒品，竟基於施用第一級毒品海洛因\n    之概括犯意，於九十四年一月三日下午四時許起至同年七月\n    二十四日下午三時許止，在臺北縣三重市○○路○段一三六\n    巷三十六弄十一號三樓九十三號或新莊市○○街四十三巷二\n    十三號住處，以將毒品海洛因加水稀釋用針筒注射至身體之\n    方式，非法施用毒品海洛因多次，平均二天施用一次；其間\n    ，甲○○於九十四年一月十七日下午三時許，在前開臺北縣\n    三重市○○路○段一三六巷三十六弄十一號三樓九十三號住\n    處，係同時將毒品海洛因、已磨成粉狀之甲基安非他命（起\n    訴書誤載為安非他命，應予更正）加水稀釋後用針筒注射至\n    身體之方式，同時非法施用毒品海洛因、甲基安非他命一次\n    。嗣甲○○先於九十四年一月十九日下午五時四十分許，在\n    臺北縣三重市○○路○段一三六巷三十六弄十一號前為警查\n    獲，並於甲○○身上及臺北縣三重市○○路○段一三六巷三\n    十六弄一號屋內，扣得供其施用之第一級毒品海洛因五包（\n    扣案毛重十六‧０四公克；驗餘淨重十二‧八九；空包裝重\n    三‧一一公克）、供其施用海洛因所用之塑膠剷管二支、注\n    射針筒十四支、海洛因殘渣（量微無法秤重）之包裝（塑膠\n    ）袋四只及供施用海洛因犯罪預備之空分裝袋二十二只，且\n    經警對其採集尿液，後經臺灣板橋地方法院檢察署檢察官命\n    令其提出新台幣三萬元交保後釋放。詎甲○○於審理中因傳\n    、拘未到，經本院發布通緝後，於同年七月二十五日為警緝\n    獲，亦經警對其採集尿液，而其二次採尿送驗結果均呈毒品\n    陽性反應，始查悉上情。\n三、案經臺北縣政府警察局淡水分局報請臺灣板橋地方法院檢察\n    署檢察官偵查起訴。\n    理  由\n一、訊據被告甲○○對於上揭時地，施用第一級毒品、第二級毒\n    品之犯罪事實，於本院審理中坦承不諱，並有供其施用之白\n    色粉末五包、塑膠剷管二支、注射針筒十四支、海洛因殘渣\n    袋四只及未使用過之分裝袋二十二只扣案可資佐證。另被告\n    二次經警查獲所採集尿液經送鑑定，第一次查獲部分呈海洛\n    因代謝物嗎啡、甲基安非他命陽性反應，第二次查獲部分則\n    呈海洛因代謝物嗎啡陽性反應（該次尿液呈安非他命陽性反\n    應部分，被告否認該次查獲前有施用安非他命，並非起訴效\n    力所及，理由詳後述），此分別有臺灣檢驗科技股份有限公\n    司九十四年二月十六日（尿液檢體編號一五二０號）、尿液\n    代碼對照表、九十四年八月八日（尿液檢體編號００二二五\n    ０號）濫用藥物尿液檢驗報告、尿液檢體委驗單各一紙在卷\n    可稽。又上述扣案之白色粉末五包經送法務部調查局鑑定，\n    確為第一級毒品海洛因（扣案毛重十六‧０四公克；驗餘淨\n    重合計十二‧八九公克，其中四包淨重八‧六二公克、純質\n    淨重七‧三０公克；另一包淨重四‧二七公克，但因海洛因\n    量微，定量分析無法檢出海洛因純質重；全部空包裝重三‧\n    一一公克）無誤，此有該局編號九十四年四月十五日調科壹\n    第000000000號鑑定通知書影本一紙附卷可憑。再\n    被告於八十八年間因施用毒品案件，經本院以八十八年度毒\n    聲字第三０八０號裁定送觀察、勒戒，因認有繼續施用毒品\n    傾向，再經本院以八十八年度毒聲字第三四二０號裁定令入\n    戒治處所施以強制戒治一年，因戒治成效經評估為良好，再\n    經本院以八十八年度毒聲字第八００一號裁定停止戒治，所\n    餘期間付保護管束，於八十八年十二月二十八日自臺灣桃園\n    女子戒治所出所，復於保護管束期間，因違反保護管束情節\n    重大，經臺灣板橋地方法院檢察署檢察官聲請撤銷保護管束\n    ，令入戒治處所施以強制戒治，本院以八十九年度毒聲字第\n    三二七八裁定後，因該裁定八十九年六月三十日送達確定時\n    ，已逾於上開保護管束期間（八十九年六月一日期滿），臺\n    灣板橋地方法院檢察署檢察官以事實上已無從執行，應視為\n    保護管束期間屆滿，乃於八十九年八月三日以八十九年度戒\n    毒偵字第四九七號為不起訴處分確定，有上開不起訴處分書\n    電腦列印本、臺灣高等法院被告全國前案紀錄表各一件附卷\n    可憑。其係強制戒治執行完畢釋放後五年內再犯施用第一級\n    、第二級毒品之罪，本案事證明確，被告犯行洵堪認定，應\n    依法論科。\n二、按海洛因、甲基安非他命分別係毒品危害防制條例第二條第\n    二項第一款、第二款所規定之第一級毒品、第二級毒品，故\n    核被告所為，係犯毒品危害防制條例第十條第一項之施用第\n    一級毒品罪，及同條第二項之施用第二級毒品罪。其施用第\n    一級毒品海洛因前後持有海洛因，施用第二級毒品甲基安非\n    他命前持有甲基安非他命之低度行為，均應為施用海洛因、\n    甲基安非他命之高度行為所吸收，不另論罪。又核被告所為\n    數施用第一級毒品之行為，時間緊接，犯罪構成要件相同，\n    顯係出於概括之犯意為之，為連續犯，應依刑法第五十六條\n    之規定以一罪論，並加重其刑。再被告於九十四年一月十七\n    日下午三時許，係同時將毒品海洛因、甲基安非他命加水稀\n    釋用針筒注射至身體之方式，非法施用毒品海洛因、甲基安\n    非他命等情，業據被告於審理中供明在卷，是被告於同時地\n    ，以同一方法，施用甲基安非他命、海洛因，因其施用甲基\n    安非他命、海洛因，僅有一個施用行為，同時觸犯上開二罪\n    名，應構成想像競合犯。而被告先後多次施用第一級毒品犯\n    罪，應先論以一連續施用第一級毒品罪，再依刑法第五十五\n    條想像競合犯之關係，就被告所犯一連續施用第一級毒品罪\n    及施用第二級毒品罪，從一重論以連續施用第一級毒品罪；\n    公訴意旨認被告所犯上開二罪應分論併罰，尚有未洽。公訴\n    人起訴事實雖僅論及被告於九十四年一月三日起至同月十九\n    日止之期間內，施用海洛因多次之犯行，惟被告其餘施用第\n    一級毒品海洛因犯行，與原起訴之被告施用海洛因行為，既\n    有連續犯之裁判上一罪關係，為起訴效力所及，本院自應一\n    併審判。爰審酌被告前有煙毒、麻藥等犯罪執行紀錄（有前\n    開臺灣高等法院被告國前案紀錄表可稽），犯罪之動機、目\n    的、手段，施用毒品犯罪對於身心健康所生之危害，施用毒\n    品之種類、次數、時間，為警查獲後猶再施用毒品，及其犯\n    罪後坦承犯行之態度等一切情狀，量處如主文所示之刑，以\n    資儆懲。\n三、扣案海洛因驗餘淨重十二‧八九公克，及海洛因殘渣袋四只\n    內之海洛因殘渣（量微無法秤重），均係第一級毒品，應依\n    毒品危害防制條例第十八條第一項前段之規定，宣告沒收銷\n    燬之。另取樣之海洛因部分，因檢驗用罄而滅失，爰不另為\n    沒收銷燬之諭知。又盛裝上開毒品海洛因之包裝袋五只（空\n    包裝重三‧一一公克），並非查獲之毒品，係被告所有且供\n    被告施用上開毒品所用（盛裝毒品）之物；塑膠剷管二支、\n    注射針筒十四支、前開含海洛因殘渣（量微無法秤重）之包\n    裝（塑膠）袋四只，均係被告所有供施用毒品犯罪所用之物\n    ，另空分裝袋二十二只並未使用過，係被告所有且係供施用\n    毒品犯罪預備之物，已據被告審理中供明在卷，均依刑法第\n    三十八條第一項第二款之規定宣告沒收。\n四、至於被告同年七月二十五日為警緝獲後，經警對其採集尿液\n    ，送驗結果另呈第二級毒品安非他命陽性反應，有上開臺灣\n    檢驗科技股份有限公司九十四年八月八日（尿液檢體編號０\n    ０二二五０號）濫用藥物尿液檢驗報告可稽，惟被告此部分\n    施用安非命犯行未據檢察官起訴或併案審理，而被告於本院\n    審理中堅詞否認九十四年七月二十五日為警緝獲前數日有何\n    施用安非他命之犯行，且距被告前述施用毒品甲基安非他命\n    之時間（即九十四年一月十七日）已逾六個月，難認時間緊\n    接，顯非基於概括犯意而為，與本案前開起訴論罪科刑部分\n    ，即無裁判上一罪之關係，自非起訴效力所及，是本院就被\n    告此部分施用安非他命之犯行，不予審究，應由檢察官另為\n    適法處理，附此敘明。\n據上論斷，應依刑事訴訟法第二百七十三條之一第一項、第二百\n九十九條第一項前段，毒品危害防制條例第十條第一項、第二項\n、第十八條第一項前段，刑法第十一條前段、第五十六條、第五\n十五條、第三十八條第一項第二款，判決如主文。\n本案經檢察官黃怡華到庭執行職務。\n中    華    民    國  九十四  年  九     月  二十三   日\n                  刑事第十九庭  法  官  楊志雄\n以上正本證明與原本無異。\n如不服本判決應於送達後十日內向本院提出上訴狀。\n                                書記官  胡勤義\n中    華    民    國  九十四  年  九    月   二十六   日\n附錄本案論罪科刑法條全文：\n毒品危害防制條例第十條\n施用第一級毒品者，處六月以上五年以下有期徒刑。\n施用第二級毒品者，處三年以下有期徒刑。\n",
  "structure": {
    "main": "甲○○連續施用第一級毒品，處有期徒刑壹年，扣案第一級毒品\n海洛因驗餘淨重合計拾貳點捌玖公克、海洛因殘渣袋肆只內之海\n洛因殘渣（微量無法秤重）均沒收銷燬之；盛裝上開第一級毒品\n海洛因之包裝袋伍只（重參點壹壹公克）、留有上開海洛因殘渣\n之包裝（塑膠）袋肆只、塑膠剷管貳支、注射針筒拾肆支、空分\n裝袋貳拾貳只均沒收。",
    "fact": "一、甲○○前有違反肅清煙毒條例、麻醉藥品管理條例等案件之\n    犯罪科刑紀錄，執行完畢已逾五年。又於民國八十八年間因\n    施用毒品案件，經本院以八十八年度毒聲字第三０八０號裁\n    定送觀察、勒戒，因認有繼續施用毒品傾向，再經本院以八\n    十八年度毒聲字第三四二０號裁定令入戒治處所施以強制戒\n    治一年，因戒治成效經評估為良好，經本院以八十八年度毒\n    聲字第八００一號裁定停止戒治，所餘期間付保護管束，於\n    八十八年十二月二十八日自臺灣桃園女子戒治所出所，復於\n    保護管束期間，因違反保護管束情節重大，經臺灣板橋地方\n    法院檢察署檢察官聲請本院以八十九年度毒聲字第三二七八\n    裁定撤銷保護管束，令入戒治處所施以強制戒治後，因該裁\n    定送達確定時，已逾上開保護管束期間（八十九年六月一日\n    期滿），臺灣板橋地方法院檢察署檢察官以事實上已無從執\n    行，應視為保護管束期間屆滿，乃於八十九年八月三日以八\n    十九年度戒毒偵字第四九七號為不起訴處分確定。\n二、詎甲○○不知悔改，於上開強制戒治執行完畢釋放後五年內\n    ，其明知海洛因、甲基安非他命分別係毒品危害防制條例所\n    規定之第一級、第二級毒品，竟基於施用第一級毒品海洛因\n    之概括犯意，於九十四年一月三日下午四時許起至同年七月\n    二十四日下午三時許止，在臺北縣三重市○○路○段一三六\n    巷三十六弄十一號三樓九十三號或新莊市○○街四十三巷二\n    十三號住處，以將毒品海洛因加水稀釋用針筒注射至身體之\n    方式，非法施用毒品海洛因多次，平均二天施用一次；其間\n    ，甲○○於九十四年一月十七日下午三時許，在前開臺北縣\n    三重市○○路○段一三六巷三十六弄十一號三樓九十三號住\n    處，係同時將毒品海洛因、已磨成粉狀之甲基安非他命（起\n    訴書誤載為安非他命，應予更正）加水稀釋後用針筒注射至\n    身體之方式，同時非法施用毒品海洛因、甲基安非他命一次\n    。嗣甲○○先於九十四年一月十九日下午五時四十分許，在\n    臺北縣三重市○○路○段一三六巷三十六弄十一號前為警查\n    獲，並於甲○○身上及臺北縣三重市○○路○段一三六巷三\n    十六弄一號屋內，扣得供其施用之第一級毒品海洛因五包（\n    扣案毛重十六‧０四公克；驗餘淨重十二‧八九；空包裝重\n    三‧一一公克）、供其施用海洛因所用之塑膠剷管二支、注\n    射針筒十四支、海洛因殘渣（量微無法秤重）之包裝（塑膠\n    ）袋四只及供施用海洛因犯罪預備之空分裝袋二十二只，且\n    經警對其採集尿液，後經臺灣板橋地方法院檢察署檢察官命\n    令其提出新台幣三萬元交保後釋放。詎甲○○於審理中因傳\n    、拘未到，經本院發布通緝後，於同年七月二十五日為警緝\n    獲，亦經警對其採集尿液，而其二次採尿送驗結果均呈毒品\n    陽性反應，始查悉上情。\n三、案經臺北縣政府警察局淡水分局報請臺灣板橋地方法院檢察\n    署檢察官偵查起訴。",
    "reason": "一、訊據被告甲○○對於上揭時地，施用第一級毒品、第二級毒\n    品之犯罪事實，於本院審理中坦承不諱，並有供其施用之白\n    色粉末五包、塑膠剷管二支、注射針筒十四支、海洛因殘渣\n    袋四只及未使用過之分裝袋二十二只扣案可資佐證。另被告\n    二次經警查獲所採集尿液經送鑑定，第一次查獲部分呈海洛\n    因代謝物嗎啡、甲基安非他命陽性反應，第二次查獲部分則\n    呈海洛因代謝物嗎啡陽性反應（該次尿液呈安非他命陽性反\n    應部分，被告否認該次查獲前有施用安非他命，並非起訴效\n    力所及，理由詳後述），此分別有臺灣檢驗科技股份有限公\n    司九十四年二月十六日（尿液檢體編號一五二０號）、尿液\n    代碼對照表、九十四年八月八日（尿液檢體編號００二二五\n    ０號）濫用藥物尿液檢驗報告、尿液檢體委驗單各一紙在卷\n    可稽。又上述扣案之白色粉末五包經送法務部調查局鑑定，\n    確為第一級毒品海洛因（扣案毛重十六‧０四公克；驗餘淨\n    重合計十二‧八九公克，其中四包淨重八‧六二公克、純質\n    淨重七‧三０公克；另一包淨重四‧二七公克，但因海洛因\n    量微，定量分析無法檢出海洛因純質重；全部空包裝重三‧\n    一一公克）無誤，此有該局編號九十四年四月十五日調科壹\n    第000000000號鑑定通知書影本一紙附卷可憑。再\n    被告於八十八年間因施用毒品案件，經本院以八十八年度毒\n    聲字第三０八０號裁定送觀察、勒戒，因認有繼續施用毒品\n    傾向，再經本院以八十八年度毒聲字第三四二０號裁定令入\n    戒治處所施以強制戒治一年，因戒治成效經評估為良好，再\n    經本院以八十八年度毒聲字第八００一號裁定停止戒治，所\n    餘期間付保護管束，於八十八年十二月二十八日自臺灣桃園\n    女子戒治所出所，復於保護管束期間，因違反保護管束情節\n    重大，經臺灣板橋地方法院檢察署檢察官聲請撤銷保護管束\n    ，令入戒治處所施以強制戒治，本院以八十九年度毒聲字第\n    三二七八裁定後，因該裁定八十九年六月三十日送達確定時\n    ，已逾於上開保護管束期間（八十九年六月一日期滿），臺\n    灣板橋地方法院檢察署檢察官以事實上已無從執行，應視為\n    保護管束期間屆滿，乃於八十九年八月三日以八十九年度戒\n    毒偵字第四九七號為不起訴處分確定，有上開不起訴處分書\n    電腦列印本、臺灣高等法院被告全國前案紀錄表各一件附卷\n    可憑。其係強制戒治執行完畢釋放後五年內再犯施用第一級\n    、第二級毒品之罪，本案事證明確，被告犯行洵堪認定，應\n    依法論科。\n二、按海洛因、甲基安非他命分別係毒品危害防制條例第二條第\n    二項第一款、第二款所規定之第一級毒品、第二級毒品，故\n    核被告所為，係犯毒品危害防制條例第十條第一項之施用第\n    一級毒品罪，及同條第二項之施用第二級毒品罪。其施用第\n    一級毒品海洛因前後持有海洛因，施用第二級毒品甲基安非\n    他命前持有甲基安非他命之低度行為，均應為施用海洛因、\n    甲基安非他命之高度行為所吸收，不另論罪。又核被告所為\n    數施用第一級毒品之行為，時間緊接，犯罪構成要件相同，\n    顯係出於概括之犯意為之，為連續犯，應依刑法第五十六條\n    之規定以一罪論，並加重其刑。再被告於九十四年一月十七\n    日下午三時許，係同時將毒品海洛因、甲基安非他命加水稀\n    釋用針筒注射至身體之方式，非法施用毒品海洛因、甲基安\n    非他命等情，業據被告於審理中供明在卷，是被告於同時地\n    ，以同一方法，施用甲基安非他命、海洛因，因其施用甲基\n    安非他命、海洛因，僅有一個施用行為，同時觸犯上開二罪\n    名，應構成想像競合犯。而被告先後多次施用第一級毒品犯\n    罪，應先論以一連續施用第一級毒品罪，再依刑法第五十五\n    條想像競合犯之關係，就被告所犯一連續施用第一級毒品罪\n    及施用第二級毒品罪，從一重論以連續施用第一級毒品罪；\n    公訴意旨認被告所犯上開二罪應分論併罰，尚有未洽。公訴\n    人起訴事實雖僅論及被告於九十四年一月三日起至同月十九\n    日止之期間內，施用海洛因多次之犯行，惟被告其餘施用第\n    一級毒品海洛因犯行，與原起訴之被告施用海洛因行為，既\n    有連續犯之裁判上一罪關係，為起訴效力所及，本院自應一\n    併審判。爰審酌被告前有煙毒、麻藥等犯罪執行紀錄（有前\n    開臺灣高等法院被告國前案紀錄表可稽），犯罪之動機、目\n    的、手段，施用毒品犯罪對於身心健康所生之危害，施用毒\n    品之種類、次數、時間，為警查獲後猶再施用毒品，及其犯\n    罪後坦承犯行之態度等一切情狀，量處如主文所示之刑，以\n    資儆懲。\n三、扣案海洛因驗餘淨重十二‧八九公克，及海洛因殘渣袋四只\n    內之海洛因殘渣（量微無法秤重），均係第一級毒品，應依\n    毒品危害防制條例第十八條第一項前段之規定，宣告沒收銷\n    燬之。另取樣之海洛因部分，因檢驗用罄而滅失，爰不另為\n    沒收銷燬之諭知。又盛裝上開毒品海洛因之包裝袋五只（空\n    包裝重三‧一一公克），並非查獲之毒品，係被告所有且供\n    被告施用上開毒品所用（盛裝毒品）之物；塑膠剷管二支、\n    注射針筒十四支、前開含海洛因殘渣（量微無法秤重）之包\n    裝（塑膠）袋四只，均係被告所有供施用毒品犯罪所用之物\n    ，另空分裝袋二十二只並未使用過，係被告所有且係供施用\n    毒品犯罪預備之物，已據被告審理中供明在卷，均依刑法第\n    三十八條第一項第二款之規定宣告沒收。\n四、至於被告同年七月二十五日為警緝獲後，經警對其採集尿液\n    ，送驗結果另呈第二級毒品安非他命陽性反應，有上開臺灣\n    檢驗科技股份有限公司九十四年八月八日（尿液檢體編號０\n    ０二二五０號）濫用藥物尿液檢驗報告可稽，惟被告此部分\n    施用安非命犯行未據檢察官起訴或併案審理，而被告於本院\n    審理中堅詞否認九十四年七月二十五日為警緝獲前數日有何\n    施用安非他命之犯行，且距被告前述施用毒品甲基安非他命\n    之時間（即九十四年一月十七日）已逾六個月，難認時間緊\n    接，顯非基於概括犯意而為，與本案前開起訴論罪科刑部分\n    ，即無裁判上一罪之關係，自非起訴效力所及，是本院就被\n    告此部分施用安非他命之犯行，不予審究，應由檢察官另為\n    適法處理，附此敘明。\n據上論斷，應依刑事訴訟法第二百七十三條之一第一項、第二百\n九十九條第一項前段，毒品危害防制條例第十條第一項、第二項\n、第十八條第一項前段，刑法第十一條前段、第五十六條、第五\n十五條、第三十八條第一項第二款，判決如主文。\n本案經檢察官黃怡華到庭執行職務。\n中    華    民    國  九十四  年  九     月  二十三   日\n                  刑事第十九庭  法  官  楊志雄\n以上正本證明與原本無異。\n如不服本判決應於送達後十日內向本院提出上訴狀。\n                                書記官  胡勤義"
  },
  "search": "臺灣板橋地方法院刑事判決94年度訴字第652號公訴人臺灣板橋地方法院檢察署檢察官被告甲○○（另案於臺灣桃園龍潭女子監獄執刑）上列被告因違反毒品危害防制條例案件，經檢察官提起公訴（九十四年度核退毒偵字第四七七號），被告於準備程序中對被訴之事實為有罪陳述，本院合議庭裁定由受命法官獨任行簡式審判程序，並判決如下：主文甲○○連續施用第一級毒品，處有期徒刑壹年，扣案第一級毒品海洛因驗餘淨重合計拾貳點捌玖公克、海洛因殘渣袋肆只內之海洛因殘渣（微量無法秤重）均沒收銷燬之；盛裝上開第一級毒品海洛因之包裝袋伍只（重參點壹壹公克）、留有上開海洛因殘渣之包裝（塑膠）袋肆只、塑膠剷管貳支、注射針筒拾肆支、空分裝袋貳拾貳只均沒收。事實一、甲○○前有違反肅清煙毒條例、麻醉藥品管理條例等案件之犯罪科刑紀錄，執行完畢已逾五年。又於民國八十八年間因施用毒品案件，經本院以八十八年度毒聲字第三０八０號裁定送觀察、勒戒，因認有繼續施用毒品傾向，再經本院以八十八年度毒聲字第三四二０號裁定令入戒治處所施以強制戒治一年，因戒治成效經評估為良好，經本院以八十八年度毒聲字第八００一號裁定停止戒治，所餘期間付保護管束，於八十八年十二月二十八日自臺灣桃園女子戒治所出所，復於保護管束期間，因違反保護管束情節重大，經臺灣板橋地方法院檢察署檢察官聲請本院以八十九年度毒聲字第三二七八裁定撤銷保護管束，令入戒治處所施以強制戒治後，因該裁定送達確定時，已逾上開保護管束期間（八十九年六月一日期滿），臺灣板橋地方法院檢察署檢察官以事實上已無從執行，應視為保護管束期間屆滿，乃於八十九年八月三日以八十九年度戒毒偵字第四九七號為不起訴處分確定。二、詎甲○○不知悔改，於上開強制戒治執行完畢釋放後五年內，其明知海洛因、甲基安非他命分別係毒品危害防制條例所規定之第一級、第二級毒品，竟基於施用第一級毒品海洛因之概括犯意，於九十四年一月三日下午四時許起至同年七月二十四日下午三時許止，在臺北縣三重市○○路○段一三六巷三十六弄十一號三樓九十三號或新莊市○○街四十三巷二十三號住處，以將毒品海洛因加水稀釋用針筒注射至身體之方式，非法施用毒品海洛因多次，平均二天施用一次；其間，甲○○於九十四年一月十七日下午三時許，在前開臺北縣三重市○○路○段一三六巷三十六弄十一號三樓九十三號住處，係同時將毒品海洛因、已磨成粉狀之甲基安非他命（起訴書誤載為安非他命，應予更正）加水稀釋後用針筒注射至身體之方式，同時非法施用毒品海洛因、甲基安非他命一次。嗣甲○○先於九十四年一月十九日下午五時四十分許，在臺北縣三重市○○路○段一三六巷三十六弄十一號前為警查獲，並於甲○○身上及臺北縣三重市○○路○段一三六巷三十六弄一號屋內，扣得供其施用之第一級毒品海洛因五包（扣案毛重十六‧０四公克；驗餘淨重十二‧八九；空包裝重三‧一一公克）、供其施用海洛因所用之塑膠剷管二支、注射針筒十四支、海洛因殘渣（量微無法秤重）之包裝（塑膠）袋四只及供施用海洛因犯罪預備之空分裝袋二十二只，且經警對其採集尿液，後經臺灣板橋地方法院檢察署檢察官命令其提出新台幣三萬元交保後釋放。詎甲○○於審理中因傳、拘未到，經本院發布通緝後，於同年七月二十五日為警緝獲，亦經警對其採集尿液，而其二次採尿送驗結果均呈毒品陽性反應，始查悉上情。三、案經臺北縣政府警察局淡水分局報請臺灣板橋地方法院檢察署檢察官偵查起訴。理由一、訊據被告甲○○對於上揭時地，施用第一級毒品、第二級毒品之犯罪事實，於本院審理中坦承不諱，並有供其施用之白色粉末五包、塑膠剷管二支、注射針筒十四支、海洛因殘渣袋四只及未使用過之分裝袋二十二只扣案可資佐證。另被告二次經警查獲所採集尿液經送鑑定，第一次查獲部分呈海洛因代謝物嗎啡、甲基安非他命陽性反應，第二次查獲部分則呈海洛因代謝物嗎啡陽性反應（該次尿液呈安非他命陽性反應部分，被告否認該次查獲前有施用安非他命，並非起訴效力所及，理由詳後述），此分別有臺灣檢驗科技股份有限公司九十四年二月十六日（尿液檢體編號一五二０號）、尿液代碼對照表、九十四年八月八日（尿液檢體編號００二二五０號）濫用藥物尿液檢驗報告、尿液檢體委驗單各一紙在卷可稽。又上述扣案之白色粉末五包經送法務部調查局鑑定，確為第一級毒品海洛因（扣案毛重十六‧０四公克；驗餘淨重合計十二‧八九公克，其中四包淨重八‧六二公克、純質淨重七‧三０公克；另一包淨重四‧二七公克，但因海洛因量微，定量分析無法檢出海洛因純質重；全部空包裝重三‧一一公克）無誤，此有該局編號九十四年四月十五日調科壹第000000000號鑑定通知書影本一紙附卷可憑。再被告於八十八年間因施用毒品案件，經本院以八十八年度毒聲字第三０八０號裁定送觀察、勒戒，因認有繼續施用毒品傾向，再經本院以八十八年度毒聲字第三四二０號裁定令入戒治處所施以強制戒治一年，因戒治成效經評估為良好，再經本院以八十八年度毒聲字第八００一號裁定停止戒治，所餘期間付保護管束，於八十八年十二月二十八日自臺灣桃園女子戒治所出所，復於保護管束期間，因違反保護管束情節重大，經臺灣板橋地方法院檢察署檢察官聲請撤銷保護管束，令入戒治處所施以強制戒治，本院以八十九年度毒聲字第三二七八裁定後，因該裁定八十九年六月三十日送達確定時，已逾於上開保護管束期間（八十九年六月一日期滿），臺灣板橋地方法院檢察署檢察官以事實上已無從執行，應視為保護管束期間屆滿，乃於八十九年八月三日以八十九年度戒毒偵字第四九七號為不起訴處分確定，有上開不起訴處分書電腦列印本、臺灣高等法院被告全國前案紀錄表各一件附卷可憑。其係強制戒治執行完畢釋放後五年內再犯施用第一級、第二級毒品之罪，本案事證明確，被告犯行洵堪認定，應依法論科。二、按海洛因、甲基安非他命分別係毒品危害防制條例第二條第二項第一款、第二款所規定之第一級毒品、第二級毒品，故核被告所為，係犯毒品危害防制條例第十條第一項之施用第一級毒品罪，及同條第二項之施用第二級毒品罪。其施用第一級毒品海洛因前後持有海洛因，施用第二級毒品甲基安非他命前持有甲基安非他命之低度行為，均應為施用海洛因、甲基安非他命之高度行為所吸收，不另論罪。又核被告所為數施用第一級毒品之行為，時間緊接，犯罪構成要件相同，顯係出於概括之犯意為之，為連續犯，應依刑法第五十六條之規定以一罪論，並加重其刑。再被告於九十四年一月十七日下午三時許，係同時將毒品海洛因、甲基安非他命加水稀釋用針筒注射至身體之方式，非法施用毒品海洛因、甲基安非他命等情，業據被告於審理中供明在卷，是被告於同時地，以同一方法，施用甲基安非他命、海洛因，因其施用甲基安非他命、海洛因，僅有一個施用行為，同時觸犯上開二罪名，應構成想像競合犯。而被告先後多次施用第一級毒品犯罪，應先論以一連續施用第一級毒品罪，再依刑法第五十五條想像競合犯之關係，就被告所犯一連續施用第一級毒品罪及施用第二級毒品罪，從一重論以連續施用第一級毒品罪；公訴意旨認被告所犯上開二罪應分論併罰，尚有未洽。公訴人起訴事實雖僅論及被告於九十四年一月三日起至同月十九日止之期間內，施用海洛因多次之犯行，惟被告其餘施用第一級毒品海洛因犯行，與原起訴之被告施用海洛因行為，既有連續犯之裁判上一罪關係，為起訴效力所及，本院自應一併審判。爰審酌被告前有煙毒、麻藥等犯罪執行紀錄（有前開臺灣高等法院被告國前案紀錄表可稽），犯罪之動機、目的、手段，施用毒品犯罪對於身心健康所生之危害，施用毒品之種類、次數、時間，為警查獲後猶再施用毒品，及其犯罪後坦承犯行之態度等一切情狀，量處如主文所示之刑，以資儆懲。三、扣案海洛因驗餘淨重十二‧八九公克，及海洛因殘渣袋四只內之海洛因殘渣（量微無法秤重），均係第一級毒品，應依毒品危害防制條例第十八條第一項前段之規定，宣告沒收銷燬之。另取樣之海洛因部分，因檢驗用罄而滅失，爰不另為沒收銷燬之諭知。又盛裝上開毒品海洛因之包裝袋五只（空包裝重三‧一一公克），並非查獲之毒品，係被告所有且供被告施用上開毒品所用（盛裝毒品）之物；塑膠剷管二支、注射針筒十四支、前開含海洛因殘渣（量微無法秤重）之包裝（塑膠）袋四只，均係被告所有供施用毒品犯罪所用之物，另空分裝袋二十二只並未使用過，係被告所有且係供施用毒品犯罪預備之物，已據被告審理中供明在卷，均依刑法第三十八條第一項第二款之規定宣告沒收。四、至於被告同年七月二十五日為警緝獲後，經警對其採集尿液，送驗結果另呈第二級毒品安非他命陽性反應，有上開臺灣檢驗科技股份有限公司九十四年八月八日（尿液檢體編號００二二五０號）濫用藥物尿液檢驗報告可稽，惟被告此部分施用安非命犯行未據檢察官起訴或併案審理，而被告於本院審理中堅詞否認九十四年七月二十五日為警緝獲前數日有何施用安非他命之犯行，且距被告前述施用毒品甲基安非他命之時間（即九十四年一月十七日）已逾六個月，難認時間緊接，顯非基於概括犯意而為，與本案前開起訴論罪科刑部分，即無裁判上一罪之關係，自非起訴效力所及，是本院就被告此部分施用安非他命之犯行，不予審究，應由檢察官另為適法處理，附此敘明。據上論斷，應依刑事訴訟法第二百七十三條之一第一項、第二百九十九條第一項前段，毒品危害防制條例第十條第一項、第二項、第十八條第一項前段，刑法第十一條前段、第五十六條、第五十五條、第三十八條第一項第二款，判決如主文。本案經檢察官黃怡華到庭執行職務。中華民國九十四年九月二十三日刑事第十九庭法官楊志雄以上正本證明與原本無異。如不服本判決應於送達後十日內向本院提出上訴狀。書記官胡勤義中華民國九十四年九月二十六日附錄本案論罪科刑法條全文：毒品危害防制條例第十條施用第一級毒品者，處六月以上五年以下有期徒刑。施用第二級毒品者，處三年以下有期徒刑。",
  "characters": {
    "judges": [
      "楊志雄"
    ],
    "prosecutors": [
      "黃怡華"
    ],
    "lawyers": [

    ],
    "clerks": [
      "胡勤義"
    ],
    "plaintiffs": [

    ],
    "defendants": [
      "甲○○"
    ],
    "prosecutor_office": [
      "臺灣板橋地方法院檢察署檢察官"
    ],
    "creditors": [

    ],
    "debtors": [

    ],
    "judicial_associate_officer": [

    ]
  },
  "adjudged_at": "2005-09-23",
  "created_at": "2016-02-06 20:44:56",
  "updated_at": "2016-02-06 20:44:56"
}