{
  "identify": "TND-94-簡-2246-20050923-1",
  "court": {
    "name": "臺灣南投地方法院",
    "code": "TND"
  },
  "division": {
    "name": "刑事",
    "code": "M"
  },
  "year": 94,
  "word": "簡",
  "number": "2246",
  "jcheck": "1",
  "reason": "毀損",
  "content": "臺灣臺南地方法院刑事簡易判決          94年度簡字第2246號\n聲  請  人  臺灣臺南地方法院檢察署檢察官\n被      告  丁○○\n被      告  甲○○\n被      告  丙○○\n上列被告因毀損案件，經檢察官聲請簡易判決處刑（94年度核退\n偵字第619號），本院逕以簡易判決處刑如下：\n    主  文\n丁○○、甲○○、丙○○共同損壞他人之鋁門上玻璃貳片，冰箱\n壹只、冰櫃玻璃肆片，足以生損害於他人，丁○○，累犯，處有\n期徒刑參月；甲○○、丙○○各處拘役伍拾日，如易科罰金均以\n參佰元折算壹日。\n    事實及理由\n一、本件犯罪事實及證據均引用附件聲請簡易處刑書之記載。\n二、核被告三人所為，均係犯刑法第三百五十四條之毀損罪。被\n    丁○○雖於警詢中稱伊未動手，惟其於偵查中業已坦承毀損\n    ，詳94年度核交字第482號第6頁，被害人劉工喜於偵查中先\n    稱「丁○○說1120元，那麼貴，比酒店還貴」，再對照其於\n    警詢中稱「該名歹徒就說那有那麼貴，我說光海尼根啤酒錢\n    就600元了，其中一名歹徒就到車上拿木棍放在肩膀上，該\n    名歹徒再次跟我說老板要付多少錢？我又說1120元，……該\n    名歹徒連同行二名男子就追進屋內要打我，幸好我躲起來」\n    ，足認被告丁○○雖未直接動手，惟與另二名被告就本件犯\n    行有犯意聯絡及行為分擔，均為共同正犯。被告丁○○有如\n    附件犯罪事實欄所載犯罪科刑執行情形，有臺灣高等法院被\n    告前案紀錄表在卷可按，其於有期徒刑執行完畢後五年內再\n    犯本件有期徒刑以上之本罪，為累犯，應依法加重其刑。爰\n    審酌被告三人酒後以費用太高為由藉故尋釁、在小吃店內公\n    然逞兇，任意砸毀損他人營業場所大門玻璃，冰箱等物，事\n    後對告訴人乙○○所生財物之損害，猶未賠償，然犯後坦認\n    犯行等一切情狀，分別量處如主文所示之刑，並均諭知如易\n    科罰金之折算標準，以資儆懲。\n三、依刑事訴訟法第四百四十九條第一項前段、第四百五十四條\n    第二項，刑法第三百五十四條、第四十一條第一項前段，罰\n    金罰鍰提高標準條例第一條前段、第二條，逕以簡易判決處\n    如主文所示之刑。\n四、如不服本判決，應於送達後十日內，向本院提出上訴狀。\n中    華    民    國    94    年    9     月    23    日\n                      刑事第三庭法  官  陳振謙\n以上正本證明與原本無異。\n如不服本判決，應於收受送達後10日內向本院提出上訴書狀（應\n附繕本）。\n                                書記官  黃雅雲\n中    華    民    國    94    年    9     月    23    日\n附錄本案論罪科刑法條全文：\n刑法第三百五十四條\n毀棄、損壞前二條以外之他人之物，或致令不堪用，足以生損害\n於公眾或他人者，處二年以下有期徒刑、拘役或五百元以下罰金\n。\n",
  "structure": {
    "main": "丁○○、甲○○、丙○○共同損壞他人之鋁門上玻璃貳片，冰箱\n壹只、冰櫃玻璃肆片，足以生損害於他人，丁○○，累犯，處有\n期徒刑參月；甲○○、丙○○各處拘役伍拾日，如易科罰金均以\n參佰元折算壹日。",
    "fact": "一、本件犯罪事實及證據均引用附件聲請簡易處刑書之記載。\n二、核被告三人所為，均係犯刑法第三百五十四條之毀損罪。被\n    丁○○雖於警詢中稱伊未動手，惟其於偵查中業已坦承毀損\n    ，詳94年度核交字第482號第6頁，被害人劉工喜於偵查中先\n    稱「丁○○說1120元，那麼貴，比酒店還貴」，再對照其於\n    警詢中稱「該名歹徒就說那有那麼貴，我說光海尼根啤酒錢\n    就600元了，其中一名歹徒就到車上拿木棍放在肩膀上，該\n    名歹徒再次跟我說老板要付多少錢？我又說1120元，……該\n    名歹徒連同行二名男子就追進屋內要打我，幸好我躲起來」\n    ，足認被告丁○○雖未直接動手，惟與另二名被告就本件犯\n    行有犯意聯絡及行為分擔，均為共同正犯。被告丁○○有如\n    附件犯罪事實欄所載犯罪科刑執行情形，有臺灣高等法院被\n    告前案紀錄表在卷可按，其於有期徒刑執行完畢後五年內再\n    犯本件有期徒刑以上之本罪，為累犯，應依法加重其刑。爰\n    審酌被告三人酒後以費用太高為由藉故尋釁、在小吃店內公\n    然逞兇，任意砸毀損他人營業場所大門玻璃，冰箱等物，事\n    後對告訴人乙○○所生財物之損害，猶未賠償，然犯後坦認\n    犯行等一切情狀，分別量處如主文所示之刑，並均諭知如易\n    科罰金之折算標準，以資儆懲。\n三、依刑事訴訟法第四百四十九條第一項前段、第四百五十四條\n    第二項，刑法第三百五十四條、第四十一條第一項前段，罰\n    金罰鍰提高標準條例第一條前段、第二條，逕以簡易判決處\n    如主文所示之刑。\n四、如不服本判決，應於送達後十日內，向本院提出上訴狀。",
    "reason": "一、本件犯罪事實及證據均引用附件聲請簡易處刑書之記載。\n二、核被告三人所為，均係犯刑法第三百五十四條之毀損罪。被\n    丁○○雖於警詢中稱伊未動手，惟其於偵查中業已坦承毀損\n    ，詳94年度核交字第482號第6頁，被害人劉工喜於偵查中先\n    稱「丁○○說1120元，那麼貴，比酒店還貴」，再對照其於\n    警詢中稱「該名歹徒就說那有那麼貴，我說光海尼根啤酒錢\n    就600元了，其中一名歹徒就到車上拿木棍放在肩膀上，該\n    名歹徒再次跟我說老板要付多少錢？我又說1120元，……該\n    名歹徒連同行二名男子就追進屋內要打我，幸好我躲起來」\n    ，足認被告丁○○雖未直接動手，惟與另二名被告就本件犯\n    行有犯意聯絡及行為分擔，均為共同正犯。被告丁○○有如\n    附件犯罪事實欄所載犯罪科刑執行情形，有臺灣高等法院被\n    告前案紀錄表在卷可按，其於有期徒刑執行完畢後五年內再\n    犯本件有期徒刑以上之本罪，為累犯，應依法加重其刑。爰\n    審酌被告三人酒後以費用太高為由藉故尋釁、在小吃店內公\n    然逞兇，任意砸毀損他人營業場所大門玻璃，冰箱等物，事\n    後對告訴人乙○○所生財物之損害，猶未賠償，然犯後坦認\n    犯行等一切情狀，分別量處如主文所示之刑，並均諭知如易\n    科罰金之折算標準，以資儆懲。\n三、依刑事訴訟法第四百四十九條第一項前段、第四百五十四條\n    第二項，刑法第三百五十四條、第四十一條第一項前段，罰\n    金罰鍰提高標準條例第一條前段、第二條，逕以簡易判決處\n    如主文所示之刑。\n四、如不服本判決，應於送達後十日內，向本院提出上訴狀。"
  },
  "search": "臺灣臺南地方法院刑事簡易判決94年度簡字第2246號聲請人臺灣臺南地方法院檢察署檢察官被告丁○○被告甲○○被告丙○○上列被告因毀損案件，經檢察官聲請簡易判決處刑（94年度核退偵字第619號），本院逕以簡易判決處刑如下：主文丁○○、甲○○、丙○○共同損壞他人之鋁門上玻璃貳片，冰箱壹只、冰櫃玻璃肆片，足以生損害於他人，丁○○，累犯，處有期徒刑參月；甲○○、丙○○各處拘役伍拾日，如易科罰金均以參佰元折算壹日。事實及理由一、本件犯罪事實及證據均引用附件聲請簡易處刑書之記載。二、核被告三人所為，均係犯刑法第三百五十四條之毀損罪。被丁○○雖於警詢中稱伊未動手，惟其於偵查中業已坦承毀損，詳94年度核交字第482號第6頁，被害人劉工喜於偵查中先稱「丁○○說1120元，那麼貴，比酒店還貴」，再對照其於警詢中稱「該名歹徒就說那有那麼貴，我說光海尼根啤酒錢就600元了，其中一名歹徒就到車上拿木棍放在肩膀上，該名歹徒再次跟我說老板要付多少錢？我又說1120元，……該名歹徒連同行二名男子就追進屋內要打我，幸好我躲起來」，足認被告丁○○雖未直接動手，惟與另二名被告就本件犯行有犯意聯絡及行為分擔，均為共同正犯。被告丁○○有如附件犯罪事實欄所載犯罪科刑執行情形，有臺灣高等法院被告前案紀錄表在卷可按，其於有期徒刑執行完畢後五年內再犯本件有期徒刑以上之本罪，為累犯，應依法加重其刑。爰審酌被告三人酒後以費用太高為由藉故尋釁、在小吃店內公然逞兇，任意砸毀損他人營業場所大門玻璃，冰箱等物，事後對告訴人乙○○所生財物之損害，猶未賠償，然犯後坦認犯行等一切情狀，分別量處如主文所示之刑，並均諭知如易科罰金之折算標準，以資儆懲。三、依刑事訴訟法第四百四十九條第一項前段、第四百五十四條第二項，刑法第三百五十四條、第四十一條第一項前段，罰金罰鍰提高標準條例第一條前段、第二條，逕以簡易判決處如主文所示之刑。四、如不服本判決，應於送達後十日內，向本院提出上訴狀。中華民國94年9月23日刑事第三庭法官陳振謙以上正本證明與原本無異。如不服本判決，應於收受送達後10日內向本院提出上訴書狀（應附繕本）。書記官黃雅雲中華民國94年9月23日附錄本案論罪科刑法條全文：刑法第三百五十四條毀棄、損壞前二條以外之他人之物，或致令不堪用，足以生損害於公眾或他人者，處二年以下有期徒刑、拘役或五百元以下罰金。",
  "characters": {
    "judges": [
      "陳振謙"
    ],
    "prosecutors": [

    ],
    "lawyers": [

    ],
    "clerks": [
      "黃雅雲"
    ],
    "plaintiffs": [

    ],
    "defendants": [
      "丁○○",
      "被      告  甲○○",
      "被      告  丙○○"
    ],
    "prosecutor_office": [
      "臺灣臺南地方法院檢察署檢察官"
    ],
    "creditors": [

    ],
    "debtors": [

    ],
    "judicial_associate_officer": [

    ]
  },
  "adjudged_at": "2005-09-23",
  "created_at": "2016-02-06 20:49:05",
  "updated_at": "2016-02-06 20:49:05"
}