{
  "identify": "PTD-93-交簡-275-20040409-1",
  "court": {
    "name": "臺灣屏東地方法院",
    "code": "PTD"
  },
  "division": {
    "name": "刑事",
    "code": "M"
  },
  "year": 93,
  "word": "交簡",
  "number": "275",
  "jcheck": "1",
  "reason": "公共危險",
  "content": "臺灣屏東地方法院刑事簡易判決                    九十三年度交簡字第二七五號\n    聲  請  人  臺灣屏東地方法院檢察署檢察官\n    被      告  甲○○\n右列被告因公共危險案件，經檢察官聲請以簡易判決處刑（九十三年度偵字第一六三\n五號），本院判決如左：\n    主      文\n甲○○服用酒類，不能安全駕駛動力交通工具而駕駛，處有期徒刑貳月，如易科罰金\n，以參佰元折算壹日。\n    事實及理由\n一、本件認定被告犯罪之事實、理由並所犯法條，除理由部分另補充：「依據卷附中\n    央警察大學所作身體酒精濃度與肇事率試驗所示，於飲酒後呼氣中酒精濃度逾每\n    公升０．８５毫克時，將出現平衡感與障礙度升高、肇事率為一般人五十倍，而\n    被告甲○○行為後經測得之呼氣酒精濃度高達每公升一點一二毫克，遠高於前開\n    數值，且被告為警查獲時，有語無論次、意識模糊、多話等酒醉症狀，有「刑法\n    第一百八十五條之三案件測試觀察記錄表」一紙在卷可稽，又被告自稱因閃避狗\n    隻不慎摔倒時，天候晴，日間自然光線，該路段為直路且路面狀態鋪有柏油，乾\n    燥，無缺陷，路面無障礙物，視距良好，此有屏東縣警察局分屏東局交通警察隊\n    所製作之道路交通事故調查報告表一紙可參，而被告亦自承肇事當時車速僅每小\n    時三十至四十公里，且並未撥打手持式行動電話等語（見警卷），依一般正常駕\n    駛人之反應能力，於相同情況之下，當足以正常行駛而無發生事故之虞，被告竟\n    仍因注意力、距離判斷之能力未足因於無外力影響下自行摔倒路面，故其因服用\n    酒類致使其安全駕駛動力交通工具之能力衰退甚明，被告辯稱交通事故與其飲酒\n    無關，不會造成人車危險云云，顯非可採。本件事證明確，被告服用酒類，不能\n    安全駕駛動力交通工具而駕駛之犯行，洵堪認定。」，其餘均引用檢察官聲請簡\n    易判決處刑書之記載（如附件）。\n二、爰審酌被告甲○○前已於九十年間，因酒醉駕車之公共危險案件，經本院以九十\n    年度屏交簡字第四四六號判處拘役四十五日，甫於九十一年三月二十七日入監執\n    行完畢，仍不知警惕，再度酒醉駕車，且酒醉程度非輕，對其他用路人已有高度\n    之危險性，又於犯罪後飾詞狡辯，不知悔改，惟念其自身已因酒醉駕車受有胸部\n    挫傷並左側第四、第五肋骨骨折、臉部及四肢多處擦傷等傷害（見卷附寶建醫院\n    診斷證明書），已受有相當教訓等一切情狀，量處如主文所示之刑，並諭知易科\n    罰金之折算標準。\n三、依刑事訴訟法第四百四十九條第一項前段、第四百五十四條第二項，刑法第一百\n    八十五條之三、第四十一條第一項前段，罰金罰鍰提高標準條例第二條，判決如\n    主文。\n中      華      民      國    九十三    年      四      月      九      日\n                                      臺灣屏東地方法院交通法庭\n                                          法  官   陳姵君\n右正本證明與原本無異。\n如不服本判決，得於判決書送達之翌日起十日內，以書狀敘述理由，向本庭提出上訴\n。\n                                          書記官   許倬維\n中      華      民      國    九十三    年      四      月      九      日\n附錄本判決論罪科刑法條全文\n刑法第一百八十五條之三：\n服用毒品、麻醉藥品、酒類或其他相類之物，不能安全駕駛動力交通工具而駕駛者，\n處一年以下有期徒刑、拘役或三萬元以下罰金。\n",
  "structure": {
    "main": "甲○○服用酒類，不能安全駕駛動力交通工具而駕駛，處有期徒刑貳月，如易科罰金\n，以參佰元折算壹日。",
    "fact": "一、本件認定被告犯罪之事實、理由並所犯法條，除理由部分另補充：「依據卷附中\n    央警察大學所作身體酒精濃度與肇事率試驗所示，於飲酒後呼氣中酒精濃度逾每\n    公升０．８５毫克時，將出現平衡感與障礙度升高、肇事率為一般人五十倍，而\n    被告甲○○行為後經測得之呼氣酒精濃度高達每公升一點一二毫克，遠高於前開\n    數值，且被告為警查獲時，有語無論次、意識模糊、多話等酒醉症狀，有「刑法\n    第一百八十五條之三案件測試觀察記錄表」一紙在卷可稽，又被告自稱因閃避狗\n    隻不慎摔倒時，天候晴，日間自然光線，該路段為直路且路面狀態鋪有柏油，乾\n    燥，無缺陷，路面無障礙物，視距良好，此有屏東縣警察局分屏東局交通警察隊\n    所製作之道路交通事故調查報告表一紙可參，而被告亦自承肇事當時車速僅每小\n    時三十至四十公里，且並未撥打手持式行動電話等語（見警卷），依一般正常駕\n    駛人之反應能力，於相同情況之下，當足以正常行駛而無發生事故之虞，被告竟\n    仍因注意力、距離判斷之能力未足因於無外力影響下自行摔倒路面，故其因服用\n    酒類致使其安全駕駛動力交通工具之能力衰退甚明，被告辯稱交通事故與其飲酒\n    無關，不會造成人車危險云云，顯非可採。本件事證明確，被告服用酒類，不能\n    安全駕駛動力交通工具而駕駛之犯行，洵堪認定。」，其餘均引用檢察官聲請簡\n    易判決處刑書之記載（如附件）。\n二、爰審酌被告甲○○前已於九十年間，因酒醉駕車之公共危險案件，經本院以九十\n    年度屏交簡字第四四六號判處拘役四十五日，甫於九十一年三月二十七日入監執\n    行完畢，仍不知警惕，再度酒醉駕車，且酒醉程度非輕，對其他用路人已有高度\n    之危險性，又於犯罪後飾詞狡辯，不知悔改，惟念其自身已因酒醉駕車受有胸部\n    挫傷並左側第四、第五肋骨骨折、臉部及四肢多處擦傷等傷害（見卷附寶建醫院\n    診斷證明書），已受有相當教訓等一切情狀，量處如主文所示之刑，並諭知易科\n    罰金之折算標準。\n三、依刑事訴訟法第四百四十九條第一項前段、第四百五十四條第二項，刑法第一百\n    八十五條之三、第四十一條第一項前段，罰金罰鍰提高標準條例第二條，判決如\n    主文。",
    "reason": "一、本件認定被告犯罪之事實、理由並所犯法條，除理由部分另補充：「依據卷附中\n    央警察大學所作身體酒精濃度與肇事率試驗所示，於飲酒後呼氣中酒精濃度逾每\n    公升０．８５毫克時，將出現平衡感與障礙度升高、肇事率為一般人五十倍，而\n    被告甲○○行為後經測得之呼氣酒精濃度高達每公升一點一二毫克，遠高於前開\n    數值，且被告為警查獲時，有語無論次、意識模糊、多話等酒醉症狀，有「刑法\n    第一百八十五條之三案件測試觀察記錄表」一紙在卷可稽，又被告自稱因閃避狗\n    隻不慎摔倒時，天候晴，日間自然光線，該路段為直路且路面狀態鋪有柏油，乾\n    燥，無缺陷，路面無障礙物，視距良好，此有屏東縣警察局分屏東局交通警察隊\n    所製作之道路交通事故調查報告表一紙可參，而被告亦自承肇事當時車速僅每小\n    時三十至四十公里，且並未撥打手持式行動電話等語（見警卷），依一般正常駕\n    駛人之反應能力，於相同情況之下，當足以正常行駛而無發生事故之虞，被告竟\n    仍因注意力、距離判斷之能力未足因於無外力影響下自行摔倒路面，故其因服用\n    酒類致使其安全駕駛動力交通工具之能力衰退甚明，被告辯稱交通事故與其飲酒\n    無關，不會造成人車危險云云，顯非可採。本件事證明確，被告服用酒類，不能\n    安全駕駛動力交通工具而駕駛之犯行，洵堪認定。」，其餘均引用檢察官聲請簡\n    易判決處刑書之記載（如附件）。\n二、爰審酌被告甲○○前已於九十年間，因酒醉駕車之公共危險案件，經本院以九十\n    年度屏交簡字第四四六號判處拘役四十五日，甫於九十一年三月二十七日入監執\n    行完畢，仍不知警惕，再度酒醉駕車，且酒醉程度非輕，對其他用路人已有高度\n    之危險性，又於犯罪後飾詞狡辯，不知悔改，惟念其自身已因酒醉駕車受有胸部\n    挫傷並左側第四、第五肋骨骨折、臉部及四肢多處擦傷等傷害（見卷附寶建醫院\n    診斷證明書），已受有相當教訓等一切情狀，量處如主文所示之刑，並諭知易科\n    罰金之折算標準。\n三、依刑事訴訟法第四百四十九條第一項前段、第四百五十四條第二項，刑法第一百\n    八十五條之三、第四十一條第一項前段，罰金罰鍰提高標準條例第二條，判決如\n    主文。"
  },
  "search": "臺灣屏東地方法院刑事簡易判決九十三年度交簡字第二七五號聲請人臺灣屏東地方法院檢察署檢察官被告甲○○右列被告因公共危險案件，經檢察官聲請以簡易判決處刑（九十三年度偵字第一六三五號），本院判決如左：主文甲○○服用酒類，不能安全駕駛動力交通工具而駕駛，處有期徒刑貳月，如易科罰金，以參佰元折算壹日。事實及理由一、本件認定被告犯罪之事實、理由並所犯法條，除理由部分另補充：「依據卷附中央警察大學所作身體酒精濃度與肇事率試驗所示，於飲酒後呼氣中酒精濃度逾每公升０．８５毫克時，將出現平衡感與障礙度升高、肇事率為一般人五十倍，而被告甲○○行為後經測得之呼氣酒精濃度高達每公升一點一二毫克，遠高於前開數值，且被告為警查獲時，有語無論次、意識模糊、多話等酒醉症狀，有「刑法第一百八十五條之三案件測試觀察記錄表」一紙在卷可稽，又被告自稱因閃避狗隻不慎摔倒時，天候晴，日間自然光線，該路段為直路且路面狀態鋪有柏油，乾燥，無缺陷，路面無障礙物，視距良好，此有屏東縣警察局分屏東局交通警察隊所製作之道路交通事故調查報告表一紙可參，而被告亦自承肇事當時車速僅每小時三十至四十公里，且並未撥打手持式行動電話等語（見警卷），依一般正常駕駛人之反應能力，於相同情況之下，當足以正常行駛而無發生事故之虞，被告竟仍因注意力、距離判斷之能力未足因於無外力影響下自行摔倒路面，故其因服用酒類致使其安全駕駛動力交通工具之能力衰退甚明，被告辯稱交通事故與其飲酒無關，不會造成人車危險云云，顯非可採。本件事證明確，被告服用酒類，不能安全駕駛動力交通工具而駕駛之犯行，洵堪認定。」，其餘均引用檢察官聲請簡易判決處刑書之記載（如附件）。二、爰審酌被告甲○○前已於九十年間，因酒醉駕車之公共危險案件，經本院以九十年度屏交簡字第四四六號判處拘役四十五日，甫於九十一年三月二十七日入監執行完畢，仍不知警惕，再度酒醉駕車，且酒醉程度非輕，對其他用路人已有高度之危險性，又於犯罪後飾詞狡辯，不知悔改，惟念其自身已因酒醉駕車受有胸部挫傷並左側第四、第五肋骨骨折、臉部及四肢多處擦傷等傷害（見卷附寶建醫院診斷證明書），已受有相當教訓等一切情狀，量處如主文所示之刑，並諭知易科罰金之折算標準。三、依刑事訴訟法第四百四十九條第一項前段、第四百五十四條第二項，刑法第一百八十五條之三、第四十一條第一項前段，罰金罰鍰提高標準條例第二條，判決如主文。中華民國九十三年四月九日臺灣屏東地方法院交通法庭法官陳姵君右正本證明與原本無異。如不服本判決，得於判決書送達之翌日起十日內，以書狀敘述理由，向本庭提出上訴。書記官許倬維中華民國九十三年四月九日附錄本判決論罪科刑法條全文刑法第一百八十五條之三：服用毒品、麻醉藥品、酒類或其他相類之物，不能安全駕駛動力交通工具而駕駛者，處一年以下有期徒刑、拘役或三萬元以下罰金。",
  "characters": {
    "judges": [
      "陳姵君"
    ],
    "prosecutors": [

    ],
    "lawyers": [

    ],
    "clerks": [
      "許倬維"
    ],
    "plaintiffs": [

    ],
    "defendants": [
      "甲○○",
      "右列被告因公共危險案件，經檢察官聲請以簡易判決處刑（九十三年度偵字第一六三",
      "五號），本院判決如左："
    ],
    "prosecutor_office": [
      "臺灣屏東地方法院檢察署檢察官"
    ],
    "creditors": [

    ],
    "debtors": [

    ],
    "judicial_associate_officer": [

    ]
  },
  "adjudged_at": "2004-04-09",
  "created_at": "2016-02-05 23:02:47",
  "updated_at": "2016-02-05 23:02:47"
}