{
  "identify": "KSD-94-交簡-1760-20050623-1",
  "court": {
    "name": "臺灣高雄地方法院",
    "code": "KSD"
  },
  "division": {
    "name": "刑事",
    "code": "M"
  },
  "year": 94,
  "word": "交簡",
  "number": "1760",
  "jcheck": "1",
  "reason": "公共危險",
  "content": "臺灣高雄地方法院刑事簡易判決        94年度交簡字第1760號\n聲  請  人  臺灣高雄地方法院檢察署檢察官\n被      告  甲○○  男  28歲.\n上列被告因公共危險案件，經檢察官聲請以簡易判決處刑（94年\n度偵字第9501號），本院判決如下：\n    主  文\n甲○○服用酒類，不能安全駕駛動力交通工具而駕駛，處有期徒\n刑月，如易科罰金，以佰元（即新臺幣玖佰元）折算壹日。\n    事實及理由\n一、本案被告甲○○之犯罪事實及證據，均引用如附件檢察官聲\n    請簡易判決處刑書所載，並分別更正如下：(1)犯罪事實所載\n    ：「（甲○○）經送醫後測得其血液中之呼氣酒精濃度為每\n    公升1.21毫克」等語，更正為：「甲○○送醫後，測得其血\n    液中之酒精濃度為242.55mg/dl ，換算呼氣中之酒精濃度為\n    公升1.21毫克」。(2)證據部分所載「酒精測定值1 紙」，更\n    正為「財團法人義大醫院93年12月24日之檢驗單號LＺ000000\n    000 號生化檢驗報告1 紙」。\n二、核被告所為，係犯刑法第185 條之3 之服用酒類不能安全駕\n    駛動力交通工具而駕駛罪。爰審酌被告明知飲用酒類後對於\n    發生道路交通事故之機率，較未飲酒者為高，竟於飲酌酒類\n    後呼氣酒精濃度測試高達每公升1.21毫克，已超過安全標準\n    之每公升0.55毫克，猶不知謹慎，仍駕駛具有高度危險性之\n    重型機車，無視於公眾生命財產安全，亦自陷於危險狀態之\n    中，嚴重侵害道路交通往來之安全，並肇致本件交通車禍事\n    故，惟念其犯後坦承犯行，尚知悔悟等一切情狀，量處如主\n    文所示之刑，並諭知易科罰金之折算標準，以為懲儆。\n三、依刑事訴訟法第449 條第1 項、第3 項、第454 條第2 項，\n    刑法第18 5條之3 、第41條第1 項前段，罰金罰鍰提高標準\n    條例第2 條規定，逕以簡易判決判處如主文所示之刑。\n四、如不服本判決，得於判決書送達之日起10日內，向本院提出\n    上訴。\n中    華    民    國    94    年    6     月    23    日\n                  交通法庭  法  官  曾鴻文\n以上正本證明與原本無異。\n如不服本判決，應於收受送達後10日內向本院提出上訴書狀。\n中    華    民    國    94    年    6     月    23    日\n                            書記官  王高山\n附錄本案論罪科刑法條：\n刑法第185條之3：\n  服用毒品、麻醉藥品、酒類及其他相類之物，不能安全駕駛動\n  力交通工具而駕駛者，處1 年以下有期徒刑、拘役或30,000元\n  以下罰金。\n",
  "structure": {
    "main": "甲○○服用酒類，不能安全駕駛動力交通工具而駕駛，處有期徒\n刑月，如易科罰金，以佰元（即新臺幣玖佰元）折算壹日。",
    "fact": "一、本案被告甲○○之犯罪事實及證據，均引用如附件檢察官聲\n    請簡易判決處刑書所載，並分別更正如下：(1)犯罪事實所載\n    ：「（甲○○）經送醫後測得其血液中之呼氣酒精濃度為每\n    公升1.21毫克」等語，更正為：「甲○○送醫後，測得其血\n    液中之酒精濃度為242.55mg/dl ，換算呼氣中之酒精濃度為\n    公升1.21毫克」。(2)證據部分所載「酒精測定值1 紙」，更\n    正為「財團法人義大醫院93年12月24日之檢驗單號LＺ000000\n    000 號生化檢驗報告1 紙」。\n二、核被告所為，係犯刑法第185 條之3 之服用酒類不能安全駕\n    駛動力交通工具而駕駛罪。爰審酌被告明知飲用酒類後對於\n    發生道路交通事故之機率，較未飲酒者為高，竟於飲酌酒類\n    後呼氣酒精濃度測試高達每公升1.21毫克，已超過安全標準\n    之每公升0.55毫克，猶不知謹慎，仍駕駛具有高度危險性之\n    重型機車，無視於公眾生命財產安全，亦自陷於危險狀態之\n    中，嚴重侵害道路交通往來之安全，並肇致本件交通車禍事\n    故，惟念其犯後坦承犯行，尚知悔悟等一切情狀，量處如主\n    文所示之刑，並諭知易科罰金之折算標準，以為懲儆。\n三、依刑事訴訟法第449 條第1 項、第3 項、第454 條第2 項，\n    刑法第18 5條之3 、第41條第1 項前段，罰金罰鍰提高標準\n    條例第2 條規定，逕以簡易判決判處如主文所示之刑。\n四、如不服本判決，得於判決書送達之日起10日內，向本院提出\n    上訴。",
    "reason": "一、本案被告甲○○之犯罪事實及證據，均引用如附件檢察官聲\n    請簡易判決處刑書所載，並分別更正如下：(1)犯罪事實所載\n    ：「（甲○○）經送醫後測得其血液中之呼氣酒精濃度為每\n    公升1.21毫克」等語，更正為：「甲○○送醫後，測得其血\n    液中之酒精濃度為242.55mg/dl ，換算呼氣中之酒精濃度為\n    公升1.21毫克」。(2)證據部分所載「酒精測定值1 紙」，更\n    正為「財團法人義大醫院93年12月24日之檢驗單號LＺ000000\n    000 號生化檢驗報告1 紙」。\n二、核被告所為，係犯刑法第185 條之3 之服用酒類不能安全駕\n    駛動力交通工具而駕駛罪。爰審酌被告明知飲用酒類後對於\n    發生道路交通事故之機率，較未飲酒者為高，竟於飲酌酒類\n    後呼氣酒精濃度測試高達每公升1.21毫克，已超過安全標準\n    之每公升0.55毫克，猶不知謹慎，仍駕駛具有高度危險性之\n    重型機車，無視於公眾生命財產安全，亦自陷於危險狀態之\n    中，嚴重侵害道路交通往來之安全，並肇致本件交通車禍事\n    故，惟念其犯後坦承犯行，尚知悔悟等一切情狀，量處如主\n    文所示之刑，並諭知易科罰金之折算標準，以為懲儆。\n三、依刑事訴訟法第449 條第1 項、第3 項、第454 條第2 項，\n    刑法第18 5條之3 、第41條第1 項前段，罰金罰鍰提高標準\n    條例第2 條規定，逕以簡易判決判處如主文所示之刑。\n四、如不服本判決，得於判決書送達之日起10日內，向本院提出\n    上訴。"
  },
  "search": "臺灣高雄地方法院刑事簡易判決94年度交簡字第1760號聲請人臺灣高雄地方法院檢察署檢察官被告甲○○男28歲.上列被告因公共危險案件，經檢察官聲請以簡易判決處刑（94年度偵字第9501號），本院判決如下：主文甲○○服用酒類，不能安全駕駛動力交通工具而駕駛，處有期徒刑月，如易科罰金，以佰元（即新臺幣玖佰元）折算壹日。事實及理由一、本案被告甲○○之犯罪事實及證據，均引用如附件檢察官聲請簡易判決處刑書所載，並分別更正如下：(1)犯罪事實所載：「（甲○○）經送醫後測得其血液中之呼氣酒精濃度為每公升1.21毫克」等語，更正為：「甲○○送醫後，測得其血液中之酒精濃度為242.55mg/dl，換算呼氣中之酒精濃度為公升1.21毫克」。(2)證據部分所載「酒精測定值1紙」，更正為「財團法人義大醫院93年12月24日之檢驗單號LＺ000000000號生化檢驗報告1紙」。二、核被告所為，係犯刑法第185條之3之服用酒類不能安全駕駛動力交通工具而駕駛罪。爰審酌被告明知飲用酒類後對於發生道路交通事故之機率，較未飲酒者為高，竟於飲酌酒類後呼氣酒精濃度測試高達每公升1.21毫克，已超過安全標準之每公升0.55毫克，猶不知謹慎，仍駕駛具有高度危險性之重型機車，無視於公眾生命財產安全，亦自陷於危險狀態之中，嚴重侵害道路交通往來之安全，並肇致本件交通車禍事故，惟念其犯後坦承犯行，尚知悔悟等一切情狀，量處如主文所示之刑，並諭知易科罰金之折算標準，以為懲儆。三、依刑事訴訟法第449條第1項、第3項、第454條第2項，刑法第185條之3、第41條第1項前段，罰金罰鍰提高標準條例第2條規定，逕以簡易判決判處如主文所示之刑。四、如不服本判決，得於判決書送達之日起10日內，向本院提出上訴。中華民國94年6月23日交通法庭法官曾鴻文以上正本證明與原本無異。如不服本判決，應於收受送達後10日內向本院提出上訴書狀。中華民國94年6月23日書記官王高山附錄本案論罪科刑法條：刑法第185條之3：服用毒品、麻醉藥品、酒類及其他相類之物，不能安全駕駛動力交通工具而駕駛者，處1年以下有期徒刑、拘役或30,000元以下罰金。",
  "characters": {
    "judges": [
      "曾鴻文"
    ],
    "prosecutors": [

    ],
    "lawyers": [

    ],
    "clerks": [
      "王高山"
    ],
    "plaintiffs": [

    ],
    "defendants": [
      "甲○○  男  28歲."
    ],
    "prosecutor_office": [
      "臺灣高雄地方法院檢察署檢察官"
    ],
    "creditors": [

    ],
    "debtors": [

    ],
    "judicial_associate_officer": [

    ]
  },
  "adjudged_at": "2005-06-23",
  "created_at": "2016-02-07 06:01:07",
  "updated_at": "2016-02-07 06:01:07"
}