{
  "identify": "PTD-94-訴-261-20050622-2",
  "court": {
    "name": "臺灣屏東地方法院",
    "code": "PTD"
  },
  "division": {
    "name": "刑事",
    "code": "M"
  },
  "year": 94,
  "word": "訴",
  "number": "261",
  "jcheck": "2",
  "reason": "違反毒品危害防制條例",
  "content": "臺灣屏東地方法院刑事判決               94年度訴字第261號\n公  訴  人  臺灣屏東地方法院檢察署檢察官\n被      告  甲○○  男  51歲.\n上列被告因違反毒品危害防制條例案件，經檢察官提起公訴（93\n年度毒偵字第2479號），被告於本院準備程序就被訴事實為有罪\n之陳述，經本院合議庭裁定由受命法官獨任依簡式審判程序審理\n，判決如下：\n    主  文\n甲○○施用第一級毒品，處有期徒刑拾月。\n    事  實\n一、甲○○前於民國八十九年間，因施用毒品案件，經本院八十\n    九年度毒聲字第二八九三號裁定送觀察、勒戒後，認有繼續\n    施用毒品之傾向，再經本院九十年度毒聲字第七三號裁定送\n    強制戒治，嗣因戒治成效良好，經本院九十年度毒聲字第二\n    ○三六號裁定停止戒治，所餘戒治期間付保護管束，且於九\n    十一年一月三十一日保護管束期滿，經臺灣屏東地方法院檢\n    察署檢察官於九十一年一月十三日以九十一年度戒毒偵字第\n    一六號不起訴處分確定。詎仍不知戒絕，又基於施用第一級\n    毒品海洛因之犯意，於九十三年九月十五日某時，在嘉義市\n    ○區○○路四○五巷十三號旁騎樓下，以將毒品海洛因摻入\n    香菸內點燃吸食之方式，施用第一級毒品海洛因一次。嗣於\n    同年九月十七日十二時四十分許，為警在嘉義市○區○○路\n    四○五巷十三號前查獲（並在同遭查獲之案外人江慶龍所坐\n    椅子下扣得所有人不明且沾有毒品海洛因殘渣之注射針筒一\n    支）。\n二、案經嘉義市警察局第一分局報告報告臺灣嘉義地方法院檢察\n    署檢察官呈請臺灣高等法院檢察署令轉臺灣屏東地方法院檢\n    察署檢察官偵查起訴。\n    理  由\n一、本件被告甲○○所犯係死刑、無期徒刑、最輕本刑為三年以\n    上有期徒刑以外之罪，其於本院準備程序中就被訴事實為有\n    罪之陳述，經本院合議庭裁定由受命法官獨任依簡式審判程\n    序，先予敘明。\n二、上揭事實，訊據被告甲○○於本院審理中坦承不諱，而被告\n    為警查獲後經採尿送鑑定結果，呈嗎啡陽性反應，有台灣檢\n    驗科技股份有限公司濫用藥物檢驗報告一份在卷可稽，是被\n    告之自白，應與事實相符。查被告前於八十九年間，因施用\n    毒品案件，經本院八十九年度毒聲字第二八九三號裁定送觀\n    察、勒戒後，認有繼續施用毒品之傾向，再經本院九十年度\n    毒聲字第七三號裁定送強制戒治，嗣因戒治成效良好，經本\n    院九十年度毒聲字第二○三六號裁定停止戒治，所餘戒治期\n    間付保護管束，且於九十一年一月三十一日保護管束期滿，\n    經臺灣屏東地方法院檢察署檢察官於九十一年一月十三日以\n    九十一年度戒毒偵字第一六號不起訴處分確定，有卷附臺灣\n    屏東地方法院檢察署刑案資料查註紀錄表、臺灣高等法院被\n    告全國前案紀錄表可參，是被告上開施用第一級毒品犯行，\n    自應依法論科。\n三、按海洛因係毒品危害防制條例所定之第一級毒品，不得非法\n    施用，是核被告所為，係犯毒品危害防制條例第十條第一項\n    施用第一級毒品罪。被告為施用毒品海洛因而持有毒品之低\n    度行為，已為其施用之高度行為所吸收，不另論罪。爰審酌\n    被告前有竊盜等前科（尚未執行完畢，有卷附臺灣屏東地方\n    法院檢察署刑案資料查註紀錄表、臺灣高等法院被告全國前\n    案紀錄表可參），復經戒斷毒癮之保安處分程序（參見前揭\n    紀錄表），猶無法徹底戒絕，顯見其意志不堅，無悔改之決\n    心，有違政府制定毒品危害防制條例之立法美意，惟考量施\n    用毒品係戕害自身健康，及犯後態度尚可等一切情狀，量處\n    如主文所示之刑。又扣案之注射針筒一支，雖經本院送請專\n    業機構鑑定結果，呈第一級毒品海洛因陽性反應，有高雄醫\n    學大學附設中和紀念醫院檢驗報告一份附卷可稽，然被告於\n    警詢及本院審理中均堅決否認為其所有等語，參酌該注射針\n    係在同遭查獲之案外人江慶龍所坐椅子下查獲乙節，有被告\n    及江慶龍警詢筆錄在卷可參，自難遽認係在被告實力支配範\n    圍內，復依其自白之施用方式，足見該注射針筒亦非被告施\n    用毒品海洛因之工具，故乏積極證據證明確與被告施用毒品\n    海洛因之犯行有關，爰不另為沒收銷燬之諭知，附此敘明。\n據上論斷，應依刑事訴訟法第二百七十三條之一第一項、第二百\n九十九條第一項前段，毒品危害防制條例第十條第一項，判決如\n主文。\n本案經檢察官劉俊儀到庭執行職務。\n中    華    民    國      94     年    6    月   22   日\n                          臺灣屏東地方法院刑事第四庭\n                              法  官  劉敏芳\n以上正本證明與原本無異。\n如不服本判決應於收受本判決送達後十日內向本院提出上訴書狀\n，其未敘述上訴理由者，並得於提起上訴後十日內向本院補提理\n由書狀（均須按他造當事人之人數附繕本）「切勿逕送上級法院\n」\n中    華    民    國    94    年    6     月    22    日\n                              書記官  許倬維\n附錄本案論罪法條：\n毒品危害防制條例第十條第一項：\n施用第一級毒品者，處六月以上五年以下有期徒刑。\n",
  "structure": {
    "main": "甲○○施用第一級毒品，處有期徒刑拾月。",
    "fact": "一、甲○○前於民國八十九年間，因施用毒品案件，經本院八十\n    九年度毒聲字第二八九三號裁定送觀察、勒戒後，認有繼續\n    施用毒品之傾向，再經本院九十年度毒聲字第七三號裁定送\n    強制戒治，嗣因戒治成效良好，經本院九十年度毒聲字第二\n    ○三六號裁定停止戒治，所餘戒治期間付保護管束，且於九\n    十一年一月三十一日保護管束期滿，經臺灣屏東地方法院檢\n    察署檢察官於九十一年一月十三日以九十一年度戒毒偵字第\n    一六號不起訴處分確定。詎仍不知戒絕，又基於施用第一級\n    毒品海洛因之犯意，於九十三年九月十五日某時，在嘉義市\n    ○區○○路四○五巷十三號旁騎樓下，以將毒品海洛因摻入\n    香菸內點燃吸食之方式，施用第一級毒品海洛因一次。嗣於\n    同年九月十七日十二時四十分許，為警在嘉義市○區○○路\n    四○五巷十三號前查獲（並在同遭查獲之案外人江慶龍所坐\n    椅子下扣得所有人不明且沾有毒品海洛因殘渣之注射針筒一\n    支）。\n二、案經嘉義市警察局第一分局報告報告臺灣嘉義地方法院檢察\n    署檢察官呈請臺灣高等法院檢察署令轉臺灣屏東地方法院檢\n    察署檢察官偵查起訴。",
    "reason": "一、本件被告甲○○所犯係死刑、無期徒刑、最輕本刑為三年以\n    上有期徒刑以外之罪，其於本院準備程序中就被訴事實為有\n    罪之陳述，經本院合議庭裁定由受命法官獨任依簡式審判程\n    序，先予敘明。\n二、上揭事實，訊據被告甲○○於本院審理中坦承不諱，而被告\n    為警查獲後經採尿送鑑定結果，呈嗎啡陽性反應，有台灣檢\n    驗科技股份有限公司濫用藥物檢驗報告一份在卷可稽，是被\n    告之自白，應與事實相符。查被告前於八十九年間，因施用\n    毒品案件，經本院八十九年度毒聲字第二八九三號裁定送觀\n    察、勒戒後，認有繼續施用毒品之傾向，再經本院九十年度\n    毒聲字第七三號裁定送強制戒治，嗣因戒治成效良好，經本\n    院九十年度毒聲字第二○三六號裁定停止戒治，所餘戒治期\n    間付保護管束，且於九十一年一月三十一日保護管束期滿，\n    經臺灣屏東地方法院檢察署檢察官於九十一年一月十三日以\n    九十一年度戒毒偵字第一六號不起訴處分確定，有卷附臺灣\n    屏東地方法院檢察署刑案資料查註紀錄表、臺灣高等法院被\n    告全國前案紀錄表可參，是被告上開施用第一級毒品犯行，\n    自應依法論科。\n三、按海洛因係毒品危害防制條例所定之第一級毒品，不得非法\n    施用，是核被告所為，係犯毒品危害防制條例第十條第一項\n    施用第一級毒品罪。被告為施用毒品海洛因而持有毒品之低\n    度行為，已為其施用之高度行為所吸收，不另論罪。爰審酌\n    被告前有竊盜等前科（尚未執行完畢，有卷附臺灣屏東地方\n    法院檢察署刑案資料查註紀錄表、臺灣高等法院被告全國前\n    案紀錄表可參），復經戒斷毒癮之保安處分程序（參見前揭\n    紀錄表），猶無法徹底戒絕，顯見其意志不堅，無悔改之決\n    心，有違政府制定毒品危害防制條例之立法美意，惟考量施\n    用毒品係戕害自身健康，及犯後態度尚可等一切情狀，量處\n    如主文所示之刑。又扣案之注射針筒一支，雖經本院送請專\n    業機構鑑定結果，呈第一級毒品海洛因陽性反應，有高雄醫\n    學大學附設中和紀念醫院檢驗報告一份附卷可稽，然被告於\n    警詢及本院審理中均堅決否認為其所有等語，參酌該注射針\n    係在同遭查獲之案外人江慶龍所坐椅子下查獲乙節，有被告\n    及江慶龍警詢筆錄在卷可參，自難遽認係在被告實力支配範\n    圍內，復依其自白之施用方式，足見該注射針筒亦非被告施\n    用毒品海洛因之工具，故乏積極證據證明確與被告施用毒品\n    海洛因之犯行有關，爰不另為沒收銷燬之諭知，附此敘明。\n據上論斷，應依刑事訴訟法第二百七十三條之一第一項、第二百\n九十九條第一項前段，毒品危害防制條例第十條第一項，判決如\n主文。\n本案經檢察官劉俊儀到庭執行職務。\n中    華    民    國      94     年    6    月   22   日\n                          臺灣屏東地方法院刑事第四庭\n                              法  官  劉敏芳\n以上正本證明與原本無異。\n如不服本判決應於收受本判決送達後十日內向本院提出上訴書狀\n，其未敘述上訴理由者，並得於提起上訴後十日內向本院補提理\n由書狀（均須按他造當事人之人數附繕本）「切勿逕送上級法院\n」"
  },
  "search": "臺灣屏東地方法院刑事判決94年度訴字第261號公訴人臺灣屏東地方法院檢察署檢察官被告甲○○男51歲.上列被告因違反毒品危害防制條例案件，經檢察官提起公訴（93年度毒偵字第2479號），被告於本院準備程序就被訴事實為有罪之陳述，經本院合議庭裁定由受命法官獨任依簡式審判程序審理，判決如下：主文甲○○施用第一級毒品，處有期徒刑拾月。事實一、甲○○前於民國八十九年間，因施用毒品案件，經本院八十九年度毒聲字第二八九三號裁定送觀察、勒戒後，認有繼續施用毒品之傾向，再經本院九十年度毒聲字第七三號裁定送強制戒治，嗣因戒治成效良好，經本院九十年度毒聲字第二○三六號裁定停止戒治，所餘戒治期間付保護管束，且於九十一年一月三十一日保護管束期滿，經臺灣屏東地方法院檢察署檢察官於九十一年一月十三日以九十一年度戒毒偵字第一六號不起訴處分確定。詎仍不知戒絕，又基於施用第一級毒品海洛因之犯意，於九十三年九月十五日某時，在嘉義市○區○○路四○五巷十三號旁騎樓下，以將毒品海洛因摻入香菸內點燃吸食之方式，施用第一級毒品海洛因一次。嗣於同年九月十七日十二時四十分許，為警在嘉義市○區○○路四○五巷十三號前查獲（並在同遭查獲之案外人江慶龍所坐椅子下扣得所有人不明且沾有毒品海洛因殘渣之注射針筒一支）。二、案經嘉義市警察局第一分局報告報告臺灣嘉義地方法院檢察署檢察官呈請臺灣高等法院檢察署令轉臺灣屏東地方法院檢察署檢察官偵查起訴。理由一、本件被告甲○○所犯係死刑、無期徒刑、最輕本刑為三年以上有期徒刑以外之罪，其於本院準備程序中就被訴事實為有罪之陳述，經本院合議庭裁定由受命法官獨任依簡式審判程序，先予敘明。二、上揭事實，訊據被告甲○○於本院審理中坦承不諱，而被告為警查獲後經採尿送鑑定結果，呈嗎啡陽性反應，有台灣檢驗科技股份有限公司濫用藥物檢驗報告一份在卷可稽，是被告之自白，應與事實相符。查被告前於八十九年間，因施用毒品案件，經本院八十九年度毒聲字第二八九三號裁定送觀察、勒戒後，認有繼續施用毒品之傾向，再經本院九十年度毒聲字第七三號裁定送強制戒治，嗣因戒治成效良好，經本院九十年度毒聲字第二○三六號裁定停止戒治，所餘戒治期間付保護管束，且於九十一年一月三十一日保護管束期滿，經臺灣屏東地方法院檢察署檢察官於九十一年一月十三日以九十一年度戒毒偵字第一六號不起訴處分確定，有卷附臺灣屏東地方法院檢察署刑案資料查註紀錄表、臺灣高等法院被告全國前案紀錄表可參，是被告上開施用第一級毒品犯行，自應依法論科。三、按海洛因係毒品危害防制條例所定之第一級毒品，不得非法施用，是核被告所為，係犯毒品危害防制條例第十條第一項施用第一級毒品罪。被告為施用毒品海洛因而持有毒品之低度行為，已為其施用之高度行為所吸收，不另論罪。爰審酌被告前有竊盜等前科（尚未執行完畢，有卷附臺灣屏東地方法院檢察署刑案資料查註紀錄表、臺灣高等法院被告全國前案紀錄表可參），復經戒斷毒癮之保安處分程序（參見前揭紀錄表），猶無法徹底戒絕，顯見其意志不堅，無悔改之決心，有違政府制定毒品危害防制條例之立法美意，惟考量施用毒品係戕害自身健康，及犯後態度尚可等一切情狀，量處如主文所示之刑。又扣案之注射針筒一支，雖經本院送請專業機構鑑定結果，呈第一級毒品海洛因陽性反應，有高雄醫學大學附設中和紀念醫院檢驗報告一份附卷可稽，然被告於警詢及本院審理中均堅決否認為其所有等語，參酌該注射針係在同遭查獲之案外人江慶龍所坐椅子下查獲乙節，有被告及江慶龍警詢筆錄在卷可參，自難遽認係在被告實力支配範圍內，復依其自白之施用方式，足見該注射針筒亦非被告施用毒品海洛因之工具，故乏積極證據證明確與被告施用毒品海洛因之犯行有關，爰不另為沒收銷燬之諭知，附此敘明。據上論斷，應依刑事訴訟法第二百七十三條之一第一項、第二百九十九條第一項前段，毒品危害防制條例第十條第一項，判決如主文。本案經檢察官劉俊儀到庭執行職務。中華民國94年6月22日臺灣屏東地方法院刑事第四庭法官劉敏芳以上正本證明與原本無異。如不服本判決應於收受本判決送達後十日內向本院提出上訴書狀，其未敘述上訴理由者，並得於提起上訴後十日內向本院補提理由書狀（均須按他造當事人之人數附繕本）「切勿逕送上級法院」中華民國94年6月22日書記官許倬維附錄本案論罪法條：毒品危害防制條例第十條第一項：施用第一級毒品者，處六月以上五年以下有期徒刑。",
  "characters": {
    "judges": [
      "劉敏芳"
    ],
    "prosecutors": [
      "劉俊儀"
    ],
    "lawyers": [

    ],
    "clerks": [
      "許倬維"
    ],
    "plaintiffs": [

    ],
    "defendants": [
      "甲○○  男  51歲."
    ],
    "prosecutor_office": [
      "臺灣屏東地方法院檢察署檢察官"
    ],
    "creditors": [

    ],
    "debtors": [

    ],
    "judicial_associate_officer": [

    ]
  },
  "adjudged_at": "2005-06-22",
  "created_at": "2016-02-07 05:56:17",
  "updated_at": "2016-02-07 05:56:17"
}