{
  "identify": "KSD-91-易-3114-20020923-1",
  "court": {
    "name": "臺灣高雄地方法院",
    "code": "KSD"
  },
  "division": {
    "name": "刑事",
    "code": "M"
  },
  "year": 91,
  "word": "易",
  "number": "3114",
  "jcheck": "1",
  "reason": "家暴傷害罪",
  "content": "臺灣高雄地方法院刑事判決                        九十一年度易字第三一一四號\n    公  訴  人  臺灣高雄地方法院檢察署檢察官\n    被      告  乙○○\n右列被告因家暴傷害罪案件，經檢察官聲請簡易判決處刑（九十一年度偵字第一五三\n三二號），經本院認不宜以簡易判決處刑，依刑事訴訟法第四百五十二條之規定，改\n依通常訴訟程序審理，本院判決如左：\n    主  文\n本件公訴不受理。\n    理   由\n一、公訴意旨係以：被告乙○○係告訴人甲○○之夫，二人間具有家庭暴力防治法第\n    三條第一款所定之家庭成員關係。被告乙○○於民國（下同）九十一年七月一日\n    二十一時三十分許，在高雄縣鳳山市○○里○○路一二九巷六十二號自宅，因細\n    故，竟基於傷害之犯意，徒手毆打其妻即告訴人甲○○之臉部等處，致告訴人甲\n    ○○受有左前額裂傷等傷害。因認被告乙○○涉犯刑法第二百七十七條第一項之\n    普通傷害罪嫌等語。\n二、按告訴乃論之罪，告訴人於第一審辯論終結前，得撤回其告訴；又告訴經撤回者\n    ，法院應諭知不受理之判決，刑事訴訟法第二百三十八條第一項，及第三百零三\n    條第三款定有明文。\n三、本件被告乙○○因傷害案件，經檢察官提起公訴，認被告乙○○係犯刑法第二百\n    七十七條第一項之傷害罪。依同法第二百八十七條前段之規定，須告訴乃論。茲\n    據告訴人甲○○於本院審理中，具狀聲請撤回其告訴，有撤回告訴狀一份在卷可\n    稽，揆諸前開說明，爰不經言詞辯論，逕為諭知不受理之判決。\n據上論斷，應依刑事訴訟法第四百五十二條、第三百零三條第三款、第三百零七條，\n判決如主文。\n中      華      民      國      九十一      年      九    月    二十三  日\n                                  臺灣高雄地方法院刑事第六庭\n                                      法  官  李怡諄\n右為正本證明與原本無異。\n如不服本判決，應於送達後十日內，向本院提出上訴狀。\n                                      書記官  陳孟瑩\n中      華      民      國    九十一      年    九      月    二十三    日\n",
  "structure": {
    "main": "本件公訴不受理。",
    "reason": "一、公訴意旨係以：被告乙○○係告訴人甲○○之夫，二人間具有家庭暴力防治法第\n    三條第一款所定之家庭成員關係。被告乙○○於民國（下同）九十一年七月一日\n    二十一時三十分許，在高雄縣鳳山市○○里○○路一二九巷六十二號自宅，因細\n    故，竟基於傷害之犯意，徒手毆打其妻即告訴人甲○○之臉部等處，致告訴人甲\n    ○○受有左前額裂傷等傷害。因認被告乙○○涉犯刑法第二百七十七條第一項之\n    普通傷害罪嫌等語。\n二、按告訴乃論之罪，告訴人於第一審辯論終結前，得撤回其告訴；又告訴經撤回者\n    ，法院應諭知不受理之判決，刑事訴訟法第二百三十八條第一項，及第三百零三\n    條第三款定有明文。\n三、本件被告乙○○因傷害案件，經檢察官提起公訴，認被告乙○○係犯刑法第二百\n    七十七條第一項之傷害罪。依同法第二百八十七條前段之規定，須告訴乃論。茲\n    據告訴人甲○○於本院審理中，具狀聲請撤回其告訴，有撤回告訴狀一份在卷可\n    稽，揆諸前開說明，爰不經言詞辯論，逕為諭知不受理之判決。\n據上論斷，應依刑事訴訟法第四百五十二條、第三百零三條第三款、第三百零七條，\n判決如主文。"
  },
  "search": "臺灣高雄地方法院刑事判決九十一年度易字第三一一四號公訴人臺灣高雄地方法院檢察署檢察官被告乙○○右列被告因家暴傷害罪案件，經檢察官聲請簡易判決處刑（九十一年度偵字第一五三三二號），經本院認不宜以簡易判決處刑，依刑事訴訟法第四百五十二條之規定，改依通常訴訟程序審理，本院判決如左：主文本件公訴不受理。理由一、公訴意旨係以：被告乙○○係告訴人甲○○之夫，二人間具有家庭暴力防治法第三條第一款所定之家庭成員關係。被告乙○○於民國（下同）九十一年七月一日二十一時三十分許，在高雄縣鳳山市○○里○○路一二九巷六十二號自宅，因細故，竟基於傷害之犯意，徒手毆打其妻即告訴人甲○○之臉部等處，致告訴人甲○○受有左前額裂傷等傷害。因認被告乙○○涉犯刑法第二百七十七條第一項之普通傷害罪嫌等語。二、按告訴乃論之罪，告訴人於第一審辯論終結前，得撤回其告訴；又告訴經撤回者，法院應諭知不受理之判決，刑事訴訟法第二百三十八條第一項，及第三百零三條第三款定有明文。三、本件被告乙○○因傷害案件，經檢察官提起公訴，認被告乙○○係犯刑法第二百七十七條第一項之傷害罪。依同法第二百八十七條前段之規定，須告訴乃論。茲據告訴人甲○○於本院審理中，具狀聲請撤回其告訴，有撤回告訴狀一份在卷可稽，揆諸前開說明，爰不經言詞辯論，逕為諭知不受理之判決。據上論斷，應依刑事訴訟法第四百五十二條、第三百零三條第三款、第三百零七條，判決如主文。中華民國九十一年九月二十三日臺灣高雄地方法院刑事第六庭法官李怡諄右為正本證明與原本無異。如不服本判決，應於送達後十日內，向本院提出上訴狀。書記官陳孟瑩中華民國九十一年九月二十三日",
  "characters": {
    "judges": [
      "李怡諄"
    ],
    "prosecutors": [

    ],
    "lawyers": [

    ],
    "clerks": [
      "陳孟瑩"
    ],
    "plaintiffs": [

    ],
    "defendants": [
      "乙○○",
      "右列被告因家暴傷害罪案件，經檢察官聲請簡易判決處刑（九十一年度偵字第一五三",
      "三二號），經本院認不宜以簡易判決處刑，依刑事訴訟法第四百五十二條之規定，改",
      "依通常訴訟程序審理，本院判決如左："
    ],
    "prosecutor_office": [
      "臺灣高雄地方法院檢察署檢察官"
    ],
    "creditors": [

    ],
    "debtors": [

    ],
    "judicial_associate_officer": [

    ]
  },
  "adjudged_at": "2002-09-23",
  "created_at": "2016-02-04 18:02:42",
  "updated_at": "2016-02-04 18:02:42"
}