{
  "identify": "HLD-100-花簡-404-20110628-1",
  "court": {
    "name": "臺灣花蓮地方法院",
    "code": "HLD"
  },
  "division": {
    "name": "刑事",
    "code": "M"
  },
  "year": 100,
  "word": "花簡",
  "number": "404",
  "jcheck": "1",
  "reason": "違反保護令罪",
  "content": "臺灣花蓮地方法院刑事簡易判決        100年度花簡字第404號\n聲  請  人  臺灣花蓮地方法院檢察署檢察官\n被      告  江威汎\n上列被告因違反保護令罪案件，經檢察官聲請以簡易判決處刑（\n100年度偵字第1738號），本院判決如下：\n    主  文\n江威汎違反法院依家庭暴力防治法第十四條第一項所為禁止實施\n家庭暴力之民事通常保護令裁定，處有期徒刑參月，如易科罰金\n，以新臺幣壹仟元折算壹日。緩刑貳年，緩刑期內付保護管束。\n    事實及理由\n一、本件犯罪事實及證據，除犯罪事實一、第1行後段補充為「\n    家庭暴力防治法第3條第 1款」、第8行後段補充「（傷害部\n    分業據撤回告訴）」、證據並所犯法條欄二、部分更正所犯\n    法條為「家庭暴力防治法第61條第 1款」外，其餘均引用檢\n    察官聲請簡易判決處刑書（如附件）之記載。\n二、按家庭暴力防治法所稱家庭暴力者，謂家庭成員間實施身體\n    或精神上不法侵害之行為；所稱家庭暴力罪者，謂家庭成員\n    間故意實施家庭暴力行為而成立其他法律所規定之犯罪，此\n    為家庭暴力防治法第 2條第1、2款所明定，是被告江威汎毆\n    打被害人邱意涵，係對被害人實施身體不法侵害之行為，係\n    犯家庭暴力防治法第61條第 1款之違反保護令罪。爰審酌被\n    告前有公共危險等前科紀錄（不構成累犯），有臺灣高等法\n    院被告前案紀錄表 1份在卷足參，經本院家事法庭裁定民事\n    通常保護令後，未遵守保護令之內容，對被害人為身體上不\n    法之侵害，違反保護令之情節，犯後坦承犯行，並與被害人\n    達成和解等一切情狀，量處如主文所示之刑及諭知易科罰金\n    之折算標準。末查，被告未曾受有期徒刑以上刑之宣告，有\n    臺灣高等法院被告前案紀錄表 1份在卷可憑，酒後失控對被\n    害人施暴，致觸犯本案犯行，被告與被害人達成和解，願意\n    戒酒，同意不再對被害人施暴，並經被害人原諒，有陳報狀\n    及和解書各 1份在卷足參，被告經此科刑之教訓，當知所警\n    惕，而無再犯之虞，且被告有正當工作，與被害人有 2名子\n    女賴其撫養，被害人亦願繼續維持婚姻及家庭生活，本院認\n    其所受刑之宣告以暫不執行為適當，宣告緩刑 2年，並依家\n    庭暴力防治法第38條第 1項之規定，宣告於緩刑期內付保護\n    管束。\n三、依刑事訴訟法第449條第 1項前段、第454條第2項、第450條\n    第1項，家庭暴力防治法第61條第 1款、第38條第1項，刑法\n    第11條前段、第41條第1項前段、第74條第1項第 1款，逕以\n    簡易判決處刑如主文。\n四、如不服本判決，得於收受判決後10日內向本院提起上訴（須\n    附繕本）。\n中    華    民    國   100    年    6     月    28    日\n                  花蓮簡易庭    法  官  湯國杰\n上列正本證明與原本無異。\n如對本判決不服，應於送達後10日內，向本院提出上訴狀（應抄\n附繕本）告訴人或被害人如對於本判決不服者，應具備理由請求\n檢察官上訴，其上訴期間之計算係以檢察官收受判決正本之日期\n為準。\n中    華    民    國   100    年    7     月    1     日\n                                書記官\n附錄本判決論罪之法律條文：\n家庭暴力防治法第61條：\n違反法院依第 14 條第 1 項、第 16 條第 3 項所為之下列裁定\n者，為本法所稱違反保護令罪，處  3 年以下有期徒刑、拘役或\n科或併科新臺幣 10 萬元以下罰金：\n一、禁止實施家庭暴力。\n二、禁止騷擾、接觸、跟蹤、通話、通信或其他非必要之聯絡行\n    為。\n三、遷出住居所。\n四、遠離住居所、工作場所、學校或其他特定場所。\n五、完成加害人處遇計畫。",
  "structure": {
    "main": "江威汎違反法院依家庭暴力防治法第十四條第一項所為禁止實施\n家庭暴力之民事通常保護令裁定，處有期徒刑參月，如易科罰金\n，以新臺幣壹仟元折算壹日。緩刑貳年，緩刑期內付保護管束。",
    "fact": "一、本件犯罪事實及證據，除犯罪事實一、第1行後段補充為「\n    家庭暴力防治法第3條第 1款」、第8行後段補充「（傷害部\n    分業據撤回告訴）」、證據並所犯法條欄二、部分更正所犯\n    法條為「家庭暴力防治法第61條第 1款」外，其餘均引用檢\n    察官聲請簡易判決處刑書（如附件）之記載。\n二、按家庭暴力防治法所稱家庭暴力者，謂家庭成員間實施身體\n    或精神上不法侵害之行為；所稱家庭暴力罪者，謂家庭成員\n    間故意實施家庭暴力行為而成立其他法律所規定之犯罪，此\n    為家庭暴力防治法第 2條第1、2款所明定，是被告江威汎毆\n    打被害人邱意涵，係對被害人實施身體不法侵害之行為，係\n    犯家庭暴力防治法第61條第 1款之違反保護令罪。爰審酌被\n    告前有公共危險等前科紀錄（不構成累犯），有臺灣高等法\n    院被告前案紀錄表 1份在卷足參，經本院家事法庭裁定民事\n    通常保護令後，未遵守保護令之內容，對被害人為身體上不\n    法之侵害，違反保護令之情節，犯後坦承犯行，並與被害人\n    達成和解等一切情狀，量處如主文所示之刑及諭知易科罰金\n    之折算標準。末查，被告未曾受有期徒刑以上刑之宣告，有\n    臺灣高等法院被告前案紀錄表 1份在卷可憑，酒後失控對被\n    害人施暴，致觸犯本案犯行，被告與被害人達成和解，願意\n    戒酒，同意不再對被害人施暴，並經被害人原諒，有陳報狀\n    及和解書各 1份在卷足參，被告經此科刑之教訓，當知所警\n    惕，而無再犯之虞，且被告有正當工作，與被害人有 2名子\n    女賴其撫養，被害人亦願繼續維持婚姻及家庭生活，本院認\n    其所受刑之宣告以暫不執行為適當，宣告緩刑 2年，並依家\n    庭暴力防治法第38條第 1項之規定，宣告於緩刑期內付保護\n    管束。\n三、依刑事訴訟法第449條第 1項前段、第454條第2項、第450條\n    第1項，家庭暴力防治法第61條第 1款、第38條第1項，刑法\n    第11條前段、第41條第1項前段、第74條第1項第 1款，逕以\n    簡易判決處刑如主文。\n四、如不服本判決，得於收受判決後10日內向本院提起上訴（須\n    附繕本）。",
    "reason": "一、本件犯罪事實及證據，除犯罪事實一、第1行後段補充為「\n    家庭暴力防治法第3條第 1款」、第8行後段補充「（傷害部\n    分業據撤回告訴）」、證據並所犯法條欄二、部分更正所犯\n    法條為「家庭暴力防治法第61條第 1款」外，其餘均引用檢\n    察官聲請簡易判決處刑書（如附件）之記載。\n二、按家庭暴力防治法所稱家庭暴力者，謂家庭成員間實施身體\n    或精神上不法侵害之行為；所稱家庭暴力罪者，謂家庭成員\n    間故意實施家庭暴力行為而成立其他法律所規定之犯罪，此\n    為家庭暴力防治法第 2條第1、2款所明定，是被告江威汎毆\n    打被害人邱意涵，係對被害人實施身體不法侵害之行為，係\n    犯家庭暴力防治法第61條第 1款之違反保護令罪。爰審酌被\n    告前有公共危險等前科紀錄（不構成累犯），有臺灣高等法\n    院被告前案紀錄表 1份在卷足參，經本院家事法庭裁定民事\n    通常保護令後，未遵守保護令之內容，對被害人為身體上不\n    法之侵害，違反保護令之情節，犯後坦承犯行，並與被害人\n    達成和解等一切情狀，量處如主文所示之刑及諭知易科罰金\n    之折算標準。末查，被告未曾受有期徒刑以上刑之宣告，有\n    臺灣高等法院被告前案紀錄表 1份在卷可憑，酒後失控對被\n    害人施暴，致觸犯本案犯行，被告與被害人達成和解，願意\n    戒酒，同意不再對被害人施暴，並經被害人原諒，有陳報狀\n    及和解書各 1份在卷足參，被告經此科刑之教訓，當知所警\n    惕，而無再犯之虞，且被告有正當工作，與被害人有 2名子\n    女賴其撫養，被害人亦願繼續維持婚姻及家庭生活，本院認\n    其所受刑之宣告以暫不執行為適當，宣告緩刑 2年，並依家\n    庭暴力防治法第38條第 1項之規定，宣告於緩刑期內付保護\n    管束。\n三、依刑事訴訟法第449條第 1項前段、第454條第2項、第450條\n    第1項，家庭暴力防治法第61條第 1款、第38條第1項，刑法\n    第11條前段、第41條第1項前段、第74條第1項第 1款，逕以\n    簡易判決處刑如主文。\n四、如不服本判決，得於收受判決後10日內向本院提起上訴（須\n    附繕本）。"
  },
  "search": "臺灣花蓮地方法院刑事簡易判決100年度花簡字第404號聲請人臺灣花蓮地方法院檢察署檢察官被告江威汎上列被告因違反保護令罪案件，經檢察官聲請以簡易判決處刑（100年度偵字第1738號），本院判決如下：主文江威汎違反法院依家庭暴力防治法第十四條第一項所為禁止實施家庭暴力之民事通常保護令裁定，處有期徒刑參月，如易科罰金，以新臺幣壹仟元折算壹日。緩刑貳年，緩刑期內付保護管束。事實及理由一、本件犯罪事實及證據，除犯罪事實一、第1行後段補充為「家庭暴力防治法第3條第1款」、第8行後段補充「（傷害部分業據撤回告訴）」、證據並所犯法條欄二、部分更正所犯法條為「家庭暴力防治法第61條第1款」外，其餘均引用檢察官聲請簡易判決處刑書（如附件）之記載。二、按家庭暴力防治法所稱家庭暴力者，謂家庭成員間實施身體或精神上不法侵害之行為；所稱家庭暴力罪者，謂家庭成員間故意實施家庭暴力行為而成立其他法律所規定之犯罪，此為家庭暴力防治法第2條第1、2款所明定，是被告江威汎毆打被害人邱意涵，係對被害人實施身體不法侵害之行為，係犯家庭暴力防治法第61條第1款之違反保護令罪。爰審酌被告前有公共危險等前科紀錄（不構成累犯），有臺灣高等法院被告前案紀錄表1份在卷足參，經本院家事法庭裁定民事通常保護令後，未遵守保護令之內容，對被害人為身體上不法之侵害，違反保護令之情節，犯後坦承犯行，並與被害人達成和解等一切情狀，量處如主文所示之刑及諭知易科罰金之折算標準。末查，被告未曾受有期徒刑以上刑之宣告，有臺灣高等法院被告前案紀錄表1份在卷可憑，酒後失控對被害人施暴，致觸犯本案犯行，被告與被害人達成和解，願意戒酒，同意不再對被害人施暴，並經被害人原諒，有陳報狀及和解書各1份在卷足參，被告經此科刑之教訓，當知所警惕，而無再犯之虞，且被告有正當工作，與被害人有2名子女賴其撫養，被害人亦願繼續維持婚姻及家庭生活，本院認其所受刑之宣告以暫不執行為適當，宣告緩刑2年，並依家庭暴力防治法第38條第1項之規定，宣告於緩刑期內付保護管束。三、依刑事訴訟法第449條第1項前段、第454條第2項、第450條第1項，家庭暴力防治法第61條第1款、第38條第1項，刑法第11條前段、第41條第1項前段、第74條第1項第1款，逕以簡易判決處刑如主文。四、如不服本判決，得於收受判決後10日內向本院提起上訴（須附繕本）。中華民國100年6月28日花蓮簡易庭法官湯國杰上列正本證明與原本無異。如對本判決不服，應於送達後10日內，向本院提出上訴狀（應抄附繕本）告訴人或被害人如對於本判決不服者，應具備理由請求檢察官上訴，其上訴期間之計算係以檢察官收受判決正本之日期為準。中華民國100年7月1日書記官附錄本判決論罪之法律條文：家庭暴力防治法第61條：違反法院依第14條第1項、第16條第3項所為之下列裁定者，為本法所稱違反保護令罪，處3年以下有期徒刑、拘役或科或併科新臺幣10萬元以下罰金：一、禁止實施家庭暴力。二、禁止騷擾、接觸、跟蹤、通話、通信或其他非必要之聯絡行為。三、遷出住居所。四、遠離住居所、工作場所、學校或其他特定場所。五、完成加害人處遇計畫。",
  "characters": {
    "judges": [
      "湯國杰"
    ],
    "prosecutors": [

    ],
    "lawyers": [

    ],
    "clerks": [
      "附錄本判決論罪之法律條文："
    ],
    "plaintiffs": [

    ],
    "defendants": [
      "江威汎"
    ],
    "prosecutor_office": [
      "臺灣花蓮地方法院檢察署檢察官"
    ],
    "creditors": [

    ],
    "debtors": [

    ],
    "judicial_associate_officer": [

    ]
  },
  "adjudged_at": "2011-06-28",
  "created_at": "2016-02-13 16:24:50",
  "updated_at": "2016-02-13 16:24:50"
}