{
  "identify": "PCD-100-簡-4266-20110629-1",
  "court": {
    "name": "臺灣新北地方法院",
    "code": "PCD"
  },
  "division": {
    "name": "刑事",
    "code": "M"
  },
  "year": 100,
  "word": "簡",
  "number": "4266",
  "jcheck": "1",
  "reason": "妨害名譽",
  "content": "臺灣板橋地方法院刑事簡易判決         100年度簡字第4266號\n聲  請  人  臺灣板橋地方法院檢察署檢察官\n被      告  陳界宏\n上列被告因妨害名譽案件，經檢察官聲請以簡易判決處刑（100\n年度偵字第149 號），本院判決如下：\n    主  文\n陳界宏公然侮辱人，處罰金新臺幣陸仟元，如易服勞役，以新臺\n幣壹仟元折算壹日。\n    事實及理由\n一、本件檢察官固就被告陳界宏涉嫌公然侮辱告訴人謝建昇「你\n    在靠啥洨」、「幹你娘」、「幹你娘雞掰」等語之部分，另\n    作成不起訴處分，此有臺灣板橋地方法院檢察署100 年度偵\n    字第149 號不起訴處分書1 份在卷可按（見偵查卷第56頁至\n    第57頁），然本件檢察官交辦案件進行單上既已載明：「經\n    請示檢察官後，僅就被告陳界宏於員警到場處理後，辱罵謝\n    建昇部分聲請簡判，餘為不起訴」一節，有臺灣板橋地方法\n    院檢察署檢察官交辦案件進行單1 紙可憑，復縱觀卷內全部\n    事證及聲請簡易判決處刑書之內容，堪認檢察官上開不起訴\n    處分，係針對告訴人指稱被告於員警到場前出言辱罵告訴人\n    之事實，並不及於員警到場後錄音存證之部分。是以，本件\n    檢察官就被告於員警到場後辱罵告訴人「幹你娘雞掰」乙事\n    ，向本院聲請簡易判決處刑，該犯罪事實與上開不起訴處分\n    書所載之事實並非同一，自無重行起訴之問題，故本院得為\n    實質審理，合先敘明。\n二、本件犯罪事實及證據，除犯罪事實欄第2 行「中山路」後補\n    充「2 段」、並末段補充「致生損害於其之名譽。」外，其\n    餘均引用檢察官聲請簡易判決處刑書之記載。\n三、核被告陳界宏所為，係犯刑法第309 條第1 項之公然侮辱罪\n    。爰審酌被告以前揭不雅言語公然侮辱告訴人，足以貶損告\n    訴人之聲譽，未尊重他人之名譽法益，兼衡其犯罪動機、目\n    的、手段、智識程度、生活狀況、犯後態度，且迄未與告訴\n    人達成和解等一切情狀，量處如主文所示之刑，並諭知易服\n    勞役之折算標準，以資懲儆。\n四、依刑事訴訟法第449 條第1 項前段、第3 項、第454 條第2\n    項，刑法第309 條第1 項、第42條第3 項前段，刑法施行法\n    第1 條之1 第1 項、第2 項前段，逕以簡易判決處刑如主文\n    。\n五、如不服本判決，得自收受送達之日起10日內向本院提出上訴\n    狀，上訴於本院第二審合議庭（須附繕本）。\n中    華    民    國    100     年    6     月   29   日\n                  刑事第二十二庭  法  官  陳苑文\n上列正本證明與原本無異。\n                                  書記官  張玫玲\n中    華    民    國    100     年    6     月   30   日\n附錄本案論罪科刑法條全文：\n中華民國刑法第309 條：\n公然侮辱人者，處拘役或3 百元以下罰金。\n以強暴犯前項之罪者，處1 年以下有期徒刑、拘役或5 百元以下\n罰金。",
  "structure": {
    "main": "陳界宏公然侮辱人，處罰金新臺幣陸仟元，如易服勞役，以新臺\n幣壹仟元折算壹日。",
    "fact": "一、本件檢察官固就被告陳界宏涉嫌公然侮辱告訴人謝建昇「你\n    在靠啥洨」、「幹你娘」、「幹你娘雞掰」等語之部分，另\n    作成不起訴處分，此有臺灣板橋地方法院檢察署100 年度偵\n    字第149 號不起訴處分書1 份在卷可按（見偵查卷第56頁至\n    第57頁），然本件檢察官交辦案件進行單上既已載明：「經\n    請示檢察官後，僅就被告陳界宏於員警到場處理後，辱罵謝\n    建昇部分聲請簡判，餘為不起訴」一節，有臺灣板橋地方法\n    院檢察署檢察官交辦案件進行單1 紙可憑，復縱觀卷內全部\n    事證及聲請簡易判決處刑書之內容，堪認檢察官上開不起訴\n    處分，係針對告訴人指稱被告於員警到場前出言辱罵告訴人\n    之事實，並不及於員警到場後錄音存證之部分。是以，本件\n    檢察官就被告於員警到場後辱罵告訴人「幹你娘雞掰」乙事\n    ，向本院聲請簡易判決處刑，該犯罪事實與上開不起訴處分\n    書所載之事實並非同一，自無重行起訴之問題，故本院得為\n    實質審理，合先敘明。\n二、本件犯罪事實及證據，除犯罪事實欄第2 行「中山路」後補\n    充「2 段」、並末段補充「致生損害於其之名譽。」外，其\n    餘均引用檢察官聲請簡易判決處刑書之記載。\n三、核被告陳界宏所為，係犯刑法第309 條第1 項之公然侮辱罪\n    。爰審酌被告以前揭不雅言語公然侮辱告訴人，足以貶損告\n    訴人之聲譽，未尊重他人之名譽法益，兼衡其犯罪動機、目\n    的、手段、智識程度、生活狀況、犯後態度，且迄未與告訴\n    人達成和解等一切情狀，量處如主文所示之刑，並諭知易服\n    勞役之折算標準，以資懲儆。\n四、依刑事訴訟法第449 條第1 項前段、第3 項、第454 條第2\n    項，刑法第309 條第1 項、第42條第3 項前段，刑法施行法\n    第1 條之1 第1 項、第2 項前段，逕以簡易判決處刑如主文\n    。\n五、如不服本判決，得自收受送達之日起10日內向本院提出上訴\n    狀，上訴於本院第二審合議庭（須附繕本）。",
    "reason": "一、本件檢察官固就被告陳界宏涉嫌公然侮辱告訴人謝建昇「你\n    在靠啥洨」、「幹你娘」、「幹你娘雞掰」等語之部分，另\n    作成不起訴處分，此有臺灣板橋地方法院檢察署100 年度偵\n    字第149 號不起訴處分書1 份在卷可按（見偵查卷第56頁至\n    第57頁），然本件檢察官交辦案件進行單上既已載明：「經\n    請示檢察官後，僅就被告陳界宏於員警到場處理後，辱罵謝\n    建昇部分聲請簡判，餘為不起訴」一節，有臺灣板橋地方法\n    院檢察署檢察官交辦案件進行單1 紙可憑，復縱觀卷內全部\n    事證及聲請簡易判決處刑書之內容，堪認檢察官上開不起訴\n    處分，係針對告訴人指稱被告於員警到場前出言辱罵告訴人\n    之事實，並不及於員警到場後錄音存證之部分。是以，本件\n    檢察官就被告於員警到場後辱罵告訴人「幹你娘雞掰」乙事\n    ，向本院聲請簡易判決處刑，該犯罪事實與上開不起訴處分\n    書所載之事實並非同一，自無重行起訴之問題，故本院得為\n    實質審理，合先敘明。\n二、本件犯罪事實及證據，除犯罪事實欄第2 行「中山路」後補\n    充「2 段」、並末段補充「致生損害於其之名譽。」外，其\n    餘均引用檢察官聲請簡易判決處刑書之記載。\n三、核被告陳界宏所為，係犯刑法第309 條第1 項之公然侮辱罪\n    。爰審酌被告以前揭不雅言語公然侮辱告訴人，足以貶損告\n    訴人之聲譽，未尊重他人之名譽法益，兼衡其犯罪動機、目\n    的、手段、智識程度、生活狀況、犯後態度，且迄未與告訴\n    人達成和解等一切情狀，量處如主文所示之刑，並諭知易服\n    勞役之折算標準，以資懲儆。\n四、依刑事訴訟法第449 條第1 項前段、第3 項、第454 條第2\n    項，刑法第309 條第1 項、第42條第3 項前段，刑法施行法\n    第1 條之1 第1 項、第2 項前段，逕以簡易判決處刑如主文\n    。\n五、如不服本判決，得自收受送達之日起10日內向本院提出上訴\n    狀，上訴於本院第二審合議庭（須附繕本）。"
  },
  "search": "臺灣板橋地方法院刑事簡易判決100年度簡字第4266號聲請人臺灣板橋地方法院檢察署檢察官被告陳界宏上列被告因妨害名譽案件，經檢察官聲請以簡易判決處刑（100年度偵字第149號），本院判決如下：主文陳界宏公然侮辱人，處罰金新臺幣陸仟元，如易服勞役，以新臺幣壹仟元折算壹日。事實及理由一、本件檢察官固就被告陳界宏涉嫌公然侮辱告訴人謝建昇「你在靠啥洨」、「幹你娘」、「幹你娘雞掰」等語之部分，另作成不起訴處分，此有臺灣板橋地方法院檢察署100年度偵字第149號不起訴處分書1份在卷可按（見偵查卷第56頁至第57頁），然本件檢察官交辦案件進行單上既已載明：「經請示檢察官後，僅就被告陳界宏於員警到場處理後，辱罵謝建昇部分聲請簡判，餘為不起訴」一節，有臺灣板橋地方法院檢察署檢察官交辦案件進行單1紙可憑，復縱觀卷內全部事證及聲請簡易判決處刑書之內容，堪認檢察官上開不起訴處分，係針對告訴人指稱被告於員警到場前出言辱罵告訴人之事實，並不及於員警到場後錄音存證之部分。是以，本件檢察官就被告於員警到場後辱罵告訴人「幹你娘雞掰」乙事，向本院聲請簡易判決處刑，該犯罪事實與上開不起訴處分書所載之事實並非同一，自無重行起訴之問題，故本院得為實質審理，合先敘明。二、本件犯罪事實及證據，除犯罪事實欄第2行「中山路」後補充「2段」、並末段補充「致生損害於其之名譽。」外，其餘均引用檢察官聲請簡易判決處刑書之記載。三、核被告陳界宏所為，係犯刑法第309條第1項之公然侮辱罪。爰審酌被告以前揭不雅言語公然侮辱告訴人，足以貶損告訴人之聲譽，未尊重他人之名譽法益，兼衡其犯罪動機、目的、手段、智識程度、生活狀況、犯後態度，且迄未與告訴人達成和解等一切情狀，量處如主文所示之刑，並諭知易服勞役之折算標準，以資懲儆。四、依刑事訴訟法第449條第1項前段、第3項、第454條第2項，刑法第309條第1項、第42條第3項前段，刑法施行法第1條之1第1項、第2項前段，逕以簡易判決處刑如主文。五、如不服本判決，得自收受送達之日起10日內向本院提出上訴狀，上訴於本院第二審合議庭（須附繕本）。中華民國100年6月29日刑事第二十二庭法官陳苑文上列正本證明與原本無異。書記官張玫玲中華民國100年6月30日附錄本案論罪科刑法條全文：中華民國刑法第309條：公然侮辱人者，處拘役或3百元以下罰金。以強暴犯前項之罪者，處1年以下有期徒刑、拘役或5百元以下罰金。",
  "characters": {
    "judges": [
      "陳苑文"
    ],
    "prosecutors": [

    ],
    "lawyers": [

    ],
    "clerks": [
      "張玫玲"
    ],
    "plaintiffs": [

    ],
    "defendants": [
      "陳界宏"
    ],
    "prosecutor_office": [
      "臺灣板橋地方法院檢察署檢察官"
    ],
    "creditors": [

    ],
    "debtors": [

    ],
    "judicial_associate_officer": [

    ]
  },
  "adjudged_at": "2011-06-29",
  "created_at": "2016-02-13 16:17:59",
  "updated_at": "2016-02-13 16:17:59"
}