{
  "identify": "TCD-100-訴-1574-20110629-1",
  "court": {
    "name": "臺灣臺中地方法院",
    "code": "TCD"
  },
  "division": {
    "name": "刑事",
    "code": "M"
  },
  "year": 100,
  "word": "訴",
  "number": "1574",
  "jcheck": "1",
  "reason": "毒品危害防制條例",
  "content": "臺灣臺中地方法院刑事判決             100年度訴字第1574號\n公  訴  人  臺灣臺中地方法院檢察署檢察官\n被      告  楊武輝\n指定辯護人  本院公設辯護人  梁乃莉\n上列被告因違反毒品危害防制條例案件，經檢察官提起公訴（10\n0年度偵緝字第806號），本院判決如下：\n    主    文\n楊武輝犯如附表所示之罪，均累犯，各量處如附表所示之刑（各\n含主刑及從刑）。應執行有期徒刑拾伍年；未扣案之門號000\n0000000號、0000000000號行動電話機具貳支\n（各含門號卡壹張）均沒收，如全部或一部不能沒收時，均追徵\n其價額；未扣案之如附表編號5至10所示款項共新臺幣陸仟伍佰\n元沒收，如全部或一部不能沒收時，以其財產抵償之。\n    犯罪事實\n一、楊武輝前曾因犯竊盜罪1罪、偽造文書罪2罪及違反麻醉藥品\n    管理條例罪4罪等案件，先後經法院各判處有期徒刑1年、4\n    月、3月、2年6月、8月、5年2月及9月確定，嗣經減刑並定\n    應執行刑【除上開所處有期徒刑5年2月不得減刑外，餘均減\n    刑2分之1，並各定應執行為有期徒刑8月又15日（竊盜罪1罪\n    、偽造文書罪2罪部分）及有期徒刑5年2月又15日確定（違\n    反麻醉藥品管理條例罪4罪部分，前經執行後假釋付保護管\n    束）】，經合併執行上開所處有期徒刑8月又15日及殘刑之\n    有期徒刑2年5月又15日，而於民國97年3月22日縮刑期滿執\n    行完畢。詎猶不知悔改，明知海洛因係屬毒品危害防制條例\n    第2條第2項第1款所管制之第1級毒品，依法不得販賣、轉讓\n    ，竟意圖營利，分別基於販賣、轉讓海洛因之犯意，以伊所\n    持用門號為0000000000號、0000000000號行動電話（均未扣\n    案）作為販毒及轉讓毒品之聯絡工具，而先後於如附表所示\n    之時間及地點，以如附表所示之方式，分別為如附表編號1\n    至4所示之轉讓海洛因各1小包（均約不足0.1公克之數量）\n    予陳晁偉施用共4次，以及如附表編號5至10所示之販賣海洛\n    因予彭士韋施用共6次之行為。嗣經員警向本院聲請核准對\n    楊武輝、陳晁偉及彭士韋所持用如附表所示之上開行動電話\n    門號予以監聽後，始循線查悉上情。\n二、案經臺中市警察局刑事警察大隊報請臺灣臺中地方法院檢察\n    署檢察官偵查起訴。\n    理    由\n一、證據能力：按被告以外之人於審判外之陳述，雖不符刑事訴\n    訟法第159條之1至第159條之4之規定，而經當事人於審判程\n    序同意作為證據，法院審酌該言詞陳述或書面陳述作成時之\n    情況，認為適當者，亦得為證據。當事人、代理人或辯護人\n    於法院調查證據時，知有第159條第1項不得為證據之情形，\n    而未於言詞辯論終結前聲明異議者，視為有前項之同意，刑\n    事訴訟法第159條之5第1項、第2項定有明文。立法意旨在於\n    傳聞證據未經當事人之反對詰問予以核實，原則上先予排除\n    ，惟若當事人已放棄詰問或未聲明異議，基於證據資料愈豐\n    富，愈有助於真實發現之理念，且強化言詞辯論主義，法院\n    自可承認該傳聞證據例外擁有證據能力。查本件檢察官、被\n    告及指定辯護人即本院公設辯護人對於證人陳晁偉及彭士韋\n    等人於警詢及偵查中所為證述，均表示不爭執（見本院案卷\n    ），並未於言詞辯論終結前聲明異議，依刑事訴訟法第159\n    條之5第2項之規定，視為同意作為證據，且本院審酌上開證\n    人等人均係於案發後不久所為之陳述，記憶猶新，又非在非\n    自由意志之情況下所為之陳述，所陳自較符事實，核無顯有\n    不可信之情況，是本院認該等言詞陳述適當，依刑事訴訟法\n    第159條之5第1項之規定，自均得為證據。次按除法律另有\n    規定外，實施刑事訴訟程序之公務員因違背法定程序取得之\n    證據，其有無證據能力之認定，應審酌人權保障及公共利益\n    之均衡維護，刑事訴訟法第158條之4定有明文；惟本案所引\n    用之通訊監察譯文等非供述證據，並無證據證明係實施刑事\n    訴訟程序之公務員違背法定程序所取得，自應認均具有證據\n    能力，合先敘明。\n二、上開犯罪事實，業據被告楊武輝於100年5月12日檢察官偵查\n    中、100年6月1日本院訊問中及100年6月15日本院審理中均\n    坦承不諱，復有證人陳晁偉於警詢及偵查中（詳見98年度聲\n    拘字第572號卷第23頁至第29頁、第30頁至第32頁、臺中市\n    警察局刑案偵查卷第21頁至第30頁及98年度偵字第28871號\n    卷第8頁背面至第9頁）及證人彭士韋於警詢及偵查中（詳見\n    98年度聲拘字第572號卷第3頁至第8頁、臺中市警察局刑案\n    偵查卷第1頁至第6頁及98年度偵字第28871號卷第4頁至第5\n    頁）證述詳實，且有如附表所示電話之監聽譯文（詳見98年\n    度偵字第28871號卷第7頁至第8頁、98年度聲拘字第572號卷\n    第33頁至第35頁、臺中市警察局刑案偵查卷第31頁至第33頁\n    ）、內政部警政署刑事警察局指認犯罪嫌疑人紀錄表（見98\n    年度聲拘字第572號卷第9頁、臺中市警察局刑案偵查卷第7\n    頁、98年度聲拘字第572號卷第36頁、臺中市警察局刑案偵\n    查卷第34頁）、通訊監察作業譯文摘要報告書（詳見98年度\n    聲拘字第572號卷第10頁至第22頁、臺中市警察局刑案偵查\n    卷第8頁至第20頁）及通訊監察案件相關案號關聯表等存卷\n    可參，足見被告上開自白，核與事實相符。又按販賣海洛因\n    係屬違法行為，非可公然為之，亦無公定價格，而每次買賣\n    之價量，可能隨時依雙方關係深淺、資力、需求量及對行情\n    之認知、來源是否充裕、查緝是否嚴緊、購買者被查獲時供\n    述購買對象之可能風險之評估等，而異其標準，非可一概而\n    論，從而販賣之利得，除被告就販賣之價量俱明確供述外，\n    委難察得實情，而本件被告既坦承確有上開販賣第1級毒品\n    之犯行，如前所述，則被告販售上開毒品確有利潤可圖，已\n    允無疑義；況參以我國政府一再宣示反毒決心，施用、販賣\n    毒品均屬違法行為，此為國人所週知，被告與購買毒品之彭\n    士韋既非至親或有特殊之情誼關係，衡情被告當無甘冒刑罰\n    制裁之重典而毫無利得，益證被告確有營利之主觀上意圖及\n    客觀行為甚明。綜上所述，本案事證明確，被告上開犯行，\n    堪予認定。\n三、查海洛因乃列為毒品危害防制條例第2條所管制之第1級毒品\n    ，依法不得非法販賣、轉讓及持有；是核被告如附表編號1\n    至4所示之所為，均係犯毒品危害防制條例第8條第1項之轉\n    讓第一級毒品罪；另如附表編號5至10所示之所為，均係犯\n    毒品危害防制條例第4條第1項之販賣第1級毒品罪。其販賣\n    或轉讓前之持有第1級毒品行為，均為各該販賣或轉讓之高\n    度行為所吸收，均不另論罪。被告所犯如附表所示數罪間，\n    犯意各別，行為互異，應分論併罰。被告前曾因犯竊盜罪1\n    罪、偽造文書罪2罪及違反麻醉藥品管理條例罪4罪等案件，\n    先後經法院各判處有期徒刑1年、4月、3月、2年6月、8月、\n    5年2月及9月確定，嗣經減刑並定應執行刑【除上開所處有\n    期徒刑5年2月不得減刑外，餘均減刑2分之1，並各定應執行\n    為有期徒刑8月又15日（竊盜罪1罪、偽造文書罪2罪部分）\n    及有期徒刑5年2月又15日確定（違反麻醉藥品管理條例罪4\n    罪部分，前經執行後假釋付保護管束）】，經合併執行上開\n    所處有期徒刑8月又15日及殘刑之有期徒刑2年5月又15日，\n    而於民國97年3月22日縮刑期滿執行完畢，此有臺灣臺中地\n    方法院檢察署刑案資料查註紀錄表及臺灣高等法院被告前案\n    紀錄表在卷可按，其於受有期徒刑執行完畢後5年以內故意\n    再犯本件有期徒刑以上之10罪，均為累犯，除法定刑為死刑\n    、無期徒刑部分，依法不得加重外，其餘部分各應依刑法第\n    47條第1項規定加重其刑。查被告雖販賣第1級毒品海洛因予\n    彭士韋，惟販賣次數為6次，且均係小額交易，6次共僅6500\n    元，與一般大毒梟動輒數十萬元、數百萬元，甚至數千萬元\n    ，有顯著之差別，而販賣第1級毒品罪之法定刑為「製造、\n    運輸、販賣第1級毒品者，處死刑或無期徒刑；處無期徒刑\n    者，得併科新臺幣2000萬元以下罰金。」，然同為販賣第1\n    級毒品之人，其原因動機不一，犯罪情節未必盡同，或有大\n    盤毒梟者，亦有中、小盤之分，甚或僅止於吸毒者友儕間為\n    求互通有無之有償轉讓者亦有之，其販賣行為所造成危害社\n    會之程度自屬有異，法律科處此類犯罪，所設之法定最低本\n    刑卻相同，不可謂不重。於此情形，倘依其情狀處以相當之\n    有期徒刑，即足以懲儆，並可達防衛社會之目的者，自非不\n    可依客觀之犯行與主觀之惡性兩者加以考量其情狀，審酌是\n    否有其可憫恕之處，而適用刑法第59條之規定酌量減輕其刑\n    ，期使個案裁判之量刑，能斟酌至當，符合比例原則。查被\n    告販賣海洛因予彭士韋之數量、次數及代價尚微，以其情節\n    論，惡性非重，在客觀上足以引起一般之同情等堪資憫恕之\n    處，揆諸上開說明，本院認如科以法定最低刑度仍嫌過重，\n    爰就被告所犯如附表編號5至10所示部分，各依刑法第59條\n    之規定予以酌量減輕其刑，並依法先加重後減輕之。又毒品\n    危害防制條例第17條原僅規定犯該條所列舉之製造、販賣、\n    運輸等罪之毒販，為鼓勵其供出毒品來源，因而破獲者，得\n    獲邀減刑之寬典，俾有效推展阻斷供給之緝毒工作；而毒販\n    之所以願意供出其上游組織之情形，使檢警機關得以進一步\n    追查破獲，類皆已於偵查或審判中自白犯罪，然上開條例並\n    未有如貪污治罪條例第8條第2項自白減刑之規定，不無造成\n    毒販可能自忖無法有效供出毒品來源之上手，難以獲得減刑\n    恩惠，因而減弱甚至斷絕其自白認罪之誘因，致使上開案件\n    之刑事訴訟程序未能儘早確定。98年5月20日修正之毒品危\n    害防制條例第17條，乃採行寬厚之刑事政策，修正原條文，\n    擴大適用範圍，除於第1項規定供出毒品來源，因而查獲其\n    他正犯或共犯者，減輕或免除其刑外，並增列第2項於偵查\n    及審判中自白者，減輕其刑之規定，以鼓勵毒販自白認罪，\n    開啟其自新之路。從而，毒販在偵查及審判中之歷次陳述，\n    各有1次以上之自白，並供出毒品來源，因而查獲其他正犯\n    或共犯之情形，即已完全合致第17條第1項、第2項規定之要\n    件，且其中第2項減刑之事由，當然為第2項減免規定所包括\n    ，依法規競合之吸收關係，應優先適用第17條第1項之規定\n    （最高法院98年度台上字第7231號著有判決可參）。而查，\n    本件並未依被告之自白並供出毒品來源，因而破獲其他上手\n    或共犯等情，此為被告於本院審理中所是認，自無依上開條\n    例第17條第1項減輕其刑之適用；然被告確曾於100年5月12\n    日檢察官偵查中、100年6月1日本院訊問中及100年6月15日\n    本院審理中均自白上開販賣及轉讓第1級毒品之罪，揆諸上\n    開說明，自應依上開條例第17條第2項規定，就如附表編號5\n    至10所示部分遞減輕之，並依法先加重後遞減輕之；另就如\n    附表編號1至4所示部分減輕之，並依法先加重後減輕之。爰\n    各審酌被告犯罪之動機、目的係為圖得一己之利益、販賣及\n    轉讓毒品之對象各為1人，又販賣毒品之數量、金額及次數\n    尚微，其販賣及轉讓毒品為增進流通毒品之管道，危害社會\n    治安非輕，惟均係小額交易或無償轉讓，暨其犯罪後坦承犯\n    行，犯罪後態度尚佳等一切情狀，分別量處被告如附表所示\n    之刑，並定其應執行刑，以示懲儆。另按毒品危害防制條例\n    第19條第1項規定，犯販賣毒品罪者，其犯罪所得之財物均\n    沒收之，係採義務沒收主義。故販賣毒品所得之對價，不問\n    其中成本若干，利潤多少，均應全部諭知沒收，貫徹政府查\n    禁煙毒之決心，以符立法本旨；又犯毒品危害防制條例第4\n    條之販賣第1級或第2級毒品罪者，依同條例19條第1項規定\n    ，其因犯罪所得之物沒收之，如全部或一部不能沒收時，追\n    徵其價額或以其財產抵償之。所稱因犯罪所得之物，自以實\n    際所得者為限，苟無所得或尚未取得者，自無從為沒收及追\n    繳或抵償之諭知（最高法院91年度臺上字第2419號、96年臺\n    上字第2331號、第5551號判決意旨參照）。又同條例19條第\n    1項並無如同條例第18條第1項所定「不問屬於犯人與否，沒\n    收之」之明文，自屬相對沒收主義之立法，是其應沒收之物\n    ，應以屬被告或共犯所有者為限。又該規定所稱「追徵其價\n    額」者，係指所沒收之物為金錢以外之其他財物而無法沒收\n    時，應追徵其價額，使其繳納與原物相當之價額；如所得財\n    物為金錢而無法沒收時，始應「以其財產抵償之」（最高法\n    院95年度台上字第305號判決意旨參照）。又所謂「其因犯\n    罪所得之財物」，並不以當場搜獲扣押者為限；而販賣毒品\n    所得之對價，不問其中何部分屬於成本，何部分屬於犯罪所\n    得之財物，應均予沒收，始與上開法條之規定符合；且因犯\n    罪所得之財物，亦不能與正常營利事業計算營利所得之情形\n    ，相提並論（最高法院65年度第5次刑庭庭推總會議決議意\n    旨參照）。又門號為0000000000號、0000000000號行動電話\n    機具各1支（各含SIM卡1張），雖未扣案；然均係被告所有\n    ，且為供被告所為如附表編號1至9所示轉讓毒品予陳晁偉或\n    販賣毒品予彭士韋所用之物，業據被告供承在卷，且經證人\n    陳晁偉及彭士韋證述詳實，並有上開電話通聯譯文存卷可參\n    ，又因尚無積極證據證明業已滅失，是應依毒品危害防制條\n    例第19條第1項之規定，各於被告所犯如附表編號1至9所示\n    犯行部分宣告沒收，如全部或一部不能沒收時，追徵其價額\n    。另如附表編號5至10所示販賣第1級毒品所得之款項，雖未\n    扣案，仍各應依同條例第19條第1項之規定，就被告所犯如\n    附表編號5至10所示部分宣告沒收，如全部或一部不能沒收\n    時，各以其財產抵償之。至未扣案門號為0000000000號之行\n    動電話1支，固屬供被告上開如附表編號10所示犯行所用之\n    物，此有上開電話通聯譯文存卷可參（附於臺中市警察局案\n    卷第11頁）；然查，證人彭士韋既稱綽號輝哥之被告乃係使\n    用上開門號為0000000000號、0000000000號電話販毒，其均\n    係撥打被告所使用上開2線電話向被告購毒等語在卷（詳見\n    臺中市警察局警詢案卷第2及23頁），且本院復查無其他積\n    極證據足認該門號0000000000號電話確為被告所有之物，依\n    上開說明，是不另為沒收及追徵其價額之諭知。\n據上論斷，應依刑事訴訟法第299條第1項前段，毒品危害防制條\n例第4條第1項、第8條第1項、第17條第2項、第19條第1項，刑法\n第11條、第47條第1項、第59條、第51條第5款，判決如主文。\n中    華    民    國   100    年    6     月    29    日\n            刑事第15庭  審判長法  官  劉國賓\n                              法  官  柯雅惠\n                              法  官  許惠瑜\n以上正本證明與原本無異。\n如不服本判決應於收受送達後10日內向本院提出上訴書狀，並應\n敘述具體理由；其未敘述上訴理由者，應於上訴期間屆滿後20日\n內向本院補提理由書（均須按他造當事人之人數附繕本）「切勿\n逕送上級法院」。\n                              書記官  楊家印\n中    華    民    國   100    年    6     月    29    日\n附表：\n┌──┬─────────────────────────────┬───────┬───────┐\n│編號│犯罪時間、地點及方式                                      │所犯法條及罪名│宣告刑        │\n├──┼─────────────────────────────┼───────┼───────┤\n│1   │ 98年4月24日下午，陳晁偉以其所持用門號0000000000號行動電話│毒品危害防制條│累犯，處有期徒│\n│    │ 與楊武輝所持用門號為0000000000號行動電話相互聯絡後，兩人 │例第8條第1項之│刑1年8月；未扣│\n│    │ 隨即相約在臺中市○○區○○路與環中路口中彰橋下路邊見面， │轉讓第1級毒品 │案之門號098932│\n│    │ 楊武輝即無償交付海洛因1小包（約僅不足0.1公克，僅足供陳晁 │罪。          │9990號行動電話│\n│    │ 偉施用1次之量）予陳晁偉收執，而無償轉讓第1級毒品海洛因供 │              │機具1支（含SIM│\n│    │ 陳晁偉施用1次。                                          │              │卡1張）沒收， │\n│    │                                                          │              │如全部或一部不│\n│    │                                                          │              │能沒收時，追徵│\n│    │                                                          │              │其價額。      │\n├──┼─────────────────────────────┼───────┼───────┤\n│2   │ 98年4月25日17時59分許，陳晁偉以其所持用門號0000000000號行│毒品危害防制條│累犯，處有期徒│\n│    │ 動電話與楊武輝所持用門號為0000000000號行動電話相互聯絡後 │例第8條第1項之│刑1年8月；未扣│\n│    │ ，兩人隨即相約在臺中市○○區○○路與環中路口中彰橋下路邊 │轉讓第1級毒品 │案之門號098932│\n│    │ 見面，楊武輝即無償交付海洛因1小包（約僅不足0.1公克，僅足 │罪。          │9990號行動電話│\n│    │ 供陳晁偉施用1次之量）予陳晁偉收執，而無償轉讓第1級毒品海 │              │機具1支（含SIM│\n│    │ 洛因供陳晁偉施用1次。                                    │              │卡1張）沒收， │\n│    │                                                          │              │如全部或一部不│\n│    │                                                          │              │能沒收時，追徵│\n│    │                                                          │              │其價額。      │\n├──┼─────────────────────────────┼───────┼───────┤\n│3   │ 98年4月26日19時20分許，陳晁偉以其所持用門號0000000000號行│毒品危害防制條│累犯，處有期徒│\n│    │ 動電話與楊武輝所持用門號為0000000000號行動電話相互聯絡後 │例第8條第1項之│刑1年8月；未扣│\n│    │ ，兩人隨即相約在臺中市○○區○○路與環中路口中彰橋下路邊 │轉讓第1級毒品 │案之門號098932│\n│    │ 見面，楊武輝即無償交付海洛因1小包（約僅不足0.1公克，僅足 │罪。          │9990號行動電話│\n│    │ 供陳晁偉施用1次之量）予陳晁偉收執，而無償轉讓第1級毒品海 │              │機具1支（含SIM│\n│    │ 洛因供陳晁偉施用1次。                                    │              │卡1張）沒收， │\n│    │                                                          │              │如全部或一部不│\n│    │                                                          │              │能沒收時，追徵│\n│    │                                                          │              │其價額。      │\n├──┼─────────────────────────────┼───────┼───────┤\n│4   │ 98年5月5日21時9分許，陳晁偉以其所持用門號0000000000號行動│毒品危害防制條│累犯，處有期徒│\n│    │ 電話與楊武輝所持用門號為0000000000號行動電話相互聯絡後， │例第8條第1項之│刑1年8月；未扣│\n│    │ 兩人隨即相約在臺中市○○區○○路與市政路口附近見面，楊武 │轉讓第1級毒品 │案之門號098932│\n│    │ 輝即無償交付海洛因1小包（約僅不足0.1公克，僅足供陳晁偉施 │罪。          │9990號行動電話│\n│    │ 用1次之量）予陳晁偉收執，而無償轉讓第1級毒品海洛因供陳晁 │              │機具1支（含SIM│\n│    │ 偉施用1次。                                              │              │卡1張）沒收， │\n│    │                                                          │              │如全部或一部不│\n│    │                                                          │              │能沒收時，追徵│\n│    │                                                          │              │其價額。      │\n├──┼─────────────────────────────┼───────┼───────┤\n│5   │98年3月28日上午11時7分許，彭士韋以其所持用門號0000000000號│毒品危害防制條│累犯，處有期徒│\n│    │之行動電話與楊武輝所持用門號為0000000000號行動電話（起訴書│例第4條第1項之│刑12年5月；未 │\n│    │誤載為0000000000號）相互連繫後，兩人隨即約在臺中縣大雅鄉（│販賣第1級毒品 │扣案之門號0917│\n│    │現改制為臺中市大雅區○○○路附近之土地公廟見面，楊武輝即販│罪。          │248763號行動電│\n│    │賣交付海洛因1小包（約0.12公克）予彭士韋，並當場向彭士韋收 │              │話機具1支（含S│\n│    │取上開交易代價新台幣（下同）500元，而販賣第1級毒品海洛因予│              │IM卡1張）沒收 │\n│    │彭士韋1次。                                               │              │，如全部或一部│\n│    │                                                          │              │不能沒收時，追│\n│    │                                                          │              │徵其價額；未扣│\n│    │                                                          │              │案之新臺幣500 │\n│    │                                                          │              │元沒收，如全部│\n│    │                                                          │              │或一部不能沒收│\n│    │                                                          │              │時，以其財產抵│\n│    │                                                          │              │償之。        │\n├──┼─────────────────────────────┼───────┼───────┤\n│6   │98年3月29日12時35分許，彭士韋以其所持用門號0000000000號之 │毒品危害防制條│累犯，處有期徒│\n│    │行動電話與楊武輝所持用門號為0000000000號行動電話（起訴書誤│例第4條第1項之│刑12年8月；未 │\n│    │載為0000000000號）相互連繫後，兩人隨即約在臺中縣大雅鄉（現│販賣第1級毒品 │扣案之門號0917│\n│    │改制為臺中市大雅區○○○路口附近見面，楊武輝即販賣交付海洛│罪。          │248763號行動電│\n│    │因6小包（每包各約0.1 2公克）予彭士韋，並當場向彭士韋收取上│              │話機具1支（含S│\n│    │開交易代價3000元，而販賣第1級毒品海洛因予彭士韋1次。      │              │IM卡1張）沒收 │\n│    │                                                          │              │，如全部或一部│\n│    │                                                          │              │不能沒收時，追│\n│    │                                                          │              │徵其價額；未扣│\n│    │                                                          │              │案之新臺幣3000│\n│    │                                                          │              │元沒收，如全部│\n│    │                                                          │              │或一部不能沒收│\n│    │                                                          │              │時，以其財產抵│\n│    │                                                          │              │償之。        │\n├──┼─────────────────────────────┼───────┼───────┤\n│7   │98年4月2日12時15分許，彭士韋以其所持用門號0000000000號之行│毒品危害防制條│累犯，處有期徒│\n│    │動電話與楊武輝所持用門號為0000000000號行動電話相互連繫後，│例第4條第1項之│刑12年5月；未 │\n│    │兩人隨即約在臺中縣大雅鄉（現改制為臺中市大雅區○○○路口附│販賣第1級毒品 │扣案之門號0989│\n│    │近見面，楊武輝即販賣交付海洛因1小包（約0.12公克）予彭士韋 │罪。          │329990號行動電│\n│    │，並當場向彭士韋收取上開交易代價500元，而販賣第1級毒品海洛│              │話機具1支（含S│\n│    │因予彭士韋1次。                                           │              │IM卡1張）沒收 │\n│    │                                                          │              │，如全部或一部│\n│    │                                                          │              │不能沒收時，追│\n│    │                                                          │              │徵其價額；未扣│\n│    │                                                          │              │案之新臺幣500 │\n│    │                                                          │              │元沒收，如全部│\n│    │                                                          │              │或一部不能沒收│\n│    │                                                          │              │時，以其財產抵│\n│    │                                                          │              │償之。        │\n├──┼─────────────────────────────┼───────┼───────┤\n│8   │98年5月3日10時48分至11時32分許，彭士韋以其所持用門號098747│毒品危害防制條│累犯，處有期徒│\n│    │0956號之行動電話與楊武輝所持用門號為0000000000號行動電話（│例第4條第1項之│刑12年6月；未 │\n│    │起訴書誤載0000000000號）相互連繫後，兩人隨即約在臺中縣大雅│販賣第1級毒品 │扣案之門號0917│\n│    │鄉（現改制為臺中市大雅區○○○路附近之土地公廟見面，楊武輝│罪。          │248763號行動電│\n│    │即販賣交付海洛因2小包（各約0.12公克）予彭士韋，並當場向彭 │              │話機具1支（含S│\n│    │士韋收取上開交易代價1000元，而販賣第1級毒品海洛因予彭士韋1│              │IM卡1張）沒收 │\n│    │次。                                                      │              │，如全部或一部│\n│    │                                                          │              │不能沒收時，追│\n│    │                                                          │              │徵其價額；未扣│\n│    │                                                          │              │案之新臺幣1000│\n│    │                                                          │              │元沒收，如全部│\n│    │                                                          │              │或一部不能沒收│\n│    │                                                          │              │時，以其財產抵│\n│    │                                                          │              │償之。        │\n├──┼─────────────────────────────┼───────┼───────┤\n│9   │98年5月5日16時47分許，彭士韋以其所持用門號0000000000號之行│毒品危害防制條│累犯，處有期徒│\n│    │動電話與楊武輝所持用門號為0000000000號行動電話（起訴書誤載│例第4條第1項之│刑12年6月；未 │\n│    │為0000000000號）相互連繫後，兩人隨即約在臺中縣沙鹿鎮（現改│販賣第1級毒品 │扣案之門號0917│\n│    │制為臺中市沙鹿區）清泉岡派出所附近修車廠外見面，楊武輝即販│罪。          │248763號行動電│\n│    │賣交付海洛因2小包（各約0.12公克）予彭士韋，並當場向彭士韋 │              │話機具1支（含S│\n│    │收取上開交易代價1000元，而販賣第1級毒品海洛因予彭士韋1次。│              │IM卡1張）沒收 │\n│    │                                                          │              │，如全部或一部│\n│    │                                                          │              │不能沒收時，追│\n│    │                                                          │              │徵其價額；未扣│\n│    │                                                          │              │案之新臺幣1000│\n│    │                                                          │              │元沒收，如全部│\n│    │                                                          │              │或一部不能沒收│\n│    │                                                          │              │時，以其財產抵│\n│    │                                                          │              │償之。        │\n├──┼─────────────────────────────┼───────┼───────┤\n│10  │98年5月7日17時59分許，彭士韋以其所持用門號0000000000號之行│毒品危害防制條│累犯，處有期徒│\n│    │動電話與楊武輝所使用門號為0000000000號行動電話（起訴書誤載│例第4條第1項之│刑12年5月；未 │\n│    │為0000000000號；因無證據證明為楊武輝所有，是不另宣告沒收及│販賣第1級毒品 │扣案之新臺幣50│\n│    │追徵價額）相互連繫後，兩人隨即約在臺中縣大雅鄉（現改制為臺│罪。          │0元沒收，如全 │\n│    │中市大雅區○○○路附近之土地公廟見面，楊武輝即販賣交付海洛│              │部或一部不能沒│\n│    │因1小包（約0.12公克）予彭士韋，並當場向彭士韋收取上開交易 │              │收時，以其財產│\n│    │代價500元，而販賣第1級毒品海洛因予彭士韋1次。             │              │抵償之。      │\n└──┴─────────────────────────────┴───────┴───────┘",
  "structure": {
    "main": "楊武輝犯如附表所示之罪，均累犯，各量處如附表所示之刑（各\n含主刑及從刑）。應執行有期徒刑拾伍年；未扣案之門號000\n0000000號、0000000000號行動電話機具貳支\n（各含門號卡壹張）均沒收，如全部或一部不能沒收時，均追徵\n其價額；未扣案之如附表編號5至10所示款項共新臺幣陸仟伍佰\n元沒收，如全部或一部不能沒收時，以其財產抵償之。",
    "fact": "一、楊武輝前曾因犯竊盜罪1罪、偽造文書罪2罪及違反麻醉藥品\n    管理條例罪4罪等案件，先後經法院各判處有期徒刑1年、4\n    月、3月、2年6月、8月、5年2月及9月確定，嗣經減刑並定\n    應執行刑【除上開所處有期徒刑5年2月不得減刑外，餘均減\n    刑2分之1，並各定應執行為有期徒刑8月又15日（竊盜罪1罪\n    、偽造文書罪2罪部分）及有期徒刑5年2月又15日確定（違\n    反麻醉藥品管理條例罪4罪部分，前經執行後假釋付保護管\n    束）】，經合併執行上開所處有期徒刑8月又15日及殘刑之\n    有期徒刑2年5月又15日，而於民國97年3月22日縮刑期滿執\n    行完畢。詎猶不知悔改，明知海洛因係屬毒品危害防制條例\n    第2條第2項第1款所管制之第1級毒品，依法不得販賣、轉讓\n    ，竟意圖營利，分別基於販賣、轉讓海洛因之犯意，以伊所\n    持用門號為0000000000號、0000000000號行動電話（均未扣\n    案）作為販毒及轉讓毒品之聯絡工具，而先後於如附表所示\n    之時間及地點，以如附表所示之方式，分別為如附表編號1\n    至4所示之轉讓海洛因各1小包（均約不足0.1公克之數量）\n    予陳晁偉施用共4次，以及如附表編號5至10所示之販賣海洛\n    因予彭士韋施用共6次之行為。嗣經員警向本院聲請核准對\n    楊武輝、陳晁偉及彭士韋所持用如附表所示之上開行動電話\n    門號予以監聽後，始循線查悉上情。\n二、案經臺中市警察局刑事警察大隊報請臺灣臺中地方法院檢察\n    署檢察官偵查起訴。\n    理    由\n一、證據能力：按被告以外之人於審判外之陳述，雖不符刑事訴\n    訟法第159條之1至第159條之4之規定，而經當事人於審判程\n    序同意作為證據，法院審酌該言詞陳述或書面陳述作成時之\n    情況，認為適當者，亦得為證據。當事人、代理人或辯護人\n    於法院調查證據時，知有第159條第1項不得為證據之情形，\n    而未於言詞辯論終結前聲明異議者，視為有前項之同意，刑\n    事訴訟法第159條之5第1項、第2項定有明文。立法意旨在於\n    傳聞證據未經當事人之反對詰問予以核實，原則上先予排除\n    ，惟若當事人已放棄詰問或未聲明異議，基於證據資料愈豐\n    富，愈有助於真實發現之理念，且強化言詞辯論主義，法院\n    自可承認該傳聞證據例外擁有證據能力。查本件檢察官、被\n    告及指定辯護人即本院公設辯護人對於證人陳晁偉及彭士韋\n    等人於警詢及偵查中所為證述，均表示不爭執（見本院案卷\n    ），並未於言詞辯論終結前聲明異議，依刑事訴訟法第159\n    條之5第2項之規定，視為同意作為證據，且本院審酌上開證\n    人等人均係於案發後不久所為之陳述，記憶猶新，又非在非\n    自由意志之情況下所為之陳述，所陳自較符事實，核無顯有\n    不可信之情況，是本院認該等言詞陳述適當，依刑事訴訟法\n    第159條之5第1項之規定，自均得為證據。次按除法律另有\n    規定外，實施刑事訴訟程序之公務員因違背法定程序取得之\n    證據，其有無證據能力之認定，應審酌人權保障及公共利益\n    之均衡維護，刑事訴訟法第158條之4定有明文；惟本案所引\n    用之通訊監察譯文等非供述證據，並無證據證明係實施刑事\n    訴訟程序之公務員違背法定程序所取得，自應認均具有證據\n    能力，合先敘明。\n二、上開犯罪事實，業據被告楊武輝於100年5月12日檢察官偵查\n    中、100年6月1日本院訊問中及100年6月15日本院審理中均\n    坦承不諱，復有證人陳晁偉於警詢及偵查中（詳見98年度聲\n    拘字第572號卷第23頁至第29頁、第30頁至第32頁、臺中市\n    警察局刑案偵查卷第21頁至第30頁及98年度偵字第28871號\n    卷第8頁背面至第9頁）及證人彭士韋於警詢及偵查中（詳見\n    98年度聲拘字第572號卷第3頁至第8頁、臺中市警察局刑案\n    偵查卷第1頁至第6頁及98年度偵字第28871號卷第4頁至第5\n    頁）證述詳實，且有如附表所示電話之監聽譯文（詳見98年\n    度偵字第28871號卷第7頁至第8頁、98年度聲拘字第572號卷\n    第33頁至第35頁、臺中市警察局刑案偵查卷第31頁至第33頁\n    ）、內政部警政署刑事警察局指認犯罪嫌疑人紀錄表（見98\n    年度聲拘字第572號卷第9頁、臺中市警察局刑案偵查卷第7\n    頁、98年度聲拘字第572號卷第36頁、臺中市警察局刑案偵\n    查卷第34頁）、通訊監察作業譯文摘要報告書（詳見98年度\n    聲拘字第572號卷第10頁至第22頁、臺中市警察局刑案偵查\n    卷第8頁至第20頁）及通訊監察案件相關案號關聯表等存卷\n    可參，足見被告上開自白，核與事實相符。又按販賣海洛因\n    係屬違法行為，非可公然為之，亦無公定價格，而每次買賣\n    之價量，可能隨時依雙方關係深淺、資力、需求量及對行情\n    之認知、來源是否充裕、查緝是否嚴緊、購買者被查獲時供\n    述購買對象之可能風險之評估等，而異其標準，非可一概而\n    論，從而販賣之利得，除被告就販賣之價量俱明確供述外，\n    委難察得實情，而本件被告既坦承確有上開販賣第1級毒品\n    之犯行，如前所述，則被告販售上開毒品確有利潤可圖，已\n    允無疑義；況參以我國政府一再宣示反毒決心，施用、販賣\n    毒品均屬違法行為，此為國人所週知，被告與購買毒品之彭\n    士韋既非至親或有特殊之情誼關係，衡情被告當無甘冒刑罰\n    制裁之重典而毫無利得，益證被告確有營利之主觀上意圖及\n    客觀行為甚明。綜上所述，本案事證明確，被告上開犯行，\n    堪予認定。\n三、查海洛因乃列為毒品危害防制條例第2條所管制之第1級毒品\n    ，依法不得非法販賣、轉讓及持有；是核被告如附表編號1\n    至4所示之所為，均係犯毒品危害防制條例第8條第1項之轉\n    讓第一級毒品罪；另如附表編號5至10所示之所為，均係犯\n    毒品危害防制條例第4條第1項之販賣第1級毒品罪。其販賣\n    或轉讓前之持有第1級毒品行為，均為各該販賣或轉讓之高\n    度行為所吸收，均不另論罪。被告所犯如附表所示數罪間，\n    犯意各別，行為互異，應分論併罰。被告前曾因犯竊盜罪1\n    罪、偽造文書罪2罪及違反麻醉藥品管理條例罪4罪等案件，\n    先後經法院各判處有期徒刑1年、4月、3月、2年6月、8月、\n    5年2月及9月確定，嗣經減刑並定應執行刑【除上開所處有\n    期徒刑5年2月不得減刑外，餘均減刑2分之1，並各定應執行\n    為有期徒刑8月又15日（竊盜罪1罪、偽造文書罪2罪部分）\n    及有期徒刑5年2月又15日確定（違反麻醉藥品管理條例罪4\n    罪部分，前經執行後假釋付保護管束）】，經合併執行上開\n    所處有期徒刑8月又15日及殘刑之有期徒刑2年5月又15日，\n    而於民國97年3月22日縮刑期滿執行完畢，此有臺灣臺中地\n    方法院檢察署刑案資料查註紀錄表及臺灣高等法院被告前案\n    紀錄表在卷可按，其於受有期徒刑執行完畢後5年以內故意\n    再犯本件有期徒刑以上之10罪，均為累犯，除法定刑為死刑\n    、無期徒刑部分，依法不得加重外，其餘部分各應依刑法第\n    47條第1項規定加重其刑。查被告雖販賣第1級毒品海洛因予\n    彭士韋，惟販賣次數為6次，且均係小額交易，6次共僅6500\n    元，與一般大毒梟動輒數十萬元、數百萬元，甚至數千萬元\n    ，有顯著之差別，而販賣第1級毒品罪之法定刑為「製造、\n    運輸、販賣第1級毒品者，處死刑或無期徒刑；處無期徒刑\n    者，得併科新臺幣2000萬元以下罰金。」，然同為販賣第1\n    級毒品之人，其原因動機不一，犯罪情節未必盡同，或有大\n    盤毒梟者，亦有中、小盤之分，甚或僅止於吸毒者友儕間為\n    求互通有無之有償轉讓者亦有之，其販賣行為所造成危害社\n    會之程度自屬有異，法律科處此類犯罪，所設之法定最低本\n    刑卻相同，不可謂不重。於此情形，倘依其情狀處以相當之\n    有期徒刑，即足以懲儆，並可達防衛社會之目的者，自非不\n    可依客觀之犯行與主觀之惡性兩者加以考量其情狀，審酌是\n    否有其可憫恕之處，而適用刑法第59條之規定酌量減輕其刑\n    ，期使個案裁判之量刑，能斟酌至當，符合比例原則。查被\n    告販賣海洛因予彭士韋之數量、次數及代價尚微，以其情節\n    論，惡性非重，在客觀上足以引起一般之同情等堪資憫恕之\n    處，揆諸上開說明，本院認如科以法定最低刑度仍嫌過重，\n    爰就被告所犯如附表編號5至10所示部分，各依刑法第59條\n    之規定予以酌量減輕其刑，並依法先加重後減輕之。又毒品\n    危害防制條例第17條原僅規定犯該條所列舉之製造、販賣、\n    運輸等罪之毒販，為鼓勵其供出毒品來源，因而破獲者，得\n    獲邀減刑之寬典，俾有效推展阻斷供給之緝毒工作；而毒販\n    之所以願意供出其上游組織之情形，使檢警機關得以進一步\n    追查破獲，類皆已於偵查或審判中自白犯罪，然上開條例並\n    未有如貪污治罪條例第8條第2項自白減刑之規定，不無造成\n    毒販可能自忖無法有效供出毒品來源之上手，難以獲得減刑\n    恩惠，因而減弱甚至斷絕其自白認罪之誘因，致使上開案件\n    之刑事訴訟程序未能儘早確定。98年5月20日修正之毒品危\n    害防制條例第17條，乃採行寬厚之刑事政策，修正原條文，\n    擴大適用範圍，除於第1項規定供出毒品來源，因而查獲其\n    他正犯或共犯者，減輕或免除其刑外，並增列第2項於偵查\n    及審判中自白者，減輕其刑之規定，以鼓勵毒販自白認罪，\n    開啟其自新之路。從而，毒販在偵查及審判中之歷次陳述，\n    各有1次以上之自白，並供出毒品來源，因而查獲其他正犯\n    或共犯之情形，即已完全合致第17條第1項、第2項規定之要\n    件，且其中第2項減刑之事由，當然為第2項減免規定所包括\n    ，依法規競合之吸收關係，應優先適用第17條第1項之規定\n    （最高法院98年度台上字第7231號著有判決可參）。而查，\n    本件並未依被告之自白並供出毒品來源，因而破獲其他上手\n    或共犯等情，此為被告於本院審理中所是認，自無依上開條\n    例第17條第1項減輕其刑之適用；然被告確曾於100年5月12\n    日檢察官偵查中、100年6月1日本院訊問中及100年6月15日\n    本院審理中均自白上開販賣及轉讓第1級毒品之罪，揆諸上\n    開說明，自應依上開條例第17條第2項規定，就如附表編號5\n    至10所示部分遞減輕之，並依法先加重後遞減輕之；另就如\n    附表編號1至4所示部分減輕之，並依法先加重後減輕之。爰\n    各審酌被告犯罪之動機、目的係為圖得一己之利益、販賣及\n    轉讓毒品之對象各為1人，又販賣毒品之數量、金額及次數\n    尚微，其販賣及轉讓毒品為增進流通毒品之管道，危害社會\n    治安非輕，惟均係小額交易或無償轉讓，暨其犯罪後坦承犯\n    行，犯罪後態度尚佳等一切情狀，分別量處被告如附表所示\n    之刑，並定其應執行刑，以示懲儆。另按毒品危害防制條例\n    第19條第1項規定，犯販賣毒品罪者，其犯罪所得之財物均\n    沒收之，係採義務沒收主義。故販賣毒品所得之對價，不問\n    其中成本若干，利潤多少，均應全部諭知沒收，貫徹政府查\n    禁煙毒之決心，以符立法本旨；又犯毒品危害防制條例第4\n    條之販賣第1級或第2級毒品罪者，依同條例19條第1項規定\n    ，其因犯罪所得之物沒收之，如全部或一部不能沒收時，追\n    徵其價額或以其財產抵償之。所稱因犯罪所得之物，自以實\n    際所得者為限，苟無所得或尚未取得者，自無從為沒收及追\n    繳或抵償之諭知（最高法院91年度臺上字第2419號、96年臺\n    上字第2331號、第5551號判決意旨參照）。又同條例19條第\n    1項並無如同條例第18條第1項所定「不問屬於犯人與否，沒\n    收之」之明文，自屬相對沒收主義之立法，是其應沒收之物\n    ，應以屬被告或共犯所有者為限。又該規定所稱「追徵其價\n    額」者，係指所沒收之物為金錢以外之其他財物而無法沒收\n    時，應追徵其價額，使其繳納與原物相當之價額；如所得財\n    物為金錢而無法沒收時，始應「以其財產抵償之」（最高法\n    院95年度台上字第305號判決意旨參照）。又所謂「其因犯\n    罪所得之財物」，並不以當場搜獲扣押者為限；而販賣毒品\n    所得之對價，不問其中何部分屬於成本，何部分屬於犯罪所\n    得之財物，應均予沒收，始與上開法條之規定符合；且因犯\n    罪所得之財物，亦不能與正常營利事業計算營利所得之情形\n    ，相提並論（最高法院65年度第5次刑庭庭推總會議決議意\n    旨參照）。又門號為0000000000號、0000000000號行動電話\n    機具各1支（各含SIM卡1張），雖未扣案；然均係被告所有\n    ，且為供被告所為如附表編號1至9所示轉讓毒品予陳晁偉或\n    販賣毒品予彭士韋所用之物，業據被告供承在卷，且經證人\n    陳晁偉及彭士韋證述詳實，並有上開電話通聯譯文存卷可參\n    ，又因尚無積極證據證明業已滅失，是應依毒品危害防制條\n    例第19條第1項之規定，各於被告所犯如附表編號1至9所示\n    犯行部分宣告沒收，如全部或一部不能沒收時，追徵其價額\n    。另如附表編號5至10所示販賣第1級毒品所得之款項，雖未\n    扣案，仍各應依同條例第19條第1項之規定，就被告所犯如\n    附表編號5至10所示部分宣告沒收，如全部或一部不能沒收\n    時，各以其財產抵償之。至未扣案門號為0000000000號之行\n    動電話1支，固屬供被告上開如附表編號10所示犯行所用之\n    物，此有上開電話通聯譯文存卷可參（附於臺中市警察局案\n    卷第11頁）；然查，證人彭士韋既稱綽號輝哥之被告乃係使\n    用上開門號為0000000000號、0000000000號電話販毒，其均\n    係撥打被告所使用上開2線電話向被告購毒等語在卷（詳見\n    臺中市警察局警詢案卷第2及23頁），且本院復查無其他積\n    極證據足認該門號0000000000號電話確為被告所有之物，依\n    上開說明，是不另為沒收及追徵其價額之諭知。\n據上論斷，應依刑事訴訟法第299條第1項前段，毒品危害防制條\n例第4條第1項、第8條第1項、第17條第2項、第19條第1項，刑法\n第11條、第47條第1項、第59條、第51條第5款，判決如主文。"
  },
  "search": "臺灣臺中地方法院刑事判決100年度訴字第1574號公訴人臺灣臺中地方法院檢察署檢察官被告楊武輝指定辯護人本院公設辯護人梁乃莉上列被告因違反毒品危害防制條例案件，經檢察官提起公訴（100年度偵緝字第806號），本院判決如下：主文楊武輝犯如附表所示之罪，均累犯，各量處如附表所示之刑（各含主刑及從刑）。應執行有期徒刑拾伍年；未扣案之門號0000000000號、0000000000號行動電話機具貳支（各含門號卡壹張）均沒收，如全部或一部不能沒收時，均追徵其價額；未扣案之如附表編號5至10所示款項共新臺幣陸仟伍佰元沒收，如全部或一部不能沒收時，以其財產抵償之。犯罪事實一、楊武輝前曾因犯竊盜罪1罪、偽造文書罪2罪及違反麻醉藥品管理條例罪4罪等案件，先後經法院各判處有期徒刑1年、4月、3月、2年6月、8月、5年2月及9月確定，嗣經減刑並定應執行刑【除上開所處有期徒刑5年2月不得減刑外，餘均減刑2分之1，並各定應執行為有期徒刑8月又15日（竊盜罪1罪、偽造文書罪2罪部分）及有期徒刑5年2月又15日確定（違反麻醉藥品管理條例罪4罪部分，前經執行後假釋付保護管束）】，經合併執行上開所處有期徒刑8月又15日及殘刑之有期徒刑2年5月又15日，而於民國97年3月22日縮刑期滿執行完畢。詎猶不知悔改，明知海洛因係屬毒品危害防制條例第2條第2項第1款所管制之第1級毒品，依法不得販賣、轉讓，竟意圖營利，分別基於販賣、轉讓海洛因之犯意，以伊所持用門號為0000000000號、0000000000號行動電話（均未扣案）作為販毒及轉讓毒品之聯絡工具，而先後於如附表所示之時間及地點，以如附表所示之方式，分別為如附表編號1至4所示之轉讓海洛因各1小包（均約不足0.1公克之數量）予陳晁偉施用共4次，以及如附表編號5至10所示之販賣海洛因予彭士韋施用共6次之行為。嗣經員警向本院聲請核准對楊武輝、陳晁偉及彭士韋所持用如附表所示之上開行動電話門號予以監聽後，始循線查悉上情。二、案經臺中市警察局刑事警察大隊報請臺灣臺中地方法院檢察署檢察官偵查起訴。理由一、證據能力：按被告以外之人於審判外之陳述，雖不符刑事訴訟法第159條之1至第159條之4之規定，而經當事人於審判程序同意作為證據，法院審酌該言詞陳述或書面陳述作成時之情況，認為適當者，亦得為證據。當事人、代理人或辯護人於法院調查證據時，知有第159條第1項不得為證據之情形，而未於言詞辯論終結前聲明異議者，視為有前項之同意，刑事訴訟法第159條之5第1項、第2項定有明文。立法意旨在於傳聞證據未經當事人之反對詰問予以核實，原則上先予排除，惟若當事人已放棄詰問或未聲明異議，基於證據資料愈豐富，愈有助於真實發現之理念，且強化言詞辯論主義，法院自可承認該傳聞證據例外擁有證據能力。查本件檢察官、被告及指定辯護人即本院公設辯護人對於證人陳晁偉及彭士韋等人於警詢及偵查中所為證述，均表示不爭執（見本院案卷），並未於言詞辯論終結前聲明異議，依刑事訴訟法第159條之5第2項之規定，視為同意作為證據，且本院審酌上開證人等人均係於案發後不久所為之陳述，記憶猶新，又非在非自由意志之情況下所為之陳述，所陳自較符事實，核無顯有不可信之情況，是本院認該等言詞陳述適當，依刑事訴訟法第159條之5第1項之規定，自均得為證據。次按除法律另有規定外，實施刑事訴訟程序之公務員因違背法定程序取得之證據，其有無證據能力之認定，應審酌人權保障及公共利益之均衡維護，刑事訴訟法第158條之4定有明文；惟本案所引用之通訊監察譯文等非供述證據，並無證據證明係實施刑事訴訟程序之公務員違背法定程序所取得，自應認均具有證據能力，合先敘明。二、上開犯罪事實，業據被告楊武輝於100年5月12日檢察官偵查中、100年6月1日本院訊問中及100年6月15日本院審理中均坦承不諱，復有證人陳晁偉於警詢及偵查中（詳見98年度聲拘字第572號卷第23頁至第29頁、第30頁至第32頁、臺中市警察局刑案偵查卷第21頁至第30頁及98年度偵字第28871號卷第8頁背面至第9頁）及證人彭士韋於警詢及偵查中（詳見98年度聲拘字第572號卷第3頁至第8頁、臺中市警察局刑案偵查卷第1頁至第6頁及98年度偵字第28871號卷第4頁至第5頁）證述詳實，且有如附表所示電話之監聽譯文（詳見98年度偵字第28871號卷第7頁至第8頁、98年度聲拘字第572號卷第33頁至第35頁、臺中市警察局刑案偵查卷第31頁至第33頁）、內政部警政署刑事警察局指認犯罪嫌疑人紀錄表（見98年度聲拘字第572號卷第9頁、臺中市警察局刑案偵查卷第7頁、98年度聲拘字第572號卷第36頁、臺中市警察局刑案偵查卷第34頁）、通訊監察作業譯文摘要報告書（詳見98年度聲拘字第572號卷第10頁至第22頁、臺中市警察局刑案偵查卷第8頁至第20頁）及通訊監察案件相關案號關聯表等存卷可參，足見被告上開自白，核與事實相符。又按販賣海洛因係屬違法行為，非可公然為之，亦無公定價格，而每次買賣之價量，可能隨時依雙方關係深淺、資力、需求量及對行情之認知、來源是否充裕、查緝是否嚴緊、購買者被查獲時供述購買對象之可能風險之評估等，而異其標準，非可一概而論，從而販賣之利得，除被告就販賣之價量俱明確供述外，委難察得實情，而本件被告既坦承確有上開販賣第1級毒品之犯行，如前所述，則被告販售上開毒品確有利潤可圖，已允無疑義；況參以我國政府一再宣示反毒決心，施用、販賣毒品均屬違法行為，此為國人所週知，被告與購買毒品之彭士韋既非至親或有特殊之情誼關係，衡情被告當無甘冒刑罰制裁之重典而毫無利得，益證被告確有營利之主觀上意圖及客觀行為甚明。綜上所述，本案事證明確，被告上開犯行，堪予認定。三、查海洛因乃列為毒品危害防制條例第2條所管制之第1級毒品，依法不得非法販賣、轉讓及持有；是核被告如附表編號1至4所示之所為，均係犯毒品危害防制條例第8條第1項之轉讓第一級毒品罪；另如附表編號5至10所示之所為，均係犯毒品危害防制條例第4條第1項之販賣第1級毒品罪。其販賣或轉讓前之持有第1級毒品行為，均為各該販賣或轉讓之高度行為所吸收，均不另論罪。被告所犯如附表所示數罪間，犯意各別，行為互異，應分論併罰。被告前曾因犯竊盜罪1罪、偽造文書罪2罪及違反麻醉藥品管理條例罪4罪等案件，先後經法院各判處有期徒刑1年、4月、3月、2年6月、8月、5年2月及9月確定，嗣經減刑並定應執行刑【除上開所處有期徒刑5年2月不得減刑外，餘均減刑2分之1，並各定應執行為有期徒刑8月又15日（竊盜罪1罪、偽造文書罪2罪部分）及有期徒刑5年2月又15日確定（違反麻醉藥品管理條例罪4罪部分，前經執行後假釋付保護管束）】，經合併執行上開所處有期徒刑8月又15日及殘刑之有期徒刑2年5月又15日，而於民國97年3月22日縮刑期滿執行完畢，此有臺灣臺中地方法院檢察署刑案資料查註紀錄表及臺灣高等法院被告前案紀錄表在卷可按，其於受有期徒刑執行完畢後5年以內故意再犯本件有期徒刑以上之10罪，均為累犯，除法定刑為死刑、無期徒刑部分，依法不得加重外，其餘部分各應依刑法第47條第1項規定加重其刑。查被告雖販賣第1級毒品海洛因予彭士韋，惟販賣次數為6次，且均係小額交易，6次共僅6500元，與一般大毒梟動輒數十萬元、數百萬元，甚至數千萬元，有顯著之差別，而販賣第1級毒品罪之法定刑為「製造、運輸、販賣第1級毒品者，處死刑或無期徒刑；處無期徒刑者，得併科新臺幣2000萬元以下罰金。」，然同為販賣第1級毒品之人，其原因動機不一，犯罪情節未必盡同，或有大盤毒梟者，亦有中、小盤之分，甚或僅止於吸毒者友儕間為求互通有無之有償轉讓者亦有之，其販賣行為所造成危害社會之程度自屬有異，法律科處此類犯罪，所設之法定最低本刑卻相同，不可謂不重。於此情形，倘依其情狀處以相當之有期徒刑，即足以懲儆，並可達防衛社會之目的者，自非不可依客觀之犯行與主觀之惡性兩者加以考量其情狀，審酌是否有其可憫恕之處，而適用刑法第59條之規定酌量減輕其刑，期使個案裁判之量刑，能斟酌至當，符合比例原則。查被告販賣海洛因予彭士韋之數量、次數及代價尚微，以其情節論，惡性非重，在客觀上足以引起一般之同情等堪資憫恕之處，揆諸上開說明，本院認如科以法定最低刑度仍嫌過重，爰就被告所犯如附表編號5至10所示部分，各依刑法第59條之規定予以酌量減輕其刑，並依法先加重後減輕之。又毒品危害防制條例第17條原僅規定犯該條所列舉之製造、販賣、運輸等罪之毒販，為鼓勵其供出毒品來源，因而破獲者，得獲邀減刑之寬典，俾有效推展阻斷供給之緝毒工作；而毒販之所以願意供出其上游組織之情形，使檢警機關得以進一步追查破獲，類皆已於偵查或審判中自白犯罪，然上開條例並未有如貪污治罪條例第8條第2項自白減刑之規定，不無造成毒販可能自忖無法有效供出毒品來源之上手，難以獲得減刑恩惠，因而減弱甚至斷絕其自白認罪之誘因，致使上開案件之刑事訴訟程序未能儘早確定。98年5月20日修正之毒品危害防制條例第17條，乃採行寬厚之刑事政策，修正原條文，擴大適用範圍，除於第1項規定供出毒品來源，因而查獲其他正犯或共犯者，減輕或免除其刑外，並增列第2項於偵查及審判中自白者，減輕其刑之規定，以鼓勵毒販自白認罪，開啟其自新之路。從而，毒販在偵查及審判中之歷次陳述，各有1次以上之自白，並供出毒品來源，因而查獲其他正犯或共犯之情形，即已完全合致第17條第1項、第2項規定之要件，且其中第2項減刑之事由，當然為第2項減免規定所包括，依法規競合之吸收關係，應優先適用第17條第1項之規定（最高法院98年度台上字第7231號著有判決可參）。而查，本件並未依被告之自白並供出毒品來源，因而破獲其他上手或共犯等情，此為被告於本院審理中所是認，自無依上開條例第17條第1項減輕其刑之適用；然被告確曾於100年5月12日檢察官偵查中、100年6月1日本院訊問中及100年6月15日本院審理中均自白上開販賣及轉讓第1級毒品之罪，揆諸上開說明，自應依上開條例第17條第2項規定，就如附表編號5至10所示部分遞減輕之，並依法先加重後遞減輕之；另就如附表編號1至4所示部分減輕之，並依法先加重後減輕之。爰各審酌被告犯罪之動機、目的係為圖得一己之利益、販賣及轉讓毒品之對象各為1人，又販賣毒品之數量、金額及次數尚微，其販賣及轉讓毒品為增進流通毒品之管道，危害社會治安非輕，惟均係小額交易或無償轉讓，暨其犯罪後坦承犯行，犯罪後態度尚佳等一切情狀，分別量處被告如附表所示之刑，並定其應執行刑，以示懲儆。另按毒品危害防制條例第19條第1項規定，犯販賣毒品罪者，其犯罪所得之財物均沒收之，係採義務沒收主義。故販賣毒品所得之對價，不問其中成本若干，利潤多少，均應全部諭知沒收，貫徹政府查禁煙毒之決心，以符立法本旨；又犯毒品危害防制條例第4條之販賣第1級或第2級毒品罪者，依同條例19條第1項規定，其因犯罪所得之物沒收之，如全部或一部不能沒收時，追徵其價額或以其財產抵償之。所稱因犯罪所得之物，自以實際所得者為限，苟無所得或尚未取得者，自無從為沒收及追繳或抵償之諭知（最高法院91年度臺上字第2419號、96年臺上字第2331號、第5551號判決意旨參照）。又同條例19條第1項並無如同條例第18條第1項所定「不問屬於犯人與否，沒收之」之明文，自屬相對沒收主義之立法，是其應沒收之物，應以屬被告或共犯所有者為限。又該規定所稱「追徵其價額」者，係指所沒收之物為金錢以外之其他財物而無法沒收時，應追徵其價額，使其繳納與原物相當之價額；如所得財物為金錢而無法沒收時，始應「以其財產抵償之」（最高法院95年度台上字第305號判決意旨參照）。又所謂「其因犯罪所得之財物」，並不以當場搜獲扣押者為限；而販賣毒品所得之對價，不問其中何部分屬於成本，何部分屬於犯罪所得之財物，應均予沒收，始與上開法條之規定符合；且因犯罪所得之財物，亦不能與正常營利事業計算營利所得之情形，相提並論（最高法院65年度第5次刑庭庭推總會議決議意旨參照）。又門號為0000000000號、0000000000號行動電話機具各1支（各含SIM卡1張），雖未扣案；然均係被告所有，且為供被告所為如附表編號1至9所示轉讓毒品予陳晁偉或販賣毒品予彭士韋所用之物，業據被告供承在卷，且經證人陳晁偉及彭士韋證述詳實，並有上開電話通聯譯文存卷可參，又因尚無積極證據證明業已滅失，是應依毒品危害防制條例第19條第1項之規定，各於被告所犯如附表編號1至9所示犯行部分宣告沒收，如全部或一部不能沒收時，追徵其價額。另如附表編號5至10所示販賣第1級毒品所得之款項，雖未扣案，仍各應依同條例第19條第1項之規定，就被告所犯如附表編號5至10所示部分宣告沒收，如全部或一部不能沒收時，各以其財產抵償之。至未扣案門號為0000000000號之行動電話1支，固屬供被告上開如附表編號10所示犯行所用之物，此有上開電話通聯譯文存卷可參（附於臺中市警察局案卷第11頁）；然查，證人彭士韋既稱綽號輝哥之被告乃係使用上開門號為0000000000號、0000000000號電話販毒，其均係撥打被告所使用上開2線電話向被告購毒等語在卷（詳見臺中市警察局警詢案卷第2及23頁），且本院復查無其他積極證據足認該門號0000000000號電話確為被告所有之物，依上開說明，是不另為沒收及追徵其價額之諭知。據上論斷，應依刑事訴訟法第299條第1項前段，毒品危害防制條例第4條第1項、第8條第1項、第17條第2項、第19條第1項，刑法第11條、第47條第1項、第59條、第51條第5款，判決如主文。中華民國100年6月29日刑事第15庭審判長法官劉國賓法官柯雅惠法官許惠瑜以上正本證明與原本無異。如不服本判決應於收受送達後10日內向本院提出上訴書狀，並應敘述具體理由；其未敘述上訴理由者，應於上訴期間屆滿後20日內向本院補提理由書（均須按他造當事人之人數附繕本）「切勿逕送上級法院」。書記官楊家印中華民國100年6月29日附表：┌──┬─────────────────────────────┬───────┬───────┐│編號│犯罪時間、地點及方式│所犯法條及罪名│宣告刑│├──┼─────────────────────────────┼───────┼───────┤│1│98年4月24日下午，陳晁偉以其所持用門號0000000000號行動電話│毒品危害防制條│累犯，處有期徒│││與楊武輝所持用門號為0000000000號行動電話相互聯絡後，兩人│例第8條第1項之│刑1年8月；未扣│││隨即相約在臺中市○○區○○路與環中路口中彰橋下路邊見面，│轉讓第1級毒品│案之門號098932│││楊武輝即無償交付海洛因1小包（約僅不足0.1公克，僅足供陳晁│罪。│9990號行動電話│││偉施用1次之量）予陳晁偉收執，而無償轉讓第1級毒品海洛因供││機具1支（含SIM│││陳晁偉施用1次。││卡1張）沒收，│││││如全部或一部不│││││能沒收時，追徵│││││其價額。│├──┼─────────────────────────────┼───────┼───────┤│2│98年4月25日17時59分許，陳晁偉以其所持用門號0000000000號行│毒品危害防制條│累犯，處有期徒│││動電話與楊武輝所持用門號為0000000000號行動電話相互聯絡後│例第8條第1項之│刑1年8月；未扣│││，兩人隨即相約在臺中市○○區○○路與環中路口中彰橋下路邊│轉讓第1級毒品│案之門號098932│││見面，楊武輝即無償交付海洛因1小包（約僅不足0.1公克，僅足│罪。│9990號行動電話│││供陳晁偉施用1次之量）予陳晁偉收執，而無償轉讓第1級毒品海││機具1支（含SIM│││洛因供陳晁偉施用1次。││卡1張）沒收，│││││如全部或一部不│││││能沒收時，追徵│││││其價額。│├──┼─────────────────────────────┼───────┼───────┤│3│98年4月26日19時20分許，陳晁偉以其所持用門號0000000000號行│毒品危害防制條│累犯，處有期徒│││動電話與楊武輝所持用門號為0000000000號行動電話相互聯絡後│例第8條第1項之│刑1年8月；未扣│││，兩人隨即相約在臺中市○○區○○路與環中路口中彰橋下路邊│轉讓第1級毒品│案之門號098932│││見面，楊武輝即無償交付海洛因1小包（約僅不足0.1公克，僅足│罪。│9990號行動電話│││供陳晁偉施用1次之量）予陳晁偉收執，而無償轉讓第1級毒品海││機具1支（含SIM│││洛因供陳晁偉施用1次。││卡1張）沒收，│││││如全部或一部不│││││能沒收時，追徵│││││其價額。│├──┼─────────────────────────────┼───────┼───────┤│4│98年5月5日21時9分許，陳晁偉以其所持用門號0000000000號行動│毒品危害防制條│累犯，處有期徒│││電話與楊武輝所持用門號為0000000000號行動電話相互聯絡後，│例第8條第1項之│刑1年8月；未扣│││兩人隨即相約在臺中市○○區○○路與市政路口附近見面，楊武│轉讓第1級毒品│案之門號098932│││輝即無償交付海洛因1小包（約僅不足0.1公克，僅足供陳晁偉施│罪。│9990號行動電話│││用1次之量）予陳晁偉收執，而無償轉讓第1級毒品海洛因供陳晁││機具1支（含SIM│││偉施用1次。││卡1張）沒收，│││││如全部或一部不│││││能沒收時，追徵│││││其價額。│├──┼─────────────────────────────┼───────┼───────┤│5│98年3月28日上午11時7分許，彭士韋以其所持用門號0000000000號│毒品危害防制條│累犯，處有期徒│││之行動電話與楊武輝所持用門號為0000000000號行動電話（起訴書│例第4條第1項之│刑12年5月；未│││誤載為0000000000號）相互連繫後，兩人隨即約在臺中縣大雅鄉（│販賣第1級毒品│扣案之門號0917│││現改制為臺中市大雅區○○○路附近之土地公廟見面，楊武輝即販│罪。│248763號行動電│││賣交付海洛因1小包（約0.12公克）予彭士韋，並當場向彭士韋收││話機具1支（含S│││取上開交易代價新台幣（下同）500元，而販賣第1級毒品海洛因予││IM卡1張）沒收│││彭士韋1次。││，如全部或一部│││││不能沒收時，追│││││徵其價額；未扣│││││案之新臺幣500│││││元沒收，如全部│││││或一部不能沒收│││││時，以其財產抵│││││償之。│├──┼─────────────────────────────┼───────┼───────┤│6│98年3月29日12時35分許，彭士韋以其所持用門號0000000000號之│毒品危害防制條│累犯，處有期徒│││行動電話與楊武輝所持用門號為0000000000號行動電話（起訴書誤│例第4條第1項之│刑12年8月；未│││載為0000000000號）相互連繫後，兩人隨即約在臺中縣大雅鄉（現│販賣第1級毒品│扣案之門號0917│││改制為臺中市大雅區○○○路口附近見面，楊武輝即販賣交付海洛│罪。│248763號行動電│││因6小包（每包各約0.12公克）予彭士韋，並當場向彭士韋收取上││話機具1支（含S│││開交易代價3000元，而販賣第1級毒品海洛因予彭士韋1次。││IM卡1張）沒收│││││，如全部或一部│││││不能沒收時，追│││││徵其價額；未扣│││││案之新臺幣3000│││││元沒收，如全部│││││或一部不能沒收│││││時，以其財產抵│││││償之。│├──┼─────────────────────────────┼───────┼───────┤│7│98年4月2日12時15分許，彭士韋以其所持用門號0000000000號之行│毒品危害防制條│累犯，處有期徒│││動電話與楊武輝所持用門號為0000000000號行動電話相互連繫後，│例第4條第1項之│刑12年5月；未│││兩人隨即約在臺中縣大雅鄉（現改制為臺中市大雅區○○○路口附│販賣第1級毒品│扣案之門號0989│││近見面，楊武輝即販賣交付海洛因1小包（約0.12公克）予彭士韋│罪。│329990號行動電│││，並當場向彭士韋收取上開交易代價500元，而販賣第1級毒品海洛││話機具1支（含S│││因予彭士韋1次。││IM卡1張）沒收│││││，如全部或一部│││││不能沒收時，追│││││徵其價額；未扣│││││案之新臺幣500│││││元沒收，如全部│││││或一部不能沒收│││││時，以其財產抵│││││償之。│├──┼─────────────────────────────┼───────┼───────┤│8│98年5月3日10時48分至11時32分許，彭士韋以其所持用門號098747│毒品危害防制條│累犯，處有期徒│││0956號之行動電話與楊武輝所持用門號為0000000000號行動電話（│例第4條第1項之│刑12年6月；未│││起訴書誤載0000000000號）相互連繫後，兩人隨即約在臺中縣大雅│販賣第1級毒品│扣案之門號0917│││鄉（現改制為臺中市大雅區○○○路附近之土地公廟見面，楊武輝│罪。│248763號行動電│││即販賣交付海洛因2小包（各約0.12公克）予彭士韋，並當場向彭││話機具1支（含S│││士韋收取上開交易代價1000元，而販賣第1級毒品海洛因予彭士韋1││IM卡1張）沒收│││次。││，如全部或一部│││││不能沒收時，追│││││徵其價額；未扣│││││案之新臺幣1000│││││元沒收，如全部│││││或一部不能沒收│││││時，以其財產抵│││││償之。│├──┼─────────────────────────────┼───────┼───────┤│9│98年5月5日16時47分許，彭士韋以其所持用門號0000000000號之行│毒品危害防制條│累犯，處有期徒│││動電話與楊武輝所持用門號為0000000000號行動電話（起訴書誤載│例第4條第1項之│刑12年6月；未│││為0000000000號）相互連繫後，兩人隨即約在臺中縣沙鹿鎮（現改│販賣第1級毒品│扣案之門號0917│││制為臺中市沙鹿區）清泉岡派出所附近修車廠外見面，楊武輝即販│罪。│248763號行動電│││賣交付海洛因2小包（各約0.12公克）予彭士韋，並當場向彭士韋││話機具1支（含S│││收取上開交易代價1000元，而販賣第1級毒品海洛因予彭士韋1次。││IM卡1張）沒收│││││，如全部或一部│││││不能沒收時，追│││││徵其價額；未扣│││││案之新臺幣1000│││││元沒收，如全部│││││或一部不能沒收│││││時，以其財產抵│││││償之。│├──┼─────────────────────────────┼───────┼───────┤│10│98年5月7日17時59分許，彭士韋以其所持用門號0000000000號之行│毒品危害防制條│累犯，處有期徒│││動電話與楊武輝所使用門號為0000000000號行動電話（起訴書誤載│例第4條第1項之│刑12年5月；未│││為0000000000號；因無證據證明為楊武輝所有，是不另宣告沒收及│販賣第1級毒品│扣案之新臺幣50│││追徵價額）相互連繫後，兩人隨即約在臺中縣大雅鄉（現改制為臺│罪。│0元沒收，如全│││中市大雅區○○○路附近之土地公廟見面，楊武輝即販賣交付海洛││部或一部不能沒│││因1小包（約0.12公克）予彭士韋，並當場向彭士韋收取上開交易││收時，以其財產│││代價500元，而販賣第1級毒品海洛因予彭士韋1次。││抵償之。│└──┴─────────────────────────────┴───────┴───────┘",
  "characters": {
    "judges": [
      "劉國賓",
      "柯雅惠",
      "許惠瑜"
    ],
    "prosecutors": [

    ],
    "lawyers": [

    ],
    "clerks": [
      "楊家印"
    ],
    "plaintiffs": [

    ],
    "defendants": [
      "楊武輝"
    ],
    "prosecutor_office": [
      "臺灣臺中地方法院檢察署檢察官"
    ],
    "creditors": [

    ],
    "debtors": [

    ],
    "judicial_associate_officer": [

    ]
  },
  "adjudged_at": "2011-06-29",
  "created_at": "2016-02-13 16:25:10",
  "updated_at": "2016-02-13 16:25:10"
}