{
  "identify": "TPH-100-家上更(一)-2-20110628-1",
  "court": {
    "name": "臺灣高等法院",
    "code": "TPH"
  },
  "division": {
    "name": "民事",
    "code": "V"
  },
  "year": 100,
  "word": "家上更(一)",
  "number": "2",
  "jcheck": "1",
  "reason": "返還股票價款（代墊扶養費用等）",
  "content": "臺灣高等法院民事判決              100年度家上更(一)字第2號\n上  訴  人  盧辰祥\n被上訴人    吳為漪（原名吳映黎）\n訴訟代理人  楊久弘律師\n上列當事人間請求返還股票價款等事件，上訴人對於中華民國98\n年10月26日臺灣臺北地方法院97年度家訴字第79號第一審判決提\n起上訴後，於本院為訴之變更，經判決後，由最高法院第1次發\n回更審，本院於100年5月31日言詞辯論終結，判決如下：\n    主  文\n被上訴人應給付上訴人新台幣壹佰柒拾貳萬玖仟伍佰元，及自民\n國九十九年二月九日起至清償日止按年息百分之五計算之利息。\n上訴人其餘變更之訴駁回。\n變更之訴及發回前第三審訴訟費用，由被上訴人負擔。\n本判決所命給付部分，於上訴人以新台幣伍拾捌萬元為被上訴人\n供擔保後，得假執行。但被上訴人如以新台幣壹佰柒拾貳萬玖仟\n伍佰元為上訴人供擔保，得免為假執行。\n上訴人其餘假執行之聲請駁回。\n    理  由\n一、按當事人於第二審為訴之變更、追加，非經他造同意，不得\n    為之，但請求之基礎事實同一者，不在此限，民事訴訟法第\n    446條第1項及第255條第1項第2款定有明文。本件上訴人在\n    原審係依不當得利之法律關係，請求被上訴人給付新台幣（\n    下同）1,729,500元及自起訴狀繕本送達翌日起至清償日止\n    ，按年息5%計算之利息（見原審卷(二)第2、15至16頁）；嗣\n    於本院審理中，變更主張：被上訴人承諾將所購買之股票返\n    還予上訴人之父盧子欽、母李美金及胞妹盧隨仁（以下合稱\n    盧子欽等3人），上訴人自盧子欽等3人受讓該股票權利，因\n    被上訴人已出售該股票，爰依受讓盧子欽等3人之股票返還\n    請求權，請求被上訴人返還相當於股票價款之金額1,729,50\n    0元，及調解聲請書繕本送達翌日起至清償日止，按年息5%\n    計算之利息（見發回前本院卷第34頁背面，本院更(一)卷第37\n    頁、40頁背面），經核上訴人於本院變更之訴所為請求之基\n    礎事實與原審所為請求之基礎事實同一，依前揭規定，應予\n    准許。合先敘明。\n二、上訴人主張：兩造原為夫妻，被上訴人於民國（下同）88年\n    間稱其得以員工身分向任職之和信電訊股份有限公司（下稱\n    和信電訊公司）承購該公司股票，盧子欽等3人乃匯款共計\n    1,729,500元予被上訴人，委託被上訴人購買和信電訊公司\n    股票（下稱系爭股票），被上訴人承諾購得系爭股票後將予\n    返還。嗣兩造於93年5月4日離婚，被上訴人未返還系爭股票\n    ，盧子欽等3人乃出具「所有權移轉證明書」（下稱系爭移\n    轉證明書），將系爭股票權利移轉予上訴人，惟系爭股票已\n    遭被上訴人全數出售，被上訴人自應返還系爭股票價款，爰\n    依系爭移轉證明書所受讓之權利，請求被上訴人給付上訴人\n    1,729,500元，並加付自調解聲請書送達翌日起之法定遲延\n    利息等語。原審為上訴人敗訴之判決，上訴人不服，於提起\n    上訴後為訴之變更，經發回前本院為上訴人勝訴之判決，被\n    上訴人不服，提起第三審上訴，經最高法院將發回前本院所\n    為上開判決廢棄，並發回本院更為審理，上訴人在本院聲明\n    ：(一)被上訴人應給付上訴人1,729,500元，及自調解聲請書\n    送達翌日起至清償日止，按年息5%計算之利息。(二)願供擔保\n    請准宣告假執行。（上訴人在原審所為其餘請求，經兩造於\n    原審成立訴訟上和解，爰就此部分之主張及陳述不予贅述，\n    附此敘明。）\n三、被上訴人則以：上訴人知悉被上訴人任職之和信電訊公司給\n    予員工認購股份之機會，乃要求盧子欽等3人代為匯款以交\n    由被上訴人認購系爭股票，被上訴人並未承諾返還系爭股票\n    。嗣兩造於93年5月4日協議離婚時，因考慮被上訴人結婚時\n    曾出資超過150萬元以購屋、裝潢及購買傢俱，並將該屋登\n    記在上訴人名下，加上離婚前3年之家庭生活費用皆由被上\n    訴人負擔，另被上訴人又同意於離婚後無條件將停車位過戶\n    予上訴人，故約定以被上訴人名義登記之系爭股票歸被上訴\n    人所有，並於離婚協議書載明，是上訴人所為本件請求，自\n    無理由等語，資為抗辯。被上訴人對於上訴人變更之訴聲明\n    ：(一)變更之訴駁回。(二)如受不利判決，願預供擔保請准宣告\n    免為假執行。\n四、經查兩造於79年12月14日結婚，被上訴人於88年間任職和信\n    電訊公司，得以員工身分承購該公司股票（未上市、上櫃）\n    ，上訴人之胞妹盧隨仁於88年5月27日匯款37萬元、上訴人\n    之父盧子欽於88年5月28日及同年月31日分別存款698,900元\n    及43萬元、上訴人之母李美金於88年5月31日匯款230,600元\n    至被上訴人設於台灣銀行之帳戶，共計1,729,500元，委託\n    被上訴人購買系爭股票，被上訴人購得後未交付所購得之系\n    爭股票予盧子欽等3人，嗣並自行出售系爭股票，兩造則於\n    93年5月4日協議離婚等情，有戶籍謄本、台灣銀行存入憑條\n    、合作金庫匯款回條聯、台灣銀行無摺存入憑條存根、台灣\n    銀行光碟櫃歷史明細查詢系統、臺灣銀行館前分行98年6月8\n    日館前存字第09800019331號函及亞東證券股份有限公司99\n    年1月18日亞證字第9909900024號函可稽（見原審卷(一)第19\n    至21、209至211、255、256、267至269頁，卷(二)第8頁，本\n    院更(一)卷第15頁），且為兩造所不爭執，均堪信為真實。\n五、上訴人主張被上訴人承諾於購得系爭股票後將返還股票予盧\n    子欽3等人，盧子欽等3人已將系爭股票權利讓與上訴人，因\n    被上訴人將系爭股票全數賣出，被上訴人自應返還相當於系\n    爭股票價款1,729,500元等語；惟為被上訴人所否認，並以\n    前詞置辯。經查：\n  (一)據證人李美金在原審到場證稱：「我所知道的當時吳小姐（\n    指被上訴人）回到我們家，因為我們是分開住，回到我家跟\n    我說以她當時的位置可以認購300張，她那時的職位我不清\n    楚，然後說她的錢只能買多少，還不夠，問我和我先生（指\n    盧子欽）要不要買，我那時候想就拿了23萬左右來買，我先\n    生拿了100多萬，我們用我們的帳戶分開匯到她的帳戶，我\n    們當時所了解的她要把她不能認購的部分讓我們來買，所以\n    我才願意，當時一定要用她的名字買，因為她在那裡工作，\n    …我們的理解是吳小姐不夠的部分不能認購的部分由我來買\n    ，實際總數我不太清楚，我是從台北銀行匯的，我先生是用\n    哪個銀行帳戶匯的我不清楚，我們不是借她錢，是我們要買\n    ，但只能用她的名義，後來我們一直不過問，因為自己人相\n    信她」，「（系爭股票）是為我自己買的，吳小姐從未跟我\n    提過股票的事，離婚前我有跟她催討過，但她就跟我說沒有\n    了，但沒有了是指什麼意思我不知道，我也不曉得和信電信\n    還在不在」，「我一直在強調就是，當時匯這錢主要的目的\n    是我要用她的名義，買我的股票，我先生也是這樣的意思，\n    我不是要借她」，「盧隨仁是我的女兒，她有寄錢給我，存\n    在我們戶頭」，「（當初買系爭股票是要）投資，因為我們\n    認為將來上市的話一定會賺錢，所以我們才願意，因為那時\n    候吳小姐說，這個不錯，她還有幾張，所以我們才願意買」\n    等語（見原審卷(一)第246至248、251頁）。而被上訴人亦自\n    承：「錢是原告（指上訴人）父親匯進來的，所以我認為（\n    系爭股票）是爸爸（指盧子欽）、媽媽（指李美金）的，雖\n    然有妹妹（指盧隨仁）的名字，但我都是跟媽媽在討論，我\n    的確拿了錢，也幫他們買了股票」，「當時沒有（向盧子欽\n    等3人借錢），是他們的（錢），只是用我的名字（買系爭\n    股票）」等語（見原審卷(一)第249頁）。足證盧子欽等3人係\n    欲利用被上訴人工作上之機會認購系爭股票，而與被上訴人\n    合意由盧子欽等3人出資，以被上訴人之名義購買系爭股票\n    ，是盧子欽等3人自得請求被上訴人返還所購得之系爭股票\n    。\n  (二)被上訴人雖抗辯其出資超過150萬元所購得之房屋登記在上\n    訴人名下，且負擔離婚前3年之家庭生活費用，又同意於離\n    婚後無條件將停車位過戶予上訴人，故兩造於離婚協議書約\n    明「雙方於婚姻關係存續中名下之財產各自擁有」，是系爭\n    股票應歸被上訴人所有等語；惟為上訴人所否認。經查：\n  1.兩造於93年5月4日所簽署離婚協議書關於兩造財產分配固約\n    定：「…(2)男（指上訴人）、女（指被上訴人）雙方於婚姻\n    關係存續中名下之財產各自擁有。(3)男、女雙方於婚姻關係\n    存續中，如在外有發生任何一切債務，各自清償，與他方無\n    涉。(4)女方名下之不動產坐落於內湖區歡樂頌社區內之地下\n    二層41號之停車位，女方同意離婚登記後無條件給予（過戶\n    ）男方」（見原審卷(一)第55至56頁），然此約定係就兩造於\n    婚姻關係存續中所取得之積極財產及消極財產進行分配，而\n    系爭股票係由盧子欽等3人出資及借用被上訴人之名義購得\n    ，實際上應歸盧子欽等3人所有，且上訴人於兩造簽訂離婚\n    協議書時並非系爭股票之權利人，衡情自無可能將系爭股票\n    列為兩造之財產而進行分配。\n  2.上訴人固曾於原審陳稱：系爭股票是爺爺奶奶要給小孩讀書\n    基金，所以匯款讓被上訴人購買股票，可以支付小孩以後費\n    用等語（原審卷(一)第23頁背面）。然查縱認盧子欽等3人借\n    用被上訴人之名義購買系爭股票，係欲供作兩造子女將來教\n    育基金之用，惟亦不能執此即謂盧子欽等3人有將系爭股票\n    贈與兩造之意，是尚不能僅憑上訴人之上開陳述，即認系爭\n    股票於兩造簽訂離婚協議書時，係歸屬於上訴人或被上訴人\n    所有，而於離婚協議時列入兩造之財產進行分配。\n  (三)被上訴人雖又抗辯其於兩造離婚當日已獲李美金同意而取得\n    系爭股票等語，惟亦為上訴人所否認。查證人李美金證稱：\n    「沒有此事。她（指被上訴人）離婚當天有打電話給我，但\n    不是提股票，是說要離婚的事，我沒有說要把股票給她」，\n    「那個時候因為他們是很急的情況下辦離婚，一時也沒有想\n    到那麼多，做父母總是不希望走到這個地步，當時聽說見證\n    人也是吳小姐找的，在這情況下我也忘記什麼事應該要趕快\n    提，所以那時沒有提（股票的事）」，「我確認沒有（說要\n    把系爭股票給被上訴人），不可能」等語（見原審卷第249\n    、251頁），已否認曾同意將系爭股票歸由被上訴人所有；\n    況購買系爭股票之資金1,729,500元，其中100餘萬元為盧子\n    欽所出資，37萬元為盧隨仁出資，李美金僅出資約23萬元，\n    ，衡情李美金焉有可能未經與盧子欽及盧隨仁商討，即在電\n    話中答應被上訴人要求，而同意系爭股票全部歸由被上訴人\n    所有。此外，被上訴人亦無法提出其他確切之證據以實其說\n    ，是被上訴人所為此部分抗辯，亦不足取。\n  (四)上訴人主張其已自盧子欽等3人受讓系爭股票權利，因系爭\n    股票已遭被上訴人出售，被上訴人自應返還相當於系爭股票\n    之價款1,729,500元等語，並提出系爭移轉證明書為證（原\n    審卷(一)第215頁），惟亦為被上訴人所否認。經查：\n  1.依系爭移轉證明書記載：「本人所有但寄放於吳麗蓉(即被\n    上訴人)名下和信電訊股票已於2005年至2007（年）間轉讓\n    予盧辰祥所有」，其上並蓋有盧子欽等3人之印章（見原審\n    卷(一)第215頁）。被上訴人雖否認系爭移轉證明書為真正，\n    惟查系爭移轉證明書固未記載出具證明書之日期，惟上訴人\n    係於97年10月13日在原審提出（見原審卷(一)第213、215頁）\n    ，當時盧子欽尚未死亡（按盧子欽係於98年10月15日死亡－\n    見發回前本院卷第9頁）。又據證人李美金在原審到場證稱\n    ：「（系爭移轉證明書）是我和我先生寫的沒錯」，「大約\n    是（西元）2005年到2007（年）中間（出具系爭移轉證明書\n    ），是他們分開後，我想把這移轉給我兒子（指上訴人）在\n    處理比較合適」，「所有權移轉證明書上面確實是我先生（\n    指盧子欽）和我女兒（指盧隨仁）的印章」，「（系爭移轉\n    證明書）是在他們離婚後（出具的）」等語（見原審卷(一)第\n    247、248、250頁）；復據上訴人提出訴外人盧隨仁請求公\n    證之公證書內載：「授權人（即盧隨仁）授權李美金處理將\n    其名下但寄放於吳麗蓉處之和信電訊股票轉讓予盧辰祥之一\n    切相關事宜，包含但不限於簽署文件、於所有權移轉證明書\n    （即系爭移轉證明書）上用印、辦理相關手續等；授權人並\n    授權李美金承認其於民國94年1月1日起至簽署本授權書之日\n    就前述和信電訊股票轉讓予盧辰祥所為之一切相關事宜，包\n    含但不限於簽署文件、於所有權移轉證明書（即系爭移轉證\n    明書）上用印、辦理相關手續等」（見發回前本院卷第72頁\n    ），由此足證系爭移轉證明書係屬真正。\n  2.於盧子欽死亡後，上訴人固在發回前本院陳稱其係以繼承人\n    之身份請求被上訴人返還系爭股票及股息（見發回前本院卷\n    第17頁背面），並將盧子欽匯予被上訴人購買系爭股票之款\n    項列入盧子欽之遺產申報遺產稅（見發回前本院卷第48頁）\n    ，惟上訴人亦陳明：盧子欽等3人將系爭股票之權利移轉予\n    上訴人，由上訴人向被上訴人請求，上訴人亦承諾於被上訴\n    人返還系爭股票後將再移轉予盧子欽等3人等語（見發回前\n    本院卷第20頁背面、23、48、68頁背面），並提出意願書為\n    證（見發回前本院卷第24頁）。堪認上訴人係基於上開返還\n    股票之承諾，而將應返還予盧子欽之股款部分列為遺產而據\n    以申報遺產稅，是尚不能執此即謂系爭移轉證明書所載內容\n    非屬真正。\n  3.被上訴人自承將盧子欽等3人所交付之1,729,500元全數購買\n    系爭股票計150張（見原審卷(一)第191、236、248、253頁，\n    卷(二)第5頁，發回前本院卷第33頁背面、62頁背面，本院更\n    (一)卷第40頁背面），而上開股票僅係盧子欽等3人借用被上\n    訴人之名義所購買，已如前述，是被上訴人原應將系爭股票\n    返還予盧子欽等3人，然盧子欽等3人已將系爭股票之權利移\n    轉予上訴人，亦如前述，是上訴人自得請求被上訴人返還系\n    爭股票。惟查被上訴人業將系爭股票全數出售，此亦為被上\n    訴人所不爭執；而系爭股票係未上市、上櫃股票，其發行公\n    司和信電訊公司已於92年間由遠傳電信股份有限公司併購，\n    此有網路資訊及亞東證券股份有限公司99年1月18日亞證字\n    第9909900024號函可稽（見原審卷(一)第257頁、發回前本院\n    卷第28頁），且為兩造所不爭，是被上訴人已無可能自證券\n    交易市場取得和信電訊公司之股票以返還上訴人。又被上訴\n    人陳明：其就出售系爭股票所得金額已不復記憶（見發回前\n    本院卷第34頁、本院更(一)卷第40頁背面）；系爭股票已經出\n    售，如應返還，即應返還上訴人所主張之1,729,500元等語\n    （見發回前本院卷第63頁），是上訴人據以請求被上訴人給\n    付1,729,500元，自屬有據，應予准許。\n  4.按給付無確定期限者，債務人於債權人得請求給付時，經其\n    催告而未為給付，自受催告時起，負遲延責任；其經債權人\n    起訴而送達訴狀，或依督促程序送達支付命令，或為其他相\n    類之行為者，與催告有同一之效力；又債務人遲延者，債權\n    人得請求其賠償因遲延而生之損害；遲延之債務，以支付金\n    錢為標的者，債權人得請求依法定利率計算之遲延利息，民\n    法第229條第2項、第231條第1項及第233條第1項本文分別定\n    有明文。查上訴人係於99年2月8日發回前本院準備程序時當\n    庭為訴之變更而向被上訴人請求（見發回前本院卷第34頁背\n    面），被上訴人亦於當日到場（見同卷第32頁），依前揭規\n    定，被上訴人就本件請求自99年2月9日起負遲延責任，是上\n    訴人得請求被上訴人給付自是日起按法定利率計算之利息。\n六、綜上所述，上訴人請求被上訴人給付1,729,500元，及自99\n    年2月9日起至清償日止，按年息5%計算之利息，為有理由，\n    應予准許；其逾此範圍所為請求為無理由，應予駁回。又就\n    上訴人勝訴部分，兩造均陳明願供擔保宣告准免假執行，經\n    核均無不合，爰分別酌定相當擔保金額准許之；至上訴人敗\n    訴部分，上訴人所為假執行之聲請即失所附麗，應併予駁回\n    。\n七、兩造其餘之攻擊或防禦方法及未經援用之證據，經本院斟酌\n    後，認為均不足以影響本判決之結果，自無予以調查或逐一\n    詳予論駁之必要。附此敘明。\n八、據上論結，本件變更之訴為一部有理由，一部無理由，依民\n    事訴訟法第463條、第390條第2項、第392條、第79條，判決\n    如主文。\n中    華    民    國   100   年    6     月    28    日\n                    民事第四庭\n                        審判長法  官  張劍男\n                              法  官  陳靜芬\n                              法  官  彭昭芬\n正本係照原本作成。\n如不服本判決，應於收受送達後20日內向本院提出上訴書狀，其\n未表明上訴理由者，應於提出上訴後20日內向本院補提理由書狀\n（均須按他造當事人之人數附繕本）上訴時應提出委任律師或具\n有律師資格之人之委任狀；委任有律師資格者，另應附具律師資\n格證書及釋明委任人與受任人有民事訴訟法第466條之1第1項但\n書或第2項（詳附註）所定關係之釋明文書影本。\n中    華    民    國   100    年    6     月    28    日\n                             書記官  丁華平\n附註：\n民事訴訟法第466條之1（第1項、第2項）：\n對於第二審判決上訴，上訴人應委任律師為訴訟代理人。但上訴\n人或其他法定代理人具有律師資格者，不在此限。\n上訴人之配偶、三親等內之血親、二親等內之姻親，或上訴人為\n法人、中央或地方機關時，其所屬專任人員具有律師資格並經法\n院認為適當者，亦得為第三審訴訟代理人。",
  "structure": {
    "main": "被上訴人應給付上訴人新台幣壹佰柒拾貳萬玖仟伍佰元，及自民\n國九十九年二月九日起至清償日止按年息百分之五計算之利息。\n上訴人其餘變更之訴駁回。\n變更之訴及發回前第三審訴訟費用，由被上訴人負擔。\n本判決所命給付部分，於上訴人以新台幣伍拾捌萬元為被上訴人\n供擔保後，得假執行。但被上訴人如以新台幣壹佰柒拾貳萬玖仟\n伍佰元為上訴人供擔保，得免為假執行。\n上訴人其餘假執行之聲請駁回。",
    "reason": "一、按當事人於第二審為訴之變更、追加，非經他造同意，不得\n    為之，但請求之基礎事實同一者，不在此限，民事訴訟法第\n    446條第1項及第255條第1項第2款定有明文。本件上訴人在\n    原審係依不當得利之法律關係，請求被上訴人給付新台幣（\n    下同）1,729,500元及自起訴狀繕本送達翌日起至清償日止\n    ，按年息5%計算之利息（見原審卷(二)第2、15至16頁）；嗣\n    於本院審理中，變更主張：被上訴人承諾將所購買之股票返\n    還予上訴人之父盧子欽、母李美金及胞妹盧隨仁（以下合稱\n    盧子欽等3人），上訴人自盧子欽等3人受讓該股票權利，因\n    被上訴人已出售該股票，爰依受讓盧子欽等3人之股票返還\n    請求權，請求被上訴人返還相當於股票價款之金額1,729,50\n    0元，及調解聲請書繕本送達翌日起至清償日止，按年息5%\n    計算之利息（見發回前本院卷第34頁背面，本院更(一)卷第37\n    頁、40頁背面），經核上訴人於本院變更之訴所為請求之基\n    礎事實與原審所為請求之基礎事實同一，依前揭規定，應予\n    准許。合先敘明。\n二、上訴人主張：兩造原為夫妻，被上訴人於民國（下同）88年\n    間稱其得以員工身分向任職之和信電訊股份有限公司（下稱\n    和信電訊公司）承購該公司股票，盧子欽等3人乃匯款共計\n    1,729,500元予被上訴人，委託被上訴人購買和信電訊公司\n    股票（下稱系爭股票），被上訴人承諾購得系爭股票後將予\n    返還。嗣兩造於93年5月4日離婚，被上訴人未返還系爭股票\n    ，盧子欽等3人乃出具「所有權移轉證明書」（下稱系爭移\n    轉證明書），將系爭股票權利移轉予上訴人，惟系爭股票已\n    遭被上訴人全數出售，被上訴人自應返還系爭股票價款，爰\n    依系爭移轉證明書所受讓之權利，請求被上訴人給付上訴人\n    1,729,500元，並加付自調解聲請書送達翌日起之法定遲延\n    利息等語。原審為上訴人敗訴之判決，上訴人不服，於提起\n    上訴後為訴之變更，經發回前本院為上訴人勝訴之判決，被\n    上訴人不服，提起第三審上訴，經最高法院將發回前本院所\n    為上開判決廢棄，並發回本院更為審理，上訴人在本院聲明\n    ：(一)被上訴人應給付上訴人1,729,500元，及自調解聲請書\n    送達翌日起至清償日止，按年息5%計算之利息。(二)願供擔保\n    請准宣告假執行。（上訴人在原審所為其餘請求，經兩造於\n    原審成立訴訟上和解，爰就此部分之主張及陳述不予贅述，\n    附此敘明。）\n三、被上訴人則以：上訴人知悉被上訴人任職之和信電訊公司給\n    予員工認購股份之機會，乃要求盧子欽等3人代為匯款以交\n    由被上訴人認購系爭股票，被上訴人並未承諾返還系爭股票\n    。嗣兩造於93年5月4日協議離婚時，因考慮被上訴人結婚時\n    曾出資超過150萬元以購屋、裝潢及購買傢俱，並將該屋登\n    記在上訴人名下，加上離婚前3年之家庭生活費用皆由被上\n    訴人負擔，另被上訴人又同意於離婚後無條件將停車位過戶\n    予上訴人，故約定以被上訴人名義登記之系爭股票歸被上訴\n    人所有，並於離婚協議書載明，是上訴人所為本件請求，自\n    無理由等語，資為抗辯。被上訴人對於上訴人變更之訴聲明\n    ：(一)變更之訴駁回。(二)如受不利判決，願預供擔保請准宣告\n    免為假執行。\n四、經查兩造於79年12月14日結婚，被上訴人於88年間任職和信\n    電訊公司，得以員工身分承購該公司股票（未上市、上櫃）\n    ，上訴人之胞妹盧隨仁於88年5月27日匯款37萬元、上訴人\n    之父盧子欽於88年5月28日及同年月31日分別存款698,900元\n    及43萬元、上訴人之母李美金於88年5月31日匯款230,600元\n    至被上訴人設於台灣銀行之帳戶，共計1,729,500元，委託\n    被上訴人購買系爭股票，被上訴人購得後未交付所購得之系\n    爭股票予盧子欽等3人，嗣並自行出售系爭股票，兩造則於\n    93年5月4日協議離婚等情，有戶籍謄本、台灣銀行存入憑條\n    、合作金庫匯款回條聯、台灣銀行無摺存入憑條存根、台灣\n    銀行光碟櫃歷史明細查詢系統、臺灣銀行館前分行98年6月8\n    日館前存字第09800019331號函及亞東證券股份有限公司99\n    年1月18日亞證字第9909900024號函可稽（見原審卷(一)第19\n    至21、209至211、255、256、267至269頁，卷(二)第8頁，本\n    院更(一)卷第15頁），且為兩造所不爭執，均堪信為真實。\n五、上訴人主張被上訴人承諾於購得系爭股票後將返還股票予盧\n    子欽3等人，盧子欽等3人已將系爭股票權利讓與上訴人，因\n    被上訴人將系爭股票全數賣出，被上訴人自應返還相當於系\n    爭股票價款1,729,500元等語；惟為被上訴人所否認，並以\n    前詞置辯。經查：\n  (一)據證人李美金在原審到場證稱：「我所知道的當時吳小姐（\n    指被上訴人）回到我們家，因為我們是分開住，回到我家跟\n    我說以她當時的位置可以認購300張，她那時的職位我不清\n    楚，然後說她的錢只能買多少，還不夠，問我和我先生（指\n    盧子欽）要不要買，我那時候想就拿了23萬左右來買，我先\n    生拿了100多萬，我們用我們的帳戶分開匯到她的帳戶，我\n    們當時所了解的她要把她不能認購的部分讓我們來買，所以\n    我才願意，當時一定要用她的名字買，因為她在那裡工作，\n    …我們的理解是吳小姐不夠的部分不能認購的部分由我來買\n    ，實際總數我不太清楚，我是從台北銀行匯的，我先生是用\n    哪個銀行帳戶匯的我不清楚，我們不是借她錢，是我們要買\n    ，但只能用她的名義，後來我們一直不過問，因為自己人相\n    信她」，「（系爭股票）是為我自己買的，吳小姐從未跟我\n    提過股票的事，離婚前我有跟她催討過，但她就跟我說沒有\n    了，但沒有了是指什麼意思我不知道，我也不曉得和信電信\n    還在不在」，「我一直在強調就是，當時匯這錢主要的目的\n    是我要用她的名義，買我的股票，我先生也是這樣的意思，\n    我不是要借她」，「盧隨仁是我的女兒，她有寄錢給我，存\n    在我們戶頭」，「（當初買系爭股票是要）投資，因為我們\n    認為將來上市的話一定會賺錢，所以我們才願意，因為那時\n    候吳小姐說，這個不錯，她還有幾張，所以我們才願意買」\n    等語（見原審卷(一)第246至248、251頁）。而被上訴人亦自\n    承：「錢是原告（指上訴人）父親匯進來的，所以我認為（\n    系爭股票）是爸爸（指盧子欽）、媽媽（指李美金）的，雖\n    然有妹妹（指盧隨仁）的名字，但我都是跟媽媽在討論，我\n    的確拿了錢，也幫他們買了股票」，「當時沒有（向盧子欽\n    等3人借錢），是他們的（錢），只是用我的名字（買系爭\n    股票）」等語（見原審卷(一)第249頁）。足證盧子欽等3人係\n    欲利用被上訴人工作上之機會認購系爭股票，而與被上訴人\n    合意由盧子欽等3人出資，以被上訴人之名義購買系爭股票\n    ，是盧子欽等3人自得請求被上訴人返還所購得之系爭股票\n    。\n  (二)被上訴人雖抗辯其出資超過150萬元所購得之房屋登記在上\n    訴人名下，且負擔離婚前3年之家庭生活費用，又同意於離\n    婚後無條件將停車位過戶予上訴人，故兩造於離婚協議書約\n    明「雙方於婚姻關係存續中名下之財產各自擁有」，是系爭\n    股票應歸被上訴人所有等語；惟為上訴人所否認。經查：\n  1.兩造於93年5月4日所簽署離婚協議書關於兩造財產分配固約\n    定：「…(2)男（指上訴人）、女（指被上訴人）雙方於婚姻\n    關係存續中名下之財產各自擁有。(3)男、女雙方於婚姻關係\n    存續中，如在外有發生任何一切債務，各自清償，與他方無\n    涉。(4)女方名下之不動產坐落於內湖區歡樂頌社區內之地下\n    二層41號之停車位，女方同意離婚登記後無條件給予（過戶\n    ）男方」（見原審卷(一)第55至56頁），然此約定係就兩造於\n    婚姻關係存續中所取得之積極財產及消極財產進行分配，而\n    系爭股票係由盧子欽等3人出資及借用被上訴人之名義購得\n    ，實際上應歸盧子欽等3人所有，且上訴人於兩造簽訂離婚\n    協議書時並非系爭股票之權利人，衡情自無可能將系爭股票\n    列為兩造之財產而進行分配。\n  2.上訴人固曾於原審陳稱：系爭股票是爺爺奶奶要給小孩讀書\n    基金，所以匯款讓被上訴人購買股票，可以支付小孩以後費\n    用等語（原審卷(一)第23頁背面）。然查縱認盧子欽等3人借\n    用被上訴人之名義購買系爭股票，係欲供作兩造子女將來教\n    育基金之用，惟亦不能執此即謂盧子欽等3人有將系爭股票\n    贈與兩造之意，是尚不能僅憑上訴人之上開陳述，即認系爭\n    股票於兩造簽訂離婚協議書時，係歸屬於上訴人或被上訴人\n    所有，而於離婚協議時列入兩造之財產進行分配。\n  (三)被上訴人雖又抗辯其於兩造離婚當日已獲李美金同意而取得\n    系爭股票等語，惟亦為上訴人所否認。查證人李美金證稱：\n    「沒有此事。她（指被上訴人）離婚當天有打電話給我，但\n    不是提股票，是說要離婚的事，我沒有說要把股票給她」，\n    「那個時候因為他們是很急的情況下辦離婚，一時也沒有想\n    到那麼多，做父母總是不希望走到這個地步，當時聽說見證\n    人也是吳小姐找的，在這情況下我也忘記什麼事應該要趕快\n    提，所以那時沒有提（股票的事）」，「我確認沒有（說要\n    把系爭股票給被上訴人），不可能」等語（見原審卷第249\n    、251頁），已否認曾同意將系爭股票歸由被上訴人所有；\n    況購買系爭股票之資金1,729,500元，其中100餘萬元為盧子\n    欽所出資，37萬元為盧隨仁出資，李美金僅出資約23萬元，\n    ，衡情李美金焉有可能未經與盧子欽及盧隨仁商討，即在電\n    話中答應被上訴人要求，而同意系爭股票全部歸由被上訴人\n    所有。此外，被上訴人亦無法提出其他確切之證據以實其說\n    ，是被上訴人所為此部分抗辯，亦不足取。\n  (四)上訴人主張其已自盧子欽等3人受讓系爭股票權利，因系爭\n    股票已遭被上訴人出售，被上訴人自應返還相當於系爭股票\n    之價款1,729,500元等語，並提出系爭移轉證明書為證（原\n    審卷(一)第215頁），惟亦為被上訴人所否認。經查：\n  1.依系爭移轉證明書記載：「本人所有但寄放於吳麗蓉(即被\n    上訴人)名下和信電訊股票已於2005年至2007（年）間轉讓\n    予盧辰祥所有」，其上並蓋有盧子欽等3人之印章（見原審\n    卷(一)第215頁）。被上訴人雖否認系爭移轉證明書為真正，\n    惟查系爭移轉證明書固未記載出具證明書之日期，惟上訴人\n    係於97年10月13日在原審提出（見原審卷(一)第213、215頁）\n    ，當時盧子欽尚未死亡（按盧子欽係於98年10月15日死亡－\n    見發回前本院卷第9頁）。又據證人李美金在原審到場證稱\n    ：「（系爭移轉證明書）是我和我先生寫的沒錯」，「大約\n    是（西元）2005年到2007（年）中間（出具系爭移轉證明書\n    ），是他們分開後，我想把這移轉給我兒子（指上訴人）在\n    處理比較合適」，「所有權移轉證明書上面確實是我先生（\n    指盧子欽）和我女兒（指盧隨仁）的印章」，「（系爭移轉\n    證明書）是在他們離婚後（出具的）」等語（見原審卷(一)第\n    247、248、250頁）；復據上訴人提出訴外人盧隨仁請求公\n    證之公證書內載：「授權人（即盧隨仁）授權李美金處理將\n    其名下但寄放於吳麗蓉處之和信電訊股票轉讓予盧辰祥之一\n    切相關事宜，包含但不限於簽署文件、於所有權移轉證明書\n    （即系爭移轉證明書）上用印、辦理相關手續等；授權人並\n    授權李美金承認其於民國94年1月1日起至簽署本授權書之日\n    就前述和信電訊股票轉讓予盧辰祥所為之一切相關事宜，包\n    含但不限於簽署文件、於所有權移轉證明書（即系爭移轉證\n    明書）上用印、辦理相關手續等」（見發回前本院卷第72頁\n    ），由此足證系爭移轉證明書係屬真正。\n  2.於盧子欽死亡後，上訴人固在發回前本院陳稱其係以繼承人\n    之身份請求被上訴人返還系爭股票及股息（見發回前本院卷\n    第17頁背面），並將盧子欽匯予被上訴人購買系爭股票之款\n    項列入盧子欽之遺產申報遺產稅（見發回前本院卷第48頁）\n    ，惟上訴人亦陳明：盧子欽等3人將系爭股票之權利移轉予\n    上訴人，由上訴人向被上訴人請求，上訴人亦承諾於被上訴\n    人返還系爭股票後將再移轉予盧子欽等3人等語（見發回前\n    本院卷第20頁背面、23、48、68頁背面），並提出意願書為\n    證（見發回前本院卷第24頁）。堪認上訴人係基於上開返還\n    股票之承諾，而將應返還予盧子欽之股款部分列為遺產而據\n    以申報遺產稅，是尚不能執此即謂系爭移轉證明書所載內容\n    非屬真正。\n  3.被上訴人自承將盧子欽等3人所交付之1,729,500元全數購買\n    系爭股票計150張（見原審卷(一)第191、236、248、253頁，\n    卷(二)第5頁，發回前本院卷第33頁背面、62頁背面，本院更\n    (一)卷第40頁背面），而上開股票僅係盧子欽等3人借用被上\n    訴人之名義所購買，已如前述，是被上訴人原應將系爭股票\n    返還予盧子欽等3人，然盧子欽等3人已將系爭股票之權利移\n    轉予上訴人，亦如前述，是上訴人自得請求被上訴人返還系\n    爭股票。惟查被上訴人業將系爭股票全數出售，此亦為被上\n    訴人所不爭執；而系爭股票係未上市、上櫃股票，其發行公\n    司和信電訊公司已於92年間由遠傳電信股份有限公司併購，\n    此有網路資訊及亞東證券股份有限公司99年1月18日亞證字\n    第9909900024號函可稽（見原審卷(一)第257頁、發回前本院\n    卷第28頁），且為兩造所不爭，是被上訴人已無可能自證券\n    交易市場取得和信電訊公司之股票以返還上訴人。又被上訴\n    人陳明：其就出售系爭股票所得金額已不復記憶（見發回前\n    本院卷第34頁、本院更(一)卷第40頁背面）；系爭股票已經出\n    售，如應返還，即應返還上訴人所主張之1,729,500元等語\n    （見發回前本院卷第63頁），是上訴人據以請求被上訴人給\n    付1,729,500元，自屬有據，應予准許。\n  4.按給付無確定期限者，債務人於債權人得請求給付時，經其\n    催告而未為給付，自受催告時起，負遲延責任；其經債權人\n    起訴而送達訴狀，或依督促程序送達支付命令，或為其他相\n    類之行為者，與催告有同一之效力；又債務人遲延者，債權\n    人得請求其賠償因遲延而生之損害；遲延之債務，以支付金\n    錢為標的者，債權人得請求依法定利率計算之遲延利息，民\n    法第229條第2項、第231條第1項及第233條第1項本文分別定\n    有明文。查上訴人係於99年2月8日發回前本院準備程序時當\n    庭為訴之變更而向被上訴人請求（見發回前本院卷第34頁背\n    面），被上訴人亦於當日到場（見同卷第32頁），依前揭規\n    定，被上訴人就本件請求自99年2月9日起負遲延責任，是上\n    訴人得請求被上訴人給付自是日起按法定利率計算之利息。\n六、綜上所述，上訴人請求被上訴人給付1,729,500元，及自99\n    年2月9日起至清償日止，按年息5%計算之利息，為有理由，\n    應予准許；其逾此範圍所為請求為無理由，應予駁回。又就\n    上訴人勝訴部分，兩造均陳明願供擔保宣告准免假執行，經\n    核均無不合，爰分別酌定相當擔保金額准許之；至上訴人敗\n    訴部分，上訴人所為假執行之聲請即失所附麗，應併予駁回\n    。\n七、兩造其餘之攻擊或防禦方法及未經援用之證據，經本院斟酌\n    後，認為均不足以影響本判決之結果，自無予以調查或逐一\n    詳予論駁之必要。附此敘明。\n八、據上論結，本件變更之訴為一部有理由，一部無理由，依民\n    事訴訟法第463條、第390條第2項、第392條、第79條，判決\n    如主文。"
  },
  "search": "臺灣高等法院民事判決100年度家上更(一)字第2號上訴人盧辰祥被上訴人吳為漪（原名吳映黎）訴訟代理人楊久弘律師上列當事人間請求返還股票價款等事件，上訴人對於中華民國98年10月26日臺灣臺北地方法院97年度家訴字第79號第一審判決提起上訴後，於本院為訴之變更，經判決後，由最高法院第1次發回更審，本院於100年5月31日言詞辯論終結，判決如下：主文被上訴人應給付上訴人新台幣壹佰柒拾貳萬玖仟伍佰元，及自民國九十九年二月九日起至清償日止按年息百分之五計算之利息。上訴人其餘變更之訴駁回。變更之訴及發回前第三審訴訟費用，由被上訴人負擔。本判決所命給付部分，於上訴人以新台幣伍拾捌萬元為被上訴人供擔保後，得假執行。但被上訴人如以新台幣壹佰柒拾貳萬玖仟伍佰元為上訴人供擔保，得免為假執行。上訴人其餘假執行之聲請駁回。理由一、按當事人於第二審為訴之變更、追加，非經他造同意，不得為之，但請求之基礎事實同一者，不在此限，民事訴訟法第446條第1項及第255條第1項第2款定有明文。本件上訴人在原審係依不當得利之法律關係，請求被上訴人給付新台幣（下同）1,729,500元及自起訴狀繕本送達翌日起至清償日止，按年息5%計算之利息（見原審卷(二)第2、15至16頁）；嗣於本院審理中，變更主張：被上訴人承諾將所購買之股票返還予上訴人之父盧子欽、母李美金及胞妹盧隨仁（以下合稱盧子欽等3人），上訴人自盧子欽等3人受讓該股票權利，因被上訴人已出售該股票，爰依受讓盧子欽等3人之股票返還請求權，請求被上訴人返還相當於股票價款之金額1,729,500元，及調解聲請書繕本送達翌日起至清償日止，按年息5%計算之利息（見發回前本院卷第34頁背面，本院更(一)卷第37頁、40頁背面），經核上訴人於本院變更之訴所為請求之基礎事實與原審所為請求之基礎事實同一，依前揭規定，應予准許。合先敘明。二、上訴人主張：兩造原為夫妻，被上訴人於民國（下同）88年間稱其得以員工身分向任職之和信電訊股份有限公司（下稱和信電訊公司）承購該公司股票，盧子欽等3人乃匯款共計1,729,500元予被上訴人，委託被上訴人購買和信電訊公司股票（下稱系爭股票），被上訴人承諾購得系爭股票後將予返還。嗣兩造於93年5月4日離婚，被上訴人未返還系爭股票，盧子欽等3人乃出具「所有權移轉證明書」（下稱系爭移轉證明書），將系爭股票權利移轉予上訴人，惟系爭股票已遭被上訴人全數出售，被上訴人自應返還系爭股票價款，爰依系爭移轉證明書所受讓之權利，請求被上訴人給付上訴人1,729,500元，並加付自調解聲請書送達翌日起之法定遲延利息等語。原審為上訴人敗訴之判決，上訴人不服，於提起上訴後為訴之變更，經發回前本院為上訴人勝訴之判決，被上訴人不服，提起第三審上訴，經最高法院將發回前本院所為上開判決廢棄，並發回本院更為審理，上訴人在本院聲明：(一)被上訴人應給付上訴人1,729,500元，及自調解聲請書送達翌日起至清償日止，按年息5%計算之利息。(二)願供擔保請准宣告假執行。（上訴人在原審所為其餘請求，經兩造於原審成立訴訟上和解，爰就此部分之主張及陳述不予贅述，附此敘明。）三、被上訴人則以：上訴人知悉被上訴人任職之和信電訊公司給予員工認購股份之機會，乃要求盧子欽等3人代為匯款以交由被上訴人認購系爭股票，被上訴人並未承諾返還系爭股票。嗣兩造於93年5月4日協議離婚時，因考慮被上訴人結婚時曾出資超過150萬元以購屋、裝潢及購買傢俱，並將該屋登記在上訴人名下，加上離婚前3年之家庭生活費用皆由被上訴人負擔，另被上訴人又同意於離婚後無條件將停車位過戶予上訴人，故約定以被上訴人名義登記之系爭股票歸被上訴人所有，並於離婚協議書載明，是上訴人所為本件請求，自無理由等語，資為抗辯。被上訴人對於上訴人變更之訴聲明：(一)變更之訴駁回。(二)如受不利判決，願預供擔保請准宣告免為假執行。四、經查兩造於79年12月14日結婚，被上訴人於88年間任職和信電訊公司，得以員工身分承購該公司股票（未上市、上櫃），上訴人之胞妹盧隨仁於88年5月27日匯款37萬元、上訴人之父盧子欽於88年5月28日及同年月31日分別存款698,900元及43萬元、上訴人之母李美金於88年5月31日匯款230,600元至被上訴人設於台灣銀行之帳戶，共計1,729,500元，委託被上訴人購買系爭股票，被上訴人購得後未交付所購得之系爭股票予盧子欽等3人，嗣並自行出售系爭股票，兩造則於93年5月4日協議離婚等情，有戶籍謄本、台灣銀行存入憑條、合作金庫匯款回條聯、台灣銀行無摺存入憑條存根、台灣銀行光碟櫃歷史明細查詢系統、臺灣銀行館前分行98年6月8日館前存字第09800019331號函及亞東證券股份有限公司99年1月18日亞證字第9909900024號函可稽（見原審卷(一)第19至21、209至211、255、256、267至269頁，卷(二)第8頁，本院更(一)卷第15頁），且為兩造所不爭執，均堪信為真實。五、上訴人主張被上訴人承諾於購得系爭股票後將返還股票予盧子欽3等人，盧子欽等3人已將系爭股票權利讓與上訴人，因被上訴人將系爭股票全數賣出，被上訴人自應返還相當於系爭股票價款1,729,500元等語；惟為被上訴人所否認，並以前詞置辯。經查：(一)據證人李美金在原審到場證稱：「我所知道的當時吳小姐（指被上訴人）回到我們家，因為我們是分開住，回到我家跟我說以她當時的位置可以認購300張，她那時的職位我不清楚，然後說她的錢只能買多少，還不夠，問我和我先生（指盧子欽）要不要買，我那時候想就拿了23萬左右來買，我先生拿了100多萬，我們用我們的帳戶分開匯到她的帳戶，我們當時所了解的她要把她不能認購的部分讓我們來買，所以我才願意，當時一定要用她的名字買，因為她在那裡工作，…我們的理解是吳小姐不夠的部分不能認購的部分由我來買，實際總數我不太清楚，我是從台北銀行匯的，我先生是用哪個銀行帳戶匯的我不清楚，我們不是借她錢，是我們要買，但只能用她的名義，後來我們一直不過問，因為自己人相信她」，「（系爭股票）是為我自己買的，吳小姐從未跟我提過股票的事，離婚前我有跟她催討過，但她就跟我說沒有了，但沒有了是指什麼意思我不知道，我也不曉得和信電信還在不在」，「我一直在強調就是，當時匯這錢主要的目的是我要用她的名義，買我的股票，我先生也是這樣的意思，我不是要借她」，「盧隨仁是我的女兒，她有寄錢給我，存在我們戶頭」，「（當初買系爭股票是要）投資，因為我們認為將來上市的話一定會賺錢，所以我們才願意，因為那時候吳小姐說，這個不錯，她還有幾張，所以我們才願意買」等語（見原審卷(一)第246至248、251頁）。而被上訴人亦自承：「錢是原告（指上訴人）父親匯進來的，所以我認為（系爭股票）是爸爸（指盧子欽）、媽媽（指李美金）的，雖然有妹妹（指盧隨仁）的名字，但我都是跟媽媽在討論，我的確拿了錢，也幫他們買了股票」，「當時沒有（向盧子欽等3人借錢），是他們的（錢），只是用我的名字（買系爭股票）」等語（見原審卷(一)第249頁）。足證盧子欽等3人係欲利用被上訴人工作上之機會認購系爭股票，而與被上訴人合意由盧子欽等3人出資，以被上訴人之名義購買系爭股票，是盧子欽等3人自得請求被上訴人返還所購得之系爭股票。(二)被上訴人雖抗辯其出資超過150萬元所購得之房屋登記在上訴人名下，且負擔離婚前3年之家庭生活費用，又同意於離婚後無條件將停車位過戶予上訴人，故兩造於離婚協議書約明「雙方於婚姻關係存續中名下之財產各自擁有」，是系爭股票應歸被上訴人所有等語；惟為上訴人所否認。經查：1.兩造於93年5月4日所簽署離婚協議書關於兩造財產分配固約定：「…(2)男（指上訴人）、女（指被上訴人）雙方於婚姻關係存續中名下之財產各自擁有。(3)男、女雙方於婚姻關係存續中，如在外有發生任何一切債務，各自清償，與他方無涉。(4)女方名下之不動產坐落於內湖區歡樂頌社區內之地下二層41號之停車位，女方同意離婚登記後無條件給予（過戶）男方」（見原審卷(一)第55至56頁），然此約定係就兩造於婚姻關係存續中所取得之積極財產及消極財產進行分配，而系爭股票係由盧子欽等3人出資及借用被上訴人之名義購得，實際上應歸盧子欽等3人所有，且上訴人於兩造簽訂離婚協議書時並非系爭股票之權利人，衡情自無可能將系爭股票列為兩造之財產而進行分配。2.上訴人固曾於原審陳稱：系爭股票是爺爺奶奶要給小孩讀書基金，所以匯款讓被上訴人購買股票，可以支付小孩以後費用等語（原審卷(一)第23頁背面）。然查縱認盧子欽等3人借用被上訴人之名義購買系爭股票，係欲供作兩造子女將來教育基金之用，惟亦不能執此即謂盧子欽等3人有將系爭股票贈與兩造之意，是尚不能僅憑上訴人之上開陳述，即認系爭股票於兩造簽訂離婚協議書時，係歸屬於上訴人或被上訴人所有，而於離婚協議時列入兩造之財產進行分配。(三)被上訴人雖又抗辯其於兩造離婚當日已獲李美金同意而取得系爭股票等語，惟亦為上訴人所否認。查證人李美金證稱：「沒有此事。她（指被上訴人）離婚當天有打電話給我，但不是提股票，是說要離婚的事，我沒有說要把股票給她」，「那個時候因為他們是很急的情況下辦離婚，一時也沒有想到那麼多，做父母總是不希望走到這個地步，當時聽說見證人也是吳小姐找的，在這情況下我也忘記什麼事應該要趕快提，所以那時沒有提（股票的事）」，「我確認沒有（說要把系爭股票給被上訴人），不可能」等語（見原審卷第249、251頁），已否認曾同意將系爭股票歸由被上訴人所有；況購買系爭股票之資金1,729,500元，其中100餘萬元為盧子欽所出資，37萬元為盧隨仁出資，李美金僅出資約23萬元，，衡情李美金焉有可能未經與盧子欽及盧隨仁商討，即在電話中答應被上訴人要求，而同意系爭股票全部歸由被上訴人所有。此外，被上訴人亦無法提出其他確切之證據以實其說，是被上訴人所為此部分抗辯，亦不足取。(四)上訴人主張其已自盧子欽等3人受讓系爭股票權利，因系爭股票已遭被上訴人出售，被上訴人自應返還相當於系爭股票之價款1,729,500元等語，並提出系爭移轉證明書為證（原審卷(一)第215頁），惟亦為被上訴人所否認。經查：1.依系爭移轉證明書記載：「本人所有但寄放於吳麗蓉(即被上訴人)名下和信電訊股票已於2005年至2007（年）間轉讓予盧辰祥所有」，其上並蓋有盧子欽等3人之印章（見原審卷(一)第215頁）。被上訴人雖否認系爭移轉證明書為真正，惟查系爭移轉證明書固未記載出具證明書之日期，惟上訴人係於97年10月13日在原審提出（見原審卷(一)第213、215頁），當時盧子欽尚未死亡（按盧子欽係於98年10月15日死亡－見發回前本院卷第9頁）。又據證人李美金在原審到場證稱：「（系爭移轉證明書）是我和我先生寫的沒錯」，「大約是（西元）2005年到2007（年）中間（出具系爭移轉證明書），是他們分開後，我想把這移轉給我兒子（指上訴人）在處理比較合適」，「所有權移轉證明書上面確實是我先生（指盧子欽）和我女兒（指盧隨仁）的印章」，「（系爭移轉證明書）是在他們離婚後（出具的）」等語（見原審卷(一)第247、248、250頁）；復據上訴人提出訴外人盧隨仁請求公證之公證書內載：「授權人（即盧隨仁）授權李美金處理將其名下但寄放於吳麗蓉處之和信電訊股票轉讓予盧辰祥之一切相關事宜，包含但不限於簽署文件、於所有權移轉證明書（即系爭移轉證明書）上用印、辦理相關手續等；授權人並授權李美金承認其於民國94年1月1日起至簽署本授權書之日就前述和信電訊股票轉讓予盧辰祥所為之一切相關事宜，包含但不限於簽署文件、於所有權移轉證明書（即系爭移轉證明書）上用印、辦理相關手續等」（見發回前本院卷第72頁），由此足證系爭移轉證明書係屬真正。2.於盧子欽死亡後，上訴人固在發回前本院陳稱其係以繼承人之身份請求被上訴人返還系爭股票及股息（見發回前本院卷第17頁背面），並將盧子欽匯予被上訴人購買系爭股票之款項列入盧子欽之遺產申報遺產稅（見發回前本院卷第48頁），惟上訴人亦陳明：盧子欽等3人將系爭股票之權利移轉予上訴人，由上訴人向被上訴人請求，上訴人亦承諾於被上訴人返還系爭股票後將再移轉予盧子欽等3人等語（見發回前本院卷第20頁背面、23、48、68頁背面），並提出意願書為證（見發回前本院卷第24頁）。堪認上訴人係基於上開返還股票之承諾，而將應返還予盧子欽之股款部分列為遺產而據以申報遺產稅，是尚不能執此即謂系爭移轉證明書所載內容非屬真正。3.被上訴人自承將盧子欽等3人所交付之1,729,500元全數購買系爭股票計150張（見原審卷(一)第191、236、248、253頁，卷(二)第5頁，發回前本院卷第33頁背面、62頁背面，本院更(一)卷第40頁背面），而上開股票僅係盧子欽等3人借用被上訴人之名義所購買，已如前述，是被上訴人原應將系爭股票返還予盧子欽等3人，然盧子欽等3人已將系爭股票之權利移轉予上訴人，亦如前述，是上訴人自得請求被上訴人返還系爭股票。惟查被上訴人業將系爭股票全數出售，此亦為被上訴人所不爭執；而系爭股票係未上市、上櫃股票，其發行公司和信電訊公司已於92年間由遠傳電信股份有限公司併購，此有網路資訊及亞東證券股份有限公司99年1月18日亞證字第9909900024號函可稽（見原審卷(一)第257頁、發回前本院卷第28頁），且為兩造所不爭，是被上訴人已無可能自證券交易市場取得和信電訊公司之股票以返還上訴人。又被上訴人陳明：其就出售系爭股票所得金額已不復記憶（見發回前本院卷第34頁、本院更(一)卷第40頁背面）；系爭股票已經出售，如應返還，即應返還上訴人所主張之1,729,500元等語（見發回前本院卷第63頁），是上訴人據以請求被上訴人給付1,729,500元，自屬有據，應予准許。4.按給付無確定期限者，債務人於債權人得請求給付時，經其催告而未為給付，自受催告時起，負遲延責任；其經債權人起訴而送達訴狀，或依督促程序送達支付命令，或為其他相類之行為者，與催告有同一之效力；又債務人遲延者，債權人得請求其賠償因遲延而生之損害；遲延之債務，以支付金錢為標的者，債權人得請求依法定利率計算之遲延利息，民法第229條第2項、第231條第1項及第233條第1項本文分別定有明文。查上訴人係於99年2月8日發回前本院準備程序時當庭為訴之變更而向被上訴人請求（見發回前本院卷第34頁背面），被上訴人亦於當日到場（見同卷第32頁），依前揭規定，被上訴人就本件請求自99年2月9日起負遲延責任，是上訴人得請求被上訴人給付自是日起按法定利率計算之利息。六、綜上所述，上訴人請求被上訴人給付1,729,500元，及自99年2月9日起至清償日止，按年息5%計算之利息，為有理由，應予准許；其逾此範圍所為請求為無理由，應予駁回。又就上訴人勝訴部分，兩造均陳明願供擔保宣告准免假執行，經核均無不合，爰分別酌定相當擔保金額准許之；至上訴人敗訴部分，上訴人所為假執行之聲請即失所附麗，應併予駁回。七、兩造其餘之攻擊或防禦方法及未經援用之證據，經本院斟酌後，認為均不足以影響本判決之結果，自無予以調查或逐一詳予論駁之必要。附此敘明。八、據上論結，本件變更之訴為一部有理由，一部無理由，依民事訴訟法第463條、第390條第2項、第392條、第79條，判決如主文。中華民國100年6月28日民事第四庭審判長法官張劍男法官陳靜芬法官彭昭芬正本係照原本作成。如不服本判決，應於收受送達後20日內向本院提出上訴書狀，其未表明上訴理由者，應於提出上訴後20日內向本院補提理由書狀（均須按他造當事人之人數附繕本）上訴時應提出委任律師或具有律師資格之人之委任狀；委任有律師資格者，另應附具律師資格證書及釋明委任人與受任人有民事訴訟法第466條之1第1項但書或第2項（詳附註）所定關係之釋明文書影本。中華民國100年6月28日書記官丁華平附註：民事訴訟法第466條之1（第1項、第2項）：對於第二審判決上訴，上訴人應委任律師為訴訟代理人。但上訴人或其他法定代理人具有律師資格者，不在此限。上訴人之配偶、三親等內之血親、二親等內之姻親，或上訴人為法人、中央或地方機關時，其所屬專任人員具有律師資格並經法院認為適當者，亦得為第三審訴訟代理人。",
  "characters": {
    "judges": [
      "張劍男",
      "陳靜芬",
      "彭昭芬"
    ],
    "prosecutors": [

    ],
    "lawyers": [
      "楊久弘",
      "有",
      "人或其他法定代理人具有"
    ],
    "clerks": [
      "丁華平"
    ],
    "plaintiffs": [

    ],
    "defendants": [

    ],
    "prosecutor_office": [

    ],
    "creditors": [

    ],
    "debtors": [

    ],
    "judicial_associate_officer": [

    ]
  },
  "adjudged_at": "2011-06-28",
  "created_at": "2016-02-13 16:27:57",
  "updated_at": "2016-02-13 16:27:57"
}