{
  "identify": "TYD-100-簡-149-20110628-1",
  "court": {
    "name": "臺灣桃園地方法院",
    "code": "TYD"
  },
  "division": {
    "name": "刑事",
    "code": "M"
  },
  "year": 100,
  "word": "簡",
  "number": "149",
  "jcheck": "1",
  "reason": "竊盜",
  "content": "臺灣桃園地方法院刑事簡易判決          100年度簡字第149號\n公  訴  人  臺灣桃園地方法院檢察署檢察官\n被      告  李友銓\n上列被告因竊盜案件，經檢察官提起公訴（100年度偵字第15111\n號），被告自白犯罪，本院認宜以簡易判決處刑，判決如下：\n    主  文\n李友銓竊盜，累犯，處有期徒刑肆月，如易科罰金，以新臺幣壹\n仟元折算壹日。\n    事實及理由\n一、本件除(一)事實部分第1 至3 行更正為：「李友銓前因竊盜等\n    案件，經本院以98年度易字第434 號判決判處有期徒刑2 月\n    ，共6 罪，定應執行有期徒刑10月確定；又因詐欺案件，經\n    本院以99年度桃簡字第148 號判決判處有期徒刑4 月確定；\n    上開案件嗣經本院以99年度聲字第3090號裁定定應執行有期\n    徒刑1 年1 月確定。李友銓就竊盜案件先於民國98年6 月25\n    日入監服刑，並於99年1 月16日縮刑期滿，同年月17日出監\n    ；嗣又於99年12月16日入監服刑，並於100 年2 月25日易科\n    罰金執行完畢出監」；(二)證據部分補充：被告李友銓於本院\n    訊問時自白犯行（見本院易字卷第7 頁背面）；(三)其餘犯罪\n    事實、證據均引用檢察官起訴書所載（如附件）。\n二、核被告李友銓所為，係犯刑法第320 條第1 項之普通竊盜罪\n    。被告曾受事實欄所載之徒刑執行完畢，此有臺灣高等法院\n    被告前案紀錄表1 份供參，其受徒刑之執行完畢，於5 年內\n    故意再犯本件有期徒刑以上之罪，為累犯，應依刑法第47條\n    第1 項規定，加重其刑。爰審酌被告之犯罪動機、手段、竊\n    得財物價值，及犯後坦承犯行，態度良好等一切情狀，量處\n    如主文所示之刑，並諭知易科罰金之折算標準，以示儆懲。\n三、依刑事訴訟法第449 條第2 項、第454 條第2 項，刑法第32\n    0 條第1 項、第47條第1 項、第41條第1 項前段，刑法施行\n    法第1條 之1 第1 項、第2 項前段，逕以簡易判決處刑如主\n    文。\n四、如不服本判決，應於判決送達後10日內，向本院提出上訴狀\n    。\n中    華    民    國   100    年    6     月    28    日\n                  刑事第四庭    法  官  林宜靜\n以上正本證明與原本無異。\n如不服本判決，應於判決送達後10日內向本院提出上訴狀（應附\n繕本）。\n                                書記官  王明玉\n中    華    民    國   100    年    7     月    1     日\n附錄論罪科刑法條\n中華民國刑法第320條\n（普通竊盜罪、竊佔罪）\n意圖為自己或第三人不法之所有，而竊取他人之動產者，為竊盜\n罪，處5  年以下有期徒刑、拘役或 5 百元以下罰金。\n意圖為自己或第三人不法之利益，而竊佔他人之不動產者，依前\n項之規定處斷。\n前二項之未遂犯罰之。",
  "structure": {
    "main": "李友銓竊盜，累犯，處有期徒刑肆月，如易科罰金，以新臺幣壹\n仟元折算壹日。",
    "fact": "一、本件除(一)事實部分第1 至3 行更正為：「李友銓前因竊盜等\n    案件，經本院以98年度易字第434 號判決判處有期徒刑2 月\n    ，共6 罪，定應執行有期徒刑10月確定；又因詐欺案件，經\n    本院以99年度桃簡字第148 號判決判處有期徒刑4 月確定；\n    上開案件嗣經本院以99年度聲字第3090號裁定定應執行有期\n    徒刑1 年1 月確定。李友銓就竊盜案件先於民國98年6 月25\n    日入監服刑，並於99年1 月16日縮刑期滿，同年月17日出監\n    ；嗣又於99年12月16日入監服刑，並於100 年2 月25日易科\n    罰金執行完畢出監」；(二)證據部分補充：被告李友銓於本院\n    訊問時自白犯行（見本院易字卷第7 頁背面）；(三)其餘犯罪\n    事實、證據均引用檢察官起訴書所載（如附件）。\n二、核被告李友銓所為，係犯刑法第320 條第1 項之普通竊盜罪\n    。被告曾受事實欄所載之徒刑執行完畢，此有臺灣高等法院\n    被告前案紀錄表1 份供參，其受徒刑之執行完畢，於5 年內\n    故意再犯本件有期徒刑以上之罪，為累犯，應依刑法第47條\n    第1 項規定，加重其刑。爰審酌被告之犯罪動機、手段、竊\n    得財物價值，及犯後坦承犯行，態度良好等一切情狀，量處\n    如主文所示之刑，並諭知易科罰金之折算標準，以示儆懲。\n三、依刑事訴訟法第449 條第2 項、第454 條第2 項，刑法第32\n    0 條第1 項、第47條第1 項、第41條第1 項前段，刑法施行\n    法第1條 之1 第1 項、第2 項前段，逕以簡易判決處刑如主\n    文。\n四、如不服本判決，應於判決送達後10日內，向本院提出上訴狀\n    。",
    "reason": "一、本件除(一)事實部分第1 至3 行更正為：「李友銓前因竊盜等\n    案件，經本院以98年度易字第434 號判決判處有期徒刑2 月\n    ，共6 罪，定應執行有期徒刑10月確定；又因詐欺案件，經\n    本院以99年度桃簡字第148 號判決判處有期徒刑4 月確定；\n    上開案件嗣經本院以99年度聲字第3090號裁定定應執行有期\n    徒刑1 年1 月確定。李友銓就竊盜案件先於民國98年6 月25\n    日入監服刑，並於99年1 月16日縮刑期滿，同年月17日出監\n    ；嗣又於99年12月16日入監服刑，並於100 年2 月25日易科\n    罰金執行完畢出監」；(二)證據部分補充：被告李友銓於本院\n    訊問時自白犯行（見本院易字卷第7 頁背面）；(三)其餘犯罪\n    事實、證據均引用檢察官起訴書所載（如附件）。\n二、核被告李友銓所為，係犯刑法第320 條第1 項之普通竊盜罪\n    。被告曾受事實欄所載之徒刑執行完畢，此有臺灣高等法院\n    被告前案紀錄表1 份供參，其受徒刑之執行完畢，於5 年內\n    故意再犯本件有期徒刑以上之罪，為累犯，應依刑法第47條\n    第1 項規定，加重其刑。爰審酌被告之犯罪動機、手段、竊\n    得財物價值，及犯後坦承犯行，態度良好等一切情狀，量處\n    如主文所示之刑，並諭知易科罰金之折算標準，以示儆懲。\n三、依刑事訴訟法第449 條第2 項、第454 條第2 項，刑法第32\n    0 條第1 項、第47條第1 項、第41條第1 項前段，刑法施行\n    法第1條 之1 第1 項、第2 項前段，逕以簡易判決處刑如主\n    文。\n四、如不服本判決，應於判決送達後10日內，向本院提出上訴狀\n    。"
  },
  "search": "臺灣桃園地方法院刑事簡易判決100年度簡字第149號公訴人臺灣桃園地方法院檢察署檢察官被告李友銓上列被告因竊盜案件，經檢察官提起公訴（100年度偵字第15111號），被告自白犯罪，本院認宜以簡易判決處刑，判決如下：主文李友銓竊盜，累犯，處有期徒刑肆月，如易科罰金，以新臺幣壹仟元折算壹日。事實及理由一、本件除(一)事實部分第1至3行更正為：「李友銓前因竊盜等案件，經本院以98年度易字第434號判決判處有期徒刑2月，共6罪，定應執行有期徒刑10月確定；又因詐欺案件，經本院以99年度桃簡字第148號判決判處有期徒刑4月確定；上開案件嗣經本院以99年度聲字第3090號裁定定應執行有期徒刑1年1月確定。李友銓就竊盜案件先於民國98年6月25日入監服刑，並於99年1月16日縮刑期滿，同年月17日出監；嗣又於99年12月16日入監服刑，並於100年2月25日易科罰金執行完畢出監」；(二)證據部分補充：被告李友銓於本院訊問時自白犯行（見本院易字卷第7頁背面）；(三)其餘犯罪事實、證據均引用檢察官起訴書所載（如附件）。二、核被告李友銓所為，係犯刑法第320條第1項之普通竊盜罪。被告曾受事實欄所載之徒刑執行完畢，此有臺灣高等法院被告前案紀錄表1份供參，其受徒刑之執行完畢，於5年內故意再犯本件有期徒刑以上之罪，為累犯，應依刑法第47條第1項規定，加重其刑。爰審酌被告之犯罪動機、手段、竊得財物價值，及犯後坦承犯行，態度良好等一切情狀，量處如主文所示之刑，並諭知易科罰金之折算標準，以示儆懲。三、依刑事訴訟法第449條第2項、第454條第2項，刑法第320條第1項、第47條第1項、第41條第1項前段，刑法施行法第1條之1第1項、第2項前段，逕以簡易判決處刑如主文。四、如不服本判決，應於判決送達後10日內，向本院提出上訴狀。中華民國100年6月28日刑事第四庭法官林宜靜以上正本證明與原本無異。如不服本判決，應於判決送達後10日內向本院提出上訴狀（應附繕本）。書記官王明玉中華民國100年7月1日附錄論罪科刑法條中華民國刑法第320條（普通竊盜罪、竊佔罪）意圖為自己或第三人不法之所有，而竊取他人之動產者，為竊盜罪，處5年以下有期徒刑、拘役或5百元以下罰金。意圖為自己或第三人不法之利益，而竊佔他人之不動產者，依前項之規定處斷。前二項之未遂犯罰之。",
  "characters": {
    "judges": [
      "林宜靜"
    ],
    "prosecutors": [

    ],
    "lawyers": [

    ],
    "clerks": [
      "王明玉"
    ],
    "plaintiffs": [

    ],
    "defendants": [
      "李友銓"
    ],
    "prosecutor_office": [
      "臺灣桃園地方法院檢察署檢察官"
    ],
    "creditors": [

    ],
    "debtors": [

    ],
    "judicial_associate_officer": [

    ]
  },
  "adjudged_at": "2011-06-28",
  "created_at": "2016-02-13 16:20:39",
  "updated_at": "2016-02-13 16:20:39"
}