{
  "identify": "TPB-90-訴-2848-20020520-1",
  "court": {
    "name": "臺北高等行政法院",
    "code": "TPB"
  },
  "division": {
    "name": "行政",
    "code": "A"
  },
  "year": 90,
  "word": "訴",
  "number": "2848",
  "jcheck": "1",
  "reason": "營業稅及稅捐稽徵法",
  "content": "臺北高等行政法院裁定                              九十年度訴字第二八四八號\n    原      告  大豐建設股份有限公司\n    代  表  人  甲○○\n    訴訟代理人  潘正芬律師\n    被      告  臺北縣政府稅捐稽徵處（原臺北縣稅捐稽徵處）\n    代  表  人  乙○○處長）.\n右當事人間因營業稅及稅捐稽徵法事件，原告不服財政部中華民國九十年二月七日台\n財訴字第０九０一三五０四一三號再訴願決定，提起行政訴訟，本院裁定如左：\n    主  文\n原告之訴駁回。\n訴訟費用由原告負擔。\n    理  由\n一、按「納稅義務人對於核定稅捐之處分如有不服，應依規定格式，敘明理由，連同\n    證明文件，依左列規定，申請復查：一、依核定稅額通知書所載有應納稅額或應\n    補徵稅額者，應於繳款書送達後，於繳納期間屆滿翌日起算三十日內，申請復查\n    。」稅捐稽徵法第三十五條第一項第一款定有明文。\n二、原告因營業稅法及稅捐稽徵法事件，經台北縣稅捐稽徵處補徵營業稅新台幣（下\n    同）一、二七四、八九九元，並裁處罰鍰一、二七四、八九九元，該補徵營業稅\n    及罰鍰繳款書，已於八十六年十月二十八日送達，有原告代表人甲○○蓋章之送\n    達證書附卷可稽。又本件補徵營業稅繳款書及罰鍰繳款書限繳期限為八十六年十\n    二月十日，經核算申請復查三十日法定不變期間應至八十七年一月九日止。惟原\n    告遲至八十七年四月十八日始向被告提出復查申請，有被告收文章及原告復查申\n    請書所載書立日期可憑，被告以復查逾期，程序駁回原告復查申請，核無不合，\n    一再訴願決定以原告未踐行合法復查程序，而為維持原處分之決定，亦屬妥適。\n    原告復對之提起行政訴訟，顯非合法，應予駁回。\n三、依行政訴訟法第一百零七條第一項第十款、第一百零四條、民事訴訟法第九十五\n    條、第七十八條，裁定如主文。\n中    華    民    國      九十一    年      五        月      二十      日\n                      臺 北 高 等 行 政 法 院   第 四 庭\n                                         審 判 長 法  官  姜素娥\n                                                  法  官  林文舟\n                                                  法  官  陳國成\n右為正本係照原本作成。\n如不服本裁定，應於送達後十日內向本院提出抗告狀（須按他造人數附繕本）。\n中    華    民    國      九十一    年      五        月    二十二      日\n                                                  書記官  王英傑\n",
  "structure": {
    "main": "原告之訴駁回。\n訴訟費用由原告負擔。",
    "reason": "一、按「納稅義務人對於核定稅捐之處分如有不服，應依規定格式，敘明理由，連同\n    證明文件，依左列規定，申請復查：一、依核定稅額通知書所載有應納稅額或應\n    補徵稅額者，應於繳款書送達後，於繳納期間屆滿翌日起算三十日內，申請復查\n    。」稅捐稽徵法第三十五條第一項第一款定有明文。\n二、原告因營業稅法及稅捐稽徵法事件，經台北縣稅捐稽徵處補徵營業稅新台幣（下\n    同）一、二七四、八九九元，並裁處罰鍰一、二七四、八九九元，該補徵營業稅\n    及罰鍰繳款書，已於八十六年十月二十八日送達，有原告代表人甲○○蓋章之送\n    達證書附卷可稽。又本件補徵營業稅繳款書及罰鍰繳款書限繳期限為八十六年十\n    二月十日，經核算申請復查三十日法定不變期間應至八十七年一月九日止。惟原\n    告遲至八十七年四月十八日始向被告提出復查申請，有被告收文章及原告復查申\n    請書所載書立日期可憑，被告以復查逾期，程序駁回原告復查申請，核無不合，\n    一再訴願決定以原告未踐行合法復查程序，而為維持原處分之決定，亦屬妥適。\n    原告復對之提起行政訴訟，顯非合法，應予駁回。\n三、依行政訴訟法第一百零七條第一項第十款、第一百零四條、民事訴訟法第九十五\n    條、第七十八條，裁定如主文。"
  },
  "search": "臺北高等行政法院裁定九十年度訴字第二八四八號原告大豐建設股份有限公司代表人甲○○訴訟代理人潘正芬律師被告臺北縣政府稅捐稽徵處（原臺北縣稅捐稽徵處）代表人乙○○處長）.右當事人間因營業稅及稅捐稽徵法事件，原告不服財政部中華民國九十年二月七日台財訴字第０九０一三五０四一三號再訴願決定，提起行政訴訟，本院裁定如左：主文原告之訴駁回。訴訟費用由原告負擔。理由一、按「納稅義務人對於核定稅捐之處分如有不服，應依規定格式，敘明理由，連同證明文件，依左列規定，申請復查：一、依核定稅額通知書所載有應納稅額或應補徵稅額者，應於繳款書送達後，於繳納期間屆滿翌日起算三十日內，申請復查。」稅捐稽徵法第三十五條第一項第一款定有明文。二、原告因營業稅法及稅捐稽徵法事件，經台北縣稅捐稽徵處補徵營業稅新台幣（下同）一、二七四、八九九元，並裁處罰鍰一、二七四、八九九元，該補徵營業稅及罰鍰繳款書，已於八十六年十月二十八日送達，有原告代表人甲○○蓋章之送達證書附卷可稽。又本件補徵營業稅繳款書及罰鍰繳款書限繳期限為八十六年十二月十日，經核算申請復查三十日法定不變期間應至八十七年一月九日止。惟原告遲至八十七年四月十八日始向被告提出復查申請，有被告收文章及原告復查申請書所載書立日期可憑，被告以復查逾期，程序駁回原告復查申請，核無不合，一再訴願決定以原告未踐行合法復查程序，而為維持原處分之決定，亦屬妥適。原告復對之提起行政訴訟，顯非合法，應予駁回。三、依行政訴訟法第一百零七條第一項第十款、第一百零四條、民事訴訟法第九十五條、第七十八條，裁定如主文。中華民國九十一年五月二十日臺北高等行政法院第四庭審判長法官姜素娥法官林文舟法官陳國成右為正本係照原本作成。如不服本裁定，應於送達後十日內向本院提出抗告狀（須按他造人數附繕本）。中華民國九十一年五月二十二日書記官王英傑",
  "characters": {
    "judges": [
      "姜素娥",
      "林文舟",
      "陳國成"
    ],
    "prosecutors": [

    ],
    "lawyers": [
      "潘正芬"
    ],
    "clerks": [
      "王英傑"
    ],
    "plaintiffs": [
      "大豐建設股份有限公司"
    ],
    "defendants": [
      "臺北縣政府稅捐稽徵處（原臺北縣稅捐稽徵處）"
    ],
    "prosecutor_office": [

    ],
    "creditors": [

    ],
    "debtors": [

    ],
    "judicial_associate_officer": [

    ]
  },
  "adjudged_at": "2002-05-20",
  "created_at": "2016-02-04 14:15:23",
  "updated_at": "2016-02-04 14:15:23"
}