{
  "identify": "TYD-100-審交重附民-30-20111125-1",
  "court": {
    "name": "臺灣桃園地方法院",
    "code": "TYD"
  },
  "division": {
    "name": "刑事",
    "code": "M"
  },
  "year": 100,
  "word": "審交重附民",
  "number": "30",
  "jcheck": "1",
  "reason": "請求賠償損害",
  "content": "臺灣桃園地方法院刑事附帶民事訴訟裁定\n                               100年度審交重附民字第30號\n原      告  張宗學\n法定代理人\n兼  原  告  帥允文\n原      告  張美華\n            張廣惠\n            張大元\n訴訟代理人  胡峰賓律師\n被      告  鍾百城\n            全國時報社有限公司\n法定代理人  鍾百城\n上列被告因過失傷害案件（100 年度審交易字第314 號），經原\n告提起附帶民事訴訟，請求損害賠償，本院裁定如下：\n    主  文\n本件移送本院民事庭。\n    理  由\n一、查原告於本院100 年度審交易字第314 號被告被訴過失傷害\n    案件審理中，提起附帶民事訴訟，請求損害賠償事件，其內\n    容係屬繁雜，非經長久時日，不能終結其審判，爰將本件附\n    帶民事訴訟移送本院民事庭。\n二、依刑事訴訟法第504 條第1 項前段規定，裁定如主文。\n中    華    民    國    100   年    11    月    25    日\n                  刑事庭  審判長法  官  游紅桃\n                                法  官  蘇昌澤\n                                法  官  潘怡華\n以上正本證明與原本無異。\n不得抗告。\n                                書記官  郭怡君\n中    華    民    國    100   年    11    月    25    日",
  "structure": {
    "main": "本件移送本院民事庭。",
    "reason": "一、查原告於本院100 年度審交易字第314 號被告被訴過失傷害\n    案件審理中，提起附帶民事訴訟，請求損害賠償事件，其內\n    容係屬繁雜，非經長久時日，不能終結其審判，爰將本件附\n    帶民事訴訟移送本院民事庭。\n二、依刑事訴訟法第504 條第1 項前段規定，裁定如主文。"
  },
  "search": "臺灣桃園地方法院刑事附帶民事訴訟裁定100年度審交重附民字第30號原告張宗學法定代理人兼原告帥允文原告張美華張廣惠張大元訴訟代理人胡峰賓律師被告鍾百城全國時報社有限公司法定代理人鍾百城上列被告因過失傷害案件（100年度審交易字第314號），經原告提起附帶民事訴訟，請求損害賠償，本院裁定如下：主文本件移送本院民事庭。理由一、查原告於本院100年度審交易字第314號被告被訴過失傷害案件審理中，提起附帶民事訴訟，請求損害賠償事件，其內容係屬繁雜，非經長久時日，不能終結其審判，爰將本件附帶民事訴訟移送本院民事庭。二、依刑事訴訟法第504條第1項前段規定，裁定如主文。中華民國100年11月25日刑事庭審判長法官游紅桃法官蘇昌澤法官潘怡華以上正本證明與原本無異。不得抗告。書記官郭怡君中華民國100年11月25日",
  "characters": {
    "judges": [
      "游紅桃",
      "蘇昌澤",
      "潘怡華"
    ],
    "prosecutors": [

    ],
    "lawyers": [
      "胡峰賓"
    ],
    "clerks": [
      "郭怡君"
    ],
    "plaintiffs": [
      "張宗學",
      "帥允文",
      "張美華"
    ],
    "defendants": [
      "鍾百城"
    ],
    "prosecutor_office": [

    ],
    "creditors": [

    ],
    "debtors": [

    ],
    "judicial_associate_officer": [

    ]
  },
  "adjudged_at": "2011-11-25",
  "created_at": "2016-02-13 00:04:13",
  "updated_at": "2016-02-13 00:04:13"
}