{
  "identify": "KSD-100-訴-775-20111013-1",
  "court": {
    "name": "臺灣高雄地方法院",
    "code": "KSD"
  },
  "division": {
    "name": "刑事",
    "code": "M"
  },
  "year": 100,
  "word": "訴",
  "number": "775",
  "jcheck": "1",
  "reason": "毒品危害防制條例",
  "content": "臺灣高雄地方法院刑事判決              100年度訴字第775號\n公  訴  人  臺灣高雄地方法院檢察署檢察官\n被      告  黃慶文\n上列被告因毒品危害防制條例案件，經檢察官提起公訴（100年\n度毒偵字第2663號），本院判決如下：\n    主  文\n黃慶文施用第一級毒品，累犯，處有期徒刑伍月，如易科罰金，\n以新臺幣壹仟元折算壹日，扣案之第一級毒品海洛因壹包（含包\n裝袋壹只，驗前凈重零點零貳捌公克，驗後凈重零點零壹捌公克\n）沒收銷燬之。\n    事  實\n一、黃慶文前於民國93年間因施用毒品案件，經法院裁定送觀察\n    、勒戒後，因認有繼續施用毒品傾向，復經法院裁定令入戒\n    治處所施以強制戒治，嗣於94年3 月17日因無繼續戒治之必\n    要而執行完畢釋放，復於前揭強制戒治執行完畢釋放5 年內\n    之98年間再犯施用毒品案件，而經本院以98年度審訴字第15\n    6號判處有期徒刑8月確定，甫於99年1月5日執行完畢。詎猶\n    不知戒絕毒癮，竟基於施用第一級毒品海洛因之犯意，於10\n    0年3月10日中午1時許，在高雄市○○區○○路上之忠孝公\n    園內，以新臺幣500元之代價，向某不詳成年男子購得約0.4\n    公克之第一級毒品海洛因後，旋返回其高雄市新興區○○○\n    路203巷37號5樓之1之居處，以針筒注射之方式，施用該甫\n    購得之海洛因1次。隨即於同日下午1時20分許，在高雄市新\n    興區○○○路322號，因行跡可疑，為警盤檢攔查，黃慶文\n    即主動取出其施用剩餘之海洛因1包（驗前凈重0.028公克，\n    驗後凈重0.018公克）予警查扣，並於警詢時坦承有施用海\n    洛因之犯行，自首而願接受裁判，且同意採尿送驗，鑑驗結\n    果確呈嗎啡陽性反應。\n二、案經高雄市政府警察局新興分局報告臺灣高雄地方法院檢察\n    署檢察官偵查後起訴。\n    理  由\n壹、證據能力部分：\n    按被告以外之人於審判外之言詞或書面陳述，除法律有規定\n    者外，不得作為證據，刑事訴訟法第159 條第1 項定有明文\n    ；另按被告以外之人於審判外之陳述，雖不符前四條之規定\n    ，而經當事人於審判程序同意作為證據，法院審酌該言詞陳\n    述或書面陳述作成時之情況，認為適當者，亦得為證據；當\n    事人、代理人或辯護人於法院調查證據時，知有第159 條第\n    1 項不得為證據之情形，而未於言詞辯論終結前聲明異議者\n    ，視為有前項之同意，同法第159 條之5 規定甚明。本判決\n    所引用之證據資料屬於被告以外之人於審判外之言詞、書面\n    陳述者，均經本院於調查證據時逐一提示並告以要旨，檢察\n    官、被告皆未於言詞辯論終結前聲明異議，本院審酌上開證\n    據作成時之情況，並無不當取供或違反自由意志而陳述等情\n    形，且與本案待證事實具有關聯性，認為以之作為本案之證\n    據屬適當，依上開法條規定，均具證據能力，核先敘明。\n貳、實體部分：\n一、訊據被告黃慶文就其於100年3 月10日中午1時許，在高雄市\n    ○○區○○路上之忠孝公園內，向某不詳成年男子購得約0.\n    4公克之第一級毒品海洛因後，旋返回其高雄市新興區○○\n    ○路203巷37號5樓之1之居處，以針筒注射之方式，施用海\n    洛因1次之情事，於本院審理中已坦承不諱〈見本院100  年\n    度訴字第775號卷（下稱訴字卷）第43頁〉，且其為警所採\n    之尿液，送驗結果確呈施用海洛因後之嗎啡陽性反應，有濫\n    用藥物尿液檢體監管記錄表、尿液採證代碼表、高雄市立凱\n    旋醫院濫用藥物尿液檢驗報告各1份在卷可稽（見警卷第13\n    至14頁、偵卷第34頁），又被告為警盤查時持有之白色粉末\n    1包，經送驗結果亦檢出海洛因成分，有扣押筆錄、扣押物\n    品目錄表及高雄市立凱旋醫院濫用藥物成品檢驗鑑定書各1\n    份在卷可憑（見警卷第4至5頁、審訴卷第18頁），足認被告\n    之自白與事實相符，洵堪採為論罪科刑之依據。被告於警詢\n    、偵訊時雖均供稱其最後一次施用海洛因之時間，係於100\n    年3月6日中午12時左右等語（見警卷第1 頁反面、偵卷第31\n    至32頁），與其於本院審理中所述不符，公訴意旨即據此而\n    認扣案之海洛因係被告於施用完畢後始購得，因而另成立持\n    有第一級毒品罪，然查，扣案之海洛因1 包毛重為0.25公克\n    一情，業載明於扣押物品目錄表（見警卷第5 頁），此與被\n    告供稱原係購入0.4公克之海洛因，購入後隨即施用一情相\n    符，且細觀該包海洛因，亦可見有經取出部分，因而殘留、\n    分布粉末在夾鍊袋周圍之情形，有照片1張在卷可按（見警\n    卷第9頁），益徵扣案之海洛因並非購入後未經施用即遭查\n    獲，是被告於本院審理所陳，購入海洛因並施用部分後，方\n    遭警察查獲等語，應堪採信。被告係於100年3月10日下午1\n    時許購入0.4公克之海洛因1包後，旋即返回其上開居處施用\n    乙節，可堪認定。依此而論，被告購入上開海洛因之目的，\n    係供己施用，亦臻明確。綜上所述，被告施用第一級毒品犯\n    行洵堪認定。\n二、按犯毒品危害防制條例第10條之罪，經觀察、勒戒後，認無\n    繼續施用毒品之傾向，應即釋放，並為不起訴處分；認有繼\n    續施用毒品之傾向者，應由檢察官聲請法院裁定令入戒治處\n    所施以強制戒治，至無繼續戒治之必要，強制戒治期滿，應\n    即釋放，由檢察官為不起訴處分。經觀察勒戒、強制戒治執\n    行完畢釋放後，5 年內再犯第10條之罪，依93年1 月9 日修\n    正施行之毒品危害防制條例第23條第2 項規定意旨，應由檢\n    察官偵查起訴。又依修正後之規定，僅限於「初犯」及「5\n    年後再犯」二種情形，始應先經觀察、勒戒或強制戒治程序\n    。倘被告於5 年內已再犯，經依法追訴處罰，縱其第3 次（\n    或第3 次以上）再度施用毒品之時間，在初犯經觀察、勒戒\n    或強制戒治執行完畢釋放5 年以後，已不合於「5 年後再犯\n    」之規定，且因已於「5 年內再犯」，顯見其再犯率甚高，\n    原實施觀察、勒戒或強制戒治，已無法收其實效，即應依該\n    條例第10條處罰（最高法院97年度第5 次刑事庭會議決議參\n    照）。查被告黃慶文前於93年間因施用毒品案件，經法院裁\n    定送觀察、勒戒後，因認有繼續施用毒品傾向，復經法院裁\n    定令入戒治處所施以強制戒治，嗣於94年3 月17日因無繼續\n    戒治之必要而執行完畢釋放，復於前揭強制戒治執行完畢釋\n    放5 年內之98年間再犯施用毒品案件，而經本院以98年度審\n    訴字第156 號判處有期徒刑8月確定，甫於99年1 月5日執行\n    完畢等情，有臺灣高等法院被告前案紀錄表存卷可查，是被\n    告於初犯經觀察勒戒、強制戒治執行完畢後，5 年內已再犯\n    毒品危害防制條例第10條之罪，並經法院判刑確定，揆諸前\n    開說明，本案自應依法追訴處罰。\n三、核被告所為，係犯毒品危害防制條例第10條第1項之施用第\n    一級毒品罪。被告持有第一級毒品海洛因後，進而施用，其\n    持有之低度行為應為施用之高度行為所吸收，不另論罪。公\n    訴意旨認被告另犯持有第一級毒品罪（見訴字卷第19頁補充\n    理由書），顯就被告施用海洛因之時點有所誤認，業據本院\n    論述如前，此部分之論罪，自有未洽，附此敘明。被告有如\n    上所載之犯罪科刑及執行情形，有臺灣高等法院被告前案紀\n    錄表1份在卷可查，其於受有期徒刑執行完畢後，5  年內故\n    意再犯本件有期徒刑以上之罪，為累犯，應依刑法第47條第\n    1項規定，加重其刑。又按犯第4條至第8 條、第10條或第11\n    條之罪，供出毒品來源，因而查獲其他正犯或共犯者，減輕\n    或免除其刑，毒品危害防制條例第17條第1 項定有明文，被\n    告於偵查中提供其毒品來源之姓名、聯絡電話、出沒地點等\n    線索後，警方因而據此上線監聽，並確實查獲該人涉嫌販毒\n    ，有臺灣高雄地方法院檢察署100年7 月27日雄檢瑞海100毒\n    偵2663字第50655 號函及附件在卷可證（見訴字卷第33至39\n    頁），符合毒品危害防制條例第17條第1 項減刑之要件，應\n    應適用該規定減輕其刑。再被告於員警執行盤查，尚未發覺\n    其上開施用毒品犯罪前，主動取出持有之第一級毒品海洛因\n    1 包予警方扣案，並於警詢時坦承施用第一級毒品犯行，而\n    同意採尿送驗，有本院公務電話記錄及被告之警詢筆錄、高\n    雄市政府警察局新興分局刑事案件移送書在卷可證（見審訴\n    卷第19頁、警卷第1頁反面至2 頁、偵卷第1頁），堪認係對\n    於未發覺之罪自首而受裁判，爰依刑法第62條前段規定，減\n    輕其刑。被告有上開數加重、減輕事由，應依刑法第71條規\n    定，先加後減，並遞減之。爰審酌被告前經觀察勒戒、強制\n    戒治，及法院以其犯施用第二級毒品罪，判處有期徒刑8 月\n    ，有臺灣高等法院被告前案紀錄表在卷可查，猶未能戒絕毒\n    癮，再犯本案施用毒品犯行，實屬不該，惟念施用毒品乃自\n    戕行為，對社會造成之危害尚非直接至鉅，且犯後自首並坦\n    承犯行，更配合供出毒品上游，態度尚佳等一切情狀，爰量\n    處如主文所示之刑，及諭知易科罰金之折算標準，末扣案之\n    白色粉末1 包，經送高雄市立凱旋醫院檢驗結果，檢出海洛\n    因成分（驗前凈重分別為0.028公克，驗後淨重為0.018公克\n    ），有該醫院出具之濫用藥物成品檢驗鑑定書在卷可稽，自\n    屬查獲之第一級毒品無訛，應依毒品危害防制條例第18條第\n    1項前段之規定，宣告沒收銷燬；另包裝毒品之包裝袋1只，\n    因與其上所殘留之毒品難以析離，且無析離之實益與必要，\n    應視同毒品，一併沒收銷燬之；至送驗耗損部分之毒品因已\n    滅失，爰不另宣告沒收銷燬，附此敘明。\n據上論斷，應依刑事訴訟法第299條第1項前段，毒品危害防制條\n例第10條第1 項、第17條第1項、第18條第1項前段，刑法第11條\n、第62條前段、第47條第1項、第41條第1項前段，判決如主文。\n本案經檢察官黃世勳到庭執行職務。\n中    華    民    國   100    年    10    月    13    日\n                  刑事第十三庭審判長法  官  黃蕙芳\n                                    法  官  陳采葳\n                                    法  官  陳筱雯\n以上正本證明與原本無異。\n如不服本判決應於收受送達後10日內向本院提出上訴書狀，並應\n敘述具體理由；如未敘述上訴理由者，應於上訴期間屆滿後20日\n內向本院補提理由書（均須按他造當事人之人數附繕本）「切勿\n逕送上級法院」。\n中    華    民    國   100    年    10    月    13    日\n                                    書記官  陳建琪\n附錄本案論罪科刑法條：\n毒品危害防制條例第10條第1項\n施用第一級毒品者，處 6 月以上 5 年以下有期徒刑。",
  "structure": {
    "main": "黃慶文施用第一級毒品，累犯，處有期徒刑伍月，如易科罰金，\n以新臺幣壹仟元折算壹日，扣案之第一級毒品海洛因壹包（含包\n裝袋壹只，驗前凈重零點零貳捌公克，驗後凈重零點零壹捌公克\n）沒收銷燬之。",
    "fact": "一、黃慶文前於民國93年間因施用毒品案件，經法院裁定送觀察\n    、勒戒後，因認有繼續施用毒品傾向，復經法院裁定令入戒\n    治處所施以強制戒治，嗣於94年3 月17日因無繼續戒治之必\n    要而執行完畢釋放，復於前揭強制戒治執行完畢釋放5 年內\n    之98年間再犯施用毒品案件，而經本院以98年度審訴字第15\n    6號判處有期徒刑8月確定，甫於99年1月5日執行完畢。詎猶\n    不知戒絕毒癮，竟基於施用第一級毒品海洛因之犯意，於10\n    0年3月10日中午1時許，在高雄市○○區○○路上之忠孝公\n    園內，以新臺幣500元之代價，向某不詳成年男子購得約0.4\n    公克之第一級毒品海洛因後，旋返回其高雄市新興區○○○\n    路203巷37號5樓之1之居處，以針筒注射之方式，施用該甫\n    購得之海洛因1次。隨即於同日下午1時20分許，在高雄市新\n    興區○○○路322號，因行跡可疑，為警盤檢攔查，黃慶文\n    即主動取出其施用剩餘之海洛因1包（驗前凈重0.028公克，\n    驗後凈重0.018公克）予警查扣，並於警詢時坦承有施用海\n    洛因之犯行，自首而願接受裁判，且同意採尿送驗，鑑驗結\n    果確呈嗎啡陽性反應。\n二、案經高雄市政府警察局新興分局報告臺灣高雄地方法院檢察\n    署檢察官偵查後起訴。",
    "reason": "壹、證據能力部分：\n    按被告以外之人於審判外之言詞或書面陳述，除法律有規定\n    者外，不得作為證據，刑事訴訟法第159 條第1 項定有明文\n    ；另按被告以外之人於審判外之陳述，雖不符前四條之規定\n    ，而經當事人於審判程序同意作為證據，法院審酌該言詞陳\n    述或書面陳述作成時之情況，認為適當者，亦得為證據；當\n    事人、代理人或辯護人於法院調查證據時，知有第159 條第\n    1 項不得為證據之情形，而未於言詞辯論終結前聲明異議者\n    ，視為有前項之同意，同法第159 條之5 規定甚明。本判決\n    所引用之證據資料屬於被告以外之人於審判外之言詞、書面\n    陳述者，均經本院於調查證據時逐一提示並告以要旨，檢察\n    官、被告皆未於言詞辯論終結前聲明異議，本院審酌上開證\n    據作成時之情況，並無不當取供或違反自由意志而陳述等情\n    形，且與本案待證事實具有關聯性，認為以之作為本案之證\n    據屬適當，依上開法條規定，均具證據能力，核先敘明。\n貳、實體部分：\n一、訊據被告黃慶文就其於100年3 月10日中午1時許，在高雄市\n    ○○區○○路上之忠孝公園內，向某不詳成年男子購得約0.\n    4公克之第一級毒品海洛因後，旋返回其高雄市新興區○○\n    ○路203巷37號5樓之1之居處，以針筒注射之方式，施用海\n    洛因1次之情事，於本院審理中已坦承不諱〈見本院100  年\n    度訴字第775號卷（下稱訴字卷）第43頁〉，且其為警所採\n    之尿液，送驗結果確呈施用海洛因後之嗎啡陽性反應，有濫\n    用藥物尿液檢體監管記錄表、尿液採證代碼表、高雄市立凱\n    旋醫院濫用藥物尿液檢驗報告各1份在卷可稽（見警卷第13\n    至14頁、偵卷第34頁），又被告為警盤查時持有之白色粉末\n    1包，經送驗結果亦檢出海洛因成分，有扣押筆錄、扣押物\n    品目錄表及高雄市立凱旋醫院濫用藥物成品檢驗鑑定書各1\n    份在卷可憑（見警卷第4至5頁、審訴卷第18頁），足認被告\n    之自白與事實相符，洵堪採為論罪科刑之依據。被告於警詢\n    、偵訊時雖均供稱其最後一次施用海洛因之時間，係於100\n    年3月6日中午12時左右等語（見警卷第1 頁反面、偵卷第31\n    至32頁），與其於本院審理中所述不符，公訴意旨即據此而\n    認扣案之海洛因係被告於施用完畢後始購得，因而另成立持\n    有第一級毒品罪，然查，扣案之海洛因1 包毛重為0.25公克\n    一情，業載明於扣押物品目錄表（見警卷第5 頁），此與被\n    告供稱原係購入0.4公克之海洛因，購入後隨即施用一情相\n    符，且細觀該包海洛因，亦可見有經取出部分，因而殘留、\n    分布粉末在夾鍊袋周圍之情形，有照片1張在卷可按（見警\n    卷第9頁），益徵扣案之海洛因並非購入後未經施用即遭查\n    獲，是被告於本院審理所陳，購入海洛因並施用部分後，方\n    遭警察查獲等語，應堪採信。被告係於100年3月10日下午1\n    時許購入0.4公克之海洛因1包後，旋即返回其上開居處施用\n    乙節，可堪認定。依此而論，被告購入上開海洛因之目的，\n    係供己施用，亦臻明確。綜上所述，被告施用第一級毒品犯\n    行洵堪認定。\n二、按犯毒品危害防制條例第10條之罪，經觀察、勒戒後，認無\n    繼續施用毒品之傾向，應即釋放，並為不起訴處分；認有繼\n    續施用毒品之傾向者，應由檢察官聲請法院裁定令入戒治處\n    所施以強制戒治，至無繼續戒治之必要，強制戒治期滿，應\n    即釋放，由檢察官為不起訴處分。經觀察勒戒、強制戒治執\n    行完畢釋放後，5 年內再犯第10條之罪，依93年1 月9 日修\n    正施行之毒品危害防制條例第23條第2 項規定意旨，應由檢\n    察官偵查起訴。又依修正後之規定，僅限於「初犯」及「5\n    年後再犯」二種情形，始應先經觀察、勒戒或強制戒治程序\n    。倘被告於5 年內已再犯，經依法追訴處罰，縱其第3 次（\n    或第3 次以上）再度施用毒品之時間，在初犯經觀察、勒戒\n    或強制戒治執行完畢釋放5 年以後，已不合於「5 年後再犯\n    」之規定，且因已於「5 年內再犯」，顯見其再犯率甚高，\n    原實施觀察、勒戒或強制戒治，已無法收其實效，即應依該\n    條例第10條處罰（最高法院97年度第5 次刑事庭會議決議參\n    照）。查被告黃慶文前於93年間因施用毒品案件，經法院裁\n    定送觀察、勒戒後，因認有繼續施用毒品傾向，復經法院裁\n    定令入戒治處所施以強制戒治，嗣於94年3 月17日因無繼續\n    戒治之必要而執行完畢釋放，復於前揭強制戒治執行完畢釋\n    放5 年內之98年間再犯施用毒品案件，而經本院以98年度審\n    訴字第156 號判處有期徒刑8月確定，甫於99年1 月5日執行\n    完畢等情，有臺灣高等法院被告前案紀錄表存卷可查，是被\n    告於初犯經觀察勒戒、強制戒治執行完畢後，5 年內已再犯\n    毒品危害防制條例第10條之罪，並經法院判刑確定，揆諸前\n    開說明，本案自應依法追訴處罰。\n三、核被告所為，係犯毒品危害防制條例第10條第1項之施用第\n    一級毒品罪。被告持有第一級毒品海洛因後，進而施用，其\n    持有之低度行為應為施用之高度行為所吸收，不另論罪。公\n    訴意旨認被告另犯持有第一級毒品罪（見訴字卷第19頁補充\n    理由書），顯就被告施用海洛因之時點有所誤認，業據本院\n    論述如前，此部分之論罪，自有未洽，附此敘明。被告有如\n    上所載之犯罪科刑及執行情形，有臺灣高等法院被告前案紀\n    錄表1份在卷可查，其於受有期徒刑執行完畢後，5  年內故\n    意再犯本件有期徒刑以上之罪，為累犯，應依刑法第47條第\n    1項規定，加重其刑。又按犯第4條至第8 條、第10條或第11\n    條之罪，供出毒品來源，因而查獲其他正犯或共犯者，減輕\n    或免除其刑，毒品危害防制條例第17條第1 項定有明文，被\n    告於偵查中提供其毒品來源之姓名、聯絡電話、出沒地點等\n    線索後，警方因而據此上線監聽，並確實查獲該人涉嫌販毒\n    ，有臺灣高雄地方法院檢察署100年7 月27日雄檢瑞海100毒\n    偵2663字第50655 號函及附件在卷可證（見訴字卷第33至39\n    頁），符合毒品危害防制條例第17條第1 項減刑之要件，應\n    應適用該規定減輕其刑。再被告於員警執行盤查，尚未發覺\n    其上開施用毒品犯罪前，主動取出持有之第一級毒品海洛因\n    1 包予警方扣案，並於警詢時坦承施用第一級毒品犯行，而\n    同意採尿送驗，有本院公務電話記錄及被告之警詢筆錄、高\n    雄市政府警察局新興分局刑事案件移送書在卷可證（見審訴\n    卷第19頁、警卷第1頁反面至2 頁、偵卷第1頁），堪認係對\n    於未發覺之罪自首而受裁判，爰依刑法第62條前段規定，減\n    輕其刑。被告有上開數加重、減輕事由，應依刑法第71條規\n    定，先加後減，並遞減之。爰審酌被告前經觀察勒戒、強制\n    戒治，及法院以其犯施用第二級毒品罪，判處有期徒刑8 月\n    ，有臺灣高等法院被告前案紀錄表在卷可查，猶未能戒絕毒\n    癮，再犯本案施用毒品犯行，實屬不該，惟念施用毒品乃自\n    戕行為，對社會造成之危害尚非直接至鉅，且犯後自首並坦\n    承犯行，更配合供出毒品上游，態度尚佳等一切情狀，爰量\n    處如主文所示之刑，及諭知易科罰金之折算標準，末扣案之\n    白色粉末1 包，經送高雄市立凱旋醫院檢驗結果，檢出海洛\n    因成分（驗前凈重分別為0.028公克，驗後淨重為0.018公克\n    ），有該醫院出具之濫用藥物成品檢驗鑑定書在卷可稽，自\n    屬查獲之第一級毒品無訛，應依毒品危害防制條例第18條第\n    1項前段之規定，宣告沒收銷燬；另包裝毒品之包裝袋1只，\n    因與其上所殘留之毒品難以析離，且無析離之實益與必要，\n    應視同毒品，一併沒收銷燬之；至送驗耗損部分之毒品因已\n    滅失，爰不另宣告沒收銷燬，附此敘明。\n據上論斷，應依刑事訴訟法第299條第1項前段，毒品危害防制條\n例第10條第1 項、第17條第1項、第18條第1項前段，刑法第11條\n、第62條前段、第47條第1項、第41條第1項前段，判決如主文。\n本案經檢察官黃世勳到庭執行職務。\n中    華    民    國   100    年    10    月    13    日\n                  刑事第十三庭審判長法  官  黃蕙芳\n                                    法  官  陳采葳\n                                    法  官  陳筱雯\n以上正本證明與原本無異。\n如不服本判決應於收受送達後10日內向本院提出上訴書狀，並應\n敘述具體理由；如未敘述上訴理由者，應於上訴期間屆滿後20日\n內向本院補提理由書（均須按他造當事人之人數附繕本）「切勿\n逕送上級法院」。"
  },
  "search": "臺灣高雄地方法院刑事判決100年度訴字第775號公訴人臺灣高雄地方法院檢察署檢察官被告黃慶文上列被告因毒品危害防制條例案件，經檢察官提起公訴（100年度毒偵字第2663號），本院判決如下：主文黃慶文施用第一級毒品，累犯，處有期徒刑伍月，如易科罰金，以新臺幣壹仟元折算壹日，扣案之第一級毒品海洛因壹包（含包裝袋壹只，驗前凈重零點零貳捌公克，驗後凈重零點零壹捌公克）沒收銷燬之。事實一、黃慶文前於民國93年間因施用毒品案件，經法院裁定送觀察、勒戒後，因認有繼續施用毒品傾向，復經法院裁定令入戒治處所施以強制戒治，嗣於94年3月17日因無繼續戒治之必要而執行完畢釋放，復於前揭強制戒治執行完畢釋放5年內之98年間再犯施用毒品案件，而經本院以98年度審訴字第156號判處有期徒刑8月確定，甫於99年1月5日執行完畢。詎猶不知戒絕毒癮，竟基於施用第一級毒品海洛因之犯意，於100年3月10日中午1時許，在高雄市○○區○○路上之忠孝公園內，以新臺幣500元之代價，向某不詳成年男子購得約0.4公克之第一級毒品海洛因後，旋返回其高雄市新興區○○○路203巷37號5樓之1之居處，以針筒注射之方式，施用該甫購得之海洛因1次。隨即於同日下午1時20分許，在高雄市新興區○○○路322號，因行跡可疑，為警盤檢攔查，黃慶文即主動取出其施用剩餘之海洛因1包（驗前凈重0.028公克，驗後凈重0.018公克）予警查扣，並於警詢時坦承有施用海洛因之犯行，自首而願接受裁判，且同意採尿送驗，鑑驗結果確呈嗎啡陽性反應。二、案經高雄市政府警察局新興分局報告臺灣高雄地方法院檢察署檢察官偵查後起訴。理由壹、證據能力部分：按被告以外之人於審判外之言詞或書面陳述，除法律有規定者外，不得作為證據，刑事訴訟法第159條第1項定有明文；另按被告以外之人於審判外之陳述，雖不符前四條之規定，而經當事人於審判程序同意作為證據，法院審酌該言詞陳述或書面陳述作成時之情況，認為適當者，亦得為證據；當事人、代理人或辯護人於法院調查證據時，知有第159條第1項不得為證據之情形，而未於言詞辯論終結前聲明異議者，視為有前項之同意，同法第159條之5規定甚明。本判決所引用之證據資料屬於被告以外之人於審判外之言詞、書面陳述者，均經本院於調查證據時逐一提示並告以要旨，檢察官、被告皆未於言詞辯論終結前聲明異議，本院審酌上開證據作成時之情況，並無不當取供或違反自由意志而陳述等情形，且與本案待證事實具有關聯性，認為以之作為本案之證據屬適當，依上開法條規定，均具證據能力，核先敘明。貳、實體部分：一、訊據被告黃慶文就其於100年3月10日中午1時許，在高雄市○○區○○路上之忠孝公園內，向某不詳成年男子購得約0.4公克之第一級毒品海洛因後，旋返回其高雄市新興區○○○路203巷37號5樓之1之居處，以針筒注射之方式，施用海洛因1次之情事，於本院審理中已坦承不諱〈見本院100年度訴字第775號卷（下稱訴字卷）第43頁〉，且其為警所採之尿液，送驗結果確呈施用海洛因後之嗎啡陽性反應，有濫用藥物尿液檢體監管記錄表、尿液採證代碼表、高雄市立凱旋醫院濫用藥物尿液檢驗報告各1份在卷可稽（見警卷第13至14頁、偵卷第34頁），又被告為警盤查時持有之白色粉末1包，經送驗結果亦檢出海洛因成分，有扣押筆錄、扣押物品目錄表及高雄市立凱旋醫院濫用藥物成品檢驗鑑定書各1份在卷可憑（見警卷第4至5頁、審訴卷第18頁），足認被告之自白與事實相符，洵堪採為論罪科刑之依據。被告於警詢、偵訊時雖均供稱其最後一次施用海洛因之時間，係於100年3月6日中午12時左右等語（見警卷第1頁反面、偵卷第31至32頁），與其於本院審理中所述不符，公訴意旨即據此而認扣案之海洛因係被告於施用完畢後始購得，因而另成立持有第一級毒品罪，然查，扣案之海洛因1包毛重為0.25公克一情，業載明於扣押物品目錄表（見警卷第5頁），此與被告供稱原係購入0.4公克之海洛因，購入後隨即施用一情相符，且細觀該包海洛因，亦可見有經取出部分，因而殘留、分布粉末在夾鍊袋周圍之情形，有照片1張在卷可按（見警卷第9頁），益徵扣案之海洛因並非購入後未經施用即遭查獲，是被告於本院審理所陳，購入海洛因並施用部分後，方遭警察查獲等語，應堪採信。被告係於100年3月10日下午1時許購入0.4公克之海洛因1包後，旋即返回其上開居處施用乙節，可堪認定。依此而論，被告購入上開海洛因之目的，係供己施用，亦臻明確。綜上所述，被告施用第一級毒品犯行洵堪認定。二、按犯毒品危害防制條例第10條之罪，經觀察、勒戒後，認無繼續施用毒品之傾向，應即釋放，並為不起訴處分；認有繼續施用毒品之傾向者，應由檢察官聲請法院裁定令入戒治處所施以強制戒治，至無繼續戒治之必要，強制戒治期滿，應即釋放，由檢察官為不起訴處分。經觀察勒戒、強制戒治執行完畢釋放後，5年內再犯第10條之罪，依93年1月9日修正施行之毒品危害防制條例第23條第2項規定意旨，應由檢察官偵查起訴。又依修正後之規定，僅限於「初犯」及「5年後再犯」二種情形，始應先經觀察、勒戒或強制戒治程序。倘被告於5年內已再犯，經依法追訴處罰，縱其第3次（或第3次以上）再度施用毒品之時間，在初犯經觀察、勒戒或強制戒治執行完畢釋放5年以後，已不合於「5年後再犯」之規定，且因已於「5年內再犯」，顯見其再犯率甚高，原實施觀察、勒戒或強制戒治，已無法收其實效，即應依該條例第10條處罰（最高法院97年度第5次刑事庭會議決議參照）。查被告黃慶文前於93年間因施用毒品案件，經法院裁定送觀察、勒戒後，因認有繼續施用毒品傾向，復經法院裁定令入戒治處所施以強制戒治，嗣於94年3月17日因無繼續戒治之必要而執行完畢釋放，復於前揭強制戒治執行完畢釋放5年內之98年間再犯施用毒品案件，而經本院以98年度審訴字第156號判處有期徒刑8月確定，甫於99年1月5日執行完畢等情，有臺灣高等法院被告前案紀錄表存卷可查，是被告於初犯經觀察勒戒、強制戒治執行完畢後，5年內已再犯毒品危害防制條例第10條之罪，並經法院判刑確定，揆諸前開說明，本案自應依法追訴處罰。三、核被告所為，係犯毒品危害防制條例第10條第1項之施用第一級毒品罪。被告持有第一級毒品海洛因後，進而施用，其持有之低度行為應為施用之高度行為所吸收，不另論罪。公訴意旨認被告另犯持有第一級毒品罪（見訴字卷第19頁補充理由書），顯就被告施用海洛因之時點有所誤認，業據本院論述如前，此部分之論罪，自有未洽，附此敘明。被告有如上所載之犯罪科刑及執行情形，有臺灣高等法院被告前案紀錄表1份在卷可查，其於受有期徒刑執行完畢後，5年內故意再犯本件有期徒刑以上之罪，為累犯，應依刑法第47條第1項規定，加重其刑。又按犯第4條至第8條、第10條或第11條之罪，供出毒品來源，因而查獲其他正犯或共犯者，減輕或免除其刑，毒品危害防制條例第17條第1項定有明文，被告於偵查中提供其毒品來源之姓名、聯絡電話、出沒地點等線索後，警方因而據此上線監聽，並確實查獲該人涉嫌販毒，有臺灣高雄地方法院檢察署100年7月27日雄檢瑞海100毒偵2663字第50655號函及附件在卷可證（見訴字卷第33至39頁），符合毒品危害防制條例第17條第1項減刑之要件，應應適用該規定減輕其刑。再被告於員警執行盤查，尚未發覺其上開施用毒品犯罪前，主動取出持有之第一級毒品海洛因1包予警方扣案，並於警詢時坦承施用第一級毒品犯行，而同意採尿送驗，有本院公務電話記錄及被告之警詢筆錄、高雄市政府警察局新興分局刑事案件移送書在卷可證（見審訴卷第19頁、警卷第1頁反面至2頁、偵卷第1頁），堪認係對於未發覺之罪自首而受裁判，爰依刑法第62條前段規定，減輕其刑。被告有上開數加重、減輕事由，應依刑法第71條規定，先加後減，並遞減之。爰審酌被告前經觀察勒戒、強制戒治，及法院以其犯施用第二級毒品罪，判處有期徒刑8月，有臺灣高等法院被告前案紀錄表在卷可查，猶未能戒絕毒癮，再犯本案施用毒品犯行，實屬不該，惟念施用毒品乃自戕行為，對社會造成之危害尚非直接至鉅，且犯後自首並坦承犯行，更配合供出毒品上游，態度尚佳等一切情狀，爰量處如主文所示之刑，及諭知易科罰金之折算標準，末扣案之白色粉末1包，經送高雄市立凱旋醫院檢驗結果，檢出海洛因成分（驗前凈重分別為0.028公克，驗後淨重為0.018公克），有該醫院出具之濫用藥物成品檢驗鑑定書在卷可稽，自屬查獲之第一級毒品無訛，應依毒品危害防制條例第18條第1項前段之規定，宣告沒收銷燬；另包裝毒品之包裝袋1只，因與其上所殘留之毒品難以析離，且無析離之實益與必要，應視同毒品，一併沒收銷燬之；至送驗耗損部分之毒品因已滅失，爰不另宣告沒收銷燬，附此敘明。據上論斷，應依刑事訴訟法第299條第1項前段，毒品危害防制條例第10條第1項、第17條第1項、第18條第1項前段，刑法第11條、第62條前段、第47條第1項、第41條第1項前段，判決如主文。本案經檢察官黃世勳到庭執行職務。中華民國100年10月13日刑事第十三庭審判長法官黃蕙芳法官陳采葳法官陳筱雯以上正本證明與原本無異。如不服本判決應於收受送達後10日內向本院提出上訴書狀，並應敘述具體理由；如未敘述上訴理由者，應於上訴期間屆滿後20日內向本院補提理由書（均須按他造當事人之人數附繕本）「切勿逕送上級法院」。中華民國100年10月13日書記官陳建琪附錄本案論罪科刑法條：毒品危害防制條例第10條第1項施用第一級毒品者，處6月以上5年以下有期徒刑。",
  "characters": {
    "judges": [
      "黃蕙芳",
      "陳采葳",
      "陳筱雯"
    ],
    "prosecutors": [
      "黃世勳"
    ],
    "lawyers": [

    ],
    "clerks": [
      "陳建琪"
    ],
    "plaintiffs": [

    ],
    "defendants": [
      "黃慶文"
    ],
    "prosecutor_office": [
      "臺灣高雄地方法院檢察署檢察官"
    ],
    "creditors": [

    ],
    "debtors": [

    ],
    "judicial_associate_officer": [

    ]
  },
  "adjudged_at": "2011-10-13",
  "created_at": "2016-02-14 06:56:22",
  "updated_at": "2016-02-14 06:56:22"
}