{
  "identify": "ILD-93-家訴-37-20050428-1",
  "court": {
    "name": "臺灣宜蘭地方法院",
    "code": "ILD"
  },
  "division": {
    "name": "民事",
    "code": "V"
  },
  "year": 93,
  "word": "家訴",
  "number": "37",
  "jcheck": "1",
  "reason": "分割遺產",
  "content": "臺灣宜蘭地方法院民事判決              93年度家訴字第37號\n原      告  Ｂ○○\n訴訟代理人  林健智律師\n被      告  玄○○\n            宇○○\n            宙○○\n            乙○○\n            地○○\n            甲○○\n            丁○○\n            庚○○\n            己○○\n            戊○○\n            丙○○\n            申○○○\n            未○○○\n            Ｄ○○\n            寅○○○\n            亥○○○\n            午○○○\n兼上列17人\n訴訟代理人  Ａ○○\n被      告  Ｉ○○\n            酉○○\n            戌○○\n            Ｌ○○○\n            黃○○\n            Ｅ○○\n            丑○○○\n上 列 7 人\n訴訟代理人  藍祐氶\n被      告  Ｆ○○\n            辛○○\n            天○○\n            Ｊ○○\n            Ｎ○○\n            壬○○○\n            癸○○○\n兼上列 7人\n訴訟代理人  Ｃ○○\n被      告  Ｋ○○○\n兼上列 1人\n訴訟代理人  Ｍ○○\n被      告  Ｈ○○\n            Ｇ○○\n            巳○○○\n            辰○○\n            卯○○\n            財政部國有財產局臺灣南區辦事處（黃鐘標遺產管\n            理人）\n上 列 1 人\n法定代理人  莊翠雲\n訴訟代理人  子○○\n上列當事人間請求分割遺產事件，本院於民國94年4月14日言詞辯\n論終結，判決如下：\n    主      文\n兩造公同共有坐落於宜蘭縣冬山鄉○○段50、76-1、145、192地\n號，面積分別為2106、1444、2188、1969平方公尺之田地按附表\n所示之應繼分比例分配兩造分別共有。\n訴訟費用由兩造按附表所示應繼分比例負擔。\n    事實及理由\n一、本件被告巳○○○、辰○○、卯○○經合法通知，未於言詞\n    辯論其日到場，被告Ｉ○○、酉○○、戌○○、Ｌ○○○、\n    黃○○、Ｅ○○、丑○○○、Ｇ○○經合法通知，未於最後\n    言詞辯論期日到場，均核無民事訴訟法第386條各款所列各\n    款情形，爰依原告之聲請，由其一造辯論而為判決。\n二、原告起訴主張坐落於宜蘭縣冬山鄉○○段50、76-1、145、\n    192地號，面積分別為2106、1444、2188、1969平方公尺之\n    田地（下稱系爭4筆田地）原為被繼承人藍老屋所有，因藍\n    老屋於民國29年2月4日死亡，系爭4筆田地雖已辦理繼承登\n    記而為兩造公同共有，惟迄未分割等情，業據其提出土地登\n    記謄本4件、繼承系統表1件及被繼承人藍老屋、兩造41人之\n    真實。\n三、按繼承人有數人時，在分割遺產前，各繼承人對於遺產全部\n    為公同共有。次按繼承人得隨時請求分割遺產，但法律另有\n    規定或契約另有訂定者，不在此限。又公同共有物分割之方\n    法，除法律另有規定外，應依關於共有物分割之規定。復按\n    共有人得隨時請求分割共有物，但因物之使用目的不能分割\n    或契約定有不可分割之期限者，不在此限；又共有物之分割\n    ，依共有人協議之方法行之，分割方法不能協議者，法院得\n    因任何共有人之聲請，以原物分配於各共有人或變賣共有物\n    ，以價金分配於各共有人。民法第1151條、第1164條、第\n    830條第2項、第823條、第824條分別定有明文。系爭4筆田\n    地為兩造公同共有，並無不能分割之情形，亦無不分割之約\n    定，因被告多人未於93年11月24日之調解期日到場，致無法\n    達成分割之協議，則原告依民法第1164條規定請求裁判分割\n    系爭4筆田地，自屬有據，應予准許。再分割之方法，不以\n    民法第824條第2項規定為限，將繼承人公同共有遺產變更為\n    分別共有，亦屬分割遺產方式之一，此觀最高法院91年度臺\n    上字第1754號、85年度臺上字第1873號判決自明，故原告主\n    張將系爭4筆田地以原物分配方式分配予兩造，並由兩造按\n    附表所示應繼分比例分別共有，既未經被告反對，其主張之\n    分割方式應屬可採。從而，原告依民法第1164條規定請求分\n    割系爭4筆田地，由兩造按如附表所示應繼分比例分別共有\n    為有理由，應予准許。\n四、又分割遺產之訴，係必要共同訴訟，原、被告之間本可互換\n    地位，本件原告起訴雖於法有據，但被告之涉訟實因訴訟性\n    質所不得不然，故判令被告負擔訴訟費用顯然有失公平，是\n    以本院認本件之訴訟費用應由兩造依應繼分之比例分擔較為\n    公允，爰諭知如主文第2項所示。\n五、據上論結，本件原告之訴為有理由，依民事訴訟法第385條\n    第1項前段、第78條、第80條之1、第85條第1項但書，判決\n    如主文。\n中    華    民    國    94    年    4     月    28    日\n                      臺灣宜蘭地方法院家事法庭\n                          法      官    周健忠\n以上正本與原本無異。\n如不服本判決，應於收受送達後20日內向本院提出上訴狀（應附\n繕本）。\n中    華    民    國    94    年    4     月    29    日\n                          書  記  官    吳慧芳\n",
  "structure": {
    "main": "兩造公同共有坐落於宜蘭縣冬山鄉○○段50、76-1、145、192地\n號，面積分別為2106、1444、2188、1969平方公尺之田地按附表\n所示之應繼分比例分配兩造分別共有。\n訴訟費用由兩造按附表所示應繼分比例負擔。",
    "fact": "一、本件被告巳○○○、辰○○、卯○○經合法通知，未於言詞\n    辯論其日到場，被告Ｉ○○、酉○○、戌○○、Ｌ○○○、\n    黃○○、Ｅ○○、丑○○○、Ｇ○○經合法通知，未於最後\n    言詞辯論期日到場，均核無民事訴訟法第386條各款所列各\n    款情形，爰依原告之聲請，由其一造辯論而為判決。\n二、原告起訴主張坐落於宜蘭縣冬山鄉○○段50、76-1、145、\n    192地號，面積分別為2106、1444、2188、1969平方公尺之\n    田地（下稱系爭4筆田地）原為被繼承人藍老屋所有，因藍\n    老屋於民國29年2月4日死亡，系爭4筆田地雖已辦理繼承登\n    記而為兩造公同共有，惟迄未分割等情，業據其提出土地登\n    記謄本4件、繼承系統表1件及被繼承人藍老屋、兩造41人之\n    真實。\n三、按繼承人有數人時，在分割遺產前，各繼承人對於遺產全部\n    為公同共有。次按繼承人得隨時請求分割遺產，但法律另有\n    規定或契約另有訂定者，不在此限。又公同共有物分割之方\n    法，除法律另有規定外，應依關於共有物分割之規定。復按\n    共有人得隨時請求分割共有物，但因物之使用目的不能分割\n    或契約定有不可分割之期限者，不在此限；又共有物之分割\n    ，依共有人協議之方法行之，分割方法不能協議者，法院得\n    因任何共有人之聲請，以原物分配於各共有人或變賣共有物\n    ，以價金分配於各共有人。民法第1151條、第1164條、第\n    830條第2項、第823條、第824條分別定有明文。系爭4筆田\n    地為兩造公同共有，並無不能分割之情形，亦無不分割之約\n    定，因被告多人未於93年11月24日之調解期日到場，致無法\n    達成分割之協議，則原告依民法第1164條規定請求裁判分割\n    系爭4筆田地，自屬有據，應予准許。再分割之方法，不以\n    民法第824條第2項規定為限，將繼承人公同共有遺產變更為\n    分別共有，亦屬分割遺產方式之一，此觀最高法院91年度臺\n    上字第1754號、85年度臺上字第1873號判決自明，故原告主\n    張將系爭4筆田地以原物分配方式分配予兩造，並由兩造按\n    附表所示應繼分比例分別共有，既未經被告反對，其主張之\n    分割方式應屬可採。從而，原告依民法第1164條規定請求分\n    割系爭4筆田地，由兩造按如附表所示應繼分比例分別共有\n    為有理由，應予准許。\n四、又分割遺產之訴，係必要共同訴訟，原、被告之間本可互換\n    地位，本件原告起訴雖於法有據，但被告之涉訟實因訴訟性\n    質所不得不然，故判令被告負擔訴訟費用顯然有失公平，是\n    以本院認本件之訴訟費用應由兩造依應繼分之比例分擔較為\n    公允，爰諭知如主文第2項所示。\n五、據上論結，本件原告之訴為有理由，依民事訴訟法第385條\n    第1項前段、第78條、第80條之1、第85條第1項但書，判決\n    如主文。",
    "reason": "一、本件被告巳○○○、辰○○、卯○○經合法通知，未於言詞\n    辯論其日到場，被告Ｉ○○、酉○○、戌○○、Ｌ○○○、\n    黃○○、Ｅ○○、丑○○○、Ｇ○○經合法通知，未於最後\n    言詞辯論期日到場，均核無民事訴訟法第386條各款所列各\n    款情形，爰依原告之聲請，由其一造辯論而為判決。\n二、原告起訴主張坐落於宜蘭縣冬山鄉○○段50、76-1、145、\n    192地號，面積分別為2106、1444、2188、1969平方公尺之\n    田地（下稱系爭4筆田地）原為被繼承人藍老屋所有，因藍\n    老屋於民國29年2月4日死亡，系爭4筆田地雖已辦理繼承登\n    記而為兩造公同共有，惟迄未分割等情，業據其提出土地登\n    記謄本4件、繼承系統表1件及被繼承人藍老屋、兩造41人之\n    真實。\n三、按繼承人有數人時，在分割遺產前，各繼承人對於遺產全部\n    為公同共有。次按繼承人得隨時請求分割遺產，但法律另有\n    規定或契約另有訂定者，不在此限。又公同共有物分割之方\n    法，除法律另有規定外，應依關於共有物分割之規定。復按\n    共有人得隨時請求分割共有物，但因物之使用目的不能分割\n    或契約定有不可分割之期限者，不在此限；又共有物之分割\n    ，依共有人協議之方法行之，分割方法不能協議者，法院得\n    因任何共有人之聲請，以原物分配於各共有人或變賣共有物\n    ，以價金分配於各共有人。民法第1151條、第1164條、第\n    830條第2項、第823條、第824條分別定有明文。系爭4筆田\n    地為兩造公同共有，並無不能分割之情形，亦無不分割之約\n    定，因被告多人未於93年11月24日之調解期日到場，致無法\n    達成分割之協議，則原告依民法第1164條規定請求裁判分割\n    系爭4筆田地，自屬有據，應予准許。再分割之方法，不以\n    民法第824條第2項規定為限，將繼承人公同共有遺產變更為\n    分別共有，亦屬分割遺產方式之一，此觀最高法院91年度臺\n    上字第1754號、85年度臺上字第1873號判決自明，故原告主\n    張將系爭4筆田地以原物分配方式分配予兩造，並由兩造按\n    附表所示應繼分比例分別共有，既未經被告反對，其主張之\n    分割方式應屬可採。從而，原告依民法第1164條規定請求分\n    割系爭4筆田地，由兩造按如附表所示應繼分比例分別共有\n    為有理由，應予准許。\n四、又分割遺產之訴，係必要共同訴訟，原、被告之間本可互換\n    地位，本件原告起訴雖於法有據，但被告之涉訟實因訴訟性\n    質所不得不然，故判令被告負擔訴訟費用顯然有失公平，是\n    以本院認本件之訴訟費用應由兩造依應繼分之比例分擔較為\n    公允，爰諭知如主文第2項所示。\n五、據上論結，本件原告之訴為有理由，依民事訴訟法第385條\n    第1項前段、第78條、第80條之1、第85條第1項但書，判決\n    如主文。"
  },
  "search": "臺灣宜蘭地方法院民事判決93年度家訴字第37號原告Ｂ○○訴訟代理人林健智律師被告玄○○宇○○宙○○乙○○地○○甲○○丁○○庚○○己○○戊○○丙○○申○○○未○○○Ｄ○○寅○○○亥○○○午○○○兼上列17人訴訟代理人Ａ○○被告Ｉ○○酉○○戌○○Ｌ○○○黃○○Ｅ○○丑○○○上列7人訴訟代理人藍祐氶被告Ｆ○○辛○○天○○Ｊ○○Ｎ○○壬○○○癸○○○兼上列7人訴訟代理人Ｃ○○被告Ｋ○○○兼上列1人訴訟代理人Ｍ○○被告Ｈ○○Ｇ○○巳○○○辰○○卯○○財政部國有財產局臺灣南區辦事處（黃鐘標遺產管理人）上列1人法定代理人莊翠雲訴訟代理人子○○上列當事人間請求分割遺產事件，本院於民國94年4月14日言詞辯論終結，判決如下：主文兩造公同共有坐落於宜蘭縣冬山鄉○○段50、76-1、145、192地號，面積分別為2106、1444、2188、1969平方公尺之田地按附表所示之應繼分比例分配兩造分別共有。訴訟費用由兩造按附表所示應繼分比例負擔。事實及理由一、本件被告巳○○○、辰○○、卯○○經合法通知，未於言詞辯論其日到場，被告Ｉ○○、酉○○、戌○○、Ｌ○○○、黃○○、Ｅ○○、丑○○○、Ｇ○○經合法通知，未於最後言詞辯論期日到場，均核無民事訴訟法第386條各款所列各款情形，爰依原告之聲請，由其一造辯論而為判決。二、原告起訴主張坐落於宜蘭縣冬山鄉○○段50、76-1、145、192地號，面積分別為2106、1444、2188、1969平方公尺之田地（下稱系爭4筆田地）原為被繼承人藍老屋所有，因藍老屋於民國29年2月4日死亡，系爭4筆田地雖已辦理繼承登記而為兩造公同共有，惟迄未分割等情，業據其提出土地登記謄本4件、繼承系統表1件及被繼承人藍老屋、兩造41人之真實。三、按繼承人有數人時，在分割遺產前，各繼承人對於遺產全部為公同共有。次按繼承人得隨時請求分割遺產，但法律另有規定或契約另有訂定者，不在此限。又公同共有物分割之方法，除法律另有規定外，應依關於共有物分割之規定。復按共有人得隨時請求分割共有物，但因物之使用目的不能分割或契約定有不可分割之期限者，不在此限；又共有物之分割，依共有人協議之方法行之，分割方法不能協議者，法院得因任何共有人之聲請，以原物分配於各共有人或變賣共有物，以價金分配於各共有人。民法第1151條、第1164條、第830條第2項、第823條、第824條分別定有明文。系爭4筆田地為兩造公同共有，並無不能分割之情形，亦無不分割之約定，因被告多人未於93年11月24日之調解期日到場，致無法達成分割之協議，則原告依民法第1164條規定請求裁判分割系爭4筆田地，自屬有據，應予准許。再分割之方法，不以民法第824條第2項規定為限，將繼承人公同共有遺產變更為分別共有，亦屬分割遺產方式之一，此觀最高法院91年度臺上字第1754號、85年度臺上字第1873號判決自明，故原告主張將系爭4筆田地以原物分配方式分配予兩造，並由兩造按附表所示應繼分比例分別共有，既未經被告反對，其主張之分割方式應屬可採。從而，原告依民法第1164條規定請求分割系爭4筆田地，由兩造按如附表所示應繼分比例分別共有為有理由，應予准許。四、又分割遺產之訴，係必要共同訴訟，原、被告之間本可互換地位，本件原告起訴雖於法有據，但被告之涉訟實因訴訟性質所不得不然，故判令被告負擔訴訟費用顯然有失公平，是以本院認本件之訴訟費用應由兩造依應繼分之比例分擔較為公允，爰諭知如主文第2項所示。五、據上論結，本件原告之訴為有理由，依民事訴訟法第385條第1項前段、第78條、第80條之1、第85條第1項但書，判決如主文。中華民國94年4月28日臺灣宜蘭地方法院家事法庭法官周健忠以上正本與原本無異。如不服本判決，應於收受送達後20日內向本院提出上訴狀（應附繕本）。中華民國94年4月29日書記官吳慧芳",
  "characters": {
    "judges": [
      "周健忠"
    ],
    "prosecutors": [

    ],
    "lawyers": [
      "林健智"
    ],
    "clerks": [

    ],
    "plaintiffs": [
      "Ｂ"
    ],
    "defendants": [
      "玄○○",
      "Ｉ○○",
      "Ｆ○○",
      "Ｋ○○○",
      "兼上列 1人",
      "Ｈ○○"
    ],
    "prosecutor_office": [

    ],
    "creditors": [

    ],
    "debtors": [

    ],
    "judicial_associate_officer": [

    ]
  },
  "adjudged_at": "2005-04-28",
  "created_at": "2016-02-06 18:20:13",
  "updated_at": "2016-02-06 18:20:13"
}