{
  "identify": "TNH-94-重上更(二)-40-20050428-1",
  "court": {
    "name": "臺灣高等法院",
    "code": "TNH"
  },
  "division": {
    "name": "刑事",
    "code": "M"
  },
  "year": 94,
  "word": "重上更(二)",
  "number": "40",
  "jcheck": "1",
  "reason": "偽造文書等",
  "content": "臺灣高等法院臺南分院刑事判決\n上  訴  人  臺灣臺南地方法院檢察署檢察官\n上  訴  人\n即  被  告  乙○○\n上  訴  人\n即  被  告  丙○○○\n上  被  告\n選任辯護人  蔡清河  律師\n上列上訴人因被告等偽造文書等案件，不服臺灣臺南地方法院88\n年度訴字第524號中華民國88年7月16日第一審判決（起訴案號：\n臺灣臺南地方法院檢察署87年度偵續字第150號），提起上訴，\n判決後，經最高法院第二次發回更審，本院判決如下：\n      主      文\n原判決撤銷。\n丙○○○、乙○○共同連續行使偽造私文書，足以生損害於他人\n，各處有期徒刑壹年。乙○○緩刑參年。\n偽造之標單上蔡朝琴、王清風、阿珍、徐安心之署押，均沒收。\n     事  實\n一、乙○○與丙○○○係夫妻二人，均明知經濟不佳而無清償能\n    力，於民國86年4月15日，在臺南縣歸仁鄉○○○路二七二\n    號住處，以乙○○名義為會首，由乙○○、丙○○○分別招\n    募甲○○等互助會會員，成立每月新臺幣（下同）1萬元之\n    互助會，連同會首共計26人之民間互助會，第一會由會員將\n    1萬元交由會首，第二會以後則由會員將欲標之利息寫於標\n    單上，並書上會員之姓名，以出價最高者得標。詎其等二人\n    竟共同基於概括意圖為自己不法所有，及行使偽造私文書之\n    犯意聯絡，於該會86年8月止會前之5月、6月及7月所開標之\n    第二、三、四次開標日期，連續推由丙○○○第二會冒用蔡\n    朝琴、王清風等名義，第三會冒用阿珍名義、第四會冒用徐\n    安心名義並偽造該等人名義之標單用以冒標，再由其連續向\n    其他互助會員詐稱第二、三、四次互助會，分別由蔡朝琴及\n    王清風、阿珍、徐安心得標，計詐得會款55萬9千8百元花用\n    （詳如附表之記載），均足生損害於蔡朝琴及王清風、阿珍\n    、徐安心及互助會員等人。\n二、案經甲○○訴由臺灣臺南地方法院檢察署檢察官偵查起訴。\n     理  由\n一、訊據上訴人即被告乙○○、丙○○○，固不諱言有以乙○○\n    名義召集上開互助會，並於第五會即止會之事實。惟均矢口\n    否認有何行使偽造私文書及詐欺之犯行，被告乙○○辯稱：\n    伊雖擔任會首及有招募部分會員，然該互助會皆由丙○○○\n    處理，伊未參與過問。被告丙○○○則辯稱：標會固有寫標\n    單，但無冒標情事，第二會確係由蔡朝琴、王清風共同標得\n    ，第三會是阿珍標得，第四會是徐安心標得，但由楊秋蘭頂\n    替，並無冒用他人名義標會詐取會款等語。\n二、惟查被告乙○○、丙○○○夫妻，確於86年4月15日以乙○\n    ○名義為會首，招募甲○○等互助會會員，成立每月新臺幣\n    （下同）1萬元之互助會，連同會首共計26人之民間互助會\n    之事實，業據乙○○、丙○○○供認在卷，並有互助會會單\n    附卷可按，上開互助會之召募及運作，據乙○○於偵查中稱\n    ：「這會是我太太在我沒空時，幫我收的，會員有部分我招\n    的，一部分在學校的是我太太招的」、（詳偵字第216號卷\n    第13頁）、「我們夫妻都有招會員，但對外都由我妻來負責\n    」、「因我妻是在學校工作，由她當會首較不合適，所以才\n    以我的名義當會首」（詳偵續字第150號卷第59頁），而丙\n    ○○○亦於偵查中供稱：「招會員一些是我先生乙○○招攬\n    的，其餘都由我主持」（詳偵續字第150號卷第69頁）、本\n    院前審亦稱：「會員我先生召的比較少，大多數是我召的，\n    會首是我先生」、「會錢大都交給我，而我先生召的人，有\n    的交給他，他再交給我」（詳本院上訴卷第43頁），足見被\n    告乙○○、丙○○○二人均有參與本件互助會之招攬、收取\n    會錢等相關事務無疑，被告乙○○辯稱：其未參與互助會事\n    宜云云，顯非事實，而不可採。\n三、本件互助會於標會時，欲參與競標之會員，需寫記載名字、\n    金額（即利息）之標單乙情，業據告訴人甲○○指訴明確（\n    詳偵續字第150號卷第107頁反面，本院更一卷第96頁），亦\n    為被告丙○○○所供認無訛（詳偵續卷第107頁），被告乙\n    ○○也供認：「每月自由競標，寫會單」等語（詳偵字卷第\n    14頁），復經證人即會員翁義明證述屬實（詳本院更一卷第\n    87頁至88頁），再參酌一般民間互助會開標之習慣，在競標\n    時亦多有寫標單，以資確定由何人以多少利息得標，惟在開\n    標確定後，亦多隨即將之銷毀丟棄不再保存等情，顯示告訴\n    人甲○○、被告乙○○、丙○○○、證人翁義明等就本件互\n    助會開標情形之上開指稱、供述、證述，符合一般民間互助\n    會開標之習慣，足認本件互助會於標會時，欲參加競標之會\n    員，均需寫記載名字、利息之標單，參與開標，以資確定由\n    何人、以多少利息得標無疑。\n四、至被告丙○○○雖辯稱：並無冒標情事，第二會係由蔡朝琴\n    、王清風標得，第三會是阿珍標得，第四會是徐安心標得，\n    但由楊秋蘭頂替等語，經查：\n    （一）證人王清風、蔡朝琴於原審中固證稱：「伊等共同標\n          得第三次或第四次會，再朋分會款」云云（詳原審卷\n          第84頁），以附合被告丙○○○之辯解，然上開證述\n          已與被告丙○○○在原審中所供陳：「第二會是會單\n          標的，他們二位金額一樣，所以一起標到，」（詳原\n          審卷第84頁）之事實不符，亦與被告丙○○○於偵查\n          中所稱：「是王清風標得後，給蔡朝琴收會款」（詳\n          偵續字第150號卷第35頁反面），會款並非由二位證\n          人朋分云云相左，且證人王清風、蔡朝琴就渠等之所\n          以會共同標會、事先有無聯絡等節，經本院前審隔離\n          訊問後，證人王清風係稱：「因當時兩人都欠錢用，\n          都想標會」、「我打電話給蔡朝琴，叫他打電話去標\n          的，我沒有打電話給會頭，我叫蔡朝琴打的」、「開\n          始標的第一會或第二會、惟證人蔡朝琴卻稱：「因為\n          我們兩個人的標金一樣才一起標的」、「我打電話跟\n          會頭說我要標多少利息，開標後會頭說王清風的標金\n          和我一樣，叫我們二個人自己去協調」、「開標前我\n          們沒有聯絡過，是各人自己去標，開標後會頭才告訴\n          我，我的利息和王清風一樣多，叫我們自己去協調，\n          看誰要讓誰，我們協調結果，決定兩個人一起標這一\n          會，一人分一半」（詳更一卷第88頁至第91頁），彼\n          此之陳述顯屬歧異矛盾，再證人蔡朝琴係被告乙○○\n          之弟，證人王清風係被告乙○○之姐夫，足見證人王\n          清風、蔡朝琴上開渠等二人共同標一會之證言，應屬\n          迴護之詞，殊不足取。\n    （二）被告丙○○○於原審中原係稱：「第三會由阿珍標到\n          ，阿珍為其朋友，名字並不清楚，阿珍我沒見過，是\n          她姪子來跟會，八十三年間即來跟會」、「阿珍是張\n          政吉的姪子，來繳會款的都是張政吉，標到多少錢已\n          忘了，標單也都丟掉了」、「標單是張政吉叫我寫名\n          字，因他怕太太知道，所以才用別人的名字」（詳原\n          審卷第58頁、第83頁），惟證人張政吉在原審卻證稱\n          ：「我都用張政吉或鄭先生名字跟會，我不認識阿珍\n          我沒有印象用阿珍名義跟過會」（詳原審卷第83頁）\n          ，是該所謂由阿珍標得會云者，亦非事實，而不足採\n          。至證人張政吉於本院前審審理時雖又證稱：「我跟\n          會有叫會頭寫我姪女阿珍名義跟會」（詳更一卷第92\n          頁），因與其前於原審中所為上開證述不符，應亦屬\n          附合被告辯解而為迴護之詞，不足採信，附此敘明。\n    （三）證人楊秋蘭於偵查、原審中固證稱：「我有借徐安心\n          的會款，再交給丙○○○」、「86年4月15日之互助\n          會，『我沒有標』，是徐安心標到後，我跟他換（即\n          向徐安心借會款），我有打電話跟徐安心講」云云（\n          詳偵續字第150號卷第69頁，原審卷第82頁反面），\n          惟因證人徐安心並未標得本件86年4月5日互助會之會\n          款，亦未將會款借給別人、或楊秋蘭，或由楊秋蘭頂\n          替等情，已據證人徐安心在偵查、原審中陳明（詳偵\n          續字第150號卷第114頁，原審卷第82頁），且證人楊\n          秋蘭在原審先則稱：「我有打電話跟徐安心講，要跟\n          他換」云云，繼於證人徐安心表示「未接到楊秋蘭電\n          話後」，即又改稱：「是我告訴楊秋惠叫他打電話給\n          徐安心，說要換成我標到會，我自己沒有打電話給徐\n          安心」云云（詳原審卷第82頁），亦見先後供述矛盾\n          不一而有瑕疵，況證人楊秋蘭又自承與被告丙○○○\n          為姊妹關係，是該證言顯係故為迴護被告之詞，難認\n          屬實情。另證人楊秋蘭於本院前審審理時雖亦證稱：\n          「第四會我要標，我打電話委託楊秋惠幫我標，但是\n          沒有標到，被徐安心標到，因為楊秋惠急用錢，我叫\n          楊秋惠去跟徐安心協調，看他願不願意把會讓給我，\n          後來楊秋惠告訴我說，徐安心答應先讓給我用」、「\n          我從頭到尾沒有與徐安心聯絡過，都是楊秋惠跟我講\n          的，所以我不知道實際情形。」（詳更一卷第94頁）\n          ，與證人楊秋蘭於原審中所為上開證述相左，復與證\n          人徐安心之證述亦不符，顯亦屬迴護之詞，均不足採\n          。綜上所述，顯見被告丙○○○上述無冒標互助會之\n          辯解，應非屬事實，而無可採信。\n    （四）被告乙○○與被告丙○○○具夫妻關係，於86年4月1\n          5日召集互助會，於取得首會款後未久之同年8月即行\n          止會，雖上開證人及告訴人等均稱標會之事務皆由被\n          告丙○○○處理。惟被告乙○○既自承有招募互助會\n          會員，並收取會款，已上前述，並曾因無力繳會款勸\n          被告丙○○○不要再招會等語在卷（見偵續字第150\n          號卷第59頁），再參諸被告丙○○○供稱：該互助會\n          之會員有一部份係由乙○○去招攬的，乙○○亦有在\n          收會款之情，亦如上述，是被告乙○○實早已知其等\n          應無任何清償資力，竟仍與被告丙○○○共同召集互\n          助會會員，且於冒標得會款後旋即倒會，顯見其等有\n          為自己不法所有之詐欺意圖，及行使偽造私文書之犯\n          意，暨互相利用他方行為以遂行犯罪目的之共同犯意\n          聯絡無疑。此外，復有互助會單影本附卷足稽。至被\n          告另稱已將會款退還會員云者，因詐欺犯為即成犯，\n          只要取得他人交付之財物即成罪，事後將財物返還，\n          並無礙於詐欺犯罪之成立。\n    （五）綜就上情參酌以觀，足認被告二人之否認犯罪及所辯\n          各節，要屬諉責推卸之詞，委無足取，本件事證明確\n          ，被告二人犯行均堪認定，應予依法論科。\n五、至最高法院發回意旨以：本案被告所詐取之互助會款若干應\n    予認定一節，經質之被告等均以事隔太久，互助會之標息若\n    干，已記不清楚，大概第二、三會在1600元左右，而第四會\n    在2500元左右，並同意第二、三會標息以1600元，第四會標\n    息以2500元計算，則以有利於被告上開標息計算，被告所冒\n    標之會款為55萬9千8百元，如附表所示。\n六、查本件互助會之標單，係於白紙上記載姓名及一定金額之標\n    息，既為被告及告訴人甲○○、證人翁義明於偵查中、本院\n    審理時供述、指訴、證述在卷，已如前述，則依民間互助會\n    之習慣，此乃表示某會員以多少利息標取會款之意思，為參\n    與競標互助會會款之用意證明，應屬刑法第220條第1項之準\n    私文書，被告行使偽造之各該標單，亦足生損害於告訴人及\n    其他活會會員。核被告二人所為，均係犯刑法第216條、第\n    210條之行使偽造私文書罪及第339條第1項之詐欺取財罪。\n    其等就該二犯罪之施行，被告彼此間互有犯意聯絡及行為分\n    擔，均應論以共同正犯。彼等偽造署押係偽造私文書之部分\n    行為，其偽造私文書之低度行為，已為其行使偽造私文書之\n    高度行為所吸收，均不另論罪。其等先後多次行使偽造私文\n    書及詐欺犯行，均各時間緊接，犯罪構成要件相同，顯均係\n    基於概括犯意而為，皆應依連續犯規定各以一罪論，並均依\n    法加重其刑。其等以一詐標行為同時詐騙數會員之會款，係\n    以一行為觸犯數罪名，應依想像競合犯之例從一罪處斷。其\n    等所犯上開二罪間，具有方法結果之牽連關係，為牽連犯，\n    應從一重之行使偽造私文書罪處斷。偽造之標會單上蔡朝琴\n    、王清風、阿珍、徐安心之署押，併依刑法第219條之規定\n    ，宣告沒收。\n七、原審法院認被告二人罪證明確，據予論罪科刑，固非無見，\n    惟查冒用他人名義在標單上書寫姓名及一定金額，依民間互\n    助會習慣，除表示投標會員之主體外，並表示該會員願意以\n    標單內所載之金額為標息而參與競標，非僅純為投標會員之\n    識別，故冒標於標單上仿偽造他人姓名，乃表示投標會員之\n    簽名意思，屬偽造之署押，依刑法第219條之規定，應為沒\n    收之諭知，法院並無裁量之餘地，原判決就被告所偽造標單\n    上之署押未予宣告沒收，尚有未洽，被告二人上訴意旨否認\n    犯罪，及檢察官上訴意旨認量刑偏輕，分別指摘原判決不當\n    ，雖均非可取，惟原判決既有可議，自應由本院將原判決予\n    以撤銷改判。爰審酌被告二人之素行、犯罪之動機、目的、\n    手段、所生危害、及其犯後態度等一切情狀，仍對其等各量\n    處如原判決所科之有期徒刑一年。又被告乙○○前未曾受有\n    期徒刑以上刑之宣告，此有其刑案資料查註紀錄表、及其全\n    國前案紀錄表在卷可佐，且念其夫妻均因本案遭判刑，倘均\n    入監執行其家庭勢必無人照拂，為免其家庭失序，本院因認\n    其經此偵審判刑教訓當已知所警惕，日後信無再犯之虞，其\n    所受宣告之刑以暫不執行為適當，爰併諭知緩刑參年，以勵\n    自新。至被告丙○○○，依卷存之刑案資料查註紀錄表，甫\n    因另案詐欺罪受有期徒刑10月執行完畢，依法自不得為緩刑\n    諭知，附此敘明。\n八、至被告丙○○○前經本院以87年度上易字第303號，於87年4\n    月14日，判處有期徒刑10月並已執行完畢之詐欺事實，經核\n    卷附之該案判決內容，其係於85年6月8日至86年3月底間，\n    連續藉詞其夫承包工程發生意外有工人死亡須理賠，而向他\n    人詐借款項花用，要與本案詐標會款之犯罪手法相異，且兩\n    案犯罪時間亦難認密接，即被告亦否認本案犯罪，是二案間\n    應無連續犯之適用，本案非該案判決效力所及，本院自得依\n    法就本案為實體之判決，併此敘明。\n九、據上論斷，應依刑事訴訟法第369條第1項前段、第364條、\n    第299條第1項前段，刑法第28條、第56條、第216條、第210\n    條、第339條第1項、第219條、第55條、第74條第1款、罰金\n    罰鍰提高標準條例第1條前段，判決如主文。\n本案經檢察官林炎昇到庭執行職務。\n中     華    民    國    94    年    4    月    28    日\n                   刑事第五庭     審判長法  官  楊明章\n                                        法  官  沈揚仁\n                                        法  官  戴勝利\n以上正本證明與原本無異。\n如不服本判決，應於收受本判決後十日內向本院提出上訴書狀。\n其未敘述上訴理由者並得於提起上訴後十日內向本院補提理由書\n狀（均須按他造當事人之人數附繕本）「切勿逕送上級法院」。\n                                        書記官  李珍鳳\n中    華    民    國    94    年    4     月    29    日\n附錄本案論罪科刑法條全文：\n刑法第二百十六條：行使第二百十條至第二百十五條之文書者，\n                  依偽造、變造文書或登載不實事項或使登載\n                  不實事項之規定處斷\n。刑法第二百十條：偽造、變造私文書，足以生損害於公眾或他\n                  人者，處五年以下有期徒刑。\n 附  表\n┌───────────────────────────┐\n│      年４月日起會，每會１萬元之互助會會員名    │\n├──┬─────┬─────┬──────┬─────┤\n│編號│冒標會員  │ 冒標標息 │ 所得金額   │備註      │\n│    │          │（新台幣）│（新台幣）  │          │\n├──┼─────┼─────┼──────┼─────┤\n│ 1. │蔡朝琴    │ 1,600元  │ 201,600元  │第二會    │\n│    │王清風    │          │            │          │\n├──┼─────┼─────┼──────┼─────┤\n│ 2. │阿珍      │ 1,600元  │ 193,200元  │第三會    │\n│    │          │          │            │          │\n├──┼─────┼─────┼──────┼─────┤\n│ 3. │徐安心    │ 2,500元  │ 165,000元  │第四會    │\n│    │          │          │            │          │\n├──┴─────┴─────┴──────┴─────┤\n│                         合計：559,800元              │\n└───────────────────────────┘\n",
  "structure": {
    "main": "原判決撤銷。\n丙○○○、乙○○共同連續行使偽造私文書，足以生損害於他人\n，各處有期徒刑壹年。乙○○緩刑參年。\n偽造之標單上蔡朝琴、王清風、阿珍、徐安心之署押，均沒收。",
    "fact": "一、乙○○與丙○○○係夫妻二人，均明知經濟不佳而無清償能\n    力，於民國86年4月15日，在臺南縣歸仁鄉○○○路二七二\n    號住處，以乙○○名義為會首，由乙○○、丙○○○分別招\n    募甲○○等互助會會員，成立每月新臺幣（下同）1萬元之\n    互助會，連同會首共計26人之民間互助會，第一會由會員將\n    1萬元交由會首，第二會以後則由會員將欲標之利息寫於標\n    單上，並書上會員之姓名，以出價最高者得標。詎其等二人\n    竟共同基於概括意圖為自己不法所有，及行使偽造私文書之\n    犯意聯絡，於該會86年8月止會前之5月、6月及7月所開標之\n    第二、三、四次開標日期，連續推由丙○○○第二會冒用蔡\n    朝琴、王清風等名義，第三會冒用阿珍名義、第四會冒用徐\n    安心名義並偽造該等人名義之標單用以冒標，再由其連續向\n    其他互助會員詐稱第二、三、四次互助會，分別由蔡朝琴及\n    王清風、阿珍、徐安心得標，計詐得會款55萬9千8百元花用\n    （詳如附表之記載），均足生損害於蔡朝琴及王清風、阿珍\n    、徐安心及互助會員等人。\n二、案經甲○○訴由臺灣臺南地方法院檢察署檢察官偵查起訴。",
    "reason": "一、訊據上訴人即被告乙○○、丙○○○，固不諱言有以乙○○\n    名義召集上開互助會，並於第五會即止會之事實。惟均矢口\n    否認有何行使偽造私文書及詐欺之犯行，被告乙○○辯稱：\n    伊雖擔任會首及有招募部分會員，然該互助會皆由丙○○○\n    處理，伊未參與過問。被告丙○○○則辯稱：標會固有寫標\n    單，但無冒標情事，第二會確係由蔡朝琴、王清風共同標得\n    ，第三會是阿珍標得，第四會是徐安心標得，但由楊秋蘭頂\n    替，並無冒用他人名義標會詐取會款等語。\n二、惟查被告乙○○、丙○○○夫妻，確於86年4月15日以乙○\n    ○名義為會首，招募甲○○等互助會會員，成立每月新臺幣\n    （下同）1萬元之互助會，連同會首共計26人之民間互助會\n    之事實，業據乙○○、丙○○○供認在卷，並有互助會會單\n    附卷可按，上開互助會之召募及運作，據乙○○於偵查中稱\n    ：「這會是我太太在我沒空時，幫我收的，會員有部分我招\n    的，一部分在學校的是我太太招的」、（詳偵字第216號卷\n    第13頁）、「我們夫妻都有招會員，但對外都由我妻來負責\n    」、「因我妻是在學校工作，由她當會首較不合適，所以才\n    以我的名義當會首」（詳偵續字第150號卷第59頁），而丙\n    ○○○亦於偵查中供稱：「招會員一些是我先生乙○○招攬\n    的，其餘都由我主持」（詳偵續字第150號卷第69頁）、本\n    院前審亦稱：「會員我先生召的比較少，大多數是我召的，\n    會首是我先生」、「會錢大都交給我，而我先生召的人，有\n    的交給他，他再交給我」（詳本院上訴卷第43頁），足見被\n    告乙○○、丙○○○二人均有參與本件互助會之招攬、收取\n    會錢等相關事務無疑，被告乙○○辯稱：其未參與互助會事\n    宜云云，顯非事實，而不可採。\n三、本件互助會於標會時，欲參與競標之會員，需寫記載名字、\n    金額（即利息）之標單乙情，業據告訴人甲○○指訴明確（\n    詳偵續字第150號卷第107頁反面，本院更一卷第96頁），亦\n    為被告丙○○○所供認無訛（詳偵續卷第107頁），被告乙\n    ○○也供認：「每月自由競標，寫會單」等語（詳偵字卷第\n    14頁），復經證人即會員翁義明證述屬實（詳本院更一卷第\n    87頁至88頁），再參酌一般民間互助會開標之習慣，在競標\n    時亦多有寫標單，以資確定由何人以多少利息得標，惟在開\n    標確定後，亦多隨即將之銷毀丟棄不再保存等情，顯示告訴\n    人甲○○、被告乙○○、丙○○○、證人翁義明等就本件互\n    助會開標情形之上開指稱、供述、證述，符合一般民間互助\n    會開標之習慣，足認本件互助會於標會時，欲參加競標之會\n    員，均需寫記載名字、利息之標單，參與開標，以資確定由\n    何人、以多少利息得標無疑。\n四、至被告丙○○○雖辯稱：並無冒標情事，第二會係由蔡朝琴\n    、王清風標得，第三會是阿珍標得，第四會是徐安心標得，\n    但由楊秋蘭頂替等語，經查：\n    （一）證人王清風、蔡朝琴於原審中固證稱：「伊等共同標\n          得第三次或第四次會，再朋分會款」云云（詳原審卷\n          第84頁），以附合被告丙○○○之辯解，然上開證述\n          已與被告丙○○○在原審中所供陳：「第二會是會單\n          標的，他們二位金額一樣，所以一起標到，」（詳原\n          審卷第84頁）之事實不符，亦與被告丙○○○於偵查\n          中所稱：「是王清風標得後，給蔡朝琴收會款」（詳\n          偵續字第150號卷第35頁反面），會款並非由二位證\n          人朋分云云相左，且證人王清風、蔡朝琴就渠等之所\n          以會共同標會、事先有無聯絡等節，經本院前審隔離\n          訊問後，證人王清風係稱：「因當時兩人都欠錢用，\n          都想標會」、「我打電話給蔡朝琴，叫他打電話去標\n          的，我沒有打電話給會頭，我叫蔡朝琴打的」、「開\n          始標的第一會或第二會、惟證人蔡朝琴卻稱：「因為\n          我們兩個人的標金一樣才一起標的」、「我打電話跟\n          會頭說我要標多少利息，開標後會頭說王清風的標金\n          和我一樣，叫我們二個人自己去協調」、「開標前我\n          們沒有聯絡過，是各人自己去標，開標後會頭才告訴\n          我，我的利息和王清風一樣多，叫我們自己去協調，\n          看誰要讓誰，我們協調結果，決定兩個人一起標這一\n          會，一人分一半」（詳更一卷第88頁至第91頁），彼\n          此之陳述顯屬歧異矛盾，再證人蔡朝琴係被告乙○○\n          之弟，證人王清風係被告乙○○之姐夫，足見證人王\n          清風、蔡朝琴上開渠等二人共同標一會之證言，應屬\n          迴護之詞，殊不足取。\n    （二）被告丙○○○於原審中原係稱：「第三會由阿珍標到\n          ，阿珍為其朋友，名字並不清楚，阿珍我沒見過，是\n          她姪子來跟會，八十三年間即來跟會」、「阿珍是張\n          政吉的姪子，來繳會款的都是張政吉，標到多少錢已\n          忘了，標單也都丟掉了」、「標單是張政吉叫我寫名\n          字，因他怕太太知道，所以才用別人的名字」（詳原\n          審卷第58頁、第83頁），惟證人張政吉在原審卻證稱\n          ：「我都用張政吉或鄭先生名字跟會，我不認識阿珍\n          我沒有印象用阿珍名義跟過會」（詳原審卷第83頁）\n          ，是該所謂由阿珍標得會云者，亦非事實，而不足採\n          。至證人張政吉於本院前審審理時雖又證稱：「我跟\n          會有叫會頭寫我姪女阿珍名義跟會」（詳更一卷第92\n          頁），因與其前於原審中所為上開證述不符，應亦屬\n          附合被告辯解而為迴護之詞，不足採信，附此敘明。\n    （三）證人楊秋蘭於偵查、原審中固證稱：「我有借徐安心\n          的會款，再交給丙○○○」、「86年4月15日之互助\n          會，『我沒有標』，是徐安心標到後，我跟他換（即\n          向徐安心借會款），我有打電話跟徐安心講」云云（\n          詳偵續字第150號卷第69頁，原審卷第82頁反面），\n          惟因證人徐安心並未標得本件86年4月5日互助會之會\n          款，亦未將會款借給別人、或楊秋蘭，或由楊秋蘭頂\n          替等情，已據證人徐安心在偵查、原審中陳明（詳偵\n          續字第150號卷第114頁，原審卷第82頁），且證人楊\n          秋蘭在原審先則稱：「我有打電話跟徐安心講，要跟\n          他換」云云，繼於證人徐安心表示「未接到楊秋蘭電\n          話後」，即又改稱：「是我告訴楊秋惠叫他打電話給\n          徐安心，說要換成我標到會，我自己沒有打電話給徐\n          安心」云云（詳原審卷第82頁），亦見先後供述矛盾\n          不一而有瑕疵，況證人楊秋蘭又自承與被告丙○○○\n          為姊妹關係，是該證言顯係故為迴護被告之詞，難認\n          屬實情。另證人楊秋蘭於本院前審審理時雖亦證稱：\n          「第四會我要標，我打電話委託楊秋惠幫我標，但是\n          沒有標到，被徐安心標到，因為楊秋惠急用錢，我叫\n          楊秋惠去跟徐安心協調，看他願不願意把會讓給我，\n          後來楊秋惠告訴我說，徐安心答應先讓給我用」、「\n          我從頭到尾沒有與徐安心聯絡過，都是楊秋惠跟我講\n          的，所以我不知道實際情形。」（詳更一卷第94頁）\n          ，與證人楊秋蘭於原審中所為上開證述相左，復與證\n          人徐安心之證述亦不符，顯亦屬迴護之詞，均不足採\n          。綜上所述，顯見被告丙○○○上述無冒標互助會之\n          辯解，應非屬事實，而無可採信。\n    （四）被告乙○○與被告丙○○○具夫妻關係，於86年4月1\n          5日召集互助會，於取得首會款後未久之同年8月即行\n          止會，雖上開證人及告訴人等均稱標會之事務皆由被\n          告丙○○○處理。惟被告乙○○既自承有招募互助會\n          會員，並收取會款，已上前述，並曾因無力繳會款勸\n          被告丙○○○不要再招會等語在卷（見偵續字第150\n          號卷第59頁），再參諸被告丙○○○供稱：該互助會\n          之會員有一部份係由乙○○去招攬的，乙○○亦有在\n          收會款之情，亦如上述，是被告乙○○實早已知其等\n          應無任何清償資力，竟仍與被告丙○○○共同召集互\n          助會會員，且於冒標得會款後旋即倒會，顯見其等有\n          為自己不法所有之詐欺意圖，及行使偽造私文書之犯\n          意，暨互相利用他方行為以遂行犯罪目的之共同犯意\n          聯絡無疑。此外，復有互助會單影本附卷足稽。至被\n          告另稱已將會款退還會員云者，因詐欺犯為即成犯，\n          只要取得他人交付之財物即成罪，事後將財物返還，\n          並無礙於詐欺犯罪之成立。\n    （五）綜就上情參酌以觀，足認被告二人之否認犯罪及所辯\n          各節，要屬諉責推卸之詞，委無足取，本件事證明確\n          ，被告二人犯行均堪認定，應予依法論科。\n五、至最高法院發回意旨以：本案被告所詐取之互助會款若干應\n    予認定一節，經質之被告等均以事隔太久，互助會之標息若\n    干，已記不清楚，大概第二、三會在1600元左右，而第四會\n    在2500元左右，並同意第二、三會標息以1600元，第四會標\n    息以2500元計算，則以有利於被告上開標息計算，被告所冒\n    標之會款為55萬9千8百元，如附表所示。\n六、查本件互助會之標單，係於白紙上記載姓名及一定金額之標\n    息，既為被告及告訴人甲○○、證人翁義明於偵查中、本院\n    審理時供述、指訴、證述在卷，已如前述，則依民間互助會\n    之習慣，此乃表示某會員以多少利息標取會款之意思，為參\n    與競標互助會會款之用意證明，應屬刑法第220條第1項之準\n    私文書，被告行使偽造之各該標單，亦足生損害於告訴人及\n    其他活會會員。核被告二人所為，均係犯刑法第216條、第\n    210條之行使偽造私文書罪及第339條第1項之詐欺取財罪。\n    其等就該二犯罪之施行，被告彼此間互有犯意聯絡及行為分\n    擔，均應論以共同正犯。彼等偽造署押係偽造私文書之部分\n    行為，其偽造私文書之低度行為，已為其行使偽造私文書之\n    高度行為所吸收，均不另論罪。其等先後多次行使偽造私文\n    書及詐欺犯行，均各時間緊接，犯罪構成要件相同，顯均係\n    基於概括犯意而為，皆應依連續犯規定各以一罪論，並均依\n    法加重其刑。其等以一詐標行為同時詐騙數會員之會款，係\n    以一行為觸犯數罪名，應依想像競合犯之例從一罪處斷。其\n    等所犯上開二罪間，具有方法結果之牽連關係，為牽連犯，\n    應從一重之行使偽造私文書罪處斷。偽造之標會單上蔡朝琴\n    、王清風、阿珍、徐安心之署押，併依刑法第219條之規定\n    ，宣告沒收。\n七、原審法院認被告二人罪證明確，據予論罪科刑，固非無見，\n    惟查冒用他人名義在標單上書寫姓名及一定金額，依民間互\n    助會習慣，除表示投標會員之主體外，並表示該會員願意以\n    標單內所載之金額為標息而參與競標，非僅純為投標會員之\n    識別，故冒標於標單上仿偽造他人姓名，乃表示投標會員之\n    簽名意思，屬偽造之署押，依刑法第219條之規定，應為沒\n    收之諭知，法院並無裁量之餘地，原判決就被告所偽造標單\n    上之署押未予宣告沒收，尚有未洽，被告二人上訴意旨否認\n    犯罪，及檢察官上訴意旨認量刑偏輕，分別指摘原判決不當\n    ，雖均非可取，惟原判決既有可議，自應由本院將原判決予\n    以撤銷改判。爰審酌被告二人之素行、犯罪之動機、目的、\n    手段、所生危害、及其犯後態度等一切情狀，仍對其等各量\n    處如原判決所科之有期徒刑一年。又被告乙○○前未曾受有\n    期徒刑以上刑之宣告，此有其刑案資料查註紀錄表、及其全\n    國前案紀錄表在卷可佐，且念其夫妻均因本案遭判刑，倘均\n    入監執行其家庭勢必無人照拂，為免其家庭失序，本院因認\n    其經此偵審判刑教訓當已知所警惕，日後信無再犯之虞，其\n    所受宣告之刑以暫不執行為適當，爰併諭知緩刑參年，以勵\n    自新。至被告丙○○○，依卷存之刑案資料查註紀錄表，甫\n    因另案詐欺罪受有期徒刑10月執行完畢，依法自不得為緩刑\n    諭知，附此敘明。\n八、至被告丙○○○前經本院以87年度上易字第303號，於87年4\n    月14日，判處有期徒刑10月並已執行完畢之詐欺事實，經核\n    卷附之該案判決內容，其係於85年6月8日至86年3月底間，\n    連續藉詞其夫承包工程發生意外有工人死亡須理賠，而向他\n    人詐借款項花用，要與本案詐標會款之犯罪手法相異，且兩\n    案犯罪時間亦難認密接，即被告亦否認本案犯罪，是二案間\n    應無連續犯之適用，本案非該案判決效力所及，本院自得依\n    法就本案為實體之判決，併此敘明。\n九、據上論斷，應依刑事訴訟法第369條第1項前段、第364條、\n    第299條第1項前段，刑法第28條、第56條、第216條、第210\n    條、第339條第1項、第219條、第55條、第74條第1款、罰金\n    罰鍰提高標準條例第1條前段，判決如主文。\n本案經檢察官林炎昇到庭執行職務。\n中     華    民    國    94    年    4    月    28    日\n                   刑事第五庭     審判長法  官  楊明章\n                                        法  官  沈揚仁\n                                        法  官  戴勝利\n以上正本證明與原本無異。\n如不服本判決，應於收受本判決後十日內向本院提出上訴書狀。\n其未敘述上訴理由者並得於提起上訴後十日內向本院補提理由書\n狀（均須按他造當事人之人數附繕本）「切勿逕送上級法院」。\n                                        書記官  李珍鳳"
  },
  "search": "臺灣高等法院臺南分院刑事判決上訴人臺灣臺南地方法院檢察署檢察官上訴人即被告乙○○上訴人即被告丙○○○上被告選任辯護人蔡清河律師上列上訴人因被告等偽造文書等案件，不服臺灣臺南地方法院88年度訴字第524號中華民國88年7月16日第一審判決（起訴案號：臺灣臺南地方法院檢察署87年度偵續字第150號），提起上訴，判決後，經最高法院第二次發回更審，本院判決如下：主文原判決撤銷。丙○○○、乙○○共同連續行使偽造私文書，足以生損害於他人，各處有期徒刑壹年。乙○○緩刑參年。偽造之標單上蔡朝琴、王清風、阿珍、徐安心之署押，均沒收。事實一、乙○○與丙○○○係夫妻二人，均明知經濟不佳而無清償能力，於民國86年4月15日，在臺南縣歸仁鄉○○○路二七二號住處，以乙○○名義為會首，由乙○○、丙○○○分別招募甲○○等互助會會員，成立每月新臺幣（下同）1萬元之互助會，連同會首共計26人之民間互助會，第一會由會員將1萬元交由會首，第二會以後則由會員將欲標之利息寫於標單上，並書上會員之姓名，以出價最高者得標。詎其等二人竟共同基於概括意圖為自己不法所有，及行使偽造私文書之犯意聯絡，於該會86年8月止會前之5月、6月及7月所開標之第二、三、四次開標日期，連續推由丙○○○第二會冒用蔡朝琴、王清風等名義，第三會冒用阿珍名義、第四會冒用徐安心名義並偽造該等人名義之標單用以冒標，再由其連續向其他互助會員詐稱第二、三、四次互助會，分別由蔡朝琴及王清風、阿珍、徐安心得標，計詐得會款55萬9千8百元花用（詳如附表之記載），均足生損害於蔡朝琴及王清風、阿珍、徐安心及互助會員等人。二、案經甲○○訴由臺灣臺南地方法院檢察署檢察官偵查起訴。理由一、訊據上訴人即被告乙○○、丙○○○，固不諱言有以乙○○名義召集上開互助會，並於第五會即止會之事實。惟均矢口否認有何行使偽造私文書及詐欺之犯行，被告乙○○辯稱：伊雖擔任會首及有招募部分會員，然該互助會皆由丙○○○處理，伊未參與過問。被告丙○○○則辯稱：標會固有寫標單，但無冒標情事，第二會確係由蔡朝琴、王清風共同標得，第三會是阿珍標得，第四會是徐安心標得，但由楊秋蘭頂替，並無冒用他人名義標會詐取會款等語。二、惟查被告乙○○、丙○○○夫妻，確於86年4月15日以乙○○名義為會首，招募甲○○等互助會會員，成立每月新臺幣（下同）1萬元之互助會，連同會首共計26人之民間互助會之事實，業據乙○○、丙○○○供認在卷，並有互助會會單附卷可按，上開互助會之召募及運作，據乙○○於偵查中稱：「這會是我太太在我沒空時，幫我收的，會員有部分我招的，一部分在學校的是我太太招的」、（詳偵字第216號卷第13頁）、「我們夫妻都有招會員，但對外都由我妻來負責」、「因我妻是在學校工作，由她當會首較不合適，所以才以我的名義當會首」（詳偵續字第150號卷第59頁），而丙○○○亦於偵查中供稱：「招會員一些是我先生乙○○招攬的，其餘都由我主持」（詳偵續字第150號卷第69頁）、本院前審亦稱：「會員我先生召的比較少，大多數是我召的，會首是我先生」、「會錢大都交給我，而我先生召的人，有的交給他，他再交給我」（詳本院上訴卷第43頁），足見被告乙○○、丙○○○二人均有參與本件互助會之招攬、收取會錢等相關事務無疑，被告乙○○辯稱：其未參與互助會事宜云云，顯非事實，而不可採。三、本件互助會於標會時，欲參與競標之會員，需寫記載名字、金額（即利息）之標單乙情，業據告訴人甲○○指訴明確（詳偵續字第150號卷第107頁反面，本院更一卷第96頁），亦為被告丙○○○所供認無訛（詳偵續卷第107頁），被告乙○○也供認：「每月自由競標，寫會單」等語（詳偵字卷第14頁），復經證人即會員翁義明證述屬實（詳本院更一卷第87頁至88頁），再參酌一般民間互助會開標之習慣，在競標時亦多有寫標單，以資確定由何人以多少利息得標，惟在開標確定後，亦多隨即將之銷毀丟棄不再保存等情，顯示告訴人甲○○、被告乙○○、丙○○○、證人翁義明等就本件互助會開標情形之上開指稱、供述、證述，符合一般民間互助會開標之習慣，足認本件互助會於標會時，欲參加競標之會員，均需寫記載名字、利息之標單，參與開標，以資確定由何人、以多少利息得標無疑。四、至被告丙○○○雖辯稱：並無冒標情事，第二會係由蔡朝琴、王清風標得，第三會是阿珍標得，第四會是徐安心標得，但由楊秋蘭頂替等語，經查：（一）證人王清風、蔡朝琴於原審中固證稱：「伊等共同標得第三次或第四次會，再朋分會款」云云（詳原審卷第84頁），以附合被告丙○○○之辯解，然上開證述已與被告丙○○○在原審中所供陳：「第二會是會單標的，他們二位金額一樣，所以一起標到，」（詳原審卷第84頁）之事實不符，亦與被告丙○○○於偵查中所稱：「是王清風標得後，給蔡朝琴收會款」（詳偵續字第150號卷第35頁反面），會款並非由二位證人朋分云云相左，且證人王清風、蔡朝琴就渠等之所以會共同標會、事先有無聯絡等節，經本院前審隔離訊問後，證人王清風係稱：「因當時兩人都欠錢用，都想標會」、「我打電話給蔡朝琴，叫他打電話去標的，我沒有打電話給會頭，我叫蔡朝琴打的」、「開始標的第一會或第二會、惟證人蔡朝琴卻稱：「因為我們兩個人的標金一樣才一起標的」、「我打電話跟會頭說我要標多少利息，開標後會頭說王清風的標金和我一樣，叫我們二個人自己去協調」、「開標前我們沒有聯絡過，是各人自己去標，開標後會頭才告訴我，我的利息和王清風一樣多，叫我們自己去協調，看誰要讓誰，我們協調結果，決定兩個人一起標這一會，一人分一半」（詳更一卷第88頁至第91頁），彼此之陳述顯屬歧異矛盾，再證人蔡朝琴係被告乙○○之弟，證人王清風係被告乙○○之姐夫，足見證人王清風、蔡朝琴上開渠等二人共同標一會之證言，應屬迴護之詞，殊不足取。（二）被告丙○○○於原審中原係稱：「第三會由阿珍標到，阿珍為其朋友，名字並不清楚，阿珍我沒見過，是她姪子來跟會，八十三年間即來跟會」、「阿珍是張政吉的姪子，來繳會款的都是張政吉，標到多少錢已忘了，標單也都丟掉了」、「標單是張政吉叫我寫名字，因他怕太太知道，所以才用別人的名字」（詳原審卷第58頁、第83頁），惟證人張政吉在原審卻證稱：「我都用張政吉或鄭先生名字跟會，我不認識阿珍我沒有印象用阿珍名義跟過會」（詳原審卷第83頁），是該所謂由阿珍標得會云者，亦非事實，而不足採。至證人張政吉於本院前審審理時雖又證稱：「我跟會有叫會頭寫我姪女阿珍名義跟會」（詳更一卷第92頁），因與其前於原審中所為上開證述不符，應亦屬附合被告辯解而為迴護之詞，不足採信，附此敘明。（三）證人楊秋蘭於偵查、原審中固證稱：「我有借徐安心的會款，再交給丙○○○」、「86年4月15日之互助會，『我沒有標』，是徐安心標到後，我跟他換（即向徐安心借會款），我有打電話跟徐安心講」云云（詳偵續字第150號卷第69頁，原審卷第82頁反面），惟因證人徐安心並未標得本件86年4月5日互助會之會款，亦未將會款借給別人、或楊秋蘭，或由楊秋蘭頂替等情，已據證人徐安心在偵查、原審中陳明（詳偵續字第150號卷第114頁，原審卷第82頁），且證人楊秋蘭在原審先則稱：「我有打電話跟徐安心講，要跟他換」云云，繼於證人徐安心表示「未接到楊秋蘭電話後」，即又改稱：「是我告訴楊秋惠叫他打電話給徐安心，說要換成我標到會，我自己沒有打電話給徐安心」云云（詳原審卷第82頁），亦見先後供述矛盾不一而有瑕疵，況證人楊秋蘭又自承與被告丙○○○為姊妹關係，是該證言顯係故為迴護被告之詞，難認屬實情。另證人楊秋蘭於本院前審審理時雖亦證稱：「第四會我要標，我打電話委託楊秋惠幫我標，但是沒有標到，被徐安心標到，因為楊秋惠急用錢，我叫楊秋惠去跟徐安心協調，看他願不願意把會讓給我，後來楊秋惠告訴我說，徐安心答應先讓給我用」、「我從頭到尾沒有與徐安心聯絡過，都是楊秋惠跟我講的，所以我不知道實際情形。」（詳更一卷第94頁），與證人楊秋蘭於原審中所為上開證述相左，復與證人徐安心之證述亦不符，顯亦屬迴護之詞，均不足採。綜上所述，顯見被告丙○○○上述無冒標互助會之辯解，應非屬事實，而無可採信。（四）被告乙○○與被告丙○○○具夫妻關係，於86年4月15日召集互助會，於取得首會款後未久之同年8月即行止會，雖上開證人及告訴人等均稱標會之事務皆由被告丙○○○處理。惟被告乙○○既自承有招募互助會會員，並收取會款，已上前述，並曾因無力繳會款勸被告丙○○○不要再招會等語在卷（見偵續字第150號卷第59頁），再參諸被告丙○○○供稱：該互助會之會員有一部份係由乙○○去招攬的，乙○○亦有在收會款之情，亦如上述，是被告乙○○實早已知其等應無任何清償資力，竟仍與被告丙○○○共同召集互助會會員，且於冒標得會款後旋即倒會，顯見其等有為自己不法所有之詐欺意圖，及行使偽造私文書之犯意，暨互相利用他方行為以遂行犯罪目的之共同犯意聯絡無疑。此外，復有互助會單影本附卷足稽。至被告另稱已將會款退還會員云者，因詐欺犯為即成犯，只要取得他人交付之財物即成罪，事後將財物返還，並無礙於詐欺犯罪之成立。（五）綜就上情參酌以觀，足認被告二人之否認犯罪及所辯各節，要屬諉責推卸之詞，委無足取，本件事證明確，被告二人犯行均堪認定，應予依法論科。五、至最高法院發回意旨以：本案被告所詐取之互助會款若干應予認定一節，經質之被告等均以事隔太久，互助會之標息若干，已記不清楚，大概第二、三會在1600元左右，而第四會在2500元左右，並同意第二、三會標息以1600元，第四會標息以2500元計算，則以有利於被告上開標息計算，被告所冒標之會款為55萬9千8百元，如附表所示。六、查本件互助會之標單，係於白紙上記載姓名及一定金額之標息，既為被告及告訴人甲○○、證人翁義明於偵查中、本院審理時供述、指訴、證述在卷，已如前述，則依民間互助會之習慣，此乃表示某會員以多少利息標取會款之意思，為參與競標互助會會款之用意證明，應屬刑法第220條第1項之準私文書，被告行使偽造之各該標單，亦足生損害於告訴人及其他活會會員。核被告二人所為，均係犯刑法第216條、第210條之行使偽造私文書罪及第339條第1項之詐欺取財罪。其等就該二犯罪之施行，被告彼此間互有犯意聯絡及行為分擔，均應論以共同正犯。彼等偽造署押係偽造私文書之部分行為，其偽造私文書之低度行為，已為其行使偽造私文書之高度行為所吸收，均不另論罪。其等先後多次行使偽造私文書及詐欺犯行，均各時間緊接，犯罪構成要件相同，顯均係基於概括犯意而為，皆應依連續犯規定各以一罪論，並均依法加重其刑。其等以一詐標行為同時詐騙數會員之會款，係以一行為觸犯數罪名，應依想像競合犯之例從一罪處斷。其等所犯上開二罪間，具有方法結果之牽連關係，為牽連犯，應從一重之行使偽造私文書罪處斷。偽造之標會單上蔡朝琴、王清風、阿珍、徐安心之署押，併依刑法第219條之規定，宣告沒收。七、原審法院認被告二人罪證明確，據予論罪科刑，固非無見，惟查冒用他人名義在標單上書寫姓名及一定金額，依民間互助會習慣，除表示投標會員之主體外，並表示該會員願意以標單內所載之金額為標息而參與競標，非僅純為投標會員之識別，故冒標於標單上仿偽造他人姓名，乃表示投標會員之簽名意思，屬偽造之署押，依刑法第219條之規定，應為沒收之諭知，法院並無裁量之餘地，原判決就被告所偽造標單上之署押未予宣告沒收，尚有未洽，被告二人上訴意旨否認犯罪，及檢察官上訴意旨認量刑偏輕，分別指摘原判決不當，雖均非可取，惟原判決既有可議，自應由本院將原判決予以撤銷改判。爰審酌被告二人之素行、犯罪之動機、目的、手段、所生危害、及其犯後態度等一切情狀，仍對其等各量處如原判決所科之有期徒刑一年。又被告乙○○前未曾受有期徒刑以上刑之宣告，此有其刑案資料查註紀錄表、及其全國前案紀錄表在卷可佐，且念其夫妻均因本案遭判刑，倘均入監執行其家庭勢必無人照拂，為免其家庭失序，本院因認其經此偵審判刑教訓當已知所警惕，日後信無再犯之虞，其所受宣告之刑以暫不執行為適當，爰併諭知緩刑參年，以勵自新。至被告丙○○○，依卷存之刑案資料查註紀錄表，甫因另案詐欺罪受有期徒刑10月執行完畢，依法自不得為緩刑諭知，附此敘明。八、至被告丙○○○前經本院以87年度上易字第303號，於87年4月14日，判處有期徒刑10月並已執行完畢之詐欺事實，經核卷附之該案判決內容，其係於85年6月8日至86年3月底間，連續藉詞其夫承包工程發生意外有工人死亡須理賠，而向他人詐借款項花用，要與本案詐標會款之犯罪手法相異，且兩案犯罪時間亦難認密接，即被告亦否認本案犯罪，是二案間應無連續犯之適用，本案非該案判決效力所及，本院自得依法就本案為實體之判決，併此敘明。九、據上論斷，應依刑事訴訟法第369條第1項前段、第364條、第299條第1項前段，刑法第28條、第56條、第216條、第210條、第339條第1項、第219條、第55條、第74條第1款、罰金罰鍰提高標準條例第1條前段，判決如主文。本案經檢察官林炎昇到庭執行職務。中華民國94年4月28日刑事第五庭審判長法官楊明章法官沈揚仁法官戴勝利以上正本證明與原本無異。如不服本判決，應於收受本判決後十日內向本院提出上訴書狀。其未敘述上訴理由者並得於提起上訴後十日內向本院補提理由書狀（均須按他造當事人之人數附繕本）「切勿逕送上級法院」。書記官李珍鳳中華民國94年4月29日附錄本案論罪科刑法條全文：刑法第二百十六條：行使第二百十條至第二百十五條之文書者，依偽造、變造文書或登載不實事項或使登載不實事項之規定處斷。刑法第二百十條：偽造、變造私文書，足以生損害於公眾或他人者，處五年以下有期徒刑。附表┌───────────────────────────┐│年４月日起會，每會１萬元之互助會會員名│├──┬─────┬─────┬──────┬─────┤│編號│冒標會員│冒標標息│所得金額│備註││││（新台幣）│（新台幣）││├──┼─────┼─────┼──────┼─────┤│1.│蔡朝琴│1,600元│201,600元│第二會│││王清風││││├──┼─────┼─────┼──────┼─────┤│2.│阿珍│1,600元│193,200元│第三會│││││││├──┼─────┼─────┼──────┼─────┤│3.│徐安心│2,500元│165,000元│第四會│││││││├──┴─────┴─────┴──────┴─────┤│合計：559,800元│└───────────────────────────┘",
  "characters": {
    "judges": [
      "楊明章",
      "沈揚仁",
      "戴勝利"
    ],
    "prosecutors": [
      "林炎昇"
    ],
    "lawyers": [

    ],
    "clerks": [
      "李珍鳳"
    ],
    "plaintiffs": [

    ],
    "defendants": [
      "乙",
      "丙",
      "選任辯護人"
    ],
    "prosecutor_office": [

    ],
    "creditors": [

    ],
    "debtors": [

    ],
    "judicial_associate_officer": [

    ]
  },
  "adjudged_at": "2005-04-28",
  "created_at": "2016-02-06 18:29:35",
  "updated_at": "2016-02-06 18:29:35"
}