{
  "identify": "TPH-94-上訴-755-20050428-1",
  "court": {
    "name": "臺灣高等法院",
    "code": "TPH"
  },
  "division": {
    "name": "刑事",
    "code": "M"
  },
  "year": 94,
  "word": "上訴",
  "number": "755",
  "jcheck": "1",
  "reason": "毒品危害防制條例",
  "content": "臺灣高等法院刑事判決                 94年度上訴字第755號\n上  訴  人  臺灣基隆地方法院檢察署檢察官\n被      告  甲○○\n上列上訴人因毒品危害防制條例案件，不服臺灣基隆地方法院93\n年度訴字第632號，中華民國94年1月28日第一審判決（起訴案號\n：臺灣基隆地方法院檢察署93年度毒偵字第1190號），提起上訴\n，本院判決如下：\n    主  文\n原判決撤銷。\n甲○○施用第一級毒品，處有期徒刑陸月，如易科罰金，以參佰\n元折算壹日；扣案之第一級毒品海洛因壹包（淨重零點零貳公克\n），沒收銷毀之，放置上開海洛因之空包裝壹只（重零點貳參公\n克），沒收。又施用第二級毒品，處有期徒刑參月，如易科罰金\n，以參佰元折算壹日。應執行有期徒刑捌月，如易科罰金，以參\n佰元折算壹日；扣案之第一級毒品海洛因壹包（淨重零點零貳公\n克），沒收銷毀之，放置上開海洛因之空包裝壹只（重零點貳參\n公克），沒收。\n    事  實\n一、甲○○曾因施用第一級毒品、第二級毒品案件，經臺灣臺中\n    地方法院於民國（下同）92年2月13日裁定送勒戒處所觀察\n    、勒戒，執行後認無繼續施用毒品之傾向，經臺灣臺中地方\n    法院檢察署檢察官於93年3月31日，以93年度毒偵緝字第56\n    號不起訴處分書為不起訴處分確定。\n二、甲○○仍不知悛悔，明知海洛因、安非他命係毒品危害防制\n    條例第二條第二項第一款、第二款所規範之第一級、第二級\n    毒品，不得非法施用、持有，仍基於施用第二級毒品安非他\n    命之犯意，在前開犯施用毒品罪後5年內，於於九十三年六\n    月二十九日中午，在台北縣貢寮鄉船澳漁港海邊停車場之小\n    客車內，以吸食方式，施用第二級毒品安非他命一次（起訴\n    書原僅記載「於93年6月30日下午5時15分採尿前之四日內，\n    在不詳地點施用第二級毒品甲基安非他命」，應更為詳實之\n    記載）。又另行起意，基於施用第一級毒品海洛因之犯意，\n    於九十三年六月二十九日晚間十時三十分許，在船澳漁港之\n    海邊，以注射右手手肘之方式，施用第一級毒品海洛因一次\n    。嗣於九十三年六月三十日下午二時三十分許，在在台北縣\n    貢寮鄉○○街三十號前，為警盤查其所搭乘之自用小客車，\n    扣得其當場向外丟棄第一級毒品海洛因一小包（淨重零點零\n    二公克，空包裝重零點二三公克）；經帶回警局訊問，警詢\n    中採其尿液經送請檢驗結果，發現呈含嗎啡及甲基安非他命\n    之陽性反應，而查獲。\n三、案經台北縣政府警察局瑞芳分局報請台灣基隆地方法院檢察\n    署檢察官偵查起訴。\n    理  由\n一、訊之被告甲○○在本院審理中，對於前揭事實已坦承不諱。\n    復查：\n  (一)警方於93年6月30日下午2時30分許，在在台北縣貢寮鄉○○\n    街30號前所扣得之白粉一包，係第一級毒品海洛因，淨重零\n    點零二公克，空包裝重零點二三公克，有法務部調查局93年\n    9月7日調科壹字第320002291號鑑定通知書乙紙在卷可證（\n    見毒偵字第1190號卷第35頁）；又，同日警詢中經採集其尿\n    液送請基隆市衛生局以酵素免疫分析法、薄層分析法檢驗結\n    果，發現呈嗎啡及甲基安非他命陽性反應，有臺北縣政府警\n    察局瑞芳分局偵辦毒品危害防制條例案件犯嫌尿液檢驗編號\n    對照表、基隆市衛生局所出具基衛檢壹字第0930010609 號\n    檢驗成績書在卷可查（見毒偵字第1190號卷第12頁、第33\n    頁）。是被告之自白核與事實相符，自屬可信；其在前揭時\n    地分別有施用第一級毒品海洛因、第二級毒品安非他命之行\n    為，堪以認定。\n  (二)被告前曾因施用第一級毒品、第二級毒品案件，經臺灣臺中\n    地方法院於92年2月13日裁定送勒戒處所觀察、勒戒，執行\n    後認無繼續施用毒品之傾向，經臺灣臺中地方法院檢察署檢\n    察官於93年3月31日，以93年度毒偵緝字第56號不起訴處分\n    書為不起訴處分確定，有臺灣臺中地方法院檢察署檢察官93\n    年度毒偵緝字第56號不起訴處分書及本院被告全國前案錄表\n    各一份在卷可憑。被告係於觀察、勒戒執行完畢後五年內第\n    二度犯施用毒品犯行之事實，亦可認定。\n  (三)本案事證巳臻明確，被告犯行洵堪認定。被告於前開不起訴\n    處分後，五年內第三度犯毒品危害防制條例第十條第一項、\n    第二項之罪，依毒品危害防制條例第二十三條第二項前段規\n    定，應予依法論科。\n二、核被告施用海洛因，所為係犯毒品危害防制條例第十條第一\n    項之施用第一級毒品罪；另施用安非他命，所為係犯毒品危\n    害防制條例第十條第二項之施用第二級毒品罪。被告非法施\n    用第一級毒品、第二級毒品前後，非法持有第一級毒品、第\n    二級毒品之低度行為，為其施用第一級毒品、第二級毒品之\n    高度行為所吸收，不另論罪。被告所犯上開二罪，其犯意各\n    別，犯罪構成要件又不相同，應予分論併罰。\n三、原審據以論罪科刑，固非無見。惟：(一)按連續犯須基於概括\n    犯意，連續數行為而犯同一罪名，所謂同一罪名，指構成犯\n    罪要件相同之罪名而言，業經司法院大法官會議釋字第一五\n    二號解釋在案（最高法院68年台上字第3056號判例參照）；\n    被告所為上揭施用第一級毒品海洛因罪，與施用第二級毒品\n    安非他命罪，其犯罪構成要並不相同；原審判決認被告所為\n    二行為，所犯為構成要件相同之罪名，顯係基於概括犯意而\n    反覆為之，為連續犯，應論以一罪，自有可議。(二)扣案毒品\n    海洛因之空包裝壹只，係供放置前揭毒品所用之物，且屬被\n    告所有，未依刑法第38條第1項第2款之規定宣告沒收，亦有\n    未當。(三)扣案之海洛因係查獲之第一級毒品，依毒品危害防\n    制條例第18條第1項之規定沒收銷毀之，在據上論結欄漏未\n    引用依據之法條；又，依刑法第41條易科罰金，已就其原定\n    數額提高一百倍，在據上論結欄漏未引用罰金罰鍰提高標準\n    條例第2條，同有未洽。公訴人之上訴意旨執前述(一)之理由\n    ，指摘原判決不當，為有理由，應由本院將原判決撤銷改判\n    。爰審酌施用毒品雖係自戕行為，然被告前曾因施用第一級\n    毒品、第二級毒品案件，經法院裁定送勒戒處所觀察、勒戒\n    ，執行後認無繼續施用毒品之傾向，甫經臺灣臺中地方法院\n    檢察署檢察官於93年3月31日以93年度毒偵緝字第56號不起\n    訴處分書為不起訴處分確定，仍再為本案之施用毒品犯行，\n    顯見其惡習已深，及其施用毒品之種類，次數各只有一次，\n    及犯罪後已坦承犯行之態度等一切情狀，分別量處如主文所\n    示之刑，並諭知易科罰金之折算標準，及定其應執行之刑。\n    扣案之海洛因（淨重零點零貳公克），係查獲之第一級毒品\n    ，應依毒品危害防制條例第18條第1項之規定，沒收銷毀之\n    ；空包裝壹只（重零點貳參公克）係供放置前揭毒品所用之\n    物，且屬被告所有，已據被告陳明在卷，應依刑法第38條第\n    1項第2款之規定，併予宣告沒收。\n四、據上論斷，應依刑事訴訟法第369條第1項前段、第364條、\n    第299條第1項前段，毒品危害防制條例第10條第1項、第2項\n    、第18條第1項，刑法第41條第1項、第38條第1項第2款，罰\n    金罰鍰提高標準條例第2條，判決如主文。\n本案經檢察官林炳雄到庭執行職務。\n中    華    民    國    94    年    4    月    28    日\n                  刑事第十三庭  審判長法  官  劉景星\n                                      法  官  陳志洋\n                                      法  官  陳博志\n以上正本證明與原本無異。\n施用第1級毒品部分如不服本判決，應於收受送達後十日內向本\n院提出上訴書狀，其未敘述上訴之理由者並得於提起上訴後十日\n內向本院補提理由書（均須按他造當事人之人數附繕本）。\n施用第2級毒品部分不得上訴。\n                                      書記官  陳嘉文\n中    華    民    國    94    年    4     月    29    日\n附錄：本案論罪科刑法條全文\n毒品危害防制條例第10條：\n施用第1級毒品者，處6月以上5年以下有期徒刑。\n施用第2 級毒品者，處3 年以下有期徒刑。\n",
  "structure": {
    "main": "原判決撤銷。\n甲○○施用第一級毒品，處有期徒刑陸月，如易科罰金，以參佰\n元折算壹日；扣案之第一級毒品海洛因壹包（淨重零點零貳公克\n），沒收銷毀之，放置上開海洛因之空包裝壹只（重零點貳參公\n克），沒收。又施用第二級毒品，處有期徒刑參月，如易科罰金\n，以參佰元折算壹日。應執行有期徒刑捌月，如易科罰金，以參\n佰元折算壹日；扣案之第一級毒品海洛因壹包（淨重零點零貳公\n克），沒收銷毀之，放置上開海洛因之空包裝壹只（重零點貳參\n公克），沒收。",
    "fact": "一、甲○○曾因施用第一級毒品、第二級毒品案件，經臺灣臺中\n    地方法院於民國（下同）92年2月13日裁定送勒戒處所觀察\n    、勒戒，執行後認無繼續施用毒品之傾向，經臺灣臺中地方\n    法院檢察署檢察官於93年3月31日，以93年度毒偵緝字第56\n    號不起訴處分書為不起訴處分確定。\n二、甲○○仍不知悛悔，明知海洛因、安非他命係毒品危害防制\n    條例第二條第二項第一款、第二款所規範之第一級、第二級\n    毒品，不得非法施用、持有，仍基於施用第二級毒品安非他\n    命之犯意，在前開犯施用毒品罪後5年內，於於九十三年六\n    月二十九日中午，在台北縣貢寮鄉船澳漁港海邊停車場之小\n    客車內，以吸食方式，施用第二級毒品安非他命一次（起訴\n    書原僅記載「於93年6月30日下午5時15分採尿前之四日內，\n    在不詳地點施用第二級毒品甲基安非他命」，應更為詳實之\n    記載）。又另行起意，基於施用第一級毒品海洛因之犯意，\n    於九十三年六月二十九日晚間十時三十分許，在船澳漁港之\n    海邊，以注射右手手肘之方式，施用第一級毒品海洛因一次\n    。嗣於九十三年六月三十日下午二時三十分許，在在台北縣\n    貢寮鄉○○街三十號前，為警盤查其所搭乘之自用小客車，\n    扣得其當場向外丟棄第一級毒品海洛因一小包（淨重零點零\n    二公克，空包裝重零點二三公克）；經帶回警局訊問，警詢\n    中採其尿液經送請檢驗結果，發現呈含嗎啡及甲基安非他命\n    之陽性反應，而查獲。\n三、案經台北縣政府警察局瑞芳分局報請台灣基隆地方法院檢察\n    署檢察官偵查起訴。",
    "reason": "一、訊之被告甲○○在本院審理中，對於前揭事實已坦承不諱。\n    復查：\n  (一)警方於93年6月30日下午2時30分許，在在台北縣貢寮鄉○○\n    街30號前所扣得之白粉一包，係第一級毒品海洛因，淨重零\n    點零二公克，空包裝重零點二三公克，有法務部調查局93年\n    9月7日調科壹字第320002291號鑑定通知書乙紙在卷可證（\n    見毒偵字第1190號卷第35頁）；又，同日警詢中經採集其尿\n    液送請基隆市衛生局以酵素免疫分析法、薄層分析法檢驗結\n    果，發現呈嗎啡及甲基安非他命陽性反應，有臺北縣政府警\n    察局瑞芳分局偵辦毒品危害防制條例案件犯嫌尿液檢驗編號\n    對照表、基隆市衛生局所出具基衛檢壹字第0930010609 號\n    檢驗成績書在卷可查（見毒偵字第1190號卷第12頁、第33\n    頁）。是被告之自白核與事實相符，自屬可信；其在前揭時\n    地分別有施用第一級毒品海洛因、第二級毒品安非他命之行\n    為，堪以認定。\n  (二)被告前曾因施用第一級毒品、第二級毒品案件，經臺灣臺中\n    地方法院於92年2月13日裁定送勒戒處所觀察、勒戒，執行\n    後認無繼續施用毒品之傾向，經臺灣臺中地方法院檢察署檢\n    察官於93年3月31日，以93年度毒偵緝字第56號不起訴處分\n    書為不起訴處分確定，有臺灣臺中地方法院檢察署檢察官93\n    年度毒偵緝字第56號不起訴處分書及本院被告全國前案錄表\n    各一份在卷可憑。被告係於觀察、勒戒執行完畢後五年內第\n    二度犯施用毒品犯行之事實，亦可認定。\n  (三)本案事證巳臻明確，被告犯行洵堪認定。被告於前開不起訴\n    處分後，五年內第三度犯毒品危害防制條例第十條第一項、\n    第二項之罪，依毒品危害防制條例第二十三條第二項前段規\n    定，應予依法論科。\n二、核被告施用海洛因，所為係犯毒品危害防制條例第十條第一\n    項之施用第一級毒品罪；另施用安非他命，所為係犯毒品危\n    害防制條例第十條第二項之施用第二級毒品罪。被告非法施\n    用第一級毒品、第二級毒品前後，非法持有第一級毒品、第\n    二級毒品之低度行為，為其施用第一級毒品、第二級毒品之\n    高度行為所吸收，不另論罪。被告所犯上開二罪，其犯意各\n    別，犯罪構成要件又不相同，應予分論併罰。\n三、原審據以論罪科刑，固非無見。惟：(一)按連續犯須基於概括\n    犯意，連續數行為而犯同一罪名，所謂同一罪名，指構成犯\n    罪要件相同之罪名而言，業經司法院大法官會議釋字第一五\n    二號解釋在案（最高法院68年台上字第3056號判例參照）；\n    被告所為上揭施用第一級毒品海洛因罪，與施用第二級毒品\n    安非他命罪，其犯罪構成要並不相同；原審判決認被告所為\n    二行為，所犯為構成要件相同之罪名，顯係基於概括犯意而\n    反覆為之，為連續犯，應論以一罪，自有可議。(二)扣案毒品\n    海洛因之空包裝壹只，係供放置前揭毒品所用之物，且屬被\n    告所有，未依刑法第38條第1項第2款之規定宣告沒收，亦有\n    未當。(三)扣案之海洛因係查獲之第一級毒品，依毒品危害防\n    制條例第18條第1項之規定沒收銷毀之，在據上論結欄漏未\n    引用依據之法條；又，依刑法第41條易科罰金，已就其原定\n    數額提高一百倍，在據上論結欄漏未引用罰金罰鍰提高標準\n    條例第2條，同有未洽。公訴人之上訴意旨執前述(一)之理由\n    ，指摘原判決不當，為有理由，應由本院將原判決撤銷改判\n    。爰審酌施用毒品雖係自戕行為，然被告前曾因施用第一級\n    毒品、第二級毒品案件，經法院裁定送勒戒處所觀察、勒戒\n    ，執行後認無繼續施用毒品之傾向，甫經臺灣臺中地方法院\n    檢察署檢察官於93年3月31日以93年度毒偵緝字第56號不起\n    訴處分書為不起訴處分確定，仍再為本案之施用毒品犯行，\n    顯見其惡習已深，及其施用毒品之種類，次數各只有一次，\n    及犯罪後已坦承犯行之態度等一切情狀，分別量處如主文所\n    示之刑，並諭知易科罰金之折算標準，及定其應執行之刑。\n    扣案之海洛因（淨重零點零貳公克），係查獲之第一級毒品\n    ，應依毒品危害防制條例第18條第1項之規定，沒收銷毀之\n    ；空包裝壹只（重零點貳參公克）係供放置前揭毒品所用之\n    物，且屬被告所有，已據被告陳明在卷，應依刑法第38條第\n    1項第2款之規定，併予宣告沒收。\n四、據上論斷，應依刑事訴訟法第369條第1項前段、第364條、\n    第299條第1項前段，毒品危害防制條例第10條第1項、第2項\n    、第18條第1項，刑法第41條第1項、第38條第1項第2款，罰\n    金罰鍰提高標準條例第2條，判決如主文。\n本案經檢察官林炳雄到庭執行職務。\n中    華    民    國    94    年    4    月    28    日\n                  刑事第十三庭  審判長法  官  劉景星\n                                      法  官  陳志洋\n                                      法  官  陳博志\n以上正本證明與原本無異。\n施用第1級毒品部分如不服本判決，應於收受送達後十日內向本\n院提出上訴書狀，其未敘述上訴之理由者並得於提起上訴後十日\n內向本院補提理由書（均須按他造當事人之人數附繕本）。\n施用第2級毒品部分不得上訴。\n                                      書記官  陳嘉文"
  },
  "search": "臺灣高等法院刑事判決94年度上訴字第755號上訴人臺灣基隆地方法院檢察署檢察官被告甲○○上列上訴人因毒品危害防制條例案件，不服臺灣基隆地方法院93年度訴字第632號，中華民國94年1月28日第一審判決（起訴案號：臺灣基隆地方法院檢察署93年度毒偵字第1190號），提起上訴，本院判決如下：主文原判決撤銷。甲○○施用第一級毒品，處有期徒刑陸月，如易科罰金，以參佰元折算壹日；扣案之第一級毒品海洛因壹包（淨重零點零貳公克），沒收銷毀之，放置上開海洛因之空包裝壹只（重零點貳參公克），沒收。又施用第二級毒品，處有期徒刑參月，如易科罰金，以參佰元折算壹日。應執行有期徒刑捌月，如易科罰金，以參佰元折算壹日；扣案之第一級毒品海洛因壹包（淨重零點零貳公克），沒收銷毀之，放置上開海洛因之空包裝壹只（重零點貳參公克），沒收。事實一、甲○○曾因施用第一級毒品、第二級毒品案件，經臺灣臺中地方法院於民國（下同）92年2月13日裁定送勒戒處所觀察、勒戒，執行後認無繼續施用毒品之傾向，經臺灣臺中地方法院檢察署檢察官於93年3月31日，以93年度毒偵緝字第56號不起訴處分書為不起訴處分確定。二、甲○○仍不知悛悔，明知海洛因、安非他命係毒品危害防制條例第二條第二項第一款、第二款所規範之第一級、第二級毒品，不得非法施用、持有，仍基於施用第二級毒品安非他命之犯意，在前開犯施用毒品罪後5年內，於於九十三年六月二十九日中午，在台北縣貢寮鄉船澳漁港海邊停車場之小客車內，以吸食方式，施用第二級毒品安非他命一次（起訴書原僅記載「於93年6月30日下午5時15分採尿前之四日內，在不詳地點施用第二級毒品甲基安非他命」，應更為詳實之記載）。又另行起意，基於施用第一級毒品海洛因之犯意，於九十三年六月二十九日晚間十時三十分許，在船澳漁港之海邊，以注射右手手肘之方式，施用第一級毒品海洛因一次。嗣於九十三年六月三十日下午二時三十分許，在在台北縣貢寮鄉○○街三十號前，為警盤查其所搭乘之自用小客車，扣得其當場向外丟棄第一級毒品海洛因一小包（淨重零點零二公克，空包裝重零點二三公克）；經帶回警局訊問，警詢中採其尿液經送請檢驗結果，發現呈含嗎啡及甲基安非他命之陽性反應，而查獲。三、案經台北縣政府警察局瑞芳分局報請台灣基隆地方法院檢察署檢察官偵查起訴。理由一、訊之被告甲○○在本院審理中，對於前揭事實已坦承不諱。復查：(一)警方於93年6月30日下午2時30分許，在在台北縣貢寮鄉○○街30號前所扣得之白粉一包，係第一級毒品海洛因，淨重零點零二公克，空包裝重零點二三公克，有法務部調查局93年9月7日調科壹字第320002291號鑑定通知書乙紙在卷可證（見毒偵字第1190號卷第35頁）；又，同日警詢中經採集其尿液送請基隆市衛生局以酵素免疫分析法、薄層分析法檢驗結果，發現呈嗎啡及甲基安非他命陽性反應，有臺北縣政府警察局瑞芳分局偵辦毒品危害防制條例案件犯嫌尿液檢驗編號對照表、基隆市衛生局所出具基衛檢壹字第0930010609號檢驗成績書在卷可查（見毒偵字第1190號卷第12頁、第33頁）。是被告之自白核與事實相符，自屬可信；其在前揭時地分別有施用第一級毒品海洛因、第二級毒品安非他命之行為，堪以認定。(二)被告前曾因施用第一級毒品、第二級毒品案件，經臺灣臺中地方法院於92年2月13日裁定送勒戒處所觀察、勒戒，執行後認無繼續施用毒品之傾向，經臺灣臺中地方法院檢察署檢察官於93年3月31日，以93年度毒偵緝字第56號不起訴處分書為不起訴處分確定，有臺灣臺中地方法院檢察署檢察官93年度毒偵緝字第56號不起訴處分書及本院被告全國前案錄表各一份在卷可憑。被告係於觀察、勒戒執行完畢後五年內第二度犯施用毒品犯行之事實，亦可認定。(三)本案事證巳臻明確，被告犯行洵堪認定。被告於前開不起訴處分後，五年內第三度犯毒品危害防制條例第十條第一項、第二項之罪，依毒品危害防制條例第二十三條第二項前段規定，應予依法論科。二、核被告施用海洛因，所為係犯毒品危害防制條例第十條第一項之施用第一級毒品罪；另施用安非他命，所為係犯毒品危害防制條例第十條第二項之施用第二級毒品罪。被告非法施用第一級毒品、第二級毒品前後，非法持有第一級毒品、第二級毒品之低度行為，為其施用第一級毒品、第二級毒品之高度行為所吸收，不另論罪。被告所犯上開二罪，其犯意各別，犯罪構成要件又不相同，應予分論併罰。三、原審據以論罪科刑，固非無見。惟：(一)按連續犯須基於概括犯意，連續數行為而犯同一罪名，所謂同一罪名，指構成犯罪要件相同之罪名而言，業經司法院大法官會議釋字第一五二號解釋在案（最高法院68年台上字第3056號判例參照）；被告所為上揭施用第一級毒品海洛因罪，與施用第二級毒品安非他命罪，其犯罪構成要並不相同；原審判決認被告所為二行為，所犯為構成要件相同之罪名，顯係基於概括犯意而反覆為之，為連續犯，應論以一罪，自有可議。(二)扣案毒品海洛因之空包裝壹只，係供放置前揭毒品所用之物，且屬被告所有，未依刑法第38條第1項第2款之規定宣告沒收，亦有未當。(三)扣案之海洛因係查獲之第一級毒品，依毒品危害防制條例第18條第1項之規定沒收銷毀之，在據上論結欄漏未引用依據之法條；又，依刑法第41條易科罰金，已就其原定數額提高一百倍，在據上論結欄漏未引用罰金罰鍰提高標準條例第2條，同有未洽。公訴人之上訴意旨執前述(一)之理由，指摘原判決不當，為有理由，應由本院將原判決撤銷改判。爰審酌施用毒品雖係自戕行為，然被告前曾因施用第一級毒品、第二級毒品案件，經法院裁定送勒戒處所觀察、勒戒，執行後認無繼續施用毒品之傾向，甫經臺灣臺中地方法院檢察署檢察官於93年3月31日以93年度毒偵緝字第56號不起訴處分書為不起訴處分確定，仍再為本案之施用毒品犯行，顯見其惡習已深，及其施用毒品之種類，次數各只有一次，及犯罪後已坦承犯行之態度等一切情狀，分別量處如主文所示之刑，並諭知易科罰金之折算標準，及定其應執行之刑。扣案之海洛因（淨重零點零貳公克），係查獲之第一級毒品，應依毒品危害防制條例第18條第1項之規定，沒收銷毀之；空包裝壹只（重零點貳參公克）係供放置前揭毒品所用之物，且屬被告所有，已據被告陳明在卷，應依刑法第38條第1項第2款之規定，併予宣告沒收。四、據上論斷，應依刑事訴訟法第369條第1項前段、第364條、第299條第1項前段，毒品危害防制條例第10條第1項、第2項、第18條第1項，刑法第41條第1項、第38條第1項第2款，罰金罰鍰提高標準條例第2條，判決如主文。本案經檢察官林炳雄到庭執行職務。中華民國94年4月28日刑事第十三庭審判長法官劉景星法官陳志洋法官陳博志以上正本證明與原本無異。施用第1級毒品部分如不服本判決，應於收受送達後十日內向本院提出上訴書狀，其未敘述上訴之理由者並得於提起上訴後十日內向本院補提理由書（均須按他造當事人之人數附繕本）。施用第2級毒品部分不得上訴。書記官陳嘉文中華民國94年4月29日附錄：本案論罪科刑法條全文毒品危害防制條例第10條：施用第1級毒品者，處6月以上5年以下有期徒刑。施用第2級毒品者，處3年以下有期徒刑。",
  "characters": {
    "judges": [
      "劉景星",
      "陳志洋",
      "陳博志"
    ],
    "prosecutors": [
      "林炳雄"
    ],
    "lawyers": [

    ],
    "clerks": [
      "陳嘉文"
    ],
    "plaintiffs": [

    ],
    "defendants": [
      "甲○○"
    ],
    "prosecutor_office": [

    ],
    "creditors": [

    ],
    "debtors": [

    ],
    "judicial_associate_officer": [

    ]
  },
  "adjudged_at": "2005-04-28",
  "created_at": "2016-02-06 18:31:13",
  "updated_at": "2016-02-06 18:31:13"
}