{
  "identify": "KSD-93-簡-1619-20040412-1",
  "court": {
    "name": "臺灣高雄地方法院",
    "code": "KSD"
  },
  "division": {
    "name": "刑事",
    "code": "M"
  },
  "year": 93,
  "word": "簡",
  "number": "1619",
  "jcheck": "1",
  "reason": "毒品危害防制條例",
  "content": "臺灣高雄地方法院刑事簡易判決                    九十三年度簡字第一六一九號\n    聲  請  人  臺灣高雄地方法院檢察署檢察官\n    被      告  甲○○\n右列被告因違反毒品危害防制條例案件，經檢察官聲請簡易判決處刑（九十二年度毒\n偵字第七三四九號），本院判決如左：\n    主      文\n甲○○施用第二級毒品，處有期徒刑貳月，如易科罰金，以參佰元折算壹日。\n    事實及理由\n一、本案犯罪事實及證據，除犯罪事實應補充更正：「甲○○前於民國九十一年七月\n    間，因施用毒品行為，經觀察、勒戒處分後，認無繼續施用毒品傾向，而經臺灣\n    高雄少年法院裁定不付審理確定。嗣復因施用第二級毒品ＭＤＭＡ案件，經觀察\n    、勒戒後，認無繼續施用毒品傾向，於九十二年七月二十四釋放，並由臺灣高雄\n    少年法院於九十二年七月三十一日，以九十二年度少調字第七九九號裁定不付審\n    理」，及證據部分應補充「臺灣高等法院被告全國前案紀錄表一份」外，餘均引\n    用如附件檢察官聲請簡易判決處刑書之記載。\n二、按被告行為後，毒品危害防制條例業於九十二年七月九日修正公布，並於九十三\n    年一月九日施行。依修正後之第三十五條第一項第三款及第二項規定：「於中華\n    民國九十二年六月六日本條例修正施行前繫屬之施用毒品案件，於修正施行後，\n    適用修正後之規定，審判中之案件，由法院依修正後規定處理之。前項情形，依\n    修正前之規定有利於行為人者，適用最有利於行為人之法律」，而依修正前第二\n    十條第三項之規定，三犯施用毒品罪者應依法起訴，嗣上開規定業經刪除，而於\n    第二十三條第二項修正為觀察、勒戒執行完畢釋放後，五年內再犯第十條之罪者\n    ，應依法追訴。從而，本案不論適用修正前或修正後之規定，被告上開施用毒品\n    犯行均應依法追訴，即不因法律修正而受有不利，自應依修正後之規定處理。是\n    核被告所為，係犯毒品危害防制條例第十條第二項之施用第二級毒品罪。其為施\n    用而持有第二級毒品命ＭＤＭＡ，持有之低度行為為施用之高度行為所吸收，不\n    另論罪。爰審酌被告施用毒品性質上屬對自我身心健康之戕害行為，對社會所造\n    成之損害並非直接、巨大，惟其屢經國家之觀察、勒戒處分，仍未能根絕毒癮，\n    且犯後否認犯行，足見其屢犯不悛等一切情狀，量處如主文所示之刑，並諭知易\n    科罰金之折算標準，以資懲儆。\n三、依刑事訴訟法第四百四十九條第一項前段、第三項、第四百五十四條第二項，毒\n    品危害防制條例第十條第二項，刑法第十一條前段、第四十一條第一項前段，罰\n    金罰鍰提高標準條例第二條，逕以簡易判決處刑如主文。\n四、如不服本判決，得於判決書送達之日起十日內，以書狀敘述理由，向本庭提出上\n    訴。\n中      華      民      國    九十三    年      四      月      十二    日\n                                    臺灣高雄地方法院高雄簡易庭\n                                        法  官  劉惠娟\n右正本證明與原本無異。\n如不服本判決，應於判決送達後十日內，向本院提出上訴狀。\n                                        書記官  陳素徵\n中      華      民      國    九十三    年      四      月      十三    日\n",
  "structure": {
    "main": "甲○○施用第二級毒品，處有期徒刑貳月，如易科罰金，以參佰元折算壹日。",
    "fact": "一、本案犯罪事實及證據，除犯罪事實應補充更正：「甲○○前於民國九十一年七月\n    間，因施用毒品行為，經觀察、勒戒處分後，認無繼續施用毒品傾向，而經臺灣\n    高雄少年法院裁定不付審理確定。嗣復因施用第二級毒品ＭＤＭＡ案件，經觀察\n    、勒戒後，認無繼續施用毒品傾向，於九十二年七月二十四釋放，並由臺灣高雄\n    少年法院於九十二年七月三十一日，以九十二年度少調字第七九九號裁定不付審\n    理」，及證據部分應補充「臺灣高等法院被告全國前案紀錄表一份」外，餘均引\n    用如附件檢察官聲請簡易判決處刑書之記載。\n二、按被告行為後，毒品危害防制條例業於九十二年七月九日修正公布，並於九十三\n    年一月九日施行。依修正後之第三十五條第一項第三款及第二項規定：「於中華\n    民國九十二年六月六日本條例修正施行前繫屬之施用毒品案件，於修正施行後，\n    適用修正後之規定，審判中之案件，由法院依修正後規定處理之。前項情形，依\n    修正前之規定有利於行為人者，適用最有利於行為人之法律」，而依修正前第二\n    十條第三項之規定，三犯施用毒品罪者應依法起訴，嗣上開規定業經刪除，而於\n    第二十三條第二項修正為觀察、勒戒執行完畢釋放後，五年內再犯第十條之罪者\n    ，應依法追訴。從而，本案不論適用修正前或修正後之規定，被告上開施用毒品\n    犯行均應依法追訴，即不因法律修正而受有不利，自應依修正後之規定處理。是\n    核被告所為，係犯毒品危害防制條例第十條第二項之施用第二級毒品罪。其為施\n    用而持有第二級毒品命ＭＤＭＡ，持有之低度行為為施用之高度行為所吸收，不\n    另論罪。爰審酌被告施用毒品性質上屬對自我身心健康之戕害行為，對社會所造\n    成之損害並非直接、巨大，惟其屢經國家之觀察、勒戒處分，仍未能根絕毒癮，\n    且犯後否認犯行，足見其屢犯不悛等一切情狀，量處如主文所示之刑，並諭知易\n    科罰金之折算標準，以資懲儆。\n三、依刑事訴訟法第四百四十九條第一項前段、第三項、第四百五十四條第二項，毒\n    品危害防制條例第十條第二項，刑法第十一條前段、第四十一條第一項前段，罰\n    金罰鍰提高標準條例第二條，逕以簡易判決處刑如主文。\n四、如不服本判決，得於判決書送達之日起十日內，以書狀敘述理由，向本庭提出上\n    訴。",
    "reason": "一、本案犯罪事實及證據，除犯罪事實應補充更正：「甲○○前於民國九十一年七月\n    間，因施用毒品行為，經觀察、勒戒處分後，認無繼續施用毒品傾向，而經臺灣\n    高雄少年法院裁定不付審理確定。嗣復因施用第二級毒品ＭＤＭＡ案件，經觀察\n    、勒戒後，認無繼續施用毒品傾向，於九十二年七月二十四釋放，並由臺灣高雄\n    少年法院於九十二年七月三十一日，以九十二年度少調字第七九九號裁定不付審\n    理」，及證據部分應補充「臺灣高等法院被告全國前案紀錄表一份」外，餘均引\n    用如附件檢察官聲請簡易判決處刑書之記載。\n二、按被告行為後，毒品危害防制條例業於九十二年七月九日修正公布，並於九十三\n    年一月九日施行。依修正後之第三十五條第一項第三款及第二項規定：「於中華\n    民國九十二年六月六日本條例修正施行前繫屬之施用毒品案件，於修正施行後，\n    適用修正後之規定，審判中之案件，由法院依修正後規定處理之。前項情形，依\n    修正前之規定有利於行為人者，適用最有利於行為人之法律」，而依修正前第二\n    十條第三項之規定，三犯施用毒品罪者應依法起訴，嗣上開規定業經刪除，而於\n    第二十三條第二項修正為觀察、勒戒執行完畢釋放後，五年內再犯第十條之罪者\n    ，應依法追訴。從而，本案不論適用修正前或修正後之規定，被告上開施用毒品\n    犯行均應依法追訴，即不因法律修正而受有不利，自應依修正後之規定處理。是\n    核被告所為，係犯毒品危害防制條例第十條第二項之施用第二級毒品罪。其為施\n    用而持有第二級毒品命ＭＤＭＡ，持有之低度行為為施用之高度行為所吸收，不\n    另論罪。爰審酌被告施用毒品性質上屬對自我身心健康之戕害行為，對社會所造\n    成之損害並非直接、巨大，惟其屢經國家之觀察、勒戒處分，仍未能根絕毒癮，\n    且犯後否認犯行，足見其屢犯不悛等一切情狀，量處如主文所示之刑，並諭知易\n    科罰金之折算標準，以資懲儆。\n三、依刑事訴訟法第四百四十九條第一項前段、第三項、第四百五十四條第二項，毒\n    品危害防制條例第十條第二項，刑法第十一條前段、第四十一條第一項前段，罰\n    金罰鍰提高標準條例第二條，逕以簡易判決處刑如主文。\n四、如不服本判決，得於判決書送達之日起十日內，以書狀敘述理由，向本庭提出上\n    訴。"
  },
  "search": "臺灣高雄地方法院刑事簡易判決九十三年度簡字第一六一九號聲請人臺灣高雄地方法院檢察署檢察官被告甲○○右列被告因違反毒品危害防制條例案件，經檢察官聲請簡易判決處刑（九十二年度毒偵字第七三四九號），本院判決如左：主文甲○○施用第二級毒品，處有期徒刑貳月，如易科罰金，以參佰元折算壹日。事實及理由一、本案犯罪事實及證據，除犯罪事實應補充更正：「甲○○前於民國九十一年七月間，因施用毒品行為，經觀察、勒戒處分後，認無繼續施用毒品傾向，而經臺灣高雄少年法院裁定不付審理確定。嗣復因施用第二級毒品ＭＤＭＡ案件，經觀察、勒戒後，認無繼續施用毒品傾向，於九十二年七月二十四釋放，並由臺灣高雄少年法院於九十二年七月三十一日，以九十二年度少調字第七九九號裁定不付審理」，及證據部分應補充「臺灣高等法院被告全國前案紀錄表一份」外，餘均引用如附件檢察官聲請簡易判決處刑書之記載。二、按被告行為後，毒品危害防制條例業於九十二年七月九日修正公布，並於九十三年一月九日施行。依修正後之第三十五條第一項第三款及第二項規定：「於中華民國九十二年六月六日本條例修正施行前繫屬之施用毒品案件，於修正施行後，適用修正後之規定，審判中之案件，由法院依修正後規定處理之。前項情形，依修正前之規定有利於行為人者，適用最有利於行為人之法律」，而依修正前第二十條第三項之規定，三犯施用毒品罪者應依法起訴，嗣上開規定業經刪除，而於第二十三條第二項修正為觀察、勒戒執行完畢釋放後，五年內再犯第十條之罪者，應依法追訴。從而，本案不論適用修正前或修正後之規定，被告上開施用毒品犯行均應依法追訴，即不因法律修正而受有不利，自應依修正後之規定處理。是核被告所為，係犯毒品危害防制條例第十條第二項之施用第二級毒品罪。其為施用而持有第二級毒品命ＭＤＭＡ，持有之低度行為為施用之高度行為所吸收，不另論罪。爰審酌被告施用毒品性質上屬對自我身心健康之戕害行為，對社會所造成之損害並非直接、巨大，惟其屢經國家之觀察、勒戒處分，仍未能根絕毒癮，且犯後否認犯行，足見其屢犯不悛等一切情狀，量處如主文所示之刑，並諭知易科罰金之折算標準，以資懲儆。三、依刑事訴訟法第四百四十九條第一項前段、第三項、第四百五十四條第二項，毒品危害防制條例第十條第二項，刑法第十一條前段、第四十一條第一項前段，罰金罰鍰提高標準條例第二條，逕以簡易判決處刑如主文。四、如不服本判決，得於判決書送達之日起十日內，以書狀敘述理由，向本庭提出上訴。中華民國九十三年四月十二日臺灣高雄地方法院高雄簡易庭法官劉惠娟右正本證明與原本無異。如不服本判決，應於判決送達後十日內，向本院提出上訴狀。書記官陳素徵中華民國九十三年四月十三日",
  "characters": {
    "judges": [
      "劉惠娟"
    ],
    "prosecutors": [

    ],
    "lawyers": [

    ],
    "clerks": [
      "陳素徵"
    ],
    "plaintiffs": [

    ],
    "defendants": [
      "甲○○",
      "右列被告因違反毒品危害防制條例案件，經檢察官聲請簡易判決處刑（九十二年度毒",
      "偵字第七三四九號），本院判決如左："
    ],
    "prosecutor_office": [
      "臺灣高雄地方法院檢察署檢察官"
    ],
    "creditors": [

    ],
    "debtors": [

    ],
    "judicial_associate_officer": [

    ]
  },
  "adjudged_at": "2004-04-12",
  "created_at": "2016-02-05 23:19:18",
  "updated_at": "2016-02-05 23:19:18"
}