{
  "identify": "KSD-99-司執消債清-136-20110422",
  "court": {
    "name": "臺灣高雄地方法院",
    "code": "KSD"
  },
  "division": {
    "name": "民事",
    "code": "V"
  },
  "year": 99,
  "word": "司執消債清",
  "number": "136",
  "jcheck": "",
  "reason": "",
  "content": "臺灣高雄地方法院民事裁定       99年度司執消債清字第136號\n聲  請  人\n即債務人    李劉賽英\n債  權  人  花旗（臺灣）商業銀行股份有限公司\n法定代理人  管國霖\n債  權  人  新加坡商星展銀行股份有限公司\n法定代理人  陳亮丞\n債  權  人  臺灣銀行股份有限公司\n法定代理人  羅澤成\n債  權  人  合作金庫商業銀行股份有限公司\n法定代理人  劉燈城\n債  權  人  力興資產管理股份有限公司\n法定代理人  趙榮芳\n債  權  人  臺灣土地銀行股份有限公司\n法定代理人  蘇樂明\n債  權  人  澳商澳盛銀行集團股份有限公司台北分公司\n法定代理人  經天瑞\n債  權  人  元誠國際資產管理股份有限公司\n法定代理人  周玉麟\n上列聲請人聲請消費者債務清理事件，於裁定開始清算程序後，\n因清算財團之財產不敷清償財團費用及債務，本院裁定如下：\n    主  文\n本件清算程序終止。\n    理  由\n一、按法院裁定開始清算程序後，如清算財團之財產不敷清償第\n    108條所定費用及債務時，法院因管理人之聲請或依職權以\n    裁定終止清算程序，消費者債務清理條例第129條第1項定有\n    明文。\n二、本件債務人聲請消費者債務清理事件，業經本院99年度消債\n    清第135號裁定開始清算程序在案，有民事裁定附卷足憑。\n    經查，債務人之財產僅有保證責任高雄市第三信用合作社及\n    正隆股份有限公司之投資，投資金額合計新台幣6,365元，\n    又債務人之配偶已於民國93年4月9日死亡，債務人並繼承大\n    筆債務，並無剩餘財產差額分配請求權可資分配，有國稅局\n    財產歸屬資料清單及債權表在卷可稽。準此，經本院審酌上\n    開資料，堪認本件債務人之財產應不敷清償本條例第108條\n    各款所定財團費用、財團債務等，若繼續進行清算程序，顯\n    無實益，徒增勞費，爰依上開規定裁定如主文。\n三、如不服本裁定，應於裁定送達後10日內，以書狀向司法事務\n    官提出異議。\n中    華    民    國   100    年    4     月    22    日\n                  民事庭    司法事務官  陳宜君",
  "structure": {
    "main": "本件清算程序終止。",
    "reason": "一、按法院裁定開始清算程序後，如清算財團之財產不敷清償第\n    108條所定費用及債務時，法院因管理人之聲請或依職權以\n    裁定終止清算程序，消費者債務清理條例第129條第1項定有\n    明文。\n二、本件債務人聲請消費者債務清理事件，業經本院99年度消債\n    清第135號裁定開始清算程序在案，有民事裁定附卷足憑。\n    經查，債務人之財產僅有保證責任高雄市第三信用合作社及\n    正隆股份有限公司之投資，投資金額合計新台幣6,365元，\n    又債務人之配偶已於民國93年4月9日死亡，債務人並繼承大\n    筆債務，並無剩餘財產差額分配請求權可資分配，有國稅局\n    財產歸屬資料清單及債權表在卷可稽。準此，經本院審酌上\n    開資料，堪認本件債務人之財產應不敷清償本條例第108條\n    各款所定財團費用、財團債務等，若繼續進行清算程序，顯\n    無實益，徒增勞費，爰依上開規定裁定如主文。\n三、如不服本裁定，應於裁定送達後10日內，以書狀向司法事務\n    官提出異議。"
  },
  "search": "臺灣高雄地方法院民事裁定99年度司執消債清字第136號聲請人即債務人李劉賽英債權人花旗（臺灣）商業銀行股份有限公司法定代理人管國霖債權人新加坡商星展銀行股份有限公司法定代理人陳亮丞債權人臺灣銀行股份有限公司法定代理人羅澤成債權人合作金庫商業銀行股份有限公司法定代理人劉燈城債權人力興資產管理股份有限公司法定代理人趙榮芳債權人臺灣土地銀行股份有限公司法定代理人蘇樂明債權人澳商澳盛銀行集團股份有限公司台北分公司法定代理人經天瑞債權人元誠國際資產管理股份有限公司法定代理人周玉麟上列聲請人聲請消費者債務清理事件，於裁定開始清算程序後，因清算財團之財產不敷清償財團費用及債務，本院裁定如下：主文本件清算程序終止。理由一、按法院裁定開始清算程序後，如清算財團之財產不敷清償第108條所定費用及債務時，法院因管理人之聲請或依職權以裁定終止清算程序，消費者債務清理條例第129條第1項定有明文。二、本件債務人聲請消費者債務清理事件，業經本院99年度消債清第135號裁定開始清算程序在案，有民事裁定附卷足憑。經查，債務人之財產僅有保證責任高雄市第三信用合作社及正隆股份有限公司之投資，投資金額合計新台幣6,365元，又債務人之配偶已於民國93年4月9日死亡，債務人並繼承大筆債務，並無剩餘財產差額分配請求權可資分配，有國稅局財產歸屬資料清單及債權表在卷可稽。準此，經本院審酌上開資料，堪認本件債務人之財產應不敷清償本條例第108條各款所定財團費用、財團債務等，若繼續進行清算程序，顯無實益，徒增勞費，爰依上開規定裁定如主文。三、如不服本裁定，應於裁定送達後10日內，以書狀向司法事務官提出異議。中華民國100年4月22日民事庭司法事務官陳宜君",
  "characters": {
    "judges": [

    ],
    "prosecutors": [

    ],
    "lawyers": [

    ],
    "clerks": [

    ],
    "plaintiffs": [

    ],
    "defendants": [

    ],
    "prosecutor_office": [
      "即債務人"
    ],
    "creditors": [
      "花旗",
      "新加坡商星展銀行股份有限公司",
      "臺灣銀行股份有限公司",
      "合作金庫商業銀行股份有限公司",
      "力興資產管理股份有限公司",
      "臺灣土地銀行股份有限公司",
      "澳商澳盛銀行集團股份有限公司台北分公司",
      "元誠國際資產管理股份有限公司"
    ],
    "debtors": [

    ],
    "judicial_associate_officer": [
      "陳宜君"
    ]
  },
  "adjudged_at": "2011-04-22",
  "created_at": "2016-02-12 08:20:41",
  "updated_at": "2016-02-12 08:20:41"
}