{
  "identify": "PCD-100-簡-2722-20110422-1",
  "court": {
    "name": "臺灣新北地方法院",
    "code": "PCD"
  },
  "division": {
    "name": "刑事",
    "code": "M"
  },
  "year": 100,
  "word": "簡",
  "number": "2722",
  "jcheck": "1",
  "reason": "傷害等",
  "content": "臺灣板橋地方法院刑事簡易判決         100年度簡字第2722號\n公  訴  人  臺灣板橋地方法院檢察署檢察官\n被      告  吳雪英\n上列被告因傷害等案件，經檢察官提起公訴（99年度偵字第2346\n1 號），被告自白犯罪，本院認宜以簡易判決處刑（原審理案號\n：100 年度易字第646 號），爰不經通常審理程序，裁定逕以簡\n易判決處刑如下：\n    主      文\n吳雪英犯傷害人之身體罪，處拘役貳拾日，如易科罰金以新台幣\n壹仟元折算壹日；又犯以強暴手段使人行無義務之事罪，處拘役\n貳拾日，如易科罰金以新台幣壹仟元折算壹日；又犯公然侮辱罪\n，處拘役拾伍日，如易科罰金以新台幣壹仟元折算壹日。應執行\n拘役伍拾日，如易科罰金以新台幣壹仟元折算壹日。\n    事實及理由\n一、本件之犯罪事實、證據除犯罪事實一第2 行之「臺北縣中和\n    市」，因臺北縣改制為新北市之故，應配合更正為「新北市\n    中和區」，以及證據部分補充被告吳雪英於本院準備程序中\n    之自白外，餘均引用如附件起訴書之記載。\n二、核被告所為，係犯刑法第277 條第1 項之傷害罪、第304 條\n    之以強暴手段使人行無義務之事罪、第309 條第1 項之公然\n    侮辱罪。被告所犯上開三罪，犯意各別，行為互殊，應予分\n    論併罰。審酌被告僅因細故即對告訴人黃玉琴以言詞及肢體\n    動作為不法侵害，所為甚為不該，幸其本件犯行，僅造成告\n    訴人右手腕擦傷及左上臂擦傷等輕微傷害，未釀成更嚴重之\n    肢體傷勢，再斟酌被告本件以前雖有賭博及毒品等案件之刑\n    事前案紀錄，惟於本件案發時日前回溯5 年內，並無其他有\n    期徒刑執行完畢之紀錄，此有臺灣高等法院被告前案紀錄表\n    1 份在卷可稽，堪認其素行尚可，且犯後業已坦承犯行，並\n    斟酌被告之犯罪動機、手段，以及迄今未獲告訴人諒解等一\n    切情狀，量處如主文所示之刑，併諭知易科罰金之折算標準\n    ，以資處罰。\n三、應依刑事訴訟法第449 條第2 項、第3 項、第454 條第2 項\n    ，刑法第277 條第1 項、第304 條第1 項、第309 條第1 項\n    、第51條第6 款、第41條第1 項前段，刑法施行法第1 條之\n    1 ，逕以簡易判決處如主文所示之刑。\n四、如不服本判決，應於判決送達之日起10日內，向本院提出上\n    訴狀。\n中    華    民    國   100    年    4     月    22    日\n                  刑事第二十一庭  法  官  李俊彥\n上列正本證明與原本無異。\n如不服本判決，應於送達後10日內敘明上訴理由，向本院提出上\n訴狀，上訴於本院第二審合議庭 (應附繕本) 。\n                                  書記官  林文達\n中    華    民    國   100    年    4     月    22    日\n附錄本判決論罪法條全文：\n刑法第277條\n傷害人之身體或健康者，處3 年以下有期徒刑、拘役或1 千元以\n下罰金。\n犯前項之罪因而致人於死者，處無期徒刑或7 年以上有期徒刑；\n致重傷者，處3 年以上10年以下有期徒刑。\n刑法第304條\n以強暴、脅迫使人行無義務之事或妨害人行使權利者，處 3 年\n以下有期徒刑、拘役或 3 百元以下罰金。\n前項之未遂犯罰之。\n刑法第309條\n公然侮辱人者，處拘役或 3 百元以下罰金。\n以強暴犯前項之罪者，處 1 年以下有期徒刑、拘役或 5 百元以\n下罰金。",
  "structure": {
    "main": "吳雪英犯傷害人之身體罪，處拘役貳拾日，如易科罰金以新台幣\n壹仟元折算壹日；又犯以強暴手段使人行無義務之事罪，處拘役\n貳拾日，如易科罰金以新台幣壹仟元折算壹日；又犯公然侮辱罪\n，處拘役拾伍日，如易科罰金以新台幣壹仟元折算壹日。應執行\n拘役伍拾日，如易科罰金以新台幣壹仟元折算壹日。",
    "fact": "一、本件之犯罪事實、證據除犯罪事實一第2 行之「臺北縣中和\n    市」，因臺北縣改制為新北市之故，應配合更正為「新北市\n    中和區」，以及證據部分補充被告吳雪英於本院準備程序中\n    之自白外，餘均引用如附件起訴書之記載。\n二、核被告所為，係犯刑法第277 條第1 項之傷害罪、第304 條\n    之以強暴手段使人行無義務之事罪、第309 條第1 項之公然\n    侮辱罪。被告所犯上開三罪，犯意各別，行為互殊，應予分\n    論併罰。審酌被告僅因細故即對告訴人黃玉琴以言詞及肢體\n    動作為不法侵害，所為甚為不該，幸其本件犯行，僅造成告\n    訴人右手腕擦傷及左上臂擦傷等輕微傷害，未釀成更嚴重之\n    肢體傷勢，再斟酌被告本件以前雖有賭博及毒品等案件之刑\n    事前案紀錄，惟於本件案發時日前回溯5 年內，並無其他有\n    期徒刑執行完畢之紀錄，此有臺灣高等法院被告前案紀錄表\n    1 份在卷可稽，堪認其素行尚可，且犯後業已坦承犯行，並\n    斟酌被告之犯罪動機、手段，以及迄今未獲告訴人諒解等一\n    切情狀，量處如主文所示之刑，併諭知易科罰金之折算標準\n    ，以資處罰。\n三、應依刑事訴訟法第449 條第2 項、第3 項、第454 條第2 項\n    ，刑法第277 條第1 項、第304 條第1 項、第309 條第1 項\n    、第51條第6 款、第41條第1 項前段，刑法施行法第1 條之\n    1 ，逕以簡易判決處如主文所示之刑。\n四、如不服本判決，應於判決送達之日起10日內，向本院提出上\n    訴狀。",
    "reason": "一、本件之犯罪事實、證據除犯罪事實一第2 行之「臺北縣中和\n    市」，因臺北縣改制為新北市之故，應配合更正為「新北市\n    中和區」，以及證據部分補充被告吳雪英於本院準備程序中\n    之自白外，餘均引用如附件起訴書之記載。\n二、核被告所為，係犯刑法第277 條第1 項之傷害罪、第304 條\n    之以強暴手段使人行無義務之事罪、第309 條第1 項之公然\n    侮辱罪。被告所犯上開三罪，犯意各別，行為互殊，應予分\n    論併罰。審酌被告僅因細故即對告訴人黃玉琴以言詞及肢體\n    動作為不法侵害，所為甚為不該，幸其本件犯行，僅造成告\n    訴人右手腕擦傷及左上臂擦傷等輕微傷害，未釀成更嚴重之\n    肢體傷勢，再斟酌被告本件以前雖有賭博及毒品等案件之刑\n    事前案紀錄，惟於本件案發時日前回溯5 年內，並無其他有\n    期徒刑執行完畢之紀錄，此有臺灣高等法院被告前案紀錄表\n    1 份在卷可稽，堪認其素行尚可，且犯後業已坦承犯行，並\n    斟酌被告之犯罪動機、手段，以及迄今未獲告訴人諒解等一\n    切情狀，量處如主文所示之刑，併諭知易科罰金之折算標準\n    ，以資處罰。\n三、應依刑事訴訟法第449 條第2 項、第3 項、第454 條第2 項\n    ，刑法第277 條第1 項、第304 條第1 項、第309 條第1 項\n    、第51條第6 款、第41條第1 項前段，刑法施行法第1 條之\n    1 ，逕以簡易判決處如主文所示之刑。\n四、如不服本判決，應於判決送達之日起10日內，向本院提出上\n    訴狀。"
  },
  "search": "臺灣板橋地方法院刑事簡易判決100年度簡字第2722號公訴人臺灣板橋地方法院檢察署檢察官被告吳雪英上列被告因傷害等案件，經檢察官提起公訴（99年度偵字第23461號），被告自白犯罪，本院認宜以簡易判決處刑（原審理案號：100年度易字第646號），爰不經通常審理程序，裁定逕以簡易判決處刑如下：主文吳雪英犯傷害人之身體罪，處拘役貳拾日，如易科罰金以新台幣壹仟元折算壹日；又犯以強暴手段使人行無義務之事罪，處拘役貳拾日，如易科罰金以新台幣壹仟元折算壹日；又犯公然侮辱罪，處拘役拾伍日，如易科罰金以新台幣壹仟元折算壹日。應執行拘役伍拾日，如易科罰金以新台幣壹仟元折算壹日。事實及理由一、本件之犯罪事實、證據除犯罪事實一第2行之「臺北縣中和市」，因臺北縣改制為新北市之故，應配合更正為「新北市中和區」，以及證據部分補充被告吳雪英於本院準備程序中之自白外，餘均引用如附件起訴書之記載。二、核被告所為，係犯刑法第277條第1項之傷害罪、第304條之以強暴手段使人行無義務之事罪、第309條第1項之公然侮辱罪。被告所犯上開三罪，犯意各別，行為互殊，應予分論併罰。審酌被告僅因細故即對告訴人黃玉琴以言詞及肢體動作為不法侵害，所為甚為不該，幸其本件犯行，僅造成告訴人右手腕擦傷及左上臂擦傷等輕微傷害，未釀成更嚴重之肢體傷勢，再斟酌被告本件以前雖有賭博及毒品等案件之刑事前案紀錄，惟於本件案發時日前回溯5年內，並無其他有期徒刑執行完畢之紀錄，此有臺灣高等法院被告前案紀錄表1份在卷可稽，堪認其素行尚可，且犯後業已坦承犯行，並斟酌被告之犯罪動機、手段，以及迄今未獲告訴人諒解等一切情狀，量處如主文所示之刑，併諭知易科罰金之折算標準，以資處罰。三、應依刑事訴訟法第449條第2項、第3項、第454條第2項，刑法第277條第1項、第304條第1項、第309條第1項、第51條第6款、第41條第1項前段，刑法施行法第1條之1，逕以簡易判決處如主文所示之刑。四、如不服本判決，應於判決送達之日起10日內，向本院提出上訴狀。中華民國100年4月22日刑事第二十一庭法官李俊彥上列正本證明與原本無異。如不服本判決，應於送達後10日內敘明上訴理由，向本院提出上訴狀，上訴於本院第二審合議庭(應附繕本)。書記官林文達中華民國100年4月22日附錄本判決論罪法條全文：刑法第277條傷害人之身體或健康者，處3年以下有期徒刑、拘役或1千元以下罰金。犯前項之罪因而致人於死者，處無期徒刑或7年以上有期徒刑；致重傷者，處3年以上10年以下有期徒刑。刑法第304條以強暴、脅迫使人行無義務之事或妨害人行使權利者，處3年以下有期徒刑、拘役或3百元以下罰金。前項之未遂犯罰之。刑法第309條公然侮辱人者，處拘役或3百元以下罰金。以強暴犯前項之罪者，處1年以下有期徒刑、拘役或5百元以下罰金。",
  "characters": {
    "judges": [
      "李俊彥"
    ],
    "prosecutors": [

    ],
    "lawyers": [

    ],
    "clerks": [
      "林文達"
    ],
    "plaintiffs": [

    ],
    "defendants": [
      "吳雪英"
    ],
    "prosecutor_office": [
      "臺灣板橋地方法院檢察署檢察官"
    ],
    "creditors": [

    ],
    "debtors": [

    ],
    "judicial_associate_officer": [

    ]
  },
  "adjudged_at": "2011-04-22",
  "created_at": "2016-02-12 08:23:53",
  "updated_at": "2016-02-12 08:23:53"
}