{
  "identify": "TPD-98-訴-1895-20111110-1",
  "court": {
    "name": "臺灣臺北地方法院",
    "code": "TPD"
  },
  "division": {
    "name": "刑事",
    "code": "M"
  },
  "year": 98,
  "word": "訴",
  "number": "1895",
  "jcheck": "1",
  "reason": "毒品危害防制條例",
  "content": "臺灣臺北地方法院刑事裁定              98年度訴字第1895號\n公  訴  人  臺灣臺北地方法院檢察署檢察官\n被      告  林雅韻\n上列被告因毒品危害防制條例案件，經檢察官提起公訴（98年度\n毒偵緝字第275、276號），本院裁定如下：\n    主  文\n本件停止審判。\n    理  由\n一、按被告心神喪失者，應於其回復以前停止審判，被告因疾病\n    不能到庭者，應於其能到庭以前停止審判，刑事訴訟法第29\n    4條第1、2項定有明文。\n二、經查：被告林雅韻因缺氧性腦病變合併四肢癱瘓，意識呆滯\n    ，全身癱瘓無法行動，轉位困難需要長時間臥床，於98年8\n    月27日經鑑定為極重度植物人，有中國醫藥大學附設醫院臺\n    北分院98年11月19日診斷證明書、該院98年9月19日至98年\n    10月17日之住院病歷資料、國防醫學院三軍總醫院附設民眾\n    診療服務處99年8月2日、100年2月14日、100年8月8日診斷\n    證明書、被告中華民國身心障礙手冊影本在卷為憑（見本院\n    卷第一宗第19、27至92、132、141、148及138頁）；復經本\n    院函詢被告長期就診之國防醫學院三軍總醫院關於其有無到\n    庭應訊能力，經該院函覆謂：被告因缺氧性腦病變合併癲癇\n    症及四肢肢體無力，目前無法自行以輪椅行動，無法與人正\n    常對答，無法理解他人話語；依其病況，需要長期復健治療\n    ，短期內恢復之可能性低等語（見本院卷第二宗第19頁），\n    足證被告因上述疾病之身體、心智狀態已達心神喪失，並無\n    法到庭接受審判，爰依刑事訴訟法第294條第1、2項規定，\n    於其能到庭以前停止審判。\n三、據上論斷，依刑事訴訟法第220條，裁定如主文。\n中    華    民    國   100    年    11    月    10    日\n                  刑事第十五庭  審判長法  官  李明益\n                                      法  官  紀凱峰\n                                      法  官  石千\n上正本證明與原本無異。\n本裁定不得抗告。\n                                      書記官  陳宏璋\n中    華    民    國   100    年    11    月    10    日",
  "structure": {
    "main": "本件停止審判。",
    "reason": "一、按被告心神喪失者，應於其回復以前停止審判，被告因疾病\n    不能到庭者，應於其能到庭以前停止審判，刑事訴訟法第29\n    4條第1、2項定有明文。\n二、經查：被告林雅韻因缺氧性腦病變合併四肢癱瘓，意識呆滯\n    ，全身癱瘓無法行動，轉位困難需要長時間臥床，於98年8\n    月27日經鑑定為極重度植物人，有中國醫藥大學附設醫院臺\n    北分院98年11月19日診斷證明書、該院98年9月19日至98年\n    10月17日之住院病歷資料、國防醫學院三軍總醫院附設民眾\n    診療服務處99年8月2日、100年2月14日、100年8月8日診斷\n    證明書、被告中華民國身心障礙手冊影本在卷為憑（見本院\n    卷第一宗第19、27至92、132、141、148及138頁）；復經本\n    院函詢被告長期就診之國防醫學院三軍總醫院關於其有無到\n    庭應訊能力，經該院函覆謂：被告因缺氧性腦病變合併癲癇\n    症及四肢肢體無力，目前無法自行以輪椅行動，無法與人正\n    常對答，無法理解他人話語；依其病況，需要長期復健治療\n    ，短期內恢復之可能性低等語（見本院卷第二宗第19頁），\n    足證被告因上述疾病之身體、心智狀態已達心神喪失，並無\n    法到庭接受審判，爰依刑事訴訟法第294條第1、2項規定，\n    於其能到庭以前停止審判。\n三、據上論斷，依刑事訴訟法第220條，裁定如主文。"
  },
  "search": "臺灣臺北地方法院刑事裁定98年度訴字第1895號公訴人臺灣臺北地方法院檢察署檢察官被告林雅韻上列被告因毒品危害防制條例案件，經檢察官提起公訴（98年度毒偵緝字第275、276號），本院裁定如下：主文本件停止審判。理由一、按被告心神喪失者，應於其回復以前停止審判，被告因疾病不能到庭者，應於其能到庭以前停止審判，刑事訴訟法第294條第1、2項定有明文。二、經查：被告林雅韻因缺氧性腦病變合併四肢癱瘓，意識呆滯，全身癱瘓無法行動，轉位困難需要長時間臥床，於98年8月27日經鑑定為極重度植物人，有中國醫藥大學附設醫院臺北分院98年11月19日診斷證明書、該院98年9月19日至98年10月17日之住院病歷資料、國防醫學院三軍總醫院附設民眾診療服務處99年8月2日、100年2月14日、100年8月8日診斷證明書、被告中華民國身心障礙手冊影本在卷為憑（見本院卷第一宗第19、27至92、132、141、148及138頁）；復經本院函詢被告長期就診之國防醫學院三軍總醫院關於其有無到庭應訊能力，經該院函覆謂：被告因缺氧性腦病變合併癲癇症及四肢肢體無力，目前無法自行以輪椅行動，無法與人正常對答，無法理解他人話語；依其病況，需要長期復健治療，短期內恢復之可能性低等語（見本院卷第二宗第19頁），足證被告因上述疾病之身體、心智狀態已達心神喪失，並無法到庭接受審判，爰依刑事訴訟法第294條第1、2項規定，於其能到庭以前停止審判。三、據上論斷，依刑事訴訟法第220條，裁定如主文。中華民國100年11月10日刑事第十五庭審判長法官李明益法官紀凱峰法官石千上正本證明與原本無異。本裁定不得抗告。書記官陳宏璋中華民國100年11月10日",
  "characters": {
    "judges": [
      "李明益",
      "紀凱峰",
      "石千"
    ],
    "prosecutors": [

    ],
    "lawyers": [

    ],
    "clerks": [
      "陳宏璋"
    ],
    "plaintiffs": [

    ],
    "defendants": [
      "林雅韻"
    ],
    "prosecutor_office": [
      "臺灣臺北地方法院檢察署檢察官"
    ],
    "creditors": [

    ],
    "debtors": [

    ],
    "judicial_associate_officer": [

    ]
  },
  "adjudged_at": "2011-11-10",
  "created_at": "2016-02-12 23:02:21",
  "updated_at": "2016-02-12 23:02:21"
}