{
  "identify": "TYD-100-訴-374-20111109-2",
  "court": {
    "name": "臺灣桃園地方法院",
    "code": "TYD"
  },
  "division": {
    "name": "刑事",
    "code": "M"
  },
  "year": 100,
  "word": "訴",
  "number": "374",
  "jcheck": "2",
  "reason": "毒品危害防制條例",
  "content": "臺灣桃園地方法院刑事裁定              100年度訴字第374號\n公  訴  人  臺灣桃園地方法院檢察署檢察官\n被      告  姜志豪\n選任辯護人  曾智群律師\n上列被告因為違反毒品危害防制條例案件，經檢察官提起公訴（\n99年度偵緝字第1739號、99年度偵字第23735 號、99年度毒偵字\n第5324號），本院裁定如下：\n    主  文\n姜志豪自民國壹佰年拾壹月拾柒日起延長羈押貳月。\n    理  由\n一、按羈押被告，審判中不得逾3 月，但有繼續羈押之必要者，\n    得於期間未滿前，經法院依刑事訴訟法第101 條或第101 條\n    之1 之規定訊問被告後，以裁定延長之，延長羈押期間，審\n    判中每次不得逾2 月，刑事訴訟法第108 條第1 項及第5 項\n    分別定有明文。\n二、查被告姜志豪因違反毒品危害防制條例案件，經臺灣桃園地\n    方法院檢察署檢察官提起公訴，因被告於本院審理時傳拘無\n    著，經本院發布通緝，被告於民國100 年8 月16日通緝到案\n    ，本院訊問後，認被告犯罪嫌疑重大，所涉犯販賣第二級毒\n    品罪，係屬最輕本刑為5 年以上有期徒刑之罪，且被告係經\n    本院通緝到案，有逃亡之事實，核有刑事訴訟法第101 條第\n    1 項第1 款、第3 款所定羈押之事由，非予羈押，顯難進行\n    審判，有羈押之必要，而於100 年8 月17日裁定羈押。茲本\n    院經訊問被告後，認前述刑事訴訟法第101 條第1 項第1款\n    、第3 款之羈押原因仍然存在，且有繼續羈押之必要，是被\n    告應自100 年11月17日起延長羈押2 月。\n三、依刑事訴訟法第108 條第1 項、第2項，裁定如主文。\n中    華    民    國   100    年    11    月    9     日\n                  刑事第十四庭審判長法  官   鍾雅蘭\n                                    法  官   楊麗文\n                                    法  官   張永輝\n以上正本證明與原本無異。\n如不服本裁定，應於裁定送達後5 日內向本院提出抗告狀。\n                                    書記官   張良煜\n中    華    民    國   100    年    11    月    9     日",
  "structure": {
    "main": "姜志豪自民國壹佰年拾壹月拾柒日起延長羈押貳月。",
    "reason": "一、按羈押被告，審判中不得逾3 月，但有繼續羈押之必要者，\n    得於期間未滿前，經法院依刑事訴訟法第101 條或第101 條\n    之1 之規定訊問被告後，以裁定延長之，延長羈押期間，審\n    判中每次不得逾2 月，刑事訴訟法第108 條第1 項及第5 項\n    分別定有明文。\n二、查被告姜志豪因違反毒品危害防制條例案件，經臺灣桃園地\n    方法院檢察署檢察官提起公訴，因被告於本院審理時傳拘無\n    著，經本院發布通緝，被告於民國100 年8 月16日通緝到案\n    ，本院訊問後，認被告犯罪嫌疑重大，所涉犯販賣第二級毒\n    品罪，係屬最輕本刑為5 年以上有期徒刑之罪，且被告係經\n    本院通緝到案，有逃亡之事實，核有刑事訴訟法第101 條第\n    1 項第1 款、第3 款所定羈押之事由，非予羈押，顯難進行\n    審判，有羈押之必要，而於100 年8 月17日裁定羈押。茲本\n    院經訊問被告後，認前述刑事訴訟法第101 條第1 項第1款\n    、第3 款之羈押原因仍然存在，且有繼續羈押之必要，是被\n    告應自100 年11月17日起延長羈押2 月。\n三、依刑事訴訟法第108 條第1 項、第2項，裁定如主文。"
  },
  "search": "臺灣桃園地方法院刑事裁定100年度訴字第374號公訴人臺灣桃園地方法院檢察署檢察官被告姜志豪選任辯護人曾智群律師上列被告因為違反毒品危害防制條例案件，經檢察官提起公訴（99年度偵緝字第1739號、99年度偵字第23735號、99年度毒偵字第5324號），本院裁定如下：主文姜志豪自民國壹佰年拾壹月拾柒日起延長羈押貳月。理由一、按羈押被告，審判中不得逾3月，但有繼續羈押之必要者，得於期間未滿前，經法院依刑事訴訟法第101條或第101條之1之規定訊問被告後，以裁定延長之，延長羈押期間，審判中每次不得逾2月，刑事訴訟法第108條第1項及第5項分別定有明文。二、查被告姜志豪因違反毒品危害防制條例案件，經臺灣桃園地方法院檢察署檢察官提起公訴，因被告於本院審理時傳拘無著，經本院發布通緝，被告於民國100年8月16日通緝到案，本院訊問後，認被告犯罪嫌疑重大，所涉犯販賣第二級毒品罪，係屬最輕本刑為5年以上有期徒刑之罪，且被告係經本院通緝到案，有逃亡之事實，核有刑事訴訟法第101條第1項第1款、第3款所定羈押之事由，非予羈押，顯難進行審判，有羈押之必要，而於100年8月17日裁定羈押。茲本院經訊問被告後，認前述刑事訴訟法第101條第1項第1款、第3款之羈押原因仍然存在，且有繼續羈押之必要，是被告應自100年11月17日起延長羈押2月。三、依刑事訴訟法第108條第1項、第2項，裁定如主文。中華民國100年11月9日刑事第十四庭審判長法官鍾雅蘭法官楊麗文法官張永輝以上正本證明與原本無異。如不服本裁定，應於裁定送達後5日內向本院提出抗告狀。書記官張良煜中華民國100年11月9日",
  "characters": {
    "judges": [
      "鍾雅蘭",
      "楊麗文",
      "張永輝"
    ],
    "prosecutors": [

    ],
    "lawyers": [
      "曾智群"
    ],
    "clerks": [
      "張良煜"
    ],
    "plaintiffs": [

    ],
    "defendants": [
      "姜志豪"
    ],
    "prosecutor_office": [
      "臺灣桃園地方法院檢察署檢察官"
    ],
    "creditors": [

    ],
    "debtors": [

    ],
    "judicial_associate_officer": [

    ]
  },
  "adjudged_at": "2011-11-09",
  "created_at": "2016-02-12 23:13:36",
  "updated_at": "2016-02-12 23:13:36"
}