{
  "identify": "TPD-100-簡-1386-20110602-1",
  "court": {
    "name": "臺灣臺北地方法院",
    "code": "TPD"
  },
  "division": {
    "name": "刑事",
    "code": "M"
  },
  "year": 100,
  "word": "簡",
  "number": "1386",
  "jcheck": "1",
  "reason": "毒品危害防制條例",
  "content": "臺灣臺北地方法院刑事簡易判決         100年度簡字第1386號\n聲  請  人  臺灣臺北地方法院檢察署檢察官\n被      告  詹志豪\n上列被告因違反毒品危害防制條例案件，經檢察官聲請以簡易判\n決處刑（99年度偵字第21848 號），本院判決如下：\n    主  文\n詹志豪持有第三級毒品純質淨重二十公克以上，處有期徒刑貳月\n，如易科罰金，以新臺幣壹仟元折算壹日。扣案第三級毒品愷他\n命柒包（驗餘總毛重貳拾伍點零肆捌柒公克），均沒收之。\n    事實及理由\n一、本件除犯罪事實中被告詹志豪購買愷他命之時間補充為「民\n    國99年9 月14日下午11時至12時之間某時許」外，其餘犯罪\n    事實及證據均引用檢察官聲請簡易判決處刑書所載（如附件\n    ）。\n二、核被告所為，係犯毒品危害防制條例第11條第5 項之持有第\n    三級毒品純質淨重20公克以上罪。爰審酌被告持有前開毒品\n    ，顯可能滋生其他犯罪，惡化治安，其所為自應受有相當程\n    度之刑事非難；惟另考量被告於警詢、偵訊中均坦承犯行，\n    及持有毒品之數量、期間等一切情狀，量處如主文所示之刑\n    ，並諭知易科罰金之折算標準。\n三、按毒品危害防制條例第18條第1 項後段規定查獲之第三、四\n    級毒品，無正當理由而擅自持有者，沒入銷燬之；此應沒入\n    銷燬之毒品，專指查獲施用或持有純質淨重未逾法定重量（\n    未成罪）之第三、四級毒品而言；倘屬同條例相關法條明文\n    規定處罰之犯罪行為，即非該條項應依行政程序沒入銷燬之\n    範圍；再同條例對於查獲之製造、運輸、販賣、意圖販賣而\n    持有、以非法方法使人施用、引誘他人施用及轉讓、持有一\n    定重量以上第三、四級毒品之沒收，並無特別規定，如其行\n    為已構成犯罪，則該毒品即屬不受法律保護之違禁物，應回\n    歸刑法之適用，依刑法第38條第1 項第1 款之規定沒收之，\n    始為適法（最高法院98年度臺上字第2889號、99年度臺上字\n    第2733號判決意旨參照）。本件所扣得之第三級毒品愷他命\n    7 包（驗餘總毛重為25.0487 公克），自應依刑法第38條第\n    1 項第1 款規定宣告沒收之（已鑑驗耗損之第三級毒品愷他\n    命，因已滅失，毋庸再予宣告沒收）。\n四、依刑事訴訟法第449條第1項前段、第3項、第450條第1項、\n    第454 條第2 項，毒品危害防制條例第11條第5 項，刑法第\n    11條前段、第41條第1 項前段、第38條第1 項第1 款，逕以\n    簡易判決處如主文所示之刑。\n五、如不服本件判決，得自收受本判決送達之日起10日內，向本\n    院提起上訴，由本院合議庭（二審）審理。\n中    華    民    國   100    年    6     月    2     日\n                  刑事第十九庭  法  官  高若珊\n上正本證明與原本無異。\n如不服本判決應於收受送達後10日內向本院提出上訴書狀，並應\n敘述具體理由；其未敘述上訴理由者，應於上訴期間屆滿後20日\n內向本院補提理由書（均須按他造當事人之人數附繕本）「切勿\n逕送上級法院」。\n                                書記官  游曉婷\n中    華    民    國   100    年    6     月    3     日\n附錄論罪科刑法條全文\n毒品危害防制條例第11條\n持有第一級毒品者，處 3 年以下有期徒刑、拘役或新臺幣 5 萬\n元以下罰金。\n持有第二級毒品者，處 2 年以下有期徒刑、拘役或新臺幣 3 萬\n元以下罰金。\n持有第一級毒品純質淨重十公克以上者，處 1 年以上 7 年以下\n有期徒刑，得併科新臺幣 1 百萬元以下罰金。\n持有第二級毒品純質淨重二十公克以上者，處 6 月以上 5 年以\n下有期徒刑，得併科新臺幣 70 萬元以下罰金。\n持有第三級毒品純質淨重二十公克以上者，處 3 年以下有期徒\n刑，得併科新臺幣 30 萬元以下罰金。\n持有第四級毒品純質淨重二十公克以上者，處 1 年以下有期徒\n刑，得併科新臺幣 10 萬元以下罰金。\n持有專供製造或施用第一級、第二級毒品之器具者，處 1 年以\n下有期徒刑、拘役或新臺幣 1 萬元以下罰金。",
  "structure": {
    "main": "詹志豪持有第三級毒品純質淨重二十公克以上，處有期徒刑貳月\n，如易科罰金，以新臺幣壹仟元折算壹日。扣案第三級毒品愷他\n命柒包（驗餘總毛重貳拾伍點零肆捌柒公克），均沒收之。",
    "fact": "一、本件除犯罪事實中被告詹志豪購買愷他命之時間補充為「民\n    國99年9 月14日下午11時至12時之間某時許」外，其餘犯罪\n    事實及證據均引用檢察官聲請簡易判決處刑書所載（如附件\n    ）。\n二、核被告所為，係犯毒品危害防制條例第11條第5 項之持有第\n    三級毒品純質淨重20公克以上罪。爰審酌被告持有前開毒品\n    ，顯可能滋生其他犯罪，惡化治安，其所為自應受有相當程\n    度之刑事非難；惟另考量被告於警詢、偵訊中均坦承犯行，\n    及持有毒品之數量、期間等一切情狀，量處如主文所示之刑\n    ，並諭知易科罰金之折算標準。\n三、按毒品危害防制條例第18條第1 項後段規定查獲之第三、四\n    級毒品，無正當理由而擅自持有者，沒入銷燬之；此應沒入\n    銷燬之毒品，專指查獲施用或持有純質淨重未逾法定重量（\n    未成罪）之第三、四級毒品而言；倘屬同條例相關法條明文\n    規定處罰之犯罪行為，即非該條項應依行政程序沒入銷燬之\n    範圍；再同條例對於查獲之製造、運輸、販賣、意圖販賣而\n    持有、以非法方法使人施用、引誘他人施用及轉讓、持有一\n    定重量以上第三、四級毒品之沒收，並無特別規定，如其行\n    為已構成犯罪，則該毒品即屬不受法律保護之違禁物，應回\n    歸刑法之適用，依刑法第38條第1 項第1 款之規定沒收之，\n    始為適法（最高法院98年度臺上字第2889號、99年度臺上字\n    第2733號判決意旨參照）。本件所扣得之第三級毒品愷他命\n    7 包（驗餘總毛重為25.0487 公克），自應依刑法第38條第\n    1 項第1 款規定宣告沒收之（已鑑驗耗損之第三級毒品愷他\n    命，因已滅失，毋庸再予宣告沒收）。\n四、依刑事訴訟法第449條第1項前段、第3項、第450條第1項、\n    第454 條第2 項，毒品危害防制條例第11條第5 項，刑法第\n    11條前段、第41條第1 項前段、第38條第1 項第1 款，逕以\n    簡易判決處如主文所示之刑。\n五、如不服本件判決，得自收受本判決送達之日起10日內，向本\n    院提起上訴，由本院合議庭（二審）審理。",
    "reason": "一、本件除犯罪事實中被告詹志豪購買愷他命之時間補充為「民\n    國99年9 月14日下午11時至12時之間某時許」外，其餘犯罪\n    事實及證據均引用檢察官聲請簡易判決處刑書所載（如附件\n    ）。\n二、核被告所為，係犯毒品危害防制條例第11條第5 項之持有第\n    三級毒品純質淨重20公克以上罪。爰審酌被告持有前開毒品\n    ，顯可能滋生其他犯罪，惡化治安，其所為自應受有相當程\n    度之刑事非難；惟另考量被告於警詢、偵訊中均坦承犯行，\n    及持有毒品之數量、期間等一切情狀，量處如主文所示之刑\n    ，並諭知易科罰金之折算標準。\n三、按毒品危害防制條例第18條第1 項後段規定查獲之第三、四\n    級毒品，無正當理由而擅自持有者，沒入銷燬之；此應沒入\n    銷燬之毒品，專指查獲施用或持有純質淨重未逾法定重量（\n    未成罪）之第三、四級毒品而言；倘屬同條例相關法條明文\n    規定處罰之犯罪行為，即非該條項應依行政程序沒入銷燬之\n    範圍；再同條例對於查獲之製造、運輸、販賣、意圖販賣而\n    持有、以非法方法使人施用、引誘他人施用及轉讓、持有一\n    定重量以上第三、四級毒品之沒收，並無特別規定，如其行\n    為已構成犯罪，則該毒品即屬不受法律保護之違禁物，應回\n    歸刑法之適用，依刑法第38條第1 項第1 款之規定沒收之，\n    始為適法（最高法院98年度臺上字第2889號、99年度臺上字\n    第2733號判決意旨參照）。本件所扣得之第三級毒品愷他命\n    7 包（驗餘總毛重為25.0487 公克），自應依刑法第38條第\n    1 項第1 款規定宣告沒收之（已鑑驗耗損之第三級毒品愷他\n    命，因已滅失，毋庸再予宣告沒收）。\n四、依刑事訴訟法第449條第1項前段、第3項、第450條第1項、\n    第454 條第2 項，毒品危害防制條例第11條第5 項，刑法第\n    11條前段、第41條第1 項前段、第38條第1 項第1 款，逕以\n    簡易判決處如主文所示之刑。\n五、如不服本件判決，得自收受本判決送達之日起10日內，向本\n    院提起上訴，由本院合議庭（二審）審理。"
  },
  "search": "臺灣臺北地方法院刑事簡易判決100年度簡字第1386號聲請人臺灣臺北地方法院檢察署檢察官被告詹志豪上列被告因違反毒品危害防制條例案件，經檢察官聲請以簡易判決處刑（99年度偵字第21848號），本院判決如下：主文詹志豪持有第三級毒品純質淨重二十公克以上，處有期徒刑貳月，如易科罰金，以新臺幣壹仟元折算壹日。扣案第三級毒品愷他命柒包（驗餘總毛重貳拾伍點零肆捌柒公克），均沒收之。事實及理由一、本件除犯罪事實中被告詹志豪購買愷他命之時間補充為「民國99年9月14日下午11時至12時之間某時許」外，其餘犯罪事實及證據均引用檢察官聲請簡易判決處刑書所載（如附件）。二、核被告所為，係犯毒品危害防制條例第11條第5項之持有第三級毒品純質淨重20公克以上罪。爰審酌被告持有前開毒品，顯可能滋生其他犯罪，惡化治安，其所為自應受有相當程度之刑事非難；惟另考量被告於警詢、偵訊中均坦承犯行，及持有毒品之數量、期間等一切情狀，量處如主文所示之刑，並諭知易科罰金之折算標準。三、按毒品危害防制條例第18條第1項後段規定查獲之第三、四級毒品，無正當理由而擅自持有者，沒入銷燬之；此應沒入銷燬之毒品，專指查獲施用或持有純質淨重未逾法定重量（未成罪）之第三、四級毒品而言；倘屬同條例相關法條明文規定處罰之犯罪行為，即非該條項應依行政程序沒入銷燬之範圍；再同條例對於查獲之製造、運輸、販賣、意圖販賣而持有、以非法方法使人施用、引誘他人施用及轉讓、持有一定重量以上第三、四級毒品之沒收，並無特別規定，如其行為已構成犯罪，則該毒品即屬不受法律保護之違禁物，應回歸刑法之適用，依刑法第38條第1項第1款之規定沒收之，始為適法（最高法院98年度臺上字第2889號、99年度臺上字第2733號判決意旨參照）。本件所扣得之第三級毒品愷他命7包（驗餘總毛重為25.0487公克），自應依刑法第38條第1項第1款規定宣告沒收之（已鑑驗耗損之第三級毒品愷他命，因已滅失，毋庸再予宣告沒收）。四、依刑事訴訟法第449條第1項前段、第3項、第450條第1項、第454條第2項，毒品危害防制條例第11條第5項，刑法第11條前段、第41條第1項前段、第38條第1項第1款，逕以簡易判決處如主文所示之刑。五、如不服本件判決，得自收受本判決送達之日起10日內，向本院提起上訴，由本院合議庭（二審）審理。中華民國100年6月2日刑事第十九庭法官高若珊上正本證明與原本無異。如不服本判決應於收受送達後10日內向本院提出上訴書狀，並應敘述具體理由；其未敘述上訴理由者，應於上訴期間屆滿後20日內向本院補提理由書（均須按他造當事人之人數附繕本）「切勿逕送上級法院」。書記官游曉婷中華民國100年6月3日附錄論罪科刑法條全文毒品危害防制條例第11條持有第一級毒品者，處3年以下有期徒刑、拘役或新臺幣5萬元以下罰金。持有第二級毒品者，處2年以下有期徒刑、拘役或新臺幣3萬元以下罰金。持有第一級毒品純質淨重十公克以上者，處1年以上7年以下有期徒刑，得併科新臺幣1百萬元以下罰金。持有第二級毒品純質淨重二十公克以上者，處6月以上5年以下有期徒刑，得併科新臺幣70萬元以下罰金。持有第三級毒品純質淨重二十公克以上者，處3年以下有期徒刑，得併科新臺幣30萬元以下罰金。持有第四級毒品純質淨重二十公克以上者，處1年以下有期徒刑，得併科新臺幣10萬元以下罰金。持有專供製造或施用第一級、第二級毒品之器具者，處1年以下有期徒刑、拘役或新臺幣1萬元以下罰金。",
  "characters": {
    "judges": [
      "高若珊"
    ],
    "prosecutors": [

    ],
    "lawyers": [

    ],
    "clerks": [
      "游曉婷"
    ],
    "plaintiffs": [

    ],
    "defendants": [
      "詹志豪"
    ],
    "prosecutor_office": [
      "臺灣臺北地方法院檢察署檢察官"
    ],
    "creditors": [

    ],
    "debtors": [

    ],
    "judicial_associate_officer": [

    ]
  },
  "adjudged_at": "2011-06-02",
  "created_at": "2016-02-13 15:29:04",
  "updated_at": "2016-02-13 15:29:04"
}