{
  "identify": "ULD-100-聲-572-20110602-1",
  "court": {
    "name": "臺灣雲林地方法院",
    "code": "ULD"
  },
  "division": {
    "name": "刑事",
    "code": "M"
  },
  "year": 100,
  "word": "聲",
  "number": "572",
  "jcheck": "1",
  "reason": "宣告沒收物",
  "content": "臺灣雲林地方法院刑事裁定              100年度聲字第572號\n聲  請  人  臺灣雲林地方法院檢察署檢察官\n被      告  薛武易\n上列聲請人因被告違反毒品危害防制條例案件（100 年度戒毒偵\n字第40、41號），聲請單獨宣告沒收銷燬違禁物（100 年度聲沒\n字第83號），本院裁定如下：\n    主  文\n扣案之含有第一級毒品海洛因成分之塊狀物（合計淨重拾參點肆\n捌公克，驗餘淨重拾參點肆壹公克，純度百分之柒拾陸點肆陸，\n純質淨重拾點參壹公克）、第二級毒品甲基安非他命成分之白色\n透明結晶顆粒（驗餘淨重分別為貳點貳玖參捌公克、零點零柒伍\n參公克，合計貳點參陸玖壹公克）均沒收銷燬。\n    理  由\n一、按違禁物得單獨宣告沒收，且違禁物，不問屬於犯罪行為人\n    與否，沒收之；又按查獲之第一、二級毒品，不問屬於犯人\n    與否，沒收銷燬之，刑法第40條第2項、第38條第1項第1款\n    、第2項、毒品危害防制條例第18條第1項前段分別定有明文\n    。\n二、聲請意旨略以：被告薛武易（因本件施用第一、二級毒品之\n    犯行，經臺灣雲林地方法院檢察署檢察官前於民國100 年4\n    月22日，以100 年度戒毒偵字第40、41號不起訴處分書，認\n    為被告已無繼續強制戒治必要為由，而為不起訴處分確定在\n    案。經查，本件警方查獲被告施用第一、二級毒品海洛因、\n    甲基安非他命時，同時扣得被告）持有(一)、疑似第一級毒品\n    海洛因之碎塊狀物品2 包（毛重14.1公克），經送法務部調\n    查局濫用藥物實驗室鑑定後，均含有第一級毒品海洛因成分\n    ，有該局99年6 月9 日調科壹字第09923012530 號鑑定書。\n    (二)、白色透明結晶塊1 袋（毛重2.36公克），經交由交通部\n    民用航空局航空醫務中心鑑定後，檢出第二級毒品甲基安非\n    他命成分，有該中心99年6 月3 日航藥鑑字第0993571 號毒\n    品鑑定書。(三)、顆粒1 包（毛重0.3 公克），經送憲兵司令\n    部刑事鑑識中心鑑定結果，亦含有第二級毒品甲基安非他命\n    成分，此有該中心98年11月10日憲直刑鑑字第0980001970號\n    鑑定書等各1 紙附卷可稽，爰依刑法第40條第2 項、毒品危\n    害防制條例第18條第1 項前段聲請單獨宣告沒收銷燬之。\n三、經查：被告前因施用第一、二級毒品之犯行，經臺灣雲林地\n    方法院檢察署檢察官於100 年4 月22日，以100 年度戒毒偵\n    字第40、41號不起訴處分書，認為被告已無繼續強制戒治必\n    要為由，而為不起訴處分確定在案。本件警方於查獲被告施\n    用毒品海洛因、甲基安非他命時，同時扣得被告持有(一)、疑\n    似第一級毒品海洛因之碎塊狀物品2 包（毛重14.1公克），\n    經送法務部調查局濫用藥物實驗室鑑定後，均含有第一級毒\n    品海洛因成分（合計淨重13.48 公克，驗餘淨重13.41 公克\n    ，純度百分之76.46 ，純質淨重10.31 公克），有該局99年\n    6 月9 日調科壹字第09923012530 號鑑定書（詳見臺灣板橋\n    地方法院檢察署99年度毒偵字第4123號偵查卷第133 或134\n    頁）。(二)、白色透明結晶塊1 袋（毛重2.36公克），經交由\n    交通部民用航空局航空醫務中心鑑定後，檢出含有第二級毒\n    品甲基安非他命成分（驗餘淨重為2 點2938公克），有該中\n    心99年6 月3 日航藥鑑字第0993571 號毒品鑑定書（詳見臺\n    灣板橋地方法院檢察署99年度毒偵字第4123號偵查卷第117\n    頁）。(三)、顆粒1 包（毛重0.3 公克），經送憲兵司令部刑\n    事鑑識中心鑑定結果，亦含有第二級毒品甲基安非他命成分\n    （驗餘淨重為0.0753公克），此有該中心98年11月10日憲直\n    刑鑑字第0980001970號鑑定書（詳見臺灣雲林地方法院檢察\n    署98年度偵字第4975號偵查卷第24頁）等各1 紙附卷可稽，\n    揆諸首開說明，聲請人聲請沒收銷燬扣案之海洛因、甲基安\n    非他命，洵屬於法有據，應予准許。\n四、依刑事訴訟法第220 條、刑法第40條第2 項，毒品危害防制\n    條例第18條第1 項前段，裁定如主文。\n中    華    民    國   100    年    6     月    2     日\n                  刑事第五庭  法  官  張文俊\n以上正本證明與原本無異。\n如不服本裁定，應於送達後5 日內，向本院提出抗告狀（須附繕\n本）。\n                              書記官  金雅芳\n中    華    民    國  100     年    6     月     3     日",
  "structure": {
    "main": "扣案之含有第一級毒品海洛因成分之塊狀物（合計淨重拾參點肆\n捌公克，驗餘淨重拾參點肆壹公克，純度百分之柒拾陸點肆陸，\n純質淨重拾點參壹公克）、第二級毒品甲基安非他命成分之白色\n透明結晶顆粒（驗餘淨重分別為貳點貳玖參捌公克、零點零柒伍\n參公克，合計貳點參陸玖壹公克）均沒收銷燬。",
    "reason": "一、按違禁物得單獨宣告沒收，且違禁物，不問屬於犯罪行為人\n    與否，沒收之；又按查獲之第一、二級毒品，不問屬於犯人\n    與否，沒收銷燬之，刑法第40條第2項、第38條第1項第1款\n    、第2項、毒品危害防制條例第18條第1項前段分別定有明文\n    。\n二、聲請意旨略以：被告薛武易（因本件施用第一、二級毒品之\n    犯行，經臺灣雲林地方法院檢察署檢察官前於民國100 年4\n    月22日，以100 年度戒毒偵字第40、41號不起訴處分書，認\n    為被告已無繼續強制戒治必要為由，而為不起訴處分確定在\n    案。經查，本件警方查獲被告施用第一、二級毒品海洛因、\n    甲基安非他命時，同時扣得被告）持有(一)、疑似第一級毒品\n    海洛因之碎塊狀物品2 包（毛重14.1公克），經送法務部調\n    查局濫用藥物實驗室鑑定後，均含有第一級毒品海洛因成分\n    ，有該局99年6 月9 日調科壹字第09923012530 號鑑定書。\n    (二)、白色透明結晶塊1 袋（毛重2.36公克），經交由交通部\n    民用航空局航空醫務中心鑑定後，檢出第二級毒品甲基安非\n    他命成分，有該中心99年6 月3 日航藥鑑字第0993571 號毒\n    品鑑定書。(三)、顆粒1 包（毛重0.3 公克），經送憲兵司令\n    部刑事鑑識中心鑑定結果，亦含有第二級毒品甲基安非他命\n    成分，此有該中心98年11月10日憲直刑鑑字第0980001970號\n    鑑定書等各1 紙附卷可稽，爰依刑法第40條第2 項、毒品危\n    害防制條例第18條第1 項前段聲請單獨宣告沒收銷燬之。\n三、經查：被告前因施用第一、二級毒品之犯行，經臺灣雲林地\n    方法院檢察署檢察官於100 年4 月22日，以100 年度戒毒偵\n    字第40、41號不起訴處分書，認為被告已無繼續強制戒治必\n    要為由，而為不起訴處分確定在案。本件警方於查獲被告施\n    用毒品海洛因、甲基安非他命時，同時扣得被告持有(一)、疑\n    似第一級毒品海洛因之碎塊狀物品2 包（毛重14.1公克），\n    經送法務部調查局濫用藥物實驗室鑑定後，均含有第一級毒\n    品海洛因成分（合計淨重13.48 公克，驗餘淨重13.41 公克\n    ，純度百分之76.46 ，純質淨重10.31 公克），有該局99年\n    6 月9 日調科壹字第09923012530 號鑑定書（詳見臺灣板橋\n    地方法院檢察署99年度毒偵字第4123號偵查卷第133 或134\n    頁）。(二)、白色透明結晶塊1 袋（毛重2.36公克），經交由\n    交通部民用航空局航空醫務中心鑑定後，檢出含有第二級毒\n    品甲基安非他命成分（驗餘淨重為2 點2938公克），有該中\n    心99年6 月3 日航藥鑑字第0993571 號毒品鑑定書（詳見臺\n    灣板橋地方法院檢察署99年度毒偵字第4123號偵查卷第117\n    頁）。(三)、顆粒1 包（毛重0.3 公克），經送憲兵司令部刑\n    事鑑識中心鑑定結果，亦含有第二級毒品甲基安非他命成分\n    （驗餘淨重為0.0753公克），此有該中心98年11月10日憲直\n    刑鑑字第0980001970號鑑定書（詳見臺灣雲林地方法院檢察\n    署98年度偵字第4975號偵查卷第24頁）等各1 紙附卷可稽，\n    揆諸首開說明，聲請人聲請沒收銷燬扣案之海洛因、甲基安\n    非他命，洵屬於法有據，應予准許。\n四、依刑事訴訟法第220 條、刑法第40條第2 項，毒品危害防制\n    條例第18條第1 項前段，裁定如主文。"
  },
  "search": "臺灣雲林地方法院刑事裁定100年度聲字第572號聲請人臺灣雲林地方法院檢察署檢察官被告薛武易上列聲請人因被告違反毒品危害防制條例案件（100年度戒毒偵字第40、41號），聲請單獨宣告沒收銷燬違禁物（100年度聲沒字第83號），本院裁定如下：主文扣案之含有第一級毒品海洛因成分之塊狀物（合計淨重拾參點肆捌公克，驗餘淨重拾參點肆壹公克，純度百分之柒拾陸點肆陸，純質淨重拾點參壹公克）、第二級毒品甲基安非他命成分之白色透明結晶顆粒（驗餘淨重分別為貳點貳玖參捌公克、零點零柒伍參公克，合計貳點參陸玖壹公克）均沒收銷燬。理由一、按違禁物得單獨宣告沒收，且違禁物，不問屬於犯罪行為人與否，沒收之；又按查獲之第一、二級毒品，不問屬於犯人與否，沒收銷燬之，刑法第40條第2項、第38條第1項第1款、第2項、毒品危害防制條例第18條第1項前段分別定有明文。二、聲請意旨略以：被告薛武易（因本件施用第一、二級毒品之犯行，經臺灣雲林地方法院檢察署檢察官前於民國100年4月22日，以100年度戒毒偵字第40、41號不起訴處分書，認為被告已無繼續強制戒治必要為由，而為不起訴處分確定在案。經查，本件警方查獲被告施用第一、二級毒品海洛因、甲基安非他命時，同時扣得被告）持有(一)、疑似第一級毒品海洛因之碎塊狀物品2包（毛重14.1公克），經送法務部調查局濫用藥物實驗室鑑定後，均含有第一級毒品海洛因成分，有該局99年6月9日調科壹字第09923012530號鑑定書。(二)、白色透明結晶塊1袋（毛重2.36公克），經交由交通部民用航空局航空醫務中心鑑定後，檢出第二級毒品甲基安非他命成分，有該中心99年6月3日航藥鑑字第0993571號毒品鑑定書。(三)、顆粒1包（毛重0.3公克），經送憲兵司令部刑事鑑識中心鑑定結果，亦含有第二級毒品甲基安非他命成分，此有該中心98年11月10日憲直刑鑑字第0980001970號鑑定書等各1紙附卷可稽，爰依刑法第40條第2項、毒品危害防制條例第18條第1項前段聲請單獨宣告沒收銷燬之。三、經查：被告前因施用第一、二級毒品之犯行，經臺灣雲林地方法院檢察署檢察官於100年4月22日，以100年度戒毒偵字第40、41號不起訴處分書，認為被告已無繼續強制戒治必要為由，而為不起訴處分確定在案。本件警方於查獲被告施用毒品海洛因、甲基安非他命時，同時扣得被告持有(一)、疑似第一級毒品海洛因之碎塊狀物品2包（毛重14.1公克），經送法務部調查局濫用藥物實驗室鑑定後，均含有第一級毒品海洛因成分（合計淨重13.48公克，驗餘淨重13.41公克，純度百分之76.46，純質淨重10.31公克），有該局99年6月9日調科壹字第09923012530號鑑定書（詳見臺灣板橋地方法院檢察署99年度毒偵字第4123號偵查卷第133或134頁）。(二)、白色透明結晶塊1袋（毛重2.36公克），經交由交通部民用航空局航空醫務中心鑑定後，檢出含有第二級毒品甲基安非他命成分（驗餘淨重為2點2938公克），有該中心99年6月3日航藥鑑字第0993571號毒品鑑定書（詳見臺灣板橋地方法院檢察署99年度毒偵字第4123號偵查卷第117頁）。(三)、顆粒1包（毛重0.3公克），經送憲兵司令部刑事鑑識中心鑑定結果，亦含有第二級毒品甲基安非他命成分（驗餘淨重為0.0753公克），此有該中心98年11月10日憲直刑鑑字第0980001970號鑑定書（詳見臺灣雲林地方法院檢察署98年度偵字第4975號偵查卷第24頁）等各1紙附卷可稽，揆諸首開說明，聲請人聲請沒收銷燬扣案之海洛因、甲基安非他命，洵屬於法有據，應予准許。四、依刑事訴訟法第220條、刑法第40條第2項，毒品危害防制條例第18條第1項前段，裁定如主文。中華民國100年6月2日刑事第五庭法官張文俊以上正本證明與原本無異。如不服本裁定，應於送達後5日內，向本院提出抗告狀（須附繕本）。書記官金雅芳中華民國100年6月3日",
  "characters": {
    "judges": [
      "張文俊"
    ],
    "prosecutors": [

    ],
    "lawyers": [

    ],
    "clerks": [
      "金雅芳"
    ],
    "plaintiffs": [

    ],
    "defendants": [
      "薛武易"
    ],
    "prosecutor_office": [
      "臺灣雲林地方法院檢察署檢察官"
    ],
    "creditors": [

    ],
    "debtors": [

    ],
    "judicial_associate_officer": [

    ]
  },
  "adjudged_at": "2011-06-02",
  "created_at": "2016-02-13 15:31:22",
  "updated_at": "2016-02-13 15:31:22"
}