{
  "identify": "SCD-94-交易-36-20050609-1",
  "court": {
    "name": "臺灣新竹地方法院",
    "code": "SCD"
  },
  "division": {
    "name": "刑事",
    "code": "M"
  },
  "year": 94,
  "word": "交易",
  "number": "36",
  "jcheck": "1",
  "reason": "業務過失傷害",
  "content": "臺灣新竹地方法院刑事判決              94年度交易字第36號\n公  訴  人  臺灣新竹地方法院檢察署檢察官\n被      告  乙○○  男  30歲.\n上列被告因業務過失傷害案件，經檢察官提起公訴（94年偵字第\n1096號），本院判決如下：\n    主  文\n本件公訴不受理。\n    理  由\n一、按告訴乃論之罪，告訴人於第一審辯論終結前得撤回其告訴\n    ，又告訴經撤回者，應諭知不受理之判決，並得不經言詞辯\n    論為之，刑事訴訟法第238條第1項、第303條第3款、第307條\n    定有明文。\n二、查本件告訴人甲○○告訴被告乙○○業務過失傷害案件，公\n    訴人認係觸犯刑法第284條第2項前段之罪，依同法第287條\n    前段之規定，須告訴乃論。茲據告訴人甲○○於民國94年5\n    月24日當庭撤回其告訴，依照首開說明，本件爰不經言詞辯\n    論，逕為諭知不受理之判決。\n三、據上論斷，應依刑事訴訟法第303條第3款、第307條，判決\n    如主文。\n中    華    民    國    94    年    6     月    9     日\n                  刑事第三庭    審判長法  官   汪銘欽\n                                      法  官   黃美盈\n                                      法  官   楊麗文\n以上正本證明與原本無異。\n如不服本判決，應於判決送達後10日內向本院提出上訴狀（應附\n繕本），上訴於\n臺灣高等法院。\n中    華    民    國    94    年    6     月    9     日\n                                      書記官   賴寶合\n",
  "structure": {
    "main": "本件公訴不受理。",
    "reason": "一、按告訴乃論之罪，告訴人於第一審辯論終結前得撤回其告訴\n    ，又告訴經撤回者，應諭知不受理之判決，並得不經言詞辯\n    論為之，刑事訴訟法第238條第1項、第303條第3款、第307條\n    定有明文。\n二、查本件告訴人甲○○告訴被告乙○○業務過失傷害案件，公\n    訴人認係觸犯刑法第284條第2項前段之罪，依同法第287條\n    前段之規定，須告訴乃論。茲據告訴人甲○○於民國94年5\n    月24日當庭撤回其告訴，依照首開說明，本件爰不經言詞辯\n    論，逕為諭知不受理之判決。\n三、據上論斷，應依刑事訴訟法第303條第3款、第307條，判決\n    如主文。"
  },
  "search": "臺灣新竹地方法院刑事判決94年度交易字第36號公訴人臺灣新竹地方法院檢察署檢察官被告乙○○男30歲.上列被告因業務過失傷害案件，經檢察官提起公訴（94年偵字第1096號），本院判決如下：主文本件公訴不受理。理由一、按告訴乃論之罪，告訴人於第一審辯論終結前得撤回其告訴，又告訴經撤回者，應諭知不受理之判決，並得不經言詞辯論為之，刑事訴訟法第238條第1項、第303條第3款、第307條定有明文。二、查本件告訴人甲○○告訴被告乙○○業務過失傷害案件，公訴人認係觸犯刑法第284條第2項前段之罪，依同法第287條前段之規定，須告訴乃論。茲據告訴人甲○○於民國94年5月24日當庭撤回其告訴，依照首開說明，本件爰不經言詞辯論，逕為諭知不受理之判決。三、據上論斷，應依刑事訴訟法第303條第3款、第307條，判決如主文。中華民國94年6月9日刑事第三庭審判長法官汪銘欽法官黃美盈法官楊麗文以上正本證明與原本無異。如不服本判決，應於判決送達後10日內向本院提出上訴狀（應附繕本），上訴於臺灣高等法院。中華民國94年6月9日書記官賴寶合",
  "characters": {
    "judges": [
      "汪銘欽",
      "黃美盈",
      "楊麗文"
    ],
    "prosecutors": [

    ],
    "lawyers": [

    ],
    "clerks": [
      "賴寶合"
    ],
    "plaintiffs": [

    ],
    "defendants": [
      "乙○○  男  30歲."
    ],
    "prosecutor_office": [
      "臺灣新竹地方法院檢察署檢察官"
    ],
    "creditors": [

    ],
    "debtors": [

    ],
    "judicial_associate_officer": [

    ]
  },
  "adjudged_at": "2005-06-09",
  "created_at": "2016-02-07 05:08:51",
  "updated_at": "2016-02-07 05:08:51"
}