{
  "identify": "SLD-94-聲判-8-20050609-1",
  "court": {
    "name": "臺灣士林地方法院",
    "code": "SLD"
  },
  "division": {
    "name": "刑事",
    "code": "M"
  },
  "year": 94,
  "word": "聲判",
  "number": "8",
  "jcheck": "1",
  "reason": "聲請交付審判",
  "content": "臺灣士林地方法院刑事裁定               94年度聲判字第8號\n聲  請  人  丙○○\n代  理  人  甲○○律師\n被      告  乙○○\n上列聲請人因告訴被告偽造文書等案件，不服臺灣高等法院檢察\n署檢察長於中華民國94年1 月19日94年度上聲議字第292 號駁回\n再議之處分（原不起訴處分案號：臺灣士林地方法院檢察署92年\n度偵10575）， 聲請交付審判，本院裁定如下：\n    主  文\n聲請駁回。\n    理  由\n一、本件聲請人以被告乙○○涉犯偽造文書等罪嫌，向臺灣士林\n    地方法院檢察署檢察官提出告訴，經該檢察署檢察官以92年\n    度偵字第10575 號為不起訴處分後，聲請人不服而聲請再議\n    ，經臺灣高等法院檢察署檢察長以94年度上聲議字第292 號\n    處分書敘明再議為無理由而駁回再議之聲請，而聲請人於民\n    國94年2 月1 日收該處分書後10日內，向本院聲請交付審判\n    ，有該送達證書及聲請交付審判狀在卷可憑，程序上並無不\n    合，合先敘明。\n二、聲請交付審判意旨略以：（一）被告乙○○於臺北市○○路\n    ○ 段90巷19號2 樓開設神壇「靈能學院」，而共同被告蔡龍\n    木（另經起訴）係其姨丈並於泰國投資經商，而蔡龍木於民\n    國83年間，透過被告乙○○向聲請人等投資人詐稱投資泰國\n    房地產獲利無窮，聲請人等信以為真，先後投資新台幣（下\n    同）約5 千4 百多萬元，惟實際上乙○○、蔡龍木僅在泰國\n    購買少數不毛之地，且係利用不相關之第三人名義登記，並\n    虛構聲請人等股東同意，以前開土地向銀行抵押貸款，嗣後\n    又擅將聲請人等之股東資格註銷，顯見被告有偽造文書及侵\n    占之罪責。（二）被告自稱投資18,850 ,000 元泰幣，與聲\n    請人等所投資之金額至少為73,000,000元之多，惟被告所提\n    之匯款單25張共計不過54,066,482元，已短少15,000,000元\n    之多，顯有侵占及背信之罪嫌。（三）被告與蔡龍木侵占之\n    款項均係聲請人於本國交付予被告，被告所涉犯罪之行為地\n    既在本國內，自有刑法之適用，檢察官遽以被告涉嫌之犯行\n    ，其行為地均在泰國，即謂無適用我國刑法之餘地，實有偏\n    袒被告之可議。（四）檢察官未傳訊蔡龍木到庭與被告對質\n    ，無法釐清投資金額之流向云云。\n三、按告訴人不服上級法院檢察署檢察長或檢察總長認再議為無\n    理由而駁回之處分者，得於接受處分書後10日內委任律師提\n    出理由狀，向該管第一審法院聲請交付審判。法院認為交付\n    審判之聲請不合法或無理由者，應駁回之。刑事訴訟法第\n    258 條之1 、第258 條之3 第2 項前段，分別定有明文。又\n    向法院聲請交付審判，係新增對於「檢察官不起訴或緩起訴\n    裁量權」制衡之一種外部監督機制，法院僅就檢察官所為不\n    起訴或緩起訴之處分是否正確加以審查，以防止檢察機關濫\n    權，法院並非檢察官之延伸，法院亦不負擔偵查之作為。依\n    此立法精神，同法第258 條之3 第3 項規定法院審查聲請交\n    付審判案件時「得為必要之調查」，其調查證據之範圍，自\n    應以偵查中曾顯現之證據為限；而同法第260 條對於不起訴\n    處分已確定或緩起訴處分期滿未經撤銷因發現新事實新證據\n    者得再行起訴之規定，其立法理由說明該條所謂不起訴處分\n    已確定者，包括「聲請法院交付審判復經駁回者」之情形在\n    內，是前述「得為必要之調查」，其調查證據範圍，更應以\n    偵查中曾顯現之證據為限，不得就告訴人新提出之證據再為\n    調查，亦不得蒐集偵查卷以外之證據，否則，將與刑事訴訟\n    法第260 條之再行起訴規定，混淆不清，亦將使法院兼任檢\n    察官而有回復「糾問制度」之虞；且法院裁定交付審判，即\n    如同檢察官提起公訴使案件進入審判程序，是法院裁定交付\n    審判之前提，必須偵查卷內所存證據已符合刑事訴訟法第\n    251 條第1 項規定「足認被告有犯罪嫌疑」檢察官應提起公\n    訴之情形，亦即該案件已經跨越起訴門檻，否則，縱或法院\n    對於檢察官所認定之基礎事實有不同判斷，但如該案件仍須\n    另行蒐證偵查始能判斷應否交付審判者，因交付審判審查制\n    度並無如同再議救濟制度得為發回原檢察官續行偵查之設計\n    ，法院仍應依同法第258 條之3 第2 項前段規定，以聲請無\n    理由裁定駁回。\n四、本件聲請人雖以前揭理由認被告乙○○涉有偽造文書等罪嫌\n    ，而向本院聲請交付審判。然前揭不起訴處分書及駁回再議\n    處分書已就聲請人於偵查時提出之告訴理由予以斟酌，並詳\n    加論述所憑證據及其認定之理由，關於此點，業經本院依職\n    權調閱前開偵查卷宗查核無誤。經查：\n（一）被告乙○○自83年9 月5 日起，陸續收取聲請人及被害人\n      等之投資款項，分別是聲請人丙○○1 千7 百28萬9 千6\n      百50元、高耀仁2 百50萬7 千元、李秀葉4 百46萬9 千元\n      、吳美容5 百31萬6 千元、李榮華2 百64萬3千4 百元、\n      張清泉5 百37萬零3 百零5 元，及黃金圓、陳淑貞、張明\n      珠（三人合夥）共5 百萬元泰幣、李木祥2 百80萬元泰幣\n      。而被告自83年3 月12日起至86年8 月22日止，陸續將上\n      開資金以匯款方式匯至泰國給蔡龍木收取，共計達5 千7\n      百零6 萬6 千4 百82元（泰幣5千3百90萬6 千2百17點92\n      元），縱依聲請人所主張，將被告所提關於83年3 月12日\n      至83年6 月2 日及86年8 月22日之匯款刪除（該部分非無\n      可能即被告自己之投資金額），再將李木祥所投資泰幣2\n      百80萬銖及陳淑貞等3 人合計出資泰幣5 百萬銖，以最不\n      利被告之賣出匯率即1 ：1.08960 計算，被告匯款給蔡龍\n      木之總金額即新台幣4 千7 百零6 萬4 千1 百71元，仍超\n      過聲請人及被害人交付之投資金額即約新台幣4 千6 百零\n      9 萬4 千2 百35元，被告所辯其業將聲請人及被害人等所\n      交付連同自己之投資金額匯款至泰國給蔡龍木，尚非無據\n      ，故無證據足認被告有不法所有之意圖等情，業經臺灣高\n      等法院以91年度上易字第2201號確定判決認定屬實在案（\n      按被告於該案中被訴詐欺罪嫌，經判決無罪確定），有該\n      案號判決一份在卷可憑（見他字1020號卷第8 頁）。是被\n      告既將聲請人及被害人等所交付之投資金額匯款至泰國給\n      蔡龍木，被告自無犯侵占罪責可言。又聲請人另主張檢察\n      官未傳訊蔡龍木到案說明，調查證據顯有疏漏云云。惟該\n      部分，因被告乙○○無涉犯侵占罪，是原檢察官認為已無\n      調查其他證據之必要，至於聲請人所指之蔡龍木，並未於\n      偵查中呈現，亦未經檢察官偵辦，且非屬檢察官不起訴處\n      分範圍，依據前開說明，聲請法院交付審判之調查證據範\n      圍，應以偵查中曾顯現之證據為限，本院自不得就聲請人\n      新提出之證據進行調查，亦不得蒐集偵查卷以外之證據，\n      否則，將與刑事訴訟法第260 條之再行起訴規定混淆不清\n      ，將使法院兼任檢察官而有回復「糾問制度」之虞業如前\n      述，是聲請人上開主張，顯屬不合規定，並非本院審理之\n      範圍。\n（二）再者，蔡龍木係私自以6 萊土地向泰國銀行辦理抵押借款\n      300 萬元泰幣供其個人週轉之用等情，業據被告於偵查中\n      供稱：「立國公司是蔡龍木在泰國成立的公司」、「蔡龍\n      木在91年3 月去開庭時，有承認拿土地向銀行借款300 萬\n      泰幣做為個人週轉用，所以這個錢不是我拿去抵押貸款的\n      」、「在泰國要成為公司的股東要本人親自拿護照去辦理\n      ，成立公司都是蔡龍木去辦理的」等語（見92年度偵字第\n      10575 號偵查卷第10頁至第11頁），核與蔡龍木於台灣板\n      橋地方法院91年3 月5 日審理時供述：「（問：你是否有\n      拿土地抵押借款？）我有拿6 萊土地向泰國銀行借款300\n      萬泰幣，我拿到300 萬元做為我個人週轉用」等語相符（\n      見台灣板橋地方法院89年度易字第4224號卷第402 頁），\n      足見此部分行為乃被告蔡龍木個人行為，與被告乙○○無\n      涉，是聲請人認被告參與抵押貸款而有偽造文書之情事，\n      尚屬無據。\n（三）又按刑法第342 條第1 項之背信罪，係以行為人為他人處\n      理事務，意圖為自己或第三人不法之利益，或損害本人利\n      益，而為違背其任務之行為，致生於損害於本人之財產或\n      其他利益為要件。經查，本件被告自83年9 月7 日至84年\n      8 月16日匯款予蔡龍木之總金額為4 千7 百零6 萬4 千1\n      百71元，其間金額雖稍有短少，惟被告向聲請人等投資人\n      所收取之款項僅部分係以匯款方式交付予蔡龍木，另有部\n      分款項則係交付予蔡龍木或其妻，交付現金部分因未取據\n      ，致無從計算詳細總額等情，業據被告於偵查中供稱：「\n      我是根據投資人和蔡龍木的指示來匯錢，我沒有侵占。中\n      間的差額有補到其他月份，匯錢的部分不能只看單月份要\n      看整個匯款的單據」、「有些是用匯的，有些是用現金，\n      現金是交給他或他的太太」、「有部分是拿現金給蔡龍木\n      和他太太，有些是用匯的，所以匯款明細上所記載的並不\n      是全部的金額」、「現金部分最少有1 千多萬」、「蔡龍\n      木他們沒有簽收據給我」（見92年度偵字第10575 號偵查\n      卷第121 頁、第289 頁、第294 頁），核與證人李木祥於\n      偵查中陳稱：「51萊土地部分他有帶現金到泰國給蔡龍木\n      」等語相符（見同前偵查卷第317 頁），是被告乙○○除\n      以匯款方式外，亦另有以交付現金之方式予蔡龍木無訛，\n      況就聲請人所提出泰國買地6 萊、4 萊土地付款辦法所記\n      載投資人之付款方式亦多係以現金交付予被告，足徵被告\n      辯稱部分投資款係以現金交付等語，亦尚非無據。故縱使\n      被告於前揭時間內之匯款金額較投資人所繳付之款項略少\n      ，亦難遽認該短少部分即為其所侵占。況被告乙○○既有\n      出資，亦遵守約定已將聲請人等之投資金額匯款予蔡龍木\n      ，並非違背其任務，且投資海外不動產事業本具有相當之\n      風險存在，縱使嗣後投資失利，亦難謂有損害聲請人等財\n      產或利益之可言，自與背信罪之成立要件未合。\n（四）再按刑法第5 條規定，本法於凡在中華民國領域外犯左列\n      各罪者，適用之：1.內亂罪。2.外患罪。3.偽造貨幣罪。\n      4. 第201條及第202 條之偽造有價證券罪。5.第211 條、\n      第214 條、第216 條及第218 條之偽造文書印文罪。6.鴉\n      片罪。7.第296 條之妨害自由罪。8.第333 條及第334 條\n      之海盜罪。又按刑法第7 條規定，本法於中華民國人民在\n      中華民國領域外犯前2 條以外之罪，而其最輕本刑為3 年\n      以上有期徒刑者，適用之。聲請人向本院聲請交付審判，\n      指訴被告乙○○擅自將在泰國所購買之土地登記予不相關\n      之第3 人，並以該土地向泰國銀行抵押貸款，又泰國「立\n      國公司」於臺灣召開股東會議時，出列席之股東並無李木\n      祥，惟被告於泰國所成立之「大中公司」所列之公司創辦\n      人卻有李木祥之名，因認被告涉有偽造私文書、背信及侵\n      占罪云云。然查，聲請人丙○○於偵查中證稱：「被告擅\n      自將土地登記不相關第3 人並且將土地拿去辦理抵押貸款\n      係在泰國」、「立國公司章程有列李木祥，被告偽造公司\n      股東名冊，偽造文書的土地在泰國」、「立國是被告在泰\n      國申請設立的」等語（見92年度偵字第10575 號偵查卷第\n      56 頁）， 顯見被告上揭所申請成立之公司及購買土地辦\n      理抵押等行為均在泰國完成無訛，復有土地謄本、土地所\n      有權地主證明及大中公司章程影本在卷可稽。再者，被告\n      於偵查中供稱：丙○○等投資人所收款項有些是用匯的，\n      有些是用現金，現金是交給蔡龍木或他的太太等語（見92\n      年度偵字第1057 5號偵查卷第289 頁），是聲請人等將錢\n      交予被告乙○○後，由被告匯款至蔡龍木於泰國之帳戶後\n      ，再由蔡龍木於泰國提領該款項，或由被告直接交予蔡龍\n      木或他的太太，足徵被告縱有偽造文書、背信及侵占之犯\n      行，其犯罪之行為地與結果地亦皆在泰國。再觀諸聲請人\n      所指稱：被告侵占之款項均係聲請人於本國交付予被告等\n      情，則縱使聲請人交付投資金額係在台灣，然因被告具體\n      違背委任義務之舉止，係發生在泰國，且被告須忠實為聲\n      請人履行義務之地點亦係泰國，而非在我國境內，則被告\n      之行為地自係在泰國，又聲請人所受之損害，亦應係其在\n      泰國之事業所受之利益損失，被告之偽造文書、背信及侵\n      占行為之結果，皆發生在泰國，是被告所為核係在我國境\n      外犯罪甚明。綜上而論，被告既係在我國領域外犯罪，又\n      前揭偽造文書、背信及侵占罪，均非刑法第5 條所規定之\n      罪名，且其法定刑亦非刑法第7 條所定之最輕本刑3 年以\n      上有期徒刑之罪情形，揆諸上揭說明，我國法院對被告上\n      述行為自無審判權。\n五、綜上所述，原不起訴處分書及聲請再議處分書既已詳予調查\n    偵查卷內所存證據，並敘明理由，既無積極證據證明被告乙\n    ○○涉有聲請人所指訴之偽造文書、背信及侵占犯行，尚難\n    以聲請人之片面指訴，遽認被告涉有本件犯行；且原處分所\n    載證據取捨及事實認定之理由，尚無違背經驗法則或論理法\n    則之情事，是原檢察官及臺灣高等法院檢察署檢察長以被告\n    犯罪嫌疑不足，分別予以不起訴處分及駁回再議之聲請，並\n    無不當。本件聲請交付審判意旨仍執陳詞，對於原處分漫加\n    指摘求予審判，顯無理由，應予駁回。\n六、依刑事訴訟法第258條之3第2項前段，裁定如主文。\n中    華    民    國    94    年    6     月    9     日\n                  刑事第三庭審判長法  官  李正紀\n                                  法  官  吳祚丞\n                                  法  官  王俊雄\n以上正本證明與原本無異。\n本裁定不得抗告。\n                                  書記官  許秋莉\n中    華    民    國    94    年    6     月    9     日\n",
  "structure": {
    "main": "聲請駁回。",
    "reason": "一、本件聲請人以被告乙○○涉犯偽造文書等罪嫌，向臺灣士林\n    地方法院檢察署檢察官提出告訴，經該檢察署檢察官以92年\n    度偵字第10575 號為不起訴處分後，聲請人不服而聲請再議\n    ，經臺灣高等法院檢察署檢察長以94年度上聲議字第292 號\n    處分書敘明再議為無理由而駁回再議之聲請，而聲請人於民\n    國94年2 月1 日收該處分書後10日內，向本院聲請交付審判\n    ，有該送達證書及聲請交付審判狀在卷可憑，程序上並無不\n    合，合先敘明。\n二、聲請交付審判意旨略以：（一）被告乙○○於臺北市○○路\n    ○ 段90巷19號2 樓開設神壇「靈能學院」，而共同被告蔡龍\n    木（另經起訴）係其姨丈並於泰國投資經商，而蔡龍木於民\n    國83年間，透過被告乙○○向聲請人等投資人詐稱投資泰國\n    房地產獲利無窮，聲請人等信以為真，先後投資新台幣（下\n    同）約5 千4 百多萬元，惟實際上乙○○、蔡龍木僅在泰國\n    購買少數不毛之地，且係利用不相關之第三人名義登記，並\n    虛構聲請人等股東同意，以前開土地向銀行抵押貸款，嗣後\n    又擅將聲請人等之股東資格註銷，顯見被告有偽造文書及侵\n    占之罪責。（二）被告自稱投資18,850 ,000 元泰幣，與聲\n    請人等所投資之金額至少為73,000,000元之多，惟被告所提\n    之匯款單25張共計不過54,066,482元，已短少15,000,000元\n    之多，顯有侵占及背信之罪嫌。（三）被告與蔡龍木侵占之\n    款項均係聲請人於本國交付予被告，被告所涉犯罪之行為地\n    既在本國內，自有刑法之適用，檢察官遽以被告涉嫌之犯行\n    ，其行為地均在泰國，即謂無適用我國刑法之餘地，實有偏\n    袒被告之可議。（四）檢察官未傳訊蔡龍木到庭與被告對質\n    ，無法釐清投資金額之流向云云。\n三、按告訴人不服上級法院檢察署檢察長或檢察總長認再議為無\n    理由而駁回之處分者，得於接受處分書後10日內委任律師提\n    出理由狀，向該管第一審法院聲請交付審判。法院認為交付\n    審判之聲請不合法或無理由者，應駁回之。刑事訴訟法第\n    258 條之1 、第258 條之3 第2 項前段，分別定有明文。又\n    向法院聲請交付審判，係新增對於「檢察官不起訴或緩起訴\n    裁量權」制衡之一種外部監督機制，法院僅就檢察官所為不\n    起訴或緩起訴之處分是否正確加以審查，以防止檢察機關濫\n    權，法院並非檢察官之延伸，法院亦不負擔偵查之作為。依\n    此立法精神，同法第258 條之3 第3 項規定法院審查聲請交\n    付審判案件時「得為必要之調查」，其調查證據之範圍，自\n    應以偵查中曾顯現之證據為限；而同法第260 條對於不起訴\n    處分已確定或緩起訴處分期滿未經撤銷因發現新事實新證據\n    者得再行起訴之規定，其立法理由說明該條所謂不起訴處分\n    已確定者，包括「聲請法院交付審判復經駁回者」之情形在\n    內，是前述「得為必要之調查」，其調查證據範圍，更應以\n    偵查中曾顯現之證據為限，不得就告訴人新提出之證據再為\n    調查，亦不得蒐集偵查卷以外之證據，否則，將與刑事訴訟\n    法第260 條之再行起訴規定，混淆不清，亦將使法院兼任檢\n    察官而有回復「糾問制度」之虞；且法院裁定交付審判，即\n    如同檢察官提起公訴使案件進入審判程序，是法院裁定交付\n    審判之前提，必須偵查卷內所存證據已符合刑事訴訟法第\n    251 條第1 項規定「足認被告有犯罪嫌疑」檢察官應提起公\n    訴之情形，亦即該案件已經跨越起訴門檻，否則，縱或法院\n    對於檢察官所認定之基礎事實有不同判斷，但如該案件仍須\n    另行蒐證偵查始能判斷應否交付審判者，因交付審判審查制\n    度並無如同再議救濟制度得為發回原檢察官續行偵查之設計\n    ，法院仍應依同法第258 條之3 第2 項前段規定，以聲請無\n    理由裁定駁回。\n四、本件聲請人雖以前揭理由認被告乙○○涉有偽造文書等罪嫌\n    ，而向本院聲請交付審判。然前揭不起訴處分書及駁回再議\n    處分書已就聲請人於偵查時提出之告訴理由予以斟酌，並詳\n    加論述所憑證據及其認定之理由，關於此點，業經本院依職\n    權調閱前開偵查卷宗查核無誤。經查：\n（一）被告乙○○自83年9 月5 日起，陸續收取聲請人及被害人\n      等之投資款項，分別是聲請人丙○○1 千7 百28萬9 千6\n      百50元、高耀仁2 百50萬7 千元、李秀葉4 百46萬9 千元\n      、吳美容5 百31萬6 千元、李榮華2 百64萬3千4 百元、\n      張清泉5 百37萬零3 百零5 元，及黃金圓、陳淑貞、張明\n      珠（三人合夥）共5 百萬元泰幣、李木祥2 百80萬元泰幣\n      。而被告自83年3 月12日起至86年8 月22日止，陸續將上\n      開資金以匯款方式匯至泰國給蔡龍木收取，共計達5 千7\n      百零6 萬6 千4 百82元（泰幣5千3百90萬6 千2百17點92\n      元），縱依聲請人所主張，將被告所提關於83年3 月12日\n      至83年6 月2 日及86年8 月22日之匯款刪除（該部分非無\n      可能即被告自己之投資金額），再將李木祥所投資泰幣2\n      百80萬銖及陳淑貞等3 人合計出資泰幣5 百萬銖，以最不\n      利被告之賣出匯率即1 ：1.08960 計算，被告匯款給蔡龍\n      木之總金額即新台幣4 千7 百零6 萬4 千1 百71元，仍超\n      過聲請人及被害人交付之投資金額即約新台幣4 千6 百零\n      9 萬4 千2 百35元，被告所辯其業將聲請人及被害人等所\n      交付連同自己之投資金額匯款至泰國給蔡龍木，尚非無據\n      ，故無證據足認被告有不法所有之意圖等情，業經臺灣高\n      等法院以91年度上易字第2201號確定判決認定屬實在案（\n      按被告於該案中被訴詐欺罪嫌，經判決無罪確定），有該\n      案號判決一份在卷可憑（見他字1020號卷第8 頁）。是被\n      告既將聲請人及被害人等所交付之投資金額匯款至泰國給\n      蔡龍木，被告自無犯侵占罪責可言。又聲請人另主張檢察\n      官未傳訊蔡龍木到案說明，調查證據顯有疏漏云云。惟該\n      部分，因被告乙○○無涉犯侵占罪，是原檢察官認為已無\n      調查其他證據之必要，至於聲請人所指之蔡龍木，並未於\n      偵查中呈現，亦未經檢察官偵辦，且非屬檢察官不起訴處\n      分範圍，依據前開說明，聲請法院交付審判之調查證據範\n      圍，應以偵查中曾顯現之證據為限，本院自不得就聲請人\n      新提出之證據進行調查，亦不得蒐集偵查卷以外之證據，\n      否則，將與刑事訴訟法第260 條之再行起訴規定混淆不清\n      ，將使法院兼任檢察官而有回復「糾問制度」之虞業如前\n      述，是聲請人上開主張，顯屬不合規定，並非本院審理之\n      範圍。\n（二）再者，蔡龍木係私自以6 萊土地向泰國銀行辦理抵押借款\n      300 萬元泰幣供其個人週轉之用等情，業據被告於偵查中\n      供稱：「立國公司是蔡龍木在泰國成立的公司」、「蔡龍\n      木在91年3 月去開庭時，有承認拿土地向銀行借款300 萬\n      泰幣做為個人週轉用，所以這個錢不是我拿去抵押貸款的\n      」、「在泰國要成為公司的股東要本人親自拿護照去辦理\n      ，成立公司都是蔡龍木去辦理的」等語（見92年度偵字第\n      10575 號偵查卷第10頁至第11頁），核與蔡龍木於台灣板\n      橋地方法院91年3 月5 日審理時供述：「（問：你是否有\n      拿土地抵押借款？）我有拿6 萊土地向泰國銀行借款300\n      萬泰幣，我拿到300 萬元做為我個人週轉用」等語相符（\n      見台灣板橋地方法院89年度易字第4224號卷第402 頁），\n      足見此部分行為乃被告蔡龍木個人行為，與被告乙○○無\n      涉，是聲請人認被告參與抵押貸款而有偽造文書之情事，\n      尚屬無據。\n（三）又按刑法第342 條第1 項之背信罪，係以行為人為他人處\n      理事務，意圖為自己或第三人不法之利益，或損害本人利\n      益，而為違背其任務之行為，致生於損害於本人之財產或\n      其他利益為要件。經查，本件被告自83年9 月7 日至84年\n      8 月16日匯款予蔡龍木之總金額為4 千7 百零6 萬4 千1\n      百71元，其間金額雖稍有短少，惟被告向聲請人等投資人\n      所收取之款項僅部分係以匯款方式交付予蔡龍木，另有部\n      分款項則係交付予蔡龍木或其妻，交付現金部分因未取據\n      ，致無從計算詳細總額等情，業據被告於偵查中供稱：「\n      我是根據投資人和蔡龍木的指示來匯錢，我沒有侵占。中\n      間的差額有補到其他月份，匯錢的部分不能只看單月份要\n      看整個匯款的單據」、「有些是用匯的，有些是用現金，\n      現金是交給他或他的太太」、「有部分是拿現金給蔡龍木\n      和他太太，有些是用匯的，所以匯款明細上所記載的並不\n      是全部的金額」、「現金部分最少有1 千多萬」、「蔡龍\n      木他們沒有簽收據給我」（見92年度偵字第10575 號偵查\n      卷第121 頁、第289 頁、第294 頁），核與證人李木祥於\n      偵查中陳稱：「51萊土地部分他有帶現金到泰國給蔡龍木\n      」等語相符（見同前偵查卷第317 頁），是被告乙○○除\n      以匯款方式外，亦另有以交付現金之方式予蔡龍木無訛，\n      況就聲請人所提出泰國買地6 萊、4 萊土地付款辦法所記\n      載投資人之付款方式亦多係以現金交付予被告，足徵被告\n      辯稱部分投資款係以現金交付等語，亦尚非無據。故縱使\n      被告於前揭時間內之匯款金額較投資人所繳付之款項略少\n      ，亦難遽認該短少部分即為其所侵占。況被告乙○○既有\n      出資，亦遵守約定已將聲請人等之投資金額匯款予蔡龍木\n      ，並非違背其任務，且投資海外不動產事業本具有相當之\n      風險存在，縱使嗣後投資失利，亦難謂有損害聲請人等財\n      產或利益之可言，自與背信罪之成立要件未合。\n（四）再按刑法第5 條規定，本法於凡在中華民國領域外犯左列\n      各罪者，適用之：1.內亂罪。2.外患罪。3.偽造貨幣罪。\n      4. 第201條及第202 條之偽造有價證券罪。5.第211 條、\n      第214 條、第216 條及第218 條之偽造文書印文罪。6.鴉\n      片罪。7.第296 條之妨害自由罪。8.第333 條及第334 條\n      之海盜罪。又按刑法第7 條規定，本法於中華民國人民在\n      中華民國領域外犯前2 條以外之罪，而其最輕本刑為3 年\n      以上有期徒刑者，適用之。聲請人向本院聲請交付審判，\n      指訴被告乙○○擅自將在泰國所購買之土地登記予不相關\n      之第3 人，並以該土地向泰國銀行抵押貸款，又泰國「立\n      國公司」於臺灣召開股東會議時，出列席之股東並無李木\n      祥，惟被告於泰國所成立之「大中公司」所列之公司創辦\n      人卻有李木祥之名，因認被告涉有偽造私文書、背信及侵\n      占罪云云。然查，聲請人丙○○於偵查中證稱：「被告擅\n      自將土地登記不相關第3 人並且將土地拿去辦理抵押貸款\n      係在泰國」、「立國公司章程有列李木祥，被告偽造公司\n      股東名冊，偽造文書的土地在泰國」、「立國是被告在泰\n      國申請設立的」等語（見92年度偵字第10575 號偵查卷第\n      56 頁）， 顯見被告上揭所申請成立之公司及購買土地辦\n      理抵押等行為均在泰國完成無訛，復有土地謄本、土地所\n      有權地主證明及大中公司章程影本在卷可稽。再者，被告\n      於偵查中供稱：丙○○等投資人所收款項有些是用匯的，\n      有些是用現金，現金是交給蔡龍木或他的太太等語（見92\n      年度偵字第1057 5號偵查卷第289 頁），是聲請人等將錢\n      交予被告乙○○後，由被告匯款至蔡龍木於泰國之帳戶後\n      ，再由蔡龍木於泰國提領該款項，或由被告直接交予蔡龍\n      木或他的太太，足徵被告縱有偽造文書、背信及侵占之犯\n      行，其犯罪之行為地與結果地亦皆在泰國。再觀諸聲請人\n      所指稱：被告侵占之款項均係聲請人於本國交付予被告等\n      情，則縱使聲請人交付投資金額係在台灣，然因被告具體\n      違背委任義務之舉止，係發生在泰國，且被告須忠實為聲\n      請人履行義務之地點亦係泰國，而非在我國境內，則被告\n      之行為地自係在泰國，又聲請人所受之損害，亦應係其在\n      泰國之事業所受之利益損失，被告之偽造文書、背信及侵\n      占行為之結果，皆發生在泰國，是被告所為核係在我國境\n      外犯罪甚明。綜上而論，被告既係在我國領域外犯罪，又\n      前揭偽造文書、背信及侵占罪，均非刑法第5 條所規定之\n      罪名，且其法定刑亦非刑法第7 條所定之最輕本刑3 年以\n      上有期徒刑之罪情形，揆諸上揭說明，我國法院對被告上\n      述行為自無審判權。\n五、綜上所述，原不起訴處分書及聲請再議處分書既已詳予調查\n    偵查卷內所存證據，並敘明理由，既無積極證據證明被告乙\n    ○○涉有聲請人所指訴之偽造文書、背信及侵占犯行，尚難\n    以聲請人之片面指訴，遽認被告涉有本件犯行；且原處分所\n    載證據取捨及事實認定之理由，尚無違背經驗法則或論理法\n    則之情事，是原檢察官及臺灣高等法院檢察署檢察長以被告\n    犯罪嫌疑不足，分別予以不起訴處分及駁回再議之聲請，並\n    無不當。本件聲請交付審判意旨仍執陳詞，對於原處分漫加\n    指摘求予審判，顯無理由，應予駁回。\n六、依刑事訴訟法第258條之3第2項前段，裁定如主文。"
  },
  "search": "臺灣士林地方法院刑事裁定94年度聲判字第8號聲請人丙○○代理人甲○○律師被告乙○○上列聲請人因告訴被告偽造文書等案件，不服臺灣高等法院檢察署檢察長於中華民國94年1月19日94年度上聲議字第292號駁回再議之處分（原不起訴處分案號：臺灣士林地方法院檢察署92年度偵10575），聲請交付審判，本院裁定如下：主文聲請駁回。理由一、本件聲請人以被告乙○○涉犯偽造文書等罪嫌，向臺灣士林地方法院檢察署檢察官提出告訴，經該檢察署檢察官以92年度偵字第10575號為不起訴處分後，聲請人不服而聲請再議，經臺灣高等法院檢察署檢察長以94年度上聲議字第292號處分書敘明再議為無理由而駁回再議之聲請，而聲請人於民國94年2月1日收該處分書後10日內，向本院聲請交付審判，有該送達證書及聲請交付審判狀在卷可憑，程序上並無不合，合先敘明。二、聲請交付審判意旨略以：（一）被告乙○○於臺北市○○路○段90巷19號2樓開設神壇「靈能學院」，而共同被告蔡龍木（另經起訴）係其姨丈並於泰國投資經商，而蔡龍木於民國83年間，透過被告乙○○向聲請人等投資人詐稱投資泰國房地產獲利無窮，聲請人等信以為真，先後投資新台幣（下同）約5千4百多萬元，惟實際上乙○○、蔡龍木僅在泰國購買少數不毛之地，且係利用不相關之第三人名義登記，並虛構聲請人等股東同意，以前開土地向銀行抵押貸款，嗣後又擅將聲請人等之股東資格註銷，顯見被告有偽造文書及侵占之罪責。（二）被告自稱投資18,850,000元泰幣，與聲請人等所投資之金額至少為73,000,000元之多，惟被告所提之匯款單25張共計不過54,066,482元，已短少15,000,000元之多，顯有侵占及背信之罪嫌。（三）被告與蔡龍木侵占之款項均係聲請人於本國交付予被告，被告所涉犯罪之行為地既在本國內，自有刑法之適用，檢察官遽以被告涉嫌之犯行，其行為地均在泰國，即謂無適用我國刑法之餘地，實有偏袒被告之可議。（四）檢察官未傳訊蔡龍木到庭與被告對質，無法釐清投資金額之流向云云。三、按告訴人不服上級法院檢察署檢察長或檢察總長認再議為無理由而駁回之處分者，得於接受處分書後10日內委任律師提出理由狀，向該管第一審法院聲請交付審判。法院認為交付審判之聲請不合法或無理由者，應駁回之。刑事訴訟法第258條之1、第258條之3第2項前段，分別定有明文。又向法院聲請交付審判，係新增對於「檢察官不起訴或緩起訴裁量權」制衡之一種外部監督機制，法院僅就檢察官所為不起訴或緩起訴之處分是否正確加以審查，以防止檢察機關濫權，法院並非檢察官之延伸，法院亦不負擔偵查之作為。依此立法精神，同法第258條之3第3項規定法院審查聲請交付審判案件時「得為必要之調查」，其調查證據之範圍，自應以偵查中曾顯現之證據為限；而同法第260條對於不起訴處分已確定或緩起訴處分期滿未經撤銷因發現新事實新證據者得再行起訴之規定，其立法理由說明該條所謂不起訴處分已確定者，包括「聲請法院交付審判復經駁回者」之情形在內，是前述「得為必要之調查」，其調查證據範圍，更應以偵查中曾顯現之證據為限，不得就告訴人新提出之證據再為調查，亦不得蒐集偵查卷以外之證據，否則，將與刑事訴訟法第260條之再行起訴規定，混淆不清，亦將使法院兼任檢察官而有回復「糾問制度」之虞；且法院裁定交付審判，即如同檢察官提起公訴使案件進入審判程序，是法院裁定交付審判之前提，必須偵查卷內所存證據已符合刑事訴訟法第251條第1項規定「足認被告有犯罪嫌疑」檢察官應提起公訴之情形，亦即該案件已經跨越起訴門檻，否則，縱或法院對於檢察官所認定之基礎事實有不同判斷，但如該案件仍須另行蒐證偵查始能判斷應否交付審判者，因交付審判審查制度並無如同再議救濟制度得為發回原檢察官續行偵查之設計，法院仍應依同法第258條之3第2項前段規定，以聲請無理由裁定駁回。四、本件聲請人雖以前揭理由認被告乙○○涉有偽造文書等罪嫌，而向本院聲請交付審判。然前揭不起訴處分書及駁回再議處分書已就聲請人於偵查時提出之告訴理由予以斟酌，並詳加論述所憑證據及其認定之理由，關於此點，業經本院依職權調閱前開偵查卷宗查核無誤。經查：（一）被告乙○○自83年9月5日起，陸續收取聲請人及被害人等之投資款項，分別是聲請人丙○○1千7百28萬9千6百50元、高耀仁2百50萬7千元、李秀葉4百46萬9千元、吳美容5百31萬6千元、李榮華2百64萬3千4百元、張清泉5百37萬零3百零5元，及黃金圓、陳淑貞、張明珠（三人合夥）共5百萬元泰幣、李木祥2百80萬元泰幣。而被告自83年3月12日起至86年8月22日止，陸續將上開資金以匯款方式匯至泰國給蔡龍木收取，共計達5千7百零6萬6千4百82元（泰幣5千3百90萬6千2百17點92元），縱依聲請人所主張，將被告所提關於83年3月12日至83年6月2日及86年8月22日之匯款刪除（該部分非無可能即被告自己之投資金額），再將李木祥所投資泰幣2百80萬銖及陳淑貞等3人合計出資泰幣5百萬銖，以最不利被告之賣出匯率即1：1.08960計算，被告匯款給蔡龍木之總金額即新台幣4千7百零6萬4千1百71元，仍超過聲請人及被害人交付之投資金額即約新台幣4千6百零9萬4千2百35元，被告所辯其業將聲請人及被害人等所交付連同自己之投資金額匯款至泰國給蔡龍木，尚非無據，故無證據足認被告有不法所有之意圖等情，業經臺灣高等法院以91年度上易字第2201號確定判決認定屬實在案（按被告於該案中被訴詐欺罪嫌，經判決無罪確定），有該案號判決一份在卷可憑（見他字1020號卷第8頁）。是被告既將聲請人及被害人等所交付之投資金額匯款至泰國給蔡龍木，被告自無犯侵占罪責可言。又聲請人另主張檢察官未傳訊蔡龍木到案說明，調查證據顯有疏漏云云。惟該部分，因被告乙○○無涉犯侵占罪，是原檢察官認為已無調查其他證據之必要，至於聲請人所指之蔡龍木，並未於偵查中呈現，亦未經檢察官偵辦，且非屬檢察官不起訴處分範圍，依據前開說明，聲請法院交付審判之調查證據範圍，應以偵查中曾顯現之證據為限，本院自不得就聲請人新提出之證據進行調查，亦不得蒐集偵查卷以外之證據，否則，將與刑事訴訟法第260條之再行起訴規定混淆不清，將使法院兼任檢察官而有回復「糾問制度」之虞業如前述，是聲請人上開主張，顯屬不合規定，並非本院審理之範圍。（二）再者，蔡龍木係私自以6萊土地向泰國銀行辦理抵押借款300萬元泰幣供其個人週轉之用等情，業據被告於偵查中供稱：「立國公司是蔡龍木在泰國成立的公司」、「蔡龍木在91年3月去開庭時，有承認拿土地向銀行借款300萬泰幣做為個人週轉用，所以這個錢不是我拿去抵押貸款的」、「在泰國要成為公司的股東要本人親自拿護照去辦理，成立公司都是蔡龍木去辦理的」等語（見92年度偵字第10575號偵查卷第10頁至第11頁），核與蔡龍木於台灣板橋地方法院91年3月5日審理時供述：「（問：你是否有拿土地抵押借款？）我有拿6萊土地向泰國銀行借款300萬泰幣，我拿到300萬元做為我個人週轉用」等語相符（見台灣板橋地方法院89年度易字第4224號卷第402頁），足見此部分行為乃被告蔡龍木個人行為，與被告乙○○無涉，是聲請人認被告參與抵押貸款而有偽造文書之情事，尚屬無據。（三）又按刑法第342條第1項之背信罪，係以行為人為他人處理事務，意圖為自己或第三人不法之利益，或損害本人利益，而為違背其任務之行為，致生於損害於本人之財產或其他利益為要件。經查，本件被告自83年9月7日至84年8月16日匯款予蔡龍木之總金額為4千7百零6萬4千1百71元，其間金額雖稍有短少，惟被告向聲請人等投資人所收取之款項僅部分係以匯款方式交付予蔡龍木，另有部分款項則係交付予蔡龍木或其妻，交付現金部分因未取據，致無從計算詳細總額等情，業據被告於偵查中供稱：「我是根據投資人和蔡龍木的指示來匯錢，我沒有侵占。中間的差額有補到其他月份，匯錢的部分不能只看單月份要看整個匯款的單據」、「有些是用匯的，有些是用現金，現金是交給他或他的太太」、「有部分是拿現金給蔡龍木和他太太，有些是用匯的，所以匯款明細上所記載的並不是全部的金額」、「現金部分最少有1千多萬」、「蔡龍木他們沒有簽收據給我」（見92年度偵字第10575號偵查卷第121頁、第289頁、第294頁），核與證人李木祥於偵查中陳稱：「51萊土地部分他有帶現金到泰國給蔡龍木」等語相符（見同前偵查卷第317頁），是被告乙○○除以匯款方式外，亦另有以交付現金之方式予蔡龍木無訛，況就聲請人所提出泰國買地6萊、4萊土地付款辦法所記載投資人之付款方式亦多係以現金交付予被告，足徵被告辯稱部分投資款係以現金交付等語，亦尚非無據。故縱使被告於前揭時間內之匯款金額較投資人所繳付之款項略少，亦難遽認該短少部分即為其所侵占。況被告乙○○既有出資，亦遵守約定已將聲請人等之投資金額匯款予蔡龍木，並非違背其任務，且投資海外不動產事業本具有相當之風險存在，縱使嗣後投資失利，亦難謂有損害聲請人等財產或利益之可言，自與背信罪之成立要件未合。（四）再按刑法第5條規定，本法於凡在中華民國領域外犯左列各罪者，適用之：1.內亂罪。2.外患罪。3.偽造貨幣罪。4.第201條及第202條之偽造有價證券罪。5.第211條、第214條、第216條及第218條之偽造文書印文罪。6.鴉片罪。7.第296條之妨害自由罪。8.第333條及第334條之海盜罪。又按刑法第7條規定，本法於中華民國人民在中華民國領域外犯前2條以外之罪，而其最輕本刑為3年以上有期徒刑者，適用之。聲請人向本院聲請交付審判，指訴被告乙○○擅自將在泰國所購買之土地登記予不相關之第3人，並以該土地向泰國銀行抵押貸款，又泰國「立國公司」於臺灣召開股東會議時，出列席之股東並無李木祥，惟被告於泰國所成立之「大中公司」所列之公司創辦人卻有李木祥之名，因認被告涉有偽造私文書、背信及侵占罪云云。然查，聲請人丙○○於偵查中證稱：「被告擅自將土地登記不相關第3人並且將土地拿去辦理抵押貸款係在泰國」、「立國公司章程有列李木祥，被告偽造公司股東名冊，偽造文書的土地在泰國」、「立國是被告在泰國申請設立的」等語（見92年度偵字第10575號偵查卷第56頁），顯見被告上揭所申請成立之公司及購買土地辦理抵押等行為均在泰國完成無訛，復有土地謄本、土地所有權地主證明及大中公司章程影本在卷可稽。再者，被告於偵查中供稱：丙○○等投資人所收款項有些是用匯的，有些是用現金，現金是交給蔡龍木或他的太太等語（見92年度偵字第10575號偵查卷第289頁），是聲請人等將錢交予被告乙○○後，由被告匯款至蔡龍木於泰國之帳戶後，再由蔡龍木於泰國提領該款項，或由被告直接交予蔡龍木或他的太太，足徵被告縱有偽造文書、背信及侵占之犯行，其犯罪之行為地與結果地亦皆在泰國。再觀諸聲請人所指稱：被告侵占之款項均係聲請人於本國交付予被告等情，則縱使聲請人交付投資金額係在台灣，然因被告具體違背委任義務之舉止，係發生在泰國，且被告須忠實為聲請人履行義務之地點亦係泰國，而非在我國境內，則被告之行為地自係在泰國，又聲請人所受之損害，亦應係其在泰國之事業所受之利益損失，被告之偽造文書、背信及侵占行為之結果，皆發生在泰國，是被告所為核係在我國境外犯罪甚明。綜上而論，被告既係在我國領域外犯罪，又前揭偽造文書、背信及侵占罪，均非刑法第5條所規定之罪名，且其法定刑亦非刑法第7條所定之最輕本刑3年以上有期徒刑之罪情形，揆諸上揭說明，我國法院對被告上述行為自無審判權。五、綜上所述，原不起訴處分書及聲請再議處分書既已詳予調查偵查卷內所存證據，並敘明理由，既無積極證據證明被告乙○○涉有聲請人所指訴之偽造文書、背信及侵占犯行，尚難以聲請人之片面指訴，遽認被告涉有本件犯行；且原處分所載證據取捨及事實認定之理由，尚無違背經驗法則或論理法則之情事，是原檢察官及臺灣高等法院檢察署檢察長以被告犯罪嫌疑不足，分別予以不起訴處分及駁回再議之聲請，並無不當。本件聲請交付審判意旨仍執陳詞，對於原處分漫加指摘求予審判，顯無理由，應予駁回。六、依刑事訴訟法第258條之3第2項前段，裁定如主文。中華民國94年6月9日刑事第三庭審判長法官李正紀法官吳祚丞法官王俊雄以上正本證明與原本無異。本裁定不得抗告。書記官許秋莉中華民國94年6月9日",
  "characters": {
    "judges": [
      "李正紀",
      "吳祚丞",
      "王俊雄"
    ],
    "prosecutors": [

    ],
    "lawyers": [

    ],
    "clerks": [
      "許秋莉"
    ],
    "plaintiffs": [

    ],
    "defendants": [
      "乙○○"
    ],
    "prosecutor_office": [
      "丙"
    ],
    "creditors": [

    ],
    "debtors": [

    ],
    "judicial_associate_officer": [

    ]
  },
  "adjudged_at": "2005-06-09",
  "created_at": "2016-02-07 05:09:56",
  "updated_at": "2016-02-07 05:09:56"
}