{
  "identify": "PTD-94-交簡-75-20050218-1",
  "court": {
    "name": "臺灣屏東地方法院",
    "code": "PTD"
  },
  "division": {
    "name": "刑事",
    "code": "M"
  },
  "year": 94,
  "word": "交簡",
  "number": "75",
  "jcheck": "1",
  "reason": "公共危險",
  "content": "臺灣屏東地方法院刑事簡易判決                      九十四年度交簡字第七五號\n    聲  請  人  臺灣屏東地方法院檢察署檢察官\n    被      告  甲○○  男  四.\n右列被告因公共危險案件，經檢察官聲請以簡易判決處刑（九十四年度偵字第二０五\n號），本院判決如左：\n     主  文\n甲○○服用酒類，不能安全駕駛動力交通工具而駕駛，累犯，處拘役肆拾日，如易科\n罰金，以佰元折算壹日。\n    事實及理由\n一、本院認定被告之犯罪事實，除(一)犯罪事實欄第二行「明知自己不能安全駕駛動力\n    交通工具」更改為「因酒醉反應遲鈍」，第七行「車號ＬＤ—90號曳引車」應更\n    正為「車牌號碼六０二—ＧＢ曳引車，拖載半拖車一部（車牌號碼：ＬＤ─九０\n    ）」，另補充(1)甲○○曾於民國八十八年間因過失傷害案件，經台灣桃園地方法\n    院判處有期徒刑三月確定，於八十九年五月二十九日易科罰金執行完畢，猶不知\n    悔改。(2)甲○○明知服用酒類，不能安全駕駛動力交通工具時，即不得騎乘機車\n    上路。(3)其吐氣所含酒精成份已達每公升零點八七毫克，並呈中度酩酊、運動失\n    調、平衡障礙、判斷力遲鈍等症狀，顯有酒醉不能安全駕駛動力交通工具之情形\n    。(二)證據欄補充：且依卷附血液中酒精濃度與酒醉程度及呈現症狀之關係表所示\n    ，被告當時已呈現中度酩酊、運動失調、平衡障礙、判斷力遲鈍等症狀外，餘與\n    檢察官聲請簡易判決處刑書之記載相同，茲引用之（如附件）。\n二、核被告酒醉駕車之行為，係犯刑法一百八十五條之三服用酒類，不能安全駕駛動\n    力交通工具而駕駛罪。被告曾於八十八年間因過失傷害案件，經台灣桃園地方法\n    院判處有期徒刑三月確定，於八十九年五月二十九日易科罰金執行完畢，有臺灣\n    屏東地方法院檢察署刑案資料查註紀錄表及臺灣高等法院被告全國前案紀錄表各\n    一份在卷可佐，其於五年內再犯有期徒刑以上刑之本罪，為累犯，應依法加重其\n    刑。爰審酌被告素行、犯罪動機、生活狀況、酒醉程度、漠視一般往來之公眾及\n    駕駛人之用路安全，且政府各相關機關業就酒醉駕車之危害性以學校教育、媒體\n    傳播等方式一再宣導，為時甚久，被告應對於該項誡命知之甚詳，猶不知警惕及\n    犯罪後態度等一切情狀，量處如主文所示之刑，並諭知易科罰金之折算標準。\n三、依刑事訴訟法第四百四十九條第一項前段、第四百五十四條第二項，刑法第一百\n    八十五條之三、第四十七條、第四十一條第一項前段，罰金罰鍰提高標準條例第\n    二條，逕以簡易判決處以如主文所示之刑。\n中      華      民      國    九十四    年      二      月     十八     日\n                                      臺灣屏東地方法院交通法庭\n                                          法  官  余德正\n右正本證明與原本無異。\n如不服本判決，得於判決書送達之翌日起十日內，以書狀敘述理由，向本庭提出上訴\n。\n                                          書記官  潘美碧\n中      華      民      國    九十四    年      二      月  二十一      日\n附錄本判決論罪科刑法條全文\n刑法第一百八十五條之三：\n服用毒品、麻醉藥品、酒類或其他相類之物，不能安全駕駛動力交通工具而駕駛者，\n處一年以下有期徒刑、拘役或三萬元以下罰金。\n",
  "structure": {
    "main": "甲○○服用酒類，不能安全駕駛動力交通工具而駕駛，累犯，處拘役肆拾日，如易科\n罰金，以佰元折算壹日。",
    "fact": "一、本院認定被告之犯罪事實，除(一)犯罪事實欄第二行「明知自己不能安全駕駛動力\n    交通工具」更改為「因酒醉反應遲鈍」，第七行「車號ＬＤ—90號曳引車」應更\n    正為「車牌號碼六０二—ＧＢ曳引車，拖載半拖車一部（車牌號碼：ＬＤ─九０\n    ）」，另補充(1)甲○○曾於民國八十八年間因過失傷害案件，經台灣桃園地方法\n    院判處有期徒刑三月確定，於八十九年五月二十九日易科罰金執行完畢，猶不知\n    悔改。(2)甲○○明知服用酒類，不能安全駕駛動力交通工具時，即不得騎乘機車\n    上路。(3)其吐氣所含酒精成份已達每公升零點八七毫克，並呈中度酩酊、運動失\n    調、平衡障礙、判斷力遲鈍等症狀，顯有酒醉不能安全駕駛動力交通工具之情形\n    。(二)證據欄補充：且依卷附血液中酒精濃度與酒醉程度及呈現症狀之關係表所示\n    ，被告當時已呈現中度酩酊、運動失調、平衡障礙、判斷力遲鈍等症狀外，餘與\n    檢察官聲請簡易判決處刑書之記載相同，茲引用之（如附件）。\n二、核被告酒醉駕車之行為，係犯刑法一百八十五條之三服用酒類，不能安全駕駛動\n    力交通工具而駕駛罪。被告曾於八十八年間因過失傷害案件，經台灣桃園地方法\n    院判處有期徒刑三月確定，於八十九年五月二十九日易科罰金執行完畢，有臺灣\n    屏東地方法院檢察署刑案資料查註紀錄表及臺灣高等法院被告全國前案紀錄表各\n    一份在卷可佐，其於五年內再犯有期徒刑以上刑之本罪，為累犯，應依法加重其\n    刑。爰審酌被告素行、犯罪動機、生活狀況、酒醉程度、漠視一般往來之公眾及\n    駕駛人之用路安全，且政府各相關機關業就酒醉駕車之危害性以學校教育、媒體\n    傳播等方式一再宣導，為時甚久，被告應對於該項誡命知之甚詳，猶不知警惕及\n    犯罪後態度等一切情狀，量處如主文所示之刑，並諭知易科罰金之折算標準。\n三、依刑事訴訟法第四百四十九條第一項前段、第四百五十四條第二項，刑法第一百\n    八十五條之三、第四十七條、第四十一條第一項前段，罰金罰鍰提高標準條例第\n    二條，逕以簡易判決處以如主文所示之刑。",
    "reason": "一、本院認定被告之犯罪事實，除(一)犯罪事實欄第二行「明知自己不能安全駕駛動力\n    交通工具」更改為「因酒醉反應遲鈍」，第七行「車號ＬＤ—90號曳引車」應更\n    正為「車牌號碼六０二—ＧＢ曳引車，拖載半拖車一部（車牌號碼：ＬＤ─九０\n    ）」，另補充(1)甲○○曾於民國八十八年間因過失傷害案件，經台灣桃園地方法\n    院判處有期徒刑三月確定，於八十九年五月二十九日易科罰金執行完畢，猶不知\n    悔改。(2)甲○○明知服用酒類，不能安全駕駛動力交通工具時，即不得騎乘機車\n    上路。(3)其吐氣所含酒精成份已達每公升零點八七毫克，並呈中度酩酊、運動失\n    調、平衡障礙、判斷力遲鈍等症狀，顯有酒醉不能安全駕駛動力交通工具之情形\n    。(二)證據欄補充：且依卷附血液中酒精濃度與酒醉程度及呈現症狀之關係表所示\n    ，被告當時已呈現中度酩酊、運動失調、平衡障礙、判斷力遲鈍等症狀外，餘與\n    檢察官聲請簡易判決處刑書之記載相同，茲引用之（如附件）。\n二、核被告酒醉駕車之行為，係犯刑法一百八十五條之三服用酒類，不能安全駕駛動\n    力交通工具而駕駛罪。被告曾於八十八年間因過失傷害案件，經台灣桃園地方法\n    院判處有期徒刑三月確定，於八十九年五月二十九日易科罰金執行完畢，有臺灣\n    屏東地方法院檢察署刑案資料查註紀錄表及臺灣高等法院被告全國前案紀錄表各\n    一份在卷可佐，其於五年內再犯有期徒刑以上刑之本罪，為累犯，應依法加重其\n    刑。爰審酌被告素行、犯罪動機、生活狀況、酒醉程度、漠視一般往來之公眾及\n    駕駛人之用路安全，且政府各相關機關業就酒醉駕車之危害性以學校教育、媒體\n    傳播等方式一再宣導，為時甚久，被告應對於該項誡命知之甚詳，猶不知警惕及\n    犯罪後態度等一切情狀，量處如主文所示之刑，並諭知易科罰金之折算標準。\n三、依刑事訴訟法第四百四十九條第一項前段、第四百五十四條第二項，刑法第一百\n    八十五條之三、第四十七條、第四十一條第一項前段，罰金罰鍰提高標準條例第\n    二條，逕以簡易判決處以如主文所示之刑。"
  },
  "search": "臺灣屏東地方法院刑事簡易判決九十四年度交簡字第七五號聲請人臺灣屏東地方法院檢察署檢察官被告甲○○男四.右列被告因公共危險案件，經檢察官聲請以簡易判決處刑（九十四年度偵字第二０五號），本院判決如左：主文甲○○服用酒類，不能安全駕駛動力交通工具而駕駛，累犯，處拘役肆拾日，如易科罰金，以佰元折算壹日。事實及理由一、本院認定被告之犯罪事實，除(一)犯罪事實欄第二行「明知自己不能安全駕駛動力交通工具」更改為「因酒醉反應遲鈍」，第七行「車號ＬＤ—90號曳引車」應更正為「車牌號碼六０二—ＧＢ曳引車，拖載半拖車一部（車牌號碼：ＬＤ─九０）」，另補充(1)甲○○曾於民國八十八年間因過失傷害案件，經台灣桃園地方法院判處有期徒刑三月確定，於八十九年五月二十九日易科罰金執行完畢，猶不知悔改。(2)甲○○明知服用酒類，不能安全駕駛動力交通工具時，即不得騎乘機車上路。(3)其吐氣所含酒精成份已達每公升零點八七毫克，並呈中度酩酊、運動失調、平衡障礙、判斷力遲鈍等症狀，顯有酒醉不能安全駕駛動力交通工具之情形。(二)證據欄補充：且依卷附血液中酒精濃度與酒醉程度及呈現症狀之關係表所示，被告當時已呈現中度酩酊、運動失調、平衡障礙、判斷力遲鈍等症狀外，餘與檢察官聲請簡易判決處刑書之記載相同，茲引用之（如附件）。二、核被告酒醉駕車之行為，係犯刑法一百八十五條之三服用酒類，不能安全駕駛動力交通工具而駕駛罪。被告曾於八十八年間因過失傷害案件，經台灣桃園地方法院判處有期徒刑三月確定，於八十九年五月二十九日易科罰金執行完畢，有臺灣屏東地方法院檢察署刑案資料查註紀錄表及臺灣高等法院被告全國前案紀錄表各一份在卷可佐，其於五年內再犯有期徒刑以上刑之本罪，為累犯，應依法加重其刑。爰審酌被告素行、犯罪動機、生活狀況、酒醉程度、漠視一般往來之公眾及駕駛人之用路安全，且政府各相關機關業就酒醉駕車之危害性以學校教育、媒體傳播等方式一再宣導，為時甚久，被告應對於該項誡命知之甚詳，猶不知警惕及犯罪後態度等一切情狀，量處如主文所示之刑，並諭知易科罰金之折算標準。三、依刑事訴訟法第四百四十九條第一項前段、第四百五十四條第二項，刑法第一百八十五條之三、第四十七條、第四十一條第一項前段，罰金罰鍰提高標準條例第二條，逕以簡易判決處以如主文所示之刑。中華民國九十四年二月十八日臺灣屏東地方法院交通法庭法官余德正右正本證明與原本無異。如不服本判決，得於判決書送達之翌日起十日內，以書狀敘述理由，向本庭提出上訴。書記官潘美碧中華民國九十四年二月二十一日附錄本判決論罪科刑法條全文刑法第一百八十五條之三：服用毒品、麻醉藥品、酒類或其他相類之物，不能安全駕駛動力交通工具而駕駛者，處一年以下有期徒刑、拘役或三萬元以下罰金。",
  "characters": {
    "judges": [
      "余德正"
    ],
    "prosecutors": [

    ],
    "lawyers": [

    ],
    "clerks": [
      "潘美碧"
    ],
    "plaintiffs": [

    ],
    "defendants": [
      "甲○○  男  四.",
      "右列被告因公共危險案件，經檢察官聲請以簡易判決處刑（九十四年度偵字第二０五",
      "號），本院判決如左："
    ],
    "prosecutor_office": [
      "臺灣屏東地方法院檢察署檢察官"
    ],
    "creditors": [

    ],
    "debtors": [

    ],
    "judicial_associate_officer": [

    ]
  },
  "adjudged_at": "2005-02-18",
  "created_at": "2016-02-06 16:36:32",
  "updated_at": "2016-02-06 16:36:32"
}