{
  "identify": "CHD-94-易-473-20050615-1",
  "court": {
    "name": "臺灣彰化地方法院",
    "code": "CHD"
  },
  "division": {
    "name": "刑事",
    "code": "M"
  },
  "year": 94,
  "word": "易",
  "number": "473",
  "jcheck": "1",
  "reason": "毒品危害防制條例",
  "content": "臺灣彰化地方法院刑事判決               94年度易字第473號\n公  訴  人  臺灣彰化地方法院檢察署檢察官\n被      告  甲○○  男  24歲.\n                    身分證統一.\n                    住彰化縣彰.\n選任辯護人  辛武律師\n上列被告因違反毒品危害防制條例案件，經檢察官聲請簡易判決\n處刑（93年度毒偵字第4326號），本院彰化簡易庭認不宜以簡易\n程序判決處刑，簽移由本院合議庭審理，嗣被告於準備程序就被\n訴事實為有罪之陳述，經本院合議庭裁定由受命法官獨任行簡式\n審判程序，判決如下：\n    主      文\n陳宗庭施用第二級毒品，處有期徒刑月，如易科罰金，以佰\n元折算壹日。\n    事實及理由\n一、犯罪事實：\n    甲○○前因違反毒品危害防制條例案件，經送觀察、勒戒後\n    ，認無繼續施用毒品之傾向，於民國93年8月4日執行完畢釋\n    放，並台灣彰化地方法院檢察署檢察官於同年月20日以93年\n    度毒偵字第1365號為不起訴處分確定。惟其猶未能戒除毒癮\n    ，於觀察、勒戒執行完畢釋放後5年內，又於93年8月19日，\n    在彰化縣彰化市○○路○段556巷24號8樓之租屋處，以吞食\n    膠囊之方式，施用第二級毒品MDMA一次，嗣於93年8 月20日\n    下午3 時30分許，為警持搜索票在上述租屋處查獲，經其同\n    意採尿送驗，結果呈MDA及MDMA陽性反應，始悉上情。\n二、被告甲○○於準備程序中，就被訴犯罪事實為有罪之陳述，\n    且所犯係死刑、無期徒刑、最輕本刑為3年以上有期徒刑以\n    外之罪，經本院合議庭依刑事訴訟法第273條之1第1項之規\n    定，裁定由法官一人獨任進行簡式審判程序。\n三、本案證據：\n    (一)中山醫學大學附設醫院藥物濫用檢測中心檢驗報告。\n    (二)台中縣警察局刑警隊網偵組委託鑑驗尿液代號與真實姓名\n      對照表。\n    (三)行政院衛生署管制藥品管理局94年3月22日管檢字第09400\n      1777號函文（說明服用ＭＤＭＡ後之生理反應，及經人體\n      代謝後尿液檢驗之反應）。\n    (四)被告之自白。\n    (五)台灣高等法院被告全國前案紀錄表。\n    (六)財團法人彰化基督教醫院診斷證明書。\n    (七)里長證明書。\n    (八)被告甲○○薪資證明書、工作證明，及所屬公司之彰化縣\n      政府營利事業登記證。\n四、應依刑事訴訟法第273條之1第1項、第299條第1 項前段、第\n    310 條之2、第454條第1項，毒品危害防制條例第10條第2項\n    ，刑法第11條前段、第41條第1項第2款，罰金罰鍰提高標準\n    條例第1條前段、第2條，判決如主文。\n五、如不服本判決，應於判決送達後10日內，向本院提出上訴狀\n    （須附繕本），上訴於台灣高等法院台中分院。\n中    華    民    國    94    年    6    月    15    日\n                  刑事第三庭       法    官  黃玉齡\n以上正本證明與原本無異。\n中    華    民    國    94    年    6    月    20    日\n                                     書記官  林怡吟\n附錄本案論罪科刑法條全文：\n毒品危害防制條例第十條\n(1)施用第一級毒品者，處六月以上五年以下有期徒刑。\n(2)施用第二級毒品者，處三年以下有期徒刑。\n",
  "structure": {
    "main": "陳宗庭施用第二級毒品，處有期徒刑月，如易科罰金，以佰\n元折算壹日。",
    "fact": "一、犯罪事實：\n    甲○○前因違反毒品危害防制條例案件，經送觀察、勒戒後\n    ，認無繼續施用毒品之傾向，於民國93年8月4日執行完畢釋\n    放，並台灣彰化地方法院檢察署檢察官於同年月20日以93年\n    度毒偵字第1365號為不起訴處分確定。惟其猶未能戒除毒癮\n    ，於觀察、勒戒執行完畢釋放後5年內，又於93年8月19日，\n    在彰化縣彰化市○○路○段556巷24號8樓之租屋處，以吞食\n    膠囊之方式，施用第二級毒品MDMA一次，嗣於93年8 月20日\n    下午3 時30分許，為警持搜索票在上述租屋處查獲，經其同\n    意採尿送驗，結果呈MDA及MDMA陽性反應，始悉上情。\n二、被告甲○○於準備程序中，就被訴犯罪事實為有罪之陳述，\n    且所犯係死刑、無期徒刑、最輕本刑為3年以上有期徒刑以\n    外之罪，經本院合議庭依刑事訴訟法第273條之1第1項之規\n    定，裁定由法官一人獨任進行簡式審判程序。\n三、本案證據：\n    (一)中山醫學大學附設醫院藥物濫用檢測中心檢驗報告。\n    (二)台中縣警察局刑警隊網偵組委託鑑驗尿液代號與真實姓名\n      對照表。\n    (三)行政院衛生署管制藥品管理局94年3月22日管檢字第09400\n      1777號函文（說明服用ＭＤＭＡ後之生理反應，及經人體\n      代謝後尿液檢驗之反應）。\n    (四)被告之自白。\n    (五)台灣高等法院被告全國前案紀錄表。\n    (六)財團法人彰化基督教醫院診斷證明書。\n    (七)里長證明書。\n    (八)被告甲○○薪資證明書、工作證明，及所屬公司之彰化縣\n      政府營利事業登記證。\n四、應依刑事訴訟法第273條之1第1項、第299條第1 項前段、第\n    310 條之2、第454條第1項，毒品危害防制條例第10條第2項\n    ，刑法第11條前段、第41條第1項第2款，罰金罰鍰提高標準\n    條例第1條前段、第2條，判決如主文。\n五、如不服本判決，應於判決送達後10日內，向本院提出上訴狀\n    （須附繕本），上訴於台灣高等法院台中分院。",
    "reason": "一、犯罪事實：\n    甲○○前因違反毒品危害防制條例案件，經送觀察、勒戒後\n    ，認無繼續施用毒品之傾向，於民國93年8月4日執行完畢釋\n    放，並台灣彰化地方法院檢察署檢察官於同年月20日以93年\n    度毒偵字第1365號為不起訴處分確定。惟其猶未能戒除毒癮\n    ，於觀察、勒戒執行完畢釋放後5年內，又於93年8月19日，\n    在彰化縣彰化市○○路○段556巷24號8樓之租屋處，以吞食\n    膠囊之方式，施用第二級毒品MDMA一次，嗣於93年8 月20日\n    下午3 時30分許，為警持搜索票在上述租屋處查獲，經其同\n    意採尿送驗，結果呈MDA及MDMA陽性反應，始悉上情。\n二、被告甲○○於準備程序中，就被訴犯罪事實為有罪之陳述，\n    且所犯係死刑、無期徒刑、最輕本刑為3年以上有期徒刑以\n    外之罪，經本院合議庭依刑事訴訟法第273條之1第1項之規\n    定，裁定由法官一人獨任進行簡式審判程序。\n三、本案證據：\n    (一)中山醫學大學附設醫院藥物濫用檢測中心檢驗報告。\n    (二)台中縣警察局刑警隊網偵組委託鑑驗尿液代號與真實姓名\n      對照表。\n    (三)行政院衛生署管制藥品管理局94年3月22日管檢字第09400\n      1777號函文（說明服用ＭＤＭＡ後之生理反應，及經人體\n      代謝後尿液檢驗之反應）。\n    (四)被告之自白。\n    (五)台灣高等法院被告全國前案紀錄表。\n    (六)財團法人彰化基督教醫院診斷證明書。\n    (七)里長證明書。\n    (八)被告甲○○薪資證明書、工作證明，及所屬公司之彰化縣\n      政府營利事業登記證。\n四、應依刑事訴訟法第273條之1第1項、第299條第1 項前段、第\n    310 條之2、第454條第1項，毒品危害防制條例第10條第2項\n    ，刑法第11條前段、第41條第1項第2款，罰金罰鍰提高標準\n    條例第1條前段、第2條，判決如主文。\n五、如不服本判決，應於判決送達後10日內，向本院提出上訴狀\n    （須附繕本），上訴於台灣高等法院台中分院。"
  },
  "search": "臺灣彰化地方法院刑事判決94年度易字第473號公訴人臺灣彰化地方法院檢察署檢察官被告甲○○男24歲.身分證統一.住彰化縣彰.選任辯護人辛武律師上列被告因違反毒品危害防制條例案件，經檢察官聲請簡易判決處刑（93年度毒偵字第4326號），本院彰化簡易庭認不宜以簡易程序判決處刑，簽移由本院合議庭審理，嗣被告於準備程序就被訴事實為有罪之陳述，經本院合議庭裁定由受命法官獨任行簡式審判程序，判決如下：主文陳宗庭施用第二級毒品，處有期徒刑月，如易科罰金，以佰元折算壹日。事實及理由一、犯罪事實：甲○○前因違反毒品危害防制條例案件，經送觀察、勒戒後，認無繼續施用毒品之傾向，於民國93年8月4日執行完畢釋放，並台灣彰化地方法院檢察署檢察官於同年月20日以93年度毒偵字第1365號為不起訴處分確定。惟其猶未能戒除毒癮，於觀察、勒戒執行完畢釋放後5年內，又於93年8月19日，在彰化縣彰化市○○路○段556巷24號8樓之租屋處，以吞食膠囊之方式，施用第二級毒品MDMA一次，嗣於93年8月20日下午3時30分許，為警持搜索票在上述租屋處查獲，經其同意採尿送驗，結果呈MDA及MDMA陽性反應，始悉上情。二、被告甲○○於準備程序中，就被訴犯罪事實為有罪之陳述，且所犯係死刑、無期徒刑、最輕本刑為3年以上有期徒刑以外之罪，經本院合議庭依刑事訴訟法第273條之1第1項之規定，裁定由法官一人獨任進行簡式審判程序。三、本案證據：(一)中山醫學大學附設醫院藥物濫用檢測中心檢驗報告。(二)台中縣警察局刑警隊網偵組委託鑑驗尿液代號與真實姓名對照表。(三)行政院衛生署管制藥品管理局94年3月22日管檢字第094001777號函文（說明服用ＭＤＭＡ後之生理反應，及經人體代謝後尿液檢驗之反應）。(四)被告之自白。(五)台灣高等法院被告全國前案紀錄表。(六)財團法人彰化基督教醫院診斷證明書。(七)里長證明書。(八)被告甲○○薪資證明書、工作證明，及所屬公司之彰化縣政府營利事業登記證。四、應依刑事訴訟法第273條之1第1項、第299條第1項前段、第310條之2、第454條第1項，毒品危害防制條例第10條第2項，刑法第11條前段、第41條第1項第2款，罰金罰鍰提高標準條例第1條前段、第2條，判決如主文。五、如不服本判決，應於判決送達後10日內，向本院提出上訴狀（須附繕本），上訴於台灣高等法院台中分院。中華民國94年6月15日刑事第三庭法官黃玉齡以上正本證明與原本無異。中華民國94年6月20日書記官林怡吟附錄本案論罪科刑法條全文：毒品危害防制條例第十條(1)施用第一級毒品者，處六月以上五年以下有期徒刑。(2)施用第二級毒品者，處三年以下有期徒刑。",
  "characters": {
    "judges": [
      "黃玉齡"
    ],
    "prosecutors": [

    ],
    "lawyers": [
      "辛武"
    ],
    "clerks": [
      "林怡吟"
    ],
    "plaintiffs": [

    ],
    "defendants": [
      "甲○○  男  24歲."
    ],
    "prosecutor_office": [
      "臺灣彰化地方法院檢察署檢察官"
    ],
    "creditors": [

    ],
    "debtors": [

    ],
    "judicial_associate_officer": [

    ]
  },
  "adjudged_at": "2005-06-15",
  "created_at": "2016-02-07 04:51:02",
  "updated_at": "2016-02-07 04:51:02"
}