{
  "identify": "KSH-94-抗-105-20050614-1",
  "court": {
    "name": "臺灣高等法院",
    "code": "KSH"
  },
  "division": {
    "name": "刑事",
    "code": "M"
  },
  "year": 94,
  "word": "抗",
  "number": "105",
  "jcheck": "1",
  "reason": "聲請定其應執行刑",
  "content": "臺灣高等法院高雄分院刑事裁定           94年度抗字第105號\n抗  告  人\n即受刑人    甲○○\n上列抗告人因聲請定其應執行刑案件，不服台灣高雄地方法院94\n年4 月28日裁定 (94年度聲字第1129號)， 提起抗告，本院裁定\n如下：\n    主  文\n抗告駁回。\n    理  由\n一、查受刑人因違反毒品危害防制條例等二罪，經原審法院先後\n    判處如附表所示之刑，均經分別確定在案，茲檢察官應聲請\n    定其應執行之刑，原審審認聲請為正當，定其應執行之有期\n    徒刑1 年6 月，核無不合，本件抗告未具理由，應予駁回。\n二、據上論結，應依刑事訴訟法第412條，裁定如主文。\n中    華    民    國    94    年    6     月    14    日\n                  刑事第一庭  審判長法  官  郭雅美\n                                    法  官  江泰章\n                                    法  官  莊崑山\n以上正本證明與原本無異。\n如不服本裁定應於送達後5 日內向本院提出再抗告狀。\n中    華    民    國    94    年    6     月    14    日\n                                    書記官  鄔維玲\n",
  "structure": {
    "main": "抗告駁回。",
    "reason": "一、查受刑人因違反毒品危害防制條例等二罪，經原審法院先後\n    判處如附表所示之刑，均經分別確定在案，茲檢察官應聲請\n    定其應執行之刑，原審審認聲請為正當，定其應執行之有期\n    徒刑1 年6 月，核無不合，本件抗告未具理由，應予駁回。\n二、據上論結，應依刑事訴訟法第412條，裁定如主文。"
  },
  "search": "臺灣高等法院高雄分院刑事裁定94年度抗字第105號抗告人即受刑人甲○○上列抗告人因聲請定其應執行刑案件，不服台灣高雄地方法院94年4月28日裁定(94年度聲字第1129號)，提起抗告，本院裁定如下：主文抗告駁回。理由一、查受刑人因違反毒品危害防制條例等二罪，經原審法院先後判處如附表所示之刑，均經分別確定在案，茲檢察官應聲請定其應執行之刑，原審審認聲請為正當，定其應執行之有期徒刑1年6月，核無不合，本件抗告未具理由，應予駁回。二、據上論結，應依刑事訴訟法第412條，裁定如主文。中華民國94年6月14日刑事第一庭審判長法官郭雅美法官江泰章法官莊崑山以上正本證明與原本無異。如不服本裁定應於送達後5日內向本院提出再抗告狀。中華民國94年6月14日書記官鄔維玲",
  "characters": {
    "judges": [
      "郭雅美",
      "江泰章",
      "莊崑山"
    ],
    "prosecutors": [

    ],
    "lawyers": [

    ],
    "clerks": [
      "鄔維玲"
    ],
    "plaintiffs": [

    ],
    "defendants": [

    ],
    "prosecutor_office": [

    ],
    "creditors": [

    ],
    "debtors": [

    ],
    "judicial_associate_officer": [

    ]
  },
  "adjudged_at": "2005-06-14",
  "created_at": "2016-02-07 04:54:27",
  "updated_at": "2016-02-07 04:54:27"
}