{
  "identify": "TCD-100-除-618-20110809-1",
  "court": {
    "name": "臺灣臺中地方法院",
    "code": "TCD"
  },
  "division": {
    "name": "民事",
    "code": "V"
  },
  "year": 100,
  "word": "除",
  "number": "618",
  "jcheck": "1",
  "reason": "除權判決",
  "content": "臺灣臺中地方法院民事判決              100年度除字第618號\n聲  請  人  賴朝慶\n上聲請人聲請宣告證券無效事件，本院判決如下：\n    主    文\n如附表所示之證券無效。\n訴訟費用新臺幣壹仟元由聲請人負擔。\n    理    由\n一、上開證券，經本院以100年度司催更字第2號公示催告。\n二、所定申報權利期間，已於100年6月18日屆滿，迄今無人申報\n    權利。\n三、依民事訴訟法第564條第1項判決如主文。\n中    華    民    國  100    年    8    月     9      日\n                  民事第三庭    法  官  林金灶\n上為正本證明係照原本作成。\n本判決不得上訴。\n中    華    民    國  100    年    8    月     9      日\n                                書記官  蕭榮峰\n┌──────────────────────────────────────────────┐\n│支票附表：                                                                100年度除字第618號│\n├──┬─────────┬─────────┬──────┬──────┬──────┬──┤\n│編號│  發    票    人  │  付    款    人  │ 發  票  日 │ 票 面 金 額│ 支 票 號 碼│備考│\n│    │                  │                  │            │ （新臺幣） │            │    │\n├──┼─────────┼─────────┼──────┼──────┼──────┼──┤\n│001 │台灣銀行台中分行  │台灣銀行台中分行  │99年1月21日 │652,306元   │FA0000000   │    │\n└──┴─────────┴─────────┴──────┴──────┴──────┴──┘",
  "structure": {
    "main": "如附表所示之證券無效。\n訴訟費用新臺幣壹仟元由聲請人負擔。",
    "reason": "一、上開證券，經本院以100年度司催更字第2號公示催告。\n二、所定申報權利期間，已於100年6月18日屆滿，迄今無人申報\n    權利。\n三、依民事訴訟法第564條第1項判決如主文。"
  },
  "search": "臺灣臺中地方法院民事判決100年度除字第618號聲請人賴朝慶上聲請人聲請宣告證券無效事件，本院判決如下：主文如附表所示之證券無效。訴訟費用新臺幣壹仟元由聲請人負擔。理由一、上開證券，經本院以100年度司催更字第2號公示催告。二、所定申報權利期間，已於100年6月18日屆滿，迄今無人申報權利。三、依民事訴訟法第564條第1項判決如主文。中華民國100年8月9日民事第三庭法官林金灶上為正本證明係照原本作成。本判決不得上訴。中華民國100年8月9日書記官蕭榮峰┌──────────────────────────────────────────────┐│支票附表：100年度除字第618號│├──┬─────────┬─────────┬──────┬──────┬──────┬──┤│編號│發票人│付款人│發票日│票面金額│支票號碼│備考││││││（新臺幣）│││├──┼─────────┼─────────┼──────┼──────┼──────┼──┤│001│台灣銀行台中分行│台灣銀行台中分行│99年1月21日│652,306元│FA0000000││└──┴─────────┴─────────┴──────┴──────┴──────┴──┘",
  "characters": {
    "judges": [
      "林金灶"
    ],
    "prosecutors": [

    ],
    "lawyers": [

    ],
    "clerks": [
      "蕭榮峰"
    ],
    "plaintiffs": [

    ],
    "defendants": [

    ],
    "prosecutor_office": [
      "賴朝慶"
    ],
    "creditors": [

    ],
    "debtors": [

    ],
    "judicial_associate_officer": [

    ]
  },
  "adjudged_at": "2011-08-09",
  "created_at": "2016-02-12 17:16:51",
  "updated_at": "2016-02-12 17:16:51"
}