{
  "identify": "TCD-100-中簡-1863-20110810-1",
  "court": {
    "name": "臺灣臺中地方法院",
    "code": "TCD"
  },
  "division": {
    "name": "刑事",
    "code": "M"
  },
  "year": 100,
  "word": "中簡",
  "number": "1863",
  "jcheck": "1",
  "reason": "賭博",
  "content": "臺灣臺中地方法院刑事簡易判決       100年度中簡字第1863號\n聲  請  人  臺灣臺中地方法院檢察署檢察官\n被      告  劉金炳\n上列被告因賭博案件，經檢察官聲請以簡易判決處刑（一百年度\n速偵字第三○八三號），本院判決如下：\n    主      文\n劉金炳意圖營利，聚眾賭博，處有期徒刑月，如易科罰金，以\n新臺幣壹仟元折算壹日。扣案之簽單陸張、傳真機壹臺，均沒收\n。\n    事實及理由\n一、本案除檢察官聲請簡易判決處刑書證據並所犯法條欄一第二\n    行「並有」後方補充「本院一百年度聲搜字第一九五八號搜\n    索票」外，其餘犯罪事實及證據均引用檢察官聲請簡易判決\n    處刑書（如附件）之記載。\n二、查扣案之簽單乃當場賭博之器具，依同法第二百六十六條第\n    二項規定，不問屬於犯人與否，沒收之，係採義務沒收主義\n    ，自應優先於採職權主義之同法第三十八條第一項第二款而\n    適用（最高法院八十七年度台非字第二○七號判決意旨參照\n    ），是扣案之簽單六張係當場賭博之器具，應依刑法第二百\n    六十六條第二項規定宣告沒收之。又扣案之傳真機一臺，為\n    被告劉金炳所有，供犯賭博罪所用之物，爰依刑法第三十八\n    條第一項第二款之規定宣告沒收之。\n三、依刑事訴訟法第四百四十九條第一項前段、第四百五十條第\n    一項、第四百五十四條第二項，刑法第二百六十六條第一項\n    前段、第二項、第二百六十八條、第五十五條、第四十一條\n    第一項前段、第三十八條第一項第二款，刑法施行法第一條\n    之一第一項、第二項前段，逕以簡易判決處如主文所示之刑\n    。\n如不服本判決，應於判決送達後十日內，向本院提出上訴狀（須\n附繕本）。\n中    華    民    國   100    年    8     月    10    日\n                    臺中簡易庭  法  官  黃裕仁\n上正本證明與原本無異。\n                                書記官  何惠文\n中    華    民    國   100    年    8     月    10    日\n附錄論罪科刑法條\n刑法第二百六十六條\n在公共場所或公眾得出入之場所賭博財物者，處一千元以下罰金\n，但以供人暫時娛樂之物為賭博者，不在此限。\n當場賭博之器具與在賭檯或兌換籌碼處之財物，不問屬於犯人與\n否，沒收之。\n刑法第二百六十八條\n意圖營利，供給賭博場所或聚眾賭博者，處三年以下有期徒刑，\n得併科三千元以下罰金。",
  "structure": {
    "main": "劉金炳意圖營利，聚眾賭博，處有期徒刑月，如易科罰金，以\n新臺幣壹仟元折算壹日。扣案之簽單陸張、傳真機壹臺，均沒收\n。",
    "fact": "一、本案除檢察官聲請簡易判決處刑書證據並所犯法條欄一第二\n    行「並有」後方補充「本院一百年度聲搜字第一九五八號搜\n    索票」外，其餘犯罪事實及證據均引用檢察官聲請簡易判決\n    處刑書（如附件）之記載。\n二、查扣案之簽單乃當場賭博之器具，依同法第二百六十六條第\n    二項規定，不問屬於犯人與否，沒收之，係採義務沒收主義\n    ，自應優先於採職權主義之同法第三十八條第一項第二款而\n    適用（最高法院八十七年度台非字第二○七號判決意旨參照\n    ），是扣案之簽單六張係當場賭博之器具，應依刑法第二百\n    六十六條第二項規定宣告沒收之。又扣案之傳真機一臺，為\n    被告劉金炳所有，供犯賭博罪所用之物，爰依刑法第三十八\n    條第一項第二款之規定宣告沒收之。\n三、依刑事訴訟法第四百四十九條第一項前段、第四百五十條第\n    一項、第四百五十四條第二項，刑法第二百六十六條第一項\n    前段、第二項、第二百六十八條、第五十五條、第四十一條\n    第一項前段、第三十八條第一項第二款，刑法施行法第一條\n    之一第一項、第二項前段，逕以簡易判決處如主文所示之刑\n    。\n如不服本判決，應於判決送達後十日內，向本院提出上訴狀（須\n附繕本）。",
    "reason": "一、本案除檢察官聲請簡易判決處刑書證據並所犯法條欄一第二\n    行「並有」後方補充「本院一百年度聲搜字第一九五八號搜\n    索票」外，其餘犯罪事實及證據均引用檢察官聲請簡易判決\n    處刑書（如附件）之記載。\n二、查扣案之簽單乃當場賭博之器具，依同法第二百六十六條第\n    二項規定，不問屬於犯人與否，沒收之，係採義務沒收主義\n    ，自應優先於採職權主義之同法第三十八條第一項第二款而\n    適用（最高法院八十七年度台非字第二○七號判決意旨參照\n    ），是扣案之簽單六張係當場賭博之器具，應依刑法第二百\n    六十六條第二項規定宣告沒收之。又扣案之傳真機一臺，為\n    被告劉金炳所有，供犯賭博罪所用之物，爰依刑法第三十八\n    條第一項第二款之規定宣告沒收之。\n三、依刑事訴訟法第四百四十九條第一項前段、第四百五十條第\n    一項、第四百五十四條第二項，刑法第二百六十六條第一項\n    前段、第二項、第二百六十八條、第五十五條、第四十一條\n    第一項前段、第三十八條第一項第二款，刑法施行法第一條\n    之一第一項、第二項前段，逕以簡易判決處如主文所示之刑\n    。\n如不服本判決，應於判決送達後十日內，向本院提出上訴狀（須\n附繕本）。"
  },
  "search": "臺灣臺中地方法院刑事簡易判決100年度中簡字第1863號聲請人臺灣臺中地方法院檢察署檢察官被告劉金炳上列被告因賭博案件，經檢察官聲請以簡易判決處刑（一百年度速偵字第三○八三號），本院判決如下：主文劉金炳意圖營利，聚眾賭博，處有期徒刑月，如易科罰金，以新臺幣壹仟元折算壹日。扣案之簽單陸張、傳真機壹臺，均沒收。事實及理由一、本案除檢察官聲請簡易判決處刑書證據並所犯法條欄一第二行「並有」後方補充「本院一百年度聲搜字第一九五八號搜索票」外，其餘犯罪事實及證據均引用檢察官聲請簡易判決處刑書（如附件）之記載。二、查扣案之簽單乃當場賭博之器具，依同法第二百六十六條第二項規定，不問屬於犯人與否，沒收之，係採義務沒收主義，自應優先於採職權主義之同法第三十八條第一項第二款而適用（最高法院八十七年度台非字第二○七號判決意旨參照），是扣案之簽單六張係當場賭博之器具，應依刑法第二百六十六條第二項規定宣告沒收之。又扣案之傳真機一臺，為被告劉金炳所有，供犯賭博罪所用之物，爰依刑法第三十八條第一項第二款之規定宣告沒收之。三、依刑事訴訟法第四百四十九條第一項前段、第四百五十條第一項、第四百五十四條第二項，刑法第二百六十六條第一項前段、第二項、第二百六十八條、第五十五條、第四十一條第一項前段、第三十八條第一項第二款，刑法施行法第一條之一第一項、第二項前段，逕以簡易判決處如主文所示之刑。如不服本判決，應於判決送達後十日內，向本院提出上訴狀（須附繕本）。中華民國100年8月10日臺中簡易庭法官黃裕仁上正本證明與原本無異。書記官何惠文中華民國100年8月10日附錄論罪科刑法條刑法第二百六十六條在公共場所或公眾得出入之場所賭博財物者，處一千元以下罰金，但以供人暫時娛樂之物為賭博者，不在此限。當場賭博之器具與在賭檯或兌換籌碼處之財物，不問屬於犯人與否，沒收之。刑法第二百六十八條意圖營利，供給賭博場所或聚眾賭博者，處三年以下有期徒刑，得併科三千元以下罰金。",
  "characters": {
    "judges": [
      "黃裕仁"
    ],
    "prosecutors": [

    ],
    "lawyers": [

    ],
    "clerks": [
      "何惠文"
    ],
    "plaintiffs": [

    ],
    "defendants": [
      "劉金炳"
    ],
    "prosecutor_office": [
      "臺灣臺中地方法院檢察署檢察官"
    ],
    "creditors": [

    ],
    "debtors": [

    ],
    "judicial_associate_officer": [

    ]
  },
  "adjudged_at": "2011-08-10",
  "created_at": "2016-02-12 17:34:47",
  "updated_at": "2016-02-12 17:34:47"
}