{
  "identify": "KSD-100-簡-5625-20111021-1",
  "court": {
    "name": "臺灣高雄地方法院",
    "code": "KSD"
  },
  "division": {
    "name": "刑事",
    "code": "M"
  },
  "year": 100,
  "word": "簡",
  "number": "5625",
  "jcheck": "1",
  "reason": "毒品危害防制條例",
  "content": "臺灣高雄地方法院刑事簡易判決         100年度簡字第5625號\n聲  請  人  臺灣高雄地方法院檢察署檢察官\n被      告  陳禮興\n上列被告因違反毒品危害防制條例案件，經檢察官聲請簡易判決\n處刑（100年度毒偵字第5103號），本院判決如下：\n    主      文\n陳禮興施用第二級毒品，累犯，處有期徒刑陸月，如易科罰金，\n以新臺幣壹仟元折算壹日。\n    事實及理由\n一、本件犯罪事實及證據，除犯罪事實欄一第6～7行：「復基於\n    施用第二級毒品甲基安非他命之犯意」之記載，應補充為：\n    「竟於前揭強制戒治執行完畢釋放後5 年內，復基於施用第\n    二級毒品甲基安非他命之犯意」之記載外，餘均引用檢察官\n    聲請簡易判決處刑書之記載（如附件）。\n二、核被告陳禮興所為，係犯毒品危害防制條例第10條第2 項之\n    施用第二級毒品罪。其施用第二級毒品前持有該毒品之低度\n    行為，應為其施用之高度行為所吸收，不另論罪。又被告有\n    如聲請簡易判決處刑書所載之犯罪科刑及執行情形，有臺灣\n    高等法院被告前案紀錄表1 份可查，其於受有期徒刑執行完\n    畢後，5 年內故意再犯本件有期徒刑以上之罪，為累犯，應\n    依刑法第47條第1項規定，加重其刑。茲審酌被告前因施用\n    毒品案件經觀察、勒戒、強制戒治後，猶未思積極戒毒，竟\n    再犯本件施用第二級毒品犯行，實應非難，而其曾有施用第\n    二級毒品之刑事前案，經法院判處有期徒刑3月確定，此品\n    行資料有上開前案紀錄表可佐，惟念施用毒品乃自戕行為，\n    對社會造成之危害尚非直接甚鉅，兼衡其自稱生活狀況為勉\n    持、智識程度為國中畢業及犯後坦承犯行等一切情狀，爰量\n    處如主文所示之刑，併諭知有期徒刑如易科罰金之折算標準\n    ，以資儆懲。\n三、依刑事訴訟法第449 條第1 項前段、第3 項、第454 條第 2\n    項，毒品危害防制條例第10條第2 項，刑法第11條前段、第\n    47條第1 項、第41條第1 項前段，逕以簡易判決處刑如主文\n    。\n四、如不服本判決，應自收受本判決書送達之日起10日內，向本\n    院提起上訴狀（須附繕本及表明上訴理由），上訴於本院管\n    轄之第二審地方法院合議庭。\n中    華    民    國    100   年    10    月    21    日\n                  高雄簡易庭  法  官  柯盛益\n以上正本，係照原本作成，證明與原本無異。\n中    華    民    國    100   年    10    月    21    日\n                              書記官  簡文清\n附錄本判決論罪科刑之法條全文：\n毒品危害防制條例第10條第2 項\n施用第二級毒品者，處 3 年以下有期徒刑。\n附件：\n臺灣高雄地方法院檢察署檢察官聲請簡易判決處刑書\n                                   100年度毒偵字第5103號\n    被    告  陳禮興  男  45歲（民國○○年○○月○○日生）\n                      住高雄市三民區○○○街13之2號\n                      居高雄市三民區○○○路653號15樓之4\n                      國民身分證統一編號：Ｚ000000000號\n                      (另案於法務部矯正署高雄看守所羈押\n                      中)\n上列被告因違反毒品危害防制條例案件，業經偵查終結，認為宜\n以簡易判決處刑，茲將犯罪事實及證據並所犯法條分敘如下：\n        犯罪事實\n一、陳禮興前因施用毒品案件，經送觀察、勒戒後，認有繼續施\n    用毒品之傾向，復送強制戒治，於民國96年11月26日執行完\n    畢釋放出所，並由本署檢察官以96年度戒毒偵字第417號為\n    不起訴處分確定。又因施用毒品案件，經臺灣高雄地方法院\n    以97年度審簡字第5911號判處有期徒刑3月確定，於98年5月\n    16日執行完畢。詎其猶不知悔改，復基於施用第二級毒品甲\n    基安非他命之犯意，於99年10月11日20時許，於高雄市三民\n    區○○○街13之2號住處，以將甲基安非他命置於玻璃球內\n    ，用火燒烤產生煙霧，以吸食煙霧之方式，施用第二級毒品\n    甲基安非他命1次。嗣於99年10月14日18時15分許，因其係\n    毒品列管人口，復經其同意，採集其尿液送檢驗，結果呈甲\n    基安非他命之陽性反應，始悉上情。\n二、案經高雄市政府警察局三民第二分局移送偵辦。\n             證據並所犯法條\n一、上開犯罪事實，業據被告陳禮興於本署偵詢中坦承不諱，且\n    其為警查獲當日所採集之尿液經檢驗結果，確呈甲基安非他\n    命之陽性反應，復有列管毒品人口尿液檢體採集送驗紀錄表\n    （檢體編號：VＺ00000000000號）、高雄市立凱旋醫院出具\n    之濫用藥物尿液檢驗報告（檢體編號：VＺ00000000000號）\n    各1紙附卷可稽。是被告之自白與事實相符，本件事證明確\n    ，被告犯嫌洵堪認定。\n二、核被告陳禮興所為，係犯毒品危害防制條例第10條第2項施\n    用第二級毒品罪嫌。其為施用而持有第二級毒品之低度行為\n    ，為施用第二級毒品之高度行為所吸收，不另論罪。又其曾\n    受有期徒刑執行完畢，有本署刑案資料查註紀錄表附卷可參\n    ，5年內故意再犯本件有期徒刑以上之罪，為累犯，請依刑\n    法第47條第1項之規定，加重其刑。\n三、依毒品危害防制條例第23條第2項、刑事訴訟法第451條第1\n    項聲請以簡易判決處刑。\n    此  致\n臺灣高雄地方法院\n中    華    民    國  100     年    8    月     25    日\n                              檢  察  官   楊 婉 莉",
  "structure": {
    "main": "陳禮興施用第二級毒品，累犯，處有期徒刑陸月，如易科罰金，\n以新臺幣壹仟元折算壹日。",
    "fact": "一、本件犯罪事實及證據，除犯罪事實欄一第6～7行：「復基於\n    施用第二級毒品甲基安非他命之犯意」之記載，應補充為：\n    「竟於前揭強制戒治執行完畢釋放後5 年內，復基於施用第\n    二級毒品甲基安非他命之犯意」之記載外，餘均引用檢察官\n    聲請簡易判決處刑書之記載（如附件）。\n二、核被告陳禮興所為，係犯毒品危害防制條例第10條第2 項之\n    施用第二級毒品罪。其施用第二級毒品前持有該毒品之低度\n    行為，應為其施用之高度行為所吸收，不另論罪。又被告有\n    如聲請簡易判決處刑書所載之犯罪科刑及執行情形，有臺灣\n    高等法院被告前案紀錄表1 份可查，其於受有期徒刑執行完\n    畢後，5 年內故意再犯本件有期徒刑以上之罪，為累犯，應\n    依刑法第47條第1項規定，加重其刑。茲審酌被告前因施用\n    毒品案件經觀察、勒戒、強制戒治後，猶未思積極戒毒，竟\n    再犯本件施用第二級毒品犯行，實應非難，而其曾有施用第\n    二級毒品之刑事前案，經法院判處有期徒刑3月確定，此品\n    行資料有上開前案紀錄表可佐，惟念施用毒品乃自戕行為，\n    對社會造成之危害尚非直接甚鉅，兼衡其自稱生活狀況為勉\n    持、智識程度為國中畢業及犯後坦承犯行等一切情狀，爰量\n    處如主文所示之刑，併諭知有期徒刑如易科罰金之折算標準\n    ，以資儆懲。\n三、依刑事訴訟法第449 條第1 項前段、第3 項、第454 條第 2\n    項，毒品危害防制條例第10條第2 項，刑法第11條前段、第\n    47條第1 項、第41條第1 項前段，逕以簡易判決處刑如主文\n    。\n四、如不服本判決，應自收受本判決書送達之日起10日內，向本\n    院提起上訴狀（須附繕本及表明上訴理由），上訴於本院管\n    轄之第二審地方法院合議庭。",
    "reason": "一、本件犯罪事實及證據，除犯罪事實欄一第6～7行：「復基於\n    施用第二級毒品甲基安非他命之犯意」之記載，應補充為：\n    「竟於前揭強制戒治執行完畢釋放後5 年內，復基於施用第\n    二級毒品甲基安非他命之犯意」之記載外，餘均引用檢察官\n    聲請簡易判決處刑書之記載（如附件）。\n二、核被告陳禮興所為，係犯毒品危害防制條例第10條第2 項之\n    施用第二級毒品罪。其施用第二級毒品前持有該毒品之低度\n    行為，應為其施用之高度行為所吸收，不另論罪。又被告有\n    如聲請簡易判決處刑書所載之犯罪科刑及執行情形，有臺灣\n    高等法院被告前案紀錄表1 份可查，其於受有期徒刑執行完\n    畢後，5 年內故意再犯本件有期徒刑以上之罪，為累犯，應\n    依刑法第47條第1項規定，加重其刑。茲審酌被告前因施用\n    毒品案件經觀察、勒戒、強制戒治後，猶未思積極戒毒，竟\n    再犯本件施用第二級毒品犯行，實應非難，而其曾有施用第\n    二級毒品之刑事前案，經法院判處有期徒刑3月確定，此品\n    行資料有上開前案紀錄表可佐，惟念施用毒品乃自戕行為，\n    對社會造成之危害尚非直接甚鉅，兼衡其自稱生活狀況為勉\n    持、智識程度為國中畢業及犯後坦承犯行等一切情狀，爰量\n    處如主文所示之刑，併諭知有期徒刑如易科罰金之折算標準\n    ，以資儆懲。\n三、依刑事訴訟法第449 條第1 項前段、第3 項、第454 條第 2\n    項，毒品危害防制條例第10條第2 項，刑法第11條前段、第\n    47條第1 項、第41條第1 項前段，逕以簡易判決處刑如主文\n    。\n四、如不服本判決，應自收受本判決書送達之日起10日內，向本\n    院提起上訴狀（須附繕本及表明上訴理由），上訴於本院管\n    轄之第二審地方法院合議庭。"
  },
  "search": "臺灣高雄地方法院刑事簡易判決100年度簡字第5625號聲請人臺灣高雄地方法院檢察署檢察官被告陳禮興上列被告因違反毒品危害防制條例案件，經檢察官聲請簡易判決處刑（100年度毒偵字第5103號），本院判決如下：主文陳禮興施用第二級毒品，累犯，處有期徒刑陸月，如易科罰金，以新臺幣壹仟元折算壹日。事實及理由一、本件犯罪事實及證據，除犯罪事實欄一第6～7行：「復基於施用第二級毒品甲基安非他命之犯意」之記載，應補充為：「竟於前揭強制戒治執行完畢釋放後5年內，復基於施用第二級毒品甲基安非他命之犯意」之記載外，餘均引用檢察官聲請簡易判決處刑書之記載（如附件）。二、核被告陳禮興所為，係犯毒品危害防制條例第10條第2項之施用第二級毒品罪。其施用第二級毒品前持有該毒品之低度行為，應為其施用之高度行為所吸收，不另論罪。又被告有如聲請簡易判決處刑書所載之犯罪科刑及執行情形，有臺灣高等法院被告前案紀錄表1份可查，其於受有期徒刑執行完畢後，5年內故意再犯本件有期徒刑以上之罪，為累犯，應依刑法第47條第1項規定，加重其刑。茲審酌被告前因施用毒品案件經觀察、勒戒、強制戒治後，猶未思積極戒毒，竟再犯本件施用第二級毒品犯行，實應非難，而其曾有施用第二級毒品之刑事前案，經法院判處有期徒刑3月確定，此品行資料有上開前案紀錄表可佐，惟念施用毒品乃自戕行為，對社會造成之危害尚非直接甚鉅，兼衡其自稱生活狀況為勉持、智識程度為國中畢業及犯後坦承犯行等一切情狀，爰量處如主文所示之刑，併諭知有期徒刑如易科罰金之折算標準，以資儆懲。三、依刑事訴訟法第449條第1項前段、第3項、第454條第2項，毒品危害防制條例第10條第2項，刑法第11條前段、第47條第1項、第41條第1項前段，逕以簡易判決處刑如主文。四、如不服本判決，應自收受本判決書送達之日起10日內，向本院提起上訴狀（須附繕本及表明上訴理由），上訴於本院管轄之第二審地方法院合議庭。中華民國100年10月21日高雄簡易庭法官柯盛益以上正本，係照原本作成，證明與原本無異。中華民國100年10月21日書記官簡文清附錄本判決論罪科刑之法條全文：毒品危害防制條例第10條第2項施用第二級毒品者，處3年以下有期徒刑。附件：臺灣高雄地方法院檢察署檢察官聲請簡易判決處刑書100年度毒偵字第5103號被告陳禮興男45歲（民國○○年○○月○○日生）住高雄市三民區○○○街13之2號居高雄市三民區○○○路653號15樓之4國民身分證統一編號：Ｚ000000000號(另案於法務部矯正署高雄看守所羈押中)上列被告因違反毒品危害防制條例案件，業經偵查終結，認為宜以簡易判決處刑，茲將犯罪事實及證據並所犯法條分敘如下：犯罪事實一、陳禮興前因施用毒品案件，經送觀察、勒戒後，認有繼續施用毒品之傾向，復送強制戒治，於民國96年11月26日執行完畢釋放出所，並由本署檢察官以96年度戒毒偵字第417號為不起訴處分確定。又因施用毒品案件，經臺灣高雄地方法院以97年度審簡字第5911號判處有期徒刑3月確定，於98年5月16日執行完畢。詎其猶不知悔改，復基於施用第二級毒品甲基安非他命之犯意，於99年10月11日20時許，於高雄市三民區○○○街13之2號住處，以將甲基安非他命置於玻璃球內，用火燒烤產生煙霧，以吸食煙霧之方式，施用第二級毒品甲基安非他命1次。嗣於99年10月14日18時15分許，因其係毒品列管人口，復經其同意，採集其尿液送檢驗，結果呈甲基安非他命之陽性反應，始悉上情。二、案經高雄市政府警察局三民第二分局移送偵辦。證據並所犯法條一、上開犯罪事實，業據被告陳禮興於本署偵詢中坦承不諱，且其為警查獲當日所採集之尿液經檢驗結果，確呈甲基安非他命之陽性反應，復有列管毒品人口尿液檢體採集送驗紀錄表（檢體編號：VＺ00000000000號）、高雄市立凱旋醫院出具之濫用藥物尿液檢驗報告（檢體編號：VＺ00000000000號）各1紙附卷可稽。是被告之自白與事實相符，本件事證明確，被告犯嫌洵堪認定。二、核被告陳禮興所為，係犯毒品危害防制條例第10條第2項施用第二級毒品罪嫌。其為施用而持有第二級毒品之低度行為，為施用第二級毒品之高度行為所吸收，不另論罪。又其曾受有期徒刑執行完畢，有本署刑案資料查註紀錄表附卷可參，5年內故意再犯本件有期徒刑以上之罪，為累犯，請依刑法第47條第1項之規定，加重其刑。三、依毒品危害防制條例第23條第2項、刑事訴訟法第451條第1項聲請以簡易判決處刑。此致臺灣高雄地方法院中華民國100年8月25日檢察官楊婉莉",
  "characters": {
    "judges": [
      "柯盛益"
    ],
    "prosecutors": [

    ],
    "lawyers": [

    ],
    "clerks": [
      "簡文清"
    ],
    "plaintiffs": [

    ],
    "defendants": [
      "陳禮興",
      "陳禮興  男  45歲（民國○○年○○月○○日生）"
    ],
    "prosecutor_office": [
      "臺灣高雄地方法院檢察署檢察官"
    ],
    "creditors": [

    ],
    "debtors": [

    ],
    "judicial_associate_officer": [

    ]
  },
  "adjudged_at": "2011-10-21",
  "created_at": "2016-02-14 07:54:40",
  "updated_at": "2016-02-14 07:54:40"
}