{
  "identify": "MLD-100-苗交簡-962-20111020-1",
  "court": {
    "name": "臺灣苗栗地方法院",
    "code": "MLD"
  },
  "division": {
    "name": "刑事",
    "code": "M"
  },
  "year": 100,
  "word": "苗交簡",
  "number": "962",
  "jcheck": "1",
  "reason": "公共危險",
  "content": "臺灣苗栗地方法院刑事簡易判決      100年度苗交簡字第962號\n聲  請  人  臺灣苗栗地方法院檢察署檢察官\n被      告  王進國\n上列被告因公共危險案件，經檢察官聲請以簡易判決處刑（100\n年度偵字第4963號），本院判決如下：\n    主  文\n王進國犯不能安全駕駛動力交通工具罪，處罰金新臺幣柒萬元，\n如易服勞役，以新臺幣壹仟元折算壹日。\n    事實及理由\n一、本件犯罪事實及證據均引用檢察官聲請簡易判決處刑書內容\n    之記載（如附件）。\n二、應適用之法條：\n   （一）刑事訴訟法第449 條第1 項、第454 條第1、2 項。\n   （二）刑法第185條之3、第42條第3 項前段。\n   （三）刑法施行法第1 條之1 。\n三、如不服本簡易判決，得自判決送達之日起十日內，向本院提\n    起上訴。\n中    華    民    國  100     年    10     月    20    日\n                 苗栗簡易庭    法  官  林靜雯\n本件正本證明與原本無異。\n如不服本判決應於收受判決後10日內向本院提出上訴書狀，並應\n敘述具體理由。其未敘述上訴理由者，應於上訴期間屆滿後20日\n內向本院補提理由書（均須附繕本）「切勿逕送上級法院」。\n                               書記官  劉千瑄\n中    華    民    國   100    年    10     月    20    日\n附錄本判決論罪科刑法條：\n中華民國刑法第185條之3：\n服用毒品、麻醉藥品、酒類或其他相類之物，不能安全駕駛動力\n交通工具而駕駛者，處1 年以下有期徒刑、拘役或科或併科15萬\n元以下罰金。\n附件：\n臺灣苗栗地方法院檢察署檢察官聲請簡易判決處刑書\n                                     100年度偵字第4963號\n    被      告  王進國  男  52歲（民國○○年○月○○日生）\n                        住苗栗縣竹南鎮○○里○鄰○○街16\n                          號\n                        國民身分證統一編號：Ｚ000000000號\n上列被告因公共危險案件，業經偵查終結，認宜聲請簡易判決處\n刑，茲將犯罪事實及證據並所犯法條分敘如下：\n        犯罪事實\n一、王進國自民國100年8月2日14時許起至同日16時許止，在苗\n    栗縣頭份鎮○○路長榮小吃店飲用啤酒後，已達不能安全駕\n    駛動力交通工具之程度，竟隨即騎乘車號FN6-979號重型機\n    車自上開小吃店出發，欲返回苗栗縣竹南鎮○○里○鄰○○\n    街16號住處。嗣於同日16時19分許，行經苗栗縣竹南鎮○市\n    路與公教路口時，為警攔檢發現有飲酒跡象，並測試其呼氣\n    酒精濃度含量達每公升0.84毫克而查獲。\n二、案經苗栗縣警察局移送偵辦。\n        證據並所犯法條\n一、證據：（一）被告王進國之自白，（二）酒精測定紀錄表、\n    刑法第185條之3案件測試觀察紀錄表、汽機車駕駛人酒後生\n    理協調平衡檢測紀錄表各1份及舉發違反道路交通管理事件\n    通知單1聯。\n二、核被告所為，係犯刑法第185條之3服用酒類不能安全駕駛動\n    力交通工具罪嫌。\n三、依刑事訴訟法第451條第1項聲請逕以簡易判決處刑。\n    此    致\n臺灣苗栗地方法院\n中    華    民    國  100    年    9    月    26    日\n                              檢察官  王兆琳\n本件證明與原本無異\n中    華    民    國  100    年    10   月    3     日\n                              書記官  張穎文\n附錄參考法條：\n刑法第185條之3\n服用毒品、麻醉藥品、酒類或其他相類之物，不能安全駕駛動力\n交通工具而駕駛者，處 1 年以下有期徒刑、拘役或科或併科 15\n萬元以下罰金。",
  "structure": {
    "main": "王進國犯不能安全駕駛動力交通工具罪，處罰金新臺幣柒萬元，\n如易服勞役，以新臺幣壹仟元折算壹日。",
    "fact": "一、本件犯罪事實及證據均引用檢察官聲請簡易判決處刑書內容\n    之記載（如附件）。\n二、應適用之法條：\n   （一）刑事訴訟法第449 條第1 項、第454 條第1、2 項。\n   （二）刑法第185條之3、第42條第3 項前段。\n   （三）刑法施行法第1 條之1 。\n三、如不服本簡易判決，得自判決送達之日起十日內，向本院提\n    起上訴。",
    "reason": "一、本件犯罪事實及證據均引用檢察官聲請簡易判決處刑書內容\n    之記載（如附件）。\n二、應適用之法條：\n   （一）刑事訴訟法第449 條第1 項、第454 條第1、2 項。\n   （二）刑法第185條之3、第42條第3 項前段。\n   （三）刑法施行法第1 條之1 。\n三、如不服本簡易判決，得自判決送達之日起十日內，向本院提\n    起上訴。"
  },
  "search": "臺灣苗栗地方法院刑事簡易判決100年度苗交簡字第962號聲請人臺灣苗栗地方法院檢察署檢察官被告王進國上列被告因公共危險案件，經檢察官聲請以簡易判決處刑（100年度偵字第4963號），本院判決如下：主文王進國犯不能安全駕駛動力交通工具罪，處罰金新臺幣柒萬元，如易服勞役，以新臺幣壹仟元折算壹日。事實及理由一、本件犯罪事實及證據均引用檢察官聲請簡易判決處刑書內容之記載（如附件）。二、應適用之法條：（一）刑事訴訟法第449條第1項、第454條第1、2項。（二）刑法第185條之3、第42條第3項前段。（三）刑法施行法第1條之1。三、如不服本簡易判決，得自判決送達之日起十日內，向本院提起上訴。中華民國100年10月20日苗栗簡易庭法官林靜雯本件正本證明與原本無異。如不服本判決應於收受判決後10日內向本院提出上訴書狀，並應敘述具體理由。其未敘述上訴理由者，應於上訴期間屆滿後20日內向本院補提理由書（均須附繕本）「切勿逕送上級法院」。書記官劉千瑄中華民國100年10月20日附錄本判決論罪科刑法條：中華民國刑法第185條之3：服用毒品、麻醉藥品、酒類或其他相類之物，不能安全駕駛動力交通工具而駕駛者，處1年以下有期徒刑、拘役或科或併科15萬元以下罰金。附件：臺灣苗栗地方法院檢察署檢察官聲請簡易判決處刑書100年度偵字第4963號被告王進國男52歲（民國○○年○月○○日生）住苗栗縣竹南鎮○○里○鄰○○街16號國民身分證統一編號：Ｚ000000000號上列被告因公共危險案件，業經偵查終結，認宜聲請簡易判決處刑，茲將犯罪事實及證據並所犯法條分敘如下：犯罪事實一、王進國自民國100年8月2日14時許起至同日16時許止，在苗栗縣頭份鎮○○路長榮小吃店飲用啤酒後，已達不能安全駕駛動力交通工具之程度，竟隨即騎乘車號FN6-979號重型機車自上開小吃店出發，欲返回苗栗縣竹南鎮○○里○鄰○○街16號住處。嗣於同日16時19分許，行經苗栗縣竹南鎮○市路與公教路口時，為警攔檢發現有飲酒跡象，並測試其呼氣酒精濃度含量達每公升0.84毫克而查獲。二、案經苗栗縣警察局移送偵辦。證據並所犯法條一、證據：（一）被告王進國之自白，（二）酒精測定紀錄表、刑法第185條之3案件測試觀察紀錄表、汽機車駕駛人酒後生理協調平衡檢測紀錄表各1份及舉發違反道路交通管理事件通知單1聯。二、核被告所為，係犯刑法第185條之3服用酒類不能安全駕駛動力交通工具罪嫌。三、依刑事訴訟法第451條第1項聲請逕以簡易判決處刑。此致臺灣苗栗地方法院中華民國100年9月26日檢察官王兆琳本件證明與原本無異中華民國100年10月3日書記官張穎文附錄參考法條：刑法第185條之3服用毒品、麻醉藥品、酒類或其他相類之物，不能安全駕駛動力交通工具而駕駛者，處1年以下有期徒刑、拘役或科或併科15萬元以下罰金。",
  "characters": {
    "judges": [
      "林靜雯"
    ],
    "prosecutors": [

    ],
    "lawyers": [

    ],
    "clerks": [
      "劉千瑄",
      "張穎文"
    ],
    "plaintiffs": [

    ],
    "defendants": [
      "王進國",
      "王進國  男  52歲（民國○○年○月○○日生）"
    ],
    "prosecutor_office": [
      "臺灣苗栗地方法院檢察署檢察官"
    ],
    "creditors": [

    ],
    "debtors": [

    ],
    "judicial_associate_officer": [

    ]
  },
  "adjudged_at": "2011-10-20",
  "created_at": "2016-02-14 07:44:14",
  "updated_at": "2016-02-14 07:44:14"
}