{
  "identify": "TPH-100-重上更(二)-65-20111020-1",
  "court": {
    "name": "臺灣高等法院",
    "code": "TPH"
  },
  "division": {
    "name": "刑事",
    "code": "M"
  },
  "year": 100,
  "word": "重上更(二)",
  "number": "65",
  "jcheck": "1",
  "reason": "偽造文書等",
  "content": "臺灣高等法院刑事判決           100年度重上更(二)字第65號\n上  訴  人\n即  被  告  陳任寬\n選任辯護人  鍾永盛律師\n            黃當庭律師\n上列上訴人因偽造文書等案件，不服臺灣士林地方法院89年度訴\n字第164 號，中華民國91年10月25日第一審判決（起訴案號：臺\n灣士林地方法院檢察署88年度偵字第12021 號、89年度偵字第63\n9 號），提起上訴，本院判決後，經最高法院第二次發回更審，\n判決如下：\n    主  文\n原判決關於陳任寬部分撤銷。\n陳任寬共同連續犯行使偽造私文書罪，處有期徒刑壹年玖月。扣\n案如附表五所示之偽造信用卡陸張、附表五編號五所示偽造之「\n陳憲欽」署押壹枚、如附表三所示簽帳單上偽造之署押各壹枚（\n留存於商店存根或存根副本聯上）及姓名身分證號碼對照表壹紙\n，均沒收。\n    事  實\n一、陳任寬因急需金錢週轉票款，而明知以真實姓名年籍不詳，\n    綽號「昌哥」之成年男子（下稱「昌哥」）為首之偽卡集團\n    係使用偽造信用卡購買財物以謀利，其為能賺取金錢，竟仍\n    與「昌哥」及真實姓名年籍不詳，綽號「阿強」之成年男子\n    （下稱「阿強」）等人基於行使偽造信用卡、偽造署押、行\n    使偽造簽帳單、詐欺取財之概括犯意聯絡，由陳任寬與「阿\n    強」等人依「昌哥」指示，持如附表一編號一至一一四五號\n    所示燒錄他人真正內碼之偽造信用卡，於附表一編號一至一\n    一四五號所示之時間，前往附表一編號一至一一四五號所示\n    之「震旦行股份有限公司」（下稱震旦行）臺北市區各分店\n    ，刷卡購買行動電話等通信器材。陳任寬與「昌哥」、「阿\n    強」等人復與震旦行之員工洪清芬（任該公司「區輔導」，\n    經本院上訴審判處有期徒刑1 年，減為有期徒刑6 月，於更\n    一審撤回上訴後確定）基於犯意聯絡，先後於附表一編號一\n    至一一四五號所示之時間、地點，而與林慶和（任「雙連店\n    店長」，經原審判處有期徒刑1 年確定）、許靜怡（任「雙\n    連店店員」，經原審判處有期徒刑8 月確定）、高梅峰（任\n    「雙連店店員」，未據起訴）、蘇曉倩（任「吉林店店長」\n    ，經原審判處有期徒刑6 月確定）、陳辜韋（任「吉林店店\n    員」，經本院上訴審判處有期徒刑7 月，減為有期徒刑3 月\n    又15日確定）、張建平（任「吉林店店員」，未據起訴）、\n    王冠文（任「延平二店店長」，經本院上訴審判處有期徒刑\n    7 月，減為有期徒刑3 月又15日確定）、曾雅琪（任「延平\n    二店店員」，未據起訴）、邱榕濱（任「延平二店店員」，\n    未據起訴）、周榮輝（任「迪化店店長」，經原審判處有期\n    徒刑6 月確定）、劉志宏（任「迪化店店員」，經本院上訴\n    審判處有期徒刑7 月，減為有期徒刑3 月又15日確定）、古\n    紹龍（任「迪化店店員」，經本院上訴審判處有期徒刑7 月\n    ，減為有期徒刑3 月又15日確定）、陳蕙英（任「長安店店\n    長」，經本院上訴審判處有期徒刑6 月，減為有期徒刑3 月\n    確定）、彭毓璋（任「長安店店員」，未據起訴）、吳榮崇\n    （任「長安店店員」，未據起訴）、林介士（任「長安二店\n    店長」，經本院上訴審判處有期徒刑7 月，減為有期徒刑3\n    月又15日確定）、李孟廉（任「長安二店店員」，未據起訴\n    ）、彭婉綾（任「長安二店店員」，未據起訴）、黃文彬（\n    任「民權店店長」，經本院上訴審判處有期徒刑5 月，減為\n    有期徒刑2 月又15日確定）、陳宗宏（任「民權店店員」，\n    經本院上訴審判處有期徒刑6 月，減為有期徒刑3 月確定）\n    、張賀鈞（任「民權二店店長」，經本院上訴審判處有期徒\n    刑7 月，減為有期徒刑3 月又15日確定）、黃子虔（任「民\n    權二店店員」，未據起訴）、呂佳峰（任「民權二店店員」\n    ，未據起訴）、李尉仁（任「長春店店長」，經本院上訴審\n    判處有期徒刑7 月，減為有期徒刑3 月又15日確定）、周俊\n    雄（任「長春店店員」，未據起訴）、黃筱苓（任「長春店\n    店員」，未據起訴）、黃耀賢（任「民生二店店員」，經本\n    院上訴審判處有期徒刑6 月，減為有期徒刑3 月確定）等人\n    ，分別就其等各自任職分店部分（詳如附表四所示），基於\n    行使偽造信用卡、偽造署押、行使偽造簽帳單、詐欺取財之\n    概括犯意；而由陳任寬與「阿強」等人擔任「刷手」，持「\n    昌哥」所交付、附表一編號一至一一四五號所示、內已燒錄\n    自他人真正信用卡側錄內碼之偽造信用卡刷卡，並於刷卡通\n    過後，再依「昌哥」所交付之姓名身分證號對照表上之記載\n    ，在簽帳單上以複寫方式1 次偽造如附表三所示之署押1 式\n    3 枚（第一聯顧客存根，第二聯商店存根，第三聯存根副本\n    ），並由洪清芬事先以電話或親自到場指示林慶和、蘇曉倩\n    、陳辜韋、王冠文、周榮輝、劉志宏、古紹龍、陳蕙英、林\n    介士、黃文彬、陳宗宏等人及無參與犯罪意思之丁鳳琴、張\n    世昇（均經本院更一審判決無罪確定），分別於如附表一所\n    示之時間、地點，配合陳任寬與「阿強」等人刷卡結帳，或\n    由林慶和、許靜怡、高梅峰、蘇曉倩、陳辜韋、王冠文、周\n    榮輝、劉志宏、古紹龍、陳蕙英、林介士、黃文彬、陳宗宏\n    、張賀鈞、李尉仁、黃耀賢等人自行於如附表一所示之時間\n    、地點配合陳任寬與「阿強」等人刷卡結帳，並於刷卡通過\n    後交付如附表二所示刷卡金額之行動電話等通信器材予陳任\n    寬與「阿強」等人，足以生損害於震旦行、如附表三所示之\n    發卡銀行及如附表三所示被偽造署押之人（各分店所涉犯行\n    詳如附表四所示）。\n二、嗣經警於民國88年11月24日晚上7 時許，在臺北市○○○路\n    80號之震旦行雙連店內當場查獲陳任寬，並扣得「昌哥」所\n    交付、供其刷卡使用、如附表五所示之偽造信用卡共6 張、\n    姓名身分證號碼對照表1 紙，以及已完成刷卡之簽帳單3 紙\n    、刷卡所得之行動電話4 支（MOTOROLA牌V3699 型、MOTORO\n    LA牌V2088 型、NOKIA 牌3210型、易利信牌T28 型）；再依\n    其供述於同日晚間9 時許前往臺北市○○路132 號震旦行吉\n    林店，扣得簽帳單2 紙、刷卡所得之行動電話2 支（MOTORO\n    LA牌3688型、NOKIA 牌3210型）、無線話機1 台（國際牌TC\n    M416型）、透明皮套1 個（3210）、桌上型電子計算機1 台\n    、液晶充電器1 台（3210）及大哥大吊飾2 個，而循線查獲\n    上情。\n三、案經內政部警政署刑事警察局移送臺灣士林地方法院檢察署\n    檢察官偵查起訴。\n    理  由\n壹、證據能力方面：\n    按被告以外之人於審判外之陳述，雖不符刑事訴訟法第159\n    條之1 至第159 條之4 之規定，而經當事人於審判程序同意\n    作為證據，法院審酌該言詞陳述或書面陳述作成時之情況，\n    認為適當者，亦得為證據；當事人、代理人或辯護人於法院\n    調查證據時，知有刑事訴訟法第159 條第1 項不得為證據之\n    情形，而未於言詞辯論終結前聲明異議者，視為有前項之同\n    意，刑事訴訟法第159條之5第1項、第2項分別定有明文。立\n    法意旨在於傳聞證據未經當事人之反對詰問予以核實，原則\n    上先予排除。惟若當事人已放棄反對詰問權，於審判程序中\n    表明同意該等傳聞證據可作為證據；或於言詞辯論終結前未\n    聲明異議，基於尊重當事人對傳聞證據之處分權，及證據資\n    料愈豐富，愈有助於真實發見之理念，且強化言詞辯論主義\n    ，使訴訟程序得以順暢進行，上開傳聞證據亦均具有證據能\n    力。經查，本件以下所引用之被告以外之人於審判外之供述\n    或非供述證據，因檢察官、被告陳任寬及其選任辯護人已於\n    本院準備程序就證據能力均表示沒意見（見本院卷第27-32\n    頁），且迄至言詞辯論終結前均未聲明異議，而本院審酌上\n    開供述或非供述等證據資料製作時之情況，無不當取供及證\n    明力明顯過低之瑕疵，認以之作為證據應屬適當，揆諸前開\n    規定，本院認前揭證據資料有證據能力，合先敘明。\n貳、認定上訴人即被告犯罪事實所憑之證據及理由：\n一、訊據被告陳任寬對於上揭事實坦白承認，惟辯以：附表一所\n    載有很多之消費並非由伊前往刷卡，不應認定伊為共犯云云\n    。經查：\n（一）上揭事實業據被告於偵查、原審及本院歷審審理時均坦承\n      不諱，並核與證人即共犯林慶和、許靜怡、蘇曉倩、陳辜\n      韋、王冠文、周榮輝、劉志宏、古紹龍、陳蕙英、林介士\n      、陳宗宏、李尉仁等人分別於警詢、本院上訴審審理時所\n      證述被告於其等所任職之震旦行分店與其等、原同案被告\n      洪清芬共同參與上開犯行，而持偽造信用卡前來各分店刷\n      卡消費等情一致（見89年度偵字第639 號偵查卷一第45頁\n      、第57-59 頁、第176-178 頁、第127- 129頁、第60 -62\n      頁、第76-78 頁、第73-75 頁、第146- 148頁、第160-16\n      1 頁、第134-135 頁、第105-107 頁；卷二第47-48 頁；\n      本院上訴審卷二第225-227 頁、第146-150 頁、第151-15\n      3 頁、第186-187 頁；卷三第6-7 頁、第39-41 頁），且\n      由證人即原同案被告丁鳳琴、張世昇分別於本院上訴審審\n      理時就原同案被告洪清芬確曾要求其等協助被告為行使偽\n      造信用卡及詐欺取財等犯行一節結證述明確在卷（見本院\n      上訴審卷二第183-184 頁、卷三第4-5 頁）。再經原審當\n      庭勘驗證人即民權店店員陳宗宏所提供之民權店錄影帶製\n      有勘驗筆錄（見原審卷二第135 頁、第185 頁至第188 頁\n      ）、當庭勘驗證人即吉林店店員陳辜韋所提供之吉林店錄\n      影帶製有勘驗筆錄（見原審卷三第281 頁至第283 頁）。\n      此外，復有上開「昌哥」所交付、供被告刷卡使用、如附\n      表五所示之偽造信用卡共6 張、姓名身分證號碼對照表1\n      紙、以及已完成刷卡之簽帳單、刷卡所得之行動電話6 台\n      （MOTOROLA牌V3699 型、MOTOROLA牌V2088 型、NOKIA 牌\n      3210型、易利信牌T28 型、MOTOROLA牌3688型、NOKIA 牌\n      3210型）、無線話機1 台（國際牌TCM416）、透明皮套1\n      個（3210）、桌上型電子計算機1 台、液晶充電器1 台（\n      3210）及大哥大吊飾2 個等物扣案為證，及刷卡消費紀錄\n      在卷可稽。足認被告上開任意性自白，核與事實相符，可\n      以採取。\n（二）至被告雖辯以：附表一所載有很多之消費並非由伊前往刷\n      卡，不應認定伊為共犯云云。然按共同實施犯罪行為之人\n      ，在合同意思範圍以內，各自分擔犯罪行為之一部，相互\n      利用他人之行為，以達其犯罪之目的者，即應對於全部所\n      發生之結果，共同負責（最高法院28年上字第3110號判例\n      同此意旨）。而據前述。被告既已分別與原同案被告洪清\n      芬、林慶和、許靜怡、蘇曉倩、陳辜韋、王冠文、曾雅琪\n      、周榮輝、劉志宏、古紹龍、陳蕙英、林介士、陳宗宏、\n      張賀鈞、李尉仁、黃耀賢等人在偽造如附表三所示之署押\n      之意思範圍以內，各自分擔犯罪行為之一部，並相互利用\n      他人之行為，以達其犯罪之目的者，被告即應對於全部所\n      發生之結果，縱附表三簽帳單上偽造之署押，並非全為被\n      告所親簽，然其基於與「昌哥」為首之集團共同犯罪之意\n      思，相互分擔部分之行為，仍應就全部犯罪事實共負責任\n      。從而，被告所辯上情自非可取。\n（三）綜上所述，本件事證明確，被告上揭犯行，足可認定，應\n      依法論科。\n二、新舊法之比較與適用：\n    被告陳任寬行為後，刑法部分條文業於94年1 月7 日修正，\n    94年2 月2 日公布，95年7 月1 日施行，現行刑法第2 條第\n    1 項規定：「行為後法律有變更者，適用行為時之法律，但\n    行為後之法律有利於行為人者，適用最有利於行為人之法律\n    。」上開規定乃與刑法第1 條罪刑法定主義契合，而貫徹法\n    律禁止溯及既往原則，係規範行為後法律變更所生新舊法律\n    比較適用之準據法，是刑法第2 條本身雖經修正，但刑法第\n    2 條既屬適用法律之準據法，本身尚無比較新舊法之問題，\n    應一律適用裁判時之現行刑法第2 條規定以決定適用之刑罰\n    法律。又本次刑法修正之比較新舊法，應就罪刑有關之共犯\n    、未遂犯、想像競合犯、牽連犯、連續犯、結合犯、以及累\n    犯加重、自首減輕暨其他法定加減原因（如身分加減）與加\n    減例等一切情形，綜其全部罪刑之結果而為比較，最高法院\n    95年5 月23日95年度第8 次刑庭會議決議可資參照。又法院\n    裁判時已在新法施行之後，如新舊法條文之內容有所修正，\n    除其修正係無關乎處罰之輕重或要件內容之不同，而僅為其\n    他純文字之修正，非該條所指之法律有變更者，可毋庸依該\n    規定為新舊法之比較，而應依一般法律適用原則，適用裁判\n    時法外，即應適用新法第2 條第1 項之規定，為「從舊從輕\n    」之比較。經查：\n（一）修正前刑法第28條規定：「二人以上共同實施犯罪之行為\n      者，皆為正犯」，修正後刑法第28條則規定：「二人以上\n      共同實行犯罪之行為者，皆為正犯」，其中「實施」一語\n      ，涵蓋陰謀、預備、著手及實行之概念在內，其範圍較廣\n      ；而「實行」則著重於直接從事構成犯罪事實之行為，其\n      範圍較狹，是修正後刑法共同正犯之範圍已有限縮，共同\n      正犯之範圍既因此而有變動，自屬犯罪後法律有變更，而\n      非僅屬純文字修正，應有新舊法比較適用之問題（參照最\n      高法院96年度臺上字第3773號判決意旨），被告就上開犯\n      罪行為，依新舊法均成立共同正犯，適用新法並無較有利\n      於被告。\n（二）刑法第33條第5 款業已修正為：「主刑之種類如下：五、\n      罰金：新臺幣一千元以上，以百元計算之」，已將法定刑\n      罰金之最低額提高為新臺幣一千元，與該條文修正前規定\n      罰金最低額為銀元一元，而依現行法規所定貨幣單位折算\n      新臺幣條例第2 條，換算為新臺幣僅為新臺幣三元。因此\n      ，比較上述修正前、後之刑罰法律，自以被告行為時關於\n      科處罰金刑之法律較有利於被告。\n（三）修正後刑法業已刪除第55條後段關於牽連犯之規定，此刪\n      除雖非犯罪構成要件之變更，但顯已影響行為人刑罰之法\n      律效果，自屬法律有變更，經比較新、舊法結果，以修正\n      前第55條後段牽連犯之規定，將被告之數行為以一罪論，\n      顯較有利於被告。\n（四）刑法第56條連續犯之規定，業經修正刪除，此刪除雖非犯\n      罪構成要件之變更，但顯已影響行為人刑罰之法律效果，\n      自屬法律有變更，應依新法第2 條第1 項規定為新舊法之\n      比較（最高法院95年度第8 次刑事庭會議決議參照）。新\n      法修正施行後，被告上開先後多次行使偽造準私文書、行\n      使偽造私文書及詐欺取財之犯行，均須分論併罰，是比較\n      新舊法之結果，應適用較有利於被告之行為時法律即修正\n      前刑法第56條規定，各依連續犯規定以一罪論。\n（五）再被告陳任寬等人行為後，刑法增訂第201 條之1 已於90\n      年6 月20日公布施行，增訂第201 條之1 「意圖供行使之\n      用，而偽造、變造信用卡、金融卡、儲值卡或其他相類作\n      為簽帳、提款、轉帳或支付工具之電磁紀錄物之用者，處\n      一年以上七年以下有期徒刑，得併科三萬元以下罰金。」\n      、「行使偽造、變造之信用卡、金融卡、儲值卡或其他相\n      類作為簽帳、提款、轉帳或支付工具之電磁紀錄物之用，\n      而收受或交付於人者，處五年以下有期徒刑，得併科三萬\n      元以下罰金。」與前開從一重處斷之刑法第216 條、第21\n      0 條之行使偽造私文書罪，處五年以下有期徒刑；比較新\n      舊法之適用，應以刑法第216 條、第210 條之規定顯較有\n      利於被告，依刑法第2 條第1 項前段，自應適用舊法。\n（六）經綜合法律修正前後之整體比較，揆諸前揭最高法院決議\n      及修正後刑法第2 條第1 項之「從舊從輕」原則，適用修\n      正前之刑罰法律，對被告較為有利，自應整體適用修正前\n      刑法之相關規定。\n三、論罪科刑部分：\n（一）按信用卡係表示持卡人與發卡銀行間成立消費付款委託契\n      約之電磁紀錄，屬刑法第220 條規定所稱之準私文書。被\n      告等人就於附表二所載時、地，行使偽造信用卡之所為，\n      均係犯刑法第216 條、第220 條、第210 條行使偽造準私\n      文書罪。\n（二）又簽帳單係以文字為一定之意思表示，具有存續性，且屬\n      法律上有關係之事項，為文書之一種，並為私人製作之文\n      書。被告等人於附表三所示時、地，於簽帳單私文書上偽\n      造署押並持以行使之所為，均係犯刑法第216 條、第210\n      條行使偽造私文書罪。至附表二所示通過刷卡，然署押不\n      詳之部分，雖經原審於90年7 月23日裁定命震旦行提出供\n      扣押（見原審卷二第271 頁），而震旦行表示因90年間之\n      納莉颱風淹水、公司多次搬遷，致留存之簽帳單等相關資\n      料均因均已不知去向，有刑事陳報狀1 紙在卷可考（見原\n      審卷四第213 頁），故無從認定署押是否存在，基於「罪\n      疑利益歸於被告」之原則，自應為被告有利之認定，而認\n      此部分被告與共犯並無偽造署押之犯行，附此說明。再被\n      告等人偽造署押為偽造私文書之部分行為，偽造私文書後\n      持以行使，偽造私文書之低度行為，應為行使之高度行為\n      所吸收，均不另論罪。\n（三）被告於附表一所示時、地，共同持偽造信用卡刷卡購物之\n      所為，均係犯刑法第339 條第1 項之詐欺取財罪，未通過\n      刷卡部分詐欺取財犯行尚屬未遂，則係犯同法第339 條第\n      3 項、第1 項之詐欺取財未遂罪。\n（四）被告、「昌哥」、「阿強」、震旦行區輔導即原同案被告\n      洪清芬等人，與震旦行所屬如附表四所示震旦行各分店店\n      長、店員即原同案被告林慶和、許靜怡、蘇曉倩、陳辜韋\n      、王冠文、周榮輝、劉志宏、古紹龍、陳蕙英、林介士、\n      黃文彬、陳宗宏、張賀鈞、李尉仁、黃耀賢等人分別就上\n      開其各自任職分店部分（詳如附表四所示）行使偽造準私\n      文書、行使偽造私文書及詐欺取財既、未遂之犯行，彼此\n      間互有犯意之聯絡及行為之分擔，皆為共同正犯。另被告\n      、「昌哥」、「阿強」與洪清芬等人，就震旦行民族店部\n      分犯行（即附表一編號一七五至一八二）亦有犯意之聯絡\n      及行為之分擔，均為共同正犯。\n（五）被告先後多次行使偽造準私文書、行使偽造私文書、詐欺\n      取財既遂、詐欺取財未遂犯行，均各時間緊接，手段相同\n      ，觸犯構成要件相同之罪名，顯各係基於概括犯意反覆為\n      之，均為連續犯（詐欺取財既遂與未遂部分應論以連續詐\n      欺取財既遂），均應依修正前刑法第56條之規定加重其刑\n      ，並論以一連續行使偽造準私文書罪、一連續行使偽造私\n      文書罪、一連續詐欺取財既遂罪。\n（六）被告所犯上開連續行使偽造準私文書罪、連續行使偽造私\n      文書罪、連續詐欺取財既遂罪間，有方法結果之牽連關係\n      ，應依修正前刑法第55條前段規定，從一重之連續行使偽\n      造私文書罪處斷。\n四、原審以被告犯罪事證明確，予以論罪科刑，固非無見。惟查\n    ：（一）被告所犯刑法第216 條、第220 條、第210 條行使\n    偽造準私文書罪應僅限於如附表二所示之犯行；又其於簽帳\n    單私文書上偽造署押並持以行使所犯刑法第216 條、第210\n    條行使偽造私文書罪亦僅限於如附表三所示之犯行。原審遽\n    認被告就附表一所示各次行為均構成刑法第216 條、第220\n    條、第210 條行使偽造準私文書罪及刑法第216 條、第210\n    條行使偽造私文書罪，已有違誤。（二）震旦行所屬如附表\n    一、二、三所示各分店店長及店員（除原同案被告丁鳳琴、\n    張世昇未有犯意之聯絡外）僅係分別就其各自任職分店部分\n    （詳如附表四所示），與被告、原同案被告洪清芬及「昌哥\n    」、「阿強」等人間，就上開如附表一、二、三所示犯行，\n    有犯意之聯絡及行為之分擔，皆為共同正犯；原審認震旦行\n    所屬如附表一、二、三所示各分店店長、店員等人均與被告\n    、洪清芬與「昌哥」、「阿強」等人間就上開犯行，相互間\n    有犯意之聯絡及行為之分擔，皆為共同正犯，亦有未洽。（\n    三）除附表三所示各次犯行「刷卡已通過」並載明偽造之署\n    押外，尚無從推認被告與「阿強」等人就附表一所示各次刷\n    卡未通過及刷卡通過但未於簽單上載明署押等部分（即「簽\n    帳單上偽造之署押」各欄內記載「不詳」之部分），被告及\n    其他共犯有何在簽帳單上偽造他人之署押而偽造簽帳單以行\n    使之行為。從而，其等就此部分自無成立偽造私文書及行使\n    偽造私文書罪之可言，惟原判決就被告此部分所為併論以偽\n    造私文書及行使偽造私文書罪，已如前述，並將此部分偽造\n    簽帳單上之署押宣告沒收，自有未合。（四）扣案共有如附\n    表五所示之6 張偽造之信用卡，已據本院更一審當庭勘驗，\n    有勘驗筆錄在卷可佐（見本院更一審卷第85頁至第90頁），\n    原審僅沒收如附表五編號一至五號所示之5 張偽造信用卡，\n    漏未沒收附表五編號六之偽造信用卡，顯有未當，且原判決\n    未依被告犯罪之具體情節，單獨於其之主文項下宣告相關之\n    從刑，亦非無可議。（五）刑法於被告行為後已有修正，原\n    審未及比較，及未及適用刑事妥速審判法，均尚有未洽。被\n    告提起上訴，仍執附表一所示各次犯行，伊並非全部都有參\n    與，不應均論以共犯等詞，指摘原判決不當，雖無理由，惟\n    原判決既有上揭可議之處，自仍應由本院將原判決關於被告\n    陳任寬部分撤銷改判。\n五、按「自第一審繫屬日起已逾八年未能判決確定之案件，除依\n    法應諭知無罪判決者外，經被告聲請，法院審酌下列事項，\n    認侵害被告受迅速審判之權利，情節重大，有予適當救濟之\n    必要者，得酌量減輕其刑：一、訴訟程序之延滯，是否係因\n    被告之事由。二、案件在法律及事實上之複雜程度與訴訟程\n    序延滯之衡平關係。三、其他與迅速審判有關之事項。」刑\n    事妥速審判法第7 條定有明文。經查，本案係於89年3 月23\n    日繫屬於原審法院，有原審法院收文章戳在卷可佐（見原審\n    卷一第1 頁），故自第一審繫屬日起至97年3 月22日止，案\n    件繫屬已滿8 年，被告於本院辯論終結前以言詞並由辯護人\n    為其具狀聲請依上開規定酌減其刑（見本院卷第19頁正面、\n    第33頁），審酌本案訴訟程序之延滯，並無被告因逃亡而遭\n    通緝、因病而停止審判、另案長期在國外羈押或服刑、或意\n    圖阻撓訴訟程序之順利進行，一再無理由之聲請迴避等，屬\n    被告個人事由所造成案件之延滯之情形，又本案尚非重大繁\n    雜之犯罪事件，亦無待證事實需多次鑑定、當事人眾多、調\n    查程序須在國外或大陸地區進行、經濟犯罪資金流向複雜或\n    法定停止審判之情狀，而本案審判程序進行逾8 年，被告自\n    第一審起到庭應訊次數達20餘次，對其受迅速審判之權利之\n    影響，應屬重大，爰依前開規定，酌量減輕其刑。\n六、爰審酌被告時值青年，不思正途，僅因個人急需金錢週轉竟\n    與「昌哥」為首之偽卡集團合作，並擔任刷手，結合前開震\n    旦行員工，而多次持偽造信用卡到震旦行臺北市區各分店刷\n    卡消費，所為非是，影響金融交易秩序之程度非輕，及其犯\n    罪之動機、目的、手段、犯罪所得、次數、所生損害，兼衡\n    被告犯後尚能坦承犯行之態度、素行等一切情狀，量處如主\n    文第2 項所示之刑。末查，被告所為上開犯行，犯罪時間固\n    均在96年4 月24日以前，惟其宣告刑逾有期徒刑1 年6 月，\n    有中華民國九十六年罪犯減刑條例第3 條第1 項第15款所定\n    不予減刑之情形，自均不予減刑，併予說明。\n七、沒收部分：\n（一）扣案偽造如附表五所示之信用卡6 張、姓名身分證號碼對\n      照表1 紙，均為被告及「昌哥」等人所有，供其等犯本件\n      之罪所用之物，均應依刑法第38條第1 項第2 款規定宣告\n      沒收。\n（二）附表五編號五之信用卡上偽造之「陳憲欽」署押1 枚，及\n      在如附表三所示簽帳單上偽造之署押各1 枚（留存於商店\n      存根或存根副本聯上），均應依刑法第219 條之規定，宣\n      告沒收。\n（三）其餘簽帳單上之署押，或不存在、或已滅失、或與被告之\n      犯行無涉，爰均不宣告沒收。\n（四）至扣案之行動電話6 台（MOTOROLA牌V3699 型、MOTOROLA\n      牌V2088 型、NOKIA 牌3210型、易利信牌T28 型、MOTORO\n      LA牌3688型、NOKIA 牌3210型）、無線話機1 台（國際牌\n      TCM416型）、透明皮套1 個（3210）、桌上型電子計算機\n      1 台、液晶充電器1 台（3210）及大哥大吊飾2 個，因屬\n      刷卡所得之贓物，爰不予宣告沒收。另其餘扣案物品，或\n      非屬被告所有，或非供本件犯罪所用之物，尚乏沒收之依\n      據，亦爰不予宣告沒收，併此敘明。\n據上論斷，應依刑事訴訟法第369條第1項前段、第364條、第299\n條第1 項前段，刑法第2 條第1 項前段、第219 條、第38條第1\n項第2 款，修正前刑法第28條、第56條、第210 條、第220 條、\n第216 條、第339 條第1 項、第55條，刑法施行法第1 條之1 ，\n刑事妥速審判法第7 條，判決如主文。\n本案經檢察官黃全祿到庭執行職務。\n中    華    民    國   100    年    10    月    20    日\n                    刑事第十二庭審判長法  官  蔡永昌\n                                      法  官  蘇隆惠\n                                      法  官  王美玲\n以上正本證明與原本無異。\n如不服本判決，應於收受送達後10日內向本院提出上訴書狀，其\n未敘述上訴之理由者並得於提起上訴後10日內向本院補提理由書\n（均須按他造當事人之人數附繕本）「切勿逕送上級法院」。\n                                      書記官  蔡儒萍\n中    華    民    國   100    年    10    月    20    日\n附錄本案論罪科刑法條全文：\n刑法第210條：\n偽造、變造私文書，足以生損害於公眾或他人者，處五年以下有\n期徒刑。\n刑法第216條：\n行使第二百十條至第二百十五條之文書者，依偽造、變造文書或\n登載不實事項或使登載不實事項之規定處斷。\n修正前刑法第220條：\n在紙上或物品上之文字、符號、圖畫、照像，依習慣或特約，足\n以為表示其用意之證明者，關於本章及本章以外各罪，以文書論\n。\n錄音、錄影或電磁紀錄，藉機器或電腦之處理所顯示之聲音、影\n像或符號，足以為表示其用意之證明者，亦同。\n稱電磁紀錄，指以電子、磁性或其他無法以人之知覺直接認識之\n方式所製成之紀錄，而供電腦處理之用者。\n刑法第339條第1項：\n意圖為自己或第三人不法之所有，以詐術使人將本人或第三人之\n物交付者，處五年以下有期徒刑、拘役或科或併科一千元以下罰\n金。",
  "structure": {
    "main": "原判決關於陳任寬部分撤銷。\n陳任寬共同連續犯行使偽造私文書罪，處有期徒刑壹年玖月。扣\n案如附表五所示之偽造信用卡陸張、附表五編號五所示偽造之「\n陳憲欽」署押壹枚、如附表三所示簽帳單上偽造之署押各壹枚（\n留存於商店存根或存根副本聯上）及姓名身分證號碼對照表壹紙\n，均沒收。",
    "fact": "一、陳任寬因急需金錢週轉票款，而明知以真實姓名年籍不詳，\n    綽號「昌哥」之成年男子（下稱「昌哥」）為首之偽卡集團\n    係使用偽造信用卡購買財物以謀利，其為能賺取金錢，竟仍\n    與「昌哥」及真實姓名年籍不詳，綽號「阿強」之成年男子\n    （下稱「阿強」）等人基於行使偽造信用卡、偽造署押、行\n    使偽造簽帳單、詐欺取財之概括犯意聯絡，由陳任寬與「阿\n    強」等人依「昌哥」指示，持如附表一編號一至一一四五號\n    所示燒錄他人真正內碼之偽造信用卡，於附表一編號一至一\n    一四五號所示之時間，前往附表一編號一至一一四五號所示\n    之「震旦行股份有限公司」（下稱震旦行）臺北市區各分店\n    ，刷卡購買行動電話等通信器材。陳任寬與「昌哥」、「阿\n    強」等人復與震旦行之員工洪清芬（任該公司「區輔導」，\n    經本院上訴審判處有期徒刑1 年，減為有期徒刑6 月，於更\n    一審撤回上訴後確定）基於犯意聯絡，先後於附表一編號一\n    至一一四五號所示之時間、地點，而與林慶和（任「雙連店\n    店長」，經原審判處有期徒刑1 年確定）、許靜怡（任「雙\n    連店店員」，經原審判處有期徒刑8 月確定）、高梅峰（任\n    「雙連店店員」，未據起訴）、蘇曉倩（任「吉林店店長」\n    ，經原審判處有期徒刑6 月確定）、陳辜韋（任「吉林店店\n    員」，經本院上訴審判處有期徒刑7 月，減為有期徒刑3 月\n    又15日確定）、張建平（任「吉林店店員」，未據起訴）、\n    王冠文（任「延平二店店長」，經本院上訴審判處有期徒刑\n    7 月，減為有期徒刑3 月又15日確定）、曾雅琪（任「延平\n    二店店員」，未據起訴）、邱榕濱（任「延平二店店員」，\n    未據起訴）、周榮輝（任「迪化店店長」，經原審判處有期\n    徒刑6 月確定）、劉志宏（任「迪化店店員」，經本院上訴\n    審判處有期徒刑7 月，減為有期徒刑3 月又15日確定）、古\n    紹龍（任「迪化店店員」，經本院上訴審判處有期徒刑7 月\n    ，減為有期徒刑3 月又15日確定）、陳蕙英（任「長安店店\n    長」，經本院上訴審判處有期徒刑6 月，減為有期徒刑3 月\n    確定）、彭毓璋（任「長安店店員」，未據起訴）、吳榮崇\n    （任「長安店店員」，未據起訴）、林介士（任「長安二店\n    店長」，經本院上訴審判處有期徒刑7 月，減為有期徒刑3\n    月又15日確定）、李孟廉（任「長安二店店員」，未據起訴\n    ）、彭婉綾（任「長安二店店員」，未據起訴）、黃文彬（\n    任「民權店店長」，經本院上訴審判處有期徒刑5 月，減為\n    有期徒刑2 月又15日確定）、陳宗宏（任「民權店店員」，\n    經本院上訴審判處有期徒刑6 月，減為有期徒刑3 月確定）\n    、張賀鈞（任「民權二店店長」，經本院上訴審判處有期徒\n    刑7 月，減為有期徒刑3 月又15日確定）、黃子虔（任「民\n    權二店店員」，未據起訴）、呂佳峰（任「民權二店店員」\n    ，未據起訴）、李尉仁（任「長春店店長」，經本院上訴審\n    判處有期徒刑7 月，減為有期徒刑3 月又15日確定）、周俊\n    雄（任「長春店店員」，未據起訴）、黃筱苓（任「長春店\n    店員」，未據起訴）、黃耀賢（任「民生二店店員」，經本\n    院上訴審判處有期徒刑6 月，減為有期徒刑3 月確定）等人\n    ，分別就其等各自任職分店部分（詳如附表四所示），基於\n    行使偽造信用卡、偽造署押、行使偽造簽帳單、詐欺取財之\n    概括犯意；而由陳任寬與「阿強」等人擔任「刷手」，持「\n    昌哥」所交付、附表一編號一至一一四五號所示、內已燒錄\n    自他人真正信用卡側錄內碼之偽造信用卡刷卡，並於刷卡通\n    過後，再依「昌哥」所交付之姓名身分證號對照表上之記載\n    ，在簽帳單上以複寫方式1 次偽造如附表三所示之署押1 式\n    3 枚（第一聯顧客存根，第二聯商店存根，第三聯存根副本\n    ），並由洪清芬事先以電話或親自到場指示林慶和、蘇曉倩\n    、陳辜韋、王冠文、周榮輝、劉志宏、古紹龍、陳蕙英、林\n    介士、黃文彬、陳宗宏等人及無參與犯罪意思之丁鳳琴、張\n    世昇（均經本院更一審判決無罪確定），分別於如附表一所\n    示之時間、地點，配合陳任寬與「阿強」等人刷卡結帳，或\n    由林慶和、許靜怡、高梅峰、蘇曉倩、陳辜韋、王冠文、周\n    榮輝、劉志宏、古紹龍、陳蕙英、林介士、黃文彬、陳宗宏\n    、張賀鈞、李尉仁、黃耀賢等人自行於如附表一所示之時間\n    、地點配合陳任寬與「阿強」等人刷卡結帳，並於刷卡通過\n    後交付如附表二所示刷卡金額之行動電話等通信器材予陳任\n    寬與「阿強」等人，足以生損害於震旦行、如附表三所示之\n    發卡銀行及如附表三所示被偽造署押之人（各分店所涉犯行\n    詳如附表四所示）。\n二、嗣經警於民國88年11月24日晚上7 時許，在臺北市○○○路\n    80號之震旦行雙連店內當場查獲陳任寬，並扣得「昌哥」所\n    交付、供其刷卡使用、如附表五所示之偽造信用卡共6 張、\n    姓名身分證號碼對照表1 紙，以及已完成刷卡之簽帳單3 紙\n    、刷卡所得之行動電話4 支（MOTOROLA牌V3699 型、MOTORO\n    LA牌V2088 型、NOKIA 牌3210型、易利信牌T28 型）；再依\n    其供述於同日晚間9 時許前往臺北市○○路132 號震旦行吉\n    林店，扣得簽帳單2 紙、刷卡所得之行動電話2 支（MOTORO\n    LA牌3688型、NOKIA 牌3210型）、無線話機1 台（國際牌TC\n    M416型）、透明皮套1 個（3210）、桌上型電子計算機1 台\n    、液晶充電器1 台（3210）及大哥大吊飾2 個，而循線查獲\n    上情。\n三、案經內政部警政署刑事警察局移送臺灣士林地方法院檢察署\n    檢察官偵查起訴。",
    "reason": "壹、證據能力方面：\n    按被告以外之人於審判外之陳述，雖不符刑事訴訟法第159\n    條之1 至第159 條之4 之規定，而經當事人於審判程序同意\n    作為證據，法院審酌該言詞陳述或書面陳述作成時之情況，\n    認為適當者，亦得為證據；當事人、代理人或辯護人於法院\n    調查證據時，知有刑事訴訟法第159 條第1 項不得為證據之\n    情形，而未於言詞辯論終結前聲明異議者，視為有前項之同\n    意，刑事訴訟法第159條之5第1項、第2項分別定有明文。立\n    法意旨在於傳聞證據未經當事人之反對詰問予以核實，原則\n    上先予排除。惟若當事人已放棄反對詰問權，於審判程序中\n    表明同意該等傳聞證據可作為證據；或於言詞辯論終結前未\n    聲明異議，基於尊重當事人對傳聞證據之處分權，及證據資\n    料愈豐富，愈有助於真實發見之理念，且強化言詞辯論主義\n    ，使訴訟程序得以順暢進行，上開傳聞證據亦均具有證據能\n    力。經查，本件以下所引用之被告以外之人於審判外之供述\n    或非供述證據，因檢察官、被告陳任寬及其選任辯護人已於\n    本院準備程序就證據能力均表示沒意見（見本院卷第27-32\n    頁），且迄至言詞辯論終結前均未聲明異議，而本院審酌上\n    開供述或非供述等證據資料製作時之情況，無不當取供及證\n    明力明顯過低之瑕疵，認以之作為證據應屬適當，揆諸前開\n    規定，本院認前揭證據資料有證據能力，合先敘明。\n貳、認定上訴人即被告犯罪事實所憑之證據及理由：\n一、訊據被告陳任寬對於上揭事實坦白承認，惟辯以：附表一所\n    載有很多之消費並非由伊前往刷卡，不應認定伊為共犯云云\n    。經查：\n（一）上揭事實業據被告於偵查、原審及本院歷審審理時均坦承\n      不諱，並核與證人即共犯林慶和、許靜怡、蘇曉倩、陳辜\n      韋、王冠文、周榮輝、劉志宏、古紹龍、陳蕙英、林介士\n      、陳宗宏、李尉仁等人分別於警詢、本院上訴審審理時所\n      證述被告於其等所任職之震旦行分店與其等、原同案被告\n      洪清芬共同參與上開犯行，而持偽造信用卡前來各分店刷\n      卡消費等情一致（見89年度偵字第639 號偵查卷一第45頁\n      、第57-59 頁、第176-178 頁、第127- 129頁、第60 -62\n      頁、第76-78 頁、第73-75 頁、第146- 148頁、第160-16\n      1 頁、第134-135 頁、第105-107 頁；卷二第47-48 頁；\n      本院上訴審卷二第225-227 頁、第146-150 頁、第151-15\n      3 頁、第186-187 頁；卷三第6-7 頁、第39-41 頁），且\n      由證人即原同案被告丁鳳琴、張世昇分別於本院上訴審審\n      理時就原同案被告洪清芬確曾要求其等協助被告為行使偽\n      造信用卡及詐欺取財等犯行一節結證述明確在卷（見本院\n      上訴審卷二第183-184 頁、卷三第4-5 頁）。再經原審當\n      庭勘驗證人即民權店店員陳宗宏所提供之民權店錄影帶製\n      有勘驗筆錄（見原審卷二第135 頁、第185 頁至第188 頁\n      ）、當庭勘驗證人即吉林店店員陳辜韋所提供之吉林店錄\n      影帶製有勘驗筆錄（見原審卷三第281 頁至第283 頁）。\n      此外，復有上開「昌哥」所交付、供被告刷卡使用、如附\n      表五所示之偽造信用卡共6 張、姓名身分證號碼對照表1\n      紙、以及已完成刷卡之簽帳單、刷卡所得之行動電話6 台\n      （MOTOROLA牌V3699 型、MOTOROLA牌V2088 型、NOKIA 牌\n      3210型、易利信牌T28 型、MOTOROLA牌3688型、NOKIA 牌\n      3210型）、無線話機1 台（國際牌TCM416）、透明皮套1\n      個（3210）、桌上型電子計算機1 台、液晶充電器1 台（\n      3210）及大哥大吊飾2 個等物扣案為證，及刷卡消費紀錄\n      在卷可稽。足認被告上開任意性自白，核與事實相符，可\n      以採取。\n（二）至被告雖辯以：附表一所載有很多之消費並非由伊前往刷\n      卡，不應認定伊為共犯云云。然按共同實施犯罪行為之人\n      ，在合同意思範圍以內，各自分擔犯罪行為之一部，相互\n      利用他人之行為，以達其犯罪之目的者，即應對於全部所\n      發生之結果，共同負責（最高法院28年上字第3110號判例\n      同此意旨）。而據前述。被告既已分別與原同案被告洪清\n      芬、林慶和、許靜怡、蘇曉倩、陳辜韋、王冠文、曾雅琪\n      、周榮輝、劉志宏、古紹龍、陳蕙英、林介士、陳宗宏、\n      張賀鈞、李尉仁、黃耀賢等人在偽造如附表三所示之署押\n      之意思範圍以內，各自分擔犯罪行為之一部，並相互利用\n      他人之行為，以達其犯罪之目的者，被告即應對於全部所\n      發生之結果，縱附表三簽帳單上偽造之署押，並非全為被\n      告所親簽，然其基於與「昌哥」為首之集團共同犯罪之意\n      思，相互分擔部分之行為，仍應就全部犯罪事實共負責任\n      。從而，被告所辯上情自非可取。\n（三）綜上所述，本件事證明確，被告上揭犯行，足可認定，應\n      依法論科。\n二、新舊法之比較與適用：\n    被告陳任寬行為後，刑法部分條文業於94年1 月7 日修正，\n    94年2 月2 日公布，95年7 月1 日施行，現行刑法第2 條第\n    1 項規定：「行為後法律有變更者，適用行為時之法律，但\n    行為後之法律有利於行為人者，適用最有利於行為人之法律\n    。」上開規定乃與刑法第1 條罪刑法定主義契合，而貫徹法\n    律禁止溯及既往原則，係規範行為後法律變更所生新舊法律\n    比較適用之準據法，是刑法第2 條本身雖經修正，但刑法第\n    2 條既屬適用法律之準據法，本身尚無比較新舊法之問題，\n    應一律適用裁判時之現行刑法第2 條規定以決定適用之刑罰\n    法律。又本次刑法修正之比較新舊法，應就罪刑有關之共犯\n    、未遂犯、想像競合犯、牽連犯、連續犯、結合犯、以及累\n    犯加重、自首減輕暨其他法定加減原因（如身分加減）與加\n    減例等一切情形，綜其全部罪刑之結果而為比較，最高法院\n    95年5 月23日95年度第8 次刑庭會議決議可資參照。又法院\n    裁判時已在新法施行之後，如新舊法條文之內容有所修正，\n    除其修正係無關乎處罰之輕重或要件內容之不同，而僅為其\n    他純文字之修正，非該條所指之法律有變更者，可毋庸依該\n    規定為新舊法之比較，而應依一般法律適用原則，適用裁判\n    時法外，即應適用新法第2 條第1 項之規定，為「從舊從輕\n    」之比較。經查：\n（一）修正前刑法第28條規定：「二人以上共同實施犯罪之行為\n      者，皆為正犯」，修正後刑法第28條則規定：「二人以上\n      共同實行犯罪之行為者，皆為正犯」，其中「實施」一語\n      ，涵蓋陰謀、預備、著手及實行之概念在內，其範圍較廣\n      ；而「實行」則著重於直接從事構成犯罪事實之行為，其\n      範圍較狹，是修正後刑法共同正犯之範圍已有限縮，共同\n      正犯之範圍既因此而有變動，自屬犯罪後法律有變更，而\n      非僅屬純文字修正，應有新舊法比較適用之問題（參照最\n      高法院96年度臺上字第3773號判決意旨），被告就上開犯\n      罪行為，依新舊法均成立共同正犯，適用新法並無較有利\n      於被告。\n（二）刑法第33條第5 款業已修正為：「主刑之種類如下：五、\n      罰金：新臺幣一千元以上，以百元計算之」，已將法定刑\n      罰金之最低額提高為新臺幣一千元，與該條文修正前規定\n      罰金最低額為銀元一元，而依現行法規所定貨幣單位折算\n      新臺幣條例第2 條，換算為新臺幣僅為新臺幣三元。因此\n      ，比較上述修正前、後之刑罰法律，自以被告行為時關於\n      科處罰金刑之法律較有利於被告。\n（三）修正後刑法業已刪除第55條後段關於牽連犯之規定，此刪\n      除雖非犯罪構成要件之變更，但顯已影響行為人刑罰之法\n      律效果，自屬法律有變更，經比較新、舊法結果，以修正\n      前第55條後段牽連犯之規定，將被告之數行為以一罪論，\n      顯較有利於被告。\n（四）刑法第56條連續犯之規定，業經修正刪除，此刪除雖非犯\n      罪構成要件之變更，但顯已影響行為人刑罰之法律效果，\n      自屬法律有變更，應依新法第2 條第1 項規定為新舊法之\n      比較（最高法院95年度第8 次刑事庭會議決議參照）。新\n      法修正施行後，被告上開先後多次行使偽造準私文書、行\n      使偽造私文書及詐欺取財之犯行，均須分論併罰，是比較\n      新舊法之結果，應適用較有利於被告之行為時法律即修正\n      前刑法第56條規定，各依連續犯規定以一罪論。\n（五）再被告陳任寬等人行為後，刑法增訂第201 條之1 已於90\n      年6 月20日公布施行，增訂第201 條之1 「意圖供行使之\n      用，而偽造、變造信用卡、金融卡、儲值卡或其他相類作\n      為簽帳、提款、轉帳或支付工具之電磁紀錄物之用者，處\n      一年以上七年以下有期徒刑，得併科三萬元以下罰金。」\n      、「行使偽造、變造之信用卡、金融卡、儲值卡或其他相\n      類作為簽帳、提款、轉帳或支付工具之電磁紀錄物之用，\n      而收受或交付於人者，處五年以下有期徒刑，得併科三萬\n      元以下罰金。」與前開從一重處斷之刑法第216 條、第21\n      0 條之行使偽造私文書罪，處五年以下有期徒刑；比較新\n      舊法之適用，應以刑法第216 條、第210 條之規定顯較有\n      利於被告，依刑法第2 條第1 項前段，自應適用舊法。\n（六）經綜合法律修正前後之整體比較，揆諸前揭最高法院決議\n      及修正後刑法第2 條第1 項之「從舊從輕」原則，適用修\n      正前之刑罰法律，對被告較為有利，自應整體適用修正前\n      刑法之相關規定。\n三、論罪科刑部分：\n（一）按信用卡係表示持卡人與發卡銀行間成立消費付款委託契\n      約之電磁紀錄，屬刑法第220 條規定所稱之準私文書。被\n      告等人就於附表二所載時、地，行使偽造信用卡之所為，\n      均係犯刑法第216 條、第220 條、第210 條行使偽造準私\n      文書罪。\n（二）又簽帳單係以文字為一定之意思表示，具有存續性，且屬\n      法律上有關係之事項，為文書之一種，並為私人製作之文\n      書。被告等人於附表三所示時、地，於簽帳單私文書上偽\n      造署押並持以行使之所為，均係犯刑法第216 條、第210\n      條行使偽造私文書罪。至附表二所示通過刷卡，然署押不\n      詳之部分，雖經原審於90年7 月23日裁定命震旦行提出供\n      扣押（見原審卷二第271 頁），而震旦行表示因90年間之\n      納莉颱風淹水、公司多次搬遷，致留存之簽帳單等相關資\n      料均因均已不知去向，有刑事陳報狀1 紙在卷可考（見原\n      審卷四第213 頁），故無從認定署押是否存在，基於「罪\n      疑利益歸於被告」之原則，自應為被告有利之認定，而認\n      此部分被告與共犯並無偽造署押之犯行，附此說明。再被\n      告等人偽造署押為偽造私文書之部分行為，偽造私文書後\n      持以行使，偽造私文書之低度行為，應為行使之高度行為\n      所吸收，均不另論罪。\n（三）被告於附表一所示時、地，共同持偽造信用卡刷卡購物之\n      所為，均係犯刑法第339 條第1 項之詐欺取財罪，未通過\n      刷卡部分詐欺取財犯行尚屬未遂，則係犯同法第339 條第\n      3 項、第1 項之詐欺取財未遂罪。\n（四）被告、「昌哥」、「阿強」、震旦行區輔導即原同案被告\n      洪清芬等人，與震旦行所屬如附表四所示震旦行各分店店\n      長、店員即原同案被告林慶和、許靜怡、蘇曉倩、陳辜韋\n      、王冠文、周榮輝、劉志宏、古紹龍、陳蕙英、林介士、\n      黃文彬、陳宗宏、張賀鈞、李尉仁、黃耀賢等人分別就上\n      開其各自任職分店部分（詳如附表四所示）行使偽造準私\n      文書、行使偽造私文書及詐欺取財既、未遂之犯行，彼此\n      間互有犯意之聯絡及行為之分擔，皆為共同正犯。另被告\n      、「昌哥」、「阿強」與洪清芬等人，就震旦行民族店部\n      分犯行（即附表一編號一七五至一八二）亦有犯意之聯絡\n      及行為之分擔，均為共同正犯。\n（五）被告先後多次行使偽造準私文書、行使偽造私文書、詐欺\n      取財既遂、詐欺取財未遂犯行，均各時間緊接，手段相同\n      ，觸犯構成要件相同之罪名，顯各係基於概括犯意反覆為\n      之，均為連續犯（詐欺取財既遂與未遂部分應論以連續詐\n      欺取財既遂），均應依修正前刑法第56條之規定加重其刑\n      ，並論以一連續行使偽造準私文書罪、一連續行使偽造私\n      文書罪、一連續詐欺取財既遂罪。\n（六）被告所犯上開連續行使偽造準私文書罪、連續行使偽造私\n      文書罪、連續詐欺取財既遂罪間，有方法結果之牽連關係\n      ，應依修正前刑法第55條前段規定，從一重之連續行使偽\n      造私文書罪處斷。\n四、原審以被告犯罪事證明確，予以論罪科刑，固非無見。惟查\n    ：（一）被告所犯刑法第216 條、第220 條、第210 條行使\n    偽造準私文書罪應僅限於如附表二所示之犯行；又其於簽帳\n    單私文書上偽造署押並持以行使所犯刑法第216 條、第210\n    條行使偽造私文書罪亦僅限於如附表三所示之犯行。原審遽\n    認被告就附表一所示各次行為均構成刑法第216 條、第220\n    條、第210 條行使偽造準私文書罪及刑法第216 條、第210\n    條行使偽造私文書罪，已有違誤。（二）震旦行所屬如附表\n    一、二、三所示各分店店長及店員（除原同案被告丁鳳琴、\n    張世昇未有犯意之聯絡外）僅係分別就其各自任職分店部分\n    （詳如附表四所示），與被告、原同案被告洪清芬及「昌哥\n    」、「阿強」等人間，就上開如附表一、二、三所示犯行，\n    有犯意之聯絡及行為之分擔，皆為共同正犯；原審認震旦行\n    所屬如附表一、二、三所示各分店店長、店員等人均與被告\n    、洪清芬與「昌哥」、「阿強」等人間就上開犯行，相互間\n    有犯意之聯絡及行為之分擔，皆為共同正犯，亦有未洽。（\n    三）除附表三所示各次犯行「刷卡已通過」並載明偽造之署\n    押外，尚無從推認被告與「阿強」等人就附表一所示各次刷\n    卡未通過及刷卡通過但未於簽單上載明署押等部分（即「簽\n    帳單上偽造之署押」各欄內記載「不詳」之部分），被告及\n    其他共犯有何在簽帳單上偽造他人之署押而偽造簽帳單以行\n    使之行為。從而，其等就此部分自無成立偽造私文書及行使\n    偽造私文書罪之可言，惟原判決就被告此部分所為併論以偽\n    造私文書及行使偽造私文書罪，已如前述，並將此部分偽造\n    簽帳單上之署押宣告沒收，自有未合。（四）扣案共有如附\n    表五所示之6 張偽造之信用卡，已據本院更一審當庭勘驗，\n    有勘驗筆錄在卷可佐（見本院更一審卷第85頁至第90頁），\n    原審僅沒收如附表五編號一至五號所示之5 張偽造信用卡，\n    漏未沒收附表五編號六之偽造信用卡，顯有未當，且原判決\n    未依被告犯罪之具體情節，單獨於其之主文項下宣告相關之\n    從刑，亦非無可議。（五）刑法於被告行為後已有修正，原\n    審未及比較，及未及適用刑事妥速審判法，均尚有未洽。被\n    告提起上訴，仍執附表一所示各次犯行，伊並非全部都有參\n    與，不應均論以共犯等詞，指摘原判決不當，雖無理由，惟\n    原判決既有上揭可議之處，自仍應由本院將原判決關於被告\n    陳任寬部分撤銷改判。\n五、按「自第一審繫屬日起已逾八年未能判決確定之案件，除依\n    法應諭知無罪判決者外，經被告聲請，法院審酌下列事項，\n    認侵害被告受迅速審判之權利，情節重大，有予適當救濟之\n    必要者，得酌量減輕其刑：一、訴訟程序之延滯，是否係因\n    被告之事由。二、案件在法律及事實上之複雜程度與訴訟程\n    序延滯之衡平關係。三、其他與迅速審判有關之事項。」刑\n    事妥速審判法第7 條定有明文。經查，本案係於89年3 月23\n    日繫屬於原審法院，有原審法院收文章戳在卷可佐（見原審\n    卷一第1 頁），故自第一審繫屬日起至97年3 月22日止，案\n    件繫屬已滿8 年，被告於本院辯論終結前以言詞並由辯護人\n    為其具狀聲請依上開規定酌減其刑（見本院卷第19頁正面、\n    第33頁），審酌本案訴訟程序之延滯，並無被告因逃亡而遭\n    通緝、因病而停止審判、另案長期在國外羈押或服刑、或意\n    圖阻撓訴訟程序之順利進行，一再無理由之聲請迴避等，屬\n    被告個人事由所造成案件之延滯之情形，又本案尚非重大繁\n    雜之犯罪事件，亦無待證事實需多次鑑定、當事人眾多、調\n    查程序須在國外或大陸地區進行、經濟犯罪資金流向複雜或\n    法定停止審判之情狀，而本案審判程序進行逾8 年，被告自\n    第一審起到庭應訊次數達20餘次，對其受迅速審判之權利之\n    影響，應屬重大，爰依前開規定，酌量減輕其刑。\n六、爰審酌被告時值青年，不思正途，僅因個人急需金錢週轉竟\n    與「昌哥」為首之偽卡集團合作，並擔任刷手，結合前開震\n    旦行員工，而多次持偽造信用卡到震旦行臺北市區各分店刷\n    卡消費，所為非是，影響金融交易秩序之程度非輕，及其犯\n    罪之動機、目的、手段、犯罪所得、次數、所生損害，兼衡\n    被告犯後尚能坦承犯行之態度、素行等一切情狀，量處如主\n    文第2 項所示之刑。末查，被告所為上開犯行，犯罪時間固\n    均在96年4 月24日以前，惟其宣告刑逾有期徒刑1 年6 月，\n    有中華民國九十六年罪犯減刑條例第3 條第1 項第15款所定\n    不予減刑之情形，自均不予減刑，併予說明。\n七、沒收部分：\n（一）扣案偽造如附表五所示之信用卡6 張、姓名身分證號碼對\n      照表1 紙，均為被告及「昌哥」等人所有，供其等犯本件\n      之罪所用之物，均應依刑法第38條第1 項第2 款規定宣告\n      沒收。\n（二）附表五編號五之信用卡上偽造之「陳憲欽」署押1 枚，及\n      在如附表三所示簽帳單上偽造之署押各1 枚（留存於商店\n      存根或存根副本聯上），均應依刑法第219 條之規定，宣\n      告沒收。\n（三）其餘簽帳單上之署押，或不存在、或已滅失、或與被告之\n      犯行無涉，爰均不宣告沒收。\n（四）至扣案之行動電話6 台（MOTOROLA牌V3699 型、MOTOROLA\n      牌V2088 型、NOKIA 牌3210型、易利信牌T28 型、MOTORO\n      LA牌3688型、NOKIA 牌3210型）、無線話機1 台（國際牌\n      TCM416型）、透明皮套1 個（3210）、桌上型電子計算機\n      1 台、液晶充電器1 台（3210）及大哥大吊飾2 個，因屬\n      刷卡所得之贓物，爰不予宣告沒收。另其餘扣案物品，或\n      非屬被告所有，或非供本件犯罪所用之物，尚乏沒收之依\n      據，亦爰不予宣告沒收，併此敘明。\n據上論斷，應依刑事訴訟法第369條第1項前段、第364條、第299\n條第1 項前段，刑法第2 條第1 項前段、第219 條、第38條第1\n項第2 款，修正前刑法第28條、第56條、第210 條、第220 條、\n第216 條、第339 條第1 項、第55條，刑法施行法第1 條之1 ，\n刑事妥速審判法第7 條，判決如主文。\n本案經檢察官黃全祿到庭執行職務。\n中    華    民    國   100    年    10    月    20    日\n                    刑事第十二庭審判長法  官  蔡永昌\n                                      法  官  蘇隆惠\n                                      法  官  王美玲\n以上正本證明與原本無異。\n如不服本判決，應於收受送達後10日內向本院提出上訴書狀，其\n未敘述上訴之理由者並得於提起上訴後10日內向本院補提理由書\n（均須按他造當事人之人數附繕本）「切勿逕送上級法院」。\n                                      書記官  蔡儒萍"
  },
  "search": "臺灣高等法院刑事判決100年度重上更(二)字第65號上訴人即被告陳任寬選任辯護人鍾永盛律師黃當庭律師上列上訴人因偽造文書等案件，不服臺灣士林地方法院89年度訴字第164號，中華民國91年10月25日第一審判決（起訴案號：臺灣士林地方法院檢察署88年度偵字第12021號、89年度偵字第639號），提起上訴，本院判決後，經最高法院第二次發回更審，判決如下：主文原判決關於陳任寬部分撤銷。陳任寬共同連續犯行使偽造私文書罪，處有期徒刑壹年玖月。扣案如附表五所示之偽造信用卡陸張、附表五編號五所示偽造之「陳憲欽」署押壹枚、如附表三所示簽帳單上偽造之署押各壹枚（留存於商店存根或存根副本聯上）及姓名身分證號碼對照表壹紙，均沒收。事實一、陳任寬因急需金錢週轉票款，而明知以真實姓名年籍不詳，綽號「昌哥」之成年男子（下稱「昌哥」）為首之偽卡集團係使用偽造信用卡購買財物以謀利，其為能賺取金錢，竟仍與「昌哥」及真實姓名年籍不詳，綽號「阿強」之成年男子（下稱「阿強」）等人基於行使偽造信用卡、偽造署押、行使偽造簽帳單、詐欺取財之概括犯意聯絡，由陳任寬與「阿強」等人依「昌哥」指示，持如附表一編號一至一一四五號所示燒錄他人真正內碼之偽造信用卡，於附表一編號一至一一四五號所示之時間，前往附表一編號一至一一四五號所示之「震旦行股份有限公司」（下稱震旦行）臺北市區各分店，刷卡購買行動電話等通信器材。陳任寬與「昌哥」、「阿強」等人復與震旦行之員工洪清芬（任該公司「區輔導」，經本院上訴審判處有期徒刑1年，減為有期徒刑6月，於更一審撤回上訴後確定）基於犯意聯絡，先後於附表一編號一至一一四五號所示之時間、地點，而與林慶和（任「雙連店店長」，經原審判處有期徒刑1年確定）、許靜怡（任「雙連店店員」，經原審判處有期徒刑8月確定）、高梅峰（任「雙連店店員」，未據起訴）、蘇曉倩（任「吉林店店長」，經原審判處有期徒刑6月確定）、陳辜韋（任「吉林店店員」，經本院上訴審判處有期徒刑7月，減為有期徒刑3月又15日確定）、張建平（任「吉林店店員」，未據起訴）、王冠文（任「延平二店店長」，經本院上訴審判處有期徒刑7月，減為有期徒刑3月又15日確定）、曾雅琪（任「延平二店店員」，未據起訴）、邱榕濱（任「延平二店店員」，未據起訴）、周榮輝（任「迪化店店長」，經原審判處有期徒刑6月確定）、劉志宏（任「迪化店店員」，經本院上訴審判處有期徒刑7月，減為有期徒刑3月又15日確定）、古紹龍（任「迪化店店員」，經本院上訴審判處有期徒刑7月，減為有期徒刑3月又15日確定）、陳蕙英（任「長安店店長」，經本院上訴審判處有期徒刑6月，減為有期徒刑3月確定）、彭毓璋（任「長安店店員」，未據起訴）、吳榮崇（任「長安店店員」，未據起訴）、林介士（任「長安二店店長」，經本院上訴審判處有期徒刑7月，減為有期徒刑3月又15日確定）、李孟廉（任「長安二店店員」，未據起訴）、彭婉綾（任「長安二店店員」，未據起訴）、黃文彬（任「民權店店長」，經本院上訴審判處有期徒刑5月，減為有期徒刑2月又15日確定）、陳宗宏（任「民權店店員」，經本院上訴審判處有期徒刑6月，減為有期徒刑3月確定）、張賀鈞（任「民權二店店長」，經本院上訴審判處有期徒刑7月，減為有期徒刑3月又15日確定）、黃子虔（任「民權二店店員」，未據起訴）、呂佳峰（任「民權二店店員」，未據起訴）、李尉仁（任「長春店店長」，經本院上訴審判處有期徒刑7月，減為有期徒刑3月又15日確定）、周俊雄（任「長春店店員」，未據起訴）、黃筱苓（任「長春店店員」，未據起訴）、黃耀賢（任「民生二店店員」，經本院上訴審判處有期徒刑6月，減為有期徒刑3月確定）等人，分別就其等各自任職分店部分（詳如附表四所示），基於行使偽造信用卡、偽造署押、行使偽造簽帳單、詐欺取財之概括犯意；而由陳任寬與「阿強」等人擔任「刷手」，持「昌哥」所交付、附表一編號一至一一四五號所示、內已燒錄自他人真正信用卡側錄內碼之偽造信用卡刷卡，並於刷卡通過後，再依「昌哥」所交付之姓名身分證號對照表上之記載，在簽帳單上以複寫方式1次偽造如附表三所示之署押1式3枚（第一聯顧客存根，第二聯商店存根，第三聯存根副本），並由洪清芬事先以電話或親自到場指示林慶和、蘇曉倩、陳辜韋、王冠文、周榮輝、劉志宏、古紹龍、陳蕙英、林介士、黃文彬、陳宗宏等人及無參與犯罪意思之丁鳳琴、張世昇（均經本院更一審判決無罪確定），分別於如附表一所示之時間、地點，配合陳任寬與「阿強」等人刷卡結帳，或由林慶和、許靜怡、高梅峰、蘇曉倩、陳辜韋、王冠文、周榮輝、劉志宏、古紹龍、陳蕙英、林介士、黃文彬、陳宗宏、張賀鈞、李尉仁、黃耀賢等人自行於如附表一所示之時間、地點配合陳任寬與「阿強」等人刷卡結帳，並於刷卡通過後交付如附表二所示刷卡金額之行動電話等通信器材予陳任寬與「阿強」等人，足以生損害於震旦行、如附表三所示之發卡銀行及如附表三所示被偽造署押之人（各分店所涉犯行詳如附表四所示）。二、嗣經警於民國88年11月24日晚上7時許，在臺北市○○○路80號之震旦行雙連店內當場查獲陳任寬，並扣得「昌哥」所交付、供其刷卡使用、如附表五所示之偽造信用卡共6張、姓名身分證號碼對照表1紙，以及已完成刷卡之簽帳單3紙、刷卡所得之行動電話4支（MOTOROLA牌V3699型、MOTOROLA牌V2088型、NOKIA牌3210型、易利信牌T28型）；再依其供述於同日晚間9時許前往臺北市○○路132號震旦行吉林店，扣得簽帳單2紙、刷卡所得之行動電話2支（MOTOROLA牌3688型、NOKIA牌3210型）、無線話機1台（國際牌TCM416型）、透明皮套1個（3210）、桌上型電子計算機1台、液晶充電器1台（3210）及大哥大吊飾2個，而循線查獲上情。三、案經內政部警政署刑事警察局移送臺灣士林地方法院檢察署檢察官偵查起訴。理由壹、證據能力方面：按被告以外之人於審判外之陳述，雖不符刑事訴訟法第159條之1至第159條之4之規定，而經當事人於審判程序同意作為證據，法院審酌該言詞陳述或書面陳述作成時之情況，認為適當者，亦得為證據；當事人、代理人或辯護人於法院調查證據時，知有刑事訴訟法第159條第1項不得為證據之情形，而未於言詞辯論終結前聲明異議者，視為有前項之同意，刑事訴訟法第159條之5第1項、第2項分別定有明文。立法意旨在於傳聞證據未經當事人之反對詰問予以核實，原則上先予排除。惟若當事人已放棄反對詰問權，於審判程序中表明同意該等傳聞證據可作為證據；或於言詞辯論終結前未聲明異議，基於尊重當事人對傳聞證據之處分權，及證據資料愈豐富，愈有助於真實發見之理念，且強化言詞辯論主義，使訴訟程序得以順暢進行，上開傳聞證據亦均具有證據能力。經查，本件以下所引用之被告以外之人於審判外之供述或非供述證據，因檢察官、被告陳任寬及其選任辯護人已於本院準備程序就證據能力均表示沒意見（見本院卷第27-32頁），且迄至言詞辯論終結前均未聲明異議，而本院審酌上開供述或非供述等證據資料製作時之情況，無不當取供及證明力明顯過低之瑕疵，認以之作為證據應屬適當，揆諸前開規定，本院認前揭證據資料有證據能力，合先敘明。貳、認定上訴人即被告犯罪事實所憑之證據及理由：一、訊據被告陳任寬對於上揭事實坦白承認，惟辯以：附表一所載有很多之消費並非由伊前往刷卡，不應認定伊為共犯云云。經查：（一）上揭事實業據被告於偵查、原審及本院歷審審理時均坦承不諱，並核與證人即共犯林慶和、許靜怡、蘇曉倩、陳辜韋、王冠文、周榮輝、劉志宏、古紹龍、陳蕙英、林介士、陳宗宏、李尉仁等人分別於警詢、本院上訴審審理時所證述被告於其等所任職之震旦行分店與其等、原同案被告洪清芬共同參與上開犯行，而持偽造信用卡前來各分店刷卡消費等情一致（見89年度偵字第639號偵查卷一第45頁、第57-59頁、第176-178頁、第127-129頁、第60-62頁、第76-78頁、第73-75頁、第146-148頁、第160-161頁、第134-135頁、第105-107頁；卷二第47-48頁；本院上訴審卷二第225-227頁、第146-150頁、第151-153頁、第186-187頁；卷三第6-7頁、第39-41頁），且由證人即原同案被告丁鳳琴、張世昇分別於本院上訴審審理時就原同案被告洪清芬確曾要求其等協助被告為行使偽造信用卡及詐欺取財等犯行一節結證述明確在卷（見本院上訴審卷二第183-184頁、卷三第4-5頁）。再經原審當庭勘驗證人即民權店店員陳宗宏所提供之民權店錄影帶製有勘驗筆錄（見原審卷二第135頁、第185頁至第188頁）、當庭勘驗證人即吉林店店員陳辜韋所提供之吉林店錄影帶製有勘驗筆錄（見原審卷三第281頁至第283頁）。此外，復有上開「昌哥」所交付、供被告刷卡使用、如附表五所示之偽造信用卡共6張、姓名身分證號碼對照表1紙、以及已完成刷卡之簽帳單、刷卡所得之行動電話6台（MOTOROLA牌V3699型、MOTOROLA牌V2088型、NOKIA牌3210型、易利信牌T28型、MOTOROLA牌3688型、NOKIA牌3210型）、無線話機1台（國際牌TCM416）、透明皮套1個（3210）、桌上型電子計算機1台、液晶充電器1台（3210）及大哥大吊飾2個等物扣案為證，及刷卡消費紀錄在卷可稽。足認被告上開任意性自白，核與事實相符，可以採取。（二）至被告雖辯以：附表一所載有很多之消費並非由伊前往刷卡，不應認定伊為共犯云云。然按共同實施犯罪行為之人，在合同意思範圍以內，各自分擔犯罪行為之一部，相互利用他人之行為，以達其犯罪之目的者，即應對於全部所發生之結果，共同負責（最高法院28年上字第3110號判例同此意旨）。而據前述。被告既已分別與原同案被告洪清芬、林慶和、許靜怡、蘇曉倩、陳辜韋、王冠文、曾雅琪、周榮輝、劉志宏、古紹龍、陳蕙英、林介士、陳宗宏、張賀鈞、李尉仁、黃耀賢等人在偽造如附表三所示之署押之意思範圍以內，各自分擔犯罪行為之一部，並相互利用他人之行為，以達其犯罪之目的者，被告即應對於全部所發生之結果，縱附表三簽帳單上偽造之署押，並非全為被告所親簽，然其基於與「昌哥」為首之集團共同犯罪之意思，相互分擔部分之行為，仍應就全部犯罪事實共負責任。從而，被告所辯上情自非可取。（三）綜上所述，本件事證明確，被告上揭犯行，足可認定，應依法論科。二、新舊法之比較與適用：被告陳任寬行為後，刑法部分條文業於94年1月7日修正，94年2月2日公布，95年7月1日施行，現行刑法第2條第1項規定：「行為後法律有變更者，適用行為時之法律，但行為後之法律有利於行為人者，適用最有利於行為人之法律。」上開規定乃與刑法第1條罪刑法定主義契合，而貫徹法律禁止溯及既往原則，係規範行為後法律變更所生新舊法律比較適用之準據法，是刑法第2條本身雖經修正，但刑法第2條既屬適用法律之準據法，本身尚無比較新舊法之問題，應一律適用裁判時之現行刑法第2條規定以決定適用之刑罰法律。又本次刑法修正之比較新舊法，應就罪刑有關之共犯、未遂犯、想像競合犯、牽連犯、連續犯、結合犯、以及累犯加重、自首減輕暨其他法定加減原因（如身分加減）與加減例等一切情形，綜其全部罪刑之結果而為比較，最高法院95年5月23日95年度第8次刑庭會議決議可資參照。又法院裁判時已在新法施行之後，如新舊法條文之內容有所修正，除其修正係無關乎處罰之輕重或要件內容之不同，而僅為其他純文字之修正，非該條所指之法律有變更者，可毋庸依該規定為新舊法之比較，而應依一般法律適用原則，適用裁判時法外，即應適用新法第2條第1項之規定，為「從舊從輕」之比較。經查：（一）修正前刑法第28條規定：「二人以上共同實施犯罪之行為者，皆為正犯」，修正後刑法第28條則規定：「二人以上共同實行犯罪之行為者，皆為正犯」，其中「實施」一語，涵蓋陰謀、預備、著手及實行之概念在內，其範圍較廣；而「實行」則著重於直接從事構成犯罪事實之行為，其範圍較狹，是修正後刑法共同正犯之範圍已有限縮，共同正犯之範圍既因此而有變動，自屬犯罪後法律有變更，而非僅屬純文字修正，應有新舊法比較適用之問題（參照最高法院96年度臺上字第3773號判決意旨），被告就上開犯罪行為，依新舊法均成立共同正犯，適用新法並無較有利於被告。（二）刑法第33條第5款業已修正為：「主刑之種類如下：五、罰金：新臺幣一千元以上，以百元計算之」，已將法定刑罰金之最低額提高為新臺幣一千元，與該條文修正前規定罰金最低額為銀元一元，而依現行法規所定貨幣單位折算新臺幣條例第2條，換算為新臺幣僅為新臺幣三元。因此，比較上述修正前、後之刑罰法律，自以被告行為時關於科處罰金刑之法律較有利於被告。（三）修正後刑法業已刪除第55條後段關於牽連犯之規定，此刪除雖非犯罪構成要件之變更，但顯已影響行為人刑罰之法律效果，自屬法律有變更，經比較新、舊法結果，以修正前第55條後段牽連犯之規定，將被告之數行為以一罪論，顯較有利於被告。（四）刑法第56條連續犯之規定，業經修正刪除，此刪除雖非犯罪構成要件之變更，但顯已影響行為人刑罰之法律效果，自屬法律有變更，應依新法第2條第1項規定為新舊法之比較（最高法院95年度第8次刑事庭會議決議參照）。新法修正施行後，被告上開先後多次行使偽造準私文書、行使偽造私文書及詐欺取財之犯行，均須分論併罰，是比較新舊法之結果，應適用較有利於被告之行為時法律即修正前刑法第56條規定，各依連續犯規定以一罪論。（五）再被告陳任寬等人行為後，刑法增訂第201條之1已於90年6月20日公布施行，增訂第201條之1「意圖供行使之用，而偽造、變造信用卡、金融卡、儲值卡或其他相類作為簽帳、提款、轉帳或支付工具之電磁紀錄物之用者，處一年以上七年以下有期徒刑，得併科三萬元以下罰金。」、「行使偽造、變造之信用卡、金融卡、儲值卡或其他相類作為簽帳、提款、轉帳或支付工具之電磁紀錄物之用，而收受或交付於人者，處五年以下有期徒刑，得併科三萬元以下罰金。」與前開從一重處斷之刑法第216條、第210條之行使偽造私文書罪，處五年以下有期徒刑；比較新舊法之適用，應以刑法第216條、第210條之規定顯較有利於被告，依刑法第2條第1項前段，自應適用舊法。（六）經綜合法律修正前後之整體比較，揆諸前揭最高法院決議及修正後刑法第2條第1項之「從舊從輕」原則，適用修正前之刑罰法律，對被告較為有利，自應整體適用修正前刑法之相關規定。三、論罪科刑部分：（一）按信用卡係表示持卡人與發卡銀行間成立消費付款委託契約之電磁紀錄，屬刑法第220條規定所稱之準私文書。被告等人就於附表二所載時、地，行使偽造信用卡之所為，均係犯刑法第216條、第220條、第210條行使偽造準私文書罪。（二）又簽帳單係以文字為一定之意思表示，具有存續性，且屬法律上有關係之事項，為文書之一種，並為私人製作之文書。被告等人於附表三所示時、地，於簽帳單私文書上偽造署押並持以行使之所為，均係犯刑法第216條、第210條行使偽造私文書罪。至附表二所示通過刷卡，然署押不詳之部分，雖經原審於90年7月23日裁定命震旦行提出供扣押（見原審卷二第271頁），而震旦行表示因90年間之納莉颱風淹水、公司多次搬遷，致留存之簽帳單等相關資料均因均已不知去向，有刑事陳報狀1紙在卷可考（見原審卷四第213頁），故無從認定署押是否存在，基於「罪疑利益歸於被告」之原則，自應為被告有利之認定，而認此部分被告與共犯並無偽造署押之犯行，附此說明。再被告等人偽造署押為偽造私文書之部分行為，偽造私文書後持以行使，偽造私文書之低度行為，應為行使之高度行為所吸收，均不另論罪。（三）被告於附表一所示時、地，共同持偽造信用卡刷卡購物之所為，均係犯刑法第339條第1項之詐欺取財罪，未通過刷卡部分詐欺取財犯行尚屬未遂，則係犯同法第339條第3項、第1項之詐欺取財未遂罪。（四）被告、「昌哥」、「阿強」、震旦行區輔導即原同案被告洪清芬等人，與震旦行所屬如附表四所示震旦行各分店店長、店員即原同案被告林慶和、許靜怡、蘇曉倩、陳辜韋、王冠文、周榮輝、劉志宏、古紹龍、陳蕙英、林介士、黃文彬、陳宗宏、張賀鈞、李尉仁、黃耀賢等人分別就上開其各自任職分店部分（詳如附表四所示）行使偽造準私文書、行使偽造私文書及詐欺取財既、未遂之犯行，彼此間互有犯意之聯絡及行為之分擔，皆為共同正犯。另被告、「昌哥」、「阿強」與洪清芬等人，就震旦行民族店部分犯行（即附表一編號一七五至一八二）亦有犯意之聯絡及行為之分擔，均為共同正犯。（五）被告先後多次行使偽造準私文書、行使偽造私文書、詐欺取財既遂、詐欺取財未遂犯行，均各時間緊接，手段相同，觸犯構成要件相同之罪名，顯各係基於概括犯意反覆為之，均為連續犯（詐欺取財既遂與未遂部分應論以連續詐欺取財既遂），均應依修正前刑法第56條之規定加重其刑，並論以一連續行使偽造準私文書罪、一連續行使偽造私文書罪、一連續詐欺取財既遂罪。（六）被告所犯上開連續行使偽造準私文書罪、連續行使偽造私文書罪、連續詐欺取財既遂罪間，有方法結果之牽連關係，應依修正前刑法第55條前段規定，從一重之連續行使偽造私文書罪處斷。四、原審以被告犯罪事證明確，予以論罪科刑，固非無見。惟查：（一）被告所犯刑法第216條、第220條、第210條行使偽造準私文書罪應僅限於如附表二所示之犯行；又其於簽帳單私文書上偽造署押並持以行使所犯刑法第216條、第210條行使偽造私文書罪亦僅限於如附表三所示之犯行。原審遽認被告就附表一所示各次行為均構成刑法第216條、第220條、第210條行使偽造準私文書罪及刑法第216條、第210條行使偽造私文書罪，已有違誤。（二）震旦行所屬如附表一、二、三所示各分店店長及店員（除原同案被告丁鳳琴、張世昇未有犯意之聯絡外）僅係分別就其各自任職分店部分（詳如附表四所示），與被告、原同案被告洪清芬及「昌哥」、「阿強」等人間，就上開如附表一、二、三所示犯行，有犯意之聯絡及行為之分擔，皆為共同正犯；原審認震旦行所屬如附表一、二、三所示各分店店長、店員等人均與被告、洪清芬與「昌哥」、「阿強」等人間就上開犯行，相互間有犯意之聯絡及行為之分擔，皆為共同正犯，亦有未洽。（三）除附表三所示各次犯行「刷卡已通過」並載明偽造之署押外，尚無從推認被告與「阿強」等人就附表一所示各次刷卡未通過及刷卡通過但未於簽單上載明署押等部分（即「簽帳單上偽造之署押」各欄內記載「不詳」之部分），被告及其他共犯有何在簽帳單上偽造他人之署押而偽造簽帳單以行使之行為。從而，其等就此部分自無成立偽造私文書及行使偽造私文書罪之可言，惟原判決就被告此部分所為併論以偽造私文書及行使偽造私文書罪，已如前述，並將此部分偽造簽帳單上之署押宣告沒收，自有未合。（四）扣案共有如附表五所示之6張偽造之信用卡，已據本院更一審當庭勘驗，有勘驗筆錄在卷可佐（見本院更一審卷第85頁至第90頁），原審僅沒收如附表五編號一至五號所示之5張偽造信用卡，漏未沒收附表五編號六之偽造信用卡，顯有未當，且原判決未依被告犯罪之具體情節，單獨於其之主文項下宣告相關之從刑，亦非無可議。（五）刑法於被告行為後已有修正，原審未及比較，及未及適用刑事妥速審判法，均尚有未洽。被告提起上訴，仍執附表一所示各次犯行，伊並非全部都有參與，不應均論以共犯等詞，指摘原判決不當，雖無理由，惟原判決既有上揭可議之處，自仍應由本院將原判決關於被告陳任寬部分撤銷改判。五、按「自第一審繫屬日起已逾八年未能判決確定之案件，除依法應諭知無罪判決者外，經被告聲請，法院審酌下列事項，認侵害被告受迅速審判之權利，情節重大，有予適當救濟之必要者，得酌量減輕其刑：一、訴訟程序之延滯，是否係因被告之事由。二、案件在法律及事實上之複雜程度與訴訟程序延滯之衡平關係。三、其他與迅速審判有關之事項。」刑事妥速審判法第7條定有明文。經查，本案係於89年3月23日繫屬於原審法院，有原審法院收文章戳在卷可佐（見原審卷一第1頁），故自第一審繫屬日起至97年3月22日止，案件繫屬已滿8年，被告於本院辯論終結前以言詞並由辯護人為其具狀聲請依上開規定酌減其刑（見本院卷第19頁正面、第33頁），審酌本案訴訟程序之延滯，並無被告因逃亡而遭通緝、因病而停止審判、另案長期在國外羈押或服刑、或意圖阻撓訴訟程序之順利進行，一再無理由之聲請迴避等，屬被告個人事由所造成案件之延滯之情形，又本案尚非重大繁雜之犯罪事件，亦無待證事實需多次鑑定、當事人眾多、調查程序須在國外或大陸地區進行、經濟犯罪資金流向複雜或法定停止審判之情狀，而本案審判程序進行逾8年，被告自第一審起到庭應訊次數達20餘次，對其受迅速審判之權利之影響，應屬重大，爰依前開規定，酌量減輕其刑。六、爰審酌被告時值青年，不思正途，僅因個人急需金錢週轉竟與「昌哥」為首之偽卡集團合作，並擔任刷手，結合前開震旦行員工，而多次持偽造信用卡到震旦行臺北市區各分店刷卡消費，所為非是，影響金融交易秩序之程度非輕，及其犯罪之動機、目的、手段、犯罪所得、次數、所生損害，兼衡被告犯後尚能坦承犯行之態度、素行等一切情狀，量處如主文第2項所示之刑。末查，被告所為上開犯行，犯罪時間固均在96年4月24日以前，惟其宣告刑逾有期徒刑1年6月，有中華民國九十六年罪犯減刑條例第3條第1項第15款所定不予減刑之情形，自均不予減刑，併予說明。七、沒收部分：（一）扣案偽造如附表五所示之信用卡6張、姓名身分證號碼對照表1紙，均為被告及「昌哥」等人所有，供其等犯本件之罪所用之物，均應依刑法第38條第1項第2款規定宣告沒收。（二）附表五編號五之信用卡上偽造之「陳憲欽」署押1枚，及在如附表三所示簽帳單上偽造之署押各1枚（留存於商店存根或存根副本聯上），均應依刑法第219條之規定，宣告沒收。（三）其餘簽帳單上之署押，或不存在、或已滅失、或與被告之犯行無涉，爰均不宣告沒收。（四）至扣案之行動電話6台（MOTOROLA牌V3699型、MOTOROLA牌V2088型、NOKIA牌3210型、易利信牌T28型、MOTOROLA牌3688型、NOKIA牌3210型）、無線話機1台（國際牌TCM416型）、透明皮套1個（3210）、桌上型電子計算機1台、液晶充電器1台（3210）及大哥大吊飾2個，因屬刷卡所得之贓物，爰不予宣告沒收。另其餘扣案物品，或非屬被告所有，或非供本件犯罪所用之物，尚乏沒收之依據，亦爰不予宣告沒收，併此敘明。據上論斷，應依刑事訴訟法第369條第1項前段、第364條、第299條第1項前段，刑法第2條第1項前段、第219條、第38條第1項第2款，修正前刑法第28條、第56條、第210條、第220條、第216條、第339條第1項、第55條，刑法施行法第1條之1，刑事妥速審判法第7條，判決如主文。本案經檢察官黃全祿到庭執行職務。中華民國100年10月20日刑事第十二庭審判長法官蔡永昌法官蘇隆惠法官王美玲以上正本證明與原本無異。如不服本判決，應於收受送達後10日內向本院提出上訴書狀，其未敘述上訴之理由者並得於提起上訴後10日內向本院補提理由書（均須按他造當事人之人數附繕本）「切勿逕送上級法院」。書記官蔡儒萍中華民國100年10月20日附錄本案論罪科刑法條全文：刑法第210條：偽造、變造私文書，足以生損害於公眾或他人者，處五年以下有期徒刑。刑法第216條：行使第二百十條至第二百十五條之文書者，依偽造、變造文書或登載不實事項或使登載不實事項之規定處斷。修正前刑法第220條：在紙上或物品上之文字、符號、圖畫、照像，依習慣或特約，足以為表示其用意之證明者，關於本章及本章以外各罪，以文書論。錄音、錄影或電磁紀錄，藉機器或電腦之處理所顯示之聲音、影像或符號，足以為表示其用意之證明者，亦同。稱電磁紀錄，指以電子、磁性或其他無法以人之知覺直接認識之方式所製成之紀錄，而供電腦處理之用者。刑法第339條第1項：意圖為自己或第三人不法之所有，以詐術使人將本人或第三人之物交付者，處五年以下有期徒刑、拘役或科或併科一千元以下罰金。",
  "characters": {
    "judges": [
      "蔡永昌",
      "蘇隆惠",
      "王美玲"
    ],
    "prosecutors": [
      "黃全祿"
    ],
    "lawyers": [
      "鍾永盛",
      "黃當庭"
    ],
    "clerks": [
      "蔡儒萍"
    ],
    "plaintiffs": [

    ],
    "defendants": [
      "陳任寬"
    ],
    "prosecutor_office": [

    ],
    "creditors": [

    ],
    "debtors": [

    ],
    "judicial_associate_officer": [

    ]
  },
  "adjudged_at": "2011-10-20",
  "created_at": "2016-02-14 07:37:03",
  "updated_at": "2016-02-14 07:37:03"
}