{
  "identify": "TCD-94-訴-1313-20051128-2",
  "court": {
    "name": "臺灣臺中地方法院",
    "code": "TCD"
  },
  "division": {
    "name": "刑事",
    "code": "M"
  },
  "year": 94,
  "word": "訴",
  "number": "1313",
  "jcheck": "2",
  "reason": "毒品危害防制條例",
  "content": "臺灣臺中地方法院刑事裁定              94年度訴字第1313號\n聲  請  人  臺灣臺中地方法院檢察署檢察官\n被      告  甲○○\n即  具保人\n                    國民\n上列被告因違反毒品危害防制條例案件，本院裁定如下：\n    主  文\n甲○○繳納之保證金新臺幣壹萬元，沒入之。\n    理  由\n一、按具保之被告逃匿者，應命具保人繳納指定之保證金額，並\n    沒入之，不繳納者，強制執行，保證金已繳納者，沒入之；\n    前項規定，於檢察官依第九十三條第三項但書及第二百二十\n    八條第四項命具保者，準用之；沒入保證金，以法院之裁定\n    行之，刑事訴訟法第一百十八條、第一百二十一條第一項分\n    別定有明文。\n二、經查：被告甲○○因違反毒品危害防制條例案件，經臺灣臺\n    中地方法院檢察署檢察官指定保證金新臺幣一萬元，由被告\n    自行繳納現金後，已將被告釋放。而被告於保釋後，屢經合\n    法傳拘無著，顯已逃匿，業經本院發布通緝之事實，有臺灣\n    臺中地方法院檢察署刑事保證書、保證金收據及本院送達證\n    書、拘提報告書及通緝書等附卷可稽，爰依刑事訴訟法第一\n    百十八條、第一百二十一條第一項，裁定如主文。\n中    華    民    國    94    年    11    月    28    日\n                  刑事第三庭  審判長法  官  張靜琪\n                                    法  官  賴妙雲\n                                    法  官  郭妙俐\n上正本證明與原本無異。\n如不服本裁定，應於送達後五日，內向本院提出抗告狀。\n                                    書記官  黃雅青\n中    華    民    國    94    年    12    月     1    日\n",
  "structure": {
    "main": "甲○○繳納之保證金新臺幣壹萬元，沒入之。",
    "reason": "一、按具保之被告逃匿者，應命具保人繳納指定之保證金額，並\n    沒入之，不繳納者，強制執行，保證金已繳納者，沒入之；\n    前項規定，於檢察官依第九十三條第三項但書及第二百二十\n    八條第四項命具保者，準用之；沒入保證金，以法院之裁定\n    行之，刑事訴訟法第一百十八條、第一百二十一條第一項分\n    別定有明文。\n二、經查：被告甲○○因違反毒品危害防制條例案件，經臺灣臺\n    中地方法院檢察署檢察官指定保證金新臺幣一萬元，由被告\n    自行繳納現金後，已將被告釋放。而被告於保釋後，屢經合\n    法傳拘無著，顯已逃匿，業經本院發布通緝之事實，有臺灣\n    臺中地方法院檢察署刑事保證書、保證金收據及本院送達證\n    書、拘提報告書及通緝書等附卷可稽，爰依刑事訴訟法第一\n    百十八條、第一百二十一條第一項，裁定如主文。"
  },
  "search": "臺灣臺中地方法院刑事裁定94年度訴字第1313號聲請人臺灣臺中地方法院檢察署檢察官被告甲○○即具保人國民上列被告因違反毒品危害防制條例案件，本院裁定如下：主文甲○○繳納之保證金新臺幣壹萬元，沒入之。理由一、按具保之被告逃匿者，應命具保人繳納指定之保證金額，並沒入之，不繳納者，強制執行，保證金已繳納者，沒入之；前項規定，於檢察官依第九十三條第三項但書及第二百二十八條第四項命具保者，準用之；沒入保證金，以法院之裁定行之，刑事訴訟法第一百十八條、第一百二十一條第一項分別定有明文。二、經查：被告甲○○因違反毒品危害防制條例案件，經臺灣臺中地方法院檢察署檢察官指定保證金新臺幣一萬元，由被告自行繳納現金後，已將被告釋放。而被告於保釋後，屢經合法傳拘無著，顯已逃匿，業經本院發布通緝之事實，有臺灣臺中地方法院檢察署刑事保證書、保證金收據及本院送達證書、拘提報告書及通緝書等附卷可稽，爰依刑事訴訟法第一百十八條、第一百二十一條第一項，裁定如主文。中華民國94年11月28日刑事第三庭審判長法官張靜琪法官賴妙雲法官郭妙俐上正本證明與原本無異。如不服本裁定，應於送達後五日，內向本院提出抗告狀。書記官黃雅青中華民國94年12月1日",
  "characters": {
    "judges": [
      "張靜琪",
      "賴妙雲",
      "郭妙俐"
    ],
    "prosecutors": [

    ],
    "lawyers": [

    ],
    "clerks": [
      "黃雅青"
    ],
    "plaintiffs": [

    ],
    "defendants": [
      "甲○○",
      "即  具保人"
    ],
    "prosecutor_office": [
      "臺灣臺中地方法院檢察署檢察官"
    ],
    "creditors": [

    ],
    "debtors": [

    ],
    "judicial_associate_officer": [

    ]
  },
  "adjudged_at": "2005-11-28",
  "created_at": "2016-02-06 23:40:51",
  "updated_at": "2016-02-06 23:40:51"
}