{
  "identify": "TPB-93-簡-1262-20050119-1",
  "court": {
    "name": "臺北高等行政法院",
    "code": "TPB"
  },
  "division": {
    "name": "行政",
    "code": "A"
  },
  "year": 93,
  "word": "簡",
  "number": "1262",
  "jcheck": "1",
  "reason": "就業服務法",
  "content": "臺北高等行政法院裁定\n                                     93年度簡字第01262號\n原      告  力碩國際開發有限公司\n代  表  人  甲○○○\n被      告  臺南縣政府\n代  表  人  乙○○（縣長）\n上列當事人間因就業服務法事件，原告不服行政院勞工委員會中\n華民國93年9月3日勞訴字第0930016754號訴願決定，提起行政訴\n訟。本院裁定如下：\n    主  文\n本件移送於高雄高等行政法院。\n    理  由\n一、按「對於公法人之訴訟，由其公務所所在地之行政法院管轄\n    。其以公法人之機關為被告時，由該機關所在地之行政法院\n    管轄。」、「民事訴訟法．．第28條．．之規定，於本節準\n    用之。」、「簡易程序除本章別有規定外，仍適用通常訴訟\n    程序之規定。」行政訴訟法第13條第1項、第18條、第236條\n    分別定有明文。又按「訴訟之全部或一部，法院認為無管轄\n    權者，依原告聲請或依職權以裁定移送於其管轄法院。」民\n    事訴訟法第28條第1項亦有明文。\n二、經查本件係原告對於為公法人機關之被告台南縣政府之訴訟\n    ，依首揭行政訴訟法第13條第1項之規定，由為公法人機關\n    之被告台南縣政府所在地之行政法院即高雄高等行政法院管\n    轄，本院無管轄權，原告對被告向本院提起行政訴訟，尚有\n    違誤，爰依首揭行政訴訟法第18條、第236條、民事訴訟法\n    第28條第1項之規定，依職權移送於有管轄權之高雄高等行\n    政法院。\n中    華    民    國    94    年    1    月    19     日\n                            第六庭 法  官  曹瑞卿\n上為正本係照原本作成。\n本件以訴訟事件所涉及之法律見解具有原則性者為限，始得於本\n裁定送達後10日內向本院提出抗告狀（須按他造人數附繕本），\n並經最高行政法院許可後方得抗告。\n中    華    民    國    94    年    1    月    19     日\n                                   書記官  方偉皓\n",
  "structure": {
    "main": "本件移送於高雄高等行政法院。",
    "reason": "一、按「對於公法人之訴訟，由其公務所所在地之行政法院管轄\n    。其以公法人之機關為被告時，由該機關所在地之行政法院\n    管轄。」、「民事訴訟法．．第28條．．之規定，於本節準\n    用之。」、「簡易程序除本章別有規定外，仍適用通常訴訟\n    程序之規定。」行政訴訟法第13條第1項、第18條、第236條\n    分別定有明文。又按「訴訟之全部或一部，法院認為無管轄\n    權者，依原告聲請或依職權以裁定移送於其管轄法院。」民\n    事訴訟法第28條第1項亦有明文。\n二、經查本件係原告對於為公法人機關之被告台南縣政府之訴訟\n    ，依首揭行政訴訟法第13條第1項之規定，由為公法人機關\n    之被告台南縣政府所在地之行政法院即高雄高等行政法院管\n    轄，本院無管轄權，原告對被告向本院提起行政訴訟，尚有\n    違誤，爰依首揭行政訴訟法第18條、第236條、民事訴訟法\n    第28條第1項之規定，依職權移送於有管轄權之高雄高等行\n    政法院。"
  },
  "search": "臺北高等行政法院裁定93年度簡字第01262號原告力碩國際開發有限公司代表人甲○○○被告臺南縣政府代表人乙○○（縣長）上列當事人間因就業服務法事件，原告不服行政院勞工委員會中華民國93年9月3日勞訴字第0930016754號訴願決定，提起行政訴訟。本院裁定如下：主文本件移送於高雄高等行政法院。理由一、按「對於公法人之訴訟，由其公務所所在地之行政法院管轄。其以公法人之機關為被告時，由該機關所在地之行政法院管轄。」、「民事訴訟法．．第28條．．之規定，於本節準用之。」、「簡易程序除本章別有規定外，仍適用通常訴訟程序之規定。」行政訴訟法第13條第1項、第18條、第236條分別定有明文。又按「訴訟之全部或一部，法院認為無管轄權者，依原告聲請或依職權以裁定移送於其管轄法院。」民事訴訟法第28條第1項亦有明文。二、經查本件係原告對於為公法人機關之被告台南縣政府之訴訟，依首揭行政訴訟法第13條第1項之規定，由為公法人機關之被告台南縣政府所在地之行政法院即高雄高等行政法院管轄，本院無管轄權，原告對被告向本院提起行政訴訟，尚有違誤，爰依首揭行政訴訟法第18條、第236條、民事訴訟法第28條第1項之規定，依職權移送於有管轄權之高雄高等行政法院。中華民國94年1月19日第六庭法官曹瑞卿上為正本係照原本作成。本件以訴訟事件所涉及之法律見解具有原則性者為限，始得於本裁定送達後10日內向本院提出抗告狀（須按他造人數附繕本），並經最高行政法院許可後方得抗告。中華民國94年1月19日書記官方偉皓",
  "characters": {
    "judges": [
      "曹瑞卿"
    ],
    "prosecutors": [

    ],
    "lawyers": [

    ],
    "clerks": [
      "方偉皓"
    ],
    "plaintiffs": [
      "力碩國際開發有限公司"
    ],
    "defendants": [
      "臺南縣政府",
      "代  表  人  乙○○（縣長）"
    ],
    "prosecutor_office": [

    ],
    "creditors": [

    ],
    "debtors": [

    ],
    "judicial_associate_officer": [

    ]
  },
  "adjudged_at": "2005-01-19",
  "created_at": "2016-02-07 02:29:55",
  "updated_at": "2016-02-07 02:29:55"
}