{
  "identify": "KLD-94-基簡-329-20050505-1",
  "court": {
    "name": "臺灣基隆地方法院",
    "code": "KLD"
  },
  "division": {
    "name": "刑事",
    "code": "M"
  },
  "year": 94,
  "word": "基簡",
  "number": "329",
  "jcheck": "1",
  "reason": "侵占遺失物",
  "content": "臺灣基隆地方法院刑事簡易判決         94年度基簡字第329號\n聲  請  人  臺灣基隆地方法院檢察署檢察官\n被      告  丙○○  男  41歲.\n上列被告因侵占遺失物案件，經檢察官聲請以簡易判決處刑（94\n年度偵字第1375號），本院判決如下：\n    主  文\n丙○○意圖為自己不法之所有，而侵占遺失物，處罰金仟元，\n如易服勞役，以佰元折算壹日。\n    事實及理由\n一、本件犯罪事實、證據及應適用之法條均引用如附件檢察官聲\n    請簡易判決處刑書之記載。\n二、依刑事訴訟法第449條第1項前段、第454條第2項，刑法第33\n    7條、第42條第2項，罰金罰鍰提高標準條例第1條前段、第2\n    條，逕以簡易判決處刑如主文。\n如不服本件判決，自收受送達之日起10日內，向本院提起上訴。\n中    華    民    國    94    年    5    月    5      日\n                  刑事第三庭法  官  王美婷\n以上正本證明與原本無異。\n如不服本判決，應於判決送達後10日內，向本院提出上訴書狀，\n上訴於本院合議庭，並按他造當事人之人數附具繕本。\n中    華    民    國    94    年    5    月    6      日\n                            書記官  劉珍珍\n附錄論罪法條\n刑法第337條：\n    意圖為自己或第三人不法之所有，而侵占遺失物、漂流物或\n    其他離本人所持有之物者，處500元以下罰金。\n附件：\n臺灣基隆地方法院檢察署檢察官聲請簡易判決處刑書\n                                       94年度偵字第1375號\n     被  告  丙○○  男  41歲（民國○○年○月○日生）\n                     住基隆巿安樂區○○路78巷27號\n                     居基隆市○○區○○路199號\n                     國民身分證統一編號：Ｚ000000000號\n上列被告因侵占案件，業經偵查終結，認為宜以簡易判決處刑，\n茲將犯罪事實及證據並所犯法條分敘如下：\n        犯罪事實\n一、丙○○於民國94年4 月1日11時許，在基隆巿安和二街15號\n    B棟「東帝士大潤發量販店」機車停車場，拾獲乙○○遺忘\n    放置在機車上之皮包1只（內有身分證、機車駕照、行車執\n    照、健保卡、誠泰銀行信用卡2 張、中國信託銀行信用卡2\n    張、聯邦銀行信用卡3張、台新銀行、萬泰銀行、安信銀行\n    信用卡各1張、台北銀行、基隆二信提款卡各1張、新台幣3\n    千元及摩托羅拉型號E365手機1支），竟意圖為自己不法之\n    所有，予以侵占入己。同日14時30分迄15 時許，丙○○持\n    其中2張聯邦銀行信用卡，至基隆巿源遠路碇內郵局及復興\n    路復興郵局取領現金，因密碼錯誤而未果。嗣於同日17 時\n    30 分許，為警循線在丙○○暖中路住所查獲，並起出乙○\n    ○遺失之皮包等物。\n二、案經乙○○訴由基隆巿警察局第二分局報告偵辦。\n         證據並所犯法條\n一、證據：（一）被告丙○○於警詢及本署之自白，（二）告訴\n    人乙○○於警詢指訴，（三）告訴人立具之贓物領據1紙 ，\n    （四）現場採證照片9幀附卷可資佐證，被告犯嫌已堪認定\n    。\n二、所犯法條：核被告所為，係犯刑法第337 條之侵占遺失物罪\n    嫌。\n三、依刑事訴訟法第451條第1項聲請逕以簡易判決處刑。\n    此  致\n臺灣基隆地方法院基隆簡易庭\n中    華    民    國    94    年    4     月    7     日\n                               檢察官  甲  ○  ○\n本件正本證明與原本無異\n中    華    民    國    94    年    4     月    21    日\n                              書記官  林  亮  珠\n附錄所犯法條：\n刑法第337條\n     意圖為自己或第三人不法之所有，而侵占遺失物、漂流物或\n     其他離本人所持有之物者，處500 元以下罰金。\n",
  "structure": {
    "main": "丙○○意圖為自己不法之所有，而侵占遺失物，處罰金仟元，\n如易服勞役，以佰元折算壹日。",
    "fact": "一、本件犯罪事實、證據及應適用之法條均引用如附件檢察官聲\n    請簡易判決處刑書之記載。\n二、依刑事訴訟法第449條第1項前段、第454條第2項，刑法第33\n    7條、第42條第2項，罰金罰鍰提高標準條例第1條前段、第2\n    條，逕以簡易判決處刑如主文。\n如不服本件判決，自收受送達之日起10日內，向本院提起上訴。",
    "reason": "一、本件犯罪事實、證據及應適用之法條均引用如附件檢察官聲\n    請簡易判決處刑書之記載。\n二、依刑事訴訟法第449條第1項前段、第454條第2項，刑法第33\n    7條、第42條第2項，罰金罰鍰提高標準條例第1條前段、第2\n    條，逕以簡易判決處刑如主文。\n如不服本件判決，自收受送達之日起10日內，向本院提起上訴。"
  },
  "search": "臺灣基隆地方法院刑事簡易判決94年度基簡字第329號聲請人臺灣基隆地方法院檢察署檢察官被告丙○○男41歲.上列被告因侵占遺失物案件，經檢察官聲請以簡易判決處刑（94年度偵字第1375號），本院判決如下：主文丙○○意圖為自己不法之所有，而侵占遺失物，處罰金仟元，如易服勞役，以佰元折算壹日。事實及理由一、本件犯罪事實、證據及應適用之法條均引用如附件檢察官聲請簡易判決處刑書之記載。二、依刑事訴訟法第449條第1項前段、第454條第2項，刑法第337條、第42條第2項，罰金罰鍰提高標準條例第1條前段、第2條，逕以簡易判決處刑如主文。如不服本件判決，自收受送達之日起10日內，向本院提起上訴。中華民國94年5月5日刑事第三庭法官王美婷以上正本證明與原本無異。如不服本判決，應於判決送達後10日內，向本院提出上訴書狀，上訴於本院合議庭，並按他造當事人之人數附具繕本。中華民國94年5月6日書記官劉珍珍附錄論罪法條刑法第337條：意圖為自己或第三人不法之所有，而侵占遺失物、漂流物或其他離本人所持有之物者，處500元以下罰金。附件：臺灣基隆地方法院檢察署檢察官聲請簡易判決處刑書94年度偵字第1375號被告丙○○男41歲（民國○○年○月○日生）住基隆巿安樂區○○路78巷27號居基隆市○○區○○路199號國民身分證統一編號：Ｚ000000000號上列被告因侵占案件，業經偵查終結，認為宜以簡易判決處刑，茲將犯罪事實及證據並所犯法條分敘如下：犯罪事實一、丙○○於民國94年4月1日11時許，在基隆巿安和二街15號B棟「東帝士大潤發量販店」機車停車場，拾獲乙○○遺忘放置在機車上之皮包1只（內有身分證、機車駕照、行車執照、健保卡、誠泰銀行信用卡2張、中國信託銀行信用卡2張、聯邦銀行信用卡3張、台新銀行、萬泰銀行、安信銀行信用卡各1張、台北銀行、基隆二信提款卡各1張、新台幣3千元及摩托羅拉型號E365手機1支），竟意圖為自己不法之所有，予以侵占入己。同日14時30分迄15時許，丙○○持其中2張聯邦銀行信用卡，至基隆巿源遠路碇內郵局及復興路復興郵局取領現金，因密碼錯誤而未果。嗣於同日17時30分許，為警循線在丙○○暖中路住所查獲，並起出乙○○遺失之皮包等物。二、案經乙○○訴由基隆巿警察局第二分局報告偵辦。證據並所犯法條一、證據：（一）被告丙○○於警詢及本署之自白，（二）告訴人乙○○於警詢指訴，（三）告訴人立具之贓物領據1紙，（四）現場採證照片9幀附卷可資佐證，被告犯嫌已堪認定。二、所犯法條：核被告所為，係犯刑法第337條之侵占遺失物罪嫌。三、依刑事訴訟法第451條第1項聲請逕以簡易判決處刑。此致臺灣基隆地方法院基隆簡易庭中華民國94年4月7日檢察官甲○○本件正本證明與原本無異中華民國94年4月21日書記官林亮珠附錄所犯法條：刑法第337條意圖為自己或第三人不法之所有，而侵占遺失物、漂流物或其他離本人所持有之物者，處500元以下罰金。",
  "characters": {
    "judges": [
      "王美婷"
    ],
    "prosecutors": [

    ],
    "lawyers": [

    ],
    "clerks": [
      "劉珍珍",
      "林亮珠"
    ],
    "plaintiffs": [

    ],
    "defendants": [
      "丙○○  男  41歲.",
      "丙○○  男  41歲（民國○○年○月○日生）"
    ],
    "prosecutor_office": [
      "臺灣基隆地方法院檢察署檢察官"
    ],
    "creditors": [

    ],
    "debtors": [

    ],
    "judicial_associate_officer": [

    ]
  },
  "adjudged_at": "2005-05-05",
  "created_at": "2016-02-06 15:02:39",
  "updated_at": "2016-02-06 15:02:39"
}