{
  "identify": "KLD-100-易-556-20111230-1",
  "court": {
    "name": "臺灣基隆地方法院",
    "code": "KLD"
  },
  "division": {
    "name": "刑事",
    "code": "M"
  },
  "year": 100,
  "word": "易",
  "number": "556",
  "jcheck": "1",
  "reason": "毒品危害防制條例",
  "content": "臺灣基隆地方法院刑事判決              100年度易字第556號\n公  訴  人  臺灣基隆地方法院檢察署檢察官\n被      告  杜文義\n上列被告因違反毒品危害防制條例案件，經檢察官提起公訴（\n100 年度毒偵字第2345號），被告並於準備程序進行中為有罪之\n陳述，本院乃裁定以簡式審判程序進行審理，並判決如下：\n    主  文\n杜文義施用第二級毒品，處有期徒刑月，如易科罰金，以新臺\n幣壹仟元折算壹日。\n    事  實\n一、杜文義前因施用毒品案件，經送觀察、勒戒，認無繼續施用\n    毒品之傾向，於民國87年7 月29日執行完畢釋放，並由臺灣\n    基隆地方法院檢察署檢察官以87年度偵字第2970號為不起訴\n    處分確定。復於上開觀察、勒戒執行完畢釋放後5 年以內，\n    因施用第二級毒品案件，先經裁定送強制戒治，於90年2 月\n    6 日期滿執行完畢；該案並經本院以88年度易字第200 號判\n    處有期徒刑8 月確定。又因施用第二級毒品案件，經本院以\n    89年度易字第426 號判處有期徒刑10月確定。另因犯偽造文\n    書、恐嚇等案件，分別經臺灣高等法院各判處有期徒刑4 月\n    、4 月確定，前開3 罪，嗣經臺灣高等法院合併定應執行刑\n    為有期徒刑1 年4 月確定，上揭數罪接續執行，於92年1 月\n    5 日執行完畢。再因施用第二級毒品案件，經本院以92年度\n    易字第119 號判處有期徒刑10月確定，於93年3 月26日易科\n    罰金執行完畢。復因施用第二級毒品案件，經臺灣高等法院\n    以90年度上易字第1792號判處有期徒刑10月確定，於94年6\n    月9 日執行完畢。再因施用第二級毒品案件，經臺灣高等法\n    院以94年度上易字第2018號判處有期徒刑1 年1 月確定；再\n    因施用第一級毒品案件，經本院以94年度訴字第1066號判處\n    有期徒刑8 月確定，前開2 罪，嗣經本院以96年度聲減字第\n    1326號裁定，經減刑後定應執行有期徒刑9 月15日確定。復\n    再因施用第二級毒品、持有第一級毒品、偽造文書等案件，\n    經臺灣宜蘭地方法院以96年度訴字第572 號判處應執行有期\n    徒刑3 年8 月確定，前揭數罪接續執行，於100 年6 月3 日\n    縮刑期滿假釋出監（至101 年4 月24日期滿，未構成累犯）\n    。\n二、杜文義猶不思戒除毒癮，復基於施用第二級毒品甲基安非他\n    命之犯意，於100 年9 月21日22時許，在新北市○○區○○\n    路77號住所，將甲基安非他命置於玻璃球吸食器內燒烤使生\n    霧化白煙再以口鼻吸食，藉以施用第二級毒品甲基安非他命\n    1 次。嗣於隔（22）日3 時25分許，因涉及另案，為警通知\n    到案，嗣經杜文義同意後採集尿液送驗，結果呈安非他命暨\n    甲基安非他命陽性反應。\n三、案經基隆巿警察局第二分局報告臺灣基隆地方法院檢察署檢\n    察官偵查起訴。\n    理  由\n壹、程序事項\n    本件被告所犯者非為死刑、無期徒刑、最輕本刑為3 年以上\n    有期徒刑之罪或高等法院管轄第一審案件，其於準備程序進\n    行中，先就被訴事實為有罪之陳述，經告知其簡式審判程序\n    之旨，並聽取公訴人、被告之意見後，本院業依刑事訴訟法\n    第273 條之1 第1 項規定，裁定改以簡式審判程序進行本案\n    之審理。\n貳、實體事項\n一、上開事實，業據被告杜文義於偵訊、本院審理時坦承在卷，\n    且經其同意後為警所採集之尿液送驗後，結果呈甲基安非他\n    命、安非他命之陽性反應，有台灣尖端先進生技醫藥股份有\n    限公司100 年10月20日濫用藥物檢驗報告、基隆巿警察局第\n    二分局偵辦毒品危害防制條例案件尿液檢體對照表（編號\n    000-0-000 號）各1 紙附卷可稽，被告之自白核與事實相符\n    ，可以採信。本案事證明確，應依法論科。\n二、查甲基安非他命係毒品危害防制條例第2 條第2 項第2 款所\n    定之第二級毒品，核被告所為，係犯毒品危害防制條例第10\n    條第2 項之施用第二級毒品罪。爰審酌其犯罪之動機、曾有\n    施用毒品之前科仍不知戒除，惟犯罪後坦承犯行，且所犯施\n    用毒品犯行乃戕害自己身心健康，並未危及他人等一切情狀\n    ，量處如主文所示之刑，並諭知易科罰金之折算標準。\n據上論斷，應依刑事訴訟法第284 條之1 、第273 條之1 第1 項\n、第299 條第1 項前段，毒品危害防制條例第10條第2 項，刑法\n第11條前段、第41條第1 項前段，判決如主文。\n本案經檢察官林明志到庭執行職務。\n中    華    民    國   100    年    12    月    30    日\n                  刑事第五庭法    官  吳佳齡\n以上正本證明與原本無異。\n如不服本判決應於收受送達後10日內向本院提出上訴書狀，並應\n敘述具體理由；其未敘述上訴理由者，應於上訴期間屆滿後20日\n內向本院補提理由書（均須按他造當事人之人數附繕本）「切勿\n逕送上級法院」。\n中    華    民    國   100    年    12    月    30    日\n                            書 記 官  莊智凱\n附錄論罪法條：\n毒品危害防制條例第10條\n施用第一級毒品者，處 6 月以上 5 年以下有期徒刑。\n施用第二級毒品者，處 3 年以下有期徒刑。",
  "structure": {
    "main": "杜文義施用第二級毒品，處有期徒刑月，如易科罰金，以新臺\n幣壹仟元折算壹日。",
    "fact": "一、杜文義前因施用毒品案件，經送觀察、勒戒，認無繼續施用\n    毒品之傾向，於民國87年7 月29日執行完畢釋放，並由臺灣\n    基隆地方法院檢察署檢察官以87年度偵字第2970號為不起訴\n    處分確定。復於上開觀察、勒戒執行完畢釋放後5 年以內，\n    因施用第二級毒品案件，先經裁定送強制戒治，於90年2 月\n    6 日期滿執行完畢；該案並經本院以88年度易字第200 號判\n    處有期徒刑8 月確定。又因施用第二級毒品案件，經本院以\n    89年度易字第426 號判處有期徒刑10月確定。另因犯偽造文\n    書、恐嚇等案件，分別經臺灣高等法院各判處有期徒刑4 月\n    、4 月確定，前開3 罪，嗣經臺灣高等法院合併定應執行刑\n    為有期徒刑1 年4 月確定，上揭數罪接續執行，於92年1 月\n    5 日執行完畢。再因施用第二級毒品案件，經本院以92年度\n    易字第119 號判處有期徒刑10月確定，於93年3 月26日易科\n    罰金執行完畢。復因施用第二級毒品案件，經臺灣高等法院\n    以90年度上易字第1792號判處有期徒刑10月確定，於94年6\n    月9 日執行完畢。再因施用第二級毒品案件，經臺灣高等法\n    院以94年度上易字第2018號判處有期徒刑1 年1 月確定；再\n    因施用第一級毒品案件，經本院以94年度訴字第1066號判處\n    有期徒刑8 月確定，前開2 罪，嗣經本院以96年度聲減字第\n    1326號裁定，經減刑後定應執行有期徒刑9 月15日確定。復\n    再因施用第二級毒品、持有第一級毒品、偽造文書等案件，\n    經臺灣宜蘭地方法院以96年度訴字第572 號判處應執行有期\n    徒刑3 年8 月確定，前揭數罪接續執行，於100 年6 月3 日\n    縮刑期滿假釋出監（至101 年4 月24日期滿，未構成累犯）\n    。\n二、杜文義猶不思戒除毒癮，復基於施用第二級毒品甲基安非他\n    命之犯意，於100 年9 月21日22時許，在新北市○○區○○\n    路77號住所，將甲基安非他命置於玻璃球吸食器內燒烤使生\n    霧化白煙再以口鼻吸食，藉以施用第二級毒品甲基安非他命\n    1 次。嗣於隔（22）日3 時25分許，因涉及另案，為警通知\n    到案，嗣經杜文義同意後採集尿液送驗，結果呈安非他命暨\n    甲基安非他命陽性反應。\n三、案經基隆巿警察局第二分局報告臺灣基隆地方法院檢察署檢\n    察官偵查起訴。",
    "reason": "壹、程序事項\n    本件被告所犯者非為死刑、無期徒刑、最輕本刑為3 年以上\n    有期徒刑之罪或高等法院管轄第一審案件，其於準備程序進\n    行中，先就被訴事實為有罪之陳述，經告知其簡式審判程序\n    之旨，並聽取公訴人、被告之意見後，本院業依刑事訴訟法\n    第273 條之1 第1 項規定，裁定改以簡式審判程序進行本案\n    之審理。\n貳、實體事項\n一、上開事實，業據被告杜文義於偵訊、本院審理時坦承在卷，\n    且經其同意後為警所採集之尿液送驗後，結果呈甲基安非他\n    命、安非他命之陽性反應，有台灣尖端先進生技醫藥股份有\n    限公司100 年10月20日濫用藥物檢驗報告、基隆巿警察局第\n    二分局偵辦毒品危害防制條例案件尿液檢體對照表（編號\n    000-0-000 號）各1 紙附卷可稽，被告之自白核與事實相符\n    ，可以採信。本案事證明確，應依法論科。\n二、查甲基安非他命係毒品危害防制條例第2 條第2 項第2 款所\n    定之第二級毒品，核被告所為，係犯毒品危害防制條例第10\n    條第2 項之施用第二級毒品罪。爰審酌其犯罪之動機、曾有\n    施用毒品之前科仍不知戒除，惟犯罪後坦承犯行，且所犯施\n    用毒品犯行乃戕害自己身心健康，並未危及他人等一切情狀\n    ，量處如主文所示之刑，並諭知易科罰金之折算標準。\n據上論斷，應依刑事訴訟法第284 條之1 、第273 條之1 第1 項\n、第299 條第1 項前段，毒品危害防制條例第10條第2 項，刑法\n第11條前段、第41條第1 項前段，判決如主文。\n本案經檢察官林明志到庭執行職務。\n中    華    民    國   100    年    12    月    30    日\n                  刑事第五庭法    官  吳佳齡\n以上正本證明與原本無異。\n如不服本判決應於收受送達後10日內向本院提出上訴書狀，並應\n敘述具體理由；其未敘述上訴理由者，應於上訴期間屆滿後20日\n內向本院補提理由書（均須按他造當事人之人數附繕本）「切勿\n逕送上級法院」。"
  },
  "search": "臺灣基隆地方法院刑事判決100年度易字第556號公訴人臺灣基隆地方法院檢察署檢察官被告杜文義上列被告因違反毒品危害防制條例案件，經檢察官提起公訴（100年度毒偵字第2345號），被告並於準備程序進行中為有罪之陳述，本院乃裁定以簡式審判程序進行審理，並判決如下：主文杜文義施用第二級毒品，處有期徒刑月，如易科罰金，以新臺幣壹仟元折算壹日。事實一、杜文義前因施用毒品案件，經送觀察、勒戒，認無繼續施用毒品之傾向，於民國87年7月29日執行完畢釋放，並由臺灣基隆地方法院檢察署檢察官以87年度偵字第2970號為不起訴處分確定。復於上開觀察、勒戒執行完畢釋放後5年以內，因施用第二級毒品案件，先經裁定送強制戒治，於90年2月6日期滿執行完畢；該案並經本院以88年度易字第200號判處有期徒刑8月確定。又因施用第二級毒品案件，經本院以89年度易字第426號判處有期徒刑10月確定。另因犯偽造文書、恐嚇等案件，分別經臺灣高等法院各判處有期徒刑4月、4月確定，前開3罪，嗣經臺灣高等法院合併定應執行刑為有期徒刑1年4月確定，上揭數罪接續執行，於92年1月5日執行完畢。再因施用第二級毒品案件，經本院以92年度易字第119號判處有期徒刑10月確定，於93年3月26日易科罰金執行完畢。復因施用第二級毒品案件，經臺灣高等法院以90年度上易字第1792號判處有期徒刑10月確定，於94年6月9日執行完畢。再因施用第二級毒品案件，經臺灣高等法院以94年度上易字第2018號判處有期徒刑1年1月確定；再因施用第一級毒品案件，經本院以94年度訴字第1066號判處有期徒刑8月確定，前開2罪，嗣經本院以96年度聲減字第1326號裁定，經減刑後定應執行有期徒刑9月15日確定。復再因施用第二級毒品、持有第一級毒品、偽造文書等案件，經臺灣宜蘭地方法院以96年度訴字第572號判處應執行有期徒刑3年8月確定，前揭數罪接續執行，於100年6月3日縮刑期滿假釋出監（至101年4月24日期滿，未構成累犯）。二、杜文義猶不思戒除毒癮，復基於施用第二級毒品甲基安非他命之犯意，於100年9月21日22時許，在新北市○○區○○路77號住所，將甲基安非他命置於玻璃球吸食器內燒烤使生霧化白煙再以口鼻吸食，藉以施用第二級毒品甲基安非他命1次。嗣於隔（22）日3時25分許，因涉及另案，為警通知到案，嗣經杜文義同意後採集尿液送驗，結果呈安非他命暨甲基安非他命陽性反應。三、案經基隆巿警察局第二分局報告臺灣基隆地方法院檢察署檢察官偵查起訴。理由壹、程序事項本件被告所犯者非為死刑、無期徒刑、最輕本刑為3年以上有期徒刑之罪或高等法院管轄第一審案件，其於準備程序進行中，先就被訴事實為有罪之陳述，經告知其簡式審判程序之旨，並聽取公訴人、被告之意見後，本院業依刑事訴訟法第273條之1第1項規定，裁定改以簡式審判程序進行本案之審理。貳、實體事項一、上開事實，業據被告杜文義於偵訊、本院審理時坦承在卷，且經其同意後為警所採集之尿液送驗後，結果呈甲基安非他命、安非他命之陽性反應，有台灣尖端先進生技醫藥股份有限公司100年10月20日濫用藥物檢驗報告、基隆巿警察局第二分局偵辦毒品危害防制條例案件尿液檢體對照表（編號000-0-000號）各1紙附卷可稽，被告之自白核與事實相符，可以採信。本案事證明確，應依法論科。二、查甲基安非他命係毒品危害防制條例第2條第2項第2款所定之第二級毒品，核被告所為，係犯毒品危害防制條例第10條第2項之施用第二級毒品罪。爰審酌其犯罪之動機、曾有施用毒品之前科仍不知戒除，惟犯罪後坦承犯行，且所犯施用毒品犯行乃戕害自己身心健康，並未危及他人等一切情狀，量處如主文所示之刑，並諭知易科罰金之折算標準。據上論斷，應依刑事訴訟法第284條之1、第273條之1第1項、第299條第1項前段，毒品危害防制條例第10條第2項，刑法第11條前段、第41條第1項前段，判決如主文。本案經檢察官林明志到庭執行職務。中華民國100年12月30日刑事第五庭法官吳佳齡以上正本證明與原本無異。如不服本判決應於收受送達後10日內向本院提出上訴書狀，並應敘述具體理由；其未敘述上訴理由者，應於上訴期間屆滿後20日內向本院補提理由書（均須按他造當事人之人數附繕本）「切勿逕送上級法院」。中華民國100年12月30日書記官莊智凱附錄論罪法條：毒品危害防制條例第10條施用第一級毒品者，處6月以上5年以下有期徒刑。施用第二級毒品者，處3年以下有期徒刑。",
  "characters": {
    "judges": [
      "吳佳齡"
    ],
    "prosecutors": [
      "林明志"
    ],
    "lawyers": [

    ],
    "clerks": [

    ],
    "plaintiffs": [

    ],
    "defendants": [
      "杜文義"
    ],
    "prosecutor_office": [
      "臺灣基隆地方法院檢察署檢察官"
    ],
    "creditors": [

    ],
    "debtors": [

    ],
    "judicial_associate_officer": [

    ]
  },
  "adjudged_at": "2011-12-30",
  "created_at": "2016-02-13 13:43:52",
  "updated_at": "2016-02-13 13:43:52"
}