{
  "identify": "PTD-100-交易-423-20111230-1",
  "court": {
    "name": "臺灣屏東地方法院",
    "code": "PTD"
  },
  "division": {
    "name": "刑事",
    "code": "M"
  },
  "year": 100,
  "word": "交易",
  "number": "423",
  "jcheck": "1",
  "reason": "公共危險等",
  "content": "臺灣屏東地方法院刑事判決            100年度交易字第423號\n公  訴  人  臺灣屏東地方法院檢察署檢察官\n被      告  湯純妮\n被      告  林榮家\n上列被告因過失傷害案件，經檢察官提起公訴（100 年度偵字第\n4482號），本院判決如下：\n    主  文\n本件公訴不受理。\n    理  由\n一、公訴意旨略以：被告湯純妮於民國100 年3 月12日上午10時\n    30分許，在屏東縣新埤鄉友人住處飲用摻有不明酒類之中藥\n    藥酒後，已達不能安全駕駛動力交通工具之程度，竟仍駕駛\n    車牌號碼OD-8946 號自小貨車上路，於同日上午11時15分許\n    ，沿屏東縣潮州鎮○○路由南往北方向直行，行至無號誌之\n    南京路與永康街交岔路口右轉進入永康街時，本應注意車前\n    狀況，減速右轉，小心通過，而依當時天候晴朗、日間自然\n    光線、路面乾燥無缺陷且視距良好亦無不能注意之情形，竟\n    因不勝酒力而疏未注意即貿然右轉；適有被告林榮家所駕駛\n    車牌號碼ZC-6367 號自小客車附載其妻梁雅茱，沿屏東縣潮\n    州鎮○○街由西往東方向直行，行至無號誌之永康街與南京\n    路交岔路口時，本應注意少線道車應暫停，讓多線道車先行\n    後，方得續行，且依當時情形亦無不能注意之情事，亦疏未\n    注意而貿然直行，致兩車閃避不及並發生碰撞，湯純妮因此\n    受有頭部外傷、胸部挫傷等傷害；梁雅茱則受有頸部及左肩\n    挫傷等傷害。嗣經警據報前往現場處理，並委請安泰醫療社\n    團法人潮州安泰醫院對湯純妮抽血檢測，測得湯純妮之血液\n    酒精濃度達155MG/DL（換算為呼氣酒精濃度為每公升0.77毫\n    克），始悉上情（就湯純妮涉及公共危險部分本院另行判決\n    ），因認被告湯純妮及被告林榮家均涉刑法第284 條第1 項\n    前段之過失傷害罪嫌，被告湯純妮酒醉駕車，因而肇事致人\n    受傷，依法應負刑事責任，其過失傷害部分並應依道路交通\n    管理處罰條例第86條第1 項規定加重其刑云云。\n二、按告訴乃論之罪，告訴人於第一審辯論終結前，得撤回其告\n    訴；又告訴經撤回者，法院應諭知不受理之判決，刑事訴訟\n    法第238 條第1 項，及第303 條第3 款定有明文。\n三、本件被告湯純妮等2 人因過失傷害案件，經檢察官提起公訴\n    ，認被告湯純妮等2 人均係犯刑法第284 條第1 項前段之過\n    失傷害罪（被告林榮家於警詢時曾表示其腰椎受傷也要對被\n    告湯純妮提起告訴，因被告湯純妮係一過失駕車行為傷害林\n    榮家及梁雅茱，為裁判上一罪，檢察官起訴書就被告湯純妮\n    過失傷害林榮家部分縱未起訴，本院仍應加以審理），依同\n    法第287 條前段之規定須告訴乃論。茲據告訴人林榮家、梁\n    雅茱（被告為湯純妮）、湯純妮（被告為林榮家）於本院\n    100 年12月21日審理時，提出刑事撤回告訴聲請狀或當庭聲\n    請撤回告訴等，揆諸前開說明，爰不經言詞辯論，就被告湯\n    純妮及被告林榮家所犯過失傷害部分，均諭知不受理之判決\n    。\n四、據上論斷，應依刑事訴訟法第303條第3款、第307條，判決\n    如主文。\n中    華    民    國   100    年    12    月    30    日\n                    交通法庭    法  官  黃紀錄\n如不服本判決應於收受判決後10日內向本院提出上訴書狀，並\n應敘述具體理由；其未敘述上訴理由者，應於上訴期間屆滿後\n20日內向本院補提理由書（均須按他造當事人之人數附繕本）\n「切勿逕送上級法院」。\n中    華    民    國    101   年     1    月     2    日\n                                書記官  戴仲敏",
  "structure": {
    "main": "本件公訴不受理。",
    "reason": "一、公訴意旨略以：被告湯純妮於民國100 年3 月12日上午10時\n    30分許，在屏東縣新埤鄉友人住處飲用摻有不明酒類之中藥\n    藥酒後，已達不能安全駕駛動力交通工具之程度，竟仍駕駛\n    車牌號碼OD-8946 號自小貨車上路，於同日上午11時15分許\n    ，沿屏東縣潮州鎮○○路由南往北方向直行，行至無號誌之\n    南京路與永康街交岔路口右轉進入永康街時，本應注意車前\n    狀況，減速右轉，小心通過，而依當時天候晴朗、日間自然\n    光線、路面乾燥無缺陷且視距良好亦無不能注意之情形，竟\n    因不勝酒力而疏未注意即貿然右轉；適有被告林榮家所駕駛\n    車牌號碼ZC-6367 號自小客車附載其妻梁雅茱，沿屏東縣潮\n    州鎮○○街由西往東方向直行，行至無號誌之永康街與南京\n    路交岔路口時，本應注意少線道車應暫停，讓多線道車先行\n    後，方得續行，且依當時情形亦無不能注意之情事，亦疏未\n    注意而貿然直行，致兩車閃避不及並發生碰撞，湯純妮因此\n    受有頭部外傷、胸部挫傷等傷害；梁雅茱則受有頸部及左肩\n    挫傷等傷害。嗣經警據報前往現場處理，並委請安泰醫療社\n    團法人潮州安泰醫院對湯純妮抽血檢測，測得湯純妮之血液\n    酒精濃度達155MG/DL（換算為呼氣酒精濃度為每公升0.77毫\n    克），始悉上情（就湯純妮涉及公共危險部分本院另行判決\n    ），因認被告湯純妮及被告林榮家均涉刑法第284 條第1 項\n    前段之過失傷害罪嫌，被告湯純妮酒醉駕車，因而肇事致人\n    受傷，依法應負刑事責任，其過失傷害部分並應依道路交通\n    管理處罰條例第86條第1 項規定加重其刑云云。\n二、按告訴乃論之罪，告訴人於第一審辯論終結前，得撤回其告\n    訴；又告訴經撤回者，法院應諭知不受理之判決，刑事訴訟\n    法第238 條第1 項，及第303 條第3 款定有明文。\n三、本件被告湯純妮等2 人因過失傷害案件，經檢察官提起公訴\n    ，認被告湯純妮等2 人均係犯刑法第284 條第1 項前段之過\n    失傷害罪（被告林榮家於警詢時曾表示其腰椎受傷也要對被\n    告湯純妮提起告訴，因被告湯純妮係一過失駕車行為傷害林\n    榮家及梁雅茱，為裁判上一罪，檢察官起訴書就被告湯純妮\n    過失傷害林榮家部分縱未起訴，本院仍應加以審理），依同\n    法第287 條前段之規定須告訴乃論。茲據告訴人林榮家、梁\n    雅茱（被告為湯純妮）、湯純妮（被告為林榮家）於本院\n    100 年12月21日審理時，提出刑事撤回告訴聲請狀或當庭聲\n    請撤回告訴等，揆諸前開說明，爰不經言詞辯論，就被告湯\n    純妮及被告林榮家所犯過失傷害部分，均諭知不受理之判決\n    。\n四、據上論斷，應依刑事訴訟法第303條第3款、第307條，判決\n    如主文。"
  },
  "search": "臺灣屏東地方法院刑事判決100年度交易字第423號公訴人臺灣屏東地方法院檢察署檢察官被告湯純妮被告林榮家上列被告因過失傷害案件，經檢察官提起公訴（100年度偵字第4482號），本院判決如下：主文本件公訴不受理。理由一、公訴意旨略以：被告湯純妮於民國100年3月12日上午10時30分許，在屏東縣新埤鄉友人住處飲用摻有不明酒類之中藥藥酒後，已達不能安全駕駛動力交通工具之程度，竟仍駕駛車牌號碼OD-8946號自小貨車上路，於同日上午11時15分許，沿屏東縣潮州鎮○○路由南往北方向直行，行至無號誌之南京路與永康街交岔路口右轉進入永康街時，本應注意車前狀況，減速右轉，小心通過，而依當時天候晴朗、日間自然光線、路面乾燥無缺陷且視距良好亦無不能注意之情形，竟因不勝酒力而疏未注意即貿然右轉；適有被告林榮家所駕駛車牌號碼ZC-6367號自小客車附載其妻梁雅茱，沿屏東縣潮州鎮○○街由西往東方向直行，行至無號誌之永康街與南京路交岔路口時，本應注意少線道車應暫停，讓多線道車先行後，方得續行，且依當時情形亦無不能注意之情事，亦疏未注意而貿然直行，致兩車閃避不及並發生碰撞，湯純妮因此受有頭部外傷、胸部挫傷等傷害；梁雅茱則受有頸部及左肩挫傷等傷害。嗣經警據報前往現場處理，並委請安泰醫療社團法人潮州安泰醫院對湯純妮抽血檢測，測得湯純妮之血液酒精濃度達155MG/DL（換算為呼氣酒精濃度為每公升0.77毫克），始悉上情（就湯純妮涉及公共危險部分本院另行判決），因認被告湯純妮及被告林榮家均涉刑法第284條第1項前段之過失傷害罪嫌，被告湯純妮酒醉駕車，因而肇事致人受傷，依法應負刑事責任，其過失傷害部分並應依道路交通管理處罰條例第86條第1項規定加重其刑云云。二、按告訴乃論之罪，告訴人於第一審辯論終結前，得撤回其告訴；又告訴經撤回者，法院應諭知不受理之判決，刑事訴訟法第238條第1項，及第303條第3款定有明文。三、本件被告湯純妮等2人因過失傷害案件，經檢察官提起公訴，認被告湯純妮等2人均係犯刑法第284條第1項前段之過失傷害罪（被告林榮家於警詢時曾表示其腰椎受傷也要對被告湯純妮提起告訴，因被告湯純妮係一過失駕車行為傷害林榮家及梁雅茱，為裁判上一罪，檢察官起訴書就被告湯純妮過失傷害林榮家部分縱未起訴，本院仍應加以審理），依同法第287條前段之規定須告訴乃論。茲據告訴人林榮家、梁雅茱（被告為湯純妮）、湯純妮（被告為林榮家）於本院100年12月21日審理時，提出刑事撤回告訴聲請狀或當庭聲請撤回告訴等，揆諸前開說明，爰不經言詞辯論，就被告湯純妮及被告林榮家所犯過失傷害部分，均諭知不受理之判決。四、據上論斷，應依刑事訴訟法第303條第3款、第307條，判決如主文。中華民國100年12月30日交通法庭法官黃紀錄如不服本判決應於收受判決後10日內向本院提出上訴書狀，並應敘述具體理由；其未敘述上訴理由者，應於上訴期間屆滿後20日內向本院補提理由書（均須按他造當事人之人數附繕本）「切勿逕送上級法院」。中華民國101年1月2日書記官戴仲敏",
  "characters": {
    "judges": [
      "黃紀錄"
    ],
    "prosecutors": [

    ],
    "lawyers": [

    ],
    "clerks": [

    ],
    "plaintiffs": [

    ],
    "defendants": [
      "湯純妮",
      "被      告  林榮家"
    ],
    "prosecutor_office": [
      "臺灣屏東地方法院檢察署檢察官"
    ],
    "creditors": [

    ],
    "debtors": [

    ],
    "judicial_associate_officer": [

    ]
  },
  "adjudged_at": "2011-12-30",
  "created_at": "2016-02-13 14:04:03",
  "updated_at": "2016-02-13 14:04:03"
}