{
  "identify": "TCD-100-交易-1039-20111230-1",
  "court": {
    "name": "臺灣臺中地方法院",
    "code": "TCD"
  },
  "division": {
    "name": "刑事",
    "code": "M"
  },
  "year": 100,
  "word": "交易",
  "number": "1039",
  "jcheck": "1",
  "reason": "過失傷害",
  "content": "臺灣臺中地方法院刑事判決           100年度交易字第1039號\n公  訴  人  臺灣臺中地方法院檢察署檢察官\n被      告  王國芳\n上列被告因過失傷害案件，經檢察官提起公訴（100 年度偵字第\n20942 號），本院判決如下：\n    主  文\n本件公訴不受理。\n    理  由\n一、本件公訴意旨略以：被告王國芳於民國100 年1 月26日凌晨\n    ，駕駛車牌號碼7738-LP 號自用小客車，沿臺中市○○區○\n    ○路由西往東方向行駛，於同日凌晨1 時15分許，行經梧棲\n    區○○路與光復路交岔口時，原應注意支線道車應讓幹線道\n    車先行，而依當時天候晴朗、夜間有照明、道路為柏油路、\n    、路面乾燥、無缺陷、無障礙物、視距良好等情況，並無不\n    能注意之情事，竟疏未注意及此，即貿然通過該交岔路口，\n    適告訴人何佳沛騎乘車牌號碼SQ3 -278號輕型機車，沿梧棲\n    區○○路由北往南方向直行，亦行經上開路口，2 車因而發\n    生碰撞，致告訴人何佳沛人車倒地，因而受有右股骨幹骨折\n    之傷害。案經告訴人何佳沛提出告訴，因認被告王國芳涉有\n    刑法第284 條第1 項前段之過失傷害罪嫌。\n二、按告訴乃論之罪，告訴人於第一審辯論終結前，得撤回其告\n    訴；又告訴經撤回者，應諭知不受理之判決，並得不經言詞\n    辯論為之，刑事訴訟法第238 條第1 項、第303 條第3 款、\n    第307 條，分別定有明文。經查，本件被告王國芳被訴犯有\n    刑法第284 條第1 項前段之過失傷害罪，依同法第287 條前\n    段之規定係屬告訴乃論之罪，茲據告訴人何佳沛於第一審辯\n    論終結前，具狀撤回告訴，此有撤回告訴狀1 份在卷可稽，\n    揆諸上開說明，爰就此部分，不經言詞辯論，諭知不受理之\n    判決。\n據上論斷，應依刑事訴訟法第303 條第3 款、第307 條，判決如\n主文。\n中    華    民    國  100     年    12    月    30    日\n                    交通法庭    法  官  胡芷瑜\n以上正本證明與原本無異。\n如不服本判決，應於收受送達後10日內向本院提出上訴書狀，並\n應敘述具體理由；其未敘述上訴理由者，應於上訴期間屆滿後20\n日內向本院補提理由書（均須按他造當事人之人數附繕本）「切\n勿逕送上級法院」。\n                                書記官  曾惠雅\n中    華    民    國  100     年    12    月    30    日",
  "structure": {
    "main": "本件公訴不受理。",
    "reason": "一、本件公訴意旨略以：被告王國芳於民國100 年1 月26日凌晨\n    ，駕駛車牌號碼7738-LP 號自用小客車，沿臺中市○○區○\n    ○路由西往東方向行駛，於同日凌晨1 時15分許，行經梧棲\n    區○○路與光復路交岔口時，原應注意支線道車應讓幹線道\n    車先行，而依當時天候晴朗、夜間有照明、道路為柏油路、\n    、路面乾燥、無缺陷、無障礙物、視距良好等情況，並無不\n    能注意之情事，竟疏未注意及此，即貿然通過該交岔路口，\n    適告訴人何佳沛騎乘車牌號碼SQ3 -278號輕型機車，沿梧棲\n    區○○路由北往南方向直行，亦行經上開路口，2 車因而發\n    生碰撞，致告訴人何佳沛人車倒地，因而受有右股骨幹骨折\n    之傷害。案經告訴人何佳沛提出告訴，因認被告王國芳涉有\n    刑法第284 條第1 項前段之過失傷害罪嫌。\n二、按告訴乃論之罪，告訴人於第一審辯論終結前，得撤回其告\n    訴；又告訴經撤回者，應諭知不受理之判決，並得不經言詞\n    辯論為之，刑事訴訟法第238 條第1 項、第303 條第3 款、\n    第307 條，分別定有明文。經查，本件被告王國芳被訴犯有\n    刑法第284 條第1 項前段之過失傷害罪，依同法第287 條前\n    段之規定係屬告訴乃論之罪，茲據告訴人何佳沛於第一審辯\n    論終結前，具狀撤回告訴，此有撤回告訴狀1 份在卷可稽，\n    揆諸上開說明，爰就此部分，不經言詞辯論，諭知不受理之\n    判決。\n據上論斷，應依刑事訴訟法第303 條第3 款、第307 條，判決如\n主文。"
  },
  "search": "臺灣臺中地方法院刑事判決100年度交易字第1039號公訴人臺灣臺中地方法院檢察署檢察官被告王國芳上列被告因過失傷害案件，經檢察官提起公訴（100年度偵字第20942號），本院判決如下：主文本件公訴不受理。理由一、本件公訴意旨略以：被告王國芳於民國100年1月26日凌晨，駕駛車牌號碼7738-LP號自用小客車，沿臺中市○○區○○路由西往東方向行駛，於同日凌晨1時15分許，行經梧棲區○○路與光復路交岔口時，原應注意支線道車應讓幹線道車先行，而依當時天候晴朗、夜間有照明、道路為柏油路、、路面乾燥、無缺陷、無障礙物、視距良好等情況，並無不能注意之情事，竟疏未注意及此，即貿然通過該交岔路口，適告訴人何佳沛騎乘車牌號碼SQ3-278號輕型機車，沿梧棲區○○路由北往南方向直行，亦行經上開路口，2車因而發生碰撞，致告訴人何佳沛人車倒地，因而受有右股骨幹骨折之傷害。案經告訴人何佳沛提出告訴，因認被告王國芳涉有刑法第284條第1項前段之過失傷害罪嫌。二、按告訴乃論之罪，告訴人於第一審辯論終結前，得撤回其告訴；又告訴經撤回者，應諭知不受理之判決，並得不經言詞辯論為之，刑事訴訟法第238條第1項、第303條第3款、第307條，分別定有明文。經查，本件被告王國芳被訴犯有刑法第284條第1項前段之過失傷害罪，依同法第287條前段之規定係屬告訴乃論之罪，茲據告訴人何佳沛於第一審辯論終結前，具狀撤回告訴，此有撤回告訴狀1份在卷可稽，揆諸上開說明，爰就此部分，不經言詞辯論，諭知不受理之判決。據上論斷，應依刑事訴訟法第303條第3款、第307條，判決如主文。中華民國100年12月30日交通法庭法官胡芷瑜以上正本證明與原本無異。如不服本判決，應於收受送達後10日內向本院提出上訴書狀，並應敘述具體理由；其未敘述上訴理由者，應於上訴期間屆滿後20日內向本院補提理由書（均須按他造當事人之人數附繕本）「切勿逕送上級法院」。書記官曾惠雅中華民國100年12月30日",
  "characters": {
    "judges": [
      "胡芷瑜"
    ],
    "prosecutors": [

    ],
    "lawyers": [

    ],
    "clerks": [
      "曾惠雅"
    ],
    "plaintiffs": [

    ],
    "defendants": [
      "王國芳"
    ],
    "prosecutor_office": [
      "臺灣臺中地方法院檢察署檢察官"
    ],
    "creditors": [

    ],
    "debtors": [

    ],
    "judicial_associate_officer": [

    ]
  },
  "adjudged_at": "2011-12-30",
  "created_at": "2016-02-13 13:30:36",
  "updated_at": "2016-02-13 13:30:36"
}