{
  "identify": "TND-100-訴-1559-20111229-1",
  "court": {
    "name": "臺灣南投地方法院",
    "code": "TND"
  },
  "division": {
    "name": "刑事",
    "code": "M"
  },
  "year": 100,
  "word": "訴",
  "number": "1559",
  "jcheck": "1",
  "reason": "違反毒品危害防制條例",
  "content": "臺灣臺南地方法院刑事判決             100年度訴字第1559號\n公  訴  人  臺灣臺南地方法院檢察署檢察官\n被      告  方峙斌\n上列被告因違反毒品危害防制條例案件，經檢察官提起公訴（10\n0年度毒偵字第1927號），被告於本院準備程序進行中，先就被\n訴事實為有罪之陳述，經本院合議庭裁定由受命法官獨任進行簡\n式審判程序，判決如下：\n    主  文\n方峙斌施用第一級毒品，處有期徒刑陸月，如易科罰金，以新臺\n幣貳仟元折算壹日。\n    事  實\n一、方峙斌前於民國97年間，因施用第一級毒品，經本院以97年\n    度毒聲字第226號裁定送觀察、勒戒後，認無繼續施用毒品\n    傾向，於97年8月8日執行完畢釋放。詎其仍未戒除毒癮，於\n    觀察、勒戒執行完畢釋放後5年內，明知海洛因為毒品危害\n    防制條例所列管之第一級毒品，依法不得施用、持有，竟基\n    於施用第一級毒品海洛因之犯意，於100年6月13日晚間6時\n    許，在其位於臺南市○○區○○路1段388巷31號住處二樓房\n    間內，以針筒注射之方式，施用第一級毒品海洛因1次。嗣\n    因方峙斌接獲臺灣臺南地方法院檢察署證人傳票，自願陪同\n    專案人員到憲兵隊說明案情，經其同意後，於100年6月16日\n    下午3時20分許採尿送驗，結果呈嗎啡陽性反應，使知悉上\n    情。\n二、案經高雄市政府警察局小港分局報請臺灣臺南地方法院檢察\n    署檢察官偵查起訴。\n    理    由\n一、本案被告方峙斌所犯係死刑、無期徒刑、最輕本刑為三年以\n    上有期徒刑以外之罪，亦非高等法院管轄之第一審案件，而\n    被告於本院行準備程序中，就被訴事實為有罪之陳述，經告\n    知簡式審判程序之旨，並聽取公訴人及被告之意見後，本院\n    合議庭依刑事訴訟法第273條之1第1項規定，裁定由受命法\n    官獨任進行簡式審判程序，合先敘明。\n二、訊據被告對於上揭犯罪事實坦承不諱，且其於100年6月16日\n    下午3時20分許，由警經其同意所採集之尿液檢體（編號J1\n    00296號），係由其親自排尿、裝填及封籤等情，業據被告\n    於警詢時供承無訛，並有高雄市政府警察局小港分局毒品案\n    件嫌疑人尿液代碼姓名登記表1紙在卷可據，而該尿液檢體\n    經送鑑驗結果，確呈嗎啡（即海洛因主要代謝物）之陽性反\n    應，則有臺灣檢驗科技股份有限公司100年7月6日編號KH/20\n    11/00000000號濫用藥物檢驗報告附卷足憑。又施用海洛因\n    後於尿液中排出之最長時限，受施用劑量、施用方式、個人\n    體質及代謝情況等因素影響，因個案而異，一般可檢出之最\n    長時間為海洛因服用後2至4天，此為本院職務上已知之事實\n    ，足認被告自白與事實相符，本案事證已臻明確，其於上開\n    時、地施用海洛因之犯行，堪以認定。\n三、按觀察、勒戒或強制戒治執行完畢釋放後，5年內再犯毒品\n    危害防制條例第10條之罪，檢察官或少年法院（地方法院少\n    年法庭）應依法追訴或裁定交付審理，毒品危害防制條例第\n    23條第2項定有明文。查被告前曾因施用毒品，受有如事實\n    欄所示之觀察、勒戒執行情形，有本院被告前案紀錄表附卷\n    可稽。從而，被告於前揭時地施用第一級毒品海洛因1次，\n    顯係在觀察、勒戒執行完畢釋放後5年內再犯毒品危害防制\n    條例第10條之罪，是公訴人依法追訴，並無不合，自應依法\n    論科。\n四、核被告方峙斌所為，係犯毒品危害防制條例第10條第1項之\n    施用第一級毒品罪。其於施用前持有海洛因之低度行為，應\n    為施用之高度行為所吸收，不另論罪。爰審酌被告自述教育\n    程度為國中畢業，已婚，目前擔任廚師，每月收入約新臺幣\n    （下同）3萬元，有一年僅6歲之幼女及雙親需其扶養照護，\n    全家生計均仰賴被告撐持等智識程度、生活狀況；其前因施\n    用毒品經觀察、勒戒後，仍無法斷絕施用毒品惡習，顯見其\n    意志力薄弱，惟施用毒品僅戕害自己身心，並無加害他人，\n    且其犯後始終坦承犯行，並於犯罪後之100年9月28日起定期\n    至奇美醫院進行戒毒治療，已有成效，分別於100年11月15\n    日、同年12月1日檢驗均無毒品反應等情，業據提出診斷證\n    明書影本1紙、藥毒物檢驗報告2份為證，顯見其確有悔悟之\n    心，態度良好等一切情狀，量處如主文所示之刑，並諭知易\n    科罰金之折算標準。\n據上論斷，應依刑事訴訟法第273條之1第1項、第299條第1項前\n段，毒品危害防制條例第10條第1項，刑法第11條前段、第41條\n第1項前段，判決如主文。\n本案經檢察官郭書鳴到庭執行職務\n中    華    民    國   100    年    12    月    29    日\n                  刑事第十一庭法  官   許嘉容\n以上正本證明與原本無異。\n如不服本判決應於收受本判決後10日內向本院提出上訴書狀，並\n應敘述具體理由。其未敘述上訴理由者，應於上訴期間屆滿後20\n日內向本院補提理由書狀（均須按他造當事人之人數附繕本）「\n切勿逕送上級法院」。\n                              書記官   陳玉芬\n中    華    民    國   100    年    12    月    29    日\n附錄本案論罪科刑法條：\n毒品危害防制條例第10條第1項\n施用第一級毒品者，處6月以上5年以下有期徒刑。",
  "structure": {
    "main": "方峙斌施用第一級毒品，處有期徒刑陸月，如易科罰金，以新臺\n幣貳仟元折算壹日。",
    "fact": "一、方峙斌前於民國97年間，因施用第一級毒品，經本院以97年\n    度毒聲字第226號裁定送觀察、勒戒後，認無繼續施用毒品\n    傾向，於97年8月8日執行完畢釋放。詎其仍未戒除毒癮，於\n    觀察、勒戒執行完畢釋放後5年內，明知海洛因為毒品危害\n    防制條例所列管之第一級毒品，依法不得施用、持有，竟基\n    於施用第一級毒品海洛因之犯意，於100年6月13日晚間6時\n    許，在其位於臺南市○○區○○路1段388巷31號住處二樓房\n    間內，以針筒注射之方式，施用第一級毒品海洛因1次。嗣\n    因方峙斌接獲臺灣臺南地方法院檢察署證人傳票，自願陪同\n    專案人員到憲兵隊說明案情，經其同意後，於100年6月16日\n    下午3時20分許採尿送驗，結果呈嗎啡陽性反應，使知悉上\n    情。\n二、案經高雄市政府警察局小港分局報請臺灣臺南地方法院檢察\n    署檢察官偵查起訴。",
    "reason": "一、本案被告方峙斌所犯係死刑、無期徒刑、最輕本刑為三年以\n    上有期徒刑以外之罪，亦非高等法院管轄之第一審案件，而\n    被告於本院行準備程序中，就被訴事實為有罪之陳述，經告\n    知簡式審判程序之旨，並聽取公訴人及被告之意見後，本院\n    合議庭依刑事訴訟法第273條之1第1項規定，裁定由受命法\n    官獨任進行簡式審判程序，合先敘明。\n二、訊據被告對於上揭犯罪事實坦承不諱，且其於100年6月16日\n    下午3時20分許，由警經其同意所採集之尿液檢體（編號J1\n    00296號），係由其親自排尿、裝填及封籤等情，業據被告\n    於警詢時供承無訛，並有高雄市政府警察局小港分局毒品案\n    件嫌疑人尿液代碼姓名登記表1紙在卷可據，而該尿液檢體\n    經送鑑驗結果，確呈嗎啡（即海洛因主要代謝物）之陽性反\n    應，則有臺灣檢驗科技股份有限公司100年7月6日編號KH/20\n    11/00000000號濫用藥物檢驗報告附卷足憑。又施用海洛因\n    後於尿液中排出之最長時限，受施用劑量、施用方式、個人\n    體質及代謝情況等因素影響，因個案而異，一般可檢出之最\n    長時間為海洛因服用後2至4天，此為本院職務上已知之事實\n    ，足認被告自白與事實相符，本案事證已臻明確，其於上開\n    時、地施用海洛因之犯行，堪以認定。\n三、按觀察、勒戒或強制戒治執行完畢釋放後，5年內再犯毒品\n    危害防制條例第10條之罪，檢察官或少年法院（地方法院少\n    年法庭）應依法追訴或裁定交付審理，毒品危害防制條例第\n    23條第2項定有明文。查被告前曾因施用毒品，受有如事實\n    欄所示之觀察、勒戒執行情形，有本院被告前案紀錄表附卷\n    可稽。從而，被告於前揭時地施用第一級毒品海洛因1次，\n    顯係在觀察、勒戒執行完畢釋放後5年內再犯毒品危害防制\n    條例第10條之罪，是公訴人依法追訴，並無不合，自應依法\n    論科。\n四、核被告方峙斌所為，係犯毒品危害防制條例第10條第1項之\n    施用第一級毒品罪。其於施用前持有海洛因之低度行為，應\n    為施用之高度行為所吸收，不另論罪。爰審酌被告自述教育\n    程度為國中畢業，已婚，目前擔任廚師，每月收入約新臺幣\n    （下同）3萬元，有一年僅6歲之幼女及雙親需其扶養照護，\n    全家生計均仰賴被告撐持等智識程度、生活狀況；其前因施\n    用毒品經觀察、勒戒後，仍無法斷絕施用毒品惡習，顯見其\n    意志力薄弱，惟施用毒品僅戕害自己身心，並無加害他人，\n    且其犯後始終坦承犯行，並於犯罪後之100年9月28日起定期\n    至奇美醫院進行戒毒治療，已有成效，分別於100年11月15\n    日、同年12月1日檢驗均無毒品反應等情，業據提出診斷證\n    明書影本1紙、藥毒物檢驗報告2份為證，顯見其確有悔悟之\n    心，態度良好等一切情狀，量處如主文所示之刑，並諭知易\n    科罰金之折算標準。\n據上論斷，應依刑事訴訟法第273條之1第1項、第299條第1項前\n段，毒品危害防制條例第10條第1項，刑法第11條前段、第41條\n第1項前段，判決如主文。\n本案經檢察官郭書鳴到庭執行職務\n中    華    民    國   100    年    12    月    29    日\n                  刑事第十一庭法  官   許嘉容\n以上正本證明與原本無異。\n如不服本判決應於收受本判決後10日內向本院提出上訴書狀，並\n應敘述具體理由。其未敘述上訴理由者，應於上訴期間屆滿後20\n日內向本院補提理由書狀（均須按他造當事人之人數附繕本）「\n切勿逕送上級法院」。\n                              書記官   陳玉芬"
  },
  "search": "臺灣臺南地方法院刑事判決100年度訴字第1559號公訴人臺灣臺南地方法院檢察署檢察官被告方峙斌上列被告因違反毒品危害防制條例案件，經檢察官提起公訴（100年度毒偵字第1927號），被告於本院準備程序進行中，先就被訴事實為有罪之陳述，經本院合議庭裁定由受命法官獨任進行簡式審判程序，判決如下：主文方峙斌施用第一級毒品，處有期徒刑陸月，如易科罰金，以新臺幣貳仟元折算壹日。事實一、方峙斌前於民國97年間，因施用第一級毒品，經本院以97年度毒聲字第226號裁定送觀察、勒戒後，認無繼續施用毒品傾向，於97年8月8日執行完畢釋放。詎其仍未戒除毒癮，於觀察、勒戒執行完畢釋放後5年內，明知海洛因為毒品危害防制條例所列管之第一級毒品，依法不得施用、持有，竟基於施用第一級毒品海洛因之犯意，於100年6月13日晚間6時許，在其位於臺南市○○區○○路1段388巷31號住處二樓房間內，以針筒注射之方式，施用第一級毒品海洛因1次。嗣因方峙斌接獲臺灣臺南地方法院檢察署證人傳票，自願陪同專案人員到憲兵隊說明案情，經其同意後，於100年6月16日下午3時20分許採尿送驗，結果呈嗎啡陽性反應，使知悉上情。二、案經高雄市政府警察局小港分局報請臺灣臺南地方法院檢察署檢察官偵查起訴。理由一、本案被告方峙斌所犯係死刑、無期徒刑、最輕本刑為三年以上有期徒刑以外之罪，亦非高等法院管轄之第一審案件，而被告於本院行準備程序中，就被訴事實為有罪之陳述，經告知簡式審判程序之旨，並聽取公訴人及被告之意見後，本院合議庭依刑事訴訟法第273條之1第1項規定，裁定由受命法官獨任進行簡式審判程序，合先敘明。二、訊據被告對於上揭犯罪事實坦承不諱，且其於100年6月16日下午3時20分許，由警經其同意所採集之尿液檢體（編號J100296號），係由其親自排尿、裝填及封籤等情，業據被告於警詢時供承無訛，並有高雄市政府警察局小港分局毒品案件嫌疑人尿液代碼姓名登記表1紙在卷可據，而該尿液檢體經送鑑驗結果，確呈嗎啡（即海洛因主要代謝物）之陽性反應，則有臺灣檢驗科技股份有限公司100年7月6日編號KH/2011/00000000號濫用藥物檢驗報告附卷足憑。又施用海洛因後於尿液中排出之最長時限，受施用劑量、施用方式、個人體質及代謝情況等因素影響，因個案而異，一般可檢出之最長時間為海洛因服用後2至4天，此為本院職務上已知之事實，足認被告自白與事實相符，本案事證已臻明確，其於上開時、地施用海洛因之犯行，堪以認定。三、按觀察、勒戒或強制戒治執行完畢釋放後，5年內再犯毒品危害防制條例第10條之罪，檢察官或少年法院（地方法院少年法庭）應依法追訴或裁定交付審理，毒品危害防制條例第23條第2項定有明文。查被告前曾因施用毒品，受有如事實欄所示之觀察、勒戒執行情形，有本院被告前案紀錄表附卷可稽。從而，被告於前揭時地施用第一級毒品海洛因1次，顯係在觀察、勒戒執行完畢釋放後5年內再犯毒品危害防制條例第10條之罪，是公訴人依法追訴，並無不合，自應依法論科。四、核被告方峙斌所為，係犯毒品危害防制條例第10條第1項之施用第一級毒品罪。其於施用前持有海洛因之低度行為，應為施用之高度行為所吸收，不另論罪。爰審酌被告自述教育程度為國中畢業，已婚，目前擔任廚師，每月收入約新臺幣（下同）3萬元，有一年僅6歲之幼女及雙親需其扶養照護，全家生計均仰賴被告撐持等智識程度、生活狀況；其前因施用毒品經觀察、勒戒後，仍無法斷絕施用毒品惡習，顯見其意志力薄弱，惟施用毒品僅戕害自己身心，並無加害他人，且其犯後始終坦承犯行，並於犯罪後之100年9月28日起定期至奇美醫院進行戒毒治療，已有成效，分別於100年11月15日、同年12月1日檢驗均無毒品反應等情，業據提出診斷證明書影本1紙、藥毒物檢驗報告2份為證，顯見其確有悔悟之心，態度良好等一切情狀，量處如主文所示之刑，並諭知易科罰金之折算標準。據上論斷，應依刑事訴訟法第273條之1第1項、第299條第1項前段，毒品危害防制條例第10條第1項，刑法第11條前段、第41條第1項前段，判決如主文。本案經檢察官郭書鳴到庭執行職務中華民國100年12月29日刑事第十一庭法官許嘉容以上正本證明與原本無異。如不服本判決應於收受本判決後10日內向本院提出上訴書狀，並應敘述具體理由。其未敘述上訴理由者，應於上訴期間屆滿後20日內向本院補提理由書狀（均須按他造當事人之人數附繕本）「切勿逕送上級法院」。書記官陳玉芬中華民國100年12月29日附錄本案論罪科刑法條：毒品危害防制條例第10條第1項施用第一級毒品者，處6月以上5年以下有期徒刑。",
  "characters": {
    "judges": [
      "許嘉容"
    ],
    "prosecutors": [
      "郭書鳴"
    ],
    "lawyers": [

    ],
    "clerks": [
      "陳玉芬"
    ],
    "plaintiffs": [

    ],
    "defendants": [
      "方峙斌"
    ],
    "prosecutor_office": [
      "臺灣臺南地方法院檢察署檢察官"
    ],
    "creditors": [

    ],
    "debtors": [

    ],
    "judicial_associate_officer": [

    ]
  },
  "adjudged_at": "2011-12-29",
  "created_at": "2016-02-13 13:37:25",
  "updated_at": "2016-02-13 13:37:25"
}