{
  "identify": "TND-100-交簡-3289-20111229-1",
  "court": {
    "name": "臺灣臺南地方法院",
    "code": "TND"
  },
  "division": {
    "name": "刑事",
    "code": "M"
  },
  "year": 100,
  "word": "交簡",
  "number": "3289",
  "jcheck": "1",
  "reason": "公共危險",
  "content": "臺灣臺南地方法院刑事簡易判決   100年度交簡字第3289號\n聲  請  人  臺灣臺南地方法院檢察署檢察官\n被      告  陳錫泰\n上列被告因公共危險案件，經檢察官聲請以簡易判決處刑（100\n年度速偵字第150號），本院判決如下：\n    主  文\n陳錫泰因服用酒類，不能安全駕駛動力交通工具而駕駛，處有期\n徒刑參月，如易科罰金，以新臺幣壹仟元折算壹日。\n    理  由\n一、本件犯罪事實、證據，與檢察官聲請簡易判決處刑書之記載\n    相同，茲引用之（如附件）。\n二、核被告所為，係犯刑法第185條之3第1項公共危險罪。另按\n    刑法第185條之3條業於100年11月30日經總統以華總一義字\n    第10000263911號令修正公布，並自公布日施行，於100年12\n    月2日生效，查被告本件醉後駕車行為係發生在100年12月5\n    日，自應適用修正後刑法第185條之3第1項：「服用毒品、\n    麻醉藥品、酒類或其他相類之物，不能安全駕駛動力交通工\n    具而駕駛者，處2年以下有期徒刑、拘役或科或併科20萬元\n    以下罰金。」之規定，本件聲請簡易判決處刑書附錄所犯法\n    條部分記載：『中華民國刑法第185 條之3：「服用毒品、\n    麻醉藥品、酒類或其他相類之物，不能安全駕駛動力交通工\n    具而駕駛者，處1年以下有期徒刑、拘役或科或併科15萬元\n    以下罰金。」』等語，係屬誤載，附此敘明。\n三、本院審酌被告已有2次醉後駕車行為為警查獲之紀錄，且目\n    前仍在前案緩起訴處分期間，有臺灣高等法院被告前案紀錄\n    表1份附卷可參，詎其猶不知悔改，第3度醉後駕車，且本次\n    為警查獲時所測得之吐氣酒精濃度高達每公升0.88毫克，惡\n    性非輕，惟念其犯罪後業已坦白承認所為，犯後態度尚稱良\n    好，且未造成其他人員、財物之損失等一切情狀，本院乃量\n    處如主文所示之刑，並諭知易科罰金之折算標準。至於被告\n    雖辯稱係因當日為女兒歸寧婚宴，有友人遠道而來赴宴，婚\n    宴後又邀約聚會，因時值深夜，無法招攬計程車，才會不得\n    已醉後騎乘機車外出赴約云云，並提出喜帖1份為證。查，\n    縱被告所稱上情屬實，然被告已有醉後駕車為警查獲之紀錄\n    ，且仍因前案醉後駕車之違法行為尚在緩起訴處分期間，已\n    如前述，其應較一般人更深知不得醉後駕車，因此，其陳稱\n    上述違法行為之動機，實不值同情，本院難依此作為從輕量\n    刑之參考依據，附此敘明。\n四、應依刑事訴訟法第449條第1項前段、第3項、第454條第2項\n    ，第185條之3第1項、第41條第1項前段，刑法施行法第1條\n    之1，逕以簡易判決如主文。\n五、如不服本判決，得自收受送達之日起10日內向本院提出上訴\n    狀，上訴於本院第二審合議庭（須附繕本）。\n中    華    民    國   100    年    12    月    29    日\n                  刑事第十庭    法  官  陳淑勤\n以上正本證明與原本無異。\n如不服本判決應於收受送達後10日內向本院提出上訴書狀（應附\n繕本）。\n                                書記官  蔡志賢\n中    華    民    國   100    年    12    月    30    日\n附錄本案論罪科刑法條：\n刑法第185條之3第1項\n服用毒品、麻醉藥品、酒類或其他相類之物，不能安全駕駛動力\n交通工具而駕駛者，處2年以下有期徒刑、拘役或科或併科20 萬\n元以下罰金。",
  "structure": {
    "main": "陳錫泰因服用酒類，不能安全駕駛動力交通工具而駕駛，處有期\n徒刑參月，如易科罰金，以新臺幣壹仟元折算壹日。",
    "reason": "一、本件犯罪事實、證據，與檢察官聲請簡易判決處刑書之記載\n    相同，茲引用之（如附件）。\n二、核被告所為，係犯刑法第185條之3第1項公共危險罪。另按\n    刑法第185條之3條業於100年11月30日經總統以華總一義字\n    第10000263911號令修正公布，並自公布日施行，於100年12\n    月2日生效，查被告本件醉後駕車行為係發生在100年12月5\n    日，自應適用修正後刑法第185條之3第1項：「服用毒品、\n    麻醉藥品、酒類或其他相類之物，不能安全駕駛動力交通工\n    具而駕駛者，處2年以下有期徒刑、拘役或科或併科20萬元\n    以下罰金。」之規定，本件聲請簡易判決處刑書附錄所犯法\n    條部分記載：『中華民國刑法第185 條之3：「服用毒品、\n    麻醉藥品、酒類或其他相類之物，不能安全駕駛動力交通工\n    具而駕駛者，處1年以下有期徒刑、拘役或科或併科15萬元\n    以下罰金。」』等語，係屬誤載，附此敘明。\n三、本院審酌被告已有2次醉後駕車行為為警查獲之紀錄，且目\n    前仍在前案緩起訴處分期間，有臺灣高等法院被告前案紀錄\n    表1份附卷可參，詎其猶不知悔改，第3度醉後駕車，且本次\n    為警查獲時所測得之吐氣酒精濃度高達每公升0.88毫克，惡\n    性非輕，惟念其犯罪後業已坦白承認所為，犯後態度尚稱良\n    好，且未造成其他人員、財物之損失等一切情狀，本院乃量\n    處如主文所示之刑，並諭知易科罰金之折算標準。至於被告\n    雖辯稱係因當日為女兒歸寧婚宴，有友人遠道而來赴宴，婚\n    宴後又邀約聚會，因時值深夜，無法招攬計程車，才會不得\n    已醉後騎乘機車外出赴約云云，並提出喜帖1份為證。查，\n    縱被告所稱上情屬實，然被告已有醉後駕車為警查獲之紀錄\n    ，且仍因前案醉後駕車之違法行為尚在緩起訴處分期間，已\n    如前述，其應較一般人更深知不得醉後駕車，因此，其陳稱\n    上述違法行為之動機，實不值同情，本院難依此作為從輕量\n    刑之參考依據，附此敘明。\n四、應依刑事訴訟法第449條第1項前段、第3項、第454條第2項\n    ，第185條之3第1項、第41條第1項前段，刑法施行法第1條\n    之1，逕以簡易判決如主文。\n五、如不服本判決，得自收受送達之日起10日內向本院提出上訴\n    狀，上訴於本院第二審合議庭（須附繕本）。"
  },
  "search": "臺灣臺南地方法院刑事簡易判決100年度交簡字第3289號聲請人臺灣臺南地方法院檢察署檢察官被告陳錫泰上列被告因公共危險案件，經檢察官聲請以簡易判決處刑（100年度速偵字第150號），本院判決如下：主文陳錫泰因服用酒類，不能安全駕駛動力交通工具而駕駛，處有期徒刑參月，如易科罰金，以新臺幣壹仟元折算壹日。理由一、本件犯罪事實、證據，與檢察官聲請簡易判決處刑書之記載相同，茲引用之（如附件）。二、核被告所為，係犯刑法第185條之3第1項公共危險罪。另按刑法第185條之3條業於100年11月30日經總統以華總一義字第10000263911號令修正公布，並自公布日施行，於100年12月2日生效，查被告本件醉後駕車行為係發生在100年12月5日，自應適用修正後刑法第185條之3第1項：「服用毒品、麻醉藥品、酒類或其他相類之物，不能安全駕駛動力交通工具而駕駛者，處2年以下有期徒刑、拘役或科或併科20萬元以下罰金。」之規定，本件聲請簡易判決處刑書附錄所犯法條部分記載：『中華民國刑法第185條之3：「服用毒品、麻醉藥品、酒類或其他相類之物，不能安全駕駛動力交通工具而駕駛者，處1年以下有期徒刑、拘役或科或併科15萬元以下罰金。」』等語，係屬誤載，附此敘明。三、本院審酌被告已有2次醉後駕車行為為警查獲之紀錄，且目前仍在前案緩起訴處分期間，有臺灣高等法院被告前案紀錄表1份附卷可參，詎其猶不知悔改，第3度醉後駕車，且本次為警查獲時所測得之吐氣酒精濃度高達每公升0.88毫克，惡性非輕，惟念其犯罪後業已坦白承認所為，犯後態度尚稱良好，且未造成其他人員、財物之損失等一切情狀，本院乃量處如主文所示之刑，並諭知易科罰金之折算標準。至於被告雖辯稱係因當日為女兒歸寧婚宴，有友人遠道而來赴宴，婚宴後又邀約聚會，因時值深夜，無法招攬計程車，才會不得已醉後騎乘機車外出赴約云云，並提出喜帖1份為證。查，縱被告所稱上情屬實，然被告已有醉後駕車為警查獲之紀錄，且仍因前案醉後駕車之違法行為尚在緩起訴處分期間，已如前述，其應較一般人更深知不得醉後駕車，因此，其陳稱上述違法行為之動機，實不值同情，本院難依此作為從輕量刑之參考依據，附此敘明。四、應依刑事訴訟法第449條第1項前段、第3項、第454條第2項，第185條之3第1項、第41條第1項前段，刑法施行法第1條之1，逕以簡易判決如主文。五、如不服本判決，得自收受送達之日起10日內向本院提出上訴狀，上訴於本院第二審合議庭（須附繕本）。中華民國100年12月29日刑事第十庭法官陳淑勤以上正本證明與原本無異。如不服本判決應於收受送達後10日內向本院提出上訴書狀（應附繕本）。書記官蔡志賢中華民國100年12月30日附錄本案論罪科刑法條：刑法第185條之3第1項服用毒品、麻醉藥品、酒類或其他相類之物，不能安全駕駛動力交通工具而駕駛者，處2年以下有期徒刑、拘役或科或併科20萬元以下罰金。",
  "characters": {
    "judges": [
      "陳淑勤"
    ],
    "prosecutors": [

    ],
    "lawyers": [

    ],
    "clerks": [
      "蔡志賢"
    ],
    "plaintiffs": [

    ],
    "defendants": [
      "陳錫泰"
    ],
    "prosecutor_office": [
      "臺灣臺南地方法院檢察署檢察官"
    ],
    "creditors": [

    ],
    "debtors": [

    ],
    "judicial_associate_officer": [

    ]
  },
  "adjudged_at": "2011-12-29",
  "created_at": "2016-02-13 13:46:13",
  "updated_at": "2016-02-13 13:46:13"
}