{
  "identify": "TYD-100-訴-747-20111230-1",
  "court": {
    "name": "臺灣桃園地方法院",
    "code": "TYD"
  },
  "division": {
    "name": "刑事",
    "code": "M"
  },
  "year": 100,
  "word": "訴",
  "number": "747",
  "jcheck": "1",
  "reason": "商業會計法等",
  "content": "臺灣桃園地方法院刑事判決              100年度訴字第747號\n公  訴  人  臺灣桃園地方法院檢察署檢察官\n被      告  林燦榮\n選任辯護人  郭啟榮律師\n上列被告因商業會計法等案件，經檢察官提起公訴（99年度偵字\n第19812 、23189 號），本院判決如下：\n    主  文\n林燦榮連續犯商業會計法第七十一條第一款之填製不實罪，處有\n期徒刑伍月，如易科罰金，以銀元佰元即新臺幣玖佰元折算壹\n日；減為有期徒刑貳月又拾伍日，如易科罰金，以銀元佰元即\n新臺幣玖佰元折算壹日。又連續犯稅捐稽徵法第四十三條第一項\n之幫助逃漏稅捐罪，處有期徒刑參月，如易科罰金，以銀元佰\n元即新臺幣玖佰元折算壹日；減為有期徒刑壹月又拾伍日，如易\n科罰金，以銀元佰元即新臺幣玖佰元折算壹日。又連續犯稅捐\n稽徵法第四十一條第一項之逃漏稅捐罪，處有期徒刑陸月，如易\n科罰金，以銀元佰元即新臺幣玖佰元折算壹日；減為有期徒刑\n參月，如易科罰金，以銀元佰元即新臺幣玖佰元折算壹日。應\n執行有期徒刑陸月，如易科罰金，以銀元佰元即新臺幣玖佰元\n折算壹日。緩刑貳年。\n    事  實\n一、林燦榮於民國90至93年間，為址設桃園縣龍潭鄉九龍村23鄰\n    九座寮43-6號之「金太陽精密工業股份有限公司（下稱金太\n    陽公司）」之負責人，係商業會計法規範之商業負責人，處\n    理公司之會計及開立統一發票事務；林燦榮另為址設桃園市\n    ○○里○○路2 段1 號4 樓之「鋒沐股份有限公司（下稱鋒\n    沐公司）」之實際負責人，鋒沐公司、金太陽公司均為稅捐\n    稽徵法之納稅義務人。林燦榮明知統一發票係商業會計法所\n    規定之會計憑證，倘無實際銷售營業或提供勞務之事實，不\n    得虛偽開立，竟違反營業人銷售貨物或勞務時，應依據所銷\n    售貨物或勞務之實際內容據實開立統一發票之規定，基於不\n    實填載會計憑證、幫助逃漏稅捐及逃漏稅捐之概括犯意，而\n    為下列行為：\n（一）其明知鋒沐公司於90年11月起至91年12月間止，並無銷貨\n      予「莊頭北工業股份有限公司（下稱莊頭北公司）」之事\n      實，惟為虛增鋒沐公司營收，竟連續填製不實事項而虛偽\n      開立如附表一所示，面額共計新臺幣（下同）67,192,274\n      元，無實際上交易事實之不實銷項統一發票共91紙，交付\n      納稅義務人莊頭北公司充作進貨憑證，供莊頭北公司持向\n      稅捐稽徵機關申報各期營業稅時，誆稱該等統一發票係進\n      項成本而為行使，持以虛報為進項成本以扣抵銷項稅額，\n      而幫助莊頭北公司逃漏營業稅，足以生損害於稅捐稽徵機\n      關對於稅捐稽徵業務管理與課稅之公平及正確性。\n（二）林燦榮明知鋒沐公司於90年11月至91年10月間，並無向劉\n      敏雄（另案為不起訴處分）所經營之「連勝莊興業有限公\n      司（下稱連勝莊公司）」進貨；於91年3 月至12月間，亦\n      未向白晉強（已歿）所經營之「豐莊興業有限公司（下稱\n      豐莊公司）」進貨；然為避免前開虛增營收之行為將大幅\n      提高應繳營業稅，竟基於幫助鋒沐公司逃漏稅捐之概括犯\n      意，經由莊頭北公司負責人取得如附表二編號1 所示連勝\n      莊公司所虛開，面額總計46,725,186元之不實統一發票共\n      74張及如附表二編號2 所示豐莊公司所虛開之面額總計24\n      ,012,895元之不實統一發票63張，充作鋒沐公司進項憑證\n      ，申報扣抵銷項稅額，以此逃漏如附表二各扣除虛報銷項\n      及進項稅額實際逃漏稅額欄所示之營業稅，總計逃漏稅額\n      671,802 元，以此方式侵害國家稅收，足以生損害於稅捐\n      稽徵機關對於稅捐稽徵業務管理與課稅之公平及正確性。\n（三）其復明知金太陽公司於92年6 月起至93年6 月間止，與虛\n      設行號之「天技科技有限公司（下稱天技公司）」、「赫\n      拉科技股份有限公司（下稱赫拉公司）」間並無實際營業\n      往來之事實，惟為虛增金太陽公司營收、提高業績，而承\n      上揭連續填製不實事項之犯意，填製不實會計憑證而虛偽\n      開立如附表三所示，面額共計36,237,323元，無實際上交\n      易事實之不實銷項統一發票共41紙，分別交付天技公司、\n      赫拉公司充作進貨憑證，天技、赫拉公司並持向稅捐稽徵\n      機關申報不實進項（虛設公司並無實際營業行為，無逃漏\n      營業稅之問題），足以生損害於稅捐稽徵機關對於稅捐稽\n      徵業務管理正確性。\n（四）林燦榮明知金太陽公司於92年7 月至93年5 月間，並無向\n      天技公司、赫拉公司進貨，而基於逃漏稅捐之概括犯意，\n      取得如附表四編號1 所示天技公司所虛開，面額計28,340\n      ,060元之不實統一發票28張、附表四編號2 所示赫拉公司\n      所虛開，面額計4,802,450 元之統一發票4 張，充作金太\n      陽公司進項憑證，申報扣抵銷項稅額，以此逃漏如附表四\n      各扣除虛報銷項及進項稅額實際逃漏稅額欄所示之營業稅\n      ，總計逃漏稅額576,794 元，足以生損害於稅捐稽徵機關\n      對於稅捐稽徵業務管理與課稅之公平及正確性。\n二、案經財政部臺灣省北區國稅局移送及臺灣桃園地方法院檢察\n    署檢察官自動檢舉偵查起訴。\n    理  由\n一、本件經本院加以審酌之下列所引用各項證據方法之證據能力\n    ，業經檢察官、被告及辯護人於準備程序均不爭執其證據能\n    力並同意作為證據（見本院審訴字卷第20頁反面），且於言\n    詞辯論終結前未聲明異議，本院審酌該等書面陳述作成之情\n    況，核無違法取證或其他瑕疵，且與待證事實具有關聯性，\n    認為以之作為證據為適當，依刑事訴訟法第159 條之5 規定\n    ，得採為證據。\n二、認定犯罪事實之證據及理由：\n（一）上開事實，業據被告於本院自白（見本院訴字卷第58頁反\n      面）。\n（二）並經證人即另案被告曾繁堯、劉敏雄、陳森炎、莊浩仁證\n      述明確（分見第20654 號偵查卷一第190 至194 頁、卷二\n      第108 至111 、131 至134 頁）。\n（三）及財政部臺灣省北區國稅局查緝案件稽查報告及相關資料\n      、鋒沐公司90年11月至91年12月進項來源分析表、銷項去\n      路明細、營業人進銷項交易對彙加明細表、開立不實統一\n      發票明細表、專案申請調檔統一發票查核名冊及清單、已\n      扣抵銷項稅額專案申請調檔統一發票查名冊及清單、欠稅\n      總歸戶查詢情形表、及申報書跨中心查詢、鋒沐公司申報\n      書跨中心查詢1 紙暨進銷或統一發票來源分析、莊頭北公\n      司營業稅年度資料查詢- 進項來源明細（見第20654 號偵\n      查卷一第5 至13、159 至183 頁、卷二第4 、5 至21、23\n      至51頁）等證在卷可查。\n（四）及金太陽公司92年5 月至93年6 月進項來源分析表、銷項\n      去路明細、營業人進銷項交易對彙加明細表、開立不實統\n      一發票明細表、專案申請調檔統一發票查名冊及清單、已\n      扣抵銷項稅額專案申請調檔統一發票查核名冊清單、欠稅\n      總歸戶查詢情形表、申報書跨中心查詢、金太陽公司營業\n      人銷售額與稅額申報書等（見第19812 號偵查卷第5 至12\n      、25至56頁）可稽。\n（五）此外，並有財政部臺灣省北區國稅局函暨檢附之鋒沐公司\n      、金太陽公司扣除虛報銷項及進項稅額按每期實際逃漏稅\n      計算表、財政部臺灣省北區國稅局桃園縣分局函暨檢附之\n      鋒沐公司90、91年度營利事業所得稅結算申報核定通知書\n      及調整法令及依據說明書等件（見本院訴字卷第9 至13、\n      17至21、25至40頁）在卷可資佐證。\n（六）綜上，足認被告前揭任意性之自白，核與事實相符，堪以\n      採信。是本案事證明確，被告犯行洵堪認定。\n三、論罪科刑：\n（一）新舊法比較：被告行為後，刑法業於94年2 月2 日修正公\n      布，95年7 月1 日起施行。按行為後法律有變更者，適用\n      行為時之法律，但行為後之法律有利於行為人者，適用最\n      有利於行為人之法律，修正後刑法第2 條第1 項定有明文\n      。此條規定係規範行為後法律變更所生新舊法律比較適用\n      之準據法，本身尚無新舊法比較之問題，於新法施行後，\n      應一律適用新法第2 條第1 項之規定，為「從舊從輕」之\n      比較。而本次法律變更，比較時應就罪刑有關之共犯、未\n      遂犯、想像競合犯、牽連犯、連續犯、結合犯，以及累犯\n      加重、自首減輕暨其他法定加減原因（如身分加減）與加\n      減例等一切情形，綜其全部罪刑之結果而為比較（最高法\n      院95年5 月23日95年度第8 次刑事庭會議決議參照）。經\n      查：\n   1、修正前商業會計法第71條第1 款、稅捐稽徵法第43條第1\n      項，法定刑罰金部分，依修正後刑法第33條第5 款之規定\n      ，最低額為新臺幣1,000 元，惟依被告行為時之刑法第33\n      條第5 款規定，罰金之最低額僅新臺幣30元。比較修正前\n      後之刑罰法律，適用修正前之規定，對被告較為有利。\n   2、修正後刑法業已刪除第56條連續犯之規定。是於新法修正\n      施行後，行為人之數犯罪行為，即須分論併罰。此刪除雖\n      非犯罪構成要件之變更，但顯已影響行為人刑罰之法律效\n      果，自屬法律有變更，比較新舊法結果，適用被告行為時\n      法律即依舊法論以連續犯，對被告較為有利。\n   3、刑法第55條關於牽連犯之規定亦經刪除，則被告所犯各罪\n      ，應予分論併罰，比較新舊法結果，以適用被告行為時之\n      法律即修正前刑法第55條牽連犯之規定，較有利於被告。\n   4、罰金刑之加重，依修正後刑法第67條規定，其最高度及最\n      低度同加重之，較修正前刑法第68條所定，僅加重其最高\n      度，為不利於被告。\n   5、關於易科罰金之折算標準，依被告行為時之刑法第41條第\n      1 項、罰金罰鍰提高標準條例第2 條規定，係以銀元100\n      元、200 元或300 元，即新臺幣300 元、600 元或900 元\n      折算1 日；依修正後刑法第41條第1 項，則係以新臺幣1,\n      000 元、2,000 元或3,000 元折算1 日，經比較新舊法，\n      舊法對被告較為有利。\n   6、關於定應執行刑，被告行為後，修正後刑法第51條第5 款\n      規定：「宣告多數有期徒刑者，於各刑中之最長期以上，\n      各刑合併之刑期以下，定其刑期。但不得逾30年。」，與\n      修正前同條款規定：「宣告多數有期徒刑者，於各刑中之\n      最長期以上，各刑合併之刑期以下，定其刑期。但不得逾\n      20年。」之規定比較，自以修正前規定，對被告較為有利\n      。\n   7、綜上，經綜合法律修正前後之整體比較，揆諸前揭最高法\n      院決議及修正後刑法第2 條第1 項之「從舊從輕」原則，\n      適用94年2 月2 日修正前之刑罰法律，對被告較為有利，\n      自應適用修正前刑法之相關規定。\n   8、又查被告行為後，商業會計法第71條亦於95年5 月24日修\n      正公佈，並自同年月26日起施行。該條法定刑中關於罰金\n      部分，由修正前「或科或併科新臺幣15萬元以下罰金」，\n      經修正提高為「或科或併科新臺幣60萬元以下罰金」，依\n      刑法第2 條第1 項前段之「從舊從輕」原則，適用修正前\n      之規定。又被告行為後，稅捐稽徵法第47條業於98年5 月\n      27日修正公布，同年月29日生效，修正前第47條規定：「\n      本法關於納稅義務人、扣繳義務人及代徵人應處徒刑之規\n      定，於左列之人適用之：一、公司法規定之公司負責人。\n      二、民法或其他法律規定對外代表法人之董事或理事。三\n      、商業登記法規定之商業負責人。四、其他非法人團體之\n      代表人或管理人。」修正後該條則另立第二項規定「前項\n      規定之人與實際負責業務之人不同時，以實際負責業務之\n      人為準」。可見舊法並未將「實際負責人」列為公司負責\n      人（最高法院95年度台上字第741 號判決意旨參照）。查\n      鋒沐公司自84年間起至93年間，登記負責人均為曾繁堯一\n      節，有桃園縣稅捐稽徵處函及該公司之營利事業統一發證\n      變更登記申請書、變更登記事項卡等附卷可證（見第2065\n      4 號偵查卷一第24、30、40至41、43、46、55頁），而被\n      告自承係負責鋒沐公司實際營運，為鋒沐公司實際負責人\n      等語（見第20654 號偵查卷一第191 至192 頁），並經證\n      人曾繁堯證述屬實（見同上卷頁），揆諸上開說明，本件\n      被告就鋒沐公司而言，並非稅捐稽徵法第47條處罰之客體\n      。惟被告既實際負責鋒沐公司營運，而取得附表二所示不\n      實統一發票，充當鋒沐公司進項憑證以扣抵營業稅額，自\n      屬幫助鋒沐公司逃漏營業稅。至被告為金太陽公司登記負\n      責人，亦為實際負責人，依修正前稅捐稽徵法第47條規定\n      ，被告應論以該法第47條第1 款、第41條之公司負責人為\n      納稅義務人以不正當方法逃漏稅捐罪，法定刑為5 年以下\n      有期徒刑，然依修正後稅捐稽徵法第47條規定，被告既為\n      實際負責之人，仍應論以該法第47條第1 項第1 款、第41\n      條之罪，尚無新舊法比較適用之問題，逕用行為時之法律\n      ，併此敘明。\n（二）罪名：\n   1、按統一發票，係為證明事項之經過造具記帳所根據之憑證\n      ，屬原始憑證，屬商業會計法第15條第1 款之會計憑證。\n      是核被告就犯罪事實一（一），填製如附表一所示內容不\n      實之統一發票，交付莊頭北公司作為進項憑證，莊頭北公\n      司並持以向稅捐機關申報扣抵營業稅款，幫助莊頭北公司\n      納稅義務人逃漏營業稅，核其所為，係犯95年5 月24日修\n      正前商業會計法第71條第1 款以不實之事項填製會計憑證\n      或登入帳冊罪、稅捐稽徵法第43條第1 項幫助納稅義務人\n      逃漏稅捐罪。又商業會計法第71條第1 款以明知不實之事\n      項而填製會計憑證或記入帳冊之罪，原即含有業務上登載\n      不實之本質，應不再另論刑法第215 條之業務上登載不實\n      文書罪。\n   2、就犯罪事實一（二）部分，被告為鋒沐公司實際負責人，\n      向附表二所示之連勝莊、豐莊公司取得不實統一發票，持\n      向稅捐稽徵機申報扣抵營業稅額之所為，幫助鋒沐公司犯\n      稅捐稽徵法第41條以不正當方法逃漏稅捐罪，核其所為，\n      係犯稅捐稽徵法第43條第1 項幫助納稅義務人逃漏稅捐罪\n      。起訴書認被告係犯稅捐稽徵法第47條第1 款、第41條之\n      罪，尚有未洽，然基本犯罪事實相同，應予變更起訴法條\n      ；又本院已當庭諭知變更之起訴法條，其防禦權應可受保\n      障，不致造成突襲，併此說明。\n   3、就犯罪事實一（三）部分，按營業人無銷貨事實出售統一\n      發票牟取不法之利益，非屬營業稅課徵之標的，免予課徵\n      營業稅，業經財政部78年8 月3 日台財稅字第780195193\n      號函釋在案；稅捐稽徵法第41條之逃漏稅捐罪，係屬結果\n      犯，須發生逃漏應繳納稅捐之結果，始足構成。而行為人\n      虛設公司、行號，為製造該虛設公司、行號確有營業之假\n      象，乃與其他虛設公司、行號彼此間對開發票，或自有實\n      際營業而無實際銷售貨物或勞務之公司、行號取得發票，\n      因該虛設公司、行號並無實際營業行為，即無逃漏營業稅\n      捐之可言（最高法院99年度台上字第7817號判決參照），\n      查天技、赫拉公司於附表三所示之期間內，涉嫌與其他營\n      業人相互循環開立不實統一發票，經財政部臺灣省中區國\n      稅局移送偵辦在案，有刑事案件移送書在卷可按（見第19\n      812 號卷第41至46頁），是天技公司、赫拉公司係屬虛設\n      行號應堪認定，則此2 公司縱有自被告經營之金太陽公司\n      取得不實之進貨統一發票，亦無繳納營業稅而有逃漏營業\n      稅，則被告自亦無何幫助逃漏營業稅之情。是被告填製如\n      附表三所示內容不實之統一發票，交付如附表三所示天技\n      、赫拉公司作為進項憑證，核其所為，係犯95年5 月24日\n      修正前商業會計法第71條第1 款以不實之事項填製會計憑\n      證或登入帳冊罪。\n   4、就犯罪事實一（四）部分，被告為金太陽公司負責人，向\n      附表四所示之天技、赫拉公司取得不實統一發票，持向稅\n      捐稽徵機申報扣抵營業稅額，核其所為，係犯稅捐稽徵法\n      第41條、第47條第1 項逃漏稅捐罪。\n（三）被告就犯罪事實一（二）鋒沐公司於91年4 月、91年10月\n      、91年12月申報扣抵營業稅額，扣除虛報銷項及進項稅額\n      而幫助鋒沐公司實際逃漏如附表二每期實際逃漏稅欄所示\n      之稅額，及其就犯罪事實一（四）金太陽公司92年8 月、\n      92年12月、93年2 月、93年4 月申報扣抵營業稅額，扣除\n      虛報銷項及進項稅額而使金太陽公司實際逃漏如附表四每\n      期實際逃漏稅欄所示之稅額；暨其先後多次填製不實統一\n      發票交付莊頭北公司及天技、赫拉公司，並以此方式多次\n      幫助莊頭北公司逃漏營業稅之行為，均時間緊接，所犯各\n      為構成要件相同之罪名，顯係各基於概括犯意反覆實施，\n      均為連續犯，各應依修正前刑法第56條之規定，以一罪論\n      ，並加重其刑。被告就犯罪事實一（一）以填製不實會計\n      憑證之方式幫助他人逃漏營業稅，所犯上開二罪間，有手\n      段、目的之牽連關係，應依修正前刑法第55條後段規定，\n      從一重論以修正前商業會計法第71條第1 款之罪。公訴意\n      旨就此部分認係想像競合犯，尚有未洽，應予更正。\n（四）數罪併罰：被告就犯罪事實一（一）、（三）所犯連續商\n      業負責人填製不實會計憑證罪，犯罪事實一（二）所犯連\n      續幫助納稅義務人逃漏稅捐罪，犯罪事實一（四）所犯連\n      續逃漏稅捐罪，其犯意不同，行為互殊，均應予分論併罰\n      。\n（五）科刑：爰審酌被告之犯罪動機、目的、手段、其行為對於\n      稅捐稽徵機關課稅公正性及正確性之影響，及兼衡被告於\n      本院審理時終能坦承犯行，態度尚佳等一切情狀，分別量\n      處如主文所示之刑。\n（六）減刑：又被告上開犯罪時間均係在96年4 月24日以前，所\n      犯之罪，均合於中華民國九十六年罪犯減刑條例規定之減\n      刑條件，依該條例第2 條第1 項第3 款規定，各減其刑期\n      二分之一，並就減刑後之刑，定其應執行之刑，並依同條\n      例第9 條、修正前刑法第41條第1 項前段及95年5 月17日\n      修正刪除前罰金罰鍰提高標準條例第2 條之規定定其易科\n      罰金之折算標準。\n（七）緩刑：末查被告前未曾受有期徒刑以上刑之宣告一節，有\n      臺灣高等法院被告前案紀錄表1 紙在卷可稽，因一時失慮\n      ，偶罹刑典，事後已坦承犯行，顯有悔意，且業已向中華\n      社會福利聯合勸募協會為公益捐款15萬元，其經此刑之宣\n      告後，應已知警惕而無再犯之虞，故本院認為以暫不執行\n      為適當，併諭知宣告緩刑2 年，以啟自新。又緩刑之宣告\n      以裁判時之狀態為準，當然適用新法之規定，不再適用舊\n      法，併予說明。\n（八）不另為無罪諭知部分：被告於犯罪事實一（二）、（四）\n      所為幫助逃漏稅捐及逃漏稅捐犯行，應按各次營業稅申報\n      期間認係各別為之，已如上開說明；再按稅捐稽徵法第41\n      條之規定係屬結果犯，除犯罪之目的在逃漏營業稅外，並\n      須有逃漏應納營業稅之結果事實，始足構成該條之罪。查\n      如附表二所示之鋒沐公司於90年12月、91年2 月、91年6\n      月及91年8 月，固有向連勝莊公司、豐莊公司收取如附表\n      二所示之各該月不實統一發票作為進貨憑證，然經扣除虛\n      報銷項及進項稅額後，上開各次營業稅申報計算後漏稅額\n      為0 ，並未發生逃漏應繳納營業稅之結果，與稅捐稽徵法\n      第43條第1 項幫助逃漏稅捐罪之構成要件有間，被告就此\n      部分並不成立稅捐稽徵法第43條第1 項幫助逃漏稅捐罪之\n      幫助犯。又如附表四所示之金太陽公司於92年10月、93年\n      6 月，固有向天技公司、赫拉公司收取如附表四所示之各\n      該月不實統一發票作為進貨憑證，然經扣除虛報銷項及進\n      項稅額後，上開各次營業稅申報計算後漏稅額為0 ，亦未\n      發生逃漏應繳納稅捐之結果，與稅捐稽徵法第41條逃漏稅\n      捐罪之構成要件有間，被告就此部分亦不成立稅捐稽徵法\n      第41條逃漏稅捐罪，此部分本應為被告無罪之諭知，惟檢\n      察官認為此部分若成立犯罪，與上開論罪科刑部分有連續\n      犯裁判上一罪之關係，就此部分爰不另為無罪之諭知。\n據上論斷，應依刑事訴訟法第第299 條第1 項前段、第300 條，\n95年5 月24日修正前之商業會計法第71條第1 款，修正前稅捐稽\n徵法第47條第1 項，修正前刑法第56條、第55條、第41條第1 項\n前段、第51條第5 款，稅捐稽徵法第41條、第43條第1 項，刑法\n第2 條第1 項前段、第11條前段、第74條第1 項第1 款，修正刪\n除前罰金罰鍰提高標準條例第2 條，現行法規所定貨幣單位折算\n新臺幣條例第2 條，中華民國九十六年罪犯減刑條例第2 條第1\n項第3 款、第7 條、第9 條、第10條第1 項，判決如主文。\n本案經檢察官陳睿明到庭執行職務。\n中    華    民    國   100    年    12    月    30    日\n                刑事第十四庭  審判長 法  官  鍾雅蘭\n                                     法  官  郭俊德\n                                     法  官  楊麗文\n以上正本證明與原本無異。\n如不服本判決應於收受判決後10日內向本院提出上訴書狀，並應\n敘述具體理由。其未敘述上訴理由者，應於上訴期間屆滿後20日\n內向本院補提理由書( 均須按他造當事人之人數附繕本) 「切勿\n逕送上級法院」。\n                                     書記官  柯凱騰\n中    華    民    國   100    年    12    月    30    日\n附錄本案論罪科刑法條全文\n修正前商業會計法第71條\n商業負責人、主辦及經辦會計人員或依法受託代他人處理會計事\n務之人員有下列情事之一者，處5 年以下有期徒刑、拘役或科或\n併科新臺幣15萬元以下罰金：\n一、以明知為不實之事項，而填製會計憑證或記入帳冊。\n二、故意使應保存之會計憑證、會計帳簿報表滅失毀損。\n三、偽造或變造會計憑證、會計帳簿報表內容或毀損其頁數。\n四、故意遺漏會計事項不為記錄，致使財務報表發生不實之結果\n    。\n五、其他利用不正當方法，致使會計事項或財務報表發生不實之\n    結果。\n稅捐稽徵法第41條\n納稅義務人以詐術或其他不正當方法逃漏稅捐者，處5 年以下有\n期徒刑、拘役或科或併科新臺幣6 萬元以下罰金。\n稅捐稽徵法第43條\n教唆或幫助犯第41條或第42條之罪者，處3 年以下有期徒刑、拘\n役或科新台幣6 萬元以下罰金。\n稅務人員、執行業務之律師、會計師或其他合法代理人犯前項之\n罪者，加重其刑至二分之一。\n稅務稽徵人員違反第33條規定者，除觸犯刑法者移送法辦外，處\n1 萬元以上5 萬元以下罰鍰。\n附表一：鋒沐公司虛開統一發票明細\n┌─┬──────┬────┬──────┬──────┬─────┐\n│編│營業人名稱  │開立年月│發票字軌號碼│銷售金額（新│逃漏營業稅│\n│號│            │        │            │臺幣）      │稅額      │\n├─┼──────┼────┼──────┼──────┼─────┤\n│1 │莊頭北工業股│90年11月│KB00000000  │2,153,640元 │10,682元  │\n│  │份有限公司  ├────┼──────┼──────┼─────┤\n│  │            │90年12月│KB00000000  │1,055,125元 │52,756元  │\n│  │            ├────┼──────┼──────┼─────┤\n│  │            │90年12月│KB00000000  │3,994,500 元│199,725元 │\n│  │            ├────┼──────┼──────┼─────┤\n│  │            │90年12月│KB00000000  │2,589,000元 │129,450元 │\n│  │            ├────┼──────┼──────┼─────┤\n│  │            │90年12月│KB00000000  │2,058,255元 │102,913元 │\n│  │            ├────┼──────┼──────┼─────┤\n│  │            │90年12月│KB00000000  │3,997,163元 │199,858元 │\n│  │            ├────┼──────┼──────┼─────┤\n│  │            │90年12月│KB00000000  │1,196,000元 │59,800元  │\n│  │            ├────┼──────┼──────┼─────┤\n│  │            │90年12月│KB00000000  │734,052元   │36,703元  │\n│  │            ├────┼──────┼──────┼─────┤\n│  │            │90年12月│KB00000000  │837,200元   │41,860元  │\n│  │            ├────┼──────┼──────┼─────┤\n│  │            │90年12月│KB00000000  │1,064,300元 │53,215元  │\n│  │            ├────┼──────┼──────┼─────┤\n│  │            │90年12月│KB00000000  │1,784,210元 │89,211元  │\n│  │            ├────┼──────┼──────┼─────┤\n│  │            │90年12月│KB00000000  │1,941,750 元│97,088元  │\n│  │            ├────┼──────┼──────┼─────┤\n│  │            │90年12月│KB00000000  │1,331,500元 │66,575元  │\n│  │            ├────┼──────┼──────┼─────┤\n│  │            │90年12月│KB00000000  │1,294,500元 │64,725元  │\n│  │            ├────┼──────┼──────┼─────┤\n│  │            │90年12月│KB00000000  │1,331,500元 │66,575元  │\n│  │            ├────┼──────┼──────┼─────┤\n│  │            │90年12月│KB00000000  │1,294,500元 │64,725元  │\n│  │            ├────┼──────┼──────┼─────┤\n│  │            │90年12月│KB00000000  │2,663,000元 │133,150元 │\n│  │            ├────┼──────┼──────┼─────┤\n│  │            │91年1 月│LA00000000  │1,327,560 元│66,378元  │\n│  │            ├────┼──────┼──────┼─────┤\n│  │            │91年1 月│LA00000000  │301,290元   │15,065元  │\n│  │            ├────┼──────┼──────┼─────┤\n│  │            │91年2 月│LA00000000  │205,520元   │10,276元  │\n│  │            ├────┼──────┼──────┼─────┤\n│  │            │91年2 月│LA00000000  │1,065,200元 │53,260元  │\n│  │            ├────┼──────┼──────┼─────┤\n│  │            │91年2 月│LA00000000  │380,583元   │19,029元  │\n│  │            ├────┼──────┼──────┼─────┤\n│  │            │91年3 月│LZ00000000  │40,099元    │2,005元   │\n│  │            ├────┼──────┼──────┼─────┤\n│  │            │91年3 月│LZ00000000  │30,813元    │1,541元   │\n│  │            ├────┼──────┼──────┼─────┤\n│  │            │91年3 月│LZ00000000  │87,398元    │4,370元   │\n│  │            ├────┼──────┼──────┼─────┤\n│  │            │91年3 月│LZ00000000  │232,764元   │11,638元  │\n│  │            ├────┼──────┼──────┼─────┤\n│  │            │91年3 月│LZ00000000  │234,625元   │11,731元  │\n│  │            ├────┼──────┼──────┼─────┤\n│  │            │91年3 月│LZ00000000  │158,316元   │7,916元   │\n│  │            ├────┼──────┼──────┼─────┤\n│  │            │91年3 月│LZ00000000  │265,195元   │13,260元  │\n│  │            ├────┼──────┼──────┼─────┤\n│  │            │91年3 月│LZ00000000  │161,210元   │8,061元   │\n│  │            ├────┼──────┼──────┼─────┤\n│  │            │91年3 月│LZ00000000  │212,280元   │10,614元  │\n│  │            ├────┼──────┼──────┼─────┤\n│  │            │91年3 月│LZ00000000  │442,600元   │22,130元  │\n│  │            ├────┼──────┼──────┼─────┤\n│  │            │91年3 月│LZ00000000  │997,002元   │49,850元  │\n│  │            ├────┼──────┼──────┼─────┤\n│  │            │91年3 月│LZ00000000  │1,256,187元 │62,809元  │\n│  │            ├────┼──────┼──────┼─────┤\n│  │            │91年4 月│LZ00000000  │389,852元   │19,493元  │\n│  │            ├────┼──────┼──────┼─────┤\n│  │            │91年4 月│LZ00000000  │639,557元   │31,978元  │\n│  │            ├────┼──────┼──────┼─────┤\n│  │            │91年4 月│LZ00000000  │653,686元   │32,684元  │\n│  │            ├────┼──────┼──────┼─────┤\n│  │            │91年4 月│LZ00000000  │1,294,515元 │64,726元  │\n│  │            ├────┼──────┼──────┼─────┤\n│  │            │91年4 月│LZ00000000  │1,354,561元 │67,728元  │\n│  │            ├────┼──────┼──────┼─────┤\n│  │            │91年4 月│LZ00000000  │291,910元   │14,596元  │\n│  │            ├────┼──────┼──────┼─────┤\n│  │            │91年6 月│MY00000000  │662,000元   │33,100元  │\n│  │            ├────┼──────┼──────┼─────┤\n│  │            │91年6 月│MY00000000  │443,900元   │22,195元  │\n│  │            ├────┼──────┼──────┼─────┤\n│  │            │91年6 月│MY00000000  │653,305元   │32,665元  │\n│  │            ├────┼──────┼──────┼─────┤\n│  │            │91年6 月│MY00000000  │1,544,000元 │77,200元  │\n│  │            ├────┼──────┼──────┼─────┤\n│  │            │91年6 月│MY00000000  │744,700元   │37,235元  │\n│  │            ├────┼──────┼──────┼─────┤\n│  │            │91年6 月│MY00000000  │637,000元   │31,850元  │\n│  │            ├────┼──────┼──────┼─────┤\n│  │            │91年6 月│MY00000000  │796,250元   │39,813元  │\n│  │            ├────┼──────┼──────┼─────┤\n│  │            │91年6 月│MY00000000  │123,660元   │6,183元   │\n│  │            ├────┼──────┼──────┼─────┤\n│  │            │91年6 月│MY00000000  │255,099元   │12,755元  │\n│  │            ├────┼──────┼──────┼─────┤\n│  │            │91年6 月│MY00000000  │570,210元   │28,511元  │\n│  │            ├────┼──────┼──────┼─────┤\n│  │            │91年6 月│MY00000000  │432,668元   │21,633元  │\n│  │            ├────┴──────┴──────┴─────┤\n│  │            │91年7 月│NX00000000  │1,078,590元 │53,930元  │\n│  │            ├────┼──────┼──────┼─────┤\n│  │            │91年7 月│NX00000000  │1,007,460元 │50,373元  │\n│  │            ├────┼──────┼──────┼─────┤\n│  │            │91年7 月│NX00000000  │965,000元   │48,250元  │\n│  │            ├────┼──────┼──────┼─────┤\n│  │            │91年7 月│NX00000000  │345,400元   │17,270元  │\n│  │            ├────┼──────┼──────┼─────┤\n│  │            │91年7 月│NX00000000  │578,496元   │28,925元  │\n│  │            ├────┼──────┼──────┼─────┤\n│  │            │91年8 月│NX00000000  │446,526 元  │22,326元  │\n│  │            ├────┼──────┼──────┼─────┤\n│  │            │91年8 月│NX00000000  │113,099元   │5,655元   │\n│  │            ├────┼──────┼──────┼─────┤\n│  │            │91年8 月│NX00000000  │378,290元   │18,915元  │\n│  │            ├────┼──────┼──────┼─────┤\n│  │            │91年8 月│NX00000000  │538,970元   │26,949元  │\n│  │            ├────┼──────┼──────┼─────┤\n│  │            │91年8 月│NX00000000  │576,822元   │28,841元  │\n│  │            ├────┼──────┼──────┼─────┤\n│  │            │91年8 月│NX00000000  │30,240元    │1,512元   │\n│  │            ├────┼──────┼──────┼─────┤\n│  │            │91年8 月│NX0000000   │42,596元    │2,130元   │\n│  │            ├────┼──────┼──────┼─────┤\n│  │            │91年8 月│NX0000000   │63,640元    │3,182元   │\n│  │            ├────┼──────┼──────┼─────┤\n│  │            │91年8 月│NX0000000   │42,183元    │2,109元   │\n│  │            ├────┼──────┼──────┼─────┤\n│  │            │91年9 月│PW00000000  │654,905元   │32,745元  │\n│  │            ├────┼──────┼──────┼─────┤\n│  │            │91年9 月│PW00000000  │531,030元   │26,552 元 │\n│  │            ├────┼──────┼──────┼─────┤\n│  │            │91年9 月│PW00000000  │62,322元    │3,116 元  │\n│  │            ├────┼──────┼──────┼─────┤\n│  │            │91年9 月│PW00000000  │581,102元   │29,055 元 │\n│  │            ├────┼──────┼──────┼─────┤\n│  │            │91年9 月│PW00000000  │86,816元    │4,341 元  │\n│  │            ├────┼──────┼──────┼─────┤\n│  │            │91年9 月│PW00000000  │16,800元    │840 元    │\n│  │            ├────┼──────┼──────┼─────┤\n│  │            │91年9 月│PW00000000  │56,070元    │2,804 元  │\n│  │            ├────┼──────┼──────┼─────┤\n│  │            │91年9 月│PW00000000  │59,814元    │2,991 元  │\n│  │            ├────┼──────┼──────┼─────┤\n│  │            │91年9 月│PW00000000  │121,560元   │6,078 元  │\n│  │            ├────┼──────┼──────┼─────┤\n│  │            │91年10月│PW00000000  │47,845元    │2,392 元  │\n│  │            ├────┼──────┼──────┼─────┤\n│  │            │91年10月│PW00000000  │131,480元   │6,574 元  │\n│  │            ├────┼──────┼──────┼─────┤\n│  │            │91年10月│PW00000000  │44,032元    │2,202 元  │\n│  │            ├────┼──────┼──────┼─────┤\n│  │            │91年10月│PW00000000  │131,480元   │6,574 元  │\n│  │            ├────┴──────┴──────┴─────┤\n│  │            │91年12月│QV00000000  │792,590元   │39,630 元 │\n│  │            ├────┼──────┼──────┼─────┤\n│  │            │91年12月│QV00000000  │600,160元   │30,008 元 │\n│  │            ├────┼──────┼──────┼─────┤\n│  │            │91年12月│QV00000000  │727,200元   │36,360 元 │\n│  │            ├────┼──────┼──────┼─────┤\n│  │            │91年12月│QV00000000  │502,080元   │25,104元  │\n│  │            ├────┼──────┼──────┼─────┤\n│  │            │91年12月│QV00000000  │745,590元   │37,280元  │\n│  │            ├────┼──────┼──────┼─────┤\n│  │            │91年12月│QV00000000  │728,476元   │36,424元  │\n│  │            ├────┼──────┼──────┼─────┤\n│  │            │91年12月│QV00000000  │947,800元   │47,390元  │\n│  │            ├────┼──────┼──────┼─────┤\n│  │            │91年12月│QV00000000  │627,600元   │31,380元  │\n│  │            ├────┼──────┼──────┼─────┤\n│  │            │91年12月│QV00000000  │846,250元   │42,313元  │\n│  │            ├────┼──────┼──────┼─────┤\n│  │            │91年12月│QV00000000  │207,090元   │10,355元  │\n│  │            ├────┼──────┼──────┼─────┤\n│  │            │91年12月│QV00000000  │439,800元   │21,990元  │\n│  │            ├────┼──────┼──────┼─────┤\n│  │            │91年12月│QV00000000  │378,375元   │18,919元  │\n│  │            ├────┼──────┼──────┼─────┤\n│  │            │91年12月│QV00000000  │710,985元   │35,549元  │\n├─┴──────┴────┴──────┼──────┼─────┤\n│    合        計                        │67,192,274元│3,359,622 │\n│                                        │            │元        │\n└────────────────────┴──────┴─────┘\n 附表二：鋒沐公司以不實發票申報扣抵銷稅項明細\n┌─┬──────┬────┬───────┬─────┬────┐\n│編│被告取得不實│開立年月│發票字軌號碼  │虛進金額（│虛進稅額│\n│號│發票之營業人│        │              │新臺幣）  │（新臺幣│\n│  │名稱        │        │              │          │）      │\n├─┼──────┼────┼───────┼─────┼────┤\n│1 │連勝莊興業有│90年11月│KB00000000    │586,480 元│29,324元│\n│  │限公司      ├────┼───────┼─────┼────┤\n│  │            │90年11月│KB00000000    │800,210元 │40,011元│\n│  │            ├────┼───────┼─────┼────┤\n│  │            │90年11月│KB00000000    │813,030元 │40,652元│\n│  │            ├────┼───────┼─────┼────┤\n│  │            │90年11月│KB00000000    │479,520元 │23,976元│\n│  │            ├────┼───────┼─────┼────┤\n│  │            │90年11月│KB00000000    │738,360元 │36,918元│\n│  │            ├────┼───────┼─────┼────┤\n│  │            │90年11月│KB00000000    │882,600元 │44,130元│\n│  │            ├────┼───────┼─────┼────┤\n│  │            │90年11月│KB00000000    │829,040元 │41,452元│\n│  │            ├────┼───────┼─────┼────┤\n│  │            │90年11月│KB00000000    │522,637元 │26,132元│\n│  │            ├────┼───────┼─────┼────┤\n│  │            │90年11月│KB00000000    │768,270元 │38,414元│\n│  │            ├────┼───────┼─────┼────┤\n│  │            │90年11月│KB00000000    │603,000元 │30,150元│\n│  │            ├────┼───────┼─────┼────┤\n│  │            │90年11月│KB00000000    │736,200元 │36,810元│\n│  │            ├────┼───────┼─────┼────┤\n│  │            │90年11月│KB00000000    │780,000元 │39,000元│\n│  │            ├────┼───────┼─────┼────┤\n│  │            │90年11月│KB00000000    │892,350元 │44,618元│\n│  │            ├────┼───────┼─────┼────┤\n│  │            │90年11月│KB00000000    │732,440元 │36,622元│\n│  │            ├────┼───────┼─────┼────┤\n│  │            │90年11月│KB00000000    │703,110元 │35,156元│\n│  │            ├────┼───────┼─────┼────┤\n│  │            │90年11月│KB00000000    │632,350元 │31,618元│\n│  │            ├────┼───────┼─────┼────┤\n│  │            │90年11月│KB00000000    │779,260元 │38,963元│\n│  │            ├────┼───────┼─────┼────┤\n│  │            │90年11月│KB00000000    │588,280元 │29,414元│\n│  │            ├────┼───────┼─────┼────┤\n│  │            │90年11月│KB00000000    │773,240元 │38,667元│\n│  │            ├────┼───────┼─────┼────┤\n│  │            │90年11月│KB00000000    │743,070元 │37,154元│\n│  │            ├────┼───────┼─────┼────┤\n│  │            │90年11月│KB00000000    │864,290元 │43,215元│\n│  │            ├────┼───────┼─────┼────┤\n│  │            │90年11月│KB00000000    │699,410元 │34,971元│\n│  │            ├────┼───────┼─────┼────┤\n│  │            │90年11月│KB00000000    │490,650 元│24,533元│\n│  │            ├────┼───────┼─────┼────┤\n│  │            │90年11月│KB00000000    │756,800元 │37,840元│\n│  │            ├────┼───────┼─────┼────┤\n│  │            │90年12月│KB00000000    │732,440元 │36,622元│\n│  │            ├────┼───────┼─────┼────┤\n│  │            │90年12月│KB00000000    │512,496元 │25,625元│\n│  │            ├────┼───────┼─────┼────┤\n│  │            │90年12月│KB00000000    │858,329元 │42,916元│\n│  │            ├────┼───────┼─────┼────┤\n│  │            │90年12月│KB00000000    │529,170 元│26,459元│\n│  │            ├────┼───────┼─────┼────┤\n│  │            │90年12月│KB00000000    │619,376元 │30,969元│\n│  │            ├────┼───────┼─────┼────┤\n│  │            │90年12月│KB00000000    │783,700元 │39,185元│\n│  │            ├────┼───────┼─────┼────┤\n│  │            │90年12月│KB00000000    │716,840元 │35,842元│\n│  │            ├────┼───────┼─────┼────┤\n│  │            │90年12月│KB00000000    │499,370元 │24,969元│\n│  │            ├────┼───────┼─────┼────┤\n│  │            │90年12月│KB00000000    │527,400元 │26,370元│\n│  │            ├────┼───────┼─────┼────┤\n│  │            │90年12月│KB00000000    │522,740元 │26,137元│\n│  │            ├────┼───────┼─────┼────┤\n│  │            │90年12月│KB00000000    │796,760元 │39,838元│\n│  │            ├────┼───────┼─────┼────┤\n│  │            │90年12月│KB00000000    │600,590元 │30,030元│\n│  │            ├────┼───────┼─────┼────┤\n│  │            │90年12月│KB00000000    │632,900元 │31,645元│\n│  │            ├────┼───────┼─────┼────┤\n│  │            │90年12月│KB00000000    │629,220元 │31,461元│\n│  │            ├────┼───────┼─────┼────┤\n│  │            │90年12月│KB00000000    │768,900元 │38,445元│\n│  │            ├────┼───────┼─────┼────┤\n│  │            │90年12月│KB00000000    │434,840元 │21,742元│\n│  │            ├────┼───────┼─────┼────┤\n│  │            │90年12月│KB00000000    │584,920元 │29,246元│\n│  │            ├────┼───────┼─────┼────┤\n│  │            │90年12月│KB00000000    │493,100元 │24,655元│\n│  │            ├────┼───────┼─────┼────┤\n│  │            │90年12月│KB00000000    │618,070元 │30,904元│\n│  │            ├────┼───────┼─────┼────┤\n│  │            │90年12月│KB00000000    │500,500元 │25,025元│\n│  │            ├────┼───────┼─────┼────┤\n│  │            │90年12月│KB00000000    │717,640元 │35,882元│\n│  │            ├────┼───────┼─────┼────┤\n│  │            │90年12月│KB00000000    │596,690元 │29,835元│\n│  │            ├────┼───────┼─────┼────┤\n│  │            │90年12月│KB00000000    │341,680元 │17,084元│\n│  │            ├────┼───────┼─────┼────┤\n│  │            │90年12月│KB00000000    │521,480元 │26,074元│\n│  │            ├────┼───────┼─────┼────┤\n│  │            │90年12月│KB00000000    │341,910元 │17,096元│\n│  │            ├────┼───────┼─────┼────┤\n│  │            │90年12月│KB00000000    │522,640元 │26,132元│\n│  │            ├────┼───────┼─────┼────┤\n│  │            │90年12月│KB00000000    │635,820元 │31,791元│\n│  │            ├────┼───────┼─────┼────┤\n│  │            │90年12月│KB00000000    │388,220元 │19,411元│\n│  │            ├────┼───────┼─────┼────┤\n│  │            │90年12月│KB00000000    │635,860元 │31,793元│\n│  │            ├────┼───────┼─────┼────┤\n│  │            │91年3 月│MA00000000    │4,559,100 │227,955 │\n│  │            │        │              │元        │元      │\n│  │            ├────┼───────┼─────┼────┤\n│  │            │91年5 月│MZ00000000    │627,416元 │31,371元│\n│  │            ├────┼───────┼─────┼────┤\n│  │            │91年5 月│MZ00000000    │2,582,416 │129,121 │\n│  │            │        │              │元        │元      │\n│  │            ├────┼───────┼─────┼────┤\n│  │            │91年5 月│MZ00000000    │1,483,983 │74,199元│\n│  │            │        │              │元        │        │\n│  │            ├────┼───────┼─────┼────┤\n│  │            │91年7 月│NY00000000    │300,014元 │15,000元│\n│  │            ├────┼───────┼─────┼────┤\n│  │            │91年7 月│NY00000000    │111,436元 │5,572元 │\n│  │            ├────┼───────┼─────┼────┤\n│  │            │91年7 月│NY00000000    │41,567元  │2,078元 │\n│  │            ├────┼───────┼─────┼────┤\n│  │            │91年7 月│NY00000000    │29,797元  │1,490元 │\n│  │            ├────┼───────┼─────┼────┤\n│  │            │91年8 月│NY00000000    │423,692元 │21,185元│\n│  │            ├────┼───────┼─────┼────┤\n│  │            │91年8 月│NY00000000    │85,540元  │4,277元 │\n│  │            ├────┼───────┼─────┼────┤\n│  │            │91年8 月│NY00000000    │16,554元  │828元   │\n│  │            ├────┼───────┼─────┼────┤\n│  │            │91年8 月│NY00000000    │55,252元  │2,763元 │\n│  │            ├────┼───────┼─────┼────┤\n│  │            │91年9 月│PX00000000    │103,953元 │5,198元 │\n│  │            ├────┼───────┼─────┼────┤\n│  │            │91年9 月│PX00000000    │404,858元 │20,243元│\n│  │            ├────┼───────┼─────┼────┤\n│  │            │91年9 月│PX00000000    │327,738元 │16,387元│\n│  │            ├────┼───────┼─────┼────┤\n│  │            │91年9 月│PX00000000    │191,436元 │9,572元 │\n│  │            ├────┼───────┼─────┼────┤\n│  │            │91年9 月│PX00000000    │682,591元 │34,130元│\n│  │            ├────┼───────┼─────┼────┤\n│  │            │91年10月│PX00000000    │148,357元 │7,417元 │\n│  │            ├────┼───────┼─────┼────┤\n│  │            │91年10月│PX00000000    │172,171元 │8,608元 │\n│  │            ├────┼───────┼─────┼────┤\n│  │            │91年10月│PX00000000    │35,248元  │1,762元 │\n│  │            ├────┼───────┼─────┼────┤\n│  │            │91年10月│PX00000000    │83,769元  │4,188元 │\n├─┴──────┴────┴───────┼─────┼────┤\n│                       小        計       │46,725,186│2,336,26│\n│                                          │元        │元      │\n├─┬──────┬────┬───────┼─────┼────┤\n│2 │豐莊興業有限│91年3 月│MA00000000    │413,028元 │20,651元│\n│  │公司        ├────┼───────┼─────┼────┤\n│  │            │91年3 月│MA00000000    │301,330元 │15,067元│\n│  │            ├────┼───────┼─────┼────┤\n│  │            │91年3 月│MA00000000    │278,249元 │13,912元│\n│  │            ├────┼───────┼─────┼────┤\n│  │            │91年3 月│MA00000000    │327,635元 │16,382元│\n│  │            ├────┼───────┼─────┼────┤\n│  │            │91年3 月│MA00000000    │247,096元 │12,355元│\n│  │            ├────┼───────┼─────┼────┤\n│  │            │91年3 月│MA00000000    │315,671元 │15,784元│\n│  │            ├────┼───────┼─────┼────┤\n│  │            │91年3 月│MA00000000    │303,993元 │15,200元│\n│  │            ├────┼───────┼─────┼────┤\n│  │            │91年3 月│MA00000000    │270,507元 │13,525元│\n│  │            ├────┼───────┼─────┼────┤\n│  │            │91年3 月│MA00000000    │240,170元 │12,009元│\n│  │            ├────┼───────┼─────┼────┤\n│  │            │91年3 月│MA00000000    │543,515元 │27,176元│\n│  │            ├────┼───────┼─────┼────┤\n│  │            │91年3 月│MA00000000    │276,130元 │13,807元│\n│  │            ├────┼───────┼─────┼────┤\n│  │            │91年3 月│MA00000000    │160,830元 │8,042元 │\n│  │            ├────┼───────┼─────┼────┤\n│  │            │91年3 月│MA00000000    │251,200元 │12,560元│\n│  │            ├────┼───────┼─────┼────┤\n│  │            │91年5 月│MZ00000000    │154,912元 │7,746元 │\n│  │            ├────┼───────┼─────┼────┤\n│  │            │91年5 月│MZ00000000    │250,672元 │12,534元│\n│  │            ├────┼───────┼─────┼────┤\n│  │            │91年5 月│MZ00000000    │878,344元 │43,917元│\n│  │            ├────┼───────┼─────┼────┤\n│  │            │91年5 月│MZ00000000    │508,996元 │25,449元│\n│  │            ├────┼───────┼─────┼────┤\n│  │            │91年5 月│MZ00000000    │997,676元 │49,884元│\n│  │            ├────┼───────┼─────┼────┤\n│  │            │91年5 月│MZ00000000    │1,356,488 │67,825元│\n│  │            │        │              │元        │        │\n│  │            │        │              │          │        │\n│  │            ├────┼───────┼─────┼────┤\n│  │            │91年7 月│NY00000000    │415,020元 │20,751元│\n│  │            ├────┼───────┼─────┼────┤\n│  │            │91年7 月│NY00000000    │537,072元 │26,854元│\n│  │            ├────┼───────┼─────┼────┤\n│  │            │91年7 月│NY00000000    │453,225元 │22,661元│\n│  │            ├────┼───────┼─────┼────┤\n│  │            │91年7 月│NY00000000    │568,364元 │28,418元│\n│  │            ├────┼───────┼─────┼────┤\n│  │            │91年7 月│NY00000000    │254,126元 │12,706元│\n│  │            ├────┼───────┼─────┼────┤\n│  │            │91年7 月│NY00000000    │437,823元 │21,891元│\n│  │            ├────┼───────┼─────┼────┤\n│  │            │91年8 月│NY00000000    │43,476元  │2,174元 │\n│  │            ├────┼───────┼─────┼────┤\n│  │            │91年8 月│NY00000000    │60,034元  │3,002元 │\n│  │            ├────┼───────┼─────┼────┤\n│  │            │91年8 月│NY00000000    │39,729元  │1,986元 │\n│  │            ├────┼───────┼─────┼────┤\n│  │            │91年8 月│NY00000000    │61,407元  │3,070元 │\n│  │            ├────┼───────┼─────┼────┤\n│  │            │91年8 月│NY00000000    │62,389元  │3,119元 │\n│  │            ├────┼───────┼─────┼────┤\n│  │            │91年8 月│NY00000000    │41,764元  │2,088元 │\n│  │            ├────┼───────┼─────┼────┤\n│  │            │91年9 月│PX00000000    │211,144元 │10,557元│\n│  │            ├────┼───────┼─────┼────┤\n│  │            │91年9 月│PX00000000    │484,852元 │24,243元│\n│  │            ├────┼───────┼─────┼────┤\n│  │            │91年9 月│PX00000000    │157,405元 │7,870元 │\n│  │            ├────┼───────┼─────┼────┤\n│  │            │91年9 月│PX00000000    │50,869元  │2,543元 │\n│  │            ├────┼───────┼─────┼────┤\n│  │            │91年9 月│PX00000000    │207,619元 │10,381元│\n│  │            ├────┼───────┼─────┼────┤\n│  │            │91年9 月│PX00000000    │106,979元 │5,349元 │\n│  │            ├────┼───────┼─────┼────┤\n│  │            │91年10月│PX00000000    │302,191元 │15,110元│\n│  │            ├────┼───────┼─────┼────┤\n│  │            │91年10月│PX00000000    │246,714元 │12,336元│\n│  │            ├────┼───────┼─────┼────┤\n│  │            │91年10月│PX00000000    │406,780元 │20,339元│\n│  │            ├────┼───────┼─────┼────┤\n│  │            │91年10月│PX00000000    │307,381元 │15,369元│\n│  │            ├────┼───────┼─────┼────┤\n│  │            │91年10月│PX00000000    │309,808元 │15,490元│\n│  │            ├────┼───────┼─────┼────┤\n│  │            │91年11月│QW00000000    │630,614元 │31,531元│\n│  │            ├────┼───────┼─────┼────┤\n│  │            │91年11月│QW00000000    │300,171元 │15,009元│\n│  │            ├────┼───────┼─────┼────┤\n│  │            │91年11月│QW00000000    │702,606元 │35,130元│\n│  │            ├────┼───────┼─────┼────┤\n│  │            │91年11月│QW00000000    │494,712元 │24,735元│\n│  │            ├────┼───────┼─────┼────┤\n│  │            │91年11月│QW00000000    │425,438元 │21,272元│\n│  │            ├────┼───────┼─────┼────┤\n│  │            │91年11月│QW00000000    │500,285元 │25,014元│\n│  │            ├────┼───────┼─────┼────┤\n│  │            │91年11月│QW00000000    │309,195元 │15,460元│\n│  │            ├────┼───────┼─────┼────┤\n│  │            │91年11月│QW00000000    │500,285元 │25,014元│\n│  │            ├────┼───────┼─────┼────┤\n│  │            │91年11月│QW00000000    │637,344元 │31,867元│\n│  │            ├────┼───────┼─────┼────┤\n│  │            │91年11月│QW00000000    │372,762元 │18,638元│\n│  │            ├────┼───────┼─────┼────┤\n│  │            │91年11月│QW00000000    │16,931元  │847元   │\n│  │            ├────┼───────┼─────┼────┤\n│  │            │91年12月│QW00000000    │415,212元 │20,761元│\n│  │            ├────┼───────┼─────┼────┤\n│  │            │91年12月│QW00000000    │350,077元 │17,504元│\n│  │            ├────┼───────┼─────┼────┤\n│  │            │91年12月│QW00000000    │1,322,201 │66,110元│\n│  │            │        │              │元        │        │\n│  │            ├────┼───────┼─────┼────┤\n│  │            │91年12月│QW00000000    │154,598元 │7,730元 │\n│  │            ├────┼───────┼─────┼────┤\n│  │            │91年12月│QW00000000    │806,655元 │40,333元│\n│  │            ├────┼───────┼─────┼────┤\n│  │            │91年12月│QW00000000    │901,175元 │45,059元│\n│  │            ├────┼───────┼─────┼────┤\n│  │            │91年12月│QW00000000    │123,992元 │6,199元 │\n│  │            ├────┼───────┼─────┼────┤\n│  │            │91年12月│QW00000000    │333,523元 │16,676元│\n│  │            ├────┼───────┼─────┼────┤\n│  │            │91年12月│QW00000000    │837,976元 │41,899元│\n│  │            ├────┼───────┼─────┼────┤\n│  │            │91年12月│QW00000000    │34,530元  │1,727元 │\n├─┴──────┴────┴───────┼─────┼────┤\n│                       小        計       │24,012,895│1,200,64│\n│                                          │元        │元      │\n├─────────────────────┼─────┼────┤\n│1+2     合               計               │70,738,081│3,536,91│\n│                                          │元        │元      │\n├─────────────────────┼─────┴────┤\n│90年12月扣除虛報銷項及進項稅額實際逃漏稅額│0元                 │\n├─────────────────────┼──────────┤\n│91年2 月扣除虛報銷項及進項稅額實際逃漏稅額│0元                 │\n├─────────────────────┼──────────┤\n│91年4 月扣除虛報銷項及進項稅額實際逃漏稅額│168,108元           │\n├─────────────────────┼──────────┤\n│91年6 月扣除虛報銷項及進項稅額實際逃漏稅額│0元                 │\n├─────────────────────┼──────────┤\n│91年8 月扣除虛報銷項及進項稅額實際逃漏稅額│0元                 │\n├─────────────────────┼──────────┤\n│91年10月扣除虛報銷項及進項稅額實際逃漏稅額│251,544元           │\n├─────────────────────┼──────────┤\n│91年12月扣除虛報銷項及進項稅額實際逃漏稅額│252,150元           │\n├─────────────────────┼──────────┤\n│總計逃漏稅額                              │671,802元           │\n└─────────────────────┴──────────┘\n附表三：金太陽公司開立不實發票明細\n┌─┬──────┬────┬──────┬──────┬─────┐\n│編│營業人名稱  │開立年月│發票字軌號碼│銷售金額（新│逃漏營業稅│\n│號│            │        │            │臺幣）      │稅額：無  │\n├─┼──────┼────┼──────┼──────┼─────┤\n│1 │天技科技有限│92年6 月│TU00000000  │  456,750元 │虛設行號  │\n│  │            ├────┼──────┼──────┼─────┤\n│  │            │92年6月 │TU00000000  │  395,040元 │虛設行號  │\n│  │            ├────┼──────┼──────┼─────┤\n│  │            │92年6月 │TU00000000  │  426,660元 │虛設行號  │\n│  │            ├────┼──────┼──────┼─────┤\n│  │            │92年6月 │TU00000000  │  456,750元 │虛設行號  │\n│  │            ├────┼──────┼──────┼─────┤\n│  │            │92年6月 │TU00000000  │  394,800元 │虛設行號  │\n│  │            ├────┼──────┼──────┼─────┤\n│  │            │92年6月 │TU00000000  │  426,660元 │虛設行號  │\n│  │            ├────┼──────┼──────┼─────┤\n│  │            │92年6月 │TU00000000  │  456,750元 │虛設行號  │\n│  │            ├────┼──────┼──────┼─────┤\n│  │            │92年6月 │TU00000000  │  456,750元 │虛設行號  │\n│  │            ├────┼──────┼──────┼─────┤\n│  │            │92年6月 │TU00000000  │  395,040元 │虛設行號  │\n│  │            ├────┼──────┼──────┼─────┤\n│  │            │92年6月 │TU00000000  │  426,660元 │虛設行號  │\n│  │            ├────┼──────┼──────┼─────┤\n│  │            │92年6月 │TU00000000  │  456,750元 │虛設行號  │\n│  │            ├────┼──────┼──────┼─────┤\n│  │            │92年6月 │TU00000000  │  426,660元 │虛設行號  │\n│  │            ├────┼──────┼──────┼─────┤\n│  │            │92年6月 │TU00000000  │  231,420元 │虛設行號  │\n│  │            ├────┼──────┼──────┼─────┤\n│  │            │92年6月 │TU00000000  │  433,224元 │虛設行號  │\n│  │            ├────┼──────┼──────┼─────┤\n│  │            │92年8月 │UU00000000  │  475,530元 │虛設行號  │\n│  │            ├────┼──────┼──────┼─────┤\n│  │            │92年8月 │UU00000000  │2,176,090元 │虛設行號  │\n│  │            ├────┼──────┼──────┼─────┤\n│  │            │92年8月 │UU00000000  │  384,930元 │虛設行號  │\n│  │            ├────┼──────┼──────┼─────┤\n│  │            │93年4月 │YU00000000  │1,339,000元 │虛設行號  │\n│  │            ├────┼──────┼──────┼─────┤\n│  │            │93年6月 │ZU00000000  │  870,000元 │虛設行號  │\n│  │            ├────┼──────┼──────┼─────┤\n│  │            │93年6月 │ZU00000000  │  492,000元 │虛設行號  │\n│  │            ├────┼──────┼──────┼─────┤\n│  │            │93年6月 │ZU00000000  │  620,000元 │虛設行號  │\n│  │            ├────┼──────┼──────┼─────┤\n│  │            │93年6月 │ZU00000000  │  436,000元 │虛設行號  │\n│  │            ├────┼──────┼──────┼─────┤\n│  │            │93年6月 │ZU00000000  │  436,000元 │虛設行號  │\n│  │            ├────┼──────┼──────┼─────┤\n│  │            │93年6月 │ZU00000000  │  436,000元 │虛設行號  │\n│  │            ├────┼──────┼──────┼─────┤\n│  │            │93年6月 │ZU00000000  │  697,600元 │虛設行號  │\n│  │            ├────┼──────┼──────┼─────┤\n│  │            │93年6月 │ZU00000000  │  588,000元 │虛設行號  │\n├─┼──────┼────┼──────┼──────┼─────┤\n│2 │赫拉科技股份│92年8月 │UU00000000  │   96,000元 │虛設行號  │\n│  │有限公司    ├────┼──────┼──────┼─────┤\n│  │            │92年8月 │UU00000000  │1,776,000 元│虛設行號  │\n│  │            ├────┼──────┼──────┼─────┤\n│  │            │92年8月 │UU00000000  │2,285,730元 │虛設行號  │\n│  │            ├────┼──────┼──────┼─────┤\n│  │            │92年8月 │UU00000000  │1,331,200元 │虛設行號  │\n│  │            ├────┼──────┼──────┼─────┤\n│  │            │92年10月│VU00000000  │1,617,465元 │虛設行號  │\n│  │            ├────┼──────┼──────┼─────┤\n│  │            │92年10月│VU00000000  │  740,465元 │虛設行號  │\n│  │            ├────┼──────┼──────┼─────┤\n│  │            │92年10月│VU00000000  │1,488,672元 │虛設行號  │\n│  │            ├────┼──────┼──────┼─────┤\n│  │            │92年10月│VU00000000  │1,802,133元 │虛設行號  │\n│  │            ├────┼──────┼──────┼─────┤\n│  │            │93年2月 │XU00000000  │1,020,600元 │虛設行號  │\n│  │            ├────┼──────┼──────┼─────┤\n│  │            │93年2月 │XU00000000  │1,537,350 元│虛設行號  │\n│  │            ├────┼──────┼──────┼─────┤\n│  │            │93年2月 │XU00000000  │1,727,400元 │虛設行號  │\n│  │            ├────┼──────┼──────┼─────┤\n│  │            │93年2月 │XU00000000  │1,324,000元 │虛設行號  │\n│  │            ├────┼──────┼──────┼─────┤\n│  │            │93年6月 │ZU00000000  │2,580,000元 │虛設行號  │\n│  │            ├────┼──────┼──────┼─────┤\n│  │            │93年6月 │ZU00000000  │  903,000元 │虛設行號  │\n├─┴──────┴────┴──────┼──────┼─────┤\n│    合        計                        │36,237,323元│無        │\n│                                        │            │          │\n└────────────────────┴──────┴─────┘\n附表四：金太陽公司以不實發票申報扣抵銷稅項明細\n┌─┬──────┬────┬─────┬──────┬─────┐\n│編│不實發票之營│開立年月│發票字軌號│銷售金額（新│申報扣抵銷│\n│號│業人名稱    │        │碼        │臺幣）      │項稅額（新│\n│  │            │        │          │            │臺幣）    │\n├─┼──────┼────┼─────┼──────┼─────┤\n│1 │天技科技有限│92年7月 │UU00000000│2,152,910元 │107,646元 │\n│  │公司        ├────┼─────┼──────┼─────┤\n│  │            │92年8 月│UU00000000│1,753,180元 │ 87,659元 │\n│  │            ├────┼─────┼──────┼─────┤\n│  │            │92年8 月│UU00000000│2,482,650元 │124,133元 │\n│  │            ├────┼─────┼──────┼─────┤\n│  │            │92年12月│WU00000000│1,111,500元 │ 55,575元 │\n│  │            ├────┼─────┼──────┼─────┤\n│  │            │92年12月│WU00000000│1,669,800元 │ 83,490元 │\n│  │            ├────┼─────┼──────┼─────┤\n│  │            │92年12月│WU00000000│  844,320元 │ 42,216元 │\n│  │            ├────┼─────┼──────┼─────┤\n│  │            │92年12月│WU00000000│1,111,500元 │ 55,575元 │\n│  │            ├────┼─────┼──────┼─────┤\n│  │            │92年12月│WU00000000│  710,000元 │ 35,500元 │\n│  │            ├────┼─────┼──────┼─────┤\n│  │            │92年12月│WU00000000│  694,000元 │ 34,700元 │\n│  │            ├────┼─────┼──────┼─────┤\n│  │            │92年12月│WU00000000│  726,000元 │ 36,300元 │\n│  │            ├────┼─────┼──────┼─────┤\n│  │            │92年12月│WU00000000│  375,560元 │ 18,778元 │\n│  │            ├────┼─────┼──────┼─────┤\n│  │            │92年12月│WU00000000│1,111,500元 │ 55,575元 │\n│  │            ├────┼─────┼──────┼─────┤\n│  │            │92年12月│WU00000000│1,003,500元 │ 50,175元 │\n│  │            ├────┼─────┼──────┼─────┤\n│  │            │92年12月│WU00000000│  653,200元 │ 32,660元 │\n│  │            ├────┼─────┼──────┼─────┤\n│  │            │92年12月│WU00000000│  936,540元 │ 46,827元 │\n│  │            ├────┼─────┼──────┼─────┤\n│  │            │92年12月│WU00000000│  530,000元 │ 26,500元 │\n│  │            ├────┼─────┼──────┼─────┤\n│  │            │92年12月│WU00000000│1,111,500元 │ 55,575元 │\n│  │            ├────┼─────┼──────┼─────┤\n│  │            │92年12月│WU00000000│  805,000元 │ 40,250元 │\n│  │            ├────┼─────┼──────┼─────┤\n│  │            │92年12月│WU00000000│1,159,200元 │ 57,960元 │\n│  │            ├────┼─────┼──────┼─────┤\n│  │            │92年12月│WU00000000│1,145,100 元│ 57,255元 │\n│  │            ├────┼─────┼──────┼─────┤\n│  │            │92年12月│WU00000000│  624,600元 │ 31,230元 │\n│  │            ├────┼─────┼──────┼─────┤\n│  │            │92年12月│WU00000000│  669,000元 │ 33,450元 │\n│  │            ├────┼─────┼──────┼─────┤\n│  │            │92年12月│WU00000000│1,003,500 元│ 50,175元 │\n│  │            ├────┼─────┼──────┼─────┤\n│  │            │93年 4月│YU00000000│1,376,000元 │ 68,800元 │\n│  │            ├────┼─────┼──────┼─────┤\n│  │            │93年5月 │ZU00000000│  820,000元 │ 41,000元 │\n│  │            ├────┼─────┼──────┼─────┤\n│  │            │93年5月 │ZU00000000│  820,000元 │ 41,000元 │\n│  │            ├────┼─────┼──────┼─────┤\n│  │            │93年5月 │ZU00000000│  820,000元 │ 41,000元 │\n│  │            ├────┼─────┼──────┼─────┤\n│  │            │93年5月 │ZU00000000│  120,000元 │  6,000元 │\n├─┼──────┼────┼─────┼──────┼─────┤\n│2 │赫拉科技股份│92年12月│WU00000000│1,383,050 元│ 69,153元 │\n│  │有限公司    ├────┼─────┼──────┼─────┤\n│  │            │92年12月│WU00000000│1,188,450 元│ 59,423元 │\n│  │            ├────┼─────┼──────┼─────┤\n│  │            │92年12月│WU00000000│1,188,450 元│ 59,423元 │\n│  │            ├────┼─────┼──────┼─────┤\n│  │            │92年12月│WU00000000│1,402,500元 │ 52,125元 │\n├─┴──────┴────┴─────┼──────┼─────┤\n│    合        計                      │33,142,510元│1,657,128 │\n│                                      │            │元        │\n├───────────────────┴─┬────┴─────┤\n│92年8 月扣除虛報銷項及進項稅額實際逃漏稅額│2,414元             │\n├─────────────────────┼──────────┤\n│92年10月扣除虛報銷項及進項稅額實際逃漏稅額│0元                 │\n├─────────────────────┼──────────┤\n│92年12月扣除虛報銷項及進項稅額實際逃漏稅額│265,977元           │\n├─────────────────────┼──────────┤\n│93年2 月扣除虛報銷項及進項稅額實際逃漏稅額│262,921元           │\n├─────────────────────┼──────────┤\n│93年4 月扣除虛報銷項及進項稅額實際逃漏稅額│45,482元            │\n├─────────────────────┼──────────┤\n│93年6 月扣除虛報銷項及進項稅額實際逃漏稅額│0元                 │\n├─────────────────────┼──────────┤\n│總計逃漏稅額                              │576,794元           │\n└─────────────────────┴──────────┘",
  "structure": {
    "main": "林燦榮連續犯商業會計法第七十一條第一款之填製不實罪，處有\n期徒刑伍月，如易科罰金，以銀元佰元即新臺幣玖佰元折算壹\n日；減為有期徒刑貳月又拾伍日，如易科罰金，以銀元佰元即\n新臺幣玖佰元折算壹日。又連續犯稅捐稽徵法第四十三條第一項\n之幫助逃漏稅捐罪，處有期徒刑參月，如易科罰金，以銀元佰\n元即新臺幣玖佰元折算壹日；減為有期徒刑壹月又拾伍日，如易\n科罰金，以銀元佰元即新臺幣玖佰元折算壹日。又連續犯稅捐\n稽徵法第四十一條第一項之逃漏稅捐罪，處有期徒刑陸月，如易\n科罰金，以銀元佰元即新臺幣玖佰元折算壹日；減為有期徒刑\n參月，如易科罰金，以銀元佰元即新臺幣玖佰元折算壹日。應\n執行有期徒刑陸月，如易科罰金，以銀元佰元即新臺幣玖佰元\n折算壹日。緩刑貳年。",
    "fact": "一、林燦榮於民國90至93年間，為址設桃園縣龍潭鄉九龍村23鄰\n    九座寮43-6號之「金太陽精密工業股份有限公司（下稱金太\n    陽公司）」之負責人，係商業會計法規範之商業負責人，處\n    理公司之會計及開立統一發票事務；林燦榮另為址設桃園市\n    ○○里○○路2 段1 號4 樓之「鋒沐股份有限公司（下稱鋒\n    沐公司）」之實際負責人，鋒沐公司、金太陽公司均為稅捐\n    稽徵法之納稅義務人。林燦榮明知統一發票係商業會計法所\n    規定之會計憑證，倘無實際銷售營業或提供勞務之事實，不\n    得虛偽開立，竟違反營業人銷售貨物或勞務時，應依據所銷\n    售貨物或勞務之實際內容據實開立統一發票之規定，基於不\n    實填載會計憑證、幫助逃漏稅捐及逃漏稅捐之概括犯意，而\n    為下列行為：\n（一）其明知鋒沐公司於90年11月起至91年12月間止，並無銷貨\n      予「莊頭北工業股份有限公司（下稱莊頭北公司）」之事\n      實，惟為虛增鋒沐公司營收，竟連續填製不實事項而虛偽\n      開立如附表一所示，面額共計新臺幣（下同）67,192,274\n      元，無實際上交易事實之不實銷項統一發票共91紙，交付\n      納稅義務人莊頭北公司充作進貨憑證，供莊頭北公司持向\n      稅捐稽徵機關申報各期營業稅時，誆稱該等統一發票係進\n      項成本而為行使，持以虛報為進項成本以扣抵銷項稅額，\n      而幫助莊頭北公司逃漏營業稅，足以生損害於稅捐稽徵機\n      關對於稅捐稽徵業務管理與課稅之公平及正確性。\n（二）林燦榮明知鋒沐公司於90年11月至91年10月間，並無向劉\n      敏雄（另案為不起訴處分）所經營之「連勝莊興業有限公\n      司（下稱連勝莊公司）」進貨；於91年3 月至12月間，亦\n      未向白晉強（已歿）所經營之「豐莊興業有限公司（下稱\n      豐莊公司）」進貨；然為避免前開虛增營收之行為將大幅\n      提高應繳營業稅，竟基於幫助鋒沐公司逃漏稅捐之概括犯\n      意，經由莊頭北公司負責人取得如附表二編號1 所示連勝\n      莊公司所虛開，面額總計46,725,186元之不實統一發票共\n      74張及如附表二編號2 所示豐莊公司所虛開之面額總計24\n      ,012,895元之不實統一發票63張，充作鋒沐公司進項憑證\n      ，申報扣抵銷項稅額，以此逃漏如附表二各扣除虛報銷項\n      及進項稅額實際逃漏稅額欄所示之營業稅，總計逃漏稅額\n      671,802 元，以此方式侵害國家稅收，足以生損害於稅捐\n      稽徵機關對於稅捐稽徵業務管理與課稅之公平及正確性。\n（三）其復明知金太陽公司於92年6 月起至93年6 月間止，與虛\n      設行號之「天技科技有限公司（下稱天技公司）」、「赫\n      拉科技股份有限公司（下稱赫拉公司）」間並無實際營業\n      往來之事實，惟為虛增金太陽公司營收、提高業績，而承\n      上揭連續填製不實事項之犯意，填製不實會計憑證而虛偽\n      開立如附表三所示，面額共計36,237,323元，無實際上交\n      易事實之不實銷項統一發票共41紙，分別交付天技公司、\n      赫拉公司充作進貨憑證，天技、赫拉公司並持向稅捐稽徵\n      機關申報不實進項（虛設公司並無實際營業行為，無逃漏\n      營業稅之問題），足以生損害於稅捐稽徵機關對於稅捐稽\n      徵業務管理正確性。\n（四）林燦榮明知金太陽公司於92年7 月至93年5 月間，並無向\n      天技公司、赫拉公司進貨，而基於逃漏稅捐之概括犯意，\n      取得如附表四編號1 所示天技公司所虛開，面額計28,340\n      ,060元之不實統一發票28張、附表四編號2 所示赫拉公司\n      所虛開，面額計4,802,450 元之統一發票4 張，充作金太\n      陽公司進項憑證，申報扣抵銷項稅額，以此逃漏如附表四\n      各扣除虛報銷項及進項稅額實際逃漏稅額欄所示之營業稅\n      ，總計逃漏稅額576,794 元，足以生損害於稅捐稽徵機關\n      對於稅捐稽徵業務管理與課稅之公平及正確性。\n二、案經財政部臺灣省北區國稅局移送及臺灣桃園地方法院檢察\n    署檢察官自動檢舉偵查起訴。",
    "reason": "一、本件經本院加以審酌之下列所引用各項證據方法之證據能力\n    ，業經檢察官、被告及辯護人於準備程序均不爭執其證據能\n    力並同意作為證據（見本院審訴字卷第20頁反面），且於言\n    詞辯論終結前未聲明異議，本院審酌該等書面陳述作成之情\n    況，核無違法取證或其他瑕疵，且與待證事實具有關聯性，\n    認為以之作為證據為適當，依刑事訴訟法第159 條之5 規定\n    ，得採為證據。\n二、認定犯罪事實之證據及理由：\n（一）上開事實，業據被告於本院自白（見本院訴字卷第58頁反\n      面）。\n（二）並經證人即另案被告曾繁堯、劉敏雄、陳森炎、莊浩仁證\n      述明確（分見第20654 號偵查卷一第190 至194 頁、卷二\n      第108 至111 、131 至134 頁）。\n（三）及財政部臺灣省北區國稅局查緝案件稽查報告及相關資料\n      、鋒沐公司90年11月至91年12月進項來源分析表、銷項去\n      路明細、營業人進銷項交易對彙加明細表、開立不實統一\n      發票明細表、專案申請調檔統一發票查核名冊及清單、已\n      扣抵銷項稅額專案申請調檔統一發票查名冊及清單、欠稅\n      總歸戶查詢情形表、及申報書跨中心查詢、鋒沐公司申報\n      書跨中心查詢1 紙暨進銷或統一發票來源分析、莊頭北公\n      司營業稅年度資料查詢- 進項來源明細（見第20654 號偵\n      查卷一第5 至13、159 至183 頁、卷二第4 、5 至21、23\n      至51頁）等證在卷可查。\n（四）及金太陽公司92年5 月至93年6 月進項來源分析表、銷項\n      去路明細、營業人進銷項交易對彙加明細表、開立不實統\n      一發票明細表、專案申請調檔統一發票查名冊及清單、已\n      扣抵銷項稅額專案申請調檔統一發票查核名冊清單、欠稅\n      總歸戶查詢情形表、申報書跨中心查詢、金太陽公司營業\n      人銷售額與稅額申報書等（見第19812 號偵查卷第5 至12\n      、25至56頁）可稽。\n（五）此外，並有財政部臺灣省北區國稅局函暨檢附之鋒沐公司\n      、金太陽公司扣除虛報銷項及進項稅額按每期實際逃漏稅\n      計算表、財政部臺灣省北區國稅局桃園縣分局函暨檢附之\n      鋒沐公司90、91年度營利事業所得稅結算申報核定通知書\n      及調整法令及依據說明書等件（見本院訴字卷第9 至13、\n      17至21、25至40頁）在卷可資佐證。\n（六）綜上，足認被告前揭任意性之自白，核與事實相符，堪以\n      採信。是本案事證明確，被告犯行洵堪認定。\n三、論罪科刑：\n（一）新舊法比較：被告行為後，刑法業於94年2 月2 日修正公\n      布，95年7 月1 日起施行。按行為後法律有變更者，適用\n      行為時之法律，但行為後之法律有利於行為人者，適用最\n      有利於行為人之法律，修正後刑法第2 條第1 項定有明文\n      。此條規定係規範行為後法律變更所生新舊法律比較適用\n      之準據法，本身尚無新舊法比較之問題，於新法施行後，\n      應一律適用新法第2 條第1 項之規定，為「從舊從輕」之\n      比較。而本次法律變更，比較時應就罪刑有關之共犯、未\n      遂犯、想像競合犯、牽連犯、連續犯、結合犯，以及累犯\n      加重、自首減輕暨其他法定加減原因（如身分加減）與加\n      減例等一切情形，綜其全部罪刑之結果而為比較（最高法\n      院95年5 月23日95年度第8 次刑事庭會議決議參照）。經\n      查：\n   1、修正前商業會計法第71條第1 款、稅捐稽徵法第43條第1\n      項，法定刑罰金部分，依修正後刑法第33條第5 款之規定\n      ，最低額為新臺幣1,000 元，惟依被告行為時之刑法第33\n      條第5 款規定，罰金之最低額僅新臺幣30元。比較修正前\n      後之刑罰法律，適用修正前之規定，對被告較為有利。\n   2、修正後刑法業已刪除第56條連續犯之規定。是於新法修正\n      施行後，行為人之數犯罪行為，即須分論併罰。此刪除雖\n      非犯罪構成要件之變更，但顯已影響行為人刑罰之法律效\n      果，自屬法律有變更，比較新舊法結果，適用被告行為時\n      法律即依舊法論以連續犯，對被告較為有利。\n   3、刑法第55條關於牽連犯之規定亦經刪除，則被告所犯各罪\n      ，應予分論併罰，比較新舊法結果，以適用被告行為時之\n      法律即修正前刑法第55條牽連犯之規定，較有利於被告。\n   4、罰金刑之加重，依修正後刑法第67條規定，其最高度及最\n      低度同加重之，較修正前刑法第68條所定，僅加重其最高\n      度，為不利於被告。\n   5、關於易科罰金之折算標準，依被告行為時之刑法第41條第\n      1 項、罰金罰鍰提高標準條例第2 條規定，係以銀元100\n      元、200 元或300 元，即新臺幣300 元、600 元或900 元\n      折算1 日；依修正後刑法第41條第1 項，則係以新臺幣1,\n      000 元、2,000 元或3,000 元折算1 日，經比較新舊法，\n      舊法對被告較為有利。\n   6、關於定應執行刑，被告行為後，修正後刑法第51條第5 款\n      規定：「宣告多數有期徒刑者，於各刑中之最長期以上，\n      各刑合併之刑期以下，定其刑期。但不得逾30年。」，與\n      修正前同條款規定：「宣告多數有期徒刑者，於各刑中之\n      最長期以上，各刑合併之刑期以下，定其刑期。但不得逾\n      20年。」之規定比較，自以修正前規定，對被告較為有利\n      。\n   7、綜上，經綜合法律修正前後之整體比較，揆諸前揭最高法\n      院決議及修正後刑法第2 條第1 項之「從舊從輕」原則，\n      適用94年2 月2 日修正前之刑罰法律，對被告較為有利，\n      自應適用修正前刑法之相關規定。\n   8、又查被告行為後，商業會計法第71條亦於95年5 月24日修\n      正公佈，並自同年月26日起施行。該條法定刑中關於罰金\n      部分，由修正前「或科或併科新臺幣15萬元以下罰金」，\n      經修正提高為「或科或併科新臺幣60萬元以下罰金」，依\n      刑法第2 條第1 項前段之「從舊從輕」原則，適用修正前\n      之規定。又被告行為後，稅捐稽徵法第47條業於98年5 月\n      27日修正公布，同年月29日生效，修正前第47條規定：「\n      本法關於納稅義務人、扣繳義務人及代徵人應處徒刑之規\n      定，於左列之人適用之：一、公司法規定之公司負責人。\n      二、民法或其他法律規定對外代表法人之董事或理事。三\n      、商業登記法規定之商業負責人。四、其他非法人團體之\n      代表人或管理人。」修正後該條則另立第二項規定「前項\n      規定之人與實際負責業務之人不同時，以實際負責業務之\n      人為準」。可見舊法並未將「實際負責人」列為公司負責\n      人（最高法院95年度台上字第741 號判決意旨參照）。查\n      鋒沐公司自84年間起至93年間，登記負責人均為曾繁堯一\n      節，有桃園縣稅捐稽徵處函及該公司之營利事業統一發證\n      變更登記申請書、變更登記事項卡等附卷可證（見第2065\n      4 號偵查卷一第24、30、40至41、43、46、55頁），而被\n      告自承係負責鋒沐公司實際營運，為鋒沐公司實際負責人\n      等語（見第20654 號偵查卷一第191 至192 頁），並經證\n      人曾繁堯證述屬實（見同上卷頁），揆諸上開說明，本件\n      被告就鋒沐公司而言，並非稅捐稽徵法第47條處罰之客體\n      。惟被告既實際負責鋒沐公司營運，而取得附表二所示不\n      實統一發票，充當鋒沐公司進項憑證以扣抵營業稅額，自\n      屬幫助鋒沐公司逃漏營業稅。至被告為金太陽公司登記負\n      責人，亦為實際負責人，依修正前稅捐稽徵法第47條規定\n      ，被告應論以該法第47條第1 款、第41條之公司負責人為\n      納稅義務人以不正當方法逃漏稅捐罪，法定刑為5 年以下\n      有期徒刑，然依修正後稅捐稽徵法第47條規定，被告既為\n      實際負責之人，仍應論以該法第47條第1 項第1 款、第41\n      條之罪，尚無新舊法比較適用之問題，逕用行為時之法律\n      ，併此敘明。\n（二）罪名：\n   1、按統一發票，係為證明事項之經過造具記帳所根據之憑證\n      ，屬原始憑證，屬商業會計法第15條第1 款之會計憑證。\n      是核被告就犯罪事實一（一），填製如附表一所示內容不\n      實之統一發票，交付莊頭北公司作為進項憑證，莊頭北公\n      司並持以向稅捐機關申報扣抵營業稅款，幫助莊頭北公司\n      納稅義務人逃漏營業稅，核其所為，係犯95年5 月24日修\n      正前商業會計法第71條第1 款以不實之事項填製會計憑證\n      或登入帳冊罪、稅捐稽徵法第43條第1 項幫助納稅義務人\n      逃漏稅捐罪。又商業會計法第71條第1 款以明知不實之事\n      項而填製會計憑證或記入帳冊之罪，原即含有業務上登載\n      不實之本質，應不再另論刑法第215 條之業務上登載不實\n      文書罪。\n   2、就犯罪事實一（二）部分，被告為鋒沐公司實際負責人，\n      向附表二所示之連勝莊、豐莊公司取得不實統一發票，持\n      向稅捐稽徵機申報扣抵營業稅額之所為，幫助鋒沐公司犯\n      稅捐稽徵法第41條以不正當方法逃漏稅捐罪，核其所為，\n      係犯稅捐稽徵法第43條第1 項幫助納稅義務人逃漏稅捐罪\n      。起訴書認被告係犯稅捐稽徵法第47條第1 款、第41條之\n      罪，尚有未洽，然基本犯罪事實相同，應予變更起訴法條\n      ；又本院已當庭諭知變更之起訴法條，其防禦權應可受保\n      障，不致造成突襲，併此說明。\n   3、就犯罪事實一（三）部分，按營業人無銷貨事實出售統一\n      發票牟取不法之利益，非屬營業稅課徵之標的，免予課徵\n      營業稅，業經財政部78年8 月3 日台財稅字第780195193\n      號函釋在案；稅捐稽徵法第41條之逃漏稅捐罪，係屬結果\n      犯，須發生逃漏應繳納稅捐之結果，始足構成。而行為人\n      虛設公司、行號，為製造該虛設公司、行號確有營業之假\n      象，乃與其他虛設公司、行號彼此間對開發票，或自有實\n      際營業而無實際銷售貨物或勞務之公司、行號取得發票，\n      因該虛設公司、行號並無實際營業行為，即無逃漏營業稅\n      捐之可言（最高法院99年度台上字第7817號判決參照），\n      查天技、赫拉公司於附表三所示之期間內，涉嫌與其他營\n      業人相互循環開立不實統一發票，經財政部臺灣省中區國\n      稅局移送偵辦在案，有刑事案件移送書在卷可按（見第19\n      812 號卷第41至46頁），是天技公司、赫拉公司係屬虛設\n      行號應堪認定，則此2 公司縱有自被告經營之金太陽公司\n      取得不實之進貨統一發票，亦無繳納營業稅而有逃漏營業\n      稅，則被告自亦無何幫助逃漏營業稅之情。是被告填製如\n      附表三所示內容不實之統一發票，交付如附表三所示天技\n      、赫拉公司作為進項憑證，核其所為，係犯95年5 月24日\n      修正前商業會計法第71條第1 款以不實之事項填製會計憑\n      證或登入帳冊罪。\n   4、就犯罪事實一（四）部分，被告為金太陽公司負責人，向\n      附表四所示之天技、赫拉公司取得不實統一發票，持向稅\n      捐稽徵機申報扣抵營業稅額，核其所為，係犯稅捐稽徵法\n      第41條、第47條第1 項逃漏稅捐罪。\n（三）被告就犯罪事實一（二）鋒沐公司於91年4 月、91年10月\n      、91年12月申報扣抵營業稅額，扣除虛報銷項及進項稅額\n      而幫助鋒沐公司實際逃漏如附表二每期實際逃漏稅欄所示\n      之稅額，及其就犯罪事實一（四）金太陽公司92年8 月、\n      92年12月、93年2 月、93年4 月申報扣抵營業稅額，扣除\n      虛報銷項及進項稅額而使金太陽公司實際逃漏如附表四每\n      期實際逃漏稅欄所示之稅額；暨其先後多次填製不實統一\n      發票交付莊頭北公司及天技、赫拉公司，並以此方式多次\n      幫助莊頭北公司逃漏營業稅之行為，均時間緊接，所犯各\n      為構成要件相同之罪名，顯係各基於概括犯意反覆實施，\n      均為連續犯，各應依修正前刑法第56條之規定，以一罪論\n      ，並加重其刑。被告就犯罪事實一（一）以填製不實會計\n      憑證之方式幫助他人逃漏營業稅，所犯上開二罪間，有手\n      段、目的之牽連關係，應依修正前刑法第55條後段規定，\n      從一重論以修正前商業會計法第71條第1 款之罪。公訴意\n      旨就此部分認係想像競合犯，尚有未洽，應予更正。\n（四）數罪併罰：被告就犯罪事實一（一）、（三）所犯連續商\n      業負責人填製不實會計憑證罪，犯罪事實一（二）所犯連\n      續幫助納稅義務人逃漏稅捐罪，犯罪事實一（四）所犯連\n      續逃漏稅捐罪，其犯意不同，行為互殊，均應予分論併罰\n      。\n（五）科刑：爰審酌被告之犯罪動機、目的、手段、其行為對於\n      稅捐稽徵機關課稅公正性及正確性之影響，及兼衡被告於\n      本院審理時終能坦承犯行，態度尚佳等一切情狀，分別量\n      處如主文所示之刑。\n（六）減刑：又被告上開犯罪時間均係在96年4 月24日以前，所\n      犯之罪，均合於中華民國九十六年罪犯減刑條例規定之減\n      刑條件，依該條例第2 條第1 項第3 款規定，各減其刑期\n      二分之一，並就減刑後之刑，定其應執行之刑，並依同條\n      例第9 條、修正前刑法第41條第1 項前段及95年5 月17日\n      修正刪除前罰金罰鍰提高標準條例第2 條之規定定其易科\n      罰金之折算標準。\n（七）緩刑：末查被告前未曾受有期徒刑以上刑之宣告一節，有\n      臺灣高等法院被告前案紀錄表1 紙在卷可稽，因一時失慮\n      ，偶罹刑典，事後已坦承犯行，顯有悔意，且業已向中華\n      社會福利聯合勸募協會為公益捐款15萬元，其經此刑之宣\n      告後，應已知警惕而無再犯之虞，故本院認為以暫不執行\n      為適當，併諭知宣告緩刑2 年，以啟自新。又緩刑之宣告\n      以裁判時之狀態為準，當然適用新法之規定，不再適用舊\n      法，併予說明。\n（八）不另為無罪諭知部分：被告於犯罪事實一（二）、（四）\n      所為幫助逃漏稅捐及逃漏稅捐犯行，應按各次營業稅申報\n      期間認係各別為之，已如上開說明；再按稅捐稽徵法第41\n      條之規定係屬結果犯，除犯罪之目的在逃漏營業稅外，並\n      須有逃漏應納營業稅之結果事實，始足構成該條之罪。查\n      如附表二所示之鋒沐公司於90年12月、91年2 月、91年6\n      月及91年8 月，固有向連勝莊公司、豐莊公司收取如附表\n      二所示之各該月不實統一發票作為進貨憑證，然經扣除虛\n      報銷項及進項稅額後，上開各次營業稅申報計算後漏稅額\n      為0 ，並未發生逃漏應繳納營業稅之結果，與稅捐稽徵法\n      第43條第1 項幫助逃漏稅捐罪之構成要件有間，被告就此\n      部分並不成立稅捐稽徵法第43條第1 項幫助逃漏稅捐罪之\n      幫助犯。又如附表四所示之金太陽公司於92年10月、93年\n      6 月，固有向天技公司、赫拉公司收取如附表四所示之各\n      該月不實統一發票作為進貨憑證，然經扣除虛報銷項及進\n      項稅額後，上開各次營業稅申報計算後漏稅額為0 ，亦未\n      發生逃漏應繳納稅捐之結果，與稅捐稽徵法第41條逃漏稅\n      捐罪之構成要件有間，被告就此部分亦不成立稅捐稽徵法\n      第41條逃漏稅捐罪，此部分本應為被告無罪之諭知，惟檢\n      察官認為此部分若成立犯罪，與上開論罪科刑部分有連續\n      犯裁判上一罪之關係，就此部分爰不另為無罪之諭知。\n據上論斷，應依刑事訴訟法第第299 條第1 項前段、第300 條，\n95年5 月24日修正前之商業會計法第71條第1 款，修正前稅捐稽\n徵法第47條第1 項，修正前刑法第56條、第55條、第41條第1 項\n前段、第51條第5 款，稅捐稽徵法第41條、第43條第1 項，刑法\n第2 條第1 項前段、第11條前段、第74條第1 項第1 款，修正刪\n除前罰金罰鍰提高標準條例第2 條，現行法規所定貨幣單位折算\n新臺幣條例第2 條，中華民國九十六年罪犯減刑條例第2 條第1\n項第3 款、第7 條、第9 條、第10條第1 項，判決如主文。\n本案經檢察官陳睿明到庭執行職務。\n中    華    民    國   100    年    12    月    30    日\n                刑事第十四庭  審判長 法  官  鍾雅蘭\n                                     法  官  郭俊德\n                                     法  官  楊麗文\n以上正本證明與原本無異。\n如不服本判決應於收受判決後10日內向本院提出上訴書狀，並應\n敘述具體理由。其未敘述上訴理由者，應於上訴期間屆滿後20日\n內向本院補提理由書( 均須按他造當事人之人數附繕本) 「切勿\n逕送上級法院」。\n                                     書記官  柯凱騰"
  },
  "search": "臺灣桃園地方法院刑事判決100年度訴字第747號公訴人臺灣桃園地方法院檢察署檢察官被告林燦榮選任辯護人郭啟榮律師上列被告因商業會計法等案件，經檢察官提起公訴（99年度偵字第19812、23189號），本院判決如下：主文林燦榮連續犯商業會計法第七十一條第一款之填製不實罪，處有期徒刑伍月，如易科罰金，以銀元佰元即新臺幣玖佰元折算壹日；減為有期徒刑貳月又拾伍日，如易科罰金，以銀元佰元即新臺幣玖佰元折算壹日。又連續犯稅捐稽徵法第四十三條第一項之幫助逃漏稅捐罪，處有期徒刑參月，如易科罰金，以銀元佰元即新臺幣玖佰元折算壹日；減為有期徒刑壹月又拾伍日，如易科罰金，以銀元佰元即新臺幣玖佰元折算壹日。又連續犯稅捐稽徵法第四十一條第一項之逃漏稅捐罪，處有期徒刑陸月，如易科罰金，以銀元佰元即新臺幣玖佰元折算壹日；減為有期徒刑參月，如易科罰金，以銀元佰元即新臺幣玖佰元折算壹日。應執行有期徒刑陸月，如易科罰金，以銀元佰元即新臺幣玖佰元折算壹日。緩刑貳年。事實一、林燦榮於民國90至93年間，為址設桃園縣龍潭鄉九龍村23鄰九座寮43-6號之「金太陽精密工業股份有限公司（下稱金太陽公司）」之負責人，係商業會計法規範之商業負責人，處理公司之會計及開立統一發票事務；林燦榮另為址設桃園市○○里○○路2段1號4樓之「鋒沐股份有限公司（下稱鋒沐公司）」之實際負責人，鋒沐公司、金太陽公司均為稅捐稽徵法之納稅義務人。林燦榮明知統一發票係商業會計法所規定之會計憑證，倘無實際銷售營業或提供勞務之事實，不得虛偽開立，竟違反營業人銷售貨物或勞務時，應依據所銷售貨物或勞務之實際內容據實開立統一發票之規定，基於不實填載會計憑證、幫助逃漏稅捐及逃漏稅捐之概括犯意，而為下列行為：（一）其明知鋒沐公司於90年11月起至91年12月間止，並無銷貨予「莊頭北工業股份有限公司（下稱莊頭北公司）」之事實，惟為虛增鋒沐公司營收，竟連續填製不實事項而虛偽開立如附表一所示，面額共計新臺幣（下同）67,192,274元，無實際上交易事實之不實銷項統一發票共91紙，交付納稅義務人莊頭北公司充作進貨憑證，供莊頭北公司持向稅捐稽徵機關申報各期營業稅時，誆稱該等統一發票係進項成本而為行使，持以虛報為進項成本以扣抵銷項稅額，而幫助莊頭北公司逃漏營業稅，足以生損害於稅捐稽徵機關對於稅捐稽徵業務管理與課稅之公平及正確性。（二）林燦榮明知鋒沐公司於90年11月至91年10月間，並無向劉敏雄（另案為不起訴處分）所經營之「連勝莊興業有限公司（下稱連勝莊公司）」進貨；於91年3月至12月間，亦未向白晉強（已歿）所經營之「豐莊興業有限公司（下稱豐莊公司）」進貨；然為避免前開虛增營收之行為將大幅提高應繳營業稅，竟基於幫助鋒沐公司逃漏稅捐之概括犯意，經由莊頭北公司負責人取得如附表二編號1所示連勝莊公司所虛開，面額總計46,725,186元之不實統一發票共74張及如附表二編號2所示豐莊公司所虛開之面額總計24,012,895元之不實統一發票63張，充作鋒沐公司進項憑證，申報扣抵銷項稅額，以此逃漏如附表二各扣除虛報銷項及進項稅額實際逃漏稅額欄所示之營業稅，總計逃漏稅額671,802元，以此方式侵害國家稅收，足以生損害於稅捐稽徵機關對於稅捐稽徵業務管理與課稅之公平及正確性。（三）其復明知金太陽公司於92年6月起至93年6月間止，與虛設行號之「天技科技有限公司（下稱天技公司）」、「赫拉科技股份有限公司（下稱赫拉公司）」間並無實際營業往來之事實，惟為虛增金太陽公司營收、提高業績，而承上揭連續填製不實事項之犯意，填製不實會計憑證而虛偽開立如附表三所示，面額共計36,237,323元，無實際上交易事實之不實銷項統一發票共41紙，分別交付天技公司、赫拉公司充作進貨憑證，天技、赫拉公司並持向稅捐稽徵機關申報不實進項（虛設公司並無實際營業行為，無逃漏營業稅之問題），足以生損害於稅捐稽徵機關對於稅捐稽徵業務管理正確性。（四）林燦榮明知金太陽公司於92年7月至93年5月間，並無向天技公司、赫拉公司進貨，而基於逃漏稅捐之概括犯意，取得如附表四編號1所示天技公司所虛開，面額計28,340,060元之不實統一發票28張、附表四編號2所示赫拉公司所虛開，面額計4,802,450元之統一發票4張，充作金太陽公司進項憑證，申報扣抵銷項稅額，以此逃漏如附表四各扣除虛報銷項及進項稅額實際逃漏稅額欄所示之營業稅，總計逃漏稅額576,794元，足以生損害於稅捐稽徵機關對於稅捐稽徵業務管理與課稅之公平及正確性。二、案經財政部臺灣省北區國稅局移送及臺灣桃園地方法院檢察署檢察官自動檢舉偵查起訴。理由一、本件經本院加以審酌之下列所引用各項證據方法之證據能力，業經檢察官、被告及辯護人於準備程序均不爭執其證據能力並同意作為證據（見本院審訴字卷第20頁反面），且於言詞辯論終結前未聲明異議，本院審酌該等書面陳述作成之情況，核無違法取證或其他瑕疵，且與待證事實具有關聯性，認為以之作為證據為適當，依刑事訴訟法第159條之5規定，得採為證據。二、認定犯罪事實之證據及理由：（一）上開事實，業據被告於本院自白（見本院訴字卷第58頁反面）。（二）並經證人即另案被告曾繁堯、劉敏雄、陳森炎、莊浩仁證述明確（分見第20654號偵查卷一第190至194頁、卷二第108至111、131至134頁）。（三）及財政部臺灣省北區國稅局查緝案件稽查報告及相關資料、鋒沐公司90年11月至91年12月進項來源分析表、銷項去路明細、營業人進銷項交易對彙加明細表、開立不實統一發票明細表、專案申請調檔統一發票查核名冊及清單、已扣抵銷項稅額專案申請調檔統一發票查名冊及清單、欠稅總歸戶查詢情形表、及申報書跨中心查詢、鋒沐公司申報書跨中心查詢1紙暨進銷或統一發票來源分析、莊頭北公司營業稅年度資料查詢-進項來源明細（見第20654號偵查卷一第5至13、159至183頁、卷二第4、5至21、23至51頁）等證在卷可查。（四）及金太陽公司92年5月至93年6月進項來源分析表、銷項去路明細、營業人進銷項交易對彙加明細表、開立不實統一發票明細表、專案申請調檔統一發票查名冊及清單、已扣抵銷項稅額專案申請調檔統一發票查核名冊清單、欠稅總歸戶查詢情形表、申報書跨中心查詢、金太陽公司營業人銷售額與稅額申報書等（見第19812號偵查卷第5至12、25至56頁）可稽。（五）此外，並有財政部臺灣省北區國稅局函暨檢附之鋒沐公司、金太陽公司扣除虛報銷項及進項稅額按每期實際逃漏稅計算表、財政部臺灣省北區國稅局桃園縣分局函暨檢附之鋒沐公司90、91年度營利事業所得稅結算申報核定通知書及調整法令及依據說明書等件（見本院訴字卷第9至13、17至21、25至40頁）在卷可資佐證。（六）綜上，足認被告前揭任意性之自白，核與事實相符，堪以採信。是本案事證明確，被告犯行洵堪認定。三、論罪科刑：（一）新舊法比較：被告行為後，刑法業於94年2月2日修正公布，95年7月1日起施行。按行為後法律有變更者，適用行為時之法律，但行為後之法律有利於行為人者，適用最有利於行為人之法律，修正後刑法第2條第1項定有明文。此條規定係規範行為後法律變更所生新舊法律比較適用之準據法，本身尚無新舊法比較之問題，於新法施行後，應一律適用新法第2條第1項之規定，為「從舊從輕」之比較。而本次法律變更，比較時應就罪刑有關之共犯、未遂犯、想像競合犯、牽連犯、連續犯、結合犯，以及累犯加重、自首減輕暨其他法定加減原因（如身分加減）與加減例等一切情形，綜其全部罪刑之結果而為比較（最高法院95年5月23日95年度第8次刑事庭會議決議參照）。經查：1、修正前商業會計法第71條第1款、稅捐稽徵法第43條第1項，法定刑罰金部分，依修正後刑法第33條第5款之規定，最低額為新臺幣1,000元，惟依被告行為時之刑法第33條第5款規定，罰金之最低額僅新臺幣30元。比較修正前後之刑罰法律，適用修正前之規定，對被告較為有利。2、修正後刑法業已刪除第56條連續犯之規定。是於新法修正施行後，行為人之數犯罪行為，即須分論併罰。此刪除雖非犯罪構成要件之變更，但顯已影響行為人刑罰之法律效果，自屬法律有變更，比較新舊法結果，適用被告行為時法律即依舊法論以連續犯，對被告較為有利。3、刑法第55條關於牽連犯之規定亦經刪除，則被告所犯各罪，應予分論併罰，比較新舊法結果，以適用被告行為時之法律即修正前刑法第55條牽連犯之規定，較有利於被告。4、罰金刑之加重，依修正後刑法第67條規定，其最高度及最低度同加重之，較修正前刑法第68條所定，僅加重其最高度，為不利於被告。5、關於易科罰金之折算標準，依被告行為時之刑法第41條第1項、罰金罰鍰提高標準條例第2條規定，係以銀元100元、200元或300元，即新臺幣300元、600元或900元折算1日；依修正後刑法第41條第1項，則係以新臺幣1,000元、2,000元或3,000元折算1日，經比較新舊法，舊法對被告較為有利。6、關於定應執行刑，被告行為後，修正後刑法第51條第5款規定：「宣告多數有期徒刑者，於各刑中之最長期以上，各刑合併之刑期以下，定其刑期。但不得逾30年。」，與修正前同條款規定：「宣告多數有期徒刑者，於各刑中之最長期以上，各刑合併之刑期以下，定其刑期。但不得逾20年。」之規定比較，自以修正前規定，對被告較為有利。7、綜上，經綜合法律修正前後之整體比較，揆諸前揭最高法院決議及修正後刑法第2條第1項之「從舊從輕」原則，適用94年2月2日修正前之刑罰法律，對被告較為有利，自應適用修正前刑法之相關規定。8、又查被告行為後，商業會計法第71條亦於95年5月24日修正公佈，並自同年月26日起施行。該條法定刑中關於罰金部分，由修正前「或科或併科新臺幣15萬元以下罰金」，經修正提高為「或科或併科新臺幣60萬元以下罰金」，依刑法第2條第1項前段之「從舊從輕」原則，適用修正前之規定。又被告行為後，稅捐稽徵法第47條業於98年5月27日修正公布，同年月29日生效，修正前第47條規定：「本法關於納稅義務人、扣繳義務人及代徵人應處徒刑之規定，於左列之人適用之：一、公司法規定之公司負責人。二、民法或其他法律規定對外代表法人之董事或理事。三、商業登記法規定之商業負責人。四、其他非法人團體之代表人或管理人。」修正後該條則另立第二項規定「前項規定之人與實際負責業務之人不同時，以實際負責業務之人為準」。可見舊法並未將「實際負責人」列為公司負責人（最高法院95年度台上字第741號判決意旨參照）。查鋒沐公司自84年間起至93年間，登記負責人均為曾繁堯一節，有桃園縣稅捐稽徵處函及該公司之營利事業統一發證變更登記申請書、變更登記事項卡等附卷可證（見第20654號偵查卷一第24、30、40至41、43、46、55頁），而被告自承係負責鋒沐公司實際營運，為鋒沐公司實際負責人等語（見第20654號偵查卷一第191至192頁），並經證人曾繁堯證述屬實（見同上卷頁），揆諸上開說明，本件被告就鋒沐公司而言，並非稅捐稽徵法第47條處罰之客體。惟被告既實際負責鋒沐公司營運，而取得附表二所示不實統一發票，充當鋒沐公司進項憑證以扣抵營業稅額，自屬幫助鋒沐公司逃漏營業稅。至被告為金太陽公司登記負責人，亦為實際負責人，依修正前稅捐稽徵法第47條規定，被告應論以該法第47條第1款、第41條之公司負責人為納稅義務人以不正當方法逃漏稅捐罪，法定刑為5年以下有期徒刑，然依修正後稅捐稽徵法第47條規定，被告既為實際負責之人，仍應論以該法第47條第1項第1款、第41條之罪，尚無新舊法比較適用之問題，逕用行為時之法律，併此敘明。（二）罪名：1、按統一發票，係為證明事項之經過造具記帳所根據之憑證，屬原始憑證，屬商業會計法第15條第1款之會計憑證。是核被告就犯罪事實一（一），填製如附表一所示內容不實之統一發票，交付莊頭北公司作為進項憑證，莊頭北公司並持以向稅捐機關申報扣抵營業稅款，幫助莊頭北公司納稅義務人逃漏營業稅，核其所為，係犯95年5月24日修正前商業會計法第71條第1款以不實之事項填製會計憑證或登入帳冊罪、稅捐稽徵法第43條第1項幫助納稅義務人逃漏稅捐罪。又商業會計法第71條第1款以明知不實之事項而填製會計憑證或記入帳冊之罪，原即含有業務上登載不實之本質，應不再另論刑法第215條之業務上登載不實文書罪。2、就犯罪事實一（二）部分，被告為鋒沐公司實際負責人，向附表二所示之連勝莊、豐莊公司取得不實統一發票，持向稅捐稽徵機申報扣抵營業稅額之所為，幫助鋒沐公司犯稅捐稽徵法第41條以不正當方法逃漏稅捐罪，核其所為，係犯稅捐稽徵法第43條第1項幫助納稅義務人逃漏稅捐罪。起訴書認被告係犯稅捐稽徵法第47條第1款、第41條之罪，尚有未洽，然基本犯罪事實相同，應予變更起訴法條；又本院已當庭諭知變更之起訴法條，其防禦權應可受保障，不致造成突襲，併此說明。3、就犯罪事實一（三）部分，按營業人無銷貨事實出售統一發票牟取不法之利益，非屬營業稅課徵之標的，免予課徵營業稅，業經財政部78年8月3日台財稅字第780195193號函釋在案；稅捐稽徵法第41條之逃漏稅捐罪，係屬結果犯，須發生逃漏應繳納稅捐之結果，始足構成。而行為人虛設公司、行號，為製造該虛設公司、行號確有營業之假象，乃與其他虛設公司、行號彼此間對開發票，或自有實際營業而無實際銷售貨物或勞務之公司、行號取得發票，因該虛設公司、行號並無實際營業行為，即無逃漏營業稅捐之可言（最高法院99年度台上字第7817號判決參照），查天技、赫拉公司於附表三所示之期間內，涉嫌與其他營業人相互循環開立不實統一發票，經財政部臺灣省中區國稅局移送偵辦在案，有刑事案件移送書在卷可按（見第19812號卷第41至46頁），是天技公司、赫拉公司係屬虛設行號應堪認定，則此2公司縱有自被告經營之金太陽公司取得不實之進貨統一發票，亦無繳納營業稅而有逃漏營業稅，則被告自亦無何幫助逃漏營業稅之情。是被告填製如附表三所示內容不實之統一發票，交付如附表三所示天技、赫拉公司作為進項憑證，核其所為，係犯95年5月24日修正前商業會計法第71條第1款以不實之事項填製會計憑證或登入帳冊罪。4、就犯罪事實一（四）部分，被告為金太陽公司負責人，向附表四所示之天技、赫拉公司取得不實統一發票，持向稅捐稽徵機申報扣抵營業稅額，核其所為，係犯稅捐稽徵法第41條、第47條第1項逃漏稅捐罪。（三）被告就犯罪事實一（二）鋒沐公司於91年4月、91年10月、91年12月申報扣抵營業稅額，扣除虛報銷項及進項稅額而幫助鋒沐公司實際逃漏如附表二每期實際逃漏稅欄所示之稅額，及其就犯罪事實一（四）金太陽公司92年8月、92年12月、93年2月、93年4月申報扣抵營業稅額，扣除虛報銷項及進項稅額而使金太陽公司實際逃漏如附表四每期實際逃漏稅欄所示之稅額；暨其先後多次填製不實統一發票交付莊頭北公司及天技、赫拉公司，並以此方式多次幫助莊頭北公司逃漏營業稅之行為，均時間緊接，所犯各為構成要件相同之罪名，顯係各基於概括犯意反覆實施，均為連續犯，各應依修正前刑法第56條之規定，以一罪論，並加重其刑。被告就犯罪事實一（一）以填製不實會計憑證之方式幫助他人逃漏營業稅，所犯上開二罪間，有手段、目的之牽連關係，應依修正前刑法第55條後段規定，從一重論以修正前商業會計法第71條第1款之罪。公訴意旨就此部分認係想像競合犯，尚有未洽，應予更正。（四）數罪併罰：被告就犯罪事實一（一）、（三）所犯連續商業負責人填製不實會計憑證罪，犯罪事實一（二）所犯連續幫助納稅義務人逃漏稅捐罪，犯罪事實一（四）所犯連續逃漏稅捐罪，其犯意不同，行為互殊，均應予分論併罰。（五）科刑：爰審酌被告之犯罪動機、目的、手段、其行為對於稅捐稽徵機關課稅公正性及正確性之影響，及兼衡被告於本院審理時終能坦承犯行，態度尚佳等一切情狀，分別量處如主文所示之刑。（六）減刑：又被告上開犯罪時間均係在96年4月24日以前，所犯之罪，均合於中華民國九十六年罪犯減刑條例規定之減刑條件，依該條例第2條第1項第3款規定，各減其刑期二分之一，並就減刑後之刑，定其應執行之刑，並依同條例第9條、修正前刑法第41條第1項前段及95年5月17日修正刪除前罰金罰鍰提高標準條例第2條之規定定其易科罰金之折算標準。（七）緩刑：末查被告前未曾受有期徒刑以上刑之宣告一節，有臺灣高等法院被告前案紀錄表1紙在卷可稽，因一時失慮，偶罹刑典，事後已坦承犯行，顯有悔意，且業已向中華社會福利聯合勸募協會為公益捐款15萬元，其經此刑之宣告後，應已知警惕而無再犯之虞，故本院認為以暫不執行為適當，併諭知宣告緩刑2年，以啟自新。又緩刑之宣告以裁判時之狀態為準，當然適用新法之規定，不再適用舊法，併予說明。（八）不另為無罪諭知部分：被告於犯罪事實一（二）、（四）所為幫助逃漏稅捐及逃漏稅捐犯行，應按各次營業稅申報期間認係各別為之，已如上開說明；再按稅捐稽徵法第41條之規定係屬結果犯，除犯罪之目的在逃漏營業稅外，並須有逃漏應納營業稅之結果事實，始足構成該條之罪。查如附表二所示之鋒沐公司於90年12月、91年2月、91年6月及91年8月，固有向連勝莊公司、豐莊公司收取如附表二所示之各該月不實統一發票作為進貨憑證，然經扣除虛報銷項及進項稅額後，上開各次營業稅申報計算後漏稅額為0，並未發生逃漏應繳納營業稅之結果，與稅捐稽徵法第43條第1項幫助逃漏稅捐罪之構成要件有間，被告就此部分並不成立稅捐稽徵法第43條第1項幫助逃漏稅捐罪之幫助犯。又如附表四所示之金太陽公司於92年10月、93年6月，固有向天技公司、赫拉公司收取如附表四所示之各該月不實統一發票作為進貨憑證，然經扣除虛報銷項及進項稅額後，上開各次營業稅申報計算後漏稅額為0，亦未發生逃漏應繳納稅捐之結果，與稅捐稽徵法第41條逃漏稅捐罪之構成要件有間，被告就此部分亦不成立稅捐稽徵法第41條逃漏稅捐罪，此部分本應為被告無罪之諭知，惟檢察官認為此部分若成立犯罪，與上開論罪科刑部分有連續犯裁判上一罪之關係，就此部分爰不另為無罪之諭知。據上論斷，應依刑事訴訟法第第299條第1項前段、第300條，95年5月24日修正前之商業會計法第71條第1款，修正前稅捐稽徵法第47條第1項，修正前刑法第56條、第55條、第41條第1項前段、第51條第5款，稅捐稽徵法第41條、第43條第1項，刑法第2條第1項前段、第11條前段、第74條第1項第1款，修正刪除前罰金罰鍰提高標準條例第2條，現行法規所定貨幣單位折算新臺幣條例第2條，中華民國九十六年罪犯減刑條例第2條第1項第3款、第7條、第9條、第10條第1項，判決如主文。本案經檢察官陳睿明到庭執行職務。中華民國100年12月30日刑事第十四庭審判長法官鍾雅蘭法官郭俊德法官楊麗文以上正本證明與原本無異。如不服本判決應於收受判決後10日內向本院提出上訴書狀，並應敘述具體理由。其未敘述上訴理由者，應於上訴期間屆滿後20日內向本院補提理由書(均須按他造當事人之人數附繕本)「切勿逕送上級法院」。書記官柯凱騰中華民國100年12月30日附錄本案論罪科刑法條全文修正前商業會計法第71條商業負責人、主辦及經辦會計人員或依法受託代他人處理會計事務之人員有下列情事之一者，處5年以下有期徒刑、拘役或科或併科新臺幣15萬元以下罰金：一、以明知為不實之事項，而填製會計憑證或記入帳冊。二、故意使應保存之會計憑證、會計帳簿報表滅失毀損。三、偽造或變造會計憑證、會計帳簿報表內容或毀損其頁數。四、故意遺漏會計事項不為記錄，致使財務報表發生不實之結果。五、其他利用不正當方法，致使會計事項或財務報表發生不實之結果。稅捐稽徵法第41條納稅義務人以詐術或其他不正當方法逃漏稅捐者，處5年以下有期徒刑、拘役或科或併科新臺幣6萬元以下罰金。稅捐稽徵法第43條教唆或幫助犯第41條或第42條之罪者，處3年以下有期徒刑、拘役或科新台幣6萬元以下罰金。稅務人員、執行業務之律師、會計師或其他合法代理人犯前項之罪者，加重其刑至二分之一。稅務稽徵人員違反第33條規定者，除觸犯刑法者移送法辦外，處1萬元以上5萬元以下罰鍰。附表一：鋒沐公司虛開統一發票明細┌─┬──────┬────┬──────┬──────┬─────┐│編│營業人名稱│開立年月│發票字軌號碼│銷售金額（新│逃漏營業稅││號││││臺幣）│稅額│├─┼──────┼────┼──────┼──────┼─────┤│1│莊頭北工業股│90年11月│KB00000000│2,153,640元│10,682元│││份有限公司├────┼──────┼──────┼─────┤│││90年12月│KB00000000│1,055,125元│52,756元│││├────┼──────┼──────┼─────┤│││90年12月│KB00000000│3,994,500元│199,725元│││├────┼──────┼──────┼─────┤│││90年12月│KB00000000│2,589,000元│129,450元│││├────┼──────┼──────┼─────┤│││90年12月│KB00000000│2,058,255元│102,913元│││├────┼──────┼──────┼─────┤│││90年12月│KB00000000│3,997,163元│199,858元│││├────┼──────┼──────┼─────┤│││90年12月│KB00000000│1,196,000元│59,800元│││├────┼──────┼──────┼─────┤│││90年12月│KB00000000│734,052元│36,703元│││├────┼──────┼──────┼─────┤│││90年12月│KB00000000│837,200元│41,860元│││├────┼──────┼──────┼─────┤│││90年12月│KB00000000│1,064,300元│53,215元│││├────┼──────┼──────┼─────┤│││90年12月│KB00000000│1,784,210元│89,211元│││├────┼──────┼──────┼─────┤│││90年12月│KB00000000│1,941,750元│97,088元│││├────┼──────┼──────┼─────┤│││90年12月│KB00000000│1,331,500元│66,575元│││├────┼──────┼──────┼─────┤│││90年12月│KB00000000│1,294,500元│64,725元│││├────┼──────┼──────┼─────┤│││90年12月│KB00000000│1,331,500元│66,575元│││├────┼──────┼──────┼─────┤│││90年12月│KB00000000│1,294,500元│64,725元│││├────┼──────┼──────┼─────┤│││90年12月│KB00000000│2,663,000元│133,150元│││├────┼──────┼──────┼─────┤│││91年1月│LA00000000│1,327,560元│66,378元│││├────┼──────┼──────┼─────┤│││91年1月│LA00000000│301,290元│15,065元│││├────┼──────┼──────┼─────┤│││91年2月│LA00000000│205,520元│10,276元│││├────┼──────┼──────┼─────┤│││91年2月│LA00000000│1,065,200元│53,260元│││├────┼──────┼──────┼─────┤│││91年2月│LA00000000│380,583元│19,029元│││├────┼──────┼──────┼─────┤│││91年3月│LZ00000000│40,099元│2,005元│││├────┼──────┼──────┼─────┤│││91年3月│LZ00000000│30,813元│1,541元│││├────┼──────┼──────┼─────┤│││91年3月│LZ00000000│87,398元│4,370元│││├────┼──────┼──────┼─────┤│││91年3月│LZ00000000│232,764元│11,638元│││├────┼──────┼──────┼─────┤│││91年3月│LZ00000000│234,625元│11,731元│││├────┼──────┼──────┼─────┤│││91年3月│LZ00000000│158,316元│7,916元│││├────┼──────┼──────┼─────┤│││91年3月│LZ00000000│265,195元│13,260元│││├────┼──────┼──────┼─────┤│││91年3月│LZ00000000│161,210元│8,061元│││├────┼──────┼──────┼─────┤│││91年3月│LZ00000000│212,280元│10,614元│││├────┼──────┼──────┼─────┤│││91年3月│LZ00000000│442,600元│22,130元│││├────┼──────┼──────┼─────┤│││91年3月│LZ00000000│997,002元│49,850元│││├────┼──────┼──────┼─────┤│││91年3月│LZ00000000│1,256,187元│62,809元│││├────┼──────┼──────┼─────┤│││91年4月│LZ00000000│389,852元│19,493元│││├────┼──────┼──────┼─────┤│││91年4月│LZ00000000│639,557元│31,978元│││├────┼──────┼──────┼─────┤│││91年4月│LZ00000000│653,686元│32,684元│││├────┼──────┼──────┼─────┤│││91年4月│LZ00000000│1,294,515元│64,726元│││├────┼──────┼──────┼─────┤│││91年4月│LZ00000000│1,354,561元│67,728元│││├────┼──────┼──────┼─────┤│││91年4月│LZ00000000│291,910元│14,596元│││├────┼──────┼──────┼─────┤│││91年6月│MY00000000│662,000元│33,100元│││├────┼──────┼──────┼─────┤│││91年6月│MY00000000│443,900元│22,195元│││├────┼──────┼──────┼─────┤│││91年6月│MY00000000│653,305元│32,665元│││├────┼──────┼──────┼─────┤│││91年6月│MY00000000│1,544,000元│77,200元│││├────┼──────┼──────┼─────┤│││91年6月│MY00000000│744,700元│37,235元│││├────┼──────┼──────┼─────┤│││91年6月│MY00000000│637,000元│31,850元│││├────┼──────┼──────┼─────┤│││91年6月│MY00000000│796,250元│39,813元│││├────┼──────┼──────┼─────┤│││91年6月│MY00000000│123,660元│6,183元│││├────┼──────┼──────┼─────┤│││91年6月│MY00000000│255,099元│12,755元│││├────┼──────┼──────┼─────┤│││91年6月│MY00000000│570,210元│28,511元│││├────┼──────┼──────┼─────┤│││91年6月│MY00000000│432,668元│21,633元│││├────┴──────┴──────┴─────┤│││91年7月│NX00000000│1,078,590元│53,930元│││├────┼──────┼──────┼─────┤│││91年7月│NX00000000│1,007,460元│50,373元│││├────┼──────┼──────┼─────┤│││91年7月│NX00000000│965,000元│48,250元│││├────┼──────┼──────┼─────┤│││91年7月│NX00000000│345,400元│17,270元│││├────┼──────┼──────┼─────┤│││91年7月│NX00000000│578,496元│28,925元│││├────┼──────┼──────┼─────┤│││91年8月│NX00000000│446,526元│22,326元│││├────┼──────┼──────┼─────┤│││91年8月│NX00000000│113,099元│5,655元│││├────┼──────┼──────┼─────┤│││91年8月│NX00000000│378,290元│18,915元│││├────┼──────┼──────┼─────┤│││91年8月│NX00000000│538,970元│26,949元│││├────┼──────┼──────┼─────┤│││91年8月│NX00000000│576,822元│28,841元│││├────┼──────┼──────┼─────┤│││91年8月│NX00000000│30,240元│1,512元│││├────┼──────┼──────┼─────┤│││91年8月│NX0000000│42,596元│2,130元│││├────┼──────┼──────┼─────┤│││91年8月│NX0000000│63,640元│3,182元│││├────┼──────┼──────┼─────┤│││91年8月│NX0000000│42,183元│2,109元│││├────┼──────┼──────┼─────┤│││91年9月│PW00000000│654,905元│32,745元│││├────┼──────┼──────┼─────┤│││91年9月│PW00000000│531,030元│26,552元│││├────┼──────┼──────┼─────┤│││91年9月│PW00000000│62,322元│3,116元│││├────┼──────┼──────┼─────┤│││91年9月│PW00000000│581,102元│29,055元│││├────┼──────┼──────┼─────┤│││91年9月│PW00000000│86,816元│4,341元│││├────┼──────┼──────┼─────┤│││91年9月│PW00000000│16,800元│840元│││├────┼──────┼──────┼─────┤│││91年9月│PW00000000│56,070元│2,804元│││├────┼──────┼──────┼─────┤│││91年9月│PW00000000│59,814元│2,991元│││├────┼──────┼──────┼─────┤│││91年9月│PW00000000│121,560元│6,078元│││├────┼──────┼──────┼─────┤│││91年10月│PW00000000│47,845元│2,392元│││├────┼──────┼──────┼─────┤│││91年10月│PW00000000│131,480元│6,574元│││├────┼──────┼──────┼─────┤│││91年10月│PW00000000│44,032元│2,202元│││├────┼──────┼──────┼─────┤│││91年10月│PW00000000│131,480元│6,574元│││├────┴──────┴──────┴─────┤│││91年12月│QV00000000│792,590元│39,630元│││├────┼──────┼──────┼─────┤│││91年12月│QV00000000│600,160元│30,008元│││├────┼──────┼──────┼─────┤│││91年12月│QV00000000│727,200元│36,360元│││├────┼──────┼──────┼─────┤│││91年12月│QV00000000│502,080元│25,104元│││├────┼──────┼──────┼─────┤│││91年12月│QV00000000│745,590元│37,280元│││├────┼──────┼──────┼─────┤│││91年12月│QV00000000│728,476元│36,424元│││├────┼──────┼──────┼─────┤│││91年12月│QV00000000│947,800元│47,390元│││├────┼──────┼──────┼─────┤│││91年12月│QV00000000│627,600元│31,380元│││├────┼──────┼──────┼─────┤│││91年12月│QV00000000│846,250元│42,313元│││├────┼──────┼──────┼─────┤│││91年12月│QV00000000│207,090元│10,355元│││├────┼──────┼──────┼─────┤│││91年12月│QV00000000│439,800元│21,990元│││├────┼──────┼──────┼─────┤│││91年12月│QV00000000│378,375元│18,919元│││├────┼──────┼──────┼─────┤│││91年12月│QV00000000│710,985元│35,549元│├─┴──────┴────┴──────┼──────┼─────┤│合計│67,192,274元│3,359,622││││元│└────────────────────┴──────┴─────┘附表二：鋒沐公司以不實發票申報扣抵銷稅項明細┌─┬──────┬────┬───────┬─────┬────┐│編│被告取得不實│開立年月│發票字軌號碼│虛進金額（│虛進稅額││號│發票之營業人│││新臺幣）│（新臺幣│││名稱││││）│├─┼──────┼────┼───────┼─────┼────┤│1│連勝莊興業有│90年11月│KB00000000│586,480元│29,324元│││限公司├────┼───────┼─────┼────┤│││90年11月│KB00000000│800,210元│40,011元│││├────┼───────┼─────┼────┤│││90年11月│KB00000000│813,030元│40,652元│││├────┼───────┼─────┼────┤│││90年11月│KB00000000│479,520元│23,976元│││├────┼───────┼─────┼────┤│││90年11月│KB00000000│738,360元│36,918元│││├────┼───────┼─────┼────┤│││90年11月│KB00000000│882,600元│44,130元│││├────┼───────┼─────┼────┤│││90年11月│KB00000000│829,040元│41,452元│││├────┼───────┼─────┼────┤│││90年11月│KB00000000│522,637元│26,132元│││├────┼───────┼─────┼────┤│││90年11月│KB00000000│768,270元│38,414元│││├────┼───────┼─────┼────┤│││90年11月│KB00000000│603,000元│30,150元│││├────┼───────┼─────┼────┤│││90年11月│KB00000000│736,200元│36,810元│││├────┼───────┼─────┼────┤│││90年11月│KB00000000│780,000元│39,000元│││├────┼───────┼─────┼────┤│││90年11月│KB00000000│892,350元│44,618元│││├────┼───────┼─────┼────┤│││90年11月│KB00000000│732,440元│36,622元│││├────┼───────┼─────┼────┤│││90年11月│KB00000000│703,110元│35,156元│││├────┼───────┼─────┼────┤│││90年11月│KB00000000│632,350元│31,618元│││├────┼───────┼─────┼────┤│││90年11月│KB00000000│779,260元│38,963元│││├────┼───────┼─────┼────┤│││90年11月│KB00000000│588,280元│29,414元│││├────┼───────┼─────┼────┤│││90年11月│KB00000000│773,240元│38,667元│││├────┼───────┼─────┼────┤│││90年11月│KB00000000│743,070元│37,154元│││├────┼───────┼─────┼────┤│││90年11月│KB00000000│864,290元│43,215元│││├────┼───────┼─────┼────┤│││90年11月│KB00000000│699,410元│34,971元│││├────┼───────┼─────┼────┤│││90年11月│KB00000000│490,650元│24,533元│││├────┼───────┼─────┼────┤│││90年11月│KB00000000│756,800元│37,840元│││├────┼───────┼─────┼────┤│││90年12月│KB00000000│732,440元│36,622元│││├────┼───────┼─────┼────┤│││90年12月│KB00000000│512,496元│25,625元│││├────┼───────┼─────┼────┤│││90年12月│KB00000000│858,329元│42,916元│││├────┼───────┼─────┼────┤│││90年12月│KB00000000│529,170元│26,459元│││├────┼───────┼─────┼────┤│││90年12月│KB00000000│619,376元│30,969元│││├────┼───────┼─────┼────┤│││90年12月│KB00000000│783,700元│39,185元│││├────┼───────┼─────┼────┤│││90年12月│KB00000000│716,840元│35,842元│││├────┼───────┼─────┼────┤│││90年12月│KB00000000│499,370元│24,969元│││├────┼───────┼─────┼────┤│││90年12月│KB00000000│527,400元│26,370元│││├────┼───────┼─────┼────┤│││90年12月│KB00000000│522,740元│26,137元│││├────┼───────┼─────┼────┤│││90年12月│KB00000000│796,760元│39,838元│││├────┼───────┼─────┼────┤│││90年12月│KB00000000│600,590元│30,030元│││├────┼───────┼─────┼────┤│││90年12月│KB00000000│632,900元│31,645元│││├────┼───────┼─────┼────┤│││90年12月│KB00000000│629,220元│31,461元│││├────┼───────┼─────┼────┤│││90年12月│KB00000000│768,900元│38,445元│││├────┼───────┼─────┼────┤│││90年12月│KB00000000│434,840元│21,742元│││├────┼───────┼─────┼────┤│││90年12月│KB00000000│584,920元│29,246元│││├────┼───────┼─────┼────┤│││90年12月│KB00000000│493,100元│24,655元│││├────┼───────┼─────┼────┤│││90年12月│KB00000000│618,070元│30,904元│││├────┼───────┼─────┼────┤│││90年12月│KB00000000│500,500元│25,025元│││├────┼───────┼─────┼────┤│││90年12月│KB00000000│717,640元│35,882元│││├────┼───────┼─────┼────┤│││90年12月│KB00000000│596,690元│29,835元│││├────┼───────┼─────┼────┤│││90年12月│KB00000000│341,680元│17,084元│││├────┼───────┼─────┼────┤│││90年12月│KB00000000│521,480元│26,074元│││├────┼───────┼─────┼────┤│││90年12月│KB00000000│341,910元│17,096元│││├────┼───────┼─────┼────┤│││90年12月│KB00000000│522,640元│26,132元│││├────┼───────┼─────┼────┤│││90年12月│KB00000000│635,820元│31,791元│││├────┼───────┼─────┼────┤│││90年12月│KB00000000│388,220元│19,411元│││├────┼───────┼─────┼────┤│││90年12月│KB00000000│635,860元│31,793元│││├────┼───────┼─────┼────┤│││91年3月│MA00000000│4,559,100│227,955││││││元│元│││├────┼───────┼─────┼────┤│││91年5月│MZ00000000│627,416元│31,371元│││├────┼───────┼─────┼────┤│││91年5月│MZ00000000│2,582,416│129,121││││││元│元│││├────┼───────┼─────┼────┤│││91年5月│MZ00000000│1,483,983│74,199元││││││元││││├────┼───────┼─────┼────┤│││91年7月│NY00000000│300,014元│15,000元│││├────┼───────┼─────┼────┤│││91年7月│NY00000000│111,436元│5,572元│││├────┼───────┼─────┼────┤│││91年7月│NY00000000│41,567元│2,078元│││├────┼───────┼─────┼────┤│││91年7月│NY00000000│29,797元│1,490元│││├────┼───────┼─────┼────┤│││91年8月│NY00000000│423,692元│21,185元│││├────┼───────┼─────┼────┤│││91年8月│NY00000000│85,540元│4,277元│││├────┼───────┼─────┼────┤│││91年8月│NY00000000│16,554元│828元│││├────┼───────┼─────┼────┤│││91年8月│NY00000000│55,252元│2,763元│││├────┼───────┼─────┼────┤│││91年9月│PX00000000│103,953元│5,198元│││├────┼───────┼─────┼────┤│││91年9月│PX00000000│404,858元│20,243元│││├────┼───────┼─────┼────┤│││91年9月│PX00000000│327,738元│16,387元│││├────┼───────┼─────┼────┤│││91年9月│PX00000000│191,436元│9,572元│││├────┼───────┼─────┼────┤│││91年9月│PX00000000│682,591元│34,130元│││├────┼───────┼─────┼────┤│││91年10月│PX00000000│148,357元│7,417元│││├────┼───────┼─────┼────┤│││91年10月│PX00000000│172,171元│8,608元│││├────┼───────┼─────┼────┤│││91年10月│PX00000000│35,248元│1,762元│││├────┼───────┼─────┼────┤│││91年10月│PX00000000│83,769元│4,188元│├─┴──────┴────┴───────┼─────┼────┤│小計│46,725,186│2,336,26│││元│元│├─┬──────┬────┬───────┼─────┼────┤│2│豐莊興業有限│91年3月│MA00000000│413,028元│20,651元│││公司├────┼───────┼─────┼────┤│││91年3月│MA00000000│301,330元│15,067元│││├────┼───────┼─────┼────┤│││91年3月│MA00000000│278,249元│13,912元│││├────┼───────┼─────┼────┤│││91年3月│MA00000000│327,635元│16,382元│││├────┼───────┼─────┼────┤│││91年3月│MA00000000│247,096元│12,355元│││├────┼───────┼─────┼────┤│││91年3月│MA00000000│315,671元│15,784元│││├────┼───────┼─────┼────┤│││91年3月│MA00000000│303,993元│15,200元│││├────┼───────┼─────┼────┤│││91年3月│MA00000000│270,507元│13,525元│││├────┼───────┼─────┼────┤│││91年3月│MA00000000│240,170元│12,009元│││├────┼───────┼─────┼────┤│││91年3月│MA00000000│543,515元│27,176元│││├────┼───────┼─────┼────┤│││91年3月│MA00000000│276,130元│13,807元│││├────┼───────┼─────┼────┤│││91年3月│MA00000000│160,830元│8,042元│││├────┼───────┼─────┼────┤│││91年3月│MA00000000│251,200元│12,560元│││├────┼───────┼─────┼────┤│││91年5月│MZ00000000│154,912元│7,746元│││├────┼───────┼─────┼────┤│││91年5月│MZ00000000│250,672元│12,534元│││├────┼───────┼─────┼────┤│││91年5月│MZ00000000│878,344元│43,917元│││├────┼───────┼─────┼────┤│││91年5月│MZ00000000│508,996元│25,449元│││├────┼───────┼─────┼────┤│││91年5月│MZ00000000│997,676元│49,884元│││├────┼───────┼─────┼────┤│││91年5月│MZ00000000│1,356,488│67,825元││││││元│││││││││││├────┼───────┼─────┼────┤│││91年7月│NY00000000│415,020元│20,751元│││├────┼───────┼─────┼────┤│││91年7月│NY00000000│537,072元│26,854元│││├────┼───────┼─────┼────┤│││91年7月│NY00000000│453,225元│22,661元│││├────┼───────┼─────┼────┤│││91年7月│NY00000000│568,364元│28,418元│││├────┼───────┼─────┼────┤│││91年7月│NY00000000│254,126元│12,706元│││├────┼───────┼─────┼────┤│││91年7月│NY00000000│437,823元│21,891元│││├────┼───────┼─────┼────┤│││91年8月│NY00000000│43,476元│2,174元│││├────┼───────┼─────┼────┤│││91年8月│NY00000000│60,034元│3,002元│││├────┼───────┼─────┼────┤│││91年8月│NY00000000│39,729元│1,986元│││├────┼───────┼─────┼────┤│││91年8月│NY00000000│61,407元│3,070元│││├────┼───────┼─────┼────┤│││91年8月│NY00000000│62,389元│3,119元│││├────┼───────┼─────┼────┤│││91年8月│NY00000000│41,764元│2,088元│││├────┼───────┼─────┼────┤│││91年9月│PX00000000│211,144元│10,557元│││├────┼───────┼─────┼────┤│││91年9月│PX00000000│484,852元│24,243元│││├────┼───────┼─────┼────┤│││91年9月│PX00000000│157,405元│7,870元│││├────┼───────┼─────┼────┤│││91年9月│PX00000000│50,869元│2,543元│││├────┼───────┼─────┼────┤│││91年9月│PX00000000│207,619元│10,381元│││├────┼───────┼─────┼────┤│││91年9月│PX00000000│106,979元│5,349元│││├────┼───────┼─────┼────┤│││91年10月│PX00000000│302,191元│15,110元│││├────┼───────┼─────┼────┤│││91年10月│PX00000000│246,714元│12,336元│││├────┼───────┼─────┼────┤│││91年10月│PX00000000│406,780元│20,339元│││├────┼───────┼─────┼────┤│││91年10月│PX00000000│307,381元│15,369元│││├────┼───────┼─────┼────┤│││91年10月│PX00000000│309,808元│15,490元│││├────┼───────┼─────┼────┤│││91年11月│QW00000000│630,614元│31,531元│││├────┼───────┼─────┼────┤│││91年11月│QW00000000│300,171元│15,009元│││├────┼───────┼─────┼────┤│││91年11月│QW00000000│702,606元│35,130元│││├────┼───────┼─────┼────┤│││91年11月│QW00000000│494,712元│24,735元│││├────┼───────┼─────┼────┤│││91年11月│QW00000000│425,438元│21,272元│││├────┼───────┼─────┼────┤│││91年11月│QW00000000│500,285元│25,014元│││├────┼───────┼─────┼────┤│││91年11月│QW00000000│309,195元│15,460元│││├────┼───────┼─────┼────┤│││91年11月│QW00000000│500,285元│25,014元│││├────┼───────┼─────┼────┤│││91年11月│QW00000000│637,344元│31,867元│││├────┼───────┼─────┼────┤│││91年11月│QW00000000│372,762元│18,638元│││├────┼───────┼─────┼────┤│││91年11月│QW00000000│16,931元│847元│││├────┼───────┼─────┼────┤│││91年12月│QW00000000│415,212元│20,761元│││├────┼───────┼─────┼────┤│││91年12月│QW00000000│350,077元│17,504元│││├────┼───────┼─────┼────┤│││91年12月│QW00000000│1,322,201│66,110元││││││元││││├────┼───────┼─────┼────┤│││91年12月│QW00000000│154,598元│7,730元│││├────┼───────┼─────┼────┤│││91年12月│QW00000000│806,655元│40,333元│││├────┼───────┼─────┼────┤│││91年12月│QW00000000│901,175元│45,059元│││├────┼───────┼─────┼────┤│││91年12月│QW00000000│123,992元│6,199元│││├────┼───────┼─────┼────┤│││91年12月│QW00000000│333,523元│16,676元│││├────┼───────┼─────┼────┤│││91年12月│QW00000000│837,976元│41,899元│││├────┼───────┼─────┼────┤│││91年12月│QW00000000│34,530元│1,727元│├─┴──────┴────┴───────┼─────┼────┤│小計│24,012,895│1,200,64│││元│元│├─────────────────────┼─────┼────┤│1+2合計│70,738,081│3,536,91│││元│元│├─────────────────────┼─────┴────┤│90年12月扣除虛報銷項及進項稅額實際逃漏稅額│0元│├─────────────────────┼──────────┤│91年2月扣除虛報銷項及進項稅額實際逃漏稅額│0元│├─────────────────────┼──────────┤│91年4月扣除虛報銷項及進項稅額實際逃漏稅額│168,108元│├─────────────────────┼──────────┤│91年6月扣除虛報銷項及進項稅額實際逃漏稅額│0元│├─────────────────────┼──────────┤│91年8月扣除虛報銷項及進項稅額實際逃漏稅額│0元│├─────────────────────┼──────────┤│91年10月扣除虛報銷項及進項稅額實際逃漏稅額│251,544元│├─────────────────────┼──────────┤│91年12月扣除虛報銷項及進項稅額實際逃漏稅額│252,150元│├─────────────────────┼──────────┤│總計逃漏稅額│671,802元│└─────────────────────┴──────────┘附表三：金太陽公司開立不實發票明細┌─┬──────┬────┬──────┬──────┬─────┐│編│營業人名稱│開立年月│發票字軌號碼│銷售金額（新│逃漏營業稅││號││││臺幣）│稅額：無│├─┼──────┼────┼──────┼──────┼─────┤│1│天技科技有限│92年6月│TU00000000│456,750元│虛設行號│││├────┼──────┼──────┼─────┤│││92年6月│TU00000000│395,040元│虛設行號│││├────┼──────┼──────┼─────┤│││92年6月│TU00000000│426,660元│虛設行號│││├────┼──────┼──────┼─────┤│││92年6月│TU00000000│456,750元│虛設行號│││├────┼──────┼──────┼─────┤│││92年6月│TU00000000│394,800元│虛設行號│││├────┼──────┼──────┼─────┤│││92年6月│TU00000000│426,660元│虛設行號│││├────┼──────┼──────┼─────┤│││92年6月│TU00000000│456,750元│虛設行號│││├────┼──────┼──────┼─────┤│││92年6月│TU00000000│456,750元│虛設行號│││├────┼──────┼──────┼─────┤│││92年6月│TU00000000│395,040元│虛設行號│││├────┼──────┼──────┼─────┤│││92年6月│TU00000000│426,660元│虛設行號│││├────┼──────┼──────┼─────┤│││92年6月│TU00000000│456,750元│虛設行號│││├────┼──────┼──────┼─────┤│││92年6月│TU00000000│426,660元│虛設行號│││├────┼──────┼──────┼─────┤│││92年6月│TU00000000│231,420元│虛設行號│││├────┼──────┼──────┼─────┤│││92年6月│TU00000000│433,224元│虛設行號│││├────┼──────┼──────┼─────┤│││92年8月│UU00000000│475,530元│虛設行號│││├────┼──────┼──────┼─────┤│││92年8月│UU00000000│2,176,090元│虛設行號│││├────┼──────┼──────┼─────┤│││92年8月│UU00000000│384,930元│虛設行號│││├────┼──────┼──────┼─────┤│││93年4月│YU00000000│1,339,000元│虛設行號│││├────┼──────┼──────┼─────┤│││93年6月│ZU00000000│870,000元│虛設行號│││├────┼──────┼──────┼─────┤│││93年6月│ZU00000000│492,000元│虛設行號│││├────┼──────┼──────┼─────┤│││93年6月│ZU00000000│620,000元│虛設行號│││├────┼──────┼──────┼─────┤│││93年6月│ZU00000000│436,000元│虛設行號│││├────┼──────┼──────┼─────┤│││93年6月│ZU00000000│436,000元│虛設行號│││├────┼──────┼──────┼─────┤│││93年6月│ZU00000000│436,000元│虛設行號│││├────┼──────┼──────┼─────┤│││93年6月│ZU00000000│697,600元│虛設行號│││├────┼──────┼──────┼─────┤│││93年6月│ZU00000000│588,000元│虛設行號│├─┼──────┼────┼──────┼──────┼─────┤│2│赫拉科技股份│92年8月│UU00000000│96,000元│虛設行號│││有限公司├────┼──────┼──────┼─────┤│││92年8月│UU00000000│1,776,000元│虛設行號│││├────┼──────┼──────┼─────┤│││92年8月│UU00000000│2,285,730元│虛設行號│││├────┼──────┼──────┼─────┤│││92年8月│UU00000000│1,331,200元│虛設行號│││├────┼──────┼──────┼─────┤│││92年10月│VU00000000│1,617,465元│虛設行號│││├────┼──────┼──────┼─────┤│││92年10月│VU00000000│740,465元│虛設行號│││├────┼──────┼──────┼─────┤│││92年10月│VU00000000│1,488,672元│虛設行號│││├────┼──────┼──────┼─────┤│││92年10月│VU00000000│1,802,133元│虛設行號│││├────┼──────┼──────┼─────┤│││93年2月│XU00000000│1,020,600元│虛設行號│││├────┼──────┼──────┼─────┤│││93年2月│XU00000000│1,537,350元│虛設行號│││├────┼──────┼──────┼─────┤│││93年2月│XU00000000│1,727,400元│虛設行號│││├────┼──────┼──────┼─────┤│││93年2月│XU00000000│1,324,000元│虛設行號│││├────┼──────┼──────┼─────┤│││93年6月│ZU00000000│2,580,000元│虛設行號│││├────┼──────┼──────┼─────┤│││93年6月│ZU00000000│903,000元│虛設行號│├─┴──────┴────┴──────┼──────┼─────┤│合計│36,237,323元│無│││││└────────────────────┴──────┴─────┘附表四：金太陽公司以不實發票申報扣抵銷稅項明細┌─┬──────┬────┬─────┬──────┬─────┐│編│不實發票之營│開立年月│發票字軌號│銷售金額（新│申報扣抵銷││號│業人名稱││碼│臺幣）│項稅額（新│││││││臺幣）│├─┼──────┼────┼─────┼──────┼─────┤│1│天技科技有限│92年7月│UU00000000│2,152,910元│107,646元│││公司├────┼─────┼──────┼─────┤│││92年8月│UU00000000│1,753,180元│87,659元│││├────┼─────┼──────┼─────┤│││92年8月│UU00000000│2,482,650元│124,133元│││├────┼─────┼──────┼─────┤│││92年12月│WU00000000│1,111,500元│55,575元│││├────┼─────┼──────┼─────┤│││92年12月│WU00000000│1,669,800元│83,490元│││├────┼─────┼──────┼─────┤│││92年12月│WU00000000│844,320元│42,216元│││├────┼─────┼──────┼─────┤│││92年12月│WU00000000│1,111,500元│55,575元│││├────┼─────┼──────┼─────┤│││92年12月│WU00000000│710,000元│35,500元│││├────┼─────┼──────┼─────┤│││92年12月│WU00000000│694,000元│34,700元│││├────┼─────┼──────┼─────┤│││92年12月│WU00000000│726,000元│36,300元│││├────┼─────┼──────┼─────┤│││92年12月│WU00000000│375,560元│18,778元│││├────┼─────┼──────┼─────┤│││92年12月│WU00000000│1,111,500元│55,575元│││├────┼─────┼──────┼─────┤│││92年12月│WU00000000│1,003,500元│50,175元│││├────┼─────┼──────┼─────┤│││92年12月│WU00000000│653,200元│32,660元│││├────┼─────┼──────┼─────┤│││92年12月│WU00000000│936,540元│46,827元│││├────┼─────┼──────┼─────┤│││92年12月│WU00000000│530,000元│26,500元│││├────┼─────┼──────┼─────┤│││92年12月│WU00000000│1,111,500元│55,575元│││├────┼─────┼──────┼─────┤│││92年12月│WU00000000│805,000元│40,250元│││├────┼─────┼──────┼─────┤│││92年12月│WU00000000│1,159,200元│57,960元│││├────┼─────┼──────┼─────┤│││92年12月│WU00000000│1,145,100元│57,255元│││├────┼─────┼──────┼─────┤│││92年12月│WU00000000│624,600元│31,230元│││├────┼─────┼──────┼─────┤│││92年12月│WU00000000│669,000元│33,450元│││├────┼─────┼──────┼─────┤│││92年12月│WU00000000│1,003,500元│50,175元│││├────┼─────┼──────┼─────┤│││93年4月│YU00000000│1,376,000元│68,800元│││├────┼─────┼──────┼─────┤│││93年5月│ZU00000000│820,000元│41,000元│││├────┼─────┼──────┼─────┤│││93年5月│ZU00000000│820,000元│41,000元│││├────┼─────┼──────┼─────┤│││93年5月│ZU00000000│820,000元│41,000元│││├────┼─────┼──────┼─────┤│││93年5月│ZU00000000│120,000元│6,000元│├─┼──────┼────┼─────┼──────┼─────┤│2│赫拉科技股份│92年12月│WU00000000│1,383,050元│69,153元│││有限公司├────┼─────┼──────┼─────┤│││92年12月│WU00000000│1,188,450元│59,423元│││├────┼─────┼──────┼─────┤│││92年12月│WU00000000│1,188,450元│59,423元│││├────┼─────┼──────┼─────┤│││92年12月│WU00000000│1,402,500元│52,125元│├─┴──────┴────┴─────┼──────┼─────┤│合計│33,142,510元│1,657,128││││元│├───────────────────┴─┬────┴─────┤│92年8月扣除虛報銷項及進項稅額實際逃漏稅額│2,414元│├─────────────────────┼──────────┤│92年10月扣除虛報銷項及進項稅額實際逃漏稅額│0元│├─────────────────────┼──────────┤│92年12月扣除虛報銷項及進項稅額實際逃漏稅額│265,977元│├─────────────────────┼──────────┤│93年2月扣除虛報銷項及進項稅額實際逃漏稅額│262,921元│├─────────────────────┼──────────┤│93年4月扣除虛報銷項及進項稅額實際逃漏稅額│45,482元│├─────────────────────┼──────────┤│93年6月扣除虛報銷項及進項稅額實際逃漏稅額│0元│├─────────────────────┼──────────┤│總計逃漏稅額│576,794元│└─────────────────────┴──────────┘",
  "characters": {
    "judges": [
      "鍾雅蘭",
      "郭俊德",
      "楊麗文"
    ],
    "prosecutors": [
      "陳睿明"
    ],
    "lawyers": [
      "郭啟榮"
    ],
    "clerks": [
      "柯凱騰"
    ],
    "plaintiffs": [

    ],
    "defendants": [
      "林燦榮"
    ],
    "prosecutor_office": [
      "臺灣桃園地方法院檢察署檢察官"
    ],
    "creditors": [

    ],
    "debtors": [

    ],
    "judicial_associate_officer": [

    ]
  },
  "adjudged_at": "2011-12-30",
  "created_at": "2016-02-13 13:33:53",
  "updated_at": "2016-02-13 13:33:53"
}