{
  "identify": "PCD-99-訴-1152-20110520-2",
  "court": {
    "name": "臺灣新北地方法院",
    "code": "PCD"
  },
  "division": {
    "name": "民事",
    "code": "V"
  },
  "year": 99,
  "word": "訴",
  "number": "1152",
  "jcheck": "2",
  "reason": "返還買賣價金",
  "content": "臺灣板橋地方法院民事判決              99年度訴字第1152號\n原      告  高鴻鵬\n訴訟代理人  劉韋廷律師\n複代理人    林財生律師\n被      告  瓏山林企業股份有限公司\n兼法定代理\n人          林鴻堯\n上二人共同\n訴訟代理人  劉宏邈律師\n上列當事人間請求返還買賣價金事件，經本院於民國100 年4 月\n20日言詞辯論終結，判決如下：\n    主  文\n原告之訴及假執行之聲請均駁回。\n訴訟費用由原告負擔。\n    事實及理由\n一、原告主張：\n  (一)原告於民國97年3 月23日向被告瓏山林企業股份有限公司（\n    下稱瓏山林公司）與林鴻聯購買坐落新北市○○區○○段第\n    557 、558 、559 、560 、565 、566 、567 地號等7 筆土\n    地上「時尚女人香」建案編號A10 棟9 樓房屋1 戶及其基地\n    （下稱系爭房地），並與被告瓏山林企業股份有限公司（下\n    稱瓏山林公司）簽訂房屋預定買賣契約書（下稱系爭房屋買\n    賣契約），與被告林鴻聯簽訂土地預定買賣契約書（下稱系\n    爭土地買賣契約），約定系爭房地總價金為新臺幣（下同）\n    265 萬元。依系爭土地買賣契約第11條、系爭房屋買賣契約\n    第26條約定，此兩契約及其附件為不可分割之給付，具有連\n    帶及不可分之關係。被告瓏山林公司於售屋廣告上標明貸款\n    成數為8 成5 純銀貸，然其後被告瓏山林公司因貸款成數與\n    廣告不符造成眾多消費者糾紛，經平面媒體、消保官及公平\n    交易委員會等認定有違反消費者保護法及平交易法之嫌。是\n    故被告要求降低貸款成數為7 成5 ，即200 萬元為貸款，自\n    備款為65萬元，原告本有疑慮，但被告之銷售人員一再保證\n    系爭房地價值很高，一定可以貸到房地價值總額7 成5 亦即\n    200 萬元，原告受其蠱惑，且被告未給予原告契約審閱期間\n    ，於簽約當日直接要求原告簽訂買賣契約，原告因此陸續給\n    付自備款65萬元、代書費用36,700元及預繳費用26,769元，\n    共計713,469 元。原告與被告等簽訂之系爭房地買賣契約約\n    定，委託被告等向銀行申請以系爭房地抵押貸款，其內容略\n    為「土地/ 房屋總價內之部分價款（即契約附件1 ：房屋價\n    款分期付款明細表中可委辦貸款抵繳之期款總額），由買方\n    與賣方洽訂之金融機構之貸款給付，最長期限為20年，以買\n    賣雙方簽立「代辦申請貸款委託書」（即契約附件11）依約\n    定辦妥一切貸款手續」。是被告等負有義務依系爭房地買賣\n    契約內附件，依照約定貸款成數7 成5 ，辦妥一切貸款手續\n    ，其委託貸款金額為房屋76萬元、土地124 萬元，共200 萬\n    元。詎料，配合被告系爭建案貸款業務之渣打銀行，通知原\n    告鑑價結果，系爭房地價值過低，僅有每坪17至18萬元，故\n    核貸金額僅為170 萬元，原告遂反映上情於被告。惟被告之\n    客服人員態度極差，以「自己去找別家銀行問呀！」「如果\n    你有錢就不必害怕貸不到了！」等惡言相向，拒絕處理。被\n    告甚至於97年8 月14日寄發存證信函，要求於5 日內繳付貸\n    款差額，否則依約沒入原告全部已繳款項，原告則於97年8\n    月20日寄發存證信函告知被告違約，並以涉及詐欺等罪責，\n    請求其依照契約協助辦理足額貸款，否則於函到後3 日解除\n    契約，然被告卻置若罔聞，更在97年9 月23日發函解除契約\n    ，並沒入原告已繳之土地買賣自備款40萬元、房屋買賣自備\n    款25萬元及預繳費用26,769元共計676,769 元。被告等妄稱\n    因原告貸款條件不符以致無法如數貸足。然原告曾以個人名\n    義向承辦系爭房地抵押貸款之渣打銀行申請貸款30萬元，獲\n    銀行全額核貸，足證原告個人貸款條件良好，非如被告所稱\n    貸款條件不符。被告身為知名企業，為經濟上之強者，為其\n    商譽應依誠實信用原則為交易，然被告卻以廣告訛騙消費者\n    ，再以定型化契約內容規避責任，並曲解契約條款內容，藉\n    此沒收消費者所繳之款項，此有消保會申訴調解記錄可證，\n    其中所列之訴消費者共19人，皆因系爭房地價值過低導致核\n    貸不足，與被告產生糾紛而向消保官申訴，足見被告以此方\n    法預謀設陷，坑害消費者，且本案經媒體大幅報導，足證被\n    告確有前開事證。\n  (二)原告主張系爭房地買賣契約內之定型化契約條款不構成契約\n    之一部，依民法第179 條、第182 條請求被告返還不當得利\n    ：\n  1.系爭房屋買賣契約之賣方為被告瓏山林公司，系爭土地買賣\n    契約之賣方為被告林鴻聯，瓏山林公司為消費者保護法第2\n    條第2 款之企業經營者當無疑義，應適用消費者保護法之各\n    項規定。\n  2.系爭土地買賣契約與房屋買賣契約為同日簽訂，且契約內已\n    約定兩者為連帶不可分之關係，與當事人之意思，具有不可\n    分割之依存關係，依臺灣高等法院88年度上字第304 號判決\n    意旨，系爭房屋買賣契約具有無效或解除之事由，系爭土地\n    買賣契約亦應該當此事由。\n  3.原告簽訂系爭房地買賣契約時，未有合理審閱期限，且簽約\n    當日，因被告之銷售員一再強力推銷並要求立刻簽訂契約，\n    原告迫於無奈，僅得簽名蓋章。按最高法院98年度台上字第\n    168 號判決意旨，倘企業經營者於定型化契約上加註消費者\n    拋棄審閱期間之條款，為顯失公平，仍為無效，應由企業經\n    營者證明已給予合理審閱期間，倘未能舉證已給予消費者合\n    理審閱期間，定型化契約條款不構成契約內容之一部。被告\n    雖表示原告選擇拋棄合理審期之約款，未強迫原告云云，然\n    被告於定型化契約要求原告簽名放棄合理審閱期間，該拋棄\n    審閱期間之條款按前開判決見解，為顯失公平應為無效。且\n    事實上被告確未提供合理審閱期間，定型化契約條款應不構\n    成契約之內容，依消費者保護法第11條之1 規定，原告主張\n    系爭土地買賣契約第5 條及第10條，系爭房屋買賣契約第18\n    條及第23條（即貸款及違約條款），對於原告規範之內容不\n    公平，應不構成契約內容之一部。則被告依據系爭土地買賣\n    契約第5 條及第10條，系爭房屋買賣契約第18條及第23條沒\n    收原告所繳款項676,769 元，即無法律上原因，原告爰依民\n    法第179 條及第182 條，請求被告等返還不當利益676,769\n    元，及自解除契約時起，按年息百分之5 計算之利息。\n  (三)原告依「預售屋買賣定型化契約應記載及不得記載事項」第\n    17點第2 款第2 目、民法第359 條之規定解除契約，並依民\n    法第179 條不當得利請求返還自備款及預繳款項共676,769\n    元：\n  1.依據內政部於90年9 月3 日公告之「預售屋買賣定型化契約\n    應記載及不得記載事項」中第18點第2 項第2 款（原告綜合\n    言辭辯論意旨狀誤載為第17點第2 款第2 目）及消費者保護\n    法第17條、消費者保護法施行細則第15條規定，買方解除契\n    約後，得依民法第179 條請求賣方返還已給付之價金及預付\n    款項。\n  2.原告與被告等所簽訂之系爭契約，就貸款條件約定僅有第18\n    條：「倘因買方貸款條件不符合致不能核貸或無法如數貸足\n    ，則其原欲貸款部份之價款應於賣方通知後七日內以現金一\n    次補足，否則即系違約。」然依照「預售屋買賣定型化契約\n    應記載及不得記載事項」第18點第2 項第2 款：「由賣方洽\n    定辦理之貸款金額少於預訂貸款金額，若可歸責於賣方時，\n    如賣方不能補足不足額部分，買方有權解除契約。」是依消\n    費者保護法施行細則第15條及「預售屋買賣定型化契約應記\n    載及不得記載事項」第18點仍構成契約之內容，系爭房地之\n    抵押貸款，因被告販售房地之價值過低，導致銀行僅願核貸\n    170 萬元，與原先預定之200 萬元有30萬元之差額，故貸款\n    金額少於預定貸款金額系可歸責於被告，且原告在同一時間\n    以相同經濟能力為條件向承辦系爭房地抵押貸款之銀行即渣\n    打銀行申請貸款30萬元，獲銀行全額核貸，足證系爭房地抵\n    押貸款核貸金額不足30萬元，係因為被告之房地價值過低所\n    致，非因原告個人貸款條件不符，原告有權據此解除契約。\n  3.被告經原告寄發存證信函催告協助貸款後，仍不補足差額，\n    買方於97年8 月23日解除契約。契約關係消滅後，原告所給\n    付之自備款及預繳款項共676,769 元，被告等即無保有之法\n    律上原因，應返還之。另按民法第182 條規定，被告受領價\n    金並應附利息，一併返還於原告，故原告得主張自解除契約\n    起，按年息百分之5 計算之利息。\n  4.另原告主張民法第359 條物之瑕疵擔保效力，解除契約，並\n    請求回復原狀，返還原告已給付之價金共676,769 元：按出\n    賣人應擔保其物於危險移轉時具有其所保證之品質，是故買\n    賣之物有瑕疵，而出賣人應負擔保之責者，買受人得解除其\n    契約或請求減少其價金。解除契約後依民法第259 條、第17\n    9 條及第182 條，請求返還受領給付之金錢及利息。被告等\n    於系爭契約訂定時，保證該房屋之價值為1 坪23萬元以上，\n    亦保證最後於銀行貸款時得貸足總額之7 成5 即為200 萬元\n    ，原告因被告等保證可貸款200 萬元方購買之，若無法貸至\n    200 萬元，原告即不會考慮購買系爭房地，然事後該房屋經\n    銀行鑑價，1 坪僅價值17萬元，系爭房地未如其所稱高價，\n    導致無法貸足200 萬元，同時被告等亦未依其保證貸足200\n    萬元，系爭房屋並無被告所保證之品質，是故原告得依民法\n    第359 條解除契約，並請求依民法第259 條回復原狀。被告\n    林鴻聯應返還其自原告受領之款項40萬元、被告瓏山林公司\n    應返還自原告受領之自備款25萬元及與預繳款項26,769元共\n    276,769 元。並應給付自解除契約翌日起按週年利率百分之\n    5 之利息。\n  (四)系爭土地買賣契約第5 條及第10條、房屋買賣契約第18條及\n    第23條，縱為契約之一部亦因對契約之他方顯失公平違反消\n    保法第12條、民法247 條之1 、預售屋買賣定型化契約應記\n    載事項及不得記載事項第24條第2 款而無效：\n  1.觀以系爭房屋買賣契約第18條、第23條之規定與綜合契約內\n    其他條款約定，買賣雙方所負之義務顯不相當，若係因買方\n    貸款條件不符合，需沒收高達房屋總價百分之20之違約金，\n    相較之下，被告雖負有義務協助辦理抵押貸款，但若因被告\n    之原因致貸款不足額時，卻未有罰則或任何處理方法，導致\n    消費者需負擔顯不相當之賠償責任。是故定型化契約之貸款\n    及違約條款與平等互惠原則即有不合，依消費者保護法第12\n    條及消費者保護法施行細則第14條規定，契約條款違反誠信\n    原則，對消費者顯失公平者，無效。\n  2.次查，原告確實未有合理審閱期間，系爭契約內文字未有任\n    何修改，事實上原告於自決定購屋至簽定契約時間極短暫，\n    被告之銷售員僅要求原告儘快簽約，不僅未提供合理審閱期\n    間，亦無任何可供磋商變更契約條款之機會，最終簽訂之契\n    約亦按照被告所提供之範本簽訂，未有任何更改，原告無任\n    何磋商餘地，被告稱原告得磋商變更云云，顯不足採。\n  3.再查，系爭契約條款約定委託被告貸得總數7 成5 之貸款，\n    然未約定倘因可歸責於被告致使貸款不成或成數不足時應如\n    何處理，被告依契約所負之貸款義務違反時，均無任何處理\n    方式或罰則，相較之下，被告於契約內貸款約定（房屋契約\n    第18條、土地契約第5 條）僅約定倘買方貸款條件不符致貸\n    款不成或成數不足之處理方式，並依房屋契約第23條、土地\n    契約第10條約定有高額賠償金，雙方顯有地位不平等、所負\n    義務不相當之情形。\n  4.末查，比較「預售屋買賣定型化契約應記載及不得記載事項\n    」第18點第2 款，完整規範當貸款金額少於約定貸款貸款金\n    額時，區分不可歸責雙方、可歸責於賣方與可歸責於買方之\n    處理方式，然被告所使用之系爭契約僅約定倘貸款金額不足\n    ，原告應一次以現金補足，否則為違約，並未將被告即賣方\n    違約規範於契約中，明顯使原告負有不相當之義務，系爭契\n    約之貸款及違約條款違反消費者保護法第12條顯失公平為無\n    效。\n  5.按「預售屋買賣定型化契約應記載事項及不得記載事項」第\n    24條第2 款是以消費者違約時，企業經營者固得沒收一定比\n    例之買賣價金，然其比例上限不得超過房地價值百分之15。\n    被告於契約內約定違約時沒收總價金百分20，核與內政部公\n    告之定型化契約範本上限為百分之15不符，超出部份應屬無\n    效。況被告實際沒收金額為原告全額已繳價金及非屬買賣價\n    金之預繳款項共676,769 元，比例已高達總價金百分之25\n    ，被告稱依法行事，實屬狡辯，明顯違反「預售屋買賣定型\n    化契約應記載事項及不得記載事項」第24條第2 款之規定，\n    係屬違法，被告以此誆騙消費者，彰彰甚明。\n  (五)被告未依照契約義務協助貸得足額貸款，為民法第227 條不\n    完全給付，原告定相當期間命被告協助貸款，逾期不履行即\n    得解除契約：\n  1.被告依照契約及廣告內容，應協助信用條件良好之原告貸得\n    總價7 成5 之貸款，然最終核貸金額不足係因被告房地價值\n    1 坪僅17萬，較被告所稱之1 坪20萬低，故銀行因供擔保設\n    定之不動產價值不足，僅願核貸170 萬，貸款差額30萬為可\n    歸責於被告致不完全給付，原告得催告被告給付並得解除契\n    約。\n  2.原告於97年8 月20日寄發存證信函告知被告違約，並以涉及\n    詐欺等罪責，請求其依照契約協助辦理足額貸款，否則於函\n    到後3 日解除契約，然被告於97年8 月21日收到後卻置若罔\n    聞，原告解除契約自屬合法。\n  (六)原告依民法第245 條之1 規定，請求因被告等對契約重要事\n    項為惡意隱匿不實說明所致之損害：\n  1.系爭房屋價金7 成5 以抵押房地貸款支付，是故抵押貸款之\n    金額，是否可全額貸足，即為契約上重要關係事項。\n  2.原告於訂立契約時，向被告等之銷售人員詢問房屋抵押貸款\n    之詳情，其以一定可以貸至200 萬元為由搪塞。對於貸款額\n    度可能會因系爭房地價值過低，導致核貸金額不足之事，完\n    全未曾提及，是故就此重要事項為惡意隱瞞，已該當民法第\n    245 之1 條第1 項第1 款之事由，被告等惡意隱瞞，亦違反\n    誠實及信用方法，致原告受有損害。\n  3.另被告等之銷售人員於看屋一在主張該樣品屋內可做夾層之\n    設計，並提供夾層之樣品屋，使原告誤信購買系爭房屋後，\n    可為夾層屋之設計而為之購買，詎料，購買後查閱相關資料\n    始知悉夾層屋之設計係屬不法，並經被告事後承認，此乃就\n    交易上重要事項惡意隱匿、不實說明，已該當民法第245 條\n    之1 第1 項第1 款及第3 款事由，應對原告負賠償之責。\n  4.原告因信被告等之說明，締結契約，交付自備款共65萬元及\n    預繳之費用26,769元，卻遭被告沒收全額，受有損害共676,\n    769 元，被告應為賠償。\n  (七)聲明：1.被告瓏山林公司應給付原告276,796 元，及自97年\n    8 月24日起至清償日止，按週年利率百分之5 計算之利息。\n    2.被告林鴻聯應給付原告40萬元，及自97年8 月24日起至清\n    償日止，按週年利率百分之5 計算之利息。3.原告願供擔保\n    請准宣告假執行。\n二、被告則抗辯：\n  (一)原告稱被告之銷售人員一再保證系爭房地價值很高，一定可\n    以貸到房地價值總額7 成5 亦即200 萬元，嗣配合系爭建物\n    貸款業務之渣打銀行核貸金額僅為170 萬元。是被告未依照\n    契約義務協助貸得足額貸款，為民法第227 條不完全給付，\n    原告定相當期間命被告協助貸款，逾期不履行即得解除契約\n    云云，顯與事實有違：\n  1.查銀行是否核貸款項達7 成5 ，乃銀行依承購戶個人之資力\n    、信用條件而為決定，被告公司僅為銷售房地之建商，並無\n    能力對承購戶資力、將來發生呆帳風險作專業之評估，實無\n    可能擅自代銀行決定貸款之條件，或毫無條件即承諾、保證\n    承購戶可貸款7 成5 ，而自陷承購戶將來發生無力償還貸款\n    時，須賠償銀行損失或自行進行冗長之訴訟程序。是原告稱\n    被告銷售系爭房地時，有保證貸款7 成5 云云，洵非事實，\n    被告鄭重否認之。\n  2.訴外人即渣打銀行貸款承辦人李汪恩於98年7 月3 日下午2\n    時13分在臺灣臺北地方法院檢察署98年度他字第589 號詐欺\n    案所作詢問筆錄第2 頁及第5 頁證稱：「（問：高總共跟你\n    們貸款幾次？所帶金額多少？核准金額多少？）第一次是97\n    年3 月28日來申辦信用貸款30萬，皆如數核准貸款。第二次\n    是97年5 月9 日申請房貸170 萬，於5 月13日核准，但至8\n    月21日因告訴人未對保，公司規定超過3 個月未對保所以取\n    消該筆房貸。後來告訴人在同一天97年8 月21日又以相同抵\n    押物（時尚女人香的房屋）再次申請170 萬元貸款，核准日\n    期是97年8 月27日，但這次一樣是超過三個月沒對保以致其\n    貸款被取消。在97年7 月14日還有一次是以高自己的房屋（\n    桃園縣龜山鄉○○路○段122 號之5 號7 樓）來申請貸款\n    380 萬元並如數核准撥款。」等語（見本院卷第338 頁），\n    又訴外人即渣打銀行貸款部主管李思賓於同次筆錄證稱：「\n    （問：告訴人時尚女人跟你們申請貸款到底金額多少？）依\n    照文件上是170 萬元」等語（見本院卷第339 頁），另原告\n    於同次筆錄陳稱：「（問告訴人：該文件上為何會有你的簽\n    名，你當初申請貸款是否為170 萬元？）因為我已繳了一些\n    款項在被告那邊，雖然我貸的款項是200 萬，但我怕錢被被\n    告他們沒收，所以只核准170 萬元我只好同意」等語（見本\n    院卷第341 頁），可知，原告自始申請貸款金額為170 萬元\n    而非200 萬元。是本件原告顯係刻意誤導、扭曲或混淆其貸\n    款銀行渣打銀行已准予原告申請貸款170 萬元，而原告逾3\n    個月沒對保以致貸款銀行取消貸款之事實，進而影響法院之\n    公正判斷。尤其，原告亦在97年7 月14日用自身房屋向渣打\n    銀行申請380 萬元並如數核准撥款，原告竟逾期仍不履行給\n    付第6 期房地價金之義務，益徵原告自始既無誠意履行系爭\n    房地買賣契約。\n  3.且依兩造土地間預定買賣契約書第5 條、房屋預定買賣契約\n    書第18條皆明白約定「…倘因買方貸款條件不符合，致不能\n    核貸或無法如數貸足及買方中途改變主意自願不貸或未能如\n    期協辦或主動向核貸金融機構拒絕貸款者，視為放棄貸款，\n    則其原欲貸款部分之價款應於賣方通知後，7 日內以現金一\n    次向賣方繳清，否則即係違約。…」，而土地、房屋預定買\n    賣契約書皆有給予原告行使契約審閱期之機會，銷售人員亦\n    會作充分之說明，在在足證被告確無保證貸款7 成5 ，否則\n    買賣契約自無可能為如此之約定。按「…簽訂契約時倘雙方\n    已就廣告內容另為斟酌、約定，或企業經營者並未再據原屬\n    『要約引誘』之廣告為訂約之說明、洽談，使之成為具體之\n    『要約』，縱其廣告之內容不實，應受消費者保護法或公平\n    交易法之規範，自難逕謂該廣告為要約或已當然成為契約之\n    一部。」，此有最高法院92年台上字第2694號判決意旨可稽\n    。是縱如原告所言，售屋人員於銷售時有謂「保證一定可以\n    貸到房地價值總額7 成5 亦即200 萬元」云云，然系爭房地\n    預定買賣契約既無保證貸款7 成5 之約定，甚至於土地預定\n    買賣契約書第5 條、房屋預定買賣契約書第18條明白規定貸\n    款成數不足時，買方須負補足差額之責任，原告之訴顯然無\n    據，遑論被告公司自始否認有保證貸款7 成5 情事。\n  4.抑有進者，一般銀行貸款大致可分為房屋貸款、汽車貸款、\n    保單貸款、定存單貸款、信用貸款、公教貸款、小額信貸（\n    企業員工）等種類。然原告自始即知貸款成數最高為7 成5\n    「純銀貸」，且眾所皆知「銀行貸款」並非完全等同「房屋\n    抵押貸款」，原告自無陷於錯誤可言，縱使系爭房地核貸金\n    額僅為170 萬元，惟原告仍可依信貸等方式補足貸款差額。\n    今原告在起訴狀第4 頁第4 行中，亦聲稱原告曾以個人名義\n    向承辦系爭房地抵押貸款之銀行渣打銀行貸款30萬，在在足\n    徵原告自可貸足系爭房屋、土地第6 期價款，但其捨此不為\n    ，自可歸責於原告不履行契約給付義務。\n  (二)原告主張簽訂系爭契約時，未有合理審閱期限，且系爭定型\n    化契約條款違反誠實信用、平等互惠原則，原告可依消費者\n    保護法第11條之1 、第12條及其施行細則第14條、民法第24\n    7 之1 等規定，主張系爭土地契約第5 條、第10條及房屋契\n    約第18條及第23條（即貸款及違約條款）不構成契約之內容\n    ，再依民法第179 條請求返還不當得利云云，並無理由：\n  1.按「…按消費者保護法第11條之1 第1 、2 項規定係規範企\n    業經營者必須給予消費者合理之審閱期間，不可限制消費者\n    簽訂契約之期間。所謂契約審閱期間，乃使消費者在訂立契\n    約前有充裕時間瞭解契約之內容，然並非如原告在契約審閱\n    期間內縱使已瞭解契約內容並進而提前簽約，而事後仍得任\n    意反悔，以審閱期間未用盡為由主張不受契約之拘束。惟倘\n    企業經營者未限制消費者簽名及交回契約書之期間，應認企\n    業經營者已留予消費者合理之契約審閱期間，消費者非不得\n    於簽名前就契約書之內容詳加閱讀，如消費者卻不為此途，\n    而於未看清內容，完全瞭解契約內容前即於契約書上簽名，\n    自係權利之拋棄。又如消費者已有詳細審閱契約之機會，該\n    條之保護目的已達；……。是若消費者於簽約審閱契約條款\n    內容之期間，雖未達規定期間，惟企業經營者未有妨礙消費\n    者事先審閱契約之行為，消費者有充分了解契約條款之機會\n    ，且於充分了解後同意與企業經營者成立契約關係，基於其\n    他考量而選擇放棄審閱期間者，要僅係消費者自行放棄權利\n    ，法無禁止拋棄之明文，在現代私法自治及契約自由原則之\n    下，並無不可，亦不影響其簽名之效力，自不得引用上開消\n    費者保護法第11條之1 之規定主張所簽立之條款無效。再者\n    ，企業經營者為使消費者更易於掌握契約條款重要內容，而\n    於契約條款下要求消費者簽名以慎重其事，對於消費者並無\n    不利，更與消費者保護法立法旨趣無違。消費者事後自不得\n    以審閱契約條款內容之期間未達規定期間，主張契約條款不\n    構成契約之內容，且其行使權利顯然違反民法第148 條第2\n    項所定誠信原則，應認消費者為此主張無理由。」，臺灣臺\n    北地方法院96年度消字第18號判決可資參照。而行政院院消\n    費者保護委員會於89年1 月15日台89消保法字第00056 號函\n    亦同此意旨。\n  2.關於消保法第11條之1 規定定型化契約審閱期間之立法意旨\n    ，乃在保護消費者無法就契約內容與企業經營者為個別磋商\n    ，只能對企營經營者所提供之定型化契約條款予以附合，而\n    無討價還價之餘地而言。查被告在原告簽署系爭房地買賣契\n    約前，顯已提供2 種選擇方式，一為原告自得可依內政部公\n    告，在契約簽立前享有至少5 天以上之契約審閱權，並可攜\n    回契約影本審閱，另一則為原告已逐條審閱充分瞭解契約條\n    文，認無顯失公平之處，同意提早簽約並無疑義。今被告已\n    充分給予原告機會詳細瞭解系爭契約內容及行使審閱契約之\n    權益，嗣原告乃出於自由意志同意提早簽約，始在「審閱契\n    約權利書」簽章於其上，自得視為原告自行放棄審閱契約之\n    權利。是本件「審閱契約權利書」之內容乃出於雙方合意之\n    契約條款，應無對原告權利造成不利影響。尤且原告本身亦\n    擔任公司法務經理一職，具備高於一般消費者之法律知識及\n    能力，揆諸前開說明，本件顯無前揭條文之適用，原告自不\n    得事後反悔，再主張未享有合理審閱期間。\n  3.就系爭房屋、土地買賣契約書第18條及第5 條內容部分：\n  (1)查原告自始即負有給付價金予被告義務，今被告已協助原告\n    辦理抵押貸款170 萬元，亦無向原告保證貸足200 萬元，原\n    告倘能任意指摘被告負有補足貸款差額30萬元，則變向加重\n    被告之契約責任，且將原告不給付價金之不利益由被告承擔\n    ，不惟對被告難謂公平，更有違一般市場機制。\n  (2)揆諸系爭房屋預定買賣契約書附件11之「代辦申請貸款委託\n    書」（系爭土地預定買賣契約書附件2 亦同此意旨，），即\n    明確表示委託賣方以買方所購之房屋、車位及其土地持分等\n    代向賣方指定之金融機構申請抵押貸款；雙方間有關貸款事\n    宜，悉依「時尚女人香」房屋、土地買賣契約書第18條及第\n    5 條規定辦理等語，而附件內容僅短短數句，系爭契約條款\n    亦重覆數次，更經原告審閱後始簽章其上，自無為原告所不\n    及知或無磋商變更餘地可言。尤且「代辦申請貸款委託書」\n    已將系爭房屋、土地買賣契約書第18條及第5 條特別明文規\n    定，並迭經原告同意始簽章於其上，乃屬特別磋商合意條款\n    ，非等同一般定型化契約條款。是原告一再指摘系爭房屋、\n    土地買賣契約書第18條及第5 條不構成契約一部分，顯屬無\n    稽。\n  4.就系爭房屋、土地買賣契約第23條及第10條內容部分：查兩\n    造簽署系爭房屋買賣契約時，原告同意簽約並未表示任何異\n    議，且買賣雙方若發生違約情事時，均要賠償對方違約金20\n    ％，而內政部公告之「預售屋買賣定型化契約應記載及不得\n    記載事項」第24條關於違約之處罰，亦明白規定可沒收一定\n    百分比之違約金。故系爭房地買賣契約條款，並無原告所指\n    「免除或減輕預定契約條款之當事人之責任者。」、「加重\n    他方當事人之責任者」、「其他於他方當事人有重大不利益\n    者。」等情事。基上所述，原告指謫被告違反消保法第11條\n    之1、 第12條、民法第247 之1 等規定，再依民法第179 條\n    請求返還不當得利云云，洵屬無據。\n  (三)本件原告復主張被告等就交易上重要事項惡意隱匿、不實說\n    明，已該當民法第245 條之1 第1 項第1 款及第3 款事由云\n    云：\n  1.原告主張被告對於貸款額度可能會因系爭房地價值過低，導\n    致核貸金額不足之事，完全未曾提及，被告等惡意隱瞞，致\n    原告受有損害云云，惟查貸款銀行已如原告所願貸足170 萬\n    元，自無核貸金額不足之情事，而被告更無向原告保證貸款\n    成數7 成5 ，業如上述。尤其被告所提供之系爭房地自始既\n    無瑕疵存在，導致市場交易價值受到影響而下滑，更無給付\n    與對待給付間之價值顯不相當之情形，故原告指謫被告所供\n    買賣之物有瑕疵，損及原告受領系爭房地之價值云云，就此\n    有利於己之事實者，依民事訴訟法第277 條規定，原告自應\n    先負舉證真正之責任，否則空言主張，自不足為採。\n  2.又原告聲稱購買後查閱相關資料始知悉夾層屋之設計不法，\n    並經被告事後承認，此乃就交易上重要事項惡意隱匿、不實\n    說明云云。惟揆諸臺灣臺北地方法院檢察署檢察官98年度偵\n    字第18099 號不起訴處分書第3 頁及第4 頁可知，系爭房屋\n    樣品屋照片之隔層體部分係僅作為儲藏室等空間使用，樣品\n    屋落地窗旁之樓梯及置衣間隔層，則未與原結構體完全相連\n    ，顯與房屋原結構體之功能不同，且隔層體之面積顯小於樓\n    地板之3 分之1 ，足堪認定原告所供樣品屋照片僅表示系爭\n    房屋可作如樣品屋所示之「隔層」，自得在室內進行2 次施\n    工「隔層」，並不須申請建照執照。是原告誤將樣品屋合法\n    「隔層」認為「夾層」，而認被告有隱瞞違法「夾層」之事\n    實，顯與事實有重大違誤，是原告諉稱被告等違反民法第24\n    5 條之1 第1 項第1 款及第3 款事由云云，顯屬子虛，自不\n    足採。\n  (四)查原告於97年8 月20日所寄發之龜山迴龍郵局第50號存證信\n    所為解除契約之意思表示，顯已違反系民法第227 條、第22\n    9 條第2 項及第254 條之規定，是原告依民法第179 條規定\n    ，請求被告等返還已給付之價金共676,769 元云云，洵無理\n    由：\n  1.查原告民事起訴狀第14頁第5 點亦不否認被告若有協助貸款\n    之給付義務，亦屬「非定期限之給付」，是依民法第227 條\n    第1 項、第229 條第2 項、第254 條規定，原告為此主張自\n    應先定相當期限催告被告履行，被告始負遲延責任，倘被告\n    遲延仍未為給付，原告即應再定相當期限催告被告履行，逾\n    期仍未履行時，原告始得合法解除契約。\n  2.原告於97年8 月20日所寄龜山迴龍郵局第50號存證信函僅表\n    示「…今限貴號等於文到三日內依約提供足額房地貸款並為\n    所有權移轉登記，逾期本人即逕行解除本件買賣契約」云云\n    ，核與前揭規範，僅能認為原告係第1 次通知被告於確定期\n    限履行契約之存證信函，被告於送達後3 日內仍未履行，亦\n    僅生遲延責任之情事。惟查原告於遲延給付後，原告即未依\n    民法第254 條規定，為第2 次催告程序（即取得解除契約權\n    ），且原告亦未發存證信函表達系爭房地買賣契約已遭解除\n    （即解除契約之意思表示），故原告未踐行合法催告程序，\n    即逕行解除系爭房地買賣契約，自不生效力。\n  (五)被告得以97年8 月14日存證信函解除契約沒收原告之款項：\n  1.按「…倘因買方貸款條件不符合，致不能核貸或無法如數貸\n    足及買方中途改變主意自願不貸或未能如期協辦或主動向核\n    貸金融機構拒絕貸款者，視為放棄貸款…」、又「買方若不\n    辦貸款時，須按附件1 『房屋價款分期付款明細表』中可委\n    辦貸款抵繳之期款應於使用執照核發日起第30天應繳納之期\n    款於期限內繳納；並依賣方通知指定日期配合辦理產權移轉\n    相關手續；若逾期依本約第7 條第2 項加計規定遲延利息，\n    並經賣方以存證信函催告後5 日仍未繳者，依本約第23條之\n    約定處理，未付清前賣方得拒絕辦理產權登記於買方。」，\n    乃系爭房屋預定買賣契約書第18條第1 項、第3 項所明文約\n    定（土地預定買賣契約書第5 條第1 項、第3 項亦同此意旨\n    ）。\n  2.查原告已逾繳款期限多日，雖經被告催告繳納，原告仍置若\n    罔聞，被告迫於無奈，始於97年9 月16日寄發臺北興安郵局\n    第2142號存證信函存證信函予原告，明確催告原告應於函達\n    5 日內繳付已逾期限之核貸差額共計30萬元，否則沒入原告\n    已繳之全部款項，同時解除買賣合約之意思表示。縱原告一\n    再抗辯被告保證系爭房地可貸至房地價值總額7 成5 亦即20\n    0 萬元云云，惟原告自始申請貸款金額即為170 萬元，而承\n    貸銀行亦如數核准撥款，竟逾3 個月未對保而遭貸款銀行取\n    消該筆房貸，自是可歸責原告之事由所致，已詳如上述，是\n    原告自不得以上開理由抗辯。原告迄至97年9 月23日止仍未\n    繳納銀行核貸差額，被告始再以臺北興安郵局第2166號存證\n    信函通知解除契約及沒入買賣價金之停止條件已成就。揆諸\n    上開說明，系爭買賣契約既因原告違約逾期未繳納價款而解\n    除，其訴請返還買賣價金云云，自無理由。\n  (六)聲明：1.原告之訴及假執行之聲請均駁回。2.如受不利判決\n    ，被告願供擔保，請准宣告免為假執行。\n三、兩造不爭執之事項：\n  (一)原告先於96年5 月12日向被告瓏山公司與林鴻聯購買坐落新\n    北市○○區○○段第557 、558 、559 、560 、565 、56 6\n    、567 地號等7 筆土地上「時尚女人香」建案編號A15 棟11\n    樓房屋1 戶及其基地（下稱A15 棟11樓房地），並與被告瓏\n    山林公司簽訂房屋預定買賣契約書及與被告林鴻聯簽訂土地\n    預定買賣契約書。嗣於房屋建築完成後，因原告對於A15 棟\n    11樓房屋之格局不滿意，乃與被告等協議更換買賣標的為同\n    建案編號A10 棟9 樓系爭房地，並於97年3 月23日與被告瓏\n    山林公司簽訂系爭房屋買賣契約，及與被告林鴻聯簽訂系爭\n    土地買賣契約，約定系爭房地總價金為265 萬元（見本院卷\n    第238 頁正反面證人葉惠雯之證詞、第240 頁反面證人王寶\n    玉之證詞、第21至78頁系爭房屋及土地買賣契約影本各1 份\n    ）。\n  (二)原告已給付被告等自備款65萬元、代書費用36,700元及預繳\n    費用26,769元，共計713,469 元（見本院卷第91至93頁統一\n    發票影本2 紙、費用明細及代收款客戶簽認表暨收據影本各\n    1紙 ）。\n  (三)原告於97年8 月20日以龜山迴龍郵局第50號存證信函通知被\n    告於文到3 日內依約提供足額房地貸款並為所有權移轉登記\n    ，逾期原告即逕行解除本件買賣契約（見本院卷第97至100\n    頁上開存證信函）。\n  (四)被告於97年9 月16日以臺北興安郵局第2142號存證信函催告\n    原告應於函達5 日內繳付已逾期限之核貸差額共計30萬元，\n    否則沒入原告已繳之全部款項，同時解除買賣合約。原告至\n    97年9 月23日止未繳納銀行核貸差額30萬元，被告復以臺北\n    興安郵局第2166號存證信函通知原告解除契約及沒入買賣價\n    金676, 769元（見本院卷第160 至162 頁上開存證信函及回\n    執）。\n四、兩造爭執事項：\n  (一)原告主張被告未提供契約合理審閱期間，依消費者保護法第\n    11條之1 規定，系爭土地買賣契約第5 條、第10條及系爭房\n    屋買賣契約第18條及第23條之約定為定型化契約條款，不構\n    成契約之一部，原告得依民法第179 條、第182 條規定請求\n    被告返還沒收款項之不當得利及利息，有無理由？如有理由\n    ，被告應返回之金額為若干？\n  (二)原告主張以龜山迴籠郵局第50號存證信函解除系爭房屋及土\n    地買賣契約，並依民法第179 條、第182 條規定請求被告返\n    還不當得利，另依民法第259 條規定請求回復原狀，有無理\n    由？如有理由，被告應返回之金額為若干？\n  1.原告主張系爭房地抵押貸款金額因房地價值過低，致銀行僅\n    願核貸170 萬元，與原先預定之貸款200 萬元有30萬元之差\n    額，經原告寄發存證信函催告被告協助貸款後，被告未理會\n    ，原告依「預售屋買賣定型化契約應記載及不得記載事項」\n    第18點第2 項第2 款及民法第359 條之規定於97年8 月23日\n    解除契約，有無理由？\n  2.原告主張被告未依照契約義務協助貸得200 萬元貸款，為民\n    法第227 條不完全給付，原告定相當期間命被告協助貸款，\n    被告逾期仍不履行，原告得解除契約，有無理由？\n  (三)原告主張系爭土地買賣契約第5 條及第10條、房屋買賣契約\n    第18條及第23條，縱為契約之一部亦因對契約之他方顯失公\n    平，違反消費者保護法第12條、民法247 條之1 、預售屋買\n    賣定型化契約應記載事項及不得記載事項第24條第2 項而無\n    效，並依民法第179 條、第182 條規定請求被告返還不當得\n    利，有無理由？如有理由，被告應返回之金額為若干？\n  (四)原告主張被告就系爭房地因價值過低導致核貸金額不足，及\n    夾層屋之設計係屬不法等重要事項惡意隱瞞，違反誠實及信\n    用方法，致原告受有損害，依民法第245 之1 條第1 項第1\n    款、第3 款規定應負損害賠償責任，有無理由？如有理由，\n    被告應賠償之金額為若干？\n五、本院之判斷：\n  (一)原告主張被告未提供契約合理審閱期間，依消費者保護法第\n    11條之1 規定，系爭土地買賣契約第5 條、第10條及系爭房\n    屋買賣契約第18條及第23條之約定為定型化契約條款，不構\n    成契約之一部，原告得依民法第179 條、第182 條規定請求\n    被告返還沒收款項之不當得利及利息，有無理由？如有理由\n    ，被告應返回之金額為若干？\n  1.按「企業經營者與消費者訂立定型化契約前，應有30日以內\n    之合理期間，供消費者審閱全部條款內容。違反前規定者，\n    該條款不構成契約之內容。但消費者得主張該條款仍構成契\n    約之內容。」，消費者保護法施行細則第11條第1 項、第2\n    項定有明文。該條之目的在給予消費者充分瞭解契約內容之\n    機會，並規範企業經營者不得在未給予消費者審閱契約內容\n    之機會前，限制消費者簽訂契約之時間，以避免消費者於匆\n    忙間不及瞭解其依契約所得主張之權利及應負擔之義務，致\n    訂立顯失公平之契約而受有損害，故只須消費者於簽約前已\n    充分瞭解該契約之權利義務關係，或有可認其能認識契約權\n    利義務關係之合理審閱期間，即不得引用上開規定而主張契\n    約無效。是以企業經營者如未限制消費者必須於何時簽名，\n    何時將契約書交回，應認企業經營者已留予消費者合理之契\n    約審閱期間，即便消費者未看清該契約之內容，即於契約書\n    上簽名並交回契約書，然消費者非不得於簽名前就契約書之\n    內容，詳加閱讀。其不為此之圖，卻於完全瞭解契約內容前\n    即於契約書上簽名，係對自身權利之拋棄，尚非法所不許，\n    亦不影響其簽名之效力。\n  2.原告主張簽訂系爭房地買賣契約時，被告未提供合理審閱期\n    限，且簽約當日因被告之銷售員一再強力推銷並要求立刻簽\n    訂契約，原告迫於無奈，僅得簽名蓋章。依消費者保護法第\n    11條之1 規定，原告主張系爭土地買賣契約第5 條及第10條\n    ，系爭房屋買賣契約第18條及第23條（即貸款及違約條款）\n    ，對於原告規範之內容不公平，應不構成契約內容之一部。\n    則被告依據上開約定沒收原告所繳款項676,769 元，即無法\n    律上原因，原告得依民法第179 條及第182 條，請求被告等\n    返還不當利益等語。被告則抗辯已充分給予原告機會詳細瞭\n    解系爭契約內容及行使審閱契約之權益，原告係出於自由意\n    志同意提早簽約，始在「審閱契約權利書」簽章於其上，自\n    得視為原告自行放棄審閱契約之權利。本件「審閱契約權利\n    書」之內容乃出於雙方合意之契約條款，應無對原告權利造\n    成不利影響。且原告擔任公司法務經理一職，具備高於一般\n    消費者之法律知識及能力，本件顯無前揭條文之適用，原告\n    自不得事後反悔，再主張未享有合理審閱期間等語。\n  2.查本件原告先於96年5 月12日向被告瓏山公司與林鴻聯購買\n    A15 棟11樓房地，並與被告瓏山林公司簽訂房屋預定買賣契\n    約書及與被告林鴻聯簽訂土地預定買賣契約書。嗣於房屋建\n    築完成後，因原告對於A15 棟11樓房屋之格局不滿意，乃與\n    被告等協議更換買賣標的為同建案編號A10 棟9 樓系爭房地\n    ，並於97年3 月23日與被告瓏山林公司簽訂系爭房屋買賣契\n    約，及與被告林鴻聯簽訂系爭土地買賣契約，約定系爭房地\n    總價金為265 萬元之事實，為兩造所不爭執，復經證人葉惠\n    雯、王寶玉證述在卷，並有系爭房屋及土地買賣契約影本各\n    1 份在卷可稽（見本院卷第238 頁正反面、第240 頁反面、\n    第21至78頁），堪以信實。又兩造間於96年5 月12日就A15\n    棟11樓房地所簽訂之房屋預定買賣契約書，與兩造於97 年3\n    月23日就A10 棟9 樓系爭房地所簽訂之系爭房屋及土地買賣\n    契約之內容均相同，僅買賣標的不同，此為兩造所不爭執，\n    是原告自96年5 月12日與被告簽訂A15 棟11樓房地契約後至\n    97年3 月23日與被告簽訂A10 棟9 樓系爭房地契約時，原告\n    已有10個月以上之期間足以充分審閱相同內容之系爭房地買\n    賣契約，而此其間已超過消費者保護法第11條之1 所規定之\n    30日審閱期間，是即便原告未看清該契約之內容，即於契約\n    書上簽名並交回契約書，然原告非不得於系爭房地買賣契約\n    簽名前就契約書之內容，詳加閱讀。其不為此之圖，卻於完\n    全瞭解契約內容前即於契約書上簽名，係對自身權利之拋棄\n    ，尚非法所不許，亦不影響其簽名之效力。再者，本件並無\n    證據證明被告有限制原告必須於何時簽名，何時將契約書交\n    回，應認被告已留予原告合理之契約審閱期間，是原告非不\n    得於簽名前就契約書之內容，詳加閱讀。則原告既仍願與被\n    告簽訂系爭買賣契約，自不能再以被告未提供合理審閱期間\n    為由，主張系爭土地買賣契約第5 條及第10條與系爭房屋買\n    賣契約第18條及第23條，不構成契約內容之一部。\n  3.從而，原告主張被告未提供契約合理審閱期間，系爭土地買\n    賣契約第5 條、第10條及系爭房屋買賣契約第18條、第23條\n    之約定為定型化契約條款，不構成契約之一部，被告依該等\n    約定沒收原告繳納之款項，即無法律上原因，原告得依民法\n    第179 條、第182 條請求被告返還不當得利及利息云云，即\n    屬無據，而不足採。\n  (二)原告主張以龜山迴籠郵局第50號存證信函解除系爭房屋及土\n    地買賣契約，並依民法第179 條、第182 條規定請求被告返\n    還不當得利，有無理由？如有理由，被告應返回之金額為若\n    干？\n  1.原告主張系爭房地抵押貸款金額因房地價值過低，致銀行僅\n    願核貸170 萬元，與原先預定之貸款200 萬元有30萬元之差\n    額，經原告寄發存證信函催告被告協助貸款後，被告未理會\n    ，原告依「預售屋買賣定型化契約應記載及不得記載事項」\n    第18點第2 項第2 款及民法第359 條之規定於97年8 月23\n    日解除契約等語，為被告所否認。經查：\n  (1)按「預售屋買賣定型化契約應記載及不得記載事項」第18點\n    第2 款第2 目規定：前款由賣方洽定辦理之貸款金額少於預\n    定貸款金額，其差額於可歸責於賣方時，差額部分，賣方應\n    依原承諾貸款相同年限及條件由買方分期清償。如賣方不能\n    補足不足額部分，買方有權解除契約。又按買賣因物有瑕疵\n    ，而出賣人依前五條之規定，應負擔保之責者，買受人得解\n    除其契約或請求減少其價金。但依情形，解除契約顯失公平\n    者，買受人僅得請求減少價金，民法第359 條亦有明文。\n  (2)查為導正預售屋買賣契約書之內容，使其符合誠實信用及平\n    等互惠原則，促進公平交易，確保消費者權益，內政部依消\n    費者保護法第17條第1 項規定，於90年9 月3 日公布「預售\n    屋買賣定型化契約應記載及不得記載事項」，其後曾於98年\n    8 月10日、98年10月30日、99年8 月16日及100 年3 月24日\n    作微幅修正。而本件系爭房地買賣，係於房屋建築完成後，\n    原告至現場看屋，因對原本購買之A15 棟11樓預售房屋結構\n    不滿意，而與被告協議換屋，故兩造再於97年3 月23日就A1\n    0 棟9 樓系爭房地簽定系爭買賣契約，則系爭房地買賣契約\n    雖名為房屋、土地「預定買賣契約書」，惟係於系爭房屋建\n    築完成後，經兩造確認買賣之標的為A10 棟9 樓房地所締結\n    之契約，斯時買賣標的A10 棟9 樓房屋已經存在，與預售屋\n    買賣契約訂立時買賣標的尚未存在之性質不同，是系爭房地\n    買賣契約其性質應非屬預售屋買賣，而應屬一般之成屋買賣\n    ，是兩造間系爭房地買賣契約關係，應無「預售屋買賣定型\n    化契約應記載事項及不得記載事項」之適用。是原告主張依\n    「預售屋買賣定型化契約應記載及不得記載事項」第18點第\n    2 款第2 目規定，其有權解除契約云云，尚無足採。\n  (3)次查，經本院依職權函詢渣打銀行關於原告以系爭房地申辦\n    貸款之情形，該銀行以100 年2 月25日渣打商銀SCBCL 字第\n    1001002655號函回覆表示：原告於97年3 月間購買系爭房地\n    後，自行向該銀行申辦貸款，當時核定原告得貸款之金額為\n    170 萬元，但因批示決核後逾3 個月原告未申請撥款，故該\n    行予以駁回等語，有上開函文暨貸款資料1 份附卷可稽（見\n    本院卷第308 至316 頁）。又參以訴外人即渣打銀行貸款承\n    辦人李汪恩於臺灣臺北地方法院檢察署98年度他字第589 號\n    詐欺案98年7 月3 日下午2 時13分詢問筆錄證稱：「（問：\n    高總共跟你們貸款幾次？所貸金額多少？核准金額多少？）\n    第一次是97年3 月28日來申辦信用貸款30萬，皆如數核准貸\n    款。第二次是97年5 月9 日申請房貸170 萬，於5 月13日核\n    准，但至8 月21日因告訴人（即本件原告，下同）未對保，\n    公司規定超過3 個月未對保所以取消該筆房貸。後來告訴人\n    在同一天97年8 月21日又以相同抵押物（時尚女人香的房屋\n    ）再次申請170 萬元貸款，核准日期是97年8 月27日，但這\n    次一樣是超過三個月沒對保以致其貸款被取消。在97年7 月\n    14日還有一次是以高自己的房屋（桃園縣龜山鄉○○路○段\n    122 號之5 號7 樓）來申請貸款380 萬元並如數核准撥款。\n    」等語（見本院卷第338 頁）；及訴外人即渣打銀行貸款部\n    主管李思賓於同次筆錄證稱：「依文件來看是告訴人2 次均\n    親自遞件以時尚女人香來申請貸款170 萬，我們綜合申請人\n    的收入、抵押品及信用狀況來評估准許貸款之金額，告訴人\n    2 次所貸的170 萬元都如數核准，只是因為超過3 個月未對\n    保故予取消。... （是否該約300 戶的貸款是由你們承辦？\n    ）是。一般來說確實可以貸到房價的7 到85成。... （告訴\n    人剛才有說他97年3 月2 日有一筆信貸30萬元，是否影響到\n    他後來申請200 萬卻貸得170 萬的房貸？）是。」等語（見\n    本院卷第339 至342 頁）；另原告於同次筆錄陳稱：「（問\n    告訴人：該文件上為何會有你的簽名，你當初申請貸款是否\n    為170 萬元？）因為我已繳了一些款項在被告那邊，雖然我\n    貸的款項是200 萬，但我怕錢被被告他們沒收，所以只核准\n    170 萬元我只好同意」等語（見本院卷第341 頁）。由上足\n    徵，原告係自行遞件以系爭房地向渣打銀行申請貸款170 萬\n    元，並非由被告洽定辦理貸款，且因原告於97年3 月2 日已\n    有申請一筆信用貸款30萬元，致影響到渣打銀行評估本件核\n    貸之金額為170 萬，況且依李思賓之上開證詞，本件時尚女\n    人香建案約300 戶的貸款均由渣打銀行承辦，一般來說確實\n    可以貸到房地價格的7 到85成之金額，並無因房地價格過低\n    ，而無法貸足房地價格7 到85成金額之情形。從而，原告主\n    張系爭房地抵押貸款金額因房地價值過低，致銀行僅願核貸\n    170 萬元，與原先預定之貸款200 萬元有30萬元之差額云云\n    ，即屬無據，不足採信。另原告主張依民法第359 條之規定\n    解除系爭房地買賣契約，惟始終未舉證證明系爭房地有何瑕\n    疵存在，則其此部分主張，亦乏依據，而無足取。\n  2.原告主張被告未依照契約義務協助貸得200 萬元貸款，為民\n    法第227 條不完全給付，原告定相當期間命被告協助貸款，\n    被告逾期仍不履行，原告得解除契約，有無理由？\n    查本件係原告自行遞件以系爭房地向渣打銀行申請貸款170\n    萬元，並非由被告洽定辦理貸款，且因原告於97年3 月2 日\n    已有申請一筆信用貸款30萬元，致影響到渣打銀行評估本件\n    核貸之金額為170 萬，又依李思賓之上開證詞，本件時尚女\n    人香建案約300 戶的貸款均由渣打銀行承辦，一般來說確實\n    可以貸到房價的7 到85成之金額等情，俱如前述，是原告就\n    系爭房地未能貸得其預期之貸款200 萬元，顯係可歸責於其\n    自身之事由所致，則原告主張被告未依照契約義務協助貸得\n    200 萬元貸款，有民法第227 條不完全給付情形，原告得定\n    相當期間命被告協助貸款，被告逾期仍不履行，原告得解除\n    契約云云，即屬無據。\n  3.從而，原告主張以龜山迴籠郵局第50號存證信函解除系爭房\n    屋及土地買賣契約，並依民法第179 條、第182 條規定請求\n    被告返還不當得利，即無理由，不應准許。\n  (三)原告主張系爭土地買賣契約第5 條及第10條、房屋買賣契約\n    第18條及第23條，縱為契約之一部亦因對契約之他方顯失公\n    平，違反消費者保護法第12條、民法247 條之1 、預售屋買\n    賣定型化契約應記載事項及不得記載事項第24條第4 項而無\n    效，並依民法第179 條、第182 條規定請求被告返還不當得\n    利，有無理由？如有理由，被告應返回之金額為若干？\n  1.按消費者保護法第12條規定：定型化契約中之條款違反誠信\n    原則，對消費者顯失公平者，無效。定型化契約中之條款有\n    下列情形之一者，推定其顯失公平：一、違反平等互惠原則\n    者。二、條款與其所排除不予適用之任意規定之立法意旨顯\n    相矛盾者。三、契約之主要權利或義務，因受條款之限制，\n    致契約之目的難以達成者。又消費者保護法施行細則第14條\n    規定：定型化契約條款，有下列情事之一者，為違反平等互\n    惠原則：一、當事人間之給付與對待給付顯不相當者。二、\n    消費者應負擔非其所能控制之危險者。三、消費者違約時，\n    應負擔顯不相當之賠償責任者。四、其他顯有不利於消費者\n    之情形者。再民法第247 條之1 規定：依照當事人一方預定\n    用於同類契約之條款而訂定之契約，為左列各款之約定，按\n    其情形顯失公平者，該部分約定無效：一、免除或減輕預定\n    契約條款之當事人之責任者。二、加重他方當事人之責任者\n    。三、使他方當事人拋棄權利或限制其行使權利者。四、其\n    他於他方當事人有重大不利益者。又預售屋買賣定型化契約\n    應記載事項及不得記載事項第24條第4 項規定：買方違反有\n    關「付款條件及方式」之規定者，賣方得沒收依房地總價款\n    百分之＿（最高不得超過百分之十五）計算之金額。但該沒\n    收之金額超過已繳價款者，則以已繳價款為限，買賣雙方並\n    得解除本契約。\n  2.原告主張系爭房屋買賣契約第18條、第23條、土地買賣契約\n    第5 條及第10條之規定與綜合契約內其他條款約定，若因買\n    方貸款條件不符合，需沒收高達房屋總價百分之20之違約金\n    ，相較之下，被告雖負有義務協助辦理抵押貸款，但若因被\n    告之原因致貸款不足額時，卻未有罰則或任何處理方法，買\n    賣雙方所負之義務顯不相當，明顯使原告負有不相當之義務\n    ，故系爭房地契約定型化契約之貸款及違約條款與平等互惠\n    原則即有不合，依消費者保護法第12條、消費者保護法施行\n    細則第14條規定，契約條款違反誠信原則，對消費者顯失公\n    平者，無效；且按「預售屋買賣定型化契約應記載事項及不\n    得記載事項」第24條第2 款是以消費者違約時，企業經營者\n    固得沒收一定比例之買賣價金，然其比例上限不得超過房地\n    價值百分之15。被告於契約內約定違約時沒收總價金百分20\n    ，核與內政部公告之定型化契約範本上限為百分之15不符，\n    超出部份應屬無效；況被告實際沒收金額為原告全額已繳價\n    金及非屬買賣價金之預繳款項共676,769 元，比例已高達總\n    價金百分之25，明顯違反「預售屋買賣定型化契約應記載事\n    項及不得記載事項」第24條第2 款之規定，係屬違法等語，\n    為被告所否認。\n  3.查系爭房屋買賣契約第18條第1 項及土地買賣契約第5 條第\n    1 項均約定：倘因買方貸款條件不符合致不能核貸或無法如\n    數貸足，則其原欲貸款部份之價款應於賣方通知後七日內以\n    現金一次補足，否則即係違約（見本院卷第27頁、第74 頁\n    反面）。觀此內容，乃係因可歸責於買方之事由致不能核貸\n    或無法如數貸足，而約定買方應補足貸款差額之約定，並無\n    消費者保護法第12條及民法第247 條之1 所規定違反誠信原\n    則、顯失公平等情形，自非無效之約定。又系爭房屋買賣契\n    約第23條第2 項及土地買賣契約第10條第2 項約定：買方違\n    反房屋買賣契約第7 條、第15條第3 項及第18條約定，或違\n    反土地買賣契約第4 條之約定，買方得沒收依房地總價款百\n    分之20計算之金額；而系爭房屋買賣契約於第23條第1 項及\n    土地買賣契約第10條第1 項亦約定：賣方違反房屋買賣契約\n    第11條、第12條第2 項及第21條之約定者，或賣方違反土地\n    賣賣契約第8 條之約定者，買方均得解除契約，賣方除應將\n    買方已繳之房地價款及遲延利息全部退還賣方外，並應同時\n    賠償房地總價款百分之20之違約金（見本院卷第28、76 頁\n    ）。足徵系爭房屋買賣契約第23條及土地買賣契約第10 條\n    有關違約處罰之約定，對於可歸責於買賣雙方之違約罰則均\n    有約定，且賠償之比例均以房地總價款百分之20計算，是該\n    等約定即無原告所主張買賣雙方所負之義務顯不相當，明顯\n    使原告負有不相當之義務之情形，應無消費者保護法第12條\n    及民法第247 條之1 所規定違反誠信原則、顯失公平等情形\n    ，自非無效之約定。再者，「預售屋買賣定型化契約應記載\n    事項及不得記載事項」第24條第2 款所定賣方得沒收依房地\n    總價款最高不得超過百分之15計算之金額之規定，乃係針對\n    預售屋買賣而為之規定。而系爭房地買賣契約其性質非屬預\n    售屋買賣，而應屬一般之成屋買賣，兩造間系爭房地買賣契\n    約關係，並無「預售屋買賣定型化契約應記載事項及不得記\n    載事項」之適用，有如前述，則原告主張被告沒收金額為原\n    告全額已繳價金及非屬買賣價金之預繳款項共676,769 元，\n    比例已高達總價金百分之25，明顯違反「預售屋買賣定型化\n    契約應記載事項及不得記載事項」第24條第2 款之規定云云\n    ，即屬無據。又系爭房屋買賣契約第23條第2 項及土地買賣\n    契約第10條第2 項約定沒收買方房地總價百分之20之比例，\n    並非顯然過高，故無消費者保護法第12條及民法第247 條之\n    1 所規定違反誠信原則、顯失公平等情形，自非無效之約定\n    。是被告依據系爭契約上開約定解除契約，沒收原告已繳之\n    價金，即非無法律上之原因，並無不當得利之情形。\n  4.從而，原告主張系爭土地買賣契約第5 條及第10條、房屋買\n    賣契約第18條及第23條，縱為契約之一部亦因對契約之他方\n    顯失公平，違反消費者保護法第12條、民法247 條之1 、預\n    售屋買賣定型化契約應記載事項及不得記載事項第24條第4\n    項而無效，並依民法第179 條、第182 條規定請求被告返還\n    不當得利，為無理由，不應准許。\n  (四)原告主張被告就系爭房地因價值過低導致核貸金額不足，及\n    夾層屋之設計係屬不法等重要事項惡意隱瞞，違反誠實及信\n    用方法，致原告受有損害，依民法第245 之1 條第1 項第1\n    款、第3 款規定應負損害賠償責任，有無理由？如有理由，\n    被告應賠償之金額為若干？\n  1.按民法第245條之1第1項第1 款、第3 款規定：契約未成立\n    時，當事人為準備或商議訂立契約而有左列情形之一者，對\n    於非因過失而信契約能成立致受損害之他方當事人，負賠償\n    責任：一、就訂約有重要關係之事項，對他方之詢問，惡意\n    隱匿或為不實之說明者。... 三、其他顯然違反誠實及信用\n    方法者。\n  2.原告主張於訂立系爭契約時，被告之銷售人員表示一定可以\n    貸至200 萬元，對於貸款額度可能會因系爭房地價值過低，\n    導致核貸金額不足之事，完全未曾提及，是故就此重要事項\n    為惡意隱瞞，已該當民法第245 之1 條第1 項第1 款之事由\n    ，被告等惡意隱瞞，亦違反誠實及信用方法，致原告受有損\n    害；又被告之銷售人員於看屋一再表示該樣品屋內可做夾層\n    之設計，並提供夾層之樣品屋，使原告誤信購買系爭房屋後\n    ，可為夾層屋之設計而為之購買，詎購買後查閱相關資料始\n    知悉夾層屋之設計係屬不法，此乃就交易上重要事項惡意隱\n    匿、不實說明，已該當民法第245 條之1 第1 項第1 款及第\n    3 款事由，應對原告負賠償之責等語，並聲請傳喚證人楊鴻\n    彬及提出廣告單影本4 紙為證（見本院卷第79至82頁），惟\n    此為被告所否認。\n  3.查本件因原告於97年3 月2 日已有申請一筆信用貸款30萬元\n    ，致影響到渣打銀行評估本件核貸之金額為170 萬，又依李\n    思賓之上開證詞，本件時尚女人香建案約300 戶的貸款均由\n    渣打銀行承辦，一般來說確實可以貸到房價的7 到85成之金\n    額等情，有如前述，是本件貸款金額未達原告預期之200 萬\n    元即房地總價款之75成，乃歸因於原告本身之因素所致。則\n    原告主張訂立系爭契約時，被告之銷售人員表示一定可以貸\n    至200 萬元，惡意隱瞞貸款額度可能會因系爭房地價值過低\n    ，導致核貸金額不足之事，亦違反誠實及信用方法，該當民\n    法第245 之1 條第1 項第1 款及第3 款之事由，應負賠償責\n    任云云，並無足採。\n  4.次查，證人楊鴻彬於本院言詞辯論時證稱：伊與原告去看建\n    案時尚女人香樣品屋，挑高大概7 米多，有點像樓中樓形式\n    的套房，直走有個小樓梯可以上去，樓梯的旁邊有餐廳及客\n    廳，樓上是個小房間，可以在上面睡覺，小房間下面是客廳\n    及餐廳。... 業務員說可以做兩個樣子，一個是像樣品屋這\n    樣挑高的，一個是一般沒有挑高的，建商會幫我們做好，但\n    是房屋的總價是一樣的等語（見本院卷第239 頁反面），固\n    足認定被告展示之樣品屋係作夾層之裝潢設計。惟觀諸原告\n    所提出之廣告單，並無隻字片語提及「夾層屋」係屬合法建\n    物之內容，原告復未提出證據證明被告之銷售人員曾表示夾\n    層屋係合法，而原告及證人所參觀之樣品屋以夾層之裝潢予\n    以展現，屬空間利用方法之參考展示，僅供購買者作其房屋\n    裝潢設計之參考，尚難認樣品屋以夾層之裝潢展示，即遽認\n    被告有將夾層屋之設計係屬不法等重要事項惡意隱瞞，違反\n    誠實及信用方法之情形。則原告主張被告惡意隱瞞夾層屋之\n    設計係屬不法等重要事項，違反誠實及信用方法，致原告受\n    有損害，依民法第245 之1 條第1 項第1 款、第3 款規定應\n    負損害賠償責任云云，並無可採。\n六、綜上所述，原告主張依民法第179 條、第182 條、第245 之\n    1 條第1 項第1 款、第3 款之規定，請求：(一)被告應給付原\n    告276,796元，及自97年8 月24日起至清償日止，按週年利\n    率百分之5 計算之利息。(二)被告林鴻聯應給付原告40萬元，\n    及自97年8 月24日起至清償日止，按週年利率百分之5 計算\n    之利息，均無理由，應予駁回。又原告之訴既經駁回，其假\n    行之聲請亦失所附麗，併予駁回。\n七、本件事證已臻明確，兩造其餘攻擊防禦方法及未經援用之證\n    據，經審酌後，核與判決結果不生影響，爰不一一論述。\n八、據上論結，本件原告之訴為無理由，依民事訴訟法第79條，\n    判決如主文。\n中    華    民    國   100    年    5     月    20    日\n                  民事第二庭    法  官  張筱琪\n以上正本係照原本作成\n如對本判決上訴，須於判決送達後20日內向本院提出上訴狀\n中    華    民    國   100    年    5     月    20    日\n                                書記官  連思斐",
  "structure": {
    "main": "原告之訴及假執行之聲請均駁回。\n訴訟費用由原告負擔。",
    "fact": "一、原告主張：\n  (一)原告於民國97年3 月23日向被告瓏山林企業股份有限公司（\n    下稱瓏山林公司）與林鴻聯購買坐落新北市○○區○○段第\n    557 、558 、559 、560 、565 、566 、567 地號等7 筆土\n    地上「時尚女人香」建案編號A10 棟9 樓房屋1 戶及其基地\n    （下稱系爭房地），並與被告瓏山林企業股份有限公司（下\n    稱瓏山林公司）簽訂房屋預定買賣契約書（下稱系爭房屋買\n    賣契約），與被告林鴻聯簽訂土地預定買賣契約書（下稱系\n    爭土地買賣契約），約定系爭房地總價金為新臺幣（下同）\n    265 萬元。依系爭土地買賣契約第11條、系爭房屋買賣契約\n    第26條約定，此兩契約及其附件為不可分割之給付，具有連\n    帶及不可分之關係。被告瓏山林公司於售屋廣告上標明貸款\n    成數為8 成5 純銀貸，然其後被告瓏山林公司因貸款成數與\n    廣告不符造成眾多消費者糾紛，經平面媒體、消保官及公平\n    交易委員會等認定有違反消費者保護法及平交易法之嫌。是\n    故被告要求降低貸款成數為7 成5 ，即200 萬元為貸款，自\n    備款為65萬元，原告本有疑慮，但被告之銷售人員一再保證\n    系爭房地價值很高，一定可以貸到房地價值總額7 成5 亦即\n    200 萬元，原告受其蠱惑，且被告未給予原告契約審閱期間\n    ，於簽約當日直接要求原告簽訂買賣契約，原告因此陸續給\n    付自備款65萬元、代書費用36,700元及預繳費用26,769元，\n    共計713,469 元。原告與被告等簽訂之系爭房地買賣契約約\n    定，委託被告等向銀行申請以系爭房地抵押貸款，其內容略\n    為「土地/ 房屋總價內之部分價款（即契約附件1 ：房屋價\n    款分期付款明細表中可委辦貸款抵繳之期款總額），由買方\n    與賣方洽訂之金融機構之貸款給付，最長期限為20年，以買\n    賣雙方簽立「代辦申請貸款委託書」（即契約附件11）依約\n    定辦妥一切貸款手續」。是被告等負有義務依系爭房地買賣\n    契約內附件，依照約定貸款成數7 成5 ，辦妥一切貸款手續\n    ，其委託貸款金額為房屋76萬元、土地124 萬元，共200 萬\n    元。詎料，配合被告系爭建案貸款業務之渣打銀行，通知原\n    告鑑價結果，系爭房地價值過低，僅有每坪17至18萬元，故\n    核貸金額僅為170 萬元，原告遂反映上情於被告。惟被告之\n    客服人員態度極差，以「自己去找別家銀行問呀！」「如果\n    你有錢就不必害怕貸不到了！」等惡言相向，拒絕處理。被\n    告甚至於97年8 月14日寄發存證信函，要求於5 日內繳付貸\n    款差額，否則依約沒入原告全部已繳款項，原告則於97年8\n    月20日寄發存證信函告知被告違約，並以涉及詐欺等罪責，\n    請求其依照契約協助辦理足額貸款，否則於函到後3 日解除\n    契約，然被告卻置若罔聞，更在97年9 月23日發函解除契約\n    ，並沒入原告已繳之土地買賣自備款40萬元、房屋買賣自備\n    款25萬元及預繳費用26,769元共計676,769 元。被告等妄稱\n    因原告貸款條件不符以致無法如數貸足。然原告曾以個人名\n    義向承辦系爭房地抵押貸款之渣打銀行申請貸款30萬元，獲\n    銀行全額核貸，足證原告個人貸款條件良好，非如被告所稱\n    貸款條件不符。被告身為知名企業，為經濟上之強者，為其\n    商譽應依誠實信用原則為交易，然被告卻以廣告訛騙消費者\n    ，再以定型化契約內容規避責任，並曲解契約條款內容，藉\n    此沒收消費者所繳之款項，此有消保會申訴調解記錄可證，\n    其中所列之訴消費者共19人，皆因系爭房地價值過低導致核\n    貸不足，與被告產生糾紛而向消保官申訴，足見被告以此方\n    法預謀設陷，坑害消費者，且本案經媒體大幅報導，足證被\n    告確有前開事證。\n  (二)原告主張系爭房地買賣契約內之定型化契約條款不構成契約\n    之一部，依民法第179 條、第182 條請求被告返還不當得利\n    ：\n  1.系爭房屋買賣契約之賣方為被告瓏山林公司，系爭土地買賣\n    契約之賣方為被告林鴻聯，瓏山林公司為消費者保護法第2\n    條第2 款之企業經營者當無疑義，應適用消費者保護法之各\n    項規定。\n  2.系爭土地買賣契約與房屋買賣契約為同日簽訂，且契約內已\n    約定兩者為連帶不可分之關係，與當事人之意思，具有不可\n    分割之依存關係，依臺灣高等法院88年度上字第304 號判決\n    意旨，系爭房屋買賣契約具有無效或解除之事由，系爭土地\n    買賣契約亦應該當此事由。\n  3.原告簽訂系爭房地買賣契約時，未有合理審閱期限，且簽約\n    當日，因被告之銷售員一再強力推銷並要求立刻簽訂契約，\n    原告迫於無奈，僅得簽名蓋章。按最高法院98年度台上字第\n    168 號判決意旨，倘企業經營者於定型化契約上加註消費者\n    拋棄審閱期間之條款，為顯失公平，仍為無效，應由企業經\n    營者證明已給予合理審閱期間，倘未能舉證已給予消費者合\n    理審閱期間，定型化契約條款不構成契約內容之一部。被告\n    雖表示原告選擇拋棄合理審期之約款，未強迫原告云云，然\n    被告於定型化契約要求原告簽名放棄合理審閱期間，該拋棄\n    審閱期間之條款按前開判決見解，為顯失公平應為無效。且\n    事實上被告確未提供合理審閱期間，定型化契約條款應不構\n    成契約之內容，依消費者保護法第11條之1 規定，原告主張\n    系爭土地買賣契約第5 條及第10條，系爭房屋買賣契約第18\n    條及第23條（即貸款及違約條款），對於原告規範之內容不\n    公平，應不構成契約內容之一部。則被告依據系爭土地買賣\n    契約第5 條及第10條，系爭房屋買賣契約第18條及第23條沒\n    收原告所繳款項676,769 元，即無法律上原因，原告爰依民\n    法第179 條及第182 條，請求被告等返還不當利益676,769\n    元，及自解除契約時起，按年息百分之5 計算之利息。\n  (三)原告依「預售屋買賣定型化契約應記載及不得記載事項」第\n    17點第2 款第2 目、民法第359 條之規定解除契約，並依民\n    法第179 條不當得利請求返還自備款及預繳款項共676,769\n    元：\n  1.依據內政部於90年9 月3 日公告之「預售屋買賣定型化契約\n    應記載及不得記載事項」中第18點第2 項第2 款（原告綜合\n    言辭辯論意旨狀誤載為第17點第2 款第2 目）及消費者保護\n    法第17條、消費者保護法施行細則第15條規定，買方解除契\n    約後，得依民法第179 條請求賣方返還已給付之價金及預付\n    款項。\n  2.原告與被告等所簽訂之系爭契約，就貸款條件約定僅有第18\n    條：「倘因買方貸款條件不符合致不能核貸或無法如數貸足\n    ，則其原欲貸款部份之價款應於賣方通知後七日內以現金一\n    次補足，否則即系違約。」然依照「預售屋買賣定型化契約\n    應記載及不得記載事項」第18點第2 項第2 款：「由賣方洽\n    定辦理之貸款金額少於預訂貸款金額，若可歸責於賣方時，\n    如賣方不能補足不足額部分，買方有權解除契約。」是依消\n    費者保護法施行細則第15條及「預售屋買賣定型化契約應記\n    載及不得記載事項」第18點仍構成契約之內容，系爭房地之\n    抵押貸款，因被告販售房地之價值過低，導致銀行僅願核貸\n    170 萬元，與原先預定之200 萬元有30萬元之差額，故貸款\n    金額少於預定貸款金額系可歸責於被告，且原告在同一時間\n    以相同經濟能力為條件向承辦系爭房地抵押貸款之銀行即渣\n    打銀行申請貸款30萬元，獲銀行全額核貸，足證系爭房地抵\n    押貸款核貸金額不足30萬元，係因為被告之房地價值過低所\n    致，非因原告個人貸款條件不符，原告有權據此解除契約。\n  3.被告經原告寄發存證信函催告協助貸款後，仍不補足差額，\n    買方於97年8 月23日解除契約。契約關係消滅後，原告所給\n    付之自備款及預繳款項共676,769 元，被告等即無保有之法\n    律上原因，應返還之。另按民法第182 條規定，被告受領價\n    金並應附利息，一併返還於原告，故原告得主張自解除契約\n    起，按年息百分之5 計算之利息。\n  4.另原告主張民法第359 條物之瑕疵擔保效力，解除契約，並\n    請求回復原狀，返還原告已給付之價金共676,769 元：按出\n    賣人應擔保其物於危險移轉時具有其所保證之品質，是故買\n    賣之物有瑕疵，而出賣人應負擔保之責者，買受人得解除其\n    契約或請求減少其價金。解除契約後依民法第259 條、第17\n    9 條及第182 條，請求返還受領給付之金錢及利息。被告等\n    於系爭契約訂定時，保證該房屋之價值為1 坪23萬元以上，\n    亦保證最後於銀行貸款時得貸足總額之7 成5 即為200 萬元\n    ，原告因被告等保證可貸款200 萬元方購買之，若無法貸至\n    200 萬元，原告即不會考慮購買系爭房地，然事後該房屋經\n    銀行鑑價，1 坪僅價值17萬元，系爭房地未如其所稱高價，\n    導致無法貸足200 萬元，同時被告等亦未依其保證貸足200\n    萬元，系爭房屋並無被告所保證之品質，是故原告得依民法\n    第359 條解除契約，並請求依民法第259 條回復原狀。被告\n    林鴻聯應返還其自原告受領之款項40萬元、被告瓏山林公司\n    應返還自原告受領之自備款25萬元及與預繳款項26,769元共\n    276,769 元。並應給付自解除契約翌日起按週年利率百分之\n    5 之利息。\n  (四)系爭土地買賣契約第5 條及第10條、房屋買賣契約第18條及\n    第23條，縱為契約之一部亦因對契約之他方顯失公平違反消\n    保法第12條、民法247 條之1 、預售屋買賣定型化契約應記\n    載事項及不得記載事項第24條第2 款而無效：\n  1.觀以系爭房屋買賣契約第18條、第23條之規定與綜合契約內\n    其他條款約定，買賣雙方所負之義務顯不相當，若係因買方\n    貸款條件不符合，需沒收高達房屋總價百分之20之違約金，\n    相較之下，被告雖負有義務協助辦理抵押貸款，但若因被告\n    之原因致貸款不足額時，卻未有罰則或任何處理方法，導致\n    消費者需負擔顯不相當之賠償責任。是故定型化契約之貸款\n    及違約條款與平等互惠原則即有不合，依消費者保護法第12\n    條及消費者保護法施行細則第14條規定，契約條款違反誠信\n    原則，對消費者顯失公平者，無效。\n  2.次查，原告確實未有合理審閱期間，系爭契約內文字未有任\n    何修改，事實上原告於自決定購屋至簽定契約時間極短暫，\n    被告之銷售員僅要求原告儘快簽約，不僅未提供合理審閱期\n    間，亦無任何可供磋商變更契約條款之機會，最終簽訂之契\n    約亦按照被告所提供之範本簽訂，未有任何更改，原告無任\n    何磋商餘地，被告稱原告得磋商變更云云，顯不足採。\n  3.再查，系爭契約條款約定委託被告貸得總數7 成5 之貸款，\n    然未約定倘因可歸責於被告致使貸款不成或成數不足時應如\n    何處理，被告依契約所負之貸款義務違反時，均無任何處理\n    方式或罰則，相較之下，被告於契約內貸款約定（房屋契約\n    第18條、土地契約第5 條）僅約定倘買方貸款條件不符致貸\n    款不成或成數不足之處理方式，並依房屋契約第23條、土地\n    契約第10條約定有高額賠償金，雙方顯有地位不平等、所負\n    義務不相當之情形。\n  4.末查，比較「預售屋買賣定型化契約應記載及不得記載事項\n    」第18點第2 款，完整規範當貸款金額少於約定貸款貸款金\n    額時，區分不可歸責雙方、可歸責於賣方與可歸責於買方之\n    處理方式，然被告所使用之系爭契約僅約定倘貸款金額不足\n    ，原告應一次以現金補足，否則為違約，並未將被告即賣方\n    違約規範於契約中，明顯使原告負有不相當之義務，系爭契\n    約之貸款及違約條款違反消費者保護法第12條顯失公平為無\n    效。\n  5.按「預售屋買賣定型化契約應記載事項及不得記載事項」第\n    24條第2 款是以消費者違約時，企業經營者固得沒收一定比\n    例之買賣價金，然其比例上限不得超過房地價值百分之15。\n    被告於契約內約定違約時沒收總價金百分20，核與內政部公\n    告之定型化契約範本上限為百分之15不符，超出部份應屬無\n    效。況被告實際沒收金額為原告全額已繳價金及非屬買賣價\n    金之預繳款項共676,769 元，比例已高達總價金百分之25\n    ，被告稱依法行事，實屬狡辯，明顯違反「預售屋買賣定型\n    化契約應記載事項及不得記載事項」第24條第2 款之規定，\n    係屬違法，被告以此誆騙消費者，彰彰甚明。\n  (五)被告未依照契約義務協助貸得足額貸款，為民法第227 條不\n    完全給付，原告定相當期間命被告協助貸款，逾期不履行即\n    得解除契約：\n  1.被告依照契約及廣告內容，應協助信用條件良好之原告貸得\n    總價7 成5 之貸款，然最終核貸金額不足係因被告房地價值\n    1 坪僅17萬，較被告所稱之1 坪20萬低，故銀行因供擔保設\n    定之不動產價值不足，僅願核貸170 萬，貸款差額30萬為可\n    歸責於被告致不完全給付，原告得催告被告給付並得解除契\n    約。\n  2.原告於97年8 月20日寄發存證信函告知被告違約，並以涉及\n    詐欺等罪責，請求其依照契約協助辦理足額貸款，否則於函\n    到後3 日解除契約，然被告於97年8 月21日收到後卻置若罔\n    聞，原告解除契約自屬合法。\n  (六)原告依民法第245 條之1 規定，請求因被告等對契約重要事\n    項為惡意隱匿不實說明所致之損害：\n  1.系爭房屋價金7 成5 以抵押房地貸款支付，是故抵押貸款之\n    金額，是否可全額貸足，即為契約上重要關係事項。\n  2.原告於訂立契約時，向被告等之銷售人員詢問房屋抵押貸款\n    之詳情，其以一定可以貸至200 萬元為由搪塞。對於貸款額\n    度可能會因系爭房地價值過低，導致核貸金額不足之事，完\n    全未曾提及，是故就此重要事項為惡意隱瞞，已該當民法第\n    245 之1 條第1 項第1 款之事由，被告等惡意隱瞞，亦違反\n    誠實及信用方法，致原告受有損害。\n  3.另被告等之銷售人員於看屋一在主張該樣品屋內可做夾層之\n    設計，並提供夾層之樣品屋，使原告誤信購買系爭房屋後，\n    可為夾層屋之設計而為之購買，詎料，購買後查閱相關資料\n    始知悉夾層屋之設計係屬不法，並經被告事後承認，此乃就\n    交易上重要事項惡意隱匿、不實說明，已該當民法第245 條\n    之1 第1 項第1 款及第3 款事由，應對原告負賠償之責。\n  4.原告因信被告等之說明，締結契約，交付自備款共65萬元及\n    預繳之費用26,769元，卻遭被告沒收全額，受有損害共676,\n    769 元，被告應為賠償。\n  (七)聲明：1.被告瓏山林公司應給付原告276,796 元，及自97年\n    8 月24日起至清償日止，按週年利率百分之5 計算之利息。\n    2.被告林鴻聯應給付原告40萬元，及自97年8 月24日起至清\n    償日止，按週年利率百分之5 計算之利息。3.原告願供擔保\n    請准宣告假執行。\n二、被告則抗辯：\n  (一)原告稱被告之銷售人員一再保證系爭房地價值很高，一定可\n    以貸到房地價值總額7 成5 亦即200 萬元，嗣配合系爭建物\n    貸款業務之渣打銀行核貸金額僅為170 萬元。是被告未依照\n    契約義務協助貸得足額貸款，為民法第227 條不完全給付，\n    原告定相當期間命被告協助貸款，逾期不履行即得解除契約\n    云云，顯與事實有違：\n  1.查銀行是否核貸款項達7 成5 ，乃銀行依承購戶個人之資力\n    、信用條件而為決定，被告公司僅為銷售房地之建商，並無\n    能力對承購戶資力、將來發生呆帳風險作專業之評估，實無\n    可能擅自代銀行決定貸款之條件，或毫無條件即承諾、保證\n    承購戶可貸款7 成5 ，而自陷承購戶將來發生無力償還貸款\n    時，須賠償銀行損失或自行進行冗長之訴訟程序。是原告稱\n    被告銷售系爭房地時，有保證貸款7 成5 云云，洵非事實，\n    被告鄭重否認之。\n  2.訴外人即渣打銀行貸款承辦人李汪恩於98年7 月3 日下午2\n    時13分在臺灣臺北地方法院檢察署98年度他字第589 號詐欺\n    案所作詢問筆錄第2 頁及第5 頁證稱：「（問：高總共跟你\n    們貸款幾次？所帶金額多少？核准金額多少？）第一次是97\n    年3 月28日來申辦信用貸款30萬，皆如數核准貸款。第二次\n    是97年5 月9 日申請房貸170 萬，於5 月13日核准，但至8\n    月21日因告訴人未對保，公司規定超過3 個月未對保所以取\n    消該筆房貸。後來告訴人在同一天97年8 月21日又以相同抵\n    押物（時尚女人香的房屋）再次申請170 萬元貸款，核准日\n    期是97年8 月27日，但這次一樣是超過三個月沒對保以致其\n    貸款被取消。在97年7 月14日還有一次是以高自己的房屋（\n    桃園縣龜山鄉○○路○段122 號之5 號7 樓）來申請貸款\n    380 萬元並如數核准撥款。」等語（見本院卷第338 頁），\n    又訴外人即渣打銀行貸款部主管李思賓於同次筆錄證稱：「\n    （問：告訴人時尚女人跟你們申請貸款到底金額多少？）依\n    照文件上是170 萬元」等語（見本院卷第339 頁），另原告\n    於同次筆錄陳稱：「（問告訴人：該文件上為何會有你的簽\n    名，你當初申請貸款是否為170 萬元？）因為我已繳了一些\n    款項在被告那邊，雖然我貸的款項是200 萬，但我怕錢被被\n    告他們沒收，所以只核准170 萬元我只好同意」等語（見本\n    院卷第341 頁），可知，原告自始申請貸款金額為170 萬元\n    而非200 萬元。是本件原告顯係刻意誤導、扭曲或混淆其貸\n    款銀行渣打銀行已准予原告申請貸款170 萬元，而原告逾3\n    個月沒對保以致貸款銀行取消貸款之事實，進而影響法院之\n    公正判斷。尤其，原告亦在97年7 月14日用自身房屋向渣打\n    銀行申請380 萬元並如數核准撥款，原告竟逾期仍不履行給\n    付第6 期房地價金之義務，益徵原告自始既無誠意履行系爭\n    房地買賣契約。\n  3.且依兩造土地間預定買賣契約書第5 條、房屋預定買賣契約\n    書第18條皆明白約定「…倘因買方貸款條件不符合，致不能\n    核貸或無法如數貸足及買方中途改變主意自願不貸或未能如\n    期協辦或主動向核貸金融機構拒絕貸款者，視為放棄貸款，\n    則其原欲貸款部分之價款應於賣方通知後，7 日內以現金一\n    次向賣方繳清，否則即係違約。…」，而土地、房屋預定買\n    賣契約書皆有給予原告行使契約審閱期之機會，銷售人員亦\n    會作充分之說明，在在足證被告確無保證貸款7 成5 ，否則\n    買賣契約自無可能為如此之約定。按「…簽訂契約時倘雙方\n    已就廣告內容另為斟酌、約定，或企業經營者並未再據原屬\n    『要約引誘』之廣告為訂約之說明、洽談，使之成為具體之\n    『要約』，縱其廣告之內容不實，應受消費者保護法或公平\n    交易法之規範，自難逕謂該廣告為要約或已當然成為契約之\n    一部。」，此有最高法院92年台上字第2694號判決意旨可稽\n    。是縱如原告所言，售屋人員於銷售時有謂「保證一定可以\n    貸到房地價值總額7 成5 亦即200 萬元」云云，然系爭房地\n    預定買賣契約既無保證貸款7 成5 之約定，甚至於土地預定\n    買賣契約書第5 條、房屋預定買賣契約書第18條明白規定貸\n    款成數不足時，買方須負補足差額之責任，原告之訴顯然無\n    據，遑論被告公司自始否認有保證貸款7 成5 情事。\n  4.抑有進者，一般銀行貸款大致可分為房屋貸款、汽車貸款、\n    保單貸款、定存單貸款、信用貸款、公教貸款、小額信貸（\n    企業員工）等種類。然原告自始即知貸款成數最高為7 成5\n    「純銀貸」，且眾所皆知「銀行貸款」並非完全等同「房屋\n    抵押貸款」，原告自無陷於錯誤可言，縱使系爭房地核貸金\n    額僅為170 萬元，惟原告仍可依信貸等方式補足貸款差額。\n    今原告在起訴狀第4 頁第4 行中，亦聲稱原告曾以個人名義\n    向承辦系爭房地抵押貸款之銀行渣打銀行貸款30萬，在在足\n    徵原告自可貸足系爭房屋、土地第6 期價款，但其捨此不為\n    ，自可歸責於原告不履行契約給付義務。\n  (二)原告主張簽訂系爭契約時，未有合理審閱期限，且系爭定型\n    化契約條款違反誠實信用、平等互惠原則，原告可依消費者\n    保護法第11條之1 、第12條及其施行細則第14條、民法第24\n    7 之1 等規定，主張系爭土地契約第5 條、第10條及房屋契\n    約第18條及第23條（即貸款及違約條款）不構成契約之內容\n    ，再依民法第179 條請求返還不當得利云云，並無理由：\n  1.按「…按消費者保護法第11條之1 第1 、2 項規定係規範企\n    業經營者必須給予消費者合理之審閱期間，不可限制消費者\n    簽訂契約之期間。所謂契約審閱期間，乃使消費者在訂立契\n    約前有充裕時間瞭解契約之內容，然並非如原告在契約審閱\n    期間內縱使已瞭解契約內容並進而提前簽約，而事後仍得任\n    意反悔，以審閱期間未用盡為由主張不受契約之拘束。惟倘\n    企業經營者未限制消費者簽名及交回契約書之期間，應認企\n    業經營者已留予消費者合理之契約審閱期間，消費者非不得\n    於簽名前就契約書之內容詳加閱讀，如消費者卻不為此途，\n    而於未看清內容，完全瞭解契約內容前即於契約書上簽名，\n    自係權利之拋棄。又如消費者已有詳細審閱契約之機會，該\n    條之保護目的已達；……。是若消費者於簽約審閱契約條款\n    內容之期間，雖未達規定期間，惟企業經營者未有妨礙消費\n    者事先審閱契約之行為，消費者有充分了解契約條款之機會\n    ，且於充分了解後同意與企業經營者成立契約關係，基於其\n    他考量而選擇放棄審閱期間者，要僅係消費者自行放棄權利\n    ，法無禁止拋棄之明文，在現代私法自治及契約自由原則之\n    下，並無不可，亦不影響其簽名之效力，自不得引用上開消\n    費者保護法第11條之1 之規定主張所簽立之條款無效。再者\n    ，企業經營者為使消費者更易於掌握契約條款重要內容，而\n    於契約條款下要求消費者簽名以慎重其事，對於消費者並無\n    不利，更與消費者保護法立法旨趣無違。消費者事後自不得\n    以審閱契約條款內容之期間未達規定期間，主張契約條款不\n    構成契約之內容，且其行使權利顯然違反民法第148 條第2\n    項所定誠信原則，應認消費者為此主張無理由。」，臺灣臺\n    北地方法院96年度消字第18號判決可資參照。而行政院院消\n    費者保護委員會於89年1 月15日台89消保法字第00056 號函\n    亦同此意旨。\n  2.關於消保法第11條之1 規定定型化契約審閱期間之立法意旨\n    ，乃在保護消費者無法就契約內容與企業經營者為個別磋商\n    ，只能對企營經營者所提供之定型化契約條款予以附合，而\n    無討價還價之餘地而言。查被告在原告簽署系爭房地買賣契\n    約前，顯已提供2 種選擇方式，一為原告自得可依內政部公\n    告，在契約簽立前享有至少5 天以上之契約審閱權，並可攜\n    回契約影本審閱，另一則為原告已逐條審閱充分瞭解契約條\n    文，認無顯失公平之處，同意提早簽約並無疑義。今被告已\n    充分給予原告機會詳細瞭解系爭契約內容及行使審閱契約之\n    權益，嗣原告乃出於自由意志同意提早簽約，始在「審閱契\n    約權利書」簽章於其上，自得視為原告自行放棄審閱契約之\n    權利。是本件「審閱契約權利書」之內容乃出於雙方合意之\n    契約條款，應無對原告權利造成不利影響。尤且原告本身亦\n    擔任公司法務經理一職，具備高於一般消費者之法律知識及\n    能力，揆諸前開說明，本件顯無前揭條文之適用，原告自不\n    得事後反悔，再主張未享有合理審閱期間。\n  3.就系爭房屋、土地買賣契約書第18條及第5 條內容部分：\n  (1)查原告自始即負有給付價金予被告義務，今被告已協助原告\n    辦理抵押貸款170 萬元，亦無向原告保證貸足200 萬元，原\n    告倘能任意指摘被告負有補足貸款差額30萬元，則變向加重\n    被告之契約責任，且將原告不給付價金之不利益由被告承擔\n    ，不惟對被告難謂公平，更有違一般市場機制。\n  (2)揆諸系爭房屋預定買賣契約書附件11之「代辦申請貸款委託\n    書」（系爭土地預定買賣契約書附件2 亦同此意旨，），即\n    明確表示委託賣方以買方所購之房屋、車位及其土地持分等\n    代向賣方指定之金融機構申請抵押貸款；雙方間有關貸款事\n    宜，悉依「時尚女人香」房屋、土地買賣契約書第18條及第\n    5 條規定辦理等語，而附件內容僅短短數句，系爭契約條款\n    亦重覆數次，更經原告審閱後始簽章其上，自無為原告所不\n    及知或無磋商變更餘地可言。尤且「代辦申請貸款委託書」\n    已將系爭房屋、土地買賣契約書第18條及第5 條特別明文規\n    定，並迭經原告同意始簽章於其上，乃屬特別磋商合意條款\n    ，非等同一般定型化契約條款。是原告一再指摘系爭房屋、\n    土地買賣契約書第18條及第5 條不構成契約一部分，顯屬無\n    稽。\n  4.就系爭房屋、土地買賣契約第23條及第10條內容部分：查兩\n    造簽署系爭房屋買賣契約時，原告同意簽約並未表示任何異\n    議，且買賣雙方若發生違約情事時，均要賠償對方違約金20\n    ％，而內政部公告之「預售屋買賣定型化契約應記載及不得\n    記載事項」第24條關於違約之處罰，亦明白規定可沒收一定\n    百分比之違約金。故系爭房地買賣契約條款，並無原告所指\n    「免除或減輕預定契約條款之當事人之責任者。」、「加重\n    他方當事人之責任者」、「其他於他方當事人有重大不利益\n    者。」等情事。基上所述，原告指謫被告違反消保法第11條\n    之1、 第12條、民法第247 之1 等規定，再依民法第179 條\n    請求返還不當得利云云，洵屬無據。\n  (三)本件原告復主張被告等就交易上重要事項惡意隱匿、不實說\n    明，已該當民法第245 條之1 第1 項第1 款及第3 款事由云\n    云：\n  1.原告主張被告對於貸款額度可能會因系爭房地價值過低，導\n    致核貸金額不足之事，完全未曾提及，被告等惡意隱瞞，致\n    原告受有損害云云，惟查貸款銀行已如原告所願貸足170 萬\n    元，自無核貸金額不足之情事，而被告更無向原告保證貸款\n    成數7 成5 ，業如上述。尤其被告所提供之系爭房地自始既\n    無瑕疵存在，導致市場交易價值受到影響而下滑，更無給付\n    與對待給付間之價值顯不相當之情形，故原告指謫被告所供\n    買賣之物有瑕疵，損及原告受領系爭房地之價值云云，就此\n    有利於己之事實者，依民事訴訟法第277 條規定，原告自應\n    先負舉證真正之責任，否則空言主張，自不足為採。\n  2.又原告聲稱購買後查閱相關資料始知悉夾層屋之設計不法，\n    並經被告事後承認，此乃就交易上重要事項惡意隱匿、不實\n    說明云云。惟揆諸臺灣臺北地方法院檢察署檢察官98年度偵\n    字第18099 號不起訴處分書第3 頁及第4 頁可知，系爭房屋\n    樣品屋照片之隔層體部分係僅作為儲藏室等空間使用，樣品\n    屋落地窗旁之樓梯及置衣間隔層，則未與原結構體完全相連\n    ，顯與房屋原結構體之功能不同，且隔層體之面積顯小於樓\n    地板之3 分之1 ，足堪認定原告所供樣品屋照片僅表示系爭\n    房屋可作如樣品屋所示之「隔層」，自得在室內進行2 次施\n    工「隔層」，並不須申請建照執照。是原告誤將樣品屋合法\n    「隔層」認為「夾層」，而認被告有隱瞞違法「夾層」之事\n    實，顯與事實有重大違誤，是原告諉稱被告等違反民法第24\n    5 條之1 第1 項第1 款及第3 款事由云云，顯屬子虛，自不\n    足採。\n  (四)查原告於97年8 月20日所寄發之龜山迴龍郵局第50號存證信\n    所為解除契約之意思表示，顯已違反系民法第227 條、第22\n    9 條第2 項及第254 條之規定，是原告依民法第179 條規定\n    ，請求被告等返還已給付之價金共676,769 元云云，洵無理\n    由：\n  1.查原告民事起訴狀第14頁第5 點亦不否認被告若有協助貸款\n    之給付義務，亦屬「非定期限之給付」，是依民法第227 條\n    第1 項、第229 條第2 項、第254 條規定，原告為此主張自\n    應先定相當期限催告被告履行，被告始負遲延責任，倘被告\n    遲延仍未為給付，原告即應再定相當期限催告被告履行，逾\n    期仍未履行時，原告始得合法解除契約。\n  2.原告於97年8 月20日所寄龜山迴龍郵局第50號存證信函僅表\n    示「…今限貴號等於文到三日內依約提供足額房地貸款並為\n    所有權移轉登記，逾期本人即逕行解除本件買賣契約」云云\n    ，核與前揭規範，僅能認為原告係第1 次通知被告於確定期\n    限履行契約之存證信函，被告於送達後3 日內仍未履行，亦\n    僅生遲延責任之情事。惟查原告於遲延給付後，原告即未依\n    民法第254 條規定，為第2 次催告程序（即取得解除契約權\n    ），且原告亦未發存證信函表達系爭房地買賣契約已遭解除\n    （即解除契約之意思表示），故原告未踐行合法催告程序，\n    即逕行解除系爭房地買賣契約，自不生效力。\n  (五)被告得以97年8 月14日存證信函解除契約沒收原告之款項：\n  1.按「…倘因買方貸款條件不符合，致不能核貸或無法如數貸\n    足及買方中途改變主意自願不貸或未能如期協辦或主動向核\n    貸金融機構拒絕貸款者，視為放棄貸款…」、又「買方若不\n    辦貸款時，須按附件1 『房屋價款分期付款明細表』中可委\n    辦貸款抵繳之期款應於使用執照核發日起第30天應繳納之期\n    款於期限內繳納；並依賣方通知指定日期配合辦理產權移轉\n    相關手續；若逾期依本約第7 條第2 項加計規定遲延利息，\n    並經賣方以存證信函催告後5 日仍未繳者，依本約第23條之\n    約定處理，未付清前賣方得拒絕辦理產權登記於買方。」，\n    乃系爭房屋預定買賣契約書第18條第1 項、第3 項所明文約\n    定（土地預定買賣契約書第5 條第1 項、第3 項亦同此意旨\n    ）。\n  2.查原告已逾繳款期限多日，雖經被告催告繳納，原告仍置若\n    罔聞，被告迫於無奈，始於97年9 月16日寄發臺北興安郵局\n    第2142號存證信函存證信函予原告，明確催告原告應於函達\n    5 日內繳付已逾期限之核貸差額共計30萬元，否則沒入原告\n    已繳之全部款項，同時解除買賣合約之意思表示。縱原告一\n    再抗辯被告保證系爭房地可貸至房地價值總額7 成5 亦即20\n    0 萬元云云，惟原告自始申請貸款金額即為170 萬元，而承\n    貸銀行亦如數核准撥款，竟逾3 個月未對保而遭貸款銀行取\n    消該筆房貸，自是可歸責原告之事由所致，已詳如上述，是\n    原告自不得以上開理由抗辯。原告迄至97年9 月23日止仍未\n    繳納銀行核貸差額，被告始再以臺北興安郵局第2166號存證\n    信函通知解除契約及沒入買賣價金之停止條件已成就。揆諸\n    上開說明，系爭買賣契約既因原告違約逾期未繳納價款而解\n    除，其訴請返還買賣價金云云，自無理由。\n  (六)聲明：1.原告之訴及假執行之聲請均駁回。2.如受不利判決\n    ，被告願供擔保，請准宣告免為假執行。\n三、兩造不爭執之事項：\n  (一)原告先於96年5 月12日向被告瓏山公司與林鴻聯購買坐落新\n    北市○○區○○段第557 、558 、559 、560 、565 、56 6\n    、567 地號等7 筆土地上「時尚女人香」建案編號A15 棟11\n    樓房屋1 戶及其基地（下稱A15 棟11樓房地），並與被告瓏\n    山林公司簽訂房屋預定買賣契約書及與被告林鴻聯簽訂土地\n    預定買賣契約書。嗣於房屋建築完成後，因原告對於A15 棟\n    11樓房屋之格局不滿意，乃與被告等協議更換買賣標的為同\n    建案編號A10 棟9 樓系爭房地，並於97年3 月23日與被告瓏\n    山林公司簽訂系爭房屋買賣契約，及與被告林鴻聯簽訂系爭\n    土地買賣契約，約定系爭房地總價金為265 萬元（見本院卷\n    第238 頁正反面證人葉惠雯之證詞、第240 頁反面證人王寶\n    玉之證詞、第21至78頁系爭房屋及土地買賣契約影本各1 份\n    ）。\n  (二)原告已給付被告等自備款65萬元、代書費用36,700元及預繳\n    費用26,769元，共計713,469 元（見本院卷第91至93頁統一\n    發票影本2 紙、費用明細及代收款客戶簽認表暨收據影本各\n    1紙 ）。\n  (三)原告於97年8 月20日以龜山迴龍郵局第50號存證信函通知被\n    告於文到3 日內依約提供足額房地貸款並為所有權移轉登記\n    ，逾期原告即逕行解除本件買賣契約（見本院卷第97至100\n    頁上開存證信函）。\n  (四)被告於97年9 月16日以臺北興安郵局第2142號存證信函催告\n    原告應於函達5 日內繳付已逾期限之核貸差額共計30萬元，\n    否則沒入原告已繳之全部款項，同時解除買賣合約。原告至\n    97年9 月23日止未繳納銀行核貸差額30萬元，被告復以臺北\n    興安郵局第2166號存證信函通知原告解除契約及沒入買賣價\n    金676, 769元（見本院卷第160 至162 頁上開存證信函及回\n    執）。\n四、兩造爭執事項：\n  (一)原告主張被告未提供契約合理審閱期間，依消費者保護法第\n    11條之1 規定，系爭土地買賣契約第5 條、第10條及系爭房\n    屋買賣契約第18條及第23條之約定為定型化契約條款，不構\n    成契約之一部，原告得依民法第179 條、第182 條規定請求\n    被告返還沒收款項之不當得利及利息，有無理由？如有理由\n    ，被告應返回之金額為若干？\n  (二)原告主張以龜山迴籠郵局第50號存證信函解除系爭房屋及土\n    地買賣契約，並依民法第179 條、第182 條規定請求被告返\n    還不當得利，另依民法第259 條規定請求回復原狀，有無理\n    由？如有理由，被告應返回之金額為若干？\n  1.原告主張系爭房地抵押貸款金額因房地價值過低，致銀行僅\n    願核貸170 萬元，與原先預定之貸款200 萬元有30萬元之差\n    額，經原告寄發存證信函催告被告協助貸款後，被告未理會\n    ，原告依「預售屋買賣定型化契約應記載及不得記載事項」\n    第18點第2 項第2 款及民法第359 條之規定於97年8 月23日\n    解除契約，有無理由？\n  2.原告主張被告未依照契約義務協助貸得200 萬元貸款，為民\n    法第227 條不完全給付，原告定相當期間命被告協助貸款，\n    被告逾期仍不履行，原告得解除契約，有無理由？\n  (三)原告主張系爭土地買賣契約第5 條及第10條、房屋買賣契約\n    第18條及第23條，縱為契約之一部亦因對契約之他方顯失公\n    平，違反消費者保護法第12條、民法247 條之1 、預售屋買\n    賣定型化契約應記載事項及不得記載事項第24條第2 項而無\n    效，並依民法第179 條、第182 條規定請求被告返還不當得\n    利，有無理由？如有理由，被告應返回之金額為若干？\n  (四)原告主張被告就系爭房地因價值過低導致核貸金額不足，及\n    夾層屋之設計係屬不法等重要事項惡意隱瞞，違反誠實及信\n    用方法，致原告受有損害，依民法第245 之1 條第1 項第1\n    款、第3 款規定應負損害賠償責任，有無理由？如有理由，\n    被告應賠償之金額為若干？\n五、本院之判斷：\n  (一)原告主張被告未提供契約合理審閱期間，依消費者保護法第\n    11條之1 規定，系爭土地買賣契約第5 條、第10條及系爭房\n    屋買賣契約第18條及第23條之約定為定型化契約條款，不構\n    成契約之一部，原告得依民法第179 條、第182 條規定請求\n    被告返還沒收款項之不當得利及利息，有無理由？如有理由\n    ，被告應返回之金額為若干？\n  1.按「企業經營者與消費者訂立定型化契約前，應有30日以內\n    之合理期間，供消費者審閱全部條款內容。違反前規定者，\n    該條款不構成契約之內容。但消費者得主張該條款仍構成契\n    約之內容。」，消費者保護法施行細則第11條第1 項、第2\n    項定有明文。該條之目的在給予消費者充分瞭解契約內容之\n    機會，並規範企業經營者不得在未給予消費者審閱契約內容\n    之機會前，限制消費者簽訂契約之時間，以避免消費者於匆\n    忙間不及瞭解其依契約所得主張之權利及應負擔之義務，致\n    訂立顯失公平之契約而受有損害，故只須消費者於簽約前已\n    充分瞭解該契約之權利義務關係，或有可認其能認識契約權\n    利義務關係之合理審閱期間，即不得引用上開規定而主張契\n    約無效。是以企業經營者如未限制消費者必須於何時簽名，\n    何時將契約書交回，應認企業經營者已留予消費者合理之契\n    約審閱期間，即便消費者未看清該契約之內容，即於契約書\n    上簽名並交回契約書，然消費者非不得於簽名前就契約書之\n    內容，詳加閱讀。其不為此之圖，卻於完全瞭解契約內容前\n    即於契約書上簽名，係對自身權利之拋棄，尚非法所不許，\n    亦不影響其簽名之效力。\n  2.原告主張簽訂系爭房地買賣契約時，被告未提供合理審閱期\n    限，且簽約當日因被告之銷售員一再強力推銷並要求立刻簽\n    訂契約，原告迫於無奈，僅得簽名蓋章。依消費者保護法第\n    11條之1 規定，原告主張系爭土地買賣契約第5 條及第10條\n    ，系爭房屋買賣契約第18條及第23條（即貸款及違約條款）\n    ，對於原告規範之內容不公平，應不構成契約內容之一部。\n    則被告依據上開約定沒收原告所繳款項676,769 元，即無法\n    律上原因，原告得依民法第179 條及第182 條，請求被告等\n    返還不當利益等語。被告則抗辯已充分給予原告機會詳細瞭\n    解系爭契約內容及行使審閱契約之權益，原告係出於自由意\n    志同意提早簽約，始在「審閱契約權利書」簽章於其上，自\n    得視為原告自行放棄審閱契約之權利。本件「審閱契約權利\n    書」之內容乃出於雙方合意之契約條款，應無對原告權利造\n    成不利影響。且原告擔任公司法務經理一職，具備高於一般\n    消費者之法律知識及能力，本件顯無前揭條文之適用，原告\n    自不得事後反悔，再主張未享有合理審閱期間等語。\n  2.查本件原告先於96年5 月12日向被告瓏山公司與林鴻聯購買\n    A15 棟11樓房地，並與被告瓏山林公司簽訂房屋預定買賣契\n    約書及與被告林鴻聯簽訂土地預定買賣契約書。嗣於房屋建\n    築完成後，因原告對於A15 棟11樓房屋之格局不滿意，乃與\n    被告等協議更換買賣標的為同建案編號A10 棟9 樓系爭房地\n    ，並於97年3 月23日與被告瓏山林公司簽訂系爭房屋買賣契\n    約，及與被告林鴻聯簽訂系爭土地買賣契約，約定系爭房地\n    總價金為265 萬元之事實，為兩造所不爭執，復經證人葉惠\n    雯、王寶玉證述在卷，並有系爭房屋及土地買賣契約影本各\n    1 份在卷可稽（見本院卷第238 頁正反面、第240 頁反面、\n    第21至78頁），堪以信實。又兩造間於96年5 月12日就A15\n    棟11樓房地所簽訂之房屋預定買賣契約書，與兩造於97 年3\n    月23日就A10 棟9 樓系爭房地所簽訂之系爭房屋及土地買賣\n    契約之內容均相同，僅買賣標的不同，此為兩造所不爭執，\n    是原告自96年5 月12日與被告簽訂A15 棟11樓房地契約後至\n    97年3 月23日與被告簽訂A10 棟9 樓系爭房地契約時，原告\n    已有10個月以上之期間足以充分審閱相同內容之系爭房地買\n    賣契約，而此其間已超過消費者保護法第11條之1 所規定之\n    30日審閱期間，是即便原告未看清該契約之內容，即於契約\n    書上簽名並交回契約書，然原告非不得於系爭房地買賣契約\n    簽名前就契約書之內容，詳加閱讀。其不為此之圖，卻於完\n    全瞭解契約內容前即於契約書上簽名，係對自身權利之拋棄\n    ，尚非法所不許，亦不影響其簽名之效力。再者，本件並無\n    證據證明被告有限制原告必須於何時簽名，何時將契約書交\n    回，應認被告已留予原告合理之契約審閱期間，是原告非不\n    得於簽名前就契約書之內容，詳加閱讀。則原告既仍願與被\n    告簽訂系爭買賣契約，自不能再以被告未提供合理審閱期間\n    為由，主張系爭土地買賣契約第5 條及第10條與系爭房屋買\n    賣契約第18條及第23條，不構成契約內容之一部。\n  3.從而，原告主張被告未提供契約合理審閱期間，系爭土地買\n    賣契約第5 條、第10條及系爭房屋買賣契約第18條、第23條\n    之約定為定型化契約條款，不構成契約之一部，被告依該等\n    約定沒收原告繳納之款項，即無法律上原因，原告得依民法\n    第179 條、第182 條請求被告返還不當得利及利息云云，即\n    屬無據，而不足採。\n  (二)原告主張以龜山迴籠郵局第50號存證信函解除系爭房屋及土\n    地買賣契約，並依民法第179 條、第182 條規定請求被告返\n    還不當得利，有無理由？如有理由，被告應返回之金額為若\n    干？\n  1.原告主張系爭房地抵押貸款金額因房地價值過低，致銀行僅\n    願核貸170 萬元，與原先預定之貸款200 萬元有30萬元之差\n    額，經原告寄發存證信函催告被告協助貸款後，被告未理會\n    ，原告依「預售屋買賣定型化契約應記載及不得記載事項」\n    第18點第2 項第2 款及民法第359 條之規定於97年8 月23\n    日解除契約等語，為被告所否認。經查：\n  (1)按「預售屋買賣定型化契約應記載及不得記載事項」第18點\n    第2 款第2 目規定：前款由賣方洽定辦理之貸款金額少於預\n    定貸款金額，其差額於可歸責於賣方時，差額部分，賣方應\n    依原承諾貸款相同年限及條件由買方分期清償。如賣方不能\n    補足不足額部分，買方有權解除契約。又按買賣因物有瑕疵\n    ，而出賣人依前五條之規定，應負擔保之責者，買受人得解\n    除其契約或請求減少其價金。但依情形，解除契約顯失公平\n    者，買受人僅得請求減少價金，民法第359 條亦有明文。\n  (2)查為導正預售屋買賣契約書之內容，使其符合誠實信用及平\n    等互惠原則，促進公平交易，確保消費者權益，內政部依消\n    費者保護法第17條第1 項規定，於90年9 月3 日公布「預售\n    屋買賣定型化契約應記載及不得記載事項」，其後曾於98年\n    8 月10日、98年10月30日、99年8 月16日及100 年3 月24日\n    作微幅修正。而本件系爭房地買賣，係於房屋建築完成後，\n    原告至現場看屋，因對原本購買之A15 棟11樓預售房屋結構\n    不滿意，而與被告協議換屋，故兩造再於97年3 月23日就A1\n    0 棟9 樓系爭房地簽定系爭買賣契約，則系爭房地買賣契約\n    雖名為房屋、土地「預定買賣契約書」，惟係於系爭房屋建\n    築完成後，經兩造確認買賣之標的為A10 棟9 樓房地所締結\n    之契約，斯時買賣標的A10 棟9 樓房屋已經存在，與預售屋\n    買賣契約訂立時買賣標的尚未存在之性質不同，是系爭房地\n    買賣契約其性質應非屬預售屋買賣，而應屬一般之成屋買賣\n    ，是兩造間系爭房地買賣契約關係，應無「預售屋買賣定型\n    化契約應記載事項及不得記載事項」之適用。是原告主張依\n    「預售屋買賣定型化契約應記載及不得記載事項」第18點第\n    2 款第2 目規定，其有權解除契約云云，尚無足採。\n  (3)次查，經本院依職權函詢渣打銀行關於原告以系爭房地申辦\n    貸款之情形，該銀行以100 年2 月25日渣打商銀SCBCL 字第\n    1001002655號函回覆表示：原告於97年3 月間購買系爭房地\n    後，自行向該銀行申辦貸款，當時核定原告得貸款之金額為\n    170 萬元，但因批示決核後逾3 個月原告未申請撥款，故該\n    行予以駁回等語，有上開函文暨貸款資料1 份附卷可稽（見\n    本院卷第308 至316 頁）。又參以訴外人即渣打銀行貸款承\n    辦人李汪恩於臺灣臺北地方法院檢察署98年度他字第589 號\n    詐欺案98年7 月3 日下午2 時13分詢問筆錄證稱：「（問：\n    高總共跟你們貸款幾次？所貸金額多少？核准金額多少？）\n    第一次是97年3 月28日來申辦信用貸款30萬，皆如數核准貸\n    款。第二次是97年5 月9 日申請房貸170 萬，於5 月13日核\n    准，但至8 月21日因告訴人（即本件原告，下同）未對保，\n    公司規定超過3 個月未對保所以取消該筆房貸。後來告訴人\n    在同一天97年8 月21日又以相同抵押物（時尚女人香的房屋\n    ）再次申請170 萬元貸款，核准日期是97年8 月27日，但這\n    次一樣是超過三個月沒對保以致其貸款被取消。在97年7 月\n    14日還有一次是以高自己的房屋（桃園縣龜山鄉○○路○段\n    122 號之5 號7 樓）來申請貸款380 萬元並如數核准撥款。\n    」等語（見本院卷第338 頁）；及訴外人即渣打銀行貸款部\n    主管李思賓於同次筆錄證稱：「依文件來看是告訴人2 次均\n    親自遞件以時尚女人香來申請貸款170 萬，我們綜合申請人\n    的收入、抵押品及信用狀況來評估准許貸款之金額，告訴人\n    2 次所貸的170 萬元都如數核准，只是因為超過3 個月未對\n    保故予取消。... （是否該約300 戶的貸款是由你們承辦？\n    ）是。一般來說確實可以貸到房價的7 到85成。... （告訴\n    人剛才有說他97年3 月2 日有一筆信貸30萬元，是否影響到\n    他後來申請200 萬卻貸得170 萬的房貸？）是。」等語（見\n    本院卷第339 至342 頁）；另原告於同次筆錄陳稱：「（問\n    告訴人：該文件上為何會有你的簽名，你當初申請貸款是否\n    為170 萬元？）因為我已繳了一些款項在被告那邊，雖然我\n    貸的款項是200 萬，但我怕錢被被告他們沒收，所以只核准\n    170 萬元我只好同意」等語（見本院卷第341 頁）。由上足\n    徵，原告係自行遞件以系爭房地向渣打銀行申請貸款170 萬\n    元，並非由被告洽定辦理貸款，且因原告於97年3 月2 日已\n    有申請一筆信用貸款30萬元，致影響到渣打銀行評估本件核\n    貸之金額為170 萬，況且依李思賓之上開證詞，本件時尚女\n    人香建案約300 戶的貸款均由渣打銀行承辦，一般來說確實\n    可以貸到房地價格的7 到85成之金額，並無因房地價格過低\n    ，而無法貸足房地價格7 到85成金額之情形。從而，原告主\n    張系爭房地抵押貸款金額因房地價值過低，致銀行僅願核貸\n    170 萬元，與原先預定之貸款200 萬元有30萬元之差額云云\n    ，即屬無據，不足採信。另原告主張依民法第359 條之規定\n    解除系爭房地買賣契約，惟始終未舉證證明系爭房地有何瑕\n    疵存在，則其此部分主張，亦乏依據，而無足取。\n  2.原告主張被告未依照契約義務協助貸得200 萬元貸款，為民\n    法第227 條不完全給付，原告定相當期間命被告協助貸款，\n    被告逾期仍不履行，原告得解除契約，有無理由？\n    查本件係原告自行遞件以系爭房地向渣打銀行申請貸款170\n    萬元，並非由被告洽定辦理貸款，且因原告於97年3 月2 日\n    已有申請一筆信用貸款30萬元，致影響到渣打銀行評估本件\n    核貸之金額為170 萬，又依李思賓之上開證詞，本件時尚女\n    人香建案約300 戶的貸款均由渣打銀行承辦，一般來說確實\n    可以貸到房價的7 到85成之金額等情，俱如前述，是原告就\n    系爭房地未能貸得其預期之貸款200 萬元，顯係可歸責於其\n    自身之事由所致，則原告主張被告未依照契約義務協助貸得\n    200 萬元貸款，有民法第227 條不完全給付情形，原告得定\n    相當期間命被告協助貸款，被告逾期仍不履行，原告得解除\n    契約云云，即屬無據。\n  3.從而，原告主張以龜山迴籠郵局第50號存證信函解除系爭房\n    屋及土地買賣契約，並依民法第179 條、第182 條規定請求\n    被告返還不當得利，即無理由，不應准許。\n  (三)原告主張系爭土地買賣契約第5 條及第10條、房屋買賣契約\n    第18條及第23條，縱為契約之一部亦因對契約之他方顯失公\n    平，違反消費者保護法第12條、民法247 條之1 、預售屋買\n    賣定型化契約應記載事項及不得記載事項第24條第4 項而無\n    效，並依民法第179 條、第182 條規定請求被告返還不當得\n    利，有無理由？如有理由，被告應返回之金額為若干？\n  1.按消費者保護法第12條規定：定型化契約中之條款違反誠信\n    原則，對消費者顯失公平者，無效。定型化契約中之條款有\n    下列情形之一者，推定其顯失公平：一、違反平等互惠原則\n    者。二、條款與其所排除不予適用之任意規定之立法意旨顯\n    相矛盾者。三、契約之主要權利或義務，因受條款之限制，\n    致契約之目的難以達成者。又消費者保護法施行細則第14條\n    規定：定型化契約條款，有下列情事之一者，為違反平等互\n    惠原則：一、當事人間之給付與對待給付顯不相當者。二、\n    消費者應負擔非其所能控制之危險者。三、消費者違約時，\n    應負擔顯不相當之賠償責任者。四、其他顯有不利於消費者\n    之情形者。再民法第247 條之1 規定：依照當事人一方預定\n    用於同類契約之條款而訂定之契約，為左列各款之約定，按\n    其情形顯失公平者，該部分約定無效：一、免除或減輕預定\n    契約條款之當事人之責任者。二、加重他方當事人之責任者\n    。三、使他方當事人拋棄權利或限制其行使權利者。四、其\n    他於他方當事人有重大不利益者。又預售屋買賣定型化契約\n    應記載事項及不得記載事項第24條第4 項規定：買方違反有\n    關「付款條件及方式」之規定者，賣方得沒收依房地總價款\n    百分之＿（最高不得超過百分之十五）計算之金額。但該沒\n    收之金額超過已繳價款者，則以已繳價款為限，買賣雙方並\n    得解除本契約。\n  2.原告主張系爭房屋買賣契約第18條、第23條、土地買賣契約\n    第5 條及第10條之規定與綜合契約內其他條款約定，若因買\n    方貸款條件不符合，需沒收高達房屋總價百分之20之違約金\n    ，相較之下，被告雖負有義務協助辦理抵押貸款，但若因被\n    告之原因致貸款不足額時，卻未有罰則或任何處理方法，買\n    賣雙方所負之義務顯不相當，明顯使原告負有不相當之義務\n    ，故系爭房地契約定型化契約之貸款及違約條款與平等互惠\n    原則即有不合，依消費者保護法第12條、消費者保護法施行\n    細則第14條規定，契約條款違反誠信原則，對消費者顯失公\n    平者，無效；且按「預售屋買賣定型化契約應記載事項及不\n    得記載事項」第24條第2 款是以消費者違約時，企業經營者\n    固得沒收一定比例之買賣價金，然其比例上限不得超過房地\n    價值百分之15。被告於契約內約定違約時沒收總價金百分20\n    ，核與內政部公告之定型化契約範本上限為百分之15不符，\n    超出部份應屬無效；況被告實際沒收金額為原告全額已繳價\n    金及非屬買賣價金之預繳款項共676,769 元，比例已高達總\n    價金百分之25，明顯違反「預售屋買賣定型化契約應記載事\n    項及不得記載事項」第24條第2 款之規定，係屬違法等語，\n    為被告所否認。\n  3.查系爭房屋買賣契約第18條第1 項及土地買賣契約第5 條第\n    1 項均約定：倘因買方貸款條件不符合致不能核貸或無法如\n    數貸足，則其原欲貸款部份之價款應於賣方通知後七日內以\n    現金一次補足，否則即係違約（見本院卷第27頁、第74 頁\n    反面）。觀此內容，乃係因可歸責於買方之事由致不能核貸\n    或無法如數貸足，而約定買方應補足貸款差額之約定，並無\n    消費者保護法第12條及民法第247 條之1 所規定違反誠信原\n    則、顯失公平等情形，自非無效之約定。又系爭房屋買賣契\n    約第23條第2 項及土地買賣契約第10條第2 項約定：買方違\n    反房屋買賣契約第7 條、第15條第3 項及第18條約定，或違\n    反土地買賣契約第4 條之約定，買方得沒收依房地總價款百\n    分之20計算之金額；而系爭房屋買賣契約於第23條第1 項及\n    土地買賣契約第10條第1 項亦約定：賣方違反房屋買賣契約\n    第11條、第12條第2 項及第21條之約定者，或賣方違反土地\n    賣賣契約第8 條之約定者，買方均得解除契約，賣方除應將\n    買方已繳之房地價款及遲延利息全部退還賣方外，並應同時\n    賠償房地總價款百分之20之違約金（見本院卷第28、76 頁\n    ）。足徵系爭房屋買賣契約第23條及土地買賣契約第10 條\n    有關違約處罰之約定，對於可歸責於買賣雙方之違約罰則均\n    有約定，且賠償之比例均以房地總價款百分之20計算，是該\n    等約定即無原告所主張買賣雙方所負之義務顯不相當，明顯\n    使原告負有不相當之義務之情形，應無消費者保護法第12條\n    及民法第247 條之1 所規定違反誠信原則、顯失公平等情形\n    ，自非無效之約定。再者，「預售屋買賣定型化契約應記載\n    事項及不得記載事項」第24條第2 款所定賣方得沒收依房地\n    總價款最高不得超過百分之15計算之金額之規定，乃係針對\n    預售屋買賣而為之規定。而系爭房地買賣契約其性質非屬預\n    售屋買賣，而應屬一般之成屋買賣，兩造間系爭房地買賣契\n    約關係，並無「預售屋買賣定型化契約應記載事項及不得記\n    載事項」之適用，有如前述，則原告主張被告沒收金額為原\n    告全額已繳價金及非屬買賣價金之預繳款項共676,769 元，\n    比例已高達總價金百分之25，明顯違反「預售屋買賣定型化\n    契約應記載事項及不得記載事項」第24條第2 款之規定云云\n    ，即屬無據。又系爭房屋買賣契約第23條第2 項及土地買賣\n    契約第10條第2 項約定沒收買方房地總價百分之20之比例，\n    並非顯然過高，故無消費者保護法第12條及民法第247 條之\n    1 所規定違反誠信原則、顯失公平等情形，自非無效之約定\n    。是被告依據系爭契約上開約定解除契約，沒收原告已繳之\n    價金，即非無法律上之原因，並無不當得利之情形。\n  4.從而，原告主張系爭土地買賣契約第5 條及第10條、房屋買\n    賣契約第18條及第23條，縱為契約之一部亦因對契約之他方\n    顯失公平，違反消費者保護法第12條、民法247 條之1 、預\n    售屋買賣定型化契約應記載事項及不得記載事項第24條第4\n    項而無效，並依民法第179 條、第182 條規定請求被告返還\n    不當得利，為無理由，不應准許。\n  (四)原告主張被告就系爭房地因價值過低導致核貸金額不足，及\n    夾層屋之設計係屬不法等重要事項惡意隱瞞，違反誠實及信\n    用方法，致原告受有損害，依民法第245 之1 條第1 項第1\n    款、第3 款規定應負損害賠償責任，有無理由？如有理由，\n    被告應賠償之金額為若干？\n  1.按民法第245條之1第1項第1 款、第3 款規定：契約未成立\n    時，當事人為準備或商議訂立契約而有左列情形之一者，對\n    於非因過失而信契約能成立致受損害之他方當事人，負賠償\n    責任：一、就訂約有重要關係之事項，對他方之詢問，惡意\n    隱匿或為不實之說明者。... 三、其他顯然違反誠實及信用\n    方法者。\n  2.原告主張於訂立系爭契約時，被告之銷售人員表示一定可以\n    貸至200 萬元，對於貸款額度可能會因系爭房地價值過低，\n    導致核貸金額不足之事，完全未曾提及，是故就此重要事項\n    為惡意隱瞞，已該當民法第245 之1 條第1 項第1 款之事由\n    ，被告等惡意隱瞞，亦違反誠實及信用方法，致原告受有損\n    害；又被告之銷售人員於看屋一再表示該樣品屋內可做夾層\n    之設計，並提供夾層之樣品屋，使原告誤信購買系爭房屋後\n    ，可為夾層屋之設計而為之購買，詎購買後查閱相關資料始\n    知悉夾層屋之設計係屬不法，此乃就交易上重要事項惡意隱\n    匿、不實說明，已該當民法第245 條之1 第1 項第1 款及第\n    3 款事由，應對原告負賠償之責等語，並聲請傳喚證人楊鴻\n    彬及提出廣告單影本4 紙為證（見本院卷第79至82頁），惟\n    此為被告所否認。\n  3.查本件因原告於97年3 月2 日已有申請一筆信用貸款30萬元\n    ，致影響到渣打銀行評估本件核貸之金額為170 萬，又依李\n    思賓之上開證詞，本件時尚女人香建案約300 戶的貸款均由\n    渣打銀行承辦，一般來說確實可以貸到房價的7 到85成之金\n    額等情，有如前述，是本件貸款金額未達原告預期之200 萬\n    元即房地總價款之75成，乃歸因於原告本身之因素所致。則\n    原告主張訂立系爭契約時，被告之銷售人員表示一定可以貸\n    至200 萬元，惡意隱瞞貸款額度可能會因系爭房地價值過低\n    ，導致核貸金額不足之事，亦違反誠實及信用方法，該當民\n    法第245 之1 條第1 項第1 款及第3 款之事由，應負賠償責\n    任云云，並無足採。\n  4.次查，證人楊鴻彬於本院言詞辯論時證稱：伊與原告去看建\n    案時尚女人香樣品屋，挑高大概7 米多，有點像樓中樓形式\n    的套房，直走有個小樓梯可以上去，樓梯的旁邊有餐廳及客\n    廳，樓上是個小房間，可以在上面睡覺，小房間下面是客廳\n    及餐廳。... 業務員說可以做兩個樣子，一個是像樣品屋這\n    樣挑高的，一個是一般沒有挑高的，建商會幫我們做好，但\n    是房屋的總價是一樣的等語（見本院卷第239 頁反面），固\n    足認定被告展示之樣品屋係作夾層之裝潢設計。惟觀諸原告\n    所提出之廣告單，並無隻字片語提及「夾層屋」係屬合法建\n    物之內容，原告復未提出證據證明被告之銷售人員曾表示夾\n    層屋係合法，而原告及證人所參觀之樣品屋以夾層之裝潢予\n    以展現，屬空間利用方法之參考展示，僅供購買者作其房屋\n    裝潢設計之參考，尚難認樣品屋以夾層之裝潢展示，即遽認\n    被告有將夾層屋之設計係屬不法等重要事項惡意隱瞞，違反\n    誠實及信用方法之情形。則原告主張被告惡意隱瞞夾層屋之\n    設計係屬不法等重要事項，違反誠實及信用方法，致原告受\n    有損害，依民法第245 之1 條第1 項第1 款、第3 款規定應\n    負損害賠償責任云云，並無可採。\n六、綜上所述，原告主張依民法第179 條、第182 條、第245 之\n    1 條第1 項第1 款、第3 款之規定，請求：(一)被告應給付原\n    告276,796元，及自97年8 月24日起至清償日止，按週年利\n    率百分之5 計算之利息。(二)被告林鴻聯應給付原告40萬元，\n    及自97年8 月24日起至清償日止，按週年利率百分之5 計算\n    之利息，均無理由，應予駁回。又原告之訴既經駁回，其假\n    行之聲請亦失所附麗，併予駁回。\n七、本件事證已臻明確，兩造其餘攻擊防禦方法及未經援用之證\n    據，經審酌後，核與判決結果不生影響，爰不一一論述。\n八、據上論結，本件原告之訴為無理由，依民事訴訟法第79條，\n    判決如主文。",
    "reason": "一、原告主張：\n  (一)原告於民國97年3 月23日向被告瓏山林企業股份有限公司（\n    下稱瓏山林公司）與林鴻聯購買坐落新北市○○區○○段第\n    557 、558 、559 、560 、565 、566 、567 地號等7 筆土\n    地上「時尚女人香」建案編號A10 棟9 樓房屋1 戶及其基地\n    （下稱系爭房地），並與被告瓏山林企業股份有限公司（下\n    稱瓏山林公司）簽訂房屋預定買賣契約書（下稱系爭房屋買\n    賣契約），與被告林鴻聯簽訂土地預定買賣契約書（下稱系\n    爭土地買賣契約），約定系爭房地總價金為新臺幣（下同）\n    265 萬元。依系爭土地買賣契約第11條、系爭房屋買賣契約\n    第26條約定，此兩契約及其附件為不可分割之給付，具有連\n    帶及不可分之關係。被告瓏山林公司於售屋廣告上標明貸款\n    成數為8 成5 純銀貸，然其後被告瓏山林公司因貸款成數與\n    廣告不符造成眾多消費者糾紛，經平面媒體、消保官及公平\n    交易委員會等認定有違反消費者保護法及平交易法之嫌。是\n    故被告要求降低貸款成數為7 成5 ，即200 萬元為貸款，自\n    備款為65萬元，原告本有疑慮，但被告之銷售人員一再保證\n    系爭房地價值很高，一定可以貸到房地價值總額7 成5 亦即\n    200 萬元，原告受其蠱惑，且被告未給予原告契約審閱期間\n    ，於簽約當日直接要求原告簽訂買賣契約，原告因此陸續給\n    付自備款65萬元、代書費用36,700元及預繳費用26,769元，\n    共計713,469 元。原告與被告等簽訂之系爭房地買賣契約約\n    定，委託被告等向銀行申請以系爭房地抵押貸款，其內容略\n    為「土地/ 房屋總價內之部分價款（即契約附件1 ：房屋價\n    款分期付款明細表中可委辦貸款抵繳之期款總額），由買方\n    與賣方洽訂之金融機構之貸款給付，最長期限為20年，以買\n    賣雙方簽立「代辦申請貸款委託書」（即契約附件11）依約\n    定辦妥一切貸款手續」。是被告等負有義務依系爭房地買賣\n    契約內附件，依照約定貸款成數7 成5 ，辦妥一切貸款手續\n    ，其委託貸款金額為房屋76萬元、土地124 萬元，共200 萬\n    元。詎料，配合被告系爭建案貸款業務之渣打銀行，通知原\n    告鑑價結果，系爭房地價值過低，僅有每坪17至18萬元，故\n    核貸金額僅為170 萬元，原告遂反映上情於被告。惟被告之\n    客服人員態度極差，以「自己去找別家銀行問呀！」「如果\n    你有錢就不必害怕貸不到了！」等惡言相向，拒絕處理。被\n    告甚至於97年8 月14日寄發存證信函，要求於5 日內繳付貸\n    款差額，否則依約沒入原告全部已繳款項，原告則於97年8\n    月20日寄發存證信函告知被告違約，並以涉及詐欺等罪責，\n    請求其依照契約協助辦理足額貸款，否則於函到後3 日解除\n    契約，然被告卻置若罔聞，更在97年9 月23日發函解除契約\n    ，並沒入原告已繳之土地買賣自備款40萬元、房屋買賣自備\n    款25萬元及預繳費用26,769元共計676,769 元。被告等妄稱\n    因原告貸款條件不符以致無法如數貸足。然原告曾以個人名\n    義向承辦系爭房地抵押貸款之渣打銀行申請貸款30萬元，獲\n    銀行全額核貸，足證原告個人貸款條件良好，非如被告所稱\n    貸款條件不符。被告身為知名企業，為經濟上之強者，為其\n    商譽應依誠實信用原則為交易，然被告卻以廣告訛騙消費者\n    ，再以定型化契約內容規避責任，並曲解契約條款內容，藉\n    此沒收消費者所繳之款項，此有消保會申訴調解記錄可證，\n    其中所列之訴消費者共19人，皆因系爭房地價值過低導致核\n    貸不足，與被告產生糾紛而向消保官申訴，足見被告以此方\n    法預謀設陷，坑害消費者，且本案經媒體大幅報導，足證被\n    告確有前開事證。\n  (二)原告主張系爭房地買賣契約內之定型化契約條款不構成契約\n    之一部，依民法第179 條、第182 條請求被告返還不當得利\n    ：\n  1.系爭房屋買賣契約之賣方為被告瓏山林公司，系爭土地買賣\n    契約之賣方為被告林鴻聯，瓏山林公司為消費者保護法第2\n    條第2 款之企業經營者當無疑義，應適用消費者保護法之各\n    項規定。\n  2.系爭土地買賣契約與房屋買賣契約為同日簽訂，且契約內已\n    約定兩者為連帶不可分之關係，與當事人之意思，具有不可\n    分割之依存關係，依臺灣高等法院88年度上字第304 號判決\n    意旨，系爭房屋買賣契約具有無效或解除之事由，系爭土地\n    買賣契約亦應該當此事由。\n  3.原告簽訂系爭房地買賣契約時，未有合理審閱期限，且簽約\n    當日，因被告之銷售員一再強力推銷並要求立刻簽訂契約，\n    原告迫於無奈，僅得簽名蓋章。按最高法院98年度台上字第\n    168 號判決意旨，倘企業經營者於定型化契約上加註消費者\n    拋棄審閱期間之條款，為顯失公平，仍為無效，應由企業經\n    營者證明已給予合理審閱期間，倘未能舉證已給予消費者合\n    理審閱期間，定型化契約條款不構成契約內容之一部。被告\n    雖表示原告選擇拋棄合理審期之約款，未強迫原告云云，然\n    被告於定型化契約要求原告簽名放棄合理審閱期間，該拋棄\n    審閱期間之條款按前開判決見解，為顯失公平應為無效。且\n    事實上被告確未提供合理審閱期間，定型化契約條款應不構\n    成契約之內容，依消費者保護法第11條之1 規定，原告主張\n    系爭土地買賣契約第5 條及第10條，系爭房屋買賣契約第18\n    條及第23條（即貸款及違約條款），對於原告規範之內容不\n    公平，應不構成契約內容之一部。則被告依據系爭土地買賣\n    契約第5 條及第10條，系爭房屋買賣契約第18條及第23條沒\n    收原告所繳款項676,769 元，即無法律上原因，原告爰依民\n    法第179 條及第182 條，請求被告等返還不當利益676,769\n    元，及自解除契約時起，按年息百分之5 計算之利息。\n  (三)原告依「預售屋買賣定型化契約應記載及不得記載事項」第\n    17點第2 款第2 目、民法第359 條之規定解除契約，並依民\n    法第179 條不當得利請求返還自備款及預繳款項共676,769\n    元：\n  1.依據內政部於90年9 月3 日公告之「預售屋買賣定型化契約\n    應記載及不得記載事項」中第18點第2 項第2 款（原告綜合\n    言辭辯論意旨狀誤載為第17點第2 款第2 目）及消費者保護\n    法第17條、消費者保護法施行細則第15條規定，買方解除契\n    約後，得依民法第179 條請求賣方返還已給付之價金及預付\n    款項。\n  2.原告與被告等所簽訂之系爭契約，就貸款條件約定僅有第18\n    條：「倘因買方貸款條件不符合致不能核貸或無法如數貸足\n    ，則其原欲貸款部份之價款應於賣方通知後七日內以現金一\n    次補足，否則即系違約。」然依照「預售屋買賣定型化契約\n    應記載及不得記載事項」第18點第2 項第2 款：「由賣方洽\n    定辦理之貸款金額少於預訂貸款金額，若可歸責於賣方時，\n    如賣方不能補足不足額部分，買方有權解除契約。」是依消\n    費者保護法施行細則第15條及「預售屋買賣定型化契約應記\n    載及不得記載事項」第18點仍構成契約之內容，系爭房地之\n    抵押貸款，因被告販售房地之價值過低，導致銀行僅願核貸\n    170 萬元，與原先預定之200 萬元有30萬元之差額，故貸款\n    金額少於預定貸款金額系可歸責於被告，且原告在同一時間\n    以相同經濟能力為條件向承辦系爭房地抵押貸款之銀行即渣\n    打銀行申請貸款30萬元，獲銀行全額核貸，足證系爭房地抵\n    押貸款核貸金額不足30萬元，係因為被告之房地價值過低所\n    致，非因原告個人貸款條件不符，原告有權據此解除契約。\n  3.被告經原告寄發存證信函催告協助貸款後，仍不補足差額，\n    買方於97年8 月23日解除契約。契約關係消滅後，原告所給\n    付之自備款及預繳款項共676,769 元，被告等即無保有之法\n    律上原因，應返還之。另按民法第182 條規定，被告受領價\n    金並應附利息，一併返還於原告，故原告得主張自解除契約\n    起，按年息百分之5 計算之利息。\n  4.另原告主張民法第359 條物之瑕疵擔保效力，解除契約，並\n    請求回復原狀，返還原告已給付之價金共676,769 元：按出\n    賣人應擔保其物於危險移轉時具有其所保證之品質，是故買\n    賣之物有瑕疵，而出賣人應負擔保之責者，買受人得解除其\n    契約或請求減少其價金。解除契約後依民法第259 條、第17\n    9 條及第182 條，請求返還受領給付之金錢及利息。被告等\n    於系爭契約訂定時，保證該房屋之價值為1 坪23萬元以上，\n    亦保證最後於銀行貸款時得貸足總額之7 成5 即為200 萬元\n    ，原告因被告等保證可貸款200 萬元方購買之，若無法貸至\n    200 萬元，原告即不會考慮購買系爭房地，然事後該房屋經\n    銀行鑑價，1 坪僅價值17萬元，系爭房地未如其所稱高價，\n    導致無法貸足200 萬元，同時被告等亦未依其保證貸足200\n    萬元，系爭房屋並無被告所保證之品質，是故原告得依民法\n    第359 條解除契約，並請求依民法第259 條回復原狀。被告\n    林鴻聯應返還其自原告受領之款項40萬元、被告瓏山林公司\n    應返還自原告受領之自備款25萬元及與預繳款項26,769元共\n    276,769 元。並應給付自解除契約翌日起按週年利率百分之\n    5 之利息。\n  (四)系爭土地買賣契約第5 條及第10條、房屋買賣契約第18條及\n    第23條，縱為契約之一部亦因對契約之他方顯失公平違反消\n    保法第12條、民法247 條之1 、預售屋買賣定型化契約應記\n    載事項及不得記載事項第24條第2 款而無效：\n  1.觀以系爭房屋買賣契約第18條、第23條之規定與綜合契約內\n    其他條款約定，買賣雙方所負之義務顯不相當，若係因買方\n    貸款條件不符合，需沒收高達房屋總價百分之20之違約金，\n    相較之下，被告雖負有義務協助辦理抵押貸款，但若因被告\n    之原因致貸款不足額時，卻未有罰則或任何處理方法，導致\n    消費者需負擔顯不相當之賠償責任。是故定型化契約之貸款\n    及違約條款與平等互惠原則即有不合，依消費者保護法第12\n    條及消費者保護法施行細則第14條規定，契約條款違反誠信\n    原則，對消費者顯失公平者，無效。\n  2.次查，原告確實未有合理審閱期間，系爭契約內文字未有任\n    何修改，事實上原告於自決定購屋至簽定契約時間極短暫，\n    被告之銷售員僅要求原告儘快簽約，不僅未提供合理審閱期\n    間，亦無任何可供磋商變更契約條款之機會，最終簽訂之契\n    約亦按照被告所提供之範本簽訂，未有任何更改，原告無任\n    何磋商餘地，被告稱原告得磋商變更云云，顯不足採。\n  3.再查，系爭契約條款約定委託被告貸得總數7 成5 之貸款，\n    然未約定倘因可歸責於被告致使貸款不成或成數不足時應如\n    何處理，被告依契約所負之貸款義務違反時，均無任何處理\n    方式或罰則，相較之下，被告於契約內貸款約定（房屋契約\n    第18條、土地契約第5 條）僅約定倘買方貸款條件不符致貸\n    款不成或成數不足之處理方式，並依房屋契約第23條、土地\n    契約第10條約定有高額賠償金，雙方顯有地位不平等、所負\n    義務不相當之情形。\n  4.末查，比較「預售屋買賣定型化契約應記載及不得記載事項\n    」第18點第2 款，完整規範當貸款金額少於約定貸款貸款金\n    額時，區分不可歸責雙方、可歸責於賣方與可歸責於買方之\n    處理方式，然被告所使用之系爭契約僅約定倘貸款金額不足\n    ，原告應一次以現金補足，否則為違約，並未將被告即賣方\n    違約規範於契約中，明顯使原告負有不相當之義務，系爭契\n    約之貸款及違約條款違反消費者保護法第12條顯失公平為無\n    效。\n  5.按「預售屋買賣定型化契約應記載事項及不得記載事項」第\n    24條第2 款是以消費者違約時，企業經營者固得沒收一定比\n    例之買賣價金，然其比例上限不得超過房地價值百分之15。\n    被告於契約內約定違約時沒收總價金百分20，核與內政部公\n    告之定型化契約範本上限為百分之15不符，超出部份應屬無\n    效。況被告實際沒收金額為原告全額已繳價金及非屬買賣價\n    金之預繳款項共676,769 元，比例已高達總價金百分之25\n    ，被告稱依法行事，實屬狡辯，明顯違反「預售屋買賣定型\n    化契約應記載事項及不得記載事項」第24條第2 款之規定，\n    係屬違法，被告以此誆騙消費者，彰彰甚明。\n  (五)被告未依照契約義務協助貸得足額貸款，為民法第227 條不\n    完全給付，原告定相當期間命被告協助貸款，逾期不履行即\n    得解除契約：\n  1.被告依照契約及廣告內容，應協助信用條件良好之原告貸得\n    總價7 成5 之貸款，然最終核貸金額不足係因被告房地價值\n    1 坪僅17萬，較被告所稱之1 坪20萬低，故銀行因供擔保設\n    定之不動產價值不足，僅願核貸170 萬，貸款差額30萬為可\n    歸責於被告致不完全給付，原告得催告被告給付並得解除契\n    約。\n  2.原告於97年8 月20日寄發存證信函告知被告違約，並以涉及\n    詐欺等罪責，請求其依照契約協助辦理足額貸款，否則於函\n    到後3 日解除契約，然被告於97年8 月21日收到後卻置若罔\n    聞，原告解除契約自屬合法。\n  (六)原告依民法第245 條之1 規定，請求因被告等對契約重要事\n    項為惡意隱匿不實說明所致之損害：\n  1.系爭房屋價金7 成5 以抵押房地貸款支付，是故抵押貸款之\n    金額，是否可全額貸足，即為契約上重要關係事項。\n  2.原告於訂立契約時，向被告等之銷售人員詢問房屋抵押貸款\n    之詳情，其以一定可以貸至200 萬元為由搪塞。對於貸款額\n    度可能會因系爭房地價值過低，導致核貸金額不足之事，完\n    全未曾提及，是故就此重要事項為惡意隱瞞，已該當民法第\n    245 之1 條第1 項第1 款之事由，被告等惡意隱瞞，亦違反\n    誠實及信用方法，致原告受有損害。\n  3.另被告等之銷售人員於看屋一在主張該樣品屋內可做夾層之\n    設計，並提供夾層之樣品屋，使原告誤信購買系爭房屋後，\n    可為夾層屋之設計而為之購買，詎料，購買後查閱相關資料\n    始知悉夾層屋之設計係屬不法，並經被告事後承認，此乃就\n    交易上重要事項惡意隱匿、不實說明，已該當民法第245 條\n    之1 第1 項第1 款及第3 款事由，應對原告負賠償之責。\n  4.原告因信被告等之說明，締結契約，交付自備款共65萬元及\n    預繳之費用26,769元，卻遭被告沒收全額，受有損害共676,\n    769 元，被告應為賠償。\n  (七)聲明：1.被告瓏山林公司應給付原告276,796 元，及自97年\n    8 月24日起至清償日止，按週年利率百分之5 計算之利息。\n    2.被告林鴻聯應給付原告40萬元，及自97年8 月24日起至清\n    償日止，按週年利率百分之5 計算之利息。3.原告願供擔保\n    請准宣告假執行。\n二、被告則抗辯：\n  (一)原告稱被告之銷售人員一再保證系爭房地價值很高，一定可\n    以貸到房地價值總額7 成5 亦即200 萬元，嗣配合系爭建物\n    貸款業務之渣打銀行核貸金額僅為170 萬元。是被告未依照\n    契約義務協助貸得足額貸款，為民法第227 條不完全給付，\n    原告定相當期間命被告協助貸款，逾期不履行即得解除契約\n    云云，顯與事實有違：\n  1.查銀行是否核貸款項達7 成5 ，乃銀行依承購戶個人之資力\n    、信用條件而為決定，被告公司僅為銷售房地之建商，並無\n    能力對承購戶資力、將來發生呆帳風險作專業之評估，實無\n    可能擅自代銀行決定貸款之條件，或毫無條件即承諾、保證\n    承購戶可貸款7 成5 ，而自陷承購戶將來發生無力償還貸款\n    時，須賠償銀行損失或自行進行冗長之訴訟程序。是原告稱\n    被告銷售系爭房地時，有保證貸款7 成5 云云，洵非事實，\n    被告鄭重否認之。\n  2.訴外人即渣打銀行貸款承辦人李汪恩於98年7 月3 日下午2\n    時13分在臺灣臺北地方法院檢察署98年度他字第589 號詐欺\n    案所作詢問筆錄第2 頁及第5 頁證稱：「（問：高總共跟你\n    們貸款幾次？所帶金額多少？核准金額多少？）第一次是97\n    年3 月28日來申辦信用貸款30萬，皆如數核准貸款。第二次\n    是97年5 月9 日申請房貸170 萬，於5 月13日核准，但至8\n    月21日因告訴人未對保，公司規定超過3 個月未對保所以取\n    消該筆房貸。後來告訴人在同一天97年8 月21日又以相同抵\n    押物（時尚女人香的房屋）再次申請170 萬元貸款，核准日\n    期是97年8 月27日，但這次一樣是超過三個月沒對保以致其\n    貸款被取消。在97年7 月14日還有一次是以高自己的房屋（\n    桃園縣龜山鄉○○路○段122 號之5 號7 樓）來申請貸款\n    380 萬元並如數核准撥款。」等語（見本院卷第338 頁），\n    又訴外人即渣打銀行貸款部主管李思賓於同次筆錄證稱：「\n    （問：告訴人時尚女人跟你們申請貸款到底金額多少？）依\n    照文件上是170 萬元」等語（見本院卷第339 頁），另原告\n    於同次筆錄陳稱：「（問告訴人：該文件上為何會有你的簽\n    名，你當初申請貸款是否為170 萬元？）因為我已繳了一些\n    款項在被告那邊，雖然我貸的款項是200 萬，但我怕錢被被\n    告他們沒收，所以只核准170 萬元我只好同意」等語（見本\n    院卷第341 頁），可知，原告自始申請貸款金額為170 萬元\n    而非200 萬元。是本件原告顯係刻意誤導、扭曲或混淆其貸\n    款銀行渣打銀行已准予原告申請貸款170 萬元，而原告逾3\n    個月沒對保以致貸款銀行取消貸款之事實，進而影響法院之\n    公正判斷。尤其，原告亦在97年7 月14日用自身房屋向渣打\n    銀行申請380 萬元並如數核准撥款，原告竟逾期仍不履行給\n    付第6 期房地價金之義務，益徵原告自始既無誠意履行系爭\n    房地買賣契約。\n  3.且依兩造土地間預定買賣契約書第5 條、房屋預定買賣契約\n    書第18條皆明白約定「…倘因買方貸款條件不符合，致不能\n    核貸或無法如數貸足及買方中途改變主意自願不貸或未能如\n    期協辦或主動向核貸金融機構拒絕貸款者，視為放棄貸款，\n    則其原欲貸款部分之價款應於賣方通知後，7 日內以現金一\n    次向賣方繳清，否則即係違約。…」，而土地、房屋預定買\n    賣契約書皆有給予原告行使契約審閱期之機會，銷售人員亦\n    會作充分之說明，在在足證被告確無保證貸款7 成5 ，否則\n    買賣契約自無可能為如此之約定。按「…簽訂契約時倘雙方\n    已就廣告內容另為斟酌、約定，或企業經營者並未再據原屬\n    『要約引誘』之廣告為訂約之說明、洽談，使之成為具體之\n    『要約』，縱其廣告之內容不實，應受消費者保護法或公平\n    交易法之規範，自難逕謂該廣告為要約或已當然成為契約之\n    一部。」，此有最高法院92年台上字第2694號判決意旨可稽\n    。是縱如原告所言，售屋人員於銷售時有謂「保證一定可以\n    貸到房地價值總額7 成5 亦即200 萬元」云云，然系爭房地\n    預定買賣契約既無保證貸款7 成5 之約定，甚至於土地預定\n    買賣契約書第5 條、房屋預定買賣契約書第18條明白規定貸\n    款成數不足時，買方須負補足差額之責任，原告之訴顯然無\n    據，遑論被告公司自始否認有保證貸款7 成5 情事。\n  4.抑有進者，一般銀行貸款大致可分為房屋貸款、汽車貸款、\n    保單貸款、定存單貸款、信用貸款、公教貸款、小額信貸（\n    企業員工）等種類。然原告自始即知貸款成數最高為7 成5\n    「純銀貸」，且眾所皆知「銀行貸款」並非完全等同「房屋\n    抵押貸款」，原告自無陷於錯誤可言，縱使系爭房地核貸金\n    額僅為170 萬元，惟原告仍可依信貸等方式補足貸款差額。\n    今原告在起訴狀第4 頁第4 行中，亦聲稱原告曾以個人名義\n    向承辦系爭房地抵押貸款之銀行渣打銀行貸款30萬，在在足\n    徵原告自可貸足系爭房屋、土地第6 期價款，但其捨此不為\n    ，自可歸責於原告不履行契約給付義務。\n  (二)原告主張簽訂系爭契約時，未有合理審閱期限，且系爭定型\n    化契約條款違反誠實信用、平等互惠原則，原告可依消費者\n    保護法第11條之1 、第12條及其施行細則第14條、民法第24\n    7 之1 等規定，主張系爭土地契約第5 條、第10條及房屋契\n    約第18條及第23條（即貸款及違約條款）不構成契約之內容\n    ，再依民法第179 條請求返還不當得利云云，並無理由：\n  1.按「…按消費者保護法第11條之1 第1 、2 項規定係規範企\n    業經營者必須給予消費者合理之審閱期間，不可限制消費者\n    簽訂契約之期間。所謂契約審閱期間，乃使消費者在訂立契\n    約前有充裕時間瞭解契約之內容，然並非如原告在契約審閱\n    期間內縱使已瞭解契約內容並進而提前簽約，而事後仍得任\n    意反悔，以審閱期間未用盡為由主張不受契約之拘束。惟倘\n    企業經營者未限制消費者簽名及交回契約書之期間，應認企\n    業經營者已留予消費者合理之契約審閱期間，消費者非不得\n    於簽名前就契約書之內容詳加閱讀，如消費者卻不為此途，\n    而於未看清內容，完全瞭解契約內容前即於契約書上簽名，\n    自係權利之拋棄。又如消費者已有詳細審閱契約之機會，該\n    條之保護目的已達；……。是若消費者於簽約審閱契約條款\n    內容之期間，雖未達規定期間，惟企業經營者未有妨礙消費\n    者事先審閱契約之行為，消費者有充分了解契約條款之機會\n    ，且於充分了解後同意與企業經營者成立契約關係，基於其\n    他考量而選擇放棄審閱期間者，要僅係消費者自行放棄權利\n    ，法無禁止拋棄之明文，在現代私法自治及契約自由原則之\n    下，並無不可，亦不影響其簽名之效力，自不得引用上開消\n    費者保護法第11條之1 之規定主張所簽立之條款無效。再者\n    ，企業經營者為使消費者更易於掌握契約條款重要內容，而\n    於契約條款下要求消費者簽名以慎重其事，對於消費者並無\n    不利，更與消費者保護法立法旨趣無違。消費者事後自不得\n    以審閱契約條款內容之期間未達規定期間，主張契約條款不\n    構成契約之內容，且其行使權利顯然違反民法第148 條第2\n    項所定誠信原則，應認消費者為此主張無理由。」，臺灣臺\n    北地方法院96年度消字第18號判決可資參照。而行政院院消\n    費者保護委員會於89年1 月15日台89消保法字第00056 號函\n    亦同此意旨。\n  2.關於消保法第11條之1 規定定型化契約審閱期間之立法意旨\n    ，乃在保護消費者無法就契約內容與企業經營者為個別磋商\n    ，只能對企營經營者所提供之定型化契約條款予以附合，而\n    無討價還價之餘地而言。查被告在原告簽署系爭房地買賣契\n    約前，顯已提供2 種選擇方式，一為原告自得可依內政部公\n    告，在契約簽立前享有至少5 天以上之契約審閱權，並可攜\n    回契約影本審閱，另一則為原告已逐條審閱充分瞭解契約條\n    文，認無顯失公平之處，同意提早簽約並無疑義。今被告已\n    充分給予原告機會詳細瞭解系爭契約內容及行使審閱契約之\n    權益，嗣原告乃出於自由意志同意提早簽約，始在「審閱契\n    約權利書」簽章於其上，自得視為原告自行放棄審閱契約之\n    權利。是本件「審閱契約權利書」之內容乃出於雙方合意之\n    契約條款，應無對原告權利造成不利影響。尤且原告本身亦\n    擔任公司法務經理一職，具備高於一般消費者之法律知識及\n    能力，揆諸前開說明，本件顯無前揭條文之適用，原告自不\n    得事後反悔，再主張未享有合理審閱期間。\n  3.就系爭房屋、土地買賣契約書第18條及第5 條內容部分：\n  (1)查原告自始即負有給付價金予被告義務，今被告已協助原告\n    辦理抵押貸款170 萬元，亦無向原告保證貸足200 萬元，原\n    告倘能任意指摘被告負有補足貸款差額30萬元，則變向加重\n    被告之契約責任，且將原告不給付價金之不利益由被告承擔\n    ，不惟對被告難謂公平，更有違一般市場機制。\n  (2)揆諸系爭房屋預定買賣契約書附件11之「代辦申請貸款委託\n    書」（系爭土地預定買賣契約書附件2 亦同此意旨，），即\n    明確表示委託賣方以買方所購之房屋、車位及其土地持分等\n    代向賣方指定之金融機構申請抵押貸款；雙方間有關貸款事\n    宜，悉依「時尚女人香」房屋、土地買賣契約書第18條及第\n    5 條規定辦理等語，而附件內容僅短短數句，系爭契約條款\n    亦重覆數次，更經原告審閱後始簽章其上，自無為原告所不\n    及知或無磋商變更餘地可言。尤且「代辦申請貸款委託書」\n    已將系爭房屋、土地買賣契約書第18條及第5 條特別明文規\n    定，並迭經原告同意始簽章於其上，乃屬特別磋商合意條款\n    ，非等同一般定型化契約條款。是原告一再指摘系爭房屋、\n    土地買賣契約書第18條及第5 條不構成契約一部分，顯屬無\n    稽。\n  4.就系爭房屋、土地買賣契約第23條及第10條內容部分：查兩\n    造簽署系爭房屋買賣契約時，原告同意簽約並未表示任何異\n    議，且買賣雙方若發生違約情事時，均要賠償對方違約金20\n    ％，而內政部公告之「預售屋買賣定型化契約應記載及不得\n    記載事項」第24條關於違約之處罰，亦明白規定可沒收一定\n    百分比之違約金。故系爭房地買賣契約條款，並無原告所指\n    「免除或減輕預定契約條款之當事人之責任者。」、「加重\n    他方當事人之責任者」、「其他於他方當事人有重大不利益\n    者。」等情事。基上所述，原告指謫被告違反消保法第11條\n    之1、 第12條、民法第247 之1 等規定，再依民法第179 條\n    請求返還不當得利云云，洵屬無據。\n  (三)本件原告復主張被告等就交易上重要事項惡意隱匿、不實說\n    明，已該當民法第245 條之1 第1 項第1 款及第3 款事由云\n    云：\n  1.原告主張被告對於貸款額度可能會因系爭房地價值過低，導\n    致核貸金額不足之事，完全未曾提及，被告等惡意隱瞞，致\n    原告受有損害云云，惟查貸款銀行已如原告所願貸足170 萬\n    元，自無核貸金額不足之情事，而被告更無向原告保證貸款\n    成數7 成5 ，業如上述。尤其被告所提供之系爭房地自始既\n    無瑕疵存在，導致市場交易價值受到影響而下滑，更無給付\n    與對待給付間之價值顯不相當之情形，故原告指謫被告所供\n    買賣之物有瑕疵，損及原告受領系爭房地之價值云云，就此\n    有利於己之事實者，依民事訴訟法第277 條規定，原告自應\n    先負舉證真正之責任，否則空言主張，自不足為採。\n  2.又原告聲稱購買後查閱相關資料始知悉夾層屋之設計不法，\n    並經被告事後承認，此乃就交易上重要事項惡意隱匿、不實\n    說明云云。惟揆諸臺灣臺北地方法院檢察署檢察官98年度偵\n    字第18099 號不起訴處分書第3 頁及第4 頁可知，系爭房屋\n    樣品屋照片之隔層體部分係僅作為儲藏室等空間使用，樣品\n    屋落地窗旁之樓梯及置衣間隔層，則未與原結構體完全相連\n    ，顯與房屋原結構體之功能不同，且隔層體之面積顯小於樓\n    地板之3 分之1 ，足堪認定原告所供樣品屋照片僅表示系爭\n    房屋可作如樣品屋所示之「隔層」，自得在室內進行2 次施\n    工「隔層」，並不須申請建照執照。是原告誤將樣品屋合法\n    「隔層」認為「夾層」，而認被告有隱瞞違法「夾層」之事\n    實，顯與事實有重大違誤，是原告諉稱被告等違反民法第24\n    5 條之1 第1 項第1 款及第3 款事由云云，顯屬子虛，自不\n    足採。\n  (四)查原告於97年8 月20日所寄發之龜山迴龍郵局第50號存證信\n    所為解除契約之意思表示，顯已違反系民法第227 條、第22\n    9 條第2 項及第254 條之規定，是原告依民法第179 條規定\n    ，請求被告等返還已給付之價金共676,769 元云云，洵無理\n    由：\n  1.查原告民事起訴狀第14頁第5 點亦不否認被告若有協助貸款\n    之給付義務，亦屬「非定期限之給付」，是依民法第227 條\n    第1 項、第229 條第2 項、第254 條規定，原告為此主張自\n    應先定相當期限催告被告履行，被告始負遲延責任，倘被告\n    遲延仍未為給付，原告即應再定相當期限催告被告履行，逾\n    期仍未履行時，原告始得合法解除契約。\n  2.原告於97年8 月20日所寄龜山迴龍郵局第50號存證信函僅表\n    示「…今限貴號等於文到三日內依約提供足額房地貸款並為\n    所有權移轉登記，逾期本人即逕行解除本件買賣契約」云云\n    ，核與前揭規範，僅能認為原告係第1 次通知被告於確定期\n    限履行契約之存證信函，被告於送達後3 日內仍未履行，亦\n    僅生遲延責任之情事。惟查原告於遲延給付後，原告即未依\n    民法第254 條規定，為第2 次催告程序（即取得解除契約權\n    ），且原告亦未發存證信函表達系爭房地買賣契約已遭解除\n    （即解除契約之意思表示），故原告未踐行合法催告程序，\n    即逕行解除系爭房地買賣契約，自不生效力。\n  (五)被告得以97年8 月14日存證信函解除契約沒收原告之款項：\n  1.按「…倘因買方貸款條件不符合，致不能核貸或無法如數貸\n    足及買方中途改變主意自願不貸或未能如期協辦或主動向核\n    貸金融機構拒絕貸款者，視為放棄貸款…」、又「買方若不\n    辦貸款時，須按附件1 『房屋價款分期付款明細表』中可委\n    辦貸款抵繳之期款應於使用執照核發日起第30天應繳納之期\n    款於期限內繳納；並依賣方通知指定日期配合辦理產權移轉\n    相關手續；若逾期依本約第7 條第2 項加計規定遲延利息，\n    並經賣方以存證信函催告後5 日仍未繳者，依本約第23條之\n    約定處理，未付清前賣方得拒絕辦理產權登記於買方。」，\n    乃系爭房屋預定買賣契約書第18條第1 項、第3 項所明文約\n    定（土地預定買賣契約書第5 條第1 項、第3 項亦同此意旨\n    ）。\n  2.查原告已逾繳款期限多日，雖經被告催告繳納，原告仍置若\n    罔聞，被告迫於無奈，始於97年9 月16日寄發臺北興安郵局\n    第2142號存證信函存證信函予原告，明確催告原告應於函達\n    5 日內繳付已逾期限之核貸差額共計30萬元，否則沒入原告\n    已繳之全部款項，同時解除買賣合約之意思表示。縱原告一\n    再抗辯被告保證系爭房地可貸至房地價值總額7 成5 亦即20\n    0 萬元云云，惟原告自始申請貸款金額即為170 萬元，而承\n    貸銀行亦如數核准撥款，竟逾3 個月未對保而遭貸款銀行取\n    消該筆房貸，自是可歸責原告之事由所致，已詳如上述，是\n    原告自不得以上開理由抗辯。原告迄至97年9 月23日止仍未\n    繳納銀行核貸差額，被告始再以臺北興安郵局第2166號存證\n    信函通知解除契約及沒入買賣價金之停止條件已成就。揆諸\n    上開說明，系爭買賣契約既因原告違約逾期未繳納價款而解\n    除，其訴請返還買賣價金云云，自無理由。\n  (六)聲明：1.原告之訴及假執行之聲請均駁回。2.如受不利判決\n    ，被告願供擔保，請准宣告免為假執行。\n三、兩造不爭執之事項：\n  (一)原告先於96年5 月12日向被告瓏山公司與林鴻聯購買坐落新\n    北市○○區○○段第557 、558 、559 、560 、565 、56 6\n    、567 地號等7 筆土地上「時尚女人香」建案編號A15 棟11\n    樓房屋1 戶及其基地（下稱A15 棟11樓房地），並與被告瓏\n    山林公司簽訂房屋預定買賣契約書及與被告林鴻聯簽訂土地\n    預定買賣契約書。嗣於房屋建築完成後，因原告對於A15 棟\n    11樓房屋之格局不滿意，乃與被告等協議更換買賣標的為同\n    建案編號A10 棟9 樓系爭房地，並於97年3 月23日與被告瓏\n    山林公司簽訂系爭房屋買賣契約，及與被告林鴻聯簽訂系爭\n    土地買賣契約，約定系爭房地總價金為265 萬元（見本院卷\n    第238 頁正反面證人葉惠雯之證詞、第240 頁反面證人王寶\n    玉之證詞、第21至78頁系爭房屋及土地買賣契約影本各1 份\n    ）。\n  (二)原告已給付被告等自備款65萬元、代書費用36,700元及預繳\n    費用26,769元，共計713,469 元（見本院卷第91至93頁統一\n    發票影本2 紙、費用明細及代收款客戶簽認表暨收據影本各\n    1紙 ）。\n  (三)原告於97年8 月20日以龜山迴龍郵局第50號存證信函通知被\n    告於文到3 日內依約提供足額房地貸款並為所有權移轉登記\n    ，逾期原告即逕行解除本件買賣契約（見本院卷第97至100\n    頁上開存證信函）。\n  (四)被告於97年9 月16日以臺北興安郵局第2142號存證信函催告\n    原告應於函達5 日內繳付已逾期限之核貸差額共計30萬元，\n    否則沒入原告已繳之全部款項，同時解除買賣合約。原告至\n    97年9 月23日止未繳納銀行核貸差額30萬元，被告復以臺北\n    興安郵局第2166號存證信函通知原告解除契約及沒入買賣價\n    金676, 769元（見本院卷第160 至162 頁上開存證信函及回\n    執）。\n四、兩造爭執事項：\n  (一)原告主張被告未提供契約合理審閱期間，依消費者保護法第\n    11條之1 規定，系爭土地買賣契約第5 條、第10條及系爭房\n    屋買賣契約第18條及第23條之約定為定型化契約條款，不構\n    成契約之一部，原告得依民法第179 條、第182 條規定請求\n    被告返還沒收款項之不當得利及利息，有無理由？如有理由\n    ，被告應返回之金額為若干？\n  (二)原告主張以龜山迴籠郵局第50號存證信函解除系爭房屋及土\n    地買賣契約，並依民法第179 條、第182 條規定請求被告返\n    還不當得利，另依民法第259 條規定請求回復原狀，有無理\n    由？如有理由，被告應返回之金額為若干？\n  1.原告主張系爭房地抵押貸款金額因房地價值過低，致銀行僅\n    願核貸170 萬元，與原先預定之貸款200 萬元有30萬元之差\n    額，經原告寄發存證信函催告被告協助貸款後，被告未理會\n    ，原告依「預售屋買賣定型化契約應記載及不得記載事項」\n    第18點第2 項第2 款及民法第359 條之規定於97年8 月23日\n    解除契約，有無理由？\n  2.原告主張被告未依照契約義務協助貸得200 萬元貸款，為民\n    法第227 條不完全給付，原告定相當期間命被告協助貸款，\n    被告逾期仍不履行，原告得解除契約，有無理由？\n  (三)原告主張系爭土地買賣契約第5 條及第10條、房屋買賣契約\n    第18條及第23條，縱為契約之一部亦因對契約之他方顯失公\n    平，違反消費者保護法第12條、民法247 條之1 、預售屋買\n    賣定型化契約應記載事項及不得記載事項第24條第2 項而無\n    效，並依民法第179 條、第182 條規定請求被告返還不當得\n    利，有無理由？如有理由，被告應返回之金額為若干？\n  (四)原告主張被告就系爭房地因價值過低導致核貸金額不足，及\n    夾層屋之設計係屬不法等重要事項惡意隱瞞，違反誠實及信\n    用方法，致原告受有損害，依民法第245 之1 條第1 項第1\n    款、第3 款規定應負損害賠償責任，有無理由？如有理由，\n    被告應賠償之金額為若干？\n五、本院之判斷：\n  (一)原告主張被告未提供契約合理審閱期間，依消費者保護法第\n    11條之1 規定，系爭土地買賣契約第5 條、第10條及系爭房\n    屋買賣契約第18條及第23條之約定為定型化契約條款，不構\n    成契約之一部，原告得依民法第179 條、第182 條規定請求\n    被告返還沒收款項之不當得利及利息，有無理由？如有理由\n    ，被告應返回之金額為若干？\n  1.按「企業經營者與消費者訂立定型化契約前，應有30日以內\n    之合理期間，供消費者審閱全部條款內容。違反前規定者，\n    該條款不構成契約之內容。但消費者得主張該條款仍構成契\n    約之內容。」，消費者保護法施行細則第11條第1 項、第2\n    項定有明文。該條之目的在給予消費者充分瞭解契約內容之\n    機會，並規範企業經營者不得在未給予消費者審閱契約內容\n    之機會前，限制消費者簽訂契約之時間，以避免消費者於匆\n    忙間不及瞭解其依契約所得主張之權利及應負擔之義務，致\n    訂立顯失公平之契約而受有損害，故只須消費者於簽約前已\n    充分瞭解該契約之權利義務關係，或有可認其能認識契約權\n    利義務關係之合理審閱期間，即不得引用上開規定而主張契\n    約無效。是以企業經營者如未限制消費者必須於何時簽名，\n    何時將契約書交回，應認企業經營者已留予消費者合理之契\n    約審閱期間，即便消費者未看清該契約之內容，即於契約書\n    上簽名並交回契約書，然消費者非不得於簽名前就契約書之\n    內容，詳加閱讀。其不為此之圖，卻於完全瞭解契約內容前\n    即於契約書上簽名，係對自身權利之拋棄，尚非法所不許，\n    亦不影響其簽名之效力。\n  2.原告主張簽訂系爭房地買賣契約時，被告未提供合理審閱期\n    限，且簽約當日因被告之銷售員一再強力推銷並要求立刻簽\n    訂契約，原告迫於無奈，僅得簽名蓋章。依消費者保護法第\n    11條之1 規定，原告主張系爭土地買賣契約第5 條及第10條\n    ，系爭房屋買賣契約第18條及第23條（即貸款及違約條款）\n    ，對於原告規範之內容不公平，應不構成契約內容之一部。\n    則被告依據上開約定沒收原告所繳款項676,769 元，即無法\n    律上原因，原告得依民法第179 條及第182 條，請求被告等\n    返還不當利益等語。被告則抗辯已充分給予原告機會詳細瞭\n    解系爭契約內容及行使審閱契約之權益，原告係出於自由意\n    志同意提早簽約，始在「審閱契約權利書」簽章於其上，自\n    得視為原告自行放棄審閱契約之權利。本件「審閱契約權利\n    書」之內容乃出於雙方合意之契約條款，應無對原告權利造\n    成不利影響。且原告擔任公司法務經理一職，具備高於一般\n    消費者之法律知識及能力，本件顯無前揭條文之適用，原告\n    自不得事後反悔，再主張未享有合理審閱期間等語。\n  2.查本件原告先於96年5 月12日向被告瓏山公司與林鴻聯購買\n    A15 棟11樓房地，並與被告瓏山林公司簽訂房屋預定買賣契\n    約書及與被告林鴻聯簽訂土地預定買賣契約書。嗣於房屋建\n    築完成後，因原告對於A15 棟11樓房屋之格局不滿意，乃與\n    被告等協議更換買賣標的為同建案編號A10 棟9 樓系爭房地\n    ，並於97年3 月23日與被告瓏山林公司簽訂系爭房屋買賣契\n    約，及與被告林鴻聯簽訂系爭土地買賣契約，約定系爭房地\n    總價金為265 萬元之事實，為兩造所不爭執，復經證人葉惠\n    雯、王寶玉證述在卷，並有系爭房屋及土地買賣契約影本各\n    1 份在卷可稽（見本院卷第238 頁正反面、第240 頁反面、\n    第21至78頁），堪以信實。又兩造間於96年5 月12日就A15\n    棟11樓房地所簽訂之房屋預定買賣契約書，與兩造於97 年3\n    月23日就A10 棟9 樓系爭房地所簽訂之系爭房屋及土地買賣\n    契約之內容均相同，僅買賣標的不同，此為兩造所不爭執，\n    是原告自96年5 月12日與被告簽訂A15 棟11樓房地契約後至\n    97年3 月23日與被告簽訂A10 棟9 樓系爭房地契約時，原告\n    已有10個月以上之期間足以充分審閱相同內容之系爭房地買\n    賣契約，而此其間已超過消費者保護法第11條之1 所規定之\n    30日審閱期間，是即便原告未看清該契約之內容，即於契約\n    書上簽名並交回契約書，然原告非不得於系爭房地買賣契約\n    簽名前就契約書之內容，詳加閱讀。其不為此之圖，卻於完\n    全瞭解契約內容前即於契約書上簽名，係對自身權利之拋棄\n    ，尚非法所不許，亦不影響其簽名之效力。再者，本件並無\n    證據證明被告有限制原告必須於何時簽名，何時將契約書交\n    回，應認被告已留予原告合理之契約審閱期間，是原告非不\n    得於簽名前就契約書之內容，詳加閱讀。則原告既仍願與被\n    告簽訂系爭買賣契約，自不能再以被告未提供合理審閱期間\n    為由，主張系爭土地買賣契約第5 條及第10條與系爭房屋買\n    賣契約第18條及第23條，不構成契約內容之一部。\n  3.從而，原告主張被告未提供契約合理審閱期間，系爭土地買\n    賣契約第5 條、第10條及系爭房屋買賣契約第18條、第23條\n    之約定為定型化契約條款，不構成契約之一部，被告依該等\n    約定沒收原告繳納之款項，即無法律上原因，原告得依民法\n    第179 條、第182 條請求被告返還不當得利及利息云云，即\n    屬無據，而不足採。\n  (二)原告主張以龜山迴籠郵局第50號存證信函解除系爭房屋及土\n    地買賣契約，並依民法第179 條、第182 條規定請求被告返\n    還不當得利，有無理由？如有理由，被告應返回之金額為若\n    干？\n  1.原告主張系爭房地抵押貸款金額因房地價值過低，致銀行僅\n    願核貸170 萬元，與原先預定之貸款200 萬元有30萬元之差\n    額，經原告寄發存證信函催告被告協助貸款後，被告未理會\n    ，原告依「預售屋買賣定型化契約應記載及不得記載事項」\n    第18點第2 項第2 款及民法第359 條之規定於97年8 月23\n    日解除契約等語，為被告所否認。經查：\n  (1)按「預售屋買賣定型化契約應記載及不得記載事項」第18點\n    第2 款第2 目規定：前款由賣方洽定辦理之貸款金額少於預\n    定貸款金額，其差額於可歸責於賣方時，差額部分，賣方應\n    依原承諾貸款相同年限及條件由買方分期清償。如賣方不能\n    補足不足額部分，買方有權解除契約。又按買賣因物有瑕疵\n    ，而出賣人依前五條之規定，應負擔保之責者，買受人得解\n    除其契約或請求減少其價金。但依情形，解除契約顯失公平\n    者，買受人僅得請求減少價金，民法第359 條亦有明文。\n  (2)查為導正預售屋買賣契約書之內容，使其符合誠實信用及平\n    等互惠原則，促進公平交易，確保消費者權益，內政部依消\n    費者保護法第17條第1 項規定，於90年9 月3 日公布「預售\n    屋買賣定型化契約應記載及不得記載事項」，其後曾於98年\n    8 月10日、98年10月30日、99年8 月16日及100 年3 月24日\n    作微幅修正。而本件系爭房地買賣，係於房屋建築完成後，\n    原告至現場看屋，因對原本購買之A15 棟11樓預售房屋結構\n    不滿意，而與被告協議換屋，故兩造再於97年3 月23日就A1\n    0 棟9 樓系爭房地簽定系爭買賣契約，則系爭房地買賣契約\n    雖名為房屋、土地「預定買賣契約書」，惟係於系爭房屋建\n    築完成後，經兩造確認買賣之標的為A10 棟9 樓房地所締結\n    之契約，斯時買賣標的A10 棟9 樓房屋已經存在，與預售屋\n    買賣契約訂立時買賣標的尚未存在之性質不同，是系爭房地\n    買賣契約其性質應非屬預售屋買賣，而應屬一般之成屋買賣\n    ，是兩造間系爭房地買賣契約關係，應無「預售屋買賣定型\n    化契約應記載事項及不得記載事項」之適用。是原告主張依\n    「預售屋買賣定型化契約應記載及不得記載事項」第18點第\n    2 款第2 目規定，其有權解除契約云云，尚無足採。\n  (3)次查，經本院依職權函詢渣打銀行關於原告以系爭房地申辦\n    貸款之情形，該銀行以100 年2 月25日渣打商銀SCBCL 字第\n    1001002655號函回覆表示：原告於97年3 月間購買系爭房地\n    後，自行向該銀行申辦貸款，當時核定原告得貸款之金額為\n    170 萬元，但因批示決核後逾3 個月原告未申請撥款，故該\n    行予以駁回等語，有上開函文暨貸款資料1 份附卷可稽（見\n    本院卷第308 至316 頁）。又參以訴外人即渣打銀行貸款承\n    辦人李汪恩於臺灣臺北地方法院檢察署98年度他字第589 號\n    詐欺案98年7 月3 日下午2 時13分詢問筆錄證稱：「（問：\n    高總共跟你們貸款幾次？所貸金額多少？核准金額多少？）\n    第一次是97年3 月28日來申辦信用貸款30萬，皆如數核准貸\n    款。第二次是97年5 月9 日申請房貸170 萬，於5 月13日核\n    准，但至8 月21日因告訴人（即本件原告，下同）未對保，\n    公司規定超過3 個月未對保所以取消該筆房貸。後來告訴人\n    在同一天97年8 月21日又以相同抵押物（時尚女人香的房屋\n    ）再次申請170 萬元貸款，核准日期是97年8 月27日，但這\n    次一樣是超過三個月沒對保以致其貸款被取消。在97年7 月\n    14日還有一次是以高自己的房屋（桃園縣龜山鄉○○路○段\n    122 號之5 號7 樓）來申請貸款380 萬元並如數核准撥款。\n    」等語（見本院卷第338 頁）；及訴外人即渣打銀行貸款部\n    主管李思賓於同次筆錄證稱：「依文件來看是告訴人2 次均\n    親自遞件以時尚女人香來申請貸款170 萬，我們綜合申請人\n    的收入、抵押品及信用狀況來評估准許貸款之金額，告訴人\n    2 次所貸的170 萬元都如數核准，只是因為超過3 個月未對\n    保故予取消。... （是否該約300 戶的貸款是由你們承辦？\n    ）是。一般來說確實可以貸到房價的7 到85成。... （告訴\n    人剛才有說他97年3 月2 日有一筆信貸30萬元，是否影響到\n    他後來申請200 萬卻貸得170 萬的房貸？）是。」等語（見\n    本院卷第339 至342 頁）；另原告於同次筆錄陳稱：「（問\n    告訴人：該文件上為何會有你的簽名，你當初申請貸款是否\n    為170 萬元？）因為我已繳了一些款項在被告那邊，雖然我\n    貸的款項是200 萬，但我怕錢被被告他們沒收，所以只核准\n    170 萬元我只好同意」等語（見本院卷第341 頁）。由上足\n    徵，原告係自行遞件以系爭房地向渣打銀行申請貸款170 萬\n    元，並非由被告洽定辦理貸款，且因原告於97年3 月2 日已\n    有申請一筆信用貸款30萬元，致影響到渣打銀行評估本件核\n    貸之金額為170 萬，況且依李思賓之上開證詞，本件時尚女\n    人香建案約300 戶的貸款均由渣打銀行承辦，一般來說確實\n    可以貸到房地價格的7 到85成之金額，並無因房地價格過低\n    ，而無法貸足房地價格7 到85成金額之情形。從而，原告主\n    張系爭房地抵押貸款金額因房地價值過低，致銀行僅願核貸\n    170 萬元，與原先預定之貸款200 萬元有30萬元之差額云云\n    ，即屬無據，不足採信。另原告主張依民法第359 條之規定\n    解除系爭房地買賣契約，惟始終未舉證證明系爭房地有何瑕\n    疵存在，則其此部分主張，亦乏依據，而無足取。\n  2.原告主張被告未依照契約義務協助貸得200 萬元貸款，為民\n    法第227 條不完全給付，原告定相當期間命被告協助貸款，\n    被告逾期仍不履行，原告得解除契約，有無理由？\n    查本件係原告自行遞件以系爭房地向渣打銀行申請貸款170\n    萬元，並非由被告洽定辦理貸款，且因原告於97年3 月2 日\n    已有申請一筆信用貸款30萬元，致影響到渣打銀行評估本件\n    核貸之金額為170 萬，又依李思賓之上開證詞，本件時尚女\n    人香建案約300 戶的貸款均由渣打銀行承辦，一般來說確實\n    可以貸到房價的7 到85成之金額等情，俱如前述，是原告就\n    系爭房地未能貸得其預期之貸款200 萬元，顯係可歸責於其\n    自身之事由所致，則原告主張被告未依照契約義務協助貸得\n    200 萬元貸款，有民法第227 條不完全給付情形，原告得定\n    相當期間命被告協助貸款，被告逾期仍不履行，原告得解除\n    契約云云，即屬無據。\n  3.從而，原告主張以龜山迴籠郵局第50號存證信函解除系爭房\n    屋及土地買賣契約，並依民法第179 條、第182 條規定請求\n    被告返還不當得利，即無理由，不應准許。\n  (三)原告主張系爭土地買賣契約第5 條及第10條、房屋買賣契約\n    第18條及第23條，縱為契約之一部亦因對契約之他方顯失公\n    平，違反消費者保護法第12條、民法247 條之1 、預售屋買\n    賣定型化契約應記載事項及不得記載事項第24條第4 項而無\n    效，並依民法第179 條、第182 條規定請求被告返還不當得\n    利，有無理由？如有理由，被告應返回之金額為若干？\n  1.按消費者保護法第12條規定：定型化契約中之條款違反誠信\n    原則，對消費者顯失公平者，無效。定型化契約中之條款有\n    下列情形之一者，推定其顯失公平：一、違反平等互惠原則\n    者。二、條款與其所排除不予適用之任意規定之立法意旨顯\n    相矛盾者。三、契約之主要權利或義務，因受條款之限制，\n    致契約之目的難以達成者。又消費者保護法施行細則第14條\n    規定：定型化契約條款，有下列情事之一者，為違反平等互\n    惠原則：一、當事人間之給付與對待給付顯不相當者。二、\n    消費者應負擔非其所能控制之危險者。三、消費者違約時，\n    應負擔顯不相當之賠償責任者。四、其他顯有不利於消費者\n    之情形者。再民法第247 條之1 規定：依照當事人一方預定\n    用於同類契約之條款而訂定之契約，為左列各款之約定，按\n    其情形顯失公平者，該部分約定無效：一、免除或減輕預定\n    契約條款之當事人之責任者。二、加重他方當事人之責任者\n    。三、使他方當事人拋棄權利或限制其行使權利者。四、其\n    他於他方當事人有重大不利益者。又預售屋買賣定型化契約\n    應記載事項及不得記載事項第24條第4 項規定：買方違反有\n    關「付款條件及方式」之規定者，賣方得沒收依房地總價款\n    百分之＿（最高不得超過百分之十五）計算之金額。但該沒\n    收之金額超過已繳價款者，則以已繳價款為限，買賣雙方並\n    得解除本契約。\n  2.原告主張系爭房屋買賣契約第18條、第23條、土地買賣契約\n    第5 條及第10條之規定與綜合契約內其他條款約定，若因買\n    方貸款條件不符合，需沒收高達房屋總價百分之20之違約金\n    ，相較之下，被告雖負有義務協助辦理抵押貸款，但若因被\n    告之原因致貸款不足額時，卻未有罰則或任何處理方法，買\n    賣雙方所負之義務顯不相當，明顯使原告負有不相當之義務\n    ，故系爭房地契約定型化契約之貸款及違約條款與平等互惠\n    原則即有不合，依消費者保護法第12條、消費者保護法施行\n    細則第14條規定，契約條款違反誠信原則，對消費者顯失公\n    平者，無效；且按「預售屋買賣定型化契約應記載事項及不\n    得記載事項」第24條第2 款是以消費者違約時，企業經營者\n    固得沒收一定比例之買賣價金，然其比例上限不得超過房地\n    價值百分之15。被告於契約內約定違約時沒收總價金百分20\n    ，核與內政部公告之定型化契約範本上限為百分之15不符，\n    超出部份應屬無效；況被告實際沒收金額為原告全額已繳價\n    金及非屬買賣價金之預繳款項共676,769 元，比例已高達總\n    價金百分之25，明顯違反「預售屋買賣定型化契約應記載事\n    項及不得記載事項」第24條第2 款之規定，係屬違法等語，\n    為被告所否認。\n  3.查系爭房屋買賣契約第18條第1 項及土地買賣契約第5 條第\n    1 項均約定：倘因買方貸款條件不符合致不能核貸或無法如\n    數貸足，則其原欲貸款部份之價款應於賣方通知後七日內以\n    現金一次補足，否則即係違約（見本院卷第27頁、第74 頁\n    反面）。觀此內容，乃係因可歸責於買方之事由致不能核貸\n    或無法如數貸足，而約定買方應補足貸款差額之約定，並無\n    消費者保護法第12條及民法第247 條之1 所規定違反誠信原\n    則、顯失公平等情形，自非無效之約定。又系爭房屋買賣契\n    約第23條第2 項及土地買賣契約第10條第2 項約定：買方違\n    反房屋買賣契約第7 條、第15條第3 項及第18條約定，或違\n    反土地買賣契約第4 條之約定，買方得沒收依房地總價款百\n    分之20計算之金額；而系爭房屋買賣契約於第23條第1 項及\n    土地買賣契約第10條第1 項亦約定：賣方違反房屋買賣契約\n    第11條、第12條第2 項及第21條之約定者，或賣方違反土地\n    賣賣契約第8 條之約定者，買方均得解除契約，賣方除應將\n    買方已繳之房地價款及遲延利息全部退還賣方外，並應同時\n    賠償房地總價款百分之20之違約金（見本院卷第28、76 頁\n    ）。足徵系爭房屋買賣契約第23條及土地買賣契約第10 條\n    有關違約處罰之約定，對於可歸責於買賣雙方之違約罰則均\n    有約定，且賠償之比例均以房地總價款百分之20計算，是該\n    等約定即無原告所主張買賣雙方所負之義務顯不相當，明顯\n    使原告負有不相當之義務之情形，應無消費者保護法第12條\n    及民法第247 條之1 所規定違反誠信原則、顯失公平等情形\n    ，自非無效之約定。再者，「預售屋買賣定型化契約應記載\n    事項及不得記載事項」第24條第2 款所定賣方得沒收依房地\n    總價款最高不得超過百分之15計算之金額之規定，乃係針對\n    預售屋買賣而為之規定。而系爭房地買賣契約其性質非屬預\n    售屋買賣，而應屬一般之成屋買賣，兩造間系爭房地買賣契\n    約關係，並無「預售屋買賣定型化契約應記載事項及不得記\n    載事項」之適用，有如前述，則原告主張被告沒收金額為原\n    告全額已繳價金及非屬買賣價金之預繳款項共676,769 元，\n    比例已高達總價金百分之25，明顯違反「預售屋買賣定型化\n    契約應記載事項及不得記載事項」第24條第2 款之規定云云\n    ，即屬無據。又系爭房屋買賣契約第23條第2 項及土地買賣\n    契約第10條第2 項約定沒收買方房地總價百分之20之比例，\n    並非顯然過高，故無消費者保護法第12條及民法第247 條之\n    1 所規定違反誠信原則、顯失公平等情形，自非無效之約定\n    。是被告依據系爭契約上開約定解除契約，沒收原告已繳之\n    價金，即非無法律上之原因，並無不當得利之情形。\n  4.從而，原告主張系爭土地買賣契約第5 條及第10條、房屋買\n    賣契約第18條及第23條，縱為契約之一部亦因對契約之他方\n    顯失公平，違反消費者保護法第12條、民法247 條之1 、預\n    售屋買賣定型化契約應記載事項及不得記載事項第24條第4\n    項而無效，並依民法第179 條、第182 條規定請求被告返還\n    不當得利，為無理由，不應准許。\n  (四)原告主張被告就系爭房地因價值過低導致核貸金額不足，及\n    夾層屋之設計係屬不法等重要事項惡意隱瞞，違反誠實及信\n    用方法，致原告受有損害，依民法第245 之1 條第1 項第1\n    款、第3 款規定應負損害賠償責任，有無理由？如有理由，\n    被告應賠償之金額為若干？\n  1.按民法第245條之1第1項第1 款、第3 款規定：契約未成立\n    時，當事人為準備或商議訂立契約而有左列情形之一者，對\n    於非因過失而信契約能成立致受損害之他方當事人，負賠償\n    責任：一、就訂約有重要關係之事項，對他方之詢問，惡意\n    隱匿或為不實之說明者。... 三、其他顯然違反誠實及信用\n    方法者。\n  2.原告主張於訂立系爭契約時，被告之銷售人員表示一定可以\n    貸至200 萬元，對於貸款額度可能會因系爭房地價值過低，\n    導致核貸金額不足之事，完全未曾提及，是故就此重要事項\n    為惡意隱瞞，已該當民法第245 之1 條第1 項第1 款之事由\n    ，被告等惡意隱瞞，亦違反誠實及信用方法，致原告受有損\n    害；又被告之銷售人員於看屋一再表示該樣品屋內可做夾層\n    之設計，並提供夾層之樣品屋，使原告誤信購買系爭房屋後\n    ，可為夾層屋之設計而為之購買，詎購買後查閱相關資料始\n    知悉夾層屋之設計係屬不法，此乃就交易上重要事項惡意隱\n    匿、不實說明，已該當民法第245 條之1 第1 項第1 款及第\n    3 款事由，應對原告負賠償之責等語，並聲請傳喚證人楊鴻\n    彬及提出廣告單影本4 紙為證（見本院卷第79至82頁），惟\n    此為被告所否認。\n  3.查本件因原告於97年3 月2 日已有申請一筆信用貸款30萬元\n    ，致影響到渣打銀行評估本件核貸之金額為170 萬，又依李\n    思賓之上開證詞，本件時尚女人香建案約300 戶的貸款均由\n    渣打銀行承辦，一般來說確實可以貸到房價的7 到85成之金\n    額等情，有如前述，是本件貸款金額未達原告預期之200 萬\n    元即房地總價款之75成，乃歸因於原告本身之因素所致。則\n    原告主張訂立系爭契約時，被告之銷售人員表示一定可以貸\n    至200 萬元，惡意隱瞞貸款額度可能會因系爭房地價值過低\n    ，導致核貸金額不足之事，亦違反誠實及信用方法，該當民\n    法第245 之1 條第1 項第1 款及第3 款之事由，應負賠償責\n    任云云，並無足採。\n  4.次查，證人楊鴻彬於本院言詞辯論時證稱：伊與原告去看建\n    案時尚女人香樣品屋，挑高大概7 米多，有點像樓中樓形式\n    的套房，直走有個小樓梯可以上去，樓梯的旁邊有餐廳及客\n    廳，樓上是個小房間，可以在上面睡覺，小房間下面是客廳\n    及餐廳。... 業務員說可以做兩個樣子，一個是像樣品屋這\n    樣挑高的，一個是一般沒有挑高的，建商會幫我們做好，但\n    是房屋的總價是一樣的等語（見本院卷第239 頁反面），固\n    足認定被告展示之樣品屋係作夾層之裝潢設計。惟觀諸原告\n    所提出之廣告單，並無隻字片語提及「夾層屋」係屬合法建\n    物之內容，原告復未提出證據證明被告之銷售人員曾表示夾\n    層屋係合法，而原告及證人所參觀之樣品屋以夾層之裝潢予\n    以展現，屬空間利用方法之參考展示，僅供購買者作其房屋\n    裝潢設計之參考，尚難認樣品屋以夾層之裝潢展示，即遽認\n    被告有將夾層屋之設計係屬不法等重要事項惡意隱瞞，違反\n    誠實及信用方法之情形。則原告主張被告惡意隱瞞夾層屋之\n    設計係屬不法等重要事項，違反誠實及信用方法，致原告受\n    有損害，依民法第245 之1 條第1 項第1 款、第3 款規定應\n    負損害賠償責任云云，並無可採。\n六、綜上所述，原告主張依民法第179 條、第182 條、第245 之\n    1 條第1 項第1 款、第3 款之規定，請求：(一)被告應給付原\n    告276,796元，及自97年8 月24日起至清償日止，按週年利\n    率百分之5 計算之利息。(二)被告林鴻聯應給付原告40萬元，\n    及自97年8 月24日起至清償日止，按週年利率百分之5 計算\n    之利息，均無理由，應予駁回。又原告之訴既經駁回，其假\n    行之聲請亦失所附麗，併予駁回。\n七、本件事證已臻明確，兩造其餘攻擊防禦方法及未經援用之證\n    據，經審酌後，核與判決結果不生影響，爰不一一論述。\n八、據上論結，本件原告之訴為無理由，依民事訴訟法第79條，\n    判決如主文。"
  },
  "search": "臺灣板橋地方法院民事判決99年度訴字第1152號原告高鴻鵬訴訟代理人劉韋廷律師複代理人林財生律師被告瓏山林企業股份有限公司兼法定代理人林鴻堯上二人共同訴訟代理人劉宏邈律師上列當事人間請求返還買賣價金事件，經本院於民國100年4月20日言詞辯論終結，判決如下：主文原告之訴及假執行之聲請均駁回。訴訟費用由原告負擔。事實及理由一、原告主張：(一)原告於民國97年3月23日向被告瓏山林企業股份有限公司（下稱瓏山林公司）與林鴻聯購買坐落新北市○○區○○段第557、558、559、560、565、566、567地號等7筆土地上「時尚女人香」建案編號A10棟9樓房屋1戶及其基地（下稱系爭房地），並與被告瓏山林企業股份有限公司（下稱瓏山林公司）簽訂房屋預定買賣契約書（下稱系爭房屋買賣契約），與被告林鴻聯簽訂土地預定買賣契約書（下稱系爭土地買賣契約），約定系爭房地總價金為新臺幣（下同）265萬元。依系爭土地買賣契約第11條、系爭房屋買賣契約第26條約定，此兩契約及其附件為不可分割之給付，具有連帶及不可分之關係。被告瓏山林公司於售屋廣告上標明貸款成數為8成5純銀貸，然其後被告瓏山林公司因貸款成數與廣告不符造成眾多消費者糾紛，經平面媒體、消保官及公平交易委員會等認定有違反消費者保護法及平交易法之嫌。是故被告要求降低貸款成數為7成5，即200萬元為貸款，自備款為65萬元，原告本有疑慮，但被告之銷售人員一再保證系爭房地價值很高，一定可以貸到房地價值總額7成5亦即200萬元，原告受其蠱惑，且被告未給予原告契約審閱期間，於簽約當日直接要求原告簽訂買賣契約，原告因此陸續給付自備款65萬元、代書費用36,700元及預繳費用26,769元，共計713,469元。原告與被告等簽訂之系爭房地買賣契約約定，委託被告等向銀行申請以系爭房地抵押貸款，其內容略為「土地/房屋總價內之部分價款（即契約附件1：房屋價款分期付款明細表中可委辦貸款抵繳之期款總額），由買方與賣方洽訂之金融機構之貸款給付，最長期限為20年，以買賣雙方簽立「代辦申請貸款委託書」（即契約附件11）依約定辦妥一切貸款手續」。是被告等負有義務依系爭房地買賣契約內附件，依照約定貸款成數7成5，辦妥一切貸款手續，其委託貸款金額為房屋76萬元、土地124萬元，共200萬元。詎料，配合被告系爭建案貸款業務之渣打銀行，通知原告鑑價結果，系爭房地價值過低，僅有每坪17至18萬元，故核貸金額僅為170萬元，原告遂反映上情於被告。惟被告之客服人員態度極差，以「自己去找別家銀行問呀！」「如果你有錢就不必害怕貸不到了！」等惡言相向，拒絕處理。被告甚至於97年8月14日寄發存證信函，要求於5日內繳付貸款差額，否則依約沒入原告全部已繳款項，原告則於97年8月20日寄發存證信函告知被告違約，並以涉及詐欺等罪責，請求其依照契約協助辦理足額貸款，否則於函到後3日解除契約，然被告卻置若罔聞，更在97年9月23日發函解除契約，並沒入原告已繳之土地買賣自備款40萬元、房屋買賣自備款25萬元及預繳費用26,769元共計676,769元。被告等妄稱因原告貸款條件不符以致無法如數貸足。然原告曾以個人名義向承辦系爭房地抵押貸款之渣打銀行申請貸款30萬元，獲銀行全額核貸，足證原告個人貸款條件良好，非如被告所稱貸款條件不符。被告身為知名企業，為經濟上之強者，為其商譽應依誠實信用原則為交易，然被告卻以廣告訛騙消費者，再以定型化契約內容規避責任，並曲解契約條款內容，藉此沒收消費者所繳之款項，此有消保會申訴調解記錄可證，其中所列之訴消費者共19人，皆因系爭房地價值過低導致核貸不足，與被告產生糾紛而向消保官申訴，足見被告以此方法預謀設陷，坑害消費者，且本案經媒體大幅報導，足證被告確有前開事證。(二)原告主張系爭房地買賣契約內之定型化契約條款不構成契約之一部，依民法第179條、第182條請求被告返還不當得利：1.系爭房屋買賣契約之賣方為被告瓏山林公司，系爭土地買賣契約之賣方為被告林鴻聯，瓏山林公司為消費者保護法第2條第2款之企業經營者當無疑義，應適用消費者保護法之各項規定。2.系爭土地買賣契約與房屋買賣契約為同日簽訂，且契約內已約定兩者為連帶不可分之關係，與當事人之意思，具有不可分割之依存關係，依臺灣高等法院88年度上字第304號判決意旨，系爭房屋買賣契約具有無效或解除之事由，系爭土地買賣契約亦應該當此事由。3.原告簽訂系爭房地買賣契約時，未有合理審閱期限，且簽約當日，因被告之銷售員一再強力推銷並要求立刻簽訂契約，原告迫於無奈，僅得簽名蓋章。按最高法院98年度台上字第168號判決意旨，倘企業經營者於定型化契約上加註消費者拋棄審閱期間之條款，為顯失公平，仍為無效，應由企業經營者證明已給予合理審閱期間，倘未能舉證已給予消費者合理審閱期間，定型化契約條款不構成契約內容之一部。被告雖表示原告選擇拋棄合理審期之約款，未強迫原告云云，然被告於定型化契約要求原告簽名放棄合理審閱期間，該拋棄審閱期間之條款按前開判決見解，為顯失公平應為無效。且事實上被告確未提供合理審閱期間，定型化契約條款應不構成契約之內容，依消費者保護法第11條之1規定，原告主張系爭土地買賣契約第5條及第10條，系爭房屋買賣契約第18條及第23條（即貸款及違約條款），對於原告規範之內容不公平，應不構成契約內容之一部。則被告依據系爭土地買賣契約第5條及第10條，系爭房屋買賣契約第18條及第23條沒收原告所繳款項676,769元，即無法律上原因，原告爰依民法第179條及第182條，請求被告等返還不當利益676,769元，及自解除契約時起，按年息百分之5計算之利息。(三)原告依「預售屋買賣定型化契約應記載及不得記載事項」第17點第2款第2目、民法第359條之規定解除契約，並依民法第179條不當得利請求返還自備款及預繳款項共676,769元：1.依據內政部於90年9月3日公告之「預售屋買賣定型化契約應記載及不得記載事項」中第18點第2項第2款（原告綜合言辭辯論意旨狀誤載為第17點第2款第2目）及消費者保護法第17條、消費者保護法施行細則第15條規定，買方解除契約後，得依民法第179條請求賣方返還已給付之價金及預付款項。2.原告與被告等所簽訂之系爭契約，就貸款條件約定僅有第18條：「倘因買方貸款條件不符合致不能核貸或無法如數貸足，則其原欲貸款部份之價款應於賣方通知後七日內以現金一次補足，否則即系違約。」然依照「預售屋買賣定型化契約應記載及不得記載事項」第18點第2項第2款：「由賣方洽定辦理之貸款金額少於預訂貸款金額，若可歸責於賣方時，如賣方不能補足不足額部分，買方有權解除契約。」是依消費者保護法施行細則第15條及「預售屋買賣定型化契約應記載及不得記載事項」第18點仍構成契約之內容，系爭房地之抵押貸款，因被告販售房地之價值過低，導致銀行僅願核貸170萬元，與原先預定之200萬元有30萬元之差額，故貸款金額少於預定貸款金額系可歸責於被告，且原告在同一時間以相同經濟能力為條件向承辦系爭房地抵押貸款之銀行即渣打銀行申請貸款30萬元，獲銀行全額核貸，足證系爭房地抵押貸款核貸金額不足30萬元，係因為被告之房地價值過低所致，非因原告個人貸款條件不符，原告有權據此解除契約。3.被告經原告寄發存證信函催告協助貸款後，仍不補足差額，買方於97年8月23日解除契約。契約關係消滅後，原告所給付之自備款及預繳款項共676,769元，被告等即無保有之法律上原因，應返還之。另按民法第182條規定，被告受領價金並應附利息，一併返還於原告，故原告得主張自解除契約起，按年息百分之5計算之利息。4.另原告主張民法第359條物之瑕疵擔保效力，解除契約，並請求回復原狀，返還原告已給付之價金共676,769元：按出賣人應擔保其物於危險移轉時具有其所保證之品質，是故買賣之物有瑕疵，而出賣人應負擔保之責者，買受人得解除其契約或請求減少其價金。解除契約後依民法第259條、第179條及第182條，請求返還受領給付之金錢及利息。被告等於系爭契約訂定時，保證該房屋之價值為1坪23萬元以上，亦保證最後於銀行貸款時得貸足總額之7成5即為200萬元，原告因被告等保證可貸款200萬元方購買之，若無法貸至200萬元，原告即不會考慮購買系爭房地，然事後該房屋經銀行鑑價，1坪僅價值17萬元，系爭房地未如其所稱高價，導致無法貸足200萬元，同時被告等亦未依其保證貸足200萬元，系爭房屋並無被告所保證之品質，是故原告得依民法第359條解除契約，並請求依民法第259條回復原狀。被告林鴻聯應返還其自原告受領之款項40萬元、被告瓏山林公司應返還自原告受領之自備款25萬元及與預繳款項26,769元共276,769元。並應給付自解除契約翌日起按週年利率百分之5之利息。(四)系爭土地買賣契約第5條及第10條、房屋買賣契約第18條及第23條，縱為契約之一部亦因對契約之他方顯失公平違反消保法第12條、民法247條之1、預售屋買賣定型化契約應記載事項及不得記載事項第24條第2款而無效：1.觀以系爭房屋買賣契約第18條、第23條之規定與綜合契約內其他條款約定，買賣雙方所負之義務顯不相當，若係因買方貸款條件不符合，需沒收高達房屋總價百分之20之違約金，相較之下，被告雖負有義務協助辦理抵押貸款，但若因被告之原因致貸款不足額時，卻未有罰則或任何處理方法，導致消費者需負擔顯不相當之賠償責任。是故定型化契約之貸款及違約條款與平等互惠原則即有不合，依消費者保護法第12條及消費者保護法施行細則第14條規定，契約條款違反誠信原則，對消費者顯失公平者，無效。2.次查，原告確實未有合理審閱期間，系爭契約內文字未有任何修改，事實上原告於自決定購屋至簽定契約時間極短暫，被告之銷售員僅要求原告儘快簽約，不僅未提供合理審閱期間，亦無任何可供磋商變更契約條款之機會，最終簽訂之契約亦按照被告所提供之範本簽訂，未有任何更改，原告無任何磋商餘地，被告稱原告得磋商變更云云，顯不足採。3.再查，系爭契約條款約定委託被告貸得總數7成5之貸款，然未約定倘因可歸責於被告致使貸款不成或成數不足時應如何處理，被告依契約所負之貸款義務違反時，均無任何處理方式或罰則，相較之下，被告於契約內貸款約定（房屋契約第18條、土地契約第5條）僅約定倘買方貸款條件不符致貸款不成或成數不足之處理方式，並依房屋契約第23條、土地契約第10條約定有高額賠償金，雙方顯有地位不平等、所負義務不相當之情形。4.末查，比較「預售屋買賣定型化契約應記載及不得記載事項」第18點第2款，完整規範當貸款金額少於約定貸款貸款金額時，區分不可歸責雙方、可歸責於賣方與可歸責於買方之處理方式，然被告所使用之系爭契約僅約定倘貸款金額不足，原告應一次以現金補足，否則為違約，並未將被告即賣方違約規範於契約中，明顯使原告負有不相當之義務，系爭契約之貸款及違約條款違反消費者保護法第12條顯失公平為無效。5.按「預售屋買賣定型化契約應記載事項及不得記載事項」第24條第2款是以消費者違約時，企業經營者固得沒收一定比例之買賣價金，然其比例上限不得超過房地價值百分之15。被告於契約內約定違約時沒收總價金百分20，核與內政部公告之定型化契約範本上限為百分之15不符，超出部份應屬無效。況被告實際沒收金額為原告全額已繳價金及非屬買賣價金之預繳款項共676,769元，比例已高達總價金百分之25，被告稱依法行事，實屬狡辯，明顯違反「預售屋買賣定型化契約應記載事項及不得記載事項」第24條第2款之規定，係屬違法，被告以此誆騙消費者，彰彰甚明。(五)被告未依照契約義務協助貸得足額貸款，為民法第227條不完全給付，原告定相當期間命被告協助貸款，逾期不履行即得解除契約：1.被告依照契約及廣告內容，應協助信用條件良好之原告貸得總價7成5之貸款，然最終核貸金額不足係因被告房地價值1坪僅17萬，較被告所稱之1坪20萬低，故銀行因供擔保設定之不動產價值不足，僅願核貸170萬，貸款差額30萬為可歸責於被告致不完全給付，原告得催告被告給付並得解除契約。2.原告於97年8月20日寄發存證信函告知被告違約，並以涉及詐欺等罪責，請求其依照契約協助辦理足額貸款，否則於函到後3日解除契約，然被告於97年8月21日收到後卻置若罔聞，原告解除契約自屬合法。(六)原告依民法第245條之1規定，請求因被告等對契約重要事項為惡意隱匿不實說明所致之損害：1.系爭房屋價金7成5以抵押房地貸款支付，是故抵押貸款之金額，是否可全額貸足，即為契約上重要關係事項。2.原告於訂立契約時，向被告等之銷售人員詢問房屋抵押貸款之詳情，其以一定可以貸至200萬元為由搪塞。對於貸款額度可能會因系爭房地價值過低，導致核貸金額不足之事，完全未曾提及，是故就此重要事項為惡意隱瞞，已該當民法第245之1條第1項第1款之事由，被告等惡意隱瞞，亦違反誠實及信用方法，致原告受有損害。3.另被告等之銷售人員於看屋一在主張該樣品屋內可做夾層之設計，並提供夾層之樣品屋，使原告誤信購買系爭房屋後，可為夾層屋之設計而為之購買，詎料，購買後查閱相關資料始知悉夾層屋之設計係屬不法，並經被告事後承認，此乃就交易上重要事項惡意隱匿、不實說明，已該當民法第245條之1第1項第1款及第3款事由，應對原告負賠償之責。4.原告因信被告等之說明，締結契約，交付自備款共65萬元及預繳之費用26,769元，卻遭被告沒收全額，受有損害共676,769元，被告應為賠償。(七)聲明：1.被告瓏山林公司應給付原告276,796元，及自97年8月24日起至清償日止，按週年利率百分之5計算之利息。2.被告林鴻聯應給付原告40萬元，及自97年8月24日起至清償日止，按週年利率百分之5計算之利息。3.原告願供擔保請准宣告假執行。二、被告則抗辯：(一)原告稱被告之銷售人員一再保證系爭房地價值很高，一定可以貸到房地價值總額7成5亦即200萬元，嗣配合系爭建物貸款業務之渣打銀行核貸金額僅為170萬元。是被告未依照契約義務協助貸得足額貸款，為民法第227條不完全給付，原告定相當期間命被告協助貸款，逾期不履行即得解除契約云云，顯與事實有違：1.查銀行是否核貸款項達7成5，乃銀行依承購戶個人之資力、信用條件而為決定，被告公司僅為銷售房地之建商，並無能力對承購戶資力、將來發生呆帳風險作專業之評估，實無可能擅自代銀行決定貸款之條件，或毫無條件即承諾、保證承購戶可貸款7成5，而自陷承購戶將來發生無力償還貸款時，須賠償銀行損失或自行進行冗長之訴訟程序。是原告稱被告銷售系爭房地時，有保證貸款7成5云云，洵非事實，被告鄭重否認之。2.訴外人即渣打銀行貸款承辦人李汪恩於98年7月3日下午2時13分在臺灣臺北地方法院檢察署98年度他字第589號詐欺案所作詢問筆錄第2頁及第5頁證稱：「（問：高總共跟你們貸款幾次？所帶金額多少？核准金額多少？）第一次是97年3月28日來申辦信用貸款30萬，皆如數核准貸款。第二次是97年5月9日申請房貸170萬，於5月13日核准，但至8月21日因告訴人未對保，公司規定超過3個月未對保所以取消該筆房貸。後來告訴人在同一天97年8月21日又以相同抵押物（時尚女人香的房屋）再次申請170萬元貸款，核准日期是97年8月27日，但這次一樣是超過三個月沒對保以致其貸款被取消。在97年7月14日還有一次是以高自己的房屋（桃園縣龜山鄉○○路○段122號之5號7樓）來申請貸款380萬元並如數核准撥款。」等語（見本院卷第338頁），又訴外人即渣打銀行貸款部主管李思賓於同次筆錄證稱：「（問：告訴人時尚女人跟你們申請貸款到底金額多少？）依照文件上是170萬元」等語（見本院卷第339頁），另原告於同次筆錄陳稱：「（問告訴人：該文件上為何會有你的簽名，你當初申請貸款是否為170萬元？）因為我已繳了一些款項在被告那邊，雖然我貸的款項是200萬，但我怕錢被被告他們沒收，所以只核准170萬元我只好同意」等語（見本院卷第341頁），可知，原告自始申請貸款金額為170萬元而非200萬元。是本件原告顯係刻意誤導、扭曲或混淆其貸款銀行渣打銀行已准予原告申請貸款170萬元，而原告逾3個月沒對保以致貸款銀行取消貸款之事實，進而影響法院之公正判斷。尤其，原告亦在97年7月14日用自身房屋向渣打銀行申請380萬元並如數核准撥款，原告竟逾期仍不履行給付第6期房地價金之義務，益徵原告自始既無誠意履行系爭房地買賣契約。3.且依兩造土地間預定買賣契約書第5條、房屋預定買賣契約書第18條皆明白約定「…倘因買方貸款條件不符合，致不能核貸或無法如數貸足及買方中途改變主意自願不貸或未能如期協辦或主動向核貸金融機構拒絕貸款者，視為放棄貸款，則其原欲貸款部分之價款應於賣方通知後，7日內以現金一次向賣方繳清，否則即係違約。…」，而土地、房屋預定買賣契約書皆有給予原告行使契約審閱期之機會，銷售人員亦會作充分之說明，在在足證被告確無保證貸款7成5，否則買賣契約自無可能為如此之約定。按「…簽訂契約時倘雙方已就廣告內容另為斟酌、約定，或企業經營者並未再據原屬『要約引誘』之廣告為訂約之說明、洽談，使之成為具體之『要約』，縱其廣告之內容不實，應受消費者保護法或公平交易法之規範，自難逕謂該廣告為要約或已當然成為契約之一部。」，此有最高法院92年台上字第2694號判決意旨可稽。是縱如原告所言，售屋人員於銷售時有謂「保證一定可以貸到房地價值總額7成5亦即200萬元」云云，然系爭房地預定買賣契約既無保證貸款7成5之約定，甚至於土地預定買賣契約書第5條、房屋預定買賣契約書第18條明白規定貸款成數不足時，買方須負補足差額之責任，原告之訴顯然無據，遑論被告公司自始否認有保證貸款7成5情事。4.抑有進者，一般銀行貸款大致可分為房屋貸款、汽車貸款、保單貸款、定存單貸款、信用貸款、公教貸款、小額信貸（企業員工）等種類。然原告自始即知貸款成數最高為7成5「純銀貸」，且眾所皆知「銀行貸款」並非完全等同「房屋抵押貸款」，原告自無陷於錯誤可言，縱使系爭房地核貸金額僅為170萬元，惟原告仍可依信貸等方式補足貸款差額。今原告在起訴狀第4頁第4行中，亦聲稱原告曾以個人名義向承辦系爭房地抵押貸款之銀行渣打銀行貸款30萬，在在足徵原告自可貸足系爭房屋、土地第6期價款，但其捨此不為，自可歸責於原告不履行契約給付義務。(二)原告主張簽訂系爭契約時，未有合理審閱期限，且系爭定型化契約條款違反誠實信用、平等互惠原則，原告可依消費者保護法第11條之1、第12條及其施行細則第14條、民法第247之1等規定，主張系爭土地契約第5條、第10條及房屋契約第18條及第23條（即貸款及違約條款）不構成契約之內容，再依民法第179條請求返還不當得利云云，並無理由：1.按「…按消費者保護法第11條之1第1、2項規定係規範企業經營者必須給予消費者合理之審閱期間，不可限制消費者簽訂契約之期間。所謂契約審閱期間，乃使消費者在訂立契約前有充裕時間瞭解契約之內容，然並非如原告在契約審閱期間內縱使已瞭解契約內容並進而提前簽約，而事後仍得任意反悔，以審閱期間未用盡為由主張不受契約之拘束。惟倘企業經營者未限制消費者簽名及交回契約書之期間，應認企業經營者已留予消費者合理之契約審閱期間，消費者非不得於簽名前就契約書之內容詳加閱讀，如消費者卻不為此途，而於未看清內容，完全瞭解契約內容前即於契約書上簽名，自係權利之拋棄。又如消費者已有詳細審閱契約之機會，該條之保護目的已達；……。是若消費者於簽約審閱契約條款內容之期間，雖未達規定期間，惟企業經營者未有妨礙消費者事先審閱契約之行為，消費者有充分了解契約條款之機會，且於充分了解後同意與企業經營者成立契約關係，基於其他考量而選擇放棄審閱期間者，要僅係消費者自行放棄權利，法無禁止拋棄之明文，在現代私法自治及契約自由原則之下，並無不可，亦不影響其簽名之效力，自不得引用上開消費者保護法第11條之1之規定主張所簽立之條款無效。再者，企業經營者為使消費者更易於掌握契約條款重要內容，而於契約條款下要求消費者簽名以慎重其事，對於消費者並無不利，更與消費者保護法立法旨趣無違。消費者事後自不得以審閱契約條款內容之期間未達規定期間，主張契約條款不構成契約之內容，且其行使權利顯然違反民法第148條第2項所定誠信原則，應認消費者為此主張無理由。」，臺灣臺北地方法院96年度消字第18號判決可資參照。而行政院院消費者保護委員會於89年1月15日台89消保法字第00056號函亦同此意旨。2.關於消保法第11條之1規定定型化契約審閱期間之立法意旨，乃在保護消費者無法就契約內容與企業經營者為個別磋商，只能對企營經營者所提供之定型化契約條款予以附合，而無討價還價之餘地而言。查被告在原告簽署系爭房地買賣契約前，顯已提供2種選擇方式，一為原告自得可依內政部公告，在契約簽立前享有至少5天以上之契約審閱權，並可攜回契約影本審閱，另一則為原告已逐條審閱充分瞭解契約條文，認無顯失公平之處，同意提早簽約並無疑義。今被告已充分給予原告機會詳細瞭解系爭契約內容及行使審閱契約之權益，嗣原告乃出於自由意志同意提早簽約，始在「審閱契約權利書」簽章於其上，自得視為原告自行放棄審閱契約之權利。是本件「審閱契約權利書」之內容乃出於雙方合意之契約條款，應無對原告權利造成不利影響。尤且原告本身亦擔任公司法務經理一職，具備高於一般消費者之法律知識及能力，揆諸前開說明，本件顯無前揭條文之適用，原告自不得事後反悔，再主張未享有合理審閱期間。3.就系爭房屋、土地買賣契約書第18條及第5條內容部分：(1)查原告自始即負有給付價金予被告義務，今被告已協助原告辦理抵押貸款170萬元，亦無向原告保證貸足200萬元，原告倘能任意指摘被告負有補足貸款差額30萬元，則變向加重被告之契約責任，且將原告不給付價金之不利益由被告承擔，不惟對被告難謂公平，更有違一般市場機制。(2)揆諸系爭房屋預定買賣契約書附件11之「代辦申請貸款委託書」（系爭土地預定買賣契約書附件2亦同此意旨，），即明確表示委託賣方以買方所購之房屋、車位及其土地持分等代向賣方指定之金融機構申請抵押貸款；雙方間有關貸款事宜，悉依「時尚女人香」房屋、土地買賣契約書第18條及第5條規定辦理等語，而附件內容僅短短數句，系爭契約條款亦重覆數次，更經原告審閱後始簽章其上，自無為原告所不及知或無磋商變更餘地可言。尤且「代辦申請貸款委託書」已將系爭房屋、土地買賣契約書第18條及第5條特別明文規定，並迭經原告同意始簽章於其上，乃屬特別磋商合意條款，非等同一般定型化契約條款。是原告一再指摘系爭房屋、土地買賣契約書第18條及第5條不構成契約一部分，顯屬無稽。4.就系爭房屋、土地買賣契約第23條及第10條內容部分：查兩造簽署系爭房屋買賣契約時，原告同意簽約並未表示任何異議，且買賣雙方若發生違約情事時，均要賠償對方違約金20％，而內政部公告之「預售屋買賣定型化契約應記載及不得記載事項」第24條關於違約之處罰，亦明白規定可沒收一定百分比之違約金。故系爭房地買賣契約條款，並無原告所指「免除或減輕預定契約條款之當事人之責任者。」、「加重他方當事人之責任者」、「其他於他方當事人有重大不利益者。」等情事。基上所述，原告指謫被告違反消保法第11條之1、第12條、民法第247之1等規定，再依民法第179條請求返還不當得利云云，洵屬無據。(三)本件原告復主張被告等就交易上重要事項惡意隱匿、不實說明，已該當民法第245條之1第1項第1款及第3款事由云云：1.原告主張被告對於貸款額度可能會因系爭房地價值過低，導致核貸金額不足之事，完全未曾提及，被告等惡意隱瞞，致原告受有損害云云，惟查貸款銀行已如原告所願貸足170萬元，自無核貸金額不足之情事，而被告更無向原告保證貸款成數7成5，業如上述。尤其被告所提供之系爭房地自始既無瑕疵存在，導致市場交易價值受到影響而下滑，更無給付與對待給付間之價值顯不相當之情形，故原告指謫被告所供買賣之物有瑕疵，損及原告受領系爭房地之價值云云，就此有利於己之事實者，依民事訴訟法第277條規定，原告自應先負舉證真正之責任，否則空言主張，自不足為採。2.又原告聲稱購買後查閱相關資料始知悉夾層屋之設計不法，並經被告事後承認，此乃就交易上重要事項惡意隱匿、不實說明云云。惟揆諸臺灣臺北地方法院檢察署檢察官98年度偵字第18099號不起訴處分書第3頁及第4頁可知，系爭房屋樣品屋照片之隔層體部分係僅作為儲藏室等空間使用，樣品屋落地窗旁之樓梯及置衣間隔層，則未與原結構體完全相連，顯與房屋原結構體之功能不同，且隔層體之面積顯小於樓地板之3分之1，足堪認定原告所供樣品屋照片僅表示系爭房屋可作如樣品屋所示之「隔層」，自得在室內進行2次施工「隔層」，並不須申請建照執照。是原告誤將樣品屋合法「隔層」認為「夾層」，而認被告有隱瞞違法「夾層」之事實，顯與事實有重大違誤，是原告諉稱被告等違反民法第245條之1第1項第1款及第3款事由云云，顯屬子虛，自不足採。(四)查原告於97年8月20日所寄發之龜山迴龍郵局第50號存證信所為解除契約之意思表示，顯已違反系民法第227條、第229條第2項及第254條之規定，是原告依民法第179條規定，請求被告等返還已給付之價金共676,769元云云，洵無理由：1.查原告民事起訴狀第14頁第5點亦不否認被告若有協助貸款之給付義務，亦屬「非定期限之給付」，是依民法第227條第1項、第229條第2項、第254條規定，原告為此主張自應先定相當期限催告被告履行，被告始負遲延責任，倘被告遲延仍未為給付，原告即應再定相當期限催告被告履行，逾期仍未履行時，原告始得合法解除契約。2.原告於97年8月20日所寄龜山迴龍郵局第50號存證信函僅表示「…今限貴號等於文到三日內依約提供足額房地貸款並為所有權移轉登記，逾期本人即逕行解除本件買賣契約」云云，核與前揭規範，僅能認為原告係第1次通知被告於確定期限履行契約之存證信函，被告於送達後3日內仍未履行，亦僅生遲延責任之情事。惟查原告於遲延給付後，原告即未依民法第254條規定，為第2次催告程序（即取得解除契約權），且原告亦未發存證信函表達系爭房地買賣契約已遭解除（即解除契約之意思表示），故原告未踐行合法催告程序，即逕行解除系爭房地買賣契約，自不生效力。(五)被告得以97年8月14日存證信函解除契約沒收原告之款項：1.按「…倘因買方貸款條件不符合，致不能核貸或無法如數貸足及買方中途改變主意自願不貸或未能如期協辦或主動向核貸金融機構拒絕貸款者，視為放棄貸款…」、又「買方若不辦貸款時，須按附件1『房屋價款分期付款明細表』中可委辦貸款抵繳之期款應於使用執照核發日起第30天應繳納之期款於期限內繳納；並依賣方通知指定日期配合辦理產權移轉相關手續；若逾期依本約第7條第2項加計規定遲延利息，並經賣方以存證信函催告後5日仍未繳者，依本約第23條之約定處理，未付清前賣方得拒絕辦理產權登記於買方。」，乃系爭房屋預定買賣契約書第18條第1項、第3項所明文約定（土地預定買賣契約書第5條第1項、第3項亦同此意旨）。2.查原告已逾繳款期限多日，雖經被告催告繳納，原告仍置若罔聞，被告迫於無奈，始於97年9月16日寄發臺北興安郵局第2142號存證信函存證信函予原告，明確催告原告應於函達5日內繳付已逾期限之核貸差額共計30萬元，否則沒入原告已繳之全部款項，同時解除買賣合約之意思表示。縱原告一再抗辯被告保證系爭房地可貸至房地價值總額7成5亦即200萬元云云，惟原告自始申請貸款金額即為170萬元，而承貸銀行亦如數核准撥款，竟逾3個月未對保而遭貸款銀行取消該筆房貸，自是可歸責原告之事由所致，已詳如上述，是原告自不得以上開理由抗辯。原告迄至97年9月23日止仍未繳納銀行核貸差額，被告始再以臺北興安郵局第2166號存證信函通知解除契約及沒入買賣價金之停止條件已成就。揆諸上開說明，系爭買賣契約既因原告違約逾期未繳納價款而解除，其訴請返還買賣價金云云，自無理由。(六)聲明：1.原告之訴及假執行之聲請均駁回。2.如受不利判決，被告願供擔保，請准宣告免為假執行。三、兩造不爭執之事項：(一)原告先於96年5月12日向被告瓏山公司與林鴻聯購買坐落新北市○○區○○段第557、558、559、560、565、566、567地號等7筆土地上「時尚女人香」建案編號A15棟11樓房屋1戶及其基地（下稱A15棟11樓房地），並與被告瓏山林公司簽訂房屋預定買賣契約書及與被告林鴻聯簽訂土地預定買賣契約書。嗣於房屋建築完成後，因原告對於A15棟11樓房屋之格局不滿意，乃與被告等協議更換買賣標的為同建案編號A10棟9樓系爭房地，並於97年3月23日與被告瓏山林公司簽訂系爭房屋買賣契約，及與被告林鴻聯簽訂系爭土地買賣契約，約定系爭房地總價金為265萬元（見本院卷第238頁正反面證人葉惠雯之證詞、第240頁反面證人王寶玉之證詞、第21至78頁系爭房屋及土地買賣契約影本各1份）。(二)原告已給付被告等自備款65萬元、代書費用36,700元及預繳費用26,769元，共計713,469元（見本院卷第91至93頁統一發票影本2紙、費用明細及代收款客戶簽認表暨收據影本各1紙）。(三)原告於97年8月20日以龜山迴龍郵局第50號存證信函通知被告於文到3日內依約提供足額房地貸款並為所有權移轉登記，逾期原告即逕行解除本件買賣契約（見本院卷第97至100頁上開存證信函）。(四)被告於97年9月16日以臺北興安郵局第2142號存證信函催告原告應於函達5日內繳付已逾期限之核貸差額共計30萬元，否則沒入原告已繳之全部款項，同時解除買賣合約。原告至97年9月23日止未繳納銀行核貸差額30萬元，被告復以臺北興安郵局第2166號存證信函通知原告解除契約及沒入買賣價金676,769元（見本院卷第160至162頁上開存證信函及回執）。四、兩造爭執事項：(一)原告主張被告未提供契約合理審閱期間，依消費者保護法第11條之1規定，系爭土地買賣契約第5條、第10條及系爭房屋買賣契約第18條及第23條之約定為定型化契約條款，不構成契約之一部，原告得依民法第179條、第182條規定請求被告返還沒收款項之不當得利及利息，有無理由？如有理由，被告應返回之金額為若干？(二)原告主張以龜山迴籠郵局第50號存證信函解除系爭房屋及土地買賣契約，並依民法第179條、第182條規定請求被告返還不當得利，另依民法第259條規定請求回復原狀，有無理由？如有理由，被告應返回之金額為若干？1.原告主張系爭房地抵押貸款金額因房地價值過低，致銀行僅願核貸170萬元，與原先預定之貸款200萬元有30萬元之差額，經原告寄發存證信函催告被告協助貸款後，被告未理會，原告依「預售屋買賣定型化契約應記載及不得記載事項」第18點第2項第2款及民法第359條之規定於97年8月23日解除契約，有無理由？2.原告主張被告未依照契約義務協助貸得200萬元貸款，為民法第227條不完全給付，原告定相當期間命被告協助貸款，被告逾期仍不履行，原告得解除契約，有無理由？(三)原告主張系爭土地買賣契約第5條及第10條、房屋買賣契約第18條及第23條，縱為契約之一部亦因對契約之他方顯失公平，違反消費者保護法第12條、民法247條之1、預售屋買賣定型化契約應記載事項及不得記載事項第24條第2項而無效，並依民法第179條、第182條規定請求被告返還不當得利，有無理由？如有理由，被告應返回之金額為若干？(四)原告主張被告就系爭房地因價值過低導致核貸金額不足，及夾層屋之設計係屬不法等重要事項惡意隱瞞，違反誠實及信用方法，致原告受有損害，依民法第245之1條第1項第1款、第3款規定應負損害賠償責任，有無理由？如有理由，被告應賠償之金額為若干？五、本院之判斷：(一)原告主張被告未提供契約合理審閱期間，依消費者保護法第11條之1規定，系爭土地買賣契約第5條、第10條及系爭房屋買賣契約第18條及第23條之約定為定型化契約條款，不構成契約之一部，原告得依民法第179條、第182條規定請求被告返還沒收款項之不當得利及利息，有無理由？如有理由，被告應返回之金額為若干？1.按「企業經營者與消費者訂立定型化契約前，應有30日以內之合理期間，供消費者審閱全部條款內容。違反前規定者，該條款不構成契約之內容。但消費者得主張該條款仍構成契約之內容。」，消費者保護法施行細則第11條第1項、第2項定有明文。該條之目的在給予消費者充分瞭解契約內容之機會，並規範企業經營者不得在未給予消費者審閱契約內容之機會前，限制消費者簽訂契約之時間，以避免消費者於匆忙間不及瞭解其依契約所得主張之權利及應負擔之義務，致訂立顯失公平之契約而受有損害，故只須消費者於簽約前已充分瞭解該契約之權利義務關係，或有可認其能認識契約權利義務關係之合理審閱期間，即不得引用上開規定而主張契約無效。是以企業經營者如未限制消費者必須於何時簽名，何時將契約書交回，應認企業經營者已留予消費者合理之契約審閱期間，即便消費者未看清該契約之內容，即於契約書上簽名並交回契約書，然消費者非不得於簽名前就契約書之內容，詳加閱讀。其不為此之圖，卻於完全瞭解契約內容前即於契約書上簽名，係對自身權利之拋棄，尚非法所不許，亦不影響其簽名之效力。2.原告主張簽訂系爭房地買賣契約時，被告未提供合理審閱期限，且簽約當日因被告之銷售員一再強力推銷並要求立刻簽訂契約，原告迫於無奈，僅得簽名蓋章。依消費者保護法第11條之1規定，原告主張系爭土地買賣契約第5條及第10條，系爭房屋買賣契約第18條及第23條（即貸款及違約條款），對於原告規範之內容不公平，應不構成契約內容之一部。則被告依據上開約定沒收原告所繳款項676,769元，即無法律上原因，原告得依民法第179條及第182條，請求被告等返還不當利益等語。被告則抗辯已充分給予原告機會詳細瞭解系爭契約內容及行使審閱契約之權益，原告係出於自由意志同意提早簽約，始在「審閱契約權利書」簽章於其上，自得視為原告自行放棄審閱契約之權利。本件「審閱契約權利書」之內容乃出於雙方合意之契約條款，應無對原告權利造成不利影響。且原告擔任公司法務經理一職，具備高於一般消費者之法律知識及能力，本件顯無前揭條文之適用，原告自不得事後反悔，再主張未享有合理審閱期間等語。2.查本件原告先於96年5月12日向被告瓏山公司與林鴻聯購買A15棟11樓房地，並與被告瓏山林公司簽訂房屋預定買賣契約書及與被告林鴻聯簽訂土地預定買賣契約書。嗣於房屋建築完成後，因原告對於A15棟11樓房屋之格局不滿意，乃與被告等協議更換買賣標的為同建案編號A10棟9樓系爭房地，並於97年3月23日與被告瓏山林公司簽訂系爭房屋買賣契約，及與被告林鴻聯簽訂系爭土地買賣契約，約定系爭房地總價金為265萬元之事實，為兩造所不爭執，復經證人葉惠雯、王寶玉證述在卷，並有系爭房屋及土地買賣契約影本各1份在卷可稽（見本院卷第238頁正反面、第240頁反面、第21至78頁），堪以信實。又兩造間於96年5月12日就A15棟11樓房地所簽訂之房屋預定買賣契約書，與兩造於97年3月23日就A10棟9樓系爭房地所簽訂之系爭房屋及土地買賣契約之內容均相同，僅買賣標的不同，此為兩造所不爭執，是原告自96年5月12日與被告簽訂A15棟11樓房地契約後至97年3月23日與被告簽訂A10棟9樓系爭房地契約時，原告已有10個月以上之期間足以充分審閱相同內容之系爭房地買賣契約，而此其間已超過消費者保護法第11條之1所規定之30日審閱期間，是即便原告未看清該契約之內容，即於契約書上簽名並交回契約書，然原告非不得於系爭房地買賣契約簽名前就契約書之內容，詳加閱讀。其不為此之圖，卻於完全瞭解契約內容前即於契約書上簽名，係對自身權利之拋棄，尚非法所不許，亦不影響其簽名之效力。再者，本件並無證據證明被告有限制原告必須於何時簽名，何時將契約書交回，應認被告已留予原告合理之契約審閱期間，是原告非不得於簽名前就契約書之內容，詳加閱讀。則原告既仍願與被告簽訂系爭買賣契約，自不能再以被告未提供合理審閱期間為由，主張系爭土地買賣契約第5條及第10條與系爭房屋買賣契約第18條及第23條，不構成契約內容之一部。3.從而，原告主張被告未提供契約合理審閱期間，系爭土地買賣契約第5條、第10條及系爭房屋買賣契約第18條、第23條之約定為定型化契約條款，不構成契約之一部，被告依該等約定沒收原告繳納之款項，即無法律上原因，原告得依民法第179條、第182條請求被告返還不當得利及利息云云，即屬無據，而不足採。(二)原告主張以龜山迴籠郵局第50號存證信函解除系爭房屋及土地買賣契約，並依民法第179條、第182條規定請求被告返還不當得利，有無理由？如有理由，被告應返回之金額為若干？1.原告主張系爭房地抵押貸款金額因房地價值過低，致銀行僅願核貸170萬元，與原先預定之貸款200萬元有30萬元之差額，經原告寄發存證信函催告被告協助貸款後，被告未理會，原告依「預售屋買賣定型化契約應記載及不得記載事項」第18點第2項第2款及民法第359條之規定於97年8月23日解除契約等語，為被告所否認。經查：(1)按「預售屋買賣定型化契約應記載及不得記載事項」第18點第2款第2目規定：前款由賣方洽定辦理之貸款金額少於預定貸款金額，其差額於可歸責於賣方時，差額部分，賣方應依原承諾貸款相同年限及條件由買方分期清償。如賣方不能補足不足額部分，買方有權解除契約。又按買賣因物有瑕疵，而出賣人依前五條之規定，應負擔保之責者，買受人得解除其契約或請求減少其價金。但依情形，解除契約顯失公平者，買受人僅得請求減少價金，民法第359條亦有明文。(2)查為導正預售屋買賣契約書之內容，使其符合誠實信用及平等互惠原則，促進公平交易，確保消費者權益，內政部依消費者保護法第17條第1項規定，於90年9月3日公布「預售屋買賣定型化契約應記載及不得記載事項」，其後曾於98年8月10日、98年10月30日、99年8月16日及100年3月24日作微幅修正。而本件系爭房地買賣，係於房屋建築完成後，原告至現場看屋，因對原本購買之A15棟11樓預售房屋結構不滿意，而與被告協議換屋，故兩造再於97年3月23日就A10棟9樓系爭房地簽定系爭買賣契約，則系爭房地買賣契約雖名為房屋、土地「預定買賣契約書」，惟係於系爭房屋建築完成後，經兩造確認買賣之標的為A10棟9樓房地所締結之契約，斯時買賣標的A10棟9樓房屋已經存在，與預售屋買賣契約訂立時買賣標的尚未存在之性質不同，是系爭房地買賣契約其性質應非屬預售屋買賣，而應屬一般之成屋買賣，是兩造間系爭房地買賣契約關係，應無「預售屋買賣定型化契約應記載事項及不得記載事項」之適用。是原告主張依「預售屋買賣定型化契約應記載及不得記載事項」第18點第2款第2目規定，其有權解除契約云云，尚無足採。(3)次查，經本院依職權函詢渣打銀行關於原告以系爭房地申辦貸款之情形，該銀行以100年2月25日渣打商銀SCBCL字第1001002655號函回覆表示：原告於97年3月間購買系爭房地後，自行向該銀行申辦貸款，當時核定原告得貸款之金額為170萬元，但因批示決核後逾3個月原告未申請撥款，故該行予以駁回等語，有上開函文暨貸款資料1份附卷可稽（見本院卷第308至316頁）。又參以訴外人即渣打銀行貸款承辦人李汪恩於臺灣臺北地方法院檢察署98年度他字第589號詐欺案98年7月3日下午2時13分詢問筆錄證稱：「（問：高總共跟你們貸款幾次？所貸金額多少？核准金額多少？）第一次是97年3月28日來申辦信用貸款30萬，皆如數核准貸款。第二次是97年5月9日申請房貸170萬，於5月13日核准，但至8月21日因告訴人（即本件原告，下同）未對保，公司規定超過3個月未對保所以取消該筆房貸。後來告訴人在同一天97年8月21日又以相同抵押物（時尚女人香的房屋）再次申請170萬元貸款，核准日期是97年8月27日，但這次一樣是超過三個月沒對保以致其貸款被取消。在97年7月14日還有一次是以高自己的房屋（桃園縣龜山鄉○○路○段122號之5號7樓）來申請貸款380萬元並如數核准撥款。」等語（見本院卷第338頁）；及訴外人即渣打銀行貸款部主管李思賓於同次筆錄證稱：「依文件來看是告訴人2次均親自遞件以時尚女人香來申請貸款170萬，我們綜合申請人的收入、抵押品及信用狀況來評估准許貸款之金額，告訴人2次所貸的170萬元都如數核准，只是因為超過3個月未對保故予取消。...（是否該約300戶的貸款是由你們承辦？）是。一般來說確實可以貸到房價的7到85成。...（告訴人剛才有說他97年3月2日有一筆信貸30萬元，是否影響到他後來申請200萬卻貸得170萬的房貸？）是。」等語（見本院卷第339至342頁）；另原告於同次筆錄陳稱：「（問告訴人：該文件上為何會有你的簽名，你當初申請貸款是否為170萬元？）因為我已繳了一些款項在被告那邊，雖然我貸的款項是200萬，但我怕錢被被告他們沒收，所以只核准170萬元我只好同意」等語（見本院卷第341頁）。由上足徵，原告係自行遞件以系爭房地向渣打銀行申請貸款170萬元，並非由被告洽定辦理貸款，且因原告於97年3月2日已有申請一筆信用貸款30萬元，致影響到渣打銀行評估本件核貸之金額為170萬，況且依李思賓之上開證詞，本件時尚女人香建案約300戶的貸款均由渣打銀行承辦，一般來說確實可以貸到房地價格的7到85成之金額，並無因房地價格過低，而無法貸足房地價格7到85成金額之情形。從而，原告主張系爭房地抵押貸款金額因房地價值過低，致銀行僅願核貸170萬元，與原先預定之貸款200萬元有30萬元之差額云云，即屬無據，不足採信。另原告主張依民法第359條之規定解除系爭房地買賣契約，惟始終未舉證證明系爭房地有何瑕疵存在，則其此部分主張，亦乏依據，而無足取。2.原告主張被告未依照契約義務協助貸得200萬元貸款，為民法第227條不完全給付，原告定相當期間命被告協助貸款，被告逾期仍不履行，原告得解除契約，有無理由？查本件係原告自行遞件以系爭房地向渣打銀行申請貸款170萬元，並非由被告洽定辦理貸款，且因原告於97年3月2日已有申請一筆信用貸款30萬元，致影響到渣打銀行評估本件核貸之金額為170萬，又依李思賓之上開證詞，本件時尚女人香建案約300戶的貸款均由渣打銀行承辦，一般來說確實可以貸到房價的7到85成之金額等情，俱如前述，是原告就系爭房地未能貸得其預期之貸款200萬元，顯係可歸責於其自身之事由所致，則原告主張被告未依照契約義務協助貸得200萬元貸款，有民法第227條不完全給付情形，原告得定相當期間命被告協助貸款，被告逾期仍不履行，原告得解除契約云云，即屬無據。3.從而，原告主張以龜山迴籠郵局第50號存證信函解除系爭房屋及土地買賣契約，並依民法第179條、第182條規定請求被告返還不當得利，即無理由，不應准許。(三)原告主張系爭土地買賣契約第5條及第10條、房屋買賣契約第18條及第23條，縱為契約之一部亦因對契約之他方顯失公平，違反消費者保護法第12條、民法247條之1、預售屋買賣定型化契約應記載事項及不得記載事項第24條第4項而無效，並依民法第179條、第182條規定請求被告返還不當得利，有無理由？如有理由，被告應返回之金額為若干？1.按消費者保護法第12條規定：定型化契約中之條款違反誠信原則，對消費者顯失公平者，無效。定型化契約中之條款有下列情形之一者，推定其顯失公平：一、違反平等互惠原則者。二、條款與其所排除不予適用之任意規定之立法意旨顯相矛盾者。三、契約之主要權利或義務，因受條款之限制，致契約之目的難以達成者。又消費者保護法施行細則第14條規定：定型化契約條款，有下列情事之一者，為違反平等互惠原則：一、當事人間之給付與對待給付顯不相當者。二、消費者應負擔非其所能控制之危險者。三、消費者違約時，應負擔顯不相當之賠償責任者。四、其他顯有不利於消費者之情形者。再民法第247條之1規定：依照當事人一方預定用於同類契約之條款而訂定之契約，為左列各款之約定，按其情形顯失公平者，該部分約定無效：一、免除或減輕預定契約條款之當事人之責任者。二、加重他方當事人之責任者。三、使他方當事人拋棄權利或限制其行使權利者。四、其他於他方當事人有重大不利益者。又預售屋買賣定型化契約應記載事項及不得記載事項第24條第4項規定：買方違反有關「付款條件及方式」之規定者，賣方得沒收依房地總價款百分之＿（最高不得超過百分之十五）計算之金額。但該沒收之金額超過已繳價款者，則以已繳價款為限，買賣雙方並得解除本契約。2.原告主張系爭房屋買賣契約第18條、第23條、土地買賣契約第5條及第10條之規定與綜合契約內其他條款約定，若因買方貸款條件不符合，需沒收高達房屋總價百分之20之違約金，相較之下，被告雖負有義務協助辦理抵押貸款，但若因被告之原因致貸款不足額時，卻未有罰則或任何處理方法，買賣雙方所負之義務顯不相當，明顯使原告負有不相當之義務，故系爭房地契約定型化契約之貸款及違約條款與平等互惠原則即有不合，依消費者保護法第12條、消費者保護法施行細則第14條規定，契約條款違反誠信原則，對消費者顯失公平者，無效；且按「預售屋買賣定型化契約應記載事項及不得記載事項」第24條第2款是以消費者違約時，企業經營者固得沒收一定比例之買賣價金，然其比例上限不得超過房地價值百分之15。被告於契約內約定違約時沒收總價金百分20，核與內政部公告之定型化契約範本上限為百分之15不符，超出部份應屬無效；況被告實際沒收金額為原告全額已繳價金及非屬買賣價金之預繳款項共676,769元，比例已高達總價金百分之25，明顯違反「預售屋買賣定型化契約應記載事項及不得記載事項」第24條第2款之規定，係屬違法等語，為被告所否認。3.查系爭房屋買賣契約第18條第1項及土地買賣契約第5條第1項均約定：倘因買方貸款條件不符合致不能核貸或無法如數貸足，則其原欲貸款部份之價款應於賣方通知後七日內以現金一次補足，否則即係違約（見本院卷第27頁、第74頁反面）。觀此內容，乃係因可歸責於買方之事由致不能核貸或無法如數貸足，而約定買方應補足貸款差額之約定，並無消費者保護法第12條及民法第247條之1所規定違反誠信原則、顯失公平等情形，自非無效之約定。又系爭房屋買賣契約第23條第2項及土地買賣契約第10條第2項約定：買方違反房屋買賣契約第7條、第15條第3項及第18條約定，或違反土地買賣契約第4條之約定，買方得沒收依房地總價款百分之20計算之金額；而系爭房屋買賣契約於第23條第1項及土地買賣契約第10條第1項亦約定：賣方違反房屋買賣契約第11條、第12條第2項及第21條之約定者，或賣方違反土地賣賣契約第8條之約定者，買方均得解除契約，賣方除應將買方已繳之房地價款及遲延利息全部退還賣方外，並應同時賠償房地總價款百分之20之違約金（見本院卷第28、76頁）。足徵系爭房屋買賣契約第23條及土地買賣契約第10條有關違約處罰之約定，對於可歸責於買賣雙方之違約罰則均有約定，且賠償之比例均以房地總價款百分之20計算，是該等約定即無原告所主張買賣雙方所負之義務顯不相當，明顯使原告負有不相當之義務之情形，應無消費者保護法第12條及民法第247條之1所規定違反誠信原則、顯失公平等情形，自非無效之約定。再者，「預售屋買賣定型化契約應記載事項及不得記載事項」第24條第2款所定賣方得沒收依房地總價款最高不得超過百分之15計算之金額之規定，乃係針對預售屋買賣而為之規定。而系爭房地買賣契約其性質非屬預售屋買賣，而應屬一般之成屋買賣，兩造間系爭房地買賣契約關係，並無「預售屋買賣定型化契約應記載事項及不得記載事項」之適用，有如前述，則原告主張被告沒收金額為原告全額已繳價金及非屬買賣價金之預繳款項共676,769元，比例已高達總價金百分之25，明顯違反「預售屋買賣定型化契約應記載事項及不得記載事項」第24條第2款之規定云云，即屬無據。又系爭房屋買賣契約第23條第2項及土地買賣契約第10條第2項約定沒收買方房地總價百分之20之比例，並非顯然過高，故無消費者保護法第12條及民法第247條之1所規定違反誠信原則、顯失公平等情形，自非無效之約定。是被告依據系爭契約上開約定解除契約，沒收原告已繳之價金，即非無法律上之原因，並無不當得利之情形。4.從而，原告主張系爭土地買賣契約第5條及第10條、房屋買賣契約第18條及第23條，縱為契約之一部亦因對契約之他方顯失公平，違反消費者保護法第12條、民法247條之1、預售屋買賣定型化契約應記載事項及不得記載事項第24條第4項而無效，並依民法第179條、第182條規定請求被告返還不當得利，為無理由，不應准許。(四)原告主張被告就系爭房地因價值過低導致核貸金額不足，及夾層屋之設計係屬不法等重要事項惡意隱瞞，違反誠實及信用方法，致原告受有損害，依民法第245之1條第1項第1款、第3款規定應負損害賠償責任，有無理由？如有理由，被告應賠償之金額為若干？1.按民法第245條之1第1項第1款、第3款規定：契約未成立時，當事人為準備或商議訂立契約而有左列情形之一者，對於非因過失而信契約能成立致受損害之他方當事人，負賠償責任：一、就訂約有重要關係之事項，對他方之詢問，惡意隱匿或為不實之說明者。...三、其他顯然違反誠實及信用方法者。2.原告主張於訂立系爭契約時，被告之銷售人員表示一定可以貸至200萬元，對於貸款額度可能會因系爭房地價值過低，導致核貸金額不足之事，完全未曾提及，是故就此重要事項為惡意隱瞞，已該當民法第245之1條第1項第1款之事由，被告等惡意隱瞞，亦違反誠實及信用方法，致原告受有損害；又被告之銷售人員於看屋一再表示該樣品屋內可做夾層之設計，並提供夾層之樣品屋，使原告誤信購買系爭房屋後，可為夾層屋之設計而為之購買，詎購買後查閱相關資料始知悉夾層屋之設計係屬不法，此乃就交易上重要事項惡意隱匿、不實說明，已該當民法第245條之1第1項第1款及第3款事由，應對原告負賠償之責等語，並聲請傳喚證人楊鴻彬及提出廣告單影本4紙為證（見本院卷第79至82頁），惟此為被告所否認。3.查本件因原告於97年3月2日已有申請一筆信用貸款30萬元，致影響到渣打銀行評估本件核貸之金額為170萬，又依李思賓之上開證詞，本件時尚女人香建案約300戶的貸款均由渣打銀行承辦，一般來說確實可以貸到房價的7到85成之金額等情，有如前述，是本件貸款金額未達原告預期之200萬元即房地總價款之75成，乃歸因於原告本身之因素所致。則原告主張訂立系爭契約時，被告之銷售人員表示一定可以貸至200萬元，惡意隱瞞貸款額度可能會因系爭房地價值過低，導致核貸金額不足之事，亦違反誠實及信用方法，該當民法第245之1條第1項第1款及第3款之事由，應負賠償責任云云，並無足採。4.次查，證人楊鴻彬於本院言詞辯論時證稱：伊與原告去看建案時尚女人香樣品屋，挑高大概7米多，有點像樓中樓形式的套房，直走有個小樓梯可以上去，樓梯的旁邊有餐廳及客廳，樓上是個小房間，可以在上面睡覺，小房間下面是客廳及餐廳。...業務員說可以做兩個樣子，一個是像樣品屋這樣挑高的，一個是一般沒有挑高的，建商會幫我們做好，但是房屋的總價是一樣的等語（見本院卷第239頁反面），固足認定被告展示之樣品屋係作夾層之裝潢設計。惟觀諸原告所提出之廣告單，並無隻字片語提及「夾層屋」係屬合法建物之內容，原告復未提出證據證明被告之銷售人員曾表示夾層屋係合法，而原告及證人所參觀之樣品屋以夾層之裝潢予以展現，屬空間利用方法之參考展示，僅供購買者作其房屋裝潢設計之參考，尚難認樣品屋以夾層之裝潢展示，即遽認被告有將夾層屋之設計係屬不法等重要事項惡意隱瞞，違反誠實及信用方法之情形。則原告主張被告惡意隱瞞夾層屋之設計係屬不法等重要事項，違反誠實及信用方法，致原告受有損害，依民法第245之1條第1項第1款、第3款規定應負損害賠償責任云云，並無可採。六、綜上所述，原告主張依民法第179條、第182條、第245之1條第1項第1款、第3款之規定，請求：(一)被告應給付原告276,796元，及自97年8月24日起至清償日止，按週年利率百分之5計算之利息。(二)被告林鴻聯應給付原告40萬元，及自97年8月24日起至清償日止，按週年利率百分之5計算之利息，均無理由，應予駁回。又原告之訴既經駁回，其假行之聲請亦失所附麗，併予駁回。七、本件事證已臻明確，兩造其餘攻擊防禦方法及未經援用之證據，經審酌後，核與判決結果不生影響，爰不一一論述。八、據上論結，本件原告之訴為無理由，依民事訴訟法第79條，判決如主文。中華民國100年5月20日民事第二庭法官張筱琪以上正本係照原本作成如對本判決上訴，須於判決送達後20日內向本院提出上訴狀中華民國100年5月20日書記官連思斐",
  "characters": {
    "judges": [
      "張筱琪"
    ],
    "prosecutors": [

    ],
    "lawyers": [
      "劉韋廷",
      "林財生",
      "劉宏邈"
    ],
    "clerks": [

    ],
    "plaintiffs": [
      "高鴻鵬"
    ],
    "defendants": [
      "瓏山林企業股份有限公司",
      "兼法定代理"
    ],
    "prosecutor_office": [

    ],
    "creditors": [

    ],
    "debtors": [

    ],
    "judicial_associate_officer": [

    ]
  },
  "adjudged_at": "2011-05-20",
  "created_at": "2016-02-12 03:03:30",
  "updated_at": "2016-02-12 03:03:30"
}