{
  "identify": "PCD-100-交易-347-20110520-1",
  "court": {
    "name": "臺灣新北地方法院",
    "code": "PCD"
  },
  "division": {
    "name": "刑事",
    "code": "M"
  },
  "year": 100,
  "word": "交易",
  "number": "347",
  "jcheck": "1",
  "reason": "公共危險",
  "content": "臺灣板橋地方法院刑事判決            100年度交易字第347號\n公  訴  人  臺灣板橋地方法院檢察署檢察官\n被      告  劉健民\n上列被告因公共危險案件，經檢察官提起公訴（100 年度偵字第\n8401號），被告於準備程序中就被訴事實為有罪之陳述，經本院\n裁定進行簡式審判程序，判決如下：\n    主  文\n劉健民服用酒類，不能安全駕駛動力交通工具而駕駛，處有期徒\n刑陸月，如易科罰金，以新臺幣壹仟元折算壹日。\n    事  實\n一、劉健民前因公共危險案件，經本院以98年度交簡字第1652號\n    判處罰金新臺幣6 萬元確定，又因公共危險案件，經本院以\n    98年度交簡字第2576號判處拘役59日確定，於民國98年11月\n    24日執行完畢；復因公共危險案件，經本院以99年度交簡字\n    第5397號、99年度交簡字第第5273號分別判處有期徒刑3 月\n    、3 月確定，嗣經本院以100 年度聲字第1174號裁定應執行\n    有期徒刑4 月確定，於100 年3 月15日入監執行，尚未執行\n    完畢（於本案均不構成累犯）。詎猶不知悔改，於100 年3\n    月14日11時至17時許，在新北市○○區○○路附近某工地內\n    飲酒後，已達不能安全駕駛動力交通工具之程度，竟仍於同\n    日21時20分許，騎乘車牌號碼GDE －323 號重型機車，欲返\n    回其新北市○○區○○路125 巷22號住處。嗣於同日21時33\n    分許，行經新北市○○區○○路135 號前為警攔檢，經警對\n    其施以呼氣酒精濃度測試，結果測得其呼氣中酒精濃度為每\n    公升1.22毫克，因而查獲上情。\n二、案經新北市政府警察局新莊分局報告臺灣板橋地方法院檢察\n    署檢察官偵查起訴。\n    理  由\n一、本件被告劉健民所犯為死刑、無期徒刑、最輕本刑為3 年以\n    上有期徒刑以外之罪，且非高等法院管轄第一審之案件，於\n    本院準備程序進行中，被告就被訴事實為有罪之陳述，經告\n    知被告簡式審判程序之旨，並聽取公訴人及被告之意見後，\n    本院裁定進行簡式審判程序，合先敘明。\n二、上揭犯罪事實，業據被告於警詢、偵查及本院審理中坦承不\n    諱，復有新北市政府警察局新莊分局當事人酒精測定紀錄表\n    、刑法第185 條之3 案件測試觀察紀錄表、酒後時間確認單\n    、新北市政府警察局舉發違反道路交通管理事件通知單各1\n    紙附卷可稽，足見被告自白核與事實相符。從而，本案事證\n    明確，被告犯行洵堪認定，應予依法論科。\n三、核被告所為，係犯刑法第185 條之3 服用酒類不能安全駕駛\n    動力交通工具而駕駛罪。爰審酌被告前有多次酒後駕車之公\n    共危險前科紀錄，曾經法院判處罰金、拘役及有期徒刑在案\n    ，猶未能體認酒後駕車對一般往來之公眾及駕駛人自身皆具\n    有高度危險性，再度漠視自己安危，並罔顧公眾安全，於服\n    用酒類，酒後呼氣酒精濃度高達每公升1.22毫克，已處於不\n    能安全駕駛動力交通工具之狀態，仍率爾騎乘機車行駛於道\n    路上，對交通安全所生之危害非輕，及犯後坦承犯行態度良\n    好等一切情狀，參酌檢察官之具體求刑，量處如主文所示之\n    刑，並諭知易科罰金之折算標準，以資懲儆。\n據上論斷，應依刑事訴訟法第273 條之1 第1 項、第299 條第1\n項前段，刑法第185 條之3 、第41條第1 項前段，刑法施行法第\n1 條之1 第1 項，判決如主文。\n本案經檢察官楊景舜到庭執行職務。\n中    華    民    國   100    年    5     月    20    日\n                      交通法庭  法  官  廖欣儀\n以上正本證明與原本無異。\n如不服本判決應於收受判決後10日內向本院提出上訴書狀，並應\n敘述具體理由。其未敘述上訴理由者，應於上訴期間屆滿後20日\n內向本院補提理由書（均須按他造當事人之人數附繕本）「切勿\n逕送上級法院」。\n                                書記官  顏偉林\n中    華    民    國   100    年    5     月    20    日\n附錄本案論罪科刑法條全文：\n中華民國刑法第185條之3\n服用毒品、麻醉藥品、酒類或其他相類之物，不能安全駕駛動力\n交通工具而駕駛者，處1 年以下有期徒刑、拘役或科或併科15萬\n元以下罰金。",
  "structure": {
    "main": "劉健民服用酒類，不能安全駕駛動力交通工具而駕駛，處有期徒\n刑陸月，如易科罰金，以新臺幣壹仟元折算壹日。",
    "fact": "一、劉健民前因公共危險案件，經本院以98年度交簡字第1652號\n    判處罰金新臺幣6 萬元確定，又因公共危險案件，經本院以\n    98年度交簡字第2576號判處拘役59日確定，於民國98年11月\n    24日執行完畢；復因公共危險案件，經本院以99年度交簡字\n    第5397號、99年度交簡字第第5273號分別判處有期徒刑3 月\n    、3 月確定，嗣經本院以100 年度聲字第1174號裁定應執行\n    有期徒刑4 月確定，於100 年3 月15日入監執行，尚未執行\n    完畢（於本案均不構成累犯）。詎猶不知悔改，於100 年3\n    月14日11時至17時許，在新北市○○區○○路附近某工地內\n    飲酒後，已達不能安全駕駛動力交通工具之程度，竟仍於同\n    日21時20分許，騎乘車牌號碼GDE －323 號重型機車，欲返\n    回其新北市○○區○○路125 巷22號住處。嗣於同日21時33\n    分許，行經新北市○○區○○路135 號前為警攔檢，經警對\n    其施以呼氣酒精濃度測試，結果測得其呼氣中酒精濃度為每\n    公升1.22毫克，因而查獲上情。\n二、案經新北市政府警察局新莊分局報告臺灣板橋地方法院檢察\n    署檢察官偵查起訴。",
    "reason": "一、本件被告劉健民所犯為死刑、無期徒刑、最輕本刑為3 年以\n    上有期徒刑以外之罪，且非高等法院管轄第一審之案件，於\n    本院準備程序進行中，被告就被訴事實為有罪之陳述，經告\n    知被告簡式審判程序之旨，並聽取公訴人及被告之意見後，\n    本院裁定進行簡式審判程序，合先敘明。\n二、上揭犯罪事實，業據被告於警詢、偵查及本院審理中坦承不\n    諱，復有新北市政府警察局新莊分局當事人酒精測定紀錄表\n    、刑法第185 條之3 案件測試觀察紀錄表、酒後時間確認單\n    、新北市政府警察局舉發違反道路交通管理事件通知單各1\n    紙附卷可稽，足見被告自白核與事實相符。從而，本案事證\n    明確，被告犯行洵堪認定，應予依法論科。\n三、核被告所為，係犯刑法第185 條之3 服用酒類不能安全駕駛\n    動力交通工具而駕駛罪。爰審酌被告前有多次酒後駕車之公\n    共危險前科紀錄，曾經法院判處罰金、拘役及有期徒刑在案\n    ，猶未能體認酒後駕車對一般往來之公眾及駕駛人自身皆具\n    有高度危險性，再度漠視自己安危，並罔顧公眾安全，於服\n    用酒類，酒後呼氣酒精濃度高達每公升1.22毫克，已處於不\n    能安全駕駛動力交通工具之狀態，仍率爾騎乘機車行駛於道\n    路上，對交通安全所生之危害非輕，及犯後坦承犯行態度良\n    好等一切情狀，參酌檢察官之具體求刑，量處如主文所示之\n    刑，並諭知易科罰金之折算標準，以資懲儆。\n據上論斷，應依刑事訴訟法第273 條之1 第1 項、第299 條第1\n項前段，刑法第185 條之3 、第41條第1 項前段，刑法施行法第\n1 條之1 第1 項，判決如主文。\n本案經檢察官楊景舜到庭執行職務。\n中    華    民    國   100    年    5     月    20    日\n                      交通法庭  法  官  廖欣儀\n以上正本證明與原本無異。\n如不服本判決應於收受判決後10日內向本院提出上訴書狀，並應\n敘述具體理由。其未敘述上訴理由者，應於上訴期間屆滿後20日\n內向本院補提理由書（均須按他造當事人之人數附繕本）「切勿\n逕送上級法院」。\n                                書記官  顏偉林"
  },
  "search": "臺灣板橋地方法院刑事判決100年度交易字第347號公訴人臺灣板橋地方法院檢察署檢察官被告劉健民上列被告因公共危險案件，經檢察官提起公訴（100年度偵字第8401號），被告於準備程序中就被訴事實為有罪之陳述，經本院裁定進行簡式審判程序，判決如下：主文劉健民服用酒類，不能安全駕駛動力交通工具而駕駛，處有期徒刑陸月，如易科罰金，以新臺幣壹仟元折算壹日。事實一、劉健民前因公共危險案件，經本院以98年度交簡字第1652號判處罰金新臺幣6萬元確定，又因公共危險案件，經本院以98年度交簡字第2576號判處拘役59日確定，於民國98年11月24日執行完畢；復因公共危險案件，經本院以99年度交簡字第5397號、99年度交簡字第第5273號分別判處有期徒刑3月、3月確定，嗣經本院以100年度聲字第1174號裁定應執行有期徒刑4月確定，於100年3月15日入監執行，尚未執行完畢（於本案均不構成累犯）。詎猶不知悔改，於100年3月14日11時至17時許，在新北市○○區○○路附近某工地內飲酒後，已達不能安全駕駛動力交通工具之程度，竟仍於同日21時20分許，騎乘車牌號碼GDE－323號重型機車，欲返回其新北市○○區○○路125巷22號住處。嗣於同日21時33分許，行經新北市○○區○○路135號前為警攔檢，經警對其施以呼氣酒精濃度測試，結果測得其呼氣中酒精濃度為每公升1.22毫克，因而查獲上情。二、案經新北市政府警察局新莊分局報告臺灣板橋地方法院檢察署檢察官偵查起訴。理由一、本件被告劉健民所犯為死刑、無期徒刑、最輕本刑為3年以上有期徒刑以外之罪，且非高等法院管轄第一審之案件，於本院準備程序進行中，被告就被訴事實為有罪之陳述，經告知被告簡式審判程序之旨，並聽取公訴人及被告之意見後，本院裁定進行簡式審判程序，合先敘明。二、上揭犯罪事實，業據被告於警詢、偵查及本院審理中坦承不諱，復有新北市政府警察局新莊分局當事人酒精測定紀錄表、刑法第185條之3案件測試觀察紀錄表、酒後時間確認單、新北市政府警察局舉發違反道路交通管理事件通知單各1紙附卷可稽，足見被告自白核與事實相符。從而，本案事證明確，被告犯行洵堪認定，應予依法論科。三、核被告所為，係犯刑法第185條之3服用酒類不能安全駕駛動力交通工具而駕駛罪。爰審酌被告前有多次酒後駕車之公共危險前科紀錄，曾經法院判處罰金、拘役及有期徒刑在案，猶未能體認酒後駕車對一般往來之公眾及駕駛人自身皆具有高度危險性，再度漠視自己安危，並罔顧公眾安全，於服用酒類，酒後呼氣酒精濃度高達每公升1.22毫克，已處於不能安全駕駛動力交通工具之狀態，仍率爾騎乘機車行駛於道路上，對交通安全所生之危害非輕，及犯後坦承犯行態度良好等一切情狀，參酌檢察官之具體求刑，量處如主文所示之刑，並諭知易科罰金之折算標準，以資懲儆。據上論斷，應依刑事訴訟法第273條之1第1項、第299條第1項前段，刑法第185條之3、第41條第1項前段，刑法施行法第1條之1第1項，判決如主文。本案經檢察官楊景舜到庭執行職務。中華民國100年5月20日交通法庭法官廖欣儀以上正本證明與原本無異。如不服本判決應於收受判決後10日內向本院提出上訴書狀，並應敘述具體理由。其未敘述上訴理由者，應於上訴期間屆滿後20日內向本院補提理由書（均須按他造當事人之人數附繕本）「切勿逕送上級法院」。書記官顏偉林中華民國100年5月20日附錄本案論罪科刑法條全文：中華民國刑法第185條之3服用毒品、麻醉藥品、酒類或其他相類之物，不能安全駕駛動力交通工具而駕駛者，處1年以下有期徒刑、拘役或科或併科15萬元以下罰金。",
  "characters": {
    "judges": [
      "廖欣儀"
    ],
    "prosecutors": [
      "楊景舜"
    ],
    "lawyers": [

    ],
    "clerks": [
      "顏偉林"
    ],
    "plaintiffs": [

    ],
    "defendants": [
      "劉健民"
    ],
    "prosecutor_office": [
      "臺灣板橋地方法院檢察署檢察官"
    ],
    "creditors": [

    ],
    "debtors": [

    ],
    "judicial_associate_officer": [

    ]
  },
  "adjudged_at": "2011-05-20",
  "created_at": "2016-02-12 03:11:37",
  "updated_at": "2016-02-12 03:11:37"
}