{
  "identify": "TCH-100-抗-201-20110519-1",
  "court": {
    "name": "臺灣高等法院",
    "code": "TCH"
  },
  "division": {
    "name": "民事",
    "code": "V"
  },
  "year": 100,
  "word": "抗",
  "number": "201",
  "jcheck": "1",
  "reason": "保全證據",
  "content": "臺灣高等法院臺中分院民事裁定          100年度抗字第201號\n抗  告  人  許福財\n上列抗告人與相對人吳牧典間聲請保全證據事件，對於民國100\n年3月9日臺灣彰化地方法院100年度聲字第1號所為裁定提起抗告\n，本院裁定如下：\n    主  文\n抗告駁回。\n抗告訴訟費用由抗告人負擔。\n    理  由\n一、按提起抗告，應於裁定送達後十日之不變期間內為之。民事\n    訴訟法第四百八十七條前段定有明文。又提起抗告，如逾抗\n    告期間者，原法院應以裁定駁回之。民事訴訟法第四百九十\n    五條之一第一項、第四百四十二條第一項亦著有明文。\n二、本件抗告人與相對人吳牧典間聲請保全證據事件，因抗告人\n    聲請保全證據，未據繳納裁判費，亦未盡釋明之責任，經原\n    法院於民國（下同）100年2月11日裁定駁回其聲請，該裁定\n    已於100年2月15日送達於抗告人，此有送達證書在卷可證。\n    抗告人遲至100年3月2日始提起抗告，已逾抗告期間，依前\n    揭規定，其抗告自非合法，原法院因而以抗告人之抗告不合\n    法為由，以裁定駁回其抗告，於法即無違誤。抗告意旨指摘\n    原裁定不當，求予廢棄，為無理由，其抗告應予駁回。\n三、據上論結，本件抗告為無理由。爰依民事訴訟法第四百九十\n    五條之一第一項、第四百四十九條第一項、第九十五條、第\n    七十八條，裁定如主文。\n中    華    民    國   100    年    5     月    19    日\n                民事第五庭    審判長法  官  李寶堂\n                                    法  官  王重吉\n                                    法  官  古金男\n以上正本係照原本作成。\n再為抗告應以適用法規顯有錯誤為理由。\n如提起再抗告者應於裁定送達後10日內向本院提出抗告理由狀（\n須按照他造人數附具繕本）並繳納抗告裁判費新臺幣1,000元，\n同時委任律師或具有律師資格之關係人為代理人。\n                                    書記官  瑞芳\n中    華    民    國   100    年    5     月    19    日\n                                                      Ｓ",
  "structure": {
    "main": "抗告駁回。\n抗告訴訟費用由抗告人負擔。",
    "reason": "一、按提起抗告，應於裁定送達後十日之不變期間內為之。民事\n    訴訟法第四百八十七條前段定有明文。又提起抗告，如逾抗\n    告期間者，原法院應以裁定駁回之。民事訴訟法第四百九十\n    五條之一第一項、第四百四十二條第一項亦著有明文。\n二、本件抗告人與相對人吳牧典間聲請保全證據事件，因抗告人\n    聲請保全證據，未據繳納裁判費，亦未盡釋明之責任，經原\n    法院於民國（下同）100年2月11日裁定駁回其聲請，該裁定\n    已於100年2月15日送達於抗告人，此有送達證書在卷可證。\n    抗告人遲至100年3月2日始提起抗告，已逾抗告期間，依前\n    揭規定，其抗告自非合法，原法院因而以抗告人之抗告不合\n    法為由，以裁定駁回其抗告，於法即無違誤。抗告意旨指摘\n    原裁定不當，求予廢棄，為無理由，其抗告應予駁回。\n三、據上論結，本件抗告為無理由。爰依民事訴訟法第四百九十\n    五條之一第一項、第四百四十九條第一項、第九十五條、第\n    七十八條，裁定如主文。"
  },
  "search": "臺灣高等法院臺中分院民事裁定100年度抗字第201號抗告人許福財上列抗告人與相對人吳牧典間聲請保全證據事件，對於民國100年3月9日臺灣彰化地方法院100年度聲字第1號所為裁定提起抗告，本院裁定如下：主文抗告駁回。抗告訴訟費用由抗告人負擔。理由一、按提起抗告，應於裁定送達後十日之不變期間內為之。民事訴訟法第四百八十七條前段定有明文。又提起抗告，如逾抗告期間者，原法院應以裁定駁回之。民事訴訟法第四百九十五條之一第一項、第四百四十二條第一項亦著有明文。二、本件抗告人與相對人吳牧典間聲請保全證據事件，因抗告人聲請保全證據，未據繳納裁判費，亦未盡釋明之責任，經原法院於民國（下同）100年2月11日裁定駁回其聲請，該裁定已於100年2月15日送達於抗告人，此有送達證書在卷可證。抗告人遲至100年3月2日始提起抗告，已逾抗告期間，依前揭規定，其抗告自非合法，原法院因而以抗告人之抗告不合法為由，以裁定駁回其抗告，於法即無違誤。抗告意旨指摘原裁定不當，求予廢棄，為無理由，其抗告應予駁回。三、據上論結，本件抗告為無理由。爰依民事訴訟法第四百九十五條之一第一項、第四百四十九條第一項、第九十五條、第七十八條，裁定如主文。中華民國100年5月19日民事第五庭審判長法官李寶堂法官王重吉法官古金男以上正本係照原本作成。再為抗告應以適用法規顯有錯誤為理由。如提起再抗告者應於裁定送達後10日內向本院提出抗告理由狀（須按照他造人數附具繕本）並繳納抗告裁判費新臺幣1,000元，同時委任律師或具有律師資格之關係人為代理人。書記官瑞芳中華民國100年5月19日Ｓ",
  "characters": {
    "judges": [
      "李寶堂",
      "王重吉",
      "古金男"
    ],
    "prosecutors": [

    ],
    "lawyers": [
      "同時委任律師或具有"
    ],
    "clerks": [
      "瑞芳"
    ],
    "plaintiffs": [

    ],
    "defendants": [

    ],
    "prosecutor_office": [

    ],
    "creditors": [

    ],
    "debtors": [

    ],
    "judicial_associate_officer": [

    ]
  },
  "adjudged_at": "2011-05-19",
  "created_at": "2016-02-12 03:02:06",
  "updated_at": "2016-02-12 03:02:06"
}