{
  "identify": "TPH-100-重交附民-1-20110519-1",
  "court": {
    "name": "臺灣高等法院",
    "code": "TPH"
  },
  "division": {
    "name": "刑事",
    "code": "M"
  },
  "year": 100,
  "word": "重交附民",
  "number": "1",
  "jcheck": "1",
  "reason": "過失傷害",
  "content": "臺灣高等法院刑事附帶民事訴訟裁定\n原      告  簡義哲\n被      告  林清彬\n被      告  竣茂工業有限公司\n法定代理人  王添丁\n上列被告等因過失傷害案件（本院100 年度交上易字第43號），\n經原告提起附帶民事訴訟請求損害賠償，本院裁定如下：\n    主  文\n本件附帶民事訴訟移送本院民事庭。\n    理  由\n一、被告林清彬雖具狀主張：被告林清彬與原告簡義哲間之過失\n    傷害案件，業經原審臺灣板橋地方法院諭知被告林清彬無罪\n    判決（99年度交易字第774 號），刑事附帶民事訴訟部分亦\n    因刑事訴訟諭知無罪而判決駁回；依刑事訴訟法第503 條第\n    2 項之規定，原告應先就刑事部分提起上訴後，於法定期間\n    內再就刑事附帶民事訴訟部分提起上訴，其程序始稱合法，\n    而不得於其訴被駁回後，另行起訴。職是，原告前開起訴不\n    合法，應予以駁回云云。然查：\n（一）被告林清彬與原告簡義哲間之過失傷害案件，確經原審即\n      臺灣板橋地方法院以99年度交易字第774 號判決被告林清\n      彬無罪，而刑事附帶民事訴訟部分亦因刑事訴訟諭知無罪\n      而判決駁回，有臺灣板橋地方法院99年度交重附民字第45\n      號刑事附帶民事訴訟判決書影本在卷可稽，是被告林清彬\n      此部分之主張，堪信為真實。\n（二）按提起附帶民事訴訟，應於刑事訴訟起訴後第二審辯論終\n      結前為之。但在第一審辯論終結後提起上訴前，不得提起\n      （刑事訴訟法第488 條參照）；立法者之所以會允許被害\n      人於刑事訴訟進行至第二審，附帶民事訴訟雖未於第一審\n      中提起，亦得提起者，乃為便利被害人而設。查原告簡義\n      哲於原審固曾提起刑事附帶民事訴訟，惟因刑事訴訟經判\n      決無罪，依據刑事訴訟法第503 條第1 項前段之規定，該\n      刑事附帶民事訴訟本應予以駁回；然而，前開駁回判決僅\n      係程序上判決而非實體上判決，自不生所謂既判力之效果\n      。是以，原告自可依據前開規定，於第二審辯護終結前再\n      次提起刑事附帶民事訴訟（最高法院37年10月1 日決議參\n      照）。又原告乃係在檢察官提起上訴繫屬本院、尚未辯論\n      終結前之100 年3 月14日提起本件之刑事附帶民事訴訟，\n      有本院收狀戳在卷可稽，則原告前開起訴確屬合法，毋庸\n      置疑。\n（三）刑事訴訟法第503 條第1 項、第2 項固有規定：刑事訴訟\n      諭知無罪之判決者，應以判決駁回原告之訴，而前開判決\n      ，非對於刑事訴訟之判決有上訴時，不得上訴；然該條項\n      之規定，主要係因為第一審既已辯論終結，其審判業已完\n      成，縱予提起，亦已不能合併審判；且對於第一審刑事判\n      決是否提起上訴又尚未決定，第二審刑事訴訟，是否開始\n      ，即屬無從知悉，是能否附帶合併審判，尚難以預料，故\n      在此期間內，規定不能提起附帶民事訴訟，以免提起而徒\n      勞。從而，自無法僅以此條項限制提起刑事附帶民事訴訟\n      期間之規定，即遽以擴張解釋原告僅能針對原審之程序判\n      決提起上訴，而不能於第二審辯論終結前再另行提起刑事\n      附帶民事訴訟，否則勢將違背立法者為便利被害人而特別\n      規定得於第二審辯論終結前提起刑事附帶民事訴訟之意旨\n      。\n（四）綜上，原告提起本件刑事附帶民事訴訟完全合法，被告林\n      清彬前開主張，顯有誤會，不足採信。\n二、原告提起本件刑事附帶民事訴訟，其主張之賠償金額高達新\n    臺幣7,479,708元，包括有醫療費用、看護費用、機車修繕\n    費用、交通費用、減少勞動力損失、精神慰撫金等，核其主\n    張之內容繁雜，非經長久之時日不能終結其審判，自應將本\n    件附帶民事訴訟移送本院民事庭。\n三、據上論結，應依刑事訴訟法第504 條第1 項前段之規定，裁\n    定如主文。\n中    華    民    國   100    年    5     月    19    日\n                  刑事第九庭  審判長法  官  陳貽男\n                                    法  官  蔡聰明\n                                    法  官  蔡守訓\n以上正本證明與原本無異。\n不得抗告。\n                                    書記官  許俊鴻\n中    華    民    國   100    年    5     月    19    日",
  "structure": {
    "main": "本件附帶民事訴訟移送本院民事庭。",
    "reason": "一、被告林清彬雖具狀主張：被告林清彬與原告簡義哲間之過失\n    傷害案件，業經原審臺灣板橋地方法院諭知被告林清彬無罪\n    判決（99年度交易字第774 號），刑事附帶民事訴訟部分亦\n    因刑事訴訟諭知無罪而判決駁回；依刑事訴訟法第503 條第\n    2 項之規定，原告應先就刑事部分提起上訴後，於法定期間\n    內再就刑事附帶民事訴訟部分提起上訴，其程序始稱合法，\n    而不得於其訴被駁回後，另行起訴。職是，原告前開起訴不\n    合法，應予以駁回云云。然查：\n（一）被告林清彬與原告簡義哲間之過失傷害案件，確經原審即\n      臺灣板橋地方法院以99年度交易字第774 號判決被告林清\n      彬無罪，而刑事附帶民事訴訟部分亦因刑事訴訟諭知無罪\n      而判決駁回，有臺灣板橋地方法院99年度交重附民字第45\n      號刑事附帶民事訴訟判決書影本在卷可稽，是被告林清彬\n      此部分之主張，堪信為真實。\n（二）按提起附帶民事訴訟，應於刑事訴訟起訴後第二審辯論終\n      結前為之。但在第一審辯論終結後提起上訴前，不得提起\n      （刑事訴訟法第488 條參照）；立法者之所以會允許被害\n      人於刑事訴訟進行至第二審，附帶民事訴訟雖未於第一審\n      中提起，亦得提起者，乃為便利被害人而設。查原告簡義\n      哲於原審固曾提起刑事附帶民事訴訟，惟因刑事訴訟經判\n      決無罪，依據刑事訴訟法第503 條第1 項前段之規定，該\n      刑事附帶民事訴訟本應予以駁回；然而，前開駁回判決僅\n      係程序上判決而非實體上判決，自不生所謂既判力之效果\n      。是以，原告自可依據前開規定，於第二審辯護終結前再\n      次提起刑事附帶民事訴訟（最高法院37年10月1 日決議參\n      照）。又原告乃係在檢察官提起上訴繫屬本院、尚未辯論\n      終結前之100 年3 月14日提起本件之刑事附帶民事訴訟，\n      有本院收狀戳在卷可稽，則原告前開起訴確屬合法，毋庸\n      置疑。\n（三）刑事訴訟法第503 條第1 項、第2 項固有規定：刑事訴訟\n      諭知無罪之判決者，應以判決駁回原告之訴，而前開判決\n      ，非對於刑事訴訟之判決有上訴時，不得上訴；然該條項\n      之規定，主要係因為第一審既已辯論終結，其審判業已完\n      成，縱予提起，亦已不能合併審判；且對於第一審刑事判\n      決是否提起上訴又尚未決定，第二審刑事訴訟，是否開始\n      ，即屬無從知悉，是能否附帶合併審判，尚難以預料，故\n      在此期間內，規定不能提起附帶民事訴訟，以免提起而徒\n      勞。從而，自無法僅以此條項限制提起刑事附帶民事訴訟\n      期間之規定，即遽以擴張解釋原告僅能針對原審之程序判\n      決提起上訴，而不能於第二審辯論終結前再另行提起刑事\n      附帶民事訴訟，否則勢將違背立法者為便利被害人而特別\n      規定得於第二審辯論終結前提起刑事附帶民事訴訟之意旨\n      。\n（四）綜上，原告提起本件刑事附帶民事訴訟完全合法，被告林\n      清彬前開主張，顯有誤會，不足採信。\n二、原告提起本件刑事附帶民事訴訟，其主張之賠償金額高達新\n    臺幣7,479,708元，包括有醫療費用、看護費用、機車修繕\n    費用、交通費用、減少勞動力損失、精神慰撫金等，核其主\n    張之內容繁雜，非經長久之時日不能終結其審判，自應將本\n    件附帶民事訴訟移送本院民事庭。\n三、據上論結，應依刑事訴訟法第504 條第1 項前段之規定，裁\n    定如主文。"
  },
  "search": "臺灣高等法院刑事附帶民事訴訟裁定原告簡義哲被告林清彬被告竣茂工業有限公司法定代理人王添丁上列被告等因過失傷害案件（本院100年度交上易字第43號），經原告提起附帶民事訴訟請求損害賠償，本院裁定如下：主文本件附帶民事訴訟移送本院民事庭。理由一、被告林清彬雖具狀主張：被告林清彬與原告簡義哲間之過失傷害案件，業經原審臺灣板橋地方法院諭知被告林清彬無罪判決（99年度交易字第774號），刑事附帶民事訴訟部分亦因刑事訴訟諭知無罪而判決駁回；依刑事訴訟法第503條第2項之規定，原告應先就刑事部分提起上訴後，於法定期間內再就刑事附帶民事訴訟部分提起上訴，其程序始稱合法，而不得於其訴被駁回後，另行起訴。職是，原告前開起訴不合法，應予以駁回云云。然查：（一）被告林清彬與原告簡義哲間之過失傷害案件，確經原審即臺灣板橋地方法院以99年度交易字第774號判決被告林清彬無罪，而刑事附帶民事訴訟部分亦因刑事訴訟諭知無罪而判決駁回，有臺灣板橋地方法院99年度交重附民字第45號刑事附帶民事訴訟判決書影本在卷可稽，是被告林清彬此部分之主張，堪信為真實。（二）按提起附帶民事訴訟，應於刑事訴訟起訴後第二審辯論終結前為之。但在第一審辯論終結後提起上訴前，不得提起（刑事訴訟法第488條參照）；立法者之所以會允許被害人於刑事訴訟進行至第二審，附帶民事訴訟雖未於第一審中提起，亦得提起者，乃為便利被害人而設。查原告簡義哲於原審固曾提起刑事附帶民事訴訟，惟因刑事訴訟經判決無罪，依據刑事訴訟法第503條第1項前段之規定，該刑事附帶民事訴訟本應予以駁回；然而，前開駁回判決僅係程序上判決而非實體上判決，自不生所謂既判力之效果。是以，原告自可依據前開規定，於第二審辯護終結前再次提起刑事附帶民事訴訟（最高法院37年10月1日決議參照）。又原告乃係在檢察官提起上訴繫屬本院、尚未辯論終結前之100年3月14日提起本件之刑事附帶民事訴訟，有本院收狀戳在卷可稽，則原告前開起訴確屬合法，毋庸置疑。（三）刑事訴訟法第503條第1項、第2項固有規定：刑事訴訟諭知無罪之判決者，應以判決駁回原告之訴，而前開判決，非對於刑事訴訟之判決有上訴時，不得上訴；然該條項之規定，主要係因為第一審既已辯論終結，其審判業已完成，縱予提起，亦已不能合併審判；且對於第一審刑事判決是否提起上訴又尚未決定，第二審刑事訴訟，是否開始，即屬無從知悉，是能否附帶合併審判，尚難以預料，故在此期間內，規定不能提起附帶民事訴訟，以免提起而徒勞。從而，自無法僅以此條項限制提起刑事附帶民事訴訟期間之規定，即遽以擴張解釋原告僅能針對原審之程序判決提起上訴，而不能於第二審辯論終結前再另行提起刑事附帶民事訴訟，否則勢將違背立法者為便利被害人而特別規定得於第二審辯論終結前提起刑事附帶民事訴訟之意旨。（四）綜上，原告提起本件刑事附帶民事訴訟完全合法，被告林清彬前開主張，顯有誤會，不足採信。二、原告提起本件刑事附帶民事訴訟，其主張之賠償金額高達新臺幣7,479,708元，包括有醫療費用、看護費用、機車修繕費用、交通費用、減少勞動力損失、精神慰撫金等，核其主張之內容繁雜，非經長久之時日不能終結其審判，自應將本件附帶民事訴訟移送本院民事庭。三、據上論結，應依刑事訴訟法第504條第1項前段之規定，裁定如主文。中華民國100年5月19日刑事第九庭審判長法官陳貽男法官蔡聰明法官蔡守訓以上正本證明與原本無異。不得抗告。書記官許俊鴻中華民國100年5月19日",
  "characters": {
    "judges": [
      "陳貽男",
      "蔡聰明",
      "蔡守訓"
    ],
    "prosecutors": [

    ],
    "lawyers": [

    ],
    "clerks": [
      "許俊鴻"
    ],
    "plaintiffs": [
      "簡義哲"
    ],
    "defendants": [
      "林清彬",
      "被      告  竣茂工業有限公司"
    ],
    "prosecutor_office": [

    ],
    "creditors": [

    ],
    "debtors": [

    ],
    "judicial_associate_officer": [

    ]
  },
  "adjudged_at": "2011-05-19",
  "created_at": "2016-02-12 03:14:34",
  "updated_at": "2016-02-12 03:14:34"
}