{
  "identify": "CHD-100-簡-868-20110729-1",
  "court": {
    "name": "臺灣彰化地方法院",
    "code": "CHD"
  },
  "division": {
    "name": "刑事",
    "code": "M"
  },
  "year": 100,
  "word": "簡",
  "number": "868",
  "jcheck": "1",
  "reason": "詐欺",
  "content": "臺灣彰化地方法院刑事簡易判決          100年度簡字第868號\n聲  請  人  臺灣彰化地方法院檢察署檢察官\n被      告  吳敏真\n上列被告詐欺案件，經檢察官聲請簡易判決處刑（100年度偵字\n第816號），本院判決如下：\n    主  文\n吳敏真幫助意圖為自己不法之所有，以詐術使人將本人之物交付\n，處有期徒刑貳月，如易科罰金，以銀元參佰元即新臺幣玖佰元\n折算壹日；減為有期徒刑壹月，如易科罰金，以銀元參佰元即新\n臺幣玖佰元折算壹日。緩刑貳年。\n    犯罪事實及理由\n一、本件犯罪事實及證據名稱，均與檢察官聲請簡易判決處刑書\n    之記載相同，茲引用如附件。\n二、查本案被告行為後，刑法及刑法施行法業於民國94年2 月2\n    日經總統以華總一義字第09400014901 號令修正公布，並於\n    95 年7月1 日施行。按行為後法律有變更者，適用行為時之\n    法律，但行為後之法律有利於行為人者，適用最有利於行為\n    人之法律，現行刑法第2 條第1 項定有明文。此條規定乃與\n    刑法第1 條罪刑法定主義契合，而貫徹法律禁止溯及既往原\n    則，係規範行為後法律變更所生新舊法律比較適用之準據法\n    ，是刑法第2 條本身雖經修正，但刑法第2 條既屬適用法律\n    之準據法，本身尚無比較新舊法之問題，應一律適用裁判時\n    之現行刑法第2 條規定以決定適用之刑罰法律，先予辨明。\n    又以本次刑法修正之比較新舊法，應就罪刑有關之共犯、未\n    遂犯、想像競合犯、牽連犯、連續犯、結合犯，以及累犯加\n    重、自首減輕暨其他法定加減原因（如身分加減）與加減例\n    等一切情形，本於統一性及整體性原則，綜其全部罪刑之結\n    果而為比較，亦有最高法院95年度第8 次刑庭會議決議可資\n    參照。是就新舊法比較如下：\n（一）關於罰金刑：\n      修正後刑法第33條第5 款規定，已將原罰金刑最低額度由\n      銀元1 元（相當於新臺幣3 元），提高為新臺幣1 千元以\n      上，且以百元計之，比較新、舊法結果，應以被告行為時\n      即修正前刑法第33條第5 款規定有利於被告。\n（二）關於幫助犯：\n      刑法第30條第1 項、第2 項修正前規定為：「幫助他人犯\n      罪者，為從犯。雖他人不知幫助之情者，亦同。從犯之處\n      罰，得按正犯之刑減輕之」，修正後則為：「幫助他人實\n      行犯罪行為者，為幫助犯。雖他人不知幫助之情者，亦同\n      。幫助犯之處罰，得按正犯之刑減輕之」，係將「從犯」\n      修正為「幫助犯」，並明示幫助犯之成立，應以被幫助者\n      著手犯罪之實行，且具備違法性為必要，至於被幫助者是\n      否具有有責性，則不影響幫助犯之成立，而幫助犯之刑仍\n      維持依正犯之刑減輕之效果，此有修正理由可資參照。基\n      此，本案被告幫助他人所為之詐欺犯行既均已既遂，則無\n      論依照修正前或修正後刑法第30條第1 項、第2 項，對於\n      被告並無有利不利之別，並無比較新舊法之必要，故應逕\n      適用修正後之刑法第30條第1 項、第2 項論擬。\n（三）另被告行為時，本件據以論罪科刑之刑法第339 條法定刑\n      中罰金刑部分，應適用廢止前罰金罰鍰提高標準條例第1\n      條前段，依行政院會銜司法院所定標準提高至10倍，經依\n      現行法規所定貨幣單位折算新臺幣條例第2 條規定，折算\n      為新臺幣後內容為：或科或併科新臺幣3 萬元以下罰金。\n      而刑法施行法於95年6 月14日修正增訂第1 條之1 ，其第\n      1 項、第2 項規定：「中華民國94年1 月7 日刑法修正施\n      行後，刑法分則編所定罰金之貨幣單位為新臺幣。94年1\n      月7 日刑法修正時，刑法分則編未修正之條文定有罰金者\n      ，自94年1 月7 日刑法修正施行後，就其所定數額提高為\n      30倍。但72年6 月26日至96年1 月7 日新增或修正之條文\n      ，就其所定數額提高為3 倍。」查刑法第339 條自24年7\n      月1 日刑法施行起迄今未經修正，其法定刑罰金部分依照\n      前開規定，應變更為：或新臺幣3 萬元罰金。修正增訂前\n      後，其實質內容並無變更。另觀諸刑法施行法第1 條之1\n      立法理由謂：因應刑法增修條文施行後，刑法第33條第5\n      款規定，罰金貨幣單位已改為新臺幣，是以同法各罪所定\n      罰金貨幣單位，自應配合上開規定修正；且因不再適用現\n      行法規所定貨幣單位折算新臺幣條例，為使罰金數額趨於\n      一致，避免衍生新舊法比較適用問題，以緩和實務適用法\n      律之衝擊，於不變動罰金數額之前提下，而為制定。可見\n      刑法施行法第1 條之1 規定，係為取代廢止前罰金罰鍰提\n      高標準條例第1 條及現行法規所定貨幣單位折算新臺幣條\n      例第2 條而制定，具有新舊法律比較之特別準據法性質，\n      此部分自無刑法第2 條第1 項新舊法比較之問題，應逕適\n      用刑法施行法第1 條之1 第1 項、第2 項前段準據法之特\n      別規定，調整刑法第339條之法定刑，附此敘明。\n三、論罪科刑:\n（一）按刑法上之幫助犯，係對於犯罪與正犯有共同之認識，而\n      以幫助之意思，對於正犯資以助力，而未參與實施犯罪之\n      行為者而言（最高法院75年度臺上字第1509號、88年度臺\n      上字第1270號判決意旨可資參照）。是以，如未參與實施\n      犯罪構成要件之行為，且係出於幫助之意思提供助力，即\n      屬幫助犯，而非共同正犯。查前揭真實姓名、年籍均不詳\n      之詐欺集團成年人，基於意圖為自己不法所有之犯意，以\n      上述之方式，使被害人簡正宇陷於錯誤，因而交付本人之\n      財物，該詐欺集團成員所為，係犯刑法第339 條第1 項之\n      詐欺取財罪。被告雖有將本案帳戶之存摺、提款卡及密碼\n      提供予施以詐騙者使用，已如前述，惟既未見其有何參與\n      詐騙被害人行為之積極證據，固無從認屬上開詐欺取財行\n      為之共同正犯。然而，被告將其所有之帳戶提供予他人作\n      為詐欺取財之指定帳戶，乃係基於幫助他人詐欺取財之犯\n      意，而被告提供上揭帳戶予他人之行為，復屬詐欺取財構\n      成要件以外之行為，則被告自屬以幫助之意思，參與詐欺\n      取財構成要件以外之行為，是核被告吳敏真所為，係犯刑\n      法第30條第1 項前段、第339 條第1 項之幫助詐欺取財罪\n      。本案被告幫助他人犯詐欺取財罪，為從犯，本院衡其犯\n      罪情節較正犯為輕，爰依刑法第30 條 第2 項之規定，按\n      正犯之刑減輕之。爰審酌近年來詐欺集團橫行，受害者眾\n      ，破壞社會善良風氣，造成人心不安，被告任意提供帳戶\n      供他人作為實施詐欺取財犯罪之用，使警察機關難以追查\n      詐欺集團，致損害社會金融體系及妨礙民眾對他人之信賴\n      ，其犯罪所生之危害非輕，兼衡本件被害人因遭詐騙而匯\n      入被告帳戶之金額，及其犯罪動機、目的、手段及犯後態\n      度，且已與被害人簡正宇調解成立，願賠償被害人新臺幣\n      5 萬元（已賠償完畢，有被害人簡正宇於100 年7 月6 日\n      所具書狀傳真到院可參），被害人並允諾不再追究被告刑\n      事責任，有本院100 年度司斗刑簡暫調字第35號調解程序\n      筆錄附卷足稽，顯有悔意，並審之檢察官求處有期徒刑2\n      月等一切情狀，量處如主文所示之刑，並依下列所述諭知\n      易科罰金之折算標準。\n（二）茲被告行為時刑法第41條第1 項前段規定：「犯最重本刑\n      為5 年以下有期徒刑以下之刑之罪，而受6 個月以下有期\n      徒刑或拘役之宣告，因身體、教育、職業、家庭之關係或\n      其他正當事由，執行顯有困難者，得以1 元以上3 元以下\n      折算1 日，易科罰金。」而被告行為時易科罰金之折算標\n      準，依修正刪除前罰金罰鍰提高標準條例第2 條前段規定\n      ，係就原定數額提高為以100 倍折算1 日，則本件被告行\n      為時之易科罰金折算標準，係以銀元300 元折算1 日，經\n      折算為新臺幣後，應以新臺幣900 元折算為1 日。惟95\n      年7 月1 日施行之刑法第41條第1 項前段規定：「犯最重\n      本刑為5 年以下有期徒刑以下之刑之罪，而受6 個月以下\n      有期徒刑或拘役之宣告者，得以新臺幣1000元、2000元或\n      3000元折算1 日，易科罰金。」比較修正前後之易科罰金\n      折算標準，以95年7 月1 日修正公布施行前之規定，較有\n      利於受刑人。是被告上開94年間之犯行，自應依刑法第2\n      條第1 項前段，適用修正前刑法第41條第1 項前段規定及\n      修正刪除前罰金罰鍰提高標準條例第2 條前段規定，諭知\n      易科罰金之折算標準。\n（三）再查本案正犯之犯罪時間係在96年4 月24日以前，合於中\n      華民國九十六年罪犯減刑條例所定得予減刑之規定，應依\n      同條例第2 條第1 項第3 款、第7 條之規定減刑如主文所\n      示，併諭知易科罰金之折算標準，附此敘明。\n（四）按犯罪在新法施行前，新法施行後緩刑之宣告應適用新法\n      第74條規定（最高法院95年度第8 次刑事庭會議決議意旨\n      參照）。查被告前未曾因故意犯罪受有期徒刑以上刑之宣\n      告，有臺灣高等法院被告前案紀錄表1 份在卷可稽，此次\n      因一時失慮，致罹刑典，事後已坦承犯行，深具悔意，且\n      有如前開所述與被害人達成調解，本院認被告經此偵審教\n      訓，自當知所警惕，信無再犯之虞，因認前開宣告之刑以\n      暫不執行為適當，併依刑法第74條第1 項第1 款諭知緩刑\n      2 年。\n（五）被告交付予不法犯罪集團成員之前開存摺（含提款卡及密\n      碼），雖係被告供犯罪所用之物，然既已交付該集團使用\n      ，顯已移轉其所有權予該集團，而非被告所有，且均非違\n      禁物，亦別無證據足資證明係屬應沒收之物，爰不另宣告\n      沒收。況查所謂幫助犯係指就他人之犯罪加以助力，使其\n      易於實施之積極的或消極的行為而言，其犯罪態樣與實施\n      犯罪之正犯有異，其所處罰者，乃其提供助力之行為本身\n      ，而非正犯實施犯罪之行為。因此幫助犯不適用責任共同\n      之原則，對正犯所有供犯罪所用或因犯罪所得之物，勿庸\n      併為沒收之宣告（最高法院88年度臺上字第6234號判決要\n      旨參照），是前開存摺（含提款卡、密碼）雖係不法犯罪\n      集團所有供犯罪所用之物，對於幫助犯之被告，自毋庸宣\n      告沒收，附此敘明。\n四、應適用之法條：\n（一）刑事訴訟法第449條第1項、第454條第2項。\n（二）刑法第2 條第1 項前段、第30條第1 項前段、第2 項、第\n      339 條第1 項、第74條第1 項第1 款、修正前第41條第1\n      項前段。\n（三）刑法施行法第1條之1第1項、第2項前段。\n（四）修正刪除前之罰金罰緩提高標準條例第2 條。\n（五）中華民國九十六年罪犯減刑條例第2 條第1 項第3 款、第\n      7 條、第9條，逕以簡易判決處刑如主文。\n五、如不服本判決，得於判決書送達之日起10日內，以書狀敘述\n    理由，向本院提起上訴。\n中    華    民    國   100    年    7     月    29    日\n                        刑事第五庭    法  官  周淡怡\n以上正本證明與原本無異。\n如不服本件判決，得自收受送達之日起10日內，表明上訴理由，\n向本院提起上訴狀（須附繕本）。\n告訴人或被害人對於判決如有不服具備理由請求檢察官上訴者，\n其上訴期間之計算係以檢察官收受判決正本之日期為準。\n中    華    民    國   100    年    7     月    29    日\n                                      書記官  陳文新\n附錄：論罪科刑法條：\n中華民國刑法第339條\n意圖為自己或第3 人不法之所有，以詐術使人將本人或第3 人之\n物交付者，處5 年以下有期徒刑、拘役或科或併科1,000 元以下\n罰金。\n以前項方法得財產上不法之利益或使第3人得之者，亦同。\n前2項之未遂犯罰之。",
  "structure": {
    "main": "吳敏真幫助意圖為自己不法之所有，以詐術使人將本人之物交付\n，處有期徒刑貳月，如易科罰金，以銀元參佰元即新臺幣玖佰元\n折算壹日；減為有期徒刑壹月，如易科罰金，以銀元參佰元即新\n臺幣玖佰元折算壹日。緩刑貳年。",
    "fact": "一、本件犯罪事實及證據名稱，均與檢察官聲請簡易判決處刑書\n    之記載相同，茲引用如附件。\n二、查本案被告行為後，刑法及刑法施行法業於民國94年2 月2\n    日經總統以華總一義字第09400014901 號令修正公布，並於\n    95 年7月1 日施行。按行為後法律有變更者，適用行為時之\n    法律，但行為後之法律有利於行為人者，適用最有利於行為\n    人之法律，現行刑法第2 條第1 項定有明文。此條規定乃與\n    刑法第1 條罪刑法定主義契合，而貫徹法律禁止溯及既往原\n    則，係規範行為後法律變更所生新舊法律比較適用之準據法\n    ，是刑法第2 條本身雖經修正，但刑法第2 條既屬適用法律\n    之準據法，本身尚無比較新舊法之問題，應一律適用裁判時\n    之現行刑法第2 條規定以決定適用之刑罰法律，先予辨明。\n    又以本次刑法修正之比較新舊法，應就罪刑有關之共犯、未\n    遂犯、想像競合犯、牽連犯、連續犯、結合犯，以及累犯加\n    重、自首減輕暨其他法定加減原因（如身分加減）與加減例\n    等一切情形，本於統一性及整體性原則，綜其全部罪刑之結\n    果而為比較，亦有最高法院95年度第8 次刑庭會議決議可資\n    參照。是就新舊法比較如下：\n（一）關於罰金刑：\n      修正後刑法第33條第5 款規定，已將原罰金刑最低額度由\n      銀元1 元（相當於新臺幣3 元），提高為新臺幣1 千元以\n      上，且以百元計之，比較新、舊法結果，應以被告行為時\n      即修正前刑法第33條第5 款規定有利於被告。\n（二）關於幫助犯：\n      刑法第30條第1 項、第2 項修正前規定為：「幫助他人犯\n      罪者，為從犯。雖他人不知幫助之情者，亦同。從犯之處\n      罰，得按正犯之刑減輕之」，修正後則為：「幫助他人實\n      行犯罪行為者，為幫助犯。雖他人不知幫助之情者，亦同\n      。幫助犯之處罰，得按正犯之刑減輕之」，係將「從犯」\n      修正為「幫助犯」，並明示幫助犯之成立，應以被幫助者\n      著手犯罪之實行，且具備違法性為必要，至於被幫助者是\n      否具有有責性，則不影響幫助犯之成立，而幫助犯之刑仍\n      維持依正犯之刑減輕之效果，此有修正理由可資參照。基\n      此，本案被告幫助他人所為之詐欺犯行既均已既遂，則無\n      論依照修正前或修正後刑法第30條第1 項、第2 項，對於\n      被告並無有利不利之別，並無比較新舊法之必要，故應逕\n      適用修正後之刑法第30條第1 項、第2 項論擬。\n（三）另被告行為時，本件據以論罪科刑之刑法第339 條法定刑\n      中罰金刑部分，應適用廢止前罰金罰鍰提高標準條例第1\n      條前段，依行政院會銜司法院所定標準提高至10倍，經依\n      現行法規所定貨幣單位折算新臺幣條例第2 條規定，折算\n      為新臺幣後內容為：或科或併科新臺幣3 萬元以下罰金。\n      而刑法施行法於95年6 月14日修正增訂第1 條之1 ，其第\n      1 項、第2 項規定：「中華民國94年1 月7 日刑法修正施\n      行後，刑法分則編所定罰金之貨幣單位為新臺幣。94年1\n      月7 日刑法修正時，刑法分則編未修正之條文定有罰金者\n      ，自94年1 月7 日刑法修正施行後，就其所定數額提高為\n      30倍。但72年6 月26日至96年1 月7 日新增或修正之條文\n      ，就其所定數額提高為3 倍。」查刑法第339 條自24年7\n      月1 日刑法施行起迄今未經修正，其法定刑罰金部分依照\n      前開規定，應變更為：或新臺幣3 萬元罰金。修正增訂前\n      後，其實質內容並無變更。另觀諸刑法施行法第1 條之1\n      立法理由謂：因應刑法增修條文施行後，刑法第33條第5\n      款規定，罰金貨幣單位已改為新臺幣，是以同法各罪所定\n      罰金貨幣單位，自應配合上開規定修正；且因不再適用現\n      行法規所定貨幣單位折算新臺幣條例，為使罰金數額趨於\n      一致，避免衍生新舊法比較適用問題，以緩和實務適用法\n      律之衝擊，於不變動罰金數額之前提下，而為制定。可見\n      刑法施行法第1 條之1 規定，係為取代廢止前罰金罰鍰提\n      高標準條例第1 條及現行法規所定貨幣單位折算新臺幣條\n      例第2 條而制定，具有新舊法律比較之特別準據法性質，\n      此部分自無刑法第2 條第1 項新舊法比較之問題，應逕適\n      用刑法施行法第1 條之1 第1 項、第2 項前段準據法之特\n      別規定，調整刑法第339條之法定刑，附此敘明。\n三、論罪科刑:\n（一）按刑法上之幫助犯，係對於犯罪與正犯有共同之認識，而\n      以幫助之意思，對於正犯資以助力，而未參與實施犯罪之\n      行為者而言（最高法院75年度臺上字第1509號、88年度臺\n      上字第1270號判決意旨可資參照）。是以，如未參與實施\n      犯罪構成要件之行為，且係出於幫助之意思提供助力，即\n      屬幫助犯，而非共同正犯。查前揭真實姓名、年籍均不詳\n      之詐欺集團成年人，基於意圖為自己不法所有之犯意，以\n      上述之方式，使被害人簡正宇陷於錯誤，因而交付本人之\n      財物，該詐欺集團成員所為，係犯刑法第339 條第1 項之\n      詐欺取財罪。被告雖有將本案帳戶之存摺、提款卡及密碼\n      提供予施以詐騙者使用，已如前述，惟既未見其有何參與\n      詐騙被害人行為之積極證據，固無從認屬上開詐欺取財行\n      為之共同正犯。然而，被告將其所有之帳戶提供予他人作\n      為詐欺取財之指定帳戶，乃係基於幫助他人詐欺取財之犯\n      意，而被告提供上揭帳戶予他人之行為，復屬詐欺取財構\n      成要件以外之行為，則被告自屬以幫助之意思，參與詐欺\n      取財構成要件以外之行為，是核被告吳敏真所為，係犯刑\n      法第30條第1 項前段、第339 條第1 項之幫助詐欺取財罪\n      。本案被告幫助他人犯詐欺取財罪，為從犯，本院衡其犯\n      罪情節較正犯為輕，爰依刑法第30 條 第2 項之規定，按\n      正犯之刑減輕之。爰審酌近年來詐欺集團橫行，受害者眾\n      ，破壞社會善良風氣，造成人心不安，被告任意提供帳戶\n      供他人作為實施詐欺取財犯罪之用，使警察機關難以追查\n      詐欺集團，致損害社會金融體系及妨礙民眾對他人之信賴\n      ，其犯罪所生之危害非輕，兼衡本件被害人因遭詐騙而匯\n      入被告帳戶之金額，及其犯罪動機、目的、手段及犯後態\n      度，且已與被害人簡正宇調解成立，願賠償被害人新臺幣\n      5 萬元（已賠償完畢，有被害人簡正宇於100 年7 月6 日\n      所具書狀傳真到院可參），被害人並允諾不再追究被告刑\n      事責任，有本院100 年度司斗刑簡暫調字第35號調解程序\n      筆錄附卷足稽，顯有悔意，並審之檢察官求處有期徒刑2\n      月等一切情狀，量處如主文所示之刑，並依下列所述諭知\n      易科罰金之折算標準。\n（二）茲被告行為時刑法第41條第1 項前段規定：「犯最重本刑\n      為5 年以下有期徒刑以下之刑之罪，而受6 個月以下有期\n      徒刑或拘役之宣告，因身體、教育、職業、家庭之關係或\n      其他正當事由，執行顯有困難者，得以1 元以上3 元以下\n      折算1 日，易科罰金。」而被告行為時易科罰金之折算標\n      準，依修正刪除前罰金罰鍰提高標準條例第2 條前段規定\n      ，係就原定數額提高為以100 倍折算1 日，則本件被告行\n      為時之易科罰金折算標準，係以銀元300 元折算1 日，經\n      折算為新臺幣後，應以新臺幣900 元折算為1 日。惟95\n      年7 月1 日施行之刑法第41條第1 項前段規定：「犯最重\n      本刑為5 年以下有期徒刑以下之刑之罪，而受6 個月以下\n      有期徒刑或拘役之宣告者，得以新臺幣1000元、2000元或\n      3000元折算1 日，易科罰金。」比較修正前後之易科罰金\n      折算標準，以95年7 月1 日修正公布施行前之規定，較有\n      利於受刑人。是被告上開94年間之犯行，自應依刑法第2\n      條第1 項前段，適用修正前刑法第41條第1 項前段規定及\n      修正刪除前罰金罰鍰提高標準條例第2 條前段規定，諭知\n      易科罰金之折算標準。\n（三）再查本案正犯之犯罪時間係在96年4 月24日以前，合於中\n      華民國九十六年罪犯減刑條例所定得予減刑之規定，應依\n      同條例第2 條第1 項第3 款、第7 條之規定減刑如主文所\n      示，併諭知易科罰金之折算標準，附此敘明。\n（四）按犯罪在新法施行前，新法施行後緩刑之宣告應適用新法\n      第74條規定（最高法院95年度第8 次刑事庭會議決議意旨\n      參照）。查被告前未曾因故意犯罪受有期徒刑以上刑之宣\n      告，有臺灣高等法院被告前案紀錄表1 份在卷可稽，此次\n      因一時失慮，致罹刑典，事後已坦承犯行，深具悔意，且\n      有如前開所述與被害人達成調解，本院認被告經此偵審教\n      訓，自當知所警惕，信無再犯之虞，因認前開宣告之刑以\n      暫不執行為適當，併依刑法第74條第1 項第1 款諭知緩刑\n      2 年。\n（五）被告交付予不法犯罪集團成員之前開存摺（含提款卡及密\n      碼），雖係被告供犯罪所用之物，然既已交付該集團使用\n      ，顯已移轉其所有權予該集團，而非被告所有，且均非違\n      禁物，亦別無證據足資證明係屬應沒收之物，爰不另宣告\n      沒收。況查所謂幫助犯係指就他人之犯罪加以助力，使其\n      易於實施之積極的或消極的行為而言，其犯罪態樣與實施\n      犯罪之正犯有異，其所處罰者，乃其提供助力之行為本身\n      ，而非正犯實施犯罪之行為。因此幫助犯不適用責任共同\n      之原則，對正犯所有供犯罪所用或因犯罪所得之物，勿庸\n      併為沒收之宣告（最高法院88年度臺上字第6234號判決要\n      旨參照），是前開存摺（含提款卡、密碼）雖係不法犯罪\n      集團所有供犯罪所用之物，對於幫助犯之被告，自毋庸宣\n      告沒收，附此敘明。\n四、應適用之法條：\n（一）刑事訴訟法第449條第1項、第454條第2項。\n（二）刑法第2 條第1 項前段、第30條第1 項前段、第2 項、第\n      339 條第1 項、第74條第1 項第1 款、修正前第41條第1\n      項前段。\n（三）刑法施行法第1條之1第1項、第2項前段。\n（四）修正刪除前之罰金罰緩提高標準條例第2 條。\n（五）中華民國九十六年罪犯減刑條例第2 條第1 項第3 款、第\n      7 條、第9條，逕以簡易判決處刑如主文。\n五、如不服本判決，得於判決書送達之日起10日內，以書狀敘述\n    理由，向本院提起上訴。",
    "reason": "一、本件犯罪事實及證據名稱，均與檢察官聲請簡易判決處刑書\n    之記載相同，茲引用如附件。\n二、查本案被告行為後，刑法及刑法施行法業於民國94年2 月2\n    日經總統以華總一義字第09400014901 號令修正公布，並於\n    95 年7月1 日施行。按行為後法律有變更者，適用行為時之\n    法律，但行為後之法律有利於行為人者，適用最有利於行為\n    人之法律，現行刑法第2 條第1 項定有明文。此條規定乃與\n    刑法第1 條罪刑法定主義契合，而貫徹法律禁止溯及既往原\n    則，係規範行為後法律變更所生新舊法律比較適用之準據法\n    ，是刑法第2 條本身雖經修正，但刑法第2 條既屬適用法律\n    之準據法，本身尚無比較新舊法之問題，應一律適用裁判時\n    之現行刑法第2 條規定以決定適用之刑罰法律，先予辨明。\n    又以本次刑法修正之比較新舊法，應就罪刑有關之共犯、未\n    遂犯、想像競合犯、牽連犯、連續犯、結合犯，以及累犯加\n    重、自首減輕暨其他法定加減原因（如身分加減）與加減例\n    等一切情形，本於統一性及整體性原則，綜其全部罪刑之結\n    果而為比較，亦有最高法院95年度第8 次刑庭會議決議可資\n    參照。是就新舊法比較如下：\n（一）關於罰金刑：\n      修正後刑法第33條第5 款規定，已將原罰金刑最低額度由\n      銀元1 元（相當於新臺幣3 元），提高為新臺幣1 千元以\n      上，且以百元計之，比較新、舊法結果，應以被告行為時\n      即修正前刑法第33條第5 款規定有利於被告。\n（二）關於幫助犯：\n      刑法第30條第1 項、第2 項修正前規定為：「幫助他人犯\n      罪者，為從犯。雖他人不知幫助之情者，亦同。從犯之處\n      罰，得按正犯之刑減輕之」，修正後則為：「幫助他人實\n      行犯罪行為者，為幫助犯。雖他人不知幫助之情者，亦同\n      。幫助犯之處罰，得按正犯之刑減輕之」，係將「從犯」\n      修正為「幫助犯」，並明示幫助犯之成立，應以被幫助者\n      著手犯罪之實行，且具備違法性為必要，至於被幫助者是\n      否具有有責性，則不影響幫助犯之成立，而幫助犯之刑仍\n      維持依正犯之刑減輕之效果，此有修正理由可資參照。基\n      此，本案被告幫助他人所為之詐欺犯行既均已既遂，則無\n      論依照修正前或修正後刑法第30條第1 項、第2 項，對於\n      被告並無有利不利之別，並無比較新舊法之必要，故應逕\n      適用修正後之刑法第30條第1 項、第2 項論擬。\n（三）另被告行為時，本件據以論罪科刑之刑法第339 條法定刑\n      中罰金刑部分，應適用廢止前罰金罰鍰提高標準條例第1\n      條前段，依行政院會銜司法院所定標準提高至10倍，經依\n      現行法規所定貨幣單位折算新臺幣條例第2 條規定，折算\n      為新臺幣後內容為：或科或併科新臺幣3 萬元以下罰金。\n      而刑法施行法於95年6 月14日修正增訂第1 條之1 ，其第\n      1 項、第2 項規定：「中華民國94年1 月7 日刑法修正施\n      行後，刑法分則編所定罰金之貨幣單位為新臺幣。94年1\n      月7 日刑法修正時，刑法分則編未修正之條文定有罰金者\n      ，自94年1 月7 日刑法修正施行後，就其所定數額提高為\n      30倍。但72年6 月26日至96年1 月7 日新增或修正之條文\n      ，就其所定數額提高為3 倍。」查刑法第339 條自24年7\n      月1 日刑法施行起迄今未經修正，其法定刑罰金部分依照\n      前開規定，應變更為：或新臺幣3 萬元罰金。修正增訂前\n      後，其實質內容並無變更。另觀諸刑法施行法第1 條之1\n      立法理由謂：因應刑法增修條文施行後，刑法第33條第5\n      款規定，罰金貨幣單位已改為新臺幣，是以同法各罪所定\n      罰金貨幣單位，自應配合上開規定修正；且因不再適用現\n      行法規所定貨幣單位折算新臺幣條例，為使罰金數額趨於\n      一致，避免衍生新舊法比較適用問題，以緩和實務適用法\n      律之衝擊，於不變動罰金數額之前提下，而為制定。可見\n      刑法施行法第1 條之1 規定，係為取代廢止前罰金罰鍰提\n      高標準條例第1 條及現行法規所定貨幣單位折算新臺幣條\n      例第2 條而制定，具有新舊法律比較之特別準據法性質，\n      此部分自無刑法第2 條第1 項新舊法比較之問題，應逕適\n      用刑法施行法第1 條之1 第1 項、第2 項前段準據法之特\n      別規定，調整刑法第339條之法定刑，附此敘明。\n三、論罪科刑:\n（一）按刑法上之幫助犯，係對於犯罪與正犯有共同之認識，而\n      以幫助之意思，對於正犯資以助力，而未參與實施犯罪之\n      行為者而言（最高法院75年度臺上字第1509號、88年度臺\n      上字第1270號判決意旨可資參照）。是以，如未參與實施\n      犯罪構成要件之行為，且係出於幫助之意思提供助力，即\n      屬幫助犯，而非共同正犯。查前揭真實姓名、年籍均不詳\n      之詐欺集團成年人，基於意圖為自己不法所有之犯意，以\n      上述之方式，使被害人簡正宇陷於錯誤，因而交付本人之\n      財物，該詐欺集團成員所為，係犯刑法第339 條第1 項之\n      詐欺取財罪。被告雖有將本案帳戶之存摺、提款卡及密碼\n      提供予施以詐騙者使用，已如前述，惟既未見其有何參與\n      詐騙被害人行為之積極證據，固無從認屬上開詐欺取財行\n      為之共同正犯。然而，被告將其所有之帳戶提供予他人作\n      為詐欺取財之指定帳戶，乃係基於幫助他人詐欺取財之犯\n      意，而被告提供上揭帳戶予他人之行為，復屬詐欺取財構\n      成要件以外之行為，則被告自屬以幫助之意思，參與詐欺\n      取財構成要件以外之行為，是核被告吳敏真所為，係犯刑\n      法第30條第1 項前段、第339 條第1 項之幫助詐欺取財罪\n      。本案被告幫助他人犯詐欺取財罪，為從犯，本院衡其犯\n      罪情節較正犯為輕，爰依刑法第30 條 第2 項之規定，按\n      正犯之刑減輕之。爰審酌近年來詐欺集團橫行，受害者眾\n      ，破壞社會善良風氣，造成人心不安，被告任意提供帳戶\n      供他人作為實施詐欺取財犯罪之用，使警察機關難以追查\n      詐欺集團，致損害社會金融體系及妨礙民眾對他人之信賴\n      ，其犯罪所生之危害非輕，兼衡本件被害人因遭詐騙而匯\n      入被告帳戶之金額，及其犯罪動機、目的、手段及犯後態\n      度，且已與被害人簡正宇調解成立，願賠償被害人新臺幣\n      5 萬元（已賠償完畢，有被害人簡正宇於100 年7 月6 日\n      所具書狀傳真到院可參），被害人並允諾不再追究被告刑\n      事責任，有本院100 年度司斗刑簡暫調字第35號調解程序\n      筆錄附卷足稽，顯有悔意，並審之檢察官求處有期徒刑2\n      月等一切情狀，量處如主文所示之刑，並依下列所述諭知\n      易科罰金之折算標準。\n（二）茲被告行為時刑法第41條第1 項前段規定：「犯最重本刑\n      為5 年以下有期徒刑以下之刑之罪，而受6 個月以下有期\n      徒刑或拘役之宣告，因身體、教育、職業、家庭之關係或\n      其他正當事由，執行顯有困難者，得以1 元以上3 元以下\n      折算1 日，易科罰金。」而被告行為時易科罰金之折算標\n      準，依修正刪除前罰金罰鍰提高標準條例第2 條前段規定\n      ，係就原定數額提高為以100 倍折算1 日，則本件被告行\n      為時之易科罰金折算標準，係以銀元300 元折算1 日，經\n      折算為新臺幣後，應以新臺幣900 元折算為1 日。惟95\n      年7 月1 日施行之刑法第41條第1 項前段規定：「犯最重\n      本刑為5 年以下有期徒刑以下之刑之罪，而受6 個月以下\n      有期徒刑或拘役之宣告者，得以新臺幣1000元、2000元或\n      3000元折算1 日，易科罰金。」比較修正前後之易科罰金\n      折算標準，以95年7 月1 日修正公布施行前之規定，較有\n      利於受刑人。是被告上開94年間之犯行，自應依刑法第2\n      條第1 項前段，適用修正前刑法第41條第1 項前段規定及\n      修正刪除前罰金罰鍰提高標準條例第2 條前段規定，諭知\n      易科罰金之折算標準。\n（三）再查本案正犯之犯罪時間係在96年4 月24日以前，合於中\n      華民國九十六年罪犯減刑條例所定得予減刑之規定，應依\n      同條例第2 條第1 項第3 款、第7 條之規定減刑如主文所\n      示，併諭知易科罰金之折算標準，附此敘明。\n（四）按犯罪在新法施行前，新法施行後緩刑之宣告應適用新法\n      第74條規定（最高法院95年度第8 次刑事庭會議決議意旨\n      參照）。查被告前未曾因故意犯罪受有期徒刑以上刑之宣\n      告，有臺灣高等法院被告前案紀錄表1 份在卷可稽，此次\n      因一時失慮，致罹刑典，事後已坦承犯行，深具悔意，且\n      有如前開所述與被害人達成調解，本院認被告經此偵審教\n      訓，自當知所警惕，信無再犯之虞，因認前開宣告之刑以\n      暫不執行為適當，併依刑法第74條第1 項第1 款諭知緩刑\n      2 年。\n（五）被告交付予不法犯罪集團成員之前開存摺（含提款卡及密\n      碼），雖係被告供犯罪所用之物，然既已交付該集團使用\n      ，顯已移轉其所有權予該集團，而非被告所有，且均非違\n      禁物，亦別無證據足資證明係屬應沒收之物，爰不另宣告\n      沒收。況查所謂幫助犯係指就他人之犯罪加以助力，使其\n      易於實施之積極的或消極的行為而言，其犯罪態樣與實施\n      犯罪之正犯有異，其所處罰者，乃其提供助力之行為本身\n      ，而非正犯實施犯罪之行為。因此幫助犯不適用責任共同\n      之原則，對正犯所有供犯罪所用或因犯罪所得之物，勿庸\n      併為沒收之宣告（最高法院88年度臺上字第6234號判決要\n      旨參照），是前開存摺（含提款卡、密碼）雖係不法犯罪\n      集團所有供犯罪所用之物，對於幫助犯之被告，自毋庸宣\n      告沒收，附此敘明。\n四、應適用之法條：\n（一）刑事訴訟法第449條第1項、第454條第2項。\n（二）刑法第2 條第1 項前段、第30條第1 項前段、第2 項、第\n      339 條第1 項、第74條第1 項第1 款、修正前第41條第1\n      項前段。\n（三）刑法施行法第1條之1第1項、第2項前段。\n（四）修正刪除前之罰金罰緩提高標準條例第2 條。\n（五）中華民國九十六年罪犯減刑條例第2 條第1 項第3 款、第\n      7 條、第9條，逕以簡易判決處刑如主文。\n五、如不服本判決，得於判決書送達之日起10日內，以書狀敘述\n    理由，向本院提起上訴。"
  },
  "search": "臺灣彰化地方法院刑事簡易判決100年度簡字第868號聲請人臺灣彰化地方法院檢察署檢察官被告吳敏真上列被告詐欺案件，經檢察官聲請簡易判決處刑（100年度偵字第816號），本院判決如下：主文吳敏真幫助意圖為自己不法之所有，以詐術使人將本人之物交付，處有期徒刑貳月，如易科罰金，以銀元參佰元即新臺幣玖佰元折算壹日；減為有期徒刑壹月，如易科罰金，以銀元參佰元即新臺幣玖佰元折算壹日。緩刑貳年。犯罪事實及理由一、本件犯罪事實及證據名稱，均與檢察官聲請簡易判決處刑書之記載相同，茲引用如附件。二、查本案被告行為後，刑法及刑法施行法業於民國94年2月2日經總統以華總一義字第09400014901號令修正公布，並於95年7月1日施行。按行為後法律有變更者，適用行為時之法律，但行為後之法律有利於行為人者，適用最有利於行為人之法律，現行刑法第2條第1項定有明文。此條規定乃與刑法第1條罪刑法定主義契合，而貫徹法律禁止溯及既往原則，係規範行為後法律變更所生新舊法律比較適用之準據法，是刑法第2條本身雖經修正，但刑法第2條既屬適用法律之準據法，本身尚無比較新舊法之問題，應一律適用裁判時之現行刑法第2條規定以決定適用之刑罰法律，先予辨明。又以本次刑法修正之比較新舊法，應就罪刑有關之共犯、未遂犯、想像競合犯、牽連犯、連續犯、結合犯，以及累犯加重、自首減輕暨其他法定加減原因（如身分加減）與加減例等一切情形，本於統一性及整體性原則，綜其全部罪刑之結果而為比較，亦有最高法院95年度第8次刑庭會議決議可資參照。是就新舊法比較如下：（一）關於罰金刑：修正後刑法第33條第5款規定，已將原罰金刑最低額度由銀元1元（相當於新臺幣3元），提高為新臺幣1千元以上，且以百元計之，比較新、舊法結果，應以被告行為時即修正前刑法第33條第5款規定有利於被告。（二）關於幫助犯：刑法第30條第1項、第2項修正前規定為：「幫助他人犯罪者，為從犯。雖他人不知幫助之情者，亦同。從犯之處罰，得按正犯之刑減輕之」，修正後則為：「幫助他人實行犯罪行為者，為幫助犯。雖他人不知幫助之情者，亦同。幫助犯之處罰，得按正犯之刑減輕之」，係將「從犯」修正為「幫助犯」，並明示幫助犯之成立，應以被幫助者著手犯罪之實行，且具備違法性為必要，至於被幫助者是否具有有責性，則不影響幫助犯之成立，而幫助犯之刑仍維持依正犯之刑減輕之效果，此有修正理由可資參照。基此，本案被告幫助他人所為之詐欺犯行既均已既遂，則無論依照修正前或修正後刑法第30條第1項、第2項，對於被告並無有利不利之別，並無比較新舊法之必要，故應逕適用修正後之刑法第30條第1項、第2項論擬。（三）另被告行為時，本件據以論罪科刑之刑法第339條法定刑中罰金刑部分，應適用廢止前罰金罰鍰提高標準條例第1條前段，依行政院會銜司法院所定標準提高至10倍，經依現行法規所定貨幣單位折算新臺幣條例第2條規定，折算為新臺幣後內容為：或科或併科新臺幣3萬元以下罰金。而刑法施行法於95年6月14日修正增訂第1條之1，其第1項、第2項規定：「中華民國94年1月7日刑法修正施行後，刑法分則編所定罰金之貨幣單位為新臺幣。94年1月7日刑法修正時，刑法分則編未修正之條文定有罰金者，自94年1月7日刑法修正施行後，就其所定數額提高為30倍。但72年6月26日至96年1月7日新增或修正之條文，就其所定數額提高為3倍。」查刑法第339條自24年7月1日刑法施行起迄今未經修正，其法定刑罰金部分依照前開規定，應變更為：或新臺幣3萬元罰金。修正增訂前後，其實質內容並無變更。另觀諸刑法施行法第1條之1立法理由謂：因應刑法增修條文施行後，刑法第33條第5款規定，罰金貨幣單位已改為新臺幣，是以同法各罪所定罰金貨幣單位，自應配合上開規定修正；且因不再適用現行法規所定貨幣單位折算新臺幣條例，為使罰金數額趨於一致，避免衍生新舊法比較適用問題，以緩和實務適用法律之衝擊，於不變動罰金數額之前提下，而為制定。可見刑法施行法第1條之1規定，係為取代廢止前罰金罰鍰提高標準條例第1條及現行法規所定貨幣單位折算新臺幣條例第2條而制定，具有新舊法律比較之特別準據法性質，此部分自無刑法第2條第1項新舊法比較之問題，應逕適用刑法施行法第1條之1第1項、第2項前段準據法之特別規定，調整刑法第339條之法定刑，附此敘明。三、論罪科刑:（一）按刑法上之幫助犯，係對於犯罪與正犯有共同之認識，而以幫助之意思，對於正犯資以助力，而未參與實施犯罪之行為者而言（最高法院75年度臺上字第1509號、88年度臺上字第1270號判決意旨可資參照）。是以，如未參與實施犯罪構成要件之行為，且係出於幫助之意思提供助力，即屬幫助犯，而非共同正犯。查前揭真實姓名、年籍均不詳之詐欺集團成年人，基於意圖為自己不法所有之犯意，以上述之方式，使被害人簡正宇陷於錯誤，因而交付本人之財物，該詐欺集團成員所為，係犯刑法第339條第1項之詐欺取財罪。被告雖有將本案帳戶之存摺、提款卡及密碼提供予施以詐騙者使用，已如前述，惟既未見其有何參與詐騙被害人行為之積極證據，固無從認屬上開詐欺取財行為之共同正犯。然而，被告將其所有之帳戶提供予他人作為詐欺取財之指定帳戶，乃係基於幫助他人詐欺取財之犯意，而被告提供上揭帳戶予他人之行為，復屬詐欺取財構成要件以外之行為，則被告自屬以幫助之意思，參與詐欺取財構成要件以外之行為，是核被告吳敏真所為，係犯刑法第30條第1項前段、第339條第1項之幫助詐欺取財罪。本案被告幫助他人犯詐欺取財罪，為從犯，本院衡其犯罪情節較正犯為輕，爰依刑法第30條第2項之規定，按正犯之刑減輕之。爰審酌近年來詐欺集團橫行，受害者眾，破壞社會善良風氣，造成人心不安，被告任意提供帳戶供他人作為實施詐欺取財犯罪之用，使警察機關難以追查詐欺集團，致損害社會金融體系及妨礙民眾對他人之信賴，其犯罪所生之危害非輕，兼衡本件被害人因遭詐騙而匯入被告帳戶之金額，及其犯罪動機、目的、手段及犯後態度，且已與被害人簡正宇調解成立，願賠償被害人新臺幣5萬元（已賠償完畢，有被害人簡正宇於100年7月6日所具書狀傳真到院可參），被害人並允諾不再追究被告刑事責任，有本院100年度司斗刑簡暫調字第35號調解程序筆錄附卷足稽，顯有悔意，並審之檢察官求處有期徒刑2月等一切情狀，量處如主文所示之刑，並依下列所述諭知易科罰金之折算標準。（二）茲被告行為時刑法第41條第1項前段規定：「犯最重本刑為5年以下有期徒刑以下之刑之罪，而受6個月以下有期徒刑或拘役之宣告，因身體、教育、職業、家庭之關係或其他正當事由，執行顯有困難者，得以1元以上3元以下折算1日，易科罰金。」而被告行為時易科罰金之折算標準，依修正刪除前罰金罰鍰提高標準條例第2條前段規定，係就原定數額提高為以100倍折算1日，則本件被告行為時之易科罰金折算標準，係以銀元300元折算1日，經折算為新臺幣後，應以新臺幣900元折算為1日。惟95年7月1日施行之刑法第41條第1項前段規定：「犯最重本刑為5年以下有期徒刑以下之刑之罪，而受6個月以下有期徒刑或拘役之宣告者，得以新臺幣1000元、2000元或3000元折算1日，易科罰金。」比較修正前後之易科罰金折算標準，以95年7月1日修正公布施行前之規定，較有利於受刑人。是被告上開94年間之犯行，自應依刑法第2條第1項前段，適用修正前刑法第41條第1項前段規定及修正刪除前罰金罰鍰提高標準條例第2條前段規定，諭知易科罰金之折算標準。（三）再查本案正犯之犯罪時間係在96年4月24日以前，合於中華民國九十六年罪犯減刑條例所定得予減刑之規定，應依同條例第2條第1項第3款、第7條之規定減刑如主文所示，併諭知易科罰金之折算標準，附此敘明。（四）按犯罪在新法施行前，新法施行後緩刑之宣告應適用新法第74條規定（最高法院95年度第8次刑事庭會議決議意旨參照）。查被告前未曾因故意犯罪受有期徒刑以上刑之宣告，有臺灣高等法院被告前案紀錄表1份在卷可稽，此次因一時失慮，致罹刑典，事後已坦承犯行，深具悔意，且有如前開所述與被害人達成調解，本院認被告經此偵審教訓，自當知所警惕，信無再犯之虞，因認前開宣告之刑以暫不執行為適當，併依刑法第74條第1項第1款諭知緩刑2年。（五）被告交付予不法犯罪集團成員之前開存摺（含提款卡及密碼），雖係被告供犯罪所用之物，然既已交付該集團使用，顯已移轉其所有權予該集團，而非被告所有，且均非違禁物，亦別無證據足資證明係屬應沒收之物，爰不另宣告沒收。況查所謂幫助犯係指就他人之犯罪加以助力，使其易於實施之積極的或消極的行為而言，其犯罪態樣與實施犯罪之正犯有異，其所處罰者，乃其提供助力之行為本身，而非正犯實施犯罪之行為。因此幫助犯不適用責任共同之原則，對正犯所有供犯罪所用或因犯罪所得之物，勿庸併為沒收之宣告（最高法院88年度臺上字第6234號判決要旨參照），是前開存摺（含提款卡、密碼）雖係不法犯罪集團所有供犯罪所用之物，對於幫助犯之被告，自毋庸宣告沒收，附此敘明。四、應適用之法條：（一）刑事訴訟法第449條第1項、第454條第2項。（二）刑法第2條第1項前段、第30條第1項前段、第2項、第339條第1項、第74條第1項第1款、修正前第41條第1項前段。（三）刑法施行法第1條之1第1項、第2項前段。（四）修正刪除前之罰金罰緩提高標準條例第2條。（五）中華民國九十六年罪犯減刑條例第2條第1項第3款、第7條、第9條，逕以簡易判決處刑如主文。五、如不服本判決，得於判決書送達之日起10日內，以書狀敘述理由，向本院提起上訴。中華民國100年7月29日刑事第五庭法官周淡怡以上正本證明與原本無異。如不服本件判決，得自收受送達之日起10日內，表明上訴理由，向本院提起上訴狀（須附繕本）。告訴人或被害人對於判決如有不服具備理由請求檢察官上訴者，其上訴期間之計算係以檢察官收受判決正本之日期為準。中華民國100年7月29日書記官陳文新附錄：論罪科刑法條：中華民國刑法第339條意圖為自己或第3人不法之所有，以詐術使人將本人或第3人之物交付者，處5年以下有期徒刑、拘役或科或併科1,000元以下罰金。以前項方法得財產上不法之利益或使第3人得之者，亦同。前2項之未遂犯罰之。",
  "characters": {
    "judges": [
      "周淡怡"
    ],
    "prosecutors": [

    ],
    "lawyers": [

    ],
    "clerks": [
      "陳文新"
    ],
    "plaintiffs": [

    ],
    "defendants": [
      "吳敏真"
    ],
    "prosecutor_office": [
      "臺灣彰化地方法院檢察署檢察官"
    ],
    "creditors": [

    ],
    "debtors": [

    ],
    "judicial_associate_officer": [

    ]
  },
  "adjudged_at": "2011-07-29",
  "created_at": "2016-02-14 02:21:47",
  "updated_at": "2016-02-14 02:21:47"
}