{
  "identify": "KSD-100-重訴-127-20110729-1",
  "court": {
    "name": "臺灣高雄地方法院",
    "code": "KSD"
  },
  "division": {
    "name": "民事",
    "code": "V"
  },
  "year": 100,
  "word": "重訴",
  "number": "127",
  "jcheck": "1",
  "reason": "拆屋還地",
  "content": "臺灣高雄地方法院民事判決            100年度重訴字第127號\n原      告  李溫雄\n            李溫欽\n            李良璧\n            李純瑜\n            李佩珍\n            李美珍\n            黃海清即黃李瑞春之.\n            黃中正即黃李瑞春之.\n            黃中川即黃李瑞春之.\n            黃中志即黃李瑞春之.\n前列十人共同\n訴訟代理人  黃建雄律師\n被      告  李清江\n訴訟代理人  余景登律師\n被      告  李正安\n訴訟代理人  高明賢\n被      告  李文楷\n上列當事人間拆屋還地事件，經本院於民國100年6月29日言詞辯\n論終結，判決如下：\n    主      文\n被告李文楷應將坐落高雄市○○區○○段一小段一一五八、一一\n五九、一一六０、一一六一地號土地上如附圖所示A 部分（面積\n二三點二四平方公尺）之地上物拆除，並將土地返還原告。\n被告李清江應將前開土地如附圖所示B （面積二六點七五平方公\n尺）、B1（面積一點八一平方公尺）、B2（面積一五點一九平方\n公尺）、B3（二九點七七平方公尺）、B4部分（面積四九點七五\n平方公尺）之地上物拆除，並將土地返還原告。\n被告李正安應將前開土地如附圖所示C （面積六七點六二平方公\n尺）、C1部分（面積一點三八平方公尺）之地上物拆除，並將土\n地返還原告。\n訴訟費用由被告李文楷負擔百分之五，被告李清江負擔百分之二\n十六，被告李正安負擔百分之十四，餘由原告負擔。\n本判決於原告各以新台幣壹拾捌萬元、玖拾參萬元、伍拾貳萬元\n為被告李文楷、李清江、李正安供擔保後，得假執行。\n    事實及理由\n一、本件原告黃李瑞春於民國100 年2 月8 日死亡，由黃海清、\n    黃中正、黃中川、黃中志繼承，並聲明承受訴訟（見本院卷\n    一第164 頁），核無不合，應予准許。\n二、被告李文楷經合法通知，未於言詞辯論期日到場，核無民事\n    訴訟法第386 條各款所列情形，爰依原告聲請，由其一造辯\n    論而為判決。\n三、原告主張：坐落高雄市○○區○○段1 小段1158、1159、11\n    60、1161地號土地（下稱系爭土地）原為伊等之被繼承人李\n    忠恕所有，伊等於93年7  月8 日因繼承而取得，並於95年2\n    月21日辦妥所有權移轉登記，詎被告並無合法權源而在系爭\n    土地內興建如附表所示之地上物，爰依民法第767 條規定，\n    請求被告將系爭土地上之地上物拆除，並返還占用土地予伊\n    等。並聲明：(一)被告李文楷應將坐落系爭土地上如附圖所示\n    A 部分（面積23.24 平方公尺）之地上物拆除，並將土地返\n    還原告。(二)被告李清江應將坐落系爭土地上如附圖所示B （\n    面積26.75 平方公尺）、B1（面積1.81平方公尺）、B2（面\n    積15.19 平方公尺）、B3（29.77 平方公尺）、B4部分（面\n    積49.75 平方公尺）之地上物拆除，並將土地返還原告。(三)\n    被告李正安應將坐落系爭土地如附圖所示C （面積67.62 平\n    方公尺）、C1部分（面積1.38平方公尺）之地上物拆除，並\n    將土地返還原告。(四)願供擔保請准宣告假執行。\n四、被告李清江、李正安則以：系爭土地係兩造先祖自日據時期\n    所遺留之家產，依臺灣民事習慣調查報告，臺灣之家產，自\n    清代即屬父祖子孫所構成家屬之公同共有，故系爭土地依舊\n    有習慣係屬兩造共有分管家產，經兩造子孫分別搭建房屋使\n    用，伊等並非無權占有等語，資為抗辯。並聲明：原告之訴\n    駁回。\n五、李文楷未於言詞辯論期日到場，亦未提出書狀作何聲明或陳\n    述。\n六、兩造不爭執之事項：\n  (一)系爭土地原登記於原告之被繼承人李忠恕名下，原告於93年\n    7 月8 日因繼承而取得，並於95年2 月21日辦理繼承登記，\n    此有土地登記謄本在卷可稽（見本院卷一第6-13頁）。\n  (二)李文楷占用如附圖所示A 部分（面積23.24 平方公尺）；李\n    清江占用如附圖所示B （面積26.75 平方公尺）、B1（面積\n    1.81平方公尺）、B2（面積15.19平方公尺）、B3（29.77平\n    方公尺）、B4部分（面積49.75平方公尺）；李正安占用如\n    附圖所示C（面積67.62平方公尺）、C1部分（面積1.38  平\n    方公尺），業經本院會同高雄市政府地政局鹽埕地政事務所\n    人員到場履勘屬實，並製有勘驗筆錄及複丈成果圖等件附卷\n    可憑（見本院卷一第69-71、143-144、186-187頁）。\n七、本件之爭點：被告就系爭土地有無合法占有使用權源？原告\n    請求被告拆屋還地，有無理由？\n  (一)按民事，法律所未規定者，依習慣；無習慣者，依法理，民\n    法第1 條定有明文。職是，習慣僅於法律無明文規定時有補\n    充之效力。我國民法自18年10月10日已公布施行，而台灣自\n    34年光復後，脫離日本國之統治，同受我國民法規定之適用\n    。且同法第827 條規定就公同關係而共有一物，應依法律規\n    定或依契約始得成立。此外，民法物權編並未承認「家產」\n    之制度或規定「家產」為公同共有關係發生之原因。換言之\n    ，明文排除依習慣或法理成立公同共有關係，此觀物權編第\n    1 條物權法定主義之規定即明。\n  (二)查系爭1158地號土地重測前為同段180 地號，於68年2 月16\n    日分割增加同段180-1、180-2、180-3地號土地，系爭1159\n    地號土地重測前為180-1地號土地；系爭1160地號土地重測\n    前為180-2地號土地；系爭1161地號土地重測前為180-3地號\n    土地，該180-1、180-2、180-3地號土地均係於68年2月16\n    日分割自180地號土地。而180地號土地係於35年7月26日辦\n    理總登記，所有權人為訴外人李朝巡，由李忠恕於38年8月\n    28日因繼承而取得，並於42年1月28日辦理繼承登記，原告\n    再於93年7月8日因繼承而取得，並於95年2月21日辦理繼承\n    登記，此有土地登記謄本及異動索引附卷可稽（見本院卷一\n    第74-109頁），是系爭土地係於38年間辦理總登記，登記所\n    有權人為李朝巡，嗣於42年間以繼承為原因移轉登記予李忠\n    恕，原告再於95年間以繼承為原因取得系爭土地所有權，則\n    李朝巡、李忠恕及原告先後取得系爭土地所有權，均係發生\n    在台灣光復之後，並非發生在清朝或日據時代，其法律關係\n    自應以我國民法定之，而無適用習慣之餘地甚明。且家產為\n    公同共有之習慣，並非依法律規定或契約而成立公同共有關\n    係，自違反前述物權法定主義。故被告李清江、李正安辯稱\n    ：系爭土地依舊有習慣為家產，係屬兩造公同共有云云，洵\n    屬無據，委無足取。\n  (三)被告李清江、李正安辯稱：依臺灣民事習慣調查報告（見本\n    院卷二第31-34 ），臺灣之家產，自清代即屬父祖子孫所構\n    成家屬之公同共有，故系爭土地係屬兩造共有分管之家產等\n    語。然該調查報告，係就清代及日據時代所遺留未分割之財\n    產所有權之歸屬糾紛而為論述，而清代及日據時代，為我國\n    主權所不及，並無我國民法之適用，斯時有承認習慣法之必\n    要，與本件系爭土地係於台灣光復後依法辦理總登記及繼承\n    登記之情形並不相同。又縱認系爭土地於清代及日據時代係\n    屬公同共有之家產，然系爭土地既已於台灣光復後總登記為\n    李朝巡單獨所有，則該家產之公同共有關係已於上開總登記\n    時而為終止，系爭土地自非屬兩造公同共有之家產，應堪認\n    定。被告上開所辯，洵非可採。至被告另以李氏先祖多人曾\n    於系爭土地之前身180 番號設籍，故系爭土地無「鬮分」或\n    「歸就」即無分產之情事，惟設籍僅係戶籍之行政管理，非\n    所有權認定之依據，縱多人設籍同戶，亦難認該等人均為設\n    籍土地之公同共有人，被告李清江、李正安據此而為推論，\n    顯係臆測之詞，亦非可採。\n  (四)按所有人對於無權占有或侵奪其所有物者，得請求返還之。\n    對於妨害其所有權者，得請求除去之。有妨害其所有權之虞\n    者，得請求防止之。民法第767 條定有明文。系爭土地既為\n    原告所有，被告未經同意而無正當權源占有系爭土地，自屬\n    無權占有。從而，原告依民法第767 條規定，請求李文楷應\n    將坐落系爭土地上如附圖所示A 部分（面積23.24 平方公尺\n    ）之地上物拆除，並將土地返還原告；李清江應將坐落系爭\n    土地上如附圖所示B（面積26.75平方公尺）、B1（面積1.81\n    平方公尺）、B2（面積15.19平方公尺）、B3（29.77平方公\n    尺）、B4部分（面積49.75平方公尺）之地上物拆除，並將\n    土地返還原告；李正安應將坐落系爭土地如附圖所示C（面\n    積67.62平方公尺）、C1部分（面積1.38平方公尺）之地上\n    物拆除，並將土地返還原告，洵屬有據，應予准許。\n八、原告陳明願供擔保請准宣告假執行，經核無不合，爰酌定相\n    當擔保金額准許之。\n九、本件事證已臻明確，兩造其餘攻擊防禦方法及舉證，核與判\n    決無影響，毋庸逐一論列，併此敘明。\n十、據上論結，本件原告之訴為有理由，依民事訴訟法第385 條\n    第1 項前段、第85條第1 項但書、第390 條第2 項，判決如\n    主文。\n中    華    民    國   100    年    7     月    29    日\n                    民事鳳山分庭法  官  何悅芳\n以上正本係照原本作成。\n如對本判決上訴，須於判決送達後20日內向本院提出上訴狀。如\n委任律師提起上訴者，應一併繳納上訴審裁判費。\n中    華    民    國   100    年    7     月    29    日\n                                書記官  陳俐嫺",
  "structure": {
    "main": "被告李文楷應將坐落高雄市○○區○○段一小段一一五八、一一\n五九、一一六０、一一六一地號土地上如附圖所示A 部分（面積\n二三點二四平方公尺）之地上物拆除，並將土地返還原告。\n被告李清江應將前開土地如附圖所示B （面積二六點七五平方公\n尺）、B1（面積一點八一平方公尺）、B2（面積一五點一九平方\n公尺）、B3（二九點七七平方公尺）、B4部分（面積四九點七五\n平方公尺）之地上物拆除，並將土地返還原告。\n被告李正安應將前開土地如附圖所示C （面積六七點六二平方公\n尺）、C1部分（面積一點三八平方公尺）之地上物拆除，並將土\n地返還原告。\n訴訟費用由被告李文楷負擔百分之五，被告李清江負擔百分之二\n十六，被告李正安負擔百分之十四，餘由原告負擔。\n本判決於原告各以新台幣壹拾捌萬元、玖拾參萬元、伍拾貳萬元\n為被告李文楷、李清江、李正安供擔保後，得假執行。",
    "fact": "一、本件原告黃李瑞春於民國100 年2 月8 日死亡，由黃海清、\n    黃中正、黃中川、黃中志繼承，並聲明承受訴訟（見本院卷\n    一第164 頁），核無不合，應予准許。\n二、被告李文楷經合法通知，未於言詞辯論期日到場，核無民事\n    訴訟法第386 條各款所列情形，爰依原告聲請，由其一造辯\n    論而為判決。\n三、原告主張：坐落高雄市○○區○○段1 小段1158、1159、11\n    60、1161地號土地（下稱系爭土地）原為伊等之被繼承人李\n    忠恕所有，伊等於93年7  月8 日因繼承而取得，並於95年2\n    月21日辦妥所有權移轉登記，詎被告並無合法權源而在系爭\n    土地內興建如附表所示之地上物，爰依民法第767 條規定，\n    請求被告將系爭土地上之地上物拆除，並返還占用土地予伊\n    等。並聲明：(一)被告李文楷應將坐落系爭土地上如附圖所示\n    A 部分（面積23.24 平方公尺）之地上物拆除，並將土地返\n    還原告。(二)被告李清江應將坐落系爭土地上如附圖所示B （\n    面積26.75 平方公尺）、B1（面積1.81平方公尺）、B2（面\n    積15.19 平方公尺）、B3（29.77 平方公尺）、B4部分（面\n    積49.75 平方公尺）之地上物拆除，並將土地返還原告。(三)\n    被告李正安應將坐落系爭土地如附圖所示C （面積67.62 平\n    方公尺）、C1部分（面積1.38平方公尺）之地上物拆除，並\n    將土地返還原告。(四)願供擔保請准宣告假執行。\n四、被告李清江、李正安則以：系爭土地係兩造先祖自日據時期\n    所遺留之家產，依臺灣民事習慣調查報告，臺灣之家產，自\n    清代即屬父祖子孫所構成家屬之公同共有，故系爭土地依舊\n    有習慣係屬兩造共有分管家產，經兩造子孫分別搭建房屋使\n    用，伊等並非無權占有等語，資為抗辯。並聲明：原告之訴\n    駁回。\n五、李文楷未於言詞辯論期日到場，亦未提出書狀作何聲明或陳\n    述。\n六、兩造不爭執之事項：\n  (一)系爭土地原登記於原告之被繼承人李忠恕名下，原告於93年\n    7 月8 日因繼承而取得，並於95年2 月21日辦理繼承登記，\n    此有土地登記謄本在卷可稽（見本院卷一第6-13頁）。\n  (二)李文楷占用如附圖所示A 部分（面積23.24 平方公尺）；李\n    清江占用如附圖所示B （面積26.75 平方公尺）、B1（面積\n    1.81平方公尺）、B2（面積15.19平方公尺）、B3（29.77平\n    方公尺）、B4部分（面積49.75平方公尺）；李正安占用如\n    附圖所示C（面積67.62平方公尺）、C1部分（面積1.38  平\n    方公尺），業經本院會同高雄市政府地政局鹽埕地政事務所\n    人員到場履勘屬實，並製有勘驗筆錄及複丈成果圖等件附卷\n    可憑（見本院卷一第69-71、143-144、186-187頁）。\n七、本件之爭點：被告就系爭土地有無合法占有使用權源？原告\n    請求被告拆屋還地，有無理由？\n  (一)按民事，法律所未規定者，依習慣；無習慣者，依法理，民\n    法第1 條定有明文。職是，習慣僅於法律無明文規定時有補\n    充之效力。我國民法自18年10月10日已公布施行，而台灣自\n    34年光復後，脫離日本國之統治，同受我國民法規定之適用\n    。且同法第827 條規定就公同關係而共有一物，應依法律規\n    定或依契約始得成立。此外，民法物權編並未承認「家產」\n    之制度或規定「家產」為公同共有關係發生之原因。換言之\n    ，明文排除依習慣或法理成立公同共有關係，此觀物權編第\n    1 條物權法定主義之規定即明。\n  (二)查系爭1158地號土地重測前為同段180 地號，於68年2 月16\n    日分割增加同段180-1、180-2、180-3地號土地，系爭1159\n    地號土地重測前為180-1地號土地；系爭1160地號土地重測\n    前為180-2地號土地；系爭1161地號土地重測前為180-3地號\n    土地，該180-1、180-2、180-3地號土地均係於68年2月16\n    日分割自180地號土地。而180地號土地係於35年7月26日辦\n    理總登記，所有權人為訴外人李朝巡，由李忠恕於38年8月\n    28日因繼承而取得，並於42年1月28日辦理繼承登記，原告\n    再於93年7月8日因繼承而取得，並於95年2月21日辦理繼承\n    登記，此有土地登記謄本及異動索引附卷可稽（見本院卷一\n    第74-109頁），是系爭土地係於38年間辦理總登記，登記所\n    有權人為李朝巡，嗣於42年間以繼承為原因移轉登記予李忠\n    恕，原告再於95年間以繼承為原因取得系爭土地所有權，則\n    李朝巡、李忠恕及原告先後取得系爭土地所有權，均係發生\n    在台灣光復之後，並非發生在清朝或日據時代，其法律關係\n    自應以我國民法定之，而無適用習慣之餘地甚明。且家產為\n    公同共有之習慣，並非依法律規定或契約而成立公同共有關\n    係，自違反前述物權法定主義。故被告李清江、李正安辯稱\n    ：系爭土地依舊有習慣為家產，係屬兩造公同共有云云，洵\n    屬無據，委無足取。\n  (三)被告李清江、李正安辯稱：依臺灣民事習慣調查報告（見本\n    院卷二第31-34 ），臺灣之家產，自清代即屬父祖子孫所構\n    成家屬之公同共有，故系爭土地係屬兩造共有分管之家產等\n    語。然該調查報告，係就清代及日據時代所遺留未分割之財\n    產所有權之歸屬糾紛而為論述，而清代及日據時代，為我國\n    主權所不及，並無我國民法之適用，斯時有承認習慣法之必\n    要，與本件系爭土地係於台灣光復後依法辦理總登記及繼承\n    登記之情形並不相同。又縱認系爭土地於清代及日據時代係\n    屬公同共有之家產，然系爭土地既已於台灣光復後總登記為\n    李朝巡單獨所有，則該家產之公同共有關係已於上開總登記\n    時而為終止，系爭土地自非屬兩造公同共有之家產，應堪認\n    定。被告上開所辯，洵非可採。至被告另以李氏先祖多人曾\n    於系爭土地之前身180 番號設籍，故系爭土地無「鬮分」或\n    「歸就」即無分產之情事，惟設籍僅係戶籍之行政管理，非\n    所有權認定之依據，縱多人設籍同戶，亦難認該等人均為設\n    籍土地之公同共有人，被告李清江、李正安據此而為推論，\n    顯係臆測之詞，亦非可採。\n  (四)按所有人對於無權占有或侵奪其所有物者，得請求返還之。\n    對於妨害其所有權者，得請求除去之。有妨害其所有權之虞\n    者，得請求防止之。民法第767 條定有明文。系爭土地既為\n    原告所有，被告未經同意而無正當權源占有系爭土地，自屬\n    無權占有。從而，原告依民法第767 條規定，請求李文楷應\n    將坐落系爭土地上如附圖所示A 部分（面積23.24 平方公尺\n    ）之地上物拆除，並將土地返還原告；李清江應將坐落系爭\n    土地上如附圖所示B（面積26.75平方公尺）、B1（面積1.81\n    平方公尺）、B2（面積15.19平方公尺）、B3（29.77平方公\n    尺）、B4部分（面積49.75平方公尺）之地上物拆除，並將\n    土地返還原告；李正安應將坐落系爭土地如附圖所示C（面\n    積67.62平方公尺）、C1部分（面積1.38平方公尺）之地上\n    物拆除，並將土地返還原告，洵屬有據，應予准許。\n八、原告陳明願供擔保請准宣告假執行，經核無不合，爰酌定相\n    當擔保金額准許之。\n九、本件事證已臻明確，兩造其餘攻擊防禦方法及舉證，核與判\n    決無影響，毋庸逐一論列，併此敘明。\n十、據上論結，本件原告之訴為有理由，依民事訴訟法第385 條\n    第1 項前段、第85條第1 項但書、第390 條第2 項，判決如\n    主文。",
    "reason": "一、本件原告黃李瑞春於民國100 年2 月8 日死亡，由黃海清、\n    黃中正、黃中川、黃中志繼承，並聲明承受訴訟（見本院卷\n    一第164 頁），核無不合，應予准許。\n二、被告李文楷經合法通知，未於言詞辯論期日到場，核無民事\n    訴訟法第386 條各款所列情形，爰依原告聲請，由其一造辯\n    論而為判決。\n三、原告主張：坐落高雄市○○區○○段1 小段1158、1159、11\n    60、1161地號土地（下稱系爭土地）原為伊等之被繼承人李\n    忠恕所有，伊等於93年7  月8 日因繼承而取得，並於95年2\n    月21日辦妥所有權移轉登記，詎被告並無合法權源而在系爭\n    土地內興建如附表所示之地上物，爰依民法第767 條規定，\n    請求被告將系爭土地上之地上物拆除，並返還占用土地予伊\n    等。並聲明：(一)被告李文楷應將坐落系爭土地上如附圖所示\n    A 部分（面積23.24 平方公尺）之地上物拆除，並將土地返\n    還原告。(二)被告李清江應將坐落系爭土地上如附圖所示B （\n    面積26.75 平方公尺）、B1（面積1.81平方公尺）、B2（面\n    積15.19 平方公尺）、B3（29.77 平方公尺）、B4部分（面\n    積49.75 平方公尺）之地上物拆除，並將土地返還原告。(三)\n    被告李正安應將坐落系爭土地如附圖所示C （面積67.62 平\n    方公尺）、C1部分（面積1.38平方公尺）之地上物拆除，並\n    將土地返還原告。(四)願供擔保請准宣告假執行。\n四、被告李清江、李正安則以：系爭土地係兩造先祖自日據時期\n    所遺留之家產，依臺灣民事習慣調查報告，臺灣之家產，自\n    清代即屬父祖子孫所構成家屬之公同共有，故系爭土地依舊\n    有習慣係屬兩造共有分管家產，經兩造子孫分別搭建房屋使\n    用，伊等並非無權占有等語，資為抗辯。並聲明：原告之訴\n    駁回。\n五、李文楷未於言詞辯論期日到場，亦未提出書狀作何聲明或陳\n    述。\n六、兩造不爭執之事項：\n  (一)系爭土地原登記於原告之被繼承人李忠恕名下，原告於93年\n    7 月8 日因繼承而取得，並於95年2 月21日辦理繼承登記，\n    此有土地登記謄本在卷可稽（見本院卷一第6-13頁）。\n  (二)李文楷占用如附圖所示A 部分（面積23.24 平方公尺）；李\n    清江占用如附圖所示B （面積26.75 平方公尺）、B1（面積\n    1.81平方公尺）、B2（面積15.19平方公尺）、B3（29.77平\n    方公尺）、B4部分（面積49.75平方公尺）；李正安占用如\n    附圖所示C（面積67.62平方公尺）、C1部分（面積1.38  平\n    方公尺），業經本院會同高雄市政府地政局鹽埕地政事務所\n    人員到場履勘屬實，並製有勘驗筆錄及複丈成果圖等件附卷\n    可憑（見本院卷一第69-71、143-144、186-187頁）。\n七、本件之爭點：被告就系爭土地有無合法占有使用權源？原告\n    請求被告拆屋還地，有無理由？\n  (一)按民事，法律所未規定者，依習慣；無習慣者，依法理，民\n    法第1 條定有明文。職是，習慣僅於法律無明文規定時有補\n    充之效力。我國民法自18年10月10日已公布施行，而台灣自\n    34年光復後，脫離日本國之統治，同受我國民法規定之適用\n    。且同法第827 條規定就公同關係而共有一物，應依法律規\n    定或依契約始得成立。此外，民法物權編並未承認「家產」\n    之制度或規定「家產」為公同共有關係發生之原因。換言之\n    ，明文排除依習慣或法理成立公同共有關係，此觀物權編第\n    1 條物權法定主義之規定即明。\n  (二)查系爭1158地號土地重測前為同段180 地號，於68年2 月16\n    日分割增加同段180-1、180-2、180-3地號土地，系爭1159\n    地號土地重測前為180-1地號土地；系爭1160地號土地重測\n    前為180-2地號土地；系爭1161地號土地重測前為180-3地號\n    土地，該180-1、180-2、180-3地號土地均係於68年2月16\n    日分割自180地號土地。而180地號土地係於35年7月26日辦\n    理總登記，所有權人為訴外人李朝巡，由李忠恕於38年8月\n    28日因繼承而取得，並於42年1月28日辦理繼承登記，原告\n    再於93年7月8日因繼承而取得，並於95年2月21日辦理繼承\n    登記，此有土地登記謄本及異動索引附卷可稽（見本院卷一\n    第74-109頁），是系爭土地係於38年間辦理總登記，登記所\n    有權人為李朝巡，嗣於42年間以繼承為原因移轉登記予李忠\n    恕，原告再於95年間以繼承為原因取得系爭土地所有權，則\n    李朝巡、李忠恕及原告先後取得系爭土地所有權，均係發生\n    在台灣光復之後，並非發生在清朝或日據時代，其法律關係\n    自應以我國民法定之，而無適用習慣之餘地甚明。且家產為\n    公同共有之習慣，並非依法律規定或契約而成立公同共有關\n    係，自違反前述物權法定主義。故被告李清江、李正安辯稱\n    ：系爭土地依舊有習慣為家產，係屬兩造公同共有云云，洵\n    屬無據，委無足取。\n  (三)被告李清江、李正安辯稱：依臺灣民事習慣調查報告（見本\n    院卷二第31-34 ），臺灣之家產，自清代即屬父祖子孫所構\n    成家屬之公同共有，故系爭土地係屬兩造共有分管之家產等\n    語。然該調查報告，係就清代及日據時代所遺留未分割之財\n    產所有權之歸屬糾紛而為論述，而清代及日據時代，為我國\n    主權所不及，並無我國民法之適用，斯時有承認習慣法之必\n    要，與本件系爭土地係於台灣光復後依法辦理總登記及繼承\n    登記之情形並不相同。又縱認系爭土地於清代及日據時代係\n    屬公同共有之家產，然系爭土地既已於台灣光復後總登記為\n    李朝巡單獨所有，則該家產之公同共有關係已於上開總登記\n    時而為終止，系爭土地自非屬兩造公同共有之家產，應堪認\n    定。被告上開所辯，洵非可採。至被告另以李氏先祖多人曾\n    於系爭土地之前身180 番號設籍，故系爭土地無「鬮分」或\n    「歸就」即無分產之情事，惟設籍僅係戶籍之行政管理，非\n    所有權認定之依據，縱多人設籍同戶，亦難認該等人均為設\n    籍土地之公同共有人，被告李清江、李正安據此而為推論，\n    顯係臆測之詞，亦非可採。\n  (四)按所有人對於無權占有或侵奪其所有物者，得請求返還之。\n    對於妨害其所有權者，得請求除去之。有妨害其所有權之虞\n    者，得請求防止之。民法第767 條定有明文。系爭土地既為\n    原告所有，被告未經同意而無正當權源占有系爭土地，自屬\n    無權占有。從而，原告依民法第767 條規定，請求李文楷應\n    將坐落系爭土地上如附圖所示A 部分（面積23.24 平方公尺\n    ）之地上物拆除，並將土地返還原告；李清江應將坐落系爭\n    土地上如附圖所示B（面積26.75平方公尺）、B1（面積1.81\n    平方公尺）、B2（面積15.19平方公尺）、B3（29.77平方公\n    尺）、B4部分（面積49.75平方公尺）之地上物拆除，並將\n    土地返還原告；李正安應將坐落系爭土地如附圖所示C（面\n    積67.62平方公尺）、C1部分（面積1.38平方公尺）之地上\n    物拆除，並將土地返還原告，洵屬有據，應予准許。\n八、原告陳明願供擔保請准宣告假執行，經核無不合，爰酌定相\n    當擔保金額准許之。\n九、本件事證已臻明確，兩造其餘攻擊防禦方法及舉證，核與判\n    決無影響，毋庸逐一論列，併此敘明。\n十、據上論結，本件原告之訴為有理由，依民事訴訟法第385 條\n    第1 項前段、第85條第1 項但書、第390 條第2 項，判決如\n    主文。"
  },
  "search": "臺灣高雄地方法院民事判決100年度重訴字第127號原告李溫雄李溫欽李良璧李純瑜李佩珍李美珍黃海清即黃李瑞春之.黃中正即黃李瑞春之.黃中川即黃李瑞春之.黃中志即黃李瑞春之.前列十人共同訴訟代理人黃建雄律師被告李清江訴訟代理人余景登律師被告李正安訴訟代理人高明賢被告李文楷上列當事人間拆屋還地事件，經本院於民國100年6月29日言詞辯論終結，判決如下：主文被告李文楷應將坐落高雄市○○區○○段一小段一一五八、一一五九、一一六０、一一六一地號土地上如附圖所示A部分（面積二三點二四平方公尺）之地上物拆除，並將土地返還原告。被告李清江應將前開土地如附圖所示B（面積二六點七五平方公尺）、B1（面積一點八一平方公尺）、B2（面積一五點一九平方公尺）、B3（二九點七七平方公尺）、B4部分（面積四九點七五平方公尺）之地上物拆除，並將土地返還原告。被告李正安應將前開土地如附圖所示C（面積六七點六二平方公尺）、C1部分（面積一點三八平方公尺）之地上物拆除，並將土地返還原告。訴訟費用由被告李文楷負擔百分之五，被告李清江負擔百分之二十六，被告李正安負擔百分之十四，餘由原告負擔。本判決於原告各以新台幣壹拾捌萬元、玖拾參萬元、伍拾貳萬元為被告李文楷、李清江、李正安供擔保後，得假執行。事實及理由一、本件原告黃李瑞春於民國100年2月8日死亡，由黃海清、黃中正、黃中川、黃中志繼承，並聲明承受訴訟（見本院卷一第164頁），核無不合，應予准許。二、被告李文楷經合法通知，未於言詞辯論期日到場，核無民事訴訟法第386條各款所列情形，爰依原告聲請，由其一造辯論而為判決。三、原告主張：坐落高雄市○○區○○段1小段1158、1159、1160、1161地號土地（下稱系爭土地）原為伊等之被繼承人李忠恕所有，伊等於93年7月8日因繼承而取得，並於95年2月21日辦妥所有權移轉登記，詎被告並無合法權源而在系爭土地內興建如附表所示之地上物，爰依民法第767條規定，請求被告將系爭土地上之地上物拆除，並返還占用土地予伊等。並聲明：(一)被告李文楷應將坐落系爭土地上如附圖所示A部分（面積23.24平方公尺）之地上物拆除，並將土地返還原告。(二)被告李清江應將坐落系爭土地上如附圖所示B（面積26.75平方公尺）、B1（面積1.81平方公尺）、B2（面積15.19平方公尺）、B3（29.77平方公尺）、B4部分（面積49.75平方公尺）之地上物拆除，並將土地返還原告。(三)被告李正安應將坐落系爭土地如附圖所示C（面積67.62平方公尺）、C1部分（面積1.38平方公尺）之地上物拆除，並將土地返還原告。(四)願供擔保請准宣告假執行。四、被告李清江、李正安則以：系爭土地係兩造先祖自日據時期所遺留之家產，依臺灣民事習慣調查報告，臺灣之家產，自清代即屬父祖子孫所構成家屬之公同共有，故系爭土地依舊有習慣係屬兩造共有分管家產，經兩造子孫分別搭建房屋使用，伊等並非無權占有等語，資為抗辯。並聲明：原告之訴駁回。五、李文楷未於言詞辯論期日到場，亦未提出書狀作何聲明或陳述。六、兩造不爭執之事項：(一)系爭土地原登記於原告之被繼承人李忠恕名下，原告於93年7月8日因繼承而取得，並於95年2月21日辦理繼承登記，此有土地登記謄本在卷可稽（見本院卷一第6-13頁）。(二)李文楷占用如附圖所示A部分（面積23.24平方公尺）；李清江占用如附圖所示B（面積26.75平方公尺）、B1（面積1.81平方公尺）、B2（面積15.19平方公尺）、B3（29.77平方公尺）、B4部分（面積49.75平方公尺）；李正安占用如附圖所示C（面積67.62平方公尺）、C1部分（面積1.38平方公尺），業經本院會同高雄市政府地政局鹽埕地政事務所人員到場履勘屬實，並製有勘驗筆錄及複丈成果圖等件附卷可憑（見本院卷一第69-71、143-144、186-187頁）。七、本件之爭點：被告就系爭土地有無合法占有使用權源？原告請求被告拆屋還地，有無理由？(一)按民事，法律所未規定者，依習慣；無習慣者，依法理，民法第1條定有明文。職是，習慣僅於法律無明文規定時有補充之效力。我國民法自18年10月10日已公布施行，而台灣自34年光復後，脫離日本國之統治，同受我國民法規定之適用。且同法第827條規定就公同關係而共有一物，應依法律規定或依契約始得成立。此外，民法物權編並未承認「家產」之制度或規定「家產」為公同共有關係發生之原因。換言之，明文排除依習慣或法理成立公同共有關係，此觀物權編第1條物權法定主義之規定即明。(二)查系爭1158地號土地重測前為同段180地號，於68年2月16日分割增加同段180-1、180-2、180-3地號土地，系爭1159地號土地重測前為180-1地號土地；系爭1160地號土地重測前為180-2地號土地；系爭1161地號土地重測前為180-3地號土地，該180-1、180-2、180-3地號土地均係於68年2月16日分割自180地號土地。而180地號土地係於35年7月26日辦理總登記，所有權人為訴外人李朝巡，由李忠恕於38年8月28日因繼承而取得，並於42年1月28日辦理繼承登記，原告再於93年7月8日因繼承而取得，並於95年2月21日辦理繼承登記，此有土地登記謄本及異動索引附卷可稽（見本院卷一第74-109頁），是系爭土地係於38年間辦理總登記，登記所有權人為李朝巡，嗣於42年間以繼承為原因移轉登記予李忠恕，原告再於95年間以繼承為原因取得系爭土地所有權，則李朝巡、李忠恕及原告先後取得系爭土地所有權，均係發生在台灣光復之後，並非發生在清朝或日據時代，其法律關係自應以我國民法定之，而無適用習慣之餘地甚明。且家產為公同共有之習慣，並非依法律規定或契約而成立公同共有關係，自違反前述物權法定主義。故被告李清江、李正安辯稱：系爭土地依舊有習慣為家產，係屬兩造公同共有云云，洵屬無據，委無足取。(三)被告李清江、李正安辯稱：依臺灣民事習慣調查報告（見本院卷二第31-34），臺灣之家產，自清代即屬父祖子孫所構成家屬之公同共有，故系爭土地係屬兩造共有分管之家產等語。然該調查報告，係就清代及日據時代所遺留未分割之財產所有權之歸屬糾紛而為論述，而清代及日據時代，為我國主權所不及，並無我國民法之適用，斯時有承認習慣法之必要，與本件系爭土地係於台灣光復後依法辦理總登記及繼承登記之情形並不相同。又縱認系爭土地於清代及日據時代係屬公同共有之家產，然系爭土地既已於台灣光復後總登記為李朝巡單獨所有，則該家產之公同共有關係已於上開總登記時而為終止，系爭土地自非屬兩造公同共有之家產，應堪認定。被告上開所辯，洵非可採。至被告另以李氏先祖多人曾於系爭土地之前身180番號設籍，故系爭土地無「鬮分」或「歸就」即無分產之情事，惟設籍僅係戶籍之行政管理，非所有權認定之依據，縱多人設籍同戶，亦難認該等人均為設籍土地之公同共有人，被告李清江、李正安據此而為推論，顯係臆測之詞，亦非可採。(四)按所有人對於無權占有或侵奪其所有物者，得請求返還之。對於妨害其所有權者，得請求除去之。有妨害其所有權之虞者，得請求防止之。民法第767條定有明文。系爭土地既為原告所有，被告未經同意而無正當權源占有系爭土地，自屬無權占有。從而，原告依民法第767條規定，請求李文楷應將坐落系爭土地上如附圖所示A部分（面積23.24平方公尺）之地上物拆除，並將土地返還原告；李清江應將坐落系爭土地上如附圖所示B（面積26.75平方公尺）、B1（面積1.81平方公尺）、B2（面積15.19平方公尺）、B3（29.77平方公尺）、B4部分（面積49.75平方公尺）之地上物拆除，並將土地返還原告；李正安應將坐落系爭土地如附圖所示C（面積67.62平方公尺）、C1部分（面積1.38平方公尺）之地上物拆除，並將土地返還原告，洵屬有據，應予准許。八、原告陳明願供擔保請准宣告假執行，經核無不合，爰酌定相當擔保金額准許之。九、本件事證已臻明確，兩造其餘攻擊防禦方法及舉證，核與判決無影響，毋庸逐一論列，併此敘明。十、據上論結，本件原告之訴為有理由，依民事訴訟法第385條第1項前段、第85條第1項但書、第390條第2項，判決如主文。中華民國100年7月29日民事鳳山分庭法官何悅芳以上正本係照原本作成。如對本判決上訴，須於判決送達後20日內向本院提出上訴狀。如委任律師提起上訴者，應一併繳納上訴審裁判費。中華民國100年7月29日書記官陳俐嫺",
  "characters": {
    "judges": [
      "何悅芳"
    ],
    "prosecutors": [

    ],
    "lawyers": [
      "黃建雄",
      "余景登",
      "委任"
    ],
    "clerks": [

    ],
    "plaintiffs": [
      "李溫雄"
    ],
    "defendants": [
      "李清江",
      "李正安",
      "李文楷"
    ],
    "prosecutor_office": [

    ],
    "creditors": [

    ],
    "debtors": [

    ],
    "judicial_associate_officer": [

    ]
  },
  "adjudged_at": "2011-07-29",
  "created_at": "2016-02-14 02:11:29",
  "updated_at": "2016-02-14 02:11:29"
}