{
  "identify": "PCD-100-易-1428-20110729-1",
  "court": {
    "name": "臺灣新北地方法院",
    "code": "PCD"
  },
  "division": {
    "name": "刑事",
    "code": "M"
  },
  "year": 100,
  "word": "易",
  "number": "1428",
  "jcheck": "1",
  "reason": "詐欺",
  "content": "臺灣板橋地方法院刑事判決             100年度易字第1428號\n公  訴  人  臺灣板橋地方法院檢察署檢察官\n被      告  張資培\n上列被告因詐欺案件，經檢察官提起公訴（100 年度調偵字第26\n0 號），被告於準備程序為認罪陳述，經本院合議庭裁定由受命\n法官行簡式審判程序，判決如下：\n    主      文\n張資培共同犯詐欺取財罪，處有期徒刑陸月，如易科罰金，以新\n臺幣壹仟元折算壹日；緩刑貳年，緩刑期間付保護管束，並應接\n受拾小時之法律教育課程。\n    事實及理由\n一、本件係依刑事訴訟法第273 條之1 第1 項規定，以簡式審判\n    程序審理，合先敘明。\n二、本件犯罪事實、證據，除就證據欄部分補充：「被告於本院\n    審理時之自白」外，餘均引用如附件檢察官起訴書之記載。\n三、核被告所為，係犯刑法第339 條第1 項之詐欺取財罪；又被\n    告與真實年籍姓名不詳自稱「劉明正」之成年男子間，就本\n    件犯行，有犯意聯絡、行為分擔，應依刑法第28條規定，論\n    以共同正犯。\n四、爰審酌被告犯罪之動機、目的、手段，及犯後於本院審理時\n    坦承犯行，知所悔悟等一切情狀，就其本件犯行，量處如主\n    文所示之刑，並諭知如易科罰金之折算標準，以資懲儆；又\n    被告前未曾因故意犯罪受有期徒刑以上刑之宣告，有臺灣高\n    等法院被告前案紀錄表1 份在卷可參，其因一時失慮，致罹\n    刑典，經此次偵審、科刑教訓後，應知警惕而無再犯之虞，\n    本院認前述對其所宣告之刑，以暫不執行為適當，爰依刑法\n    第74條第1 項第1 款規定，併予宣告緩刑2 年，以啟自新；\n    惟為使被告能深切記取教訓，及強化其法治觀念，使於緩刑\n    期內深知警惕，避免再度犯罪，茲併依刑法第74條第2 項第\n    8 款規定，命被告應接受30小時之法律教育課程，另依刑法\n    第93條第1 項第2 款規定，宣告緩刑期間付保護管束（被告\n    若違反刑法第74條第2 項第8 款所定預防再犯所為之必要命\n    令情節重大者，檢察官得斟酌依刑法第75條之1 第1 項第4\n    款規定聲請撤銷緩刑，併此敘明）。\n據上論斷，應依刑事訴訟法第273 條之1 第1 項、第299 條第1\n項前段、第310 條之2 、第454 條第2 項，刑法第28條、第339\n條第1 項、第41條第1 項前段、第74條第1 項第1 款、第2 項第\n8 款、第93條第1 項第2 款，刑法施行法第1 條之1 ，判決如主\n文。\n本案經檢察官高智美到庭執行職務。\n中    華    民    國   100    年    7     月    29    日\n                  刑事第二十庭  法  官  陳明偉\n上列正本證明與原本無異。\n如不服本判決，應於判決送達後10日內敘明上訴理由，向本院提\n出上訴狀 (應附繕本)，上訴於臺灣高等法院。其未敘述上訴理\n由者，應於上訴期間屆滿後20日內向本院補提理由書「切勿逕送\n上級法院」。\n                                書記官  尤怡文\n中    華    民    國   100    年    7     月    29    日\n附錄本案論罪科刑法條全文：\n中華民國刑法第339條\n意圖為自己或第三人不法之所有，以詐術使人將本人或第三人之\n物交付者，處5 年以下有期徒刑、拘役或科或併科1 千元以下罰\n金。\n以前項方法得財產上不法之利益或使第三人得之者，亦同。\n前二項之未遂犯罰之。",
  "structure": {
    "main": "張資培共同犯詐欺取財罪，處有期徒刑陸月，如易科罰金，以新\n臺幣壹仟元折算壹日；緩刑貳年，緩刑期間付保護管束，並應接\n受拾小時之法律教育課程。",
    "fact": "一、本件係依刑事訴訟法第273 條之1 第1 項規定，以簡式審判\n    程序審理，合先敘明。\n二、本件犯罪事實、證據，除就證據欄部分補充：「被告於本院\n    審理時之自白」外，餘均引用如附件檢察官起訴書之記載。\n三、核被告所為，係犯刑法第339 條第1 項之詐欺取財罪；又被\n    告與真實年籍姓名不詳自稱「劉明正」之成年男子間，就本\n    件犯行，有犯意聯絡、行為分擔，應依刑法第28條規定，論\n    以共同正犯。\n四、爰審酌被告犯罪之動機、目的、手段，及犯後於本院審理時\n    坦承犯行，知所悔悟等一切情狀，就其本件犯行，量處如主\n    文所示之刑，並諭知如易科罰金之折算標準，以資懲儆；又\n    被告前未曾因故意犯罪受有期徒刑以上刑之宣告，有臺灣高\n    等法院被告前案紀錄表1 份在卷可參，其因一時失慮，致罹\n    刑典，經此次偵審、科刑教訓後，應知警惕而無再犯之虞，\n    本院認前述對其所宣告之刑，以暫不執行為適當，爰依刑法\n    第74條第1 項第1 款規定，併予宣告緩刑2 年，以啟自新；\n    惟為使被告能深切記取教訓，及強化其法治觀念，使於緩刑\n    期內深知警惕，避免再度犯罪，茲併依刑法第74條第2 項第\n    8 款規定，命被告應接受30小時之法律教育課程，另依刑法\n    第93條第1 項第2 款規定，宣告緩刑期間付保護管束（被告\n    若違反刑法第74條第2 項第8 款所定預防再犯所為之必要命\n    令情節重大者，檢察官得斟酌依刑法第75條之1 第1 項第4\n    款規定聲請撤銷緩刑，併此敘明）。\n據上論斷，應依刑事訴訟法第273 條之1 第1 項、第299 條第1\n項前段、第310 條之2 、第454 條第2 項，刑法第28條、第339\n條第1 項、第41條第1 項前段、第74條第1 項第1 款、第2 項第\n8 款、第93條第1 項第2 款，刑法施行法第1 條之1 ，判決如主\n文。\n本案經檢察官高智美到庭執行職務。",
    "reason": "一、本件係依刑事訴訟法第273 條之1 第1 項規定，以簡式審判\n    程序審理，合先敘明。\n二、本件犯罪事實、證據，除就證據欄部分補充：「被告於本院\n    審理時之自白」外，餘均引用如附件檢察官起訴書之記載。\n三、核被告所為，係犯刑法第339 條第1 項之詐欺取財罪；又被\n    告與真實年籍姓名不詳自稱「劉明正」之成年男子間，就本\n    件犯行，有犯意聯絡、行為分擔，應依刑法第28條規定，論\n    以共同正犯。\n四、爰審酌被告犯罪之動機、目的、手段，及犯後於本院審理時\n    坦承犯行，知所悔悟等一切情狀，就其本件犯行，量處如主\n    文所示之刑，並諭知如易科罰金之折算標準，以資懲儆；又\n    被告前未曾因故意犯罪受有期徒刑以上刑之宣告，有臺灣高\n    等法院被告前案紀錄表1 份在卷可參，其因一時失慮，致罹\n    刑典，經此次偵審、科刑教訓後，應知警惕而無再犯之虞，\n    本院認前述對其所宣告之刑，以暫不執行為適當，爰依刑法\n    第74條第1 項第1 款規定，併予宣告緩刑2 年，以啟自新；\n    惟為使被告能深切記取教訓，及強化其法治觀念，使於緩刑\n    期內深知警惕，避免再度犯罪，茲併依刑法第74條第2 項第\n    8 款規定，命被告應接受30小時之法律教育課程，另依刑法\n    第93條第1 項第2 款規定，宣告緩刑期間付保護管束（被告\n    若違反刑法第74條第2 項第8 款所定預防再犯所為之必要命\n    令情節重大者，檢察官得斟酌依刑法第75條之1 第1 項第4\n    款規定聲請撤銷緩刑，併此敘明）。\n據上論斷，應依刑事訴訟法第273 條之1 第1 項、第299 條第1\n項前段、第310 條之2 、第454 條第2 項，刑法第28條、第339\n條第1 項、第41條第1 項前段、第74條第1 項第1 款、第2 項第\n8 款、第93條第1 項第2 款，刑法施行法第1 條之1 ，判決如主\n文。\n本案經檢察官高智美到庭執行職務。"
  },
  "search": "臺灣板橋地方法院刑事判決100年度易字第1428號公訴人臺灣板橋地方法院檢察署檢察官被告張資培上列被告因詐欺案件，經檢察官提起公訴（100年度調偵字第260號），被告於準備程序為認罪陳述，經本院合議庭裁定由受命法官行簡式審判程序，判決如下：主文張資培共同犯詐欺取財罪，處有期徒刑陸月，如易科罰金，以新臺幣壹仟元折算壹日；緩刑貳年，緩刑期間付保護管束，並應接受拾小時之法律教育課程。事實及理由一、本件係依刑事訴訟法第273條之1第1項規定，以簡式審判程序審理，合先敘明。二、本件犯罪事實、證據，除就證據欄部分補充：「被告於本院審理時之自白」外，餘均引用如附件檢察官起訴書之記載。三、核被告所為，係犯刑法第339條第1項之詐欺取財罪；又被告與真實年籍姓名不詳自稱「劉明正」之成年男子間，就本件犯行，有犯意聯絡、行為分擔，應依刑法第28條規定，論以共同正犯。四、爰審酌被告犯罪之動機、目的、手段，及犯後於本院審理時坦承犯行，知所悔悟等一切情狀，就其本件犯行，量處如主文所示之刑，並諭知如易科罰金之折算標準，以資懲儆；又被告前未曾因故意犯罪受有期徒刑以上刑之宣告，有臺灣高等法院被告前案紀錄表1份在卷可參，其因一時失慮，致罹刑典，經此次偵審、科刑教訓後，應知警惕而無再犯之虞，本院認前述對其所宣告之刑，以暫不執行為適當，爰依刑法第74條第1項第1款規定，併予宣告緩刑2年，以啟自新；惟為使被告能深切記取教訓，及強化其法治觀念，使於緩刑期內深知警惕，避免再度犯罪，茲併依刑法第74條第2項第8款規定，命被告應接受30小時之法律教育課程，另依刑法第93條第1項第2款規定，宣告緩刑期間付保護管束（被告若違反刑法第74條第2項第8款所定預防再犯所為之必要命令情節重大者，檢察官得斟酌依刑法第75條之1第1項第4款規定聲請撤銷緩刑，併此敘明）。據上論斷，應依刑事訴訟法第273條之1第1項、第299條第1項前段、第310條之2、第454條第2項，刑法第28條、第339條第1項、第41條第1項前段、第74條第1項第1款、第2項第8款、第93條第1項第2款，刑法施行法第1條之1，判決如主文。本案經檢察官高智美到庭執行職務。中華民國100年7月29日刑事第二十庭法官陳明偉上列正本證明與原本無異。如不服本判決，應於判決送達後10日內敘明上訴理由，向本院提出上訴狀(應附繕本)，上訴於臺灣高等法院。其未敘述上訴理由者，應於上訴期間屆滿後20日內向本院補提理由書「切勿逕送上級法院」。書記官尤怡文中華民國100年7月29日附錄本案論罪科刑法條全文：中華民國刑法第339條意圖為自己或第三人不法之所有，以詐術使人將本人或第三人之物交付者，處5年以下有期徒刑、拘役或科或併科1千元以下罰金。以前項方法得財產上不法之利益或使第三人得之者，亦同。前二項之未遂犯罰之。",
  "characters": {
    "judges": [
      "陳明偉"
    ],
    "prosecutors": [
      "高智美"
    ],
    "lawyers": [

    ],
    "clerks": [
      "尤怡文"
    ],
    "plaintiffs": [

    ],
    "defendants": [
      "張資培"
    ],
    "prosecutor_office": [
      "臺灣板橋地方法院檢察署檢察官"
    ],
    "creditors": [

    ],
    "debtors": [

    ],
    "judicial_associate_officer": [

    ]
  },
  "adjudged_at": "2011-07-29",
  "created_at": "2016-02-14 01:43:54",
  "updated_at": "2016-02-14 01:43:54"
}