{
  "identify": "TCD-99-選-12-20110729-4",
  "court": {
    "name": "臺灣臺中地方法院",
    "code": "TCD"
  },
  "division": {
    "name": "民事",
    "code": "V"
  },
  "year": 99,
  "word": "選",
  "number": "12",
  "jcheck": "4",
  "reason": "當選無效",
  "content": "臺灣臺中地方法院民事裁定  99年度選字第12號\n上  訴  人\n即  原  告  林清松\n被 上訴 人\n即  被  告  謝榮慶\n上當事人間當選無效事件，上訴人對於民國100年6月3日本院第\n一審判決提起上訴，本院裁定如下：\n    主    文\n上訴駁回。\n第二審訴訟費用由上訴人負擔。\n    理    由\n一、按上訴不合程式或有其他不合法之情形而可以補正者，原第\n    一審法院應定期間命其補正，如不於期間內補正，應以裁定\n    駁回之，民事訴訟法第442條第2項定有明文。次按向第二審\n    法院上訴，應依民事訴訟法第77條之13及第77條之14規定，\n    加徵裁判費10分之5；且依前開規定繳納裁判費，此為必須\n    具備之程式。\n二、查本件上訴人提起第二審上訴，未據繳裁判費，經本院於10\n    0年6月28日裁定，限上訴人於收受裁定送達後5日內補正，\n    此項裁定於100年7月4日送達，有送達證書在卷可稽。然上\n    訴人逾期迄今仍未補正，亦有本院民事科查詢簡答表1份在\n    卷可證，則上訴人上訴自非合法，應予駁回。\n三、依民事訴訟法第442條第2項、第95條、第78條，裁定如主文\n    。\n中    華    民    國   100    年    7     月    29    日\n                  民事第二庭審判長法  官  王  銘\n                                  法  官  陳卿和\n                                  法  官  吳崇道\n正本係照原本作成\n如不服本裁定應於送達後10日內向本院提出抗告狀，並繳納抗告\n費新臺幣1,000元。\n中    華    民    國   100    年    7     月    29    日\n                                  書記官",
  "structure": {
    "main": "上訴駁回。\n第二審訴訟費用由上訴人負擔。",
    "reason": "一、按上訴不合程式或有其他不合法之情形而可以補正者，原第\n    一審法院應定期間命其補正，如不於期間內補正，應以裁定\n    駁回之，民事訴訟法第442條第2項定有明文。次按向第二審\n    法院上訴，應依民事訴訟法第77條之13及第77條之14規定，\n    加徵裁判費10分之5；且依前開規定繳納裁判費，此為必須\n    具備之程式。\n二、查本件上訴人提起第二審上訴，未據繳裁判費，經本院於10\n    0年6月28日裁定，限上訴人於收受裁定送達後5日內補正，\n    此項裁定於100年7月4日送達，有送達證書在卷可稽。然上\n    訴人逾期迄今仍未補正，亦有本院民事科查詢簡答表1份在\n    卷可證，則上訴人上訴自非合法，應予駁回。\n三、依民事訴訟法第442條第2項、第95條、第78條，裁定如主文\n    。"
  },
  "search": "臺灣臺中地方法院民事裁定99年度選字第12號上訴人即原告林清松被上訴人即被告謝榮慶上當事人間當選無效事件，上訴人對於民國100年6月3日本院第一審判決提起上訴，本院裁定如下：主文上訴駁回。第二審訴訟費用由上訴人負擔。理由一、按上訴不合程式或有其他不合法之情形而可以補正者，原第一審法院應定期間命其補正，如不於期間內補正，應以裁定駁回之，民事訴訟法第442條第2項定有明文。次按向第二審法院上訴，應依民事訴訟法第77條之13及第77條之14規定，加徵裁判費10分之5；且依前開規定繳納裁判費，此為必須具備之程式。二、查本件上訴人提起第二審上訴，未據繳裁判費，經本院於100年6月28日裁定，限上訴人於收受裁定送達後5日內補正，此項裁定於100年7月4日送達，有送達證書在卷可稽。然上訴人逾期迄今仍未補正，亦有本院民事科查詢簡答表1份在卷可證，則上訴人上訴自非合法，應予駁回。三、依民事訴訟法第442條第2項、第95條、第78條，裁定如主文。中華民國100年7月29日民事第二庭審判長法官王銘法官陳卿和法官吳崇道正本係照原本作成如不服本裁定應於送達後10日內向本院提出抗告狀，並繳納抗告費新臺幣1,000元。中華民國100年7月29日書記官",
  "characters": {
    "judges": [
      "王銘",
      "陳卿和",
      "吳崇道"
    ],
    "prosecutors": [

    ],
    "lawyers": [

    ],
    "clerks": [

    ],
    "plaintiffs": [
      "林清松"
    ],
    "defendants": [
      "謝榮慶"
    ],
    "prosecutor_office": [

    ],
    "creditors": [

    ],
    "debtors": [

    ],
    "judicial_associate_officer": [

    ]
  },
  "adjudged_at": "2011-07-29",
  "created_at": "2016-02-14 01:41:20",
  "updated_at": "2016-02-14 01:41:20"
}