{
  "identify": "TPD-100-聲-1960-20110729-1",
  "court": {
    "name": "臺灣臺北地方法院",
    "code": "TPD"
  },
  "division": {
    "name": "刑事",
    "code": "M"
  },
  "year": 100,
  "word": "聲",
  "number": "1960",
  "jcheck": "1",
  "reason": "聲請定其應執行刑",
  "content": "臺灣臺北地方法院刑事裁定             100年度聲字第1960號\n聲  請  人  臺灣臺北地方法院檢察署檢察官\n受  刑  人  林凱新\n上列聲請人因受刑人數罪併罰有二裁判以上，聲請定其應執行之\n刑，本院裁定如下：\n    主  文\n林凱新因附表等罪，所處如附表所示之刑，應執行有期徒刑肆年\n陸月。\n    理  由\n一、查受刑人林凱新犯詐欺等罪，先後經臺灣士林地方法院、臺\n    灣高等法院及本院判處如附表所示之刑，並均分別確定在案\n    。茲檢察官聲請定其應執行之刑，本院審核認聲請為正當，\n    應定其應執行之刑。\n二、爰依刑事訴訟法第477 條第1 項，刑法第53條、第51條第5\n    款，裁定如主文。\n中    華    民    國   100    年    7     月    29    日\n                  刑事第十六庭  法  官  葉藍鸚\n以上正本證明與原本無異。\n如不服本裁定，應於裁定送達後5日內向本院提出抗告狀。\n                                書記官  黃芝凌\n中    華    民    國   100    年    7     月    29    日\n附表\n┌──┬──────┬────┬────┬───────┬─────┐\n│編號│  罪    名  │宣 告 刑│犯罪日期│最後事實審法院│判決日期  │\n│    │            │        │        ├───────┼─────┤\n│    │            │        │        │ 案        號 │確定日期  │\n├──┼──────┼────┼────┼───────┼─────┤\n│ 1  │詐欺        │有期徒刑│97.06.02│士林地院      │99.03.23  │\n│    │            │4月     │        ├───────┼─────┤\n│    │            │        │        │99年度審簡字第│99.06.29  │\n│    │            │        │        │310號         │          │\n├──┼──────┼────┼────┼───────┼─────┤\n│ 2  │詐欺        │有期徒刑│97.06.26│士林地院      │99.03.23  │\n│    │            │3月     │        ├───────┼─────┤\n│    │            │        │        │99年度審簡字第│99.06.29  │\n│    │            │        │        │310號         │          │\n├──┼──────┼────┼────┼───────┼─────┤\n│ 3  │毒品危害防制│有期徒刑│98.03.24│士林地院      │99.03.24  │\n│    │條例        │10月    │        ├───────┼─────┤\n│    │            │        │        │99年度審訴緝字│99.08.10  │\n│    │            │        │        │第4號         │          │\n├──┼──────┼────┼────┼───────┼─────┤\n│ 4  │毒品危害防制│有期徒刑│98.04.22│士林地院      │99.03.24  │\n│    │條例        │8 月    │        ├───────┼─────┤\n│    │            │        │        │99年度審訴緝字│99.08.24  │\n│    │            │        │        │第3號         │          │\n├──┼──────┼────┼────┼───────┼─────┤\n│ 5  │偽造文書    │有期徒刑│99.01.29│本院          │99.05.21  │\n│    │            │6月     │        ├───────┼─────┤\n│    │            │        │        │99年度簡字第  │99.08.31  │\n│    │            │        │        │1849號        │          │\n├──┼──────┼────┼────┼───────┼─────┤\n│ 6  │偽造文書    │有期徒刑│97.09.27│臺灣高院      │99.09.28  │\n│    │            │5 月    │晚間7 時├───────┼─────┤\n│    │            │        │11分許  │99年度上訴字第│99.10.26  │\n│    │            │        │        │2229號        │          │\n│    ├──────┼────┼────┼───────┼─────┤\n│    │偽造文書    │有期徒刑│97.09.28│同上          │99.09.28  │\n│    │            │5月     │上午10時├───────┼─────┤\n│    │            │        │45分    │同上          │99.10.26  │\n│    │            │        │        │              │          │\n│    ├──────┼────┼────┼───────┼─────┤\n│    │偽造文書    │有期徒刑│97.09.29│同上          │99.09.28  │\n│    │            │5月     │下午4 時├───────┼─────┤\n│    │            │        │43分    │同上          │99.10.26  │\n│    │            │        │        │              │          │\n│    ├──────┼────┼────┼───────┼─────┤\n│    │偽造文書    │有期徒刑│97.09.29│同上          │99.09.28  │\n│    │            │5月     │下午5 時├───────┼─────┤\n│    │            │        │18分    │同上          │99.10.26  │\n│    │            │        │        │              │          │\n│    ├──────┼────┼────┼───────┼─────┤\n│    │偽造文書    │有期徒刑│97.09.29│同上          │99.09.28  │\n│    │            │5月     │下午5 時├───────┼─────┤\n│    │            │        │55分    │同上          │99.10.26  │\n│    │            │        │        │              │          │\n│    ├──────┼────┼────┼───────┼─────┤\n│    │偽造文書    │有期徒刑│97.09.29│同上          │99.09.28  │\n│    │            │5月     │晚間7 時├───────┼─────┤\n│    │            │        │29分    │同上          │99.10.26  │\n│    │            │        │        │              │          │\n│    ├──────┼────┼────┼───────┼─────┤\n│    │詐欺        │有期徒刑│97.09.29│同上          │99.09.28  │\n│    │            │4月     │下午5 時├───────┼─────┤\n│    │            │        │43分    │同上          │99.10.26  │\n│    │            │        │        │              │          │\n│    ├──────┼────┼────┼───────┼─────┤\n│    │詐欺        │有期徒刑│97.09.29│同上          │99.09.28  │\n│    │            │3月     │晚間7 時├───────┼─────┤\n│    │            │        │50分    │同上          │99.10.26  │\n│    │            │        │        │              │          │\n│    ├──────┼────┼────┼───────┼─────┤\n│    │詐欺        │有期徒刑│97.09.30│同上          │99.09.28  │\n│    │            │3月     │        ├───────┼─────┤\n│    │            │        │        │同上          │99.10.26  │\n│    │            │        │        │              │          │\n│    ├──────┼────┼────┼───────┼─────┤\n│    │竊盜        │有期徒刑│97.09.27│同上          │99.09.28  │\n│    │            │3月     │凌晨    ├───────┼─────┤\n│    │            │        │        │同上          │99.10.26  │\n│    │            │        │        │              │          │\n├──┼──────┼────┼────┼───────┼─────┤\n│ 7  │侵占        │有期徒刑│98.01.01│本院          │99.06.18  │\n│    │            │8月     │        ├───────┼─────┤\n│    │            │        │        │99年度易緝字第│99.10.19  │\n│    │            │        │        │42號          │          │\n├──┼──────┼────┼────┼───────┼─────┤\n│ 8  │偽造文書    │有期徒刑│97.12.30│本院          │100.04.14 │\n│    │            │4月     │至98.1.1├───────┼─────┤\n│    │            │        │        │100 年度簡字第│100.05.12 │\n│    │            │        │        │1266號        │          │\n├──┼──────┼────┼────┼───────┼─────┤\n│ 9  │偽造文書    │有期徒刑│98.03.22│本院          │100.04.14 │\n│    │            │3月     │        ├───────┼─────┤\n│    │            │        │        │100 年度簡字第│100.05.12 │\n│    │            │        │        │1266號        │          │\n└──┴──────┴────┴────┴───────┴─────┘",
  "structure": {
    "main": "林凱新因附表等罪，所處如附表所示之刑，應執行有期徒刑肆年\n陸月。",
    "reason": "一、查受刑人林凱新犯詐欺等罪，先後經臺灣士林地方法院、臺\n    灣高等法院及本院判處如附表所示之刑，並均分別確定在案\n    。茲檢察官聲請定其應執行之刑，本院審核認聲請為正當，\n    應定其應執行之刑。\n二、爰依刑事訴訟法第477 條第1 項，刑法第53條、第51條第5\n    款，裁定如主文。"
  },
  "search": "臺灣臺北地方法院刑事裁定100年度聲字第1960號聲請人臺灣臺北地方法院檢察署檢察官受刑人林凱新上列聲請人因受刑人數罪併罰有二裁判以上，聲請定其應執行之刑，本院裁定如下：主文林凱新因附表等罪，所處如附表所示之刑，應執行有期徒刑肆年陸月。理由一、查受刑人林凱新犯詐欺等罪，先後經臺灣士林地方法院、臺灣高等法院及本院判處如附表所示之刑，並均分別確定在案。茲檢察官聲請定其應執行之刑，本院審核認聲請為正當，應定其應執行之刑。二、爰依刑事訴訟法第477條第1項，刑法第53條、第51條第5款，裁定如主文。中華民國100年7月29日刑事第十六庭法官葉藍鸚以上正本證明與原本無異。如不服本裁定，應於裁定送達後5日內向本院提出抗告狀。書記官黃芝凌中華民國100年7月29日附表┌──┬──────┬────┬────┬───────┬─────┐│編號│罪名│宣告刑│犯罪日期│最後事實審法院│判決日期│││││├───────┼─────┤│││││案號│確定日期│├──┼──────┼────┼────┼───────┼─────┤│1│詐欺│有期徒刑│97.06.02│士林地院│99.03.23││││4月│├───────┼─────┤│││││99年度審簡字第│99.06.29││││││310號││├──┼──────┼────┼────┼───────┼─────┤│2│詐欺│有期徒刑│97.06.26│士林地院│99.03.23││││3月│├───────┼─────┤│││││99年度審簡字第│99.06.29││││││310號││├──┼──────┼────┼────┼───────┼─────┤│3│毒品危害防制│有期徒刑│98.03.24│士林地院│99.03.24│││條例│10月│├───────┼─────┤│││││99年度審訴緝字│99.08.10││││││第4號││├──┼──────┼────┼────┼───────┼─────┤│4│毒品危害防制│有期徒刑│98.04.22│士林地院│99.03.24│││條例│8月│├───────┼─────┤│││││99年度審訴緝字│99.08.24││││││第3號││├──┼──────┼────┼────┼───────┼─────┤│5│偽造文書│有期徒刑│99.01.29│本院│99.05.21││││6月│├───────┼─────┤│││││99年度簡字第│99.08.31││││││1849號││├──┼──────┼────┼────┼───────┼─────┤│6│偽造文書│有期徒刑│97.09.27│臺灣高院│99.09.28││││5月│晚間7時├───────┼─────┤││││11分許│99年度上訴字第│99.10.26││││││2229號│││├──────┼────┼────┼───────┼─────┤││偽造文書│有期徒刑│97.09.28│同上│99.09.28││││5月│上午10時├───────┼─────┤││││45分│同上│99.10.26│││││││││├──────┼────┼────┼───────┼─────┤││偽造文書│有期徒刑│97.09.29│同上│99.09.28││││5月│下午4時├───────┼─────┤││││43分│同上│99.10.26│││││││││├──────┼────┼────┼───────┼─────┤││偽造文書│有期徒刑│97.09.29│同上│99.09.28││││5月│下午5時├───────┼─────┤││││18分│同上│99.10.26│││││││││├──────┼────┼────┼───────┼─────┤││偽造文書│有期徒刑│97.09.29│同上│99.09.28││││5月│下午5時├───────┼─────┤││││55分│同上│99.10.26│││││││││├──────┼────┼────┼───────┼─────┤││偽造文書│有期徒刑│97.09.29│同上│99.09.28││││5月│晚間7時├───────┼─────┤││││29分│同上│99.10.26│││││││││├──────┼────┼────┼───────┼─────┤││詐欺│有期徒刑│97.09.29│同上│99.09.28││││4月│下午5時├───────┼─────┤││││43分│同上│99.10.26│││││││││├──────┼────┼────┼───────┼─────┤││詐欺│有期徒刑│97.09.29│同上│99.09.28││││3月│晚間7時├───────┼─────┤││││50分│同上│99.10.26│││││││││├──────┼────┼────┼───────┼─────┤││詐欺│有期徒刑│97.09.30│同上│99.09.28││││3月│├───────┼─────┤│││││同上│99.10.26│││││││││├──────┼────┼────┼───────┼─────┤││竊盜│有期徒刑│97.09.27│同上│99.09.28││││3月│凌晨├───────┼─────┤│││││同上│99.10.26││││││││├──┼──────┼────┼────┼───────┼─────┤│7│侵占│有期徒刑│98.01.01│本院│99.06.18││││8月│├───────┼─────┤│││││99年度易緝字第│99.10.19││││││42號││├──┼──────┼────┼────┼───────┼─────┤│8│偽造文書│有期徒刑│97.12.30│本院│100.04.14││││4月│至98.1.1├───────┼─────┤│││││100年度簡字第│100.05.12││││││1266號││├──┼──────┼────┼────┼───────┼─────┤│9│偽造文書│有期徒刑│98.03.22│本院│100.04.14││││3月│├───────┼─────┤│││││100年度簡字第│100.05.12││││││1266號││└──┴──────┴────┴────┴───────┴─────┘",
  "characters": {
    "judges": [
      "葉藍鸚"
    ],
    "prosecutors": [

    ],
    "lawyers": [

    ],
    "clerks": [
      "黃芝凌"
    ],
    "plaintiffs": [

    ],
    "defendants": [

    ],
    "prosecutor_office": [
      "臺灣臺北地方法院檢察署檢察官"
    ],
    "creditors": [

    ],
    "debtors": [

    ],
    "judicial_associate_officer": [

    ]
  },
  "adjudged_at": "2011-07-29",
  "created_at": "2016-02-14 01:39:11",
  "updated_at": "2016-02-14 01:39:11"
}