{
  "identify": "TYD-100-壢交簡-1420-20110729-1",
  "court": {
    "name": "臺灣桃園地方法院",
    "code": "TYD"
  },
  "division": {
    "name": "刑事",
    "code": "M"
  },
  "year": 100,
  "word": "壢交簡",
  "number": "1420",
  "jcheck": "1",
  "reason": "公共危險",
  "content": "臺灣桃園地方法院刑事簡易判決     100年度壢交簡字第1420號\n聲  請  人  臺灣桃園地方法院檢察署檢察官\n被      告  覃子君\n上列被告因公共危險案件，經檢察官聲請以簡易判決處刑（100\n年度偵字第9974號），本院判決如下：\n    主      文\n覃子君服用酒類，不能安全駕駛動力交通工具而駕駛，累犯，處\n有期徒刑參月，如易科罰金，以新臺幣壹仟元折算壹日。\n    事實及理由\n一、本件犯罪事實及證據，除犯罪事實應補充「被告覃子君前於\n    民國95年間因飲酒後駕車案件，經本院以95年度壢交簡字第\n    2279號判決判處拘役55日確定，於96年10月4 日易科罰金執\n    行完畢；又於97年間因飲酒後駕車案件，經本院以97年度壢\n    交簡字第1261號判決判處有期徒刑3 月確定，於97年12月22\n    日執行完畢；另於97年間再因飲酒後駕車案件，經本院以97\n    年度壢交簡字第1460號判決判處拘役30日確定，於98年1 月\n    21日執行完畢」外，其餘均引用檢察官聲請簡易判決處刑書\n    之記載（如附件聲請書）。\n二、核被告覃子君所為，係犯刑法第185 條之3 之服用酒類不能\n    安全駕駛動力交通工具而駕駛罪。被告有前揭犯罪科刑及執\n    行之紀錄，有臺灣高等法院被告前案紀錄表在卷可按，於5\n    年以內故意再犯本件有期徒刑之罪，為累犯，應依刑法第47\n    條第1 項規定加重其刑。爰審酌被告前有多次飲酒後駕車之\n    犯罪紀錄，猶不知警惕，明知服用酒類後，於不能安全駕駛\n    之情形下，竟仍貿然騎乘機車上路，危及道路交通安全，且\n    乏尊重其他用路人生命、財產安全之觀念，所為非是，及被\n    告被查獲後，經測得之呼氣所含酒精成分達每公升0.56毫克\n    之犯罪情節，被告之智識程度、犯罪所生危害、素行及犯後\n    態度等一切情狀，量處如主文所示之刑，並諭知易科罰金之\n    折算標準，以示懲儆。\n三、據上論斷，應依刑事訴訟法第449 條第1 項前段、第3 項、\n    第454 條第2 項，刑法第185 條之3 、第47條第1 項、第41\n    條第1 項前段，刑法施行法第1 條之1 第1 項，逕以簡易判\n    決處刑如主文。\n四、如不服本判決，應於判決送達後10日內，向本院提出上訴狀\n    ，上訴於本院合議庭。\n中    華    民    國   100    年    7     月    29    日\n                  交 通 法 庭   法  官  劉為丕\n以上正本證明與原本無異。\n如不服本判決，應於判決送達後10日內向本院提出上訴狀（應附\n繕本）。\n                                書記官  陳淑瓊\n中    華    民    國   100    年    8     月    5     日\n附錄論罪科刑法條：\n中華民國刑法第185條之3\n服用毒品、麻醉藥品、酒類或其他相類之物，不能安全駕駛動力\n交通工具而駕駛者，處 1 年以下有期徒刑、拘役或科或併科 15\n萬元以下罰金。",
  "structure": {
    "main": "覃子君服用酒類，不能安全駕駛動力交通工具而駕駛，累犯，處\n有期徒刑參月，如易科罰金，以新臺幣壹仟元折算壹日。",
    "fact": "一、本件犯罪事實及證據，除犯罪事實應補充「被告覃子君前於\n    民國95年間因飲酒後駕車案件，經本院以95年度壢交簡字第\n    2279號判決判處拘役55日確定，於96年10月4 日易科罰金執\n    行完畢；又於97年間因飲酒後駕車案件，經本院以97年度壢\n    交簡字第1261號判決判處有期徒刑3 月確定，於97年12月22\n    日執行完畢；另於97年間再因飲酒後駕車案件，經本院以97\n    年度壢交簡字第1460號判決判處拘役30日確定，於98年1 月\n    21日執行完畢」外，其餘均引用檢察官聲請簡易判決處刑書\n    之記載（如附件聲請書）。\n二、核被告覃子君所為，係犯刑法第185 條之3 之服用酒類不能\n    安全駕駛動力交通工具而駕駛罪。被告有前揭犯罪科刑及執\n    行之紀錄，有臺灣高等法院被告前案紀錄表在卷可按，於5\n    年以內故意再犯本件有期徒刑之罪，為累犯，應依刑法第47\n    條第1 項規定加重其刑。爰審酌被告前有多次飲酒後駕車之\n    犯罪紀錄，猶不知警惕，明知服用酒類後，於不能安全駕駛\n    之情形下，竟仍貿然騎乘機車上路，危及道路交通安全，且\n    乏尊重其他用路人生命、財產安全之觀念，所為非是，及被\n    告被查獲後，經測得之呼氣所含酒精成分達每公升0.56毫克\n    之犯罪情節，被告之智識程度、犯罪所生危害、素行及犯後\n    態度等一切情狀，量處如主文所示之刑，並諭知易科罰金之\n    折算標準，以示懲儆。\n三、據上論斷，應依刑事訴訟法第449 條第1 項前段、第3 項、\n    第454 條第2 項，刑法第185 條之3 、第47條第1 項、第41\n    條第1 項前段，刑法施行法第1 條之1 第1 項，逕以簡易判\n    決處刑如主文。\n四、如不服本判決，應於判決送達後10日內，向本院提出上訴狀\n    ，上訴於本院合議庭。",
    "reason": "一、本件犯罪事實及證據，除犯罪事實應補充「被告覃子君前於\n    民國95年間因飲酒後駕車案件，經本院以95年度壢交簡字第\n    2279號判決判處拘役55日確定，於96年10月4 日易科罰金執\n    行完畢；又於97年間因飲酒後駕車案件，經本院以97年度壢\n    交簡字第1261號判決判處有期徒刑3 月確定，於97年12月22\n    日執行完畢；另於97年間再因飲酒後駕車案件，經本院以97\n    年度壢交簡字第1460號判決判處拘役30日確定，於98年1 月\n    21日執行完畢」外，其餘均引用檢察官聲請簡易判決處刑書\n    之記載（如附件聲請書）。\n二、核被告覃子君所為，係犯刑法第185 條之3 之服用酒類不能\n    安全駕駛動力交通工具而駕駛罪。被告有前揭犯罪科刑及執\n    行之紀錄，有臺灣高等法院被告前案紀錄表在卷可按，於5\n    年以內故意再犯本件有期徒刑之罪，為累犯，應依刑法第47\n    條第1 項規定加重其刑。爰審酌被告前有多次飲酒後駕車之\n    犯罪紀錄，猶不知警惕，明知服用酒類後，於不能安全駕駛\n    之情形下，竟仍貿然騎乘機車上路，危及道路交通安全，且\n    乏尊重其他用路人生命、財產安全之觀念，所為非是，及被\n    告被查獲後，經測得之呼氣所含酒精成分達每公升0.56毫克\n    之犯罪情節，被告之智識程度、犯罪所生危害、素行及犯後\n    態度等一切情狀，量處如主文所示之刑，並諭知易科罰金之\n    折算標準，以示懲儆。\n三、據上論斷，應依刑事訴訟法第449 條第1 項前段、第3 項、\n    第454 條第2 項，刑法第185 條之3 、第47條第1 項、第41\n    條第1 項前段，刑法施行法第1 條之1 第1 項，逕以簡易判\n    決處刑如主文。\n四、如不服本判決，應於判決送達後10日內，向本院提出上訴狀\n    ，上訴於本院合議庭。"
  },
  "search": "臺灣桃園地方法院刑事簡易判決100年度壢交簡字第1420號聲請人臺灣桃園地方法院檢察署檢察官被告覃子君上列被告因公共危險案件，經檢察官聲請以簡易判決處刑（100年度偵字第9974號），本院判決如下：主文覃子君服用酒類，不能安全駕駛動力交通工具而駕駛，累犯，處有期徒刑參月，如易科罰金，以新臺幣壹仟元折算壹日。事實及理由一、本件犯罪事實及證據，除犯罪事實應補充「被告覃子君前於民國95年間因飲酒後駕車案件，經本院以95年度壢交簡字第2279號判決判處拘役55日確定，於96年10月4日易科罰金執行完畢；又於97年間因飲酒後駕車案件，經本院以97年度壢交簡字第1261號判決判處有期徒刑3月確定，於97年12月22日執行完畢；另於97年間再因飲酒後駕車案件，經本院以97年度壢交簡字第1460號判決判處拘役30日確定，於98年1月21日執行完畢」外，其餘均引用檢察官聲請簡易判決處刑書之記載（如附件聲請書）。二、核被告覃子君所為，係犯刑法第185條之3之服用酒類不能安全駕駛動力交通工具而駕駛罪。被告有前揭犯罪科刑及執行之紀錄，有臺灣高等法院被告前案紀錄表在卷可按，於5年以內故意再犯本件有期徒刑之罪，為累犯，應依刑法第47條第1項規定加重其刑。爰審酌被告前有多次飲酒後駕車之犯罪紀錄，猶不知警惕，明知服用酒類後，於不能安全駕駛之情形下，竟仍貿然騎乘機車上路，危及道路交通安全，且乏尊重其他用路人生命、財產安全之觀念，所為非是，及被告被查獲後，經測得之呼氣所含酒精成分達每公升0.56毫克之犯罪情節，被告之智識程度、犯罪所生危害、素行及犯後態度等一切情狀，量處如主文所示之刑，並諭知易科罰金之折算標準，以示懲儆。三、據上論斷，應依刑事訴訟法第449條第1項前段、第3項、第454條第2項，刑法第185條之3、第47條第1項、第41條第1項前段，刑法施行法第1條之1第1項，逕以簡易判決處刑如主文。四、如不服本判決，應於判決送達後10日內，向本院提出上訴狀，上訴於本院合議庭。中華民國100年7月29日交通法庭法官劉為丕以上正本證明與原本無異。如不服本判決，應於判決送達後10日內向本院提出上訴狀（應附繕本）。書記官陳淑瓊中華民國100年8月5日附錄論罪科刑法條：中華民國刑法第185條之3服用毒品、麻醉藥品、酒類或其他相類之物，不能安全駕駛動力交通工具而駕駛者，處1年以下有期徒刑、拘役或科或併科15萬元以下罰金。",
  "characters": {
    "judges": [
      "劉為丕"
    ],
    "prosecutors": [

    ],
    "lawyers": [

    ],
    "clerks": [
      "陳淑瓊"
    ],
    "plaintiffs": [

    ],
    "defendants": [
      "覃子君"
    ],
    "prosecutor_office": [
      "臺灣桃園地方法院檢察署檢察官"
    ],
    "creditors": [

    ],
    "debtors": [

    ],
    "judicial_associate_officer": [

    ]
  },
  "adjudged_at": "2011-07-29",
  "created_at": "2016-02-14 02:07:28",
  "updated_at": "2016-02-14 02:07:28"
}