{
  "identify": "PCD-100-聲-2655-20110719-1",
  "court": {
    "name": "臺灣新北地方法院",
    "code": "PCD"
  },
  "division": {
    "name": "刑事",
    "code": "M"
  },
  "year": 100,
  "word": "聲",
  "number": "2655",
  "jcheck": "1",
  "reason": "聲請宣告沒收違禁物",
  "content": "臺灣板橋地方法院刑事裁定             100年度聲字第2655號\n聲  請  人  臺灣板橋地方法院檢察署檢察官\n被      告  呂理斌\n上列聲請人因聲請宣告沒收違禁物案件（100 年度聲沒字第466\n號），本院裁定如下：\n    主  文\n扣案之第二級毒品甲基安非他命壹包（驗餘淨重零點壹零捌捌公\n克），沒收銷燬之。\n其餘聲請駁回。\n    理  由\n一、聲請意旨略以：被告呂理斌違反毒品危害防制條例案件，業\n    經臺灣板橋地方法院檢察署檢察官以98年度偵字第29437 號\n    處分不起訴確定在案，扣案之甲基安非他命1 包（驗餘淨重\n    0.1088公克）及愷他命1 包（驗餘淨重1.7586公克），屬違\n    禁物，爰依刑法第38條第1 項第1 款、第2 項、第40條第2\n    項及毒品危害防制條例第18條第1 項前段規定，聲請法院裁\n    定宣告沒收銷燬之。\n二、按違禁物不問屬於犯人與否，均應宣告沒收，並得單獨宣告\n    沒收，刑法第38條第1 項第1 款、第2 項及第40條第2 項定\n    有明文；違禁物未經裁判沒收者，得由檢察官聲請法院以裁\n    定沒收之，司法院著有18年院字第67號、30年院字第2169號\n    解釋可資參照；又，甲基安非他命係第二級毒品，毒品危害\n    防制條例第2 條第2 項第2 款定有明文；查獲之毒品，不問\n    屬於犯人與否，均沒收銷燬之，毒品危害防制條例第18條第\n    1 項前段亦定有明文。\n三、經查：臺灣板橋地方法院檢察署98年度偵字第29437 號被告\n    呂理斌違反毒品危害防制條例一案，臺灣臺北看守所（現改\n    制為法務部矯正署臺北看守所）於98年9 月5 日18時，在辦\n    理新收人犯檢查身體之際，該所管理員在被告呂理斌之休閒\n    褲口袋內查獲白色透明結晶物質1 包，經送交通部民用航空\n    局航空醫務中心檢驗結果，確含甲基安非他命成分，實稱毛\n    重0. 3890 公克，淨重0.1090公克，取樣0.0002公克，餘重\n    0.108 8 公克，有該中心於98年9 月22日出具之航藥鑑字第\n    098482 9號毒品鑑定書1 紙存卷可稽（見臺灣板橋地方法院\n    檢察署98年度偵字第29437 號偵卷第5 頁）。故上開扣案物\n    自屬毒品危害防制條例第2 條第2 項第2 款所列管之第二級\n    毒品，為違禁物，是除檢驗用罄部分業已滅失毋庸宣告沒收\n    銷燬外，應依毒品危害防制條例第18條第1 項前段規定宣告\n    沒收銷燬之。又被告涉嫌持有上開甲基安非他命1 包之犯行\n    ，嗣經臺灣板橋地方法院檢察署檢察官以其持有甲基安非他\n    命之行為，為其施用甲基安非他命之高度行為所吸收，而被\n    告施用甲基安非他命之犯行業經本院以98年度簡字第9147號\n    判決處有期徒刑6 月確定在案，而於99年1 月27日以98年度\n    偵字第29437 號處分不起訴，已確定在案，亦有該不起訴處\n    分書1 份在卷可考。從而，聲請人聲請本院將上開甲基安非\n    他命1包宣告沒收銷燬之，核無不合，應予准許。\n四、至於臺灣臺北看守所於98年9 月5 日18時，同時在被告之休\n    閒褲口袋內查獲白色細結晶物質1 包，經交通部民用航空局\n    航空醫務中心檢驗結果，含愷他命（Ketamine) 成分，實稱\n    毛重0.0390公克，淨重1.7590公克，取樣0.0004公克鑑驗用\n    罄，驗餘淨重1.7586公克，亦有該中心出具之上開毒品鑑定\n    書1 紙附卷可憑。被告於警詢及偵查中固坦承有施用愷他命\n    之行為。惟被告持有及施用上開愷他命之行為，不構成犯罪\n    ，檢察官亦未就被告持有或施用上開愷他命之行為處分不起\n    訴，則扣案之上開愷他命尚非屬絕對禁止持有之違禁物。再\n    者，持有第三級毒品純質淨重未達20公克以上者，既無刑責\n    之規定，則所查獲之第三級毒品應如何處理，在實務上衍生\n    諸多疑問。毒品危害防制條例於92年6 月6 日修正時，即據\n    此修正該條例第18條第1 項前段為「查獲之第一、二級毒品\n    及專供製造或施用第一、二級毒品之器具，不問屬於犯人與\n    否，均沒收銷燬之；查獲之第三、四級毒品及製造或施用毒\n    品之器具，無正當理由而擅自持有者，均沒入銷燬之」，以\n    為處理之依據。參諸其修正理由，係鑑於持有及施用第三、\n    四級毒品，均未科以刑事罰，為免實務上對於該條例第18條\n    第1 項前段之適用產生疑義，始予明定，顯係有意區別查獲\n    之第一、二級毒品及第三、四級毒品之處分程序。從而，查\n    獲之第三、四級毒品，依上揭法條規定，應以行政處分之「\n    沒入銷燬」程序處理，始符法制，無庸聲請法院單獨宣告沒\n    收。是聲請人聲請就上開第三級毒品愷他命宣告沒收銷燬之\n    ，於法尚有未合，此部分聲請應予駁回。\n五、爰依刑事訴訟法第220 條，刑法第40條第2 項，毒品危害防\n    制條例第18條第1 項前段，裁定如主文。\n中    華    民    國    100     年    7     月    19  日\n                  刑事第三庭    法  官  樊季康\n以上正本證明與原本無異\n如不服本裁定應於送達後5日內向本院提出抗告狀\n                                書記官  陳秀慧\n中    華    民    國   100    年    7     月    19    日",
  "structure": {
    "main": "扣案之第二級毒品甲基安非他命壹包（驗餘淨重零點壹零捌捌公\n克），沒收銷燬之。\n其餘聲請駁回。",
    "reason": "一、聲請意旨略以：被告呂理斌違反毒品危害防制條例案件，業\n    經臺灣板橋地方法院檢察署檢察官以98年度偵字第29437 號\n    處分不起訴確定在案，扣案之甲基安非他命1 包（驗餘淨重\n    0.1088公克）及愷他命1 包（驗餘淨重1.7586公克），屬違\n    禁物，爰依刑法第38條第1 項第1 款、第2 項、第40條第2\n    項及毒品危害防制條例第18條第1 項前段規定，聲請法院裁\n    定宣告沒收銷燬之。\n二、按違禁物不問屬於犯人與否，均應宣告沒收，並得單獨宣告\n    沒收，刑法第38條第1 項第1 款、第2 項及第40條第2 項定\n    有明文；違禁物未經裁判沒收者，得由檢察官聲請法院以裁\n    定沒收之，司法院著有18年院字第67號、30年院字第2169號\n    解釋可資參照；又，甲基安非他命係第二級毒品，毒品危害\n    防制條例第2 條第2 項第2 款定有明文；查獲之毒品，不問\n    屬於犯人與否，均沒收銷燬之，毒品危害防制條例第18條第\n    1 項前段亦定有明文。\n三、經查：臺灣板橋地方法院檢察署98年度偵字第29437 號被告\n    呂理斌違反毒品危害防制條例一案，臺灣臺北看守所（現改\n    制為法務部矯正署臺北看守所）於98年9 月5 日18時，在辦\n    理新收人犯檢查身體之際，該所管理員在被告呂理斌之休閒\n    褲口袋內查獲白色透明結晶物質1 包，經送交通部民用航空\n    局航空醫務中心檢驗結果，確含甲基安非他命成分，實稱毛\n    重0. 3890 公克，淨重0.1090公克，取樣0.0002公克，餘重\n    0.108 8 公克，有該中心於98年9 月22日出具之航藥鑑字第\n    098482 9號毒品鑑定書1 紙存卷可稽（見臺灣板橋地方法院\n    檢察署98年度偵字第29437 號偵卷第5 頁）。故上開扣案物\n    自屬毒品危害防制條例第2 條第2 項第2 款所列管之第二級\n    毒品，為違禁物，是除檢驗用罄部分業已滅失毋庸宣告沒收\n    銷燬外，應依毒品危害防制條例第18條第1 項前段規定宣告\n    沒收銷燬之。又被告涉嫌持有上開甲基安非他命1 包之犯行\n    ，嗣經臺灣板橋地方法院檢察署檢察官以其持有甲基安非他\n    命之行為，為其施用甲基安非他命之高度行為所吸收，而被\n    告施用甲基安非他命之犯行業經本院以98年度簡字第9147號\n    判決處有期徒刑6 月確定在案，而於99年1 月27日以98年度\n    偵字第29437 號處分不起訴，已確定在案，亦有該不起訴處\n    分書1 份在卷可考。從而，聲請人聲請本院將上開甲基安非\n    他命1包宣告沒收銷燬之，核無不合，應予准許。\n四、至於臺灣臺北看守所於98年9 月5 日18時，同時在被告之休\n    閒褲口袋內查獲白色細結晶物質1 包，經交通部民用航空局\n    航空醫務中心檢驗結果，含愷他命（Ketamine) 成分，實稱\n    毛重0.0390公克，淨重1.7590公克，取樣0.0004公克鑑驗用\n    罄，驗餘淨重1.7586公克，亦有該中心出具之上開毒品鑑定\n    書1 紙附卷可憑。被告於警詢及偵查中固坦承有施用愷他命\n    之行為。惟被告持有及施用上開愷他命之行為，不構成犯罪\n    ，檢察官亦未就被告持有或施用上開愷他命之行為處分不起\n    訴，則扣案之上開愷他命尚非屬絕對禁止持有之違禁物。再\n    者，持有第三級毒品純質淨重未達20公克以上者，既無刑責\n    之規定，則所查獲之第三級毒品應如何處理，在實務上衍生\n    諸多疑問。毒品危害防制條例於92年6 月6 日修正時，即據\n    此修正該條例第18條第1 項前段為「查獲之第一、二級毒品\n    及專供製造或施用第一、二級毒品之器具，不問屬於犯人與\n    否，均沒收銷燬之；查獲之第三、四級毒品及製造或施用毒\n    品之器具，無正當理由而擅自持有者，均沒入銷燬之」，以\n    為處理之依據。參諸其修正理由，係鑑於持有及施用第三、\n    四級毒品，均未科以刑事罰，為免實務上對於該條例第18條\n    第1 項前段之適用產生疑義，始予明定，顯係有意區別查獲\n    之第一、二級毒品及第三、四級毒品之處分程序。從而，查\n    獲之第三、四級毒品，依上揭法條規定，應以行政處分之「\n    沒入銷燬」程序處理，始符法制，無庸聲請法院單獨宣告沒\n    收。是聲請人聲請就上開第三級毒品愷他命宣告沒收銷燬之\n    ，於法尚有未合，此部分聲請應予駁回。\n五、爰依刑事訴訟法第220 條，刑法第40條第2 項，毒品危害防\n    制條例第18條第1 項前段，裁定如主文。"
  },
  "search": "臺灣板橋地方法院刑事裁定100年度聲字第2655號聲請人臺灣板橋地方法院檢察署檢察官被告呂理斌上列聲請人因聲請宣告沒收違禁物案件（100年度聲沒字第466號），本院裁定如下：主文扣案之第二級毒品甲基安非他命壹包（驗餘淨重零點壹零捌捌公克），沒收銷燬之。其餘聲請駁回。理由一、聲請意旨略以：被告呂理斌違反毒品危害防制條例案件，業經臺灣板橋地方法院檢察署檢察官以98年度偵字第29437號處分不起訴確定在案，扣案之甲基安非他命1包（驗餘淨重0.1088公克）及愷他命1包（驗餘淨重1.7586公克），屬違禁物，爰依刑法第38條第1項第1款、第2項、第40條第2項及毒品危害防制條例第18條第1項前段規定，聲請法院裁定宣告沒收銷燬之。二、按違禁物不問屬於犯人與否，均應宣告沒收，並得單獨宣告沒收，刑法第38條第1項第1款、第2項及第40條第2項定有明文；違禁物未經裁判沒收者，得由檢察官聲請法院以裁定沒收之，司法院著有18年院字第67號、30年院字第2169號解釋可資參照；又，甲基安非他命係第二級毒品，毒品危害防制條例第2條第2項第2款定有明文；查獲之毒品，不問屬於犯人與否，均沒收銷燬之，毒品危害防制條例第18條第1項前段亦定有明文。三、經查：臺灣板橋地方法院檢察署98年度偵字第29437號被告呂理斌違反毒品危害防制條例一案，臺灣臺北看守所（現改制為法務部矯正署臺北看守所）於98年9月5日18時，在辦理新收人犯檢查身體之際，該所管理員在被告呂理斌之休閒褲口袋內查獲白色透明結晶物質1包，經送交通部民用航空局航空醫務中心檢驗結果，確含甲基安非他命成分，實稱毛重0.3890公克，淨重0.1090公克，取樣0.0002公克，餘重0.1088公克，有該中心於98年9月22日出具之航藥鑑字第0984829號毒品鑑定書1紙存卷可稽（見臺灣板橋地方法院檢察署98年度偵字第29437號偵卷第5頁）。故上開扣案物自屬毒品危害防制條例第2條第2項第2款所列管之第二級毒品，為違禁物，是除檢驗用罄部分業已滅失毋庸宣告沒收銷燬外，應依毒品危害防制條例第18條第1項前段規定宣告沒收銷燬之。又被告涉嫌持有上開甲基安非他命1包之犯行，嗣經臺灣板橋地方法院檢察署檢察官以其持有甲基安非他命之行為，為其施用甲基安非他命之高度行為所吸收，而被告施用甲基安非他命之犯行業經本院以98年度簡字第9147號判決處有期徒刑6月確定在案，而於99年1月27日以98年度偵字第29437號處分不起訴，已確定在案，亦有該不起訴處分書1份在卷可考。從而，聲請人聲請本院將上開甲基安非他命1包宣告沒收銷燬之，核無不合，應予准許。四、至於臺灣臺北看守所於98年9月5日18時，同時在被告之休閒褲口袋內查獲白色細結晶物質1包，經交通部民用航空局航空醫務中心檢驗結果，含愷他命（Ketamine)成分，實稱毛重0.0390公克，淨重1.7590公克，取樣0.0004公克鑑驗用罄，驗餘淨重1.7586公克，亦有該中心出具之上開毒品鑑定書1紙附卷可憑。被告於警詢及偵查中固坦承有施用愷他命之行為。惟被告持有及施用上開愷他命之行為，不構成犯罪，檢察官亦未就被告持有或施用上開愷他命之行為處分不起訴，則扣案之上開愷他命尚非屬絕對禁止持有之違禁物。再者，持有第三級毒品純質淨重未達20公克以上者，既無刑責之規定，則所查獲之第三級毒品應如何處理，在實務上衍生諸多疑問。毒品危害防制條例於92年6月6日修正時，即據此修正該條例第18條第1項前段為「查獲之第一、二級毒品及專供製造或施用第一、二級毒品之器具，不問屬於犯人與否，均沒收銷燬之；查獲之第三、四級毒品及製造或施用毒品之器具，無正當理由而擅自持有者，均沒入銷燬之」，以為處理之依據。參諸其修正理由，係鑑於持有及施用第三、四級毒品，均未科以刑事罰，為免實務上對於該條例第18條第1項前段之適用產生疑義，始予明定，顯係有意區別查獲之第一、二級毒品及第三、四級毒品之處分程序。從而，查獲之第三、四級毒品，依上揭法條規定，應以行政處分之「沒入銷燬」程序處理，始符法制，無庸聲請法院單獨宣告沒收。是聲請人聲請就上開第三級毒品愷他命宣告沒收銷燬之，於法尚有未合，此部分聲請應予駁回。五、爰依刑事訴訟法第220條，刑法第40條第2項，毒品危害防制條例第18條第1項前段，裁定如主文。中華民國100年7月19日刑事第三庭法官樊季康以上正本證明與原本無異如不服本裁定應於送達後5日內向本院提出抗告狀書記官陳秀慧中華民國100年7月19日",
  "characters": {
    "judges": [
      "樊季康"
    ],
    "prosecutors": [

    ],
    "lawyers": [

    ],
    "clerks": [
      "陳秀慧"
    ],
    "plaintiffs": [

    ],
    "defendants": [
      "呂理斌"
    ],
    "prosecutor_office": [
      "臺灣板橋地方法院檢察署檢察官"
    ],
    "creditors": [

    ],
    "debtors": [

    ],
    "judicial_associate_officer": [

    ]
  },
  "adjudged_at": "2011-07-19",
  "created_at": "2016-02-14 00:05:16",
  "updated_at": "2016-02-14 00:05:16"
}