{
  "identify": "KSD-94-訴-138-20050519-1",
  "court": {
    "name": "臺灣高雄地方法院",
    "code": "KSD"
  },
  "division": {
    "name": "民事",
    "code": "V"
  },
  "year": 94,
  "word": "訴",
  "number": "138",
  "jcheck": "1",
  "reason": "清償借款",
  "content": "臺灣高雄地方法院民事判決      94年度訴字第138號\n原      告  保證責任高雄市第二信用合作社\n法定代理人  乙○○\n訴訟代理人  甲○○\n            丙○○\n被      告  丁○○\n            戊○○○\n上列當事人間請求清償借款事件，本院於民國94年5 月12言詞辯\n論終結，判決如下：\n    主    文\n被告應連帶給付原告新台幣壹佰陸拾萬伍仟貳佰伍拾陸元，及自\n民國九十二年三月二十七日起至清償日止按年息百分之八點八計\n算之利息，暨自前開日期起至清償日止，逾期在六個月以內者，\n按前開利率之一成，逾期超過六個月者，按前開利率之二成計付\n之違約金。\n訴訟費用由被告連帶負擔。\n本判決於原告以新台幣伍拾參萬陸仟元或同額之中央政府建設公\n債供擔保後得假執行。\n    事實及理由\n一、本件被告經合法通知，均未於言詞辯論期日到場，核無民事\n    訴訟法第386 條各款所列情形，爰依原告聲請，由其一造辯\n    論而為判決。\n二、原告主張：被告丁○○於民國89年3 月24日邀同被告戊○○\n    ○為連帶保證人，向原告借款新台幣（下同）350 萬元，約\n    定於90年3 月24日清償，利息按年息9.24% 計算，調整基本\n    放款利率時隨同調整。遲延清償時，除仍按前開利率計息外\n    ，逾期在6 個月以內者，按前開利率之1 成，逾期超過6 個\n    月者，按前開利率之2 成計付違約金。惟被告丁○○屆期未\n    清償，經原告聲請拍賣抵押物受償2,799,031 元後，尚有如\n    主文第1 項所示之金額未受償，爰依消費借貸及連帶保證之\n    法律關係起訴等語，並聲明：(一)如主文第1 項所示。(二)願供\n    擔保准宣告假執行。\n三、被告均未於言詞辯論期日到場，亦未提出準備書狀作任何聲\n    明或陳述。\n四、按借用人應於約定期限內，返還與借用物種類、品質、數量\n    相同之物；而遲延之債務，以支付金錢為標的者，債權人得\n    請求依法定利率計算之遲延利息，但約定利率較高者，仍從\n    其約定利率，民法第478 條前段、第233 條第1 項分別定有\n    明文。又稱保證者，謂當事人約定，一方於他方之債務人不\n    履行債務時，由其代負履行責任之契約。保證債務，除契約\n    另有訂定外，包含主債務之利息、違約金、損害賠償及其他\n    從屬於主債務之負擔，民法第739 條、第740 條亦分別定有\n    明文。又保證債務之所謂連帶，係指保證人與主債務人負同\n    一債務，對於債權人各負全部給付之責任而言（最高法院45\n    年臺上字第1426號判例意旨參照）。查原告主張之事實，已\n    據其提出借據、分配表、借款申請書各1 份、授信申請書 2\n    份、授信約定書6 份（見本院卷第8 至12頁、第24至33頁）\n    為證。被告經合法通知，未到庭爭執，亦未提出書狀作任何\n    聲明或陳述，本院依調查證據之結果，認原告之主張堪信為\n    真實。從而，原告依據消費借貸及連帶保證之法律關係，請\n    求被告連帶給付如主文第1 項所示之金額，即屬正當，應予\n    准許。\n五、原告陳明願供擔保，聲請宣告假執行，核無不合，爰酌定相\n    當擔保金額准許之。\n六、結論：原告之訴為有理由，依民事訴訟法第385 條第1 項前\n    段、第85條第2項，第390條第2項，判決如主文。\n中    華    民    國   94   年    5    月      19     日\n                  民事第五庭\n                      審判長法  官  陳嘉惠\n                            法  官  郭慧珊\n                            法  官  方錦源\n正本係照原本作成。\n如不服本判決，應於送達後20日內，向本院提出上訴狀。\n中    華    民    國   94   年    5    月      19     日\n                            書記官  邱靜銘\n",
  "structure": {
    "main": "被告應連帶給付原告新台幣壹佰陸拾萬伍仟貳佰伍拾陸元，及自\n民國九十二年三月二十七日起至清償日止按年息百分之八點八計\n算之利息，暨自前開日期起至清償日止，逾期在六個月以內者，\n按前開利率之一成，逾期超過六個月者，按前開利率之二成計付\n之違約金。\n訴訟費用由被告連帶負擔。\n本判決於原告以新台幣伍拾參萬陸仟元或同額之中央政府建設公\n債供擔保後得假執行。",
    "fact": "一、本件被告經合法通知，均未於言詞辯論期日到場，核無民事\n    訴訟法第386 條各款所列情形，爰依原告聲請，由其一造辯\n    論而為判決。\n二、原告主張：被告丁○○於民國89年3 月24日邀同被告戊○○\n    ○為連帶保證人，向原告借款新台幣（下同）350 萬元，約\n    定於90年3 月24日清償，利息按年息9.24% 計算，調整基本\n    放款利率時隨同調整。遲延清償時，除仍按前開利率計息外\n    ，逾期在6 個月以內者，按前開利率之1 成，逾期超過6 個\n    月者，按前開利率之2 成計付違約金。惟被告丁○○屆期未\n    清償，經原告聲請拍賣抵押物受償2,799,031 元後，尚有如\n    主文第1 項所示之金額未受償，爰依消費借貸及連帶保證之\n    法律關係起訴等語，並聲明：(一)如主文第1 項所示。(二)願供\n    擔保准宣告假執行。\n三、被告均未於言詞辯論期日到場，亦未提出準備書狀作任何聲\n    明或陳述。\n四、按借用人應於約定期限內，返還與借用物種類、品質、數量\n    相同之物；而遲延之債務，以支付金錢為標的者，債權人得\n    請求依法定利率計算之遲延利息，但約定利率較高者，仍從\n    其約定利率，民法第478 條前段、第233 條第1 項分別定有\n    明文。又稱保證者，謂當事人約定，一方於他方之債務人不\n    履行債務時，由其代負履行責任之契約。保證債務，除契約\n    另有訂定外，包含主債務之利息、違約金、損害賠償及其他\n    從屬於主債務之負擔，民法第739 條、第740 條亦分別定有\n    明文。又保證債務之所謂連帶，係指保證人與主債務人負同\n    一債務，對於債權人各負全部給付之責任而言（最高法院45\n    年臺上字第1426號判例意旨參照）。查原告主張之事實，已\n    據其提出借據、分配表、借款申請書各1 份、授信申請書 2\n    份、授信約定書6 份（見本院卷第8 至12頁、第24至33頁）\n    為證。被告經合法通知，未到庭爭執，亦未提出書狀作任何\n    聲明或陳述，本院依調查證據之結果，認原告之主張堪信為\n    真實。從而，原告依據消費借貸及連帶保證之法律關係，請\n    求被告連帶給付如主文第1 項所示之金額，即屬正當，應予\n    准許。\n五、原告陳明願供擔保，聲請宣告假執行，核無不合，爰酌定相\n    當擔保金額准許之。\n六、結論：原告之訴為有理由，依民事訴訟法第385 條第1 項前\n    段、第85條第2項，第390條第2項，判決如主文。",
    "reason": "一、本件被告經合法通知，均未於言詞辯論期日到場，核無民事\n    訴訟法第386 條各款所列情形，爰依原告聲請，由其一造辯\n    論而為判決。\n二、原告主張：被告丁○○於民國89年3 月24日邀同被告戊○○\n    ○為連帶保證人，向原告借款新台幣（下同）350 萬元，約\n    定於90年3 月24日清償，利息按年息9.24% 計算，調整基本\n    放款利率時隨同調整。遲延清償時，除仍按前開利率計息外\n    ，逾期在6 個月以內者，按前開利率之1 成，逾期超過6 個\n    月者，按前開利率之2 成計付違約金。惟被告丁○○屆期未\n    清償，經原告聲請拍賣抵押物受償2,799,031 元後，尚有如\n    主文第1 項所示之金額未受償，爰依消費借貸及連帶保證之\n    法律關係起訴等語，並聲明：(一)如主文第1 項所示。(二)願供\n    擔保准宣告假執行。\n三、被告均未於言詞辯論期日到場，亦未提出準備書狀作任何聲\n    明或陳述。\n四、按借用人應於約定期限內，返還與借用物種類、品質、數量\n    相同之物；而遲延之債務，以支付金錢為標的者，債權人得\n    請求依法定利率計算之遲延利息，但約定利率較高者，仍從\n    其約定利率，民法第478 條前段、第233 條第1 項分別定有\n    明文。又稱保證者，謂當事人約定，一方於他方之債務人不\n    履行債務時，由其代負履行責任之契約。保證債務，除契約\n    另有訂定外，包含主債務之利息、違約金、損害賠償及其他\n    從屬於主債務之負擔，民法第739 條、第740 條亦分別定有\n    明文。又保證債務之所謂連帶，係指保證人與主債務人負同\n    一債務，對於債權人各負全部給付之責任而言（最高法院45\n    年臺上字第1426號判例意旨參照）。查原告主張之事實，已\n    據其提出借據、分配表、借款申請書各1 份、授信申請書 2\n    份、授信約定書6 份（見本院卷第8 至12頁、第24至33頁）\n    為證。被告經合法通知，未到庭爭執，亦未提出書狀作任何\n    聲明或陳述，本院依調查證據之結果，認原告之主張堪信為\n    真實。從而，原告依據消費借貸及連帶保證之法律關係，請\n    求被告連帶給付如主文第1 項所示之金額，即屬正當，應予\n    准許。\n五、原告陳明願供擔保，聲請宣告假執行，核無不合，爰酌定相\n    當擔保金額准許之。\n六、結論：原告之訴為有理由，依民事訴訟法第385 條第1 項前\n    段、第85條第2項，第390條第2項，判決如主文。"
  },
  "search": "臺灣高雄地方法院民事判決94年度訴字第138號原告保證責任高雄市第二信用合作社法定代理人乙○○訴訟代理人甲○○丙○○被告丁○○戊○○○上列當事人間請求清償借款事件，本院於民國94年5月12言詞辯論終結，判決如下：主文被告應連帶給付原告新台幣壹佰陸拾萬伍仟貳佰伍拾陸元，及自民國九十二年三月二十七日起至清償日止按年息百分之八點八計算之利息，暨自前開日期起至清償日止，逾期在六個月以內者，按前開利率之一成，逾期超過六個月者，按前開利率之二成計付之違約金。訴訟費用由被告連帶負擔。本判決於原告以新台幣伍拾參萬陸仟元或同額之中央政府建設公債供擔保後得假執行。事實及理由一、本件被告經合法通知，均未於言詞辯論期日到場，核無民事訴訟法第386條各款所列情形，爰依原告聲請，由其一造辯論而為判決。二、原告主張：被告丁○○於民國89年3月24日邀同被告戊○○○為連帶保證人，向原告借款新台幣（下同）350萬元，約定於90年3月24日清償，利息按年息9.24%計算，調整基本放款利率時隨同調整。遲延清償時，除仍按前開利率計息外，逾期在6個月以內者，按前開利率之1成，逾期超過6個月者，按前開利率之2成計付違約金。惟被告丁○○屆期未清償，經原告聲請拍賣抵押物受償2,799,031元後，尚有如主文第1項所示之金額未受償，爰依消費借貸及連帶保證之法律關係起訴等語，並聲明：(一)如主文第1項所示。(二)願供擔保准宣告假執行。三、被告均未於言詞辯論期日到場，亦未提出準備書狀作任何聲明或陳述。四、按借用人應於約定期限內，返還與借用物種類、品質、數量相同之物；而遲延之債務，以支付金錢為標的者，債權人得請求依法定利率計算之遲延利息，但約定利率較高者，仍從其約定利率，民法第478條前段、第233條第1項分別定有明文。又稱保證者，謂當事人約定，一方於他方之債務人不履行債務時，由其代負履行責任之契約。保證債務，除契約另有訂定外，包含主債務之利息、違約金、損害賠償及其他從屬於主債務之負擔，民法第739條、第740條亦分別定有明文。又保證債務之所謂連帶，係指保證人與主債務人負同一債務，對於債權人各負全部給付之責任而言（最高法院45年臺上字第1426號判例意旨參照）。查原告主張之事實，已據其提出借據、分配表、借款申請書各1份、授信申請書2份、授信約定書6份（見本院卷第8至12頁、第24至33頁）為證。被告經合法通知，未到庭爭執，亦未提出書狀作任何聲明或陳述，本院依調查證據之結果，認原告之主張堪信為真實。從而，原告依據消費借貸及連帶保證之法律關係，請求被告連帶給付如主文第1項所示之金額，即屬正當，應予准許。五、原告陳明願供擔保，聲請宣告假執行，核無不合，爰酌定相當擔保金額准許之。六、結論：原告之訴為有理由，依民事訴訟法第385條第1項前段、第85條第2項，第390條第2項，判決如主文。中華民國94年5月19日民事第五庭審判長法官陳嘉惠法官郭慧珊法官方錦源正本係照原本作成。如不服本判決，應於送達後20日內，向本院提出上訴狀。中華民國94年5月19日書記官邱靜銘",
  "characters": {
    "judges": [
      "陳嘉惠",
      "郭慧珊",
      "方錦源"
    ],
    "prosecutors": [

    ],
    "lawyers": [

    ],
    "clerks": [
      "邱靜銘"
    ],
    "plaintiffs": [
      "保證責任高雄市第二信用合作社"
    ],
    "defendants": [
      "丁○○"
    ],
    "prosecutor_office": [

    ],
    "creditors": [

    ],
    "debtors": [

    ],
    "judicial_associate_officer": [

    ]
  },
  "adjudged_at": "2005-05-19",
  "created_at": "2016-02-06 16:21:47",
  "updated_at": "2016-02-06 16:21:47"
}