{
  "identify": "TCD-94-中簡-1215-20050520-1",
  "court": {
    "name": "臺灣臺中地方法院",
    "code": "TCD"
  },
  "division": {
    "name": "刑事",
    "code": "M"
  },
  "year": 94,
  "word": "中簡",
  "number": "1215",
  "jcheck": "1",
  "reason": "侵占",
  "content": "臺灣臺中地方法院刑事簡易判決                  九十四年度中簡字第一二一五號\n    聲  請  人  臺灣臺中地方法院檢察署檢察官\n    被      告  甲○○\n右列被告因侵占案件，經檢察官聲請以簡易判決處刑（九十四年度撤緩偵字第一二三\n號），本院判決如左：\n    主          文\n甲○○意圖為自己不法之所有，而侵占離本人所持有之物，處罰金仟元，如易服勞\n役，以佰元折算壹日。\n    犯罪事實及理由\n一、本案犯罪事實、證據及應適用之法條，除附件之檢察官聲請簡易判決處刑書犯罪\n    事實欄第一行關於「九十二年四月七日」記載之後，應補充「上午六時許」外，\n    其餘均引用如附件所示檢察官聲請簡易判決處刑書之記載。\n二、依刑事訴訟法第四百四十九條第一項前段、第四百五十四條第二項，刑法第三百\n    三十七條、第四十二條第二項，罰金罰鍰提高標準條例第一條前段、第二條，逕\n    以簡易判決處如主文所示之刑。\n如不服本簡易判決，得於簡易判決送達之日起十日內，以書狀敘述理由，向本庭提出\n上訴（須附繕本）。\n中      華      民      國      九十四      年    五    月    二十      日\n                                  臺灣臺中地方法院臺中簡易庭\n                                          法  官  楊真明\n右正本證明與原本無異。\n中      華      民      國      九十四      年    五    月    二十      日\n                                          書記官\n附錄本案論罪科刑法條\n中華民國刑法第三百三十七條：\n  意圖為自己或第三人不法之所有，而侵占遺失物、漂流物或其他離本人所持有之物\n  者，處五百元以下罰金。\n",
  "structure": {
    "main": "甲○○意圖為自己不法之所有，而侵占離本人所持有之物，處罰金仟元，如易服勞\n役，以佰元折算壹日。",
    "fact": "一、本案犯罪事實、證據及應適用之法條，除附件之檢察官聲請簡易判決處刑書犯罪\n    事實欄第一行關於「九十二年四月七日」記載之後，應補充「上午六時許」外，\n    其餘均引用如附件所示檢察官聲請簡易判決處刑書之記載。\n二、依刑事訴訟法第四百四十九條第一項前段、第四百五十四條第二項，刑法第三百\n    三十七條、第四十二條第二項，罰金罰鍰提高標準條例第一條前段、第二條，逕\n    以簡易判決處如主文所示之刑。\n如不服本簡易判決，得於簡易判決送達之日起十日內，以書狀敘述理由，向本庭提出\n上訴（須附繕本）。",
    "reason": "一、本案犯罪事實、證據及應適用之法條，除附件之檢察官聲請簡易判決處刑書犯罪\n    事實欄第一行關於「九十二年四月七日」記載之後，應補充「上午六時許」外，\n    其餘均引用如附件所示檢察官聲請簡易判決處刑書之記載。\n二、依刑事訴訟法第四百四十九條第一項前段、第四百五十四條第二項，刑法第三百\n    三十七條、第四十二條第二項，罰金罰鍰提高標準條例第一條前段、第二條，逕\n    以簡易判決處如主文所示之刑。\n如不服本簡易判決，得於簡易判決送達之日起十日內，以書狀敘述理由，向本庭提出\n上訴（須附繕本）。"
  },
  "search": "臺灣臺中地方法院刑事簡易判決九十四年度中簡字第一二一五號聲請人臺灣臺中地方法院檢察署檢察官被告甲○○右列被告因侵占案件，經檢察官聲請以簡易判決處刑（九十四年度撤緩偵字第一二三號），本院判決如左：主文甲○○意圖為自己不法之所有，而侵占離本人所持有之物，處罰金仟元，如易服勞役，以佰元折算壹日。犯罪事實及理由一、本案犯罪事實、證據及應適用之法條，除附件之檢察官聲請簡易判決處刑書犯罪事實欄第一行關於「九十二年四月七日」記載之後，應補充「上午六時許」外，其餘均引用如附件所示檢察官聲請簡易判決處刑書之記載。二、依刑事訴訟法第四百四十九條第一項前段、第四百五十四條第二項，刑法第三百三十七條、第四十二條第二項，罰金罰鍰提高標準條例第一條前段、第二條，逕以簡易判決處如主文所示之刑。如不服本簡易判決，得於簡易判決送達之日起十日內，以書狀敘述理由，向本庭提出上訴（須附繕本）。中華民國九十四年五月二十日臺灣臺中地方法院臺中簡易庭法官楊真明右正本證明與原本無異。中華民國九十四年五月二十日書記官附錄本案論罪科刑法條中華民國刑法第三百三十七條：意圖為自己或第三人不法之所有，而侵占遺失物、漂流物或其他離本人所持有之物者，處五百元以下罰金。",
  "characters": {
    "judges": [
      "楊真明"
    ],
    "prosecutors": [

    ],
    "lawyers": [

    ],
    "clerks": [
      "附錄本案論罪科刑法條"
    ],
    "plaintiffs": [

    ],
    "defendants": [
      "甲○○",
      "右列被告因侵占案件，經檢察官聲請以簡易判決處刑（九十四年度撤緩偵字第一二三",
      "號），本院判決如左："
    ],
    "prosecutor_office": [
      "臺灣臺中地方法院檢察署檢察官"
    ],
    "creditors": [

    ],
    "debtors": [

    ],
    "judicial_associate_officer": [

    ]
  },
  "adjudged_at": "2005-05-20",
  "created_at": "2016-02-06 16:22:00",
  "updated_at": "2016-02-06 16:22:00"
}