{
  "identify": "TPB-90-訴-4545-20020717-1",
  "court": {
    "name": "臺北高等行政法院",
    "code": "TPB"
  },
  "division": {
    "name": "行政",
    "code": "A"
  },
  "year": 90,
  "word": "訴",
  "number": "4545",
  "jcheck": "1",
  "reason": "商標異議",
  "content": "臺北高等行政法院判決                              九十年度訴字第四五四五號\n                              .\n    原      告  丞燕國際股份有限公司\n    代  表  人  甲○○董事長.\n    訴訟代理人  劉緒倫律師\n    複  代理人  徐東昇律師\n    被      告  經濟部智慧財產局\n    代  表  人  陳明邦（局長）\n    訴訟代理人  丙○○\n    參  加  人  金燕企業有限公司\n    代  表  人  乙○○\n右當事人間因商標異議事件，原告不服經濟部中華民國九十年四月二十六日經（九○\n）訴字第○九○○六三○七九五○號訴願決定，提起行政訴訟，本院判決如左：\n    主  文\n原告之訴駁回。\n訴訟費用由原告負擔。\n    事  實\n一、事實概要：原告於民國八十七年十二月二日以「E.EXCEL INTERNATIONAL及E設計\n    圖」商標作為註冊第七一四八五九號「E.EXCEL」商標之聯合商標，指定使用於\n    當時商標法施行細則第四十九條所定商品及服務分類表第五類之醫療補助用營養\n    製劑、維他命等商品，向被告（原經濟部中央標準局，八十八年一月二十六日改\n    制為經濟部智慧財產局）申請註冊，經被告審查，准列為審定第八七八一九四號\n    聯合商標。嗣參加人金燕企業有限公司以該審定聯合商標有違商標法第三十七條\n    第七、十二款之規定，對之提起異議。經被告審查，以八十九年十二月二十九日\n    中台異字第八八七六九三號商標異議審定書為異議成立之處分。原告不服，提起\n    訴願，遭決定駁回，遂提起行政訴訟。本院於九十一年五月十四日開庭行準備程\n    序，經原、被告陳述意見後，認有使參加人獨立參加訴訟之必要，爰裁定命其參\n    加本件被告之訴訟。\n二、兩造聲明：\n    (一)原告聲明：請求撤銷原處分及訴願決定。訴訟費用由被告負擔。\n    (二)被告聲明：如主文所示。\n三、兩造之爭點：原告所申請註冊審定第八七八一九四號「E.EXCEL INTERNATIONAL\n    及E設計圖」聯合商標（如附圖一），與參加人所申請註冊第四六七五一五號之\n    「燕子圖」商標（如附圖二），是否構成近似？\n    (一)原告主張：\n      (1)按商標圖樣相同或近似於他人同一商品或類似商品之註冊商標者，不得申請\n        註冊，固為商標法第三十七條第一項第十二款之規定，惟商標圖樣是否構成\n        近似，應以具有普通知識經驗之購買人，於異時異地購買時，施以普通所用\n        之注意，有無混同誤認之虞判斷之。本案被告以系爭審定第八七八一九四號\n        「E.EXCEL INTERNATIONAL及E設計圖」商標圖樣係由外文「E.EXCEL\n        INTERNATIONAL」及燕子設計圖所聯合組成，與參加人據以異議之註冊第四\n        六七五一五號「燕子圖」商標圖樣相較，二者均以燕子設計圖為其商標圖樣\n        之主要部分，不論設色及構圖意匠均相彷彿，異時異地隔離觀察，難謂無使\n        商品購買者產生混淆誤認之虞，應屬近似之商標；惟被告所言構成近似之論\n        據，殊屬違法不當。\n      (2)「燕子」為自然生物，據以異議商標申請註冊前後，皆有他人以不同態樣之\n        燕子圖申請註冊在案：\n        燕子為自然界既有生物，非參加人所創造，無獨占專用之理。\n        據以異議商標申請註冊前，已有註冊第八八四九一號、第一一六二二一號\n          等多件商標註冊在先，都以燕子圖作為設計主體，僅在數量及飛翔方向上\n          略有不同。\n        據以異議商標申請註冊後，亦有多件以燕子圖作為設計主體之商標獲准註\n          冊在案。\n        他類商品中，亦有多件以燕子圖作為設計主體之商標獲准在案。\n        是以，消費者並不會將「燕子圖」與參加人產生唯一之聯想。\n      (3)系爭商標附加有顯而易見能與據以異議商標相區異之特徵，二商標無混同之\n        慮：原告系爭商標是一存留字母原形與圓形圖綜合設計之Ｅ字圖標誌，清晰\n        明顯之E.EXCEL INTERNATIONAL文字環繞於右，具備顯而易見之特徵，消費\n        者一眼見之即知產品出處與來源，能與據爭商標相區異，無混同誤認之慮。\n      (4)系爭商標與與據以異議商標，二商標本體在構圖、意義、意匠及外觀上亦有\n        明顯差異，無混同誤認之慮：\n        原告系爭商標：\n          Ａ、構圖：在半圓弧線及英文E.EXCEL INTERNATIONAL組合成之外環中置\n                    放「E」字設計圖。\n          Ｂ、意義：商標名稱E.EXCEL取自英文Extra Excellent有超越卓越之意。\n          Ｃ、意匠：基於公司及商標名稱皆為E.EXCEL，故以「E」字為商標主體，\n                    外圍環以弧線及英文字組合而成之圓形，藉以表達原告商品行\n                    銷全球之企圖心。\n          Ｄ、外觀：「E」設計圖及E.EXCEL INTERNATIONAL。\n        據以異議商標：\n          Ａ、構圖：線條輕盈之具象燕子圖。\n          Ｂ、意義：圖形。\n          Ｃ、意匠：燕子。\n          Ｄ、外觀：燕子圖。\n        由以上比較，明顯可見二商標予人之整體印象及意義差異顯然，無令人發生\n        混淆誤認之虞，此可參被告前身中央標準局編印之「商標手冊」第四十二頁\n        第十三項所載「商標稍有不同，通常認為構成近似，但該差異部分影響商標\n        之整體印象或具其他不同意義，而無混淆誤認之虞者，不為近似」，及前行\n        政法院七十年度判字第三三七號及八十一年度判字第二○二二號判決。\n      (5)參加人據以異議商標變換新設計圖之意圖不明，但其設計手法顯然襲自原告\n        系爭商標設計態樣：\n        原告系爭商標自七十九年創立以來即延用至今。然參加人於八十八年對已\n          併存註冊八年之久，原告註冊第四九七一一二號商標提起評定，其意圖為\n          何未明？\n        末查，從近期商標公報公告資料，得知參加人將其據以異議商標之外圍亦\n          飾以呈圓弧設計之英文字樣，核其設計手法顯然襲用系爭商標態樣，其意\n          圖為何未明？\n      (6)綜上所陳，原告商標與據以異議商標應非屬近似商標，無令一般商品購買人\n        產生混淆誤認之虞。\n    (二)被告主張：\n      (1)按商標異議案件，依商標法施行細則第四十條第一款規定，應適用異議審定\n        時之規定，合先敘明。\n      (2)次按商標圖樣相同或近似於他人同一商品或類似商品之註冊商標者，不得申\n        請註冊，為本件商標異議審定時商標法第三十七條第十二款所明定。而商標\n        圖樣之近似，以具有普通知識經驗之購買人，於購買時施以普通所用之注意\n        ，有無混同誤認之虞判斷之，復為商標法施行細則第十五條第一項所明定。\n        又商標在外觀、觀念或讀音方面有一近似者，即為近似之商標。查本件系爭\n        審定第八七八一九四號「E.EXCEL INTERNATIONAL及E設計圖」商標圖樣係由\n        外文「E.EXCEL INTERNATIONAL」及燕子設計圖所聯合組成，與參加人據以\n        異議之註冊第四六七五一五號「燕子圖」商標圖樣相較，二者均以燕子設計\n        圖為其商標圖樣之主要部分，不論設色及構圖意匠均相彷彿，二造商標於異\n        時異地隔離觀察，難謂無使商品購買者產生混同誤認之虞，應屬構成近似之\n        商標；又前者指定使用於醫療補助用營養製劑、維他命等商品，與後者指定\n        使用於中西藥品，復屬同一或類似商品，揆諸前揭說明，自有首揭法條規定\n        之適用。\n    (三)參加人主張：\n      (1)系爭商標係由一外文形成右半外環連結外環內置一呈外文Ｅ狀之左向飛燕圖\n        形所組成，然其外環文字細小，使用於化妝品瓶罐等包裝容器上無法引起注\n        意，故主要部在於中央之燕子圖。二造燕子圖形之比較，特徵相同─抽象、\n        平面、向左展飛、上下翅膀等。系爭商圖形只是略作粗、細、圓、方的調整\n        ，致總體構設匠技態樣均相同，使人立即產起聯想引起混淆，且使用於相同\n        商品，當屬近似無疑。\n      (2)參加人公司於民國五十八年成立，為國內化妝品先進，除自始即與日本\n        化研工業株式技術合作外，並使用相同的燕子商標，該日商亦於中國大\n        陸註冊使用同樣商標，並於其他多國註冊使用同一商標。據以異議之「燕子\n        圖」最早由日商公司於民國五十七年註冊，嗣由參加人於民國六十年起陸續\n        註冊於頭髮、臉部化妝品相關類別，迄今三十年。\n      (3)參加人之燕子商標具二、三十年歷史者七件，十年以上有十件，另有接續註\n        冊者，可謂歷史悠久，並廣為相關事業所熟知。\n      (4)據以異議商標知名事證諸如：成功執行商標權利─撤銷成功之案例有十件，\n        其中有被認定為知名者（附於原異議申請書）。\n      (5)系爭商標圖樣與據以異議商標近似認定之處分，圖樣、案情完全相同，共有\n        五案，故二者之是否近似，迭經不同人審查，均獲相同之見解，故極為客觀\n        。五案之案號如下：\n        註冊第四九七一一二號包裝容器類─其於訴願後已確定撤銷。\n        審定第八三七六四六號化粧品─鈞院判決（八九年訴一七七三號）原告之\n          訴駁回。\n        註冊第八六五○三二號化粧品─鈞院判決（九十年訴一六○號）原告之訴\n          駁回。\n        審定第九一三四○六號藥品─原處分撤銷（中台異字第G00000000）。\n        審定第八七八一九四號藥品─本案。\n      (6)原告指訴系爭商標外圍有英文，故不生近似混淆之虞。殊不知商標之混淆主\n        要在於商標圖樣之主要部分─容易引起注意部分。尤以藥品包裝盒罐、草藥\n        茶包、錠片包裝體積皆不大，所要標示之商標符號面積就更為細小了，因此\n        ，其外圍英文根本看不到、看不清楚。故原告紙上談兵，規避事實。再者，\n        由於商標標示面積小，二者燕子圖形就更無法細膩比對了。又首揭法條適用\n        ，係以商標圖樣相同或近似並均使用於同一或類似商品為要件，至於商標之\n        知名度或行銷通路如何，要非所問，更何況參加人具有知名之事實。\n      (7)綜上可知，系爭燕子圖與據以異議之燕子圖作比較，無論在客觀上有本體外\n        觀及相同使用之混淆，且主觀上亦有因襲之不良本質，其註冊同時有違首揭\n        二法條之規定屬實，依法應予撤銷審定。\n    理  由\n一、按商標圖樣「相同或近似於他人同一商品或類似商品之註冊商標者」，不得申請\n    註冊，為本案異議審定時商標法第三十七條第十二款所明定。而衡酌商標是否近\n    似，以具有普通知識經驗之購買人，於購買時施以普通所用之注意，有無混同誤\n    認之虞判斷之；又所謂類似商品，應依一般社會通念、市場交易情形，並參酌該\n    商品之原材料、用途、功能、產製者、行銷管道及場所或買受人等各種相關因素\n    判斷之，同法施行細則第十五條第一、二項亦定有明文。再「構成雙方商標之圖\n    形或文字等若隔離觀察其主要部分近似者，縱其附屬部分外觀殊異，仍不能謂非\n    近似之商標」，前行政法院（現已改制為最高行政法院）著有三十一年判字第四\n    號判例。\n二、本件系爭審定第八七八一九四號「E.EXCEL INTERNATIONAL及E設計圖」聯合商標\n    圖樣上之圖形（如附圖一），與據以異議之註冊第四六七五一五號「燕子圖」商\n    標圖樣上之圖形（如附圖二）相較，前者係由外文Ｅ狀之左向飛燕圖形嵌置於由\n    外文E.EXCEL INTERNATIONAL右半環連結實線之左半環內所組成，後者則係由一\n    呈外文Ｅ狀之左向飛燕圖形在上，中文燕子牌、日文及英文SWALLOW字\n    樣分別依序排列所組成，兩者商標圖樣上俱有燕子圖形，系爭商標固無中文及日\n    文字樣，且兩者商標英文字樣復不相同，惟兩者商標圖樣上之燕子均係頭部朝左\n    之飛向姿勢，具有二隻翅膀，且均係以呈外文Ｅ狀之抽象燕子設計構圖，整體外\n    觀實極相彷彿，其主要部分構圖意匠、造型及整體觀念上相彷，異時異地隔離觀\n    察時，有使一般商品購買者產生混淆誤認之虞，應屬近似商標。況系爭商標指定\n    使用之醫療補助用營養製劑、維他命等商品，與據以異議商標指定使用之藥品商\n    品，復屬同一或類似商品，自有首揭法條規定之適用。又系爭商標既依商標法第\n    三十七條第十二款規定應評決為無效，則其是否另有同條第七款規定之適用，自\n    無庸審究。再商標註冊案件之審查，係以與據以核駁之案例或引證比較，至其他\n    案例是否妥適，與本件無關，亦非本件所應予審酌，併此敘明。從而被告以系爭\n    商標與據以異議商標，其主要部分圖形設色及構圖意匠相彷，異時異地隔離觀察\n    ，均有致一般消費者混同誤認之虞，復均指定使用於同一或類似商品，為近似之\n    商標，乃為異議成立之處分，揆之首揭規定及說明，洵無違誤，訴願決定予以維\n    持，亦無不合，原告起訴意旨為無理由，應予駁回。\n據上論結，本件原告之訴為無理由，爰依行政訴訟法第九十八條第三項前段，判決如\n主文。\n中      華      民      國    九十一    年      七      月     十七     日\n                           臺 北 高 等 行 政 法 院  第二庭\n                                             審判長 法  官  徐瑞晃\n                                                    法  官  吳慧娟\n                                                    法  官  李得灶\n右為正本係照原本作成。\n如不服本判決，應於送達後二十日內向本院提出上訴狀並表明上訴理由，如於本判決\n宣示後送達前提起上訴者，應於判決送達後二十日內補提上訴理由書（須按他造人數\n附繕本）。\n中      華      民      國    九十一    年      七      月    二十六    日\n                                                    書記官  陳清容\n",
  "structure": {
    "main": "原告之訴駁回。\n訴訟費用由原告負擔。",
    "fact": "一、事實概要：原告於民國八十七年十二月二日以「E.EXCEL INTERNATIONAL及E設計\n    圖」商標作為註冊第七一四八五九號「E.EXCEL」商標之聯合商標，指定使用於\n    當時商標法施行細則第四十九條所定商品及服務分類表第五類之醫療補助用營養\n    製劑、維他命等商品，向被告（原經濟部中央標準局，八十八年一月二十六日改\n    制為經濟部智慧財產局）申請註冊，經被告審查，准列為審定第八七八一九四號\n    聯合商標。嗣參加人金燕企業有限公司以該審定聯合商標有違商標法第三十七條\n    第七、十二款之規定，對之提起異議。經被告審查，以八十九年十二月二十九日\n    中台異字第八八七六九三號商標異議審定書為異議成立之處分。原告不服，提起\n    訴願，遭決定駁回，遂提起行政訴訟。本院於九十一年五月十四日開庭行準備程\n    序，經原、被告陳述意見後，認有使參加人獨立參加訴訟之必要，爰裁定命其參\n    加本件被告之訴訟。\n二、兩造聲明：\n    (一)原告聲明：請求撤銷原處分及訴願決定。訴訟費用由被告負擔。\n    (二)被告聲明：如主文所示。\n三、兩造之爭點：原告所申請註冊審定第八七八一九四號「E.EXCEL INTERNATIONAL\n    及E設計圖」聯合商標（如附圖一），與參加人所申請註冊第四六七五一五號之\n    「燕子圖」商標（如附圖二），是否構成近似？\n    (一)原告主張：\n      (1)按商標圖樣相同或近似於他人同一商品或類似商品之註冊商標者，不得申請\n        註冊，固為商標法第三十七條第一項第十二款之規定，惟商標圖樣是否構成\n        近似，應以具有普通知識經驗之購買人，於異時異地購買時，施以普通所用\n        之注意，有無混同誤認之虞判斷之。本案被告以系爭審定第八七八一九四號\n        「E.EXCEL INTERNATIONAL及E設計圖」商標圖樣係由外文「E.EXCEL\n        INTERNATIONAL」及燕子設計圖所聯合組成，與參加人據以異議之註冊第四\n        六七五一五號「燕子圖」商標圖樣相較，二者均以燕子設計圖為其商標圖樣\n        之主要部分，不論設色及構圖意匠均相彷彿，異時異地隔離觀察，難謂無使\n        商品購買者產生混淆誤認之虞，應屬近似之商標；惟被告所言構成近似之論\n        據，殊屬違法不當。\n      (2)「燕子」為自然生物，據以異議商標申請註冊前後，皆有他人以不同態樣之\n        燕子圖申請註冊在案：\n        燕子為自然界既有生物，非參加人所創造，無獨占專用之理。\n        據以異議商標申請註冊前，已有註冊第八八四九一號、第一一六二二一號\n          等多件商標註冊在先，都以燕子圖作為設計主體，僅在數量及飛翔方向上\n          略有不同。\n        據以異議商標申請註冊後，亦有多件以燕子圖作為設計主體之商標獲准註\n          冊在案。\n        他類商品中，亦有多件以燕子圖作為設計主體之商標獲准在案。\n        是以，消費者並不會將「燕子圖」與參加人產生唯一之聯想。\n      (3)系爭商標附加有顯而易見能與據以異議商標相區異之特徵，二商標無混同之\n        慮：原告系爭商標是一存留字母原形與圓形圖綜合設計之Ｅ字圖標誌，清晰\n        明顯之E.EXCEL INTERNATIONAL文字環繞於右，具備顯而易見之特徵，消費\n        者一眼見之即知產品出處與來源，能與據爭商標相區異，無混同誤認之慮。\n      (4)系爭商標與與據以異議商標，二商標本體在構圖、意義、意匠及外觀上亦有\n        明顯差異，無混同誤認之慮：\n        原告系爭商標：\n          Ａ、構圖：在半圓弧線及英文E.EXCEL INTERNATIONAL組合成之外環中置\n                    放「E」字設計圖。\n          Ｂ、意義：商標名稱E.EXCEL取自英文Extra Excellent有超越卓越之意。\n          Ｃ、意匠：基於公司及商標名稱皆為E.EXCEL，故以「E」字為商標主體，\n                    外圍環以弧線及英文字組合而成之圓形，藉以表達原告商品行\n                    銷全球之企圖心。\n          Ｄ、外觀：「E」設計圖及E.EXCEL INTERNATIONAL。\n        據以異議商標：\n          Ａ、構圖：線條輕盈之具象燕子圖。\n          Ｂ、意義：圖形。\n          Ｃ、意匠：燕子。\n          Ｄ、外觀：燕子圖。\n        由以上比較，明顯可見二商標予人之整體印象及意義差異顯然，無令人發生\n        混淆誤認之虞，此可參被告前身中央標準局編印之「商標手冊」第四十二頁\n        第十三項所載「商標稍有不同，通常認為構成近似，但該差異部分影響商標\n        之整體印象或具其他不同意義，而無混淆誤認之虞者，不為近似」，及前行\n        政法院七十年度判字第三三七號及八十一年度判字第二○二二號判決。\n      (5)參加人據以異議商標變換新設計圖之意圖不明，但其設計手法顯然襲自原告\n        系爭商標設計態樣：\n        原告系爭商標自七十九年創立以來即延用至今。然參加人於八十八年對已\n          併存註冊八年之久，原告註冊第四九七一一二號商標提起評定，其意圖為\n          何未明？\n        末查，從近期商標公報公告資料，得知參加人將其據以異議商標之外圍亦\n          飾以呈圓弧設計之英文字樣，核其設計手法顯然襲用系爭商標態樣，其意\n          圖為何未明？\n      (6)綜上所陳，原告商標與據以異議商標應非屬近似商標，無令一般商品購買人\n        產生混淆誤認之虞。\n    (二)被告主張：\n      (1)按商標異議案件，依商標法施行細則第四十條第一款規定，應適用異議審定\n        時之規定，合先敘明。\n      (2)次按商標圖樣相同或近似於他人同一商品或類似商品之註冊商標者，不得申\n        請註冊，為本件商標異議審定時商標法第三十七條第十二款所明定。而商標\n        圖樣之近似，以具有普通知識經驗之購買人，於購買時施以普通所用之注意\n        ，有無混同誤認之虞判斷之，復為商標法施行細則第十五條第一項所明定。\n        又商標在外觀、觀念或讀音方面有一近似者，即為近似之商標。查本件系爭\n        審定第八七八一九四號「E.EXCEL INTERNATIONAL及E設計圖」商標圖樣係由\n        外文「E.EXCEL INTERNATIONAL」及燕子設計圖所聯合組成，與參加人據以\n        異議之註冊第四六七五一五號「燕子圖」商標圖樣相較，二者均以燕子設計\n        圖為其商標圖樣之主要部分，不論設色及構圖意匠均相彷彿，二造商標於異\n        時異地隔離觀察，難謂無使商品購買者產生混同誤認之虞，應屬構成近似之\n        商標；又前者指定使用於醫療補助用營養製劑、維他命等商品，與後者指定\n        使用於中西藥品，復屬同一或類似商品，揆諸前揭說明，自有首揭法條規定\n        之適用。\n    (三)參加人主張：\n      (1)系爭商標係由一外文形成右半外環連結外環內置一呈外文Ｅ狀之左向飛燕圖\n        形所組成，然其外環文字細小，使用於化妝品瓶罐等包裝容器上無法引起注\n        意，故主要部在於中央之燕子圖。二造燕子圖形之比較，特徵相同─抽象、\n        平面、向左展飛、上下翅膀等。系爭商圖形只是略作粗、細、圓、方的調整\n        ，致總體構設匠技態樣均相同，使人立即產起聯想引起混淆，且使用於相同\n        商品，當屬近似無疑。\n      (2)參加人公司於民國五十八年成立，為國內化妝品先進，除自始即與日本\n        化研工業株式技術合作外，並使用相同的燕子商標，該日商亦於中國大\n        陸註冊使用同樣商標，並於其他多國註冊使用同一商標。據以異議之「燕子\n        圖」最早由日商公司於民國五十七年註冊，嗣由參加人於民國六十年起陸續\n        註冊於頭髮、臉部化妝品相關類別，迄今三十年。\n      (3)參加人之燕子商標具二、三十年歷史者七件，十年以上有十件，另有接續註\n        冊者，可謂歷史悠久，並廣為相關事業所熟知。\n      (4)據以異議商標知名事證諸如：成功執行商標權利─撤銷成功之案例有十件，\n        其中有被認定為知名者（附於原異議申請書）。\n      (5)系爭商標圖樣與據以異議商標近似認定之處分，圖樣、案情完全相同，共有\n        五案，故二者之是否近似，迭經不同人審查，均獲相同之見解，故極為客觀\n        。五案之案號如下：\n        註冊第四九七一一二號包裝容器類─其於訴願後已確定撤銷。\n        審定第八三七六四六號化粧品─鈞院判決（八九年訴一七七三號）原告之\n          訴駁回。\n        註冊第八六五○三二號化粧品─鈞院判決（九十年訴一六○號）原告之訴\n          駁回。\n        審定第九一三四○六號藥品─原處分撤銷（中台異字第G00000000）。\n        審定第八七八一九四號藥品─本案。\n      (6)原告指訴系爭商標外圍有英文，故不生近似混淆之虞。殊不知商標之混淆主\n        要在於商標圖樣之主要部分─容易引起注意部分。尤以藥品包裝盒罐、草藥\n        茶包、錠片包裝體積皆不大，所要標示之商標符號面積就更為細小了，因此\n        ，其外圍英文根本看不到、看不清楚。故原告紙上談兵，規避事實。再者，\n        由於商標標示面積小，二者燕子圖形就更無法細膩比對了。又首揭法條適用\n        ，係以商標圖樣相同或近似並均使用於同一或類似商品為要件，至於商標之\n        知名度或行銷通路如何，要非所問，更何況參加人具有知名之事實。\n      (7)綜上可知，系爭燕子圖與據以異議之燕子圖作比較，無論在客觀上有本體外\n        觀及相同使用之混淆，且主觀上亦有因襲之不良本質，其註冊同時有違首揭\n        二法條之規定屬實，依法應予撤銷審定。",
    "reason": "一、按商標圖樣「相同或近似於他人同一商品或類似商品之註冊商標者」，不得申請\n    註冊，為本案異議審定時商標法第三十七條第十二款所明定。而衡酌商標是否近\n    似，以具有普通知識經驗之購買人，於購買時施以普通所用之注意，有無混同誤\n    認之虞判斷之；又所謂類似商品，應依一般社會通念、市場交易情形，並參酌該\n    商品之原材料、用途、功能、產製者、行銷管道及場所或買受人等各種相關因素\n    判斷之，同法施行細則第十五條第一、二項亦定有明文。再「構成雙方商標之圖\n    形或文字等若隔離觀察其主要部分近似者，縱其附屬部分外觀殊異，仍不能謂非\n    近似之商標」，前行政法院（現已改制為最高行政法院）著有三十一年判字第四\n    號判例。\n二、本件系爭審定第八七八一九四號「E.EXCEL INTERNATIONAL及E設計圖」聯合商標\n    圖樣上之圖形（如附圖一），與據以異議之註冊第四六七五一五號「燕子圖」商\n    標圖樣上之圖形（如附圖二）相較，前者係由外文Ｅ狀之左向飛燕圖形嵌置於由\n    外文E.EXCEL INTERNATIONAL右半環連結實線之左半環內所組成，後者則係由一\n    呈外文Ｅ狀之左向飛燕圖形在上，中文燕子牌、日文及英文SWALLOW字\n    樣分別依序排列所組成，兩者商標圖樣上俱有燕子圖形，系爭商標固無中文及日\n    文字樣，且兩者商標英文字樣復不相同，惟兩者商標圖樣上之燕子均係頭部朝左\n    之飛向姿勢，具有二隻翅膀，且均係以呈外文Ｅ狀之抽象燕子設計構圖，整體外\n    觀實極相彷彿，其主要部分構圖意匠、造型及整體觀念上相彷，異時異地隔離觀\n    察時，有使一般商品購買者產生混淆誤認之虞，應屬近似商標。況系爭商標指定\n    使用之醫療補助用營養製劑、維他命等商品，與據以異議商標指定使用之藥品商\n    品，復屬同一或類似商品，自有首揭法條規定之適用。又系爭商標既依商標法第\n    三十七條第十二款規定應評決為無效，則其是否另有同條第七款規定之適用，自\n    無庸審究。再商標註冊案件之審查，係以與據以核駁之案例或引證比較，至其他\n    案例是否妥適，與本件無關，亦非本件所應予審酌，併此敘明。從而被告以系爭\n    商標與據以異議商標，其主要部分圖形設色及構圖意匠相彷，異時異地隔離觀察\n    ，均有致一般消費者混同誤認之虞，復均指定使用於同一或類似商品，為近似之\n    商標，乃為異議成立之處分，揆之首揭規定及說明，洵無違誤，訴願決定予以維\n    持，亦無不合，原告起訴意旨為無理由，應予駁回。\n據上論結，本件原告之訴為無理由，爰依行政訴訟法第九十八條第三項前段，判決如\n主文。\n中      華      民      國    九十一    年      七      月     十七     日\n                           臺 北 高 等 行 政 法 院  第二庭\n                                             審判長 法  官  徐瑞晃\n                                                    法  官  吳慧娟\n                                                    法  官  李得灶\n右為正本係照原本作成。\n如不服本判決，應於送達後二十日內向本院提出上訴狀並表明上訴理由，如於本判決\n宣示後送達前提起上訴者，應於判決送達後二十日內補提上訴理由書（須按他造人數\n附繕本）。"
  },
  "search": "臺北高等行政法院判決九十年度訴字第四五四五號.原告丞燕國際股份有限公司代表人甲○○董事長.訴訟代理人劉緒倫律師複代理人徐東昇律師被告經濟部智慧財產局代表人陳明邦（局長）訴訟代理人丙○○參加人金燕企業有限公司代表人乙○○右當事人間因商標異議事件，原告不服經濟部中華民國九十年四月二十六日經（九○）訴字第○九○○六三○七九五○號訴願決定，提起行政訴訟，本院判決如左：主文原告之訴駁回。訴訟費用由原告負擔。事實一、事實概要：原告於民國八十七年十二月二日以「E.EXCELINTERNATIONAL及E設計圖」商標作為註冊第七一四八五九號「E.EXCEL」商標之聯合商標，指定使用於當時商標法施行細則第四十九條所定商品及服務分類表第五類之醫療補助用營養製劑、維他命等商品，向被告（原經濟部中央標準局，八十八年一月二十六日改制為經濟部智慧財產局）申請註冊，經被告審查，准列為審定第八七八一九四號聯合商標。嗣參加人金燕企業有限公司以該審定聯合商標有違商標法第三十七條第七、十二款之規定，對之提起異議。經被告審查，以八十九年十二月二十九日中台異字第八八七六九三號商標異議審定書為異議成立之處分。原告不服，提起訴願，遭決定駁回，遂提起行政訴訟。本院於九十一年五月十四日開庭行準備程序，經原、被告陳述意見後，認有使參加人獨立參加訴訟之必要，爰裁定命其參加本件被告之訴訟。二、兩造聲明：(一)原告聲明：請求撤銷原處分及訴願決定。訴訟費用由被告負擔。(二)被告聲明：如主文所示。三、兩造之爭點：原告所申請註冊審定第八七八一九四號「E.EXCELINTERNATIONAL及E設計圖」聯合商標（如附圖一），與參加人所申請註冊第四六七五一五號之「燕子圖」商標（如附圖二），是否構成近似？(一)原告主張：(1)按商標圖樣相同或近似於他人同一商品或類似商品之註冊商標者，不得申請註冊，固為商標法第三十七條第一項第十二款之規定，惟商標圖樣是否構成近似，應以具有普通知識經驗之購買人，於異時異地購買時，施以普通所用之注意，有無混同誤認之虞判斷之。本案被告以系爭審定第八七八一九四號「E.EXCELINTERNATIONAL及E設計圖」商標圖樣係由外文「E.EXCELINTERNATIONAL」及燕子設計圖所聯合組成，與參加人據以異議之註冊第四六七五一五號「燕子圖」商標圖樣相較，二者均以燕子設計圖為其商標圖樣之主要部分，不論設色及構圖意匠均相彷彿，異時異地隔離觀察，難謂無使商品購買者產生混淆誤認之虞，應屬近似之商標；惟被告所言構成近似之論據，殊屬違法不當。(2)「燕子」為自然生物，據以異議商標申請註冊前後，皆有他人以不同態樣之燕子圖申請註冊在案：燕子為自然界既有生物，非參加人所創造，無獨占專用之理。據以異議商標申請註冊前，已有註冊第八八四九一號、第一一六二二一號等多件商標註冊在先，都以燕子圖作為設計主體，僅在數量及飛翔方向上略有不同。據以異議商標申請註冊後，亦有多件以燕子圖作為設計主體之商標獲准註冊在案。他類商品中，亦有多件以燕子圖作為設計主體之商標獲准在案。是以，消費者並不會將「燕子圖」與參加人產生唯一之聯想。(3)系爭商標附加有顯而易見能與據以異議商標相區異之特徵，二商標無混同之慮：原告系爭商標是一存留字母原形與圓形圖綜合設計之Ｅ字圖標誌，清晰明顯之E.EXCELINTERNATIONAL文字環繞於右，具備顯而易見之特徵，消費者一眼見之即知產品出處與來源，能與據爭商標相區異，無混同誤認之慮。(4)系爭商標與與據以異議商標，二商標本體在構圖、意義、意匠及外觀上亦有明顯差異，無混同誤認之慮：原告系爭商標：Ａ、構圖：在半圓弧線及英文E.EXCELINTERNATIONAL組合成之外環中置放「E」字設計圖。Ｂ、意義：商標名稱E.EXCEL取自英文ExtraExcellent有超越卓越之意。Ｃ、意匠：基於公司及商標名稱皆為E.EXCEL，故以「E」字為商標主體，外圍環以弧線及英文字組合而成之圓形，藉以表達原告商品行銷全球之企圖心。Ｄ、外觀：「E」設計圖及E.EXCELINTERNATIONAL。據以異議商標：Ａ、構圖：線條輕盈之具象燕子圖。Ｂ、意義：圖形。Ｃ、意匠：燕子。Ｄ、外觀：燕子圖。由以上比較，明顯可見二商標予人之整體印象及意義差異顯然，無令人發生混淆誤認之虞，此可參被告前身中央標準局編印之「商標手冊」第四十二頁第十三項所載「商標稍有不同，通常認為構成近似，但該差異部分影響商標之整體印象或具其他不同意義，而無混淆誤認之虞者，不為近似」，及前行政法院七十年度判字第三三七號及八十一年度判字第二○二二號判決。(5)參加人據以異議商標變換新設計圖之意圖不明，但其設計手法顯然襲自原告系爭商標設計態樣：原告系爭商標自七十九年創立以來即延用至今。然參加人於八十八年對已併存註冊八年之久，原告註冊第四九七一一二號商標提起評定，其意圖為何未明？末查，從近期商標公報公告資料，得知參加人將其據以異議商標之外圍亦飾以呈圓弧設計之英文字樣，核其設計手法顯然襲用系爭商標態樣，其意圖為何未明？(6)綜上所陳，原告商標與據以異議商標應非屬近似商標，無令一般商品購買人產生混淆誤認之虞。(二)被告主張：(1)按商標異議案件，依商標法施行細則第四十條第一款規定，應適用異議審定時之規定，合先敘明。(2)次按商標圖樣相同或近似於他人同一商品或類似商品之註冊商標者，不得申請註冊，為本件商標異議審定時商標法第三十七條第十二款所明定。而商標圖樣之近似，以具有普通知識經驗之購買人，於購買時施以普通所用之注意，有無混同誤認之虞判斷之，復為商標法施行細則第十五條第一項所明定。又商標在外觀、觀念或讀音方面有一近似者，即為近似之商標。查本件系爭審定第八七八一九四號「E.EXCELINTERNATIONAL及E設計圖」商標圖樣係由外文「E.EXCELINTERNATIONAL」及燕子設計圖所聯合組成，與參加人據以異議之註冊第四六七五一五號「燕子圖」商標圖樣相較，二者均以燕子設計圖為其商標圖樣之主要部分，不論設色及構圖意匠均相彷彿，二造商標於異時異地隔離觀察，難謂無使商品購買者產生混同誤認之虞，應屬構成近似之商標；又前者指定使用於醫療補助用營養製劑、維他命等商品，與後者指定使用於中西藥品，復屬同一或類似商品，揆諸前揭說明，自有首揭法條規定之適用。(三)參加人主張：(1)系爭商標係由一外文形成右半外環連結外環內置一呈外文Ｅ狀之左向飛燕圖形所組成，然其外環文字細小，使用於化妝品瓶罐等包裝容器上無法引起注意，故主要部在於中央之燕子圖。二造燕子圖形之比較，特徵相同─抽象、平面、向左展飛、上下翅膀等。系爭商圖形只是略作粗、細、圓、方的調整，致總體構設匠技態樣均相同，使人立即產起聯想引起混淆，且使用於相同商品，當屬近似無疑。(2)參加人公司於民國五十八年成立，為國內化妝品先進，除自始即與日本化研工業株式技術合作外，並使用相同的燕子商標，該日商亦於中國大陸註冊使用同樣商標，並於其他多國註冊使用同一商標。據以異議之「燕子圖」最早由日商公司於民國五十七年註冊，嗣由參加人於民國六十年起陸續註冊於頭髮、臉部化妝品相關類別，迄今三十年。(3)參加人之燕子商標具二、三十年歷史者七件，十年以上有十件，另有接續註冊者，可謂歷史悠久，並廣為相關事業所熟知。(4)據以異議商標知名事證諸如：成功執行商標權利─撤銷成功之案例有十件，其中有被認定為知名者（附於原異議申請書）。(5)系爭商標圖樣與據以異議商標近似認定之處分，圖樣、案情完全相同，共有五案，故二者之是否近似，迭經不同人審查，均獲相同之見解，故極為客觀。五案之案號如下：註冊第四九七一一二號包裝容器類─其於訴願後已確定撤銷。審定第八三七六四六號化粧品─鈞院判決（八九年訴一七七三號）原告之訴駁回。註冊第八六五○三二號化粧品─鈞院判決（九十年訴一六○號）原告之訴駁回。審定第九一三四○六號藥品─原處分撤銷（中台異字第G00000000）。審定第八七八一九四號藥品─本案。(6)原告指訴系爭商標外圍有英文，故不生近似混淆之虞。殊不知商標之混淆主要在於商標圖樣之主要部分─容易引起注意部分。尤以藥品包裝盒罐、草藥茶包、錠片包裝體積皆不大，所要標示之商標符號面積就更為細小了，因此，其外圍英文根本看不到、看不清楚。故原告紙上談兵，規避事實。再者，由於商標標示面積小，二者燕子圖形就更無法細膩比對了。又首揭法條適用，係以商標圖樣相同或近似並均使用於同一或類似商品為要件，至於商標之知名度或行銷通路如何，要非所問，更何況參加人具有知名之事實。(7)綜上可知，系爭燕子圖與據以異議之燕子圖作比較，無論在客觀上有本體外觀及相同使用之混淆，且主觀上亦有因襲之不良本質，其註冊同時有違首揭二法條之規定屬實，依法應予撤銷審定。理由一、按商標圖樣「相同或近似於他人同一商品或類似商品之註冊商標者」，不得申請註冊，為本案異議審定時商標法第三十七條第十二款所明定。而衡酌商標是否近似，以具有普通知識經驗之購買人，於購買時施以普通所用之注意，有無混同誤認之虞判斷之；又所謂類似商品，應依一般社會通念、市場交易情形，並參酌該商品之原材料、用途、功能、產製者、行銷管道及場所或買受人等各種相關因素判斷之，同法施行細則第十五條第一、二項亦定有明文。再「構成雙方商標之圖形或文字等若隔離觀察其主要部分近似者，縱其附屬部分外觀殊異，仍不能謂非近似之商標」，前行政法院（現已改制為最高行政法院）著有三十一年判字第四號判例。二、本件系爭審定第八七八一九四號「E.EXCELINTERNATIONAL及E設計圖」聯合商標圖樣上之圖形（如附圖一），與據以異議之註冊第四六七五一五號「燕子圖」商標圖樣上之圖形（如附圖二）相較，前者係由外文Ｅ狀之左向飛燕圖形嵌置於由外文E.EXCELINTERNATIONAL右半環連結實線之左半環內所組成，後者則係由一呈外文Ｅ狀之左向飛燕圖形在上，中文燕子牌、日文及英文SWALLOW字樣分別依序排列所組成，兩者商標圖樣上俱有燕子圖形，系爭商標固無中文及日文字樣，且兩者商標英文字樣復不相同，惟兩者商標圖樣上之燕子均係頭部朝左之飛向姿勢，具有二隻翅膀，且均係以呈外文Ｅ狀之抽象燕子設計構圖，整體外觀實極相彷彿，其主要部分構圖意匠、造型及整體觀念上相彷，異時異地隔離觀察時，有使一般商品購買者產生混淆誤認之虞，應屬近似商標。況系爭商標指定使用之醫療補助用營養製劑、維他命等商品，與據以異議商標指定使用之藥品商品，復屬同一或類似商品，自有首揭法條規定之適用。又系爭商標既依商標法第三十七條第十二款規定應評決為無效，則其是否另有同條第七款規定之適用，自無庸審究。再商標註冊案件之審查，係以與據以核駁之案例或引證比較，至其他案例是否妥適，與本件無關，亦非本件所應予審酌，併此敘明。從而被告以系爭商標與據以異議商標，其主要部分圖形設色及構圖意匠相彷，異時異地隔離觀察，均有致一般消費者混同誤認之虞，復均指定使用於同一或類似商品，為近似之商標，乃為異議成立之處分，揆之首揭規定及說明，洵無違誤，訴願決定予以維持，亦無不合，原告起訴意旨為無理由，應予駁回。據上論結，本件原告之訴為無理由，爰依行政訴訟法第九十八條第三項前段，判決如主文。中華民國九十一年七月十七日臺北高等行政法院第二庭審判長法官徐瑞晃法官吳慧娟法官李得灶右為正本係照原本作成。如不服本判決，應於送達後二十日內向本院提出上訴狀並表明上訴理由，如於本判決宣示後送達前提起上訴者，應於判決送達後二十日內補提上訴理由書（須按他造人數附繕本）。中華民國九十一年七月二十六日書記官陳清容",
  "characters": {
    "judges": [
      "徐瑞晃",
      "吳慧娟",
      "李得灶"
    ],
    "prosecutors": [

    ],
    "lawyers": [
      "劉緒倫",
      "徐東昇"
    ],
    "clerks": [
      "陳清容"
    ],
    "plaintiffs": [
      "丞燕國際股份有限公司"
    ],
    "defendants": [
      "經濟部智慧財產局"
    ],
    "prosecutor_office": [

    ],
    "creditors": [

    ],
    "debtors": [

    ],
    "judicial_associate_officer": [

    ]
  },
  "adjudged_at": "2002-07-17",
  "created_at": "2016-02-05 17:55:55",
  "updated_at": "2016-02-05 17:55:55"
}