{
  "identify": "KSD-94-交簡-651-20050114-1",
  "court": {
    "name": "臺灣高雄地方法院",
    "code": "KSD"
  },
  "division": {
    "name": "刑事",
    "code": "M"
  },
  "year": 94,
  "word": "交簡",
  "number": "651",
  "jcheck": "1",
  "reason": "公共危險",
  "content": "臺灣高雄地方法院刑事簡易判決                        九十四年度交簡字第六五一號\n    聲  請  人  臺灣高雄地方法院檢察署檢察官\n    被      告  甲○○  男  四.\n右列被告因公共危險案件，經檢察官聲請以簡易判決處刑（九十四年度調偵字第三八\n號），本院判決如左：\n    主  文\n甲○○服用酒類，不能安全駕駛動力交通工具而駕駛，處拘役參拾日，如易科罰金，\n以參佰元折算壹日。\n    事實及理由\n一、本件犯罪事實及證據均引用檢察官聲請簡易判決處刑書之記載（如附件）。\n二、核被告甲○○所為，係犯刑法第一百八十五條之三服用酒類不能安全駕駛動力交\n    通工具而駕駛罪。爰審酌被告於飲酒後酒精濃度達每公升零點七七毫克之情況下\n    ，仍貿然騎乘機車行駛於公眾往來之道路上，無視於公眾生命財產安全之情狀，\n    所犯情節嚴重，惟念及未曾受有期徒刑以上刑之宣告，有臺灣高等法院被告全國\n    前案紀錄表在卷可佐，素行尚稱良好，及被告於犯後坦承犯行，態度良好等一切\n    情狀，量處如主文所示之刑，並諭知易科罰金之折算標準，以資懲儆。\n三、依刑事訴訟法第四百四十九條第一項前段、第三項、第四百五十四條第二項，刑\n    法第一百八十五條之三、第四十一條第一項前段，罰金罰鍰提高標準條例第二條\n    ，逕以簡易判決處如主文所示之刑。\n四、如不服本判決，得於判決書送達之日起十日內，以書狀敘述理由，向本院提起上\n    訴。\n中      華      民      國    九十四    年      一      月     十四     日\n                                  臺灣高雄地方法院交通法庭\n                                      法  官  洪能超\n右正本證明與原本無異。\n                                      書記官  曾小玲\n中      華      民      國    九十四    年      一      月     十四     日\n附錄本案論罪科刑法條全文：\n刑法第一百八十五條之三：\n服用毒品、麻醉藥品、酒類或其他相類之物，不能安全駕駛動力交通工具而駕駛者，\n處一年以下有期徒刑、拘役或三萬元以下罰金。\n",
  "structure": {
    "main": "甲○○服用酒類，不能安全駕駛動力交通工具而駕駛，處拘役參拾日，如易科罰金，\n以參佰元折算壹日。",
    "fact": "一、本件犯罪事實及證據均引用檢察官聲請簡易判決處刑書之記載（如附件）。\n二、核被告甲○○所為，係犯刑法第一百八十五條之三服用酒類不能安全駕駛動力交\n    通工具而駕駛罪。爰審酌被告於飲酒後酒精濃度達每公升零點七七毫克之情況下\n    ，仍貿然騎乘機車行駛於公眾往來之道路上，無視於公眾生命財產安全之情狀，\n    所犯情節嚴重，惟念及未曾受有期徒刑以上刑之宣告，有臺灣高等法院被告全國\n    前案紀錄表在卷可佐，素行尚稱良好，及被告於犯後坦承犯行，態度良好等一切\n    情狀，量處如主文所示之刑，並諭知易科罰金之折算標準，以資懲儆。\n三、依刑事訴訟法第四百四十九條第一項前段、第三項、第四百五十四條第二項，刑\n    法第一百八十五條之三、第四十一條第一項前段，罰金罰鍰提高標準條例第二條\n    ，逕以簡易判決處如主文所示之刑。\n四、如不服本判決，得於判決書送達之日起十日內，以書狀敘述理由，向本院提起上\n    訴。",
    "reason": "一、本件犯罪事實及證據均引用檢察官聲請簡易判決處刑書之記載（如附件）。\n二、核被告甲○○所為，係犯刑法第一百八十五條之三服用酒類不能安全駕駛動力交\n    通工具而駕駛罪。爰審酌被告於飲酒後酒精濃度達每公升零點七七毫克之情況下\n    ，仍貿然騎乘機車行駛於公眾往來之道路上，無視於公眾生命財產安全之情狀，\n    所犯情節嚴重，惟念及未曾受有期徒刑以上刑之宣告，有臺灣高等法院被告全國\n    前案紀錄表在卷可佐，素行尚稱良好，及被告於犯後坦承犯行，態度良好等一切\n    情狀，量處如主文所示之刑，並諭知易科罰金之折算標準，以資懲儆。\n三、依刑事訴訟法第四百四十九條第一項前段、第三項、第四百五十四條第二項，刑\n    法第一百八十五條之三、第四十一條第一項前段，罰金罰鍰提高標準條例第二條\n    ，逕以簡易判決處如主文所示之刑。\n四、如不服本判決，得於判決書送達之日起十日內，以書狀敘述理由，向本院提起上\n    訴。"
  },
  "search": "臺灣高雄地方法院刑事簡易判決九十四年度交簡字第六五一號聲請人臺灣高雄地方法院檢察署檢察官被告甲○○男四.右列被告因公共危險案件，經檢察官聲請以簡易判決處刑（九十四年度調偵字第三八號），本院判決如左：主文甲○○服用酒類，不能安全駕駛動力交通工具而駕駛，處拘役參拾日，如易科罰金，以參佰元折算壹日。事實及理由一、本件犯罪事實及證據均引用檢察官聲請簡易判決處刑書之記載（如附件）。二、核被告甲○○所為，係犯刑法第一百八十五條之三服用酒類不能安全駕駛動力交通工具而駕駛罪。爰審酌被告於飲酒後酒精濃度達每公升零點七七毫克之情況下，仍貿然騎乘機車行駛於公眾往來之道路上，無視於公眾生命財產安全之情狀，所犯情節嚴重，惟念及未曾受有期徒刑以上刑之宣告，有臺灣高等法院被告全國前案紀錄表在卷可佐，素行尚稱良好，及被告於犯後坦承犯行，態度良好等一切情狀，量處如主文所示之刑，並諭知易科罰金之折算標準，以資懲儆。三、依刑事訴訟法第四百四十九條第一項前段、第三項、第四百五十四條第二項，刑法第一百八十五條之三、第四十一條第一項前段，罰金罰鍰提高標準條例第二條，逕以簡易判決處如主文所示之刑。四、如不服本判決，得於判決書送達之日起十日內，以書狀敘述理由，向本院提起上訴。中華民國九十四年一月十四日臺灣高雄地方法院交通法庭法官洪能超右正本證明與原本無異。書記官曾小玲中華民國九十四年一月十四日附錄本案論罪科刑法條全文：刑法第一百八十五條之三：服用毒品、麻醉藥品、酒類或其他相類之物，不能安全駕駛動力交通工具而駕駛者，處一年以下有期徒刑、拘役或三萬元以下罰金。",
  "characters": {
    "judges": [
      "洪能超"
    ],
    "prosecutors": [

    ],
    "lawyers": [

    ],
    "clerks": [
      "曾小玲"
    ],
    "plaintiffs": [

    ],
    "defendants": [
      "甲○○  男  四.",
      "右列被告因公共危險案件，經檢察官聲請以簡易判決處刑（九十四年度調偵字第三八",
      "號），本院判決如左："
    ],
    "prosecutor_office": [
      "臺灣高雄地方法院檢察署檢察官"
    ],
    "creditors": [

    ],
    "debtors": [

    ],
    "judicial_associate_officer": [

    ]
  },
  "adjudged_at": "2005-01-14",
  "created_at": "2016-02-07 01:17:56",
  "updated_at": "2016-02-07 01:17:56"
}