{
  "identify": "TYD-94-壢交簡-32-20050113-1",
  "court": {
    "name": "臺灣桃園地方法院",
    "code": "TYD"
  },
  "division": {
    "name": "刑事",
    "code": "M"
  },
  "year": 94,
  "word": "壢交簡",
  "number": "32",
  "jcheck": "1",
  "reason": "公共危險",
  "content": "臺灣桃園地方法院刑事簡易判決        94年度壢交簡字第32號\n公  訴  人  臺灣桃園地方法院檢察署檢察官\n被      告  甲○○  男  29歲.\n上列被告因公共危險案件，經檢察官聲請以簡易判決處刑（九十\n三年度偵字第一七四七六號），本院判決如下：\n    主      文\n甲○○服用酒類，不能安全駕駛動力交通工具而駕駛，處罰金\n萬元，如易服勞役，以佰元折算壹日。\n    事實及理由\n一、本件犯罪事實及證據，均引用檢察官聲請簡易判決處刑書之\n    記載（如附件）。\n二、依刑事訴訟法第四百四十九條第一項、第三項、第四百五十\n    四條第二項，刑法第一百八十五條之三、第四十二條第二項\n    ，罰金罰鍰提高標準條例第二條，逕以簡易判決處刑如主文\n    。\n三、如不服本判決，得於判決書送達之翌日起十日內，以書狀敘\n    述理由向本庭提出上訴。（須附繕本）\n中    華    民    國    94    年    1     月    13    日\n                  臺灣桃園地方法院交通法庭\n                      法  官  朱美璘\n以上正本證明與原本無異\n如不服本判決，應於判決送達後10日內，向本院提出上訴狀。\n中    華    民    國    94    年    1     月    14    日\n                      書記官  楊鳳滿\n本案論罪科刑法條：\n中華民國刑法第一百八十五條之三\n服用毒品、麻醉藥品、酒類或其他相類之物，不能安全駕駛動力\n交通工具而駕駛者，處一年以下有期徒刑、拘役或三萬元以下罰\n金。\n",
  "structure": {
    "main": "甲○○服用酒類，不能安全駕駛動力交通工具而駕駛，處罰金\n萬元，如易服勞役，以佰元折算壹日。",
    "fact": "一、本件犯罪事實及證據，均引用檢察官聲請簡易判決處刑書之\n    記載（如附件）。\n二、依刑事訴訟法第四百四十九條第一項、第三項、第四百五十\n    四條第二項，刑法第一百八十五條之三、第四十二條第二項\n    ，罰金罰鍰提高標準條例第二條，逕以簡易判決處刑如主文\n    。\n三、如不服本判決，得於判決書送達之翌日起十日內，以書狀敘\n    述理由向本庭提出上訴。（須附繕本）",
    "reason": "一、本件犯罪事實及證據，均引用檢察官聲請簡易判決處刑書之\n    記載（如附件）。\n二、依刑事訴訟法第四百四十九條第一項、第三項、第四百五十\n    四條第二項，刑法第一百八十五條之三、第四十二條第二項\n    ，罰金罰鍰提高標準條例第二條，逕以簡易判決處刑如主文\n    。\n三、如不服本判決，得於判決書送達之翌日起十日內，以書狀敘\n    述理由向本庭提出上訴。（須附繕本）"
  },
  "search": "臺灣桃園地方法院刑事簡易判決94年度壢交簡字第32號公訴人臺灣桃園地方法院檢察署檢察官被告甲○○男29歲.上列被告因公共危險案件，經檢察官聲請以簡易判決處刑（九十三年度偵字第一七四七六號），本院判決如下：主文甲○○服用酒類，不能安全駕駛動力交通工具而駕駛，處罰金萬元，如易服勞役，以佰元折算壹日。事實及理由一、本件犯罪事實及證據，均引用檢察官聲請簡易判決處刑書之記載（如附件）。二、依刑事訴訟法第四百四十九條第一項、第三項、第四百五十四條第二項，刑法第一百八十五條之三、第四十二條第二項，罰金罰鍰提高標準條例第二條，逕以簡易判決處刑如主文。三、如不服本判決，得於判決書送達之翌日起十日內，以書狀敘述理由向本庭提出上訴。（須附繕本）中華民國94年1月13日臺灣桃園地方法院交通法庭法官朱美璘以上正本證明與原本無異如不服本判決，應於判決送達後10日內，向本院提出上訴狀。中華民國94年1月14日書記官楊鳳滿本案論罪科刑法條：中華民國刑法第一百八十五條之三服用毒品、麻醉藥品、酒類或其他相類之物，不能安全駕駛動力交通工具而駕駛者，處一年以下有期徒刑、拘役或三萬元以下罰金。",
  "characters": {
    "judges": [
      "朱美璘"
    ],
    "prosecutors": [

    ],
    "lawyers": [

    ],
    "clerks": [
      "楊鳳滿"
    ],
    "plaintiffs": [

    ],
    "defendants": [
      "甲○○  男  29歲."
    ],
    "prosecutor_office": [
      "臺灣桃園地方法院檢察署檢察官"
    ],
    "creditors": [

    ],
    "debtors": [

    ],
    "judicial_associate_officer": [

    ]
  },
  "adjudged_at": "2005-01-13",
  "created_at": "2016-02-07 01:16:29",
  "updated_at": "2016-02-07 01:16:29"
}