{
  "identify": "SCD-94-訴-326-20051230-3",
  "court": {
    "name": "臺灣新竹地方法院",
    "code": "SCD"
  },
  "division": {
    "name": "民事",
    "code": "V"
  },
  "year": 94,
  "word": "訴",
  "number": "326",
  "jcheck": "3",
  "reason": "返還消費借貸款",
  "content": "臺灣新竹地方法院民事判決               94年度訴字第326號\n原      告  華僑商業銀行股份有限公司\n法定代理人  丙○○\n訴訟代理人  乙○○\n被      告  訊音有限公司\n兼法定代理  戊○○\n人\n被      告  甲○○\n            丁○○\n                        799.\n            己○\n            庚○○\n            辛○○\n上列當事人間返還消費借貸款事件，本院於民國94年12月22日辯\n論終結，判決如下：\n    主  文\n被告應連帶給付原告新臺幣壹佰陸拾伍萬壹仟佰拾元，及自\n民國九十四年二月十五日起至清償日止，按年息百分之六點七八\n計算之利息，暨自民國九十四年三月十六日起至清償日止，逾期\n六個月以內者，按上開利率百分之十，超過六個月者，按上開利\n率百分之二十計算之違約金。\n訴訟費用由被告連帶負擔。\n    事實及理由\n一、程序方面：\n(一)、按訴狀送達後，原告不得將原訴變更或追加他訴，但擴張或\n    減縮應受判決事項之聲明者，不在此限，民事訴訟法第255\n    條第1項第3款定有明文。查本件原告起訴時原係請求被告應\n    連帶給付原告1,651,330元，及自94年1月21日起至清償日止\n    ，按年息百分之6.78計算之利息，暨自94年2月22日起至清\n    償日止，逾期6個月以內者，按上開利率百分之10，超過6\n    個月者，按上開利率百分之20計算之違約金，嗣將請求之聲\n    明減縮為如主文第1項所示，核係屬減縮應受判決事項之聲\n    明，自應准許。\n(二)、本件被告等均經合法通知，均未於最後言詞辯論期日到場，\n    核無民事訴訟法第386條各款所列情形，爰依原告之聲請，\n    由其一造辯論而為判決。\n二、原告主張：被告訊音有限公司（下稱訊音公司）於民國（下\n    同）92年4月15日，邀同被告戊○○、甲○○、丁○○、己\n    ○、庚○○、辛○○為連帶保證人，與原告簽訂借據，借款\n    新臺幣（下同）4,000,000元，借款期間自92年4月15日起至\n    95年4月15日止，共分36期，按期平均攤還，借款利率按原\n    告銀行基準利率加3.95％計算，並於每年1月、4月、7月及\n    10月21日依原告銀行基準利率變動而調整，並自調整日起，\n    按調整後之年利率計算。倘逾期償付本息時，除按約定利率\n    支付遲延利息外，逾期6個月以內者，按上開利率百分之10\n    ，逾期6個月以上者，按上開利率百分之20計付違約金。詎\n    被告訊音公司公司自94年1月21日起即未依約繳款，尚欠本\n    金1,651,330元，依約定書第5條之約定，全部債務視為到期\n    ，應將所欠款項全數清償，然屢經催討仍置之不理，而被告\n    戊○○、甲○○、丁○○、己○、庚○○、辛○○既為連帶\n    保證人，依法應負連帶清償責任，為此爰依消費借貸及連帶\n    保證之法律關係提起本件訴訟，請求被告連帶給付如主文第\n    1項所示之金額、利息及違約金等語。\n三、被告方面：\n(一)、被告訊音公司、戊○○、甲○○、丁○○、己○、辛○○均\n    經合法通知，未於言詞辯論期日到場，亦未提出書狀作何聲\n    明或陳述。\n(二)、被告庚○○據其先前陳述，其願與原告詳談還款方式，並聲\n    明：原告之訴駁回；如受不利之判決，願供擔保，請准宣告\n    免為假執行。\n四、得心證之理由：\n(一)、原告主張之前揭事實，業據其提出約定書7份、借據、保證\n    書、現放各筆餘額查詢、往來明細資料查詢、計息明細資料\n    查詢各1份為證，核與其所述相符，被告訊音公司、戊○○\n    、甲○○、丁○○、己○、辛○○迄未到場爭執，亦未提出\n    任何有利於己之聲明、陳述或證據，以供本院審酌，而被告\n    庚○○則不爭執原告主張之金額，僅表明願與原告談還款方\n    式，則本院依調查證據之結果及斟酌全辯論意旨，自堪信原\n    告之主張為真實。\n(二)、按消費借貸者，謂當事人一方移轉金錢或其他代替物之所有\n    權於他方，而約定他方以種類、品質、數量相同之物返還之\n    契約，民法第474條第1項定有明文；又按保證債務之所謂連\n    帶，係指保證人與主債務人負同一債務，對於債權人各負全\n    部給付之責任者而言，此就民法第272條第1項規定連帶債務\n    之文義參照觀之甚明，最高法院45年台上字第1426號著有判\n    例可資參照。本件被告訊音公司既為系爭債務之債務人，被\n    告戊○○、甲○○、丁○○、己○、庚○○、辛○○為其連\n    帶保證人，自應就其保證債務負全部給付之責。從而，原告\n    依消費借貸及連帶保證之法律關係，請求被告連帶給付如主\n    文第1項所示之金額，即無不合，應予准許。\n五、被告庚○○陳明願供擔保請准宣告免為假執行，惟原告並未\n    聲請假執行，被告之聲請核無必要，併此敘明。\n六、據上論結，本件原告之訴為有理由，依民事訴訟法第385條\n    第1項前段、第85條第2項，判決如主文。\n中    華    民    國    94    年    12    月    30    日\n                  民事第一庭    法  官  黃珮禎\n以上正本係照原本作成。\n如對本判決上訴，須於判決送達後20日內向本院提出上訴狀。\n中    華    民    國    94    年    12    月    30    日\n                                書記官  黎秀娟\n",
  "structure": {
    "main": "被告應連帶給付原告新臺幣壹佰陸拾伍萬壹仟佰拾元，及自\n民國九十四年二月十五日起至清償日止，按年息百分之六點七八\n計算之利息，暨自民國九十四年三月十六日起至清償日止，逾期\n六個月以內者，按上開利率百分之十，超過六個月者，按上開利\n率百分之二十計算之違約金。\n訴訟費用由被告連帶負擔。",
    "fact": "一、程序方面：\n(一)、按訴狀送達後，原告不得將原訴變更或追加他訴，但擴張或\n    減縮應受判決事項之聲明者，不在此限，民事訴訟法第255\n    條第1項第3款定有明文。查本件原告起訴時原係請求被告應\n    連帶給付原告1,651,330元，及自94年1月21日起至清償日止\n    ，按年息百分之6.78計算之利息，暨自94年2月22日起至清\n    償日止，逾期6個月以內者，按上開利率百分之10，超過6\n    個月者，按上開利率百分之20計算之違約金，嗣將請求之聲\n    明減縮為如主文第1項所示，核係屬減縮應受判決事項之聲\n    明，自應准許。\n(二)、本件被告等均經合法通知，均未於最後言詞辯論期日到場，\n    核無民事訴訟法第386條各款所列情形，爰依原告之聲請，\n    由其一造辯論而為判決。\n二、原告主張：被告訊音有限公司（下稱訊音公司）於民國（下\n    同）92年4月15日，邀同被告戊○○、甲○○、丁○○、己\n    ○、庚○○、辛○○為連帶保證人，與原告簽訂借據，借款\n    新臺幣（下同）4,000,000元，借款期間自92年4月15日起至\n    95年4月15日止，共分36期，按期平均攤還，借款利率按原\n    告銀行基準利率加3.95％計算，並於每年1月、4月、7月及\n    10月21日依原告銀行基準利率變動而調整，並自調整日起，\n    按調整後之年利率計算。倘逾期償付本息時，除按約定利率\n    支付遲延利息外，逾期6個月以內者，按上開利率百分之10\n    ，逾期6個月以上者，按上開利率百分之20計付違約金。詎\n    被告訊音公司公司自94年1月21日起即未依約繳款，尚欠本\n    金1,651,330元，依約定書第5條之約定，全部債務視為到期\n    ，應將所欠款項全數清償，然屢經催討仍置之不理，而被告\n    戊○○、甲○○、丁○○、己○、庚○○、辛○○既為連帶\n    保證人，依法應負連帶清償責任，為此爰依消費借貸及連帶\n    保證之法律關係提起本件訴訟，請求被告連帶給付如主文第\n    1項所示之金額、利息及違約金等語。\n三、被告方面：\n(一)、被告訊音公司、戊○○、甲○○、丁○○、己○、辛○○均\n    經合法通知，未於言詞辯論期日到場，亦未提出書狀作何聲\n    明或陳述。\n(二)、被告庚○○據其先前陳述，其願與原告詳談還款方式，並聲\n    明：原告之訴駁回；如受不利之判決，願供擔保，請准宣告\n    免為假執行。\n四、得心證之理由：\n(一)、原告主張之前揭事實，業據其提出約定書7份、借據、保證\n    書、現放各筆餘額查詢、往來明細資料查詢、計息明細資料\n    查詢各1份為證，核與其所述相符，被告訊音公司、戊○○\n    、甲○○、丁○○、己○、辛○○迄未到場爭執，亦未提出\n    任何有利於己之聲明、陳述或證據，以供本院審酌，而被告\n    庚○○則不爭執原告主張之金額，僅表明願與原告談還款方\n    式，則本院依調查證據之結果及斟酌全辯論意旨，自堪信原\n    告之主張為真實。\n(二)、按消費借貸者，謂當事人一方移轉金錢或其他代替物之所有\n    權於他方，而約定他方以種類、品質、數量相同之物返還之\n    契約，民法第474條第1項定有明文；又按保證債務之所謂連\n    帶，係指保證人與主債務人負同一債務，對於債權人各負全\n    部給付之責任者而言，此就民法第272條第1項規定連帶債務\n    之文義參照觀之甚明，最高法院45年台上字第1426號著有判\n    例可資參照。本件被告訊音公司既為系爭債務之債務人，被\n    告戊○○、甲○○、丁○○、己○、庚○○、辛○○為其連\n    帶保證人，自應就其保證債務負全部給付之責。從而，原告\n    依消費借貸及連帶保證之法律關係，請求被告連帶給付如主\n    文第1項所示之金額，即無不合，應予准許。\n五、被告庚○○陳明願供擔保請准宣告免為假執行，惟原告並未\n    聲請假執行，被告之聲請核無必要，併此敘明。\n六、據上論結，本件原告之訴為有理由，依民事訴訟法第385條\n    第1項前段、第85條第2項，判決如主文。",
    "reason": "一、程序方面：\n(一)、按訴狀送達後，原告不得將原訴變更或追加他訴，但擴張或\n    減縮應受判決事項之聲明者，不在此限，民事訴訟法第255\n    條第1項第3款定有明文。查本件原告起訴時原係請求被告應\n    連帶給付原告1,651,330元，及自94年1月21日起至清償日止\n    ，按年息百分之6.78計算之利息，暨自94年2月22日起至清\n    償日止，逾期6個月以內者，按上開利率百分之10，超過6\n    個月者，按上開利率百分之20計算之違約金，嗣將請求之聲\n    明減縮為如主文第1項所示，核係屬減縮應受判決事項之聲\n    明，自應准許。\n(二)、本件被告等均經合法通知，均未於最後言詞辯論期日到場，\n    核無民事訴訟法第386條各款所列情形，爰依原告之聲請，\n    由其一造辯論而為判決。\n二、原告主張：被告訊音有限公司（下稱訊音公司）於民國（下\n    同）92年4月15日，邀同被告戊○○、甲○○、丁○○、己\n    ○、庚○○、辛○○為連帶保證人，與原告簽訂借據，借款\n    新臺幣（下同）4,000,000元，借款期間自92年4月15日起至\n    95年4月15日止，共分36期，按期平均攤還，借款利率按原\n    告銀行基準利率加3.95％計算，並於每年1月、4月、7月及\n    10月21日依原告銀行基準利率變動而調整，並自調整日起，\n    按調整後之年利率計算。倘逾期償付本息時，除按約定利率\n    支付遲延利息外，逾期6個月以內者，按上開利率百分之10\n    ，逾期6個月以上者，按上開利率百分之20計付違約金。詎\n    被告訊音公司公司自94年1月21日起即未依約繳款，尚欠本\n    金1,651,330元，依約定書第5條之約定，全部債務視為到期\n    ，應將所欠款項全數清償，然屢經催討仍置之不理，而被告\n    戊○○、甲○○、丁○○、己○、庚○○、辛○○既為連帶\n    保證人，依法應負連帶清償責任，為此爰依消費借貸及連帶\n    保證之法律關係提起本件訴訟，請求被告連帶給付如主文第\n    1項所示之金額、利息及違約金等語。\n三、被告方面：\n(一)、被告訊音公司、戊○○、甲○○、丁○○、己○、辛○○均\n    經合法通知，未於言詞辯論期日到場，亦未提出書狀作何聲\n    明或陳述。\n(二)、被告庚○○據其先前陳述，其願與原告詳談還款方式，並聲\n    明：原告之訴駁回；如受不利之判決，願供擔保，請准宣告\n    免為假執行。\n四、得心證之理由：\n(一)、原告主張之前揭事實，業據其提出約定書7份、借據、保證\n    書、現放各筆餘額查詢、往來明細資料查詢、計息明細資料\n    查詢各1份為證，核與其所述相符，被告訊音公司、戊○○\n    、甲○○、丁○○、己○、辛○○迄未到場爭執，亦未提出\n    任何有利於己之聲明、陳述或證據，以供本院審酌，而被告\n    庚○○則不爭執原告主張之金額，僅表明願與原告談還款方\n    式，則本院依調查證據之結果及斟酌全辯論意旨，自堪信原\n    告之主張為真實。\n(二)、按消費借貸者，謂當事人一方移轉金錢或其他代替物之所有\n    權於他方，而約定他方以種類、品質、數量相同之物返還之\n    契約，民法第474條第1項定有明文；又按保證債務之所謂連\n    帶，係指保證人與主債務人負同一債務，對於債權人各負全\n    部給付之責任者而言，此就民法第272條第1項規定連帶債務\n    之文義參照觀之甚明，最高法院45年台上字第1426號著有判\n    例可資參照。本件被告訊音公司既為系爭債務之債務人，被\n    告戊○○、甲○○、丁○○、己○、庚○○、辛○○為其連\n    帶保證人，自應就其保證債務負全部給付之責。從而，原告\n    依消費借貸及連帶保證之法律關係，請求被告連帶給付如主\n    文第1項所示之金額，即無不合，應予准許。\n五、被告庚○○陳明願供擔保請准宣告免為假執行，惟原告並未\n    聲請假執行，被告之聲請核無必要，併此敘明。\n六、據上論結，本件原告之訴為有理由，依民事訴訟法第385條\n    第1項前段、第85條第2項，判決如主文。"
  },
  "search": "臺灣新竹地方法院民事判決94年度訴字第326號原告華僑商業銀行股份有限公司法定代理人丙○○訴訟代理人乙○○被告訊音有限公司兼法定代理戊○○人被告甲○○丁○○799.己○庚○○辛○○上列當事人間返還消費借貸款事件，本院於民國94年12月22日辯論終結，判決如下：主文被告應連帶給付原告新臺幣壹佰陸拾伍萬壹仟佰拾元，及自民國九十四年二月十五日起至清償日止，按年息百分之六點七八計算之利息，暨自民國九十四年三月十六日起至清償日止，逾期六個月以內者，按上開利率百分之十，超過六個月者，按上開利率百分之二十計算之違約金。訴訟費用由被告連帶負擔。事實及理由一、程序方面：(一)、按訴狀送達後，原告不得將原訴變更或追加他訴，但擴張或減縮應受判決事項之聲明者，不在此限，民事訴訟法第255條第1項第3款定有明文。查本件原告起訴時原係請求被告應連帶給付原告1,651,330元，及自94年1月21日起至清償日止，按年息百分之6.78計算之利息，暨自94年2月22日起至清償日止，逾期6個月以內者，按上開利率百分之10，超過6個月者，按上開利率百分之20計算之違約金，嗣將請求之聲明減縮為如主文第1項所示，核係屬減縮應受判決事項之聲明，自應准許。(二)、本件被告等均經合法通知，均未於最後言詞辯論期日到場，核無民事訴訟法第386條各款所列情形，爰依原告之聲請，由其一造辯論而為判決。二、原告主張：被告訊音有限公司（下稱訊音公司）於民國（下同）92年4月15日，邀同被告戊○○、甲○○、丁○○、己○、庚○○、辛○○為連帶保證人，與原告簽訂借據，借款新臺幣（下同）4,000,000元，借款期間自92年4月15日起至95年4月15日止，共分36期，按期平均攤還，借款利率按原告銀行基準利率加3.95％計算，並於每年1月、4月、7月及10月21日依原告銀行基準利率變動而調整，並自調整日起，按調整後之年利率計算。倘逾期償付本息時，除按約定利率支付遲延利息外，逾期6個月以內者，按上開利率百分之10，逾期6個月以上者，按上開利率百分之20計付違約金。詎被告訊音公司公司自94年1月21日起即未依約繳款，尚欠本金1,651,330元，依約定書第5條之約定，全部債務視為到期，應將所欠款項全數清償，然屢經催討仍置之不理，而被告戊○○、甲○○、丁○○、己○、庚○○、辛○○既為連帶保證人，依法應負連帶清償責任，為此爰依消費借貸及連帶保證之法律關係提起本件訴訟，請求被告連帶給付如主文第1項所示之金額、利息及違約金等語。三、被告方面：(一)、被告訊音公司、戊○○、甲○○、丁○○、己○、辛○○均經合法通知，未於言詞辯論期日到場，亦未提出書狀作何聲明或陳述。(二)、被告庚○○據其先前陳述，其願與原告詳談還款方式，並聲明：原告之訴駁回；如受不利之判決，願供擔保，請准宣告免為假執行。四、得心證之理由：(一)、原告主張之前揭事實，業據其提出約定書7份、借據、保證書、現放各筆餘額查詢、往來明細資料查詢、計息明細資料查詢各1份為證，核與其所述相符，被告訊音公司、戊○○、甲○○、丁○○、己○、辛○○迄未到場爭執，亦未提出任何有利於己之聲明、陳述或證據，以供本院審酌，而被告庚○○則不爭執原告主張之金額，僅表明願與原告談還款方式，則本院依調查證據之結果及斟酌全辯論意旨，自堪信原告之主張為真實。(二)、按消費借貸者，謂當事人一方移轉金錢或其他代替物之所有權於他方，而約定他方以種類、品質、數量相同之物返還之契約，民法第474條第1項定有明文；又按保證債務之所謂連帶，係指保證人與主債務人負同一債務，對於債權人各負全部給付之責任者而言，此就民法第272條第1項規定連帶債務之文義參照觀之甚明，最高法院45年台上字第1426號著有判例可資參照。本件被告訊音公司既為系爭債務之債務人，被告戊○○、甲○○、丁○○、己○、庚○○、辛○○為其連帶保證人，自應就其保證債務負全部給付之責。從而，原告依消費借貸及連帶保證之法律關係，請求被告連帶給付如主文第1項所示之金額，即無不合，應予准許。五、被告庚○○陳明願供擔保請准宣告免為假執行，惟原告並未聲請假執行，被告之聲請核無必要，併此敘明。六、據上論結，本件原告之訴為有理由，依民事訴訟法第385條第1項前段、第85條第2項，判決如主文。中華民國94年12月30日民事第一庭法官黃珮禎以上正本係照原本作成。如對本判決上訴，須於判決送達後20日內向本院提出上訴狀。中華民國94年12月30日書記官黎秀娟",
  "characters": {
    "judges": [
      "黃珮禎"
    ],
    "prosecutors": [

    ],
    "lawyers": [

    ],
    "clerks": [
      "黎秀娟"
    ],
    "plaintiffs": [
      "華僑商業銀行股份有限公司"
    ],
    "defendants": [
      "訊音有限公司",
      "兼法定代理  戊○○",
      "甲○○"
    ],
    "prosecutor_office": [

    ],
    "creditors": [

    ],
    "debtors": [

    ],
    "judicial_associate_officer": [

    ]
  },
  "adjudged_at": "2005-12-30",
  "created_at": "2016-02-07 04:00:03",
  "updated_at": "2016-02-07 04:00:03"
}