{
  "identify": "TND-94-簡-2998-20051230-1",
  "court": {
    "name": "臺灣南投地方法院",
    "code": "TND"
  },
  "division": {
    "name": "刑事",
    "code": "M"
  },
  "year": 94,
  "word": "簡",
  "number": "2998",
  "jcheck": "1",
  "reason": "偽造文書等",
  "content": "臺灣臺南地方法院刑事簡易判決          94年度簡字第2998號\n聲  請  人  臺灣臺南地方法院檢察署檢察官\n被      告  甲○○\n                      樓\n上列被告因偽造文書等案件，經檢察官聲請以簡易判決處刑（94\n年度發查偵字第428號），本院判決如下：\n    主  文\n甲○○連續行使偽造私文書，足以生損害於他人，處有期徒刑\n月，如易科罰金，以佰元折算壹日。緩刑年。\n如附表所示偽造之署押共肆枚均沒收。\n    事實及理由\n一、本件犯罪事實及證據均引用檢察官聲請簡易判決處刑書之記\n    載（如附件）。\n二、依刑事訴訟法第449條第1項、第450條第1項、454條第2項，\n    刑法第56條、第216條、第210項、第339條第1項、第55條、\n    第41條第1項前段、第74條第1款、第219條，罰金罰鍰提高\n    標準條例第1條前段、第2條，逕以簡易判決處刑如主文。\n三、如不服本件判決，得自收受送達之日起10日內，向本院提起\n    上訴。\n中    華    民    國    94    年    12    月    30    日\n                  刑事第四庭    法  官  陳欽賢\n以上正本證明與原本無異。\n                                書記官  陳麗雅\n中    華    民    國    94    年    12    月    30    日\n附錄本案論罪科刑法條：\n中華民國刑法第216條\n(行使偽造變造或登載不實之文書罪)\n行使第 210 條至第 215 條之文書者，依偽造、變造文書或登載\n不實事項或使登載不實事項之規定處斷。\n中華民國刑法第210條\n(偽造變造私文書罪)\n偽造、變造私文書，足以生損害於公眾或他人者，處 5 年以下\n有期徒刑。\n附表：\n┌─┬────────────────┬─────┬─────┐\n│編│    文（物）  件  名  稱        │沒收之署押│備註      │\n│號│                                │          │          │\n├─┼────────────────┼─────┼─────┤\n│1.│誠泰銀行信用卡申請書            │戴林麗珠簽│          │\n│  │                                │名1枚。   │          │\n│  │                                │          │          │\n├─┼────────────────┼─────┼─────┤\n│2.│92年7月8日簽帳單                │戴林麗珠簽│          │\n│  │（新台幣24,900元）              │名1枚。   │          │\n│  │                                │          │          │\n├─┼────────────────┼─────┼─────┤\n│3.│94年7月10日簽帳單               │戴林麗珠簽│          │\n│  │（新台幣24,149元）              │名1枚。   │          │\n│  │                                │          │          │\n├─┼────────────────┼─────┼─────┤\n│4.│誠泰銀行0000000000000000信用卡背│戴林麗珠簽│信用卡未據│\n│  │面                              │名1枚。   │扣案      │\n│  │                                │          │          │\n└─┴────────────────┴─────┴─────┘\n",
  "structure": {
    "main": "甲○○連續行使偽造私文書，足以生損害於他人，處有期徒刑\n月，如易科罰金，以佰元折算壹日。緩刑年。\n如附表所示偽造之署押共肆枚均沒收。",
    "fact": "一、本件犯罪事實及證據均引用檢察官聲請簡易判決處刑書之記\n    載（如附件）。\n二、依刑事訴訟法第449條第1項、第450條第1項、454條第2項，\n    刑法第56條、第216條、第210項、第339條第1項、第55條、\n    第41條第1項前段、第74條第1款、第219條，罰金罰鍰提高\n    標準條例第1條前段、第2條，逕以簡易判決處刑如主文。\n三、如不服本件判決，得自收受送達之日起10日內，向本院提起\n    上訴。",
    "reason": "一、本件犯罪事實及證據均引用檢察官聲請簡易判決處刑書之記\n    載（如附件）。\n二、依刑事訴訟法第449條第1項、第450條第1項、454條第2項，\n    刑法第56條、第216條、第210項、第339條第1項、第55條、\n    第41條第1項前段、第74條第1款、第219條，罰金罰鍰提高\n    標準條例第1條前段、第2條，逕以簡易判決處刑如主文。\n三、如不服本件判決，得自收受送達之日起10日內，向本院提起\n    上訴。"
  },
  "search": "臺灣臺南地方法院刑事簡易判決94年度簡字第2998號聲請人臺灣臺南地方法院檢察署檢察官被告甲○○樓上列被告因偽造文書等案件，經檢察官聲請以簡易判決處刑（94年度發查偵字第428號），本院判決如下：主文甲○○連續行使偽造私文書，足以生損害於他人，處有期徒刑月，如易科罰金，以佰元折算壹日。緩刑年。如附表所示偽造之署押共肆枚均沒收。事實及理由一、本件犯罪事實及證據均引用檢察官聲請簡易判決處刑書之記載（如附件）。二、依刑事訴訟法第449條第1項、第450條第1項、454條第2項，刑法第56條、第216條、第210項、第339條第1項、第55條、第41條第1項前段、第74條第1款、第219條，罰金罰鍰提高標準條例第1條前段、第2條，逕以簡易判決處刑如主文。三、如不服本件判決，得自收受送達之日起10日內，向本院提起上訴。中華民國94年12月30日刑事第四庭法官陳欽賢以上正本證明與原本無異。書記官陳麗雅中華民國94年12月30日附錄本案論罪科刑法條：中華民國刑法第216條(行使偽造變造或登載不實之文書罪)行使第210條至第215條之文書者，依偽造、變造文書或登載不實事項或使登載不實事項之規定處斷。中華民國刑法第210條(偽造變造私文書罪)偽造、變造私文書，足以生損害於公眾或他人者，處5年以下有期徒刑。附表：┌─┬────────────────┬─────┬─────┐│編│文（物）件名稱│沒收之署押│備註││號││││├─┼────────────────┼─────┼─────┤│1.│誠泰銀行信用卡申請書│戴林麗珠簽│││││名1枚。│││││││├─┼────────────────┼─────┼─────┤│2.│92年7月8日簽帳單│戴林麗珠簽││││（新台幣24,900元）│名1枚。│││││││├─┼────────────────┼─────┼─────┤│3.│94年7月10日簽帳單│戴林麗珠簽││││（新台幣24,149元）│名1枚。│││││││├─┼────────────────┼─────┼─────┤│4.│誠泰銀行0000000000000000信用卡背│戴林麗珠簽│信用卡未據│││面│名1枚。│扣案││││││└─┴────────────────┴─────┴─────┘",
  "characters": {
    "judges": [
      "陳欽賢"
    ],
    "prosecutors": [

    ],
    "lawyers": [

    ],
    "clerks": [
      "陳麗雅"
    ],
    "plaintiffs": [

    ],
    "defendants": [
      "甲○○"
    ],
    "prosecutor_office": [
      "臺灣臺南地方法院檢察署檢察官"
    ],
    "creditors": [

    ],
    "debtors": [

    ],
    "judicial_associate_officer": [

    ]
  },
  "adjudged_at": "2005-12-30",
  "created_at": "2016-02-07 04:27:40",
  "updated_at": "2016-02-07 04:27:40"
}