{
  "identify": "TPD-94-訴-6795-20051230-1",
  "court": {
    "name": "臺灣臺北地方法院",
    "code": "TPD"
  },
  "division": {
    "name": "民事",
    "code": "V"
  },
  "year": 94,
  "word": "訴",
  "number": "6795",
  "jcheck": "1",
  "reason": "清償借款",
  "content": "臺灣臺北地方法院民事判決              94年度訴字第6795號\n原      告  中國信託商業銀行股份有限公司\n法定代理人  乙○○\n訴訟代理人  庚○○\n被      告  太瑞行旅行社股份有限公司\n法定代理人  丙○○\n            戊○○\n            丁○○\n被      告  甲○○\n            丁○○\n            己○○\n上列當事人間請求清償借款事件，本院於民國94年12月26日言詞\n辯論終結，判決如下：\n    主      文\n被告應連帶給付原告新台幣玖拾貳萬壹仟柒佰貳拾參元，及自民\n國94年9月29日起至清償日止，按年息13%計算之利息，並自民國\n94年10月30日起至清償日止，逾期在6個月以內者，按上開利率\n10%，逾期超過6個月者，按上開利率20% 計算之違約金。\n訴訟費用由被告連帶負擔。\n    事實及理由\n一、按當事人得以合意定第一審管轄法院，民事訴訟法第24條第\n    1 項前段定有明文。查，兩造既已於借據約定書第 6 條約\n    定，同意以本院為第一審管轄法院（見本院卷第7頁），則\n    本院就本件訴訟自有管轄權，合先陳明。\n二、查，被告太瑞行旅行社股份有限公司（下稱太瑞行旅行社）\n    於民國94年10月10日經主管機關准予解散，且未依章程或股\n    東會另行選任清算人情，有卷附公司變更登記表、本院審理\n    查詢單可參（見本院卷第1頁、第25至28頁），故依據公司\n    法第322條第1項前段規定，自應以該公司董事（並以公司登\n    記表登記為準據）即丁○○、丙○○、戊○○等3人為該公\n    司之清算人，合先陳明。\n三、又太瑞行旅行社雖僅有董事丙○○一人到庭，為其到庭所為\n    訴訟行為係屬有利於該公司行為，爰依民事訴訟法第56條第\n    1款規定，自應視為該公司業已合法到庭，併予敘明。\n四、本件被告丁○○經合法通知後，未於言詞辯論期日到場，核\n    無民事訴訟法第386條所列各款情形，應依原告之聲請，准\n    由其一造辯論而為判決。\n五、原告主張：(一)太瑞行旅行社於94年7月28日向伊借款新台幣(\n    下同)1,000,000 元，並邀被告丁○○、甲○○、己○○為\n    連帶保證人，並約定自94年7月29日起至95年7月29日止分期\n    清償，利息按年息13%並採固定利率計算，遲延履行給付本\n    息時，即喪失期限利益，視為全部到期，且除仍按上開利率\n    計息外，其逾期在6個月以內者，按上開利率10%，逾期超過\n    6個月者，按上開利率20%計算之違約金。詎太瑞行旅行社自\n    94年9月29日起，即未依約履行債務，依約即已喪失期限利\n    益，上列借款應視為全部到期。目前仍積欠伊本金921,723\n    元、及自94年9月29日起算之利息、違約金。爰依借款契約\n    及連帶保證契約之法律關係，提起本訴等情。並於本院聲明\n    ：如主文第1項所示。\n六、甲○○、己○○及太瑞行旅行社法定代理人丙○○則以：伊\n    等並未處理太瑞行旅行社業務，係由丁○○處理，不清楚該\n    公司財務狀況等語，資為抗辯。並於本院聲明：原告之訴駁\n    回。\n七、經查，原告主張上列之事實，業據提出借據、授信額度動用\n    確認書、事前徵信查詢彙總資料、事前徵信查詢放款貸放明\n    細資料查詢、放款歷史交易查詢等件為證（見本院卷第6頁\n    至15頁、第69頁至73頁），甲○○、己○○易自陳為系爭借\n    款之連帶保證人乙事（見本院卷第67頁反面），且丁○○經\n    合法通知後（見本院卷第57頁），亦未提出任何書狀爭執，\n    視同自認（民事訴訟法第280條第3項準用第1項規定參照）\n    ，故原告主張之事實，堪信為真。從而，原告依借款契約及\n    連帶保證契約之法律關係，訴請被告應連帶給付如主文第1\n    項所示，為有理由，應予准許。\n八、據上論結，本件原告之訴為有理由，依民事訴訟法第385條\n    第1項前段、第85條第2項，判決如主文。\n中    華    民    國    94    年    12    月    30    日\n                  民事第一庭    法  官  楊絮雲\n以上正本係照原本作成\n如對本判決上訴，須於判決送達後20日內向本院提出上訴狀\n中    華    民    國    94    年    12    月    30    日\n                                書記官  高秋芬\n",
  "structure": {
    "main": "被告應連帶給付原告新台幣玖拾貳萬壹仟柒佰貳拾參元，及自民\n國94年9月29日起至清償日止，按年息13%計算之利息，並自民國\n94年10月30日起至清償日止，逾期在6個月以內者，按上開利率\n10%，逾期超過6個月者，按上開利率20% 計算之違約金。\n訴訟費用由被告連帶負擔。",
    "fact": "一、按當事人得以合意定第一審管轄法院，民事訴訟法第24條第\n    1 項前段定有明文。查，兩造既已於借據約定書第 6 條約\n    定，同意以本院為第一審管轄法院（見本院卷第7頁），則\n    本院就本件訴訟自有管轄權，合先陳明。\n二、查，被告太瑞行旅行社股份有限公司（下稱太瑞行旅行社）\n    於民國94年10月10日經主管機關准予解散，且未依章程或股\n    東會另行選任清算人情，有卷附公司變更登記表、本院審理\n    查詢單可參（見本院卷第1頁、第25至28頁），故依據公司\n    法第322條第1項前段規定，自應以該公司董事（並以公司登\n    記表登記為準據）即丁○○、丙○○、戊○○等3人為該公\n    司之清算人，合先陳明。\n三、又太瑞行旅行社雖僅有董事丙○○一人到庭，為其到庭所為\n    訴訟行為係屬有利於該公司行為，爰依民事訴訟法第56條第\n    1款規定，自應視為該公司業已合法到庭，併予敘明。\n四、本件被告丁○○經合法通知後，未於言詞辯論期日到場，核\n    無民事訴訟法第386條所列各款情形，應依原告之聲請，准\n    由其一造辯論而為判決。\n五、原告主張：(一)太瑞行旅行社於94年7月28日向伊借款新台幣(\n    下同)1,000,000 元，並邀被告丁○○、甲○○、己○○為\n    連帶保證人，並約定自94年7月29日起至95年7月29日止分期\n    清償，利息按年息13%並採固定利率計算，遲延履行給付本\n    息時，即喪失期限利益，視為全部到期，且除仍按上開利率\n    計息外，其逾期在6個月以內者，按上開利率10%，逾期超過\n    6個月者，按上開利率20%計算之違約金。詎太瑞行旅行社自\n    94年9月29日起，即未依約履行債務，依約即已喪失期限利\n    益，上列借款應視為全部到期。目前仍積欠伊本金921,723\n    元、及自94年9月29日起算之利息、違約金。爰依借款契約\n    及連帶保證契約之法律關係，提起本訴等情。並於本院聲明\n    ：如主文第1項所示。\n六、甲○○、己○○及太瑞行旅行社法定代理人丙○○則以：伊\n    等並未處理太瑞行旅行社業務，係由丁○○處理，不清楚該\n    公司財務狀況等語，資為抗辯。並於本院聲明：原告之訴駁\n    回。\n七、經查，原告主張上列之事實，業據提出借據、授信額度動用\n    確認書、事前徵信查詢彙總資料、事前徵信查詢放款貸放明\n    細資料查詢、放款歷史交易查詢等件為證（見本院卷第6頁\n    至15頁、第69頁至73頁），甲○○、己○○易自陳為系爭借\n    款之連帶保證人乙事（見本院卷第67頁反面），且丁○○經\n    合法通知後（見本院卷第57頁），亦未提出任何書狀爭執，\n    視同自認（民事訴訟法第280條第3項準用第1項規定參照）\n    ，故原告主張之事實，堪信為真。從而，原告依借款契約及\n    連帶保證契約之法律關係，訴請被告應連帶給付如主文第1\n    項所示，為有理由，應予准許。\n八、據上論結，本件原告之訴為有理由，依民事訴訟法第385條\n    第1項前段、第85條第2項，判決如主文。",
    "reason": "一、按當事人得以合意定第一審管轄法院，民事訴訟法第24條第\n    1 項前段定有明文。查，兩造既已於借據約定書第 6 條約\n    定，同意以本院為第一審管轄法院（見本院卷第7頁），則\n    本院就本件訴訟自有管轄權，合先陳明。\n二、查，被告太瑞行旅行社股份有限公司（下稱太瑞行旅行社）\n    於民國94年10月10日經主管機關准予解散，且未依章程或股\n    東會另行選任清算人情，有卷附公司變更登記表、本院審理\n    查詢單可參（見本院卷第1頁、第25至28頁），故依據公司\n    法第322條第1項前段規定，自應以該公司董事（並以公司登\n    記表登記為準據）即丁○○、丙○○、戊○○等3人為該公\n    司之清算人，合先陳明。\n三、又太瑞行旅行社雖僅有董事丙○○一人到庭，為其到庭所為\n    訴訟行為係屬有利於該公司行為，爰依民事訴訟法第56條第\n    1款規定，自應視為該公司業已合法到庭，併予敘明。\n四、本件被告丁○○經合法通知後，未於言詞辯論期日到場，核\n    無民事訴訟法第386條所列各款情形，應依原告之聲請，准\n    由其一造辯論而為判決。\n五、原告主張：(一)太瑞行旅行社於94年7月28日向伊借款新台幣(\n    下同)1,000,000 元，並邀被告丁○○、甲○○、己○○為\n    連帶保證人，並約定自94年7月29日起至95年7月29日止分期\n    清償，利息按年息13%並採固定利率計算，遲延履行給付本\n    息時，即喪失期限利益，視為全部到期，且除仍按上開利率\n    計息外，其逾期在6個月以內者，按上開利率10%，逾期超過\n    6個月者，按上開利率20%計算之違約金。詎太瑞行旅行社自\n    94年9月29日起，即未依約履行債務，依約即已喪失期限利\n    益，上列借款應視為全部到期。目前仍積欠伊本金921,723\n    元、及自94年9月29日起算之利息、違約金。爰依借款契約\n    及連帶保證契約之法律關係，提起本訴等情。並於本院聲明\n    ：如主文第1項所示。\n六、甲○○、己○○及太瑞行旅行社法定代理人丙○○則以：伊\n    等並未處理太瑞行旅行社業務，係由丁○○處理，不清楚該\n    公司財務狀況等語，資為抗辯。並於本院聲明：原告之訴駁\n    回。\n七、經查，原告主張上列之事實，業據提出借據、授信額度動用\n    確認書、事前徵信查詢彙總資料、事前徵信查詢放款貸放明\n    細資料查詢、放款歷史交易查詢等件為證（見本院卷第6頁\n    至15頁、第69頁至73頁），甲○○、己○○易自陳為系爭借\n    款之連帶保證人乙事（見本院卷第67頁反面），且丁○○經\n    合法通知後（見本院卷第57頁），亦未提出任何書狀爭執，\n    視同自認（民事訴訟法第280條第3項準用第1項規定參照）\n    ，故原告主張之事實，堪信為真。從而，原告依借款契約及\n    連帶保證契約之法律關係，訴請被告應連帶給付如主文第1\n    項所示，為有理由，應予准許。\n八、據上論結，本件原告之訴為有理由，依民事訴訟法第385條\n    第1項前段、第85條第2項，判決如主文。"
  },
  "search": "臺灣臺北地方法院民事判決94年度訴字第6795號原告中國信託商業銀行股份有限公司法定代理人乙○○訴訟代理人庚○○被告太瑞行旅行社股份有限公司法定代理人丙○○戊○○丁○○被告甲○○丁○○己○○上列當事人間請求清償借款事件，本院於民國94年12月26日言詞辯論終結，判決如下：主文被告應連帶給付原告新台幣玖拾貳萬壹仟柒佰貳拾參元，及自民國94年9月29日起至清償日止，按年息13%計算之利息，並自民國94年10月30日起至清償日止，逾期在6個月以內者，按上開利率10%，逾期超過6個月者，按上開利率20%計算之違約金。訴訟費用由被告連帶負擔。事實及理由一、按當事人得以合意定第一審管轄法院，民事訴訟法第24條第1項前段定有明文。查，兩造既已於借據約定書第6條約定，同意以本院為第一審管轄法院（見本院卷第7頁），則本院就本件訴訟自有管轄權，合先陳明。二、查，被告太瑞行旅行社股份有限公司（下稱太瑞行旅行社）於民國94年10月10日經主管機關准予解散，且未依章程或股東會另行選任清算人情，有卷附公司變更登記表、本院審理查詢單可參（見本院卷第1頁、第25至28頁），故依據公司法第322條第1項前段規定，自應以該公司董事（並以公司登記表登記為準據）即丁○○、丙○○、戊○○等3人為該公司之清算人，合先陳明。三、又太瑞行旅行社雖僅有董事丙○○一人到庭，為其到庭所為訴訟行為係屬有利於該公司行為，爰依民事訴訟法第56條第1款規定，自應視為該公司業已合法到庭，併予敘明。四、本件被告丁○○經合法通知後，未於言詞辯論期日到場，核無民事訴訟法第386條所列各款情形，應依原告之聲請，准由其一造辯論而為判決。五、原告主張：(一)太瑞行旅行社於94年7月28日向伊借款新台幣(下同)1,000,000元，並邀被告丁○○、甲○○、己○○為連帶保證人，並約定自94年7月29日起至95年7月29日止分期清償，利息按年息13%並採固定利率計算，遲延履行給付本息時，即喪失期限利益，視為全部到期，且除仍按上開利率計息外，其逾期在6個月以內者，按上開利率10%，逾期超過6個月者，按上開利率20%計算之違約金。詎太瑞行旅行社自94年9月29日起，即未依約履行債務，依約即已喪失期限利益，上列借款應視為全部到期。目前仍積欠伊本金921,723元、及自94年9月29日起算之利息、違約金。爰依借款契約及連帶保證契約之法律關係，提起本訴等情。並於本院聲明：如主文第1項所示。六、甲○○、己○○及太瑞行旅行社法定代理人丙○○則以：伊等並未處理太瑞行旅行社業務，係由丁○○處理，不清楚該公司財務狀況等語，資為抗辯。並於本院聲明：原告之訴駁回。七、經查，原告主張上列之事實，業據提出借據、授信額度動用確認書、事前徵信查詢彙總資料、事前徵信查詢放款貸放明細資料查詢、放款歷史交易查詢等件為證（見本院卷第6頁至15頁、第69頁至73頁），甲○○、己○○易自陳為系爭借款之連帶保證人乙事（見本院卷第67頁反面），且丁○○經合法通知後（見本院卷第57頁），亦未提出任何書狀爭執，視同自認（民事訴訟法第280條第3項準用第1項規定參照），故原告主張之事實，堪信為真。從而，原告依借款契約及連帶保證契約之法律關係，訴請被告應連帶給付如主文第1項所示，為有理由，應予准許。八、據上論結，本件原告之訴為有理由，依民事訴訟法第385條第1項前段、第85條第2項，判決如主文。中華民國94年12月30日民事第一庭法官楊絮雲以上正本係照原本作成如對本判決上訴，須於判決送達後20日內向本院提出上訴狀中華民國94年12月30日書記官高秋芬",
  "characters": {
    "judges": [
      "楊絮雲"
    ],
    "prosecutors": [

    ],
    "lawyers": [

    ],
    "clerks": [
      "高秋芬"
    ],
    "plaintiffs": [
      "中國信託商業銀行股份有限公司"
    ],
    "defendants": [
      "太瑞行旅行社股份有限公司",
      "甲○○"
    ],
    "prosecutor_office": [

    ],
    "creditors": [

    ],
    "debtors": [

    ],
    "judicial_associate_officer": [

    ]
  },
  "adjudged_at": "2005-12-30",
  "created_at": "2016-02-07 04:26:59",
  "updated_at": "2016-02-07 04:26:59"
}