{
  "identify": "TPD-100-訴-979-20111018-1",
  "court": {
    "name": "臺灣臺北地方法院",
    "code": "TPD"
  },
  "division": {
    "name": "刑事",
    "code": "M"
  },
  "year": 100,
  "word": "訴",
  "number": "979",
  "jcheck": "1",
  "reason": "偽造文書",
  "content": "臺灣臺北地方法院刑事判決              100年度訴字第979號\n公  訴  人  臺灣臺北地方法院檢察署檢察官\n被      告  黃千容\n上列被告因偽造文書案件，經檢察官聲請簡易判決處刑（100 年\n度偵緝字第1064號），本院認不宜依簡易判決處刑（100 年度簡\n字第2970號），改依通常程序，被告於準備程序中就犯罪事實為\n有罪之陳述，本院改行簡式審判程序，由受命法官獨任審理，判\n決如下：\n    主  文\n黃千容犯行使偽造私文書罪，處有期徒刑貳月，如易科罰金，以\n新臺幣壹仟元折算壹日；緩刑貳年，緩刑期內付保護管束。臺北\n市政府警察局北市警交字第ＡＥＸ二七九三九三號舉發違反道路\n交通管理事件通知單移送聯及存根聯上收受通知聯者簽章欄內偽\n造之「蔡宜臻」署押各壹枚均沒收。\n    事  實\n一、黃千容於民國97年12月14日中午12時50分許，騎乘車牌號碼\n    921-BGY 號重型機車，行經臺北市○○區○○路與襄陽路口\n    ，因騎乘機車不依規定二段式左轉，經臺北市政府警察局中\n    正第一分局警備隊警員施明宏攔停舉發時，為免除上開違規\n    罰緩，竟於警當場開立臺北市政府警察局北市警交字第AEX2\n    79393 號舉發違反道路交通管理事件通知單（下稱舉發通知\n    單）時，冒用「蔡宜臻」之名義，基於偽造署押進而行使偽\n    造私文書之犯意，在該通知單上之收受通知聯者簽章欄內偽\n    簽「蔡宜臻」之署押1 枚（1 式3 聯，分別為第1 聯通知聯\n    、第2 聯移送聯、第3 聯存根聯，黃千容在第2 聯移送聯上\n    偽造署押複寫至第3 聯存根聯上），表示蔡宜臻本人出具領\n    收該通知單之證明而交付警員，足以生損害於蔡宜臻及警察\n    機關對道路交通管理之正確性。嗣經蔡宜臻收受交通部公路\n    總局嘉義區監理所嘉義市監理站關於上開交通違規事項通知\n    ，進而報警處理，始悉上情。\n二、案經蔡宜臻訴由臺北市政府警察局中正第一分局報告臺灣臺\n    北地方法院檢察署檢察官偵查聲請簡易判決處刑。\n    理  由\n一、按刑事訴訟法第273 條之1 第1 項規定除被告所犯為死刑、\n    無期徒刑、最輕本刑為3 年以上有期徒刑之罪、或高等法院\n    管轄第一審案件者外，於審判期日前之程序進行中，被告先\n    就被訴事實為有罪之陳述時，審判長得告知被告簡式審判程\n    序之旨，並聽取當事人、代理人、辯護人及輔佐人之意見後\n    ，裁定進行簡式審判程序。經查，本件被告黃千容被訴偽造\n    文書一案，為前開不得進行簡式審判程序以外之案件，且被\n    告於本院行準備程序時就被訴事實為有罪之陳述，本院告知\n    被告簡式審判程序之旨，並聽取被告及檢察官之意見後，爰\n    依刑事訴訟法第273 條之1 第1 項之規定，當庭裁定改依簡\n    式審判程序進行審判，合先敘明。\n二、前揭事實，業據被告於本院準備程序及審理時坦承不諱（見\n    本院卷第14頁、第16頁反面），並經告訴人蔡宜臻陳述在卷\n    ，且有卷附舉發通知單影本1 紙（見99年度偵字第24806 號\n    卷第6 頁）可稽。從而，堪認被告之自白核與事實相符，自\n    得採為論罪之依據。本件事證明確，被告犯行洵堪認定，應\n    依法論科。\n三、按舉發通知單「收受通知聯者簽章」欄內偽簽他人姓名，自\n    不待依據習慣或特約，單從形式上觀察，即足以知悉係表示\n    由該他人名義出具領收通知聯之證明，此與事先在印妥內容\n    之收據上偽簽他人姓名之情形，無分軒輊，當然屬於刑法第\n    210 條所稱之私文書（最高法院83年台上字第6631號判例參\n    照）。核被告所為，係犯刑法第216 條、第210 條之行使偽\n    造私文書罪。被告偽造「蔡宜臻」署押之行為，為偽造私文\n    書之部分行為，又偽造私文書之低度行為，應為行使偽造私\n    文書之高度行為所吸收，均不另論罪。爰審酌被告並無前科\n    ，有上開被告前案紀錄表在卷可查，目前在學而缺乏社會經\n    驗及歷練，為卸免交通違規罰鍰之責，冒用他人名義簽署上\n    揭舉發通知單進而行使之犯罪動機，於本院審理中坦承犯行\n    ，犯罪後態度尚可等一切情狀，量處如主文所示之刑，併諭\n    知易科罰金之折算標準，以示儆懲。末查被告前未曾受有期\n    徒刑以上刑之宣告，其經此偵審過程，自當知所警惕而無虞\n    再犯，本院綜核各情認上開刑之宣告，已足策其悔悟，因認\n    所宣告之刑，以暫不執行為適當，併諭知緩刑2 年，以啟自\n    新。惟被告騎乘機車違反交通規則，遭警開單舉發，為免課\n    受罰鍰，竟以他人名義簽署於舉發通知單上，致生損害於告\n    訴人及警察機關道路交通管理之正確性，顯對法律未有適當\n    之認識，為使之具備正確之法律觀念並提供必要之協助及督\n    促，爰依法宣告緩刑期內付保護管束，俾由地方法院檢察署\n    之觀護人予以適當之督促，並發揮緩刑制度之立意及避免短\n    期自由刑執行肇致之弊端。\n四、至舉發通知單移送聯及存根聯，既經被告持以行使，顯非屬\n    被告所有之物，然其上偽造「蔡宜臻」之署押各1 枚，應依\n    刑法第219 條之規定，不問屬於犯人與否，均宣告沒收之，\n    附此敘明。\n據上論斷，應依刑事訴訟法第452 條、第273 條之1 第1 項、第\n299 條第1 項前段，刑法第216 條、第210 條、第219 條、第41\n條第1 項前段、第74條第1 項第1 款、第93條第1 項，判決如主\n文。\n本案經檢察官蘇維達到庭執行職務\n中    華    民    國    100   年    10    月    18    日\n                  刑事第六庭  法  官  黃傅偉\n以上正本證明與原本無異。\n如不服本判決應於收受送達後10日內向本院提出上訴書狀，並應\n敘述具體理由；其未敘述上訴理由者，應於上訴期間屆滿後20日\n內向本院補提理由書（均須按他造當事人之人數附繕本）「切勿\n逕送上級法院」。告訴人或被害人如對於本判決不服者，應具備\n理由請求檢察官上訴，其上訴期間之計算係以檢察官收受判決正\n本之日期為準。\n                              書記官  劉子豪\n中    華    民    國   100    年    10    月    18    日\n附錄本案論罪法條全文\n中華民國刑法第210條\n（偽造變造私文書罪）\n偽造、變造私文書，足以生損害於公眾或他人者，處5 年以下有\n期徒刑。\n中華民國刑法第216條\n（行使偽造變造或登載不實之文書罪）\n行使第210 條至第215 條之文書者，依偽造、變造文書或登載不\n實事項或使登載不實事項之規定處斷。",
  "structure": {
    "main": "黃千容犯行使偽造私文書罪，處有期徒刑貳月，如易科罰金，以\n新臺幣壹仟元折算壹日；緩刑貳年，緩刑期內付保護管束。臺北\n市政府警察局北市警交字第ＡＥＸ二七九三九三號舉發違反道路\n交通管理事件通知單移送聯及存根聯上收受通知聯者簽章欄內偽\n造之「蔡宜臻」署押各壹枚均沒收。",
    "fact": "一、黃千容於民國97年12月14日中午12時50分許，騎乘車牌號碼\n    921-BGY 號重型機車，行經臺北市○○區○○路與襄陽路口\n    ，因騎乘機車不依規定二段式左轉，經臺北市政府警察局中\n    正第一分局警備隊警員施明宏攔停舉發時，為免除上開違規\n    罰緩，竟於警當場開立臺北市政府警察局北市警交字第AEX2\n    79393 號舉發違反道路交通管理事件通知單（下稱舉發通知\n    單）時，冒用「蔡宜臻」之名義，基於偽造署押進而行使偽\n    造私文書之犯意，在該通知單上之收受通知聯者簽章欄內偽\n    簽「蔡宜臻」之署押1 枚（1 式3 聯，分別為第1 聯通知聯\n    、第2 聯移送聯、第3 聯存根聯，黃千容在第2 聯移送聯上\n    偽造署押複寫至第3 聯存根聯上），表示蔡宜臻本人出具領\n    收該通知單之證明而交付警員，足以生損害於蔡宜臻及警察\n    機關對道路交通管理之正確性。嗣經蔡宜臻收受交通部公路\n    總局嘉義區監理所嘉義市監理站關於上開交通違規事項通知\n    ，進而報警處理，始悉上情。\n二、案經蔡宜臻訴由臺北市政府警察局中正第一分局報告臺灣臺\n    北地方法院檢察署檢察官偵查聲請簡易判決處刑。",
    "reason": "一、按刑事訴訟法第273 條之1 第1 項規定除被告所犯為死刑、\n    無期徒刑、最輕本刑為3 年以上有期徒刑之罪、或高等法院\n    管轄第一審案件者外，於審判期日前之程序進行中，被告先\n    就被訴事實為有罪之陳述時，審判長得告知被告簡式審判程\n    序之旨，並聽取當事人、代理人、辯護人及輔佐人之意見後\n    ，裁定進行簡式審判程序。經查，本件被告黃千容被訴偽造\n    文書一案，為前開不得進行簡式審判程序以外之案件，且被\n    告於本院行準備程序時就被訴事實為有罪之陳述，本院告知\n    被告簡式審判程序之旨，並聽取被告及檢察官之意見後，爰\n    依刑事訴訟法第273 條之1 第1 項之規定，當庭裁定改依簡\n    式審判程序進行審判，合先敘明。\n二、前揭事實，業據被告於本院準備程序及審理時坦承不諱（見\n    本院卷第14頁、第16頁反面），並經告訴人蔡宜臻陳述在卷\n    ，且有卷附舉發通知單影本1 紙（見99年度偵字第24806 號\n    卷第6 頁）可稽。從而，堪認被告之自白核與事實相符，自\n    得採為論罪之依據。本件事證明確，被告犯行洵堪認定，應\n    依法論科。\n三、按舉發通知單「收受通知聯者簽章」欄內偽簽他人姓名，自\n    不待依據習慣或特約，單從形式上觀察，即足以知悉係表示\n    由該他人名義出具領收通知聯之證明，此與事先在印妥內容\n    之收據上偽簽他人姓名之情形，無分軒輊，當然屬於刑法第\n    210 條所稱之私文書（最高法院83年台上字第6631號判例參\n    照）。核被告所為，係犯刑法第216 條、第210 條之行使偽\n    造私文書罪。被告偽造「蔡宜臻」署押之行為，為偽造私文\n    書之部分行為，又偽造私文書之低度行為，應為行使偽造私\n    文書之高度行為所吸收，均不另論罪。爰審酌被告並無前科\n    ，有上開被告前案紀錄表在卷可查，目前在學而缺乏社會經\n    驗及歷練，為卸免交通違規罰鍰之責，冒用他人名義簽署上\n    揭舉發通知單進而行使之犯罪動機，於本院審理中坦承犯行\n    ，犯罪後態度尚可等一切情狀，量處如主文所示之刑，併諭\n    知易科罰金之折算標準，以示儆懲。末查被告前未曾受有期\n    徒刑以上刑之宣告，其經此偵審過程，自當知所警惕而無虞\n    再犯，本院綜核各情認上開刑之宣告，已足策其悔悟，因認\n    所宣告之刑，以暫不執行為適當，併諭知緩刑2 年，以啟自\n    新。惟被告騎乘機車違反交通規則，遭警開單舉發，為免課\n    受罰鍰，竟以他人名義簽署於舉發通知單上，致生損害於告\n    訴人及警察機關道路交通管理之正確性，顯對法律未有適當\n    之認識，為使之具備正確之法律觀念並提供必要之協助及督\n    促，爰依法宣告緩刑期內付保護管束，俾由地方法院檢察署\n    之觀護人予以適當之督促，並發揮緩刑制度之立意及避免短\n    期自由刑執行肇致之弊端。\n四、至舉發通知單移送聯及存根聯，既經被告持以行使，顯非屬\n    被告所有之物，然其上偽造「蔡宜臻」之署押各1 枚，應依\n    刑法第219 條之規定，不問屬於犯人與否，均宣告沒收之，\n    附此敘明。\n據上論斷，應依刑事訴訟法第452 條、第273 條之1 第1 項、第\n299 條第1 項前段，刑法第216 條、第210 條、第219 條、第41\n條第1 項前段、第74條第1 項第1 款、第93條第1 項，判決如主\n文。\n本案經檢察官蘇維達到庭執行職務\n中    華    民    國    100   年    10    月    18    日\n                  刑事第六庭  法  官  黃傅偉\n以上正本證明與原本無異。\n如不服本判決應於收受送達後10日內向本院提出上訴書狀，並應\n敘述具體理由；其未敘述上訴理由者，應於上訴期間屆滿後20日\n內向本院補提理由書（均須按他造當事人之人數附繕本）「切勿\n逕送上級法院」。告訴人或被害人如對於本判決不服者，應具備\n理由請求檢察官上訴，其上訴期間之計算係以檢察官收受判決正\n本之日期為準。\n                              書記官  劉子豪"
  },
  "search": "臺灣臺北地方法院刑事判決100年度訴字第979號公訴人臺灣臺北地方法院檢察署檢察官被告黃千容上列被告因偽造文書案件，經檢察官聲請簡易判決處刑（100年度偵緝字第1064號），本院認不宜依簡易判決處刑（100年度簡字第2970號），改依通常程序，被告於準備程序中就犯罪事實為有罪之陳述，本院改行簡式審判程序，由受命法官獨任審理，判決如下：主文黃千容犯行使偽造私文書罪，處有期徒刑貳月，如易科罰金，以新臺幣壹仟元折算壹日；緩刑貳年，緩刑期內付保護管束。臺北市政府警察局北市警交字第ＡＥＸ二七九三九三號舉發違反道路交通管理事件通知單移送聯及存根聯上收受通知聯者簽章欄內偽造之「蔡宜臻」署押各壹枚均沒收。事實一、黃千容於民國97年12月14日中午12時50分許，騎乘車牌號碼921-BGY號重型機車，行經臺北市○○區○○路與襄陽路口，因騎乘機車不依規定二段式左轉，經臺北市政府警察局中正第一分局警備隊警員施明宏攔停舉發時，為免除上開違規罰緩，竟於警當場開立臺北市政府警察局北市警交字第AEX279393號舉發違反道路交通管理事件通知單（下稱舉發通知單）時，冒用「蔡宜臻」之名義，基於偽造署押進而行使偽造私文書之犯意，在該通知單上之收受通知聯者簽章欄內偽簽「蔡宜臻」之署押1枚（1式3聯，分別為第1聯通知聯、第2聯移送聯、第3聯存根聯，黃千容在第2聯移送聯上偽造署押複寫至第3聯存根聯上），表示蔡宜臻本人出具領收該通知單之證明而交付警員，足以生損害於蔡宜臻及警察機關對道路交通管理之正確性。嗣經蔡宜臻收受交通部公路總局嘉義區監理所嘉義市監理站關於上開交通違規事項通知，進而報警處理，始悉上情。二、案經蔡宜臻訴由臺北市政府警察局中正第一分局報告臺灣臺北地方法院檢察署檢察官偵查聲請簡易判決處刑。理由一、按刑事訴訟法第273條之1第1項規定除被告所犯為死刑、無期徒刑、最輕本刑為3年以上有期徒刑之罪、或高等法院管轄第一審案件者外，於審判期日前之程序進行中，被告先就被訴事實為有罪之陳述時，審判長得告知被告簡式審判程序之旨，並聽取當事人、代理人、辯護人及輔佐人之意見後，裁定進行簡式審判程序。經查，本件被告黃千容被訴偽造文書一案，為前開不得進行簡式審判程序以外之案件，且被告於本院行準備程序時就被訴事實為有罪之陳述，本院告知被告簡式審判程序之旨，並聽取被告及檢察官之意見後，爰依刑事訴訟法第273條之1第1項之規定，當庭裁定改依簡式審判程序進行審判，合先敘明。二、前揭事實，業據被告於本院準備程序及審理時坦承不諱（見本院卷第14頁、第16頁反面），並經告訴人蔡宜臻陳述在卷，且有卷附舉發通知單影本1紙（見99年度偵字第24806號卷第6頁）可稽。從而，堪認被告之自白核與事實相符，自得採為論罪之依據。本件事證明確，被告犯行洵堪認定，應依法論科。三、按舉發通知單「收受通知聯者簽章」欄內偽簽他人姓名，自不待依據習慣或特約，單從形式上觀察，即足以知悉係表示由該他人名義出具領收通知聯之證明，此與事先在印妥內容之收據上偽簽他人姓名之情形，無分軒輊，當然屬於刑法第210條所稱之私文書（最高法院83年台上字第6631號判例參照）。核被告所為，係犯刑法第216條、第210條之行使偽造私文書罪。被告偽造「蔡宜臻」署押之行為，為偽造私文書之部分行為，又偽造私文書之低度行為，應為行使偽造私文書之高度行為所吸收，均不另論罪。爰審酌被告並無前科，有上開被告前案紀錄表在卷可查，目前在學而缺乏社會經驗及歷練，為卸免交通違規罰鍰之責，冒用他人名義簽署上揭舉發通知單進而行使之犯罪動機，於本院審理中坦承犯行，犯罪後態度尚可等一切情狀，量處如主文所示之刑，併諭知易科罰金之折算標準，以示儆懲。末查被告前未曾受有期徒刑以上刑之宣告，其經此偵審過程，自當知所警惕而無虞再犯，本院綜核各情認上開刑之宣告，已足策其悔悟，因認所宣告之刑，以暫不執行為適當，併諭知緩刑2年，以啟自新。惟被告騎乘機車違反交通規則，遭警開單舉發，為免課受罰鍰，竟以他人名義簽署於舉發通知單上，致生損害於告訴人及警察機關道路交通管理之正確性，顯對法律未有適當之認識，為使之具備正確之法律觀念並提供必要之協助及督促，爰依法宣告緩刑期內付保護管束，俾由地方法院檢察署之觀護人予以適當之督促，並發揮緩刑制度之立意及避免短期自由刑執行肇致之弊端。四、至舉發通知單移送聯及存根聯，既經被告持以行使，顯非屬被告所有之物，然其上偽造「蔡宜臻」之署押各1枚，應依刑法第219條之規定，不問屬於犯人與否，均宣告沒收之，附此敘明。據上論斷，應依刑事訴訟法第452條、第273條之1第1項、第299條第1項前段，刑法第216條、第210條、第219條、第41條第1項前段、第74條第1項第1款、第93條第1項，判決如主文。本案經檢察官蘇維達到庭執行職務中華民國100年10月18日刑事第六庭法官黃傅偉以上正本證明與原本無異。如不服本判決應於收受送達後10日內向本院提出上訴書狀，並應敘述具體理由；其未敘述上訴理由者，應於上訴期間屆滿後20日內向本院補提理由書（均須按他造當事人之人數附繕本）「切勿逕送上級法院」。告訴人或被害人如對於本判決不服者，應具備理由請求檢察官上訴，其上訴期間之計算係以檢察官收受判決正本之日期為準。書記官劉子豪中華民國100年10月18日附錄本案論罪法條全文中華民國刑法第210條（偽造變造私文書罪）偽造、變造私文書，足以生損害於公眾或他人者，處5年以下有期徒刑。中華民國刑法第216條（行使偽造變造或登載不實之文書罪）行使第210條至第215條之文書者，依偽造、變造文書或登載不實事項或使登載不實事項之規定處斷。",
  "characters": {
    "judges": [
      "黃傅偉"
    ],
    "prosecutors": [
      "蘇維達"
    ],
    "lawyers": [

    ],
    "clerks": [
      "劉子豪"
    ],
    "plaintiffs": [

    ],
    "defendants": [
      "黃千容"
    ],
    "prosecutor_office": [
      "臺灣臺北地方法院檢察署檢察官"
    ],
    "creditors": [

    ],
    "debtors": [

    ],
    "judicial_associate_officer": [

    ]
  },
  "adjudged_at": "2011-10-18",
  "created_at": "2016-02-14 04:35:10",
  "updated_at": "2016-02-14 04:35:10"
}