{
  "identify": "PCD-100-訴-39-20110131-1",
  "court": {
    "name": "臺灣新北地方法院",
    "code": "PCD"
  },
  "division": {
    "name": "刑事",
    "code": "M"
  },
  "year": 100,
  "word": "訴",
  "number": "39",
  "jcheck": "1",
  "reason": "毒品危害防制條例",
  "content": "臺灣板橋地方法院刑事判決               100年度訴字第39號\n公  訴  人  臺灣板橋地方法院檢察署檢察官\n被      告  王偉仁\n上列被告因違反毒品危害防制條例案件，經檢察官提起公訴（99\n年度毒偵字第8193號），被告於準備程序中就被訴事實為有罪之\n陳述，經告知簡式審判程序之旨，並聽取當事人之意見後，本院\n合議庭裁定由受命法官獨任進行簡式審判程序，判決如下：\n    主  文\n王偉仁施用第一級毒品，累犯，處有期徒刑玖月；又持有第一級\n毒品，累犯，處有期徒刑月，扣案之第一級毒品海洛因貳包（\n驗餘淨重零點貳陸肆零公克）均沒收銷燬之，扣案盛裝上開海洛\n因之包裝袋貳個均沒收之。應執行有期徒刑拾月，扣案之第一級\n毒品海洛因貳包（驗餘淨重零點貳陸肆零公克）均沒收銷燬之，\n扣案盛裝上開海洛因之包裝袋貳個均沒收之。\n    事  實\n一、王偉仁前於民國88年間因施用毒品案件，經本院以88年度毒\n    聲字第4689號裁定送觀察、勒戒後，認無繼續施用毒品之傾\n    向，於89年3 月13日執行完畢釋放出所，並經臺灣板橋地方\n    法院檢察署檢察官以89年度毒偵緝字第331 號為不起訴處分\n    確定。復因施用毒品案件，經本院裁定送觀察、勒戒後，認\n    有繼續施用毒品之傾向，再經本院裁定令入戒治處所施以強\n    制戒治，嗣因戒治成效良好，經本院以91年度毒聲字第4153\n    號裁定停止戒治所餘戒治期間付保護管束，於92年7 月17日\n    保護管束期滿，視為強制戒治執行完畢，並由檢察官提起公\n    訴，經本院以91年度訴字第2193號判處有期徒刑8 月、4 月\n    ，應執行有期徒刑10月確定；又因竊盜案，經本院以91年度\n    簡字第79號判處有期徒刑6 月確定，上開3 罪嗣經本院以92\n    年度聲字第1463號裁定應執行有期徒刑1 年3 月確定，於93\n    年4 月11日縮刑期滿執行完畢。再因搶奪案件，經本院以94\n    年度訴字第2303號判處有期徒刑1 年確定，於95年8 月28日\n    縮刑期滿執行完畢。詎猶不知悔改，基於施用第一級毒品海\n    洛因之犯意，於99年10月26日晚間某時許，在其位於臺北縣\n    板橋市（現改制為新北市板橋區○○○街17號3 樓住處內，\n    將海洛因加水稀釋後，以針筒注射手臂血管之方式，施用第\n    一級毒品海洛因1 次；另基於持有第一級毒品海洛因之犯意\n    ，於99年10月27日下午1 時許，在臺北縣土城市（現改制為\n    新北市土城區，下同）城林橋附近，向真實姓名年籍不詳、\n    綽號「宋仔」之成年男子取得海洛因2 包（淨重0.2660公克\n    ）而持有之。嗣於同日下午1 時20分許，在臺北縣土城市○\n    ○路○ 段與員福街口為警查獲，在員警尚未發覺其持有海洛\n    因前，主動將外套口袋中之前揭毒品海洛因2 包交付員警扣\n    案，而自動接受裁判，經其同意採尿送驗結果，呈鴉片類嗎\n    啡陽性反應，始查悉上情。\n二、案經臺北縣政府（現改制為新北市政府，下同）警察局中和\n    第一分局報告臺灣板橋地方法院檢察署檢察官偵查起訴。\n    理  由\n一、本件被告王偉仁所犯為死刑、無期徒刑、最輕本刑為3 年以\n    上有期徒刑以外之罪，且非高等法院管轄第一審之案件，於\n    本院準備程序進行中，被告就被訴事實為有罪之陳述，經告\n    知被告簡式審判程序之旨，並聽取公訴人及被告之意見後，\n    本院合議庭裁定由受命法官獨任進行簡式審判程序，合先敘\n    明。\n二、上揭犯罪事實，業據被告於警詢、偵查及本院審理中坦承不\n    諱，且被告在警局經其同意採尿送驗之結果，確呈第一級毒\n    品海洛因之代謝物嗎啡陽性反應等情，有臺北縣政府警察局\n    中和第一分局毒品案犯罪嫌犯人姓名及代號對照表、尿液檢\n    體監管紀錄表、臺灣檢驗科技股份有限公司99年11月16日出\n    具之報告編號：UL/2010/B0000000號濫用藥物檢驗報告各1\n    紙附卷可稽，而扣案之白色粉末2 包，經交通部民用航空局\n    航空醫務中心鑑定結果，確含有第一級毒品海洛因成分，此\n    有該中心99年11月9 日航藥鑑字第0996876 號毒品鑑定書1\n    紙存卷足參。此外，復有臺北縣政府警察局中和第一分局扣\n    押筆錄、扣押物品目錄表、扣案物品及查獲現場照片7 張在\n    卷可憑，足見被告自白核與事實相符。\n三、按毒品危害防制條例於92年7 月9 日修正公布，自93年1 月\n    9 日施行，其中第20條、第23條將施用毒品之刑事處遇程序\n    ，區分為「初犯」及「5 年內再犯」、「5 年後再犯」。依\n    其立法理由之說明：「初犯」，經觀察、勒戒或強制戒治後\n    ，應為不起訴處分或不付審理之裁定；經觀察、勒戒或強制\n    戒治執行完畢釋放後，「5 年內再犯」者，因其再犯率甚高\n    ，原實施之觀察、勒戒及強制戒治既已無法收其實效，爰依\n    法追訴或裁定交付審理。至於經觀察、勒戒或強制戒治執行\n    完畢釋放後，「5 年後再犯」者，前所實施之觀察、勒戒或\n    強制戒治已足以遮斷其施用毒品之毒癮，為期自新及協助其\n    斷除毒癮，仍適用「初犯」規定，先經觀察、勒戒或強制戒\n    治之程序。從而依修正後之規定，僅限於「初犯」及「5 年\n    後再犯」2 種情形，始應先經觀察、勒戒或強制戒治程序。\n    倘被告於5 年內已再犯，經依法追訴處罰，縱其第3 次（或\n    第3 次以上）再度施用毒品之時間，在初犯經觀察、勒戒或\n    強制戒治執行完畢釋放5 年以後，已不合於「5 年後再犯」\n    之規定，且因已於「5 年內再犯」，顯見其再犯率甚高，原\n    實施觀察、勒戒或強制戒治，已無法收其實效，即應依該條\n    例第10條處罰（最高法院95年5 月9 日95年度第7 次及97年\n    9 月9 日97年度第5 次刑事庭會議決議參照）。查本件被告\n    於89年3 月13日觀察、勒戒執行完畢釋放後5 年內之91年間\n    ，復因施用毒品案件，經本院裁定送觀察、勒戒後，認有繼\n    續施用毒品之傾向，再經本院裁定令入戒治處所施以強制戒\n    治，嗣因戒治成效良好，經本院以91年度毒聲字第4153號裁\n    定停止戒治所餘戒治期間付保護管束，於92年7 月17日保護\n    管束期滿，視為強制戒治執行完畢，並由檢察官提起公訴，\n    經本院以91年度訴字第2193號判處有期徒刑8 月、4 月，應\n    執行有期徒刑10月確定等情，有臺灣高等法院被告前案紀錄\n    表在卷足憑。則被告本件施用第一級毒品之時間，雖距離前\n    述強制戒治執行完畢已逾5 年，惟其前既已於5 年內再犯施\n    用毒品案件，參諸前揭說明，被告本件施用毒品之行為，即\n    不合於「5 年後再犯」之規定，自應依毒品危害防制條例第\n    10條規定追訴處罰。從而，本案事證明確，被告上開施用第\n    一級毒品之犯行，洵堪認定，應依法論科。\n四、查海洛因屬毒品危害防制條例第2 條第2 項第1 款所規定之\n    第一級毒品，核被告所為，係犯毒品危害防制條例第10條第\n    1 項施用第一級毒品罪及同條例第11條第1 項持有第一級毒\n    品罪。被告所犯上開2 罪間，犯意各別，行為互殊，應予分\n    論併罰。被告前有犯罪事實欄所載之犯罪科刑執行情形，有\n    前述前案紀錄表在卷可憑，其受有期徒刑之執行完畢後，5\n    年以內故意再犯本件有期徒刑以上之2 罪，均為累犯，皆應\n    依刑法第47條第1 項之規定加重其刑。又被告係於持有第一\n    級毒品海洛因之犯罪未經發覺前，主動向警員自首犯行而願\n    接受裁判，並交出其持有之上開海洛因2 包等情，業據被告\n    供述在卷，且其警詢筆錄亦記載甚詳（見偵查卷第3 頁反面\n    ），爰就所犯持有第一級毒品犯行依刑法第62條前段之規定\n    減輕其刑，並依法先加後減之。爰審酌被告未經許可無故持\n    有第一級毒品，行為實有不當，又其前已因施用毒品案件經\n    送觀察、勒戒及強制戒治，仍不能戒除毒癮，再次漠視法令\n    禁制而犯本罪，顯見其戒除毒癮之意志薄弱，惟念其所持有\n    海洛因之數量甚微，且施用毒品所生危害，實以自戕身心健\n    康為主，對於他人生命、身體、財產等法益，尚無明顯而重\n    大之實害，且犯後坦承犯行，態度良好等一切情狀，分別量\n    處如主文所示之刑，並定其應執行之刑。\n五、扣案之第一級毒品海洛因2 包（淨重0.2660公克，取樣0.00\n    20公克，驗餘淨重0.2640公克），為本案查獲之毒品，應依\n    毒品危害防制條例第18條第1 項前段之規定，不問屬於犯人\n    與否，沒收銷燬之；又扣案盛裝上開海洛因之包裝袋2 個，\n    均為被告所有供本案持有第一級毒品所用之物，業據被告供\n    承在卷，爰均依刑法第38條第1 項第2 款之規定宣告沒收。\n據上論斷，應依刑事訴訟法第273 條之1 第1 項、第299 條第1\n項前段，毒品危害防制條例第10條第1 項、第11條第1 項、第18\n條第1 項前段，刑法第11條前段、第47條第1 項、第62條前段、\n第51條第5 款、第38條第1 項第2 款，判決如主文。\n本案經檢察官黃致中到庭執行職務。\n中    華    民    國   100    年    1     月    31    日\n                  刑事第十四庭  法  官  廖欣儀\n以上正本證明與原本無異。\n如不服本判決應於收受判決後10日內向本院提出上訴書狀，並應\n敘述具體理由。其未敘述上訴理由者，應於上訴期間屆滿後20日\n內向本院補提理由書（均須按他造當事人之人數附繕本）「切勿\n逕送上級法院」。\n                                書記官  顏偉林\n中    華    民    國   100    年    1     月    31    日\n附錄本案論罪科刑法條全文：\n毒品危害防制條例第10條第1項\n施用第一級毒品者，處6 月以上5 年以下有期徒刑。\n毒品危害防制條例第11條第1項\n持有第一級毒品者，處3 年以下有期徒刑、拘役或新臺幣5 萬元\n以下罰金。",
  "structure": {
    "main": "王偉仁施用第一級毒品，累犯，處有期徒刑玖月；又持有第一級\n毒品，累犯，處有期徒刑月，扣案之第一級毒品海洛因貳包（\n驗餘淨重零點貳陸肆零公克）均沒收銷燬之，扣案盛裝上開海洛\n因之包裝袋貳個均沒收之。應執行有期徒刑拾月，扣案之第一級\n毒品海洛因貳包（驗餘淨重零點貳陸肆零公克）均沒收銷燬之，\n扣案盛裝上開海洛因之包裝袋貳個均沒收之。",
    "fact": "一、王偉仁前於民國88年間因施用毒品案件，經本院以88年度毒\n    聲字第4689號裁定送觀察、勒戒後，認無繼續施用毒品之傾\n    向，於89年3 月13日執行完畢釋放出所，並經臺灣板橋地方\n    法院檢察署檢察官以89年度毒偵緝字第331 號為不起訴處分\n    確定。復因施用毒品案件，經本院裁定送觀察、勒戒後，認\n    有繼續施用毒品之傾向，再經本院裁定令入戒治處所施以強\n    制戒治，嗣因戒治成效良好，經本院以91年度毒聲字第4153\n    號裁定停止戒治所餘戒治期間付保護管束，於92年7 月17日\n    保護管束期滿，視為強制戒治執行完畢，並由檢察官提起公\n    訴，經本院以91年度訴字第2193號判處有期徒刑8 月、4 月\n    ，應執行有期徒刑10月確定；又因竊盜案，經本院以91年度\n    簡字第79號判處有期徒刑6 月確定，上開3 罪嗣經本院以92\n    年度聲字第1463號裁定應執行有期徒刑1 年3 月確定，於93\n    年4 月11日縮刑期滿執行完畢。再因搶奪案件，經本院以94\n    年度訴字第2303號判處有期徒刑1 年確定，於95年8 月28日\n    縮刑期滿執行完畢。詎猶不知悔改，基於施用第一級毒品海\n    洛因之犯意，於99年10月26日晚間某時許，在其位於臺北縣\n    板橋市（現改制為新北市板橋區○○○街17號3 樓住處內，\n    將海洛因加水稀釋後，以針筒注射手臂血管之方式，施用第\n    一級毒品海洛因1 次；另基於持有第一級毒品海洛因之犯意\n    ，於99年10月27日下午1 時許，在臺北縣土城市（現改制為\n    新北市土城區，下同）城林橋附近，向真實姓名年籍不詳、\n    綽號「宋仔」之成年男子取得海洛因2 包（淨重0.2660公克\n    ）而持有之。嗣於同日下午1 時20分許，在臺北縣土城市○\n    ○路○ 段與員福街口為警查獲，在員警尚未發覺其持有海洛\n    因前，主動將外套口袋中之前揭毒品海洛因2 包交付員警扣\n    案，而自動接受裁判，經其同意採尿送驗結果，呈鴉片類嗎\n    啡陽性反應，始查悉上情。\n二、案經臺北縣政府（現改制為新北市政府，下同）警察局中和\n    第一分局報告臺灣板橋地方法院檢察署檢察官偵查起訴。",
    "reason": "一、本件被告王偉仁所犯為死刑、無期徒刑、最輕本刑為3 年以\n    上有期徒刑以外之罪，且非高等法院管轄第一審之案件，於\n    本院準備程序進行中，被告就被訴事實為有罪之陳述，經告\n    知被告簡式審判程序之旨，並聽取公訴人及被告之意見後，\n    本院合議庭裁定由受命法官獨任進行簡式審判程序，合先敘\n    明。\n二、上揭犯罪事實，業據被告於警詢、偵查及本院審理中坦承不\n    諱，且被告在警局經其同意採尿送驗之結果，確呈第一級毒\n    品海洛因之代謝物嗎啡陽性反應等情，有臺北縣政府警察局\n    中和第一分局毒品案犯罪嫌犯人姓名及代號對照表、尿液檢\n    體監管紀錄表、臺灣檢驗科技股份有限公司99年11月16日出\n    具之報告編號：UL/2010/B0000000號濫用藥物檢驗報告各1\n    紙附卷可稽，而扣案之白色粉末2 包，經交通部民用航空局\n    航空醫務中心鑑定結果，確含有第一級毒品海洛因成分，此\n    有該中心99年11月9 日航藥鑑字第0996876 號毒品鑑定書1\n    紙存卷足參。此外，復有臺北縣政府警察局中和第一分局扣\n    押筆錄、扣押物品目錄表、扣案物品及查獲現場照片7 張在\n    卷可憑，足見被告自白核與事實相符。\n三、按毒品危害防制條例於92年7 月9 日修正公布，自93年1 月\n    9 日施行，其中第20條、第23條將施用毒品之刑事處遇程序\n    ，區分為「初犯」及「5 年內再犯」、「5 年後再犯」。依\n    其立法理由之說明：「初犯」，經觀察、勒戒或強制戒治後\n    ，應為不起訴處分或不付審理之裁定；經觀察、勒戒或強制\n    戒治執行完畢釋放後，「5 年內再犯」者，因其再犯率甚高\n    ，原實施之觀察、勒戒及強制戒治既已無法收其實效，爰依\n    法追訴或裁定交付審理。至於經觀察、勒戒或強制戒治執行\n    完畢釋放後，「5 年後再犯」者，前所實施之觀察、勒戒或\n    強制戒治已足以遮斷其施用毒品之毒癮，為期自新及協助其\n    斷除毒癮，仍適用「初犯」規定，先經觀察、勒戒或強制戒\n    治之程序。從而依修正後之規定，僅限於「初犯」及「5 年\n    後再犯」2 種情形，始應先經觀察、勒戒或強制戒治程序。\n    倘被告於5 年內已再犯，經依法追訴處罰，縱其第3 次（或\n    第3 次以上）再度施用毒品之時間，在初犯經觀察、勒戒或\n    強制戒治執行完畢釋放5 年以後，已不合於「5 年後再犯」\n    之規定，且因已於「5 年內再犯」，顯見其再犯率甚高，原\n    實施觀察、勒戒或強制戒治，已無法收其實效，即應依該條\n    例第10條處罰（最高法院95年5 月9 日95年度第7 次及97年\n    9 月9 日97年度第5 次刑事庭會議決議參照）。查本件被告\n    於89年3 月13日觀察、勒戒執行完畢釋放後5 年內之91年間\n    ，復因施用毒品案件，經本院裁定送觀察、勒戒後，認有繼\n    續施用毒品之傾向，再經本院裁定令入戒治處所施以強制戒\n    治，嗣因戒治成效良好，經本院以91年度毒聲字第4153號裁\n    定停止戒治所餘戒治期間付保護管束，於92年7 月17日保護\n    管束期滿，視為強制戒治執行完畢，並由檢察官提起公訴，\n    經本院以91年度訴字第2193號判處有期徒刑8 月、4 月，應\n    執行有期徒刑10月確定等情，有臺灣高等法院被告前案紀錄\n    表在卷足憑。則被告本件施用第一級毒品之時間，雖距離前\n    述強制戒治執行完畢已逾5 年，惟其前既已於5 年內再犯施\n    用毒品案件，參諸前揭說明，被告本件施用毒品之行為，即\n    不合於「5 年後再犯」之規定，自應依毒品危害防制條例第\n    10條規定追訴處罰。從而，本案事證明確，被告上開施用第\n    一級毒品之犯行，洵堪認定，應依法論科。\n四、查海洛因屬毒品危害防制條例第2 條第2 項第1 款所規定之\n    第一級毒品，核被告所為，係犯毒品危害防制條例第10條第\n    1 項施用第一級毒品罪及同條例第11條第1 項持有第一級毒\n    品罪。被告所犯上開2 罪間，犯意各別，行為互殊，應予分\n    論併罰。被告前有犯罪事實欄所載之犯罪科刑執行情形，有\n    前述前案紀錄表在卷可憑，其受有期徒刑之執行完畢後，5\n    年以內故意再犯本件有期徒刑以上之2 罪，均為累犯，皆應\n    依刑法第47條第1 項之規定加重其刑。又被告係於持有第一\n    級毒品海洛因之犯罪未經發覺前，主動向警員自首犯行而願\n    接受裁判，並交出其持有之上開海洛因2 包等情，業據被告\n    供述在卷，且其警詢筆錄亦記載甚詳（見偵查卷第3 頁反面\n    ），爰就所犯持有第一級毒品犯行依刑法第62條前段之規定\n    減輕其刑，並依法先加後減之。爰審酌被告未經許可無故持\n    有第一級毒品，行為實有不當，又其前已因施用毒品案件經\n    送觀察、勒戒及強制戒治，仍不能戒除毒癮，再次漠視法令\n    禁制而犯本罪，顯見其戒除毒癮之意志薄弱，惟念其所持有\n    海洛因之數量甚微，且施用毒品所生危害，實以自戕身心健\n    康為主，對於他人生命、身體、財產等法益，尚無明顯而重\n    大之實害，且犯後坦承犯行，態度良好等一切情狀，分別量\n    處如主文所示之刑，並定其應執行之刑。\n五、扣案之第一級毒品海洛因2 包（淨重0.2660公克，取樣0.00\n    20公克，驗餘淨重0.2640公克），為本案查獲之毒品，應依\n    毒品危害防制條例第18條第1 項前段之規定，不問屬於犯人\n    與否，沒收銷燬之；又扣案盛裝上開海洛因之包裝袋2 個，\n    均為被告所有供本案持有第一級毒品所用之物，業據被告供\n    承在卷，爰均依刑法第38條第1 項第2 款之規定宣告沒收。\n據上論斷，應依刑事訴訟法第273 條之1 第1 項、第299 條第1\n項前段，毒品危害防制條例第10條第1 項、第11條第1 項、第18\n條第1 項前段，刑法第11條前段、第47條第1 項、第62條前段、\n第51條第5 款、第38條第1 項第2 款，判決如主文。\n本案經檢察官黃致中到庭執行職務。\n中    華    民    國   100    年    1     月    31    日\n                  刑事第十四庭  法  官  廖欣儀\n以上正本證明與原本無異。\n如不服本判決應於收受判決後10日內向本院提出上訴書狀，並應\n敘述具體理由。其未敘述上訴理由者，應於上訴期間屆滿後20日\n內向本院補提理由書（均須按他造當事人之人數附繕本）「切勿\n逕送上級法院」。\n                                書記官  顏偉林"
  },
  "search": "臺灣板橋地方法院刑事判決100年度訴字第39號公訴人臺灣板橋地方法院檢察署檢察官被告王偉仁上列被告因違反毒品危害防制條例案件，經檢察官提起公訴（99年度毒偵字第8193號），被告於準備程序中就被訴事實為有罪之陳述，經告知簡式審判程序之旨，並聽取當事人之意見後，本院合議庭裁定由受命法官獨任進行簡式審判程序，判決如下：主文王偉仁施用第一級毒品，累犯，處有期徒刑玖月；又持有第一級毒品，累犯，處有期徒刑月，扣案之第一級毒品海洛因貳包（驗餘淨重零點貳陸肆零公克）均沒收銷燬之，扣案盛裝上開海洛因之包裝袋貳個均沒收之。應執行有期徒刑拾月，扣案之第一級毒品海洛因貳包（驗餘淨重零點貳陸肆零公克）均沒收銷燬之，扣案盛裝上開海洛因之包裝袋貳個均沒收之。事實一、王偉仁前於民國88年間因施用毒品案件，經本院以88年度毒聲字第4689號裁定送觀察、勒戒後，認無繼續施用毒品之傾向，於89年3月13日執行完畢釋放出所，並經臺灣板橋地方法院檢察署檢察官以89年度毒偵緝字第331號為不起訴處分確定。復因施用毒品案件，經本院裁定送觀察、勒戒後，認有繼續施用毒品之傾向，再經本院裁定令入戒治處所施以強制戒治，嗣因戒治成效良好，經本院以91年度毒聲字第4153號裁定停止戒治所餘戒治期間付保護管束，於92年7月17日保護管束期滿，視為強制戒治執行完畢，並由檢察官提起公訴，經本院以91年度訴字第2193號判處有期徒刑8月、4月，應執行有期徒刑10月確定；又因竊盜案，經本院以91年度簡字第79號判處有期徒刑6月確定，上開3罪嗣經本院以92年度聲字第1463號裁定應執行有期徒刑1年3月確定，於93年4月11日縮刑期滿執行完畢。再因搶奪案件，經本院以94年度訴字第2303號判處有期徒刑1年確定，於95年8月28日縮刑期滿執行完畢。詎猶不知悔改，基於施用第一級毒品海洛因之犯意，於99年10月26日晚間某時許，在其位於臺北縣板橋市（現改制為新北市板橋區○○○街17號3樓住處內，將海洛因加水稀釋後，以針筒注射手臂血管之方式，施用第一級毒品海洛因1次；另基於持有第一級毒品海洛因之犯意，於99年10月27日下午1時許，在臺北縣土城市（現改制為新北市土城區，下同）城林橋附近，向真實姓名年籍不詳、綽號「宋仔」之成年男子取得海洛因2包（淨重0.2660公克）而持有之。嗣於同日下午1時20分許，在臺北縣土城市○○路○段與員福街口為警查獲，在員警尚未發覺其持有海洛因前，主動將外套口袋中之前揭毒品海洛因2包交付員警扣案，而自動接受裁判，經其同意採尿送驗結果，呈鴉片類嗎啡陽性反應，始查悉上情。二、案經臺北縣政府（現改制為新北市政府，下同）警察局中和第一分局報告臺灣板橋地方法院檢察署檢察官偵查起訴。理由一、本件被告王偉仁所犯為死刑、無期徒刑、最輕本刑為3年以上有期徒刑以外之罪，且非高等法院管轄第一審之案件，於本院準備程序進行中，被告就被訴事實為有罪之陳述，經告知被告簡式審判程序之旨，並聽取公訴人及被告之意見後，本院合議庭裁定由受命法官獨任進行簡式審判程序，合先敘明。二、上揭犯罪事實，業據被告於警詢、偵查及本院審理中坦承不諱，且被告在警局經其同意採尿送驗之結果，確呈第一級毒品海洛因之代謝物嗎啡陽性反應等情，有臺北縣政府警察局中和第一分局毒品案犯罪嫌犯人姓名及代號對照表、尿液檢體監管紀錄表、臺灣檢驗科技股份有限公司99年11月16日出具之報告編號：UL/2010/B0000000號濫用藥物檢驗報告各1紙附卷可稽，而扣案之白色粉末2包，經交通部民用航空局航空醫務中心鑑定結果，確含有第一級毒品海洛因成分，此有該中心99年11月9日航藥鑑字第0996876號毒品鑑定書1紙存卷足參。此外，復有臺北縣政府警察局中和第一分局扣押筆錄、扣押物品目錄表、扣案物品及查獲現場照片7張在卷可憑，足見被告自白核與事實相符。三、按毒品危害防制條例於92年7月9日修正公布，自93年1月9日施行，其中第20條、第23條將施用毒品之刑事處遇程序，區分為「初犯」及「5年內再犯」、「5年後再犯」。依其立法理由之說明：「初犯」，經觀察、勒戒或強制戒治後，應為不起訴處分或不付審理之裁定；經觀察、勒戒或強制戒治執行完畢釋放後，「5年內再犯」者，因其再犯率甚高，原實施之觀察、勒戒及強制戒治既已無法收其實效，爰依法追訴或裁定交付審理。至於經觀察、勒戒或強制戒治執行完畢釋放後，「5年後再犯」者，前所實施之觀察、勒戒或強制戒治已足以遮斷其施用毒品之毒癮，為期自新及協助其斷除毒癮，仍適用「初犯」規定，先經觀察、勒戒或強制戒治之程序。從而依修正後之規定，僅限於「初犯」及「5年後再犯」2種情形，始應先經觀察、勒戒或強制戒治程序。倘被告於5年內已再犯，經依法追訴處罰，縱其第3次（或第3次以上）再度施用毒品之時間，在初犯經觀察、勒戒或強制戒治執行完畢釋放5年以後，已不合於「5年後再犯」之規定，且因已於「5年內再犯」，顯見其再犯率甚高，原實施觀察、勒戒或強制戒治，已無法收其實效，即應依該條例第10條處罰（最高法院95年5月9日95年度第7次及97年9月9日97年度第5次刑事庭會議決議參照）。查本件被告於89年3月13日觀察、勒戒執行完畢釋放後5年內之91年間，復因施用毒品案件，經本院裁定送觀察、勒戒後，認有繼續施用毒品之傾向，再經本院裁定令入戒治處所施以強制戒治，嗣因戒治成效良好，經本院以91年度毒聲字第4153號裁定停止戒治所餘戒治期間付保護管束，於92年7月17日保護管束期滿，視為強制戒治執行完畢，並由檢察官提起公訴，經本院以91年度訴字第2193號判處有期徒刑8月、4月，應執行有期徒刑10月確定等情，有臺灣高等法院被告前案紀錄表在卷足憑。則被告本件施用第一級毒品之時間，雖距離前述強制戒治執行完畢已逾5年，惟其前既已於5年內再犯施用毒品案件，參諸前揭說明，被告本件施用毒品之行為，即不合於「5年後再犯」之規定，自應依毒品危害防制條例第10條規定追訴處罰。從而，本案事證明確，被告上開施用第一級毒品之犯行，洵堪認定，應依法論科。四、查海洛因屬毒品危害防制條例第2條第2項第1款所規定之第一級毒品，核被告所為，係犯毒品危害防制條例第10條第1項施用第一級毒品罪及同條例第11條第1項持有第一級毒品罪。被告所犯上開2罪間，犯意各別，行為互殊，應予分論併罰。被告前有犯罪事實欄所載之犯罪科刑執行情形，有前述前案紀錄表在卷可憑，其受有期徒刑之執行完畢後，5年以內故意再犯本件有期徒刑以上之2罪，均為累犯，皆應依刑法第47條第1項之規定加重其刑。又被告係於持有第一級毒品海洛因之犯罪未經發覺前，主動向警員自首犯行而願接受裁判，並交出其持有之上開海洛因2包等情，業據被告供述在卷，且其警詢筆錄亦記載甚詳（見偵查卷第3頁反面），爰就所犯持有第一級毒品犯行依刑法第62條前段之規定減輕其刑，並依法先加後減之。爰審酌被告未經許可無故持有第一級毒品，行為實有不當，又其前已因施用毒品案件經送觀察、勒戒及強制戒治，仍不能戒除毒癮，再次漠視法令禁制而犯本罪，顯見其戒除毒癮之意志薄弱，惟念其所持有海洛因之數量甚微，且施用毒品所生危害，實以自戕身心健康為主，對於他人生命、身體、財產等法益，尚無明顯而重大之實害，且犯後坦承犯行，態度良好等一切情狀，分別量處如主文所示之刑，並定其應執行之刑。五、扣案之第一級毒品海洛因2包（淨重0.2660公克，取樣0.0020公克，驗餘淨重0.2640公克），為本案查獲之毒品，應依毒品危害防制條例第18條第1項前段之規定，不問屬於犯人與否，沒收銷燬之；又扣案盛裝上開海洛因之包裝袋2個，均為被告所有供本案持有第一級毒品所用之物，業據被告供承在卷，爰均依刑法第38條第1項第2款之規定宣告沒收。據上論斷，應依刑事訴訟法第273條之1第1項、第299條第1項前段，毒品危害防制條例第10條第1項、第11條第1項、第18條第1項前段，刑法第11條前段、第47條第1項、第62條前段、第51條第5款、第38條第1項第2款，判決如主文。本案經檢察官黃致中到庭執行職務。中華民國100年1月31日刑事第十四庭法官廖欣儀以上正本證明與原本無異。如不服本判決應於收受判決後10日內向本院提出上訴書狀，並應敘述具體理由。其未敘述上訴理由者，應於上訴期間屆滿後20日內向本院補提理由書（均須按他造當事人之人數附繕本）「切勿逕送上級法院」。書記官顏偉林中華民國100年1月31日附錄本案論罪科刑法條全文：毒品危害防制條例第10條第1項施用第一級毒品者，處6月以上5年以下有期徒刑。毒品危害防制條例第11條第1項持有第一級毒品者，處3年以下有期徒刑、拘役或新臺幣5萬元以下罰金。",
  "characters": {
    "judges": [
      "廖欣儀"
    ],
    "prosecutors": [
      "黃致中"
    ],
    "lawyers": [

    ],
    "clerks": [
      "顏偉林"
    ],
    "plaintiffs": [

    ],
    "defendants": [
      "王偉仁"
    ],
    "prosecutor_office": [
      "臺灣板橋地方法院檢察署檢察官"
    ],
    "creditors": [

    ],
    "debtors": [

    ],
    "judicial_associate_officer": [

    ]
  },
  "adjudged_at": "2011-01-31",
  "created_at": "2016-02-13 09:23:51",
  "updated_at": "2016-02-13 09:23:51"
}