{
  "identify": "SCD-100-竹交簡-29-20110131-1",
  "court": {
    "name": "臺灣新竹地方法院",
    "code": "SCD"
  },
  "division": {
    "name": "刑事",
    "code": "M"
  },
  "year": 100,
  "word": "竹交簡",
  "number": "29",
  "jcheck": "1",
  "reason": "公共危險",
  "content": "臺灣新竹地方法院刑事簡易判決       100年度竹交簡字第29號\n聲  請  人  臺灣新竹地方法院檢察署檢察官\n被      告  徐曉屏\n上列被告因公共危險案件，經檢察官聲請以簡易判決處刑（99年\n度偵字第9144號），本院判決如下:\n    主  文\n徐曉屏服用酒類，不能安全駕駛動力交通工具而駕駛，處罰金新\n臺幣陸萬元。如易服勞役，以新臺幣壹仟元折算壹日。\n    事實及理由\n一、本件犯罪事實、證據及應適用法條，除證據欄應補充「警員\n    廖大慶所出具之偵查報告1 份、行車執照影本1 份、駕駛執\n    照影本1 份」外，餘均引用檢察官聲請簡易判決刑書之記載\n    （如附件）。\n二、按酒精濃度呼氣已達每公升0.55毫克時，肇事率為一般正常\n    人之10倍，認已達不能安全駕駛之標準，有法務部88年5 月\n    18日所發之法88檢字第001669號函及其所附之88年5 月10日\n    會議紀錄足參，而被告經酒精濃度之呼氣測試，已達每公升\n    0.62毫克，此有道路交通事故當事人酒精測定紀錄表1 紙在\n    卷可稽。其於駕駛過程中，對員警指揮及交通號誌無反應或\n    遲緩，駕駛判斷力，顯然欠佳；且駕駛有蛇行，車身搖擺不\n    定，轉彎半徑過大或過小等駕駛操控力欠佳之情形；又為警\n    查獲後，命其雙腳併攏，兩手緊貼大腿將一腳向前抬高離地\n    15公分，並停止不動30秒，及命其閉雙眼，30秒內朗誦阿拉\n    伯數字，由1001至1030，其皆測試不合格等情事，此有員警\n    製作之刑法第185 條之3 案件測試觀察紀錄表、汽機車駕駛\n    人酒後生理協調平衡檢測紀錄表等附卷足憑，堪認被告顯有\n    不能安全駕駛動力交通工具之危險甚明。\n三、依刑事訴訟法第449 條第1 項前段、第454 條第2 項，刑法\n    第185 條之3 、第42條第3 項前段，刑法施行法第1 條之1\n    第1 項，逕以簡易判決處刑如主文。\n四、如不服本判決，得自收受送達之日起10日內，向本院提起上\n    訴。\n中    華    民    國   100    年    1     月    31    日\n                  新竹簡易庭    法  官    楊惠芬\n以上正本證明與原本無異。\n中    華    民    國   100    年    1     月    31    日\n                                書記官    許弘杰\n附錄本案論罪科刑法條：\n刑法第185 條之3 ：\n服用毒品、麻醉藥品、酒類或其他相類之物，不能安全駕駛動力\n交通工具而駕駛者，處一年以下有期徒刑、拘役或科或併科十五\n萬元以下罰金。\n附件：\n臺灣新竹地方法院檢察署檢察官聲請簡易判決處刑書\n                                      99年度偵字第9144號\n被      告  徐曉屏  女  28歲（民國○○年○月○○日生）\n                        住新竹縣竹北市○○里○鄰○○街276\n                        巷38弄8號\n                        國民身分證統一編號：Ｚ000000000號\n上列被告因公共危險案件，業經偵查終結，認為宜聲請以簡易判\n決處刑，茲將犯罪事實及證據並所犯法條分敘如下：\n        犯罪事實\n一、徐曉屏明知在服用酒類或其他相類之物後，將使其駕駛車輛\n    時之注意力減低、反應能力趨緩，而危及其他用路人之行車\n    往來安全。竟於民國99年11月21日23時許，在新竹市○○街\n    大潤發對面某快炒店內飲用啤酒約2 瓶，已達不能安全駕駛\n    動力交通工具之狀態後，復於翌日即99 年11月22日凌晨1時\n    許，騎乘其所有之車牌號碼TV7-889 號重型機車離開，欲返\n    回其位於新竹縣竹北市○○里○鄰○○街276 巷38弄8號之住\n    處。嗣於99年11月22日凌晨1時50 分許，徐曉屏騎車行經新\n    竹市○○街188之2號前時，為警攔車稽查，經警測試其酒精\n    濃度呼氣值達每公升0‧62毫克。\n二、案經新竹市警察局第一分局報告偵辦。\n         證據並所犯法條\n一、證據：(一)被告徐曉屏之自白。\n          (二)酒精濃度測試0‧62MG／L數據紙1張、汽機車駕\n              駛人酒後生理協調平衡檢測紀錄表1張、刑法185\n              之3案件測試觀察紀錄表1張、新竹市警察局舉發\n              違反道路交通管理事件通知單竹市警交字第\n              E00000000號號舉發違反道路交通管理事件通知\n              單1張在卷可資佐證。\n二、所犯法條：核被告所為，係犯刑法第185條之3公共危險罪嫌\n    。\n三、依刑事訴訟法第451條第1項聲請逕以簡易判決處刑。\n     此    致\n臺灣新竹地方法院\n中    華    民    國    99    年    12    月    29    日\n                              檢察官  林  佳  穎\n本件證明與原本無異\n中    華    民    國   100    年    1     月    4     日\n                              書記官  曾  美  松",
  "structure": {
    "main": "徐曉屏服用酒類，不能安全駕駛動力交通工具而駕駛，處罰金新\n臺幣陸萬元。如易服勞役，以新臺幣壹仟元折算壹日。",
    "fact": "一、本件犯罪事實、證據及應適用法條，除證據欄應補充「警員\n    廖大慶所出具之偵查報告1 份、行車執照影本1 份、駕駛執\n    照影本1 份」外，餘均引用檢察官聲請簡易判決刑書之記載\n    （如附件）。\n二、按酒精濃度呼氣已達每公升0.55毫克時，肇事率為一般正常\n    人之10倍，認已達不能安全駕駛之標準，有法務部88年5 月\n    18日所發之法88檢字第001669號函及其所附之88年5 月10日\n    會議紀錄足參，而被告經酒精濃度之呼氣測試，已達每公升\n    0.62毫克，此有道路交通事故當事人酒精測定紀錄表1 紙在\n    卷可稽。其於駕駛過程中，對員警指揮及交通號誌無反應或\n    遲緩，駕駛判斷力，顯然欠佳；且駕駛有蛇行，車身搖擺不\n    定，轉彎半徑過大或過小等駕駛操控力欠佳之情形；又為警\n    查獲後，命其雙腳併攏，兩手緊貼大腿將一腳向前抬高離地\n    15公分，並停止不動30秒，及命其閉雙眼，30秒內朗誦阿拉\n    伯數字，由1001至1030，其皆測試不合格等情事，此有員警\n    製作之刑法第185 條之3 案件測試觀察紀錄表、汽機車駕駛\n    人酒後生理協調平衡檢測紀錄表等附卷足憑，堪認被告顯有\n    不能安全駕駛動力交通工具之危險甚明。\n三、依刑事訴訟法第449 條第1 項前段、第454 條第2 項，刑法\n    第185 條之3 、第42條第3 項前段，刑法施行法第1 條之1\n    第1 項，逕以簡易判決處刑如主文。\n四、如不服本判決，得自收受送達之日起10日內，向本院提起上\n    訴。",
    "reason": "一、本件犯罪事實、證據及應適用法條，除證據欄應補充「警員\n    廖大慶所出具之偵查報告1 份、行車執照影本1 份、駕駛執\n    照影本1 份」外，餘均引用檢察官聲請簡易判決刑書之記載\n    （如附件）。\n二、按酒精濃度呼氣已達每公升0.55毫克時，肇事率為一般正常\n    人之10倍，認已達不能安全駕駛之標準，有法務部88年5 月\n    18日所發之法88檢字第001669號函及其所附之88年5 月10日\n    會議紀錄足參，而被告經酒精濃度之呼氣測試，已達每公升\n    0.62毫克，此有道路交通事故當事人酒精測定紀錄表1 紙在\n    卷可稽。其於駕駛過程中，對員警指揮及交通號誌無反應或\n    遲緩，駕駛判斷力，顯然欠佳；且駕駛有蛇行，車身搖擺不\n    定，轉彎半徑過大或過小等駕駛操控力欠佳之情形；又為警\n    查獲後，命其雙腳併攏，兩手緊貼大腿將一腳向前抬高離地\n    15公分，並停止不動30秒，及命其閉雙眼，30秒內朗誦阿拉\n    伯數字，由1001至1030，其皆測試不合格等情事，此有員警\n    製作之刑法第185 條之3 案件測試觀察紀錄表、汽機車駕駛\n    人酒後生理協調平衡檢測紀錄表等附卷足憑，堪認被告顯有\n    不能安全駕駛動力交通工具之危險甚明。\n三、依刑事訴訟法第449 條第1 項前段、第454 條第2 項，刑法\n    第185 條之3 、第42條第3 項前段，刑法施行法第1 條之1\n    第1 項，逕以簡易判決處刑如主文。\n四、如不服本判決，得自收受送達之日起10日內，向本院提起上\n    訴。"
  },
  "search": "臺灣新竹地方法院刑事簡易判決100年度竹交簡字第29號聲請人臺灣新竹地方法院檢察署檢察官被告徐曉屏上列被告因公共危險案件，經檢察官聲請以簡易判決處刑（99年度偵字第9144號），本院判決如下:主文徐曉屏服用酒類，不能安全駕駛動力交通工具而駕駛，處罰金新臺幣陸萬元。如易服勞役，以新臺幣壹仟元折算壹日。事實及理由一、本件犯罪事實、證據及應適用法條，除證據欄應補充「警員廖大慶所出具之偵查報告1份、行車執照影本1份、駕駛執照影本1份」外，餘均引用檢察官聲請簡易判決刑書之記載（如附件）。二、按酒精濃度呼氣已達每公升0.55毫克時，肇事率為一般正常人之10倍，認已達不能安全駕駛之標準，有法務部88年5月18日所發之法88檢字第001669號函及其所附之88年5月10日會議紀錄足參，而被告經酒精濃度之呼氣測試，已達每公升0.62毫克，此有道路交通事故當事人酒精測定紀錄表1紙在卷可稽。其於駕駛過程中，對員警指揮及交通號誌無反應或遲緩，駕駛判斷力，顯然欠佳；且駕駛有蛇行，車身搖擺不定，轉彎半徑過大或過小等駕駛操控力欠佳之情形；又為警查獲後，命其雙腳併攏，兩手緊貼大腿將一腳向前抬高離地15公分，並停止不動30秒，及命其閉雙眼，30秒內朗誦阿拉伯數字，由1001至1030，其皆測試不合格等情事，此有員警製作之刑法第185條之3案件測試觀察紀錄表、汽機車駕駛人酒後生理協調平衡檢測紀錄表等附卷足憑，堪認被告顯有不能安全駕駛動力交通工具之危險甚明。三、依刑事訴訟法第449條第1項前段、第454條第2項，刑法第185條之3、第42條第3項前段，刑法施行法第1條之1第1項，逕以簡易判決處刑如主文。四、如不服本判決，得自收受送達之日起10日內，向本院提起上訴。中華民國100年1月31日新竹簡易庭法官楊惠芬以上正本證明與原本無異。中華民國100年1月31日書記官許弘杰附錄本案論罪科刑法條：刑法第185條之3：服用毒品、麻醉藥品、酒類或其他相類之物，不能安全駕駛動力交通工具而駕駛者，處一年以下有期徒刑、拘役或科或併科十五萬元以下罰金。附件：臺灣新竹地方法院檢察署檢察官聲請簡易判決處刑書99年度偵字第9144號被告徐曉屏女28歲（民國○○年○月○○日生）住新竹縣竹北市○○里○鄰○○街276巷38弄8號國民身分證統一編號：Ｚ000000000號上列被告因公共危險案件，業經偵查終結，認為宜聲請以簡易判決處刑，茲將犯罪事實及證據並所犯法條分敘如下：犯罪事實一、徐曉屏明知在服用酒類或其他相類之物後，將使其駕駛車輛時之注意力減低、反應能力趨緩，而危及其他用路人之行車往來安全。竟於民國99年11月21日23時許，在新竹市○○街大潤發對面某快炒店內飲用啤酒約2瓶，已達不能安全駕駛動力交通工具之狀態後，復於翌日即99年11月22日凌晨1時許，騎乘其所有之車牌號碼TV7-889號重型機車離開，欲返回其位於新竹縣竹北市○○里○鄰○○街276巷38弄8號之住處。嗣於99年11月22日凌晨1時50分許，徐曉屏騎車行經新竹市○○街188之2號前時，為警攔車稽查，經警測試其酒精濃度呼氣值達每公升0‧62毫克。二、案經新竹市警察局第一分局報告偵辦。證據並所犯法條一、證據：(一)被告徐曉屏之自白。(二)酒精濃度測試0‧62MG／L數據紙1張、汽機車駕駛人酒後生理協調平衡檢測紀錄表1張、刑法185之3案件測試觀察紀錄表1張、新竹市警察局舉發違反道路交通管理事件通知單竹市警交字第E00000000號號舉發違反道路交通管理事件通知單1張在卷可資佐證。二、所犯法條：核被告所為，係犯刑法第185條之3公共危險罪嫌。三、依刑事訴訟法第451條第1項聲請逕以簡易判決處刑。此致臺灣新竹地方法院中華民國99年12月29日檢察官林佳穎本件證明與原本無異中華民國100年1月4日書記官曾美松",
  "characters": {
    "judges": [
      "楊惠芬"
    ],
    "prosecutors": [

    ],
    "lawyers": [

    ],
    "clerks": [
      "許弘杰"
    ],
    "plaintiffs": [

    ],
    "defendants": [
      "徐曉屏",
      "徐曉屏  女  28歲（民國○○年○月○○日生）"
    ],
    "prosecutor_office": [
      "臺灣新竹地方法院檢察署檢察官"
    ],
    "creditors": [

    ],
    "debtors": [

    ],
    "judicial_associate_officer": [

    ]
  },
  "adjudged_at": "2011-01-31",
  "created_at": "2016-02-13 09:06:25",
  "updated_at": "2016-02-13 09:06:25"
}