{
  "identify": "CHD-94-訴-171-20050215-1",
  "court": {
    "name": "臺灣彰化地方法院",
    "code": "CHD"
  },
  "division": {
    "name": "刑事",
    "code": "M"
  },
  "year": 94,
  "word": "訴",
  "number": "171",
  "jcheck": "1",
  "reason": "毒品危害防制條例",
  "content": "臺灣彰化地方法院刑事判決                          九十四年度訴字第一七一號\n    公  訴  人  臺灣彰化地方法院檢察署檢察官\n    被      告  甲○○\n右列被告因違反毒品危害防制條例案件，經檢察官提起公訴（九十三年度毒偵字第四\n八一九號），本院依刑事訴訟法第二百七十三條之一第一項之規定，裁定改用簡式審\n判程序判決如左：\n    主  文\n甲○○連續施用第壹級毒品，處有期徒刑拾月。\n扣案之注射針筒壹支，沒收銷燬之。\n    事  實\n一、甲○○（原名粘富新）前於民國八十九年間，因違反毒品危害防制條例案件，經\n    本院裁定送觀察、勒戒後，認為無繼續施用毒品之傾向，由臺灣彰化地方法院檢\n    察署檢察官於八十九年六月八日，以八十九年度毒偵字第一六七七號為不起訴處\n    分確定；又於九十一年三月、四月間，因違反毒品危害防制條例案件，另經本院\n    裁定送觀察、勒戒後，仍認為無繼續施用毒品之傾向，嗣於九十一年七月三十日\n    其觀察、勒戒執行完畢出所後，由臺灣彰化地方法院檢察署檢察官於九十一年八\n    月十日，以九十一年度毒偵字第一二九五號為不起訴處分確定。惟其仍不知悔改\n    ，復基於施用第一級毒品海洛因之概括犯意，自九十三年八月中旬某日起，至同\n    年十二月十四日上午八時三十分許止，在其位於彰化縣福興鄉○○村○○街五十\n    七號之住所處等地，以將第一級毒品海洛因置於扣案之注射針筒內加水稀釋後，\n    再持以注射手臂血管之方式，連續施用第一級毒品海洛因多次，平均每二天施用\n    一次，嗣於九十三年十二月十四日上午十時四十分許，在彰化縣鹿港鎮○○里○\n    ○○路與民生路口處為警查獲，並當場扣得注射針筒一支，始知上情。\n二、案經彰化縣警察局鹿港分局報告臺灣彰化地方法院檢察署檢察官偵查起訴。\n    理  由\n一、訊據被告甲○○對其前揭連續施用第一級毒品之犯罪事實均坦白承認，且其為警\n    查獲時，經警採集其尿液送驗，結果確呈嗎啡陽性反應，此有彰化縣衛生局煙毒\n    尿液檢驗成績書一紙附卷可稽，並有注射針筒一支扣案可相佐證；此外，復有刑\n    案資料查註紀錄表、全國施用毒品案件紀錄表及前開臺灣彰化地方法院檢察署九\n    十一年度毒偵字第一二九五號不起訴處分書各一份在卷可考，足認被告之自白與\n    事實相符而得採信，被告犯行堪予認定，應依法予以論科。\n二、核被告甲○○所為，係犯毒品危害防制條例第十條第一項之施用第一級毒品罪。\n    其施用毒品前、後持有毒品及專供施用毒品器具之行為，已為其施用毒品犯行所\n    吸收，不另論處。又其先後多次施用第一級海洛因之犯行，時間緊接、所犯構成\n    要件相同，顯係基於概括犯意為之，應依連續犯之規定論以一罪，並依法加重其\n    刑。爰審酌被告犯罪之動機、目的、方法、手段、所生危害，其前因施用毒品，\n    先後二次經送觀察、勒戒後，均認為無繼續施用毒品之傾向，卻仍未能改其施用\n    毒品之惡習，品行不佳，及其犯後對其犯行坦白承認，犯後態度良好等一切情狀\n    ，量處如主文所示之刑，以示懲儆。至扣案之注射針筒一支，係被告所有且專供\n    其施用第一級毒品海洛因所用之器具，業據被告供明在卷，自應依同條例第十八\n    條第一項前段之規定宣告沒收並諭知銷燬。\n三、據上論斷，應依刑事訴訟法第二百七十三條之一第一項、第二百九十九條第一項\n    前段，毒品危害防制條例第十條第一項、第十八條第一項前段，刑法第十一條前\n    段、第五十六條，判決如主文。\n本案經檢察官林裕斌到庭執行職務。\n中      華      民      國    九十四  年      二      月     十五     日\n                                  臺灣彰化地方法院刑事第一庭\n                                      法      官  葛  永  輝\n右正本證明與原本無異。\n如不服本判決，應於判決送達後十日內向本院提出上訴狀( 須附繕本 )。\n                                      法院書記官  施  惠  卿\n中      華      民      國    九十四    年      二      月     十六     日\n毒品危害防制條例第十條\n施用第一級毒品者，處六月以上五年以下有期徒刑。\n施用第二級毒品者，處三年以下有期徒刑。\n",
  "structure": {
    "main": "甲○○連續施用第壹級毒品，處有期徒刑拾月。\n扣案之注射針筒壹支，沒收銷燬之。",
    "fact": "一、甲○○（原名粘富新）前於民國八十九年間，因違反毒品危害防制條例案件，經\n    本院裁定送觀察、勒戒後，認為無繼續施用毒品之傾向，由臺灣彰化地方法院檢\n    察署檢察官於八十九年六月八日，以八十九年度毒偵字第一六七七號為不起訴處\n    分確定；又於九十一年三月、四月間，因違反毒品危害防制條例案件，另經本院\n    裁定送觀察、勒戒後，仍認為無繼續施用毒品之傾向，嗣於九十一年七月三十日\n    其觀察、勒戒執行完畢出所後，由臺灣彰化地方法院檢察署檢察官於九十一年八\n    月十日，以九十一年度毒偵字第一二九五號為不起訴處分確定。惟其仍不知悔改\n    ，復基於施用第一級毒品海洛因之概括犯意，自九十三年八月中旬某日起，至同\n    年十二月十四日上午八時三十分許止，在其位於彰化縣福興鄉○○村○○街五十\n    七號之住所處等地，以將第一級毒品海洛因置於扣案之注射針筒內加水稀釋後，\n    再持以注射手臂血管之方式，連續施用第一級毒品海洛因多次，平均每二天施用\n    一次，嗣於九十三年十二月十四日上午十時四十分許，在彰化縣鹿港鎮○○里○\n    ○○路與民生路口處為警查獲，並當場扣得注射針筒一支，始知上情。\n二、案經彰化縣警察局鹿港分局報告臺灣彰化地方法院檢察署檢察官偵查起訴。",
    "reason": "一、訊據被告甲○○對其前揭連續施用第一級毒品之犯罪事實均坦白承認，且其為警\n    查獲時，經警採集其尿液送驗，結果確呈嗎啡陽性反應，此有彰化縣衛生局煙毒\n    尿液檢驗成績書一紙附卷可稽，並有注射針筒一支扣案可相佐證；此外，復有刑\n    案資料查註紀錄表、全國施用毒品案件紀錄表及前開臺灣彰化地方法院檢察署九\n    十一年度毒偵字第一二九五號不起訴處分書各一份在卷可考，足認被告之自白與\n    事實相符而得採信，被告犯行堪予認定，應依法予以論科。\n二、核被告甲○○所為，係犯毒品危害防制條例第十條第一項之施用第一級毒品罪。\n    其施用毒品前、後持有毒品及專供施用毒品器具之行為，已為其施用毒品犯行所\n    吸收，不另論處。又其先後多次施用第一級海洛因之犯行，時間緊接、所犯構成\n    要件相同，顯係基於概括犯意為之，應依連續犯之規定論以一罪，並依法加重其\n    刑。爰審酌被告犯罪之動機、目的、方法、手段、所生危害，其前因施用毒品，\n    先後二次經送觀察、勒戒後，均認為無繼續施用毒品之傾向，卻仍未能改其施用\n    毒品之惡習，品行不佳，及其犯後對其犯行坦白承認，犯後態度良好等一切情狀\n    ，量處如主文所示之刑，以示懲儆。至扣案之注射針筒一支，係被告所有且專供\n    其施用第一級毒品海洛因所用之器具，業據被告供明在卷，自應依同條例第十八\n    條第一項前段之規定宣告沒收並諭知銷燬。\n三、據上論斷，應依刑事訴訟法第二百七十三條之一第一項、第二百九十九條第一項\n    前段，毒品危害防制條例第十條第一項、第十八條第一項前段，刑法第十一條前\n    段、第五十六條，判決如主文。\n本案經檢察官林裕斌到庭執行職務。\n中      華      民      國    九十四  年      二      月     十五     日\n                                  臺灣彰化地方法院刑事第一庭\n                                      法      官  葛  永  輝\n右正本證明與原本無異。\n如不服本判決，應於判決送達後十日內向本院提出上訴狀( 須附繕本 )。\n                                      法院書記官  施  惠  卿"
  },
  "search": "臺灣彰化地方法院刑事判決九十四年度訴字第一七一號公訴人臺灣彰化地方法院檢察署檢察官被告甲○○右列被告因違反毒品危害防制條例案件，經檢察官提起公訴（九十三年度毒偵字第四八一九號），本院依刑事訴訟法第二百七十三條之一第一項之規定，裁定改用簡式審判程序判決如左：主文甲○○連續施用第壹級毒品，處有期徒刑拾月。扣案之注射針筒壹支，沒收銷燬之。事實一、甲○○（原名粘富新）前於民國八十九年間，因違反毒品危害防制條例案件，經本院裁定送觀察、勒戒後，認為無繼續施用毒品之傾向，由臺灣彰化地方法院檢察署檢察官於八十九年六月八日，以八十九年度毒偵字第一六七七號為不起訴處分確定；又於九十一年三月、四月間，因違反毒品危害防制條例案件，另經本院裁定送觀察、勒戒後，仍認為無繼續施用毒品之傾向，嗣於九十一年七月三十日其觀察、勒戒執行完畢出所後，由臺灣彰化地方法院檢察署檢察官於九十一年八月十日，以九十一年度毒偵字第一二九五號為不起訴處分確定。惟其仍不知悔改，復基於施用第一級毒品海洛因之概括犯意，自九十三年八月中旬某日起，至同年十二月十四日上午八時三十分許止，在其位於彰化縣福興鄉○○村○○街五十七號之住所處等地，以將第一級毒品海洛因置於扣案之注射針筒內加水稀釋後，再持以注射手臂血管之方式，連續施用第一級毒品海洛因多次，平均每二天施用一次，嗣於九十三年十二月十四日上午十時四十分許，在彰化縣鹿港鎮○○里○○○路與民生路口處為警查獲，並當場扣得注射針筒一支，始知上情。二、案經彰化縣警察局鹿港分局報告臺灣彰化地方法院檢察署檢察官偵查起訴。理由一、訊據被告甲○○對其前揭連續施用第一級毒品之犯罪事實均坦白承認，且其為警查獲時，經警採集其尿液送驗，結果確呈嗎啡陽性反應，此有彰化縣衛生局煙毒尿液檢驗成績書一紙附卷可稽，並有注射針筒一支扣案可相佐證；此外，復有刑案資料查註紀錄表、全國施用毒品案件紀錄表及前開臺灣彰化地方法院檢察署九十一年度毒偵字第一二九五號不起訴處分書各一份在卷可考，足認被告之自白與事實相符而得採信，被告犯行堪予認定，應依法予以論科。二、核被告甲○○所為，係犯毒品危害防制條例第十條第一項之施用第一級毒品罪。其施用毒品前、後持有毒品及專供施用毒品器具之行為，已為其施用毒品犯行所吸收，不另論處。又其先後多次施用第一級海洛因之犯行，時間緊接、所犯構成要件相同，顯係基於概括犯意為之，應依連續犯之規定論以一罪，並依法加重其刑。爰審酌被告犯罪之動機、目的、方法、手段、所生危害，其前因施用毒品，先後二次經送觀察、勒戒後，均認為無繼續施用毒品之傾向，卻仍未能改其施用毒品之惡習，品行不佳，及其犯後對其犯行坦白承認，犯後態度良好等一切情狀，量處如主文所示之刑，以示懲儆。至扣案之注射針筒一支，係被告所有且專供其施用第一級毒品海洛因所用之器具，業據被告供明在卷，自應依同條例第十八條第一項前段之規定宣告沒收並諭知銷燬。三、據上論斷，應依刑事訴訟法第二百七十三條之一第一項、第二百九十九條第一項前段，毒品危害防制條例第十條第一項、第十八條第一項前段，刑法第十一條前段、第五十六條，判決如主文。本案經檢察官林裕斌到庭執行職務。中華民國九十四年二月十五日臺灣彰化地方法院刑事第一庭法官葛永輝右正本證明與原本無異。如不服本判決，應於判決送達後十日內向本院提出上訴狀(須附繕本)。法院書記官施惠卿中華民國九十四年二月十六日毒品危害防制條例第十條施用第一級毒品者，處六月以上五年以下有期徒刑。施用第二級毒品者，處三年以下有期徒刑。",
  "characters": {
    "judges": [
      "葛永輝"
    ],
    "prosecutors": [
      "林裕斌"
    ],
    "lawyers": [

    ],
    "clerks": [
      "法院"
    ],
    "plaintiffs": [

    ],
    "defendants": [
      "甲○○",
      "右列被告因違反毒品危害防制條例案件，經檢察官提起公訴（九十三年度毒偵字第四",
      "八一九號），本院依刑事訴訟法第二百七十三條之一第一項之規定，裁定改用簡式審",
      "判程序判決如左："
    ],
    "prosecutor_office": [
      "臺灣彰化地方法院檢察署檢察官"
    ],
    "creditors": [

    ],
    "debtors": [

    ],
    "judicial_associate_officer": [

    ]
  },
  "adjudged_at": "2005-02-15",
  "created_at": "2016-02-06 16:42:19",
  "updated_at": "2016-02-06 16:42:19"
}