{
  "identify": "KSD-93-交易-236-20050215-1",
  "court": {
    "name": "臺灣高雄地方法院",
    "code": "KSD"
  },
  "division": {
    "name": "刑事",
    "code": "M"
  },
  "year": 93,
  "word": "交易",
  "number": "236",
  "jcheck": "1",
  "reason": "過失傷害",
  "content": "臺灣高雄地方法院刑事判決                        九十三年度交易字第二三六號\n    公  訴  人  臺灣高雄地方法院檢察署檢察官\n    被      告  甲○○  男  三.\n右列被告因過失傷害案件，經檢察官提起公訴（九十三年度偵字第一七０六六號），\n本院判決如左：\n    主   文\n本件公訴不受理。\n    理   由\n一、公訴意旨係以：被告甲○○於民國九十二年十一月二十九日八時三十分許，騎乘\n    車牌號碼ＸＸＪ─○三一號號重機車，沿高雄市○○區○○路北往南北方向行駛\n    ，途經海軍總部圍牆旁時，理應注意車前狀況，隨時採取必要之安全措施，而依\n    當時天候及路況良好，又無不能注意之情事，竟疏於注意車前狀況，致向前撞擊\n    同向沿高雄市○○區○○路北往南北方向行駛由乙○○所騎乘之腳踏車，致乙○\n    ○人車倒地，乙○○因此受有頭部外傷併腦挫傷、頭骨骨折及挫傷性顱內出血及\n    硬膜下出血等傷害，因認被告涉犯刑法第二百八十四條第一項之過失傷害罪嫌。\n二、按告訴乃論之罪，告訴人於第一審辯論終結前，得撤回其告訴；又告訴經撤回者\n    ，法院應諭知不受理之判決，刑事訴訟法第二百三十八條第一項，及第三百零三\n    條第三款定有明文。\n三、本件被告因過失傷害案件，經檢察官提起公訴，認被告係犯刑法第二百八十四條\n    第一項前段之過失傷害罪，依同法第二百八十七條前段之規定須告訴乃論。茲據\n    告訴人於九十四年二月四日具狀向本院撤回告訴，有撤回告訴狀乙份附卷可憑，\n    揆諸前開說明，爰不經言詞辯論，逕為諭知不受理之判決。\n據上論斷，應依刑事訴訟法第三百零三條第三款、第三百零七條，判決如主文。\n中      華      民      國    九十四    年      二      月    十五      日\n                                  臺灣高雄地方法院交通法庭\n                                      審判長法  官  張維君\n                                            法  官  伍逸康\n                                            法  官  劉惠娟\n右判決正本證明與原本無異\n如不服本判決，應於送達後十日內，向本院提出上訴狀。\n                                            書記官  陳素徵\n中      華      民      國    九十四    年      二      月     十五     日\n",
  "structure": {
    "main": "本件公訴不受理。",
    "reason": "一、公訴意旨係以：被告甲○○於民國九十二年十一月二十九日八時三十分許，騎乘\n    車牌號碼ＸＸＪ─○三一號號重機車，沿高雄市○○區○○路北往南北方向行駛\n    ，途經海軍總部圍牆旁時，理應注意車前狀況，隨時採取必要之安全措施，而依\n    當時天候及路況良好，又無不能注意之情事，竟疏於注意車前狀況，致向前撞擊\n    同向沿高雄市○○區○○路北往南北方向行駛由乙○○所騎乘之腳踏車，致乙○\n    ○人車倒地，乙○○因此受有頭部外傷併腦挫傷、頭骨骨折及挫傷性顱內出血及\n    硬膜下出血等傷害，因認被告涉犯刑法第二百八十四條第一項之過失傷害罪嫌。\n二、按告訴乃論之罪，告訴人於第一審辯論終結前，得撤回其告訴；又告訴經撤回者\n    ，法院應諭知不受理之判決，刑事訴訟法第二百三十八條第一項，及第三百零三\n    條第三款定有明文。\n三、本件被告因過失傷害案件，經檢察官提起公訴，認被告係犯刑法第二百八十四條\n    第一項前段之過失傷害罪，依同法第二百八十七條前段之規定須告訴乃論。茲據\n    告訴人於九十四年二月四日具狀向本院撤回告訴，有撤回告訴狀乙份附卷可憑，\n    揆諸前開說明，爰不經言詞辯論，逕為諭知不受理之判決。\n據上論斷，應依刑事訴訟法第三百零三條第三款、第三百零七條，判決如主文。"
  },
  "search": "臺灣高雄地方法院刑事判決九十三年度交易字第二三六號公訴人臺灣高雄地方法院檢察署檢察官被告甲○○男三.右列被告因過失傷害案件，經檢察官提起公訴（九十三年度偵字第一七０六六號），本院判決如左：主文本件公訴不受理。理由一、公訴意旨係以：被告甲○○於民國九十二年十一月二十九日八時三十分許，騎乘車牌號碼ＸＸＪ─○三一號號重機車，沿高雄市○○區○○路北往南北方向行駛，途經海軍總部圍牆旁時，理應注意車前狀況，隨時採取必要之安全措施，而依當時天候及路況良好，又無不能注意之情事，竟疏於注意車前狀況，致向前撞擊同向沿高雄市○○區○○路北往南北方向行駛由乙○○所騎乘之腳踏車，致乙○○人車倒地，乙○○因此受有頭部外傷併腦挫傷、頭骨骨折及挫傷性顱內出血及硬膜下出血等傷害，因認被告涉犯刑法第二百八十四條第一項之過失傷害罪嫌。二、按告訴乃論之罪，告訴人於第一審辯論終結前，得撤回其告訴；又告訴經撤回者，法院應諭知不受理之判決，刑事訴訟法第二百三十八條第一項，及第三百零三條第三款定有明文。三、本件被告因過失傷害案件，經檢察官提起公訴，認被告係犯刑法第二百八十四條第一項前段之過失傷害罪，依同法第二百八十七條前段之規定須告訴乃論。茲據告訴人於九十四年二月四日具狀向本院撤回告訴，有撤回告訴狀乙份附卷可憑，揆諸前開說明，爰不經言詞辯論，逕為諭知不受理之判決。據上論斷，應依刑事訴訟法第三百零三條第三款、第三百零七條，判決如主文。中華民國九十四年二月十五日臺灣高雄地方法院交通法庭審判長法官張維君法官伍逸康法官劉惠娟右判決正本證明與原本無異如不服本判決，應於送達後十日內，向本院提出上訴狀。書記官陳素徵中華民國九十四年二月十五日",
  "characters": {
    "judges": [
      "張維君",
      "伍逸康",
      "劉惠娟"
    ],
    "prosecutors": [

    ],
    "lawyers": [

    ],
    "clerks": [
      "陳素徵"
    ],
    "plaintiffs": [

    ],
    "defendants": [
      "甲○○  男  三.",
      "右列被告因過失傷害案件，經檢察官提起公訴（九十三年度偵字第一七０六六號），",
      "本院判決如左："
    ],
    "prosecutor_office": [
      "臺灣高雄地方法院檢察署檢察官"
    ],
    "creditors": [

    ],
    "debtors": [

    ],
    "judicial_associate_officer": [

    ]
  },
  "adjudged_at": "2005-02-15",
  "created_at": "2016-02-06 16:40:51",
  "updated_at": "2016-02-06 16:40:51"
}