{
  "identify": "SLD-94-交易-39-20050215-1",
  "court": {
    "name": "臺灣士林地方法院",
    "code": "SLD"
  },
  "division": {
    "name": "刑事",
    "code": "M"
  },
  "year": 94,
  "word": "交易",
  "number": "39",
  "jcheck": "1",
  "reason": "過失傷害",
  "content": "臺灣士林地方法院刑事判決\n公  訴  人  台灣士林地方法院檢察署檢察官\n被      告  甲○○\n上列被告因傷害案件，經檢察官聲請簡易判決處刑（93年度偵字\n第8771號），本院認不得以簡易判決處刑（93年度士交簡字第31\n號），改依通常程序審判，本院判決如後：\n    主  文\n本件公訴不受理。\n    理  由\n一、公訴意旨略以：被告甲○○於民國93年7月22日上午9時許，\n    騎乘車號ＡＺＪ－９５７號重機車，沿台北市內湖區○○○\n    道東往西方向行駛，至台北市○○區○○路2段179巷口欲左\n    轉時，本應注意車前狀況及兩車並行之間隔，隨時採取必要\n    之安全措施，而依當時之情形，並無不能情事，竟疏未注意\n    ，其重機車右側車身，擦撞前方路口正欲起步左轉，由乙○\n    ○騎乘之車牌號碼ＡＶＸ－２７６重機車左側車身，致乙○\n    ○人車倒地，乙○○並受有兩側肩膀及背部挫傷、兩側膝蓋\n    擦傷及挫傷、兩側小腿瘀傷等傷害云云。\n二、按告訴乃論之罪，告訴人於第一審辯論終結前得撤回其告訴\n    ；又告訴經撤回者，應諭知不受理之判決，並得不經言詞辯\n    論為之，刑事訴訟法第238條第1項、第303條第3款、第307\n    條分別定有明文。\n三、查本件告訴人乙○○告訴被告傷害案件，聲請簡易判決處刑\n    書認係觸犯刑法第284條第1項之過失傷害罪，依同法第287\n    條前段之規定，須告訴乃論。茲據告訴人於本院士林簡易庭\n    審理中撤回其告訴，有本院士林簡易庭94年1 月18日訊問筆\n    錄在卷可稽，依照上開說明，本件爰不經言詞辯論，逕為不\n    受理判決之諭知。\n據上論斷，應依刑事訴訟法第452 條、第303 條第3 款、第307\n條規定，判決如主文。\n中      華    民    國    94    年    2     月   15   日\n                    刑事第五庭審判長法  官  洪英花\n                                    法  官  朱光仁\n                                    法  官  彭洪媛\n以上正本證明與原本無異。\n如不服本判決，應於判決送達後10日內，向本院提出上訴狀。\n                                    書記官  趙彩彤\n中      華    民    國    94    年    2     月   15   日\n",
  "structure": {
    "main": "本件公訴不受理。",
    "reason": "一、公訴意旨略以：被告甲○○於民國93年7月22日上午9時許，\n    騎乘車號ＡＺＪ－９５７號重機車，沿台北市內湖區○○○\n    道東往西方向行駛，至台北市○○區○○路2段179巷口欲左\n    轉時，本應注意車前狀況及兩車並行之間隔，隨時採取必要\n    之安全措施，而依當時之情形，並無不能情事，竟疏未注意\n    ，其重機車右側車身，擦撞前方路口正欲起步左轉，由乙○\n    ○騎乘之車牌號碼ＡＶＸ－２７６重機車左側車身，致乙○\n    ○人車倒地，乙○○並受有兩側肩膀及背部挫傷、兩側膝蓋\n    擦傷及挫傷、兩側小腿瘀傷等傷害云云。\n二、按告訴乃論之罪，告訴人於第一審辯論終結前得撤回其告訴\n    ；又告訴經撤回者，應諭知不受理之判決，並得不經言詞辯\n    論為之，刑事訴訟法第238條第1項、第303條第3款、第307\n    條分別定有明文。\n三、查本件告訴人乙○○告訴被告傷害案件，聲請簡易判決處刑\n    書認係觸犯刑法第284條第1項之過失傷害罪，依同法第287\n    條前段之規定，須告訴乃論。茲據告訴人於本院士林簡易庭\n    審理中撤回其告訴，有本院士林簡易庭94年1 月18日訊問筆\n    錄在卷可稽，依照上開說明，本件爰不經言詞辯論，逕為不\n    受理判決之諭知。\n據上論斷，應依刑事訴訟法第452 條、第303 條第3 款、第307\n條規定，判決如主文。"
  },
  "search": "臺灣士林地方法院刑事判決公訴人台灣士林地方法院檢察署檢察官被告甲○○上列被告因傷害案件，經檢察官聲請簡易判決處刑（93年度偵字第8771號），本院認不得以簡易判決處刑（93年度士交簡字第31號），改依通常程序審判，本院判決如後：主文本件公訴不受理。理由一、公訴意旨略以：被告甲○○於民國93年7月22日上午9時許，騎乘車號ＡＺＪ－９５７號重機車，沿台北市內湖區○○○道東往西方向行駛，至台北市○○區○○路2段179巷口欲左轉時，本應注意車前狀況及兩車並行之間隔，隨時採取必要之安全措施，而依當時之情形，並無不能情事，竟疏未注意，其重機車右側車身，擦撞前方路口正欲起步左轉，由乙○○騎乘之車牌號碼ＡＶＸ－２７６重機車左側車身，致乙○○人車倒地，乙○○並受有兩側肩膀及背部挫傷、兩側膝蓋擦傷及挫傷、兩側小腿瘀傷等傷害云云。二、按告訴乃論之罪，告訴人於第一審辯論終結前得撤回其告訴；又告訴經撤回者，應諭知不受理之判決，並得不經言詞辯論為之，刑事訴訟法第238條第1項、第303條第3款、第307條分別定有明文。三、查本件告訴人乙○○告訴被告傷害案件，聲請簡易判決處刑書認係觸犯刑法第284條第1項之過失傷害罪，依同法第287條前段之規定，須告訴乃論。茲據告訴人於本院士林簡易庭審理中撤回其告訴，有本院士林簡易庭94年1月18日訊問筆錄在卷可稽，依照上開說明，本件爰不經言詞辯論，逕為不受理判決之諭知。據上論斷，應依刑事訴訟法第452條、第303條第3款、第307條規定，判決如主文。中華民國94年2月15日刑事第五庭審判長法官洪英花法官朱光仁法官彭洪媛以上正本證明與原本無異。如不服本判決，應於判決送達後10日內，向本院提出上訴狀。書記官趙彩彤中華民國94年2月15日",
  "characters": {
    "judges": [
      "洪英花",
      "朱光仁",
      "彭洪媛"
    ],
    "prosecutors": [

    ],
    "lawyers": [

    ],
    "clerks": [
      "趙彩彤"
    ],
    "plaintiffs": [

    ],
    "defendants": [
      "甲○○"
    ],
    "prosecutor_office": [
      "台灣士林地方法院檢察署檢察官"
    ],
    "creditors": [

    ],
    "debtors": [

    ],
    "judicial_associate_officer": [

    ]
  },
  "adjudged_at": "2005-02-15",
  "created_at": "2016-02-06 16:40:40",
  "updated_at": "2016-02-06 16:40:40"
}