{
  "identify": "TPD-94-簡-257-20050215-1",
  "court": {
    "name": "臺灣臺北地方法院",
    "code": "TPD"
  },
  "division": {
    "name": "刑事",
    "code": "M"
  },
  "year": 94,
  "word": "簡",
  "number": "257",
  "jcheck": "1",
  "reason": "竊盜",
  "content": "臺灣臺北地方法院刑事簡易判決           94年度簡字第257號\n    聲  請  人  臺灣臺北地方法院檢察署檢察官\n    被      告  甲○○  49歲.\n上列被告因竊盜案件，經檢察官聲請以簡易判決處刑（94年度速\n偵字第49號），本院判決如下：\n    主  文\n甲○○竊盜，處拘役伍拾日，如易科罰金以佰元折算壹日，緩\n刑年。\n    事實及理由\n一、本件犯罪事實、證據及應適用之法條，均引用檢察官聲請簡\n    易判決處刑書（如附件）之記載。\n二、又被告甲○○未曾受有期徒刑以上刑之宣告，此有臺灣高等\n    法院被告全國前案紀錄表在卷可稽，其經此次起訴審判後，\n    當能知所警惕，而無再犯之虞，本院因認所宣告之刑，以暫\n    不執行為適當，爰併宣告緩刑3年，以啟自新。\n三、依刑事訴訟法第449條第1項、第3項、第454條第2項，刑法\n    第320條第1項、第41條第1項、第74條第1款，罰金罰鍰提高\n    標準條例第1條前段、第2條，逕以簡易判決處刑如主文。\n如不服本件判決，得自收受送達之日起十日內，向本院提起上訴\n。\n中    華    民    國    94    年    2     月    15    日\n                  臺灣臺北地方法院刑事第十五庭\n                          法  官  黃雅君\n上正本證明與原本無異。\n如不服本判決，應於判決送達後10日內向本院提出上訴狀。\n                          書記官  陳麗津\n中    華    民    國    94    年    2     月    17    日\n",
  "structure": {
    "main": "甲○○竊盜，處拘役伍拾日，如易科罰金以佰元折算壹日，緩\n刑年。",
    "fact": "一、本件犯罪事實、證據及應適用之法條，均引用檢察官聲請簡\n    易判決處刑書（如附件）之記載。\n二、又被告甲○○未曾受有期徒刑以上刑之宣告，此有臺灣高等\n    法院被告全國前案紀錄表在卷可稽，其經此次起訴審判後，\n    當能知所警惕，而無再犯之虞，本院因認所宣告之刑，以暫\n    不執行為適當，爰併宣告緩刑3年，以啟自新。\n三、依刑事訴訟法第449條第1項、第3項、第454條第2項，刑法\n    第320條第1項、第41條第1項、第74條第1款，罰金罰鍰提高\n    標準條例第1條前段、第2條，逕以簡易判決處刑如主文。\n如不服本件判決，得自收受送達之日起十日內，向本院提起上訴\n。",
    "reason": "一、本件犯罪事實、證據及應適用之法條，均引用檢察官聲請簡\n    易判決處刑書（如附件）之記載。\n二、又被告甲○○未曾受有期徒刑以上刑之宣告，此有臺灣高等\n    法院被告全國前案紀錄表在卷可稽，其經此次起訴審判後，\n    當能知所警惕，而無再犯之虞，本院因認所宣告之刑，以暫\n    不執行為適當，爰併宣告緩刑3年，以啟自新。\n三、依刑事訴訟法第449條第1項、第3項、第454條第2項，刑法\n    第320條第1項、第41條第1項、第74條第1款，罰金罰鍰提高\n    標準條例第1條前段、第2條，逕以簡易判決處刑如主文。\n如不服本件判決，得自收受送達之日起十日內，向本院提起上訴\n。"
  },
  "search": "臺灣臺北地方法院刑事簡易判決94年度簡字第257號聲請人臺灣臺北地方法院檢察署檢察官被告甲○○49歲.上列被告因竊盜案件，經檢察官聲請以簡易判決處刑（94年度速偵字第49號），本院判決如下：主文甲○○竊盜，處拘役伍拾日，如易科罰金以佰元折算壹日，緩刑年。事實及理由一、本件犯罪事實、證據及應適用之法條，均引用檢察官聲請簡易判決處刑書（如附件）之記載。二、又被告甲○○未曾受有期徒刑以上刑之宣告，此有臺灣高等法院被告全國前案紀錄表在卷可稽，其經此次起訴審判後，當能知所警惕，而無再犯之虞，本院因認所宣告之刑，以暫不執行為適當，爰併宣告緩刑3年，以啟自新。三、依刑事訴訟法第449條第1項、第3項、第454條第2項，刑法第320條第1項、第41條第1項、第74條第1款，罰金罰鍰提高標準條例第1條前段、第2條，逕以簡易判決處刑如主文。如不服本件判決，得自收受送達之日起十日內，向本院提起上訴。中華民國94年2月15日臺灣臺北地方法院刑事第十五庭法官黃雅君上正本證明與原本無異。如不服本判決，應於判決送達後10日內向本院提出上訴狀。書記官陳麗津中華民國94年2月17日",
  "characters": {
    "judges": [
      "黃雅君"
    ],
    "prosecutors": [

    ],
    "lawyers": [

    ],
    "clerks": [
      "陳麗津"
    ],
    "plaintiffs": [

    ],
    "defendants": [
      "甲○○  49歲."
    ],
    "prosecutor_office": [
      "臺灣臺北地方法院檢察署檢察官"
    ],
    "creditors": [

    ],
    "debtors": [

    ],
    "judicial_associate_officer": [

    ]
  },
  "adjudged_at": "2005-02-15",
  "created_at": "2016-02-06 16:38:49",
  "updated_at": "2016-02-06 16:38:49"
}