{
  "identify": "TNH-100-聲-320-20110429-1",
  "court": {
    "name": "臺灣高等法院",
    "code": "TNH"
  },
  "division": {
    "name": "刑事",
    "code": "M"
  },
  "year": 100,
  "word": "聲",
  "number": "320",
  "jcheck": "1",
  "reason": "聲請定其應執行刑",
  "content": "臺灣高等法院臺南分院刑事裁定          100年度聲字第320號\n聲  請  人  臺灣高等法院臺南分院檢察署檢察官\n受  刑  人  張銘德\n上列聲請人因受刑人數罪併罰有二裁判以上，聲請定其應執行之\n刑（100年度執聲字第264號），本院裁定如下：\n    主  文\n張銘德所處如附表編號1、2、10、11、13至28所示之刑，應執行\n有期徒刑陸年捌月。\n張銘德所處如附表編號3至9、12所示之刑，應執行有期徒刑參年\n捌月。\n    理  由\n一、本件聲請意旨略以：\n    上列受刑人因恐嚇等數罪，先後經判決確定如附表( 其中編\n    號13之犯罪日期應係95年11月7 日之誤繕) ，應依刑法第53\n    條、第51條第5款規定，分別就(1)附表編號1、2、10、11、\n    13至28所示之刑；及(2)附表編號3至9 、12所示之刑定其應\n    執行之刑，爰依刑事訴訟法第477條第1項聲請裁定等語。\n二、按裁判確定前犯數罪者，併合處罰之。數罪併罰，分別宣告\n    宣告多數有期徒刑者，於各刑中之最長期以上，各刑合併之\n    刑期以下，定其刑期。又數罪併罰，有二裁判以上者，依刑\n    法第51條規定，定其應執行刑，刑法第50條、第51條第5 款\n    、第53條分別定有明文。查本件受刑人犯如附表編號1、2、\n    10、11、13至28所示等罪之犯罪時間，均在同表編號1 判決\n    確定(97年6 月28日)之前；其犯如附表編號3至9、12所示等\n    罪之犯罪時間，均在同表編號3 判決確定(97年11月17日)之\n    前，揆諸前開規定，應分別依刑法第50條規定，定其應執行\n    刑，合先敘明。\n三、又刑事判決關於有期徒刑得易科罰金之規定，刑法第41條定\n    有明文，惟所犯為數罪併罰，其中之一罪雖得易科罰金，但\n    因與不得易科之他罪合併處罰之結果，於定執行刑時，祇須\n    將各罪之刑合併裁量，不得易科罰金合併執行，有司法院大\n    法官會議釋字第144號及第679號解釋可資參照，是本件如附\n    表編號1、3、4、7、8 、13及14所示之罪雖得易科罰金，但\n    因分別與其他不得易科罰金之罪合併處罰之結果，已不得易\n    科罰金合併執行。\n四、按法律上屬於自由裁量之事項，有其外部性界限及內部性界\n    限，並非概無拘束。依據法律之具體規定，法院應在其範圍\n    選擇為適當之裁判者，為外部性界限；而法院為裁判時，應\n    考量法律之目的，及法律秩序之理念所在者，為內部性界限\n    ，法院為裁判時，二者均不得有所踰越。故在數罪併罰，有\n    二裁判以上，定其應執行之刑時，固屬於法院自由裁量之事\n    項，然仍應受前揭外部性界限及內部性界限之拘束（最高法\n    院80年度台非字第473號判例及93年度台非字第192號裁判要\n    旨參照）。查本件受刑人所犯如附表編號3至4、5至8及15至\n    28所示案件，分別業經臺灣臺南地方法院以97年度易字第16\n    26號判決、97年度易字第1956號判決及本院99年度上訴字第\n    115 號判決分別定應執行有期徒刑六月、二年二月及四年確\n    定，有判決書1 份在卷可按。依前開說明，本院為最後事實\n    審法院再為定應執行刑之裁判時，自應受前開裁判所為定應\n    執行刑內部界限之拘束( 按編號11、12所示之罪，雖前經本\n    院97年度上訴字第1385號判決定應執行有期徒刑一年，惟編\n    號11所示之罪，應與編號1、2、10、13至28所示之刑定執行\n    刑；編號12所示之罪，應與編號3至9所示之刑，定執行刑，\n    已如前述，則該二罪原定應執行刑一年部分，自已失其效力\n    ，附此敘明)。\n五、綜此，本件受刑人因如附表所示等罪，先後經臺灣臺南地方\n    法院及本院判處如附表所示之刑，均經分別確定在案，有臺\n    灣高等法院被告前案紀錄表及如附表所示之判決書影本各1\n    份附卷可稽，茲檢察官聲請定其應執行之刑，本院審核認為\n    聲請為正當，爰裁定如主文所示應執行之刑。\n六、爰依刑事訴訟法第477 條第1項、刑法第53條、第51條第5款\n    ，裁定如主文。\n中    華    民    國   100    年    4     月    29    日\n                  刑事第六庭    審判長法  官  董武全\n                                      法  官  孫玉文\n                                      法  官  賴純慧\n以上正本證明與原本無異。\n如不服本裁定，應於收受本裁定後五日內向本院提出抗告狀。\n                                      書記官  蔡宜均\n中    華    民    國   100    年    4     月    29    日",
  "structure": {
    "main": "張銘德所處如附表編號1、2、10、11、13至28所示之刑，應執行\n有期徒刑陸年捌月。\n張銘德所處如附表編號3至9、12所示之刑，應執行有期徒刑參年\n捌月。",
    "reason": "一、本件聲請意旨略以：\n    上列受刑人因恐嚇等數罪，先後經判決確定如附表( 其中編\n    號13之犯罪日期應係95年11月7 日之誤繕) ，應依刑法第53\n    條、第51條第5款規定，分別就(1)附表編號1、2、10、11、\n    13至28所示之刑；及(2)附表編號3至9 、12所示之刑定其應\n    執行之刑，爰依刑事訴訟法第477條第1項聲請裁定等語。\n二、按裁判確定前犯數罪者，併合處罰之。數罪併罰，分別宣告\n    宣告多數有期徒刑者，於各刑中之最長期以上，各刑合併之\n    刑期以下，定其刑期。又數罪併罰，有二裁判以上者，依刑\n    法第51條規定，定其應執行刑，刑法第50條、第51條第5 款\n    、第53條分別定有明文。查本件受刑人犯如附表編號1、2、\n    10、11、13至28所示等罪之犯罪時間，均在同表編號1 判決\n    確定(97年6 月28日)之前；其犯如附表編號3至9、12所示等\n    罪之犯罪時間，均在同表編號3 判決確定(97年11月17日)之\n    前，揆諸前開規定，應分別依刑法第50條規定，定其應執行\n    刑，合先敘明。\n三、又刑事判決關於有期徒刑得易科罰金之規定，刑法第41條定\n    有明文，惟所犯為數罪併罰，其中之一罪雖得易科罰金，但\n    因與不得易科之他罪合併處罰之結果，於定執行刑時，祇須\n    將各罪之刑合併裁量，不得易科罰金合併執行，有司法院大\n    法官會議釋字第144號及第679號解釋可資參照，是本件如附\n    表編號1、3、4、7、8 、13及14所示之罪雖得易科罰金，但\n    因分別與其他不得易科罰金之罪合併處罰之結果，已不得易\n    科罰金合併執行。\n四、按法律上屬於自由裁量之事項，有其外部性界限及內部性界\n    限，並非概無拘束。依據法律之具體規定，法院應在其範圍\n    選擇為適當之裁判者，為外部性界限；而法院為裁判時，應\n    考量法律之目的，及法律秩序之理念所在者，為內部性界限\n    ，法院為裁判時，二者均不得有所踰越。故在數罪併罰，有\n    二裁判以上，定其應執行之刑時，固屬於法院自由裁量之事\n    項，然仍應受前揭外部性界限及內部性界限之拘束（最高法\n    院80年度台非字第473號判例及93年度台非字第192號裁判要\n    旨參照）。查本件受刑人所犯如附表編號3至4、5至8及15至\n    28所示案件，分別業經臺灣臺南地方法院以97年度易字第16\n    26號判決、97年度易字第1956號判決及本院99年度上訴字第\n    115 號判決分別定應執行有期徒刑六月、二年二月及四年確\n    定，有判決書1 份在卷可按。依前開說明，本院為最後事實\n    審法院再為定應執行刑之裁判時，自應受前開裁判所為定應\n    執行刑內部界限之拘束( 按編號11、12所示之罪，雖前經本\n    院97年度上訴字第1385號判決定應執行有期徒刑一年，惟編\n    號11所示之罪，應與編號1、2、10、13至28所示之刑定執行\n    刑；編號12所示之罪，應與編號3至9所示之刑，定執行刑，\n    已如前述，則該二罪原定應執行刑一年部分，自已失其效力\n    ，附此敘明)。\n五、綜此，本件受刑人因如附表所示等罪，先後經臺灣臺南地方\n    法院及本院判處如附表所示之刑，均經分別確定在案，有臺\n    灣高等法院被告前案紀錄表及如附表所示之判決書影本各1\n    份附卷可稽，茲檢察官聲請定其應執行之刑，本院審核認為\n    聲請為正當，爰裁定如主文所示應執行之刑。\n六、爰依刑事訴訟法第477 條第1項、刑法第53條、第51條第5款\n    ，裁定如主文。"
  },
  "search": "臺灣高等法院臺南分院刑事裁定100年度聲字第320號聲請人臺灣高等法院臺南分院檢察署檢察官受刑人張銘德上列聲請人因受刑人數罪併罰有二裁判以上，聲請定其應執行之刑（100年度執聲字第264號），本院裁定如下：主文張銘德所處如附表編號1、2、10、11、13至28所示之刑，應執行有期徒刑陸年捌月。張銘德所處如附表編號3至9、12所示之刑，應執行有期徒刑參年捌月。理由一、本件聲請意旨略以：上列受刑人因恐嚇等數罪，先後經判決確定如附表(其中編號13之犯罪日期應係95年11月7日之誤繕)，應依刑法第53條、第51條第5款規定，分別就(1)附表編號1、2、10、11、13至28所示之刑；及(2)附表編號3至9、12所示之刑定其應執行之刑，爰依刑事訴訟法第477條第1項聲請裁定等語。二、按裁判確定前犯數罪者，併合處罰之。數罪併罰，分別宣告宣告多數有期徒刑者，於各刑中之最長期以上，各刑合併之刑期以下，定其刑期。又數罪併罰，有二裁判以上者，依刑法第51條規定，定其應執行刑，刑法第50條、第51條第5款、第53條分別定有明文。查本件受刑人犯如附表編號1、2、10、11、13至28所示等罪之犯罪時間，均在同表編號1判決確定(97年6月28日)之前；其犯如附表編號3至9、12所示等罪之犯罪時間，均在同表編號3判決確定(97年11月17日)之前，揆諸前開規定，應分別依刑法第50條規定，定其應執行刑，合先敘明。三、又刑事判決關於有期徒刑得易科罰金之規定，刑法第41條定有明文，惟所犯為數罪併罰，其中之一罪雖得易科罰金，但因與不得易科之他罪合併處罰之結果，於定執行刑時，祇須將各罪之刑合併裁量，不得易科罰金合併執行，有司法院大法官會議釋字第144號及第679號解釋可資參照，是本件如附表編號1、3、4、7、8、13及14所示之罪雖得易科罰金，但因分別與其他不得易科罰金之罪合併處罰之結果，已不得易科罰金合併執行。四、按法律上屬於自由裁量之事項，有其外部性界限及內部性界限，並非概無拘束。依據法律之具體規定，法院應在其範圍選擇為適當之裁判者，為外部性界限；而法院為裁判時，應考量法律之目的，及法律秩序之理念所在者，為內部性界限，法院為裁判時，二者均不得有所踰越。故在數罪併罰，有二裁判以上，定其應執行之刑時，固屬於法院自由裁量之事項，然仍應受前揭外部性界限及內部性界限之拘束（最高法院80年度台非字第473號判例及93年度台非字第192號裁判要旨參照）。查本件受刑人所犯如附表編號3至4、5至8及15至28所示案件，分別業經臺灣臺南地方法院以97年度易字第1626號判決、97年度易字第1956號判決及本院99年度上訴字第115號判決分別定應執行有期徒刑六月、二年二月及四年確定，有判決書1份在卷可按。依前開說明，本院為最後事實審法院再為定應執行刑之裁判時，自應受前開裁判所為定應執行刑內部界限之拘束(按編號11、12所示之罪，雖前經本院97年度上訴字第1385號判決定應執行有期徒刑一年，惟編號11所示之罪，應與編號1、2、10、13至28所示之刑定執行刑；編號12所示之罪，應與編號3至9所示之刑，定執行刑，已如前述，則該二罪原定應執行刑一年部分，自已失其效力，附此敘明)。五、綜此，本件受刑人因如附表所示等罪，先後經臺灣臺南地方法院及本院判處如附表所示之刑，均經分別確定在案，有臺灣高等法院被告前案紀錄表及如附表所示之判決書影本各1份附卷可稽，茲檢察官聲請定其應執行之刑，本院審核認為聲請為正當，爰裁定如主文所示應執行之刑。六、爰依刑事訴訟法第477條第1項、刑法第53條、第51條第5款，裁定如主文。中華民國100年4月29日刑事第六庭審判長法官董武全法官孫玉文法官賴純慧以上正本證明與原本無異。如不服本裁定，應於收受本裁定後五日內向本院提出抗告狀。書記官蔡宜均中華民國100年4月29日",
  "characters": {
    "judges": [
      "董武全",
      "孫玉文",
      "賴純慧"
    ],
    "prosecutors": [

    ],
    "lawyers": [

    ],
    "clerks": [
      "蔡宜均"
    ],
    "plaintiffs": [

    ],
    "defendants": [

    ],
    "prosecutor_office": [
      "臺灣高等法院臺南分院檢察署檢察官"
    ],
    "creditors": [

    ],
    "debtors": [

    ],
    "judicial_associate_officer": [

    ]
  },
  "adjudged_at": "2011-04-29",
  "created_at": "2016-02-12 10:53:21",
  "updated_at": "2016-02-12 10:53:21"
}