{
  "identify": "TPD-100-簡-1555-20110429-1",
  "court": {
    "name": "臺灣臺北地方法院",
    "code": "TPD"
  },
  "division": {
    "name": "刑事",
    "code": "M"
  },
  "year": 100,
  "word": "簡",
  "number": "1555",
  "jcheck": "1",
  "reason": "詐欺",
  "content": "臺灣臺北地方法院刑事簡易判決         100年度簡字第1555號\n聲  請  人  臺灣臺北地方法院檢察署檢察官\n被      告  李騰祥\n上列被告因詐欺案件，經檢察官提起公訴（99年度偵字第16947\n號），因被告自白犯罪，本院認為宜以簡易判決處刑，判決如下\n：\n    主  文\n李騰祥幫助意圖為自己不法之所有，以詐術使人將本人之物交付\n，處拘役伍拾玖日，如易科罰金，以新臺幣壹仟元折算壹日。\n    事實及理由\n一、本件犯罪事實、證據及應適用之法條，除引用檢察官起訴書\n    （如附件）之記載外，並補充：（一）被告李騰祥以一幫助\n    詐欺取財行為，使年籍不詳綽號「阿忠」所屬犯罪集團成員\n    之成年人得以分別詐騙被害人曾士銘等5人，致其等陷於錯\n    誤，因而交付財物，侵害被害人曾士銘等數人之財產法益，\n    係一行為而觸犯數罪名，為想像競合犯，應依刑法第55條之\n    規定從一重處斷。（二）被告所為係犯刑法第339條第1項、\n    第30條第1項之幫助詐欺取財罪，爰依刑法第30條第2項之規\n    定，按正犯之刑減輕之。\n二、應依刑事訴訟法第449條第2項、第3項、第454條第2項，刑\n    法第339條第1項、第30條第1項前段、第2項、第41條第1項\n    前段，刑法施行法第1條之1，逕以簡易判決處刑如主文。\n如不服本判決，應於送達後10日內，向本院提出上訴狀。\n中    華    民    國   100    年    4     月    29    日\n                    刑事第五庭  法  官  蕭清清\n以上正本證明與原本無異。\n                                書記官  張華瓊\n中    華    民    國   100    年    5     月    2     日\n附錄本案論罪科刑法條全文\n刑法第339條\n意圖為自己或第三人不法之所有，以詐術使人將本人或第三人之\n物交付者，處5年以下有期徒刑、拘役或科或併科1千元以下罰金\n。\n以前項方法得財產上不法之利益或使第三人得之者，亦同。\n前二項之未遂犯罰之。",
  "structure": {
    "main": "李騰祥幫助意圖為自己不法之所有，以詐術使人將本人之物交付\n，處拘役伍拾玖日，如易科罰金，以新臺幣壹仟元折算壹日。",
    "fact": "一、本件犯罪事實、證據及應適用之法條，除引用檢察官起訴書\n    （如附件）之記載外，並補充：（一）被告李騰祥以一幫助\n    詐欺取財行為，使年籍不詳綽號「阿忠」所屬犯罪集團成員\n    之成年人得以分別詐騙被害人曾士銘等5人，致其等陷於錯\n    誤，因而交付財物，侵害被害人曾士銘等數人之財產法益，\n    係一行為而觸犯數罪名，為想像競合犯，應依刑法第55條之\n    規定從一重處斷。（二）被告所為係犯刑法第339條第1項、\n    第30條第1項之幫助詐欺取財罪，爰依刑法第30條第2項之規\n    定，按正犯之刑減輕之。\n二、應依刑事訴訟法第449條第2項、第3項、第454條第2項，刑\n    法第339條第1項、第30條第1項前段、第2項、第41條第1項\n    前段，刑法施行法第1條之1，逕以簡易判決處刑如主文。\n如不服本判決，應於送達後10日內，向本院提出上訴狀。",
    "reason": "一、本件犯罪事實、證據及應適用之法條，除引用檢察官起訴書\n    （如附件）之記載外，並補充：（一）被告李騰祥以一幫助\n    詐欺取財行為，使年籍不詳綽號「阿忠」所屬犯罪集團成員\n    之成年人得以分別詐騙被害人曾士銘等5人，致其等陷於錯\n    誤，因而交付財物，侵害被害人曾士銘等數人之財產法益，\n    係一行為而觸犯數罪名，為想像競合犯，應依刑法第55條之\n    規定從一重處斷。（二）被告所為係犯刑法第339條第1項、\n    第30條第1項之幫助詐欺取財罪，爰依刑法第30條第2項之規\n    定，按正犯之刑減輕之。\n二、應依刑事訴訟法第449條第2項、第3項、第454條第2項，刑\n    法第339條第1項、第30條第1項前段、第2項、第41條第1項\n    前段，刑法施行法第1條之1，逕以簡易判決處刑如主文。\n如不服本判決，應於送達後10日內，向本院提出上訴狀。"
  },
  "search": "臺灣臺北地方法院刑事簡易判決100年度簡字第1555號聲請人臺灣臺北地方法院檢察署檢察官被告李騰祥上列被告因詐欺案件，經檢察官提起公訴（99年度偵字第16947號），因被告自白犯罪，本院認為宜以簡易判決處刑，判決如下：主文李騰祥幫助意圖為自己不法之所有，以詐術使人將本人之物交付，處拘役伍拾玖日，如易科罰金，以新臺幣壹仟元折算壹日。事實及理由一、本件犯罪事實、證據及應適用之法條，除引用檢察官起訴書（如附件）之記載外，並補充：（一）被告李騰祥以一幫助詐欺取財行為，使年籍不詳綽號「阿忠」所屬犯罪集團成員之成年人得以分別詐騙被害人曾士銘等5人，致其等陷於錯誤，因而交付財物，侵害被害人曾士銘等數人之財產法益，係一行為而觸犯數罪名，為想像競合犯，應依刑法第55條之規定從一重處斷。（二）被告所為係犯刑法第339條第1項、第30條第1項之幫助詐欺取財罪，爰依刑法第30條第2項之規定，按正犯之刑減輕之。二、應依刑事訴訟法第449條第2項、第3項、第454條第2項，刑法第339條第1項、第30條第1項前段、第2項、第41條第1項前段，刑法施行法第1條之1，逕以簡易判決處刑如主文。如不服本判決，應於送達後10日內，向本院提出上訴狀。中華民國100年4月29日刑事第五庭法官蕭清清以上正本證明與原本無異。書記官張華瓊中華民國100年5月2日附錄本案論罪科刑法條全文刑法第339條意圖為自己或第三人不法之所有，以詐術使人將本人或第三人之物交付者，處5年以下有期徒刑、拘役或科或併科1千元以下罰金。以前項方法得財產上不法之利益或使第三人得之者，亦同。前二項之未遂犯罰之。",
  "characters": {
    "judges": [
      "蕭清清"
    ],
    "prosecutors": [

    ],
    "lawyers": [

    ],
    "clerks": [
      "張華瓊"
    ],
    "plaintiffs": [

    ],
    "defendants": [
      "李騰祥"
    ],
    "prosecutor_office": [
      "臺灣臺北地方法院檢察署檢察官"
    ],
    "creditors": [

    ],
    "debtors": [

    ],
    "judicial_associate_officer": [

    ]
  },
  "adjudged_at": "2011-04-29",
  "created_at": "2016-02-12 10:54:35",
  "updated_at": "2016-02-12 10:54:35"
}