{
  "identify": "TPD-100-訴緝-56-20110429-2",
  "court": {
    "name": "臺灣臺北地方法院",
    "code": "TPD"
  },
  "division": {
    "name": "刑事",
    "code": "M"
  },
  "year": 100,
  "word": "訴緝",
  "number": "56",
  "jcheck": "2",
  "reason": "毒品危害防制條例",
  "content": "臺灣臺北地方法院刑事判決             100年度訴緝字第56號\n公  訴  人  臺灣臺北地方法院檢察署檢察官\n被      告  王志偉\n上列被告因違反毒品危害防制條例案件，經檢察官提起公訴（九\n十八年度毒偵字第二四八七號），被告於準備程序中先就被訴事\n實為有罪之陳述，經本院告以簡式審判之旨，並聽取當事人之意\n見後，本院合議庭裁定行簡式審判程序後，本院判決如下：\n    主  文\n王志偉施用第一級毒品，累犯，處有期徒刑柒月。\n    事  實\n一、王志偉於民國九十四年間因妨害公務案件，經本院判決處有\n    期徒刑六月、四月，定應執行刑八月確定，於九十五年五月\n    十六日因縮刑期滿執行完畢，又因施用毒品案件，經本院九\n    十六年度毒聲字第七號裁定送觀察、勒戒後，認有繼續施用\n    毒品之傾向，復經本院以九十六年度毒聲字第四一三號裁定\n    令入戒治處所施以強制戒治，於九十七年四月二十八日認無\n    繼續強制戒治之必要予以釋放，並經臺灣臺北地方法院檢察\n    署檢察官以九十七年度戒毒偵字第九十號不起訴處分。詎仍\n    不知悔改，竟基於施用第一級毒品海洛因之犯意，於九十八\n    年六月十六日某時，在台北縣三重市（現已改制為新北市三\n    重區○○○路○段九十三巷一號三樓三○五室居處，以將海\n    洛因置入針筒內注射方式，施用海洛因一次。嗣因王志偉另\n    犯他案經通緝，於九十八年六月十六日下午三時七分許，為\n    警於台北市○○區○○路八十九號查獲，經徵得其同意，為\n    警採尿送驗，結果呈嗎啡、可待因陽性反應，始查悉上情。\n二、案經臺北市政府警察局大同分局報告臺灣士林地方法院檢察\n    署呈請臺灣高等法院檢察署檢察長令轉臺灣臺北地方法院檢\n    察署檢察官偵查起訴。\n    理  由\n一、上揭犯罪事實業據被告於審理中坦承不諱（本院一○○年度\n    訴緝字第五十六號卷第十六頁反面、第十九頁參照），且被\n    告於九十八年六月十六日在臺北市政府警察局大同分局寧夏\n    派出所採尿，其尿液經送台灣尖端先進生技醫藥股份有限公\n    司以ＧＣ／ＭＳ氣相層析／質譜儀法確認檢驗，結果發現呈\n    嗎啡、可待因陽性反應，有應受尿液檢驗人尿液檢體採集送\n    驗紀錄表、台灣尖端先進生技醫藥股份有限公司九十八年六\n    月二十五日濫用藥物檢驗報告各一紙附卷足憑（臺灣士林地\n    方法院檢察署九十八年度毒偵字第一四○七號卷第八、十頁\n    參照），足認被告任意性自白與事實相符，本件事證明確，\n    被告之犯行堪以認定，應依法論科。\n二、核被告所為，係犯毒品危害防制條例第十條第一項之施用第\n    一級毒品罪。被告持有海洛因後，進而施用，其持有之低度\n    行為應被其施用之高度行為所吸收，不另論罪。又被告有事\n    實欄所載之犯罪科刑執行情形，有臺灣高等法院被告前案紀\n    錄表在卷足憑，其於徒刑執行完畢後五年內故意再犯本件有\n    期徒刑以上之罪，為累犯，應依刑法第四十七條第一項之規\n    定加重其刑。爰審酌被告曾因施用毒品犯行執行觀察、勒戒\n    及強制戒治，仍不知悛悔，復再施用毒品，顯見被告無改過\n    之意，惟念其施用毒品乃戕害自己身心健康，尚未危及他人\n    ，犯後坦承犯行，態度良好等一切情狀，量處如主文所示之\n    刑。\n據上論斷，應依刑事訴訟法第二百七十三條之一第一項、第二百\n九十九條第一項前段，毒品危害防制條例第十條第一項，刑法第\n十一條前段、第四十七條第一項，判決如主文。\n本案經檢察官謝憲杰到庭執行職務\n中    華    民    國   100    年    4     月    29    日\n                  刑事第九庭    法  官  鄭富城\n以上正本證明與原本無異。\n如不服本判決應於收受送達後10日內向本院提出上訴書狀，並應\n敘述具體理由；其未敘述上訴理由者，應於上訴期間屆滿後20日\n內向本院補提理由書（均須按他造當事人之人數附繕）「切勿逕\n送上級法院」。\n                                書記官  顏淑華\n中    華    民    國   100    年    4     月    29    日\n附錄論罪科刑實體法條文：\n毒品危害防制條例第10條\n施用第一級毒品者，處 6 月以上 5 年以下有期徒刑。\n施用第二級毒品者，處 3 年以下有期徒刑。",
  "structure": {
    "main": "王志偉施用第一級毒品，累犯，處有期徒刑柒月。",
    "fact": "一、王志偉於民國九十四年間因妨害公務案件，經本院判決處有\n    期徒刑六月、四月，定應執行刑八月確定，於九十五年五月\n    十六日因縮刑期滿執行完畢，又因施用毒品案件，經本院九\n    十六年度毒聲字第七號裁定送觀察、勒戒後，認有繼續施用\n    毒品之傾向，復經本院以九十六年度毒聲字第四一三號裁定\n    令入戒治處所施以強制戒治，於九十七年四月二十八日認無\n    繼續強制戒治之必要予以釋放，並經臺灣臺北地方法院檢察\n    署檢察官以九十七年度戒毒偵字第九十號不起訴處分。詎仍\n    不知悔改，竟基於施用第一級毒品海洛因之犯意，於九十八\n    年六月十六日某時，在台北縣三重市（現已改制為新北市三\n    重區○○○路○段九十三巷一號三樓三○五室居處，以將海\n    洛因置入針筒內注射方式，施用海洛因一次。嗣因王志偉另\n    犯他案經通緝，於九十八年六月十六日下午三時七分許，為\n    警於台北市○○區○○路八十九號查獲，經徵得其同意，為\n    警採尿送驗，結果呈嗎啡、可待因陽性反應，始查悉上情。\n二、案經臺北市政府警察局大同分局報告臺灣士林地方法院檢察\n    署呈請臺灣高等法院檢察署檢察長令轉臺灣臺北地方法院檢\n    察署檢察官偵查起訴。",
    "reason": "一、上揭犯罪事實業據被告於審理中坦承不諱（本院一○○年度\n    訴緝字第五十六號卷第十六頁反面、第十九頁參照），且被\n    告於九十八年六月十六日在臺北市政府警察局大同分局寧夏\n    派出所採尿，其尿液經送台灣尖端先進生技醫藥股份有限公\n    司以ＧＣ／ＭＳ氣相層析／質譜儀法確認檢驗，結果發現呈\n    嗎啡、可待因陽性反應，有應受尿液檢驗人尿液檢體採集送\n    驗紀錄表、台灣尖端先進生技醫藥股份有限公司九十八年六\n    月二十五日濫用藥物檢驗報告各一紙附卷足憑（臺灣士林地\n    方法院檢察署九十八年度毒偵字第一四○七號卷第八、十頁\n    參照），足認被告任意性自白與事實相符，本件事證明確，\n    被告之犯行堪以認定，應依法論科。\n二、核被告所為，係犯毒品危害防制條例第十條第一項之施用第\n    一級毒品罪。被告持有海洛因後，進而施用，其持有之低度\n    行為應被其施用之高度行為所吸收，不另論罪。又被告有事\n    實欄所載之犯罪科刑執行情形，有臺灣高等法院被告前案紀\n    錄表在卷足憑，其於徒刑執行完畢後五年內故意再犯本件有\n    期徒刑以上之罪，為累犯，應依刑法第四十七條第一項之規\n    定加重其刑。爰審酌被告曾因施用毒品犯行執行觀察、勒戒\n    及強制戒治，仍不知悛悔，復再施用毒品，顯見被告無改過\n    之意，惟念其施用毒品乃戕害自己身心健康，尚未危及他人\n    ，犯後坦承犯行，態度良好等一切情狀，量處如主文所示之\n    刑。\n據上論斷，應依刑事訴訟法第二百七十三條之一第一項、第二百\n九十九條第一項前段，毒品危害防制條例第十條第一項，刑法第\n十一條前段、第四十七條第一項，判決如主文。\n本案經檢察官謝憲杰到庭執行職務\n中    華    民    國   100    年    4     月    29    日\n                  刑事第九庭    法  官  鄭富城\n以上正本證明與原本無異。\n如不服本判決應於收受送達後10日內向本院提出上訴書狀，並應\n敘述具體理由；其未敘述上訴理由者，應於上訴期間屆滿後20日\n內向本院補提理由書（均須按他造當事人之人數附繕）「切勿逕\n送上級法院」。\n                                書記官  顏淑華"
  },
  "search": "臺灣臺北地方法院刑事判決100年度訴緝字第56號公訴人臺灣臺北地方法院檢察署檢察官被告王志偉上列被告因違反毒品危害防制條例案件，經檢察官提起公訴（九十八年度毒偵字第二四八七號），被告於準備程序中先就被訴事實為有罪之陳述，經本院告以簡式審判之旨，並聽取當事人之意見後，本院合議庭裁定行簡式審判程序後，本院判決如下：主文王志偉施用第一級毒品，累犯，處有期徒刑柒月。事實一、王志偉於民國九十四年間因妨害公務案件，經本院判決處有期徒刑六月、四月，定應執行刑八月確定，於九十五年五月十六日因縮刑期滿執行完畢，又因施用毒品案件，經本院九十六年度毒聲字第七號裁定送觀察、勒戒後，認有繼續施用毒品之傾向，復經本院以九十六年度毒聲字第四一三號裁定令入戒治處所施以強制戒治，於九十七年四月二十八日認無繼續強制戒治之必要予以釋放，並經臺灣臺北地方法院檢察署檢察官以九十七年度戒毒偵字第九十號不起訴處分。詎仍不知悔改，竟基於施用第一級毒品海洛因之犯意，於九十八年六月十六日某時，在台北縣三重市（現已改制為新北市三重區○○○路○段九十三巷一號三樓三○五室居處，以將海洛因置入針筒內注射方式，施用海洛因一次。嗣因王志偉另犯他案經通緝，於九十八年六月十六日下午三時七分許，為警於台北市○○區○○路八十九號查獲，經徵得其同意，為警採尿送驗，結果呈嗎啡、可待因陽性反應，始查悉上情。二、案經臺北市政府警察局大同分局報告臺灣士林地方法院檢察署呈請臺灣高等法院檢察署檢察長令轉臺灣臺北地方法院檢察署檢察官偵查起訴。理由一、上揭犯罪事實業據被告於審理中坦承不諱（本院一○○年度訴緝字第五十六號卷第十六頁反面、第十九頁參照），且被告於九十八年六月十六日在臺北市政府警察局大同分局寧夏派出所採尿，其尿液經送台灣尖端先進生技醫藥股份有限公司以ＧＣ／ＭＳ氣相層析／質譜儀法確認檢驗，結果發現呈嗎啡、可待因陽性反應，有應受尿液檢驗人尿液檢體採集送驗紀錄表、台灣尖端先進生技醫藥股份有限公司九十八年六月二十五日濫用藥物檢驗報告各一紙附卷足憑（臺灣士林地方法院檢察署九十八年度毒偵字第一四○七號卷第八、十頁參照），足認被告任意性自白與事實相符，本件事證明確，被告之犯行堪以認定，應依法論科。二、核被告所為，係犯毒品危害防制條例第十條第一項之施用第一級毒品罪。被告持有海洛因後，進而施用，其持有之低度行為應被其施用之高度行為所吸收，不另論罪。又被告有事實欄所載之犯罪科刑執行情形，有臺灣高等法院被告前案紀錄表在卷足憑，其於徒刑執行完畢後五年內故意再犯本件有期徒刑以上之罪，為累犯，應依刑法第四十七條第一項之規定加重其刑。爰審酌被告曾因施用毒品犯行執行觀察、勒戒及強制戒治，仍不知悛悔，復再施用毒品，顯見被告無改過之意，惟念其施用毒品乃戕害自己身心健康，尚未危及他人，犯後坦承犯行，態度良好等一切情狀，量處如主文所示之刑。據上論斷，應依刑事訴訟法第二百七十三條之一第一項、第二百九十九條第一項前段，毒品危害防制條例第十條第一項，刑法第十一條前段、第四十七條第一項，判決如主文。本案經檢察官謝憲杰到庭執行職務中華民國100年4月29日刑事第九庭法官鄭富城以上正本證明與原本無異。如不服本判決應於收受送達後10日內向本院提出上訴書狀，並應敘述具體理由；其未敘述上訴理由者，應於上訴期間屆滿後20日內向本院補提理由書（均須按他造當事人之人數附繕）「切勿逕送上級法院」。書記官顏淑華中華民國100年4月29日附錄論罪科刑實體法條文：毒品危害防制條例第10條施用第一級毒品者，處6月以上5年以下有期徒刑。施用第二級毒品者，處3年以下有期徒刑。",
  "characters": {
    "judges": [
      "鄭富城"
    ],
    "prosecutors": [
      "謝憲杰"
    ],
    "lawyers": [

    ],
    "clerks": [
      "顏淑華"
    ],
    "plaintiffs": [

    ],
    "defendants": [
      "王志偉"
    ],
    "prosecutor_office": [
      "臺灣臺北地方法院檢察署檢察官"
    ],
    "creditors": [

    ],
    "debtors": [

    ],
    "judicial_associate_officer": [

    ]
  },
  "adjudged_at": "2011-04-29",
  "created_at": "2016-02-12 10:54:51",
  "updated_at": "2016-02-12 10:54:51"
}