{
  "identify": "TYD-100-審交簡-43-20110429-1",
  "court": {
    "name": "臺灣桃園地方法院",
    "code": "TYD"
  },
  "division": {
    "name": "刑事",
    "code": "M"
  },
  "year": 100,
  "word": "審交簡",
  "number": "43",
  "jcheck": "1",
  "reason": "肇事遺棄罪",
  "content": "臺灣桃園地方法院刑事簡易判決       100年度審交簡字第43號\n公  訴  人  臺灣桃園地方法院檢察署檢察官\n被      告  胡菖原\n選任辯護人  蘇明淵律師\n上列被告因肇事遺棄罪案件，經檢察官提起公訴（99年度調偵字\n第673 號），被告自白犯罪，本院認為宜以簡易判決處刑，爰不\n經通常審判程序，逕以簡易判決處刑如下：\n    主  文\n胡菖原駕駛動力交通工具肇事，致人受傷而逃逸，處有期徒刑陸\n月，如易科罰金，以新臺幣壹仟元折算壹日。緩刑貳年，緩刑期\n間內並應給付張乃敏新臺幣拾貳萬伍千元，給付方式為自民國一\n百年五月十五日起，按月於每月十五日給付張乃敏新臺幣壹萬貳\n千伍百元，直至全部清償為止，如有一期未給付，視為全部到期\n。\n    事實及理由\n一、本件證據部分除補充被告胡菖原於本院準備程序時之自白及\n    告訴人張乃敏於本院準備程序時之指訴外，餘犯罪事實及證\n    據均引用如附件檢察官起訴書所載（另被告胡菖原被訴過失\n    傷害罪部分，業據告訴人張乃敏撤回告訴，此部分另由本院\n    判決公訴不受理）。\n二、核被告所為，係犯刑法第185 條之4 之駕駛動力交通工具肇\n    事，致人受傷而逃逸罪。爰審酌被告肇事傷人後逃逸，罔顧\n    傷者安危，使被害人民事損害求償困難，惟被告於犯罪後終\n    能坦承犯行，並已與告訴人張乃敏達成和解且已賠償部分損\n    害等一切情狀，量處如主文所示之刑，並諭知易科罰金之折\n    算標準，以示懲儆。末查，被告前未曾因故意犯罪受有期徒\n    刑以上刑之宣告，有卷附臺灣高等法院被告前案紀錄表1 份\n    足稽，其因一時失慮，致罹刑典，信其經此刑之宣告，應能\n    知所警惕，而無再犯之虞，復參以告訴人亦到庭表示願意給\n    予被告緩刑之機會，本院因認所宣告之刑以暫不執行為適當\n    ，爰依刑法第74條第1 項第1 款之規定，併諭知如主文所示\n    之緩刑期間，併依同法第74條第2 項第3 款之規定，命被告\n    向告訴人支付如主文所示之金額，以勵自新。\n三、據上論斷，應依刑事訴訟法第449 條第2 項、第3 項、第45\n    4 條第2 項，刑法第185 條之4 、第41條第1 項前段、第74\n    條第1 項第1 款、第2 項第3 款，逕以簡易判決處刑如主文\n    。\n四、本件係依刑事訴訟法第451 條之1 第3 項之請求所為之科刑\n    判決，依同法第455 條之1 第2 項規定，被告、檢察官均不\n    得上訴。\n中    華    民    國   100    年    4     月    29    日\n                      刑事庭  法  官  潘怡華\n以上正本證明與原本無異。\n                              書記官  施春祝\n中    華    民    國   100    年    4     月    29    日\n附錄論罪科刑依據之法條：\n中華民國刑法第185條 之4\n駕駛動力交通工具肇事，致人死傷而逃逸者，處6 月以上5 年以\n下有期徒刑。\n附件：\n臺灣桃園地方法院檢察署檢察官起訴書\n                                     99年度調偵字第673號\n    被      告  胡菖原  男  58歲（民國○○年○○月○○日生）\n                        住桃園縣楊梅市○○路○段276號\n                        國民身分證統一編號：Ｚ000000000號\n上被告因過失傷害等案件，已經偵查終結，認應該提起公訴，茲\n將犯罪事實及證據並所犯法條分敘如下：\n        犯罪事實\n一、胡菖原明知機器腳踏車應依標誌或標線之規定行駛於道路，\n    竟於民國99年2月26日晚間9時19分許，騎乘車牌號碼003-DJ\n    H號之重型機車，欲自桃園縣楊梅市○○路84號前橫越中興\n    路前往對向，於穿越道路時，原應注意車前狀況，並隨時採\n    取必要安全措施，而依當時天候晴、夜間有照明、道路型態\n    為直路、路面狀況無缺陷且無障礙物、視距良好等，並無不\n    能注意之情事，胡菖原竟疏未注意車前狀況逕行違規穿越中\n    興路，而撞擊該時沿中興路往龍潭方向行駛同行經該處，由\n    張乃敏所騎乘車牌號碼YAF-470號重型機車，致張乃敏人車\n    倒地，受有右肱骨幹閉鎖性骨折之傷害。胡菖原肇事後未停\n    車察看，反再度騎乘機車後退，避開已倒地之YAF-470號重\n    型機車再另催油門前往對向中興路89號路旁停車後，甫下車\n    前往YAF-470號重型機車倒地處察看張乃敏，惟未施以任何\n    救護行為，並為躲避責任，未留下姓名及聯絡資料亦未訴警\n    處理，即再度離開現場，並以借用廁所為由進入沈秀琴（另\n    為不起訴處分）夫妻所經營中興路89號華生藥局店內躲藏，\n    嗣救護車到場搭載張乃敏離去後，始趁隙逃逸。嗣經張乃敏\n    訴警處理，經警調取路口及華生藥局監視錄影系統，另經由\n    沈秀琴提供該日可能到店之顧客名單後，始循線查悉前情。\n二、案經張乃敏告訴及桃園縣政府警察局楊梅分局報告偵辦。\n          證據並所犯法條\n一、證據清單及待證事實：\n  ┌──┬──────────┬─────────────────────┐\n  │編號│證    據    方    法│待           證           事           實 │\n  ├──┼──────────┼─────────────────────┤\n  │一  │被告胡菖原供述      │1.其騎乘003-DJH號重型機車自桃園縣楊梅市中 │\n  │    │                    │  興路84號前未遵行道路標線指示，違規橫越中│\n  │    │                    │  興路至對向，且疏未注意車前狀況，不慎撞擊│\n  │    │                    │  該時正沿中興路往龍潭方向騎乘機車之告訴人│\n  │    │                    │  張乃敏，致告訴人受有傷害。              │\n  │    │                    │2.肇事後確未提供或對告訴人施以救護、救助行│\n  │    │                    │  為，未留下姓名、聯絡資料，或訴警處理等，│\n  │    │                    │  隨即離開現場進入華生藥局內。            │\n  ├──┼──────────┼─────────────────────┤\n  │二  │告訴人張乃敏指訴    │1.其騎乘YAF-470號重型機車沿中興路往龍潭方 │\n  │    │                    │  向行駛，行經中興路84號前時，遭違規穿越中│\n  │    │                    │  興路，由胡菖原所騎乘之重型機車碰撞，致人│\n  │    │                    │  車倒地，並受有右肱骨幹閉鎖性骨折等傷害。│\n  │    │                    │2.被告肇事後未對其施以救護行為，未報警亦未│\n  │    │                    │  叫救護車，隨即騎乘機車逃逸，令其一人在道│\n  │    │                    │  路中央等待救援。                        │\n  ├──┼──────────┼─────────────────────┤\n  │三  │同案被告沈秀琴供述  │胡菖原確於99年2月26日晚間以借用廁所為由進 │\n  │    │                    │入其夫妻所經營之華生藥局內。              │\n  ├──┼──────────┼─────────────────────┤\n  │四  │路口監視器翻拍相片16│本件交通事故發生係因銀色重型機車未遵行道路│\n  │    │張                  │標線指示，違規橫越中興路至對向，且疏未注意│\n  │    │                    │車前狀況，不慎撞擊該時正沿中興路往龍潭方向│\n  │    │                    │騎乘機車之機車騎士。發生碰撞後，銀色重型機│\n  │    │                    │車後退避開倒地機車後，再前行往對向駛去，停│\n  │    │                    │放於路旁後，雖折回查看，惟嗣又離去。      │\n  ├──┼──────────┼─────────────────────┤\n  │五  │華生藥局監視器翻拍相│胡菖原確於99年2月26日晚間有進入華生藥局。 │\n  │    │片2張               │                                          │\n  ├──┼──────────┼─────────────────────┤\n  │六  │天晟醫院診斷證明書1 │張乃敏確因此交通事故受有右肱骨幹閉鎖性骨折│\n  │    │件                  │之傷害。                                  │\n  ├──┼──────────┼─────────────────────┤\n  │七  │桃園縣政府警察局楊梅│1.事故現場情形。                          │\n  │    │分局道路交通事故現場│2.員警到場時，肇事者及肇事車輛均未停留於現│\n  │    │圖及交通事故調查報告│  場，亦未留任何資料可供查詢。            │\n  │    │表(一)(二)各1件暨現場相 │                                          │\n  │    │片6張               │                                          │\n  ├──┼──────────┼─────────────────────┤\n  │八  │桃園縣政府警察局楊梅│2車車損情形                               │\n  │    │分局刑案現場相片14張│                                          │\n  └──┴──────────┴─────────────────────┘\n二、按「道路交通管理處罰條例第62條第1項規定：『汽車駕駛\n    人，駕駛汽車肇事致人受傷或死亡，應即採取救護或其他必\n    要措施，並向警察機關報告，不得駛離』，核其立法意旨，\n    概以道路交通事故之發生，常非於己之鄰親家里，時有告救\n    不能情事，乃科以肇事者須即採取救護或其他必要措施，並\n    應向警察機關報告之法定義務，以防因就醫延誤致生無謂傷\n    亡，並俾得通知傷亡者家屬到場，以明責任，是凡肇事人於\n    行車肇事致人受傷或死亡，未即採取救護或其他必要措施，\n    並向警察機關報告，即駕車駛離現場者，均應依該規定處罰\n    （本院86年度交抗字第63號裁定意旨參照）。又刑法第185\n    條之4駕駛動力交通工具肇事致人死傷而逃逸罪係於88年4月\n    21日增訂公布，並自同年4月23日開始生效，其增設本條文\n    之立法目的，乃為維護交通，增進行車安全，促使當事人於\n    事故發生時，能對被害人即時救護，減少死傷，以保護他人\n    權益並維護社會秩序。又其立法精神在於交通事故一旦發生\n    ，且發生人員傷亡之情況，不論是撞人或被撞，或是因其他\n    事故而造成死傷，只要是在駕駛動力交通工具過程內所發生\n    者，參與這整個事故過程的當事人皆應協助防止死傷之擴大\n    ，蓋如駕駛人於事故發生後，隨即駕車逃離現場，不僅使肇\n    事責任認定困難，更可能使受傷之人喪失生命或求償無門，\n    是本條所欲規範者乃當事人於交通事故發生時（不論其有無\n    故意或過失）遺棄被害人於不顧的逃逸行為，且若謂當事人\n    之救護義務須視其有無故意、過失而定，則不僅有違刑法第\n    185條之4的立法目的與精神，本條文之功能亦將喪失殆盡。\n    故所謂駕駛動力交通工具肇事，乃指駕駛動力交通工具發生\n    交通事故，非指因故意或過失導致事故發生而逃逸者，始成\n    立本罪。就上揭規定及條文參互以觀，可知汽車駕駛人駕駛\n    汽車發生交通事故，不論其責任之歸屬為何，即有義務停留\n    在肇事現場，採取救護或其他必要措施，並向警察機關報告\n    ，以保護他人權益，並釐清肇事責任，自不待言。」台灣高\n    等法院94年交抗字第10號判決載有明文。查本件被告既未主\n    動電請救護單位對告訴人施以救護或訴警處理，更未留下姓\n    名、聯絡方式與告訴人，俾利告訴人民刑事追償及司法權責\n    單位釐清事故責任，甚且藉故進入華生藥局廁所內躲藏，以\n    規避事故現場可能有員警訪查之可能，顯見被告主觀上肇事\n    逃逸之意甚堅，是揆諸前揭判決，尚難僅因被告客觀上有移\n    置告訴人行為即遽免被告肇事逃逸之罪責。\n三、核被告所為係犯刑法第185條之4條肇事逃逸罪及同法第284\n    條第1項前段之過失傷害罪嫌。另被告所犯上開2罪間，犯意\n    各別，罪名互殊，請予分論併罰。\n四、依刑事訴訟法第251條第1項提起公訴。\n    此  致\n臺灣桃園地方法院\n中    華    民    國    99    年    12    月    7     日\n                              檢  察  官  柯 怡 如\n本件證明與原本無異\n中    華    民    國   100    年    1     月    5     日\n                              書  記  官  林 應 隆\n收受原本日期100年1月5日\n所犯法條\n中華民國刑法第185條之4\n（肇事遺棄罪）\n駕駛動力交通工具肇事，致人死傷而逃逸者，處 6 月以上 5 年\n以下有期徒刑。\n中華民國刑法第284條\n（過失傷害罪）\n因過失傷害人者，處 6 月以下有期徒刑、拘役或 5 百元以下罰\n金，致重傷者，處 1 年以下有期徒刑、拘役或 5 百元以下罰金\n。\n從事業務之人，因業務上之過失傷害人者，處 1 年以下有期徒\n刑、拘役或 1 千元以下罰金，致重傷者，處 3 年以下有期徒刑\n、拘役或 2 千元以下罰金。",
  "structure": {
    "main": "胡菖原駕駛動力交通工具肇事，致人受傷而逃逸，處有期徒刑陸\n月，如易科罰金，以新臺幣壹仟元折算壹日。緩刑貳年，緩刑期\n間內並應給付張乃敏新臺幣拾貳萬伍千元，給付方式為自民國一\n百年五月十五日起，按月於每月十五日給付張乃敏新臺幣壹萬貳\n千伍百元，直至全部清償為止，如有一期未給付，視為全部到期\n。",
    "fact": "一、本件證據部分除補充被告胡菖原於本院準備程序時之自白及\n    告訴人張乃敏於本院準備程序時之指訴外，餘犯罪事實及證\n    據均引用如附件檢察官起訴書所載（另被告胡菖原被訴過失\n    傷害罪部分，業據告訴人張乃敏撤回告訴，此部分另由本院\n    判決公訴不受理）。\n二、核被告所為，係犯刑法第185 條之4 之駕駛動力交通工具肇\n    事，致人受傷而逃逸罪。爰審酌被告肇事傷人後逃逸，罔顧\n    傷者安危，使被害人民事損害求償困難，惟被告於犯罪後終\n    能坦承犯行，並已與告訴人張乃敏達成和解且已賠償部分損\n    害等一切情狀，量處如主文所示之刑，並諭知易科罰金之折\n    算標準，以示懲儆。末查，被告前未曾因故意犯罪受有期徒\n    刑以上刑之宣告，有卷附臺灣高等法院被告前案紀錄表1 份\n    足稽，其因一時失慮，致罹刑典，信其經此刑之宣告，應能\n    知所警惕，而無再犯之虞，復參以告訴人亦到庭表示願意給\n    予被告緩刑之機會，本院因認所宣告之刑以暫不執行為適當\n    ，爰依刑法第74條第1 項第1 款之規定，併諭知如主文所示\n    之緩刑期間，併依同法第74條第2 項第3 款之規定，命被告\n    向告訴人支付如主文所示之金額，以勵自新。\n三、據上論斷，應依刑事訴訟法第449 條第2 項、第3 項、第45\n    4 條第2 項，刑法第185 條之4 、第41條第1 項前段、第74\n    條第1 項第1 款、第2 項第3 款，逕以簡易判決處刑如主文\n    。\n四、本件係依刑事訴訟法第451 條之1 第3 項之請求所為之科刑\n    判決，依同法第455 條之1 第2 項規定，被告、檢察官均不\n    得上訴。",
    "reason": "一、本件證據部分除補充被告胡菖原於本院準備程序時之自白及\n    告訴人張乃敏於本院準備程序時之指訴外，餘犯罪事實及證\n    據均引用如附件檢察官起訴書所載（另被告胡菖原被訴過失\n    傷害罪部分，業據告訴人張乃敏撤回告訴，此部分另由本院\n    判決公訴不受理）。\n二、核被告所為，係犯刑法第185 條之4 之駕駛動力交通工具肇\n    事，致人受傷而逃逸罪。爰審酌被告肇事傷人後逃逸，罔顧\n    傷者安危，使被害人民事損害求償困難，惟被告於犯罪後終\n    能坦承犯行，並已與告訴人張乃敏達成和解且已賠償部分損\n    害等一切情狀，量處如主文所示之刑，並諭知易科罰金之折\n    算標準，以示懲儆。末查，被告前未曾因故意犯罪受有期徒\n    刑以上刑之宣告，有卷附臺灣高等法院被告前案紀錄表1 份\n    足稽，其因一時失慮，致罹刑典，信其經此刑之宣告，應能\n    知所警惕，而無再犯之虞，復參以告訴人亦到庭表示願意給\n    予被告緩刑之機會，本院因認所宣告之刑以暫不執行為適當\n    ，爰依刑法第74條第1 項第1 款之規定，併諭知如主文所示\n    之緩刑期間，併依同法第74條第2 項第3 款之規定，命被告\n    向告訴人支付如主文所示之金額，以勵自新。\n三、據上論斷，應依刑事訴訟法第449 條第2 項、第3 項、第45\n    4 條第2 項，刑法第185 條之4 、第41條第1 項前段、第74\n    條第1 項第1 款、第2 項第3 款，逕以簡易判決處刑如主文\n    。\n四、本件係依刑事訴訟法第451 條之1 第3 項之請求所為之科刑\n    判決，依同法第455 條之1 第2 項規定，被告、檢察官均不\n    得上訴。"
  },
  "search": "臺灣桃園地方法院刑事簡易判決100年度審交簡字第43號公訴人臺灣桃園地方法院檢察署檢察官被告胡菖原選任辯護人蘇明淵律師上列被告因肇事遺棄罪案件，經檢察官提起公訴（99年度調偵字第673號），被告自白犯罪，本院認為宜以簡易判決處刑，爰不經通常審判程序，逕以簡易判決處刑如下：主文胡菖原駕駛動力交通工具肇事，致人受傷而逃逸，處有期徒刑陸月，如易科罰金，以新臺幣壹仟元折算壹日。緩刑貳年，緩刑期間內並應給付張乃敏新臺幣拾貳萬伍千元，給付方式為自民國一百年五月十五日起，按月於每月十五日給付張乃敏新臺幣壹萬貳千伍百元，直至全部清償為止，如有一期未給付，視為全部到期。事實及理由一、本件證據部分除補充被告胡菖原於本院準備程序時之自白及告訴人張乃敏於本院準備程序時之指訴外，餘犯罪事實及證據均引用如附件檢察官起訴書所載（另被告胡菖原被訴過失傷害罪部分，業據告訴人張乃敏撤回告訴，此部分另由本院判決公訴不受理）。二、核被告所為，係犯刑法第185條之4之駕駛動力交通工具肇事，致人受傷而逃逸罪。爰審酌被告肇事傷人後逃逸，罔顧傷者安危，使被害人民事損害求償困難，惟被告於犯罪後終能坦承犯行，並已與告訴人張乃敏達成和解且已賠償部分損害等一切情狀，量處如主文所示之刑，並諭知易科罰金之折算標準，以示懲儆。末查，被告前未曾因故意犯罪受有期徒刑以上刑之宣告，有卷附臺灣高等法院被告前案紀錄表1份足稽，其因一時失慮，致罹刑典，信其經此刑之宣告，應能知所警惕，而無再犯之虞，復參以告訴人亦到庭表示願意給予被告緩刑之機會，本院因認所宣告之刑以暫不執行為適當，爰依刑法第74條第1項第1款之規定，併諭知如主文所示之緩刑期間，併依同法第74條第2項第3款之規定，命被告向告訴人支付如主文所示之金額，以勵自新。三、據上論斷，應依刑事訴訟法第449條第2項、第3項、第454條第2項，刑法第185條之4、第41條第1項前段、第74條第1項第1款、第2項第3款，逕以簡易判決處刑如主文。四、本件係依刑事訴訟法第451條之1第3項之請求所為之科刑判決，依同法第455條之1第2項規定，被告、檢察官均不得上訴。中華民國100年4月29日刑事庭法官潘怡華以上正本證明與原本無異。書記官施春祝中華民國100年4月29日附錄論罪科刑依據之法條：中華民國刑法第185條之4駕駛動力交通工具肇事，致人死傷而逃逸者，處6月以上5年以下有期徒刑。附件：臺灣桃園地方法院檢察署檢察官起訴書99年度調偵字第673號被告胡菖原男58歲（民國○○年○○月○○日生）住桃園縣楊梅市○○路○段276號國民身分證統一編號：Ｚ000000000號上被告因過失傷害等案件，已經偵查終結，認應該提起公訴，茲將犯罪事實及證據並所犯法條分敘如下：犯罪事實一、胡菖原明知機器腳踏車應依標誌或標線之規定行駛於道路，竟於民國99年2月26日晚間9時19分許，騎乘車牌號碼003-DJH號之重型機車，欲自桃園縣楊梅市○○路84號前橫越中興路前往對向，於穿越道路時，原應注意車前狀況，並隨時採取必要安全措施，而依當時天候晴、夜間有照明、道路型態為直路、路面狀況無缺陷且無障礙物、視距良好等，並無不能注意之情事，胡菖原竟疏未注意車前狀況逕行違規穿越中興路，而撞擊該時沿中興路往龍潭方向行駛同行經該處，由張乃敏所騎乘車牌號碼YAF-470號重型機車，致張乃敏人車倒地，受有右肱骨幹閉鎖性骨折之傷害。胡菖原肇事後未停車察看，反再度騎乘機車後退，避開已倒地之YAF-470號重型機車再另催油門前往對向中興路89號路旁停車後，甫下車前往YAF-470號重型機車倒地處察看張乃敏，惟未施以任何救護行為，並為躲避責任，未留下姓名及聯絡資料亦未訴警處理，即再度離開現場，並以借用廁所為由進入沈秀琴（另為不起訴處分）夫妻所經營中興路89號華生藥局店內躲藏，嗣救護車到場搭載張乃敏離去後，始趁隙逃逸。嗣經張乃敏訴警處理，經警調取路口及華生藥局監視錄影系統，另經由沈秀琴提供該日可能到店之顧客名單後，始循線查悉前情。二、案經張乃敏告訴及桃園縣政府警察局楊梅分局報告偵辦。證據並所犯法條一、證據清單及待證事實：┌──┬──────────┬─────────────────────┐│編號│證據方法│待證事實│├──┼──────────┼─────────────────────┤│一│被告胡菖原供述│1.其騎乘003-DJH號重型機車自桃園縣楊梅市中││││興路84號前未遵行道路標線指示，違規橫越中││││興路至對向，且疏未注意車前狀況，不慎撞擊││││該時正沿中興路往龍潭方向騎乘機車之告訴人││││張乃敏，致告訴人受有傷害。││││2.肇事後確未提供或對告訴人施以救護、救助行││││為，未留下姓名、聯絡資料，或訴警處理等，││││隨即離開現場進入華生藥局內。│├──┼──────────┼─────────────────────┤│二│告訴人張乃敏指訴│1.其騎乘YAF-470號重型機車沿中興路往龍潭方││││向行駛，行經中興路84號前時，遭違規穿越中││││興路，由胡菖原所騎乘之重型機車碰撞，致人││││車倒地，並受有右肱骨幹閉鎖性骨折等傷害。││││2.被告肇事後未對其施以救護行為，未報警亦未││││叫救護車，隨即騎乘機車逃逸，令其一人在道││││路中央等待救援。│├──┼──────────┼─────────────────────┤│三│同案被告沈秀琴供述│胡菖原確於99年2月26日晚間以借用廁所為由進││││入其夫妻所經營之華生藥局內。│├──┼──────────┼─────────────────────┤│四│路口監視器翻拍相片16│本件交通事故發生係因銀色重型機車未遵行道路│││張│標線指示，違規橫越中興路至對向，且疏未注意││││車前狀況，不慎撞擊該時正沿中興路往龍潭方向││││騎乘機車之機車騎士。發生碰撞後，銀色重型機││││車後退避開倒地機車後，再前行往對向駛去，停││││放於路旁後，雖折回查看，惟嗣又離去。│├──┼──────────┼─────────────────────┤│五│華生藥局監視器翻拍相│胡菖原確於99年2月26日晚間有進入華生藥局。│││片2張││├──┼──────────┼─────────────────────┤│六│天晟醫院診斷證明書1│張乃敏確因此交通事故受有右肱骨幹閉鎖性骨折│││件│之傷害。│├──┼──────────┼─────────────────────┤│七│桃園縣政府警察局楊梅│1.事故現場情形。│││分局道路交通事故現場│2.員警到場時，肇事者及肇事車輛均未停留於現│││圖及交通事故調查報告│場，亦未留任何資料可供查詢。│││表(一)(二)各1件暨現場相││││片6張││├──┼──────────┼─────────────────────┤│八│桃園縣政府警察局楊梅│2車車損情形│││分局刑案現場相片14張││└──┴──────────┴─────────────────────┘二、按「道路交通管理處罰條例第62條第1項規定：『汽車駕駛人，駕駛汽車肇事致人受傷或死亡，應即採取救護或其他必要措施，並向警察機關報告，不得駛離』，核其立法意旨，概以道路交通事故之發生，常非於己之鄰親家里，時有告救不能情事，乃科以肇事者須即採取救護或其他必要措施，並應向警察機關報告之法定義務，以防因就醫延誤致生無謂傷亡，並俾得通知傷亡者家屬到場，以明責任，是凡肇事人於行車肇事致人受傷或死亡，未即採取救護或其他必要措施，並向警察機關報告，即駕車駛離現場者，均應依該規定處罰（本院86年度交抗字第63號裁定意旨參照）。又刑法第185條之4駕駛動力交通工具肇事致人死傷而逃逸罪係於88年4月21日增訂公布，並自同年4月23日開始生效，其增設本條文之立法目的，乃為維護交通，增進行車安全，促使當事人於事故發生時，能對被害人即時救護，減少死傷，以保護他人權益並維護社會秩序。又其立法精神在於交通事故一旦發生，且發生人員傷亡之情況，不論是撞人或被撞，或是因其他事故而造成死傷，只要是在駕駛動力交通工具過程內所發生者，參與這整個事故過程的當事人皆應協助防止死傷之擴大，蓋如駕駛人於事故發生後，隨即駕車逃離現場，不僅使肇事責任認定困難，更可能使受傷之人喪失生命或求償無門，是本條所欲規範者乃當事人於交通事故發生時（不論其有無故意或過失）遺棄被害人於不顧的逃逸行為，且若謂當事人之救護義務須視其有無故意、過失而定，則不僅有違刑法第185條之4的立法目的與精神，本條文之功能亦將喪失殆盡。故所謂駕駛動力交通工具肇事，乃指駕駛動力交通工具發生交通事故，非指因故意或過失導致事故發生而逃逸者，始成立本罪。就上揭規定及條文參互以觀，可知汽車駕駛人駕駛汽車發生交通事故，不論其責任之歸屬為何，即有義務停留在肇事現場，採取救護或其他必要措施，並向警察機關報告，以保護他人權益，並釐清肇事責任，自不待言。」台灣高等法院94年交抗字第10號判決載有明文。查本件被告既未主動電請救護單位對告訴人施以救護或訴警處理，更未留下姓名、聯絡方式與告訴人，俾利告訴人民刑事追償及司法權責單位釐清事故責任，甚且藉故進入華生藥局廁所內躲藏，以規避事故現場可能有員警訪查之可能，顯見被告主觀上肇事逃逸之意甚堅，是揆諸前揭判決，尚難僅因被告客觀上有移置告訴人行為即遽免被告肇事逃逸之罪責。三、核被告所為係犯刑法第185條之4條肇事逃逸罪及同法第284條第1項前段之過失傷害罪嫌。另被告所犯上開2罪間，犯意各別，罪名互殊，請予分論併罰。四、依刑事訴訟法第251條第1項提起公訴。此致臺灣桃園地方法院中華民國99年12月7日檢察官柯怡如本件證明與原本無異中華民國100年1月5日書記官林應隆收受原本日期100年1月5日所犯法條中華民國刑法第185條之4（肇事遺棄罪）駕駛動力交通工具肇事，致人死傷而逃逸者，處6月以上5年以下有期徒刑。中華民國刑法第284條（過失傷害罪）因過失傷害人者，處6月以下有期徒刑、拘役或5百元以下罰金，致重傷者，處1年以下有期徒刑、拘役或5百元以下罰金。從事業務之人，因業務上之過失傷害人者，處1年以下有期徒刑、拘役或1千元以下罰金，致重傷者，處3年以下有期徒刑、拘役或2千元以下罰金。",
  "characters": {
    "judges": [
      "潘怡華"
    ],
    "prosecutors": [

    ],
    "lawyers": [
      "蘇明淵"
    ],
    "clerks": [
      "施春祝"
    ],
    "plaintiffs": [

    ],
    "defendants": [
      "胡菖原",
      "胡菖原  男  58歲（民國○○年○○月○○日生）"
    ],
    "prosecutor_office": [
      "臺灣桃園地方法院檢察署檢察官"
    ],
    "creditors": [

    ],
    "debtors": [

    ],
    "judicial_associate_officer": [

    ]
  },
  "adjudged_at": "2011-04-29",
  "created_at": "2016-02-12 10:56:10",
  "updated_at": "2016-02-12 10:56:10"
}