{
  "identify": "SCD-94-竹簡-714-20051007-1",
  "court": {
    "name": "臺灣新竹地方法院",
    "code": "SCD"
  },
  "division": {
    "name": "民事",
    "code": "V"
  },
  "year": 94,
  "word": "竹簡",
  "number": "714",
  "jcheck": "1",
  "reason": "返還消費借貸款",
  "content": "臺灣新竹地方法院民事簡易判決         94年度竹簡字第714號\n原      告  新竹國際商業銀行股份有限公司\n法定代理人  乙○○\n訴訟代理人  陳書柬\n被      告  甲○○\n                        地下室.\n上列當事人間返還消費借貸款事件，本院於民國94年10月3日辯\n論終結，判決如下：\n    主  文\n被告應給付原告新臺幣壹拾參萬貳仟零玖拾參元，及其中新臺幣\n壹拾貳萬參仟零參拾壹元，自民國九十四年四月十六日起至清償\n日止，按日息萬分之五點四五計算之利息，並自民國九十四年四\n月十六日起至清償日止，逾期六個月以內者，按上開利率百分之\n十，超過六個月者，按上開利率百分之二十計算之違約金。訴訟\n費用由被告負擔。\n本判決得假執行。\n    事實及理由\n一、事實摘要：\n（一）、原告主張：被告於民國（下同）92年8月間向原告申請\n        信用卡，與原告訂立信用卡申請書及約定條款，約定被\n        告應於原告指定之日期及方式繳付帳款，若逾期未繳，\n        則喪失期限利益，應就其全部應付帳款一次全數繳清，\n        並自各筆帳款入帳日起，就該帳款按日息萬分之5.45計\n        算遲延利息，及遲誤繳款期間在6個月以內者，按上開\n        利率百分之10，遲誤繳款期間超過6個月之部分，則按\n        上開利率百分之20計算之違約金。詎被告至94年4月15\n        日止，尚欠預借現金、消費款總額新臺幣（下同）123,\n        031元，逾期（循環）利息9,062元，合計132,093 元之\n        帳款未予繳納，依約定條款之規定，被告即喪失期限之\n        利益，應將所欠帳款一次清償，惟屢經催討，被告仍置\n        之不理，為此依兩造信用卡契約及消費借貸之法律關係\n        提起本件訴訟，請求被告給付如主文第1項所示之金額\n        、利息及違約金等語。\n（二）、被告則以：其確實積欠原告上開金錢，惟目前無力清償\n        所欠款項等語置辯。\n二、程序部分：\n    按當事人得以合意定第一審管轄法院，民事訴訟法第24條第\n    1項前段定有明文；查本件依據兩造簽訂之信用卡約定條款\n    第25條約定，因信用卡契約致涉訟者，雙方合意以本院為第\n    一審管轄法院，有該信用卡約定條款一份在卷可按，是本件\n    被告之住所雖非在本院轄區，惟基於上開說明，本院對本件\n    訴訟自有管轄權，合先敘明。\n三、實體部分：\n（一）、原告主張前揭之事實，業據其提出與其所述相符之信用\n        卡申請書及信用卡約定條款、信用卡帳單明細及信用卡\n        應收帳款明細表各乙份為證，且為被告所不爭執，則參\n        諸原告提出之證據，自堪信原告之主張為真實。\n（二）、從而，原告依消費借貸及兩造信用卡契約之法律關係，\n        訴請被告給付如主文第1項所示之金額、利息及違約金\n        ，即無不合，應予准許。\n四、本件係依民事訴訟法第427條第1項適用簡易訴訟程序所為被\n    告敗訴之判決，爰依職權宣告假執行。\n五、據上論結：本件原告之訴為有理由，依民事訴訟法第436條\n    第2項、第78條、第389條第1項第3款，判決如主文。\n中    華    民    國    94    年    10    月    7     日\n                  新竹簡易庭    法  官  彭淑苑\n以上正本係照原本作成。\n如對本判決上訴，須於判決送達後20日內向本院提出上訴狀。\n中    華    民    國    94    年    10    月    7     日\n                                書記官  張永榮\n",
  "structure": {
    "main": "被告應給付原告新臺幣壹拾參萬貳仟零玖拾參元，及其中新臺幣\n壹拾貳萬參仟零參拾壹元，自民國九十四年四月十六日起至清償\n日止，按日息萬分之五點四五計算之利息，並自民國九十四年四\n月十六日起至清償日止，逾期六個月以內者，按上開利率百分之\n十，超過六個月者，按上開利率百分之二十計算之違約金。訴訟\n費用由被告負擔。\n本判決得假執行。",
    "fact": "一、事實摘要：\n（一）、原告主張：被告於民國（下同）92年8月間向原告申請\n        信用卡，與原告訂立信用卡申請書及約定條款，約定被\n        告應於原告指定之日期及方式繳付帳款，若逾期未繳，\n        則喪失期限利益，應就其全部應付帳款一次全數繳清，\n        並自各筆帳款入帳日起，就該帳款按日息萬分之5.45計\n        算遲延利息，及遲誤繳款期間在6個月以內者，按上開\n        利率百分之10，遲誤繳款期間超過6個月之部分，則按\n        上開利率百分之20計算之違約金。詎被告至94年4月15\n        日止，尚欠預借現金、消費款總額新臺幣（下同）123,\n        031元，逾期（循環）利息9,062元，合計132,093 元之\n        帳款未予繳納，依約定條款之規定，被告即喪失期限之\n        利益，應將所欠帳款一次清償，惟屢經催討，被告仍置\n        之不理，為此依兩造信用卡契約及消費借貸之法律關係\n        提起本件訴訟，請求被告給付如主文第1項所示之金額\n        、利息及違約金等語。\n（二）、被告則以：其確實積欠原告上開金錢，惟目前無力清償\n        所欠款項等語置辯。\n二、程序部分：\n    按當事人得以合意定第一審管轄法院，民事訴訟法第24條第\n    1項前段定有明文；查本件依據兩造簽訂之信用卡約定條款\n    第25條約定，因信用卡契約致涉訟者，雙方合意以本院為第\n    一審管轄法院，有該信用卡約定條款一份在卷可按，是本件\n    被告之住所雖非在本院轄區，惟基於上開說明，本院對本件\n    訴訟自有管轄權，合先敘明。\n三、實體部分：\n（一）、原告主張前揭之事實，業據其提出與其所述相符之信用\n        卡申請書及信用卡約定條款、信用卡帳單明細及信用卡\n        應收帳款明細表各乙份為證，且為被告所不爭執，則參\n        諸原告提出之證據，自堪信原告之主張為真實。\n（二）、從而，原告依消費借貸及兩造信用卡契約之法律關係，\n        訴請被告給付如主文第1項所示之金額、利息及違約金\n        ，即無不合，應予准許。\n四、本件係依民事訴訟法第427條第1項適用簡易訴訟程序所為被\n    告敗訴之判決，爰依職權宣告假執行。\n五、據上論結：本件原告之訴為有理由，依民事訴訟法第436條\n    第2項、第78條、第389條第1項第3款，判決如主文。",
    "reason": "一、事實摘要：\n（一）、原告主張：被告於民國（下同）92年8月間向原告申請\n        信用卡，與原告訂立信用卡申請書及約定條款，約定被\n        告應於原告指定之日期及方式繳付帳款，若逾期未繳，\n        則喪失期限利益，應就其全部應付帳款一次全數繳清，\n        並自各筆帳款入帳日起，就該帳款按日息萬分之5.45計\n        算遲延利息，及遲誤繳款期間在6個月以內者，按上開\n        利率百分之10，遲誤繳款期間超過6個月之部分，則按\n        上開利率百分之20計算之違約金。詎被告至94年4月15\n        日止，尚欠預借現金、消費款總額新臺幣（下同）123,\n        031元，逾期（循環）利息9,062元，合計132,093 元之\n        帳款未予繳納，依約定條款之規定，被告即喪失期限之\n        利益，應將所欠帳款一次清償，惟屢經催討，被告仍置\n        之不理，為此依兩造信用卡契約及消費借貸之法律關係\n        提起本件訴訟，請求被告給付如主文第1項所示之金額\n        、利息及違約金等語。\n（二）、被告則以：其確實積欠原告上開金錢，惟目前無力清償\n        所欠款項等語置辯。\n二、程序部分：\n    按當事人得以合意定第一審管轄法院，民事訴訟法第24條第\n    1項前段定有明文；查本件依據兩造簽訂之信用卡約定條款\n    第25條約定，因信用卡契約致涉訟者，雙方合意以本院為第\n    一審管轄法院，有該信用卡約定條款一份在卷可按，是本件\n    被告之住所雖非在本院轄區，惟基於上開說明，本院對本件\n    訴訟自有管轄權，合先敘明。\n三、實體部分：\n（一）、原告主張前揭之事實，業據其提出與其所述相符之信用\n        卡申請書及信用卡約定條款、信用卡帳單明細及信用卡\n        應收帳款明細表各乙份為證，且為被告所不爭執，則參\n        諸原告提出之證據，自堪信原告之主張為真實。\n（二）、從而，原告依消費借貸及兩造信用卡契約之法律關係，\n        訴請被告給付如主文第1項所示之金額、利息及違約金\n        ，即無不合，應予准許。\n四、本件係依民事訴訟法第427條第1項適用簡易訴訟程序所為被\n    告敗訴之判決，爰依職權宣告假執行。\n五、據上論結：本件原告之訴為有理由，依民事訴訟法第436條\n    第2項、第78條、第389條第1項第3款，判決如主文。"
  },
  "search": "臺灣新竹地方法院民事簡易判決94年度竹簡字第714號原告新竹國際商業銀行股份有限公司法定代理人乙○○訴訟代理人陳書柬被告甲○○地下室.上列當事人間返還消費借貸款事件，本院於民國94年10月3日辯論終結，判決如下：主文被告應給付原告新臺幣壹拾參萬貳仟零玖拾參元，及其中新臺幣壹拾貳萬參仟零參拾壹元，自民國九十四年四月十六日起至清償日止，按日息萬分之五點四五計算之利息，並自民國九十四年四月十六日起至清償日止，逾期六個月以內者，按上開利率百分之十，超過六個月者，按上開利率百分之二十計算之違約金。訴訟費用由被告負擔。本判決得假執行。事實及理由一、事實摘要：（一）、原告主張：被告於民國（下同）92年8月間向原告申請信用卡，與原告訂立信用卡申請書及約定條款，約定被告應於原告指定之日期及方式繳付帳款，若逾期未繳，則喪失期限利益，應就其全部應付帳款一次全數繳清，並自各筆帳款入帳日起，就該帳款按日息萬分之5.45計算遲延利息，及遲誤繳款期間在6個月以內者，按上開利率百分之10，遲誤繳款期間超過6個月之部分，則按上開利率百分之20計算之違約金。詎被告至94年4月15日止，尚欠預借現金、消費款總額新臺幣（下同）123,031元，逾期（循環）利息9,062元，合計132,093元之帳款未予繳納，依約定條款之規定，被告即喪失期限之利益，應將所欠帳款一次清償，惟屢經催討，被告仍置之不理，為此依兩造信用卡契約及消費借貸之法律關係提起本件訴訟，請求被告給付如主文第1項所示之金額、利息及違約金等語。（二）、被告則以：其確實積欠原告上開金錢，惟目前無力清償所欠款項等語置辯。二、程序部分：按當事人得以合意定第一審管轄法院，民事訴訟法第24條第1項前段定有明文；查本件依據兩造簽訂之信用卡約定條款第25條約定，因信用卡契約致涉訟者，雙方合意以本院為第一審管轄法院，有該信用卡約定條款一份在卷可按，是本件被告之住所雖非在本院轄區，惟基於上開說明，本院對本件訴訟自有管轄權，合先敘明。三、實體部分：（一）、原告主張前揭之事實，業據其提出與其所述相符之信用卡申請書及信用卡約定條款、信用卡帳單明細及信用卡應收帳款明細表各乙份為證，且為被告所不爭執，則參諸原告提出之證據，自堪信原告之主張為真實。（二）、從而，原告依消費借貸及兩造信用卡契約之法律關係，訴請被告給付如主文第1項所示之金額、利息及違約金，即無不合，應予准許。四、本件係依民事訴訟法第427條第1項適用簡易訴訟程序所為被告敗訴之判決，爰依職權宣告假執行。五、據上論結：本件原告之訴為有理由，依民事訴訟法第436條第2項、第78條、第389條第1項第3款，判決如主文。中華民國94年10月7日新竹簡易庭法官彭淑苑以上正本係照原本作成。如對本判決上訴，須於判決送達後20日內向本院提出上訴狀。中華民國94年10月7日書記官張永榮",
  "characters": {
    "judges": [
      "彭淑苑"
    ],
    "prosecutors": [

    ],
    "lawyers": [

    ],
    "clerks": [
      "張永榮"
    ],
    "plaintiffs": [
      "新竹國際商業銀行股份有限公司"
    ],
    "defendants": [
      "甲○○"
    ],
    "prosecutor_office": [

    ],
    "creditors": [

    ],
    "debtors": [

    ],
    "judicial_associate_officer": [

    ]
  },
  "adjudged_at": "2005-10-07",
  "created_at": "2016-02-07 11:03:37",
  "updated_at": "2016-02-07 11:03:37"
}