{
  "identify": "TPH-94-交上訴-53-20050719-1",
  "court": {
    "name": "臺灣高等法院",
    "code": "TPH"
  },
  "division": {
    "name": "刑事",
    "code": "M"
  },
  "year": 94,
  "word": "交上訴",
  "number": "53",
  "jcheck": "1",
  "reason": "公共危險等",
  "content": "臺灣高等法院刑事判決                94年度交上訴字第53號\n  上  訴  人\n  即  被  告  乙○○\n  選任辯護人  林月雪律師\n              江鶴鵬律師\n上列上訴人因公共危險等案件，不服臺灣士林地方法院93年度交\n訴字第35號，中華民國93年12月31日第一審判決（起訴案號：92\n年度偵字第7634號），提起上訴，本院判決如下：\n    主  文\n上訴駁回。\n    事  實\n一、乙○○於民國（下同）92年3月18日晚上10時27分許，駕駛\n    其友人甲○○所有車號3B-3859號德國賓士牌黑色自用小客\n    車，於臺北市○○區○○街交岔路口附近東側之重慶北路二\n    段右側慢車道暫停，嗣其起駛後隨即又欲自保安街由西往東\n    方向行駛，其本應注意汽車於快車道等危險地帶或交通頻繁\n    處所，不得倒車，而依當時之天候雖係陰天但夜間有照明，\n    路面乾燥、無缺陷、道路無障礙物、路況及視距均良好等情\n    況，並無不能注意之特殊情形，乃竟疏未注意，由重慶北路\n    二段外側快車道直接向後倒車，並於到達保安街口時又加速\n    由東向西倒車至重慶北路二段內側第二車道與保安街南側車\n    道口之交通頻繁處所，以便其向前直駛保安街，適由戊○○\n    所駕駛車號3E-219號營業小客車正由重慶北路二段內側第二\n    車道（起訴書誤載為第三車道）綠燈後甫起駛至該處，乙○\n    ○所駕車輛車身後保險桿部位遂直接正面撞擊戊○○車輛右\n    側下半部車身，戊○○之車輛又再往左偏撞刻亦正於重慶北\n    路二段南向北內側第二車道行駛，由丁○○騎乘附載丙○○\n    之車號BEI-327號重型機車前車頭，致丁○○與丙○○人、\n    車倒地，並因此使戊○○受有兩膝及下背挫傷等傷害，丁○\n    ○受有全身多處擦傷、頸部、右大腿挫傷等傷害，丙○○則\n    受有右手、右肘、左手、下肢多處擦傷、鈍挫傷等傷害（丁\n    ○○、丙○○所受傷害部分均未據告訴）。詎乙○○明知已\n    駕車肇事致人受傷，竟未停車查看並救護傷者戊○○、丁○\n    ○及丙○○，反為規避其法律責任，另行起意，逕自駕駛上\n    開車輛由保安街西向東直駛，逃離肇事現場，惟經戊○○機\n    警記下其車號與顏色，並分別向先後抵達現場處理之臺北市\n    政府警察局大同分局寧夏派出所及交通分隊員警黃國書、陳\n    德威報告乙○○上開車輛之車號及顏色（黑色），始經警循\n    線查獲。\n二、案經戊○○訴由臺北市政府警察局大同分局報請臺灣士林地\n    方檢法院察署檢察官偵查起訴。\n    理  由\n一、訊據上訴人即被告乙○○固不否認曾於右揭時、地間駕駛其\n    友人甲○○所有車號3B-3859號德國賓士牌黑色自用小客車\n    ，由臺北市大同區○○○路○段南向北外側車道行駛，並曾\n    於該路段與保安街交岔路口停等紅燈等事實，但否認有何過\n    失傷害及肇事逃逸等犯行，辯稱：伊當時直接沿重慶北路向\n    北行駛回士林的家，並未倒車往保安街直駛，更未倒車撞及\n    告訴人戊○○所駕營業小客車並肇事逃逸等語。\n二、惟查:\n  (一)被告確有於右揭時、地駕駛友人甲○○所有車號3B-3859號\n    德國賓士牌黑色自用小客車，於臺北市○○區○○街交岔路\n    口附近東側之重慶北路二段右側慢車道暫停，嗣其起駛後隨\n    即又欲自保安街由西往東方向行駛，竟疏未注意，由重慶北\n    路二段外側快車道直接向後倒車，並於到達保安街口時又加\n    速由東向西倒車至重慶北路二段內側第二車道與保安街南側\n    車道口之交通頻繁處所，以便其繼續向前直駛保安街，以致\n    撞擊告訴人戊○○駕駛車號3E-219號營業小客車右側下半部\n    車身，戊○○之車輛又再往左偏撞刻亦正於重慶北路二段南\n    向北內側第二車道行駛由被害人丁○○所騎乘附載丙○○之\n    車號BEI-327號重型機車前車頭，且其明知已駕車肇事致人\n    受傷，竟逕自駕駛上開車輛逃離肇事現場，但仍經戊○○記\n    下其車號及車色並分別告知員警黃國書及陳德威等情，業據\n    證人即告訴人戊○○分別於偵查及原審審理時結證稱：「（\n    問：妳當時看到的車號是幾號？）3B-3859」「（問：車子\n    的顏色呢？）黑色」「（問：廠牌呢？）賓士」「（問：妳\n    的車子怎麼被撞的？）紅燈停止，變綠燈時我往前開，那輛\n    黑色的車子本來是往前開，突然後退，之後轉彎，後保險桿\n    整面撞到我的右側車身」「（問：車號是妳提供給警察的嗎\n    ？）對，那天另外一位好心人士有追過去把車號抄回去給警\n    察，我是和那個人同時將車號提供給寧夏派出所的警員黃國\n    書」（偵查卷第92至93頁）；「（問：本件交通事故發生經\n    過情形如何？）當時我在等紅綠燈，我有看到一部車從路邊\n    開出來，後來該部車突然倒退，它原本停在路邊，我走在最\n    內側車道，我的左側是公車專屬車道，當時他在最外側車道\n    ，我認為他倒退不可能影響到我，所以我直行。沒想到他突\n    然走到十字路口速度突然加快且轉彎，就這樣撞到我了」「\n    （問：機車倒地時，被告的車輛在何處？）我眼睛張開的時\n    候，該部肇事車輛在我右側車身旁邊，與我成垂直狀態，我\n    看到他的車有踩煞車燈，他就往前開了，我就拿筆在車上白\n    板寫上他的車號，我往左看，就看到機車騎士抱起他的女乘\n    客」「（問：撞到你車的肇事車輛廠牌和顏色？）黑色賓士\n    車」「（問：是由何人將肇事車輛車號告訴警員黃國書？）\n    我不知道，當機車騎士抱起女乘客時，我走下車，叫了救護\n    車，沒有多久警員就來了，警察就問一下現場狀況，我和一\n    個機車騎士就同時說出車號，他可能有去追肇事車輛，再回\n    來跟警察說。」「（問：你在第幾線道？）我在內側第二線\n    道」「（問：撞擊你的車輛是在第幾線道？）最外側車道」\n    「（問：他是否在停止狀態？）我在停等紅燈的時候，他停\n    在過紅綠燈的右前方路邊」「（問：外側第三、四線道有無\n    其他車輛？）我剛開始等紅綠燈的時候是沒有」「（問：你\n    說有機車騎士有看到肇事車牌？）是他自己去追的。警察來\n    的時候，他自己跟警察說的。我有問他肇事車號，他為何知\n    道，他說他去追的時候看到的。後來交通大隊來的時候，他\n    就不在現場。他沒有說他追多遠。他是跟黃國書警員說的」\n    「（問：看到肇事車輛車牌的機車騎士的外表可否描述一下\n    ？）騎125CC的男性約五、六十歲，胖胖的」「（問：你車\n    前葉子板的高度有多高？撞到你的肇事車是用何部分撞到你\n    的車？）後保險桿」「（問：撞到你何部分？）我車右側車\n    身，車輛受損的部分是右前葉子板到右後門」「（問：肇事\n    車輛右邊有無停車格？）沒有，那裡是畫紅線，被告是我看\n    到的第一部車輛，在他車後沒有停其他車，他前面我沒有注\n    意，他是在十字路口轉彎後有一小段距離停在路邊」「（問\n    ：在倒退的時候，你有無注意他的車型？）我沒有注意，撞\n    的時候才注意到」「（問：你看到撞你的車，有無特徵？）\n    沒有，就是黑色賓士跑車。後面沒有車型的標示，也沒有注\n    意它是幾門車輛」「（問：當時的車流量如何？）我下車的\n    時候開始有車，變燈起步的時候，我是第一部車，我是唯一\n    等紅綠燈的車。我車子已經修理好了」「（問：肇事的時候\n    ，你如何確定該部車是黑色的？）因為它撞到我，距離很近\n    ，我上班的店在民族西路188號，民族西路184號是專門修理\n    賓士車的店，我常常在該店看賓士車，對於賓士車的車型顏\n    色很熟悉」「（問：撞擊的情形如何？）他是整個車尾撞到\n    我，當時兩部車是垂直的情形，後來他就往保安街開走」「\n    （問：賓士車尾有無受損？）沒有很明顯的受損。當時我是\n    坐在駕駛座，往右側車窗看出去，當時車窗是關著的」等語\n    綦詳（原審93年9月6日審判筆錄）。於本院審理中亦結證稱\n    被告所駕汽車車號係伊所記下，警員到場時，另有一人亦同\n    時說出相同之車號等語，核與證人即現場處理之警員黃國書\n    於原審審理時證稱：「當天我有處理這件車禍，詳細時間我\n    記不得，當時我是備差，就過去處理，現場只有一部營業小\n    客車，即戊○○所駕駛的，當時她有給我一個車號，我有記\n    載在工作記錄簿上，並通知交通隊」「（問：當天你是否第\n    一個到場處理的警員？）是的」「（問：你在偵查中有陳述\n    ：還有另外一個四、五十歲的路人提供車號給你，有何意見\n    ？）我沒有意見，因為當時車禍不只戊○○在現場，附近的\n    民眾還有二、三個人，我沒有登記路人的姓名，只有登記小\n    客車的駕駛戊○○的姓名而已，如果我第一次在偵訊中有這\n    樣說的話，應該是實在的，因為當時我有翻閱工作記錄簿」\n    「（問：你在第一次偵查庭中說，有路人提供車號給你，請\n    說明那個路人的樣子？）那個人大概四、五十歲的路人，應\n    該是住在附近的人的因為他穿拖鞋」「（問：路人有無跟你\n    講車號？）當時人蠻多的，路人應該也是有跟我講車號」「\n    （問：你到現場時，看到哪幾部車有擦撞？）只有一部營業\n    小客車還有路人的摩托車，但跟據現場所有人跟我講，是有\n    兩部自小客車擦撞，但是只有一部營業自小客車在現場」「\n    （問：你有無問路人他如何得知這個肇事車號？）沒有，他\n    主動提供的」「（問：你有無向交通隊到場的隊員講肇事車\n    號？）有的，我是把全部的資料交給他們，口頭也有講大概\n    事實的經過」「（問：你在偵查中說：戊○○跟路人一起說\n    這個車號，你現在是否記得？）那個路人大約四、五十歲，\n    頭髮有點花白，我記得戊○○有跟我講，那個路人也在旁邊\n    附和說，就是這個車號」「（問：你的意思不是說路人說一\n    個車號，戊○○也說一個車號，你聽到的車號是一樣的？）\n    路人也有講出車號來，當時戊○○跟路人都只有講車號，沒\n    有講車的廠牌、顏色等」「（問：你有無告知交通分隊有車\n    輛逃逸？）有的，我有跟交通隊說是肇事逃逸的案件，由他\n    們處理」等語相符（原審93年9月27日審判筆錄），並有其\n    當天處理本件車禍之警方工作紀錄簿影本一紙其上記載被告\n    所駕車輛之車號等情在卷可稽（原審卷第135頁）。復核與\n    證人即交通分隊警員陳德威於原審審理時證述：「我有處理\n    92年3月18日晚上10時27分在重慶北路保安街口的交通事故\n    。當時我到場的時候只有看到一部計程車停在路中間，另外\n    機車卡到安全島上，我先量現場圖，然後再到醫院處理」「\n    （問：道路交通事故調查表二上所載車號3B-3859號車號，\n    是如何得知的？（提示偵查卷40頁）是計程車駕駛說的」「\n    （問：你到場的時候，黃國書是否還在場？）還在場」「（\n    問：他有無向你告知本件交通事故事宜？）他有跟我講肇事\n    逃逸車輛的車號」「（問：你到場之後，有無路人在現場？\n    ）沒有」「（問：道路交通事故補充資料表，上面A車註明\n    賓士黑，是如何得知的？）是計程車司機跟我講後，我用電\n    腦去查的」「（問：你是否有觀察計程車右側留有遭碰撞的\n    漆？）我沒有印象，但是我確定它的右側確實被碰撞。因為\n    右側的車門整個凹陷，且是新痕」「（問：當時是否先查肇\n    逃的車是賓士車，還是告訴人先告訴你是賓士車？）她是告\n    訴我車號及一部黑色的自小客，她沒有講車種及車型」「（\n    問：根據你的經驗，計程車右側被撞的凹陷，撞擊車輛的保\n    險桿是否還可以完好？）要看保險桿的鋼樑及側撞的角度，\n    絕對有可能保險桿仍然完好。如果只是轉角地方撞到，就有\n    可能整支保險桿完好，就我所知，有些保險桿很強壯，撞到\n    他車，他車的漆會沾附在該車上，而不是該車的漆掉落在他\n    車上，我們看過很多車禍的狀況是這樣」「（問：如果是整\n    支保險桿撞到保險桿是否會損害？）如果兩部車的角度對的\n    話，還是有可能保險桿還是完好的」「（問：你在現場有無\n    路人跟你說賓士車的車號？）我到達現場時，沒有其他路人\n    ，只有告訴人跟我講。黃國書並沒有告訴我有其他路人看到\n    賓士車的車號，黃國書有跟我講賓士車的車號，但是我還是\n    去問計程車司機」等情相符（原審93年11月15日審判筆錄）\n    。此外復有道路交通事故現場圖、道路交通事故調查報告表\n    （除警方自行判斷之部分外）(一)(二)、現場照片8幀及告訴人\n    營業小客車毀損照片多幀在偵查卷可按。而告訴人戊○○與\n    被害人丁○○、丙○○所受傷害，亦有臺北市立中興醫院診\n    斷證明書（偵查卷第95頁）及財團法人馬偕紀念醫院診斷證\n    明書（偵查卷第30至31頁）各1件在卷可憑。\n  (二)綜上，被告雖否認有何過失傷害及肇事逃逸之犯行，但依告\n    訴人之指訴及證人黃國書、陳德威上揭證詞，足認告訴人於\n    突遭車禍之際，即立刻將肇事車輛之車號3B-3859及其車色\n    （黑色）告知前來處理之警員（依警方交通事故談話紀錄表\n    所載之時間為92年3月18日晚上10時38分許，此部分不涉及\n    供述，非傳聞證據），且恰與另一不詳年籍之中年路人向警\n    方告知之車號相同，而均與被告車輛之車牌及車色相符，即\n    被告亦不否認於右揭時地曾途經該處並停等紅燈，則告訴人\n    與證人均與被告素無仇怨，復受具結刑責之擔保，則何以如\n    此巧合地告訴人及該路人所指訴之車輛能與證人陳德威查證\n    後被告車輛之車號及車色均屬一致？顯見告訴人上揭指訴並\n    非虛妄，而具有可信度，復參以被害人丁○○於偵查時指述\n    ：「在被碰撞前有聽到車子煞車的尖銳聲」等語（偵查卷第\n    85頁），以及告訴人車輛之右側車身下半部（車側飾條處）\n    凹陷嚴重，其受損之高度均低於其本身保險桿之部位，而被\n    告之車輛為跑車型式，其車身本較一般車輛為低等情以觀，\n    被告確有於右揭時地駕車撞擊告訴人後復逃離現場，足堪認\n    定，其上揭所辯，均係卸責之詞，委無足採。\n三、又經原審函詢被告所駕車輛之保險公司及原廠維修公司，雖\n    分別稱：「自92年3月18日以後無出險紀錄」及「有關3B-\n    3859賓士車曾於92年12月1日進入中華賓士南港廠維修。維\n    修項目：更換室內燈開關、排檔桿橡皮、檔位開關、電動車\n    頂開關」等情，此有富邦產物保險股份有限公司93年7月12\n    日（九三）富保業發字第212號及中華賓士汽車股份有限公\n    司93年7月5日中賓字第9306013號函各1件在卷可考 (原審卷\n    第23、24頁)，但車輛維修非必在原廠為之，且因各別特殊\n    之原因亦未必辦理出險手續，為一般社會生活之通常經驗，\n    且被告車輛經警方通知到場勘驗及拍照時，距案發時間已1\n    月又4日，亦難認該車輛仍維持案發時之原狀，自均不足以\n    此而推翻前開不利之證據，而為被告有利之認定，被告聲請\n    傳喚甲○○證明被告還車時之車況，及函查該車於92年10月\n    以後之所有人，亦非有必要，均附此敘明。\n四、被告聲請將本件送請臺北市車輛行車事故鑑定委員會以電腦\n    動畫軟體重建現場，鑑定本件告訴人之汽車是否為被告汽車\n    所撞擊一節，經該委員會函復本院以「有關冀以電腦軟體\n    HEV-2D，重建車禍事故現場一事，因國內各大車廠及公路監\n    理機關對於各型車輛基本參數資料庫均尚未建立，且交通部\n    、經濟部亦未訂定相關法令，因此該軟體僅以學術研究為主\n    ... 因此本會已無使用該項軟體作為行車事故鑑定之依據」\n    ，有該委員會94年6月8日北鑑審字第09430201600號函在卷\n    可稽，雖被告據此再聲請送中央大學、成功大學、交通大學\n    或逢甲大學鑑定，於原審亦聲請送警察大學鑑定，惟查本件\n    確係被告所駕車號3B-3859號黑色賓士車違規倒車撞擊告訴\n    人所駕營業小客車，業據上開證人證述明確，其等證言核無\n    可疑之處，則本件事證已明，自無再送鑑定之必要，亦附予\n    敘明。\n五、被告辯護人於原審準備程序時主張如起訴書證據清單編號\n    二、三、五、六、八所示之證據能力應予排除（原審93年6\n    月8日準備程序筆錄），其中告訴人及證人黃國書，原審已\n    依法傳喚到庭並依證人交互詰問程序令其陳述；另被害人丁\n    ○○於警方交通事故談話紀錄表內之陳述、交通事故分析研\n    判表、談話紀錄表及補充資料表內，關於人之供述及警方自\n    行判斷之部分，依其性質均屬刑事訴訟法第159條第1項之傳\n    聞證據，原審及本院均已排除其證據能力而未採為認定本件\n    犯罪事實之依據；又本件偵查卷內之臺北市車輛行車事故鑑\n    定委員會鑑定意見書係警方囑託為之，不符刑事訴訴法第\n    198條關於鑑定之規定，亦應排除其證據能力；至道路交通\n    事故現場圖不涉及判斷之部分，應屬同法第159條之4第1款\n    之公務員職務上製作之紀錄文書，而為傳聞法則之例外，得\n    作為適格之證據；至其餘未經當事人於言詞辯論終結前聲明\n    異議之證據，本院認依其陳述作成時之情況，均係本於其自\n    由意志或職務上應為之事項，自應認其適為認定本件犯罪事\n    實之證據，併此指明。\n六、按汽車於快車道等危險地帶或交通頻繁處所，不得倒車，道\n    路交通安全規則第110條第1款定有明文。本件被告駕車行經\n    上開路段，本應注意上開規定不得倒車，且依當時之天候雖\n    係陰天但於夜間有照明，且路面乾燥、無缺陷、道路無障礙\n    物、路況及視距均良好等情況，並無不能注意之特殊情形，\n    乃竟疏未注意，逕行於快車道倒車至重慶北路二段與保安街\n    交叉路口之交通頻繁處所，以致肇事致告訴人受傷，其有過\n    失，甚為明確，又被告之過失行為與告訴人所受傷害間復具\n    有相當因果關係，且其肇事後未即時救護傷者，反加速逕行\n    離去，有如上述，是其過失傷害及肇事逃逸之犯行，均堪認\n    定，本件事證已臻明確，應依法論科。\n七、核被告所為，係犯刑法第284條第1項之過失傷害罪及第185\n    之4之肇事致人受傷逃逸罪。所犯二罪，犯意各別，行為互\n    殊，構成要件亦不相同，應予分論併罰。\n八、原審以被告犯罪，事證明確，適用刑法第185條之4、第284\n    條第1項、第51條第5款，罰金罰鍰提高標準條例第1條前段\n    之規定，審酌被告為規避己身刑責，竟於駕車肇事後逃逸無\n    蹤，置傷者於不顧，惡性非輕，犯後猶飾詞卸責，毫無悔意\n    ，且迄未賠償被害人所受損害，但其素行尚稱良好，告訴人\n    所受傷害非重暨其教育智識程度等一切情狀，分別就過失傷\n    害人罪，量處有期徒刑3月；就駕駛動力交通工具肇事，致\n    人受傷而逃逸罪，量處有期徒刑8月。並定應執行刑為有期\n    徒刑10月，經核認事用法及量刑均無不合。被告上訴猶執陳\n    詞否認犯罪，指摘原判決不當，核無理由，應駁回其上訴。\n據上論斷，應依刑事訴訟法第368條，判決如主文。\n本案經檢察官張秋雲到庭執行職務。\n中    華    民    國    94    年    7     月    19    日\n                  刑事第十五庭審判長法  官  陳榮和\n                                    法  官  張正亞\n                                    法  官  蔡國在\n以上正本證明與原本無異。\n公共危險罪部分如不服本判決，應於收受送達後十日內向本院提\n出上訴書狀，其未敘述上訴之理由者並得於提起上訴後十日內向\n本院補提理由書（均須按他造當事人之人數附繕本）。\n                                    書記官  耿鳳君\n中    華    民    國    94    年    7     月    19    日\n附錄：本案論罪科刑法條全文\n刑法第185條之4\n駕駛動力交通工具肇事，致人死傷而逃逸者，處6月以上5年以下\n有期徒刑。\n第284條第1項\n因過失傷害人者，處6月以下有期徒刑、拘役或500元以下罰金，\n致重傷者，處1年以下有期徒刑、拘役或500元以下罰金。\n",
  "structure": {
    "main": "上訴駁回。",
    "fact": "一、乙○○於民國（下同）92年3月18日晚上10時27分許，駕駛\n    其友人甲○○所有車號3B-3859號德國賓士牌黑色自用小客\n    車，於臺北市○○區○○街交岔路口附近東側之重慶北路二\n    段右側慢車道暫停，嗣其起駛後隨即又欲自保安街由西往東\n    方向行駛，其本應注意汽車於快車道等危險地帶或交通頻繁\n    處所，不得倒車，而依當時之天候雖係陰天但夜間有照明，\n    路面乾燥、無缺陷、道路無障礙物、路況及視距均良好等情\n    況，並無不能注意之特殊情形，乃竟疏未注意，由重慶北路\n    二段外側快車道直接向後倒車，並於到達保安街口時又加速\n    由東向西倒車至重慶北路二段內側第二車道與保安街南側車\n    道口之交通頻繁處所，以便其向前直駛保安街，適由戊○○\n    所駕駛車號3E-219號營業小客車正由重慶北路二段內側第二\n    車道（起訴書誤載為第三車道）綠燈後甫起駛至該處，乙○\n    ○所駕車輛車身後保險桿部位遂直接正面撞擊戊○○車輛右\n    側下半部車身，戊○○之車輛又再往左偏撞刻亦正於重慶北\n    路二段南向北內側第二車道行駛，由丁○○騎乘附載丙○○\n    之車號BEI-327號重型機車前車頭，致丁○○與丙○○人、\n    車倒地，並因此使戊○○受有兩膝及下背挫傷等傷害，丁○\n    ○受有全身多處擦傷、頸部、右大腿挫傷等傷害，丙○○則\n    受有右手、右肘、左手、下肢多處擦傷、鈍挫傷等傷害（丁\n    ○○、丙○○所受傷害部分均未據告訴）。詎乙○○明知已\n    駕車肇事致人受傷，竟未停車查看並救護傷者戊○○、丁○\n    ○及丙○○，反為規避其法律責任，另行起意，逕自駕駛上\n    開車輛由保安街西向東直駛，逃離肇事現場，惟經戊○○機\n    警記下其車號與顏色，並分別向先後抵達現場處理之臺北市\n    政府警察局大同分局寧夏派出所及交通分隊員警黃國書、陳\n    德威報告乙○○上開車輛之車號及顏色（黑色），始經警循\n    線查獲。\n二、案經戊○○訴由臺北市政府警察局大同分局報請臺灣士林地\n    方檢法院察署檢察官偵查起訴。",
    "reason": "一、訊據上訴人即被告乙○○固不否認曾於右揭時、地間駕駛其\n    友人甲○○所有車號3B-3859號德國賓士牌黑色自用小客車\n    ，由臺北市大同區○○○路○段南向北外側車道行駛，並曾\n    於該路段與保安街交岔路口停等紅燈等事實，但否認有何過\n    失傷害及肇事逃逸等犯行，辯稱：伊當時直接沿重慶北路向\n    北行駛回士林的家，並未倒車往保安街直駛，更未倒車撞及\n    告訴人戊○○所駕營業小客車並肇事逃逸等語。\n二、惟查:\n  (一)被告確有於右揭時、地駕駛友人甲○○所有車號3B-3859號\n    德國賓士牌黑色自用小客車，於臺北市○○區○○街交岔路\n    口附近東側之重慶北路二段右側慢車道暫停，嗣其起駛後隨\n    即又欲自保安街由西往東方向行駛，竟疏未注意，由重慶北\n    路二段外側快車道直接向後倒車，並於到達保安街口時又加\n    速由東向西倒車至重慶北路二段內側第二車道與保安街南側\n    車道口之交通頻繁處所，以便其繼續向前直駛保安街，以致\n    撞擊告訴人戊○○駕駛車號3E-219號營業小客車右側下半部\n    車身，戊○○之車輛又再往左偏撞刻亦正於重慶北路二段南\n    向北內側第二車道行駛由被害人丁○○所騎乘附載丙○○之\n    車號BEI-327號重型機車前車頭，且其明知已駕車肇事致人\n    受傷，竟逕自駕駛上開車輛逃離肇事現場，但仍經戊○○記\n    下其車號及車色並分別告知員警黃國書及陳德威等情，業據\n    證人即告訴人戊○○分別於偵查及原審審理時結證稱：「（\n    問：妳當時看到的車號是幾號？）3B-3859」「（問：車子\n    的顏色呢？）黑色」「（問：廠牌呢？）賓士」「（問：妳\n    的車子怎麼被撞的？）紅燈停止，變綠燈時我往前開，那輛\n    黑色的車子本來是往前開，突然後退，之後轉彎，後保險桿\n    整面撞到我的右側車身」「（問：車號是妳提供給警察的嗎\n    ？）對，那天另外一位好心人士有追過去把車號抄回去給警\n    察，我是和那個人同時將車號提供給寧夏派出所的警員黃國\n    書」（偵查卷第92至93頁）；「（問：本件交通事故發生經\n    過情形如何？）當時我在等紅綠燈，我有看到一部車從路邊\n    開出來，後來該部車突然倒退，它原本停在路邊，我走在最\n    內側車道，我的左側是公車專屬車道，當時他在最外側車道\n    ，我認為他倒退不可能影響到我，所以我直行。沒想到他突\n    然走到十字路口速度突然加快且轉彎，就這樣撞到我了」「\n    （問：機車倒地時，被告的車輛在何處？）我眼睛張開的時\n    候，該部肇事車輛在我右側車身旁邊，與我成垂直狀態，我\n    看到他的車有踩煞車燈，他就往前開了，我就拿筆在車上白\n    板寫上他的車號，我往左看，就看到機車騎士抱起他的女乘\n    客」「（問：撞到你車的肇事車輛廠牌和顏色？）黑色賓士\n    車」「（問：是由何人將肇事車輛車號告訴警員黃國書？）\n    我不知道，當機車騎士抱起女乘客時，我走下車，叫了救護\n    車，沒有多久警員就來了，警察就問一下現場狀況，我和一\n    個機車騎士就同時說出車號，他可能有去追肇事車輛，再回\n    來跟警察說。」「（問：你在第幾線道？）我在內側第二線\n    道」「（問：撞擊你的車輛是在第幾線道？）最外側車道」\n    「（問：他是否在停止狀態？）我在停等紅燈的時候，他停\n    在過紅綠燈的右前方路邊」「（問：外側第三、四線道有無\n    其他車輛？）我剛開始等紅綠燈的時候是沒有」「（問：你\n    說有機車騎士有看到肇事車牌？）是他自己去追的。警察來\n    的時候，他自己跟警察說的。我有問他肇事車號，他為何知\n    道，他說他去追的時候看到的。後來交通大隊來的時候，他\n    就不在現場。他沒有說他追多遠。他是跟黃國書警員說的」\n    「（問：看到肇事車輛車牌的機車騎士的外表可否描述一下\n    ？）騎125CC的男性約五、六十歲，胖胖的」「（問：你車\n    前葉子板的高度有多高？撞到你的肇事車是用何部分撞到你\n    的車？）後保險桿」「（問：撞到你何部分？）我車右側車\n    身，車輛受損的部分是右前葉子板到右後門」「（問：肇事\n    車輛右邊有無停車格？）沒有，那裡是畫紅線，被告是我看\n    到的第一部車輛，在他車後沒有停其他車，他前面我沒有注\n    意，他是在十字路口轉彎後有一小段距離停在路邊」「（問\n    ：在倒退的時候，你有無注意他的車型？）我沒有注意，撞\n    的時候才注意到」「（問：你看到撞你的車，有無特徵？）\n    沒有，就是黑色賓士跑車。後面沒有車型的標示，也沒有注\n    意它是幾門車輛」「（問：當時的車流量如何？）我下車的\n    時候開始有車，變燈起步的時候，我是第一部車，我是唯一\n    等紅綠燈的車。我車子已經修理好了」「（問：肇事的時候\n    ，你如何確定該部車是黑色的？）因為它撞到我，距離很近\n    ，我上班的店在民族西路188號，民族西路184號是專門修理\n    賓士車的店，我常常在該店看賓士車，對於賓士車的車型顏\n    色很熟悉」「（問：撞擊的情形如何？）他是整個車尾撞到\n    我，當時兩部車是垂直的情形，後來他就往保安街開走」「\n    （問：賓士車尾有無受損？）沒有很明顯的受損。當時我是\n    坐在駕駛座，往右側車窗看出去，當時車窗是關著的」等語\n    綦詳（原審93年9月6日審判筆錄）。於本院審理中亦結證稱\n    被告所駕汽車車號係伊所記下，警員到場時，另有一人亦同\n    時說出相同之車號等語，核與證人即現場處理之警員黃國書\n    於原審審理時證稱：「當天我有處理這件車禍，詳細時間我\n    記不得，當時我是備差，就過去處理，現場只有一部營業小\n    客車，即戊○○所駕駛的，當時她有給我一個車號，我有記\n    載在工作記錄簿上，並通知交通隊」「（問：當天你是否第\n    一個到場處理的警員？）是的」「（問：你在偵查中有陳述\n    ：還有另外一個四、五十歲的路人提供車號給你，有何意見\n    ？）我沒有意見，因為當時車禍不只戊○○在現場，附近的\n    民眾還有二、三個人，我沒有登記路人的姓名，只有登記小\n    客車的駕駛戊○○的姓名而已，如果我第一次在偵訊中有這\n    樣說的話，應該是實在的，因為當時我有翻閱工作記錄簿」\n    「（問：你在第一次偵查庭中說，有路人提供車號給你，請\n    說明那個路人的樣子？）那個人大概四、五十歲的路人，應\n    該是住在附近的人的因為他穿拖鞋」「（問：路人有無跟你\n    講車號？）當時人蠻多的，路人應該也是有跟我講車號」「\n    （問：你到現場時，看到哪幾部車有擦撞？）只有一部營業\n    小客車還有路人的摩托車，但跟據現場所有人跟我講，是有\n    兩部自小客車擦撞，但是只有一部營業自小客車在現場」「\n    （問：你有無問路人他如何得知這個肇事車號？）沒有，他\n    主動提供的」「（問：你有無向交通隊到場的隊員講肇事車\n    號？）有的，我是把全部的資料交給他們，口頭也有講大概\n    事實的經過」「（問：你在偵查中說：戊○○跟路人一起說\n    這個車號，你現在是否記得？）那個路人大約四、五十歲，\n    頭髮有點花白，我記得戊○○有跟我講，那個路人也在旁邊\n    附和說，就是這個車號」「（問：你的意思不是說路人說一\n    個車號，戊○○也說一個車號，你聽到的車號是一樣的？）\n    路人也有講出車號來，當時戊○○跟路人都只有講車號，沒\n    有講車的廠牌、顏色等」「（問：你有無告知交通分隊有車\n    輛逃逸？）有的，我有跟交通隊說是肇事逃逸的案件，由他\n    們處理」等語相符（原審93年9月27日審判筆錄），並有其\n    當天處理本件車禍之警方工作紀錄簿影本一紙其上記載被告\n    所駕車輛之車號等情在卷可稽（原審卷第135頁）。復核與\n    證人即交通分隊警員陳德威於原審審理時證述：「我有處理\n    92年3月18日晚上10時27分在重慶北路保安街口的交通事故\n    。當時我到場的時候只有看到一部計程車停在路中間，另外\n    機車卡到安全島上，我先量現場圖，然後再到醫院處理」「\n    （問：道路交通事故調查表二上所載車號3B-3859號車號，\n    是如何得知的？（提示偵查卷40頁）是計程車駕駛說的」「\n    （問：你到場的時候，黃國書是否還在場？）還在場」「（\n    問：他有無向你告知本件交通事故事宜？）他有跟我講肇事\n    逃逸車輛的車號」「（問：你到場之後，有無路人在現場？\n    ）沒有」「（問：道路交通事故補充資料表，上面A車註明\n    賓士黑，是如何得知的？）是計程車司機跟我講後，我用電\n    腦去查的」「（問：你是否有觀察計程車右側留有遭碰撞的\n    漆？）我沒有印象，但是我確定它的右側確實被碰撞。因為\n    右側的車門整個凹陷，且是新痕」「（問：當時是否先查肇\n    逃的車是賓士車，還是告訴人先告訴你是賓士車？）她是告\n    訴我車號及一部黑色的自小客，她沒有講車種及車型」「（\n    問：根據你的經驗，計程車右側被撞的凹陷，撞擊車輛的保\n    險桿是否還可以完好？）要看保險桿的鋼樑及側撞的角度，\n    絕對有可能保險桿仍然完好。如果只是轉角地方撞到，就有\n    可能整支保險桿完好，就我所知，有些保險桿很強壯，撞到\n    他車，他車的漆會沾附在該車上，而不是該車的漆掉落在他\n    車上，我們看過很多車禍的狀況是這樣」「（問：如果是整\n    支保險桿撞到保險桿是否會損害？）如果兩部車的角度對的\n    話，還是有可能保險桿還是完好的」「（問：你在現場有無\n    路人跟你說賓士車的車號？）我到達現場時，沒有其他路人\n    ，只有告訴人跟我講。黃國書並沒有告訴我有其他路人看到\n    賓士車的車號，黃國書有跟我講賓士車的車號，但是我還是\n    去問計程車司機」等情相符（原審93年11月15日審判筆錄）\n    。此外復有道路交通事故現場圖、道路交通事故調查報告表\n    （除警方自行判斷之部分外）(一)(二)、現場照片8幀及告訴人\n    營業小客車毀損照片多幀在偵查卷可按。而告訴人戊○○與\n    被害人丁○○、丙○○所受傷害，亦有臺北市立中興醫院診\n    斷證明書（偵查卷第95頁）及財團法人馬偕紀念醫院診斷證\n    明書（偵查卷第30至31頁）各1件在卷可憑。\n  (二)綜上，被告雖否認有何過失傷害及肇事逃逸之犯行，但依告\n    訴人之指訴及證人黃國書、陳德威上揭證詞，足認告訴人於\n    突遭車禍之際，即立刻將肇事車輛之車號3B-3859及其車色\n    （黑色）告知前來處理之警員（依警方交通事故談話紀錄表\n    所載之時間為92年3月18日晚上10時38分許，此部分不涉及\n    供述，非傳聞證據），且恰與另一不詳年籍之中年路人向警\n    方告知之車號相同，而均與被告車輛之車牌及車色相符，即\n    被告亦不否認於右揭時地曾途經該處並停等紅燈，則告訴人\n    與證人均與被告素無仇怨，復受具結刑責之擔保，則何以如\n    此巧合地告訴人及該路人所指訴之車輛能與證人陳德威查證\n    後被告車輛之車號及車色均屬一致？顯見告訴人上揭指訴並\n    非虛妄，而具有可信度，復參以被害人丁○○於偵查時指述\n    ：「在被碰撞前有聽到車子煞車的尖銳聲」等語（偵查卷第\n    85頁），以及告訴人車輛之右側車身下半部（車側飾條處）\n    凹陷嚴重，其受損之高度均低於其本身保險桿之部位，而被\n    告之車輛為跑車型式，其車身本較一般車輛為低等情以觀，\n    被告確有於右揭時地駕車撞擊告訴人後復逃離現場，足堪認\n    定，其上揭所辯，均係卸責之詞，委無足採。\n三、又經原審函詢被告所駕車輛之保險公司及原廠維修公司，雖\n    分別稱：「自92年3月18日以後無出險紀錄」及「有關3B-\n    3859賓士車曾於92年12月1日進入中華賓士南港廠維修。維\n    修項目：更換室內燈開關、排檔桿橡皮、檔位開關、電動車\n    頂開關」等情，此有富邦產物保險股份有限公司93年7月12\n    日（九三）富保業發字第212號及中華賓士汽車股份有限公\n    司93年7月5日中賓字第9306013號函各1件在卷可考 (原審卷\n    第23、24頁)，但車輛維修非必在原廠為之，且因各別特殊\n    之原因亦未必辦理出險手續，為一般社會生活之通常經驗，\n    且被告車輛經警方通知到場勘驗及拍照時，距案發時間已1\n    月又4日，亦難認該車輛仍維持案發時之原狀，自均不足以\n    此而推翻前開不利之證據，而為被告有利之認定，被告聲請\n    傳喚甲○○證明被告還車時之車況，及函查該車於92年10月\n    以後之所有人，亦非有必要，均附此敘明。\n四、被告聲請將本件送請臺北市車輛行車事故鑑定委員會以電腦\n    動畫軟體重建現場，鑑定本件告訴人之汽車是否為被告汽車\n    所撞擊一節，經該委員會函復本院以「有關冀以電腦軟體\n    HEV-2D，重建車禍事故現場一事，因國內各大車廠及公路監\n    理機關對於各型車輛基本參數資料庫均尚未建立，且交通部\n    、經濟部亦未訂定相關法令，因此該軟體僅以學術研究為主\n    ... 因此本會已無使用該項軟體作為行車事故鑑定之依據」\n    ，有該委員會94年6月8日北鑑審字第09430201600號函在卷\n    可稽，雖被告據此再聲請送中央大學、成功大學、交通大學\n    或逢甲大學鑑定，於原審亦聲請送警察大學鑑定，惟查本件\n    確係被告所駕車號3B-3859號黑色賓士車違規倒車撞擊告訴\n    人所駕營業小客車，業據上開證人證述明確，其等證言核無\n    可疑之處，則本件事證已明，自無再送鑑定之必要，亦附予\n    敘明。\n五、被告辯護人於原審準備程序時主張如起訴書證據清單編號\n    二、三、五、六、八所示之證據能力應予排除（原審93年6\n    月8日準備程序筆錄），其中告訴人及證人黃國書，原審已\n    依法傳喚到庭並依證人交互詰問程序令其陳述；另被害人丁\n    ○○於警方交通事故談話紀錄表內之陳述、交通事故分析研\n    判表、談話紀錄表及補充資料表內，關於人之供述及警方自\n    行判斷之部分，依其性質均屬刑事訴訟法第159條第1項之傳\n    聞證據，原審及本院均已排除其證據能力而未採為認定本件\n    犯罪事實之依據；又本件偵查卷內之臺北市車輛行車事故鑑\n    定委員會鑑定意見書係警方囑託為之，不符刑事訴訴法第\n    198條關於鑑定之規定，亦應排除其證據能力；至道路交通\n    事故現場圖不涉及判斷之部分，應屬同法第159條之4第1款\n    之公務員職務上製作之紀錄文書，而為傳聞法則之例外，得\n    作為適格之證據；至其餘未經當事人於言詞辯論終結前聲明\n    異議之證據，本院認依其陳述作成時之情況，均係本於其自\n    由意志或職務上應為之事項，自應認其適為認定本件犯罪事\n    實之證據，併此指明。\n六、按汽車於快車道等危險地帶或交通頻繁處所，不得倒車，道\n    路交通安全規則第110條第1款定有明文。本件被告駕車行經\n    上開路段，本應注意上開規定不得倒車，且依當時之天候雖\n    係陰天但於夜間有照明，且路面乾燥、無缺陷、道路無障礙\n    物、路況及視距均良好等情況，並無不能注意之特殊情形，\n    乃竟疏未注意，逕行於快車道倒車至重慶北路二段與保安街\n    交叉路口之交通頻繁處所，以致肇事致告訴人受傷，其有過\n    失，甚為明確，又被告之過失行為與告訴人所受傷害間復具\n    有相當因果關係，且其肇事後未即時救護傷者，反加速逕行\n    離去，有如上述，是其過失傷害及肇事逃逸之犯行，均堪認\n    定，本件事證已臻明確，應依法論科。\n七、核被告所為，係犯刑法第284條第1項之過失傷害罪及第185\n    之4之肇事致人受傷逃逸罪。所犯二罪，犯意各別，行為互\n    殊，構成要件亦不相同，應予分論併罰。\n八、原審以被告犯罪，事證明確，適用刑法第185條之4、第284\n    條第1項、第51條第5款，罰金罰鍰提高標準條例第1條前段\n    之規定，審酌被告為規避己身刑責，竟於駕車肇事後逃逸無\n    蹤，置傷者於不顧，惡性非輕，犯後猶飾詞卸責，毫無悔意\n    ，且迄未賠償被害人所受損害，但其素行尚稱良好，告訴人\n    所受傷害非重暨其教育智識程度等一切情狀，分別就過失傷\n    害人罪，量處有期徒刑3月；就駕駛動力交通工具肇事，致\n    人受傷而逃逸罪，量處有期徒刑8月。並定應執行刑為有期\n    徒刑10月，經核認事用法及量刑均無不合。被告上訴猶執陳\n    詞否認犯罪，指摘原判決不當，核無理由，應駁回其上訴。\n據上論斷，應依刑事訴訟法第368條，判決如主文。\n本案經檢察官張秋雲到庭執行職務。\n中    華    民    國    94    年    7     月    19    日\n                  刑事第十五庭審判長法  官  陳榮和\n                                    法  官  張正亞\n                                    法  官  蔡國在\n以上正本證明與原本無異。\n公共危險罪部分如不服本判決，應於收受送達後十日內向本院提\n出上訴書狀，其未敘述上訴之理由者並得於提起上訴後十日內向\n本院補提理由書（均須按他造當事人之人數附繕本）。\n                                    書記官  耿鳳君"
  },
  "search": "臺灣高等法院刑事判決94年度交上訴字第53號上訴人即被告乙○○選任辯護人林月雪律師江鶴鵬律師上列上訴人因公共危險等案件，不服臺灣士林地方法院93年度交訴字第35號，中華民國93年12月31日第一審判決（起訴案號：92年度偵字第7634號），提起上訴，本院判決如下：主文上訴駁回。事實一、乙○○於民國（下同）92年3月18日晚上10時27分許，駕駛其友人甲○○所有車號3B-3859號德國賓士牌黑色自用小客車，於臺北市○○區○○街交岔路口附近東側之重慶北路二段右側慢車道暫停，嗣其起駛後隨即又欲自保安街由西往東方向行駛，其本應注意汽車於快車道等危險地帶或交通頻繁處所，不得倒車，而依當時之天候雖係陰天但夜間有照明，路面乾燥、無缺陷、道路無障礙物、路況及視距均良好等情況，並無不能注意之特殊情形，乃竟疏未注意，由重慶北路二段外側快車道直接向後倒車，並於到達保安街口時又加速由東向西倒車至重慶北路二段內側第二車道與保安街南側車道口之交通頻繁處所，以便其向前直駛保安街，適由戊○○所駕駛車號3E-219號營業小客車正由重慶北路二段內側第二車道（起訴書誤載為第三車道）綠燈後甫起駛至該處，乙○○所駕車輛車身後保險桿部位遂直接正面撞擊戊○○車輛右側下半部車身，戊○○之車輛又再往左偏撞刻亦正於重慶北路二段南向北內側第二車道行駛，由丁○○騎乘附載丙○○之車號BEI-327號重型機車前車頭，致丁○○與丙○○人、車倒地，並因此使戊○○受有兩膝及下背挫傷等傷害，丁○○受有全身多處擦傷、頸部、右大腿挫傷等傷害，丙○○則受有右手、右肘、左手、下肢多處擦傷、鈍挫傷等傷害（丁○○、丙○○所受傷害部分均未據告訴）。詎乙○○明知已駕車肇事致人受傷，竟未停車查看並救護傷者戊○○、丁○○及丙○○，反為規避其法律責任，另行起意，逕自駕駛上開車輛由保安街西向東直駛，逃離肇事現場，惟經戊○○機警記下其車號與顏色，並分別向先後抵達現場處理之臺北市政府警察局大同分局寧夏派出所及交通分隊員警黃國書、陳德威報告乙○○上開車輛之車號及顏色（黑色），始經警循線查獲。二、案經戊○○訴由臺北市政府警察局大同分局報請臺灣士林地方檢法院察署檢察官偵查起訴。理由一、訊據上訴人即被告乙○○固不否認曾於右揭時、地間駕駛其友人甲○○所有車號3B-3859號德國賓士牌黑色自用小客車，由臺北市大同區○○○路○段南向北外側車道行駛，並曾於該路段與保安街交岔路口停等紅燈等事實，但否認有何過失傷害及肇事逃逸等犯行，辯稱：伊當時直接沿重慶北路向北行駛回士林的家，並未倒車往保安街直駛，更未倒車撞及告訴人戊○○所駕營業小客車並肇事逃逸等語。二、惟查:(一)被告確有於右揭時、地駕駛友人甲○○所有車號3B-3859號德國賓士牌黑色自用小客車，於臺北市○○區○○街交岔路口附近東側之重慶北路二段右側慢車道暫停，嗣其起駛後隨即又欲自保安街由西往東方向行駛，竟疏未注意，由重慶北路二段外側快車道直接向後倒車，並於到達保安街口時又加速由東向西倒車至重慶北路二段內側第二車道與保安街南側車道口之交通頻繁處所，以便其繼續向前直駛保安街，以致撞擊告訴人戊○○駕駛車號3E-219號營業小客車右側下半部車身，戊○○之車輛又再往左偏撞刻亦正於重慶北路二段南向北內側第二車道行駛由被害人丁○○所騎乘附載丙○○之車號BEI-327號重型機車前車頭，且其明知已駕車肇事致人受傷，竟逕自駕駛上開車輛逃離肇事現場，但仍經戊○○記下其車號及車色並分別告知員警黃國書及陳德威等情，業據證人即告訴人戊○○分別於偵查及原審審理時結證稱：「（問：妳當時看到的車號是幾號？）3B-3859」「（問：車子的顏色呢？）黑色」「（問：廠牌呢？）賓士」「（問：妳的車子怎麼被撞的？）紅燈停止，變綠燈時我往前開，那輛黑色的車子本來是往前開，突然後退，之後轉彎，後保險桿整面撞到我的右側車身」「（問：車號是妳提供給警察的嗎？）對，那天另外一位好心人士有追過去把車號抄回去給警察，我是和那個人同時將車號提供給寧夏派出所的警員黃國書」（偵查卷第92至93頁）；「（問：本件交通事故發生經過情形如何？）當時我在等紅綠燈，我有看到一部車從路邊開出來，後來該部車突然倒退，它原本停在路邊，我走在最內側車道，我的左側是公車專屬車道，當時他在最外側車道，我認為他倒退不可能影響到我，所以我直行。沒想到他突然走到十字路口速度突然加快且轉彎，就這樣撞到我了」「（問：機車倒地時，被告的車輛在何處？）我眼睛張開的時候，該部肇事車輛在我右側車身旁邊，與我成垂直狀態，我看到他的車有踩煞車燈，他就往前開了，我就拿筆在車上白板寫上他的車號，我往左看，就看到機車騎士抱起他的女乘客」「（問：撞到你車的肇事車輛廠牌和顏色？）黑色賓士車」「（問：是由何人將肇事車輛車號告訴警員黃國書？）我不知道，當機車騎士抱起女乘客時，我走下車，叫了救護車，沒有多久警員就來了，警察就問一下現場狀況，我和一個機車騎士就同時說出車號，他可能有去追肇事車輛，再回來跟警察說。」「（問：你在第幾線道？）我在內側第二線道」「（問：撞擊你的車輛是在第幾線道？）最外側車道」「（問：他是否在停止狀態？）我在停等紅燈的時候，他停在過紅綠燈的右前方路邊」「（問：外側第三、四線道有無其他車輛？）我剛開始等紅綠燈的時候是沒有」「（問：你說有機車騎士有看到肇事車牌？）是他自己去追的。警察來的時候，他自己跟警察說的。我有問他肇事車號，他為何知道，他說他去追的時候看到的。後來交通大隊來的時候，他就不在現場。他沒有說他追多遠。他是跟黃國書警員說的」「（問：看到肇事車輛車牌的機車騎士的外表可否描述一下？）騎125CC的男性約五、六十歲，胖胖的」「（問：你車前葉子板的高度有多高？撞到你的肇事車是用何部分撞到你的車？）後保險桿」「（問：撞到你何部分？）我車右側車身，車輛受損的部分是右前葉子板到右後門」「（問：肇事車輛右邊有無停車格？）沒有，那裡是畫紅線，被告是我看到的第一部車輛，在他車後沒有停其他車，他前面我沒有注意，他是在十字路口轉彎後有一小段距離停在路邊」「（問：在倒退的時候，你有無注意他的車型？）我沒有注意，撞的時候才注意到」「（問：你看到撞你的車，有無特徵？）沒有，就是黑色賓士跑車。後面沒有車型的標示，也沒有注意它是幾門車輛」「（問：當時的車流量如何？）我下車的時候開始有車，變燈起步的時候，我是第一部車，我是唯一等紅綠燈的車。我車子已經修理好了」「（問：肇事的時候，你如何確定該部車是黑色的？）因為它撞到我，距離很近，我上班的店在民族西路188號，民族西路184號是專門修理賓士車的店，我常常在該店看賓士車，對於賓士車的車型顏色很熟悉」「（問：撞擊的情形如何？）他是整個車尾撞到我，當時兩部車是垂直的情形，後來他就往保安街開走」「（問：賓士車尾有無受損？）沒有很明顯的受損。當時我是坐在駕駛座，往右側車窗看出去，當時車窗是關著的」等語綦詳（原審93年9月6日審判筆錄）。於本院審理中亦結證稱被告所駕汽車車號係伊所記下，警員到場時，另有一人亦同時說出相同之車號等語，核與證人即現場處理之警員黃國書於原審審理時證稱：「當天我有處理這件車禍，詳細時間我記不得，當時我是備差，就過去處理，現場只有一部營業小客車，即戊○○所駕駛的，當時她有給我一個車號，我有記載在工作記錄簿上，並通知交通隊」「（問：當天你是否第一個到場處理的警員？）是的」「（問：你在偵查中有陳述：還有另外一個四、五十歲的路人提供車號給你，有何意見？）我沒有意見，因為當時車禍不只戊○○在現場，附近的民眾還有二、三個人，我沒有登記路人的姓名，只有登記小客車的駕駛戊○○的姓名而已，如果我第一次在偵訊中有這樣說的話，應該是實在的，因為當時我有翻閱工作記錄簿」「（問：你在第一次偵查庭中說，有路人提供車號給你，請說明那個路人的樣子？）那個人大概四、五十歲的路人，應該是住在附近的人的因為他穿拖鞋」「（問：路人有無跟你講車號？）當時人蠻多的，路人應該也是有跟我講車號」「（問：你到現場時，看到哪幾部車有擦撞？）只有一部營業小客車還有路人的摩托車，但跟據現場所有人跟我講，是有兩部自小客車擦撞，但是只有一部營業自小客車在現場」「（問：你有無問路人他如何得知這個肇事車號？）沒有，他主動提供的」「（問：你有無向交通隊到場的隊員講肇事車號？）有的，我是把全部的資料交給他們，口頭也有講大概事實的經過」「（問：你在偵查中說：戊○○跟路人一起說這個車號，你現在是否記得？）那個路人大約四、五十歲，頭髮有點花白，我記得戊○○有跟我講，那個路人也在旁邊附和說，就是這個車號」「（問：你的意思不是說路人說一個車號，戊○○也說一個車號，你聽到的車號是一樣的？）路人也有講出車號來，當時戊○○跟路人都只有講車號，沒有講車的廠牌、顏色等」「（問：你有無告知交通分隊有車輛逃逸？）有的，我有跟交通隊說是肇事逃逸的案件，由他們處理」等語相符（原審93年9月27日審判筆錄），並有其當天處理本件車禍之警方工作紀錄簿影本一紙其上記載被告所駕車輛之車號等情在卷可稽（原審卷第135頁）。復核與證人即交通分隊警員陳德威於原審審理時證述：「我有處理92年3月18日晚上10時27分在重慶北路保安街口的交通事故。當時我到場的時候只有看到一部計程車停在路中間，另外機車卡到安全島上，我先量現場圖，然後再到醫院處理」「（問：道路交通事故調查表二上所載車號3B-3859號車號，是如何得知的？（提示偵查卷40頁）是計程車駕駛說的」「（問：你到場的時候，黃國書是否還在場？）還在場」「（問：他有無向你告知本件交通事故事宜？）他有跟我講肇事逃逸車輛的車號」「（問：你到場之後，有無路人在現場？）沒有」「（問：道路交通事故補充資料表，上面A車註明賓士黑，是如何得知的？）是計程車司機跟我講後，我用電腦去查的」「（問：你是否有觀察計程車右側留有遭碰撞的漆？）我沒有印象，但是我確定它的右側確實被碰撞。因為右側的車門整個凹陷，且是新痕」「（問：當時是否先查肇逃的車是賓士車，還是告訴人先告訴你是賓士車？）她是告訴我車號及一部黑色的自小客，她沒有講車種及車型」「（問：根據你的經驗，計程車右側被撞的凹陷，撞擊車輛的保險桿是否還可以完好？）要看保險桿的鋼樑及側撞的角度，絕對有可能保險桿仍然完好。如果只是轉角地方撞到，就有可能整支保險桿完好，就我所知，有些保險桿很強壯，撞到他車，他車的漆會沾附在該車上，而不是該車的漆掉落在他車上，我們看過很多車禍的狀況是這樣」「（問：如果是整支保險桿撞到保險桿是否會損害？）如果兩部車的角度對的話，還是有可能保險桿還是完好的」「（問：你在現場有無路人跟你說賓士車的車號？）我到達現場時，沒有其他路人，只有告訴人跟我講。黃國書並沒有告訴我有其他路人看到賓士車的車號，黃國書有跟我講賓士車的車號，但是我還是去問計程車司機」等情相符（原審93年11月15日審判筆錄）。此外復有道路交通事故現場圖、道路交通事故調查報告表（除警方自行判斷之部分外）(一)(二)、現場照片8幀及告訴人營業小客車毀損照片多幀在偵查卷可按。而告訴人戊○○與被害人丁○○、丙○○所受傷害，亦有臺北市立中興醫院診斷證明書（偵查卷第95頁）及財團法人馬偕紀念醫院診斷證明書（偵查卷第30至31頁）各1件在卷可憑。(二)綜上，被告雖否認有何過失傷害及肇事逃逸之犯行，但依告訴人之指訴及證人黃國書、陳德威上揭證詞，足認告訴人於突遭車禍之際，即立刻將肇事車輛之車號3B-3859及其車色（黑色）告知前來處理之警員（依警方交通事故談話紀錄表所載之時間為92年3月18日晚上10時38分許，此部分不涉及供述，非傳聞證據），且恰與另一不詳年籍之中年路人向警方告知之車號相同，而均與被告車輛之車牌及車色相符，即被告亦不否認於右揭時地曾途經該處並停等紅燈，則告訴人與證人均與被告素無仇怨，復受具結刑責之擔保，則何以如此巧合地告訴人及該路人所指訴之車輛能與證人陳德威查證後被告車輛之車號及車色均屬一致？顯見告訴人上揭指訴並非虛妄，而具有可信度，復參以被害人丁○○於偵查時指述：「在被碰撞前有聽到車子煞車的尖銳聲」等語（偵查卷第85頁），以及告訴人車輛之右側車身下半部（車側飾條處）凹陷嚴重，其受損之高度均低於其本身保險桿之部位，而被告之車輛為跑車型式，其車身本較一般車輛為低等情以觀，被告確有於右揭時地駕車撞擊告訴人後復逃離現場，足堪認定，其上揭所辯，均係卸責之詞，委無足採。三、又經原審函詢被告所駕車輛之保險公司及原廠維修公司，雖分別稱：「自92年3月18日以後無出險紀錄」及「有關3B-3859賓士車曾於92年12月1日進入中華賓士南港廠維修。維修項目：更換室內燈開關、排檔桿橡皮、檔位開關、電動車頂開關」等情，此有富邦產物保險股份有限公司93年7月12日（九三）富保業發字第212號及中華賓士汽車股份有限公司93年7月5日中賓字第9306013號函各1件在卷可考(原審卷第23、24頁)，但車輛維修非必在原廠為之，且因各別特殊之原因亦未必辦理出險手續，為一般社會生活之通常經驗，且被告車輛經警方通知到場勘驗及拍照時，距案發時間已1月又4日，亦難認該車輛仍維持案發時之原狀，自均不足以此而推翻前開不利之證據，而為被告有利之認定，被告聲請傳喚甲○○證明被告還車時之車況，及函查該車於92年10月以後之所有人，亦非有必要，均附此敘明。四、被告聲請將本件送請臺北市車輛行車事故鑑定委員會以電腦動畫軟體重建現場，鑑定本件告訴人之汽車是否為被告汽車所撞擊一節，經該委員會函復本院以「有關冀以電腦軟體HEV-2D，重建車禍事故現場一事，因國內各大車廠及公路監理機關對於各型車輛基本參數資料庫均尚未建立，且交通部、經濟部亦未訂定相關法令，因此該軟體僅以學術研究為主...因此本會已無使用該項軟體作為行車事故鑑定之依據」，有該委員會94年6月8日北鑑審字第09430201600號函在卷可稽，雖被告據此再聲請送中央大學、成功大學、交通大學或逢甲大學鑑定，於原審亦聲請送警察大學鑑定，惟查本件確係被告所駕車號3B-3859號黑色賓士車違規倒車撞擊告訴人所駕營業小客車，業據上開證人證述明確，其等證言核無可疑之處，則本件事證已明，自無再送鑑定之必要，亦附予敘明。五、被告辯護人於原審準備程序時主張如起訴書證據清單編號二、三、五、六、八所示之證據能力應予排除（原審93年6月8日準備程序筆錄），其中告訴人及證人黃國書，原審已依法傳喚到庭並依證人交互詰問程序令其陳述；另被害人丁○○於警方交通事故談話紀錄表內之陳述、交通事故分析研判表、談話紀錄表及補充資料表內，關於人之供述及警方自行判斷之部分，依其性質均屬刑事訴訟法第159條第1項之傳聞證據，原審及本院均已排除其證據能力而未採為認定本件犯罪事實之依據；又本件偵查卷內之臺北市車輛行車事故鑑定委員會鑑定意見書係警方囑託為之，不符刑事訴訴法第198條關於鑑定之規定，亦應排除其證據能力；至道路交通事故現場圖不涉及判斷之部分，應屬同法第159條之4第1款之公務員職務上製作之紀錄文書，而為傳聞法則之例外，得作為適格之證據；至其餘未經當事人於言詞辯論終結前聲明異議之證據，本院認依其陳述作成時之情況，均係本於其自由意志或職務上應為之事項，自應認其適為認定本件犯罪事實之證據，併此指明。六、按汽車於快車道等危險地帶或交通頻繁處所，不得倒車，道路交通安全規則第110條第1款定有明文。本件被告駕車行經上開路段，本應注意上開規定不得倒車，且依當時之天候雖係陰天但於夜間有照明，且路面乾燥、無缺陷、道路無障礙物、路況及視距均良好等情況，並無不能注意之特殊情形，乃竟疏未注意，逕行於快車道倒車至重慶北路二段與保安街交叉路口之交通頻繁處所，以致肇事致告訴人受傷，其有過失，甚為明確，又被告之過失行為與告訴人所受傷害間復具有相當因果關係，且其肇事後未即時救護傷者，反加速逕行離去，有如上述，是其過失傷害及肇事逃逸之犯行，均堪認定，本件事證已臻明確，應依法論科。七、核被告所為，係犯刑法第284條第1項之過失傷害罪及第185之4之肇事致人受傷逃逸罪。所犯二罪，犯意各別，行為互殊，構成要件亦不相同，應予分論併罰。八、原審以被告犯罪，事證明確，適用刑法第185條之4、第284條第1項、第51條第5款，罰金罰鍰提高標準條例第1條前段之規定，審酌被告為規避己身刑責，竟於駕車肇事後逃逸無蹤，置傷者於不顧，惡性非輕，犯後猶飾詞卸責，毫無悔意，且迄未賠償被害人所受損害，但其素行尚稱良好，告訴人所受傷害非重暨其教育智識程度等一切情狀，分別就過失傷害人罪，量處有期徒刑3月；就駕駛動力交通工具肇事，致人受傷而逃逸罪，量處有期徒刑8月。並定應執行刑為有期徒刑10月，經核認事用法及量刑均無不合。被告上訴猶執陳詞否認犯罪，指摘原判決不當，核無理由，應駁回其上訴。據上論斷，應依刑事訴訟法第368條，判決如主文。本案經檢察官張秋雲到庭執行職務。中華民國94年7月19日刑事第十五庭審判長法官陳榮和法官張正亞法官蔡國在以上正本證明與原本無異。公共危險罪部分如不服本判決，應於收受送達後十日內向本院提出上訴書狀，其未敘述上訴之理由者並得於提起上訴後十日內向本院補提理由書（均須按他造當事人之人數附繕本）。書記官耿鳳君中華民國94年7月19日附錄：本案論罪科刑法條全文刑法第185條之4駕駛動力交通工具肇事，致人死傷而逃逸者，處6月以上5年以下有期徒刑。第284條第1項因過失傷害人者，處6月以下有期徒刑、拘役或500元以下罰金，致重傷者，處1年以下有期徒刑、拘役或500元以下罰金。",
  "characters": {
    "judges": [
      "陳榮和",
      "張正亞",
      "蔡國在"
    ],
    "prosecutors": [
      "張秋雲"
    ],
    "lawyers": [
      "林月雪",
      "江鶴鵬"
    ],
    "clerks": [
      "耿鳳君"
    ],
    "plaintiffs": [

    ],
    "defendants": [
      "乙"
    ],
    "prosecutor_office": [

    ],
    "creditors": [

    ],
    "debtors": [

    ],
    "judicial_associate_officer": [

    ]
  },
  "adjudged_at": "2005-07-19",
  "created_at": "2016-02-07 08:26:51",
  "updated_at": "2016-02-07 08:26:51"
}