{
  "identify": "TPD-93-重訴-554-20040802-2",
  "court": {
    "name": "臺灣臺北地方法院",
    "code": "TPD"
  },
  "division": {
    "name": "民事",
    "code": "V"
  },
  "year": 93,
  "word": "重訴",
  "number": "554",
  "jcheck": "2",
  "reason": "侵權行為損害賠償",
  "content": "臺灣臺北地方法院民事裁定                        九十三年度重訴字第五五四號\n    原      告  丙○○\n                甲○○○\n    右  一  人\n    訴訟代理人  乙○○\n    被      告  丁○○\n當事人間請求侵權行為損害賠償事件，本院於民國九十三年八月二日所為之判決，其\n正本應更正如下：\n    主  文\n原判決正本理由欄中關於「陳清芳」記載，應更正為「李清芳」。\n    理  由\n一、按判決如有誤寫、誤算或其他類此之顯然錯誤者，法院得隨時或依聲請以裁定更\n    正之，其正本與原本不符者亦同，民事訴訟法第二百三十二條第一項定有明文。\n二、查本院前開之判決正本有如主文所示之顯然錯誤，應予更正。\n三、依首開規定裁定如主文。\n中      華      民      國    九十三    年      八      月      二      日\n                              民事第三庭  法  官    林振芳\n正本係照原本作成\n如不服本裁定應於送達後十日內向本院提出抗告狀，並繳納抗告費新臺幣一千元\n中      華      民      國    九十三    年      八      月      二      日\n                                          書記官    李淑芬\n",
  "structure": {
    "main": "原判決正本理由欄中關於「陳清芳」記載，應更正為「李清芳」。",
    "reason": "一、按判決如有誤寫、誤算或其他類此之顯然錯誤者，法院得隨時或依聲請以裁定更\n    正之，其正本與原本不符者亦同，民事訴訟法第二百三十二條第一項定有明文。\n二、查本院前開之判決正本有如主文所示之顯然錯誤，應予更正。\n三、依首開規定裁定如主文。"
  },
  "search": "臺灣臺北地方法院民事裁定九十三年度重訴字第五五四號原告丙○○甲○○○右一人訴訟代理人乙○○被告丁○○當事人間請求侵權行為損害賠償事件，本院於民國九十三年八月二日所為之判決，其正本應更正如下：主文原判決正本理由欄中關於「陳清芳」記載，應更正為「李清芳」。理由一、按判決如有誤寫、誤算或其他類此之顯然錯誤者，法院得隨時或依聲請以裁定更正之，其正本與原本不符者亦同，民事訴訟法第二百三十二條第一項定有明文。二、查本院前開之判決正本有如主文所示之顯然錯誤，應予更正。三、依首開規定裁定如主文。中華民國九十三年八月二日民事第三庭法官林振芳正本係照原本作成如不服本裁定應於送達後十日內向本院提出抗告狀，並繳納抗告費新臺幣一千元中華民國九十三年八月二日書記官李淑芬",
  "characters": {
    "judges": [
      "林振芳"
    ],
    "prosecutors": [

    ],
    "lawyers": [

    ],
    "clerks": [
      "李淑芬"
    ],
    "plaintiffs": [
      "丙"
    ],
    "defendants": [
      "丁○○",
      "當事人間請求侵權行為損害賠償事件，本院於民國九十三年八月二日所為之判決，其",
      "正本應更正如下："
    ],
    "prosecutor_office": [

    ],
    "creditors": [

    ],
    "debtors": [

    ],
    "judicial_associate_officer": [

    ]
  },
  "adjudged_at": "2004-08-02",
  "created_at": "2016-02-06 02:03:22",
  "updated_at": "2016-02-06 02:03:22"
}