{
  "identify": "KSD-91-易-131-20021009-1",
  "court": {
    "name": "臺灣高雄地方法院",
    "code": "KSD"
  },
  "division": {
    "name": "刑事",
    "code": "M"
  },
  "year": 91,
  "word": "易",
  "number": "131",
  "jcheck": "1",
  "reason": "賭博",
  "content": "臺灣高雄地方法院刑事判決                          九十一年度易字第一三一號\n    公  訴  人  臺灣高雄地方法院檢察署檢察官\n    被      告  乙○○\n    被      告  丙○○\n    被      告  甲○○○\n右列被告因賭博案件，經檢察官聲請簡易判決處刑（九十年度偵字第七五三八號），\n經本院鳳山簡易庭認為不宜以簡易判決處刑，簽請依通常程序審理，本院判決如左：\n    主  文\n乙○○、丙○○、甲○○○共同連續意圖營利，聚眾賭博，乙○○處有期徒刑肆月，\n丙○○、甲○○○各處有期徒刑參月，如易科罰金均以佰元折算壹日。\n扣案之賭資新台幣陸仟伍百元、雙面撲克牌壹拾貳張、紙質天九牌參拾貳張、未拆封\n紙質天九牌拾肆付、膠質天九牌貳付、計算機貳台、撲克牌壹付、麻將壹付、骰子壹\n批、帳冊壹本、號碼牌（下注標示）壹包、無線電壹台，均沒收之。\n    事  實\n一、丙○○、與甲○○○分別於民國八十七年及七十六年、八十九年曾犯有賭博罪之\n    紀錄，均經法院判處罰金（未構成累犯）。猶不知悔改，自九十年四月十六日起\n    ，與乙○○共同基於意圖營利之概括犯意聯絡及行為分擔，由乙○○向不知情之\n    陳千六承租高雄縣仁武鄉○○路二二九號後面工廠之房屋，在上址公眾得出入之\n    處所聚眾在該處賭博財物，並以每日新台幣（下同）一千元之代價僱請丙○○擔\n    任賭場把風工作，並由甲○○○負責作莊家，由賭客何金成、柯朝雄、許雄、陳\n    志坤、帥念宗、陳國勝、謝黃素娥、林瑞娥、黃美滿、鄭錦繡、薛玉枝、林信宏\n    、蔡慶笑等人持天九牌與莊家比點數大小定輸贏，押注賭資不限，若莊家輸，莊\n    家需依押注金額賠付賭客，乙○○再向賭客贏者抽取一成牟利，並且依莊家贏取\n    賭客金額之一定比例給付予甲○○○作為報酬，嗣於同年四月十七日下午二時三\n    十分許，在上開處所，經警當場查獲，並扣得乙○○所有供犯罪或預備供犯罪所\n    用之雙面撲克牌十二張、紙質天九牌三十二張、未拆封紙質天九牌十四付、膠質\n    天九牌二付、計算機二台、撲克牌一付、麻將一付、骰子一批、帳冊一本、號碼\n    牌（下注標示用）一包、無線電一台及上開賭客所共有之賭資六千五百元。\n二、案經高雄縣警察局林園分局報請臺灣高雄地方法院檢察署檢察官偵查聲請簡易判\n    決處刑。\n    理  由\n一、右揭犯罪事實，業據被告乙○○、丙○○、甲○○○於本院審理時均坦認不諱，\n    核與共同被告所供一致，復參以賭客之何金成、柯朝雄、許雄、陳志坤、帥念宗\n    、陳國勝、謝黃素娥、林瑞娥、黃美滿、鄭錦繡、薛玉枝、林信宏、蔡慶笑等人\n    於警訊時所陳情節相符，此外，另有被告乙○○所有供犯罪所用之雙面撲克牌十\n    二張、紙質天九牌三十二張、未拆封紙質天九牌十四付、膠質天九牌二付、計算\n    機二台、撲克牌一付、麻將一付、骰子一批、帳冊一本、號碼牌（下注標示用）\n    一包、無線電一台及賭資六千五百元等物可資佐證，本件事證明確，被告犯行堪\n    以認定。\n二、被告乙○○提供其所承租位於高雄縣仁武鄉○○路二二九號後面工廠之房屋聚眾\n    賭博以營利，自屬公眾得出入之場所，核被告三人所為均係犯刑法第二百六十八\n    條之意圖營利供給賭博場所罪及意圖營利聚眾賭博罪，與同法第二百六十六條第\n    一項前段在公眾得出入之場所賭博財物罪。被告乙○○與丙○○、甲○○○就上\n    揭犯行，有犯意之聯絡及行為之分擔，均為共同正犯。核被告所為數行為，時間\n    緊接，所犯罪名相同，顯係出於概括之犯意為之，為連續犯，爰依刑法第五十六\n    條之規定以一罪論，並加重其刑。又被告以一行為同時觸犯上開三罪名，為想像\n    競合犯，應依刑法第五十五條之規定，從情節較重之意圖營利聚眾賭博罪處斷。\n    公訴意旨雖未論及被告三人涉犯之普通賭博罪，惟此部分既與起訴之部分間，有\n    裁判上一罪關係，已如前述，本院自得併予審理。爰審酌被告丙○○、甲○○○\n    前已犯賭博案，此有台灣高等法院被告全國前案紀錄表在卷可稽，此次復犯相同\n    案由之犯行，被告乙○○提供場所及賭具，並主動聚集他人賭博，情節非輕，惟\n    被告三人犯後坦認犯行，尚有悔意等一切情狀，分別量處如主文所示之刑，並均\n    諭知易科罰金之折算標準，以資懲儆。所扣賭資六千五百元，係在賭檯上之財物\n    ，另紙質天九牌三十二張、膠質天九牌二付、骰子一批、號碼牌（下注標示用）\n    一包，為當場賭博之器具，應依刑法第二百六十六條第二項沒收之。另扣案之雙\n    面撲克牌十二張、未拆封紙質天九牌十四付、、計算機二台、撲克牌一付、麻將\n    一付、帳冊一本、一包、無線電一台為被告乙○○所有且為供犯罪或預備供犯罪\n    所用，業據被告乙○○於本院審理時所自承，應依刑法第三十八條第一項第二款\n    之規定宣告沒收。至於警方另查扣計時鐘、橡皮筋、夾子、購物發票、名片等物\n    均非犯罪所用之物或當場賭博之器具，爰不併予宣告沒收，併予敘明。\n據上論斷，應依刑事訴訟法第二百九十九條第一項前段，刑法第二十八條、第五十六\n條、第二百六十八條、第二百六十六條第一項、第四十一條第一項、第二百六十六條\n第二項、第三十八條第一項第二款、第五十五條，罰金罰鍰提高標準條例第一條前段\n、第二條，判決如主文。\n中      華      民      國    九十一    年     十       月     九       日\n                              臺灣高雄地方法院刑事庭\n                                  法  官  廖建瑜\n右正本證明與原本無異。\n如不服本判決，應於判決送達後十日內，向本院提出上訴狀。\n                                  書記官  王翌翔\n中      華      民      國    九十一  年     十       月     九       日\n",
  "structure": {
    "main": "乙○○、丙○○、甲○○○共同連續意圖營利，聚眾賭博，乙○○處有期徒刑肆月，\n丙○○、甲○○○各處有期徒刑參月，如易科罰金均以佰元折算壹日。\n扣案之賭資新台幣陸仟伍百元、雙面撲克牌壹拾貳張、紙質天九牌參拾貳張、未拆封\n紙質天九牌拾肆付、膠質天九牌貳付、計算機貳台、撲克牌壹付、麻將壹付、骰子壹\n批、帳冊壹本、號碼牌（下注標示）壹包、無線電壹台，均沒收之。",
    "fact": "一、丙○○、與甲○○○分別於民國八十七年及七十六年、八十九年曾犯有賭博罪之\n    紀錄，均經法院判處罰金（未構成累犯）。猶不知悔改，自九十年四月十六日起\n    ，與乙○○共同基於意圖營利之概括犯意聯絡及行為分擔，由乙○○向不知情之\n    陳千六承租高雄縣仁武鄉○○路二二九號後面工廠之房屋，在上址公眾得出入之\n    處所聚眾在該處賭博財物，並以每日新台幣（下同）一千元之代價僱請丙○○擔\n    任賭場把風工作，並由甲○○○負責作莊家，由賭客何金成、柯朝雄、許雄、陳\n    志坤、帥念宗、陳國勝、謝黃素娥、林瑞娥、黃美滿、鄭錦繡、薛玉枝、林信宏\n    、蔡慶笑等人持天九牌與莊家比點數大小定輸贏，押注賭資不限，若莊家輸，莊\n    家需依押注金額賠付賭客，乙○○再向賭客贏者抽取一成牟利，並且依莊家贏取\n    賭客金額之一定比例給付予甲○○○作為報酬，嗣於同年四月十七日下午二時三\n    十分許，在上開處所，經警當場查獲，並扣得乙○○所有供犯罪或預備供犯罪所\n    用之雙面撲克牌十二張、紙質天九牌三十二張、未拆封紙質天九牌十四付、膠質\n    天九牌二付、計算機二台、撲克牌一付、麻將一付、骰子一批、帳冊一本、號碼\n    牌（下注標示用）一包、無線電一台及上開賭客所共有之賭資六千五百元。\n二、案經高雄縣警察局林園分局報請臺灣高雄地方法院檢察署檢察官偵查聲請簡易判\n    決處刑。",
    "reason": "一、右揭犯罪事實，業據被告乙○○、丙○○、甲○○○於本院審理時均坦認不諱，\n    核與共同被告所供一致，復參以賭客之何金成、柯朝雄、許雄、陳志坤、帥念宗\n    、陳國勝、謝黃素娥、林瑞娥、黃美滿、鄭錦繡、薛玉枝、林信宏、蔡慶笑等人\n    於警訊時所陳情節相符，此外，另有被告乙○○所有供犯罪所用之雙面撲克牌十\n    二張、紙質天九牌三十二張、未拆封紙質天九牌十四付、膠質天九牌二付、計算\n    機二台、撲克牌一付、麻將一付、骰子一批、帳冊一本、號碼牌（下注標示用）\n    一包、無線電一台及賭資六千五百元等物可資佐證，本件事證明確，被告犯行堪\n    以認定。\n二、被告乙○○提供其所承租位於高雄縣仁武鄉○○路二二九號後面工廠之房屋聚眾\n    賭博以營利，自屬公眾得出入之場所，核被告三人所為均係犯刑法第二百六十八\n    條之意圖營利供給賭博場所罪及意圖營利聚眾賭博罪，與同法第二百六十六條第\n    一項前段在公眾得出入之場所賭博財物罪。被告乙○○與丙○○、甲○○○就上\n    揭犯行，有犯意之聯絡及行為之分擔，均為共同正犯。核被告所為數行為，時間\n    緊接，所犯罪名相同，顯係出於概括之犯意為之，為連續犯，爰依刑法第五十六\n    條之規定以一罪論，並加重其刑。又被告以一行為同時觸犯上開三罪名，為想像\n    競合犯，應依刑法第五十五條之規定，從情節較重之意圖營利聚眾賭博罪處斷。\n    公訴意旨雖未論及被告三人涉犯之普通賭博罪，惟此部分既與起訴之部分間，有\n    裁判上一罪關係，已如前述，本院自得併予審理。爰審酌被告丙○○、甲○○○\n    前已犯賭博案，此有台灣高等法院被告全國前案紀錄表在卷可稽，此次復犯相同\n    案由之犯行，被告乙○○提供場所及賭具，並主動聚集他人賭博，情節非輕，惟\n    被告三人犯後坦認犯行，尚有悔意等一切情狀，分別量處如主文所示之刑，並均\n    諭知易科罰金之折算標準，以資懲儆。所扣賭資六千五百元，係在賭檯上之財物\n    ，另紙質天九牌三十二張、膠質天九牌二付、骰子一批、號碼牌（下注標示用）\n    一包，為當場賭博之器具，應依刑法第二百六十六條第二項沒收之。另扣案之雙\n    面撲克牌十二張、未拆封紙質天九牌十四付、、計算機二台、撲克牌一付、麻將\n    一付、帳冊一本、一包、無線電一台為被告乙○○所有且為供犯罪或預備供犯罪\n    所用，業據被告乙○○於本院審理時所自承，應依刑法第三十八條第一項第二款\n    之規定宣告沒收。至於警方另查扣計時鐘、橡皮筋、夾子、購物發票、名片等物\n    均非犯罪所用之物或當場賭博之器具，爰不併予宣告沒收，併予敘明。\n據上論斷，應依刑事訴訟法第二百九十九條第一項前段，刑法第二十八條、第五十六\n條、第二百六十八條、第二百六十六條第一項、第四十一條第一項、第二百六十六條\n第二項、第三十八條第一項第二款、第五十五條，罰金罰鍰提高標準條例第一條前段\n、第二條，判決如主文。\n中      華      民      國    九十一    年     十       月     九       日\n                              臺灣高雄地方法院刑事庭\n                                  法  官  廖建瑜\n右正本證明與原本無異。\n如不服本判決，應於判決送達後十日內，向本院提出上訴狀。\n                                  書記官  王翌翔"
  },
  "search": "臺灣高雄地方法院刑事判決九十一年度易字第一三一號公訴人臺灣高雄地方法院檢察署檢察官被告乙○○被告丙○○被告甲○○○右列被告因賭博案件，經檢察官聲請簡易判決處刑（九十年度偵字第七五三八號），經本院鳳山簡易庭認為不宜以簡易判決處刑，簽請依通常程序審理，本院判決如左：主文乙○○、丙○○、甲○○○共同連續意圖營利，聚眾賭博，乙○○處有期徒刑肆月，丙○○、甲○○○各處有期徒刑參月，如易科罰金均以佰元折算壹日。扣案之賭資新台幣陸仟伍百元、雙面撲克牌壹拾貳張、紙質天九牌參拾貳張、未拆封紙質天九牌拾肆付、膠質天九牌貳付、計算機貳台、撲克牌壹付、麻將壹付、骰子壹批、帳冊壹本、號碼牌（下注標示）壹包、無線電壹台，均沒收之。事實一、丙○○、與甲○○○分別於民國八十七年及七十六年、八十九年曾犯有賭博罪之紀錄，均經法院判處罰金（未構成累犯）。猶不知悔改，自九十年四月十六日起，與乙○○共同基於意圖營利之概括犯意聯絡及行為分擔，由乙○○向不知情之陳千六承租高雄縣仁武鄉○○路二二九號後面工廠之房屋，在上址公眾得出入之處所聚眾在該處賭博財物，並以每日新台幣（下同）一千元之代價僱請丙○○擔任賭場把風工作，並由甲○○○負責作莊家，由賭客何金成、柯朝雄、許雄、陳志坤、帥念宗、陳國勝、謝黃素娥、林瑞娥、黃美滿、鄭錦繡、薛玉枝、林信宏、蔡慶笑等人持天九牌與莊家比點數大小定輸贏，押注賭資不限，若莊家輸，莊家需依押注金額賠付賭客，乙○○再向賭客贏者抽取一成牟利，並且依莊家贏取賭客金額之一定比例給付予甲○○○作為報酬，嗣於同年四月十七日下午二時三十分許，在上開處所，經警當場查獲，並扣得乙○○所有供犯罪或預備供犯罪所用之雙面撲克牌十二張、紙質天九牌三十二張、未拆封紙質天九牌十四付、膠質天九牌二付、計算機二台、撲克牌一付、麻將一付、骰子一批、帳冊一本、號碼牌（下注標示用）一包、無線電一台及上開賭客所共有之賭資六千五百元。二、案經高雄縣警察局林園分局報請臺灣高雄地方法院檢察署檢察官偵查聲請簡易判決處刑。理由一、右揭犯罪事實，業據被告乙○○、丙○○、甲○○○於本院審理時均坦認不諱，核與共同被告所供一致，復參以賭客之何金成、柯朝雄、許雄、陳志坤、帥念宗、陳國勝、謝黃素娥、林瑞娥、黃美滿、鄭錦繡、薛玉枝、林信宏、蔡慶笑等人於警訊時所陳情節相符，此外，另有被告乙○○所有供犯罪所用之雙面撲克牌十二張、紙質天九牌三十二張、未拆封紙質天九牌十四付、膠質天九牌二付、計算機二台、撲克牌一付、麻將一付、骰子一批、帳冊一本、號碼牌（下注標示用）一包、無線電一台及賭資六千五百元等物可資佐證，本件事證明確，被告犯行堪以認定。二、被告乙○○提供其所承租位於高雄縣仁武鄉○○路二二九號後面工廠之房屋聚眾賭博以營利，自屬公眾得出入之場所，核被告三人所為均係犯刑法第二百六十八條之意圖營利供給賭博場所罪及意圖營利聚眾賭博罪，與同法第二百六十六條第一項前段在公眾得出入之場所賭博財物罪。被告乙○○與丙○○、甲○○○就上揭犯行，有犯意之聯絡及行為之分擔，均為共同正犯。核被告所為數行為，時間緊接，所犯罪名相同，顯係出於概括之犯意為之，為連續犯，爰依刑法第五十六條之規定以一罪論，並加重其刑。又被告以一行為同時觸犯上開三罪名，為想像競合犯，應依刑法第五十五條之規定，從情節較重之意圖營利聚眾賭博罪處斷。公訴意旨雖未論及被告三人涉犯之普通賭博罪，惟此部分既與起訴之部分間，有裁判上一罪關係，已如前述，本院自得併予審理。爰審酌被告丙○○、甲○○○前已犯賭博案，此有台灣高等法院被告全國前案紀錄表在卷可稽，此次復犯相同案由之犯行，被告乙○○提供場所及賭具，並主動聚集他人賭博，情節非輕，惟被告三人犯後坦認犯行，尚有悔意等一切情狀，分別量處如主文所示之刑，並均諭知易科罰金之折算標準，以資懲儆。所扣賭資六千五百元，係在賭檯上之財物，另紙質天九牌三十二張、膠質天九牌二付、骰子一批、號碼牌（下注標示用）一包，為當場賭博之器具，應依刑法第二百六十六條第二項沒收之。另扣案之雙面撲克牌十二張、未拆封紙質天九牌十四付、、計算機二台、撲克牌一付、麻將一付、帳冊一本、一包、無線電一台為被告乙○○所有且為供犯罪或預備供犯罪所用，業據被告乙○○於本院審理時所自承，應依刑法第三十八條第一項第二款之規定宣告沒收。至於警方另查扣計時鐘、橡皮筋、夾子、購物發票、名片等物均非犯罪所用之物或當場賭博之器具，爰不併予宣告沒收，併予敘明。據上論斷，應依刑事訴訟法第二百九十九條第一項前段，刑法第二十八條、第五十六條、第二百六十八條、第二百六十六條第一項、第四十一條第一項、第二百六十六條第二項、第三十八條第一項第二款、第五十五條，罰金罰鍰提高標準條例第一條前段、第二條，判決如主文。中華民國九十一年十月九日臺灣高雄地方法院刑事庭法官廖建瑜右正本證明與原本無異。如不服本判決，應於判決送達後十日內，向本院提出上訴狀。書記官王翌翔中華民國九十一年十月九日",
  "characters": {
    "judges": [
      "廖建瑜"
    ],
    "prosecutors": [

    ],
    "lawyers": [

    ],
    "clerks": [
      "王翌翔"
    ],
    "plaintiffs": [

    ],
    "defendants": [
      "乙○○",
      "甲○○○",
      "右列被告因賭博案件，經檢察官聲請簡易判決處刑（九十年度偵字第七五三八號），",
      "經本院鳳山簡易庭認為不宜以簡易判決處刑，簽請依通常程序審理，本院判決如左："
    ],
    "prosecutor_office": [
      "臺灣高雄地方法院檢察署檢察官"
    ],
    "creditors": [

    ],
    "debtors": [

    ],
    "judicial_associate_officer": [

    ]
  },
  "adjudged_at": "2002-10-09",
  "created_at": "2016-02-05 18:21:20",
  "updated_at": "2016-02-05 18:21:20"
}