{
  "identify": "KSD-90-易-4598-20020109-1",
  "court": {
    "name": "臺灣高雄地方法院",
    "code": "KSD"
  },
  "division": {
    "name": "刑事",
    "code": "M"
  },
  "year": 90,
  "word": "易",
  "number": "4598",
  "jcheck": "1",
  "reason": "傷害等",
  "content": "臺灣高雄地方法院刑事判決                          九十年度易字第四五九八號\n    公  訴  人  臺灣高雄地方法院檢察署檢察官\n    被      告  甲○○\n右列被告因傷害等案件，經檢察官聲請簡易判決處刑（九十年度偵字第一六八○○號\n），經本院高雄簡易庭認不宜依簡易判決處刑，簽准改依通常程序審判，本院判決如\n左：\n    主  文\n甲○○以加害生命、身體之事，恐嚇他人，致生危害於安全，處拘役參拾日，如易科\n罰金，以參佰元折算壹日；又因過失傷害人，處拘役貳拾日，如易科罰金，以參佰元\n折算壹日；應執行拘役肆拾日，如易科罰金，以參佰元折算壹日。\n    事  實\n一、甲○○與乙○○及丙○○○分別係叔姪及叔嫂關係，具有家庭暴力防治法第三條\n    第四款所定之家庭成員關係。於民國九十年八月十三日下午二時三十分許，在高\n    雄市小港區○○○路三十六號住處，甲○○酒後因向乙○○詢問其母親電話未果\n    ，因而心生不滿，即憤而將上址住處內電風扇踢倒在地，並基於恐嚇危害安全之\n    犯意，至廚房內取出水果刀乙支，作勢欲砍乙○○，致乙○○見狀而心生畏怖，\n    並拿起椅子欲抵擋，後乙○○見甲○○不注意之際，趨前欲奪取該水果刀，兩人\n    因而發生拉扯，適丙○○○聽見吵鬧聲音而進入屋內，見狀亦欲向前搶下甲○○\n    手中之水果刀，甲○○應注意水果刀係屬利鋒，易造成人受有傷害，於拉扯間應\n    避免傷害人，依當時情況又非不能注意，竟不注意，因而劃傷前來勸阻之丙○○\n    ○，造成丙○○○受有「右手大拇指割裂傷」之傷害，並接續上開恐嚇危害安全\n    之犯意，向乙○○及丙○○○恐嚇稱：「不能讓你們吃太好，要殺給你們死（台\n    語）」等語，致使乙○○及丙○○○聞言而心生畏懼。\n二、案經乙○○及丙○○○訴請高雄市政府警察局小港分局移送台灣高雄地方法院檢\n    察署檢察官偵查起訴。\n    理  由\n一、訊據被告甲○○固坦認確與被害人乙○○及丙○○○分別係叔姪及叔嫂關係，於\n    右揭時、地酒後與被害人乙○○發生爭執，並因而造成被害人丙○○○受有上開\n    傷害之事實不諱，惟矢口否認有何上揭犯行，辯稱：當時伊雖與乙○○發生爭執\n    ，但伊並無摔電風扇，而伊到廚房內拿水果刀，係欲持之切水果用，當時乙○○\n    確有拿起椅子，又丙○○○是在拉扯時自己不小心劃傷的，並非伊所為云云。右\n    揭事實，業據證人即告訴人乙○○及丙○○○於警訊及偵、審時證述甚詳，證人\n    即告訴人乙○○證稱：於九十年八月十三日下午二時三十分許，在伊上址住處內\n    ，伊叔叔即被告甲○○酒後問伊母親電話，伊回答不知道，被告即踢倒電風扇，\n    並至廚房內取出水果刀乙支，作勢欲砍伊，伊見此情形很害怕，即拿起椅子欲抵\n    擋，後伊見被告不注意時，放下椅子向前欲搶水果刀，在拉扯時，伊嬸嬸楊劉燕\n    進來，見狀即過來欲幫伊搶水果刀，而遭被告劃傷，當時被告並稱：「不能讓你\n    們吃太好，要殺給你們死（台語）」等語，伊聽了當然會害怕，後水果刀為伊等\n    搶過來等語，證人即被害人丙○○○證陳：伊因聽見屋內吵鬧聲，即進入查看，\n    見被告手持水果刀與乙○○間發生拉扯，伊向前欲奪下被告之水果刀時，被告即\n    持水果刀由上往下劃下來，而割傷伊右手大拇指，並稱：「不能讓你們吃太好，\n    要殺給你們死（台語）」等語，伊當時聞言很害怕等語。復被告於警訊時辯稱：\n    當時伊與乙○○發生口角爭執，伊非常生氣即至廚房拿一支水果刀，並作勢欲砍\n    乙○○，乙○○拿椅子欲抵擋，後丙○○○跑過來要搶水果刀，不小心被伊割傷\n    ，伊並無故意要傷害丙○○○，又伊並無出言恐嚇他們，僅係拿水果刀要嚇乙○\n    ○，後伊即將水果刀放下云云，並於偵查時辯稱：伊確與他們發生爭執拉扯，丙\n    ○○○見伊與乙○○拉扯即過來，被刀揮到等語。又參以告訴人等係為被告之姪\n    子及兄嫂，苟無此事，告訴人等應無故意誣陷被告之理。此外，復有驗傷診斷書\n    乙紙附卷可稽，及水果刀乙支扣案可證。綜據上述事證以觀，被告於上開時、地\n    ，酒後因向告訴人乙○○詢問電話未果，心生不滿，即憤而將上址住處內電風扇\n    踢倒在地，旋至廚房內取出水果刀乙支，作勢欲砍告訴人乙○○，致告訴人乙○\n    ○見狀而心生畏怖，並拿起椅子欲抵擋，後告訴人乙○○見被告不注意之際，趨\n    前欲奪取該水果刀，兩人因而發生拉扯，適告訴人丙○○○聽見吵鬧聲音而進入\n    屋內，見狀亦欲向前搶下甲○○手中之水果刀，而遭於拉扯間之被告持該水果刀\n    不小心劃傷，造成告訴人丙○○○受有上開傷害，被告並基於恐嚇危害安全之犯\n    意，向乙○○及丙○○○恐嚇稱：「不能讓你們吃太好，要殺給你們死（台語）\n    」等語，致使乙○○及丙○○○聞言均心生畏懼等事實，堪予認定。是被告事後\n    翻異前詞，辯稱上情，要屬事後卸責之詞，不足採信。從而，本件事證明確，被\n    告上開犯行，實堪認定。\n二、核被告甲○○所為，係屬家庭暴力罪，惟因家庭暴力防治法並無特別刑罰之規定\n    ，仍論以刑法第二百八十四條第一項前段之普通過失傷害罪及第三百零五條之恐\n    嚇危害安全罪。被告先後二次恐嚇告訴人乙○○犯行，係於緊接之時間內接續為\n    之，依一般社會健全觀念，在時間差距上各行為之獨立性極為薄弱，難以強行分\n    開，在刑法評價上屬單一犯意內之數個接續行為，而為包括之一罪。又被告以一\n    行為恐嚇乙○○及丙○○○，觸犯構成要件相同之罪名，為想像競合犯，應從重\n    依一恐嚇罪處斷。公訴人認被告上開傷害告訴人丙○○○之行為，係犯刑法第二\n    百七十七條第一項之普通傷害罪，然查被告與丙○○○間並無爭執衝突，被告實\n    無傷害丙○○○之動機，且依當時拉扯間混亂情事研判，被告應係疏未注意而劃\n    傷丙○○○，應係屬過失傷害行為，公訴意旨此部分容有未洽，惟傷害之社會基\n    本事實相同，起訴法條應予變更。而被告所犯過失傷害及恐嚇危害安全二罪間，\n    犯意各別，行為互異，應予分論併罰，公訴人認係方法目的之牽連犯關係，亦有\n    誤會。爰審酌被告之品行，僅因詢問告訴人乙○○電話未果，而為本件犯行，影\n    響個人之安全，犯罪之手段、目的、造成傷害之程度，及犯後態度等一切情狀，\n    分別量處如主文所示之刑，並定其應執行之刑，且均諭知如易科罰金之折算標準\n    ，以資懲儆。至扣案之水果刀乙把，雖係被告供本件犯行所用之物，惟係屬被告\n    與被害人等家中使用之物，並非被告所有之物，又非違禁物，爰不另為沒收之諭\n    知，併此敘明。\n據上論斷，應依刑事訴訟法第二百九十九條第一項前段、第三百條，刑法第二百八十\n四條第一項前段、第三百零五條、第五十一條第六款、第五十五條，罰金罰鍰提高標\n準條例第一條前段、第二條，判決如主文。\n本案經檢察官劉河山到庭執行職務。\n中      華      民      國        九十一    年      一    月      九    日\n                                臺灣高雄地方法院刑事第六庭\n                                    法  官   洪榮家\n右正本證明與原本無異。\n如不服本判決，應於判決送達後十日內，向本院提出上訴狀。\n                                    書記官   陳寰瑛\n中      華      民      國        九十一    年      一    月      九    日\n附錄本案論罪科刑法條全文：\n刑法第二百八十四條第一項：\n  因過失傷害人者，處六月以下有期徒刑、拘役或五百元以下罰金。致重傷者，處一\n  年以下有期徒刑、拘役或五百元以下罰金。\n刑法第三百零五條：\n  以加害生命、身體、自由、名譽、財產之事，恐嚇他人致生危害於安全者，處二年\n  以下有期徒刑、拘役或三百元以下罰金。\n",
  "structure": {
    "main": "甲○○以加害生命、身體之事，恐嚇他人，致生危害於安全，處拘役參拾日，如易科\n罰金，以參佰元折算壹日；又因過失傷害人，處拘役貳拾日，如易科罰金，以參佰元\n折算壹日；應執行拘役肆拾日，如易科罰金，以參佰元折算壹日。",
    "fact": "一、甲○○與乙○○及丙○○○分別係叔姪及叔嫂關係，具有家庭暴力防治法第三條\n    第四款所定之家庭成員關係。於民國九十年八月十三日下午二時三十分許，在高\n    雄市小港區○○○路三十六號住處，甲○○酒後因向乙○○詢問其母親電話未果\n    ，因而心生不滿，即憤而將上址住處內電風扇踢倒在地，並基於恐嚇危害安全之\n    犯意，至廚房內取出水果刀乙支，作勢欲砍乙○○，致乙○○見狀而心生畏怖，\n    並拿起椅子欲抵擋，後乙○○見甲○○不注意之際，趨前欲奪取該水果刀，兩人\n    因而發生拉扯，適丙○○○聽見吵鬧聲音而進入屋內，見狀亦欲向前搶下甲○○\n    手中之水果刀，甲○○應注意水果刀係屬利鋒，易造成人受有傷害，於拉扯間應\n    避免傷害人，依當時情況又非不能注意，竟不注意，因而劃傷前來勸阻之丙○○\n    ○，造成丙○○○受有「右手大拇指割裂傷」之傷害，並接續上開恐嚇危害安全\n    之犯意，向乙○○及丙○○○恐嚇稱：「不能讓你們吃太好，要殺給你們死（台\n    語）」等語，致使乙○○及丙○○○聞言而心生畏懼。\n二、案經乙○○及丙○○○訴請高雄市政府警察局小港分局移送台灣高雄地方法院檢\n    察署檢察官偵查起訴。",
    "reason": "一、訊據被告甲○○固坦認確與被害人乙○○及丙○○○分別係叔姪及叔嫂關係，於\n    右揭時、地酒後與被害人乙○○發生爭執，並因而造成被害人丙○○○受有上開\n    傷害之事實不諱，惟矢口否認有何上揭犯行，辯稱：當時伊雖與乙○○發生爭執\n    ，但伊並無摔電風扇，而伊到廚房內拿水果刀，係欲持之切水果用，當時乙○○\n    確有拿起椅子，又丙○○○是在拉扯時自己不小心劃傷的，並非伊所為云云。右\n    揭事實，業據證人即告訴人乙○○及丙○○○於警訊及偵、審時證述甚詳，證人\n    即告訴人乙○○證稱：於九十年八月十三日下午二時三十分許，在伊上址住處內\n    ，伊叔叔即被告甲○○酒後問伊母親電話，伊回答不知道，被告即踢倒電風扇，\n    並至廚房內取出水果刀乙支，作勢欲砍伊，伊見此情形很害怕，即拿起椅子欲抵\n    擋，後伊見被告不注意時，放下椅子向前欲搶水果刀，在拉扯時，伊嬸嬸楊劉燕\n    進來，見狀即過來欲幫伊搶水果刀，而遭被告劃傷，當時被告並稱：「不能讓你\n    們吃太好，要殺給你們死（台語）」等語，伊聽了當然會害怕，後水果刀為伊等\n    搶過來等語，證人即被害人丙○○○證陳：伊因聽見屋內吵鬧聲，即進入查看，\n    見被告手持水果刀與乙○○間發生拉扯，伊向前欲奪下被告之水果刀時，被告即\n    持水果刀由上往下劃下來，而割傷伊右手大拇指，並稱：「不能讓你們吃太好，\n    要殺給你們死（台語）」等語，伊當時聞言很害怕等語。復被告於警訊時辯稱：\n    當時伊與乙○○發生口角爭執，伊非常生氣即至廚房拿一支水果刀，並作勢欲砍\n    乙○○，乙○○拿椅子欲抵擋，後丙○○○跑過來要搶水果刀，不小心被伊割傷\n    ，伊並無故意要傷害丙○○○，又伊並無出言恐嚇他們，僅係拿水果刀要嚇乙○\n    ○，後伊即將水果刀放下云云，並於偵查時辯稱：伊確與他們發生爭執拉扯，丙\n    ○○○見伊與乙○○拉扯即過來，被刀揮到等語。又參以告訴人等係為被告之姪\n    子及兄嫂，苟無此事，告訴人等應無故意誣陷被告之理。此外，復有驗傷診斷書\n    乙紙附卷可稽，及水果刀乙支扣案可證。綜據上述事證以觀，被告於上開時、地\n    ，酒後因向告訴人乙○○詢問電話未果，心生不滿，即憤而將上址住處內電風扇\n    踢倒在地，旋至廚房內取出水果刀乙支，作勢欲砍告訴人乙○○，致告訴人乙○\n    ○見狀而心生畏怖，並拿起椅子欲抵擋，後告訴人乙○○見被告不注意之際，趨\n    前欲奪取該水果刀，兩人因而發生拉扯，適告訴人丙○○○聽見吵鬧聲音而進入\n    屋內，見狀亦欲向前搶下甲○○手中之水果刀，而遭於拉扯間之被告持該水果刀\n    不小心劃傷，造成告訴人丙○○○受有上開傷害，被告並基於恐嚇危害安全之犯\n    意，向乙○○及丙○○○恐嚇稱：「不能讓你們吃太好，要殺給你們死（台語）\n    」等語，致使乙○○及丙○○○聞言均心生畏懼等事實，堪予認定。是被告事後\n    翻異前詞，辯稱上情，要屬事後卸責之詞，不足採信。從而，本件事證明確，被\n    告上開犯行，實堪認定。\n二、核被告甲○○所為，係屬家庭暴力罪，惟因家庭暴力防治法並無特別刑罰之規定\n    ，仍論以刑法第二百八十四條第一項前段之普通過失傷害罪及第三百零五條之恐\n    嚇危害安全罪。被告先後二次恐嚇告訴人乙○○犯行，係於緊接之時間內接續為\n    之，依一般社會健全觀念，在時間差距上各行為之獨立性極為薄弱，難以強行分\n    開，在刑法評價上屬單一犯意內之數個接續行為，而為包括之一罪。又被告以一\n    行為恐嚇乙○○及丙○○○，觸犯構成要件相同之罪名，為想像競合犯，應從重\n    依一恐嚇罪處斷。公訴人認被告上開傷害告訴人丙○○○之行為，係犯刑法第二\n    百七十七條第一項之普通傷害罪，然查被告與丙○○○間並無爭執衝突，被告實\n    無傷害丙○○○之動機，且依當時拉扯間混亂情事研判，被告應係疏未注意而劃\n    傷丙○○○，應係屬過失傷害行為，公訴意旨此部分容有未洽，惟傷害之社會基\n    本事實相同，起訴法條應予變更。而被告所犯過失傷害及恐嚇危害安全二罪間，\n    犯意各別，行為互異，應予分論併罰，公訴人認係方法目的之牽連犯關係，亦有\n    誤會。爰審酌被告之品行，僅因詢問告訴人乙○○電話未果，而為本件犯行，影\n    響個人之安全，犯罪之手段、目的、造成傷害之程度，及犯後態度等一切情狀，\n    分別量處如主文所示之刑，並定其應執行之刑，且均諭知如易科罰金之折算標準\n    ，以資懲儆。至扣案之水果刀乙把，雖係被告供本件犯行所用之物，惟係屬被告\n    與被害人等家中使用之物，並非被告所有之物，又非違禁物，爰不另為沒收之諭\n    知，併此敘明。\n據上論斷，應依刑事訴訟法第二百九十九條第一項前段、第三百條，刑法第二百八十\n四條第一項前段、第三百零五條、第五十一條第六款、第五十五條，罰金罰鍰提高標\n準條例第一條前段、第二條，判決如主文。\n本案經檢察官劉河山到庭執行職務。\n中      華      民      國        九十一    年      一    月      九    日\n                                臺灣高雄地方法院刑事第六庭\n                                    法  官   洪榮家\n右正本證明與原本無異。\n如不服本判決，應於判決送達後十日內，向本院提出上訴狀。\n                                    書記官   陳寰瑛"
  },
  "search": "臺灣高雄地方法院刑事判決九十年度易字第四五九八號公訴人臺灣高雄地方法院檢察署檢察官被告甲○○右列被告因傷害等案件，經檢察官聲請簡易判決處刑（九十年度偵字第一六八○○號），經本院高雄簡易庭認不宜依簡易判決處刑，簽准改依通常程序審判，本院判決如左：主文甲○○以加害生命、身體之事，恐嚇他人，致生危害於安全，處拘役參拾日，如易科罰金，以參佰元折算壹日；又因過失傷害人，處拘役貳拾日，如易科罰金，以參佰元折算壹日；應執行拘役肆拾日，如易科罰金，以參佰元折算壹日。事實一、甲○○與乙○○及丙○○○分別係叔姪及叔嫂關係，具有家庭暴力防治法第三條第四款所定之家庭成員關係。於民國九十年八月十三日下午二時三十分許，在高雄市小港區○○○路三十六號住處，甲○○酒後因向乙○○詢問其母親電話未果，因而心生不滿，即憤而將上址住處內電風扇踢倒在地，並基於恐嚇危害安全之犯意，至廚房內取出水果刀乙支，作勢欲砍乙○○，致乙○○見狀而心生畏怖，並拿起椅子欲抵擋，後乙○○見甲○○不注意之際，趨前欲奪取該水果刀，兩人因而發生拉扯，適丙○○○聽見吵鬧聲音而進入屋內，見狀亦欲向前搶下甲○○手中之水果刀，甲○○應注意水果刀係屬利鋒，易造成人受有傷害，於拉扯間應避免傷害人，依當時情況又非不能注意，竟不注意，因而劃傷前來勸阻之丙○○○，造成丙○○○受有「右手大拇指割裂傷」之傷害，並接續上開恐嚇危害安全之犯意，向乙○○及丙○○○恐嚇稱：「不能讓你們吃太好，要殺給你們死（台語）」等語，致使乙○○及丙○○○聞言而心生畏懼。二、案經乙○○及丙○○○訴請高雄市政府警察局小港分局移送台灣高雄地方法院檢察署檢察官偵查起訴。理由一、訊據被告甲○○固坦認確與被害人乙○○及丙○○○分別係叔姪及叔嫂關係，於右揭時、地酒後與被害人乙○○發生爭執，並因而造成被害人丙○○○受有上開傷害之事實不諱，惟矢口否認有何上揭犯行，辯稱：當時伊雖與乙○○發生爭執，但伊並無摔電風扇，而伊到廚房內拿水果刀，係欲持之切水果用，當時乙○○確有拿起椅子，又丙○○○是在拉扯時自己不小心劃傷的，並非伊所為云云。右揭事實，業據證人即告訴人乙○○及丙○○○於警訊及偵、審時證述甚詳，證人即告訴人乙○○證稱：於九十年八月十三日下午二時三十分許，在伊上址住處內，伊叔叔即被告甲○○酒後問伊母親電話，伊回答不知道，被告即踢倒電風扇，並至廚房內取出水果刀乙支，作勢欲砍伊，伊見此情形很害怕，即拿起椅子欲抵擋，後伊見被告不注意時，放下椅子向前欲搶水果刀，在拉扯時，伊嬸嬸楊劉燕進來，見狀即過來欲幫伊搶水果刀，而遭被告劃傷，當時被告並稱：「不能讓你們吃太好，要殺給你們死（台語）」等語，伊聽了當然會害怕，後水果刀為伊等搶過來等語，證人即被害人丙○○○證陳：伊因聽見屋內吵鬧聲，即進入查看，見被告手持水果刀與乙○○間發生拉扯，伊向前欲奪下被告之水果刀時，被告即持水果刀由上往下劃下來，而割傷伊右手大拇指，並稱：「不能讓你們吃太好，要殺給你們死（台語）」等語，伊當時聞言很害怕等語。復被告於警訊時辯稱：當時伊與乙○○發生口角爭執，伊非常生氣即至廚房拿一支水果刀，並作勢欲砍乙○○，乙○○拿椅子欲抵擋，後丙○○○跑過來要搶水果刀，不小心被伊割傷，伊並無故意要傷害丙○○○，又伊並無出言恐嚇他們，僅係拿水果刀要嚇乙○○，後伊即將水果刀放下云云，並於偵查時辯稱：伊確與他們發生爭執拉扯，丙○○○見伊與乙○○拉扯即過來，被刀揮到等語。又參以告訴人等係為被告之姪子及兄嫂，苟無此事，告訴人等應無故意誣陷被告之理。此外，復有驗傷診斷書乙紙附卷可稽，及水果刀乙支扣案可證。綜據上述事證以觀，被告於上開時、地，酒後因向告訴人乙○○詢問電話未果，心生不滿，即憤而將上址住處內電風扇踢倒在地，旋至廚房內取出水果刀乙支，作勢欲砍告訴人乙○○，致告訴人乙○○見狀而心生畏怖，並拿起椅子欲抵擋，後告訴人乙○○見被告不注意之際，趨前欲奪取該水果刀，兩人因而發生拉扯，適告訴人丙○○○聽見吵鬧聲音而進入屋內，見狀亦欲向前搶下甲○○手中之水果刀，而遭於拉扯間之被告持該水果刀不小心劃傷，造成告訴人丙○○○受有上開傷害，被告並基於恐嚇危害安全之犯意，向乙○○及丙○○○恐嚇稱：「不能讓你們吃太好，要殺給你們死（台語）」等語，致使乙○○及丙○○○聞言均心生畏懼等事實，堪予認定。是被告事後翻異前詞，辯稱上情，要屬事後卸責之詞，不足採信。從而，本件事證明確，被告上開犯行，實堪認定。二、核被告甲○○所為，係屬家庭暴力罪，惟因家庭暴力防治法並無特別刑罰之規定，仍論以刑法第二百八十四條第一項前段之普通過失傷害罪及第三百零五條之恐嚇危害安全罪。被告先後二次恐嚇告訴人乙○○犯行，係於緊接之時間內接續為之，依一般社會健全觀念，在時間差距上各行為之獨立性極為薄弱，難以強行分開，在刑法評價上屬單一犯意內之數個接續行為，而為包括之一罪。又被告以一行為恐嚇乙○○及丙○○○，觸犯構成要件相同之罪名，為想像競合犯，應從重依一恐嚇罪處斷。公訴人認被告上開傷害告訴人丙○○○之行為，係犯刑法第二百七十七條第一項之普通傷害罪，然查被告與丙○○○間並無爭執衝突，被告實無傷害丙○○○之動機，且依當時拉扯間混亂情事研判，被告應係疏未注意而劃傷丙○○○，應係屬過失傷害行為，公訴意旨此部分容有未洽，惟傷害之社會基本事實相同，起訴法條應予變更。而被告所犯過失傷害及恐嚇危害安全二罪間，犯意各別，行為互異，應予分論併罰，公訴人認係方法目的之牽連犯關係，亦有誤會。爰審酌被告之品行，僅因詢問告訴人乙○○電話未果，而為本件犯行，影響個人之安全，犯罪之手段、目的、造成傷害之程度，及犯後態度等一切情狀，分別量處如主文所示之刑，並定其應執行之刑，且均諭知如易科罰金之折算標準，以資懲儆。至扣案之水果刀乙把，雖係被告供本件犯行所用之物，惟係屬被告與被害人等家中使用之物，並非被告所有之物，又非違禁物，爰不另為沒收之諭知，併此敘明。據上論斷，應依刑事訴訟法第二百九十九條第一項前段、第三百條，刑法第二百八十四條第一項前段、第三百零五條、第五十一條第六款、第五十五條，罰金罰鍰提高標準條例第一條前段、第二條，判決如主文。本案經檢察官劉河山到庭執行職務。中華民國九十一年一月九日臺灣高雄地方法院刑事第六庭法官洪榮家右正本證明與原本無異。如不服本判決，應於判決送達後十日內，向本院提出上訴狀。書記官陳寰瑛中華民國九十一年一月九日附錄本案論罪科刑法條全文：刑法第二百八十四條第一項：因過失傷害人者，處六月以下有期徒刑、拘役或五百元以下罰金。致重傷者，處一年以下有期徒刑、拘役或五百元以下罰金。刑法第三百零五條：以加害生命、身體、自由、名譽、財產之事，恐嚇他人致生危害於安全者，處二年以下有期徒刑、拘役或三百元以下罰金。",
  "characters": {
    "judges": [
      "洪榮家"
    ],
    "prosecutors": [
      "劉河山"
    ],
    "lawyers": [

    ],
    "clerks": [
      "陳寰瑛"
    ],
    "plaintiffs": [

    ],
    "defendants": [
      "甲○○",
      "右列被告因傷害等案件，經檢察官聲請簡易判決處刑（九十年度偵字第一六八○○號",
      "），經本院高雄簡易庭認不宜依簡易判決處刑，簽准改依通常程序審判，本院判決如",
      "左："
    ],
    "prosecutor_office": [
      "臺灣高雄地方法院檢察署檢察官"
    ],
    "creditors": [

    ],
    "debtors": [

    ],
    "judicial_associate_officer": [

    ]
  },
  "adjudged_at": "2002-01-09",
  "created_at": "2016-02-05 03:40:27",
  "updated_at": "2016-02-05 03:40:27"
}