{
  "identify": "KSH-94-聲-324-20051012-1",
  "court": {
    "name": "臺灣高等法院",
    "code": "KSH"
  },
  "division": {
    "name": "刑事",
    "code": "M"
  },
  "year": 94,
  "word": "聲",
  "number": "324",
  "jcheck": "1",
  "reason": "聲請定其應執行刑",
  "content": "臺灣高等法院高雄分院刑事裁定           94年度聲字第324號\n聲  請  人  臺灣高等法院高雄分院檢察署檢察官\n受  刑  人  甲○○\n上列聲請人因受刑人數罪併罰有二裁判以上，聲請定其應執行之\n刑，本院裁定如下：\n    主  文\n甲○○因偽造有價證券等貳罪，分別處如附表所示之刑，應執行\n有期徒刑捌年肆月。\n    理  由\n受刑人甲○○因偽造有價證券等2 罪，經臺灣高等法院台中分院\n及本院先後判處如附表所示之刑，均經分別確定在案。茲檢察官\n聲請定其應執行之刑，本院審核認聲請為正當，應定其應執行之\n刑。爰依刑事訴訟法第477 條第1 項、刑法第53條、第51條第5\n款，裁定如主文。\n中    華    民    國    94    年    10    月    12    日\n                  刑事第一庭    審判長法  官  王光照\n                                      法  官  任森銓\n                                      法  官  黃仁松\n以上正本證明與原本無異。\n如不服本裁定應於送達後5 日內向本院提出抗告狀。\n中    華    民    國    94    年    10    月    12    日\n                                      書記官  黃麗蓉\n",
  "structure": {
    "main": "甲○○因偽造有價證券等貳罪，分別處如附表所示之刑，應執行\n有期徒刑捌年肆月。",
    "reason": "受刑人甲○○因偽造有價證券等2 罪，經臺灣高等法院台中分院\n及本院先後判處如附表所示之刑，均經分別確定在案。茲檢察官\n聲請定其應執行之刑，本院審核認聲請為正當，應定其應執行之\n刑。爰依刑事訴訟法第477 條第1 項、刑法第53條、第51條第5\n款，裁定如主文。"
  },
  "search": "臺灣高等法院高雄分院刑事裁定94年度聲字第324號聲請人臺灣高等法院高雄分院檢察署檢察官受刑人甲○○上列聲請人因受刑人數罪併罰有二裁判以上，聲請定其應執行之刑，本院裁定如下：主文甲○○因偽造有價證券等貳罪，分別處如附表所示之刑，應執行有期徒刑捌年肆月。理由受刑人甲○○因偽造有價證券等2罪，經臺灣高等法院台中分院及本院先後判處如附表所示之刑，均經分別確定在案。茲檢察官聲請定其應執行之刑，本院審核認聲請為正當，應定其應執行之刑。爰依刑事訴訟法第477條第1項、刑法第53條、第51條第5款，裁定如主文。中華民國94年10月12日刑事第一庭審判長法官王光照法官任森銓法官黃仁松以上正本證明與原本無異。如不服本裁定應於送達後5日內向本院提出抗告狀。中華民國94年10月12日書記官黃麗蓉",
  "characters": {
    "judges": [
      "王光照",
      "任森銓",
      "黃仁松"
    ],
    "prosecutors": [

    ],
    "lawyers": [

    ],
    "clerks": [
      "黃麗蓉"
    ],
    "plaintiffs": [

    ],
    "defendants": [

    ],
    "prosecutor_office": [
      "臺灣高等法院高雄分院檢察署檢察官"
    ],
    "creditors": [

    ],
    "debtors": [

    ],
    "judicial_associate_officer": [

    ]
  },
  "adjudged_at": "2005-10-12",
  "created_at": "2016-02-07 10:50:32",
  "updated_at": "2016-02-07 10:50:32"
}