{
  "identify": "SCD-94-重訴-146-20051012-1",
  "court": {
    "name": "臺灣新竹地方法院",
    "code": "SCD"
  },
  "division": {
    "name": "民事",
    "code": "V"
  },
  "year": 94,
  "word": "重訴",
  "number": "146",
  "jcheck": "1",
  "reason": "返還消費借貸款",
  "content": "臺灣新竹地方法院民事裁定             94年度重訴字第146號\n原      告  中國農民銀行股份有限公司\n法定代理人  甲○○\n訴訟代理人  丙○○\n被      告  乙○○\n上列當事人間請求返還消費借貸款事件，本院裁定如下：\n    主  文\n原告之訴駁回。\n訴訟費用由原告負擔。\n    理  由\n一、按提起民事訴訟應依民事訴訟法第77條之13規定繳納裁判費\n    ，此為必須具備之程式。\n二、本件原告聲請對被告乙○○以及訴外人固緯股份有限公司、\n    黃宏宗、李秋梨發支付命令，惟被告乙○○已於法定期間內\n    對支付命令提出異議，應以支付命令之聲請視為起訴，本件\n    訴訟標的金額核定為新台幣（下同）19,000,000元，應繳納\n    裁判費179,200元，而原告僅繳納1,000元，尚應補繳178,20\n    0元，經本院於民國94年9月8日裁定命原告於5日內補正。該\n    項裁定已於94年9月13日送達原告，有送達證書附卷可憑。\n三、原告逾期迄未補正，其訴顯難認為合法，應予駁回本件訴訟\n    。\n四、依民事訴訟法第249條第1項第6款、第95條、第78條，裁定\n    如主文。\n中    華    民    國    94    年    10    月    12    日\n                  民事第一庭    法  官  李珮瑜\n以上正本證明與原本無異。\n如不服本裁定應於送達後10日內向本院提出抗告狀。\n中    華    民    國    94    年    10    月    12    日\n                                書記官  廖佳玲\n",
  "structure": {
    "main": "原告之訴駁回。\n訴訟費用由原告負擔。",
    "reason": "一、按提起民事訴訟應依民事訴訟法第77條之13規定繳納裁判費\n    ，此為必須具備之程式。\n二、本件原告聲請對被告乙○○以及訴外人固緯股份有限公司、\n    黃宏宗、李秋梨發支付命令，惟被告乙○○已於法定期間內\n    對支付命令提出異議，應以支付命令之聲請視為起訴，本件\n    訴訟標的金額核定為新台幣（下同）19,000,000元，應繳納\n    裁判費179,200元，而原告僅繳納1,000元，尚應補繳178,20\n    0元，經本院於民國94年9月8日裁定命原告於5日內補正。該\n    項裁定已於94年9月13日送達原告，有送達證書附卷可憑。\n三、原告逾期迄未補正，其訴顯難認為合法，應予駁回本件訴訟\n    。\n四、依民事訴訟法第249條第1項第6款、第95條、第78條，裁定\n    如主文。"
  },
  "search": "臺灣新竹地方法院民事裁定94年度重訴字第146號原告中國農民銀行股份有限公司法定代理人甲○○訴訟代理人丙○○被告乙○○上列當事人間請求返還消費借貸款事件，本院裁定如下：主文原告之訴駁回。訴訟費用由原告負擔。理由一、按提起民事訴訟應依民事訴訟法第77條之13規定繳納裁判費，此為必須具備之程式。二、本件原告聲請對被告乙○○以及訴外人固緯股份有限公司、黃宏宗、李秋梨發支付命令，惟被告乙○○已於法定期間內對支付命令提出異議，應以支付命令之聲請視為起訴，本件訴訟標的金額核定為新台幣（下同）19,000,000元，應繳納裁判費179,200元，而原告僅繳納1,000元，尚應補繳178,200元，經本院於民國94年9月8日裁定命原告於5日內補正。該項裁定已於94年9月13日送達原告，有送達證書附卷可憑。三、原告逾期迄未補正，其訴顯難認為合法，應予駁回本件訴訟。四、依民事訴訟法第249條第1項第6款、第95條、第78條，裁定如主文。中華民國94年10月12日民事第一庭法官李珮瑜以上正本證明與原本無異。如不服本裁定應於送達後10日內向本院提出抗告狀。中華民國94年10月12日書記官廖佳玲",
  "characters": {
    "judges": [
      "李珮瑜"
    ],
    "prosecutors": [

    ],
    "lawyers": [

    ],
    "clerks": [
      "廖佳玲"
    ],
    "plaintiffs": [
      "中國農民銀行股份有限公司"
    ],
    "defendants": [
      "乙○○"
    ],
    "prosecutor_office": [

    ],
    "creditors": [

    ],
    "debtors": [

    ],
    "judicial_associate_officer": [

    ]
  },
  "adjudged_at": "2005-10-12",
  "created_at": "2016-02-07 10:55:04",
  "updated_at": "2016-02-07 10:55:04"
}