{
  "identify": "TPD-94-除-2650-20051012-1",
  "court": {
    "name": "臺灣臺北地方法院",
    "code": "TPD"
  },
  "division": {
    "name": "民事",
    "code": "V"
  },
  "year": 94,
  "word": "除",
  "number": "2650",
  "jcheck": "1",
  "reason": "除權判決",
  "content": "臺灣臺北地方法院民事判決              94年度除字第2650號\n    聲  請  人  臺北市文山區辛亥國民小學\n    法定代理人  乙○○\n    訴訟代理人  甲○○\n上列聲請人聲請除權判決事件，本院判決如下：\n    主  文\n如附表所示之證券無效。\n訴訟費用由聲請人負擔。\n    理  由\n一、上開證券，經本院以九十四年度催字第二九０號公示催告。\n二、所定申報權利期間，已於民國九十四年八月十六日屆滿，迄\n    今無人申報權利。\n三、依民事訴訟法第五百六十四條第一項，判決如主文。\n中    華    民    國   九十四   年   十   月   十二   日\n                  民事第五庭    法  官  蔡世祺\n以上正本係照原本作成。\n本判決不得上訴。\n中    華    民    國   九十四   年   十   月   十二   日\n                                書記官  黃媚鵑\n┌────────────────────────────────────────────────────────┐\n│附表：                                                                                        94年度除字第2650號│\n├──┬─────────┬─────────┬───────────┬─────────┬────────┬──┤\n│編號│ 發    票    人   │  付    款    人  │發        票        日│票面金額（新台幣）│ 支  票  號  碼 │備考│\n├──┼─────────┼─────────┼───────────┼─────────┼────────┼──┤\n│001 │台北市文山區辛亥國│富邦銀行和平分行  │93年11月26日          │100,612元         │HP0000000       │    │\n│    │民小學乙○○      │                  │                      │                  │                │    │\n└──┴─────────┴─────────┴───────────┴─────────┴────────┴──┘\n",
  "structure": {
    "main": "如附表所示之證券無效。\n訴訟費用由聲請人負擔。",
    "reason": "一、上開證券，經本院以九十四年度催字第二九０號公示催告。\n二、所定申報權利期間，已於民國九十四年八月十六日屆滿，迄\n    今無人申報權利。\n三、依民事訴訟法第五百六十四條第一項，判決如主文。"
  },
  "search": "臺灣臺北地方法院民事判決94年度除字第2650號聲請人臺北市文山區辛亥國民小學法定代理人乙○○訴訟代理人甲○○上列聲請人聲請除權判決事件，本院判決如下：主文如附表所示之證券無效。訴訟費用由聲請人負擔。理由一、上開證券，經本院以九十四年度催字第二九０號公示催告。二、所定申報權利期間，已於民國九十四年八月十六日屆滿，迄今無人申報權利。三、依民事訴訟法第五百六十四條第一項，判決如主文。中華民國九十四年十月十二日民事第五庭法官蔡世祺以上正本係照原本作成。本判決不得上訴。中華民國九十四年十月十二日書記官黃媚鵑┌────────────────────────────────────────────────────────┐│附表：94年度除字第2650號│├──┬─────────┬─────────┬───────────┬─────────┬────────┬──┤│編號│發票人│付款人│發票日│票面金額（新台幣）│支票號碼│備考│├──┼─────────┼─────────┼───────────┼─────────┼────────┼──┤│001│台北市文山區辛亥國│富邦銀行和平分行│93年11月26日│100,612元│HP0000000││││民小學乙○○││││││└──┴─────────┴─────────┴───────────┴─────────┴────────┴──┘",
  "characters": {
    "judges": [
      "蔡世祺"
    ],
    "prosecutors": [

    ],
    "lawyers": [

    ],
    "clerks": [
      "黃媚鵑"
    ],
    "plaintiffs": [

    ],
    "defendants": [

    ],
    "prosecutor_office": [
      "臺北市文山區辛亥國民小學"
    ],
    "creditors": [

    ],
    "debtors": [

    ],
    "judicial_associate_officer": [

    ]
  },
  "adjudged_at": "2005-10-12",
  "created_at": "2016-02-07 10:53:13",
  "updated_at": "2016-02-07 10:53:13"
}