{
  "identify": "KSD-100-訴-448-20110526-1",
  "court": {
    "name": "臺灣高雄地方法院",
    "code": "KSD"
  },
  "division": {
    "name": "刑事",
    "code": "M"
  },
  "year": 100,
  "word": "訴",
  "number": "448",
  "jcheck": "1",
  "reason": "毒品危害防制條例",
  "content": "臺灣高雄地方法院刑事判決              100年度訴字第448號\n公  訴  人  臺灣高雄地方法院檢察署檢察官\n被      告  盧進添\n上列被告因毒品危害防制條例案件，經檢察官提起公訴（99年度\n偵字第35452 號），經本院合議庭裁定由受命法官獨任行簡式審\n判程序，判決如下：\n    主  文\n盧進添施用第一級毒品，累犯，處有期徒刑拾月。扣案海洛因壹\n包（含包裝袋，檢驗後淨重零點零參陸公克），沒收銷燬之。\n    事  實\n一、盧進添前因違反肅清煙毒條例案件，經本院82年度訴字第97\n    號、83年度訴緝字第145 號分別判處有期徒刑3 年2 月、3\n    年4 月及褫奪公權2 年確定，2 罪接續執行，於民國85年6\n    月4 日假釋出監，嗣經撤銷假釋執行殘刑4 年1 月13日，再\n    經本院96年度聲減字第997 號裁定減刑為有期徒刑1 年8 月\n    、1 年7 月及褫奪公權1 年確定，並於96年7 月16日因徒刑\n    執行完畢出監。復因施用毒品案件，經本院97年度審毒聲字\n    第1680號裁定送觀察、勒戒後，認有繼續施用毒品傾向，再\n    經本院98年度審毒聲字第422 號裁定令入戒治處所施以強制\n    戒治，甫於99年1 月20日因停止處分執行出監，並經臺灣高\n    雄地方法院檢察署檢察官以99年度戒毒偵字第29號以強制戒\n    治期滿為不起訴處分確定。詎仍不知悔改，明知海洛因係經\n    政府公告，列為毒品危害防制條例第2 條第2 項第1 款之第\n    一級毒品，未經許可不得持有、施用，竟於強制戒治執行完\n    畢釋放後5 年內，基於施用第一級毒品海洛因之犯意，於99\n    年10月4 日22時，在高雄市大社區（99年12月25日改制前為\n    高雄縣大社鄉○○○路151 號之住處內，將海洛因摻水以針\n    筒注射之方式，施用第一級毒品海洛因1 次。嗣於同年月7\n    日9 時許，在高雄市○○街45巷口，因行跡可疑為警盤查，\n    並扣得盧進添丟棄於地之第一級毒品海洛因1 包（毛重0.28\n    公克，檢驗後淨重為0.036 公克），經採集其尿液送驗後，\n    結果呈海洛因代謝物之嗎啡陽性反應，而查悉上情。\n二、案經高雄市政府警察局移送臺灣高雄地方法院檢察署檢察官\n    偵查起訴。\n    理  由\n一、本件被告盧進添所犯係死刑、無期徒刑、最輕本刑為3 年以\n    上有期徒刑以外之罪，其於準備程序中就被訴事實為有罪之\n    陳述，經法官告知簡式審判程序之旨，並聽取公訴人及被告\n    之意見後，認為適宜由受命法官獨任進行簡式審判程序，依\n    刑事訴訟法第273 條之1 第1 項規定，裁定由受命法官獨任\n    進行審判程序。又本件之證據調查，依刑事訴訟法第273 條\n    之2 規定，不受同法第159 條第1 項、第161 條之2 、第16\n    1 條之3 、第163 條之1 及第164 條至第170 條規定之限制\n    ，均合先敘明。\n二、認定事實之證據及理由：\n  (一)上開犯罪事實，業據被告於警詢、偵查及本院坦承不諱（見\n    臺灣高雄地方法院檢察署99年度偵字第35452 號卷《下稱偵\n    查卷》第3 頁背面、第47頁、本院100 年度審訴字第198 號\n    卷《下稱本院卷(一)》第23頁背面、本院100 年度訴字第448\n    號卷《下稱本院卷(二)》第29頁），其對警方經其同意採尿送\n    驗，提供乾淨空瓶予被告親自排放尿液之過程，亦不爭執（\n    見偵查卷第3 頁背面）。被告之尿液送驗結果，經高雄市立\n    凱旋醫院以氣相層析質譜儀法(GC/MS) 確認檢驗結果，呈海\n    洛因代謝物之嗎啡陽性反應，有該院99年11月22日轉碼編號\n    ：A00000000 號濫用藥物尿液檢驗報告、濫用藥物尿液檢體\n    監管紀錄表、高雄市政府警察局前鎮分局查獲煙毒麻醉藥品\n    案件犯罪嫌疑人姓名對照表（尿液編號：I-924 ）各1 紙在\n    卷為證（見偵查卷第13、14、49頁）。扣案白色粉末1 包（\n    毛重0.28公克，檢驗前淨重0.045 公克、檢驗後淨重0.03 6\n    公克），經高雄市立凱旋醫院以氣相層析質譜儀（GC/MS ）\n    法確認檢驗結果，確實檢出第一級毒品海洛因，有高雄市政\n    府警察局前鎮分局扣押筆錄、扣押物品目錄表各1 份、採證\n    照片4 張、高雄市政府警察局前鎮分局一心派出所查獲毒品\n    危害防制條例毒品初步檢驗報告單1 紙（見偵查卷第5 至12\n    頁）及高雄市立凱旋醫院100 年1 月11日高市凱醫驗字第14\n    661 號濫用藥物成品檢驗鑑定書1 紙在卷為憑（見本院卷(一)\n    第14-1頁），足認被告自白與事實相符。\n  (二)關於扣案之第一級毒品海洛因1 包，被告於警詢時固供稱：\n    伊是於99年10月7 日8 時許，在高雄市鳳山區○○○路加油\n    站前遇到綽號叫「忠仔」的男子向其購買等語（見偵查卷第\n    3 頁背面），於偵查中供稱：毒品來源係伊查獲當天要去工\n    作在五甲一路加油站向叫「阿德」之男子購買的等語（見偵\n    查卷第48頁），惟其於本院審理時改供稱：扣案海洛因1 包\n    係伊於99年10月4 日購買施用後剩下，放在身上的等語（見\n    本院卷(一)第23頁背面、本院卷(二)第20、29頁）。被告對於持\n    有扣案海洛因1 包之時間供述前後不一，因除被告之自白外\n    ，查無證據足以佐證被告持有扣案海洛因1 包之時間為何，\n    依罪疑唯有利於被告認定之原則，應依被告於本院審理時所\n    述，認定扣案之第一級毒品海洛因1 包為被告於99年10月4\n    日施用後剩餘之毒品。\n  (三)被告前因施用毒品案件，經本院97年度審毒聲字第1680號裁\n    定送觀察、勒戒後，認有繼續施用毒品傾向，再經本院98年\n    度審毒聲字第422 號裁定令入戒治處所施以強制戒治，甫於\n    99年1 月20日因停止處分執行出監，並經臺灣高雄地方法院\n    檢察署檢察官以99年度戒毒偵字第29號以強制戒治期滿為不\n    起訴處分確定，有臺灣高等法院被告前案紀錄表在卷可稽。\n    是被告於經強制戒治執行完畢後，於5 年內再犯本件施用第\n    一級毒品犯行，檢察官逕行起訴，即無不合。\n  (四)從而，被告施用第一級毒品海洛因1 次之犯行堪以認定，應\n    依法論科。\n三、論罪科刑：\n  (一)查海洛因係屬毒品危害防制條例第2 條第2 項第1 款之第一\n    級毒品。核被告所為，係犯毒品危害防制條例第10條第1 項\n    施用第一級毒品罪。其持有第一級毒品海洛因之低度行為，\n    應為施用第一級毒品海洛因之高度行為所吸收，不另論罪。\n    被告前因違反肅清煙毒條例案件，經本院82年度訴字第97號\n    、83年度訴緝字第145 號分別判處有期徒刑3 年2 月、3 年\n    4 月及褫奪公權2 年確定，2 罪接續執行，於85年6 月4 日\n    假釋出監，嗣經撤銷假釋執行殘刑4 年1 月13日，再經本院\n    96年度聲減字第997 號裁定減刑為有期徒刑1 年8 月、1 年\n    7 月及褫奪公權1 年確定，並於96年7 月16日因徒刑執行完\n    畢出監，有臺灣高等法院被告前案紀錄表在卷可憑，其受有\n    期徒刑執行完畢後，於5 年內故意再犯本件有期徒刑以上之\n    罪，為累犯，應依刑法第47條第1 項規定，加重其刑。爰審\n    酌被告前因施用毒品甫經強制戒治執行完畢，猶未戒除施用\n    毒品惡習，仍為本案施用第一級毒品海洛因犯行，其施用毒\n    品之行為不僅戕害自身身心健康，亦間接影響社會治安，惟\n    念其坦承犯行，所犯施用毒品罪乃屬戕害自身身心健康行為\n    ，反社會性之程度較低，並考量被告犯罪動機、智識程度等\n    一切情狀，認檢察官具體求處有期徒刑1 年2 月略嫌過重，\n    量處如主文所示之刑，以資懲戒。\n  (二)扣案之白色粉末1 包（檢驗前淨重0.045 公克，檢驗後淨重\n    0.036 公克），經檢驗結果為第一級毒品海洛因，已如前所\n    述，其包裝袋因包覆毒品，顯留有毒品之殘渣，與其上殘留\n    之毒品，衡情已難以分析剝離，亦無析離實益，當應整體視\n    為毒品，不問屬於被告與否，應依毒品危害防制條例第18條\n    第1 項前段之規定宣告沒收銷燬之。至鑑驗耗用之毒品既已\n    滅失，自無庸宣告沒收。\n據上論斷，應依刑事訴訟法第273 條之1 第1 項、第299 條第1\n項前段，毒品危害防制條例第10條第1 項、第18條第1 項前段，\n刑法第11條、第47條第1 項，判決如主文。\n本案經檢察官魏豪勇到庭執行職務。\n中    華    民    國   100    年    5     月    26    日\n                  刑事第六庭    法  官  曾鈴\n以上正本證明與原本無異。\n如不服本判決應於收受送達後10日內向本院提出上訴書狀，並應\n敘述具體理由；如未敘述上訴理由者，應於上訴期間屆滿後20日\n內向本院補提理由書（均須按他造當事人之人數附繕本）「切勿\n逕送上級法院」。\n中    華    民    國   100    年    5     月    30    日\n                                書記官  李月君\n附錄本判決論罪科刑法條：\n毒品危害防制條例第10條第1 項\n施用第一級毒品者，處 6 月以上 5 年以下有期徒刑。",
  "structure": {
    "main": "盧進添施用第一級毒品，累犯，處有期徒刑拾月。扣案海洛因壹\n包（含包裝袋，檢驗後淨重零點零參陸公克），沒收銷燬之。",
    "fact": "一、盧進添前因違反肅清煙毒條例案件，經本院82年度訴字第97\n    號、83年度訴緝字第145 號分別判處有期徒刑3 年2 月、3\n    年4 月及褫奪公權2 年確定，2 罪接續執行，於民國85年6\n    月4 日假釋出監，嗣經撤銷假釋執行殘刑4 年1 月13日，再\n    經本院96年度聲減字第997 號裁定減刑為有期徒刑1 年8 月\n    、1 年7 月及褫奪公權1 年確定，並於96年7 月16日因徒刑\n    執行完畢出監。復因施用毒品案件，經本院97年度審毒聲字\n    第1680號裁定送觀察、勒戒後，認有繼續施用毒品傾向，再\n    經本院98年度審毒聲字第422 號裁定令入戒治處所施以強制\n    戒治，甫於99年1 月20日因停止處分執行出監，並經臺灣高\n    雄地方法院檢察署檢察官以99年度戒毒偵字第29號以強制戒\n    治期滿為不起訴處分確定。詎仍不知悔改，明知海洛因係經\n    政府公告，列為毒品危害防制條例第2 條第2 項第1 款之第\n    一級毒品，未經許可不得持有、施用，竟於強制戒治執行完\n    畢釋放後5 年內，基於施用第一級毒品海洛因之犯意，於99\n    年10月4 日22時，在高雄市大社區（99年12月25日改制前為\n    高雄縣大社鄉○○○路151 號之住處內，將海洛因摻水以針\n    筒注射之方式，施用第一級毒品海洛因1 次。嗣於同年月7\n    日9 時許，在高雄市○○街45巷口，因行跡可疑為警盤查，\n    並扣得盧進添丟棄於地之第一級毒品海洛因1 包（毛重0.28\n    公克，檢驗後淨重為0.036 公克），經採集其尿液送驗後，\n    結果呈海洛因代謝物之嗎啡陽性反應，而查悉上情。\n二、案經高雄市政府警察局移送臺灣高雄地方法院檢察署檢察官\n    偵查起訴。",
    "reason": "一、本件被告盧進添所犯係死刑、無期徒刑、最輕本刑為3 年以\n    上有期徒刑以外之罪，其於準備程序中就被訴事實為有罪之\n    陳述，經法官告知簡式審判程序之旨，並聽取公訴人及被告\n    之意見後，認為適宜由受命法官獨任進行簡式審判程序，依\n    刑事訴訟法第273 條之1 第1 項規定，裁定由受命法官獨任\n    進行審判程序。又本件之證據調查，依刑事訴訟法第273 條\n    之2 規定，不受同法第159 條第1 項、第161 條之2 、第16\n    1 條之3 、第163 條之1 及第164 條至第170 條規定之限制\n    ，均合先敘明。\n二、認定事實之證據及理由：\n  (一)上開犯罪事實，業據被告於警詢、偵查及本院坦承不諱（見\n    臺灣高雄地方法院檢察署99年度偵字第35452 號卷《下稱偵\n    查卷》第3 頁背面、第47頁、本院100 年度審訴字第198 號\n    卷《下稱本院卷(一)》第23頁背面、本院100 年度訴字第448\n    號卷《下稱本院卷(二)》第29頁），其對警方經其同意採尿送\n    驗，提供乾淨空瓶予被告親自排放尿液之過程，亦不爭執（\n    見偵查卷第3 頁背面）。被告之尿液送驗結果，經高雄市立\n    凱旋醫院以氣相層析質譜儀法(GC/MS) 確認檢驗結果，呈海\n    洛因代謝物之嗎啡陽性反應，有該院99年11月22日轉碼編號\n    ：A00000000 號濫用藥物尿液檢驗報告、濫用藥物尿液檢體\n    監管紀錄表、高雄市政府警察局前鎮分局查獲煙毒麻醉藥品\n    案件犯罪嫌疑人姓名對照表（尿液編號：I-924 ）各1 紙在\n    卷為證（見偵查卷第13、14、49頁）。扣案白色粉末1 包（\n    毛重0.28公克，檢驗前淨重0.045 公克、檢驗後淨重0.03 6\n    公克），經高雄市立凱旋醫院以氣相層析質譜儀（GC/MS ）\n    法確認檢驗結果，確實檢出第一級毒品海洛因，有高雄市政\n    府警察局前鎮分局扣押筆錄、扣押物品目錄表各1 份、採證\n    照片4 張、高雄市政府警察局前鎮分局一心派出所查獲毒品\n    危害防制條例毒品初步檢驗報告單1 紙（見偵查卷第5 至12\n    頁）及高雄市立凱旋醫院100 年1 月11日高市凱醫驗字第14\n    661 號濫用藥物成品檢驗鑑定書1 紙在卷為憑（見本院卷(一)\n    第14-1頁），足認被告自白與事實相符。\n  (二)關於扣案之第一級毒品海洛因1 包，被告於警詢時固供稱：\n    伊是於99年10月7 日8 時許，在高雄市鳳山區○○○路加油\n    站前遇到綽號叫「忠仔」的男子向其購買等語（見偵查卷第\n    3 頁背面），於偵查中供稱：毒品來源係伊查獲當天要去工\n    作在五甲一路加油站向叫「阿德」之男子購買的等語（見偵\n    查卷第48頁），惟其於本院審理時改供稱：扣案海洛因1 包\n    係伊於99年10月4 日購買施用後剩下，放在身上的等語（見\n    本院卷(一)第23頁背面、本院卷(二)第20、29頁）。被告對於持\n    有扣案海洛因1 包之時間供述前後不一，因除被告之自白外\n    ，查無證據足以佐證被告持有扣案海洛因1 包之時間為何，\n    依罪疑唯有利於被告認定之原則，應依被告於本院審理時所\n    述，認定扣案之第一級毒品海洛因1 包為被告於99年10月4\n    日施用後剩餘之毒品。\n  (三)被告前因施用毒品案件，經本院97年度審毒聲字第1680號裁\n    定送觀察、勒戒後，認有繼續施用毒品傾向，再經本院98年\n    度審毒聲字第422 號裁定令入戒治處所施以強制戒治，甫於\n    99年1 月20日因停止處分執行出監，並經臺灣高雄地方法院\n    檢察署檢察官以99年度戒毒偵字第29號以強制戒治期滿為不\n    起訴處分確定，有臺灣高等法院被告前案紀錄表在卷可稽。\n    是被告於經強制戒治執行完畢後，於5 年內再犯本件施用第\n    一級毒品犯行，檢察官逕行起訴，即無不合。\n  (四)從而，被告施用第一級毒品海洛因1 次之犯行堪以認定，應\n    依法論科。\n三、論罪科刑：\n  (一)查海洛因係屬毒品危害防制條例第2 條第2 項第1 款之第一\n    級毒品。核被告所為，係犯毒品危害防制條例第10條第1 項\n    施用第一級毒品罪。其持有第一級毒品海洛因之低度行為，\n    應為施用第一級毒品海洛因之高度行為所吸收，不另論罪。\n    被告前因違反肅清煙毒條例案件，經本院82年度訴字第97號\n    、83年度訴緝字第145 號分別判處有期徒刑3 年2 月、3 年\n    4 月及褫奪公權2 年確定，2 罪接續執行，於85年6 月4 日\n    假釋出監，嗣經撤銷假釋執行殘刑4 年1 月13日，再經本院\n    96年度聲減字第997 號裁定減刑為有期徒刑1 年8 月、1 年\n    7 月及褫奪公權1 年確定，並於96年7 月16日因徒刑執行完\n    畢出監，有臺灣高等法院被告前案紀錄表在卷可憑，其受有\n    期徒刑執行完畢後，於5 年內故意再犯本件有期徒刑以上之\n    罪，為累犯，應依刑法第47條第1 項規定，加重其刑。爰審\n    酌被告前因施用毒品甫經強制戒治執行完畢，猶未戒除施用\n    毒品惡習，仍為本案施用第一級毒品海洛因犯行，其施用毒\n    品之行為不僅戕害自身身心健康，亦間接影響社會治安，惟\n    念其坦承犯行，所犯施用毒品罪乃屬戕害自身身心健康行為\n    ，反社會性之程度較低，並考量被告犯罪動機、智識程度等\n    一切情狀，認檢察官具體求處有期徒刑1 年2 月略嫌過重，\n    量處如主文所示之刑，以資懲戒。\n  (二)扣案之白色粉末1 包（檢驗前淨重0.045 公克，檢驗後淨重\n    0.036 公克），經檢驗結果為第一級毒品海洛因，已如前所\n    述，其包裝袋因包覆毒品，顯留有毒品之殘渣，與其上殘留\n    之毒品，衡情已難以分析剝離，亦無析離實益，當應整體視\n    為毒品，不問屬於被告與否，應依毒品危害防制條例第18條\n    第1 項前段之規定宣告沒收銷燬之。至鑑驗耗用之毒品既已\n    滅失，自無庸宣告沒收。\n據上論斷，應依刑事訴訟法第273 條之1 第1 項、第299 條第1\n項前段，毒品危害防制條例第10條第1 項、第18條第1 項前段，\n刑法第11條、第47條第1 項，判決如主文。\n本案經檢察官魏豪勇到庭執行職務。\n中    華    民    國   100    年    5     月    26    日\n                  刑事第六庭    法  官  曾鈴\n以上正本證明與原本無異。\n如不服本判決應於收受送達後10日內向本院提出上訴書狀，並應\n敘述具體理由；如未敘述上訴理由者，應於上訴期間屆滿後20日\n內向本院補提理由書（均須按他造當事人之人數附繕本）「切勿\n逕送上級法院」。"
  },
  "search": "臺灣高雄地方法院刑事判決100年度訴字第448號公訴人臺灣高雄地方法院檢察署檢察官被告盧進添上列被告因毒品危害防制條例案件，經檢察官提起公訴（99年度偵字第35452號），經本院合議庭裁定由受命法官獨任行簡式審判程序，判決如下：主文盧進添施用第一級毒品，累犯，處有期徒刑拾月。扣案海洛因壹包（含包裝袋，檢驗後淨重零點零參陸公克），沒收銷燬之。事實一、盧進添前因違反肅清煙毒條例案件，經本院82年度訴字第97號、83年度訴緝字第145號分別判處有期徒刑3年2月、3年4月及褫奪公權2年確定，2罪接續執行，於民國85年6月4日假釋出監，嗣經撤銷假釋執行殘刑4年1月13日，再經本院96年度聲減字第997號裁定減刑為有期徒刑1年8月、1年7月及褫奪公權1年確定，並於96年7月16日因徒刑執行完畢出監。復因施用毒品案件，經本院97年度審毒聲字第1680號裁定送觀察、勒戒後，認有繼續施用毒品傾向，再經本院98年度審毒聲字第422號裁定令入戒治處所施以強制戒治，甫於99年1月20日因停止處分執行出監，並經臺灣高雄地方法院檢察署檢察官以99年度戒毒偵字第29號以強制戒治期滿為不起訴處分確定。詎仍不知悔改，明知海洛因係經政府公告，列為毒品危害防制條例第2條第2項第1款之第一級毒品，未經許可不得持有、施用，竟於強制戒治執行完畢釋放後5年內，基於施用第一級毒品海洛因之犯意，於99年10月4日22時，在高雄市大社區（99年12月25日改制前為高雄縣大社鄉○○○路151號之住處內，將海洛因摻水以針筒注射之方式，施用第一級毒品海洛因1次。嗣於同年月7日9時許，在高雄市○○街45巷口，因行跡可疑為警盤查，並扣得盧進添丟棄於地之第一級毒品海洛因1包（毛重0.28公克，檢驗後淨重為0.036公克），經採集其尿液送驗後，結果呈海洛因代謝物之嗎啡陽性反應，而查悉上情。二、案經高雄市政府警察局移送臺灣高雄地方法院檢察署檢察官偵查起訴。理由一、本件被告盧進添所犯係死刑、無期徒刑、最輕本刑為3年以上有期徒刑以外之罪，其於準備程序中就被訴事實為有罪之陳述，經法官告知簡式審判程序之旨，並聽取公訴人及被告之意見後，認為適宜由受命法官獨任進行簡式審判程序，依刑事訴訟法第273條之1第1項規定，裁定由受命法官獨任進行審判程序。又本件之證據調查，依刑事訴訟法第273條之2規定，不受同法第159條第1項、第161條之2、第161條之3、第163條之1及第164條至第170條規定之限制，均合先敘明。二、認定事實之證據及理由：(一)上開犯罪事實，業據被告於警詢、偵查及本院坦承不諱（見臺灣高雄地方法院檢察署99年度偵字第35452號卷《下稱偵查卷》第3頁背面、第47頁、本院100年度審訴字第198號卷《下稱本院卷(一)》第23頁背面、本院100年度訴字第448號卷《下稱本院卷(二)》第29頁），其對警方經其同意採尿送驗，提供乾淨空瓶予被告親自排放尿液之過程，亦不爭執（見偵查卷第3頁背面）。被告之尿液送驗結果，經高雄市立凱旋醫院以氣相層析質譜儀法(GC/MS)確認檢驗結果，呈海洛因代謝物之嗎啡陽性反應，有該院99年11月22日轉碼編號：A00000000號濫用藥物尿液檢驗報告、濫用藥物尿液檢體監管紀錄表、高雄市政府警察局前鎮分局查獲煙毒麻醉藥品案件犯罪嫌疑人姓名對照表（尿液編號：I-924）各1紙在卷為證（見偵查卷第13、14、49頁）。扣案白色粉末1包（毛重0.28公克，檢驗前淨重0.045公克、檢驗後淨重0.036公克），經高雄市立凱旋醫院以氣相層析質譜儀（GC/MS）法確認檢驗結果，確實檢出第一級毒品海洛因，有高雄市政府警察局前鎮分局扣押筆錄、扣押物品目錄表各1份、採證照片4張、高雄市政府警察局前鎮分局一心派出所查獲毒品危害防制條例毒品初步檢驗報告單1紙（見偵查卷第5至12頁）及高雄市立凱旋醫院100年1月11日高市凱醫驗字第14661號濫用藥物成品檢驗鑑定書1紙在卷為憑（見本院卷(一)第14-1頁），足認被告自白與事實相符。(二)關於扣案之第一級毒品海洛因1包，被告於警詢時固供稱：伊是於99年10月7日8時許，在高雄市鳳山區○○○路加油站前遇到綽號叫「忠仔」的男子向其購買等語（見偵查卷第3頁背面），於偵查中供稱：毒品來源係伊查獲當天要去工作在五甲一路加油站向叫「阿德」之男子購買的等語（見偵查卷第48頁），惟其於本院審理時改供稱：扣案海洛因1包係伊於99年10月4日購買施用後剩下，放在身上的等語（見本院卷(一)第23頁背面、本院卷(二)第20、29頁）。被告對於持有扣案海洛因1包之時間供述前後不一，因除被告之自白外，查無證據足以佐證被告持有扣案海洛因1包之時間為何，依罪疑唯有利於被告認定之原則，應依被告於本院審理時所述，認定扣案之第一級毒品海洛因1包為被告於99年10月4日施用後剩餘之毒品。(三)被告前因施用毒品案件，經本院97年度審毒聲字第1680號裁定送觀察、勒戒後，認有繼續施用毒品傾向，再經本院98年度審毒聲字第422號裁定令入戒治處所施以強制戒治，甫於99年1月20日因停止處分執行出監，並經臺灣高雄地方法院檢察署檢察官以99年度戒毒偵字第29號以強制戒治期滿為不起訴處分確定，有臺灣高等法院被告前案紀錄表在卷可稽。是被告於經強制戒治執行完畢後，於5年內再犯本件施用第一級毒品犯行，檢察官逕行起訴，即無不合。(四)從而，被告施用第一級毒品海洛因1次之犯行堪以認定，應依法論科。三、論罪科刑：(一)查海洛因係屬毒品危害防制條例第2條第2項第1款之第一級毒品。核被告所為，係犯毒品危害防制條例第10條第1項施用第一級毒品罪。其持有第一級毒品海洛因之低度行為，應為施用第一級毒品海洛因之高度行為所吸收，不另論罪。被告前因違反肅清煙毒條例案件，經本院82年度訴字第97號、83年度訴緝字第145號分別判處有期徒刑3年2月、3年4月及褫奪公權2年確定，2罪接續執行，於85年6月4日假釋出監，嗣經撤銷假釋執行殘刑4年1月13日，再經本院96年度聲減字第997號裁定減刑為有期徒刑1年8月、1年7月及褫奪公權1年確定，並於96年7月16日因徒刑執行完畢出監，有臺灣高等法院被告前案紀錄表在卷可憑，其受有期徒刑執行完畢後，於5年內故意再犯本件有期徒刑以上之罪，為累犯，應依刑法第47條第1項規定，加重其刑。爰審酌被告前因施用毒品甫經強制戒治執行完畢，猶未戒除施用毒品惡習，仍為本案施用第一級毒品海洛因犯行，其施用毒品之行為不僅戕害自身身心健康，亦間接影響社會治安，惟念其坦承犯行，所犯施用毒品罪乃屬戕害自身身心健康行為，反社會性之程度較低，並考量被告犯罪動機、智識程度等一切情狀，認檢察官具體求處有期徒刑1年2月略嫌過重，量處如主文所示之刑，以資懲戒。(二)扣案之白色粉末1包（檢驗前淨重0.045公克，檢驗後淨重0.036公克），經檢驗結果為第一級毒品海洛因，已如前所述，其包裝袋因包覆毒品，顯留有毒品之殘渣，與其上殘留之毒品，衡情已難以分析剝離，亦無析離實益，當應整體視為毒品，不問屬於被告與否，應依毒品危害防制條例第18條第1項前段之規定宣告沒收銷燬之。至鑑驗耗用之毒品既已滅失，自無庸宣告沒收。據上論斷，應依刑事訴訟法第273條之1第1項、第299條第1項前段，毒品危害防制條例第10條第1項、第18條第1項前段，刑法第11條、第47條第1項，判決如主文。本案經檢察官魏豪勇到庭執行職務。中華民國100年5月26日刑事第六庭法官曾鈴以上正本證明與原本無異。如不服本判決應於收受送達後10日內向本院提出上訴書狀，並應敘述具體理由；如未敘述上訴理由者，應於上訴期間屆滿後20日內向本院補提理由書（均須按他造當事人之人數附繕本）「切勿逕送上級法院」。中華民國100年5月30日書記官李月君附錄本判決論罪科刑法條：毒品危害防制條例第10條第1項施用第一級毒品者，處6月以上5年以下有期徒刑。",
  "characters": {
    "judges": [
      "曾鈴"
    ],
    "prosecutors": [
      "魏豪勇"
    ],
    "lawyers": [

    ],
    "clerks": [
      "李月君"
    ],
    "plaintiffs": [

    ],
    "defendants": [
      "盧進添"
    ],
    "prosecutor_office": [
      "臺灣高雄地方法院檢察署檢察官"
    ],
    "creditors": [

    ],
    "debtors": [

    ],
    "judicial_associate_officer": [

    ]
  },
  "adjudged_at": "2011-05-26",
  "created_at": "2016-02-12 01:48:41",
  "updated_at": "2016-02-12 01:48:41"
}