{
  "identify": "TYD-99-重訴-95-20110525-1",
  "court": {
    "name": "臺灣桃園地方法院",
    "code": "TYD"
  },
  "division": {
    "name": "民事",
    "code": "V"
  },
  "year": 99,
  "word": "重訴",
  "number": "95",
  "jcheck": "1",
  "reason": "拆屋還地等",
  "content": "臺灣桃園地方法院民事判決              99年度重訴字第95號\n原      告  陳蘇治\n            陳寶瓊\n            陳淑麗\n            陳文鶯\n            邱俊宏\n            邱勝飛\n            邱志成\n            邱碧姿\n            邱新永\n            邱顯宗\n            邱萬得\n            蔡邱玉蘭\n            邱芳汶\n            黃陳草鳳\n            葉王沅即葉陳玉嬌.\n            葉月寶即葉陳玉嬌.\n            葉美娜即葉陳玉嬌.\n            沙陳銅銀\n            陳韻\n共      同\n訴訟代理人  吳秀菊律師\n被      告  巫廖會\n兼  上一人\n訴訟代理人  巫乾正\n被      告  黃張滿妹\n            黃美華\n            黃嘉生\n            黃  河\n            黃雅英\n上五人共同\n訴訟代理人  康英彬律師\n被      告  劉鼎泰（原名劉振權）\n上列當事人間請求返拆屋還地等事件，於民國100 年4 月27日言\n詞辯論終結，本院判決如下：\n    主      文\n原告之訴及假執行之聲請均駁回。\n訴訟費用由原告負擔。\n    事實及理由\n壹、程序方面：\n    按訴狀送達後，原告不得將原訴變更或追加他訴，但有請求\n    之基礎事實同一、擴張或減縮應受判決事項之聲明、不甚礙\n    被告之防禦及訴訟之終結情形者，不在此限，民事訴訟法第\n    255 條第1 項但書第2 款、第3 款、第7 款分別定有明文。\n    查原告起訴時訴之聲明為：「(一)被告應將如附圖1 所示土地\n    上之地上物拆除（占有土地面積、地上物門牌號碼均約如附\n    圖1 附表所示，實際位置及面積請鈞院囑託地政機關測量後\n    為準），並將土地返還予原告及其他共有人。(二)被告應各給\n    付原告如附表2 第(五)欄所示金額，及自起訴狀繕本送達翌日\n    起迄清償日止，按年息百分之五計算之利息。(三)被告各應給\n    付自99年3 月1 日起迄第一項所示土地交還原告及其他共有\n    人之日，各按年給付原告如附表2 第(七)欄所示金額。(四)願供\n    擔保請准宣告假執行。」。嗣於民國100 年2 月14日具狀追\n    加巫廖會為被告，並變更聲明為：「(一)請令被告應將如下所\n    述土地上之地上物拆除（占有土地面積、地上物門牌號碼均\n    如附圖１所示），並將土地返還予原告及其他共有人。1.請\n    令被告巫乾正、巫廖會應將如附圖1 所示中壢市○○段中壢\n    老小段第11-15 地號上標示11-15 （B ）3 ㎡、14 -1 地號\n    上標示14-1（B ）129 ㎡，面積合計為132 ㎡之土地上門牌\n    號碼為中壢市○○路354 號地上物予以拆除，並將土地返還\n    予原告及其他共有人。2.請令被告黃張滿妹、黃河、黃雅英\n    、黃美華、黃嘉生等人將如附圖1 所示中壢市○○段中壢老\n    小段第14-2地號土地上標示14-2（A ）122 ㎡，面積合計12\n    2 ㎡之土地上門牌號碼為中壢市○○路356 號地上物予以拆\n    除，並將土地返還予原告及其他共有人。3.請令被告劉振權\n    將如附圖1 所示中壢市○○段中壢老小段第14-5地號土地上\n    標示14 -5 （A ）109 ㎡及同地段土地第14-6地號土地上標\n    示14-6（A ）28㎡，面積合計137 ㎡之土地上門牌號碼為中\n    壢市○○路362 號地上物予以拆除，並將土地返還予原告及\n    其他共有人。4.請令被告劉振權將如附圖1 所示中壢市○○\n    段中壢老小段第14-6地號土地上標示14-6（C ）46㎡，面積\n    合計46㎡之土地上門牌號碼為中壢市○○路364 號地上物予\n    以拆除，並將土地返還予原告及其他共有人。(二)被告各應給\n    付各原告等如附表２第(五)欄所所示金額，及自起訴狀繕本送\n    達之翌日起迄清償日止，按年息百分之五計算之利息。(三)被\n    告各應自99年3 月1 日起迄第一項所示土地交還原告及其他\n    共有人之日，各按年給付各原告如附表２第(七)欄所示金額。\n    (四)原告願供擔保，請准宣告假執行。」，核原告追加被告巫\n    廖會部分，核其請求之基礎事實與起訴之事實同一，且不甚\n    礙被告之防禦及訴訟之終結；又變更拆除及返還土地面積部\n    分，係擴張或減縮應受判決事項之聲明；揆諸前揭法律規定\n    ，均應予准許。\n貳、實體方面：\n一、原告起訴主張：\n（一）原告乃被繼承人陳蘇之全體繼承人，而原告之被繼承人\n      陳蘇乃坐落桃園縣中壢市○○段中壢老小段14-1、11-1\n      5 、14-2、14-5、14-6地號土地（下稱系爭土地）之所有\n      權人之一，所佔持分為十分之八，而陳蘇於44年7 月30\n      日過世後，原告當然繼承被繼承人之系爭土地之產權，雖\n      遲至95年5 月10日方辦理繼承登記，惟基於繼承法理原告\n      於44年7 月30日後即取得系爭土地之所有權。原告為系爭\n      土地之共有人，被告未經原告及其他共有人同意，擅自在\n      原告所有之系爭土地上興建建物，核其所為顯然係無權占\n      用原告所共有之土地，爰依民法第821 條及第767 條規定\n      ，訴請被告除去妨害及返還所有物予所有人全體，又無權\n      占有他人土地可獲得相當於租金之利益，被告無權占用系\n      爭土地，致原告對之無法使用收益，被告顯屬無法律上之\n      原因而受利益致原告受有損害，原告自得依民法第179 條\n      及最高法院61年台上字第1695號判例之規定，請求被告返\n      還起訴前五年起至返還土地之日止相當於租金之不當得利\n      。\n（二）對被告答辯之陳述：\n  １、否認兩造間有租賃關係存在，也否認被告等所繳給陳水模\n      之租金，即為被告等所占用土地之租金。\n  ２、被告等除劉鼎泰外，其屋況均已老舊，顯見渠等明知為無\n      權占有他人土地，故無積極翻修，聽憑屋況老舊之貌。\n  ３、被告等所提示之收據均無陳蘇或原告等任何一人之簽名\n      或蓋章，且原告之被繼承人陳蘇乃於44年即過世，而被\n      告所提出之收據均係陳蘇死亡後之收據，並無原告等合\n      法繼承人所立之文件，而原告並無委託或授權陳水模出租\n      土地或收取租金。陳水模並非陳蘇之繼承人，陳水模或\n      其子陳文毅無由代理或代表陳蘇或原告，且土地乃公示\n      主義，任何人均可透過地政機關查閱系爭土地所有權人為\n      何，從而並無表見代理成立之餘地。另有關共有物之租賃\n      ，實務及學說均係對共有物之「管理行為」，而系爭土地\n      之共有人含原告等迄今未分割，而被告承租系爭土地亦未\n      曾得到身為共有人之原告之同意，依民法第828 條、第82\n      0 條第1 項規定，縱認被告與系爭土地之5 分之1 共有人\n      陳水模就系爭土地有租賃關係，惟該共有人所為之管理行\n      為（出租）乃屬無效，故被告占有系爭土地仍屬無權占有\n      。被告巫乾正、巫廖會二人所有之系爭房屋係自其被繼承\n      人巫振鐮繼承而得，而巫振鐮乃於陳蘇死後於55年間才\n      於第三人處取得系爭房屋之事實上處分權，亦證渠等係無\n      權占用系爭土地。\n  ４、原告否認陳水模為被繼承人陳蘇之子孫輩財產管理人。\n      系爭土地於陳蘇死亡後係由其夫陳番管理，而陳番死亡\n      後因無人管理，故系爭土地因無人繳納稅捐於64年遭稅捐\n      機關查封，至95年時財稅單位向原告等寄交繳稅通知，原\n      告始一次性繳納500 多萬元之地價稅，足證此間並未曾出\n      現由陳水模代表原告處理系爭土地全部之情形。被告劉鼎\n      泰亦辯稱陳蘇死亡後係由陳番管理系爭土地，則被告應\n      繳納租金之對象即為陳番，而非陳水模，亦證被告辯稱陳\n      水模代表原告出租系爭土地及向渠等收取租金之事實乃不\n      實在。\n  ５、被告劉鼎泰所提出之「租借地權契約證書」其上之陳蘇\n      與陳水模之筆跡相同，顯然並非陳蘇所親簽之契約，故\n      原告亦否認該契約書乃出於陳蘇之承諾或合意。縱被告\n      劉鼎泰對系爭土地有基地租賃，惟因被告劉鼎泰始終未繳\n      付應有之租金予陳蘇或原告（被告從未提示陳蘇及原\n      告等人所立之任何租金收據），並將系爭房屋轉租圖利，\n      又違反租賃契約將系爭房屋全面改建，原告爰依土地法第\n      103 條第1 項第3 、4 、5 款為由，向被告劉鼎泰為終止\n      租賃契約之意思表示，並以本訴狀之送達為終止租賃意思\n      表示送達之時。\n  ６、被告黃河等五人自認其進駐系爭房屋乃44年以後之事情，\n      其父黃志文係後來所購及進駐系爭房屋，當時原告被繼承\n      人陳蘇已經過世，故被告之被繼承人黃志文與原告之被\n      繼承人無從成立地上權之物權及基地之租賃契約。而被告\n      所提日據時期地籍謄本與二造及本件並無關係。蓋有關上\n      開日據時期謄本所載之權利人為訴外人張詹氏冉妹，並無\n      記載為後手為權利人。尤以被告既抗辯其等有日據時代之\n      地上權，從而謹請被告先提呈其係地上權人之登記權利人\n      及日據時代其等已進駐系爭房屋之證明。縱退萬步言，假\n      若被告黃河等五人對系爭土地有基地租賃或所謂地上權之\n      關係（非表自認），惟因被告始終未繳付應有之地租予原\n      告及原告之被繼承人，原告先前即依土地法第103 條規定\n      第1 項第4 款、第5 款為由向被告為終止租賃契約之意思\n      表示，並以民法第836 條之規定撤銷被告所謂之地上權，\n      並以該狀之送達為意思表示送達之時。\n（三）並聲明：如前開變更聲明所示。\n二、被告劉鼎泰則以：被告占有、使用系爭土地乃因被告之祖父\n    劉阿昂前於39年即與原告之被繼承人陳水模、陳蘇二人訂\n    有「租借地權契約書」，依該契約書第五點記載，租約之存\n    續期間為「不限年」，故被告基於繼承原因取得系爭土地之\n    承租權而占有、使用系爭土地，實有合法權源。陳水模及其\n    子陳文毅亦基於該契約書而向被告之祖父與被告收取租金，\n    該基地租賃法律關係確係存在，不容原告隨意否認。原告對\n    該租借地權契約書不否定其真實性，僅認為並非陳蘇本人\n    簽字，及非出於陳蘇之承諾或合意，惟該契約書之簽訂後\n    至44年7 月30日陳蘇往生為止，約五年期間被告均繼續繳\n    租，陳蘇並無反對之意思表示，故原告所提並非事實，純\n    屬臆測。被告已繳清至98年5 月31日之地租，至今尚未滿二\n    年，故並不符和土地法第103 條第4 款終止租約之規定，且\n    由以往至今被告一律繳足額之租金，並非繳交1/5 之租金，\n    並由陳水模及其後人陳文毅代為收取，並提出37、38年陳蘇\n    尚未死亡前即全權委託陳水模代收租金之收據，足證從陳\n    蘇在世時即委託陳水模代收租金。又被告為租地建屋，所\n    租為被告本人及祖父劉阿昂所有之房屋，並未違反「租借地\n    權契約書」內之規定，且被告全家亦長期居住於此，並無將\n    租地轉租他人之情形，與土地法第103 條第3 、5 款規定不\n    符。另陳水模、陳蘇係共同出租人，其二人秉於該「租借\n    地權契約書」對於被告本得為全部租金給付之請求，故屬連\n    帶債權。因而，被告基於繼承原因取得系爭土地之承租權後\n    ，除中山路364 號房屋仍登記為劉阿昂所有外，362 號房屋\n    則登記於被告劉鼎泰名下，被告並依租約約定繳納租金於出\n    租人陳水模之繼承人陳文毅，依民法第284 條規定被告給付\n    租金於連帶出租人之一陳水模及其繼承人陳文毅自屬適法有\n    效，此亦無涉於陳蘇是否委託陳水模或其繼承人陳文毅代\n    理或代表受取租金。另民法第820 條係屬共有人內部對於共\n    有物管理之同意，而本件租賃關係原本即存在於土地所有權\n    人陳水模與陳蘇，故民法第820 條規定無涉於本件租賃關\n    係等語置辯。並聲明：原告之訴及其假執行聲請均駁回：如\n    受不利益判決，願供擔保請准宣告免為假執行。\n三、被告巫乾正、巫廖會則以：\n    被告所有中壢市○○路354 號房屋（該屋係於41年7 月間由\n    訴外人劉源慶出賣予訴外人吳金妹，可見該屋早於41年間即\n    存在），係坐落中壢市○○段中壢老小段14-1地號土地，是\n    由被告巫乾正之父巫振鐮繼承而得。被告巫乾正之父巫振鐮\n    先於53年8 月26日受贈於訴外人吳進發持分2 分之1 ，再於\n    55年3 月15日自訴外人吳鄧桂菊買受持分2 分之1 。至於房\n    屋基地一直是向地主陳水模承租，並繳納租金，直到陳水模\n    過世後始由其繼承人陳文毅收取租金。嗣因本案被訴，被告\n    始知悉陳水模、陳文毅共有系爭土地應有部分5 分之1 ，對\n    於土地另有其他共有人被告完全不知情，故退步言之，倘使\n    陳水模、陳文毅無權將系爭土地出租，然由被告所有之房屋\n    早於41年間即已存在，可以推定迄今系爭土地出租已超過50\n    餘年，一直均是由陳水模、陳文毅以地主身份而一脈相承，\n    其不但與被告訂立租約、協調租金數額，且按期收取租金，\n    對被告而言，陳文毅即是地主之代表，依民法第169 條規定\n    被告與陳水模、陳文毅訂立之租約亦是合法有效。系爭土地\n    出租予被告建築房屋有合法之租約，則依土地法第103 條規\n    定，本案原告並不可將土地收回。並聲明：原告之訴及假執\n    行之聲請均駁回；如受不利益判決，願供擔保請准宣告免為\n    假執行。\n四、被告黃張滿妹、黃美華、黃嘉生、黃河、黃雅英則以：\n（一）系爭被告等所共有建於原告繼承土地上之建物，經查至遲\n      建於日據時期之27年間，故斯時臺灣地區仍適用日本國民\n      法。復按系爭「中壢市○○段中壢老小段14-2地號」土地\n      於日據時期之原所有人為張詹氏冉妹，嗣張詹氏冉妹於昭\n      和6 年1 月14日將所有權一部分轉予張新鐘，於昭和8 年\n      （即民國22年）9 月5 日張詹氏冉妹與張新鐘二人將所有\n      權移轉予陳有定及「陳水模」共有（陳水模應有部分為五\n      分之一），於37年9 月23日陳有定將其應有部分移轉予「\n      陳蘇」（陳蘇應有部分為五分之四），此有日據時期\n      之土地臺帳本可稽。基此，於37年後系爭土地業由陳蘇\n      及陳水模所共有。而被告之被繼承人黃志文建屋後均按期\n      繳納基地租金於基地所有人，於22年陳水模取得系爭土地\n      所有權後即收受地租，嗣於37年陳蘇取得土地後，亦委\n      託陳水模收取地租，故其後系爭土地均由陳水模以地主暨\n      經陳蘇授權之身分向黃志文收取基地租金迄今，而陳水\n      模亦以同樣模式向同案其他被告收取基地租金。系爭房屋\n      於陳蘇取得土地時早已存在十餘年，況陳蘇乃以「買\n      賣」方式取得土地所有權，故依常理論，陳蘇於買受土\n      地時，誠不可能不知當時土地之使用現況為何。又陳水模\n      為陳蘇與配偶陳番所生，雖將陳水模出養給陳番之兄弟\n      陳泰，但原告亦自承出養未久陳泰即亡故，從而陳水模於\n      養父死亡後自幼仍由親生父母撫養，此何以原告亦自承常\n      看到陳水模在陳蘇家裡，甚至陳水模之戶籍始終設於龜\n      山，迨陳水模日後遷至坐落於系爭土地相鄰之中壢市○○\n      路352 號居住，而陳番亦曾至該住處與陳水模同住，加以\n      原告自承陳蘇往生後，系爭土地即由陳番管理，故陳番\n      亦自明知陳蘇所遺留之系爭土地有本件多位被告建屋於\n      上許久（陳蘇44年7 月亡、陳番67年8 月亡），歷經二\n      十餘年間陳番不可能不知由其子陳水模代為管理系爭土地\n      並收取租金之事實。另陳水模早於陳蘇取得系爭土地之\n      共有權，而系爭建物於陳水模取得土地後幾年始建蓋，且\n      房屋建蓋後陳水模即開始收取地租至84年間，加以陳蘇\n      之配偶即陳水模之生父陳番係於67年8 月間始亡故，而陳\n      番即設籍住於被告之隔壁（中壢市○○路352 號），故陳\n      蘇夫婦實不可能不知其所共有之土地已由被告建屋於其\n      上，甚至由其子陳水模出面代表地主收取租金數十年不間\n      斷。另系爭土地依當時之環境乃位於中壢之市區中心，非\n      屬郊區或偏僻不毛之地，且就本件訟爭各筆土地，依當時\n      之經濟狀況論，每年向建物所有人收取之租金總數亦可觀\n      ，矧占有土地持分五分之四之陳蘇更不可能就自己之土\n      地任由他人無權占有使用，故茲有陳蘇之子陳水模以土\n      地管理人或代理人身份向建物所有人收取租金，亦符常情\n      。況陳水模亦曾以陳蘇管理人之身分寄存證信函予黃志\n      文要求調整租金。\n（二）訴外人陳有定與陳水模於日據時期之昭和8 年（即民國22\n      年）取得系爭土地所有權，而系爭建物於日據時期之昭和\n      13年（民國27年）即建於系爭土地上，故當時土地及建物\n      之法律關係應依日本國之相關法律而定之，而依日本國《\n      關於地上權之法律》第1 條、最高法院72年台上字第136\n      號判決規定，當時日本國物權法乃採「意思主義」，以當\n      事人之意思表示即可成立生效，且在他人土地為所有工作\n      物而使用其土地之人推定為地上權人，故得知系爭建物所\n      有人於昭和13年即應取得地上權，從而黃志文既為系爭建\n      物之所有權人，依日本國民法規定即就系爭土地具有正當\n      使用權源。縱另一共有人即原告之被繼承人陳蘇於37年\n      取得系爭土地所有權，然依物權之「對世效力」，黃志文\n      自仍可對陳蘇主張地上權。遑論黃志文均有支付基地租\n      金予陳水模與陳蘇二人。退步言之，本件黃志文之地上\n      權縱有自始或嗣後不存在之事由，然系爭土地共有人之一\n      陳水模均以系爭土地管理人之身分向黃志文收取基地租金\n      迄今已數十年，則黃志文與系爭土地所有人間就系爭土地\n      存有基地租賃契約，故黃志文使用系爭土地亦具有使用權\n      源。退萬步言之，本件就陳水模以系爭土地共有人之管理\n      人身份向黃志文收取基地租金之行為可議，然細究陳蘇\n      自知其所共有之土地有黃志文建屋於上，復陳蘇之配偶\n      陳番亦住於相鄰土地上，且陳水模為陳番與陳蘇所生之\n      子，則陳水模對外以陳蘇代理人或管理人之名義向建物\n      所有人收取租金應為陳蘇所知悉，然陳蘇對此卻始終\n      均未表示反對意見，從而被告等自可主張民法第169 條之\n      表見代理之法律效果，故黃志文使用系爭土地亦具正當使\n      用權源。\n（三）陳水模取得系爭土地所有權後，被告之被繼承人黃志文始\n      建屋於上，且其後陳水模均代表地主至黃志文住處收取租\n      金，故系爭租金清償方式屬於往取債務，乃陳水模生前均\n      依此方式收取租金，然於85年起陳水模即因故未再向黃志\n      文收租，然黃志文為保權益乃多次催告陳水模與陳蘇之\n      繼承人收租，此有85年至98年之存證信函可稽。因陳水模\n      受催告後仍未出面收取租金，黃志文乃於99年4 月間依民\n      法第326 條規定將最近五年（至99年度）之基地租金向臺\n      灣桃園法院提存，故提存後即生清償效力。被告既先催告\n      債權人領取組金，且於債權人受領遲延時依法將應為之給\n      付物提存，故本件被告並無遲延給付租金或其他違約之情\n      ，從而原告主張依土地法第103 條第4 、5 款所定之事由\n      終止租約，亦無所據。並聲明：原告之訴及假執行之聲請\n      均駁回；如受不利益判決，願供擔保請准免為假執行。\n三、兩造不爭執事項：\n（一）訴外人陳蘇已於44年7 月30日死亡，原告為陳蘇之繼\n      承人。訴外人葉陳玉嬌為陳蘇之繼承人，葉陳玉嬌已於\n      98年10月7 日死亡，原告葉王沅、葉月寶、葉美娜為葉陳\n      玉嬌之繼承人。\n（二）坐落桃園縣中壢市○○路354 號係爭房屋屬於巫乾正、巫\n      廖惠所有；356 號係爭房屋屬於張滿妹、黃河、黃雅英、\n      黃美華、黃嘉生等人所有；362 、364 號係爭房屋屬於劉\n      振權所有；而係爭建物分別坐落於如桃園縣中壢地政事務\n      所99年12月21日之土地複丈成果圖所示之地號土地及面積\n      。\n（三）原告與訴外人陳文毅為系爭土地之共有人，訴外人陳文毅\n      之應有部分為2/10。原告等人就系爭土地之應有部分合計\n      為8/10 。\n四、本院得心證理由：\n（一）按訴外人陳水模出養予其叔叔陳泰後，由於養父不久隨即\n      死亡，因此返回本生父母處與本生父母即陳蘇與陳番共\n      同生活，業據陳水模之子陳文毅到庭證述明確（詳見本院\n      卷二第180-181 頁）。且陳水模之戶籍地原設與陳番及陳\n      蘇相同之龜山鄉○路村○○路坑21號，嗣於38年12月28\n      日與陳簡鬆結婚，至41年8 月1 日始遷至中壢鎮中壢里2\n      鄰中壢25號；而陳蘇於42年12月24日亦遷移至中壢鎮中\n      壢里2 鄰中壢25號陳水模之住處，此有戶籍謄本在卷可稽\n      。可見陳水模雖出養其叔叔陳泰，然事實上均是與本生父\n      母陳蘇與陳番共同生活互相照顧。又陳水模與陳蘇與\n      陳番共同設籍於龜山，依戶籍記載父母親為陳蘇與陳番\n      ，然於40年7 月14日始聲請更正為陳泰之養子，因此在40\n      年7 月14日前陳水模戶籍上記載之父母為陳蘇與陳番，\n      嗣於40年7 月14日始申請更正為陳泰之養子，此有戶籍謄\n      本在卷可稽。然一般外人豈可能知悉如此私人隱私之資料\n      ，且長期以來在外人眼裡陳水模即陳蘇與陳番之子女，\n      所以被告等一如往常均認為陳水模代表陳蘇與陳番之權\n      限，應可採信。\n（二）被告劉鼎泰之祖父劉阿昂於39年9 月15日與陳水模、陳蘇\n      簽立租借地權契約證書（詳見本院卷一第122 頁），原\n      告雖然否認其真正性，然當時之土地所有權人為陳水模、\n      陳蘇所有，且如前述陳水模與陳蘇、陳番均有往來甚\n      至共同生活，且當時戶籍謄本上陳水模與陳蘇、陳番是\n      為父母子女之登載，另契約書上記載之住址，與陳蘇、\n      陳水模當時之住址相符；因此對於渠等共有土地相信渠等\n      應該知悉處理之情況，可見係爭租界地權契約書，確實係\n      陳蘇與陳水模所簽立。而被告劉鼎泰所提出由訴外人陳\n      水模收取租金之收據（詳見本院卷一第123-129 頁、院二\n      第187 、188 頁），衡諸常情，陳水模與陳蘇既然共同\n      簽訂租借地權契約書，且為陳蘇子女，豈可能不幫陳蘇\n      收取租金，因此縱然陳水模收取租金之收據沒有代表或\n      代理陳蘇之字眼，然陳水模所收取之租金應包涵陳蘇\n      部分，故被告主張陳水模代表或代理陳蘇收取租金應為\n      可採。縱然陳文毅證稱：有向巫乾正及劉政權收取租金，\n      是根據父親告知，伊看父親之前簽收的收據多少，伊就收\n      多少，伊認為只是收取伊的持份部分。其僅是收取其應有\n      部分，其父親收取多少其就收取多少，其不知伊父親有無\n      幫忙陳蘇租金等語（詳見本院卷二第180 頁至181 頁）\n      ，由於陳文毅不知陳水模是如何與巫乾正、劉鼎泰約定租\n      金，僅是依照之前收取多少即收取多少。然既然依照前述\n      ，陳水模收取的租金包函陳蘇部分，則陳文毅收取的租\n      金亦包函陳蘇及原告等之部分。故被告等主張陳文毅收\n      取的租金應包函原告等之部分，應為可採。\n（三）訴外人陳番（即原告等人之被繼承人、陳蘇之配偶）與\n      被告劉鼎泰之祖父劉阿昂曾就係爭土地之租金於47年6 月\n      27日成立和解筆錄，此有和解筆錄在卷可稽（詳見本院卷\n      二第196 頁），而渠等成立和解筆錄後，劉阿昂就係爭土\n      地之租金亦係給付給陳水模，可見陳水模當時收取租金時\n      ，不僅就其所有部份，就陳蘇部分亦應一同收取，因為\n      當時縱然陳水模出養，然其依然與本生父母即陳蘇及陳\n      蕃共同生活，豈可能僅收取名下之租金，而對於陳蘇名\n      下之租金棄之不顧，顯與常情有違。且當陳蘇往生後，\n      其名下土地由陳番管理（當時並未辦理繼承登記，但實際\n      上陳番以繼承人之地位在管理系爭土地），陳番既然與劉\n      阿昂成立租金調高之和解書，豈可能沒有要求被告等繳交\n      租金；然被告等均沒有陳番具名之收據，而僅有陳水模具\n      名之收據，可見陳水模所收取租金亦應包涵名下之部分（\n      既然之前包函陳蘇部分，則衡諸常情，在沒有其他繼承\n      人出面主張有不同意見前，被告等繼續認為陳水模有代理\n      處理收取租金之權限，亦符合常情）。從而，陳水模收取\n      被告等所繳納之租金，自始即包函陳蘇名下部分，不論\n      陳蘇往生後係爭土地由陳番管理之時期亦是如此。故陳\n      水模向被告等收取之租金，在陳蘇往生後之時期，亦包\n      函陳蘇名下部份之租金。\n（四）陳水模亦曾以兼具有陳蘇管理人之身分於80年9 月26日\n      曾發函黃志文告知要提高租金為每年627,976 元，此有存\n      證信函在卷可稽（詳見本院卷二第79頁）；陳番於67年8\n      月30日往生，其往生後就陳蘇名下之土地全體繼承人均\n      未處理，而陳水模在陳番往生後，一如往常的對被告等收\n      取租金，則被告等亦一如往常的認為渠等所交付的租金，\n      包函屬於陳蘇名下之部分，應屬可採。而原告等雖均為\n      陳蘇之繼承人，然陳蘇之長子陳佳猷於86年1 月10日\n      才往生，在此之前為何共有人（繼承人）均未對被告等主\n      張任何權利，而是待95年5 月10日辦理繼承之後再向被告\n      等主張無權占有？在陳佳猷尚建在時，為何沒有對被告等\n      主張任何權利？因此於陳番往生後（即67年8 月30日）至\n      陳佳猷往生前（86年1 月10日）間，可見陳佳猷亦同意由\n      陳水模來管理系爭土地並收取租金，否則陳佳猷豈可能沒\n      有對被告等主張任何權利；再者，陳蘇名下之土地，在\n      陳蘇往生後，其繼承人到底有誰？依照法律規定與一般\n      民間習俗或許截然不同；且強求被告等去查詢資料來釐清\n      陳蘇之繼承人到底是何人，顯係強人所難之事，而被告\n      等亦無此義務。故被告等一如往常的認為陳水模繼續有代\n      理陳蘇之繼承人收取租金之權限，應為可採。\n（五）由巫乾正所提出陳水模及陳文毅所簽立之收據（詳見本院\n      卷一第139-140 頁；卷二第96-102頁）；再者係爭房屋房\n      屋稅之起課時間為16年1 月間（詳見本院卷二第103 頁）\n      ，顯見被告巫乾正、巫廖會部分，均無積欠租金之情形。\n      另由劉鼎泰所提出陳水模所簽立之收據（詳見本院卷二18\n      7 、188 頁、卷0000-000 頁），陳文毅所簽立之收據（\n      詳見本院卷一第12 9頁），可見被告劉振權部分亦無積欠\n      租金之情形。再者，由於被告黃張滿妹等5 人部分之房屋\n      於27年1 月即起課（詳見本院卷一第160 頁），且陳水模\n      亦均有向其收取租金（詳見本院卷二第55-78 頁），收取\n      到83年11月30日，雖然陳水模曾於80年9 月26日曾發文要\n      求提高租金費用，然或許兩造未達成協議，而被告自85年\n      12月2 日起每年均以存證信函加計支票涵文給陳水模；另\n      自87年10月1 日起則以存證信函催告陳水模到其住處收取\n      租金，直至96年12月3 日為止。則被告黃張滿妹等5 人部\n      份亦無積欠租金之情事。從上可知，被告等均無積欠原告\n      等，而有租金未繳之情事。\n（六）按由自己之行為表示以代理權授與他人，或知他人表示為\n      其代理人而不為反對之表示者，對於第三人應負授權人之\n      責任，民法第169 條前段雖定有明文。然由自己之行為表\n      示以代理權授與他人者，對於第三人應負授權人之責任，\n      必須本人有表見之事實，足使第三人信該他人有代理權之\n      情形存在，始足當之。我國人民將自己印章交付他人，委\n      託該他人辦理特定事項者，比比皆是，倘持有印章之該他\n      人，除受託辦理之特定事項外，其他以本人名義所為之任\n      何法律行為，均須由本人負表見代理之授權人責任，未免\n      過苛。原審徒憑上訴人曾將印章交付與呂某之事實，即認\n      被上訴人就保證契約之訂立應負表見代理之授權人責任，\n      自屬率斷（最高法院70年台上字第657 號判例意旨參照）\n      。又民法第169 條所謂知他人表示為其代理人而不為反對\n      之表示者，以本人實際知其事實為前提，其主張本人知此\n      事實者，應負舉證之責（最高法院68年台上字第1081號判\n      例意旨參照）。被告等辯稱與陳水模、陳蘇成立租借地\n      權契約書或者對於渠等建物坐落土地與地主成立租賃契約\n      ，陳水模收取之租金包函陳蘇之部分，故陳蘇及陳蘇\n      之繼承人應負表見代理人之責任云云。經查：\n  １、在陳水模與陳蘇（往生前）之時段：如前述，陳水模與\n      陳蘇、陳番亦如父母子女，則陳水模代表二人來收取被\n      告等租賃土地之租金，而陳蘇亦無提出異議，被告等也\n      均有繳納租金，顯見陳水模有代理陳蘇收取租金之權限\n      及情事。\n  ２、在陳水模與陳番（往生前）之時段：在陳蘇往生後，陳\n      番曾與劉阿昂成立租金調解筆錄，而期後之租金，仍由陳\n      水模繼續向被告等收取，則被告等信賴陳水模有代理陳蘇\n      之繼承人收取陳蘇名下土地租金之權限，亦為可採。\n  ３、在陳水模與陳番往生後之時段：在陳番往生後，陳水模繼\n      續向被告等收取渠等租地之租金，而未有其他繼承人出面\n      向被告等主張陳水模並未有如此代理權之前提下，被告等\n      依然認為陳水模有代理權並且繼續繳納租金，則被告等主\n      張陳水模有代理原告等收取租金之權限，應為可採。且原\n      告等亦不否認，未曾向被告等催告收取租金，直至提起本\n      件訴訟為止。或者一直到原告於本院對被告陳梁美靜等人\n      提起96年度訴字第413 號拆屋還地等案時，才知道原告等\n      人係陳蘇之繼承人。\n  ４、從而，原告等主張陳水模對於陳蘇並未有表現代理之情\n      況，亦未有代理陳蘇收取租金之情事及權限，顯無足採\n      。不論被告等之被繼承人取得所有之建物係早於陳蘇取\n      得係爭土地所有權之前或者之後，在陳蘇取得土地所有\n      權後，陳蘇對於陳水模代理其向被告等或渠等之被繼承\n      人收取租地租金時，並未有明確之反對陳水模沒有代理權\n      ，且當時陳水模為陳蘇之子女，外人亦容易認為陳水模\n      有代理陳蘇收取租金之權限，因此有表現代理之情事；\n      則在陳蘇往生後，未有其他繼承人出面主張陳水模未有\n      代理其他繼承人收取租金之權限前，被告等繼續認為陳水\n      模有代理之權限，而繼續繳納租金，則陳水模與陳蘇繼\n      承人間亦存有表現代理之情況；則被告等主張陳水模收取\n      之租金，包含陳蘇部分及原告等繼承人之部分，應為可\n      採。另被告等既依照先前兩造租約之約定繼續繳納租金，\n      未有遲延繳納租金之情事，原告另主張被告等有未繳納租\n      金之情事，亦無足採。\n六、綜上所述，被告等主張渠等並非無權占有原告等及被繼承人\n    陳蘇名下之土地，而係存有租賃關係，為可採信。則原告\n    本於所有權主張被告等無權占有應返還渠等建物所占有之土\n    地及基於不當得利法律關係請求被告等應給付相當於租金之\n    不當得利數額，均為無理由，均應予駁回。原告之訴既經駁\n    回，其假執行之聲請亦失所附麗，併予駁回。\n七、本件事證已臻明確，兩造其餘主張陳述及所提之證據，經審\n    酌與本院前揭判斷無影響，毋庸一一論述，附此敘明。\n八、據上論結，原告之訴為無理由，依民事訴訟法第78，判決如\n    主文。\n中    華    民    國    100     年    5   月    25    日\n                  民事第三庭    法  官  張益銘\n以上正本係照原本作成\n如對本判決上訴，須於判決送達後 20 日內向本院提出上訴狀。\n如委任律師提起上訴者，應一併繳納上訴審裁判費。\n中    華    民    國    100    年    5    月    25    日\n                            書記官  郭玉芬",
  "structure": {
    "main": "原告之訴及假執行之聲請均駁回。\n訴訟費用由原告負擔。",
    "fact": "壹、程序方面：\n    按訴狀送達後，原告不得將原訴變更或追加他訴，但有請求\n    之基礎事實同一、擴張或減縮應受判決事項之聲明、不甚礙\n    被告之防禦及訴訟之終結情形者，不在此限，民事訴訟法第\n    255 條第1 項但書第2 款、第3 款、第7 款分別定有明文。\n    查原告起訴時訴之聲明為：「(一)被告應將如附圖1 所示土地\n    上之地上物拆除（占有土地面積、地上物門牌號碼均約如附\n    圖1 附表所示，實際位置及面積請鈞院囑託地政機關測量後\n    為準），並將土地返還予原告及其他共有人。(二)被告應各給\n    付原告如附表2 第(五)欄所示金額，及自起訴狀繕本送達翌日\n    起迄清償日止，按年息百分之五計算之利息。(三)被告各應給\n    付自99年3 月1 日起迄第一項所示土地交還原告及其他共有\n    人之日，各按年給付原告如附表2 第(七)欄所示金額。(四)願供\n    擔保請准宣告假執行。」。嗣於民國100 年2 月14日具狀追\n    加巫廖會為被告，並變更聲明為：「(一)請令被告應將如下所\n    述土地上之地上物拆除（占有土地面積、地上物門牌號碼均\n    如附圖１所示），並將土地返還予原告及其他共有人。1.請\n    令被告巫乾正、巫廖會應將如附圖1 所示中壢市○○段中壢\n    老小段第11-15 地號上標示11-15 （B ）3 ㎡、14 -1 地號\n    上標示14-1（B ）129 ㎡，面積合計為132 ㎡之土地上門牌\n    號碼為中壢市○○路354 號地上物予以拆除，並將土地返還\n    予原告及其他共有人。2.請令被告黃張滿妹、黃河、黃雅英\n    、黃美華、黃嘉生等人將如附圖1 所示中壢市○○段中壢老\n    小段第14-2地號土地上標示14-2（A ）122 ㎡，面積合計12\n    2 ㎡之土地上門牌號碼為中壢市○○路356 號地上物予以拆\n    除，並將土地返還予原告及其他共有人。3.請令被告劉振權\n    將如附圖1 所示中壢市○○段中壢老小段第14-5地號土地上\n    標示14 -5 （A ）109 ㎡及同地段土地第14-6地號土地上標\n    示14-6（A ）28㎡，面積合計137 ㎡之土地上門牌號碼為中\n    壢市○○路362 號地上物予以拆除，並將土地返還予原告及\n    其他共有人。4.請令被告劉振權將如附圖1 所示中壢市○○\n    段中壢老小段第14-6地號土地上標示14-6（C ）46㎡，面積\n    合計46㎡之土地上門牌號碼為中壢市○○路364 號地上物予\n    以拆除，並將土地返還予原告及其他共有人。(二)被告各應給\n    付各原告等如附表２第(五)欄所所示金額，及自起訴狀繕本送\n    達之翌日起迄清償日止，按年息百分之五計算之利息。(三)被\n    告各應自99年3 月1 日起迄第一項所示土地交還原告及其他\n    共有人之日，各按年給付各原告如附表２第(七)欄所示金額。\n    (四)原告願供擔保，請准宣告假執行。」，核原告追加被告巫\n    廖會部分，核其請求之基礎事實與起訴之事實同一，且不甚\n    礙被告之防禦及訴訟之終結；又變更拆除及返還土地面積部\n    分，係擴張或減縮應受判決事項之聲明；揆諸前揭法律規定\n    ，均應予准許。\n貳、實體方面：\n一、原告起訴主張：\n（一）原告乃被繼承人陳蘇之全體繼承人，而原告之被繼承人\n      陳蘇乃坐落桃園縣中壢市○○段中壢老小段14-1、11-1\n      5 、14-2、14-5、14-6地號土地（下稱系爭土地）之所有\n      權人之一，所佔持分為十分之八，而陳蘇於44年7 月30\n      日過世後，原告當然繼承被繼承人之系爭土地之產權，雖\n      遲至95年5 月10日方辦理繼承登記，惟基於繼承法理原告\n      於44年7 月30日後即取得系爭土地之所有權。原告為系爭\n      土地之共有人，被告未經原告及其他共有人同意，擅自在\n      原告所有之系爭土地上興建建物，核其所為顯然係無權占\n      用原告所共有之土地，爰依民法第821 條及第767 條規定\n      ，訴請被告除去妨害及返還所有物予所有人全體，又無權\n      占有他人土地可獲得相當於租金之利益，被告無權占用系\n      爭土地，致原告對之無法使用收益，被告顯屬無法律上之\n      原因而受利益致原告受有損害，原告自得依民法第179 條\n      及最高法院61年台上字第1695號判例之規定，請求被告返\n      還起訴前五年起至返還土地之日止相當於租金之不當得利\n      。\n（二）對被告答辯之陳述：\n  １、否認兩造間有租賃關係存在，也否認被告等所繳給陳水模\n      之租金，即為被告等所占用土地之租金。\n  ２、被告等除劉鼎泰外，其屋況均已老舊，顯見渠等明知為無\n      權占有他人土地，故無積極翻修，聽憑屋況老舊之貌。\n  ３、被告等所提示之收據均無陳蘇或原告等任何一人之簽名\n      或蓋章，且原告之被繼承人陳蘇乃於44年即過世，而被\n      告所提出之收據均係陳蘇死亡後之收據，並無原告等合\n      法繼承人所立之文件，而原告並無委託或授權陳水模出租\n      土地或收取租金。陳水模並非陳蘇之繼承人，陳水模或\n      其子陳文毅無由代理或代表陳蘇或原告，且土地乃公示\n      主義，任何人均可透過地政機關查閱系爭土地所有權人為\n      何，從而並無表見代理成立之餘地。另有關共有物之租賃\n      ，實務及學說均係對共有物之「管理行為」，而系爭土地\n      之共有人含原告等迄今未分割，而被告承租系爭土地亦未\n      曾得到身為共有人之原告之同意，依民法第828 條、第82\n      0 條第1 項規定，縱認被告與系爭土地之5 分之1 共有人\n      陳水模就系爭土地有租賃關係，惟該共有人所為之管理行\n      為（出租）乃屬無效，故被告占有系爭土地仍屬無權占有\n      。被告巫乾正、巫廖會二人所有之系爭房屋係自其被繼承\n      人巫振鐮繼承而得，而巫振鐮乃於陳蘇死後於55年間才\n      於第三人處取得系爭房屋之事實上處分權，亦證渠等係無\n      權占用系爭土地。\n  ４、原告否認陳水模為被繼承人陳蘇之子孫輩財產管理人。\n      系爭土地於陳蘇死亡後係由其夫陳番管理，而陳番死亡\n      後因無人管理，故系爭土地因無人繳納稅捐於64年遭稅捐\n      機關查封，至95年時財稅單位向原告等寄交繳稅通知，原\n      告始一次性繳納500 多萬元之地價稅，足證此間並未曾出\n      現由陳水模代表原告處理系爭土地全部之情形。被告劉鼎\n      泰亦辯稱陳蘇死亡後係由陳番管理系爭土地，則被告應\n      繳納租金之對象即為陳番，而非陳水模，亦證被告辯稱陳\n      水模代表原告出租系爭土地及向渠等收取租金之事實乃不\n      實在。\n  ５、被告劉鼎泰所提出之「租借地權契約證書」其上之陳蘇\n      與陳水模之筆跡相同，顯然並非陳蘇所親簽之契約，故\n      原告亦否認該契約書乃出於陳蘇之承諾或合意。縱被告\n      劉鼎泰對系爭土地有基地租賃，惟因被告劉鼎泰始終未繳\n      付應有之租金予陳蘇或原告（被告從未提示陳蘇及原\n      告等人所立之任何租金收據），並將系爭房屋轉租圖利，\n      又違反租賃契約將系爭房屋全面改建，原告爰依土地法第\n      103 條第1 項第3 、4 、5 款為由，向被告劉鼎泰為終止\n      租賃契約之意思表示，並以本訴狀之送達為終止租賃意思\n      表示送達之時。\n  ６、被告黃河等五人自認其進駐系爭房屋乃44年以後之事情，\n      其父黃志文係後來所購及進駐系爭房屋，當時原告被繼承\n      人陳蘇已經過世，故被告之被繼承人黃志文與原告之被\n      繼承人無從成立地上權之物權及基地之租賃契約。而被告\n      所提日據時期地籍謄本與二造及本件並無關係。蓋有關上\n      開日據時期謄本所載之權利人為訴外人張詹氏冉妹，並無\n      記載為後手為權利人。尤以被告既抗辯其等有日據時代之\n      地上權，從而謹請被告先提呈其係地上權人之登記權利人\n      及日據時代其等已進駐系爭房屋之證明。縱退萬步言，假\n      若被告黃河等五人對系爭土地有基地租賃或所謂地上權之\n      關係（非表自認），惟因被告始終未繳付應有之地租予原\n      告及原告之被繼承人，原告先前即依土地法第103 條規定\n      第1 項第4 款、第5 款為由向被告為終止租賃契約之意思\n      表示，並以民法第836 條之規定撤銷被告所謂之地上權，\n      並以該狀之送達為意思表示送達之時。\n（三）並聲明：如前開變更聲明所示。\n二、被告劉鼎泰則以：被告占有、使用系爭土地乃因被告之祖父\n    劉阿昂前於39年即與原告之被繼承人陳水模、陳蘇二人訂\n    有「租借地權契約書」，依該契約書第五點記載，租約之存\n    續期間為「不限年」，故被告基於繼承原因取得系爭土地之\n    承租權而占有、使用系爭土地，實有合法權源。陳水模及其\n    子陳文毅亦基於該契約書而向被告之祖父與被告收取租金，\n    該基地租賃法律關係確係存在，不容原告隨意否認。原告對\n    該租借地權契約書不否定其真實性，僅認為並非陳蘇本人\n    簽字，及非出於陳蘇之承諾或合意，惟該契約書之簽訂後\n    至44年7 月30日陳蘇往生為止，約五年期間被告均繼續繳\n    租，陳蘇並無反對之意思表示，故原告所提並非事實，純\n    屬臆測。被告已繳清至98年5 月31日之地租，至今尚未滿二\n    年，故並不符和土地法第103 條第4 款終止租約之規定，且\n    由以往至今被告一律繳足額之租金，並非繳交1/5 之租金，\n    並由陳水模及其後人陳文毅代為收取，並提出37、38年陳蘇\n    尚未死亡前即全權委託陳水模代收租金之收據，足證從陳\n    蘇在世時即委託陳水模代收租金。又被告為租地建屋，所\n    租為被告本人及祖父劉阿昂所有之房屋，並未違反「租借地\n    權契約書」內之規定，且被告全家亦長期居住於此，並無將\n    租地轉租他人之情形，與土地法第103 條第3 、5 款規定不\n    符。另陳水模、陳蘇係共同出租人，其二人秉於該「租借\n    地權契約書」對於被告本得為全部租金給付之請求，故屬連\n    帶債權。因而，被告基於繼承原因取得系爭土地之承租權後\n    ，除中山路364 號房屋仍登記為劉阿昂所有外，362 號房屋\n    則登記於被告劉鼎泰名下，被告並依租約約定繳納租金於出\n    租人陳水模之繼承人陳文毅，依民法第284 條規定被告給付\n    租金於連帶出租人之一陳水模及其繼承人陳文毅自屬適法有\n    效，此亦無涉於陳蘇是否委託陳水模或其繼承人陳文毅代\n    理或代表受取租金。另民法第820 條係屬共有人內部對於共\n    有物管理之同意，而本件租賃關係原本即存在於土地所有權\n    人陳水模與陳蘇，故民法第820 條規定無涉於本件租賃關\n    係等語置辯。並聲明：原告之訴及其假執行聲請均駁回：如\n    受不利益判決，願供擔保請准宣告免為假執行。\n三、被告巫乾正、巫廖會則以：\n    被告所有中壢市○○路354 號房屋（該屋係於41年7 月間由\n    訴外人劉源慶出賣予訴外人吳金妹，可見該屋早於41年間即\n    存在），係坐落中壢市○○段中壢老小段14-1地號土地，是\n    由被告巫乾正之父巫振鐮繼承而得。被告巫乾正之父巫振鐮\n    先於53年8 月26日受贈於訴外人吳進發持分2 分之1 ，再於\n    55年3 月15日自訴外人吳鄧桂菊買受持分2 分之1 。至於房\n    屋基地一直是向地主陳水模承租，並繳納租金，直到陳水模\n    過世後始由其繼承人陳文毅收取租金。嗣因本案被訴，被告\n    始知悉陳水模、陳文毅共有系爭土地應有部分5 分之1 ，對\n    於土地另有其他共有人被告完全不知情，故退步言之，倘使\n    陳水模、陳文毅無權將系爭土地出租，然由被告所有之房屋\n    早於41年間即已存在，可以推定迄今系爭土地出租已超過50\n    餘年，一直均是由陳水模、陳文毅以地主身份而一脈相承，\n    其不但與被告訂立租約、協調租金數額，且按期收取租金，\n    對被告而言，陳文毅即是地主之代表，依民法第169 條規定\n    被告與陳水模、陳文毅訂立之租約亦是合法有效。系爭土地\n    出租予被告建築房屋有合法之租約，則依土地法第103 條規\n    定，本案原告並不可將土地收回。並聲明：原告之訴及假執\n    行之聲請均駁回；如受不利益判決，願供擔保請准宣告免為\n    假執行。\n四、被告黃張滿妹、黃美華、黃嘉生、黃河、黃雅英則以：\n（一）系爭被告等所共有建於原告繼承土地上之建物，經查至遲\n      建於日據時期之27年間，故斯時臺灣地區仍適用日本國民\n      法。復按系爭「中壢市○○段中壢老小段14-2地號」土地\n      於日據時期之原所有人為張詹氏冉妹，嗣張詹氏冉妹於昭\n      和6 年1 月14日將所有權一部分轉予張新鐘，於昭和8 年\n      （即民國22年）9 月5 日張詹氏冉妹與張新鐘二人將所有\n      權移轉予陳有定及「陳水模」共有（陳水模應有部分為五\n      分之一），於37年9 月23日陳有定將其應有部分移轉予「\n      陳蘇」（陳蘇應有部分為五分之四），此有日據時期\n      之土地臺帳本可稽。基此，於37年後系爭土地業由陳蘇\n      及陳水模所共有。而被告之被繼承人黃志文建屋後均按期\n      繳納基地租金於基地所有人，於22年陳水模取得系爭土地\n      所有權後即收受地租，嗣於37年陳蘇取得土地後，亦委\n      託陳水模收取地租，故其後系爭土地均由陳水模以地主暨\n      經陳蘇授權之身分向黃志文收取基地租金迄今，而陳水\n      模亦以同樣模式向同案其他被告收取基地租金。系爭房屋\n      於陳蘇取得土地時早已存在十餘年，況陳蘇乃以「買\n      賣」方式取得土地所有權，故依常理論，陳蘇於買受土\n      地時，誠不可能不知當時土地之使用現況為何。又陳水模\n      為陳蘇與配偶陳番所生，雖將陳水模出養給陳番之兄弟\n      陳泰，但原告亦自承出養未久陳泰即亡故，從而陳水模於\n      養父死亡後自幼仍由親生父母撫養，此何以原告亦自承常\n      看到陳水模在陳蘇家裡，甚至陳水模之戶籍始終設於龜\n      山，迨陳水模日後遷至坐落於系爭土地相鄰之中壢市○○\n      路352 號居住，而陳番亦曾至該住處與陳水模同住，加以\n      原告自承陳蘇往生後，系爭土地即由陳番管理，故陳番\n      亦自明知陳蘇所遺留之系爭土地有本件多位被告建屋於\n      上許久（陳蘇44年7 月亡、陳番67年8 月亡），歷經二\n      十餘年間陳番不可能不知由其子陳水模代為管理系爭土地\n      並收取租金之事實。另陳水模早於陳蘇取得系爭土地之\n      共有權，而系爭建物於陳水模取得土地後幾年始建蓋，且\n      房屋建蓋後陳水模即開始收取地租至84年間，加以陳蘇\n      之配偶即陳水模之生父陳番係於67年8 月間始亡故，而陳\n      番即設籍住於被告之隔壁（中壢市○○路352 號），故陳\n      蘇夫婦實不可能不知其所共有之土地已由被告建屋於其\n      上，甚至由其子陳水模出面代表地主收取租金數十年不間\n      斷。另系爭土地依當時之環境乃位於中壢之市區中心，非\n      屬郊區或偏僻不毛之地，且就本件訟爭各筆土地，依當時\n      之經濟狀況論，每年向建物所有人收取之租金總數亦可觀\n      ，矧占有土地持分五分之四之陳蘇更不可能就自己之土\n      地任由他人無權占有使用，故茲有陳蘇之子陳水模以土\n      地管理人或代理人身份向建物所有人收取租金，亦符常情\n      。況陳水模亦曾以陳蘇管理人之身分寄存證信函予黃志\n      文要求調整租金。\n（二）訴外人陳有定與陳水模於日據時期之昭和8 年（即民國22\n      年）取得系爭土地所有權，而系爭建物於日據時期之昭和\n      13年（民國27年）即建於系爭土地上，故當時土地及建物\n      之法律關係應依日本國之相關法律而定之，而依日本國《\n      關於地上權之法律》第1 條、最高法院72年台上字第136\n      號判決規定，當時日本國物權法乃採「意思主義」，以當\n      事人之意思表示即可成立生效，且在他人土地為所有工作\n      物而使用其土地之人推定為地上權人，故得知系爭建物所\n      有人於昭和13年即應取得地上權，從而黃志文既為系爭建\n      物之所有權人，依日本國民法規定即就系爭土地具有正當\n      使用權源。縱另一共有人即原告之被繼承人陳蘇於37年\n      取得系爭土地所有權，然依物權之「對世效力」，黃志文\n      自仍可對陳蘇主張地上權。遑論黃志文均有支付基地租\n      金予陳水模與陳蘇二人。退步言之，本件黃志文之地上\n      權縱有自始或嗣後不存在之事由，然系爭土地共有人之一\n      陳水模均以系爭土地管理人之身分向黃志文收取基地租金\n      迄今已數十年，則黃志文與系爭土地所有人間就系爭土地\n      存有基地租賃契約，故黃志文使用系爭土地亦具有使用權\n      源。退萬步言之，本件就陳水模以系爭土地共有人之管理\n      人身份向黃志文收取基地租金之行為可議，然細究陳蘇\n      自知其所共有之土地有黃志文建屋於上，復陳蘇之配偶\n      陳番亦住於相鄰土地上，且陳水模為陳番與陳蘇所生之\n      子，則陳水模對外以陳蘇代理人或管理人之名義向建物\n      所有人收取租金應為陳蘇所知悉，然陳蘇對此卻始終\n      均未表示反對意見，從而被告等自可主張民法第169 條之\n      表見代理之法律效果，故黃志文使用系爭土地亦具正當使\n      用權源。\n（三）陳水模取得系爭土地所有權後，被告之被繼承人黃志文始\n      建屋於上，且其後陳水模均代表地主至黃志文住處收取租\n      金，故系爭租金清償方式屬於往取債務，乃陳水模生前均\n      依此方式收取租金，然於85年起陳水模即因故未再向黃志\n      文收租，然黃志文為保權益乃多次催告陳水模與陳蘇之\n      繼承人收租，此有85年至98年之存證信函可稽。因陳水模\n      受催告後仍未出面收取租金，黃志文乃於99年4 月間依民\n      法第326 條規定將最近五年（至99年度）之基地租金向臺\n      灣桃園法院提存，故提存後即生清償效力。被告既先催告\n      債權人領取組金，且於債權人受領遲延時依法將應為之給\n      付物提存，故本件被告並無遲延給付租金或其他違約之情\n      ，從而原告主張依土地法第103 條第4 、5 款所定之事由\n      終止租約，亦無所據。並聲明：原告之訴及假執行之聲請\n      均駁回；如受不利益判決，願供擔保請准免為假執行。\n三、兩造不爭執事項：\n（一）訴外人陳蘇已於44年7 月30日死亡，原告為陳蘇之繼\n      承人。訴外人葉陳玉嬌為陳蘇之繼承人，葉陳玉嬌已於\n      98年10月7 日死亡，原告葉王沅、葉月寶、葉美娜為葉陳\n      玉嬌之繼承人。\n（二）坐落桃園縣中壢市○○路354 號係爭房屋屬於巫乾正、巫\n      廖惠所有；356 號係爭房屋屬於張滿妹、黃河、黃雅英、\n      黃美華、黃嘉生等人所有；362 、364 號係爭房屋屬於劉\n      振權所有；而係爭建物分別坐落於如桃園縣中壢地政事務\n      所99年12月21日之土地複丈成果圖所示之地號土地及面積\n      。\n（三）原告與訴外人陳文毅為系爭土地之共有人，訴外人陳文毅\n      之應有部分為2/10。原告等人就系爭土地之應有部分合計\n      為8/10 。\n四、本院得心證理由：\n（一）按訴外人陳水模出養予其叔叔陳泰後，由於養父不久隨即\n      死亡，因此返回本生父母處與本生父母即陳蘇與陳番共\n      同生活，業據陳水模之子陳文毅到庭證述明確（詳見本院\n      卷二第180-181 頁）。且陳水模之戶籍地原設與陳番及陳\n      蘇相同之龜山鄉○路村○○路坑21號，嗣於38年12月28\n      日與陳簡鬆結婚，至41年8 月1 日始遷至中壢鎮中壢里2\n      鄰中壢25號；而陳蘇於42年12月24日亦遷移至中壢鎮中\n      壢里2 鄰中壢25號陳水模之住處，此有戶籍謄本在卷可稽\n      。可見陳水模雖出養其叔叔陳泰，然事實上均是與本生父\n      母陳蘇與陳番共同生活互相照顧。又陳水模與陳蘇與\n      陳番共同設籍於龜山，依戶籍記載父母親為陳蘇與陳番\n      ，然於40年7 月14日始聲請更正為陳泰之養子，因此在40\n      年7 月14日前陳水模戶籍上記載之父母為陳蘇與陳番，\n      嗣於40年7 月14日始申請更正為陳泰之養子，此有戶籍謄\n      本在卷可稽。然一般外人豈可能知悉如此私人隱私之資料\n      ，且長期以來在外人眼裡陳水模即陳蘇與陳番之子女，\n      所以被告等一如往常均認為陳水模代表陳蘇與陳番之權\n      限，應可採信。\n（二）被告劉鼎泰之祖父劉阿昂於39年9 月15日與陳水模、陳蘇\n      簽立租借地權契約證書（詳見本院卷一第122 頁），原\n      告雖然否認其真正性，然當時之土地所有權人為陳水模、\n      陳蘇所有，且如前述陳水模與陳蘇、陳番均有往來甚\n      至共同生活，且當時戶籍謄本上陳水模與陳蘇、陳番是\n      為父母子女之登載，另契約書上記載之住址，與陳蘇、\n      陳水模當時之住址相符；因此對於渠等共有土地相信渠等\n      應該知悉處理之情況，可見係爭租界地權契約書，確實係\n      陳蘇與陳水模所簽立。而被告劉鼎泰所提出由訴外人陳\n      水模收取租金之收據（詳見本院卷一第123-129 頁、院二\n      第187 、188 頁），衡諸常情，陳水模與陳蘇既然共同\n      簽訂租借地權契約書，且為陳蘇子女，豈可能不幫陳蘇\n      收取租金，因此縱然陳水模收取租金之收據沒有代表或\n      代理陳蘇之字眼，然陳水模所收取之租金應包涵陳蘇\n      部分，故被告主張陳水模代表或代理陳蘇收取租金應為\n      可採。縱然陳文毅證稱：有向巫乾正及劉政權收取租金，\n      是根據父親告知，伊看父親之前簽收的收據多少，伊就收\n      多少，伊認為只是收取伊的持份部分。其僅是收取其應有\n      部分，其父親收取多少其就收取多少，其不知伊父親有無\n      幫忙陳蘇租金等語（詳見本院卷二第180 頁至181 頁）\n      ，由於陳文毅不知陳水模是如何與巫乾正、劉鼎泰約定租\n      金，僅是依照之前收取多少即收取多少。然既然依照前述\n      ，陳水模收取的租金包函陳蘇部分，則陳文毅收取的租\n      金亦包函陳蘇及原告等之部分。故被告等主張陳文毅收\n      取的租金應包函原告等之部分，應為可採。\n（三）訴外人陳番（即原告等人之被繼承人、陳蘇之配偶）與\n      被告劉鼎泰之祖父劉阿昂曾就係爭土地之租金於47年6 月\n      27日成立和解筆錄，此有和解筆錄在卷可稽（詳見本院卷\n      二第196 頁），而渠等成立和解筆錄後，劉阿昂就係爭土\n      地之租金亦係給付給陳水模，可見陳水模當時收取租金時\n      ，不僅就其所有部份，就陳蘇部分亦應一同收取，因為\n      當時縱然陳水模出養，然其依然與本生父母即陳蘇及陳\n      蕃共同生活，豈可能僅收取名下之租金，而對於陳蘇名\n      下之租金棄之不顧，顯與常情有違。且當陳蘇往生後，\n      其名下土地由陳番管理（當時並未辦理繼承登記，但實際\n      上陳番以繼承人之地位在管理系爭土地），陳番既然與劉\n      阿昂成立租金調高之和解書，豈可能沒有要求被告等繳交\n      租金；然被告等均沒有陳番具名之收據，而僅有陳水模具\n      名之收據，可見陳水模所收取租金亦應包涵名下之部分（\n      既然之前包函陳蘇部分，則衡諸常情，在沒有其他繼承\n      人出面主張有不同意見前，被告等繼續認為陳水模有代理\n      處理收取租金之權限，亦符合常情）。從而，陳水模收取\n      被告等所繳納之租金，自始即包函陳蘇名下部分，不論\n      陳蘇往生後係爭土地由陳番管理之時期亦是如此。故陳\n      水模向被告等收取之租金，在陳蘇往生後之時期，亦包\n      函陳蘇名下部份之租金。\n（四）陳水模亦曾以兼具有陳蘇管理人之身分於80年9 月26日\n      曾發函黃志文告知要提高租金為每年627,976 元，此有存\n      證信函在卷可稽（詳見本院卷二第79頁）；陳番於67年8\n      月30日往生，其往生後就陳蘇名下之土地全體繼承人均\n      未處理，而陳水模在陳番往生後，一如往常的對被告等收\n      取租金，則被告等亦一如往常的認為渠等所交付的租金，\n      包函屬於陳蘇名下之部分，應屬可採。而原告等雖均為\n      陳蘇之繼承人，然陳蘇之長子陳佳猷於86年1 月10日\n      才往生，在此之前為何共有人（繼承人）均未對被告等主\n      張任何權利，而是待95年5 月10日辦理繼承之後再向被告\n      等主張無權占有？在陳佳猷尚建在時，為何沒有對被告等\n      主張任何權利？因此於陳番往生後（即67年8 月30日）至\n      陳佳猷往生前（86年1 月10日）間，可見陳佳猷亦同意由\n      陳水模來管理系爭土地並收取租金，否則陳佳猷豈可能沒\n      有對被告等主張任何權利；再者，陳蘇名下之土地，在\n      陳蘇往生後，其繼承人到底有誰？依照法律規定與一般\n      民間習俗或許截然不同；且強求被告等去查詢資料來釐清\n      陳蘇之繼承人到底是何人，顯係強人所難之事，而被告\n      等亦無此義務。故被告等一如往常的認為陳水模繼續有代\n      理陳蘇之繼承人收取租金之權限，應為可採。\n（五）由巫乾正所提出陳水模及陳文毅所簽立之收據（詳見本院\n      卷一第139-140 頁；卷二第96-102頁）；再者係爭房屋房\n      屋稅之起課時間為16年1 月間（詳見本院卷二第103 頁）\n      ，顯見被告巫乾正、巫廖會部分，均無積欠租金之情形。\n      另由劉鼎泰所提出陳水模所簽立之收據（詳見本院卷二18\n      7 、188 頁、卷0000-000 頁），陳文毅所簽立之收據（\n      詳見本院卷一第12 9頁），可見被告劉振權部分亦無積欠\n      租金之情形。再者，由於被告黃張滿妹等5 人部分之房屋\n      於27年1 月即起課（詳見本院卷一第160 頁），且陳水模\n      亦均有向其收取租金（詳見本院卷二第55-78 頁），收取\n      到83年11月30日，雖然陳水模曾於80年9 月26日曾發文要\n      求提高租金費用，然或許兩造未達成協議，而被告自85年\n      12月2 日起每年均以存證信函加計支票涵文給陳水模；另\n      自87年10月1 日起則以存證信函催告陳水模到其住處收取\n      租金，直至96年12月3 日為止。則被告黃張滿妹等5 人部\n      份亦無積欠租金之情事。從上可知，被告等均無積欠原告\n      等，而有租金未繳之情事。\n（六）按由自己之行為表示以代理權授與他人，或知他人表示為\n      其代理人而不為反對之表示者，對於第三人應負授權人之\n      責任，民法第169 條前段雖定有明文。然由自己之行為表\n      示以代理權授與他人者，對於第三人應負授權人之責任，\n      必須本人有表見之事實，足使第三人信該他人有代理權之\n      情形存在，始足當之。我國人民將自己印章交付他人，委\n      託該他人辦理特定事項者，比比皆是，倘持有印章之該他\n      人，除受託辦理之特定事項外，其他以本人名義所為之任\n      何法律行為，均須由本人負表見代理之授權人責任，未免\n      過苛。原審徒憑上訴人曾將印章交付與呂某之事實，即認\n      被上訴人就保證契約之訂立應負表見代理之授權人責任，\n      自屬率斷（最高法院70年台上字第657 號判例意旨參照）\n      。又民法第169 條所謂知他人表示為其代理人而不為反對\n      之表示者，以本人實際知其事實為前提，其主張本人知此\n      事實者，應負舉證之責（最高法院68年台上字第1081號判\n      例意旨參照）。被告等辯稱與陳水模、陳蘇成立租借地\n      權契約書或者對於渠等建物坐落土地與地主成立租賃契約\n      ，陳水模收取之租金包函陳蘇之部分，故陳蘇及陳蘇\n      之繼承人應負表見代理人之責任云云。經查：\n  １、在陳水模與陳蘇（往生前）之時段：如前述，陳水模與\n      陳蘇、陳番亦如父母子女，則陳水模代表二人來收取被\n      告等租賃土地之租金，而陳蘇亦無提出異議，被告等也\n      均有繳納租金，顯見陳水模有代理陳蘇收取租金之權限\n      及情事。\n  ２、在陳水模與陳番（往生前）之時段：在陳蘇往生後，陳\n      番曾與劉阿昂成立租金調解筆錄，而期後之租金，仍由陳\n      水模繼續向被告等收取，則被告等信賴陳水模有代理陳蘇\n      之繼承人收取陳蘇名下土地租金之權限，亦為可採。\n  ３、在陳水模與陳番往生後之時段：在陳番往生後，陳水模繼\n      續向被告等收取渠等租地之租金，而未有其他繼承人出面\n      向被告等主張陳水模並未有如此代理權之前提下，被告等\n      依然認為陳水模有代理權並且繼續繳納租金，則被告等主\n      張陳水模有代理原告等收取租金之權限，應為可採。且原\n      告等亦不否認，未曾向被告等催告收取租金，直至提起本\n      件訴訟為止。或者一直到原告於本院對被告陳梁美靜等人\n      提起96年度訴字第413 號拆屋還地等案時，才知道原告等\n      人係陳蘇之繼承人。\n  ４、從而，原告等主張陳水模對於陳蘇並未有表現代理之情\n      況，亦未有代理陳蘇收取租金之情事及權限，顯無足採\n      。不論被告等之被繼承人取得所有之建物係早於陳蘇取\n      得係爭土地所有權之前或者之後，在陳蘇取得土地所有\n      權後，陳蘇對於陳水模代理其向被告等或渠等之被繼承\n      人收取租地租金時，並未有明確之反對陳水模沒有代理權\n      ，且當時陳水模為陳蘇之子女，外人亦容易認為陳水模\n      有代理陳蘇收取租金之權限，因此有表現代理之情事；\n      則在陳蘇往生後，未有其他繼承人出面主張陳水模未有\n      代理其他繼承人收取租金之權限前，被告等繼續認為陳水\n      模有代理之權限，而繼續繳納租金，則陳水模與陳蘇繼\n      承人間亦存有表現代理之情況；則被告等主張陳水模收取\n      之租金，包含陳蘇部分及原告等繼承人之部分，應為可\n      採。另被告等既依照先前兩造租約之約定繼續繳納租金，\n      未有遲延繳納租金之情事，原告另主張被告等有未繳納租\n      金之情事，亦無足採。\n六、綜上所述，被告等主張渠等並非無權占有原告等及被繼承人\n    陳蘇名下之土地，而係存有租賃關係，為可採信。則原告\n    本於所有權主張被告等無權占有應返還渠等建物所占有之土\n    地及基於不當得利法律關係請求被告等應給付相當於租金之\n    不當得利數額，均為無理由，均應予駁回。原告之訴既經駁\n    回，其假執行之聲請亦失所附麗，併予駁回。\n七、本件事證已臻明確，兩造其餘主張陳述及所提之證據，經審\n    酌與本院前揭判斷無影響，毋庸一一論述，附此敘明。\n八、據上論結，原告之訴為無理由，依民事訴訟法第78，判決如\n    主文。",
    "reason": "壹、程序方面：\n    按訴狀送達後，原告不得將原訴變更或追加他訴，但有請求\n    之基礎事實同一、擴張或減縮應受判決事項之聲明、不甚礙\n    被告之防禦及訴訟之終結情形者，不在此限，民事訴訟法第\n    255 條第1 項但書第2 款、第3 款、第7 款分別定有明文。\n    查原告起訴時訴之聲明為：「(一)被告應將如附圖1 所示土地\n    上之地上物拆除（占有土地面積、地上物門牌號碼均約如附\n    圖1 附表所示，實際位置及面積請鈞院囑託地政機關測量後\n    為準），並將土地返還予原告及其他共有人。(二)被告應各給\n    付原告如附表2 第(五)欄所示金額，及自起訴狀繕本送達翌日\n    起迄清償日止，按年息百分之五計算之利息。(三)被告各應給\n    付自99年3 月1 日起迄第一項所示土地交還原告及其他共有\n    人之日，各按年給付原告如附表2 第(七)欄所示金額。(四)願供\n    擔保請准宣告假執行。」。嗣於民國100 年2 月14日具狀追\n    加巫廖會為被告，並變更聲明為：「(一)請令被告應將如下所\n    述土地上之地上物拆除（占有土地面積、地上物門牌號碼均\n    如附圖１所示），並將土地返還予原告及其他共有人。1.請\n    令被告巫乾正、巫廖會應將如附圖1 所示中壢市○○段中壢\n    老小段第11-15 地號上標示11-15 （B ）3 ㎡、14 -1 地號\n    上標示14-1（B ）129 ㎡，面積合計為132 ㎡之土地上門牌\n    號碼為中壢市○○路354 號地上物予以拆除，並將土地返還\n    予原告及其他共有人。2.請令被告黃張滿妹、黃河、黃雅英\n    、黃美華、黃嘉生等人將如附圖1 所示中壢市○○段中壢老\n    小段第14-2地號土地上標示14-2（A ）122 ㎡，面積合計12\n    2 ㎡之土地上門牌號碼為中壢市○○路356 號地上物予以拆\n    除，並將土地返還予原告及其他共有人。3.請令被告劉振權\n    將如附圖1 所示中壢市○○段中壢老小段第14-5地號土地上\n    標示14 -5 （A ）109 ㎡及同地段土地第14-6地號土地上標\n    示14-6（A ）28㎡，面積合計137 ㎡之土地上門牌號碼為中\n    壢市○○路362 號地上物予以拆除，並將土地返還予原告及\n    其他共有人。4.請令被告劉振權將如附圖1 所示中壢市○○\n    段中壢老小段第14-6地號土地上標示14-6（C ）46㎡，面積\n    合計46㎡之土地上門牌號碼為中壢市○○路364 號地上物予\n    以拆除，並將土地返還予原告及其他共有人。(二)被告各應給\n    付各原告等如附表２第(五)欄所所示金額，及自起訴狀繕本送\n    達之翌日起迄清償日止，按年息百分之五計算之利息。(三)被\n    告各應自99年3 月1 日起迄第一項所示土地交還原告及其他\n    共有人之日，各按年給付各原告如附表２第(七)欄所示金額。\n    (四)原告願供擔保，請准宣告假執行。」，核原告追加被告巫\n    廖會部分，核其請求之基礎事實與起訴之事實同一，且不甚\n    礙被告之防禦及訴訟之終結；又變更拆除及返還土地面積部\n    分，係擴張或減縮應受判決事項之聲明；揆諸前揭法律規定\n    ，均應予准許。\n貳、實體方面：\n一、原告起訴主張：\n（一）原告乃被繼承人陳蘇之全體繼承人，而原告之被繼承人\n      陳蘇乃坐落桃園縣中壢市○○段中壢老小段14-1、11-1\n      5 、14-2、14-5、14-6地號土地（下稱系爭土地）之所有\n      權人之一，所佔持分為十分之八，而陳蘇於44年7 月30\n      日過世後，原告當然繼承被繼承人之系爭土地之產權，雖\n      遲至95年5 月10日方辦理繼承登記，惟基於繼承法理原告\n      於44年7 月30日後即取得系爭土地之所有權。原告為系爭\n      土地之共有人，被告未經原告及其他共有人同意，擅自在\n      原告所有之系爭土地上興建建物，核其所為顯然係無權占\n      用原告所共有之土地，爰依民法第821 條及第767 條規定\n      ，訴請被告除去妨害及返還所有物予所有人全體，又無權\n      占有他人土地可獲得相當於租金之利益，被告無權占用系\n      爭土地，致原告對之無法使用收益，被告顯屬無法律上之\n      原因而受利益致原告受有損害，原告自得依民法第179 條\n      及最高法院61年台上字第1695號判例之規定，請求被告返\n      還起訴前五年起至返還土地之日止相當於租金之不當得利\n      。\n（二）對被告答辯之陳述：\n  １、否認兩造間有租賃關係存在，也否認被告等所繳給陳水模\n      之租金，即為被告等所占用土地之租金。\n  ２、被告等除劉鼎泰外，其屋況均已老舊，顯見渠等明知為無\n      權占有他人土地，故無積極翻修，聽憑屋況老舊之貌。\n  ３、被告等所提示之收據均無陳蘇或原告等任何一人之簽名\n      或蓋章，且原告之被繼承人陳蘇乃於44年即過世，而被\n      告所提出之收據均係陳蘇死亡後之收據，並無原告等合\n      法繼承人所立之文件，而原告並無委託或授權陳水模出租\n      土地或收取租金。陳水模並非陳蘇之繼承人，陳水模或\n      其子陳文毅無由代理或代表陳蘇或原告，且土地乃公示\n      主義，任何人均可透過地政機關查閱系爭土地所有權人為\n      何，從而並無表見代理成立之餘地。另有關共有物之租賃\n      ，實務及學說均係對共有物之「管理行為」，而系爭土地\n      之共有人含原告等迄今未分割，而被告承租系爭土地亦未\n      曾得到身為共有人之原告之同意，依民法第828 條、第82\n      0 條第1 項規定，縱認被告與系爭土地之5 分之1 共有人\n      陳水模就系爭土地有租賃關係，惟該共有人所為之管理行\n      為（出租）乃屬無效，故被告占有系爭土地仍屬無權占有\n      。被告巫乾正、巫廖會二人所有之系爭房屋係自其被繼承\n      人巫振鐮繼承而得，而巫振鐮乃於陳蘇死後於55年間才\n      於第三人處取得系爭房屋之事實上處分權，亦證渠等係無\n      權占用系爭土地。\n  ４、原告否認陳水模為被繼承人陳蘇之子孫輩財產管理人。\n      系爭土地於陳蘇死亡後係由其夫陳番管理，而陳番死亡\n      後因無人管理，故系爭土地因無人繳納稅捐於64年遭稅捐\n      機關查封，至95年時財稅單位向原告等寄交繳稅通知，原\n      告始一次性繳納500 多萬元之地價稅，足證此間並未曾出\n      現由陳水模代表原告處理系爭土地全部之情形。被告劉鼎\n      泰亦辯稱陳蘇死亡後係由陳番管理系爭土地，則被告應\n      繳納租金之對象即為陳番，而非陳水模，亦證被告辯稱陳\n      水模代表原告出租系爭土地及向渠等收取租金之事實乃不\n      實在。\n  ５、被告劉鼎泰所提出之「租借地權契約證書」其上之陳蘇\n      與陳水模之筆跡相同，顯然並非陳蘇所親簽之契約，故\n      原告亦否認該契約書乃出於陳蘇之承諾或合意。縱被告\n      劉鼎泰對系爭土地有基地租賃，惟因被告劉鼎泰始終未繳\n      付應有之租金予陳蘇或原告（被告從未提示陳蘇及原\n      告等人所立之任何租金收據），並將系爭房屋轉租圖利，\n      又違反租賃契約將系爭房屋全面改建，原告爰依土地法第\n      103 條第1 項第3 、4 、5 款為由，向被告劉鼎泰為終止\n      租賃契約之意思表示，並以本訴狀之送達為終止租賃意思\n      表示送達之時。\n  ６、被告黃河等五人自認其進駐系爭房屋乃44年以後之事情，\n      其父黃志文係後來所購及進駐系爭房屋，當時原告被繼承\n      人陳蘇已經過世，故被告之被繼承人黃志文與原告之被\n      繼承人無從成立地上權之物權及基地之租賃契約。而被告\n      所提日據時期地籍謄本與二造及本件並無關係。蓋有關上\n      開日據時期謄本所載之權利人為訴外人張詹氏冉妹，並無\n      記載為後手為權利人。尤以被告既抗辯其等有日據時代之\n      地上權，從而謹請被告先提呈其係地上權人之登記權利人\n      及日據時代其等已進駐系爭房屋之證明。縱退萬步言，假\n      若被告黃河等五人對系爭土地有基地租賃或所謂地上權之\n      關係（非表自認），惟因被告始終未繳付應有之地租予原\n      告及原告之被繼承人，原告先前即依土地法第103 條規定\n      第1 項第4 款、第5 款為由向被告為終止租賃契約之意思\n      表示，並以民法第836 條之規定撤銷被告所謂之地上權，\n      並以該狀之送達為意思表示送達之時。\n（三）並聲明：如前開變更聲明所示。\n二、被告劉鼎泰則以：被告占有、使用系爭土地乃因被告之祖父\n    劉阿昂前於39年即與原告之被繼承人陳水模、陳蘇二人訂\n    有「租借地權契約書」，依該契約書第五點記載，租約之存\n    續期間為「不限年」，故被告基於繼承原因取得系爭土地之\n    承租權而占有、使用系爭土地，實有合法權源。陳水模及其\n    子陳文毅亦基於該契約書而向被告之祖父與被告收取租金，\n    該基地租賃法律關係確係存在，不容原告隨意否認。原告對\n    該租借地權契約書不否定其真實性，僅認為並非陳蘇本人\n    簽字，及非出於陳蘇之承諾或合意，惟該契約書之簽訂後\n    至44年7 月30日陳蘇往生為止，約五年期間被告均繼續繳\n    租，陳蘇並無反對之意思表示，故原告所提並非事實，純\n    屬臆測。被告已繳清至98年5 月31日之地租，至今尚未滿二\n    年，故並不符和土地法第103 條第4 款終止租約之規定，且\n    由以往至今被告一律繳足額之租金，並非繳交1/5 之租金，\n    並由陳水模及其後人陳文毅代為收取，並提出37、38年陳蘇\n    尚未死亡前即全權委託陳水模代收租金之收據，足證從陳\n    蘇在世時即委託陳水模代收租金。又被告為租地建屋，所\n    租為被告本人及祖父劉阿昂所有之房屋，並未違反「租借地\n    權契約書」內之規定，且被告全家亦長期居住於此，並無將\n    租地轉租他人之情形，與土地法第103 條第3 、5 款規定不\n    符。另陳水模、陳蘇係共同出租人，其二人秉於該「租借\n    地權契約書」對於被告本得為全部租金給付之請求，故屬連\n    帶債權。因而，被告基於繼承原因取得系爭土地之承租權後\n    ，除中山路364 號房屋仍登記為劉阿昂所有外，362 號房屋\n    則登記於被告劉鼎泰名下，被告並依租約約定繳納租金於出\n    租人陳水模之繼承人陳文毅，依民法第284 條規定被告給付\n    租金於連帶出租人之一陳水模及其繼承人陳文毅自屬適法有\n    效，此亦無涉於陳蘇是否委託陳水模或其繼承人陳文毅代\n    理或代表受取租金。另民法第820 條係屬共有人內部對於共\n    有物管理之同意，而本件租賃關係原本即存在於土地所有權\n    人陳水模與陳蘇，故民法第820 條規定無涉於本件租賃關\n    係等語置辯。並聲明：原告之訴及其假執行聲請均駁回：如\n    受不利益判決，願供擔保請准宣告免為假執行。\n三、被告巫乾正、巫廖會則以：\n    被告所有中壢市○○路354 號房屋（該屋係於41年7 月間由\n    訴外人劉源慶出賣予訴外人吳金妹，可見該屋早於41年間即\n    存在），係坐落中壢市○○段中壢老小段14-1地號土地，是\n    由被告巫乾正之父巫振鐮繼承而得。被告巫乾正之父巫振鐮\n    先於53年8 月26日受贈於訴外人吳進發持分2 分之1 ，再於\n    55年3 月15日自訴外人吳鄧桂菊買受持分2 分之1 。至於房\n    屋基地一直是向地主陳水模承租，並繳納租金，直到陳水模\n    過世後始由其繼承人陳文毅收取租金。嗣因本案被訴，被告\n    始知悉陳水模、陳文毅共有系爭土地應有部分5 分之1 ，對\n    於土地另有其他共有人被告完全不知情，故退步言之，倘使\n    陳水模、陳文毅無權將系爭土地出租，然由被告所有之房屋\n    早於41年間即已存在，可以推定迄今系爭土地出租已超過50\n    餘年，一直均是由陳水模、陳文毅以地主身份而一脈相承，\n    其不但與被告訂立租約、協調租金數額，且按期收取租金，\n    對被告而言，陳文毅即是地主之代表，依民法第169 條規定\n    被告與陳水模、陳文毅訂立之租約亦是合法有效。系爭土地\n    出租予被告建築房屋有合法之租約，則依土地法第103 條規\n    定，本案原告並不可將土地收回。並聲明：原告之訴及假執\n    行之聲請均駁回；如受不利益判決，願供擔保請准宣告免為\n    假執行。\n四、被告黃張滿妹、黃美華、黃嘉生、黃河、黃雅英則以：\n（一）系爭被告等所共有建於原告繼承土地上之建物，經查至遲\n      建於日據時期之27年間，故斯時臺灣地區仍適用日本國民\n      法。復按系爭「中壢市○○段中壢老小段14-2地號」土地\n      於日據時期之原所有人為張詹氏冉妹，嗣張詹氏冉妹於昭\n      和6 年1 月14日將所有權一部分轉予張新鐘，於昭和8 年\n      （即民國22年）9 月5 日張詹氏冉妹與張新鐘二人將所有\n      權移轉予陳有定及「陳水模」共有（陳水模應有部分為五\n      分之一），於37年9 月23日陳有定將其應有部分移轉予「\n      陳蘇」（陳蘇應有部分為五分之四），此有日據時期\n      之土地臺帳本可稽。基此，於37年後系爭土地業由陳蘇\n      及陳水模所共有。而被告之被繼承人黃志文建屋後均按期\n      繳納基地租金於基地所有人，於22年陳水模取得系爭土地\n      所有權後即收受地租，嗣於37年陳蘇取得土地後，亦委\n      託陳水模收取地租，故其後系爭土地均由陳水模以地主暨\n      經陳蘇授權之身分向黃志文收取基地租金迄今，而陳水\n      模亦以同樣模式向同案其他被告收取基地租金。系爭房屋\n      於陳蘇取得土地時早已存在十餘年，況陳蘇乃以「買\n      賣」方式取得土地所有權，故依常理論，陳蘇於買受土\n      地時，誠不可能不知當時土地之使用現況為何。又陳水模\n      為陳蘇與配偶陳番所生，雖將陳水模出養給陳番之兄弟\n      陳泰，但原告亦自承出養未久陳泰即亡故，從而陳水模於\n      養父死亡後自幼仍由親生父母撫養，此何以原告亦自承常\n      看到陳水模在陳蘇家裡，甚至陳水模之戶籍始終設於龜\n      山，迨陳水模日後遷至坐落於系爭土地相鄰之中壢市○○\n      路352 號居住，而陳番亦曾至該住處與陳水模同住，加以\n      原告自承陳蘇往生後，系爭土地即由陳番管理，故陳番\n      亦自明知陳蘇所遺留之系爭土地有本件多位被告建屋於\n      上許久（陳蘇44年7 月亡、陳番67年8 月亡），歷經二\n      十餘年間陳番不可能不知由其子陳水模代為管理系爭土地\n      並收取租金之事實。另陳水模早於陳蘇取得系爭土地之\n      共有權，而系爭建物於陳水模取得土地後幾年始建蓋，且\n      房屋建蓋後陳水模即開始收取地租至84年間，加以陳蘇\n      之配偶即陳水模之生父陳番係於67年8 月間始亡故，而陳\n      番即設籍住於被告之隔壁（中壢市○○路352 號），故陳\n      蘇夫婦實不可能不知其所共有之土地已由被告建屋於其\n      上，甚至由其子陳水模出面代表地主收取租金數十年不間\n      斷。另系爭土地依當時之環境乃位於中壢之市區中心，非\n      屬郊區或偏僻不毛之地，且就本件訟爭各筆土地，依當時\n      之經濟狀況論，每年向建物所有人收取之租金總數亦可觀\n      ，矧占有土地持分五分之四之陳蘇更不可能就自己之土\n      地任由他人無權占有使用，故茲有陳蘇之子陳水模以土\n      地管理人或代理人身份向建物所有人收取租金，亦符常情\n      。況陳水模亦曾以陳蘇管理人之身分寄存證信函予黃志\n      文要求調整租金。\n（二）訴外人陳有定與陳水模於日據時期之昭和8 年（即民國22\n      年）取得系爭土地所有權，而系爭建物於日據時期之昭和\n      13年（民國27年）即建於系爭土地上，故當時土地及建物\n      之法律關係應依日本國之相關法律而定之，而依日本國《\n      關於地上權之法律》第1 條、最高法院72年台上字第136\n      號判決規定，當時日本國物權法乃採「意思主義」，以當\n      事人之意思表示即可成立生效，且在他人土地為所有工作\n      物而使用其土地之人推定為地上權人，故得知系爭建物所\n      有人於昭和13年即應取得地上權，從而黃志文既為系爭建\n      物之所有權人，依日本國民法規定即就系爭土地具有正當\n      使用權源。縱另一共有人即原告之被繼承人陳蘇於37年\n      取得系爭土地所有權，然依物權之「對世效力」，黃志文\n      自仍可對陳蘇主張地上權。遑論黃志文均有支付基地租\n      金予陳水模與陳蘇二人。退步言之，本件黃志文之地上\n      權縱有自始或嗣後不存在之事由，然系爭土地共有人之一\n      陳水模均以系爭土地管理人之身分向黃志文收取基地租金\n      迄今已數十年，則黃志文與系爭土地所有人間就系爭土地\n      存有基地租賃契約，故黃志文使用系爭土地亦具有使用權\n      源。退萬步言之，本件就陳水模以系爭土地共有人之管理\n      人身份向黃志文收取基地租金之行為可議，然細究陳蘇\n      自知其所共有之土地有黃志文建屋於上，復陳蘇之配偶\n      陳番亦住於相鄰土地上，且陳水模為陳番與陳蘇所生之\n      子，則陳水模對外以陳蘇代理人或管理人之名義向建物\n      所有人收取租金應為陳蘇所知悉，然陳蘇對此卻始終\n      均未表示反對意見，從而被告等自可主張民法第169 條之\n      表見代理之法律效果，故黃志文使用系爭土地亦具正當使\n      用權源。\n（三）陳水模取得系爭土地所有權後，被告之被繼承人黃志文始\n      建屋於上，且其後陳水模均代表地主至黃志文住處收取租\n      金，故系爭租金清償方式屬於往取債務，乃陳水模生前均\n      依此方式收取租金，然於85年起陳水模即因故未再向黃志\n      文收租，然黃志文為保權益乃多次催告陳水模與陳蘇之\n      繼承人收租，此有85年至98年之存證信函可稽。因陳水模\n      受催告後仍未出面收取租金，黃志文乃於99年4 月間依民\n      法第326 條規定將最近五年（至99年度）之基地租金向臺\n      灣桃園法院提存，故提存後即生清償效力。被告既先催告\n      債權人領取組金，且於債權人受領遲延時依法將應為之給\n      付物提存，故本件被告並無遲延給付租金或其他違約之情\n      ，從而原告主張依土地法第103 條第4 、5 款所定之事由\n      終止租約，亦無所據。並聲明：原告之訴及假執行之聲請\n      均駁回；如受不利益判決，願供擔保請准免為假執行。\n三、兩造不爭執事項：\n（一）訴外人陳蘇已於44年7 月30日死亡，原告為陳蘇之繼\n      承人。訴外人葉陳玉嬌為陳蘇之繼承人，葉陳玉嬌已於\n      98年10月7 日死亡，原告葉王沅、葉月寶、葉美娜為葉陳\n      玉嬌之繼承人。\n（二）坐落桃園縣中壢市○○路354 號係爭房屋屬於巫乾正、巫\n      廖惠所有；356 號係爭房屋屬於張滿妹、黃河、黃雅英、\n      黃美華、黃嘉生等人所有；362 、364 號係爭房屋屬於劉\n      振權所有；而係爭建物分別坐落於如桃園縣中壢地政事務\n      所99年12月21日之土地複丈成果圖所示之地號土地及面積\n      。\n（三）原告與訴外人陳文毅為系爭土地之共有人，訴外人陳文毅\n      之應有部分為2/10。原告等人就系爭土地之應有部分合計\n      為8/10 。\n四、本院得心證理由：\n（一）按訴外人陳水模出養予其叔叔陳泰後，由於養父不久隨即\n      死亡，因此返回本生父母處與本生父母即陳蘇與陳番共\n      同生活，業據陳水模之子陳文毅到庭證述明確（詳見本院\n      卷二第180-181 頁）。且陳水模之戶籍地原設與陳番及陳\n      蘇相同之龜山鄉○路村○○路坑21號，嗣於38年12月28\n      日與陳簡鬆結婚，至41年8 月1 日始遷至中壢鎮中壢里2\n      鄰中壢25號；而陳蘇於42年12月24日亦遷移至中壢鎮中\n      壢里2 鄰中壢25號陳水模之住處，此有戶籍謄本在卷可稽\n      。可見陳水模雖出養其叔叔陳泰，然事實上均是與本生父\n      母陳蘇與陳番共同生活互相照顧。又陳水模與陳蘇與\n      陳番共同設籍於龜山，依戶籍記載父母親為陳蘇與陳番\n      ，然於40年7 月14日始聲請更正為陳泰之養子，因此在40\n      年7 月14日前陳水模戶籍上記載之父母為陳蘇與陳番，\n      嗣於40年7 月14日始申請更正為陳泰之養子，此有戶籍謄\n      本在卷可稽。然一般外人豈可能知悉如此私人隱私之資料\n      ，且長期以來在外人眼裡陳水模即陳蘇與陳番之子女，\n      所以被告等一如往常均認為陳水模代表陳蘇與陳番之權\n      限，應可採信。\n（二）被告劉鼎泰之祖父劉阿昂於39年9 月15日與陳水模、陳蘇\n      簽立租借地權契約證書（詳見本院卷一第122 頁），原\n      告雖然否認其真正性，然當時之土地所有權人為陳水模、\n      陳蘇所有，且如前述陳水模與陳蘇、陳番均有往來甚\n      至共同生活，且當時戶籍謄本上陳水模與陳蘇、陳番是\n      為父母子女之登載，另契約書上記載之住址，與陳蘇、\n      陳水模當時之住址相符；因此對於渠等共有土地相信渠等\n      應該知悉處理之情況，可見係爭租界地權契約書，確實係\n      陳蘇與陳水模所簽立。而被告劉鼎泰所提出由訴外人陳\n      水模收取租金之收據（詳見本院卷一第123-129 頁、院二\n      第187 、188 頁），衡諸常情，陳水模與陳蘇既然共同\n      簽訂租借地權契約書，且為陳蘇子女，豈可能不幫陳蘇\n      收取租金，因此縱然陳水模收取租金之收據沒有代表或\n      代理陳蘇之字眼，然陳水模所收取之租金應包涵陳蘇\n      部分，故被告主張陳水模代表或代理陳蘇收取租金應為\n      可採。縱然陳文毅證稱：有向巫乾正及劉政權收取租金，\n      是根據父親告知，伊看父親之前簽收的收據多少，伊就收\n      多少，伊認為只是收取伊的持份部分。其僅是收取其應有\n      部分，其父親收取多少其就收取多少，其不知伊父親有無\n      幫忙陳蘇租金等語（詳見本院卷二第180 頁至181 頁）\n      ，由於陳文毅不知陳水模是如何與巫乾正、劉鼎泰約定租\n      金，僅是依照之前收取多少即收取多少。然既然依照前述\n      ，陳水模收取的租金包函陳蘇部分，則陳文毅收取的租\n      金亦包函陳蘇及原告等之部分。故被告等主張陳文毅收\n      取的租金應包函原告等之部分，應為可採。\n（三）訴外人陳番（即原告等人之被繼承人、陳蘇之配偶）與\n      被告劉鼎泰之祖父劉阿昂曾就係爭土地之租金於47年6 月\n      27日成立和解筆錄，此有和解筆錄在卷可稽（詳見本院卷\n      二第196 頁），而渠等成立和解筆錄後，劉阿昂就係爭土\n      地之租金亦係給付給陳水模，可見陳水模當時收取租金時\n      ，不僅就其所有部份，就陳蘇部分亦應一同收取，因為\n      當時縱然陳水模出養，然其依然與本生父母即陳蘇及陳\n      蕃共同生活，豈可能僅收取名下之租金，而對於陳蘇名\n      下之租金棄之不顧，顯與常情有違。且當陳蘇往生後，\n      其名下土地由陳番管理（當時並未辦理繼承登記，但實際\n      上陳番以繼承人之地位在管理系爭土地），陳番既然與劉\n      阿昂成立租金調高之和解書，豈可能沒有要求被告等繳交\n      租金；然被告等均沒有陳番具名之收據，而僅有陳水模具\n      名之收據，可見陳水模所收取租金亦應包涵名下之部分（\n      既然之前包函陳蘇部分，則衡諸常情，在沒有其他繼承\n      人出面主張有不同意見前，被告等繼續認為陳水模有代理\n      處理收取租金之權限，亦符合常情）。從而，陳水模收取\n      被告等所繳納之租金，自始即包函陳蘇名下部分，不論\n      陳蘇往生後係爭土地由陳番管理之時期亦是如此。故陳\n      水模向被告等收取之租金，在陳蘇往生後之時期，亦包\n      函陳蘇名下部份之租金。\n（四）陳水模亦曾以兼具有陳蘇管理人之身分於80年9 月26日\n      曾發函黃志文告知要提高租金為每年627,976 元，此有存\n      證信函在卷可稽（詳見本院卷二第79頁）；陳番於67年8\n      月30日往生，其往生後就陳蘇名下之土地全體繼承人均\n      未處理，而陳水模在陳番往生後，一如往常的對被告等收\n      取租金，則被告等亦一如往常的認為渠等所交付的租金，\n      包函屬於陳蘇名下之部分，應屬可採。而原告等雖均為\n      陳蘇之繼承人，然陳蘇之長子陳佳猷於86年1 月10日\n      才往生，在此之前為何共有人（繼承人）均未對被告等主\n      張任何權利，而是待95年5 月10日辦理繼承之後再向被告\n      等主張無權占有？在陳佳猷尚建在時，為何沒有對被告等\n      主張任何權利？因此於陳番往生後（即67年8 月30日）至\n      陳佳猷往生前（86年1 月10日）間，可見陳佳猷亦同意由\n      陳水模來管理系爭土地並收取租金，否則陳佳猷豈可能沒\n      有對被告等主張任何權利；再者，陳蘇名下之土地，在\n      陳蘇往生後，其繼承人到底有誰？依照法律規定與一般\n      民間習俗或許截然不同；且強求被告等去查詢資料來釐清\n      陳蘇之繼承人到底是何人，顯係強人所難之事，而被告\n      等亦無此義務。故被告等一如往常的認為陳水模繼續有代\n      理陳蘇之繼承人收取租金之權限，應為可採。\n（五）由巫乾正所提出陳水模及陳文毅所簽立之收據（詳見本院\n      卷一第139-140 頁；卷二第96-102頁）；再者係爭房屋房\n      屋稅之起課時間為16年1 月間（詳見本院卷二第103 頁）\n      ，顯見被告巫乾正、巫廖會部分，均無積欠租金之情形。\n      另由劉鼎泰所提出陳水模所簽立之收據（詳見本院卷二18\n      7 、188 頁、卷0000-000 頁），陳文毅所簽立之收據（\n      詳見本院卷一第12 9頁），可見被告劉振權部分亦無積欠\n      租金之情形。再者，由於被告黃張滿妹等5 人部分之房屋\n      於27年1 月即起課（詳見本院卷一第160 頁），且陳水模\n      亦均有向其收取租金（詳見本院卷二第55-78 頁），收取\n      到83年11月30日，雖然陳水模曾於80年9 月26日曾發文要\n      求提高租金費用，然或許兩造未達成協議，而被告自85年\n      12月2 日起每年均以存證信函加計支票涵文給陳水模；另\n      自87年10月1 日起則以存證信函催告陳水模到其住處收取\n      租金，直至96年12月3 日為止。則被告黃張滿妹等5 人部\n      份亦無積欠租金之情事。從上可知，被告等均無積欠原告\n      等，而有租金未繳之情事。\n（六）按由自己之行為表示以代理權授與他人，或知他人表示為\n      其代理人而不為反對之表示者，對於第三人應負授權人之\n      責任，民法第169 條前段雖定有明文。然由自己之行為表\n      示以代理權授與他人者，對於第三人應負授權人之責任，\n      必須本人有表見之事實，足使第三人信該他人有代理權之\n      情形存在，始足當之。我國人民將自己印章交付他人，委\n      託該他人辦理特定事項者，比比皆是，倘持有印章之該他\n      人，除受託辦理之特定事項外，其他以本人名義所為之任\n      何法律行為，均須由本人負表見代理之授權人責任，未免\n      過苛。原審徒憑上訴人曾將印章交付與呂某之事實，即認\n      被上訴人就保證契約之訂立應負表見代理之授權人責任，\n      自屬率斷（最高法院70年台上字第657 號判例意旨參照）\n      。又民法第169 條所謂知他人表示為其代理人而不為反對\n      之表示者，以本人實際知其事實為前提，其主張本人知此\n      事實者，應負舉證之責（最高法院68年台上字第1081號判\n      例意旨參照）。被告等辯稱與陳水模、陳蘇成立租借地\n      權契約書或者對於渠等建物坐落土地與地主成立租賃契約\n      ，陳水模收取之租金包函陳蘇之部分，故陳蘇及陳蘇\n      之繼承人應負表見代理人之責任云云。經查：\n  １、在陳水模與陳蘇（往生前）之時段：如前述，陳水模與\n      陳蘇、陳番亦如父母子女，則陳水模代表二人來收取被\n      告等租賃土地之租金，而陳蘇亦無提出異議，被告等也\n      均有繳納租金，顯見陳水模有代理陳蘇收取租金之權限\n      及情事。\n  ２、在陳水模與陳番（往生前）之時段：在陳蘇往生後，陳\n      番曾與劉阿昂成立租金調解筆錄，而期後之租金，仍由陳\n      水模繼續向被告等收取，則被告等信賴陳水模有代理陳蘇\n      之繼承人收取陳蘇名下土地租金之權限，亦為可採。\n  ３、在陳水模與陳番往生後之時段：在陳番往生後，陳水模繼\n      續向被告等收取渠等租地之租金，而未有其他繼承人出面\n      向被告等主張陳水模並未有如此代理權之前提下，被告等\n      依然認為陳水模有代理權並且繼續繳納租金，則被告等主\n      張陳水模有代理原告等收取租金之權限，應為可採。且原\n      告等亦不否認，未曾向被告等催告收取租金，直至提起本\n      件訴訟為止。或者一直到原告於本院對被告陳梁美靜等人\n      提起96年度訴字第413 號拆屋還地等案時，才知道原告等\n      人係陳蘇之繼承人。\n  ４、從而，原告等主張陳水模對於陳蘇並未有表現代理之情\n      況，亦未有代理陳蘇收取租金之情事及權限，顯無足採\n      。不論被告等之被繼承人取得所有之建物係早於陳蘇取\n      得係爭土地所有權之前或者之後，在陳蘇取得土地所有\n      權後，陳蘇對於陳水模代理其向被告等或渠等之被繼承\n      人收取租地租金時，並未有明確之反對陳水模沒有代理權\n      ，且當時陳水模為陳蘇之子女，外人亦容易認為陳水模\n      有代理陳蘇收取租金之權限，因此有表現代理之情事；\n      則在陳蘇往生後，未有其他繼承人出面主張陳水模未有\n      代理其他繼承人收取租金之權限前，被告等繼續認為陳水\n      模有代理之權限，而繼續繳納租金，則陳水模與陳蘇繼\n      承人間亦存有表現代理之情況；則被告等主張陳水模收取\n      之租金，包含陳蘇部分及原告等繼承人之部分，應為可\n      採。另被告等既依照先前兩造租約之約定繼續繳納租金，\n      未有遲延繳納租金之情事，原告另主張被告等有未繳納租\n      金之情事，亦無足採。\n六、綜上所述，被告等主張渠等並非無權占有原告等及被繼承人\n    陳蘇名下之土地，而係存有租賃關係，為可採信。則原告\n    本於所有權主張被告等無權占有應返還渠等建物所占有之土\n    地及基於不當得利法律關係請求被告等應給付相當於租金之\n    不當得利數額，均為無理由，均應予駁回。原告之訴既經駁\n    回，其假執行之聲請亦失所附麗，併予駁回。\n七、本件事證已臻明確，兩造其餘主張陳述及所提之證據，經審\n    酌與本院前揭判斷無影響，毋庸一一論述，附此敘明。\n八、據上論結，原告之訴為無理由，依民事訴訟法第78，判決如\n    主文。"
  },
  "search": "臺灣桃園地方法院民事判決99年度重訴字第95號原告陳蘇治陳寶瓊陳淑麗陳文鶯邱俊宏邱勝飛邱志成邱碧姿邱新永邱顯宗邱萬得蔡邱玉蘭邱芳汶黃陳草鳳葉王沅即葉陳玉嬌.葉月寶即葉陳玉嬌.葉美娜即葉陳玉嬌.沙陳銅銀陳韻共同訴訟代理人吳秀菊律師被告巫廖會兼上一人訴訟代理人巫乾正被告黃張滿妹黃美華黃嘉生黃河黃雅英上五人共同訴訟代理人康英彬律師被告劉鼎泰（原名劉振權）上列當事人間請求返拆屋還地等事件，於民國100年4月27日言詞辯論終結，本院判決如下：主文原告之訴及假執行之聲請均駁回。訴訟費用由原告負擔。事實及理由壹、程序方面：按訴狀送達後，原告不得將原訴變更或追加他訴，但有請求之基礎事實同一、擴張或減縮應受判決事項之聲明、不甚礙被告之防禦及訴訟之終結情形者，不在此限，民事訴訟法第255條第1項但書第2款、第3款、第7款分別定有明文。查原告起訴時訴之聲明為：「(一)被告應將如附圖1所示土地上之地上物拆除（占有土地面積、地上物門牌號碼均約如附圖1附表所示，實際位置及面積請鈞院囑託地政機關測量後為準），並將土地返還予原告及其他共有人。(二)被告應各給付原告如附表2第(五)欄所示金額，及自起訴狀繕本送達翌日起迄清償日止，按年息百分之五計算之利息。(三)被告各應給付自99年3月1日起迄第一項所示土地交還原告及其他共有人之日，各按年給付原告如附表2第(七)欄所示金額。(四)願供擔保請准宣告假執行。」。嗣於民國100年2月14日具狀追加巫廖會為被告，並變更聲明為：「(一)請令被告應將如下所述土地上之地上物拆除（占有土地面積、地上物門牌號碼均如附圖１所示），並將土地返還予原告及其他共有人。1.請令被告巫乾正、巫廖會應將如附圖1所示中壢市○○段中壢老小段第11-15地號上標示11-15（B）3㎡、14-1地號上標示14-1（B）129㎡，面積合計為132㎡之土地上門牌號碼為中壢市○○路354號地上物予以拆除，並將土地返還予原告及其他共有人。2.請令被告黃張滿妹、黃河、黃雅英、黃美華、黃嘉生等人將如附圖1所示中壢市○○段中壢老小段第14-2地號土地上標示14-2（A）122㎡，面積合計122㎡之土地上門牌號碼為中壢市○○路356號地上物予以拆除，並將土地返還予原告及其他共有人。3.請令被告劉振權將如附圖1所示中壢市○○段中壢老小段第14-5地號土地上標示14-5（A）109㎡及同地段土地第14-6地號土地上標示14-6（A）28㎡，面積合計137㎡之土地上門牌號碼為中壢市○○路362號地上物予以拆除，並將土地返還予原告及其他共有人。4.請令被告劉振權將如附圖1所示中壢市○○段中壢老小段第14-6地號土地上標示14-6（C）46㎡，面積合計46㎡之土地上門牌號碼為中壢市○○路364號地上物予以拆除，並將土地返還予原告及其他共有人。(二)被告各應給付各原告等如附表２第(五)欄所所示金額，及自起訴狀繕本送達之翌日起迄清償日止，按年息百分之五計算之利息。(三)被告各應自99年3月1日起迄第一項所示土地交還原告及其他共有人之日，各按年給付各原告如附表２第(七)欄所示金額。(四)原告願供擔保，請准宣告假執行。」，核原告追加被告巫廖會部分，核其請求之基礎事實與起訴之事實同一，且不甚礙被告之防禦及訴訟之終結；又變更拆除及返還土地面積部分，係擴張或減縮應受判決事項之聲明；揆諸前揭法律規定，均應予准許。貳、實體方面：一、原告起訴主張：（一）原告乃被繼承人陳蘇之全體繼承人，而原告之被繼承人陳蘇乃坐落桃園縣中壢市○○段中壢老小段14-1、11-15、14-2、14-5、14-6地號土地（下稱系爭土地）之所有權人之一，所佔持分為十分之八，而陳蘇於44年7月30日過世後，原告當然繼承被繼承人之系爭土地之產權，雖遲至95年5月10日方辦理繼承登記，惟基於繼承法理原告於44年7月30日後即取得系爭土地之所有權。原告為系爭土地之共有人，被告未經原告及其他共有人同意，擅自在原告所有之系爭土地上興建建物，核其所為顯然係無權占用原告所共有之土地，爰依民法第821條及第767條規定，訴請被告除去妨害及返還所有物予所有人全體，又無權占有他人土地可獲得相當於租金之利益，被告無權占用系爭土地，致原告對之無法使用收益，被告顯屬無法律上之原因而受利益致原告受有損害，原告自得依民法第179條及最高法院61年台上字第1695號判例之規定，請求被告返還起訴前五年起至返還土地之日止相當於租金之不當得利。（二）對被告答辯之陳述：１、否認兩造間有租賃關係存在，也否認被告等所繳給陳水模之租金，即為被告等所占用土地之租金。２、被告等除劉鼎泰外，其屋況均已老舊，顯見渠等明知為無權占有他人土地，故無積極翻修，聽憑屋況老舊之貌。３、被告等所提示之收據均無陳蘇或原告等任何一人之簽名或蓋章，且原告之被繼承人陳蘇乃於44年即過世，而被告所提出之收據均係陳蘇死亡後之收據，並無原告等合法繼承人所立之文件，而原告並無委託或授權陳水模出租土地或收取租金。陳水模並非陳蘇之繼承人，陳水模或其子陳文毅無由代理或代表陳蘇或原告，且土地乃公示主義，任何人均可透過地政機關查閱系爭土地所有權人為何，從而並無表見代理成立之餘地。另有關共有物之租賃，實務及學說均係對共有物之「管理行為」，而系爭土地之共有人含原告等迄今未分割，而被告承租系爭土地亦未曾得到身為共有人之原告之同意，依民法第828條、第820條第1項規定，縱認被告與系爭土地之5分之1共有人陳水模就系爭土地有租賃關係，惟該共有人所為之管理行為（出租）乃屬無效，故被告占有系爭土地仍屬無權占有。被告巫乾正、巫廖會二人所有之系爭房屋係自其被繼承人巫振鐮繼承而得，而巫振鐮乃於陳蘇死後於55年間才於第三人處取得系爭房屋之事實上處分權，亦證渠等係無權占用系爭土地。４、原告否認陳水模為被繼承人陳蘇之子孫輩財產管理人。系爭土地於陳蘇死亡後係由其夫陳番管理，而陳番死亡後因無人管理，故系爭土地因無人繳納稅捐於64年遭稅捐機關查封，至95年時財稅單位向原告等寄交繳稅通知，原告始一次性繳納500多萬元之地價稅，足證此間並未曾出現由陳水模代表原告處理系爭土地全部之情形。被告劉鼎泰亦辯稱陳蘇死亡後係由陳番管理系爭土地，則被告應繳納租金之對象即為陳番，而非陳水模，亦證被告辯稱陳水模代表原告出租系爭土地及向渠等收取租金之事實乃不實在。５、被告劉鼎泰所提出之「租借地權契約證書」其上之陳蘇與陳水模之筆跡相同，顯然並非陳蘇所親簽之契約，故原告亦否認該契約書乃出於陳蘇之承諾或合意。縱被告劉鼎泰對系爭土地有基地租賃，惟因被告劉鼎泰始終未繳付應有之租金予陳蘇或原告（被告從未提示陳蘇及原告等人所立之任何租金收據），並將系爭房屋轉租圖利，又違反租賃契約將系爭房屋全面改建，原告爰依土地法第103條第1項第3、4、5款為由，向被告劉鼎泰為終止租賃契約之意思表示，並以本訴狀之送達為終止租賃意思表示送達之時。６、被告黃河等五人自認其進駐系爭房屋乃44年以後之事情，其父黃志文係後來所購及進駐系爭房屋，當時原告被繼承人陳蘇已經過世，故被告之被繼承人黃志文與原告之被繼承人無從成立地上權之物權及基地之租賃契約。而被告所提日據時期地籍謄本與二造及本件並無關係。蓋有關上開日據時期謄本所載之權利人為訴外人張詹氏冉妹，並無記載為後手為權利人。尤以被告既抗辯其等有日據時代之地上權，從而謹請被告先提呈其係地上權人之登記權利人及日據時代其等已進駐系爭房屋之證明。縱退萬步言，假若被告黃河等五人對系爭土地有基地租賃或所謂地上權之關係（非表自認），惟因被告始終未繳付應有之地租予原告及原告之被繼承人，原告先前即依土地法第103條規定第1項第4款、第5款為由向被告為終止租賃契約之意思表示，並以民法第836條之規定撤銷被告所謂之地上權，並以該狀之送達為意思表示送達之時。（三）並聲明：如前開變更聲明所示。二、被告劉鼎泰則以：被告占有、使用系爭土地乃因被告之祖父劉阿昂前於39年即與原告之被繼承人陳水模、陳蘇二人訂有「租借地權契約書」，依該契約書第五點記載，租約之存續期間為「不限年」，故被告基於繼承原因取得系爭土地之承租權而占有、使用系爭土地，實有合法權源。陳水模及其子陳文毅亦基於該契約書而向被告之祖父與被告收取租金，該基地租賃法律關係確係存在，不容原告隨意否認。原告對該租借地權契約書不否定其真實性，僅認為並非陳蘇本人簽字，及非出於陳蘇之承諾或合意，惟該契約書之簽訂後至44年7月30日陳蘇往生為止，約五年期間被告均繼續繳租，陳蘇並無反對之意思表示，故原告所提並非事實，純屬臆測。被告已繳清至98年5月31日之地租，至今尚未滿二年，故並不符和土地法第103條第4款終止租約之規定，且由以往至今被告一律繳足額之租金，並非繳交1/5之租金，並由陳水模及其後人陳文毅代為收取，並提出37、38年陳蘇尚未死亡前即全權委託陳水模代收租金之收據，足證從陳蘇在世時即委託陳水模代收租金。又被告為租地建屋，所租為被告本人及祖父劉阿昂所有之房屋，並未違反「租借地權契約書」內之規定，且被告全家亦長期居住於此，並無將租地轉租他人之情形，與土地法第103條第3、5款規定不符。另陳水模、陳蘇係共同出租人，其二人秉於該「租借地權契約書」對於被告本得為全部租金給付之請求，故屬連帶債權。因而，被告基於繼承原因取得系爭土地之承租權後，除中山路364號房屋仍登記為劉阿昂所有外，362號房屋則登記於被告劉鼎泰名下，被告並依租約約定繳納租金於出租人陳水模之繼承人陳文毅，依民法第284條規定被告給付租金於連帶出租人之一陳水模及其繼承人陳文毅自屬適法有效，此亦無涉於陳蘇是否委託陳水模或其繼承人陳文毅代理或代表受取租金。另民法第820條係屬共有人內部對於共有物管理之同意，而本件租賃關係原本即存在於土地所有權人陳水模與陳蘇，故民法第820條規定無涉於本件租賃關係等語置辯。並聲明：原告之訴及其假執行聲請均駁回：如受不利益判決，願供擔保請准宣告免為假執行。三、被告巫乾正、巫廖會則以：被告所有中壢市○○路354號房屋（該屋係於41年7月間由訴外人劉源慶出賣予訴外人吳金妹，可見該屋早於41年間即存在），係坐落中壢市○○段中壢老小段14-1地號土地，是由被告巫乾正之父巫振鐮繼承而得。被告巫乾正之父巫振鐮先於53年8月26日受贈於訴外人吳進發持分2分之1，再於55年3月15日自訴外人吳鄧桂菊買受持分2分之1。至於房屋基地一直是向地主陳水模承租，並繳納租金，直到陳水模過世後始由其繼承人陳文毅收取租金。嗣因本案被訴，被告始知悉陳水模、陳文毅共有系爭土地應有部分5分之1，對於土地另有其他共有人被告完全不知情，故退步言之，倘使陳水模、陳文毅無權將系爭土地出租，然由被告所有之房屋早於41年間即已存在，可以推定迄今系爭土地出租已超過50餘年，一直均是由陳水模、陳文毅以地主身份而一脈相承，其不但與被告訂立租約、協調租金數額，且按期收取租金，對被告而言，陳文毅即是地主之代表，依民法第169條規定被告與陳水模、陳文毅訂立之租約亦是合法有效。系爭土地出租予被告建築房屋有合法之租約，則依土地法第103條規定，本案原告並不可將土地收回。並聲明：原告之訴及假執行之聲請均駁回；如受不利益判決，願供擔保請准宣告免為假執行。四、被告黃張滿妹、黃美華、黃嘉生、黃河、黃雅英則以：（一）系爭被告等所共有建於原告繼承土地上之建物，經查至遲建於日據時期之27年間，故斯時臺灣地區仍適用日本國民法。復按系爭「中壢市○○段中壢老小段14-2地號」土地於日據時期之原所有人為張詹氏冉妹，嗣張詹氏冉妹於昭和6年1月14日將所有權一部分轉予張新鐘，於昭和8年（即民國22年）9月5日張詹氏冉妹與張新鐘二人將所有權移轉予陳有定及「陳水模」共有（陳水模應有部分為五分之一），於37年9月23日陳有定將其應有部分移轉予「陳蘇」（陳蘇應有部分為五分之四），此有日據時期之土地臺帳本可稽。基此，於37年後系爭土地業由陳蘇及陳水模所共有。而被告之被繼承人黃志文建屋後均按期繳納基地租金於基地所有人，於22年陳水模取得系爭土地所有權後即收受地租，嗣於37年陳蘇取得土地後，亦委託陳水模收取地租，故其後系爭土地均由陳水模以地主暨經陳蘇授權之身分向黃志文收取基地租金迄今，而陳水模亦以同樣模式向同案其他被告收取基地租金。系爭房屋於陳蘇取得土地時早已存在十餘年，況陳蘇乃以「買賣」方式取得土地所有權，故依常理論，陳蘇於買受土地時，誠不可能不知當時土地之使用現況為何。又陳水模為陳蘇與配偶陳番所生，雖將陳水模出養給陳番之兄弟陳泰，但原告亦自承出養未久陳泰即亡故，從而陳水模於養父死亡後自幼仍由親生父母撫養，此何以原告亦自承常看到陳水模在陳蘇家裡，甚至陳水模之戶籍始終設於龜山，迨陳水模日後遷至坐落於系爭土地相鄰之中壢市○○路352號居住，而陳番亦曾至該住處與陳水模同住，加以原告自承陳蘇往生後，系爭土地即由陳番管理，故陳番亦自明知陳蘇所遺留之系爭土地有本件多位被告建屋於上許久（陳蘇44年7月亡、陳番67年8月亡），歷經二十餘年間陳番不可能不知由其子陳水模代為管理系爭土地並收取租金之事實。另陳水模早於陳蘇取得系爭土地之共有權，而系爭建物於陳水模取得土地後幾年始建蓋，且房屋建蓋後陳水模即開始收取地租至84年間，加以陳蘇之配偶即陳水模之生父陳番係於67年8月間始亡故，而陳番即設籍住於被告之隔壁（中壢市○○路352號），故陳蘇夫婦實不可能不知其所共有之土地已由被告建屋於其上，甚至由其子陳水模出面代表地主收取租金數十年不間斷。另系爭土地依當時之環境乃位於中壢之市區中心，非屬郊區或偏僻不毛之地，且就本件訟爭各筆土地，依當時之經濟狀況論，每年向建物所有人收取之租金總數亦可觀，矧占有土地持分五分之四之陳蘇更不可能就自己之土地任由他人無權占有使用，故茲有陳蘇之子陳水模以土地管理人或代理人身份向建物所有人收取租金，亦符常情。況陳水模亦曾以陳蘇管理人之身分寄存證信函予黃志文要求調整租金。（二）訴外人陳有定與陳水模於日據時期之昭和8年（即民國22年）取得系爭土地所有權，而系爭建物於日據時期之昭和13年（民國27年）即建於系爭土地上，故當時土地及建物之法律關係應依日本國之相關法律而定之，而依日本國《關於地上權之法律》第1條、最高法院72年台上字第136號判決規定，當時日本國物權法乃採「意思主義」，以當事人之意思表示即可成立生效，且在他人土地為所有工作物而使用其土地之人推定為地上權人，故得知系爭建物所有人於昭和13年即應取得地上權，從而黃志文既為系爭建物之所有權人，依日本國民法規定即就系爭土地具有正當使用權源。縱另一共有人即原告之被繼承人陳蘇於37年取得系爭土地所有權，然依物權之「對世效力」，黃志文自仍可對陳蘇主張地上權。遑論黃志文均有支付基地租金予陳水模與陳蘇二人。退步言之，本件黃志文之地上權縱有自始或嗣後不存在之事由，然系爭土地共有人之一陳水模均以系爭土地管理人之身分向黃志文收取基地租金迄今已數十年，則黃志文與系爭土地所有人間就系爭土地存有基地租賃契約，故黃志文使用系爭土地亦具有使用權源。退萬步言之，本件就陳水模以系爭土地共有人之管理人身份向黃志文收取基地租金之行為可議，然細究陳蘇自知其所共有之土地有黃志文建屋於上，復陳蘇之配偶陳番亦住於相鄰土地上，且陳水模為陳番與陳蘇所生之子，則陳水模對外以陳蘇代理人或管理人之名義向建物所有人收取租金應為陳蘇所知悉，然陳蘇對此卻始終均未表示反對意見，從而被告等自可主張民法第169條之表見代理之法律效果，故黃志文使用系爭土地亦具正當使用權源。（三）陳水模取得系爭土地所有權後，被告之被繼承人黃志文始建屋於上，且其後陳水模均代表地主至黃志文住處收取租金，故系爭租金清償方式屬於往取債務，乃陳水模生前均依此方式收取租金，然於85年起陳水模即因故未再向黃志文收租，然黃志文為保權益乃多次催告陳水模與陳蘇之繼承人收租，此有85年至98年之存證信函可稽。因陳水模受催告後仍未出面收取租金，黃志文乃於99年4月間依民法第326條規定將最近五年（至99年度）之基地租金向臺灣桃園法院提存，故提存後即生清償效力。被告既先催告債權人領取組金，且於債權人受領遲延時依法將應為之給付物提存，故本件被告並無遲延給付租金或其他違約之情，從而原告主張依土地法第103條第4、5款所定之事由終止租約，亦無所據。並聲明：原告之訴及假執行之聲請均駁回；如受不利益判決，願供擔保請准免為假執行。三、兩造不爭執事項：（一）訴外人陳蘇已於44年7月30日死亡，原告為陳蘇之繼承人。訴外人葉陳玉嬌為陳蘇之繼承人，葉陳玉嬌已於98年10月7日死亡，原告葉王沅、葉月寶、葉美娜為葉陳玉嬌之繼承人。（二）坐落桃園縣中壢市○○路354號係爭房屋屬於巫乾正、巫廖惠所有；356號係爭房屋屬於張滿妹、黃河、黃雅英、黃美華、黃嘉生等人所有；362、364號係爭房屋屬於劉振權所有；而係爭建物分別坐落於如桃園縣中壢地政事務所99年12月21日之土地複丈成果圖所示之地號土地及面積。（三）原告與訴外人陳文毅為系爭土地之共有人，訴外人陳文毅之應有部分為2/10。原告等人就系爭土地之應有部分合計為8/10。四、本院得心證理由：（一）按訴外人陳水模出養予其叔叔陳泰後，由於養父不久隨即死亡，因此返回本生父母處與本生父母即陳蘇與陳番共同生活，業據陳水模之子陳文毅到庭證述明確（詳見本院卷二第180-181頁）。且陳水模之戶籍地原設與陳番及陳蘇相同之龜山鄉○路村○○路坑21號，嗣於38年12月28日與陳簡鬆結婚，至41年8月1日始遷至中壢鎮中壢里2鄰中壢25號；而陳蘇於42年12月24日亦遷移至中壢鎮中壢里2鄰中壢25號陳水模之住處，此有戶籍謄本在卷可稽。可見陳水模雖出養其叔叔陳泰，然事實上均是與本生父母陳蘇與陳番共同生活互相照顧。又陳水模與陳蘇與陳番共同設籍於龜山，依戶籍記載父母親為陳蘇與陳番，然於40年7月14日始聲請更正為陳泰之養子，因此在40年7月14日前陳水模戶籍上記載之父母為陳蘇與陳番，嗣於40年7月14日始申請更正為陳泰之養子，此有戶籍謄本在卷可稽。然一般外人豈可能知悉如此私人隱私之資料，且長期以來在外人眼裡陳水模即陳蘇與陳番之子女，所以被告等一如往常均認為陳水模代表陳蘇與陳番之權限，應可採信。（二）被告劉鼎泰之祖父劉阿昂於39年9月15日與陳水模、陳蘇簽立租借地權契約證書（詳見本院卷一第122頁），原告雖然否認其真正性，然當時之土地所有權人為陳水模、陳蘇所有，且如前述陳水模與陳蘇、陳番均有往來甚至共同生活，且當時戶籍謄本上陳水模與陳蘇、陳番是為父母子女之登載，另契約書上記載之住址，與陳蘇、陳水模當時之住址相符；因此對於渠等共有土地相信渠等應該知悉處理之情況，可見係爭租界地權契約書，確實係陳蘇與陳水模所簽立。而被告劉鼎泰所提出由訴外人陳水模收取租金之收據（詳見本院卷一第123-129頁、院二第187、188頁），衡諸常情，陳水模與陳蘇既然共同簽訂租借地權契約書，且為陳蘇子女，豈可能不幫陳蘇收取租金，因此縱然陳水模收取租金之收據沒有代表或代理陳蘇之字眼，然陳水模所收取之租金應包涵陳蘇部分，故被告主張陳水模代表或代理陳蘇收取租金應為可採。縱然陳文毅證稱：有向巫乾正及劉政權收取租金，是根據父親告知，伊看父親之前簽收的收據多少，伊就收多少，伊認為只是收取伊的持份部分。其僅是收取其應有部分，其父親收取多少其就收取多少，其不知伊父親有無幫忙陳蘇租金等語（詳見本院卷二第180頁至181頁），由於陳文毅不知陳水模是如何與巫乾正、劉鼎泰約定租金，僅是依照之前收取多少即收取多少。然既然依照前述，陳水模收取的租金包函陳蘇部分，則陳文毅收取的租金亦包函陳蘇及原告等之部分。故被告等主張陳文毅收取的租金應包函原告等之部分，應為可採。（三）訴外人陳番（即原告等人之被繼承人、陳蘇之配偶）與被告劉鼎泰之祖父劉阿昂曾就係爭土地之租金於47年6月27日成立和解筆錄，此有和解筆錄在卷可稽（詳見本院卷二第196頁），而渠等成立和解筆錄後，劉阿昂就係爭土地之租金亦係給付給陳水模，可見陳水模當時收取租金時，不僅就其所有部份，就陳蘇部分亦應一同收取，因為當時縱然陳水模出養，然其依然與本生父母即陳蘇及陳蕃共同生活，豈可能僅收取名下之租金，而對於陳蘇名下之租金棄之不顧，顯與常情有違。且當陳蘇往生後，其名下土地由陳番管理（當時並未辦理繼承登記，但實際上陳番以繼承人之地位在管理系爭土地），陳番既然與劉阿昂成立租金調高之和解書，豈可能沒有要求被告等繳交租金；然被告等均沒有陳番具名之收據，而僅有陳水模具名之收據，可見陳水模所收取租金亦應包涵名下之部分（既然之前包函陳蘇部分，則衡諸常情，在沒有其他繼承人出面主張有不同意見前，被告等繼續認為陳水模有代理處理收取租金之權限，亦符合常情）。從而，陳水模收取被告等所繳納之租金，自始即包函陳蘇名下部分，不論陳蘇往生後係爭土地由陳番管理之時期亦是如此。故陳水模向被告等收取之租金，在陳蘇往生後之時期，亦包函陳蘇名下部份之租金。（四）陳水模亦曾以兼具有陳蘇管理人之身分於80年9月26日曾發函黃志文告知要提高租金為每年627,976元，此有存證信函在卷可稽（詳見本院卷二第79頁）；陳番於67年8月30日往生，其往生後就陳蘇名下之土地全體繼承人均未處理，而陳水模在陳番往生後，一如往常的對被告等收取租金，則被告等亦一如往常的認為渠等所交付的租金，包函屬於陳蘇名下之部分，應屬可採。而原告等雖均為陳蘇之繼承人，然陳蘇之長子陳佳猷於86年1月10日才往生，在此之前為何共有人（繼承人）均未對被告等主張任何權利，而是待95年5月10日辦理繼承之後再向被告等主張無權占有？在陳佳猷尚建在時，為何沒有對被告等主張任何權利？因此於陳番往生後（即67年8月30日）至陳佳猷往生前（86年1月10日）間，可見陳佳猷亦同意由陳水模來管理系爭土地並收取租金，否則陳佳猷豈可能沒有對被告等主張任何權利；再者，陳蘇名下之土地，在陳蘇往生後，其繼承人到底有誰？依照法律規定與一般民間習俗或許截然不同；且強求被告等去查詢資料來釐清陳蘇之繼承人到底是何人，顯係強人所難之事，而被告等亦無此義務。故被告等一如往常的認為陳水模繼續有代理陳蘇之繼承人收取租金之權限，應為可採。（五）由巫乾正所提出陳水模及陳文毅所簽立之收據（詳見本院卷一第139-140頁；卷二第96-102頁）；再者係爭房屋房屋稅之起課時間為16年1月間（詳見本院卷二第103頁），顯見被告巫乾正、巫廖會部分，均無積欠租金之情形。另由劉鼎泰所提出陳水模所簽立之收據（詳見本院卷二187、188頁、卷0000-000頁），陳文毅所簽立之收據（詳見本院卷一第129頁），可見被告劉振權部分亦無積欠租金之情形。再者，由於被告黃張滿妹等5人部分之房屋於27年1月即起課（詳見本院卷一第160頁），且陳水模亦均有向其收取租金（詳見本院卷二第55-78頁），收取到83年11月30日，雖然陳水模曾於80年9月26日曾發文要求提高租金費用，然或許兩造未達成協議，而被告自85年12月2日起每年均以存證信函加計支票涵文給陳水模；另自87年10月1日起則以存證信函催告陳水模到其住處收取租金，直至96年12月3日為止。則被告黃張滿妹等5人部份亦無積欠租金之情事。從上可知，被告等均無積欠原告等，而有租金未繳之情事。（六）按由自己之行為表示以代理權授與他人，或知他人表示為其代理人而不為反對之表示者，對於第三人應負授權人之責任，民法第169條前段雖定有明文。然由自己之行為表示以代理權授與他人者，對於第三人應負授權人之責任，必須本人有表見之事實，足使第三人信該他人有代理權之情形存在，始足當之。我國人民將自己印章交付他人，委託該他人辦理特定事項者，比比皆是，倘持有印章之該他人，除受託辦理之特定事項外，其他以本人名義所為之任何法律行為，均須由本人負表見代理之授權人責任，未免過苛。原審徒憑上訴人曾將印章交付與呂某之事實，即認被上訴人就保證契約之訂立應負表見代理之授權人責任，自屬率斷（最高法院70年台上字第657號判例意旨參照）。又民法第169條所謂知他人表示為其代理人而不為反對之表示者，以本人實際知其事實為前提，其主張本人知此事實者，應負舉證之責（最高法院68年台上字第1081號判例意旨參照）。被告等辯稱與陳水模、陳蘇成立租借地權契約書或者對於渠等建物坐落土地與地主成立租賃契約，陳水模收取之租金包函陳蘇之部分，故陳蘇及陳蘇之繼承人應負表見代理人之責任云云。經查：１、在陳水模與陳蘇（往生前）之時段：如前述，陳水模與陳蘇、陳番亦如父母子女，則陳水模代表二人來收取被告等租賃土地之租金，而陳蘇亦無提出異議，被告等也均有繳納租金，顯見陳水模有代理陳蘇收取租金之權限及情事。２、在陳水模與陳番（往生前）之時段：在陳蘇往生後，陳番曾與劉阿昂成立租金調解筆錄，而期後之租金，仍由陳水模繼續向被告等收取，則被告等信賴陳水模有代理陳蘇之繼承人收取陳蘇名下土地租金之權限，亦為可採。３、在陳水模與陳番往生後之時段：在陳番往生後，陳水模繼續向被告等收取渠等租地之租金，而未有其他繼承人出面向被告等主張陳水模並未有如此代理權之前提下，被告等依然認為陳水模有代理權並且繼續繳納租金，則被告等主張陳水模有代理原告等收取租金之權限，應為可採。且原告等亦不否認，未曾向被告等催告收取租金，直至提起本件訴訟為止。或者一直到原告於本院對被告陳梁美靜等人提起96年度訴字第413號拆屋還地等案時，才知道原告等人係陳蘇之繼承人。４、從而，原告等主張陳水模對於陳蘇並未有表現代理之情況，亦未有代理陳蘇收取租金之情事及權限，顯無足採。不論被告等之被繼承人取得所有之建物係早於陳蘇取得係爭土地所有權之前或者之後，在陳蘇取得土地所有權後，陳蘇對於陳水模代理其向被告等或渠等之被繼承人收取租地租金時，並未有明確之反對陳水模沒有代理權，且當時陳水模為陳蘇之子女，外人亦容易認為陳水模有代理陳蘇收取租金之權限，因此有表現代理之情事；則在陳蘇往生後，未有其他繼承人出面主張陳水模未有代理其他繼承人收取租金之權限前，被告等繼續認為陳水模有代理之權限，而繼續繳納租金，則陳水模與陳蘇繼承人間亦存有表現代理之情況；則被告等主張陳水模收取之租金，包含陳蘇部分及原告等繼承人之部分，應為可採。另被告等既依照先前兩造租約之約定繼續繳納租金，未有遲延繳納租金之情事，原告另主張被告等有未繳納租金之情事，亦無足採。六、綜上所述，被告等主張渠等並非無權占有原告等及被繼承人陳蘇名下之土地，而係存有租賃關係，為可採信。則原告本於所有權主張被告等無權占有應返還渠等建物所占有之土地及基於不當得利法律關係請求被告等應給付相當於租金之不當得利數額，均為無理由，均應予駁回。原告之訴既經駁回，其假執行之聲請亦失所附麗，併予駁回。七、本件事證已臻明確，兩造其餘主張陳述及所提之證據，經審酌與本院前揭判斷無影響，毋庸一一論述，附此敘明。八、據上論結，原告之訴為無理由，依民事訴訟法第78，判決如主文。中華民國100年5月25日民事第三庭法官張益銘以上正本係照原本作成如對本判決上訴，須於判決送達後20日內向本院提出上訴狀。如委任律師提起上訴者，應一併繳納上訴審裁判費。中華民國100年5月25日書記官郭玉芬",
  "characters": {
    "judges": [
      "張益銘"
    ],
    "prosecutors": [

    ],
    "lawyers": [
      "吳秀菊",
      "康英彬",
      "如委任"
    ],
    "clerks": [

    ],
    "plaintiffs": [
      "陳蘇"
    ],
    "defendants": [
      "巫廖會",
      "兼  上一人",
      "黃張滿妹",
      "劉鼎泰（原名劉振權）"
    ],
    "prosecutor_office": [

    ],
    "creditors": [

    ],
    "debtors": [

    ],
    "judicial_associate_officer": [

    ]
  },
  "adjudged_at": "2011-05-25",
  "created_at": "2016-02-12 02:00:06",
  "updated_at": "2016-02-12 02:00:06"
}