{
  "identify": "TYD-93-壢交簡-1031-20040818-1",
  "court": {
    "name": "臺灣桃園地方法院",
    "code": "TYD"
  },
  "division": {
    "name": "刑事",
    "code": "M"
  },
  "year": 93,
  "word": "壢交簡",
  "number": "1031",
  "jcheck": "1",
  "reason": "公共危險等",
  "content": "臺灣桃園地方法院刑事簡易判決                九十三年度壢交簡字第一０三一號\n    聲  請  人  台灣桃園地方法院檢察署檢察官\n    被      告  甲○○  男  二.\n右被告因公共危險等案件，經檢察官聲請以簡易判決處刑（九十三年度偵字第七四八\n七號號），本院判決如左：\n    主      文\n甲○○服用酒類，不能安全駕駛動力交通工具而駕駛，處有期徒刑貳月，如易科罰金\n以參佰元折算壹日。又偽造署押，足以生損害於公眾及他人，處有期徒刑貳月，如易\n科罰金以參佰元折算壹日。偽造於桃園縣政府警察局中壢分局仁愛派出所第一、二次\n調查筆錄上之「乙○○」署名肆枚、指印伍枚均沒收。又行使偽造私文書，足以生損\n害於公眾或他人，處有期徒刑參月，如易科罰金以參佰元折算壹日。偽造於「桃園縣\n警察局舉發違反道路交通管理事件通知單」上「收受通知聯者簽章」處「乙○○」之\n署名（該通知單上下二聯複印）共二枚、「桃園縣警察局舉發交通違規移置保管車輛\n通知單」上「車輛已無貴重物品駕駛人確認後簽章」處之「乙○○」署名一枚、指印\n一枚、口卡片上之「乙○○」署名一枚，捺指印伍枚、於「違反刑法第一百八十五條\n之三查獲後測試、觀察職務報告表」、「告知通知單」、「逕行逮捕通知」本人及親\n友通知單各乙紙上之「乙○○」署名共肆枚、指印肆枚均沒收。應執行有期徒刑伍月\n，如易科罰金以參佰元折算壹日。偽造於桃園縣政府警察局中壢分局仁愛派出所第一\n、二次調查筆錄上之「乙○○」署名肆枚、指印伍枚、偽造於桃園縣警察局舉發違反\n道路交通管理事件通知單」上「收受通知聯者簽章」處「乙○○」之署名（該通知單\n上下二聯複印）共二枚、「桃園縣警察局舉發交通違規移置保管車輛通知單」上「車\n輛已無貴重物品駕駛人確認後簽章」處之「乙○○」署名一枚、指印一枚、口卡片上\n之「乙○○」署名一枚，指印伍枚、於「違反刑法第一百八十五條之三查獲後測試、\n觀察職務報告表」、「告知通知單」、「逕行逮捕通知」本人及親友通知單各乙紙上\n之「乙○○」署名、指印各肆枚均沒收。\n      事實及理由\n一、甲○○曾犯醉態駕駛罪，經法院判處拘役三十日，於民國九十二年十月二十八日\n    易科罰金執行完畢，仍不知悔改，於九十三年四月二十四日淩晨一時許，在桃園\n    縣中壢市○○○路某處飲酒後，已達不能安全駕駛動力交通工具程度，猶駕駛車\n    號SKE－５３６號輕型機車上路。嗣於同日一時十三分許，行經同市○○○路二\n    六一號前，經警攔檢進行酒精濃度測試，測得其呼氣酒精濃度每公升達０．八四\n    毫克，始知上情。詎甲○○為脫免刑責，竟基於偽造署押之接續犯意，先後於九\n    十三年四月二十四日一時四十分許、同日八時零分許，在桃園縣警察局中壢分局\n    仁愛派出所接受警員于永維詢問制作第一、二次調查筆錄時，冒用其友人「乙○\n    ○」之名應訊，在上開二份筆錄上，偽造「乙○○」署名共四枚、捺指印共五枚\n    ，足以生損害於乙○○及警詢筆錄之正確性。甲○○另基於偽造文書之接續犯意\n    ，先於九十三年四月二十四日淩晨一時十三分許，於員警開具之「桃園縣警察局\n    舉發違反道路交通管理事件通知單」上「收受通知聯者簽章」處，偽簽「乙○○\n    」之署名（該通知單上下二聯複印）共二枚、再於桃園縣警察局舉發交通違規移\n    置保管車輛通知單上「車輛已無貴重物品駕駛人確認後簽章」處偽簽「乙○○」\n    署名一枚、捺指印一枚、又於同日警方出示之口卡片上偽簽「乙○○」署名一枚\n    ，捺指印伍枚、於「違反刑法第一百八十五條之三查獲後測試、觀察職務報告表\n    」、「告知通知單」、「逕行逮捕通知」本人及親友通知單各乙紙上，偽簽「乙\n    ○○」署名共四枚、捺指印四枚，並將其中「舉發違反道路交通管理事件通知單\n    」、「口卡片」交還員警而行使之，足以生損害於乙○○本人及警察機關制作文\n    書及偵查犯罪之正確性。\n二、右揭事實，有１、被告於警詢、偵查中之自白。２、證人乙○○於警詢之證述。\n    ３、警詢筆錄二紙、舉發違反道路交通管理事件通知書二紙、移置保管車輛通知\n    單一紙、口卡片、違反刑法第一百八十五之三查獲後測試、觀察職務報告、告知\n    通知書各一紙、逕行逮捕通知書二紙在卷可證，其犯行已堪以認定。\n三、依刑事訴訟法第四百四十九條第一項，刑法第一百八十五條之三、第二百十六條\n    、第二百十條、第二百十七條、第四十一條第一項前段、第五十一條第五款、第\n    二百十九條，罰金罰鍰提高標準條例第二條，逕以簡易判決處刑如主文。\n四、如不服本判決，得於判決書送達之翌日起十日內，以書狀敘述理由，向本庭提出\n    上訴。\n中      華      民      國    九十三    年      八      月     十八     日\n                                  臺灣桃園地方法院刑事第四庭\n                                      法  官    陳世宗\n右正本證明與原本無異。\n如不服本判決，應於判決送達後十日內向本院提出上訴狀( 應附繕本 )。\n                                      書記官    沈秀珍\n中      華      民      國    九十三    年      八      月     十八    日\n附錄論罪科刑依據之法條：\n中華民國刑法第一百八十五條之三\n服用毒品、麻醉藥品、酒類或其他相類之物，不能安全駕駛動力交通工具\n而駕駛者，處一年以下有期徒刑、拘役或三萬元以下罰金。\n中華民國刑法第二百一十六條\n(行使偽造變造或登載不實之文書罪)\n行使第二百十條至第二百十五條之文書者，依偽造、變造文書或登載不實\n事項或使登載不實事項之規定處斷。\n中華民國刑法第二百一十條\n(偽造變造私文書罪)\n偽造、變造私文書，足以生損害於公眾或他人者，處五年以下有期徒刑。\n中華民國刑法第二百一十七條\n(偽造盜用印章印文或署押罪)\n偽造印章、印文或署押，足以生損害於公眾或他人者，處三年以下有期徒\n刑。\n盜用印章、印文或署押，足以生損害於公眾或他人者，亦同。\n",
  "structure": {
    "main": "甲○○服用酒類，不能安全駕駛動力交通工具而駕駛，處有期徒刑貳月，如易科罰金\n以參佰元折算壹日。又偽造署押，足以生損害於公眾及他人，處有期徒刑貳月，如易\n科罰金以參佰元折算壹日。偽造於桃園縣政府警察局中壢分局仁愛派出所第一、二次\n調查筆錄上之「乙○○」署名肆枚、指印伍枚均沒收。又行使偽造私文書，足以生損\n害於公眾或他人，處有期徒刑參月，如易科罰金以參佰元折算壹日。偽造於「桃園縣\n警察局舉發違反道路交通管理事件通知單」上「收受通知聯者簽章」處「乙○○」之\n署名（該通知單上下二聯複印）共二枚、「桃園縣警察局舉發交通違規移置保管車輛\n通知單」上「車輛已無貴重物品駕駛人確認後簽章」處之「乙○○」署名一枚、指印\n一枚、口卡片上之「乙○○」署名一枚，捺指印伍枚、於「違反刑法第一百八十五條\n之三查獲後測試、觀察職務報告表」、「告知通知單」、「逕行逮捕通知」本人及親\n友通知單各乙紙上之「乙○○」署名共肆枚、指印肆枚均沒收。應執行有期徒刑伍月\n，如易科罰金以參佰元折算壹日。偽造於桃園縣政府警察局中壢分局仁愛派出所第一\n、二次調查筆錄上之「乙○○」署名肆枚、指印伍枚、偽造於桃園縣警察局舉發違反\n道路交通管理事件通知單」上「收受通知聯者簽章」處「乙○○」之署名（該通知單\n上下二聯複印）共二枚、「桃園縣警察局舉發交通違規移置保管車輛通知單」上「車\n輛已無貴重物品駕駛人確認後簽章」處之「乙○○」署名一枚、指印一枚、口卡片上\n之「乙○○」署名一枚，指印伍枚、於「違反刑法第一百八十五條之三查獲後測試、\n觀察職務報告表」、「告知通知單」、「逕行逮捕通知」本人及親友通知單各乙紙上\n之「乙○○」署名、指印各肆枚均沒收。",
    "fact": "一、甲○○曾犯醉態駕駛罪，經法院判處拘役三十日，於民國九十二年十月二十八日\n    易科罰金執行完畢，仍不知悔改，於九十三年四月二十四日淩晨一時許，在桃園\n    縣中壢市○○○路某處飲酒後，已達不能安全駕駛動力交通工具程度，猶駕駛車\n    號SKE－５３６號輕型機車上路。嗣於同日一時十三分許，行經同市○○○路二\n    六一號前，經警攔檢進行酒精濃度測試，測得其呼氣酒精濃度每公升達０．八四\n    毫克，始知上情。詎甲○○為脫免刑責，竟基於偽造署押之接續犯意，先後於九\n    十三年四月二十四日一時四十分許、同日八時零分許，在桃園縣警察局中壢分局\n    仁愛派出所接受警員于永維詢問制作第一、二次調查筆錄時，冒用其友人「乙○\n    ○」之名應訊，在上開二份筆錄上，偽造「乙○○」署名共四枚、捺指印共五枚\n    ，足以生損害於乙○○及警詢筆錄之正確性。甲○○另基於偽造文書之接續犯意\n    ，先於九十三年四月二十四日淩晨一時十三分許，於員警開具之「桃園縣警察局\n    舉發違反道路交通管理事件通知單」上「收受通知聯者簽章」處，偽簽「乙○○\n    」之署名（該通知單上下二聯複印）共二枚、再於桃園縣警察局舉發交通違規移\n    置保管車輛通知單上「車輛已無貴重物品駕駛人確認後簽章」處偽簽「乙○○」\n    署名一枚、捺指印一枚、又於同日警方出示之口卡片上偽簽「乙○○」署名一枚\n    ，捺指印伍枚、於「違反刑法第一百八十五條之三查獲後測試、觀察職務報告表\n    」、「告知通知單」、「逕行逮捕通知」本人及親友通知單各乙紙上，偽簽「乙\n    ○○」署名共四枚、捺指印四枚，並將其中「舉發違反道路交通管理事件通知單\n    」、「口卡片」交還員警而行使之，足以生損害於乙○○本人及警察機關制作文\n    書及偵查犯罪之正確性。\n二、右揭事實，有１、被告於警詢、偵查中之自白。２、證人乙○○於警詢之證述。\n    ３、警詢筆錄二紙、舉發違反道路交通管理事件通知書二紙、移置保管車輛通知\n    單一紙、口卡片、違反刑法第一百八十五之三查獲後測試、觀察職務報告、告知\n    通知書各一紙、逕行逮捕通知書二紙在卷可證，其犯行已堪以認定。\n三、依刑事訴訟法第四百四十九條第一項，刑法第一百八十五條之三、第二百十六條\n    、第二百十條、第二百十七條、第四十一條第一項前段、第五十一條第五款、第\n    二百十九條，罰金罰鍰提高標準條例第二條，逕以簡易判決處刑如主文。\n四、如不服本判決，得於判決書送達之翌日起十日內，以書狀敘述理由，向本庭提出\n    上訴。",
    "reason": "一、甲○○曾犯醉態駕駛罪，經法院判處拘役三十日，於民國九十二年十月二十八日\n    易科罰金執行完畢，仍不知悔改，於九十三年四月二十四日淩晨一時許，在桃園\n    縣中壢市○○○路某處飲酒後，已達不能安全駕駛動力交通工具程度，猶駕駛車\n    號SKE－５３６號輕型機車上路。嗣於同日一時十三分許，行經同市○○○路二\n    六一號前，經警攔檢進行酒精濃度測試，測得其呼氣酒精濃度每公升達０．八四\n    毫克，始知上情。詎甲○○為脫免刑責，竟基於偽造署押之接續犯意，先後於九\n    十三年四月二十四日一時四十分許、同日八時零分許，在桃園縣警察局中壢分局\n    仁愛派出所接受警員于永維詢問制作第一、二次調查筆錄時，冒用其友人「乙○\n    ○」之名應訊，在上開二份筆錄上，偽造「乙○○」署名共四枚、捺指印共五枚\n    ，足以生損害於乙○○及警詢筆錄之正確性。甲○○另基於偽造文書之接續犯意\n    ，先於九十三年四月二十四日淩晨一時十三分許，於員警開具之「桃園縣警察局\n    舉發違反道路交通管理事件通知單」上「收受通知聯者簽章」處，偽簽「乙○○\n    」之署名（該通知單上下二聯複印）共二枚、再於桃園縣警察局舉發交通違規移\n    置保管車輛通知單上「車輛已無貴重物品駕駛人確認後簽章」處偽簽「乙○○」\n    署名一枚、捺指印一枚、又於同日警方出示之口卡片上偽簽「乙○○」署名一枚\n    ，捺指印伍枚、於「違反刑法第一百八十五條之三查獲後測試、觀察職務報告表\n    」、「告知通知單」、「逕行逮捕通知」本人及親友通知單各乙紙上，偽簽「乙\n    ○○」署名共四枚、捺指印四枚，並將其中「舉發違反道路交通管理事件通知單\n    」、「口卡片」交還員警而行使之，足以生損害於乙○○本人及警察機關制作文\n    書及偵查犯罪之正確性。\n二、右揭事實，有１、被告於警詢、偵查中之自白。２、證人乙○○於警詢之證述。\n    ３、警詢筆錄二紙、舉發違反道路交通管理事件通知書二紙、移置保管車輛通知\n    單一紙、口卡片、違反刑法第一百八十五之三查獲後測試、觀察職務報告、告知\n    通知書各一紙、逕行逮捕通知書二紙在卷可證，其犯行已堪以認定。\n三、依刑事訴訟法第四百四十九條第一項，刑法第一百八十五條之三、第二百十六條\n    、第二百十條、第二百十七條、第四十一條第一項前段、第五十一條第五款、第\n    二百十九條，罰金罰鍰提高標準條例第二條，逕以簡易判決處刑如主文。\n四、如不服本判決，得於判決書送達之翌日起十日內，以書狀敘述理由，向本庭提出\n    上訴。"
  },
  "search": "臺灣桃園地方法院刑事簡易判決九十三年度壢交簡字第一０三一號聲請人台灣桃園地方法院檢察署檢察官被告甲○○男二.右被告因公共危險等案件，經檢察官聲請以簡易判決處刑（九十三年度偵字第七四八七號號），本院判決如左：主文甲○○服用酒類，不能安全駕駛動力交通工具而駕駛，處有期徒刑貳月，如易科罰金以參佰元折算壹日。又偽造署押，足以生損害於公眾及他人，處有期徒刑貳月，如易科罰金以參佰元折算壹日。偽造於桃園縣政府警察局中壢分局仁愛派出所第一、二次調查筆錄上之「乙○○」署名肆枚、指印伍枚均沒收。又行使偽造私文書，足以生損害於公眾或他人，處有期徒刑參月，如易科罰金以參佰元折算壹日。偽造於「桃園縣警察局舉發違反道路交通管理事件通知單」上「收受通知聯者簽章」處「乙○○」之署名（該通知單上下二聯複印）共二枚、「桃園縣警察局舉發交通違規移置保管車輛通知單」上「車輛已無貴重物品駕駛人確認後簽章」處之「乙○○」署名一枚、指印一枚、口卡片上之「乙○○」署名一枚，捺指印伍枚、於「違反刑法第一百八十五條之三查獲後測試、觀察職務報告表」、「告知通知單」、「逕行逮捕通知」本人及親友通知單各乙紙上之「乙○○」署名共肆枚、指印肆枚均沒收。應執行有期徒刑伍月，如易科罰金以參佰元折算壹日。偽造於桃園縣政府警察局中壢分局仁愛派出所第一、二次調查筆錄上之「乙○○」署名肆枚、指印伍枚、偽造於桃園縣警察局舉發違反道路交通管理事件通知單」上「收受通知聯者簽章」處「乙○○」之署名（該通知單上下二聯複印）共二枚、「桃園縣警察局舉發交通違規移置保管車輛通知單」上「車輛已無貴重物品駕駛人確認後簽章」處之「乙○○」署名一枚、指印一枚、口卡片上之「乙○○」署名一枚，指印伍枚、於「違反刑法第一百八十五條之三查獲後測試、觀察職務報告表」、「告知通知單」、「逕行逮捕通知」本人及親友通知單各乙紙上之「乙○○」署名、指印各肆枚均沒收。事實及理由一、甲○○曾犯醉態駕駛罪，經法院判處拘役三十日，於民國九十二年十月二十八日易科罰金執行完畢，仍不知悔改，於九十三年四月二十四日淩晨一時許，在桃園縣中壢市○○○路某處飲酒後，已達不能安全駕駛動力交通工具程度，猶駕駛車號SKE－５３６號輕型機車上路。嗣於同日一時十三分許，行經同市○○○路二六一號前，經警攔檢進行酒精濃度測試，測得其呼氣酒精濃度每公升達０．八四毫克，始知上情。詎甲○○為脫免刑責，竟基於偽造署押之接續犯意，先後於九十三年四月二十四日一時四十分許、同日八時零分許，在桃園縣警察局中壢分局仁愛派出所接受警員于永維詢問制作第一、二次調查筆錄時，冒用其友人「乙○○」之名應訊，在上開二份筆錄上，偽造「乙○○」署名共四枚、捺指印共五枚，足以生損害於乙○○及警詢筆錄之正確性。甲○○另基於偽造文書之接續犯意，先於九十三年四月二十四日淩晨一時十三分許，於員警開具之「桃園縣警察局舉發違反道路交通管理事件通知單」上「收受通知聯者簽章」處，偽簽「乙○○」之署名（該通知單上下二聯複印）共二枚、再於桃園縣警察局舉發交通違規移置保管車輛通知單上「車輛已無貴重物品駕駛人確認後簽章」處偽簽「乙○○」署名一枚、捺指印一枚、又於同日警方出示之口卡片上偽簽「乙○○」署名一枚，捺指印伍枚、於「違反刑法第一百八十五條之三查獲後測試、觀察職務報告表」、「告知通知單」、「逕行逮捕通知」本人及親友通知單各乙紙上，偽簽「乙○○」署名共四枚、捺指印四枚，並將其中「舉發違反道路交通管理事件通知單」、「口卡片」交還員警而行使之，足以生損害於乙○○本人及警察機關制作文書及偵查犯罪之正確性。二、右揭事實，有１、被告於警詢、偵查中之自白。２、證人乙○○於警詢之證述。３、警詢筆錄二紙、舉發違反道路交通管理事件通知書二紙、移置保管車輛通知單一紙、口卡片、違反刑法第一百八十五之三查獲後測試、觀察職務報告、告知通知書各一紙、逕行逮捕通知書二紙在卷可證，其犯行已堪以認定。三、依刑事訴訟法第四百四十九條第一項，刑法第一百八十五條之三、第二百十六條、第二百十條、第二百十七條、第四十一條第一項前段、第五十一條第五款、第二百十九條，罰金罰鍰提高標準條例第二條，逕以簡易判決處刑如主文。四、如不服本判決，得於判決書送達之翌日起十日內，以書狀敘述理由，向本庭提出上訴。中華民國九十三年八月十八日臺灣桃園地方法院刑事第四庭法官陳世宗右正本證明與原本無異。如不服本判決，應於判決送達後十日內向本院提出上訴狀(應附繕本)。書記官沈秀珍中華民國九十三年八月十八日附錄論罪科刑依據之法條：中華民國刑法第一百八十五條之三服用毒品、麻醉藥品、酒類或其他相類之物，不能安全駕駛動力交通工具而駕駛者，處一年以下有期徒刑、拘役或三萬元以下罰金。中華民國刑法第二百一十六條(行使偽造變造或登載不實之文書罪)行使第二百十條至第二百十五條之文書者，依偽造、變造文書或登載不實事項或使登載不實事項之規定處斷。中華民國刑法第二百一十條(偽造變造私文書罪)偽造、變造私文書，足以生損害於公眾或他人者，處五年以下有期徒刑。中華民國刑法第二百一十七條(偽造盜用印章印文或署押罪)偽造印章、印文或署押，足以生損害於公眾或他人者，處三年以下有期徒刑。盜用印章、印文或署押，足以生損害於公眾或他人者，亦同。",
  "characters": {
    "judges": [
      "陳世宗"
    ],
    "prosecutors": [

    ],
    "lawyers": [

    ],
    "clerks": [
      "沈秀珍"
    ],
    "plaintiffs": [

    ],
    "defendants": [
      "甲○○  男  二.",
      "右被告因公共危險等案件，經檢察官聲請以簡易判決處刑（九十三年度偵字第七四八",
      "七號號），本院判決如左："
    ],
    "prosecutor_office": [
      "台灣桃園地方法院檢察署檢察官"
    ],
    "creditors": [

    ],
    "debtors": [

    ],
    "judicial_associate_officer": [

    ]
  },
  "adjudged_at": "2004-08-18",
  "created_at": "2016-02-06 01:45:39",
  "updated_at": "2016-02-06 01:45:39"
}