{
  "identify": "KSD-94-訴-1502-20050707-1",
  "court": {
    "name": "臺灣高雄地方法院",
    "code": "KSD"
  },
  "division": {
    "name": "民事",
    "code": "V"
  },
  "year": 94,
  "word": "訴",
  "number": "1502",
  "jcheck": "1",
  "reason": "返還不當得利",
  "content": "臺灣高雄地方法院民事裁定              94年度訴字第1502號\n原      告  丙○○\n            甲○○\n共同送達代收人  沈志祥律師\n被      告  乙○○\n當事人間請求返還不當得利事件，本院裁定如下：\n  主  文\n原告之訴及假執行之聲請均駁回。\n訴訟費用由原告負擔。\n  理  由\n一、按，提起民事訴訟，應依民事訴訟法第3 章第2 節之相關規\n    定繳納裁判費，此為必須具備之程式。又，起訴不合程式者\n    ，法院應以裁定駁回之，民事訴訟法第249 條第1 項第6 款\n    訂有明文。\n二、本件原告起訴，未據繳納裁判費，經本院於民國94年6 月15\n    日裁定命原告於5 日內補正，此裁定已於民國94年6 月23日\n    送達原告，有送達證書附卷可憑。\n三、原告逾期迄未補正，其訴顯難認為合法，又假執行之聲請亦\n    缺乏宣告依據，均應予以駁回。\n四、依民事訴訟法第249 條第1 項第6 款、第95條、第78條，裁\n    定如主文。\n中    華    民    國    94    年    7     月    7     日\n                  民事鳳山分庭法  官  郭文通\n正本係照原本作成。\n如不服本裁定應於送達後10日內向本院提出抗告狀，並繳納裁判\n費新台幣1,000元。\n中    華    民    國    94    年    7     月    7     日\n                                書記官  李崑良\n",
  "structure": {
    "main": "原告之訴及假執行之聲請均駁回。\n訴訟費用由原告負擔。",
    "reason": "一、按，提起民事訴訟，應依民事訴訟法第3 章第2 節之相關規\n    定繳納裁判費，此為必須具備之程式。又，起訴不合程式者\n    ，法院應以裁定駁回之，民事訴訟法第249 條第1 項第6 款\n    訂有明文。\n二、本件原告起訴，未據繳納裁判費，經本院於民國94年6 月15\n    日裁定命原告於5 日內補正，此裁定已於民國94年6 月23日\n    送達原告，有送達證書附卷可憑。\n三、原告逾期迄未補正，其訴顯難認為合法，又假執行之聲請亦\n    缺乏宣告依據，均應予以駁回。\n四、依民事訴訟法第249 條第1 項第6 款、第95條、第78條，裁\n    定如主文。"
  },
  "search": "臺灣高雄地方法院民事裁定94年度訴字第1502號原告丙○○甲○○共同送達代收人沈志祥律師被告乙○○當事人間請求返還不當得利事件，本院裁定如下：主文原告之訴及假執行之聲請均駁回。訴訟費用由原告負擔。理由一、按，提起民事訴訟，應依民事訴訟法第3章第2節之相關規定繳納裁判費，此為必須具備之程式。又，起訴不合程式者，法院應以裁定駁回之，民事訴訟法第249條第1項第6款訂有明文。二、本件原告起訴，未據繳納裁判費，經本院於民國94年6月15日裁定命原告於5日內補正，此裁定已於民國94年6月23日送達原告，有送達證書附卷可憑。三、原告逾期迄未補正，其訴顯難認為合法，又假執行之聲請亦缺乏宣告依據，均應予以駁回。四、依民事訴訟法第249條第1項第6款、第95條、第78條，裁定如主文。中華民國94年7月7日民事鳳山分庭法官郭文通正本係照原本作成。如不服本裁定應於送達後10日內向本院提出抗告狀，並繳納裁判費新台幣1,000元。中華民國94年7月7日書記官李崑良",
  "characters": {
    "judges": [
      "郭文通"
    ],
    "prosecutors": [

    ],
    "lawyers": [
      "沈志祥"
    ],
    "clerks": [
      "李崑良"
    ],
    "plaintiffs": [
      "丙"
    ],
    "defendants": [
      "乙○○",
      "當事人間請求返還不當得利事件，本院裁定如下："
    ],
    "prosecutor_office": [

    ],
    "creditors": [

    ],
    "debtors": [

    ],
    "judicial_associate_officer": [

    ]
  },
  "adjudged_at": "2005-07-07",
  "created_at": "2016-02-07 09:31:04",
  "updated_at": "2016-02-07 09:31:04"
}