{
  "identify": "TCD-94-醫-13-20050707-1",
  "court": {
    "name": "臺灣臺中地方法院",
    "code": "TCD"
  },
  "division": {
    "name": "民事",
    "code": "V"
  },
  "year": 94,
  "word": "醫",
  "number": "13",
  "jcheck": "1",
  "reason": "損害賠償",
  "content": "臺灣臺中地方法院民事裁定  94年度醫字第13號\n原      告  丙○○\n訴訟代理人  熊賢祺律師\n複代理人    丁○○\n被      告  中國醫藥大學附設醫院\n法定代理人  戊○○\n被      告  甲○○\n被      告  乙○○\n前列三人共同\n訴訟代理人  曾慶崇律師\n前列三人共同\n複代理人    林伸全律師\n當事人間損害賠償事件，本院裁定如下：\n    主    文\n本件於台灣高等法院台中分院94年度上字第716、720、721號過\n失傷害案件刑事訴訟終結前，停止訴訟程序。\n    理    由\n一、查本件被告甲○○、乙○○涉有過失傷害犯罪嫌疑，經台灣\n    高等法院台中分院94年度上字第716、720、721號刑事庭審\n    理中，該犯罪成立與否，確有影響於本件民事訴訟之裁判非\n    俟刑事訴訟終結，其民事訴訟即無由判斷，本院認有裁定停\n    止本件民事訴訟程序之必要。\n二、依民事訴訟法第一百八十三條，裁定如主文。\n中    華    民    國    94    年    7     月    7     日\n                  民事第一庭    法  官  吳蕙玟\n正本係照原本作成。\n如不服本裁定應於送達後10日內向本院提出抗告狀，並繳納抗告\n費新臺幣1000元。如對本裁定抗告須於裁定送達後10日內向本院\n提出抗告狀。\n中    華    民    國    94    年    7     月    7     日\n                                書記官  黃鴻鑑\n",
  "structure": {
    "main": "本件於台灣高等法院台中分院94年度上字第716、720、721號過\n失傷害案件刑事訴訟終結前，停止訴訟程序。",
    "reason": "一、查本件被告甲○○、乙○○涉有過失傷害犯罪嫌疑，經台灣\n    高等法院台中分院94年度上字第716、720、721號刑事庭審\n    理中，該犯罪成立與否，確有影響於本件民事訴訟之裁判非\n    俟刑事訴訟終結，其民事訴訟即無由判斷，本院認有裁定停\n    止本件民事訴訟程序之必要。\n二、依民事訴訟法第一百八十三條，裁定如主文。"
  },
  "search": "臺灣臺中地方法院民事裁定94年度醫字第13號原告丙○○訴訟代理人熊賢祺律師複代理人丁○○被告中國醫藥大學附設醫院法定代理人戊○○被告甲○○被告乙○○前列三人共同訴訟代理人曾慶崇律師前列三人共同複代理人林伸全律師當事人間損害賠償事件，本院裁定如下：主文本件於台灣高等法院台中分院94年度上字第716、720、721號過失傷害案件刑事訴訟終結前，停止訴訟程序。理由一、查本件被告甲○○、乙○○涉有過失傷害犯罪嫌疑，經台灣高等法院台中分院94年度上字第716、720、721號刑事庭審理中，該犯罪成立與否，確有影響於本件民事訴訟之裁判非俟刑事訴訟終結，其民事訴訟即無由判斷，本院認有裁定停止本件民事訴訟程序之必要。二、依民事訴訟法第一百八十三條，裁定如主文。中華民國94年7月7日民事第一庭法官吳蕙玟正本係照原本作成。如不服本裁定應於送達後10日內向本院提出抗告狀，並繳納抗告費新臺幣1000元。如對本裁定抗告須於裁定送達後10日內向本院提出抗告狀。中華民國94年7月7日書記官黃鴻鑑",
  "characters": {
    "judges": [
      "吳蕙玟"
    ],
    "prosecutors": [

    ],
    "lawyers": [
      "熊賢祺",
      "曾慶崇",
      "林伸全"
    ],
    "clerks": [
      "黃鴻鑑"
    ],
    "plaintiffs": [
      "丙"
    ],
    "defendants": [
      "中國醫藥大學附設醫院",
      "甲○○",
      "被      告  乙○○",
      "前列三人共同"
    ],
    "prosecutor_office": [

    ],
    "creditors": [

    ],
    "debtors": [

    ],
    "judicial_associate_officer": [

    ]
  },
  "adjudged_at": "2005-07-07",
  "created_at": "2016-02-07 09:35:39",
  "updated_at": "2016-02-07 09:35:39"
}