{
  "identify": "TPB-93-訴-2605-20050707-1",
  "court": {
    "name": "臺北高等行政法院",
    "code": "TPB"
  },
  "division": {
    "name": "行政",
    "code": "A"
  },
  "year": 93,
  "word": "訴",
  "number": "2605",
  "jcheck": "1",
  "reason": "敬老福利生活津貼",
  "content": "臺北高等行政法院判決\n                                93年度訴字第02605號\n                              .\n原      告  甲○\n訴訟代理人  戊○○\n被      告  內政部\n代  表  人  乙○○部長）住同.\n訴訟代理人  己○○\n            丁○○\n            丙○○\n上列當事人間因敬老福利生活津貼事件，原告不服行政院中華民\n國93年6月2日院臺訴字第0930085371號訴願決定，提起行政訴訟\n。本院判決如下：\n    主  文\n原告之訴駁回。\n訴訟費用由原告負擔。\n    事  實\n一、事實概要：\n    原告於民國（下同）92年7月7日申請敬老福利生活津貼，經\n    被告委託之勞工保險局（下稱勞保局）核付92年7月至92年\n    12 月敬老福利生活津貼每月新臺幣（下同）3,000元，計\n    18,000元。嗣勞保局以原告已於台灣糖業股份有限公司（下\n    稱台糖公司）領取一次退休金，自不得請領本津貼，乃以93\n    年3月1日保受福字第6617453號函（下稱原處分）請原告繳\n    還溢領敬老福利生活津貼計18,000元。原告不服，提起訴願\n    ，經遭駁回，遂提起行政訴訟。\n二、兩造聲明：\n  (一)原告聲明：\n    1.訴願決定及原處分均撤銷。\n    2.被告應繼續核發原告敬老生活津貼每月3,000元。\n   (二)被告聲明：\n    1.駁回原告之訴。\n    2.訴訟費用由原告負擔。\n三、兩造之主張：\n  (一)原告主張之理由：\n    1.行政院訴願決定駁回原告之請求，係以原告應知自台糖公\n      司退休時，已領取一次退休金，依法不得請領敬老津貼，\n      卻仍提出申請，且申請時未陳述或檢附公營事業退休之重\n      要事項資料，依行政程序法第119條第2款規定，其信賴不\n      值得保護，顯與事實不符。原告出生於18年，幼年時期正\n      逢二次世界大戰，完全未受教育至今70餘歲，僅認識一些\n      較簡單之中文字，怎有可能知道本身依法不得請領敬老津\n      貼，更何況原告是收受屏東市公所之通知才被動前往辦理\n      ，辦理時承辦人員只告知，滿65歲都有，即核對身分證及\n      收取影本，填具之帳號及蓋章亦由承辦人員代勞，根本沒\n      有要求陳述及提供其他任何資料。原告應其要求所提供之\n      資料僅有身分證影本及存摺影本，兩者皆為正確資料並無\n      所謂不正確資料，承辦人員亦未向原告詢問其他任何事項\n      ，何來所謂不完全陳述。\n    2.91年度出版的中華民國立法院大事記將制定敬老福利津貼\n      暫行條例列於衛生環境及社會福利，由此可見領取敬老津\n      貼乃是福利，原告於台糖公司領取之一次退休金，乃原告\n      受雇台糖公司20餘年，提供勞務之對價，與民營企業勞工\n      領取之退休金完全基於同一權利義務關係，被告怎可予以\n      排除原告領取該津貼之資格呢？西方著名的基督教大師奧\n      古斯丁說：「就算是強盜分配戰利品也要講求公平原則」\n      。「中華民國人民，無分男女、宗教、種族、階級、黨派\n      ，在法律上一律平等。」「凡人民之其他自由及權利，不\n      妨害社會秩序公共利益者，均受憲法之保障。」「以上各\n      條例列舉之自由權利，除為防止妨礙他人自由，避免緊急\n      危難，維持社會秩序或增進公共利益所必要者，不得以法\n      律限制之。」中華民國憲法第7條、第22條、第23條分別\n      定有明文，勞保局依據敬老津貼暫行條例之規定排除原告\n      之請領資格，顯係違反憲法之平等原則，自屬無效之行政\n      處分。\n    3.退一步而言即使原處分無違憲法平等原則，原告亦有信賴\n      利益保護原則之適用，行政程序法第8條規定，行政行為\n      ，應以誠實信用之方法為之，並應保護人民正當合理之信\n      賴，原告係經屏東市公所主動通知前往里辦公處申請敬老\n      津貼，而屏東市公所亦是依據勞保局所列之名冊而通知原\n      告，且經勞保局之審核之後才發給敬老津貼，有敬老福利\n      生活津貼申請書審核欄可茲為證。行政程序法第9條規定\n      ，行政機關就該管行政程序，應於當事人有利及不利之情\n      形一律注意。勞保局未依法定注意義務執行法定職務，自\n      不得要求原告繳回溢領之敬老津貼。\n    4.另參酌訴願法第80條及行政程序法第117條第2款、第119\n      條明定行政機關可否撤銷違法授益行政處分應予斟酌之要\n      件，即受益人有信賴授予利益之行政處分之事實；受益人\n      並無信賴不值得保護之情形；受益人之信賴利益顯然大於\n      撤銷所欲維護之公益時，該授益處分不得撤銷。按改制前\n      行政法院76年判字第474號判決略謂：「公法上之爭訟，\n      有信賴保護原則之適用，即當事人信賴行政機關之決定，\n      已就其生活關係有適當之安排者，必須給予保護或給予合\n      理之補償。」，又改制前行政法院83年判字第560號判決\n      「授予人民利益之行政處分，因違法而發生是否應予撤銷\n      時，依一般行政法理，應委諸行政機關裁量，故行政機關\n      對於公益與信賴利益之孰輕孰重，自應加以審酌衡量，如\n      撤銷對公益有重大危害或受益人之信賴利益，顯然大於撤\n      銷所欲維護之公益，且其信賴並無不值得保護之情形時，\n      自不得輕言撤銷該違法之行政處分。」及改制前行政法院\n      83年判字第151號判決：「行政機關審酌是否撤銷授予利\n      益之違法行政處分時，除受益人具有：以詐欺、脅迫或賄\n      賂方法使行政機關作成行政處分，對重要事項提出不正確\n      資料或為不完全陳述致行政機關依該資料或據不完全陳述\n      致行政機關依該資料或陳述而作成行政處分，明知處分違\n      法或因重大過失而不知等信賴不值得保護之情形外，依行\n      政法上信賴保護原則，為撤銷之行政機關應顧及受益人之\n      信賴保護利益。」。\n    5.原告領取之敬老津貼18,000元，此屬於連續之金錢給付，\n      原告信賴該行政處分之存續，且已使用所提供之給付，原\n      告具有值得保護之信賴利益，此外該敬老津貼並非原告基\n      於詐欺、脅迫或賄賂方法所獲得，亦非對重要事項提供不\n      正確資料或為不完全陳述，致使行政機關陷於錯誤而作成\n      行政處分，又此次申領敬老津貼係經由屏東縣屏東市公所\n      所發函通知原告前往辦理，發動權在於行政機關。因此原\n      告並不知核付津貼之行政處分是違法的。參諸前揭行政法\n      院判決意旨所示，原告之信賴並無不值得保護之情形，仍\n      應有信賴保護原則之適用。\n  (二)被告主張之理由：\n    1.按年滿65歲，在國內設有戶籍，且於最近3年內每年居住\n      超過183日之國民，未有領取軍人退休俸（終身生活補助\n      費）、政務人員、公教人員、公營事業人員月退休（職）\n      金或一次退休金者，得請領敬老福利生活津貼，每月\n      3,000元，為敬老福利生活津貼暫行條例第3條第1項第2款\n      所規定。敬老福利生活津貼之規劃主要在因應台灣老年人\n      口快速成長，並秉持福利資源不重複配置、政府財政負擔\n      考量與公平性原則，屬於對從未領有軍公教退休金、政府\n      補助或津貼者之補充性福利措施，以便於國民年金實施前\n      ，協助維持長者之基本生活。\n    2.原告所提有信賴利益保護原則之適用，查敬老福利生活津\n      貼申請書背後已列明不符合請領資格之排除條件其中一點\n      即已領取公營事業人員月退休（職）金或一次退休金者，\n      不得請領敬老福利生活津貼，而申請書正面書明「本人如\n      不符資格而領取敬老福利生活津貼，其溢領金額願意由本\n      人或法定繼承人負責繳還，並負相關法律責任」，原告在\n      申請書上蓋章表示同意明瞭，伊既已領取公營事業人員一\n      次退休金並於訴願書自己陳明承認，已不符合請領資格卻\n      仍向勞保局提出申請本津貼，基此，其並無值得保護之信\n      賴利益，原告須依法為此一溢領案負返還責任。\n    理  由\n一、按年滿65歲，在國內設有戶籍，且於最近3年內每年居住超\n    過183日之國民，未有領取軍人退休俸（終身生活補助費）\n    、政務人員、公教人員、公營事業人員月退休（職）金或一\n    次退休金情事者，得請領敬老福利生活津貼，每月3,000元\n    ，為敬老福利生活津貼暫行條例第3條第1項第2款所規定。\n    又「不符合請領資格而領取本津貼者，其溢領之津貼，經以\n    書面命本人或其法定繼承人自事實發生之日起60日內繳還；\n    屆期未繳還者，依法移送強制執行。」復為同條例第10條所\n    明定。\n二、本件原告於92年7月7日申請敬老福利生活津貼，經勞保局核\n    付92年7月至92年12月敬老福利生活津貼每月3,000元，計\n    18,000元，因原告於73年6月30日自台糖公司退休，領取公\n    營事業人員一次退休金，有資格檔資料明細查詢附勞保局卷\n    可稽，勞保局以原告不得請領敬老福利生活津貼，請其繳還\n    溢領敬老福利生活津貼計18,000元，揆諸首揭規定，並無不\n    合。原告主張勞保局依據敬老津貼暫行條例之規定排除原告\n    之請領資格，顯係違反憲法之平等原則，自屬無效之行政處\n    分云云，並不足採。原告雖另主張其有信賴保護原則之適用\n    云云。經查原告據以申請之敬老福利生活津貼申請書背面所\n    列請領敬老福利生活津貼說明第1點 (三)，明確記載已領取\n    公營事業人員月退休（職）金或一次退休金者，不具請領資\n    格，有該申請書影本附訴願卷為證，申請書正面則記載「本\n    人如不符資格而領取敬老福利生活津貼，其溢領金額願意由\n    本人或法定繼承人負責繳還，並負相關法律責任」等語，並\n    經原告蓋章確認，且此亦為法律之規定，申請人不得諉為不\n    知，是原告知其自台灣糖業公司退休時已領取一次退休金，\n    其申請時就其已領取公營事業人員退休金之重要事項未為完\n    全陳述，致勞保局依其陳述 (申請書所載)准其領取敬老福\n    利生活津貼，依行政程序法第119條第2款規定，其信賴不值\n    得保護，原告此部分之主張並不足採。\n三、原處分以原告已於台糖公司領取一次退休金，不得請領領取\n    敬老福利生活津貼，令原告繳還溢領敬老福利生活津貼計\n    18,000元，含有認定原告不符請領領取敬老福利生活津貼資\n    格之效力，原告自不得請求發給此項津貼，是原告請求被告\n    應繼續核發原告敬老生活津貼每月3,000元，並無理由，亦\n    應駁回。\n四、從而，原處分命原告繳還溢領敬老福利生活津貼計18,000元\n    ，並無違法，訴願決定予以維持，亦無不合。原告訴請撤銷\n    ，並請求被告應繼續核發原告敬老生活津貼每月3,000元，\n    為無理由，應予駁回。\n五、據上論結，本件原告之訴為無理由，爰依行政訴訟法第98條\n    第3項前段，判決如主文。\n中    華    民    國    94     年     7    月     7   日\n                        第一庭審判長法  官 姜素娥\n                                    法  官 陳秀\n                                   法  官 吳東都\n上為正本係照原本作成。\n如不服本判決，應於送達後20日內，向本院提出上訴狀並表明上\n訴理由，如於本判決宣示後送達前提起上訴者，應於判決送達後\n20日內補提上訴理由書（須按他造人數附繕本）。\n中    華    民    國    94     年     7    月     7   日\n                                    書記官 李金釵\n",
  "structure": {
    "main": "原告之訴駁回。\n訴訟費用由原告負擔。",
    "fact": "一、事實概要：\n    原告於民國（下同）92年7月7日申請敬老福利生活津貼，經\n    被告委託之勞工保險局（下稱勞保局）核付92年7月至92年\n    12 月敬老福利生活津貼每月新臺幣（下同）3,000元，計\n    18,000元。嗣勞保局以原告已於台灣糖業股份有限公司（下\n    稱台糖公司）領取一次退休金，自不得請領本津貼，乃以93\n    年3月1日保受福字第6617453號函（下稱原處分）請原告繳\n    還溢領敬老福利生活津貼計18,000元。原告不服，提起訴願\n    ，經遭駁回，遂提起行政訴訟。\n二、兩造聲明：\n  (一)原告聲明：\n    1.訴願決定及原處分均撤銷。\n    2.被告應繼續核發原告敬老生活津貼每月3,000元。\n   (二)被告聲明：\n    1.駁回原告之訴。\n    2.訴訟費用由原告負擔。\n三、兩造之主張：\n  (一)原告主張之理由：\n    1.行政院訴願決定駁回原告之請求，係以原告應知自台糖公\n      司退休時，已領取一次退休金，依法不得請領敬老津貼，\n      卻仍提出申請，且申請時未陳述或檢附公營事業退休之重\n      要事項資料，依行政程序法第119條第2款規定，其信賴不\n      值得保護，顯與事實不符。原告出生於18年，幼年時期正\n      逢二次世界大戰，完全未受教育至今70餘歲，僅認識一些\n      較簡單之中文字，怎有可能知道本身依法不得請領敬老津\n      貼，更何況原告是收受屏東市公所之通知才被動前往辦理\n      ，辦理時承辦人員只告知，滿65歲都有，即核對身分證及\n      收取影本，填具之帳號及蓋章亦由承辦人員代勞，根本沒\n      有要求陳述及提供其他任何資料。原告應其要求所提供之\n      資料僅有身分證影本及存摺影本，兩者皆為正確資料並無\n      所謂不正確資料，承辦人員亦未向原告詢問其他任何事項\n      ，何來所謂不完全陳述。\n    2.91年度出版的中華民國立法院大事記將制定敬老福利津貼\n      暫行條例列於衛生環境及社會福利，由此可見領取敬老津\n      貼乃是福利，原告於台糖公司領取之一次退休金，乃原告\n      受雇台糖公司20餘年，提供勞務之對價，與民營企業勞工\n      領取之退休金完全基於同一權利義務關係，被告怎可予以\n      排除原告領取該津貼之資格呢？西方著名的基督教大師奧\n      古斯丁說：「就算是強盜分配戰利品也要講求公平原則」\n      。「中華民國人民，無分男女、宗教、種族、階級、黨派\n      ，在法律上一律平等。」「凡人民之其他自由及權利，不\n      妨害社會秩序公共利益者，均受憲法之保障。」「以上各\n      條例列舉之自由權利，除為防止妨礙他人自由，避免緊急\n      危難，維持社會秩序或增進公共利益所必要者，不得以法\n      律限制之。」中華民國憲法第7條、第22條、第23條分別\n      定有明文，勞保局依據敬老津貼暫行條例之規定排除原告\n      之請領資格，顯係違反憲法之平等原則，自屬無效之行政\n      處分。\n    3.退一步而言即使原處分無違憲法平等原則，原告亦有信賴\n      利益保護原則之適用，行政程序法第8條規定，行政行為\n      ，應以誠實信用之方法為之，並應保護人民正當合理之信\n      賴，原告係經屏東市公所主動通知前往里辦公處申請敬老\n      津貼，而屏東市公所亦是依據勞保局所列之名冊而通知原\n      告，且經勞保局之審核之後才發給敬老津貼，有敬老福利\n      生活津貼申請書審核欄可茲為證。行政程序法第9條規定\n      ，行政機關就該管行政程序，應於當事人有利及不利之情\n      形一律注意。勞保局未依法定注意義務執行法定職務，自\n      不得要求原告繳回溢領之敬老津貼。\n    4.另參酌訴願法第80條及行政程序法第117條第2款、第119\n      條明定行政機關可否撤銷違法授益行政處分應予斟酌之要\n      件，即受益人有信賴授予利益之行政處分之事實；受益人\n      並無信賴不值得保護之情形；受益人之信賴利益顯然大於\n      撤銷所欲維護之公益時，該授益處分不得撤銷。按改制前\n      行政法院76年判字第474號判決略謂：「公法上之爭訟，\n      有信賴保護原則之適用，即當事人信賴行政機關之決定，\n      已就其生活關係有適當之安排者，必須給予保護或給予合\n      理之補償。」，又改制前行政法院83年判字第560號判決\n      「授予人民利益之行政處分，因違法而發生是否應予撤銷\n      時，依一般行政法理，應委諸行政機關裁量，故行政機關\n      對於公益與信賴利益之孰輕孰重，自應加以審酌衡量，如\n      撤銷對公益有重大危害或受益人之信賴利益，顯然大於撤\n      銷所欲維護之公益，且其信賴並無不值得保護之情形時，\n      自不得輕言撤銷該違法之行政處分。」及改制前行政法院\n      83年判字第151號判決：「行政機關審酌是否撤銷授予利\n      益之違法行政處分時，除受益人具有：以詐欺、脅迫或賄\n      賂方法使行政機關作成行政處分，對重要事項提出不正確\n      資料或為不完全陳述致行政機關依該資料或據不完全陳述\n      致行政機關依該資料或陳述而作成行政處分，明知處分違\n      法或因重大過失而不知等信賴不值得保護之情形外，依行\n      政法上信賴保護原則，為撤銷之行政機關應顧及受益人之\n      信賴保護利益。」。\n    5.原告領取之敬老津貼18,000元，此屬於連續之金錢給付，\n      原告信賴該行政處分之存續，且已使用所提供之給付，原\n      告具有值得保護之信賴利益，此外該敬老津貼並非原告基\n      於詐欺、脅迫或賄賂方法所獲得，亦非對重要事項提供不\n      正確資料或為不完全陳述，致使行政機關陷於錯誤而作成\n      行政處分，又此次申領敬老津貼係經由屏東縣屏東市公所\n      所發函通知原告前往辦理，發動權在於行政機關。因此原\n      告並不知核付津貼之行政處分是違法的。參諸前揭行政法\n      院判決意旨所示，原告之信賴並無不值得保護之情形，仍\n      應有信賴保護原則之適用。\n  (二)被告主張之理由：\n    1.按年滿65歲，在國內設有戶籍，且於最近3年內每年居住\n      超過183日之國民，未有領取軍人退休俸（終身生活補助\n      費）、政務人員、公教人員、公營事業人員月退休（職）\n      金或一次退休金者，得請領敬老福利生活津貼，每月\n      3,000元，為敬老福利生活津貼暫行條例第3條第1項第2款\n      所規定。敬老福利生活津貼之規劃主要在因應台灣老年人\n      口快速成長，並秉持福利資源不重複配置、政府財政負擔\n      考量與公平性原則，屬於對從未領有軍公教退休金、政府\n      補助或津貼者之補充性福利措施，以便於國民年金實施前\n      ，協助維持長者之基本生活。\n    2.原告所提有信賴利益保護原則之適用，查敬老福利生活津\n      貼申請書背後已列明不符合請領資格之排除條件其中一點\n      即已領取公營事業人員月退休（職）金或一次退休金者，\n      不得請領敬老福利生活津貼，而申請書正面書明「本人如\n      不符資格而領取敬老福利生活津貼，其溢領金額願意由本\n      人或法定繼承人負責繳還，並負相關法律責任」，原告在\n      申請書上蓋章表示同意明瞭，伊既已領取公營事業人員一\n      次退休金並於訴願書自己陳明承認，已不符合請領資格卻\n      仍向勞保局提出申請本津貼，基此，其並無值得保護之信\n      賴利益，原告須依法為此一溢領案負返還責任。",
    "reason": "一、按年滿65歲，在國內設有戶籍，且於最近3年內每年居住超\n    過183日之國民，未有領取軍人退休俸（終身生活補助費）\n    、政務人員、公教人員、公營事業人員月退休（職）金或一\n    次退休金情事者，得請領敬老福利生活津貼，每月3,000元\n    ，為敬老福利生活津貼暫行條例第3條第1項第2款所規定。\n    又「不符合請領資格而領取本津貼者，其溢領之津貼，經以\n    書面命本人或其法定繼承人自事實發生之日起60日內繳還；\n    屆期未繳還者，依法移送強制執行。」復為同條例第10條所\n    明定。\n二、本件原告於92年7月7日申請敬老福利生活津貼，經勞保局核\n    付92年7月至92年12月敬老福利生活津貼每月3,000元，計\n    18,000元，因原告於73年6月30日自台糖公司退休，領取公\n    營事業人員一次退休金，有資格檔資料明細查詢附勞保局卷\n    可稽，勞保局以原告不得請領敬老福利生活津貼，請其繳還\n    溢領敬老福利生活津貼計18,000元，揆諸首揭規定，並無不\n    合。原告主張勞保局依據敬老津貼暫行條例之規定排除原告\n    之請領資格，顯係違反憲法之平等原則，自屬無效之行政處\n    分云云，並不足採。原告雖另主張其有信賴保護原則之適用\n    云云。經查原告據以申請之敬老福利生活津貼申請書背面所\n    列請領敬老福利生活津貼說明第1點 (三)，明確記載已領取\n    公營事業人員月退休（職）金或一次退休金者，不具請領資\n    格，有該申請書影本附訴願卷為證，申請書正面則記載「本\n    人如不符資格而領取敬老福利生活津貼，其溢領金額願意由\n    本人或法定繼承人負責繳還，並負相關法律責任」等語，並\n    經原告蓋章確認，且此亦為法律之規定，申請人不得諉為不\n    知，是原告知其自台灣糖業公司退休時已領取一次退休金，\n    其申請時就其已領取公營事業人員退休金之重要事項未為完\n    全陳述，致勞保局依其陳述 (申請書所載)准其領取敬老福\n    利生活津貼，依行政程序法第119條第2款規定，其信賴不值\n    得保護，原告此部分之主張並不足採。\n三、原處分以原告已於台糖公司領取一次退休金，不得請領領取\n    敬老福利生活津貼，令原告繳還溢領敬老福利生活津貼計\n    18,000元，含有認定原告不符請領領取敬老福利生活津貼資\n    格之效力，原告自不得請求發給此項津貼，是原告請求被告\n    應繼續核發原告敬老生活津貼每月3,000元，並無理由，亦\n    應駁回。\n四、從而，原處分命原告繳還溢領敬老福利生活津貼計18,000元\n    ，並無違法，訴願決定予以維持，亦無不合。原告訴請撤銷\n    ，並請求被告應繼續核發原告敬老生活津貼每月3,000元，\n    為無理由，應予駁回。\n五、據上論結，本件原告之訴為無理由，爰依行政訴訟法第98條\n    第3項前段，判決如主文。\n中    華    民    國    94     年     7    月     7   日\n                        第一庭審判長法  官 姜素娥\n                                    法  官 陳秀\n                                   法  官 吳東都\n上為正本係照原本作成。\n如不服本判決，應於送達後20日內，向本院提出上訴狀並表明上\n訴理由，如於本判決宣示後送達前提起上訴者，應於判決送達後\n20日內補提上訴理由書（須按他造人數附繕本）。"
  },
  "search": "臺北高等行政法院判決93年度訴字第02605號.原告甲○訴訟代理人戊○○被告內政部代表人乙○○部長）住同.訴訟代理人己○○丁○○丙○○上列當事人間因敬老福利生活津貼事件，原告不服行政院中華民國93年6月2日院臺訴字第0930085371號訴願決定，提起行政訴訟。本院判決如下：主文原告之訴駁回。訴訟費用由原告負擔。事實一、事實概要：原告於民國（下同）92年7月7日申請敬老福利生活津貼，經被告委託之勞工保險局（下稱勞保局）核付92年7月至92年12月敬老福利生活津貼每月新臺幣（下同）3,000元，計18,000元。嗣勞保局以原告已於台灣糖業股份有限公司（下稱台糖公司）領取一次退休金，自不得請領本津貼，乃以93年3月1日保受福字第6617453號函（下稱原處分）請原告繳還溢領敬老福利生活津貼計18,000元。原告不服，提起訴願，經遭駁回，遂提起行政訴訟。二、兩造聲明：(一)原告聲明：1.訴願決定及原處分均撤銷。2.被告應繼續核發原告敬老生活津貼每月3,000元。(二)被告聲明：1.駁回原告之訴。2.訴訟費用由原告負擔。三、兩造之主張：(一)原告主張之理由：1.行政院訴願決定駁回原告之請求，係以原告應知自台糖公司退休時，已領取一次退休金，依法不得請領敬老津貼，卻仍提出申請，且申請時未陳述或檢附公營事業退休之重要事項資料，依行政程序法第119條第2款規定，其信賴不值得保護，顯與事實不符。原告出生於18年，幼年時期正逢二次世界大戰，完全未受教育至今70餘歲，僅認識一些較簡單之中文字，怎有可能知道本身依法不得請領敬老津貼，更何況原告是收受屏東市公所之通知才被動前往辦理，辦理時承辦人員只告知，滿65歲都有，即核對身分證及收取影本，填具之帳號及蓋章亦由承辦人員代勞，根本沒有要求陳述及提供其他任何資料。原告應其要求所提供之資料僅有身分證影本及存摺影本，兩者皆為正確資料並無所謂不正確資料，承辦人員亦未向原告詢問其他任何事項，何來所謂不完全陳述。2.91年度出版的中華民國立法院大事記將制定敬老福利津貼暫行條例列於衛生環境及社會福利，由此可見領取敬老津貼乃是福利，原告於台糖公司領取之一次退休金，乃原告受雇台糖公司20餘年，提供勞務之對價，與民營企業勞工領取之退休金完全基於同一權利義務關係，被告怎可予以排除原告領取該津貼之資格呢？西方著名的基督教大師奧古斯丁說：「就算是強盜分配戰利品也要講求公平原則」。「中華民國人民，無分男女、宗教、種族、階級、黨派，在法律上一律平等。」「凡人民之其他自由及權利，不妨害社會秩序公共利益者，均受憲法之保障。」「以上各條例列舉之自由權利，除為防止妨礙他人自由，避免緊急危難，維持社會秩序或增進公共利益所必要者，不得以法律限制之。」中華民國憲法第7條、第22條、第23條分別定有明文，勞保局依據敬老津貼暫行條例之規定排除原告之請領資格，顯係違反憲法之平等原則，自屬無效之行政處分。3.退一步而言即使原處分無違憲法平等原則，原告亦有信賴利益保護原則之適用，行政程序法第8條規定，行政行為，應以誠實信用之方法為之，並應保護人民正當合理之信賴，原告係經屏東市公所主動通知前往里辦公處申請敬老津貼，而屏東市公所亦是依據勞保局所列之名冊而通知原告，且經勞保局之審核之後才發給敬老津貼，有敬老福利生活津貼申請書審核欄可茲為證。行政程序法第9條規定，行政機關就該管行政程序，應於當事人有利及不利之情形一律注意。勞保局未依法定注意義務執行法定職務，自不得要求原告繳回溢領之敬老津貼。4.另參酌訴願法第80條及行政程序法第117條第2款、第119條明定行政機關可否撤銷違法授益行政處分應予斟酌之要件，即受益人有信賴授予利益之行政處分之事實；受益人並無信賴不值得保護之情形；受益人之信賴利益顯然大於撤銷所欲維護之公益時，該授益處分不得撤銷。按改制前行政法院76年判字第474號判決略謂：「公法上之爭訟，有信賴保護原則之適用，即當事人信賴行政機關之決定，已就其生活關係有適當之安排者，必須給予保護或給予合理之補償。」，又改制前行政法院83年判字第560號判決「授予人民利益之行政處分，因違法而發生是否應予撤銷時，依一般行政法理，應委諸行政機關裁量，故行政機關對於公益與信賴利益之孰輕孰重，自應加以審酌衡量，如撤銷對公益有重大危害或受益人之信賴利益，顯然大於撤銷所欲維護之公益，且其信賴並無不值得保護之情形時，自不得輕言撤銷該違法之行政處分。」及改制前行政法院83年判字第151號判決：「行政機關審酌是否撤銷授予利益之違法行政處分時，除受益人具有：以詐欺、脅迫或賄賂方法使行政機關作成行政處分，對重要事項提出不正確資料或為不完全陳述致行政機關依該資料或據不完全陳述致行政機關依該資料或陳述而作成行政處分，明知處分違法或因重大過失而不知等信賴不值得保護之情形外，依行政法上信賴保護原則，為撤銷之行政機關應顧及受益人之信賴保護利益。」。5.原告領取之敬老津貼18,000元，此屬於連續之金錢給付，原告信賴該行政處分之存續，且已使用所提供之給付，原告具有值得保護之信賴利益，此外該敬老津貼並非原告基於詐欺、脅迫或賄賂方法所獲得，亦非對重要事項提供不正確資料或為不完全陳述，致使行政機關陷於錯誤而作成行政處分，又此次申領敬老津貼係經由屏東縣屏東市公所所發函通知原告前往辦理，發動權在於行政機關。因此原告並不知核付津貼之行政處分是違法的。參諸前揭行政法院判決意旨所示，原告之信賴並無不值得保護之情形，仍應有信賴保護原則之適用。(二)被告主張之理由：1.按年滿65歲，在國內設有戶籍，且於最近3年內每年居住超過183日之國民，未有領取軍人退休俸（終身生活補助費）、政務人員、公教人員、公營事業人員月退休（職）金或一次退休金者，得請領敬老福利生活津貼，每月3,000元，為敬老福利生活津貼暫行條例第3條第1項第2款所規定。敬老福利生活津貼之規劃主要在因應台灣老年人口快速成長，並秉持福利資源不重複配置、政府財政負擔考量與公平性原則，屬於對從未領有軍公教退休金、政府補助或津貼者之補充性福利措施，以便於國民年金實施前，協助維持長者之基本生活。2.原告所提有信賴利益保護原則之適用，查敬老福利生活津貼申請書背後已列明不符合請領資格之排除條件其中一點即已領取公營事業人員月退休（職）金或一次退休金者，不得請領敬老福利生活津貼，而申請書正面書明「本人如不符資格而領取敬老福利生活津貼，其溢領金額願意由本人或法定繼承人負責繳還，並負相關法律責任」，原告在申請書上蓋章表示同意明瞭，伊既已領取公營事業人員一次退休金並於訴願書自己陳明承認，已不符合請領資格卻仍向勞保局提出申請本津貼，基此，其並無值得保護之信賴利益，原告須依法為此一溢領案負返還責任。理由一、按年滿65歲，在國內設有戶籍，且於最近3年內每年居住超過183日之國民，未有領取軍人退休俸（終身生活補助費）、政務人員、公教人員、公營事業人員月退休（職）金或一次退休金情事者，得請領敬老福利生活津貼，每月3,000元，為敬老福利生活津貼暫行條例第3條第1項第2款所規定。又「不符合請領資格而領取本津貼者，其溢領之津貼，經以書面命本人或其法定繼承人自事實發生之日起60日內繳還；屆期未繳還者，依法移送強制執行。」復為同條例第10條所明定。二、本件原告於92年7月7日申請敬老福利生活津貼，經勞保局核付92年7月至92年12月敬老福利生活津貼每月3,000元，計18,000元，因原告於73年6月30日自台糖公司退休，領取公營事業人員一次退休金，有資格檔資料明細查詢附勞保局卷可稽，勞保局以原告不得請領敬老福利生活津貼，請其繳還溢領敬老福利生活津貼計18,000元，揆諸首揭規定，並無不合。原告主張勞保局依據敬老津貼暫行條例之規定排除原告之請領資格，顯係違反憲法之平等原則，自屬無效之行政處分云云，並不足採。原告雖另主張其有信賴保護原則之適用云云。經查原告據以申請之敬老福利生活津貼申請書背面所列請領敬老福利生活津貼說明第1點(三)，明確記載已領取公營事業人員月退休（職）金或一次退休金者，不具請領資格，有該申請書影本附訴願卷為證，申請書正面則記載「本人如不符資格而領取敬老福利生活津貼，其溢領金額願意由本人或法定繼承人負責繳還，並負相關法律責任」等語，並經原告蓋章確認，且此亦為法律之規定，申請人不得諉為不知，是原告知其自台灣糖業公司退休時已領取一次退休金，其申請時就其已領取公營事業人員退休金之重要事項未為完全陳述，致勞保局依其陳述(申請書所載)准其領取敬老福利生活津貼，依行政程序法第119條第2款規定，其信賴不值得保護，原告此部分之主張並不足採。三、原處分以原告已於台糖公司領取一次退休金，不得請領領取敬老福利生活津貼，令原告繳還溢領敬老福利生活津貼計18,000元，含有認定原告不符請領領取敬老福利生活津貼資格之效力，原告自不得請求發給此項津貼，是原告請求被告應繼續核發原告敬老生活津貼每月3,000元，並無理由，亦應駁回。四、從而，原處分命原告繳還溢領敬老福利生活津貼計18,000元，並無違法，訴願決定予以維持，亦無不合。原告訴請撤銷，並請求被告應繼續核發原告敬老生活津貼每月3,000元，為無理由，應予駁回。五、據上論結，本件原告之訴為無理由，爰依行政訴訟法第98條第3項前段，判決如主文。中華民國94年7月7日第一庭審判長法官姜素娥法官陳秀法官吳東都上為正本係照原本作成。如不服本判決，應於送達後20日內，向本院提出上訴狀並表明上訴理由，如於本判決宣示後送達前提起上訴者，應於判決送達後20日內補提上訴理由書（須按他造人數附繕本）。中華民國94年7月7日書記官李金釵",
  "characters": {
    "judges": [
      "姜素娥",
      "陳秀",
      "吳東都"
    ],
    "prosecutors": [

    ],
    "lawyers": [

    ],
    "clerks": [
      "李金釵"
    ],
    "plaintiffs": [
      "甲"
    ],
    "defendants": [
      "內政部",
      "代  表  人  乙○○部長）住同."
    ],
    "prosecutor_office": [

    ],
    "creditors": [

    ],
    "debtors": [

    ],
    "judicial_associate_officer": [

    ]
  },
  "adjudged_at": "2005-07-07",
  "created_at": "2016-02-07 09:36:25",
  "updated_at": "2016-02-07 09:36:25"
}