{
  "identify": "PCD-100-簡-5455-20110802-1",
  "court": {
    "name": "臺灣新北地方法院",
    "code": "PCD"
  },
  "division": {
    "name": "刑事",
    "code": "M"
  },
  "year": 100,
  "word": "簡",
  "number": "5455",
  "jcheck": "1",
  "reason": "毒品危害防制條例",
  "content": "臺灣板橋地方法院刑事簡易判決         100年度簡字第5455號\n聲  請  人  臺灣板橋地方法院檢察署檢察官\n被      告  林聖宏\n上列被告因違反毒品危害防制條例案件，經檢察官聲請以簡易判\n決處刑（100年度毒偵字第4087、4199號），本院判決如下：\n    主  文\n林聖宏施用第二級毒品，累犯，處有期徒刑月，如易科罰金，\n以新臺幣壹仟元折算壹日。又施用第二級毒品，累犯，處有期徒\n刑月，如易科罰金，以新臺幣壹仟元折算壹日。應執行有期徒\n刑伍月，如易科罰金，以新臺幣壹仟元折算壹日。\n    事實及理由\n一、本件犯罪事實及證據，除證據部分補充臺北市政府警察局偵\n    辦毒品案件尿液檢體委驗單及應受尿液採驗人尿液檢體採集\n    送驗紀錄表各一份為證外，餘均引用如附件檢察官聲請簡易\n    判決處刑書之記載。\n二、查甲基安非他命為毒品危害防制條例所列之第二級毒品，不\n    得非法持有、施用，是核被告所為係犯同條例第10條第2 項\n    之施用第二級毒品罪，其施用前後持有毒品之行為，應為其\n    施用之高度行為所吸收，不另論罪。又查被告前因詐欺案經\n    本院98年度簡字第3877號判決判處有期徒刑三月，嗣於民國\n    99年7 月25日縮刑期滿執行完畢，有臺灣高等法院被告前案\n    紀錄表一份附卷可按，其於受有期徒刑執行完畢後，五年內\n    再故意犯本件有期徒刑以上之罪，為累犯，依法加重其刑。\n    爰審酌被告前因施用毒品經送觀察勒戒及強制戒治，此有前\n    開臺灣高等法院被告前案紀錄表一份在卷可考，理應深知施\n    用毒品為法所禁止之行為，竟仍未戒除毒癮，再為本件施用\n    毒品之犯行，顯見其戒除毒癮之意志薄弱，且其施用毒品戕\n    害自己身心健康，造成社會問題，兼衡其犯罪動機、目的、\n    手段及犯罪後之態度等一切情狀，分別量處如主文所示之刑\n    ，並定其應執行刑，併諭知易科罰金之折算標準，以資懲儆\n    。\n三、依刑事訴訟法第449 條第1 項前段、第3 項、第454 條第2\n    項，毒品危害防制條例第10條第2 項，刑法第11條、第47條\n    第1 項、第41條第1 項前段、第51條第5 款，逕以簡易判決\n    處刑如主文。\n四、如不服本判決，得自收受送達之日起10日內向本院提出上訴\n    狀，上訴於本院第二審合議庭（須附繕本）。\n中    華    民    國   100    年    8     月    2     日\n                  刑事第二十二庭  法  官  許映鈞\n上列正本證明與原本無異。\n                                  書記官  翁淑婷\n中    華    民    國   100    年    8     月    3     日\n附錄本案論罪科刑法條全文：\n毒品危害防制條例第10條\n施用第一級毒品者，處6月以上5年以下有期徒刑。\n施用第二級毒品者，處3年以下有期徒刑。",
  "structure": {
    "main": "林聖宏施用第二級毒品，累犯，處有期徒刑月，如易科罰金，\n以新臺幣壹仟元折算壹日。又施用第二級毒品，累犯，處有期徒\n刑月，如易科罰金，以新臺幣壹仟元折算壹日。應執行有期徒\n刑伍月，如易科罰金，以新臺幣壹仟元折算壹日。",
    "fact": "一、本件犯罪事實及證據，除證據部分補充臺北市政府警察局偵\n    辦毒品案件尿液檢體委驗單及應受尿液採驗人尿液檢體採集\n    送驗紀錄表各一份為證外，餘均引用如附件檢察官聲請簡易\n    判決處刑書之記載。\n二、查甲基安非他命為毒品危害防制條例所列之第二級毒品，不\n    得非法持有、施用，是核被告所為係犯同條例第10條第2 項\n    之施用第二級毒品罪，其施用前後持有毒品之行為，應為其\n    施用之高度行為所吸收，不另論罪。又查被告前因詐欺案經\n    本院98年度簡字第3877號判決判處有期徒刑三月，嗣於民國\n    99年7 月25日縮刑期滿執行完畢，有臺灣高等法院被告前案\n    紀錄表一份附卷可按，其於受有期徒刑執行完畢後，五年內\n    再故意犯本件有期徒刑以上之罪，為累犯，依法加重其刑。\n    爰審酌被告前因施用毒品經送觀察勒戒及強制戒治，此有前\n    開臺灣高等法院被告前案紀錄表一份在卷可考，理應深知施\n    用毒品為法所禁止之行為，竟仍未戒除毒癮，再為本件施用\n    毒品之犯行，顯見其戒除毒癮之意志薄弱，且其施用毒品戕\n    害自己身心健康，造成社會問題，兼衡其犯罪動機、目的、\n    手段及犯罪後之態度等一切情狀，分別量處如主文所示之刑\n    ，並定其應執行刑，併諭知易科罰金之折算標準，以資懲儆\n    。\n三、依刑事訴訟法第449 條第1 項前段、第3 項、第454 條第2\n    項，毒品危害防制條例第10條第2 項，刑法第11條、第47條\n    第1 項、第41條第1 項前段、第51條第5 款，逕以簡易判決\n    處刑如主文。\n四、如不服本判決，得自收受送達之日起10日內向本院提出上訴\n    狀，上訴於本院第二審合議庭（須附繕本）。",
    "reason": "一、本件犯罪事實及證據，除證據部分補充臺北市政府警察局偵\n    辦毒品案件尿液檢體委驗單及應受尿液採驗人尿液檢體採集\n    送驗紀錄表各一份為證外，餘均引用如附件檢察官聲請簡易\n    判決處刑書之記載。\n二、查甲基安非他命為毒品危害防制條例所列之第二級毒品，不\n    得非法持有、施用，是核被告所為係犯同條例第10條第2 項\n    之施用第二級毒品罪，其施用前後持有毒品之行為，應為其\n    施用之高度行為所吸收，不另論罪。又查被告前因詐欺案經\n    本院98年度簡字第3877號判決判處有期徒刑三月，嗣於民國\n    99年7 月25日縮刑期滿執行完畢，有臺灣高等法院被告前案\n    紀錄表一份附卷可按，其於受有期徒刑執行完畢後，五年內\n    再故意犯本件有期徒刑以上之罪，為累犯，依法加重其刑。\n    爰審酌被告前因施用毒品經送觀察勒戒及強制戒治，此有前\n    開臺灣高等法院被告前案紀錄表一份在卷可考，理應深知施\n    用毒品為法所禁止之行為，竟仍未戒除毒癮，再為本件施用\n    毒品之犯行，顯見其戒除毒癮之意志薄弱，且其施用毒品戕\n    害自己身心健康，造成社會問題，兼衡其犯罪動機、目的、\n    手段及犯罪後之態度等一切情狀，分別量處如主文所示之刑\n    ，並定其應執行刑，併諭知易科罰金之折算標準，以資懲儆\n    。\n三、依刑事訴訟法第449 條第1 項前段、第3 項、第454 條第2\n    項，毒品危害防制條例第10條第2 項，刑法第11條、第47條\n    第1 項、第41條第1 項前段、第51條第5 款，逕以簡易判決\n    處刑如主文。\n四、如不服本判決，得自收受送達之日起10日內向本院提出上訴\n    狀，上訴於本院第二審合議庭（須附繕本）。"
  },
  "search": "臺灣板橋地方法院刑事簡易判決100年度簡字第5455號聲請人臺灣板橋地方法院檢察署檢察官被告林聖宏上列被告因違反毒品危害防制條例案件，經檢察官聲請以簡易判決處刑（100年度毒偵字第4087、4199號），本院判決如下：主文林聖宏施用第二級毒品，累犯，處有期徒刑月，如易科罰金，以新臺幣壹仟元折算壹日。又施用第二級毒品，累犯，處有期徒刑月，如易科罰金，以新臺幣壹仟元折算壹日。應執行有期徒刑伍月，如易科罰金，以新臺幣壹仟元折算壹日。事實及理由一、本件犯罪事實及證據，除證據部分補充臺北市政府警察局偵辦毒品案件尿液檢體委驗單及應受尿液採驗人尿液檢體採集送驗紀錄表各一份為證外，餘均引用如附件檢察官聲請簡易判決處刑書之記載。二、查甲基安非他命為毒品危害防制條例所列之第二級毒品，不得非法持有、施用，是核被告所為係犯同條例第10條第2項之施用第二級毒品罪，其施用前後持有毒品之行為，應為其施用之高度行為所吸收，不另論罪。又查被告前因詐欺案經本院98年度簡字第3877號判決判處有期徒刑三月，嗣於民國99年7月25日縮刑期滿執行完畢，有臺灣高等法院被告前案紀錄表一份附卷可按，其於受有期徒刑執行完畢後，五年內再故意犯本件有期徒刑以上之罪，為累犯，依法加重其刑。爰審酌被告前因施用毒品經送觀察勒戒及強制戒治，此有前開臺灣高等法院被告前案紀錄表一份在卷可考，理應深知施用毒品為法所禁止之行為，竟仍未戒除毒癮，再為本件施用毒品之犯行，顯見其戒除毒癮之意志薄弱，且其施用毒品戕害自己身心健康，造成社會問題，兼衡其犯罪動機、目的、手段及犯罪後之態度等一切情狀，分別量處如主文所示之刑，並定其應執行刑，併諭知易科罰金之折算標準，以資懲儆。三、依刑事訴訟法第449條第1項前段、第3項、第454條第2項，毒品危害防制條例第10條第2項，刑法第11條、第47條第1項、第41條第1項前段、第51條第5款，逕以簡易判決處刑如主文。四、如不服本判決，得自收受送達之日起10日內向本院提出上訴狀，上訴於本院第二審合議庭（須附繕本）。中華民國100年8月2日刑事第二十二庭法官許映鈞上列正本證明與原本無異。書記官翁淑婷中華民國100年8月3日附錄本案論罪科刑法條全文：毒品危害防制條例第10條施用第一級毒品者，處6月以上5年以下有期徒刑。施用第二級毒品者，處3年以下有期徒刑。",
  "characters": {
    "judges": [
      "許映鈞"
    ],
    "prosecutors": [

    ],
    "lawyers": [

    ],
    "clerks": [
      "翁淑婷"
    ],
    "plaintiffs": [

    ],
    "defendants": [
      "林聖宏"
    ],
    "prosecutor_office": [
      "臺灣板橋地方法院檢察署檢察官"
    ],
    "creditors": [

    ],
    "debtors": [

    ],
    "judicial_associate_officer": [

    ]
  },
  "adjudged_at": "2011-08-02",
  "created_at": "2016-02-12 18:48:47",
  "updated_at": "2016-02-12 18:48:47"
}