{
  "identify": "TCD-100-附民-301-20110802-1",
  "court": {
    "name": "臺灣臺中地方法院",
    "code": "TCD"
  },
  "division": {
    "name": "刑事",
    "code": "M"
  },
  "year": 100,
  "word": "附民",
  "number": "301",
  "jcheck": "1",
  "reason": "請求損害賠償",
  "content": "臺灣臺中地方法院刑事附帶民事訴訟判決\n                                    100年度附民字第301號\n原      告  劉採圓\n被      告  江水治\n上列被告因違反公職人員選舉罷免法案件（本院100年度訴字第\n1601號），經原告提起附帶民事訴訟請求損害賠償事件，本院判\n決如下︰\n    主    文\n原告之訴駁回。\n    事    實\n一、原告聲明求為判決：被告江水治應給付原告劉採圓新臺幣（\n    下同）三十萬元；並自起訴狀繕本送達之翌日起至清償日止\n    ，按週年利率百分之五計算之利息；且陳明願供擔保請准宣\n    告假執行。\n二、被告江水治除於刑事案件審理時否認犯行，並未就本件為任\n    何聲明或陳述，亦未提出任何書狀。\n    理    由\n一、按刑事訴訟諭知無罪之判決者，對於附帶民事訴訟部分應以\n    判決駁回原告之訴，刑事訴訟法第五百零三條第一項前段定\n    有明文。\n二、本件被告江水治被訴違反公職人員選舉罷免法一案，業經刑\n    事判決諭知無罪在案，根據首揭說明，原告劉採圓之訴自應\n    予以駁回。又原告雖聲請願供擔保請准宣告假執行；惟本件\n    係屬民事訴訟法第四百二十七條第一項之訴訟，依民事訴訟\n    法第三百八十九條第一項第三款之規定，如為原告勝訴之判\n    決，本即應依職權宣告假執行，則原告之聲請假執行，僅為\n    促進法院職權之發動，毋庸就其聲請為准駁之裁定，併此敘\n    明。\n三、據上論斷，應依刑事訴訟法第五百零三條第一項前段，判決\n    如主文。\n中    華    民    國   100    年    8     月    2     日\n                  刑事第八庭  審判長法  官  張智雄\n                                    法  官  李慧瑜\n                                    法  官  陳思成\n以上正本證明與原本無異。\n對於本判決如不服，非對於刑事訴訟之判決有上訴時，不得上訴\n，並應於送達後十日內向本院提出。\n                                    書記官  陳淑華\n中    華    民    國   100    年    8     月    2     日",
  "structure": {
    "main": "原告之訴駁回。",
    "fact": "一、原告聲明求為判決：被告江水治應給付原告劉採圓新臺幣（\n    下同）三十萬元；並自起訴狀繕本送達之翌日起至清償日止\n    ，按週年利率百分之五計算之利息；且陳明願供擔保請准宣\n    告假執行。\n二、被告江水治除於刑事案件審理時否認犯行，並未就本件為任\n    何聲明或陳述，亦未提出任何書狀。",
    "reason": "一、按刑事訴訟諭知無罪之判決者，對於附帶民事訴訟部分應以\n    判決駁回原告之訴，刑事訴訟法第五百零三條第一項前段定\n    有明文。\n二、本件被告江水治被訴違反公職人員選舉罷免法一案，業經刑\n    事判決諭知無罪在案，根據首揭說明，原告劉採圓之訴自應\n    予以駁回。又原告雖聲請願供擔保請准宣告假執行；惟本件\n    係屬民事訴訟法第四百二十七條第一項之訴訟，依民事訴訟\n    法第三百八十九條第一項第三款之規定，如為原告勝訴之判\n    決，本即應依職權宣告假執行，則原告之聲請假執行，僅為\n    促進法院職權之發動，毋庸就其聲請為准駁之裁定，併此敘\n    明。\n三、據上論斷，應依刑事訴訟法第五百零三條第一項前段，判決\n    如主文。\n中    華    民    國   100    年    8     月    2     日\n                  刑事第八庭  審判長法  官  張智雄\n                                    法  官  李慧瑜\n                                    法  官  陳思成\n以上正本證明與原本無異。\n對於本判決如不服，非對於刑事訴訟之判決有上訴時，不得上訴\n，並應於送達後十日內向本院提出。\n                                    書記官  陳淑華"
  },
  "search": "臺灣臺中地方法院刑事附帶民事訴訟判決100年度附民字第301號原告劉採圓被告江水治上列被告因違反公職人員選舉罷免法案件（本院100年度訴字第1601號），經原告提起附帶民事訴訟請求損害賠償事件，本院判決如下︰主文原告之訴駁回。事實一、原告聲明求為判決：被告江水治應給付原告劉採圓新臺幣（下同）三十萬元；並自起訴狀繕本送達之翌日起至清償日止，按週年利率百分之五計算之利息；且陳明願供擔保請准宣告假執行。二、被告江水治除於刑事案件審理時否認犯行，並未就本件為任何聲明或陳述，亦未提出任何書狀。理由一、按刑事訴訟諭知無罪之判決者，對於附帶民事訴訟部分應以判決駁回原告之訴，刑事訴訟法第五百零三條第一項前段定有明文。二、本件被告江水治被訴違反公職人員選舉罷免法一案，業經刑事判決諭知無罪在案，根據首揭說明，原告劉採圓之訴自應予以駁回。又原告雖聲請願供擔保請准宣告假執行；惟本件係屬民事訴訟法第四百二十七條第一項之訴訟，依民事訴訟法第三百八十九條第一項第三款之規定，如為原告勝訴之判決，本即應依職權宣告假執行，則原告之聲請假執行，僅為促進法院職權之發動，毋庸就其聲請為准駁之裁定，併此敘明。三、據上論斷，應依刑事訴訟法第五百零三條第一項前段，判決如主文。中華民國100年8月2日刑事第八庭審判長法官張智雄法官李慧瑜法官陳思成以上正本證明與原本無異。對於本判決如不服，非對於刑事訴訟之判決有上訴時，不得上訴，並應於送達後十日內向本院提出。書記官陳淑華中華民國100年8月2日",
  "characters": {
    "judges": [
      "張智雄",
      "李慧瑜",
      "陳思成"
    ],
    "prosecutors": [

    ],
    "lawyers": [

    ],
    "clerks": [
      "陳淑華"
    ],
    "plaintiffs": [
      "劉採圓"
    ],
    "defendants": [
      "江水治"
    ],
    "prosecutor_office": [

    ],
    "creditors": [

    ],
    "debtors": [

    ],
    "judicial_associate_officer": [

    ]
  },
  "adjudged_at": "2011-08-02",
  "created_at": "2016-02-12 19:04:26",
  "updated_at": "2016-02-12 19:04:26"
}