{
  "identify": "KSD-94-簡-162-20050617-1",
  "court": {
    "name": "臺灣高雄地方法院",
    "code": "KSD"
  },
  "division": {
    "name": "刑事",
    "code": "M"
  },
  "year": 94,
  "word": "簡",
  "number": "162",
  "jcheck": "1",
  "reason": "違反臺灣地區與大陸地區人民關係條例",
  "content": "臺灣高雄地方法院刑事簡易判決           94年度簡字第162號\n聲  請  人  臺灣高雄地方法院檢察署檢察官\n被      告  甲○○  男  28歲.\n上列被告因違反臺灣地區與大陸地區人民關係條例案件，經檢察\n官聲請簡易判決處刑（94年度偵字第18578 號）及移送併案（94\n年度偵字第1648號），本院判決處刑如下：\n    主  文\n甲○○連續違反不得僱用大陸地區人民在臺灣地區從事未經許可\n之工作規定，處有期徒刑肆月，如易科罰金，以參佰元折算壹日\n。\n    事實及理由\n一、本件犯罪事實及證據，除犯罪事實部分並補充併案部分：「\n    甲○○明知莫珠紅、莫美虹係以探親名義來臺之大陸地區，\n    竟自民國94年1 月7 日下午5 時許起，未經依法申請許可，\n    在其所經營位於高雄縣鳳山市○○街175 巷15弄1 號『金莎\n    堡KTV 』內，以每日新臺幣（下同）500 元之代價，僱傭莫\n    珠紅及莫美虹從事上開坐檯陪酒之工作，嗣於94年1 月7日\n    晚上11時20分許，在上開地點為警查獲。」，以及證據部分\n    補充併案部分：「被告甲○○於警、偵訊時之自白，核與證\n    人即受僱之大陸女子莫珠紅、莫美虹2 人在警、偵訊中所供\n    之情節相符，並有入出境許可證影本2 份、五甲派出所檢查\n    紀錄表、營業報表7 張等在卷可稽，事證已明，此部分之犯\n    行堪予認定」外，餘均引用檢察官聲請簡易判決處刑書之記\n    載（如附件）。\n二、核被告甲○○所為，係違反臺灣地區與大陸地區人民關係條\n    例第15條第4 款僱用大陸地區人民在臺灣地區從事未經許可\n    之工作之規定，應依同條例第83條第1 項規定處罰。被告先\n    於93年間同時僱傭大陸地區人民余妹香、陳雲芳、吳賽珠、\n    廖巧平四人，復於94年1 月7 日同時僱傭莫珠紅、莫美虹二\n    人之犯行，均時間緊接，方法相同，觸犯構成要件相同之罪\n    名，顯係基於概括犯意反覆為之，應依連續犯之規定論以一\n    罪，並加重其刑。又就被告僱傭莫珠紅、莫美虹二人之犯行\n    部分，雖未經檢察官聲請簡易判決處刑，然與已聲請簡易判\n    決處刑部分，係連續犯，具有裁判上一罪之關係，本院自得\n    併予審酌，附此敘明。爰審酌政府制定臺灣地區與大陸地區\n    人民關係條例之目的，除為了保護臺灣地區人民就業，以持\n    續增進社會及經濟發展外，亦係基於考量兩岸政府或人民交\n    流現狀，避免彼岸人民在臺非法就業，有損國家安全利益，\n    被告卻未予遵守，對於我國社會及經濟之發展，自有不良影\n    響，且於93年9 月2 日僱傭大陸女子被查獲後，仍不知警惕\n    ，再為併案部分之犯行，惡性非輕等一切情狀，酌情量處如\n    主文所示之刑，並諭知易科罰金之折算標準，以資懲儆。\n三、依刑事訴訟法第449 條第1 項前段、第454 條第2 項，臺灣\n    地區與大陸地區人民關係條例第83條第1 項、第15條第4款\n    ，刑法第11條前段、第56條、第41條第1 項前段，罰金罰鍰\n    提高標準條例第2條，逕以簡易判決處刑如主文。\n如不服本判決，得自收受送達之日起10日內，向本院提起上訴。\n中    華    民    國    94    年    6     月    17    日\n                    高雄簡易庭  法  官  高思大\n以上正本，係照原本作成，證明與原本無異。\n中    華    民    國    94    年    6     月    20    日\n                                書記官  蔡語珊\n附錄本判決論罪之法條：\n臺灣地區與大陸地區人民關係條例第15條第4 款：\n左列行為不得為之：\n4 僱用或留用大陸地區人民在臺灣地區從事未經許可或與許可範\n圍不符之工作。\n臺灣地區與大陸地區人民關係條例第83條第1項：\n違反第15條第4 款或第5 款規定者，處2 年以下有期徒刑、拘役\n或科或併科新台幣30萬元以下罰金。\n",
  "structure": {
    "main": "甲○○連續違反不得僱用大陸地區人民在臺灣地區從事未經許可\n之工作規定，處有期徒刑肆月，如易科罰金，以參佰元折算壹日\n。",
    "fact": "一、本件犯罪事實及證據，除犯罪事實部分並補充併案部分：「\n    甲○○明知莫珠紅、莫美虹係以探親名義來臺之大陸地區，\n    竟自民國94年1 月7 日下午5 時許起，未經依法申請許可，\n    在其所經營位於高雄縣鳳山市○○街175 巷15弄1 號『金莎\n    堡KTV 』內，以每日新臺幣（下同）500 元之代價，僱傭莫\n    珠紅及莫美虹從事上開坐檯陪酒之工作，嗣於94年1 月7日\n    晚上11時20分許，在上開地點為警查獲。」，以及證據部分\n    補充併案部分：「被告甲○○於警、偵訊時之自白，核與證\n    人即受僱之大陸女子莫珠紅、莫美虹2 人在警、偵訊中所供\n    之情節相符，並有入出境許可證影本2 份、五甲派出所檢查\n    紀錄表、營業報表7 張等在卷可稽，事證已明，此部分之犯\n    行堪予認定」外，餘均引用檢察官聲請簡易判決處刑書之記\n    載（如附件）。\n二、核被告甲○○所為，係違反臺灣地區與大陸地區人民關係條\n    例第15條第4 款僱用大陸地區人民在臺灣地區從事未經許可\n    之工作之規定，應依同條例第83條第1 項規定處罰。被告先\n    於93年間同時僱傭大陸地區人民余妹香、陳雲芳、吳賽珠、\n    廖巧平四人，復於94年1 月7 日同時僱傭莫珠紅、莫美虹二\n    人之犯行，均時間緊接，方法相同，觸犯構成要件相同之罪\n    名，顯係基於概括犯意反覆為之，應依連續犯之規定論以一\n    罪，並加重其刑。又就被告僱傭莫珠紅、莫美虹二人之犯行\n    部分，雖未經檢察官聲請簡易判決處刑，然與已聲請簡易判\n    決處刑部分，係連續犯，具有裁判上一罪之關係，本院自得\n    併予審酌，附此敘明。爰審酌政府制定臺灣地區與大陸地區\n    人民關係條例之目的，除為了保護臺灣地區人民就業，以持\n    續增進社會及經濟發展外，亦係基於考量兩岸政府或人民交\n    流現狀，避免彼岸人民在臺非法就業，有損國家安全利益，\n    被告卻未予遵守，對於我國社會及經濟之發展，自有不良影\n    響，且於93年9 月2 日僱傭大陸女子被查獲後，仍不知警惕\n    ，再為併案部分之犯行，惡性非輕等一切情狀，酌情量處如\n    主文所示之刑，並諭知易科罰金之折算標準，以資懲儆。\n三、依刑事訴訟法第449 條第1 項前段、第454 條第2 項，臺灣\n    地區與大陸地區人民關係條例第83條第1 項、第15條第4款\n    ，刑法第11條前段、第56條、第41條第1 項前段，罰金罰鍰\n    提高標準條例第2條，逕以簡易判決處刑如主文。\n如不服本判決，得自收受送達之日起10日內，向本院提起上訴。",
    "reason": "一、本件犯罪事實及證據，除犯罪事實部分並補充併案部分：「\n    甲○○明知莫珠紅、莫美虹係以探親名義來臺之大陸地區，\n    竟自民國94年1 月7 日下午5 時許起，未經依法申請許可，\n    在其所經營位於高雄縣鳳山市○○街175 巷15弄1 號『金莎\n    堡KTV 』內，以每日新臺幣（下同）500 元之代價，僱傭莫\n    珠紅及莫美虹從事上開坐檯陪酒之工作，嗣於94年1 月7日\n    晚上11時20分許，在上開地點為警查獲。」，以及證據部分\n    補充併案部分：「被告甲○○於警、偵訊時之自白，核與證\n    人即受僱之大陸女子莫珠紅、莫美虹2 人在警、偵訊中所供\n    之情節相符，並有入出境許可證影本2 份、五甲派出所檢查\n    紀錄表、營業報表7 張等在卷可稽，事證已明，此部分之犯\n    行堪予認定」外，餘均引用檢察官聲請簡易判決處刑書之記\n    載（如附件）。\n二、核被告甲○○所為，係違反臺灣地區與大陸地區人民關係條\n    例第15條第4 款僱用大陸地區人民在臺灣地區從事未經許可\n    之工作之規定，應依同條例第83條第1 項規定處罰。被告先\n    於93年間同時僱傭大陸地區人民余妹香、陳雲芳、吳賽珠、\n    廖巧平四人，復於94年1 月7 日同時僱傭莫珠紅、莫美虹二\n    人之犯行，均時間緊接，方法相同，觸犯構成要件相同之罪\n    名，顯係基於概括犯意反覆為之，應依連續犯之規定論以一\n    罪，並加重其刑。又就被告僱傭莫珠紅、莫美虹二人之犯行\n    部分，雖未經檢察官聲請簡易判決處刑，然與已聲請簡易判\n    決處刑部分，係連續犯，具有裁判上一罪之關係，本院自得\n    併予審酌，附此敘明。爰審酌政府制定臺灣地區與大陸地區\n    人民關係條例之目的，除為了保護臺灣地區人民就業，以持\n    續增進社會及經濟發展外，亦係基於考量兩岸政府或人民交\n    流現狀，避免彼岸人民在臺非法就業，有損國家安全利益，\n    被告卻未予遵守，對於我國社會及經濟之發展，自有不良影\n    響，且於93年9 月2 日僱傭大陸女子被查獲後，仍不知警惕\n    ，再為併案部分之犯行，惡性非輕等一切情狀，酌情量處如\n    主文所示之刑，並諭知易科罰金之折算標準，以資懲儆。\n三、依刑事訴訟法第449 條第1 項前段、第454 條第2 項，臺灣\n    地區與大陸地區人民關係條例第83條第1 項、第15條第4款\n    ，刑法第11條前段、第56條、第41條第1 項前段，罰金罰鍰\n    提高標準條例第2條，逕以簡易判決處刑如主文。\n如不服本判決，得自收受送達之日起10日內，向本院提起上訴。"
  },
  "search": "臺灣高雄地方法院刑事簡易判決94年度簡字第162號聲請人臺灣高雄地方法院檢察署檢察官被告甲○○男28歲.上列被告因違反臺灣地區與大陸地區人民關係條例案件，經檢察官聲請簡易判決處刑（94年度偵字第18578號）及移送併案（94年度偵字第1648號），本院判決處刑如下：主文甲○○連續違反不得僱用大陸地區人民在臺灣地區從事未經許可之工作規定，處有期徒刑肆月，如易科罰金，以參佰元折算壹日。事實及理由一、本件犯罪事實及證據，除犯罪事實部分並補充併案部分：「甲○○明知莫珠紅、莫美虹係以探親名義來臺之大陸地區，竟自民國94年1月7日下午5時許起，未經依法申請許可，在其所經營位於高雄縣鳳山市○○街175巷15弄1號『金莎堡KTV』內，以每日新臺幣（下同）500元之代價，僱傭莫珠紅及莫美虹從事上開坐檯陪酒之工作，嗣於94年1月7日晚上11時20分許，在上開地點為警查獲。」，以及證據部分補充併案部分：「被告甲○○於警、偵訊時之自白，核與證人即受僱之大陸女子莫珠紅、莫美虹2人在警、偵訊中所供之情節相符，並有入出境許可證影本2份、五甲派出所檢查紀錄表、營業報表7張等在卷可稽，事證已明，此部分之犯行堪予認定」外，餘均引用檢察官聲請簡易判決處刑書之記載（如附件）。二、核被告甲○○所為，係違反臺灣地區與大陸地區人民關係條例第15條第4款僱用大陸地區人民在臺灣地區從事未經許可之工作之規定，應依同條例第83條第1項規定處罰。被告先於93年間同時僱傭大陸地區人民余妹香、陳雲芳、吳賽珠、廖巧平四人，復於94年1月7日同時僱傭莫珠紅、莫美虹二人之犯行，均時間緊接，方法相同，觸犯構成要件相同之罪名，顯係基於概括犯意反覆為之，應依連續犯之規定論以一罪，並加重其刑。又就被告僱傭莫珠紅、莫美虹二人之犯行部分，雖未經檢察官聲請簡易判決處刑，然與已聲請簡易判決處刑部分，係連續犯，具有裁判上一罪之關係，本院自得併予審酌，附此敘明。爰審酌政府制定臺灣地區與大陸地區人民關係條例之目的，除為了保護臺灣地區人民就業，以持續增進社會及經濟發展外，亦係基於考量兩岸政府或人民交流現狀，避免彼岸人民在臺非法就業，有損國家安全利益，被告卻未予遵守，對於我國社會及經濟之發展，自有不良影響，且於93年9月2日僱傭大陸女子被查獲後，仍不知警惕，再為併案部分之犯行，惡性非輕等一切情狀，酌情量處如主文所示之刑，並諭知易科罰金之折算標準，以資懲儆。三、依刑事訴訟法第449條第1項前段、第454條第2項，臺灣地區與大陸地區人民關係條例第83條第1項、第15條第4款，刑法第11條前段、第56條、第41條第1項前段，罰金罰鍰提高標準條例第2條，逕以簡易判決處刑如主文。如不服本判決，得自收受送達之日起10日內，向本院提起上訴。中華民國94年6月17日高雄簡易庭法官高思大以上正本，係照原本作成，證明與原本無異。中華民國94年6月20日書記官蔡語珊附錄本判決論罪之法條：臺灣地區與大陸地區人民關係條例第15條第4款：左列行為不得為之：4僱用或留用大陸地區人民在臺灣地區從事未經許可或與許可範圍不符之工作。臺灣地區與大陸地區人民關係條例第83條第1項：違反第15條第4款或第5款規定者，處2年以下有期徒刑、拘役或科或併科新台幣30萬元以下罰金。",
  "characters": {
    "judges": [
      "高思大"
    ],
    "prosecutors": [

    ],
    "lawyers": [

    ],
    "clerks": [
      "蔡語珊"
    ],
    "plaintiffs": [

    ],
    "defendants": [
      "甲○○  男  28歲."
    ],
    "prosecutor_office": [
      "臺灣高雄地方法院檢察署檢察官"
    ],
    "creditors": [

    ],
    "debtors": [

    ],
    "judicial_associate_officer": [

    ]
  },
  "adjudged_at": "2005-06-17",
  "created_at": "2016-02-07 06:33:25",
  "updated_at": "2016-02-07 06:33:25"
}