{
  "identify": "TCB-94-訴-149-20050616-1",
  "court": {
    "name": "臺中高等行政法院",
    "code": "TCB"
  },
  "division": {
    "name": "行政",
    "code": "A"
  },
  "year": 94,
  "word": "訴",
  "number": "149",
  "jcheck": "1",
  "reason": "電子遊戲場業管理條例",
  "content": "臺中高等行政法院判決\n                                     94年度訴字第00149號\n                              .\n原      告  甲○○\n訴訟代理人  施瑞章 律師\n被      告  苗栗縣政府\n代  表  人  乙○○\n訴訟代理人  丙○○\n上列當事人間因電子遊戲場業管理條例事件，原告不服經濟部中\n華民國94年1月27日經訴字第09406121850號訴願決定，提起行政\n訴訟。本院判決如下︰\n    主  文\n原告之訴駁回。\n訴訟費用由原告負擔。\n    事  實\n一、事實概要：\n    原告甲○○經被告核准登記，在苗栗縣苗栗市○○里○○鄰○\n    ○路77號（嗣後變更為苗栗縣頭份鎮○○里○○路57號1樓\n    ）開設菲力電子遊藝場，領有被告核發苗商登字第05162100\n    -5號營利事業登記證，核准營業項目為：「J701010電子遊\n    戲場業（限制級）」該商號前負責人朱文正因賭博案件，經\n    台灣苗栗地方法院91年度易字第260號刑事判決有罪確定，\n    被告以原告違反電子遊戲場業管理條例第17條第1項第6款規\n    定，依同法第31條後段規定，以93年8月26日府建工字第093\n    0088550號函撤銷菲力電子遊藝場苗商登字第05162103-1號\n    （嗣後更正為苗商登字第00000000-0號）營利事業登記證及\n    電子遊戲場業級別證，原告不服，提起行政訴訟。\n二、兩造之聲明：\n    (一)原告聲明求為判決：\n      1.訴願決定及原處分均撤銷。\n      2.訴訟費用由被告負擔。\n    (二)被告聲明求為判決：\n      1.原告之訴駁回。\n      2.訴訟費用由原告負擔。\n三、兩造之陳述：\n    (一)原告部分：\n      1.按「行政行為應受法律及一般法律原則之拘束」，為行\n        政程序法第4條所明定；是以，行政機關為行政罰之行\n        政處分時亦應受刑法第1條：「行為之處罰，以行為時\n        之法律有明文規定者，為限」所定「罪刑法定主義」之\n        科罰原則拘束。又「對人民違反行政法上義務之行為科\n        處罰鍰，涉及人民權利之限制，其處罰構成要件及數額\n        ，應由法律定之。若法律就其構成要件，授權以命令為\n        補充規定者，授權之內容及範圍應具體明確，然後據以\n        發布命令，始符憲法第23條以法律限制人民權利之意旨\n        」為司法院釋字第313號解釋所明釋。\n      2.查電子遊戲場業管理條例第31條係規定：違反第17條第\n        1項第6款規定者（即經營電子遊戲場業者，不得有涉及\n        賭博、妨害風化或其他犯罪行為），處負責人新台幣50\n        萬元以上250萬元以下罰鍰，並令其停業；經法院判決\n        有罪確定者，撤銷其公司或營利事業之登記或部分登記\n        事項。準此，電子遊戲場業之負責人有涉及賭博行為並\n        經法院判決有罪確定時，應撤銷其營利事業登記；如負\n        責人未涉及賭博行為並經法院判決有罪確定者，自不應\n        撤銷其營利事業登記。本件朱文正為負責人經營菲力電\n        子遊藝場時之營利事業登記證為苗商登字第05162103-1\n        號，固涉有賭博行為；惟朱文正出售營業予原告並經被\n        告核准變更登記營利事業登記證為苗商登字第05162103\n        號，嗣被告核准原告變更營業地址至苗栗縣頭份鎮之營\n        利事業登記為苗商登字第00000000-0號，在原告為負責\n        人經營期間，從無涉及賭博行為，被告行政處分竟以原\n        告為處分行為人，並逕指「原告開設之菲力電子遊藝場\n        ，違法經營賭博等，案經台灣苗栗地方法院91年度易字\n        第260號刑事判決確定」云云，則被告之行政處分誣捏\n        事實，適用法律並有違上開法律規定與解釋意旨。\n      3.次按「行政行為，應以誠實信用之方法為之，並應保護\n        人民正當合理之信賴」，為行政程序法第8條所明定；\n        又「信賴保護原則攸關憲法上人民權利之保障，公權力\n        行使涉及人民信賴利益而有保護之必要者，不限於授益\n        行政處分之撤銷或廢止（行政程序法第119條、第120條\n        及第126條參照），即行政法規之廢止或變更亦有其適\n        用。‧‧‧」，則為司法院釋字第525號解釋著有明文\n        。\n      4.查朱文正係於91年1月27日涉及賭博行為，遭警查獲，\n        並於91年7月23日經台灣苗栗地方法院91年度易字第260\n        號刑事判決確定。倘被告於朱文正涉及賭博行為時（91\n        年1月27日），依電子遊戲場業管理條例第31條前段規\n        定科處罰鍰並令其停業，或迅即於91年7月23日判決確\n        定後，撤銷朱文正為負責人之菲力電子遊戲場營利事業\n        登記證，則原告自不至於也不可能於91年8月12日受讓\n        朱文正之營業。是以，原告信賴被告掌管之營利事業登\n        記，並信賴被告所為兩次核准變更登記，竟於受讓營業\n        兩年後即93年8月26日突接被告以原告為行為人之撤銷\n        營利事業登記；被告所為行政處分，已違反上開法律規\n        定與解釋意旨。\n      5.再按「人民違反法律上之義務而應受行政罰之行為，法\n        律無特別規定時，雖不以出於故意為必要，仍須以過失\n        為其責任條件。但應受行政罰之行為，僅須違反禁止規\n        定或作為義務，而不以發生損害或危險為其要件者，推\n        定為有過失，於行為人不能舉證證明自己無過失時，即\n        應受處罰」，為司法院釋字第275號解釋所明釋。本件\n        原告並無電子遊戲場業管理條例第17條第1項第6款所定\n        之行為，自不應受該條例第31條規定之處罰。而且，原\n        告受讓菲力電子遊藝場之營業，並無過失；被告就本件\n        有行使公權力之行政上疏失，則為經濟部訴願決定書確\n        認，自無轉嫁原告負擔之理。原告既無故意，亦無過失\n        ，被告竟以原告為行政處罰之當事人，自有違上開解釋\n        所示行政罰原則。\n      6.末按「人民營業之自由為憲法上工作權及財產權所保障\n        。有關營業許可之條件，營業應遵守之義務及違反義務\n        應受之制裁，依憲法第23條規定，均應以法律定之，其\n        內容更須符合該條規定之要件。‧‧‧」，司法院釋字\n        第514號解釋著有明文。原告自朱文正受讓菲力電子遊\n        藝場而自為負責人之經營期間，並無涉及賭博行為而遭\n        刑事判決確定情事，自無電子遊戲場業管理條例第31條\n        規定之適用之餘地；同時，電子遊戲場業管理條例第31\n        條亦無營業承受人應承受前手違反行政義務而應受處罰\n        之規定。是以，被告所為原行政處分逕以原告為行為人\n        ，並指稱原告有涉及賭博行為並已遭刑事判決確定云云\n        ，進而撤銷原告之營利事業登記，顯有違上開解釋意旨\n        。\n    (二)被告部分：\n      1.電子遊戲場業管理條例第17條第1項第6款規定：「經營\n        電子遊戲場業者，應遵守下列事項：‧‧‧（六）不得\n        有涉及賭博、妨害風化或其他犯罪行為。」同法第31條\n        ：「違反第17條第6款規定者，處負責人新台幣50萬以\n        上250萬以下罰鍰，並令其停業，經法院有罪判決確定\n        者，撤銷其公司或營利事業之登記或部分登記事項。」\n      2.原告陳訴其非賭博罪之違法行為人，而係朱文正之營業\n        承受人，無違反電子遊戲場業管理條例第17條、31規定\n        之情事等等一節，經查菲力電子遊藝場前負責人朱文正\n        於91年1月27日於所經營之菲力電子遊藝場內經苗栗縣\n        警察局查獲涉及賭博行為，並經台灣苗栗地方法院91年\n        度易字第260號刑事判決有罪確定，菲力電子遊藝場雖\n        於91年8月11日向被告辦理營利事業負責人變更登記，\n        由朱文正變更登記為原告，惟依據經濟部89年9月1日經\n        商字第89216127號函示略以：「違反電子遊戲場業管理\n        條例第17條第1項第6款規定，雖負責人變更，仍可撤銷\n        電子遊戲場業之營利事業登記或部分登記事項。」\n      3.被告以93年8月26日府建工字第0930088550號函撤銷菲\n        力電子遊藝場營利事業登記證及電子遊戲場業營業級別\n        證之處分，依法並無不合，請駁回原告之訴。\n    理  由\n一、按「經營電子遊戲場業者，應遵守下列事項：‧‧‧六、不\n    得有涉及賭博、妨害風化或其他犯罪行為」，電子遊戲場業\n    管理條例第17條第1項第6款定有明文，違反該款規定者，依\n    同法第31條規定，處負責人新台幣50萬元以上250萬元以下\n    罰鍰，並令其停業，經法院判決有罪確定者，撤銷其公司或\n    營利事業之登記或部分登記事項。又「主管機關依法撤銷電\n    子遊戲場業營利事業登記時，應一併註銷其營業級別證‧‧\n    ‧」同條例第11條第3項前段定有明文。稽之上開規範之目\n    的，一則在對違反禁止義務之電子遊戲場業者之負責人課以\n    怠於防範或監督之罰鍰責任，另則在於違反行政法義務的商\n    業（不論是公司或獨資、合夥等商業組織）為命令停業處分\n    ，其經法院判決有罪確定者，撤銷其公司或營利事業之登記\n    ，以懲治其不法營業，並防止違規情事再犯，藉收管制行政\n    秩序之目的。\n二、本件訴外人朱文正前經被告核准於苗栗縣苗栗市○○里○○鄰\n    ○○路77號開設菲力電子遊藝場，領有被告核發苗商登字第\n    05162103-1號營利事業登記證，核准營業項目為：「J70101\n    0電子遊戲場業（限制級）」。91年1月27日經苗栗縣警察局\n    苗栗分局查獲該電子遊藝場涉有賭博行為，並經台灣苗栗地\n    方法院91年度易字第260號刑事判決有期徒刑5月確定（未上\n    訴）。被告乃以菲力電子遊藝場違法經營賭博業，經法院判\n    決有罪確定為由，依電子遊戲場業管理條例第31條之規定，\n    以93年8月26日府建工字第0930088550號函撤銷菲力電子遊\n    藝場苗商登字第05162103-1號營利事業登記證及電子遊戲場\n    業級別證，嗣復以94年1月5日府建工字第0940002248號函更\n    正上開處分所載營利事業登記證號碼為00000000-0號等情，\n    有系爭營利事業登記證、該營利事業歷次變更登記資料、刑\n    事判決影本及查詢上訴事宜之公務電話紀錄、被告上開函文\n    等分附訴願卷及本院卷可憑，自堪信為實在。\n三、原告雖起訴主張：(一)渠承受菲力電子遊藝場後，從未涉及賭\n    博行為，不應受電子遊戲場業管理條例第31條之處罰，且依\n    司法院釋字第275號解釋意旨，原告既無故意過失自不應受\n    行政罰，原處分竟以原告為處分行為人，並逕指「原告開設\n    之菲力電子遊藝場，違法經營賭博等，案經台灣苗栗地方法\n    院91年度易第260號刑事判決確定」云云，誣捏事實處分原\n    告，顯屬違法。(二)被告於朱文正涉及賭博，被告未立即對之\n    科處罰鍰並為停業之處分，且未於91年7月23日朱文正刑事\n    判決確定後隨即撤銷營利事業登記證，迄93年8月26日始為\n    系爭撤銷處分，訴願決定亦認為被告有行政疏失。原告信賴\n    被告掌管之營利事業登記，並信賴被告核准原告變更負責人\n    及變更營業地址之登記，詎被告於原告受讓營業兩年後突然\n    撤銷原告之營利事業登記證，顯違誠信原則及信賴保護原則\n    等語。經查：\n    (一)菲力電子遊藝場原設址於苗栗縣苗栗市○○里○○鄰○○路\n      77號，陳設電動機具水果檯等供人押注決定輸贏，累積積\n      分記明於寄存卡，其原負責人朱文正基於常業賭博之犯意\n      ，僱請楊昭吉喬裝成客人，提供現金供其他客人兌換積分\n      ，於91年1月27日經警查獲，朱文正於91年7月23日經判決\n      常業賭博罪，並未上訴業已確定。原告於91年8月12日受\n      讓該營利事業繼續經營，並向被告辦理負責人變更登記，\n      有營利事業統一發證變更登記申請書及被告准予變更登記\n      函等附訴願卷可考，均堪憑信。\n    (二)查商業登記法第2條規定：「本法所稱商業，謂以營利為\n      目的，以獨資或合夥方式經營之事業」，可知商業為一營\n      利事業，每一個商業即營利事業有一個統一編號，就如同\n      每一個自然人有一個身分證統一編號一般，而商號之負責\n      人雖有變動，但該商號名稱所表彰之商業即營利事業並無\n      更易，仍是同一，縱使主管機關因商業即營利事業之負責\n      人變動，而發給申請人一紙新的營利事業登記證，但該申\n      請人既沿用原商業之名稱及營利事業之統一編號，即非一\n      新設立之商業，自應繼受該商業即營利事業之權利義務（\n      最高行政法院92年度判字第95號判決參照）。又依電子遊\n      戲場業管理條例第3條規定：「本條例所稱電子遊戲場業\n      ，指設置電子遊戲機供不特定人益智娛樂之營利事業」，\n      足見電子遊戲場業為營利事業，屬於商業登記法所稱之商\n      業，自有上開見解之適用。被告辦理營利事業統一發證登\n      記，其營利事業登記證上均載有其登記字號，本件菲力電\n      子遊藝場最早申請設立時之營利事業名稱為金馬遊樂場，\n      自79年12月起其營利事業登記證字號為51621號，其後歷\n      次變更登記其登記證字號雖增加位數，但上開基本號碼「\n      51621」均包含在所編之登記證字號內。朱文正為負責人\n      時營利事業名稱已為「菲力電子遊藝場」其營利事業登記\n      證字號為苗商登字第51621-3號，原告受讓後取得之營利\n      事業登記證字號為苗商登字第05162103號（見訴願卷第45\n      頁以下），足認原告受讓前後，該營利事業之同一性並未\n      變更。準此，本件菲力電子遊藝場雖變更負責人，由原告\n      繼續經營，但該商號名稱所表彰之商業即營利事業並無更\n      易，且該原告既繼受該同一商業之權利義務，則該商業先\n      前違法經營賭博行為之法律效果，即營利事業登記證經主\n      管機關撤銷之處分，依電子遊戲場業管理條例第31條之規\n      定，原告身為負責人並無再事爭執之依據。\n    (三)況就立法目的觀之，為貫徹電子遊戲場業管理條例第31條\n      之規範目的，電子遊戲場業前因違反行政義務而應受撤銷\n      營利事業登記處分時，其後受讓該營利事業者，亦應承受\n      被撤銷營利事業登記處分之法律效果。否則，電子遊戲場\n      業者（不論係公司或獨資、合夥等商業組織）一旦涉及賭\n      博之不法行為，即可藉由轉讓變更登記而規避法律責任，\n      此一現象當非立法之本意。\n    (四)菲力電子遊藝場原登記負責人朱文正業因常業賭博罪經法\n      院判決有期徒刑5月確定，均如前述。又被告係依首揭電\n      子遊戲場業管理條例第17條第1項第6款、第31條規定，撤\n      銷菲力電子遊藝場苗商登字第00000000-0號營利事業登記\n      證，並依同法第11條第3項前段註銷其電子遊戲場業級別\n      證已如前述，亦即菲力電子遊藝場因涉及賭博行為，經被\n      告依上開法律規定而為撤銷營利事業登記之處分，並非違\n      法授益行政處分之撤銷，與被告先前准許原告負責人變更\n      登記，核屬互不相干之二事。原告所謂被告未立即對朱文\n      正科處罰鍰並為停業之處分，且未於91年朱文正刑事判決\n      確定後隨即撤銷營利事業登記證，迄兩年後始為系爭撤銷\n      處分，訴願決定亦認為被告有行政疏失云云，經查訴願決\n      定並未為如上之認定，原告就此核屬誤會。又人民構成行\n      政上信賴保護原則，須有信賴基礎、信賴表現及信賴客觀\n      上值得保護等三要件，原告亦未證明其信賴表現行為存在\n      ，自無其所稱應有信賴保護原則之適用。綜上，本件並無\n      信賴保護原則之適用，原處分亦與誠信原則無違。\n    (五)又首揭電子遊戲場業管理條例第17條第1項第6款、第31條\n      規定「撤銷營利事業登記證」，係對營利事業之管理行為\n      ，對違規情節嚴重之營利事業課以撤銷營利事業登記證之\n      處分，並非處罰負責人個人，自無須具備行政罰故意過失\n      之責任要件。原告此部分指摘核無足採。\n四、綜上所述，原告所述各節俱無足採，原處分並無違誤，訴願\n    決定予以維持亦無不合，原告訴請撤銷均無理由，應予駁回\n    。\n據上論結，本件原告之訴為無理由，依行政訴訟法第195條第1項\n後段、第98條第3項前段，判決如主文。\n中    華    民    國    94    年    6    月    16     日\n                  第二庭 審判長 法  官  王茂修\n                                法  官  王德麟\n                                法  官  許金釵\n以上正本證明與原本無異。\n如不服本判決，應於判決送達後20日內向本院提出上訴書狀，其\n未表明上訴理由者，應於提起上訴後20日內向本院提出上訴理由\n書（須依對造人數附具繕本）；如於本判決宣示或公告後送達前\n提起上訴者，應於判決送達後20日內補提上訴理由書（須附繕本\n）。未表明上訴理由者，逕以裁定駁回。\n提起上訴應預繳送達用雙掛號郵票390元（34元及5元郵票各10份\n)。\n中    華    民    國    94    年    6    月    17     日\n                                書記官  孫庠熙\n",
  "structure": {
    "main": "原告之訴駁回。\n訴訟費用由原告負擔。",
    "fact": "一、事實概要：\n    原告甲○○經被告核准登記，在苗栗縣苗栗市○○里○○鄰○\n    ○路77號（嗣後變更為苗栗縣頭份鎮○○里○○路57號1樓\n    ）開設菲力電子遊藝場，領有被告核發苗商登字第05162100\n    -5號營利事業登記證，核准營業項目為：「J701010電子遊\n    戲場業（限制級）」該商號前負責人朱文正因賭博案件，經\n    台灣苗栗地方法院91年度易字第260號刑事判決有罪確定，\n    被告以原告違反電子遊戲場業管理條例第17條第1項第6款規\n    定，依同法第31條後段規定，以93年8月26日府建工字第093\n    0088550號函撤銷菲力電子遊藝場苗商登字第05162103-1號\n    （嗣後更正為苗商登字第00000000-0號）營利事業登記證及\n    電子遊戲場業級別證，原告不服，提起行政訴訟。\n二、兩造之聲明：\n    (一)原告聲明求為判決：\n      1.訴願決定及原處分均撤銷。\n      2.訴訟費用由被告負擔。\n    (二)被告聲明求為判決：\n      1.原告之訴駁回。\n      2.訴訟費用由原告負擔。\n三、兩造之陳述：\n    (一)原告部分：\n      1.按「行政行為應受法律及一般法律原則之拘束」，為行\n        政程序法第4條所明定；是以，行政機關為行政罰之行\n        政處分時亦應受刑法第1條：「行為之處罰，以行為時\n        之法律有明文規定者，為限」所定「罪刑法定主義」之\n        科罰原則拘束。又「對人民違反行政法上義務之行為科\n        處罰鍰，涉及人民權利之限制，其處罰構成要件及數額\n        ，應由法律定之。若法律就其構成要件，授權以命令為\n        補充規定者，授權之內容及範圍應具體明確，然後據以\n        發布命令，始符憲法第23條以法律限制人民權利之意旨\n        」為司法院釋字第313號解釋所明釋。\n      2.查電子遊戲場業管理條例第31條係規定：違反第17條第\n        1項第6款規定者（即經營電子遊戲場業者，不得有涉及\n        賭博、妨害風化或其他犯罪行為），處負責人新台幣50\n        萬元以上250萬元以下罰鍰，並令其停業；經法院判決\n        有罪確定者，撤銷其公司或營利事業之登記或部分登記\n        事項。準此，電子遊戲場業之負責人有涉及賭博行為並\n        經法院判決有罪確定時，應撤銷其營利事業登記；如負\n        責人未涉及賭博行為並經法院判決有罪確定者，自不應\n        撤銷其營利事業登記。本件朱文正為負責人經營菲力電\n        子遊藝場時之營利事業登記證為苗商登字第05162103-1\n        號，固涉有賭博行為；惟朱文正出售營業予原告並經被\n        告核准變更登記營利事業登記證為苗商登字第05162103\n        號，嗣被告核准原告變更營業地址至苗栗縣頭份鎮之營\n        利事業登記為苗商登字第00000000-0號，在原告為負責\n        人經營期間，從無涉及賭博行為，被告行政處分竟以原\n        告為處分行為人，並逕指「原告開設之菲力電子遊藝場\n        ，違法經營賭博等，案經台灣苗栗地方法院91年度易字\n        第260號刑事判決確定」云云，則被告之行政處分誣捏\n        事實，適用法律並有違上開法律規定與解釋意旨。\n      3.次按「行政行為，應以誠實信用之方法為之，並應保護\n        人民正當合理之信賴」，為行政程序法第8條所明定；\n        又「信賴保護原則攸關憲法上人民權利之保障，公權力\n        行使涉及人民信賴利益而有保護之必要者，不限於授益\n        行政處分之撤銷或廢止（行政程序法第119條、第120條\n        及第126條參照），即行政法規之廢止或變更亦有其適\n        用。‧‧‧」，則為司法院釋字第525號解釋著有明文\n        。\n      4.查朱文正係於91年1月27日涉及賭博行為，遭警查獲，\n        並於91年7月23日經台灣苗栗地方法院91年度易字第260\n        號刑事判決確定。倘被告於朱文正涉及賭博行為時（91\n        年1月27日），依電子遊戲場業管理條例第31條前段規\n        定科處罰鍰並令其停業，或迅即於91年7月23日判決確\n        定後，撤銷朱文正為負責人之菲力電子遊戲場營利事業\n        登記證，則原告自不至於也不可能於91年8月12日受讓\n        朱文正之營業。是以，原告信賴被告掌管之營利事業登\n        記，並信賴被告所為兩次核准變更登記，竟於受讓營業\n        兩年後即93年8月26日突接被告以原告為行為人之撤銷\n        營利事業登記；被告所為行政處分，已違反上開法律規\n        定與解釋意旨。\n      5.再按「人民違反法律上之義務而應受行政罰之行為，法\n        律無特別規定時，雖不以出於故意為必要，仍須以過失\n        為其責任條件。但應受行政罰之行為，僅須違反禁止規\n        定或作為義務，而不以發生損害或危險為其要件者，推\n        定為有過失，於行為人不能舉證證明自己無過失時，即\n        應受處罰」，為司法院釋字第275號解釋所明釋。本件\n        原告並無電子遊戲場業管理條例第17條第1項第6款所定\n        之行為，自不應受該條例第31條規定之處罰。而且，原\n        告受讓菲力電子遊藝場之營業，並無過失；被告就本件\n        有行使公權力之行政上疏失，則為經濟部訴願決定書確\n        認，自無轉嫁原告負擔之理。原告既無故意，亦無過失\n        ，被告竟以原告為行政處罰之當事人，自有違上開解釋\n        所示行政罰原則。\n      6.末按「人民營業之自由為憲法上工作權及財產權所保障\n        。有關營業許可之條件，營業應遵守之義務及違反義務\n        應受之制裁，依憲法第23條規定，均應以法律定之，其\n        內容更須符合該條規定之要件。‧‧‧」，司法院釋字\n        第514號解釋著有明文。原告自朱文正受讓菲力電子遊\n        藝場而自為負責人之經營期間，並無涉及賭博行為而遭\n        刑事判決確定情事，自無電子遊戲場業管理條例第31條\n        規定之適用之餘地；同時，電子遊戲場業管理條例第31\n        條亦無營業承受人應承受前手違反行政義務而應受處罰\n        之規定。是以，被告所為原行政處分逕以原告為行為人\n        ，並指稱原告有涉及賭博行為並已遭刑事判決確定云云\n        ，進而撤銷原告之營利事業登記，顯有違上開解釋意旨\n        。\n    (二)被告部分：\n      1.電子遊戲場業管理條例第17條第1項第6款規定：「經營\n        電子遊戲場業者，應遵守下列事項：‧‧‧（六）不得\n        有涉及賭博、妨害風化或其他犯罪行為。」同法第31條\n        ：「違反第17條第6款規定者，處負責人新台幣50萬以\n        上250萬以下罰鍰，並令其停業，經法院有罪判決確定\n        者，撤銷其公司或營利事業之登記或部分登記事項。」\n      2.原告陳訴其非賭博罪之違法行為人，而係朱文正之營業\n        承受人，無違反電子遊戲場業管理條例第17條、31規定\n        之情事等等一節，經查菲力電子遊藝場前負責人朱文正\n        於91年1月27日於所經營之菲力電子遊藝場內經苗栗縣\n        警察局查獲涉及賭博行為，並經台灣苗栗地方法院91年\n        度易字第260號刑事判決有罪確定，菲力電子遊藝場雖\n        於91年8月11日向被告辦理營利事業負責人變更登記，\n        由朱文正變更登記為原告，惟依據經濟部89年9月1日經\n        商字第89216127號函示略以：「違反電子遊戲場業管理\n        條例第17條第1項第6款規定，雖負責人變更，仍可撤銷\n        電子遊戲場業之營利事業登記或部分登記事項。」\n      3.被告以93年8月26日府建工字第0930088550號函撤銷菲\n        力電子遊藝場營利事業登記證及電子遊戲場業營業級別\n        證之處分，依法並無不合，請駁回原告之訴。",
    "reason": "一、按「經營電子遊戲場業者，應遵守下列事項：‧‧‧六、不\n    得有涉及賭博、妨害風化或其他犯罪行為」，電子遊戲場業\n    管理條例第17條第1項第6款定有明文，違反該款規定者，依\n    同法第31條規定，處負責人新台幣50萬元以上250萬元以下\n    罰鍰，並令其停業，經法院判決有罪確定者，撤銷其公司或\n    營利事業之登記或部分登記事項。又「主管機關依法撤銷電\n    子遊戲場業營利事業登記時，應一併註銷其營業級別證‧‧\n    ‧」同條例第11條第3項前段定有明文。稽之上開規範之目\n    的，一則在對違反禁止義務之電子遊戲場業者之負責人課以\n    怠於防範或監督之罰鍰責任，另則在於違反行政法義務的商\n    業（不論是公司或獨資、合夥等商業組織）為命令停業處分\n    ，其經法院判決有罪確定者，撤銷其公司或營利事業之登記\n    ，以懲治其不法營業，並防止違規情事再犯，藉收管制行政\n    秩序之目的。\n二、本件訴外人朱文正前經被告核准於苗栗縣苗栗市○○里○○鄰\n    ○○路77號開設菲力電子遊藝場，領有被告核發苗商登字第\n    05162103-1號營利事業登記證，核准營業項目為：「J70101\n    0電子遊戲場業（限制級）」。91年1月27日經苗栗縣警察局\n    苗栗分局查獲該電子遊藝場涉有賭博行為，並經台灣苗栗地\n    方法院91年度易字第260號刑事判決有期徒刑5月確定（未上\n    訴）。被告乃以菲力電子遊藝場違法經營賭博業，經法院判\n    決有罪確定為由，依電子遊戲場業管理條例第31條之規定，\n    以93年8月26日府建工字第0930088550號函撤銷菲力電子遊\n    藝場苗商登字第05162103-1號營利事業登記證及電子遊戲場\n    業級別證，嗣復以94年1月5日府建工字第0940002248號函更\n    正上開處分所載營利事業登記證號碼為00000000-0號等情，\n    有系爭營利事業登記證、該營利事業歷次變更登記資料、刑\n    事判決影本及查詢上訴事宜之公務電話紀錄、被告上開函文\n    等分附訴願卷及本院卷可憑，自堪信為實在。\n三、原告雖起訴主張：(一)渠承受菲力電子遊藝場後，從未涉及賭\n    博行為，不應受電子遊戲場業管理條例第31條之處罰，且依\n    司法院釋字第275號解釋意旨，原告既無故意過失自不應受\n    行政罰，原處分竟以原告為處分行為人，並逕指「原告開設\n    之菲力電子遊藝場，違法經營賭博等，案經台灣苗栗地方法\n    院91年度易第260號刑事判決確定」云云，誣捏事實處分原\n    告，顯屬違法。(二)被告於朱文正涉及賭博，被告未立即對之\n    科處罰鍰並為停業之處分，且未於91年7月23日朱文正刑事\n    判決確定後隨即撤銷營利事業登記證，迄93年8月26日始為\n    系爭撤銷處分，訴願決定亦認為被告有行政疏失。原告信賴\n    被告掌管之營利事業登記，並信賴被告核准原告變更負責人\n    及變更營業地址之登記，詎被告於原告受讓營業兩年後突然\n    撤銷原告之營利事業登記證，顯違誠信原則及信賴保護原則\n    等語。經查：\n    (一)菲力電子遊藝場原設址於苗栗縣苗栗市○○里○○鄰○○路\n      77號，陳設電動機具水果檯等供人押注決定輸贏，累積積\n      分記明於寄存卡，其原負責人朱文正基於常業賭博之犯意\n      ，僱請楊昭吉喬裝成客人，提供現金供其他客人兌換積分\n      ，於91年1月27日經警查獲，朱文正於91年7月23日經判決\n      常業賭博罪，並未上訴業已確定。原告於91年8月12日受\n      讓該營利事業繼續經營，並向被告辦理負責人變更登記，\n      有營利事業統一發證變更登記申請書及被告准予變更登記\n      函等附訴願卷可考，均堪憑信。\n    (二)查商業登記法第2條規定：「本法所稱商業，謂以營利為\n      目的，以獨資或合夥方式經營之事業」，可知商業為一營\n      利事業，每一個商業即營利事業有一個統一編號，就如同\n      每一個自然人有一個身分證統一編號一般，而商號之負責\n      人雖有變動，但該商號名稱所表彰之商業即營利事業並無\n      更易，仍是同一，縱使主管機關因商業即營利事業之負責\n      人變動，而發給申請人一紙新的營利事業登記證，但該申\n      請人既沿用原商業之名稱及營利事業之統一編號，即非一\n      新設立之商業，自應繼受該商業即營利事業之權利義務（\n      最高行政法院92年度判字第95號判決參照）。又依電子遊\n      戲場業管理條例第3條規定：「本條例所稱電子遊戲場業\n      ，指設置電子遊戲機供不特定人益智娛樂之營利事業」，\n      足見電子遊戲場業為營利事業，屬於商業登記法所稱之商\n      業，自有上開見解之適用。被告辦理營利事業統一發證登\n      記，其營利事業登記證上均載有其登記字號，本件菲力電\n      子遊藝場最早申請設立時之營利事業名稱為金馬遊樂場，\n      自79年12月起其營利事業登記證字號為51621號，其後歷\n      次變更登記其登記證字號雖增加位數，但上開基本號碼「\n      51621」均包含在所編之登記證字號內。朱文正為負責人\n      時營利事業名稱已為「菲力電子遊藝場」其營利事業登記\n      證字號為苗商登字第51621-3號，原告受讓後取得之營利\n      事業登記證字號為苗商登字第05162103號（見訴願卷第45\n      頁以下），足認原告受讓前後，該營利事業之同一性並未\n      變更。準此，本件菲力電子遊藝場雖變更負責人，由原告\n      繼續經營，但該商號名稱所表彰之商業即營利事業並無更\n      易，且該原告既繼受該同一商業之權利義務，則該商業先\n      前違法經營賭博行為之法律效果，即營利事業登記證經主\n      管機關撤銷之處分，依電子遊戲場業管理條例第31條之規\n      定，原告身為負責人並無再事爭執之依據。\n    (三)況就立法目的觀之，為貫徹電子遊戲場業管理條例第31條\n      之規範目的，電子遊戲場業前因違反行政義務而應受撤銷\n      營利事業登記處分時，其後受讓該營利事業者，亦應承受\n      被撤銷營利事業登記處分之法律效果。否則，電子遊戲場\n      業者（不論係公司或獨資、合夥等商業組織）一旦涉及賭\n      博之不法行為，即可藉由轉讓變更登記而規避法律責任，\n      此一現象當非立法之本意。\n    (四)菲力電子遊藝場原登記負責人朱文正業因常業賭博罪經法\n      院判決有期徒刑5月確定，均如前述。又被告係依首揭電\n      子遊戲場業管理條例第17條第1項第6款、第31條規定，撤\n      銷菲力電子遊藝場苗商登字第00000000-0號營利事業登記\n      證，並依同法第11條第3項前段註銷其電子遊戲場業級別\n      證已如前述，亦即菲力電子遊藝場因涉及賭博行為，經被\n      告依上開法律規定而為撤銷營利事業登記之處分，並非違\n      法授益行政處分之撤銷，與被告先前准許原告負責人變更\n      登記，核屬互不相干之二事。原告所謂被告未立即對朱文\n      正科處罰鍰並為停業之處分，且未於91年朱文正刑事判決\n      確定後隨即撤銷營利事業登記證，迄兩年後始為系爭撤銷\n      處分，訴願決定亦認為被告有行政疏失云云，經查訴願決\n      定並未為如上之認定，原告就此核屬誤會。又人民構成行\n      政上信賴保護原則，須有信賴基礎、信賴表現及信賴客觀\n      上值得保護等三要件，原告亦未證明其信賴表現行為存在\n      ，自無其所稱應有信賴保護原則之適用。綜上，本件並無\n      信賴保護原則之適用，原處分亦與誠信原則無違。\n    (五)又首揭電子遊戲場業管理條例第17條第1項第6款、第31條\n      規定「撤銷營利事業登記證」，係對營利事業之管理行為\n      ，對違規情節嚴重之營利事業課以撤銷營利事業登記證之\n      處分，並非處罰負責人個人，自無須具備行政罰故意過失\n      之責任要件。原告此部分指摘核無足採。\n四、綜上所述，原告所述各節俱無足採，原處分並無違誤，訴願\n    決定予以維持亦無不合，原告訴請撤銷均無理由，應予駁回\n    。\n據上論結，本件原告之訴為無理由，依行政訴訟法第195條第1項\n後段、第98條第3項前段，判決如主文。\n中    華    民    國    94    年    6    月    16     日\n                  第二庭 審判長 法  官  王茂修\n                                法  官  王德麟\n                                法  官  許金釵\n以上正本證明與原本無異。\n如不服本判決，應於判決送達後20日內向本院提出上訴書狀，其\n未表明上訴理由者，應於提起上訴後20日內向本院提出上訴理由\n書（須依對造人數附具繕本）；如於本判決宣示或公告後送達前\n提起上訴者，應於判決送達後20日內補提上訴理由書（須附繕本\n）。未表明上訴理由者，逕以裁定駁回。\n提起上訴應預繳送達用雙掛號郵票390元（34元及5元郵票各10份\n)。"
  },
  "search": "臺中高等行政法院判決94年度訴字第00149號.原告甲○○訴訟代理人施瑞章律師被告苗栗縣政府代表人乙○○訴訟代理人丙○○上列當事人間因電子遊戲場業管理條例事件，原告不服經濟部中華民國94年1月27日經訴字第09406121850號訴願決定，提起行政訴訟。本院判決如下︰主文原告之訴駁回。訴訟費用由原告負擔。事實一、事實概要：原告甲○○經被告核准登記，在苗栗縣苗栗市○○里○○鄰○○路77號（嗣後變更為苗栗縣頭份鎮○○里○○路57號1樓）開設菲力電子遊藝場，領有被告核發苗商登字第05162100-5號營利事業登記證，核准營業項目為：「J701010電子遊戲場業（限制級）」該商號前負責人朱文正因賭博案件，經台灣苗栗地方法院91年度易字第260號刑事判決有罪確定，被告以原告違反電子遊戲場業管理條例第17條第1項第6款規定，依同法第31條後段規定，以93年8月26日府建工字第0930088550號函撤銷菲力電子遊藝場苗商登字第05162103-1號（嗣後更正為苗商登字第00000000-0號）營利事業登記證及電子遊戲場業級別證，原告不服，提起行政訴訟。二、兩造之聲明：(一)原告聲明求為判決：1.訴願決定及原處分均撤銷。2.訴訟費用由被告負擔。(二)被告聲明求為判決：1.原告之訴駁回。2.訴訟費用由原告負擔。三、兩造之陳述：(一)原告部分：1.按「行政行為應受法律及一般法律原則之拘束」，為行政程序法第4條所明定；是以，行政機關為行政罰之行政處分時亦應受刑法第1條：「行為之處罰，以行為時之法律有明文規定者，為限」所定「罪刑法定主義」之科罰原則拘束。又「對人民違反行政法上義務之行為科處罰鍰，涉及人民權利之限制，其處罰構成要件及數額，應由法律定之。若法律就其構成要件，授權以命令為補充規定者，授權之內容及範圍應具體明確，然後據以發布命令，始符憲法第23條以法律限制人民權利之意旨」為司法院釋字第313號解釋所明釋。2.查電子遊戲場業管理條例第31條係規定：違反第17條第1項第6款規定者（即經營電子遊戲場業者，不得有涉及賭博、妨害風化或其他犯罪行為），處負責人新台幣50萬元以上250萬元以下罰鍰，並令其停業；經法院判決有罪確定者，撤銷其公司或營利事業之登記或部分登記事項。準此，電子遊戲場業之負責人有涉及賭博行為並經法院判決有罪確定時，應撤銷其營利事業登記；如負責人未涉及賭博行為並經法院判決有罪確定者，自不應撤銷其營利事業登記。本件朱文正為負責人經營菲力電子遊藝場時之營利事業登記證為苗商登字第05162103-1號，固涉有賭博行為；惟朱文正出售營業予原告並經被告核准變更登記營利事業登記證為苗商登字第05162103號，嗣被告核准原告變更營業地址至苗栗縣頭份鎮之營利事業登記為苗商登字第00000000-0號，在原告為負責人經營期間，從無涉及賭博行為，被告行政處分竟以原告為處分行為人，並逕指「原告開設之菲力電子遊藝場，違法經營賭博等，案經台灣苗栗地方法院91年度易字第260號刑事判決確定」云云，則被告之行政處分誣捏事實，適用法律並有違上開法律規定與解釋意旨。3.次按「行政行為，應以誠實信用之方法為之，並應保護人民正當合理之信賴」，為行政程序法第8條所明定；又「信賴保護原則攸關憲法上人民權利之保障，公權力行使涉及人民信賴利益而有保護之必要者，不限於授益行政處分之撤銷或廢止（行政程序法第119條、第120條及第126條參照），即行政法規之廢止或變更亦有其適用。‧‧‧」，則為司法院釋字第525號解釋著有明文。4.查朱文正係於91年1月27日涉及賭博行為，遭警查獲，並於91年7月23日經台灣苗栗地方法院91年度易字第260號刑事判決確定。倘被告於朱文正涉及賭博行為時（91年1月27日），依電子遊戲場業管理條例第31條前段規定科處罰鍰並令其停業，或迅即於91年7月23日判決確定後，撤銷朱文正為負責人之菲力電子遊戲場營利事業登記證，則原告自不至於也不可能於91年8月12日受讓朱文正之營業。是以，原告信賴被告掌管之營利事業登記，並信賴被告所為兩次核准變更登記，竟於受讓營業兩年後即93年8月26日突接被告以原告為行為人之撤銷營利事業登記；被告所為行政處分，已違反上開法律規定與解釋意旨。5.再按「人民違反法律上之義務而應受行政罰之行為，法律無特別規定時，雖不以出於故意為必要，仍須以過失為其責任條件。但應受行政罰之行為，僅須違反禁止規定或作為義務，而不以發生損害或危險為其要件者，推定為有過失，於行為人不能舉證證明自己無過失時，即應受處罰」，為司法院釋字第275號解釋所明釋。本件原告並無電子遊戲場業管理條例第17條第1項第6款所定之行為，自不應受該條例第31條規定之處罰。而且，原告受讓菲力電子遊藝場之營業，並無過失；被告就本件有行使公權力之行政上疏失，則為經濟部訴願決定書確認，自無轉嫁原告負擔之理。原告既無故意，亦無過失，被告竟以原告為行政處罰之當事人，自有違上開解釋所示行政罰原則。6.末按「人民營業之自由為憲法上工作權及財產權所保障。有關營業許可之條件，營業應遵守之義務及違反義務應受之制裁，依憲法第23條規定，均應以法律定之，其內容更須符合該條規定之要件。‧‧‧」，司法院釋字第514號解釋著有明文。原告自朱文正受讓菲力電子遊藝場而自為負責人之經營期間，並無涉及賭博行為而遭刑事判決確定情事，自無電子遊戲場業管理條例第31條規定之適用之餘地；同時，電子遊戲場業管理條例第31條亦無營業承受人應承受前手違反行政義務而應受處罰之規定。是以，被告所為原行政處分逕以原告為行為人，並指稱原告有涉及賭博行為並已遭刑事判決確定云云，進而撤銷原告之營利事業登記，顯有違上開解釋意旨。(二)被告部分：1.電子遊戲場業管理條例第17條第1項第6款規定：「經營電子遊戲場業者，應遵守下列事項：‧‧‧（六）不得有涉及賭博、妨害風化或其他犯罪行為。」同法第31條：「違反第17條第6款規定者，處負責人新台幣50萬以上250萬以下罰鍰，並令其停業，經法院有罪判決確定者，撤銷其公司或營利事業之登記或部分登記事項。」2.原告陳訴其非賭博罪之違法行為人，而係朱文正之營業承受人，無違反電子遊戲場業管理條例第17條、31規定之情事等等一節，經查菲力電子遊藝場前負責人朱文正於91年1月27日於所經營之菲力電子遊藝場內經苗栗縣警察局查獲涉及賭博行為，並經台灣苗栗地方法院91年度易字第260號刑事判決有罪確定，菲力電子遊藝場雖於91年8月11日向被告辦理營利事業負責人變更登記，由朱文正變更登記為原告，惟依據經濟部89年9月1日經商字第89216127號函示略以：「違反電子遊戲場業管理條例第17條第1項第6款規定，雖負責人變更，仍可撤銷電子遊戲場業之營利事業登記或部分登記事項。」3.被告以93年8月26日府建工字第0930088550號函撤銷菲力電子遊藝場營利事業登記證及電子遊戲場業營業級別證之處分，依法並無不合，請駁回原告之訴。理由一、按「經營電子遊戲場業者，應遵守下列事項：‧‧‧六、不得有涉及賭博、妨害風化或其他犯罪行為」，電子遊戲場業管理條例第17條第1項第6款定有明文，違反該款規定者，依同法第31條規定，處負責人新台幣50萬元以上250萬元以下罰鍰，並令其停業，經法院判決有罪確定者，撤銷其公司或營利事業之登記或部分登記事項。又「主管機關依法撤銷電子遊戲場業營利事業登記時，應一併註銷其營業級別證‧‧‧」同條例第11條第3項前段定有明文。稽之上開規範之目的，一則在對違反禁止義務之電子遊戲場業者之負責人課以怠於防範或監督之罰鍰責任，另則在於違反行政法義務的商業（不論是公司或獨資、合夥等商業組織）為命令停業處分，其經法院判決有罪確定者，撤銷其公司或營利事業之登記，以懲治其不法營業，並防止違規情事再犯，藉收管制行政秩序之目的。二、本件訴外人朱文正前經被告核准於苗栗縣苗栗市○○里○○鄰○○路77號開設菲力電子遊藝場，領有被告核發苗商登字第05162103-1號營利事業登記證，核准營業項目為：「J701010電子遊戲場業（限制級）」。91年1月27日經苗栗縣警察局苗栗分局查獲該電子遊藝場涉有賭博行為，並經台灣苗栗地方法院91年度易字第260號刑事判決有期徒刑5月確定（未上訴）。被告乃以菲力電子遊藝場違法經營賭博業，經法院判決有罪確定為由，依電子遊戲場業管理條例第31條之規定，以93年8月26日府建工字第0930088550號函撤銷菲力電子遊藝場苗商登字第05162103-1號營利事業登記證及電子遊戲場業級別證，嗣復以94年1月5日府建工字第0940002248號函更正上開處分所載營利事業登記證號碼為00000000-0號等情，有系爭營利事業登記證、該營利事業歷次變更登記資料、刑事判決影本及查詢上訴事宜之公務電話紀錄、被告上開函文等分附訴願卷及本院卷可憑，自堪信為實在。三、原告雖起訴主張：(一)渠承受菲力電子遊藝場後，從未涉及賭博行為，不應受電子遊戲場業管理條例第31條之處罰，且依司法院釋字第275號解釋意旨，原告既無故意過失自不應受行政罰，原處分竟以原告為處分行為人，並逕指「原告開設之菲力電子遊藝場，違法經營賭博等，案經台灣苗栗地方法院91年度易第260號刑事判決確定」云云，誣捏事實處分原告，顯屬違法。(二)被告於朱文正涉及賭博，被告未立即對之科處罰鍰並為停業之處分，且未於91年7月23日朱文正刑事判決確定後隨即撤銷營利事業登記證，迄93年8月26日始為系爭撤銷處分，訴願決定亦認為被告有行政疏失。原告信賴被告掌管之營利事業登記，並信賴被告核准原告變更負責人及變更營業地址之登記，詎被告於原告受讓營業兩年後突然撤銷原告之營利事業登記證，顯違誠信原則及信賴保護原則等語。經查：(一)菲力電子遊藝場原設址於苗栗縣苗栗市○○里○○鄰○○路77號，陳設電動機具水果檯等供人押注決定輸贏，累積積分記明於寄存卡，其原負責人朱文正基於常業賭博之犯意，僱請楊昭吉喬裝成客人，提供現金供其他客人兌換積分，於91年1月27日經警查獲，朱文正於91年7月23日經判決常業賭博罪，並未上訴業已確定。原告於91年8月12日受讓該營利事業繼續經營，並向被告辦理負責人變更登記，有營利事業統一發證變更登記申請書及被告准予變更登記函等附訴願卷可考，均堪憑信。(二)查商業登記法第2條規定：「本法所稱商業，謂以營利為目的，以獨資或合夥方式經營之事業」，可知商業為一營利事業，每一個商業即營利事業有一個統一編號，就如同每一個自然人有一個身分證統一編號一般，而商號之負責人雖有變動，但該商號名稱所表彰之商業即營利事業並無更易，仍是同一，縱使主管機關因商業即營利事業之負責人變動，而發給申請人一紙新的營利事業登記證，但該申請人既沿用原商業之名稱及營利事業之統一編號，即非一新設立之商業，自應繼受該商業即營利事業之權利義務（最高行政法院92年度判字第95號判決參照）。又依電子遊戲場業管理條例第3條規定：「本條例所稱電子遊戲場業，指設置電子遊戲機供不特定人益智娛樂之營利事業」，足見電子遊戲場業為營利事業，屬於商業登記法所稱之商業，自有上開見解之適用。被告辦理營利事業統一發證登記，其營利事業登記證上均載有其登記字號，本件菲力電子遊藝場最早申請設立時之營利事業名稱為金馬遊樂場，自79年12月起其營利事業登記證字號為51621號，其後歷次變更登記其登記證字號雖增加位數，但上開基本號碼「51621」均包含在所編之登記證字號內。朱文正為負責人時營利事業名稱已為「菲力電子遊藝場」其營利事業登記證字號為苗商登字第51621-3號，原告受讓後取得之營利事業登記證字號為苗商登字第05162103號（見訴願卷第45頁以下），足認原告受讓前後，該營利事業之同一性並未變更。準此，本件菲力電子遊藝場雖變更負責人，由原告繼續經營，但該商號名稱所表彰之商業即營利事業並無更易，且該原告既繼受該同一商業之權利義務，則該商業先前違法經營賭博行為之法律效果，即營利事業登記證經主管機關撤銷之處分，依電子遊戲場業管理條例第31條之規定，原告身為負責人並無再事爭執之依據。(三)況就立法目的觀之，為貫徹電子遊戲場業管理條例第31條之規範目的，電子遊戲場業前因違反行政義務而應受撤銷營利事業登記處分時，其後受讓該營利事業者，亦應承受被撤銷營利事業登記處分之法律效果。否則，電子遊戲場業者（不論係公司或獨資、合夥等商業組織）一旦涉及賭博之不法行為，即可藉由轉讓變更登記而規避法律責任，此一現象當非立法之本意。(四)菲力電子遊藝場原登記負責人朱文正業因常業賭博罪經法院判決有期徒刑5月確定，均如前述。又被告係依首揭電子遊戲場業管理條例第17條第1項第6款、第31條規定，撤銷菲力電子遊藝場苗商登字第00000000-0號營利事業登記證，並依同法第11條第3項前段註銷其電子遊戲場業級別證已如前述，亦即菲力電子遊藝場因涉及賭博行為，經被告依上開法律規定而為撤銷營利事業登記之處分，並非違法授益行政處分之撤銷，與被告先前准許原告負責人變更登記，核屬互不相干之二事。原告所謂被告未立即對朱文正科處罰鍰並為停業之處分，且未於91年朱文正刑事判決確定後隨即撤銷營利事業登記證，迄兩年後始為系爭撤銷處分，訴願決定亦認為被告有行政疏失云云，經查訴願決定並未為如上之認定，原告就此核屬誤會。又人民構成行政上信賴保護原則，須有信賴基礎、信賴表現及信賴客觀上值得保護等三要件，原告亦未證明其信賴表現行為存在，自無其所稱應有信賴保護原則之適用。綜上，本件並無信賴保護原則之適用，原處分亦與誠信原則無違。(五)又首揭電子遊戲場業管理條例第17條第1項第6款、第31條規定「撤銷營利事業登記證」，係對營利事業之管理行為，對違規情節嚴重之營利事業課以撤銷營利事業登記證之處分，並非處罰負責人個人，自無須具備行政罰故意過失之責任要件。原告此部分指摘核無足採。四、綜上所述，原告所述各節俱無足採，原處分並無違誤，訴願決定予以維持亦無不合，原告訴請撤銷均無理由，應予駁回。據上論結，本件原告之訴為無理由，依行政訴訟法第195條第1項後段、第98條第3項前段，判決如主文。中華民國94年6月16日第二庭審判長法官王茂修法官王德麟法官許金釵以上正本證明與原本無異。如不服本判決，應於判決送達後20日內向本院提出上訴書狀，其未表明上訴理由者，應於提起上訴後20日內向本院提出上訴理由書（須依對造人數附具繕本）；如於本判決宣示或公告後送達前提起上訴者，應於判決送達後20日內補提上訴理由書（須附繕本）。未表明上訴理由者，逕以裁定駁回。提起上訴應預繳送達用雙掛號郵票390元（34元及5元郵票各10份)。中華民國94年6月17日書記官孫庠熙",
  "characters": {
    "judges": [
      "王茂修",
      "王德麟",
      "許金釵"
    ],
    "prosecutors": [

    ],
    "lawyers": [

    ],
    "clerks": [
      "孫庠熙"
    ],
    "plaintiffs": [
      "甲"
    ],
    "defendants": [
      "苗栗縣政府",
      "代  表  人  乙○○"
    ],
    "prosecutor_office": [

    ],
    "creditors": [

    ],
    "debtors": [

    ],
    "judicial_associate_officer": [

    ]
  },
  "adjudged_at": "2005-06-16",
  "created_at": "2016-02-07 06:33:02",
  "updated_at": "2016-02-07 06:33:02"
}