{
  "identify": "PCD-94-易-210-20050225-1",
  "court": {
    "name": "臺灣新北地方法院",
    "code": "PCD"
  },
  "division": {
    "name": "刑事",
    "code": "M"
  },
  "year": 94,
  "word": "易",
  "number": "210",
  "jcheck": "1",
  "reason": "傷害等",
  "content": "臺灣板橋地方法院刑事判決               94年度易字第210號\n聲  請  人  臺灣板橋地方法院檢察署檢察官\n被      告  甲○○\n上列被告因傷害等案件，經檢察官聲請簡易判決處刑（94年度調\n偵字第2 號），本院認有刑事訴訟法第451 條之1 第4 項但書所\n列情形，爰改用通常程序判決如下：\n    主  文\n本件公訴不受理。\n    理  由\n一、公訴意旨詳如檢察官聲請簡易判決處刑書所載（如附件）。\n二、按告訴乃論之罪，告訴人於第一審辯論終結前得撤回其告訴\n    ，又告訴經撤回者，應諭知不受理之判決，且得不經言詞辯\n    論為之，刑事訴訟法第238 條第1 項、第303 條第3 款及第\n    307 條分別定有明文。又按檢察官聲請以簡易判決處刑之案\n    件，經法院認為有第451 條之1 第4 項但書之情形者，應適\n    用通常程序審判之，同法第452條亦有明定。\n三、本件告訴人乙○○告訴被告甲○○傷害等案件，檢察官聲請\n    簡易判決處刑書認被告係觸犯刑法第277 條第1 項之普通傷\n    害罪及第354 條之毀損罪，依同法第287 條及第357 條之規\n    定，均須告訴乃論。\n四、茲據告訴人乙○○於民國94年2 月22日本院訊問時具狀撤回\n    其告訴，有撤回告訴狀一紙在卷可稽，揆諸首開說明，本件\n    應改依通常程序，並不經言詞辯論，諭知不受理之判決。\n五、據上論斷，應依刑事訴訟法第452 條、第303 條第3 款、第\n    307 條，判決如主文。\n中    華    民    國    94    年    2     月    25    日\n                  刑事第十二庭  審判長法  官  樊季康\n                                      法  官  陳明珠\n                                      法  官  劉元斐\n上列正本證明與原本無異。\n如不服本判決，應於送達後十日內向本院提出上訴書狀。\n                                 書記官   郭玉芬\n中    華    民    國    94    年    2     月    25    日\n",
  "structure": {
    "main": "本件公訴不受理。",
    "reason": "一、公訴意旨詳如檢察官聲請簡易判決處刑書所載（如附件）。\n二、按告訴乃論之罪，告訴人於第一審辯論終結前得撤回其告訴\n    ，又告訴經撤回者，應諭知不受理之判決，且得不經言詞辯\n    論為之，刑事訴訟法第238 條第1 項、第303 條第3 款及第\n    307 條分別定有明文。又按檢察官聲請以簡易判決處刑之案\n    件，經法院認為有第451 條之1 第4 項但書之情形者，應適\n    用通常程序審判之，同法第452條亦有明定。\n三、本件告訴人乙○○告訴被告甲○○傷害等案件，檢察官聲請\n    簡易判決處刑書認被告係觸犯刑法第277 條第1 項之普通傷\n    害罪及第354 條之毀損罪，依同法第287 條及第357 條之規\n    定，均須告訴乃論。\n四、茲據告訴人乙○○於民國94年2 月22日本院訊問時具狀撤回\n    其告訴，有撤回告訴狀一紙在卷可稽，揆諸首開說明，本件\n    應改依通常程序，並不經言詞辯論，諭知不受理之判決。\n五、據上論斷，應依刑事訴訟法第452 條、第303 條第3 款、第\n    307 條，判決如主文。"
  },
  "search": "臺灣板橋地方法院刑事判決94年度易字第210號聲請人臺灣板橋地方法院檢察署檢察官被告甲○○上列被告因傷害等案件，經檢察官聲請簡易判決處刑（94年度調偵字第2號），本院認有刑事訴訟法第451條之1第4項但書所列情形，爰改用通常程序判決如下：主文本件公訴不受理。理由一、公訴意旨詳如檢察官聲請簡易判決處刑書所載（如附件）。二、按告訴乃論之罪，告訴人於第一審辯論終結前得撤回其告訴，又告訴經撤回者，應諭知不受理之判決，且得不經言詞辯論為之，刑事訴訟法第238條第1項、第303條第3款及第307條分別定有明文。又按檢察官聲請以簡易判決處刑之案件，經法院認為有第451條之1第4項但書之情形者，應適用通常程序審判之，同法第452條亦有明定。三、本件告訴人乙○○告訴被告甲○○傷害等案件，檢察官聲請簡易判決處刑書認被告係觸犯刑法第277條第1項之普通傷害罪及第354條之毀損罪，依同法第287條及第357條之規定，均須告訴乃論。四、茲據告訴人乙○○於民國94年2月22日本院訊問時具狀撤回其告訴，有撤回告訴狀一紙在卷可稽，揆諸首開說明，本件應改依通常程序，並不經言詞辯論，諭知不受理之判決。五、據上論斷，應依刑事訴訟法第452條、第303條第3款、第307條，判決如主文。中華民國94年2月25日刑事第十二庭審判長法官樊季康法官陳明珠法官劉元斐上列正本證明與原本無異。如不服本判決，應於送達後十日內向本院提出上訴書狀。書記官郭玉芬中華民國94年2月25日",
  "characters": {
    "judges": [
      "樊季康",
      "陳明珠",
      "劉元斐"
    ],
    "prosecutors": [

    ],
    "lawyers": [

    ],
    "clerks": [
      "郭玉芬"
    ],
    "plaintiffs": [

    ],
    "defendants": [
      "甲○○"
    ],
    "prosecutor_office": [
      "臺灣板橋地方法院檢察署檢察官"
    ],
    "creditors": [

    ],
    "debtors": [

    ],
    "judicial_associate_officer": [

    ]
  },
  "adjudged_at": "2005-02-25",
  "created_at": "2016-02-06 17:07:38",
  "updated_at": "2016-02-06 17:07:38"
}