{
  "identify": "TPH-93-上易-707-20050224-3",
  "court": {
    "name": "臺灣高等法院",
    "code": "TPH"
  },
  "division": {
    "name": "民事",
    "code": "V"
  },
  "year": 93,
  "word": "上易",
  "number": "707",
  "jcheck": "3",
  "reason": "確認租賃關係存在",
  "content": "臺灣高等法院民事裁定                 93年度上易字第707號\n上  訴  人  甲○○\n右當事人與私立明新科技大學間確認租賃關係存在事件，上訴人\n對於中華民國九十三年十月二十六日本院判決，提起上訴，本院\n裁定如左：\n    主      文\n上訴駁回。\n第三審訴訟費用由上訴人負擔。\n    理      由\n一、按提起第三審上訴應繳納裁判費及委任律師為訴訟代理人，\n    此為必備之程式。上訴不合程式或有其他不合法之情形而可\n    以補正者，第一審法院應定期間命其補正，如不於期間內補\n    正者，應以裁定駁回之。此於提起第三審上訴準用之。次按\n    對於第二審判決上訴，上訴人應委任律師為訴訟代理人。上\n    訴人未依第一項、第二項規定委任訴訟代理人，第二審法院\n    應定期先命補正。逾期未補正亦未依第四百六十六條之二而\n    聲請訴訟救助者，第二審法院應以上訴不合法裁定駁回之。\n    民事訴訟法第四百八十一條、第四百四十二條第二項及同法\n    第四百六十六條之一定有明文。\n二、查上訴人提起上訴，未據繳納第三審裁判費，且未於上訴狀\n    內提出委任律師或具律師資格之關係人為訴訟代理人之委任\n    狀，經本院以裁定限期命其於七日內補正，上訴人甲○○業\n    於民國九十四年一月二十日收受該裁定正本送達，有送達證\n    書存卷可按，茲已逾限，仍未遵行，其上訴自非合法，應予\n    駁回，爰裁定如主文。\n中    華    民    國    94    年    2     月    24    日\n                  民事第三庭審判長法  官  林敬修\n                                  法  官  劉勝吉\n                                  法  官  藍文祥\n正本係照原本作成。\n本裁定除以適用法規顯有錯誤為理由，並經本院許可外，不得再\n抗告。如提起再抗告，應於收受後十日內委任律師為訴訟代理人\n向本院提出再抗告狀。並繳納再抗告費新台幣一千元。\n中    華    民    國    94    年    2     月    25    日\n                                  書記官  顧倪淑貞\n",
  "structure": {
    "main": "上訴駁回。\n第三審訴訟費用由上訴人負擔。",
    "reason": "一、按提起第三審上訴應繳納裁判費及委任律師為訴訟代理人，\n    此為必備之程式。上訴不合程式或有其他不合法之情形而可\n    以補正者，第一審法院應定期間命其補正，如不於期間內補\n    正者，應以裁定駁回之。此於提起第三審上訴準用之。次按\n    對於第二審判決上訴，上訴人應委任律師為訴訟代理人。上\n    訴人未依第一項、第二項規定委任訴訟代理人，第二審法院\n    應定期先命補正。逾期未補正亦未依第四百六十六條之二而\n    聲請訴訟救助者，第二審法院應以上訴不合法裁定駁回之。\n    民事訴訟法第四百八十一條、第四百四十二條第二項及同法\n    第四百六十六條之一定有明文。\n二、查上訴人提起上訴，未據繳納第三審裁判費，且未於上訴狀\n    內提出委任律師或具律師資格之關係人為訴訟代理人之委任\n    狀，經本院以裁定限期命其於七日內補正，上訴人甲○○業\n    於民國九十四年一月二十日收受該裁定正本送達，有送達證\n    書存卷可按，茲已逾限，仍未遵行，其上訴自非合法，應予\n    駁回，爰裁定如主文。"
  },
  "search": "臺灣高等法院民事裁定93年度上易字第707號上訴人甲○○右當事人與私立明新科技大學間確認租賃關係存在事件，上訴人對於中華民國九十三年十月二十六日本院判決，提起上訴，本院裁定如左：主文上訴駁回。第三審訴訟費用由上訴人負擔。理由一、按提起第三審上訴應繳納裁判費及委任律師為訴訟代理人，此為必備之程式。上訴不合程式或有其他不合法之情形而可以補正者，第一審法院應定期間命其補正，如不於期間內補正者，應以裁定駁回之。此於提起第三審上訴準用之。次按對於第二審判決上訴，上訴人應委任律師為訴訟代理人。上訴人未依第一項、第二項規定委任訴訟代理人，第二審法院應定期先命補正。逾期未補正亦未依第四百六十六條之二而聲請訴訟救助者，第二審法院應以上訴不合法裁定駁回之。民事訴訟法第四百八十一條、第四百四十二條第二項及同法第四百六十六條之一定有明文。二、查上訴人提起上訴，未據繳納第三審裁判費，且未於上訴狀內提出委任律師或具律師資格之關係人為訴訟代理人之委任狀，經本院以裁定限期命其於七日內補正，上訴人甲○○業於民國九十四年一月二十日收受該裁定正本送達，有送達證書存卷可按，茲已逾限，仍未遵行，其上訴自非合法，應予駁回，爰裁定如主文。中華民國94年2月24日民事第三庭審判長法官林敬修法官劉勝吉法官藍文祥正本係照原本作成。本裁定除以適用法規顯有錯誤為理由，並經本院許可外，不得再抗告。如提起再抗告，應於收受後十日內委任律師為訴訟代理人向本院提出再抗告狀。並繳納再抗告費新台幣一千元。中華民國94年2月25日書記官顧倪淑貞",
  "characters": {
    "judges": [
      "林敬修",
      "劉勝吉",
      "藍文祥"
    ],
    "prosecutors": [

    ],
    "lawyers": [
      "內提出委任律師或具"
    ],
    "clerks": [
      "顧倪淑貞"
    ],
    "plaintiffs": [

    ],
    "defendants": [

    ],
    "prosecutor_office": [

    ],
    "creditors": [

    ],
    "debtors": [

    ],
    "judicial_associate_officer": [

    ]
  },
  "adjudged_at": "2005-02-24",
  "created_at": "2016-02-06 17:18:41",
  "updated_at": "2016-02-06 17:18:41"
}