{
  "identify": "TYD-93-訴-1306-20050225-3",
  "court": {
    "name": "臺灣桃園地方法院",
    "code": "TYD"
  },
  "division": {
    "name": "刑事",
    "code": "M"
  },
  "year": 93,
  "word": "訴",
  "number": "1306",
  "jcheck": "3",
  "reason": "違反槍砲彈藥刀械管制條例等",
  "content": "臺灣桃園地方法院刑事裁定              93年度訴字第1306號\n公  訴  人  台灣桃園地方法院檢察署檢察官\n被      告  甲○○  男  29歲.\n選任辯護人  趙元昊律師\n右列被告因違反槍砲彈藥刀械管制條例等案件，經檢察官提起公\n訴，本院裁定如左：\n    主  文\n甲○○自民國玖拾肆年月陸日起延長羈押貳月。\n    理  由\n本件被告因違反槍砲彈藥刀械管制條例案件，經本院認有刑事訴\n訟法第一百零一條第一項第三款、第一百零一條之一第一項第五\n款之情形，而有羈押必要，於民國九十三年八月六日執行羈押，\n茲本院以前項原因依然存在，仍有繼續羈押之必要，且被告在獄\n中有具體事證證明與其父勾串證人，非予羈押，顯難進行審理，\n被告及其委任之辯護人請求停止羈押尚無理由，並為擔保日後能\n順利執行，著自民國九十四年三月六日起延長羈押二月。爰依刑\n事訴訟法第一百零八條第一項規定，裁定如主文。\n中    華    民    國    94    年    2     月    25    日\n                        臺灣桃園地方法院刑事第二庭\n                              審判長法  官  徐培元\n                                    法  官  潘進順\n                                    法  官  陳心婷\n右正本証明與原本無異。\n如不服本裁定應於送達後五日內向本院提出抗告狀。\n                                    書記官  陳青瑜\n中    華    民    國    94    年    2     月    25    日\n",
  "structure": {
    "main": "甲○○自民國玖拾肆年月陸日起延長羈押貳月。",
    "reason": "本件被告因違反槍砲彈藥刀械管制條例案件，經本院認有刑事訴\n訟法第一百零一條第一項第三款、第一百零一條之一第一項第五\n款之情形，而有羈押必要，於民國九十三年八月六日執行羈押，\n茲本院以前項原因依然存在，仍有繼續羈押之必要，且被告在獄\n中有具體事證證明與其父勾串證人，非予羈押，顯難進行審理，\n被告及其委任之辯護人請求停止羈押尚無理由，並為擔保日後能\n順利執行，著自民國九十四年三月六日起延長羈押二月。爰依刑\n事訴訟法第一百零八條第一項規定，裁定如主文。"
  },
  "search": "臺灣桃園地方法院刑事裁定93年度訴字第1306號公訴人台灣桃園地方法院檢察署檢察官被告甲○○男29歲.選任辯護人趙元昊律師右列被告因違反槍砲彈藥刀械管制條例等案件，經檢察官提起公訴，本院裁定如左：主文甲○○自民國玖拾肆年月陸日起延長羈押貳月。理由本件被告因違反槍砲彈藥刀械管制條例案件，經本院認有刑事訴訟法第一百零一條第一項第三款、第一百零一條之一第一項第五款之情形，而有羈押必要，於民國九十三年八月六日執行羈押，茲本院以前項原因依然存在，仍有繼續羈押之必要，且被告在獄中有具體事證證明與其父勾串證人，非予羈押，顯難進行審理，被告及其委任之辯護人請求停止羈押尚無理由，並為擔保日後能順利執行，著自民國九十四年三月六日起延長羈押二月。爰依刑事訴訟法第一百零八條第一項規定，裁定如主文。中華民國94年2月25日臺灣桃園地方法院刑事第二庭審判長法官徐培元法官潘進順法官陳心婷右正本証明與原本無異。如不服本裁定應於送達後五日內向本院提出抗告狀。書記官陳青瑜中華民國94年2月25日",
  "characters": {
    "judges": [
      "徐培元",
      "潘進順",
      "陳心婷"
    ],
    "prosecutors": [

    ],
    "lawyers": [
      "趙元昊"
    ],
    "clerks": [
      "陳青瑜"
    ],
    "plaintiffs": [

    ],
    "defendants": [
      "甲○○  男  29歲."
    ],
    "prosecutor_office": [
      "台灣桃園地方法院檢察署檢察官"
    ],
    "creditors": [

    ],
    "debtors": [

    ],
    "judicial_associate_officer": [

    ]
  },
  "adjudged_at": "2005-02-25",
  "created_at": "2016-02-06 17:14:41",
  "updated_at": "2016-02-06 17:14:41"
}