{
  "identify": "CYD-93-簡上-146-20040806-1",
  "court": {
    "name": "臺灣嘉義地方法院",
    "code": "CYD"
  },
  "division": {
    "name": "刑事",
    "code": "M"
  },
  "year": 93,
  "word": "簡上",
  "number": "146",
  "jcheck": "1",
  "reason": "違反動產擔保交易法",
  "content": "臺灣嘉義地方法院刑事判決                        九十三年度簡上字第一四六號\n    上  訴  人  甲○○\n右上訴人因違反動產擔保交易法案件，不服中華民國九十三年五月二十八日本院嘉義\n簡易庭九十三年度嘉簡字第四三三號第一審判決（臺灣嘉義地方法院檢察署檢察官聲\n請簡易處刑案號九十三年度偵字第二八八四號），提起上訴，本院管轄之第二審合議\n庭判決如左：\n    主  文\n上訴駁回。\n甲○○緩刑貳年。\n    事  實\n一、甲○○於民國九十一年十一月十一日以附條件買賣方式，向吳家峰（即光華機車\n    行）購買車牌號碼ＺＺＮ─二八二號輕型機車乙部，總價款為新臺幣（下同）三\n    萬七千九百五十元，雙方約定自九十一年十二月十五日起至九十二年十月十五日\n    止分十一期給付，每月十五日付款，每期付款三千四百五十元，並約定標的物之\n    存放地點為嘉義市○○路三四九巷一五號住居處。甲○○於取得前開機車之後，\n    僅繳納二期分期價金，自九十二年二月起即未再繳納分期價金，且基於不法之利\n    益，於同年月二十五日將上開機車以七千元之價格出售予位在嘉義市○○路六○\n    六號之建志機車行，嗣吳家峰追索無著而受有損害。\n二、案經被害人吳家峰訴由臺灣嘉義地方法院檢察署檢察官偵查後聲請簡易判決處刑\n    。\n    理  由\n一、認定犯罪事實所憑之証據及理由：\n    上訴人甲○○對於前揭犯罪事實坦承不諱，且與告訴人之指述相符，復有附條件\n    買賣契約書及甲○○將前開機車售予建志機車行之機車買賣合約書、機車車籍資\n    料影本各乙紙附卷足憑，上訴人之犯行足堪認定。\n二、論罪科刑之理由：\n(一)核被告所為，係犯動產擔保交易法第三十八條之罪。原審依刑事訴訟法第四百四\n    十九條第一項、第四百五十四條第二項，動產擔保交易法第三十八條、刑法第十\n    一條前段、第四十一條第一項前段，罰金罰鍰提高標準條例第一條前段、第二條\n    ，逕以簡易判決判處拘役十二日，如易科罰金以三百元折算一日，經核其認事用\n    法及量刑均屬妥適，被告上訴意旨指摘原判決不當，為無理由，應予駁回。\n(二)審酌被告犯罪後業與告訴人達成和解，有和解筆錄附卷可稽；且查被告前未曾受\n    有期徒刑以上刑之宣告，因一時失慮觸犯刑罰，事後已坦承犯行，深具悔意，經\n    此刑之宣告後，應知警惕而無再犯之虞，本院因認暫不執行其刑為當，予以宣告\n    緩刑，以啟自新。\n三、適用法律依據：\n(一)刑事訴訟法第四百五十五條之一第一項、第三項、第三百六十八條。\n(二)刑法第七十四條第一款。\n本案經檢察官黃正雄到庭執行職務\n中    華    民    國      九十三     年      八     月        六        日\n                                    臺灣嘉義地方法院刑事第五庭\n                                        審判長  法  官  黃國益\n                                                法  官  黃仁勇\n                                                法  官  黃義成\n右正本證明與原本無異。\n本件不得上訴。\n中    華    民    國      九十三     年      八     月        六        日\n                                                書記官  林育興\n論罪法條：\n動產擔保交易法第三十八條\n動產擔保交易之債務人，意圖不法之利益，將標的物遷移、出賣、出質、移轉、抵押\n或為其他處分，致生損害於債權人者，處三年以下有期徒刑、拘役或科或併科六千元\n以下之罰金。\n",
  "structure": {
    "main": "上訴駁回。\n甲○○緩刑貳年。",
    "fact": "一、甲○○於民國九十一年十一月十一日以附條件買賣方式，向吳家峰（即光華機車\n    行）購買車牌號碼ＺＺＮ─二八二號輕型機車乙部，總價款為新臺幣（下同）三\n    萬七千九百五十元，雙方約定自九十一年十二月十五日起至九十二年十月十五日\n    止分十一期給付，每月十五日付款，每期付款三千四百五十元，並約定標的物之\n    存放地點為嘉義市○○路三四九巷一五號住居處。甲○○於取得前開機車之後，\n    僅繳納二期分期價金，自九十二年二月起即未再繳納分期價金，且基於不法之利\n    益，於同年月二十五日將上開機車以七千元之價格出售予位在嘉義市○○路六○\n    六號之建志機車行，嗣吳家峰追索無著而受有損害。\n二、案經被害人吳家峰訴由臺灣嘉義地方法院檢察署檢察官偵查後聲請簡易判決處刑\n    。",
    "reason": "一、認定犯罪事實所憑之証據及理由：\n    上訴人甲○○對於前揭犯罪事實坦承不諱，且與告訴人之指述相符，復有附條件\n    買賣契約書及甲○○將前開機車售予建志機車行之機車買賣合約書、機車車籍資\n    料影本各乙紙附卷足憑，上訴人之犯行足堪認定。\n二、論罪科刑之理由：\n(一)核被告所為，係犯動產擔保交易法第三十八條之罪。原審依刑事訴訟法第四百四\n    十九條第一項、第四百五十四條第二項，動產擔保交易法第三十八條、刑法第十\n    一條前段、第四十一條第一項前段，罰金罰鍰提高標準條例第一條前段、第二條\n    ，逕以簡易判決判處拘役十二日，如易科罰金以三百元折算一日，經核其認事用\n    法及量刑均屬妥適，被告上訴意旨指摘原判決不當，為無理由，應予駁回。\n(二)審酌被告犯罪後業與告訴人達成和解，有和解筆錄附卷可稽；且查被告前未曾受\n    有期徒刑以上刑之宣告，因一時失慮觸犯刑罰，事後已坦承犯行，深具悔意，經\n    此刑之宣告後，應知警惕而無再犯之虞，本院因認暫不執行其刑為當，予以宣告\n    緩刑，以啟自新。\n三、適用法律依據：\n(一)刑事訴訟法第四百五十五條之一第一項、第三項、第三百六十八條。\n(二)刑法第七十四條第一款。\n本案經檢察官黃正雄到庭執行職務\n中    華    民    國      九十三     年      八     月        六        日\n                                    臺灣嘉義地方法院刑事第五庭\n                                        審判長  法  官  黃國益\n                                                法  官  黃仁勇\n                                                法  官  黃義成\n右正本證明與原本無異。\n本件不得上訴。"
  },
  "search": "臺灣嘉義地方法院刑事判決九十三年度簡上字第一四六號上訴人甲○○右上訴人因違反動產擔保交易法案件，不服中華民國九十三年五月二十八日本院嘉義簡易庭九十三年度嘉簡字第四三三號第一審判決（臺灣嘉義地方法院檢察署檢察官聲請簡易處刑案號九十三年度偵字第二八八四號），提起上訴，本院管轄之第二審合議庭判決如左：主文上訴駁回。甲○○緩刑貳年。事實一、甲○○於民國九十一年十一月十一日以附條件買賣方式，向吳家峰（即光華機車行）購買車牌號碼ＺＺＮ─二八二號輕型機車乙部，總價款為新臺幣（下同）三萬七千九百五十元，雙方約定自九十一年十二月十五日起至九十二年十月十五日止分十一期給付，每月十五日付款，每期付款三千四百五十元，並約定標的物之存放地點為嘉義市○○路三四九巷一五號住居處。甲○○於取得前開機車之後，僅繳納二期分期價金，自九十二年二月起即未再繳納分期價金，且基於不法之利益，於同年月二十五日將上開機車以七千元之價格出售予位在嘉義市○○路六○六號之建志機車行，嗣吳家峰追索無著而受有損害。二、案經被害人吳家峰訴由臺灣嘉義地方法院檢察署檢察官偵查後聲請簡易判決處刑。理由一、認定犯罪事實所憑之証據及理由：上訴人甲○○對於前揭犯罪事實坦承不諱，且與告訴人之指述相符，復有附條件買賣契約書及甲○○將前開機車售予建志機車行之機車買賣合約書、機車車籍資料影本各乙紙附卷足憑，上訴人之犯行足堪認定。二、論罪科刑之理由：(一)核被告所為，係犯動產擔保交易法第三十八條之罪。原審依刑事訴訟法第四百四十九條第一項、第四百五十四條第二項，動產擔保交易法第三十八條、刑法第十一條前段、第四十一條第一項前段，罰金罰鍰提高標準條例第一條前段、第二條，逕以簡易判決判處拘役十二日，如易科罰金以三百元折算一日，經核其認事用法及量刑均屬妥適，被告上訴意旨指摘原判決不當，為無理由，應予駁回。(二)審酌被告犯罪後業與告訴人達成和解，有和解筆錄附卷可稽；且查被告前未曾受有期徒刑以上刑之宣告，因一時失慮觸犯刑罰，事後已坦承犯行，深具悔意，經此刑之宣告後，應知警惕而無再犯之虞，本院因認暫不執行其刑為當，予以宣告緩刑，以啟自新。三、適用法律依據：(一)刑事訴訟法第四百五十五條之一第一項、第三項、第三百六十八條。(二)刑法第七十四條第一款。本案經檢察官黃正雄到庭執行職務中華民國九十三年八月六日臺灣嘉義地方法院刑事第五庭審判長法官黃國益法官黃仁勇法官黃義成右正本證明與原本無異。本件不得上訴。中華民國九十三年八月六日書記官林育興論罪法條：動產擔保交易法第三十八條動產擔保交易之債務人，意圖不法之利益，將標的物遷移、出賣、出質、移轉、抵押或為其他處分，致生損害於債權人者，處三年以下有期徒刑、拘役或科或併科六千元以下之罰金。",
  "characters": {
    "judges": [
      "黃國益",
      "黃仁勇",
      "黃義成"
    ],
    "prosecutors": [
      "黃正雄"
    ],
    "lawyers": [

    ],
    "clerks": [
      "林育興"
    ],
    "plaintiffs": [

    ],
    "defendants": [

    ],
    "prosecutor_office": [

    ],
    "creditors": [

    ],
    "debtors": [

    ],
    "judicial_associate_officer": [

    ]
  },
  "adjudged_at": "2004-08-06",
  "created_at": "2016-02-06 02:31:48",
  "updated_at": "2016-02-06 02:31:48"
}