{
  "identify": "TPD-93-除-1973-20040630-1",
  "court": {
    "name": "臺灣臺北地方法院",
    "code": "TPD"
  },
  "division": {
    "name": "民事",
    "code": "V"
  },
  "year": 93,
  "word": "除",
  "number": "1973",
  "jcheck": "1",
  "reason": "除權判決",
  "content": "臺灣臺北地方法院民事判決                        九十三年度除字第一九七三號\n    聲  請  人  乙○○\n    訴訟代理人  甲○○\n聲請人聲請除權判決事件，本院判決如左：\n    主  文\n如附表所示之支票無效。\n訴訟費用由聲請人負擔。\n    理  由\n一、上開支票，經本院以九十二年度催字第四三七０號公示催告。\n二、所定申報權利期間，已於民國九十三年五月三十一日屆滿，迄今均無人申報權利\n    。\n三、依民事訴訟法第五百六十四條第一項，判決如主文。\n中      華      民      國    九十三    年    六        月    三十      日\n                               民事第六庭審判長法  官   林惠瑜\n                                               法  官   詹駿鴻\n                                               法  官   姚念慈\n┌──────────────────────────────────────────────────────┐\n│附表：                                                                                                      │\n├─┬─────────┬─────────┬───────────┬────────┬────────┬──┤\n│編│  發    票    人  │  付    款    人  │發        票        日│ 票  面  金  額 │ 支  票  號  碼 │備考│\n│號│                  │                  │                      │   （新臺幣）   │                │    │\n├─┼─────────┼─────────┼───────────┼────────┼────────┼──┤\n│１│乙○○            │華南銀行新生分行  │九十年十月二十日      │二萬二千一百六十│0000000  │    │\n│  │                  │                  │                      │八元            │                │    │\n└─┴─────────┴─────────┴───────────┴────────┴────────┴──┘\n右為正本係照原本作成。\n本判決不得上訴。\n中      華      民      國    九十三    年      七      月    一        日\n                                               書記官   朱俶伶\n",
  "structure": {
    "main": "如附表所示之支票無效。\n訴訟費用由聲請人負擔。",
    "reason": "一、上開支票，經本院以九十二年度催字第四三七０號公示催告。\n二、所定申報權利期間，已於民國九十三年五月三十一日屆滿，迄今均無人申報權利\n    。\n三、依民事訴訟法第五百六十四條第一項，判決如主文。"
  },
  "search": "臺灣臺北地方法院民事判決九十三年度除字第一九七三號聲請人乙○○訴訟代理人甲○○聲請人聲請除權判決事件，本院判決如左：主文如附表所示之支票無效。訴訟費用由聲請人負擔。理由一、上開支票，經本院以九十二年度催字第四三七０號公示催告。二、所定申報權利期間，已於民國九十三年五月三十一日屆滿，迄今均無人申報權利。三、依民事訴訟法第五百六十四條第一項，判決如主文。中華民國九十三年六月三十日民事第六庭審判長法官林惠瑜法官詹駿鴻法官姚念慈┌──────────────────────────────────────────────────────┐│附表：│├─┬─────────┬─────────┬───────────┬────────┬────────┬──┤│編│發票人│付款人│發票日│票面金額│支票號碼│備考││號││││（新臺幣）│││├─┼─────────┼─────────┼───────────┼────────┼────────┼──┤│１│乙○○│華南銀行新生分行│九十年十月二十日│二萬二千一百六十│0000000│││││││八元│││└─┴─────────┴─────────┴───────────┴────────┴────────┴──┘右為正本係照原本作成。本判決不得上訴。中華民國九十三年七月一日書記官朱俶伶",
  "characters": {
    "judges": [
      "林惠瑜",
      "詹駿鴻",
      "姚念慈"
    ],
    "prosecutors": [

    ],
    "lawyers": [

    ],
    "clerks": [
      "朱俶伶"
    ],
    "plaintiffs": [

    ],
    "defendants": [

    ],
    "prosecutor_office": [
      "乙"
    ],
    "creditors": [

    ],
    "debtors": [

    ],
    "judicial_associate_officer": [

    ]
  },
  "adjudged_at": "2004-06-30",
  "created_at": "2016-02-06 09:20:58",
  "updated_at": "2016-02-06 09:20:58"
}