{
  "identify": "TYD-92-附民-155-20040629-1",
  "court": {
    "name": "臺灣桃園地方法院",
    "code": "TYD"
  },
  "division": {
    "name": "刑事",
    "code": "M"
  },
  "year": 92,
  "word": "附民",
  "number": "155",
  "jcheck": "1",
  "reason": "請求賠償損害",
  "content": "臺灣桃園地方法院刑事附帶民事訴訟判決            九十二年度附民字第一五五號\n    原      告  乙○○\n    訴訟代理人  王永春律師\n    複  代理人  邱基祥律師\n    被      告  甲○○\n                宏泰成實業有限公司\n    右  一  人\n    代  表  人  葉雙鳳\n右列被告因九十二年度訴字第二七０號違反著作權法等案件，經原告提起附帶民事訴\n訟，本院判決如左：\n    主  文\n原告之訴及假執行之聲請均駁回。\n    事  實\n一、原告訴之聲明及陳述如附件起訴狀所載。\n二、被告未為聲明及陳述。\n    理  由\n一、按刑事訴訟諭知無罪之判決者，對於附帶民事訴訟部份應以判決駁回原告之訴，\n    刑事訴訟法第五百零三條第一項前段定有明文。\n二、查本件被告甲○○、宏泰成實業有限公司被訴違反著作權法等案件，業經刑事判\n    決諭知無罪，依前揭法律規定，原告之訴自應予以駁回，其假執行聲請，亦失所\n    附麗，應併予駁回。\n三、據上論斷，應依刑事訴訟法第五百零三條第一項前段，判決如主文。\n中      華      民      國      九十三      年    六      月    二十九日\n                                        臺灣桃園地方法院刑事第九庭\n                                              審判長法  官  林明洲\n                                                    法  官  林春鈴\n                                                    法  官  黃斯偉\n右正本證明與原本無異。\n對於本判決如不服非對刑事判決上訴時不得上訴並應於送達後十日內向本院提出上訴\n狀。\n                                                    書記官  李珈慧\n中      華      民      國      九十三      年    六      月    二十九  日\n",
  "structure": {
    "main": "原告之訴及假執行之聲請均駁回。",
    "fact": "一、原告訴之聲明及陳述如附件起訴狀所載。\n二、被告未為聲明及陳述。",
    "reason": "一、按刑事訴訟諭知無罪之判決者，對於附帶民事訴訟部份應以判決駁回原告之訴，\n    刑事訴訟法第五百零三條第一項前段定有明文。\n二、查本件被告甲○○、宏泰成實業有限公司被訴違反著作權法等案件，業經刑事判\n    決諭知無罪，依前揭法律規定，原告之訴自應予以駁回，其假執行聲請，亦失所\n    附麗，應併予駁回。\n三、據上論斷，應依刑事訴訟法第五百零三條第一項前段，判決如主文。\n中      華      民      國      九十三      年    六      月    二十九日\n                                        臺灣桃園地方法院刑事第九庭\n                                              審判長法  官  林明洲\n                                                    法  官  林春鈴\n                                                    法  官  黃斯偉\n右正本證明與原本無異。\n對於本判決如不服非對刑事判決上訴時不得上訴並應於送達後十日內向本院提出上訴\n狀。\n                                                    書記官  李珈慧"
  },
  "search": "臺灣桃園地方法院刑事附帶民事訴訟判決九十二年度附民字第一五五號原告乙○○訴訟代理人王永春律師複代理人邱基祥律師被告甲○○宏泰成實業有限公司右一人代表人葉雙鳳右列被告因九十二年度訴字第二七０號違反著作權法等案件，經原告提起附帶民事訴訟，本院判決如左：主文原告之訴及假執行之聲請均駁回。事實一、原告訴之聲明及陳述如附件起訴狀所載。二、被告未為聲明及陳述。理由一、按刑事訴訟諭知無罪之判決者，對於附帶民事訴訟部份應以判決駁回原告之訴，刑事訴訟法第五百零三條第一項前段定有明文。二、查本件被告甲○○、宏泰成實業有限公司被訴違反著作權法等案件，業經刑事判決諭知無罪，依前揭法律規定，原告之訴自應予以駁回，其假執行聲請，亦失所附麗，應併予駁回。三、據上論斷，應依刑事訴訟法第五百零三條第一項前段，判決如主文。中華民國九十三年六月二十九日臺灣桃園地方法院刑事第九庭審判長法官林明洲法官林春鈴法官黃斯偉右正本證明與原本無異。對於本判決如不服非對刑事判決上訴時不得上訴並應於送達後十日內向本院提出上訴狀。書記官李珈慧中華民國九十三年六月二十九日",
  "characters": {
    "judges": [
      "林明洲",
      "林春鈴",
      "黃斯偉"
    ],
    "prosecutors": [

    ],
    "lawyers": [
      "王永春",
      "邱基祥"
    ],
    "clerks": [
      "李珈慧"
    ],
    "plaintiffs": [
      "乙"
    ],
    "defendants": [
      "甲○○"
    ],
    "prosecutor_office": [

    ],
    "creditors": [

    ],
    "debtors": [

    ],
    "judicial_associate_officer": [

    ]
  },
  "adjudged_at": "2004-06-29",
  "created_at": "2016-02-06 09:26:18",
  "updated_at": "2016-02-06 09:26:18"
}