{
  "identify": "TCD-99-交易-565-20110131-2",
  "court": {
    "name": "臺灣臺中地方法院",
    "code": "TCD"
  },
  "division": {
    "name": "刑事",
    "code": "M"
  },
  "year": 99,
  "word": "交易",
  "number": "565",
  "jcheck": "2",
  "reason": "過失傷害",
  "content": "臺灣臺中地方法院刑事裁定             99年度交易字第565號\n公  訴  人  臺灣臺中地方法院檢察署檢察官\n被      告  廖婉婷\n上列被告因過失傷害案件，本院於民國九十九年九月三十日所為\n之判決之原本及其正本，茲發現有誤，應裁定更正如下：\n    主    文\n原判決之原本及其正本當事人欄內關於被告廖婉婷之年齡、出生\n年月日應更正為「28歲」、「民國71年9月19日生」。\n    理    由\n一、按刑事判決文字，顯係誤寫，而不影響於全案情節與判決之\n    本旨者，參照民事訴訟法第二百三十二條規定，原審法院得\n    以裁定更正之。業經司法院大法官會議釋字第四三號解釋在\n    案。\n二、本件原判決之原本及其正本當事人欄內關於被告廖婉婷之出\n    生年月日、年紀之記載經核與其個人基本資料查詢結果有異\n    ，茲就此等錯誤依據其個人基本資料查詢結果予以裁定更正\n    如主文所示。\n三、爰依刑事訴訟法第二百二十條裁定如主文。\n中    華    民    國   100    年    1     月    31    日\n                        交通法庭  法  官  林學晴\n上正本證明與原本無異。\n如不服本裁定，應於送達後五日內，向本院提出抗告狀。\n                                  書記官  簡雅文\n中    華    民    國   100    年    1     月    31    日",
  "structure": {
    "main": "原判決之原本及其正本當事人欄內關於被告廖婉婷之年齡、出生\n年月日應更正為「28歲」、「民國71年9月19日生」。",
    "reason": "一、按刑事判決文字，顯係誤寫，而不影響於全案情節與判決之\n    本旨者，參照民事訴訟法第二百三十二條規定，原審法院得\n    以裁定更正之。業經司法院大法官會議釋字第四三號解釋在\n    案。\n二、本件原判決之原本及其正本當事人欄內關於被告廖婉婷之出\n    生年月日、年紀之記載經核與其個人基本資料查詢結果有異\n    ，茲就此等錯誤依據其個人基本資料查詢結果予以裁定更正\n    如主文所示。\n三、爰依刑事訴訟法第二百二十條裁定如主文。"
  },
  "search": "臺灣臺中地方法院刑事裁定99年度交易字第565號公訴人臺灣臺中地方法院檢察署檢察官被告廖婉婷上列被告因過失傷害案件，本院於民國九十九年九月三十日所為之判決之原本及其正本，茲發現有誤，應裁定更正如下：主文原判決之原本及其正本當事人欄內關於被告廖婉婷之年齡、出生年月日應更正為「28歲」、「民國71年9月19日生」。理由一、按刑事判決文字，顯係誤寫，而不影響於全案情節與判決之本旨者，參照民事訴訟法第二百三十二條規定，原審法院得以裁定更正之。業經司法院大法官會議釋字第四三號解釋在案。二、本件原判決之原本及其正本當事人欄內關於被告廖婉婷之出生年月日、年紀之記載經核與其個人基本資料查詢結果有異，茲就此等錯誤依據其個人基本資料查詢結果予以裁定更正如主文所示。三、爰依刑事訴訟法第二百二十條裁定如主文。中華民國100年1月31日交通法庭法官林學晴上正本證明與原本無異。如不服本裁定，應於送達後五日內，向本院提出抗告狀。書記官簡雅文中華民國100年1月31日",
  "characters": {
    "judges": [
      "林學晴"
    ],
    "prosecutors": [

    ],
    "lawyers": [

    ],
    "clerks": [
      "簡雅文"
    ],
    "plaintiffs": [

    ],
    "defendants": [
      "廖婉婷"
    ],
    "prosecutor_office": [
      "臺灣臺中地方法院檢察署檢察官"
    ],
    "creditors": [

    ],
    "debtors": [

    ],
    "judicial_associate_officer": [

    ]
  },
  "adjudged_at": "2011-01-31",
  "created_at": "2016-02-13 06:13:26",
  "updated_at": "2016-02-13 06:13:26"
}