{
  "identify": "KSD-100-簡-962-20110315-1",
  "court": {
    "name": "臺灣高雄地方法院",
    "code": "KSD"
  },
  "division": {
    "name": "刑事",
    "code": "M"
  },
  "year": 100,
  "word": "簡",
  "number": "962",
  "jcheck": "1",
  "reason": "毒品危害防制條例",
  "content": "臺灣高雄地方法院刑事簡易判決          100年度簡字第962號\n聲  請  人  臺灣高雄地方法院檢察署檢察官\n被      告  蔡建一\n上列被告因違反毒品危害防制條例案件，經檢察官聲請以簡易判\n決處刑（100年度毒偵字第391號），本院判決如下：\n    主      文\n蔡建一施用第二級毒品，累犯，處有期徒刑肆月，如易科罰金，\n以新臺幣壹仟元折算壹日。\n    事實及理由\n一、本件犯罪事實及證據，除犯罪事實欄一被告前科部分更正為\n    「蔡建一前因施用毒品案件，經臺灣高雄地方法院以96年度\n    毒聲字第1270號裁定送觀察、勒戒後，認無繼續施用毒品之\n    傾向，於民國96年11月20日執行完畢釋放，並經本署檢察官\n    以96年度毒偵緝字第433號為不起訴處分確定。另因贓物案\n    件，經臺灣高雄地方法院以96年度簡字第6892號判決處有期\n    徒刑5月確定（下稱第一案）；另因詐欺案件，經臺灣高等\n    法院高雄分院以97年度上易字第369號判決處有期徒刑4月，\n    減刑為有期徒刑2月確定（下稱第二案）；第一案與第二案\n    嗣經臺灣高等法院高雄分院以97年度聲字第1140號裁定定應\n    執行刑為有期徒刑6月確定，於98年7月7日縮刑期滿執行完\n    畢（構成累犯）。又因施用毒品案件，經臺灣高雄地方法院\n    以98年度審簡字第4103號判決處有期徒刑3月確定；又因施\n    用毒品案件，經臺灣屏東地方法院以99年度簡字第1789號判\n    決處有期徒刑3月確定；又因施用毒品案件，分別經臺灣屏\n    東地方法院以99年度簡字第1789號判處有期徒刑3月、臺灣\n    高雄地方法院以99年度簡字第1152號判決處有期徒刑4月確\n    定。」、倒數第3行至倒數第1行「因另涉竊盜案件為警查獲\n    ，並徵得其同意採集尿液送檢驗後，結果呈安非他命及甲基\n    安非他命之陽性反應，始悉上情。」補充更正為「因另涉竊\n    盜案件為警查獲，蔡建一於其犯罪尚未為警員發覺前，主動\n    向警員自首坦承施用毒品犯行，並同意警員對其採取尿液送\n    驗，而接受裁判，送驗結果則呈安非他命、甲基安非他命陽\n    性反應，而查悉上情。」外，餘均引用附件檢察官聲請簡易\n    判決處刑書之記載。\n二、核被告蔡建一所為，係犯毒品危害防制條例第10條第2 項之\n    施用第二級毒品罪。其施用第二級毒品前持有該毒品之低度\n    行為，應為其施用之高度行為所吸收，不另論罪。又被告有\n    如前所載之犯罪科刑及執行情形，此見前揭臺灣高等法院被\n    告前案紀錄表自明，其於受有期徒刑執行完畢後，5 年內故\n    意再犯本件有期徒刑以上之罪，為累犯，應依刑法第47條第\n    1 項規定，加重其刑。又被告於本件施用第二級毒品罪犯罪\n    被發覺前，向警員自首其施用第二級毒品犯行而受裁判，此\n    有其警詢筆錄之記載可按，爰依刑法第62條前段之規定減輕\n    其刑，並依法先加後減之。爰審酌被告前因施用毒品案件經\n    觀察、勒戒後，猶未思積極戒毒，竟再犯本件施用第二級毒\n    品犯行，實應非難，惟念施用毒品乃自戕行為，對社會造成\n    之危害尚非直接甚鉅，而其曾有贓物、詐欺及多次違反毒品\n    危害防制條例案件之刑事前科，此品行資料有臺灣高等法院\n    被告前案紀錄表一份可查，而其生活狀況為勉持、智識程度\n    為高職肄業及犯後坦承犯行等一切情狀，量處如主文所示之\n    刑，並參酌前開犯罪情狀，諭知如主文所示易科罰金之折算\n    標準。\n三、依刑事訴訟法第449 條第1 項前段、第3 項、第454 條第 2\n    項，毒品危害防制條例第10條第2 項，刑法第11條前段、第\n    47條第1 項、第62條前段、第41條第1 項前段，逕以簡易判\n    決處刑如主文。\n四、如不服本判決，得自判決送達之日起10日內，向本院提起上\n    訴。\n中    華    民    國  100    年    3    月    15    日\n                  高雄簡易庭    法  官  徐彩芳\n以上正本證明與原本無異。\n如不服本判決，應於判決送達之日起10日內向本院提出上訴書狀\n。\n中    華    民    國    100    年    3    月    15    日\n                                書記官  張義龍\n附錄本判決論罪之法條：\n毒品危害防制條例第10條\n施用第一級毒品者，處6 月以上5 年以下有期徒刑。\n施用第二級毒品者，處3 年以下有期徒刑。",
  "structure": {
    "main": "蔡建一施用第二級毒品，累犯，處有期徒刑肆月，如易科罰金，\n以新臺幣壹仟元折算壹日。",
    "fact": "一、本件犯罪事實及證據，除犯罪事實欄一被告前科部分更正為\n    「蔡建一前因施用毒品案件，經臺灣高雄地方法院以96年度\n    毒聲字第1270號裁定送觀察、勒戒後，認無繼續施用毒品之\n    傾向，於民國96年11月20日執行完畢釋放，並經本署檢察官\n    以96年度毒偵緝字第433號為不起訴處分確定。另因贓物案\n    件，經臺灣高雄地方法院以96年度簡字第6892號判決處有期\n    徒刑5月確定（下稱第一案）；另因詐欺案件，經臺灣高等\n    法院高雄分院以97年度上易字第369號判決處有期徒刑4月，\n    減刑為有期徒刑2月確定（下稱第二案）；第一案與第二案\n    嗣經臺灣高等法院高雄分院以97年度聲字第1140號裁定定應\n    執行刑為有期徒刑6月確定，於98年7月7日縮刑期滿執行完\n    畢（構成累犯）。又因施用毒品案件，經臺灣高雄地方法院\n    以98年度審簡字第4103號判決處有期徒刑3月確定；又因施\n    用毒品案件，經臺灣屏東地方法院以99年度簡字第1789號判\n    決處有期徒刑3月確定；又因施用毒品案件，分別經臺灣屏\n    東地方法院以99年度簡字第1789號判處有期徒刑3月、臺灣\n    高雄地方法院以99年度簡字第1152號判決處有期徒刑4月確\n    定。」、倒數第3行至倒數第1行「因另涉竊盜案件為警查獲\n    ，並徵得其同意採集尿液送檢驗後，結果呈安非他命及甲基\n    安非他命之陽性反應，始悉上情。」補充更正為「因另涉竊\n    盜案件為警查獲，蔡建一於其犯罪尚未為警員發覺前，主動\n    向警員自首坦承施用毒品犯行，並同意警員對其採取尿液送\n    驗，而接受裁判，送驗結果則呈安非他命、甲基安非他命陽\n    性反應，而查悉上情。」外，餘均引用附件檢察官聲請簡易\n    判決處刑書之記載。\n二、核被告蔡建一所為，係犯毒品危害防制條例第10條第2 項之\n    施用第二級毒品罪。其施用第二級毒品前持有該毒品之低度\n    行為，應為其施用之高度行為所吸收，不另論罪。又被告有\n    如前所載之犯罪科刑及執行情形，此見前揭臺灣高等法院被\n    告前案紀錄表自明，其於受有期徒刑執行完畢後，5 年內故\n    意再犯本件有期徒刑以上之罪，為累犯，應依刑法第47條第\n    1 項規定，加重其刑。又被告於本件施用第二級毒品罪犯罪\n    被發覺前，向警員自首其施用第二級毒品犯行而受裁判，此\n    有其警詢筆錄之記載可按，爰依刑法第62條前段之規定減輕\n    其刑，並依法先加後減之。爰審酌被告前因施用毒品案件經\n    觀察、勒戒後，猶未思積極戒毒，竟再犯本件施用第二級毒\n    品犯行，實應非難，惟念施用毒品乃自戕行為，對社會造成\n    之危害尚非直接甚鉅，而其曾有贓物、詐欺及多次違反毒品\n    危害防制條例案件之刑事前科，此品行資料有臺灣高等法院\n    被告前案紀錄表一份可查，而其生活狀況為勉持、智識程度\n    為高職肄業及犯後坦承犯行等一切情狀，量處如主文所示之\n    刑，並參酌前開犯罪情狀，諭知如主文所示易科罰金之折算\n    標準。\n三、依刑事訴訟法第449 條第1 項前段、第3 項、第454 條第 2\n    項，毒品危害防制條例第10條第2 項，刑法第11條前段、第\n    47條第1 項、第62條前段、第41條第1 項前段，逕以簡易判\n    決處刑如主文。\n四、如不服本判決，得自判決送達之日起10日內，向本院提起上\n    訴。",
    "reason": "一、本件犯罪事實及證據，除犯罪事實欄一被告前科部分更正為\n    「蔡建一前因施用毒品案件，經臺灣高雄地方法院以96年度\n    毒聲字第1270號裁定送觀察、勒戒後，認無繼續施用毒品之\n    傾向，於民國96年11月20日執行完畢釋放，並經本署檢察官\n    以96年度毒偵緝字第433號為不起訴處分確定。另因贓物案\n    件，經臺灣高雄地方法院以96年度簡字第6892號判決處有期\n    徒刑5月確定（下稱第一案）；另因詐欺案件，經臺灣高等\n    法院高雄分院以97年度上易字第369號判決處有期徒刑4月，\n    減刑為有期徒刑2月確定（下稱第二案）；第一案與第二案\n    嗣經臺灣高等法院高雄分院以97年度聲字第1140號裁定定應\n    執行刑為有期徒刑6月確定，於98年7月7日縮刑期滿執行完\n    畢（構成累犯）。又因施用毒品案件，經臺灣高雄地方法院\n    以98年度審簡字第4103號判決處有期徒刑3月確定；又因施\n    用毒品案件，經臺灣屏東地方法院以99年度簡字第1789號判\n    決處有期徒刑3月確定；又因施用毒品案件，分別經臺灣屏\n    東地方法院以99年度簡字第1789號判處有期徒刑3月、臺灣\n    高雄地方法院以99年度簡字第1152號判決處有期徒刑4月確\n    定。」、倒數第3行至倒數第1行「因另涉竊盜案件為警查獲\n    ，並徵得其同意採集尿液送檢驗後，結果呈安非他命及甲基\n    安非他命之陽性反應，始悉上情。」補充更正為「因另涉竊\n    盜案件為警查獲，蔡建一於其犯罪尚未為警員發覺前，主動\n    向警員自首坦承施用毒品犯行，並同意警員對其採取尿液送\n    驗，而接受裁判，送驗結果則呈安非他命、甲基安非他命陽\n    性反應，而查悉上情。」外，餘均引用附件檢察官聲請簡易\n    判決處刑書之記載。\n二、核被告蔡建一所為，係犯毒品危害防制條例第10條第2 項之\n    施用第二級毒品罪。其施用第二級毒品前持有該毒品之低度\n    行為，應為其施用之高度行為所吸收，不另論罪。又被告有\n    如前所載之犯罪科刑及執行情形，此見前揭臺灣高等法院被\n    告前案紀錄表自明，其於受有期徒刑執行完畢後，5 年內故\n    意再犯本件有期徒刑以上之罪，為累犯，應依刑法第47條第\n    1 項規定，加重其刑。又被告於本件施用第二級毒品罪犯罪\n    被發覺前，向警員自首其施用第二級毒品犯行而受裁判，此\n    有其警詢筆錄之記載可按，爰依刑法第62條前段之規定減輕\n    其刑，並依法先加後減之。爰審酌被告前因施用毒品案件經\n    觀察、勒戒後，猶未思積極戒毒，竟再犯本件施用第二級毒\n    品犯行，實應非難，惟念施用毒品乃自戕行為，對社會造成\n    之危害尚非直接甚鉅，而其曾有贓物、詐欺及多次違反毒品\n    危害防制條例案件之刑事前科，此品行資料有臺灣高等法院\n    被告前案紀錄表一份可查，而其生活狀況為勉持、智識程度\n    為高職肄業及犯後坦承犯行等一切情狀，量處如主文所示之\n    刑，並參酌前開犯罪情狀，諭知如主文所示易科罰金之折算\n    標準。\n三、依刑事訴訟法第449 條第1 項前段、第3 項、第454 條第 2\n    項，毒品危害防制條例第10條第2 項，刑法第11條前段、第\n    47條第1 項、第62條前段、第41條第1 項前段，逕以簡易判\n    決處刑如主文。\n四、如不服本判決，得自判決送達之日起10日內，向本院提起上\n    訴。"
  },
  "search": "臺灣高雄地方法院刑事簡易判決100年度簡字第962號聲請人臺灣高雄地方法院檢察署檢察官被告蔡建一上列被告因違反毒品危害防制條例案件，經檢察官聲請以簡易判決處刑（100年度毒偵字第391號），本院判決如下：主文蔡建一施用第二級毒品，累犯，處有期徒刑肆月，如易科罰金，以新臺幣壹仟元折算壹日。事實及理由一、本件犯罪事實及證據，除犯罪事實欄一被告前科部分更正為「蔡建一前因施用毒品案件，經臺灣高雄地方法院以96年度毒聲字第1270號裁定送觀察、勒戒後，認無繼續施用毒品之傾向，於民國96年11月20日執行完畢釋放，並經本署檢察官以96年度毒偵緝字第433號為不起訴處分確定。另因贓物案件，經臺灣高雄地方法院以96年度簡字第6892號判決處有期徒刑5月確定（下稱第一案）；另因詐欺案件，經臺灣高等法院高雄分院以97年度上易字第369號判決處有期徒刑4月，減刑為有期徒刑2月確定（下稱第二案）；第一案與第二案嗣經臺灣高等法院高雄分院以97年度聲字第1140號裁定定應執行刑為有期徒刑6月確定，於98年7月7日縮刑期滿執行完畢（構成累犯）。又因施用毒品案件，經臺灣高雄地方法院以98年度審簡字第4103號判決處有期徒刑3月確定；又因施用毒品案件，經臺灣屏東地方法院以99年度簡字第1789號判決處有期徒刑3月確定；又因施用毒品案件，分別經臺灣屏東地方法院以99年度簡字第1789號判處有期徒刑3月、臺灣高雄地方法院以99年度簡字第1152號判決處有期徒刑4月確定。」、倒數第3行至倒數第1行「因另涉竊盜案件為警查獲，並徵得其同意採集尿液送檢驗後，結果呈安非他命及甲基安非他命之陽性反應，始悉上情。」補充更正為「因另涉竊盜案件為警查獲，蔡建一於其犯罪尚未為警員發覺前，主動向警員自首坦承施用毒品犯行，並同意警員對其採取尿液送驗，而接受裁判，送驗結果則呈安非他命、甲基安非他命陽性反應，而查悉上情。」外，餘均引用附件檢察官聲請簡易判決處刑書之記載。二、核被告蔡建一所為，係犯毒品危害防制條例第10條第2項之施用第二級毒品罪。其施用第二級毒品前持有該毒品之低度行為，應為其施用之高度行為所吸收，不另論罪。又被告有如前所載之犯罪科刑及執行情形，此見前揭臺灣高等法院被告前案紀錄表自明，其於受有期徒刑執行完畢後，5年內故意再犯本件有期徒刑以上之罪，為累犯，應依刑法第47條第1項規定，加重其刑。又被告於本件施用第二級毒品罪犯罪被發覺前，向警員自首其施用第二級毒品犯行而受裁判，此有其警詢筆錄之記載可按，爰依刑法第62條前段之規定減輕其刑，並依法先加後減之。爰審酌被告前因施用毒品案件經觀察、勒戒後，猶未思積極戒毒，竟再犯本件施用第二級毒品犯行，實應非難，惟念施用毒品乃自戕行為，對社會造成之危害尚非直接甚鉅，而其曾有贓物、詐欺及多次違反毒品危害防制條例案件之刑事前科，此品行資料有臺灣高等法院被告前案紀錄表一份可查，而其生活狀況為勉持、智識程度為高職肄業及犯後坦承犯行等一切情狀，量處如主文所示之刑，並參酌前開犯罪情狀，諭知如主文所示易科罰金之折算標準。三、依刑事訴訟法第449條第1項前段、第3項、第454條第2項，毒品危害防制條例第10條第2項，刑法第11條前段、第47條第1項、第62條前段、第41條第1項前段，逕以簡易判決處刑如主文。四、如不服本判決，得自判決送達之日起10日內，向本院提起上訴。中華民國100年3月15日高雄簡易庭法官徐彩芳以上正本證明與原本無異。如不服本判決，應於判決送達之日起10日內向本院提出上訴書狀。中華民國100年3月15日書記官張義龍附錄本判決論罪之法條：毒品危害防制條例第10條施用第一級毒品者，處6月以上5年以下有期徒刑。施用第二級毒品者，處3年以下有期徒刑。",
  "characters": {
    "judges": [
      "徐彩芳"
    ],
    "prosecutors": [

    ],
    "lawyers": [

    ],
    "clerks": [
      "張義龍"
    ],
    "plaintiffs": [

    ],
    "defendants": [
      "蔡建一"
    ],
    "prosecutor_office": [
      "臺灣高雄地方法院檢察署檢察官"
    ],
    "creditors": [

    ],
    "debtors": [

    ],
    "judicial_associate_officer": [

    ]
  },
  "adjudged_at": "2011-03-15",
  "created_at": "2016-02-13 19:34:08",
  "updated_at": "2016-02-13 19:34:08"
}