{
  "identify": "TCD-100-交易-529-20110811-1",
  "court": {
    "name": "臺灣臺中地方法院",
    "code": "TCD"
  },
  "division": {
    "name": "刑事",
    "code": "M"
  },
  "year": 100,
  "word": "交易",
  "number": "529",
  "jcheck": "1",
  "reason": "過失傷害",
  "content": "臺灣臺中地方法院刑事判決            100年度交易字第529號\n公  訴  人  臺灣臺中地方法院檢察署檢察官\n被      告  林東元\n上列被告因過失傷害案件，經檢察官提起公訴（100年度偵字第8\n183號），本院判決如下：\n    主    文\n林東元因過失傷害人，處有期徒刑肆月，如易科罰金，以新臺幣\n壹仟元折算壹日。\n    犯罪事實\n一、林東元於民國99年11月8日上午，駕駛車牌號碼3U-8709號自\n    用小客車，沿臺中縣大甲鎮（現改制為臺中市大甲區，以下\n    仍以舊制記）幼四路由南往北方向行駛，於同日上午7時15\n    分許，途經臺中縣大甲鎮○○路與工二路之無號誌交岔路口\n    時，原應注意在該路段行駛，行車時速不得超過50公里，且\n    應注意減速慢行，作隨時停車之準備，而依當時情形為日間\n    自然光線、天候晴、柏油路面、乾燥、無缺陷、無障礙物，\n    亦無不能注意之情事，竟疏未注意及此，適同一時間，由吳\n    瓊瑤騎乘車牌號碼321-BTK號重型機車，沿臺中縣大甲鎮○\n    ○路由西往東方向行駛，行至上開無號誌之交岔路口時，因\n    林東元以超越時速50公里之速度行駛，且未作隨時停車之準\n    備，而吳瓊瑤行駛於少線道，亦未注意讓多線道之林東元先\n    行，致林東元之自用小客車不慎與吳瓊瑤之機車發生碰撞，\n    導致吳瓊瑤人車倒地，並因而受有多發性骨盆閉鎖性骨折合\n    併骨盆環破裂、損傷後硬腦膜下出血、頸部扭傷及拉傷、第\n    四頸椎、第五頸椎椎間盤破裂併神經壓迫、頭皮開放性傷口\n    、臉、頭皮、頸之挫傷及肩部挫傷等傷害。林東元於肇事後\n    即停留在現場，待警方前來處理時，當場承認其為肇事人，\n    並自願接受裁判而自首其犯行。\n二、案經吳瓊瑤訴由臺中市政府警察局大甲分局報請臺灣臺中地\n    方法院檢察署檢察官偵查起訴。\n    理  由\n壹、證據能力之說明：\n    按被告以外之人於審判外之陳述，雖不符前4條之規定，而\n    經當事人於審判程序同意作為證據，法院審酌該言詞陳述或\n    書面陳述作成時之情況，認為適當者，亦得為證據。當事人\n    、代理人或辯護人於法院調查證據時，知有第159條第1項不\n    得為證據之情形，而未於言詞辯論終結前聲明異議者，視為\n    有前項之同意，刑事訴訟法第159條之5定有明文。立法意旨\n    在於傳聞證據未經當事人之反對詰問予以核實，原則上先予\n    排除，惟若當事人已放棄詰問或未聲明異議，基於證據資料\n    愈豐富，愈有助於真實發現之理念，且強化言詞辯論主義，\n    法院自可承認該傳聞證據例外有證據能力。經查，本案檢察\n    官及被告，均未爭執本判決所引用之各項證據，復未於言詞\n    辯論終結前聲明異議，本院審酌各該證據作成時之情形，亦\n    無違法或不當取證之瑕疵，且均與本案之待證事實有關，認\n    以之作為本案之證據亦無不適當之情形，應認下列各項證據\n    均有證據能力。\n貳、實體之說明：\n一、上揭犯罪事實，業據被告林東元於偵查中及本院審理時均坦\n    承不諱，核與告訴人吳瓊瑤於警詢時指訴之情節大致相符，\n    復有道路交通事故現場圖、道路交通事故調查報告表（一）\n    、（二）、光田綜合醫院診斷證明書2張、童綜合醫院一般\n    診斷書1張及現場照片8張附卷可稽。按行車速度，依速限標\n    誌或標線之規定，無速限標誌或標線者，行車時速不得超過\n    50公里；又汽車行經無號誌之交岔路口，應減速慢行，作隨\n    時停車之準備；道路交通安全規則第93條第1項第1款前段、\n    第2款分別定有明文，被告駕車自應注意遵守上開道路交通\n    安全之規定。而依案發當時為天候晴、日間自然光線、柏油\n    路面無缺陷、無障礙物，此有前開道路交通事故調查報告表\n    （一）可參，故客觀上並無不能注意之情事，被告竟疏未注\n    意及此，以致肇事致告訴人受傷，其行為顯有過失甚明。雖\n    本件告訴人行駛於少線道，未讓多線道之被告先行，告訴人\n    亦與有過失（告訴代理人誤認被告行駛車道之白實線係設於\n    路側，並以路邊停有車輛為證，而認告訴人與被告行駛之車\n    道數相同，認告訴人並無少線道車未讓多線道車先行之過失\n    ，惟依現場圖及照片所示，被告行駛車道之白實線係設於路\n    段中而非路側，應係用以分隔快慢車道，至於路邊有車輛違\n    停，仍不得以此即認路邊係供停車之用，故被告行駛之車道\n    仍屬多線道，告訴代理人此部分所認顯有誤會；另被告雖認\n    告訴人未行駛於工二路之機車道亦有過失，惟依現場圖及照\n    片所示，告訴人行駛之工二路僅有一線道，並未有快慢車道\n    之分，被告此部分所認亦有誤會，均附此敘明），然仍不能\n    因告訴人之與有過失，而解免被告之罪責。且被告之過失行\n    為，與告訴人之傷害結果間，亦具有相當因果關係。故被告\n    之自白核與事實相符，本案事證明確，被告犯行堪以認定。\n二、核被告所為，係犯刑法第284條第1項前段之過失傷害罪。查\n    被告於肇事後即停留於現場，待警方前來處理時，當場承認\n    其為肇事人並自願接受裁判，此有臺中縣警察局道路交通事\n    故肇事人自首情形紀錄表附卷可稽，核與自首之要件相符，\n    爰依刑法第62條前段之規定，減輕其刑。爰審酌被告於本件\n    車禍之過失程度、被告雖於偵審中坦認犯行，惟迄未能與告\n    訴人達成民事和解，及告訴人所受傷勢非輕等一切情狀，量\n    處如主文所示之刑，並諭知易科罰金之折算標準。\n據上論斷，應依刑事訴訟法第299條第1項前段，刑法第284條第1\n項前段、第62條前段、第41條第1項前段，刑法施行法第1條之1\n第1項、第2項前段，判決如主文。\n本案經檢察官林秀菊到庭執行職務。\n中    華    民    國    100    年    8    月    11    日\n                  刑事第十二庭  法  官  郭瑞祥\n以上正本證明與原本無異。\n如不服本判決應於收受判決後10日內向本院提出上訴書狀，並應\n敘述具體理由；其未敘述上訴理由者，應於上訴期間屆滿後20日\n內向本院補提理由書（均須按他造當事人之人數附繕本）「切勿\n逕送上級法院」。\n                                書記官  黃雅青\n中    華    民    國    100    年    8    月    11    日\n附錄論罪科刑法條\n刑法第284條第1項\n因過失傷害人者，處 6 月以下有期徒刑、拘役或 5 百元以下罰\n金，致重傷者，處1年以下有期徒刑、拘役或5百元以下罰金。",
  "structure": {
    "main": "林東元因過失傷害人，處有期徒刑肆月，如易科罰金，以新臺幣\n壹仟元折算壹日。",
    "fact": "一、林東元於民國99年11月8日上午，駕駛車牌號碼3U-8709號自\n    用小客車，沿臺中縣大甲鎮（現改制為臺中市大甲區，以下\n    仍以舊制記）幼四路由南往北方向行駛，於同日上午7時15\n    分許，途經臺中縣大甲鎮○○路與工二路之無號誌交岔路口\n    時，原應注意在該路段行駛，行車時速不得超過50公里，且\n    應注意減速慢行，作隨時停車之準備，而依當時情形為日間\n    自然光線、天候晴、柏油路面、乾燥、無缺陷、無障礙物，\n    亦無不能注意之情事，竟疏未注意及此，適同一時間，由吳\n    瓊瑤騎乘車牌號碼321-BTK號重型機車，沿臺中縣大甲鎮○\n    ○路由西往東方向行駛，行至上開無號誌之交岔路口時，因\n    林東元以超越時速50公里之速度行駛，且未作隨時停車之準\n    備，而吳瓊瑤行駛於少線道，亦未注意讓多線道之林東元先\n    行，致林東元之自用小客車不慎與吳瓊瑤之機車發生碰撞，\n    導致吳瓊瑤人車倒地，並因而受有多發性骨盆閉鎖性骨折合\n    併骨盆環破裂、損傷後硬腦膜下出血、頸部扭傷及拉傷、第\n    四頸椎、第五頸椎椎間盤破裂併神經壓迫、頭皮開放性傷口\n    、臉、頭皮、頸之挫傷及肩部挫傷等傷害。林東元於肇事後\n    即停留在現場，待警方前來處理時，當場承認其為肇事人，\n    並自願接受裁判而自首其犯行。\n二、案經吳瓊瑤訴由臺中市政府警察局大甲分局報請臺灣臺中地\n    方法院檢察署檢察官偵查起訴。\n    理  由\n壹、證據能力之說明：\n    按被告以外之人於審判外之陳述，雖不符前4條之規定，而\n    經當事人於審判程序同意作為證據，法院審酌該言詞陳述或\n    書面陳述作成時之情況，認為適當者，亦得為證據。當事人\n    、代理人或辯護人於法院調查證據時，知有第159條第1項不\n    得為證據之情形，而未於言詞辯論終結前聲明異議者，視為\n    有前項之同意，刑事訴訟法第159條之5定有明文。立法意旨\n    在於傳聞證據未經當事人之反對詰問予以核實，原則上先予\n    排除，惟若當事人已放棄詰問或未聲明異議，基於證據資料\n    愈豐富，愈有助於真實發現之理念，且強化言詞辯論主義，\n    法院自可承認該傳聞證據例外有證據能力。經查，本案檢察\n    官及被告，均未爭執本判決所引用之各項證據，復未於言詞\n    辯論終結前聲明異議，本院審酌各該證據作成時之情形，亦\n    無違法或不當取證之瑕疵，且均與本案之待證事實有關，認\n    以之作為本案之證據亦無不適當之情形，應認下列各項證據\n    均有證據能力。\n貳、實體之說明：\n一、上揭犯罪事實，業據被告林東元於偵查中及本院審理時均坦\n    承不諱，核與告訴人吳瓊瑤於警詢時指訴之情節大致相符，\n    復有道路交通事故現場圖、道路交通事故調查報告表（一）\n    、（二）、光田綜合醫院診斷證明書2張、童綜合醫院一般\n    診斷書1張及現場照片8張附卷可稽。按行車速度，依速限標\n    誌或標線之規定，無速限標誌或標線者，行車時速不得超過\n    50公里；又汽車行經無號誌之交岔路口，應減速慢行，作隨\n    時停車之準備；道路交通安全規則第93條第1項第1款前段、\n    第2款分別定有明文，被告駕車自應注意遵守上開道路交通\n    安全之規定。而依案發當時為天候晴、日間自然光線、柏油\n    路面無缺陷、無障礙物，此有前開道路交通事故調查報告表\n    （一）可參，故客觀上並無不能注意之情事，被告竟疏未注\n    意及此，以致肇事致告訴人受傷，其行為顯有過失甚明。雖\n    本件告訴人行駛於少線道，未讓多線道之被告先行，告訴人\n    亦與有過失（告訴代理人誤認被告行駛車道之白實線係設於\n    路側，並以路邊停有車輛為證，而認告訴人與被告行駛之車\n    道數相同，認告訴人並無少線道車未讓多線道車先行之過失\n    ，惟依現場圖及照片所示，被告行駛車道之白實線係設於路\n    段中而非路側，應係用以分隔快慢車道，至於路邊有車輛違\n    停，仍不得以此即認路邊係供停車之用，故被告行駛之車道\n    仍屬多線道，告訴代理人此部分所認顯有誤會；另被告雖認\n    告訴人未行駛於工二路之機車道亦有過失，惟依現場圖及照\n    片所示，告訴人行駛之工二路僅有一線道，並未有快慢車道\n    之分，被告此部分所認亦有誤會，均附此敘明），然仍不能\n    因告訴人之與有過失，而解免被告之罪責。且被告之過失行\n    為，與告訴人之傷害結果間，亦具有相當因果關係。故被告\n    之自白核與事實相符，本案事證明確，被告犯行堪以認定。\n二、核被告所為，係犯刑法第284條第1項前段之過失傷害罪。查\n    被告於肇事後即停留於現場，待警方前來處理時，當場承認\n    其為肇事人並自願接受裁判，此有臺中縣警察局道路交通事\n    故肇事人自首情形紀錄表附卷可稽，核與自首之要件相符，\n    爰依刑法第62條前段之規定，減輕其刑。爰審酌被告於本件\n    車禍之過失程度、被告雖於偵審中坦認犯行，惟迄未能與告\n    訴人達成民事和解，及告訴人所受傷勢非輕等一切情狀，量\n    處如主文所示之刑，並諭知易科罰金之折算標準。\n據上論斷，應依刑事訴訟法第299條第1項前段，刑法第284條第1\n項前段、第62條前段、第41條第1項前段，刑法施行法第1條之1\n第1項、第2項前段，判決如主文。\n本案經檢察官林秀菊到庭執行職務。"
  },
  "search": "臺灣臺中地方法院刑事判決100年度交易字第529號公訴人臺灣臺中地方法院檢察署檢察官被告林東元上列被告因過失傷害案件，經檢察官提起公訴（100年度偵字第8183號），本院判決如下：主文林東元因過失傷害人，處有期徒刑肆月，如易科罰金，以新臺幣壹仟元折算壹日。犯罪事實一、林東元於民國99年11月8日上午，駕駛車牌號碼3U-8709號自用小客車，沿臺中縣大甲鎮（現改制為臺中市大甲區，以下仍以舊制記）幼四路由南往北方向行駛，於同日上午7時15分許，途經臺中縣大甲鎮○○路與工二路之無號誌交岔路口時，原應注意在該路段行駛，行車時速不得超過50公里，且應注意減速慢行，作隨時停車之準備，而依當時情形為日間自然光線、天候晴、柏油路面、乾燥、無缺陷、無障礙物，亦無不能注意之情事，竟疏未注意及此，適同一時間，由吳瓊瑤騎乘車牌號碼321-BTK號重型機車，沿臺中縣大甲鎮○○路由西往東方向行駛，行至上開無號誌之交岔路口時，因林東元以超越時速50公里之速度行駛，且未作隨時停車之準備，而吳瓊瑤行駛於少線道，亦未注意讓多線道之林東元先行，致林東元之自用小客車不慎與吳瓊瑤之機車發生碰撞，導致吳瓊瑤人車倒地，並因而受有多發性骨盆閉鎖性骨折合併骨盆環破裂、損傷後硬腦膜下出血、頸部扭傷及拉傷、第四頸椎、第五頸椎椎間盤破裂併神經壓迫、頭皮開放性傷口、臉、頭皮、頸之挫傷及肩部挫傷等傷害。林東元於肇事後即停留在現場，待警方前來處理時，當場承認其為肇事人，並自願接受裁判而自首其犯行。二、案經吳瓊瑤訴由臺中市政府警察局大甲分局報請臺灣臺中地方法院檢察署檢察官偵查起訴。理由壹、證據能力之說明：按被告以外之人於審判外之陳述，雖不符前4條之規定，而經當事人於審判程序同意作為證據，法院審酌該言詞陳述或書面陳述作成時之情況，認為適當者，亦得為證據。當事人、代理人或辯護人於法院調查證據時，知有第159條第1項不得為證據之情形，而未於言詞辯論終結前聲明異議者，視為有前項之同意，刑事訴訟法第159條之5定有明文。立法意旨在於傳聞證據未經當事人之反對詰問予以核實，原則上先予排除，惟若當事人已放棄詰問或未聲明異議，基於證據資料愈豐富，愈有助於真實發現之理念，且強化言詞辯論主義，法院自可承認該傳聞證據例外有證據能力。經查，本案檢察官及被告，均未爭執本判決所引用之各項證據，復未於言詞辯論終結前聲明異議，本院審酌各該證據作成時之情形，亦無違法或不當取證之瑕疵，且均與本案之待證事實有關，認以之作為本案之證據亦無不適當之情形，應認下列各項證據均有證據能力。貳、實體之說明：一、上揭犯罪事實，業據被告林東元於偵查中及本院審理時均坦承不諱，核與告訴人吳瓊瑤於警詢時指訴之情節大致相符，復有道路交通事故現場圖、道路交通事故調查報告表（一）、（二）、光田綜合醫院診斷證明書2張、童綜合醫院一般診斷書1張及現場照片8張附卷可稽。按行車速度，依速限標誌或標線之規定，無速限標誌或標線者，行車時速不得超過50公里；又汽車行經無號誌之交岔路口，應減速慢行，作隨時停車之準備；道路交通安全規則第93條第1項第1款前段、第2款分別定有明文，被告駕車自應注意遵守上開道路交通安全之規定。而依案發當時為天候晴、日間自然光線、柏油路面無缺陷、無障礙物，此有前開道路交通事故調查報告表（一）可參，故客觀上並無不能注意之情事，被告竟疏未注意及此，以致肇事致告訴人受傷，其行為顯有過失甚明。雖本件告訴人行駛於少線道，未讓多線道之被告先行，告訴人亦與有過失（告訴代理人誤認被告行駛車道之白實線係設於路側，並以路邊停有車輛為證，而認告訴人與被告行駛之車道數相同，認告訴人並無少線道車未讓多線道車先行之過失，惟依現場圖及照片所示，被告行駛車道之白實線係設於路段中而非路側，應係用以分隔快慢車道，至於路邊有車輛違停，仍不得以此即認路邊係供停車之用，故被告行駛之車道仍屬多線道，告訴代理人此部分所認顯有誤會；另被告雖認告訴人未行駛於工二路之機車道亦有過失，惟依現場圖及照片所示，告訴人行駛之工二路僅有一線道，並未有快慢車道之分，被告此部分所認亦有誤會，均附此敘明），然仍不能因告訴人之與有過失，而解免被告之罪責。且被告之過失行為，與告訴人之傷害結果間，亦具有相當因果關係。故被告之自白核與事實相符，本案事證明確，被告犯行堪以認定。二、核被告所為，係犯刑法第284條第1項前段之過失傷害罪。查被告於肇事後即停留於現場，待警方前來處理時，當場承認其為肇事人並自願接受裁判，此有臺中縣警察局道路交通事故肇事人自首情形紀錄表附卷可稽，核與自首之要件相符，爰依刑法第62條前段之規定，減輕其刑。爰審酌被告於本件車禍之過失程度、被告雖於偵審中坦認犯行，惟迄未能與告訴人達成民事和解，及告訴人所受傷勢非輕等一切情狀，量處如主文所示之刑，並諭知易科罰金之折算標準。據上論斷，應依刑事訴訟法第299條第1項前段，刑法第284條第1項前段、第62條前段、第41條第1項前段，刑法施行法第1條之1第1項、第2項前段，判決如主文。本案經檢察官林秀菊到庭執行職務。中華民國100年8月11日刑事第十二庭法官郭瑞祥以上正本證明與原本無異。如不服本判決應於收受判決後10日內向本院提出上訴書狀，並應敘述具體理由；其未敘述上訴理由者，應於上訴期間屆滿後20日內向本院補提理由書（均須按他造當事人之人數附繕本）「切勿逕送上級法院」。書記官黃雅青中華民國100年8月11日附錄論罪科刑法條刑法第284條第1項因過失傷害人者，處6月以下有期徒刑、拘役或5百元以下罰金，致重傷者，處1年以下有期徒刑、拘役或5百元以下罰金。",
  "characters": {
    "judges": [
      "郭瑞祥"
    ],
    "prosecutors": [
      "林秀菊"
    ],
    "lawyers": [

    ],
    "clerks": [
      "黃雅青"
    ],
    "plaintiffs": [

    ],
    "defendants": [
      "林東元"
    ],
    "prosecutor_office": [
      "臺灣臺中地方法院檢察署檢察官"
    ],
    "creditors": [

    ],
    "debtors": [

    ],
    "judicial_associate_officer": [

    ]
  },
  "adjudged_at": "2011-08-11",
  "created_at": "2016-02-12 17:57:21",
  "updated_at": "2016-02-12 17:57:21"
}