{
  "identify": "TPD-92-訴-803-20040820-1",
  "court": {
    "name": "臺灣臺北地方法院",
    "code": "TPD"
  },
  "division": {
    "name": "刑事",
    "code": "M"
  },
  "year": 92,
  "word": "訴",
  "number": "803",
  "jcheck": "1",
  "reason": "偽造文書",
  "content": "臺灣臺北地方法院刑事裁定                          九十二年度訴字第八０三號\n    公  訴  人  臺灣臺北地方法院檢察署檢察官\n    被      告  甲○○\n                        （現另案在臺灣臺北監獄執行中）\n右列被告因偽造文書案件，經檢察官聲請以簡易判決處刑（九十二年度偵字第三七八\n○號），本院認為不宜，改依通常程序審理，裁定如左：\n    主      文\n本院九十二年度訴字第八○三號有關由受命法官獨任進行簡式審判程序之裁定應予撤\n銷。\n    理      由\n一、本件被告甲○○所涉偽造文書案件，前因被告就被訴事實為有罪之陳述，經本院\n    合議庭於民國九十三年七月二十七日評議後裁定由受命法官獨任進行簡式審判程\n    序，並於同年八月五日審理期日當庭告知被告適用簡式審判程序之旨。惟嗣據被\n    告陳稱其所涉同一犯罪事實業經本院判決確定在案等語，本件顯有不得進行簡式\n    審判程序之情形，自應將本院前開有關由受命法官獨任進行簡式審判程序之裁定\n    予以撤銷。\n二、依刑事訴訟法第二百七十三條之一第二項，裁定如主文。\n中      華      民      國    九十三    年      八      月     二十     日\n                                      臺灣臺北地方法院刑事第十一庭\n                                          審判長法  官  劉方慈\n                                                法  官  朱夢蘋\n                                                法  官  林庚棟\n右正本證明與原本無異。\n不得抗告。\n                                                書記官  殷玉芬\n中      華      民      國    九十三    年      八      月    二十三    日\n",
  "structure": {
    "main": "本院九十二年度訴字第八○三號有關由受命法官獨任進行簡式審判程序之裁定應予撤\n銷。",
    "reason": "一、本件被告甲○○所涉偽造文書案件，前因被告就被訴事實為有罪之陳述，經本院\n    合議庭於民國九十三年七月二十七日評議後裁定由受命法官獨任進行簡式審判程\n    序，並於同年八月五日審理期日當庭告知被告適用簡式審判程序之旨。惟嗣據被\n    告陳稱其所涉同一犯罪事實業經本院判決確定在案等語，本件顯有不得進行簡式\n    審判程序之情形，自應將本院前開有關由受命法官獨任進行簡式審判程序之裁定\n    予以撤銷。\n二、依刑事訴訟法第二百七十三條之一第二項，裁定如主文。"
  },
  "search": "臺灣臺北地方法院刑事裁定九十二年度訴字第八０三號公訴人臺灣臺北地方法院檢察署檢察官被告甲○○（現另案在臺灣臺北監獄執行中）右列被告因偽造文書案件，經檢察官聲請以簡易判決處刑（九十二年度偵字第三七八○號），本院認為不宜，改依通常程序審理，裁定如左：主文本院九十二年度訴字第八○三號有關由受命法官獨任進行簡式審判程序之裁定應予撤銷。理由一、本件被告甲○○所涉偽造文書案件，前因被告就被訴事實為有罪之陳述，經本院合議庭於民國九十三年七月二十七日評議後裁定由受命法官獨任進行簡式審判程序，並於同年八月五日審理期日當庭告知被告適用簡式審判程序之旨。惟嗣據被告陳稱其所涉同一犯罪事實業經本院判決確定在案等語，本件顯有不得進行簡式審判程序之情形，自應將本院前開有關由受命法官獨任進行簡式審判程序之裁定予以撤銷。二、依刑事訴訟法第二百七十三條之一第二項，裁定如主文。中華民國九十三年八月二十日臺灣臺北地方法院刑事第十一庭審判長法官劉方慈法官朱夢蘋法官林庚棟右正本證明與原本無異。不得抗告。書記官殷玉芬中華民國九十三年八月二十三日",
  "characters": {
    "judges": [
      "劉方慈",
      "朱夢蘋",
      "林庚棟"
    ],
    "prosecutors": [

    ],
    "lawyers": [

    ],
    "clerks": [
      "殷玉芬"
    ],
    "plaintiffs": [

    ],
    "defendants": [
      "甲○○"
    ],
    "prosecutor_office": [
      "臺灣臺北地方法院檢察署檢察官"
    ],
    "creditors": [

    ],
    "debtors": [

    ],
    "judicial_associate_officer": [

    ]
  },
  "adjudged_at": "2004-08-20",
  "created_at": "2016-02-06 02:35:06",
  "updated_at": "2016-02-06 02:35:06"
}