{
  "identify": "PCD-100-簡-4010-20110622-1",
  "court": {
    "name": "臺灣新北地方法院",
    "code": "PCD"
  },
  "division": {
    "name": "刑事",
    "code": "M"
  },
  "year": 100,
  "word": "簡",
  "number": "4010",
  "jcheck": "1",
  "reason": "毒品危害防制條例",
  "content": "臺灣板橋地方法院刑事簡易判決         100年度簡字第4010號\n公  訴  人  臺灣板橋地方法院檢察署檢察官\n被      告  黃怡穎\n上列被告因違反毒品危害防制條例案件，經檢察官提起公訴（10\n0 年度毒偵字第2106號），而被告自白犯罪，本院爰改以簡易判\n決處刑如下：\n    主  文\n黃怡穎施用第二級毒品，累犯，處有期徒刑伍月，如易科罰金，\n以新臺幣壹仟元折算壹日。扣案之甲基安非他命壹包（驗餘淨重\n零點零玖伍陸公克）併同難以析離之包裝袋壹只沒收銷燬之。\n    事實及理由\n一、本件犯罪事實、證據及應適用之法條，除犯罪事實欄第4 行\n    「95年度毒偵字第1991號」更正為「95年度毒偵緝字第376\n    號」，及自第7 行「又於96年間」起至第14行「以已執行完\n    畢論」止，關於被告前案紀錄及執行之記載均刪除，又第15\n    行、第18行「安非他命」均更正為「甲基安非他命」；證據\n    部份補充：「被告於本院準備程序時之自白」外，餘均引用\n    檢察官起訴書之記載（如附件）。\n二、查甲基安非他命係毒品危害防制條例第2 條第2 項所稱之第\n    二級毒品，核被告所為，係犯毒品危害防制條例第10條第2\n    項之施用第二級毒品罪；被告為施用而持有甲基安非他命之\n    低度行為，為施用之高度行為所吸收，不另論罪；又被告前\n    因施用毒品案件，經裁定送觀察、勒戒，於95年7 月18日執\n    行觀察、勒戒完畢釋放，並由臺灣板橋地方法院檢察署檢察\n    官以95年度毒偵緝字第376 號為不起訴處分乙節，有臺灣高\n    等法院被告前案紀錄表1 份在卷可考，是以被告在前次觀察\n    、勒戒執行完畢釋放後5 年內犯施用第二級毒品罪，自應由\n    檢察官依法訴追。再者，被告因施用毒品案件經本院以96年\n    度簡字第4066號判決判處有期徒刑4 月，經減刑為有期徒刑\n    2 月後，於96年12月11日易科罰金執行完畢之事實，有臺灣\n    高等法院被告前案紀錄表1 份在卷可考，其受有期徒刑之執\n    行完畢，5 年內故意再犯本案有期徒刑以上之罪，為累犯，\n    應依刑法第47條第1 項加重其刑。\n三、爰審酌被告前已因施用毒品獲得不起訴處分之寬典，又經法\n    院論罪科刑，竟仍不知戒除，顯然漠視法令之禁制，惟犯罪\n    後坦承犯行，且所犯之施用毒品犯行乃戕害自己身心健康，\n    並未危及他人，暨其犯罪動機、目的等一切情狀，量處如主\n    文所示之刑，併諭知易科罰金之折算標準，以資懲儆。扣案\n    之白色透明結晶1 包（淨重0.096 公克，驗餘淨重0.0956公\n    克），經送驗結果，確為甲基安非他命之事實，此有交通部\n    民用航空局航空醫務中心100 年3 月21日航藥鑑字第100149\n    7 號毒品鑑定書1 份在卷可稽（見偵查卷第61頁），且係本\n    件被告施用所剩餘，業據被告於本院審理時供承在卷，爰依\n    毒品危害防制條例第18條第1 項，併同難以析離之包裝袋1\n    只宣告沒收銷燬之。至警方同日扣得之電子磅秤1 台、吸食\n    器2 組等物，並非被告所有，業據被告供述明確，亦非違禁\n    物，爰不併為沒收之宣告，附此敘明。\n四、依刑事訴訟法第449 條第2 項、第3 項、第454 條第2 項，\n    毒品危害防制條例第10條第2 項、第18條第1 項前段，刑法\n    第11條、第41條第1 項前段、第47條第1 項，逕以簡易判決\n    處如主文所示之刑。\n中    華    民    國   100    年    6     月    22    日\n                  刑事第三庭法  官  陳伯厚\n上列正本證明與原本無異。\n如不服本判決，應於送達後10日內敘明上訴理由，向本院提出上\n訴狀，上訴於本院第二審合議庭 (應附繕本) 。其未敘述上訴理\n由者，應於上訴期間屆滿後20日內向本院補提理由書「切勿逕送\n上級法院」。\n                            書記官  高建華\n中    華    民    國   100    年    6     月    23    日",
  "structure": {
    "main": "黃怡穎施用第二級毒品，累犯，處有期徒刑伍月，如易科罰金，\n以新臺幣壹仟元折算壹日。扣案之甲基安非他命壹包（驗餘淨重\n零點零玖伍陸公克）併同難以析離之包裝袋壹只沒收銷燬之。",
    "fact": "一、本件犯罪事實、證據及應適用之法條，除犯罪事實欄第4 行\n    「95年度毒偵字第1991號」更正為「95年度毒偵緝字第376\n    號」，及自第7 行「又於96年間」起至第14行「以已執行完\n    畢論」止，關於被告前案紀錄及執行之記載均刪除，又第15\n    行、第18行「安非他命」均更正為「甲基安非他命」；證據\n    部份補充：「被告於本院準備程序時之自白」外，餘均引用\n    檢察官起訴書之記載（如附件）。\n二、查甲基安非他命係毒品危害防制條例第2 條第2 項所稱之第\n    二級毒品，核被告所為，係犯毒品危害防制條例第10條第2\n    項之施用第二級毒品罪；被告為施用而持有甲基安非他命之\n    低度行為，為施用之高度行為所吸收，不另論罪；又被告前\n    因施用毒品案件，經裁定送觀察、勒戒，於95年7 月18日執\n    行觀察、勒戒完畢釋放，並由臺灣板橋地方法院檢察署檢察\n    官以95年度毒偵緝字第376 號為不起訴處分乙節，有臺灣高\n    等法院被告前案紀錄表1 份在卷可考，是以被告在前次觀察\n    、勒戒執行完畢釋放後5 年內犯施用第二級毒品罪，自應由\n    檢察官依法訴追。再者，被告因施用毒品案件經本院以96年\n    度簡字第4066號判決判處有期徒刑4 月，經減刑為有期徒刑\n    2 月後，於96年12月11日易科罰金執行完畢之事實，有臺灣\n    高等法院被告前案紀錄表1 份在卷可考，其受有期徒刑之執\n    行完畢，5 年內故意再犯本案有期徒刑以上之罪，為累犯，\n    應依刑法第47條第1 項加重其刑。\n三、爰審酌被告前已因施用毒品獲得不起訴處分之寬典，又經法\n    院論罪科刑，竟仍不知戒除，顯然漠視法令之禁制，惟犯罪\n    後坦承犯行，且所犯之施用毒品犯行乃戕害自己身心健康，\n    並未危及他人，暨其犯罪動機、目的等一切情狀，量處如主\n    文所示之刑，併諭知易科罰金之折算標準，以資懲儆。扣案\n    之白色透明結晶1 包（淨重0.096 公克，驗餘淨重0.0956公\n    克），經送驗結果，確為甲基安非他命之事實，此有交通部\n    民用航空局航空醫務中心100 年3 月21日航藥鑑字第100149\n    7 號毒品鑑定書1 份在卷可稽（見偵查卷第61頁），且係本\n    件被告施用所剩餘，業據被告於本院審理時供承在卷，爰依\n    毒品危害防制條例第18條第1 項，併同難以析離之包裝袋1\n    只宣告沒收銷燬之。至警方同日扣得之電子磅秤1 台、吸食\n    器2 組等物，並非被告所有，業據被告供述明確，亦非違禁\n    物，爰不併為沒收之宣告，附此敘明。\n四、依刑事訴訟法第449 條第2 項、第3 項、第454 條第2 項，\n    毒品危害防制條例第10條第2 項、第18條第1 項前段，刑法\n    第11條、第41條第1 項前段、第47條第1 項，逕以簡易判決\n    處如主文所示之刑。",
    "reason": "一、本件犯罪事實、證據及應適用之法條，除犯罪事實欄第4 行\n    「95年度毒偵字第1991號」更正為「95年度毒偵緝字第376\n    號」，及自第7 行「又於96年間」起至第14行「以已執行完\n    畢論」止，關於被告前案紀錄及執行之記載均刪除，又第15\n    行、第18行「安非他命」均更正為「甲基安非他命」；證據\n    部份補充：「被告於本院準備程序時之自白」外，餘均引用\n    檢察官起訴書之記載（如附件）。\n二、查甲基安非他命係毒品危害防制條例第2 條第2 項所稱之第\n    二級毒品，核被告所為，係犯毒品危害防制條例第10條第2\n    項之施用第二級毒品罪；被告為施用而持有甲基安非他命之\n    低度行為，為施用之高度行為所吸收，不另論罪；又被告前\n    因施用毒品案件，經裁定送觀察、勒戒，於95年7 月18日執\n    行觀察、勒戒完畢釋放，並由臺灣板橋地方法院檢察署檢察\n    官以95年度毒偵緝字第376 號為不起訴處分乙節，有臺灣高\n    等法院被告前案紀錄表1 份在卷可考，是以被告在前次觀察\n    、勒戒執行完畢釋放後5 年內犯施用第二級毒品罪，自應由\n    檢察官依法訴追。再者，被告因施用毒品案件經本院以96年\n    度簡字第4066號判決判處有期徒刑4 月，經減刑為有期徒刑\n    2 月後，於96年12月11日易科罰金執行完畢之事實，有臺灣\n    高等法院被告前案紀錄表1 份在卷可考，其受有期徒刑之執\n    行完畢，5 年內故意再犯本案有期徒刑以上之罪，為累犯，\n    應依刑法第47條第1 項加重其刑。\n三、爰審酌被告前已因施用毒品獲得不起訴處分之寬典，又經法\n    院論罪科刑，竟仍不知戒除，顯然漠視法令之禁制，惟犯罪\n    後坦承犯行，且所犯之施用毒品犯行乃戕害自己身心健康，\n    並未危及他人，暨其犯罪動機、目的等一切情狀，量處如主\n    文所示之刑，併諭知易科罰金之折算標準，以資懲儆。扣案\n    之白色透明結晶1 包（淨重0.096 公克，驗餘淨重0.0956公\n    克），經送驗結果，確為甲基安非他命之事實，此有交通部\n    民用航空局航空醫務中心100 年3 月21日航藥鑑字第100149\n    7 號毒品鑑定書1 份在卷可稽（見偵查卷第61頁），且係本\n    件被告施用所剩餘，業據被告於本院審理時供承在卷，爰依\n    毒品危害防制條例第18條第1 項，併同難以析離之包裝袋1\n    只宣告沒收銷燬之。至警方同日扣得之電子磅秤1 台、吸食\n    器2 組等物，並非被告所有，業據被告供述明確，亦非違禁\n    物，爰不併為沒收之宣告，附此敘明。\n四、依刑事訴訟法第449 條第2 項、第3 項、第454 條第2 項，\n    毒品危害防制條例第10條第2 項、第18條第1 項前段，刑法\n    第11條、第41條第1 項前段、第47條第1 項，逕以簡易判決\n    處如主文所示之刑。"
  },
  "search": "臺灣板橋地方法院刑事簡易判決100年度簡字第4010號公訴人臺灣板橋地方法院檢察署檢察官被告黃怡穎上列被告因違反毒品危害防制條例案件，經檢察官提起公訴（100年度毒偵字第2106號），而被告自白犯罪，本院爰改以簡易判決處刑如下：主文黃怡穎施用第二級毒品，累犯，處有期徒刑伍月，如易科罰金，以新臺幣壹仟元折算壹日。扣案之甲基安非他命壹包（驗餘淨重零點零玖伍陸公克）併同難以析離之包裝袋壹只沒收銷燬之。事實及理由一、本件犯罪事實、證據及應適用之法條，除犯罪事實欄第4行「95年度毒偵字第1991號」更正為「95年度毒偵緝字第376號」，及自第7行「又於96年間」起至第14行「以已執行完畢論」止，關於被告前案紀錄及執行之記載均刪除，又第15行、第18行「安非他命」均更正為「甲基安非他命」；證據部份補充：「被告於本院準備程序時之自白」外，餘均引用檢察官起訴書之記載（如附件）。二、查甲基安非他命係毒品危害防制條例第2條第2項所稱之第二級毒品，核被告所為，係犯毒品危害防制條例第10條第2項之施用第二級毒品罪；被告為施用而持有甲基安非他命之低度行為，為施用之高度行為所吸收，不另論罪；又被告前因施用毒品案件，經裁定送觀察、勒戒，於95年7月18日執行觀察、勒戒完畢釋放，並由臺灣板橋地方法院檢察署檢察官以95年度毒偵緝字第376號為不起訴處分乙節，有臺灣高等法院被告前案紀錄表1份在卷可考，是以被告在前次觀察、勒戒執行完畢釋放後5年內犯施用第二級毒品罪，自應由檢察官依法訴追。再者，被告因施用毒品案件經本院以96年度簡字第4066號判決判處有期徒刑4月，經減刑為有期徒刑2月後，於96年12月11日易科罰金執行完畢之事實，有臺灣高等法院被告前案紀錄表1份在卷可考，其受有期徒刑之執行完畢，5年內故意再犯本案有期徒刑以上之罪，為累犯，應依刑法第47條第1項加重其刑。三、爰審酌被告前已因施用毒品獲得不起訴處分之寬典，又經法院論罪科刑，竟仍不知戒除，顯然漠視法令之禁制，惟犯罪後坦承犯行，且所犯之施用毒品犯行乃戕害自己身心健康，並未危及他人，暨其犯罪動機、目的等一切情狀，量處如主文所示之刑，併諭知易科罰金之折算標準，以資懲儆。扣案之白色透明結晶1包（淨重0.096公克，驗餘淨重0.0956公克），經送驗結果，確為甲基安非他命之事實，此有交通部民用航空局航空醫務中心100年3月21日航藥鑑字第1001497號毒品鑑定書1份在卷可稽（見偵查卷第61頁），且係本件被告施用所剩餘，業據被告於本院審理時供承在卷，爰依毒品危害防制條例第18條第1項，併同難以析離之包裝袋1只宣告沒收銷燬之。至警方同日扣得之電子磅秤1台、吸食器2組等物，並非被告所有，業據被告供述明確，亦非違禁物，爰不併為沒收之宣告，附此敘明。四、依刑事訴訟法第449條第2項、第3項、第454條第2項，毒品危害防制條例第10條第2項、第18條第1項前段，刑法第11條、第41條第1項前段、第47條第1項，逕以簡易判決處如主文所示之刑。中華民國100年6月22日刑事第三庭法官陳伯厚上列正本證明與原本無異。如不服本判決，應於送達後10日內敘明上訴理由，向本院提出上訴狀，上訴於本院第二審合議庭(應附繕本)。其未敘述上訴理由者，應於上訴期間屆滿後20日內向本院補提理由書「切勿逕送上級法院」。書記官高建華中華民國100年6月23日",
  "characters": {
    "judges": [
      "陳伯厚"
    ],
    "prosecutors": [

    ],
    "lawyers": [

    ],
    "clerks": [
      "高建華"
    ],
    "plaintiffs": [

    ],
    "defendants": [
      "黃怡穎"
    ],
    "prosecutor_office": [
      "臺灣板橋地方法院檢察署檢察官"
    ],
    "creditors": [

    ],
    "debtors": [

    ],
    "judicial_associate_officer": [

    ]
  },
  "adjudged_at": "2011-06-22",
  "created_at": "2016-02-13 18:04:30",
  "updated_at": "2016-02-13 18:04:30"
}