{
  "identify": "PTD-100-訴-627-20110623-1",
  "court": {
    "name": "臺灣屏東地方法院",
    "code": "PTD"
  },
  "division": {
    "name": "刑事",
    "code": "M"
  },
  "year": 100,
  "word": "訴",
  "number": "627",
  "jcheck": "1",
  "reason": "違反毒品危害防制條例",
  "content": "臺灣屏東地方法院刑事判決              100年度訴字第627號\n公  訴  人  臺灣屏東地方法院檢察署檢察官\n被      告  陳惠敏\n上列被告因違反毒品危害防制條例案件，經檢察官提起公訴（10\n0 年度毒偵字第661 號），被告於本院準備程序中就被訴事實為\n有罪之陳述，經本院合議庭裁定由受命法官獨任行簡式程序審理\n，並判決如下：\n    主  文\n陳惠敏施用第一級毒品，累犯，處有期徒刑壹年。\n    事  實\n一、陳惠敏前於民國92年間因施用毒品案件，經本院以92年度毒\n    聲字第1745號裁定送觀察、勒戒後，認無繼續施用毒品之傾\n    向，於93年1 月6 日執行完畢釋放，並經臺灣屏東地方法院\n    檢察署檢察官以93年度毒偵字第9 號為不起訴處分確定；復\n    於前開觀察、勒戒執行完畢釋放後5 年內之93年間，因施用\n    毒品案件，經臺灣高等法院高雄分院以93年度上訴字第1066\n    號判決判處有期徒刑10月確定，於94年11月20日縮刑期滿執\n    行完畢（以上不構成累犯），又於97年間因施用毒品案件，\n    經本院以96年度訴字第1437號判決判處有期徒刑10月，嗣經\n    撤回上訴而判決確定，於98年4 月3 日縮刑期滿執行完畢（\n    以上構成累犯）。詎其仍不知悔改，復基於施用第一級毒品\n    海洛因之犯意，於99年12月14日上午10時許，在屏東縣內埔\n    鄉內埔工業區○○路某處車輛上，以將海洛因摻入香菸內點\n    燃抽菸之方式，施用海洛因1 次，嗣於99年12月17日上午9\n    時50分許，在屏東縣內埔鄉里○路5 號前，因形跡可疑為警\n    查獲，經警徵得其同意採集尿液檢體送驗，鑑驗結果呈嗎啡\n    陽性反應，而查悉上情。\n二、案經屏東縣政府警察局內埔分局報告臺灣屏東地方法院檢察\n    署檢察官偵查起訴，並經本院改依簡式審判程序審理。\n    理  由\n一、按簡式審判程序之證據調查，不受第159 條第1 項之限制，\n    刑事訴訟法第273 條之2 定有明文，是依上開規定，於行簡\n    式審判程序之案件，被告以外之人於審判外之陳述，除有其\n    他不得作為證據之法定事由外，應認具有證據能力。查本案\n    如下引用被告以外之人於審判外之陳述，因本案採行簡式審\n    判程序，復無其他不得作為證據之法定事由，揆諸首揭說明\n    ，應認均具有證據能力，合先敘明。\n二、上揭犯罪事實，業據被告陳惠敏於警詢、本院準備程序及審\n    理時坦承不諱（參見警卷第5 頁，本院卷第21頁背面、第23\n    頁背面、第24頁），又被告為警查獲後在警局所排尿液檢體\n    ，經送臺灣檢驗科技股份有限公司以酵素免疫分析法初步檢\n    驗，再以氣相層析質譜儀法確認檢驗結果，證實該尿液檢體\n    呈嗎啡（即施用海洛因之代謝物）陽性反應，有該公司於10\n    0 年1 月3 日實驗室檢體編號：內警分第990741號濫用藥物\n    檢驗報告、真實姓名對照表（代號：內警分第990741號）各\n    1 紙附卷可稽（參見警卷第8 、12頁）。綜上，足認被告自\n    白與事實相符，堪以採信，本案事證至為明確，被告犯行堪\n    予認定。\n三、按毒品危害防制條例於92年7 月9 日修正公布，自93年1 月\n    9 日施行，其中第20條、第23條將施用毒品之刑事處遇程序\n    區分為「初犯」、「5 年內再犯」、「5 年後再犯」。依其\n    立法理由之說明：「初犯」，經觀察、勒戒或強制戒治，應\n    為不起訴處分或不付審理之裁定；經觀察、勒戒或強制戒治\n    執行完畢釋放後，「5 年內再犯」者，因其再犯率甚高，原\n    實施之觀察、勒戒及強制戒治既已無法收其實效，爰依法追\n    訴或裁定交付審理。至於經觀察、勒戒或強制戒治執行完畢\n    釋放，「5 年後再犯」者，前所實施之觀察、勒戒或強制戒\n    治已足以遮斷其施用毒品之毒癮，為期自新及協助其斷除毒\n    癮，仍用「初犯」規定，先經觀察、勒戒或強制戒治之程序\n    。從而，依修正後之規定，祇於「初犯」及「5 年後再犯」\n    2 種情形，有其追訴條件之限制，即須於初犯經觀察、勒戒\n    或強制戒治釋放後，5 年內均無施用毒品之行為，始能認其\n    前所實施之觀察、勒戒或強制戒治已足遮斷毒癮，而得於5\n    年後再犯時，再予適用初犯之規定，重行觀察、勒戒等程序\n    。倘5 年內已經再犯，經依法再為保安處分或追訴處罰，縱\n    其第3 次（或第3 次以上）施用毒品之時間，在初犯之保安\n    處分執行完畢釋放5 年以後，即與「5 年後再犯」之情形有\n    別，且因已於「5 年內再犯」，顯見其再犯率甚高，原實施\n    觀察、勒戒或強制戒治，已無法收其實效，自無再經觀察、\n    勒戒及強制戒治之必要，應由檢察官逕行起訴，始符新法修\n    正之本旨，最高法院97年第5 次刑事庭會議決議、97年度台\n    非字第540 號及98年度台非字第56號判決意旨可資參照。查\n    本案被告前因施用毒品案件，經送觀察、勒戒後，於93年1\n    月6 日執行完畢釋放，並經臺灣屏東地方法院檢察署檢察官\n    以93年度毒偵字第9 號為不起訴處分確定；復於前開觀察、\n    勒戒執行完畢釋放後5 年內之93年間，因施用毒品案件，經\n    臺灣高等法院高雄分院以93年度上訴字第1066號判決判處有\n    期徒刑10月確定，於94年11月20日縮刑期滿執行完畢等情，\n    有臺灣高等法院被告前案紀錄表在卷可稽，是本案被告所為\n    施用毒品之犯行，距離首開觀察、勒戒執行完畢釋放雖已逾\n    5 年，惟被告在上開觀察、勒戒執行完畢釋放後5 年內，既\n    已再犯施用毒品罪，並經法院追訴、處罰，揆諸前揭說明，\n    其本次犯行即與毒品危害防制條例第20條第3 項所稱之「5\n    年後再犯」有別，是公訴人依法追訴，於法並無不合，本院\n    自應依法論科。\n四、按海洛因為毒品危害防制條例第2 條第2 項第1 款所稱之第\n    一級毒品。核被告陳惠敏所為，係犯毒品危害防制條例第10\n    條第1 項之施用第一級毒品罪；其施用前持有海洛因之低度\n    行為，應為施用海洛因之高度行為所吸收，不另論罪。被告\n    有如事實欄所載前案科刑及執行情形，有前開被告前案紀錄\n    表在卷可稽，其於有期徒刑執行完畢後5 年內，故意再犯本\n    案有期徒刑以上之罪，為累犯，應依刑法第47條第1 項之規\n    定加重其刑。查被告因長期施用毒品，經列為毒品列管調驗\n    人口，警方已高度懷疑其有繼續施用毒品之情事，經警於99\n    年12月17日9 時50分許，在屏東縣內埔鄉里○路5 號前盤查\n    被告，經其同意前往警局製作筆錄等情，有新北勢派出所警\n    製偵查報告在卷可稽（參見警卷第2 頁），是被告雖自白前\n    開施用第一級毒品犯行，然警方於其自白前，既已對其發生\n    嫌疑，將之列為偵查之對象，即已發覺其犯罪，自與自首要\n    件不符，最高法院98年度台上字第318 、4584號判決意旨可\n    資參照，附予敘明。爰審酌被告曾因施用毒品犯行送觀察、\n    勒戒執行完畢及法院判處罪刑，仍不知悛悔，復再度施用第\n    一級毒品，顯見其戒絕毒品之決心不堅，惟念其施用毒品乃\n    戕害自己身心健康，尚未危及他人，犯後一貫坦承犯行，態\n    度良好，並其犯罪之動機、目的及智識程度等一切情狀，量\n    處如主文所示之刑，以示懲儆。\n據上論斷，應依刑事訴訟法第273 條之1 第1 項、第299條第1項\n前段，毒品危害防制條例第10條第1 項，刑法第11條前段、第47\n條第1 項，判決如主文。\n本案經檢察官陳立興到庭執行職務。\n中    華    民    國   100    年    6     月    23    日\n                    刑事第五庭  法  官  謝濰仲\n以上正本證明與原本無異。\n如不服本判決應於收受判決後10日內向本院提出上訴書狀，並應\n敘述具體理由；其未敘述上訴理由者，應於上訴期間屆滿後20日\n內向本院補提理由書（均須按他造當事人之人數附繕本）「切勿\n逕送上級法院」。\n中    華    民    國   100    年    6     月    23    日\n                                書記官  陳佳君\n附錄本案論罪科刑法條全文：\n毒品危害防制條例第10條第1項\n施用第一級毒品者，處 6 月以上 5 年以下有期徒刑。",
  "structure": {
    "main": "陳惠敏施用第一級毒品，累犯，處有期徒刑壹年。",
    "fact": "一、陳惠敏前於民國92年間因施用毒品案件，經本院以92年度毒\n    聲字第1745號裁定送觀察、勒戒後，認無繼續施用毒品之傾\n    向，於93年1 月6 日執行完畢釋放，並經臺灣屏東地方法院\n    檢察署檢察官以93年度毒偵字第9 號為不起訴處分確定；復\n    於前開觀察、勒戒執行完畢釋放後5 年內之93年間，因施用\n    毒品案件，經臺灣高等法院高雄分院以93年度上訴字第1066\n    號判決判處有期徒刑10月確定，於94年11月20日縮刑期滿執\n    行完畢（以上不構成累犯），又於97年間因施用毒品案件，\n    經本院以96年度訴字第1437號判決判處有期徒刑10月，嗣經\n    撤回上訴而判決確定，於98年4 月3 日縮刑期滿執行完畢（\n    以上構成累犯）。詎其仍不知悔改，復基於施用第一級毒品\n    海洛因之犯意，於99年12月14日上午10時許，在屏東縣內埔\n    鄉內埔工業區○○路某處車輛上，以將海洛因摻入香菸內點\n    燃抽菸之方式，施用海洛因1 次，嗣於99年12月17日上午9\n    時50分許，在屏東縣內埔鄉里○路5 號前，因形跡可疑為警\n    查獲，經警徵得其同意採集尿液檢體送驗，鑑驗結果呈嗎啡\n    陽性反應，而查悉上情。\n二、案經屏東縣政府警察局內埔分局報告臺灣屏東地方法院檢察\n    署檢察官偵查起訴，並經本院改依簡式審判程序審理。",
    "reason": "一、按簡式審判程序之證據調查，不受第159 條第1 項之限制，\n    刑事訴訟法第273 條之2 定有明文，是依上開規定，於行簡\n    式審判程序之案件，被告以外之人於審判外之陳述，除有其\n    他不得作為證據之法定事由外，應認具有證據能力。查本案\n    如下引用被告以外之人於審判外之陳述，因本案採行簡式審\n    判程序，復無其他不得作為證據之法定事由，揆諸首揭說明\n    ，應認均具有證據能力，合先敘明。\n二、上揭犯罪事實，業據被告陳惠敏於警詢、本院準備程序及審\n    理時坦承不諱（參見警卷第5 頁，本院卷第21頁背面、第23\n    頁背面、第24頁），又被告為警查獲後在警局所排尿液檢體\n    ，經送臺灣檢驗科技股份有限公司以酵素免疫分析法初步檢\n    驗，再以氣相層析質譜儀法確認檢驗結果，證實該尿液檢體\n    呈嗎啡（即施用海洛因之代謝物）陽性反應，有該公司於10\n    0 年1 月3 日實驗室檢體編號：內警分第990741號濫用藥物\n    檢驗報告、真實姓名對照表（代號：內警分第990741號）各\n    1 紙附卷可稽（參見警卷第8 、12頁）。綜上，足認被告自\n    白與事實相符，堪以採信，本案事證至為明確，被告犯行堪\n    予認定。\n三、按毒品危害防制條例於92年7 月9 日修正公布，自93年1 月\n    9 日施行，其中第20條、第23條將施用毒品之刑事處遇程序\n    區分為「初犯」、「5 年內再犯」、「5 年後再犯」。依其\n    立法理由之說明：「初犯」，經觀察、勒戒或強制戒治，應\n    為不起訴處分或不付審理之裁定；經觀察、勒戒或強制戒治\n    執行完畢釋放後，「5 年內再犯」者，因其再犯率甚高，原\n    實施之觀察、勒戒及強制戒治既已無法收其實效，爰依法追\n    訴或裁定交付審理。至於經觀察、勒戒或強制戒治執行完畢\n    釋放，「5 年後再犯」者，前所實施之觀察、勒戒或強制戒\n    治已足以遮斷其施用毒品之毒癮，為期自新及協助其斷除毒\n    癮，仍用「初犯」規定，先經觀察、勒戒或強制戒治之程序\n    。從而，依修正後之規定，祇於「初犯」及「5 年後再犯」\n    2 種情形，有其追訴條件之限制，即須於初犯經觀察、勒戒\n    或強制戒治釋放後，5 年內均無施用毒品之行為，始能認其\n    前所實施之觀察、勒戒或強制戒治已足遮斷毒癮，而得於5\n    年後再犯時，再予適用初犯之規定，重行觀察、勒戒等程序\n    。倘5 年內已經再犯，經依法再為保安處分或追訴處罰，縱\n    其第3 次（或第3 次以上）施用毒品之時間，在初犯之保安\n    處分執行完畢釋放5 年以後，即與「5 年後再犯」之情形有\n    別，且因已於「5 年內再犯」，顯見其再犯率甚高，原實施\n    觀察、勒戒或強制戒治，已無法收其實效，自無再經觀察、\n    勒戒及強制戒治之必要，應由檢察官逕行起訴，始符新法修\n    正之本旨，最高法院97年第5 次刑事庭會議決議、97年度台\n    非字第540 號及98年度台非字第56號判決意旨可資參照。查\n    本案被告前因施用毒品案件，經送觀察、勒戒後，於93年1\n    月6 日執行完畢釋放，並經臺灣屏東地方法院檢察署檢察官\n    以93年度毒偵字第9 號為不起訴處分確定；復於前開觀察、\n    勒戒執行完畢釋放後5 年內之93年間，因施用毒品案件，經\n    臺灣高等法院高雄分院以93年度上訴字第1066號判決判處有\n    期徒刑10月確定，於94年11月20日縮刑期滿執行完畢等情，\n    有臺灣高等法院被告前案紀錄表在卷可稽，是本案被告所為\n    施用毒品之犯行，距離首開觀察、勒戒執行完畢釋放雖已逾\n    5 年，惟被告在上開觀察、勒戒執行完畢釋放後5 年內，既\n    已再犯施用毒品罪，並經法院追訴、處罰，揆諸前揭說明，\n    其本次犯行即與毒品危害防制條例第20條第3 項所稱之「5\n    年後再犯」有別，是公訴人依法追訴，於法並無不合，本院\n    自應依法論科。\n四、按海洛因為毒品危害防制條例第2 條第2 項第1 款所稱之第\n    一級毒品。核被告陳惠敏所為，係犯毒品危害防制條例第10\n    條第1 項之施用第一級毒品罪；其施用前持有海洛因之低度\n    行為，應為施用海洛因之高度行為所吸收，不另論罪。被告\n    有如事實欄所載前案科刑及執行情形，有前開被告前案紀錄\n    表在卷可稽，其於有期徒刑執行完畢後5 年內，故意再犯本\n    案有期徒刑以上之罪，為累犯，應依刑法第47條第1 項之規\n    定加重其刑。查被告因長期施用毒品，經列為毒品列管調驗\n    人口，警方已高度懷疑其有繼續施用毒品之情事，經警於99\n    年12月17日9 時50分許，在屏東縣內埔鄉里○路5 號前盤查\n    被告，經其同意前往警局製作筆錄等情，有新北勢派出所警\n    製偵查報告在卷可稽（參見警卷第2 頁），是被告雖自白前\n    開施用第一級毒品犯行，然警方於其自白前，既已對其發生\n    嫌疑，將之列為偵查之對象，即已發覺其犯罪，自與自首要\n    件不符，最高法院98年度台上字第318 、4584號判決意旨可\n    資參照，附予敘明。爰審酌被告曾因施用毒品犯行送觀察、\n    勒戒執行完畢及法院判處罪刑，仍不知悛悔，復再度施用第\n    一級毒品，顯見其戒絕毒品之決心不堅，惟念其施用毒品乃\n    戕害自己身心健康，尚未危及他人，犯後一貫坦承犯行，態\n    度良好，並其犯罪之動機、目的及智識程度等一切情狀，量\n    處如主文所示之刑，以示懲儆。\n據上論斷，應依刑事訴訟法第273 條之1 第1 項、第299條第1項\n前段，毒品危害防制條例第10條第1 項，刑法第11條前段、第47\n條第1 項，判決如主文。\n本案經檢察官陳立興到庭執行職務。\n中    華    民    國   100    年    6     月    23    日\n                    刑事第五庭  法  官  謝濰仲\n以上正本證明與原本無異。\n如不服本判決應於收受判決後10日內向本院提出上訴書狀，並應\n敘述具體理由；其未敘述上訴理由者，應於上訴期間屆滿後20日\n內向本院補提理由書（均須按他造當事人之人數附繕本）「切勿\n逕送上級法院」。"
  },
  "search": "臺灣屏東地方法院刑事判決100年度訴字第627號公訴人臺灣屏東地方法院檢察署檢察官被告陳惠敏上列被告因違反毒品危害防制條例案件，經檢察官提起公訴（100年度毒偵字第661號），被告於本院準備程序中就被訴事實為有罪之陳述，經本院合議庭裁定由受命法官獨任行簡式程序審理，並判決如下：主文陳惠敏施用第一級毒品，累犯，處有期徒刑壹年。事實一、陳惠敏前於民國92年間因施用毒品案件，經本院以92年度毒聲字第1745號裁定送觀察、勒戒後，認無繼續施用毒品之傾向，於93年1月6日執行完畢釋放，並經臺灣屏東地方法院檢察署檢察官以93年度毒偵字第9號為不起訴處分確定；復於前開觀察、勒戒執行完畢釋放後5年內之93年間，因施用毒品案件，經臺灣高等法院高雄分院以93年度上訴字第1066號判決判處有期徒刑10月確定，於94年11月20日縮刑期滿執行完畢（以上不構成累犯），又於97年間因施用毒品案件，經本院以96年度訴字第1437號判決判處有期徒刑10月，嗣經撤回上訴而判決確定，於98年4月3日縮刑期滿執行完畢（以上構成累犯）。詎其仍不知悔改，復基於施用第一級毒品海洛因之犯意，於99年12月14日上午10時許，在屏東縣內埔鄉內埔工業區○○路某處車輛上，以將海洛因摻入香菸內點燃抽菸之方式，施用海洛因1次，嗣於99年12月17日上午9時50分許，在屏東縣內埔鄉里○路5號前，因形跡可疑為警查獲，經警徵得其同意採集尿液檢體送驗，鑑驗結果呈嗎啡陽性反應，而查悉上情。二、案經屏東縣政府警察局內埔分局報告臺灣屏東地方法院檢察署檢察官偵查起訴，並經本院改依簡式審判程序審理。理由一、按簡式審判程序之證據調查，不受第159條第1項之限制，刑事訴訟法第273條之2定有明文，是依上開規定，於行簡式審判程序之案件，被告以外之人於審判外之陳述，除有其他不得作為證據之法定事由外，應認具有證據能力。查本案如下引用被告以外之人於審判外之陳述，因本案採行簡式審判程序，復無其他不得作為證據之法定事由，揆諸首揭說明，應認均具有證據能力，合先敘明。二、上揭犯罪事實，業據被告陳惠敏於警詢、本院準備程序及審理時坦承不諱（參見警卷第5頁，本院卷第21頁背面、第23頁背面、第24頁），又被告為警查獲後在警局所排尿液檢體，經送臺灣檢驗科技股份有限公司以酵素免疫分析法初步檢驗，再以氣相層析質譜儀法確認檢驗結果，證實該尿液檢體呈嗎啡（即施用海洛因之代謝物）陽性反應，有該公司於100年1月3日實驗室檢體編號：內警分第990741號濫用藥物檢驗報告、真實姓名對照表（代號：內警分第990741號）各1紙附卷可稽（參見警卷第8、12頁）。綜上，足認被告自白與事實相符，堪以採信，本案事證至為明確，被告犯行堪予認定。三、按毒品危害防制條例於92年7月9日修正公布，自93年1月9日施行，其中第20條、第23條將施用毒品之刑事處遇程序區分為「初犯」、「5年內再犯」、「5年後再犯」。依其立法理由之說明：「初犯」，經觀察、勒戒或強制戒治，應為不起訴處分或不付審理之裁定；經觀察、勒戒或強制戒治執行完畢釋放後，「5年內再犯」者，因其再犯率甚高，原實施之觀察、勒戒及強制戒治既已無法收其實效，爰依法追訴或裁定交付審理。至於經觀察、勒戒或強制戒治執行完畢釋放，「5年後再犯」者，前所實施之觀察、勒戒或強制戒治已足以遮斷其施用毒品之毒癮，為期自新及協助其斷除毒癮，仍用「初犯」規定，先經觀察、勒戒或強制戒治之程序。從而，依修正後之規定，祇於「初犯」及「5年後再犯」2種情形，有其追訴條件之限制，即須於初犯經觀察、勒戒或強制戒治釋放後，5年內均無施用毒品之行為，始能認其前所實施之觀察、勒戒或強制戒治已足遮斷毒癮，而得於5年後再犯時，再予適用初犯之規定，重行觀察、勒戒等程序。倘5年內已經再犯，經依法再為保安處分或追訴處罰，縱其第3次（或第3次以上）施用毒品之時間，在初犯之保安處分執行完畢釋放5年以後，即與「5年後再犯」之情形有別，且因已於「5年內再犯」，顯見其再犯率甚高，原實施觀察、勒戒或強制戒治，已無法收其實效，自無再經觀察、勒戒及強制戒治之必要，應由檢察官逕行起訴，始符新法修正之本旨，最高法院97年第5次刑事庭會議決議、97年度台非字第540號及98年度台非字第56號判決意旨可資參照。查本案被告前因施用毒品案件，經送觀察、勒戒後，於93年1月6日執行完畢釋放，並經臺灣屏東地方法院檢察署檢察官以93年度毒偵字第9號為不起訴處分確定；復於前開觀察、勒戒執行完畢釋放後5年內之93年間，因施用毒品案件，經臺灣高等法院高雄分院以93年度上訴字第1066號判決判處有期徒刑10月確定，於94年11月20日縮刑期滿執行完畢等情，有臺灣高等法院被告前案紀錄表在卷可稽，是本案被告所為施用毒品之犯行，距離首開觀察、勒戒執行完畢釋放雖已逾5年，惟被告在上開觀察、勒戒執行完畢釋放後5年內，既已再犯施用毒品罪，並經法院追訴、處罰，揆諸前揭說明，其本次犯行即與毒品危害防制條例第20條第3項所稱之「5年後再犯」有別，是公訴人依法追訴，於法並無不合，本院自應依法論科。四、按海洛因為毒品危害防制條例第2條第2項第1款所稱之第一級毒品。核被告陳惠敏所為，係犯毒品危害防制條例第10條第1項之施用第一級毒品罪；其施用前持有海洛因之低度行為，應為施用海洛因之高度行為所吸收，不另論罪。被告有如事實欄所載前案科刑及執行情形，有前開被告前案紀錄表在卷可稽，其於有期徒刑執行完畢後5年內，故意再犯本案有期徒刑以上之罪，為累犯，應依刑法第47條第1項之規定加重其刑。查被告因長期施用毒品，經列為毒品列管調驗人口，警方已高度懷疑其有繼續施用毒品之情事，經警於99年12月17日9時50分許，在屏東縣內埔鄉里○路5號前盤查被告，經其同意前往警局製作筆錄等情，有新北勢派出所警製偵查報告在卷可稽（參見警卷第2頁），是被告雖自白前開施用第一級毒品犯行，然警方於其自白前，既已對其發生嫌疑，將之列為偵查之對象，即已發覺其犯罪，自與自首要件不符，最高法院98年度台上字第318、4584號判決意旨可資參照，附予敘明。爰審酌被告曾因施用毒品犯行送觀察、勒戒執行完畢及法院判處罪刑，仍不知悛悔，復再度施用第一級毒品，顯見其戒絕毒品之決心不堅，惟念其施用毒品乃戕害自己身心健康，尚未危及他人，犯後一貫坦承犯行，態度良好，並其犯罪之動機、目的及智識程度等一切情狀，量處如主文所示之刑，以示懲儆。據上論斷，應依刑事訴訟法第273條之1第1項、第299條第1項前段，毒品危害防制條例第10條第1項，刑法第11條前段、第47條第1項，判決如主文。本案經檢察官陳立興到庭執行職務。中華民國100年6月23日刑事第五庭法官謝濰仲以上正本證明與原本無異。如不服本判決應於收受判決後10日內向本院提出上訴書狀，並應敘述具體理由；其未敘述上訴理由者，應於上訴期間屆滿後20日內向本院補提理由書（均須按他造當事人之人數附繕本）「切勿逕送上級法院」。中華民國100年6月23日書記官陳佳君附錄本案論罪科刑法條全文：毒品危害防制條例第10條第1項施用第一級毒品者，處6月以上5年以下有期徒刑。",
  "characters": {
    "judges": [
      "謝濰仲"
    ],
    "prosecutors": [
      "陳立興"
    ],
    "lawyers": [

    ],
    "clerks": [
      "陳佳君"
    ],
    "plaintiffs": [

    ],
    "defendants": [
      "陳惠敏"
    ],
    "prosecutor_office": [
      "臺灣屏東地方法院檢察署檢察官"
    ],
    "creditors": [

    ],
    "debtors": [

    ],
    "judicial_associate_officer": [

    ]
  },
  "adjudged_at": "2011-06-23",
  "created_at": "2016-02-13 17:41:53",
  "updated_at": "2016-02-13 17:41:53"
}