{
  "identify": "TND-100-家訴-27-20110622-1",
  "court": {
    "name": "臺灣南投地方法院",
    "code": "TND"
  },
  "division": {
    "name": "民事",
    "code": "V"
  },
  "year": 100,
  "word": "家訴",
  "number": "27",
  "jcheck": "1",
  "reason": "返還不當得利",
  "content": "臺灣臺南地方法院民事判決            100年度家訴字第27號\n原      告  蔣瑞福\n訴訟代理人  黃郁婷律師\n            陳建欽律師\n被      告  蔣育瑛\n訴訟代理人  陳慈鳳律師\n上列當事人間請求返還不當得利事件，本院判決如下：\n    主      文\n原告之訴及假執行之聲請均駁回。\n訴訟費用由原告負擔。\n    事實及理由\n一、原告起訴主張︰\n  (一)原告與被告為養兄妹關係，兩造之養父即被繼承人蔣錫將於\n    民國89年8月5日過世，遺留有如下之遺產：1.座落於高雄市\n    ○○區○○段29地號土地一筆，地目建，面積57.97平方公\n    尺，持分全部，及地上房屋546建號，門牌三民區○○路86\n    巷3號，持分全部（下稱系爭愛國路房地）；2.座落高雄市\n    ○○區○○段1435地號土地一筆，地目建，面積4,453平方\n    公尺，持分611/100000，及地上房屋1969建號，門牌苓雅區\n    ○○街5巷12號4樓之3，持分全部（下稱系爭德安街房地）\n    ；3.臺灣銀行高雄分行優惠儲蓄存款新臺幣(下同)349,000\n    元；4.臺灣銀行高雄分行活期儲蓄存款850元；5.高雄市第\n    三信用合作社三多分社綜合存款7,252元；6.現金10,000元\n    。按民法第1147條、第1151條之規定，上述1.至6.之財產原\n    屬兩造與被繼承人之配偶蔣張惠咥所繼承之公同共有遺產，\n    然被告在明知原告及蔣張惠咥長年均患有嚴重精神疾病、欠\n    缺辨別事理能力之情形下，竟於89年10月間未經原告及蔣張\n    惠咥之同意，持偽造之分割協議書向地政機關辦理由其單獨\n    繼承上開二筆房地，並私吞所有款項，嗣於90年3月及94年4\n    月分別將上開二筆房地出售並換取價款予以獨占，致原告及\n    蔣張惠咥受有損害，原告自得依民法第179條、第182條第2\n    項前段不當得利之規定，請求被告給付相當於遺產三分之一\n    之利益。\n  (二)按當事人互相表示意思一致者，無論其為明示或默示，契約\n    即為成立，民法第153條第1項定有明文；次按當事人主張有\n    利於己之事實者，就其事實有舉證之責任，民事訴訟法第27\n    7條本文亦定有明文；又按解釋意思表示，應探求當事人之\n    真意，不得拘泥於所用之辭句，為民法第98條所明定，故不\n    得逕以分割協議書上蓋用原告之印鑑章，即認定兩造間確有\n    上開分割協議，且上開分割協議之最大利益者係被告而非原\n    告，況據蔡凱文代書證述本件分割協議辦理過程僅接觸到被\n    告，一切都是聽被告敘述等語，原告及訴外人蔣張惠咥是否\n    確實均已達成上開分割協議之內容，尚非無疑，揆諸前開說\n    明，被告應先就分割協議是否確實存在盡舉證之責；再者，\n    分割協議書上的印章，與原告的印鑑章看似雷同，實則經放\n    大比對後，二者字體明顯不同，印鑑證明章是遭偽造、用美\n    工刀一筆一筆刻出來的，因為筆畫沒有粗細之分，分割協議\n    書上才是真正的章。\n  (三)原告是有次看到報紙刊登愛國路附近淹大水的消息，打電話\n    問被告愛國路房子有無淹水，被告稱老早就以120萬元將房\n    子出售，當時原告德安街的戶籍還在，應是94年3月之前的\n    事，原告知道房子遭賤價出售很生氣，被告當時稱要養母親\n    蔣張惠咥，原告以為被告每月要支付2萬元照顧母親，後來\n    才知蔣錫將過世後，母親是眷屬每月可領14,000元左右；原\n    告從未對被告提告，也未以書面、存證信函等方式表示異議\n    ，係因原告從未有分家的觀念，認為二棟房子和父親的存款\n    都在，原告跟被告可以兩邊房子輪流住，而原告於94年間將\n    戶籍自高雄市○○街遷出時，固不否認已知悉房屋由被告出\n    賣，但亦不得以原告至99年間始訴請被告給付不當得利，而\n    逕認被告當時有同意分割之協議，蓋原告多年來因病居住於\n    桃園地區之療養院，原告既無能力自行訴訟，復無資力委任\n    律師為己主張權利，直至創設法律扶助制度後，原告方得以\n    透過法律扶助基金會之協助主張權利，是不得以原告多年來\n    均未主張權利，而逕認原告已默示同意分割協議。\n  (四)茲因就上開二筆房地遭被告不法變賣所生損害賠償數額，恐\n    需待鈞院鑑價或調查後始得確定，是請求鈞院允許原告就上\n    開二筆房地先以被告於89年辦理繼承登記時，主管機關所核\n    定價額列計，待鈞院鑑價或調查確定上開二筆房地之價值後\n    ，再由原告依民事訴訟法第244條第4項規定為補充聲明，以\n    作最終請求金額之確定。是原告起訴金額先以上開二筆房地\n    核定價額加上(一)3.至6.遺產遭被告侵害，原告按應繼分三分\n    之一比例計算可得主張之金額為1,581,620元。再被告係於\n    89年10月5日偽造分割協議書後，於同年10月25日及10月30\n    日分別完成二筆房地之繼承登記，至此損害(惡意不當得利)\n    已然發生，原告自得併請求損害發生時即89年10月31日起至\n    清償日止，按年息百分之五計算之利息。\n  (五)聲明：\n  1.被告應給付原告新臺幣1,581,620元，及自89年10月31日起\n    至清償日止，按年息百分之五計算之利息。\n  2.原告願供擔保請准宣告假執行。\n二、被告則辯以：\n  (一)本件被告取得遺產，係因原告自行同意放棄繼承不動產及存\n    款之權利，故被告取得遺產有正當法律上原因，自不符民法\n    不當得利之要件。\n  (二)兩造養父即被繼承人蔣錫將於89年8月5日死亡，雖留下愛國\n    路與德安街二筆房地及存款357,102元，惟亦留下多筆高雄\n    銀行之貸款債務，當時原告因積欠銀行及地下錢莊債務，擔\n    心繼承上開被繼承人之遺產後遭債權銀行及地下錢莊拍賣，\n    致影響被告及養母蔣張惠咥之權利，且被繼承人蔣錫將亦留\n    下多筆銀行貸款之債務，養母蔣張惠咥中風居往療養院，無\n    力負擔貸款利息，原告負債累累，亦無力支付多筆銀行貸款\n    本息，故協議由被告一人繼承二筆不動產及存款，當時原告\n    亦自行提供印鑑證明與印鑑章等相關資料交由被告辦理繼承\n    事宜，被告即依協議內容委託蔡凱文代書辦理繼承登記事宜\n    ，並無偽造或不法之情事。\n  (三)被繼承人蔣錫將所遺留上開二筆不動產都有貸款，系爭德安\n    街房地有公教貸款180萬元(由高雄市政府委託高雄銀行辦理\n    )及高雄銀行貸款50萬元，系爭愛國路房地則有56萬元的貸\n    款，被告所提被繼承人蔣錫將之高雄銀行授信明細查詢單記\n    載30萬元、20萬元，是第一筆50萬元換貸而來，第四筆、第\n    五筆是比較早的資料，合併之後又增貸32萬元，變成56萬元\n    ，此三筆債務均由被告以其高雄銀行帳戶000000000000轉帳\n    繳交，有高雄銀行出具之存款對帳單為證，被告為早日清償\n    蔣錫將遺留債務，先於90年3月將系爭愛國路房地賣給第三\n    人黃花，由黃花向中國信託銀行貸款清償抵押貸款426,764\n    元；嗣於94年3月間將德安街房地出售予第三人郭天順，據\n    被告所提該不動產買賣契約書第六條稅費負擔第四點，約定\n    由買方負責清償該屋之二筆抵押貸款(即180萬元公教貸款及\n    50萬元貸款)，因郭天順指定登記給郭芳廷，郭芳廷即向中\n    國信託銀行貸款並設定抵押，待中國信託銀行撥款代為清償\n    前二筆貸款餘額412,036元及1,560,027元後，再由高雄銀行\n    塗銷抵押權登記，故以上三筆貸款債務，平日係以被告帳戶\n    轉帳繳交本息，於房屋出售時，則由買主貸款以賣屋價金償\n    還。\n  (四)原告知悉被告將房地出售之事，並配合於94年3月25日將戶\n    口自德安街地址遷出，是原告起訴主張未與被告協議分割遺\n    產，協議內容係被告偽造云云，顯與事實不符，亦有違常情\n    ，印鑑證明係原告提供給被告辦理分割事宜，當時因原告積\n    欠很多卡債，名下又無財產，原告也無法照顧養母，所以原\n    告同意將不動產登記給被告，被繼承人蔣錫將過世後，原告\n    就遺產分割及由被告負擔相關貸款之繳納及清償等事均知情\n    ，卻從未表示異議，從未要求將遺產分割或出賣後分配價金\n    ，且就被告如何取得原告印鑑章，也提不出具體說法，土地\n    及房屋登記為公示資料，任何人隨時可調取，原告之戶籍更\n    先後遷入此二筆房屋，當不得諉稱不知，況被告賣出系爭德\n    安街房地時，還要求原告配合將伊戶口遷走，足證原告當時\n    同意全部遺產及債務均由被告繼承，僅因伊目前窮困潦倒，\n    無經濟來源，欲藉10年前繼承之事向被告要錢，原告多年來\n    經常向被告要錢，被告有餘力時會匯錢給原告，詎原告汙衊\n    被告偽造文書並提起本件訴訟，請鈞院明察。\n  (五)聲明：原告之訴及假執行之聲請均駁回。\n三、兩造不爭執之事實：\n  (一)原告與被告為養兄妹關係，兩造之養父即被繼承人蔣錫將於\n    89年8月5日過世，遺留有遺產：1.系爭愛國路房地；2.系爭\n    德安街房地；3.存款約357,102元。\n  (二)被繼承人蔣錫將死亡後，渠遺產由兩造及蔣錫將之配偶蔣張\n    惠咥繼承，應繼分各三分之一。\n四、得心證之理由：本件原告依不當得利之法律關係，請求被告\n    應返還相當於蔣錫將遺產三分之一之利益，主要是以被告未\n    經伊及蔣張惠咥之同意，持偽造之分割協議書向地政機關辦\n    理由被告單獨繼承遺產中之二筆房地，私吞所有款項，並於\n    90年3月及94年4月分別將上開二筆房地出售換取價款予以獨\n    占，致伊及蔣張惠咥受有損害為主張之依據，惟被告則否認\n    有偽造分割協議書之事實，並辯以：其取得遺產，係因原告\n    自行同意放棄繼承不動產及存款之權利等語，是本件原告之\n    主張是否有據，應以關於蔣錫將之遺產分割協議書是否經兩\n    造同意簽立而認定，茲審酌如下：\n  (一)查蔣錫將所遺留之系爭愛國路房地，業於89年10月25日以分\n    割繼承為原因登記予被告名下；另系爭德安街房地亦於89年\n    10月30日以分割繼承為原告登記被告名下，凡此有原告所提\n    高雄市三民地政事務所網路申領異動索引、高雄市新興地政\n    事務所網路申領異動索引各1件為證，並經本院分別向高雄\n    市政府地政局三民地政事務所、及新興地政事務所調取前開\n    之分割繼承所有權移轉登記文件，分別經三民地政事務所以\n    100年2月15日高市地民價字第1000001507號函檢附該區○○\n    段29地號土地，及其上546建號，門牌三民區○○路86巷3號\n    建物之所有權移轉登記資料，及新興地政事務所以100年2月\n    15日高市地新價字第1000001374號函檢附苓雅區○○段1435\n    地號土地，及其上苓雅區○○街5巷12號4樓之3建物之移轉\n    登記資料附卷供參。而上開二份回函中之移轉登記資料均附\n    有原告(原名蔣紹武，嗣於93年2月27日更名為蔣瑞福)、被\n    告及蔣張惠咥所簽訂之分割協議書、印鑑證明。而原告對於\n    分割協議書及印鑑證明上之印鑑章式樣相似，初亦坦承：分\n    割協議書上之印章與原告印鑑章看起來十分雷同等語，惟又\n    稱對於協議書上所蓋之章是否為伊所有沒有印象等語，可見\n    原告就分割協議書關於原告之章與印鑑證明之章為同一一事\n    初亦不否認。且核對上開地政事務所函附本院所附之分割協\n    議書、印鑑證明、土地登記申請書（均影本），其上關於原\n    告更名前蔣紹武之印文，其字形雷同，亦可見該分割協議書\n    之蔣紹文印文，與印鑑證明之印文應屬同一。至原告嗣後雖\n    於言詞辯論時始質疑印鑑證明與分割協議書之印文顯然不同\n    ，印鑑證明之章是假的等語，並提出伊自行放大印鑑證明及\n    分割協議書之印文影本附卷供參，然該放大影本既為原告自\n    行重複放大，則在多次影印過程中，其紙張有無壓平、墨水\n    濃度深淺，均可能影響最後字體之樣式，此從原告所提之其\n    上蓋有「157822」編號之印鑑證明影本，經核對與本院向前\n    開三民地政事務所所調取之印鑑證明，其中字體墨色深淺有\n    別，以致原告所提印鑑證明中「蔣」字之「寸」、及「紹」\n    字之「糸」部呈現不連續，而與本院調取之印鑑證明明顯不\n    同。以此，原告僅以伊將印鑑證明及分割協議書上之印文放\n    大比對而有差異為由，主張分割協議書上之印文非伊所有，\n    已難採信。\n  (二)且查，當初辦理分割協議登記時，除提出分割協議書外，並\n    有原告之印鑑證明，已見前述，並據證人即辦理蔣錫將移產\n    分割繼承登記之代書蔡凱文證述：「（蔣錫將所有之遺產於\n    高雄市○○區○○路86巷3號房屋及高雄市○○區○○街5巷\n    12號四樓之3房屋及土地等，當初辦理遺產分割協議，是否\n    為你處理？）是的，當時應該是被告委託我辦理的。（兩造\n    有無訂立遺產分割協議？）有。（遺產分割協議有無經過兩\n    造及其他繼承人同意？）他們各蓋印鑑章並出具印鑑證明給\n    我。（訂立分割協議書時，你有無在場？）沒有。（章是由\n    何人蓋的？）是被告當時把原告的印鑑當場拿給我，並說是\n    原告委託他拿給我辦理的。（原告是否知道你去辦理分割遺\n    產的登記？）我不確定。（當時有無聯絡原告？）當時原告\n    不在高雄，且一般情形我們認為有出具印鑑證明，並交付印\n    鑑章，我們就認為有經過本人的同意，否則不會隨便將印鑑\n    章及印鑑證明交給別人。（辦理分割遺產登記後，原告有無\n    向你表示意見？）沒有。（是否直接拿到原告的印鑑章，或\n    是文件上面已經蓋好印鑑印文？）被告直接拿原告的印鑑章\n    給我，說是原告委託他拿給我的，我是當著被告的面確認文\n    件沒有問題後，我當場蓋章並將原告的印鑑章交還給被告。\n    （該分割協議書的內容，是否為你所繕打？）是的，但我是\n    依據兩造及其他繼承人的意思所繕打，我跟三個繼承人並沒\n    有全部見面，我只有與被告接觸。」等語，依證人所述，系\n    爭分割協議書固係由渠繕打，然當初被告乃將原告印鑑章及\n    印鑑證明交付證人蓋印後將印鑑章交還被告，則系爭分割協\n    議書業據附上原告之印鑑證明，已可認定。而原告已不否認\n    該印鑑證明為伊所有，雖伊就該印鑑證明如何而來，辯稱：\n    不知道，因被告把伊從台北叫回高雄，說母親中風等語；惟\n    依卷附原告申辦印鑑證明即89年8月14日當時之有效之印鑑\n    登記辦法（嗣已於98年10月13日修正）第7條規定：「依第\n    四條第一項規定申請印鑑證明應由當事人或其受委任人填具\n    申請書(格式九)並繳驗國民身分證，申請辦理。由其受委任\n    人申請者，並應附繳委任書。」以此，關於當初辦理系爭遺\n    產分割協議所附之原告印鑑證明，無論係原告本人親辦，或\n    由原告出具國民身分證委由他人辦理，無論何者，均可認定\n    該印鑑證明乃經原告同意所申辦；衡情，以印鑑證明乃係為\n    該印文係本人所有之憑據，其關係重大，非有重要事項，一\n    般人當不至無故辦理，可見原告申辦該印鑑證明，當出於特\n    殊目的。再觀兩造被繼承人蔣錫將係於89年8月5日死亡，原\n    告之印鑑證明於89年8月14日申辦，兩造之分割協議書訂立\n    日期為89年10月5日，而前述之系爭愛國路房地係於89年10\n    月25日登記予被告名下，系爭德安街房地亦於89年10月30日\n    以分割繼承為原告登記予被告名下，凡此有原告所提高雄市\n    三民地政事務所網路申領異動索引、高雄市新興地政事務所\n    網路申領異動索引各1件為證，並經本院分別向高雄市政府\n    地政局三民地政事務所、及新興地政事務所調取前開之分割\n    繼承所有權移轉登記文件，以原告之印鑑證明申辦日期介於\n    蔣錫將死亡之後，及兩造訂立分割協議書及辦理分割繼承登\n    記之前，則依上開事件之順序，已可推論原告當係於蔣錫將\n    死亡後，為辦理分割協議，而申辦印鑑證明，再憑以交付被\n    告完成遺產繼承之事宜，是原告所辯不知印鑑如何而來等語\n    ，顯為避重就輕之詞，自不可信。\n  (三)何況被告於依繼承登記取得蔣錫將之不動產後，已分別於90\n    年3月將系爭愛國路房地出售予訴外人黃花，並於90年3月8\n    日辦理所有權移轉登記，嗣又於94年3月5日將系爭德安街房\n    地出售予訴外人郭天順，並於94年4月19日辦理所有權移轉\n    登記予郭芳廷，凡此業為原告提出高雄市三民地政事務所網\n    路申領異動索引、高雄市新興地政事務所網路申領異動索引\n    、苓雅區○○段第1435地號土地登記第二類謄本等件，及被\n    告提出之不動產買賣契約書附卷供參。而原告之戶籍原設於\n    系爭德安街房屋之上，後於94年3月25日遷移至中壢，此亦\n    有原告之戶籍謄本供參，而原告亦自承伊於戶籍仍設於德安\n    街地址時即已知悉被告將前開房地出售之事實，則對照前述\n    經過，可見原告至遲於94年3月25日以前即已知悉被告出售\n    遺產之事，乃迄至99年7月29日始起訴請求返還不當得利，\n    期間相距5年，是參照原告遲未起訴或發存證信函之事實，\n    甚且於被告將德安街房地出售之前將戶籍遷移他處，可見原\n    告對於出售房地一事，不僅知情，且有配合被告而遷移戶籍\n    之意。\n  (四)且被告另抗辯：蔣錫將留下多筆銀行貸款之債務，養母蔣張\n    惠咥中風居往療養院，無力負擔貸款利息，原告負債累累，\n    亦無力支付多筆銀行貸款本息，故協議由其一人繼承二筆不\n    動產及存款，其為早日清償蔣錫將遺留債務，先於90年3月\n    將系爭愛國路房地賣給第三人黃花，由黃花向中國信託銀行\n    貸款清償抵押貸款426,764元，嗣於94年3月間將系爭德安街\n    房地出售予第三人郭天順，約定由買方負責清償該屋之二筆\n    抵押貸款，因郭天順指定登記給郭芳廷，郭芳廷即向中國信\n    託銀行貸款並設定抵押，待中國信託銀行撥款代為清償前二\n    筆貸款餘額412,036元及1,560,027元後，再由高雄銀行塗銷\n    抵押權登記，故以上三筆貸款債務，平日係以其帳戶轉帳繳\n    交本息，於房屋出售時，則由買主貸款以賣屋價金償還等語\n    。查，蔣錫將死亡當時，遺有三筆貸款，分別為：1.積欠高\n    雄銀行大發分行金額491,652元；2.積欠高雄銀行大發分行\n    金額479,749元；此二筆貸款均由被告於高雄銀行大發分行\n    所開設帳戶扣款繳納本金及利息，並於90年3月16日由中國\n    信託三民分行匯款清償第1.筆貸款，及於94年4月20日由中\n    國信託高雄分行匯款清償第2.筆貸款；此有高雄銀行股份有\n    限公司大發分行100年3月30日高銀大發字第10000052號函附\n    卷可稽；另第3.筆為國宅貸款180萬元，並於94年4月20日由\n    中國信託帳戶匯入，償還金額為1,560,027元，此亦有高雄\n    銀行股份有限公司100年4月28日高銀營字第1000002937號函\n    可參。從上所述，其中蔣錫將所遺留之第1.、2.筆借款均係\n    由被告清償，另從系爭愛國路房地係於90年3月間出售，並\n    於3月8日移轉登記，其與第1.筆貸款完全清償之時間僅相差\n    8日；而系爭德安街之房地於94年3月5日出售，並於94年4月\n    19日移轉登記，此亦與第2.、3.筆貸款之完全清償日期94年\n    4月20日亦密切相近，則參照上開事實，可認被告所辯蔣錫\n    將所遺留債務由其負責清償，嗣後並由其將系爭愛國路、德\n    安街房地出售後以所得價金清償款項等語，亦可認定。\n  (五)綜合前述，本件從蔣錫將遺產辦理分割協議登記時，已有原\n    告之印鑑證明及印鑑章，而原告就印鑑證明之由來亦答以不\n    知情，則衡諸常情，該印鑑證明當係原告申辦或由原告授意\n    辦理，而以印鑑證明之申辦時間乃在蔣錫將死亡後數日所為\n    ，且該印鑑證明申辦後未久即經代書辦理蔣錫將遺產分割協\n    議登記，更可見該印鑑證明當係為辦理分割協議而申辦；參\n    以被告於94年3月5日將德安街房地出售後，原告隨即於同月\n    25日將原設籍於德安街之戶籍遷至中壢，並參原告自承於戶\n    籍仍設於德安街之時即知被告將房地出售之事，可見原告對\n    於被告出售蔣錫將所留遺產一事，不僅知情，且亦配合辦理\n    遷移戶籍，而從原告自該時起迄今起訴時之5年餘時間均未\n    曾異議，乃於時隔5年餘又表示被告未得伊同意變賣父親遺\n    產，自不合理。再參蔣錫將所遺留債務係由被告償還，嗣並\n    以出售愛國路、德安街房地之價金償還，益可見被告所辯當\n    初繼承人協議由其繼承不動產及存款，並將房地出售後清償\n    貸款之主張，為可採信。依上，則原告對於本件系爭分割協\n    議當已知悉並同意，伊主張被告偽造分割協議書辦理繼承登\n    記，並變賣父親遺產，殊不可信。茲被告所辦理遺產分割，\n    既係本於繼承人之協議，則伊取得蔣錫將之遺產，自非無法\n    律上原因，從而原告以被告無法律上原因而受利益，致伊及\n    共同繼承人蔣張惠咥受有損害，據以依不當得利之法律關係\n    請求被告返還相當遺產三分之一之利益，於法無據，應予駁\n    回。\n五、本件法律關係已臻明確，兩造其餘之主張、抗辯，於本件之\n    認定不生影響，爰不再一一論述；又被告聲請蔣張惠咥到庭\n    訊問，惟依渠所證，語涉：「．．．我先生現在還在，住在\n    小港，他死了是死了，但他的靈還在，他天天來看我，我還\n    弄飯給他吃，我先生現在住在小港。（有無去找妳先生？）\n    我天天看得見。（如何看見的？）我是天上聖母，我是神，\n    也是人。」等語無倫次之言語，是渠之心神狀況不佳，已難\n    為有正確證述，則渠所為其餘證詞自難採認，併此敘明。\n六、據上論結，本件原告之訴為無理由，依民事訴訟法第78條，\n    判決如主文。\n中    華    民    國    100    年    6    月    22    日\n                  家事法庭    法  官  林富郎\n以上為正本係照原本作成\n如對本判決上訴，須於判決送達後20日內向本院提出上訴狀（附\n具繕本），如委任律師提起上訴者，應一併繳納上訴審裁判費。\n中    華    民    國    100    年    6    月    22    日\n                              書記官  劉毓如",
  "structure": {
    "main": "原告之訴及假執行之聲請均駁回。\n訴訟費用由原告負擔。",
    "fact": "一、原告起訴主張︰\n  (一)原告與被告為養兄妹關係，兩造之養父即被繼承人蔣錫將於\n    民國89年8月5日過世，遺留有如下之遺產：1.座落於高雄市\n    ○○區○○段29地號土地一筆，地目建，面積57.97平方公\n    尺，持分全部，及地上房屋546建號，門牌三民區○○路86\n    巷3號，持分全部（下稱系爭愛國路房地）；2.座落高雄市\n    ○○區○○段1435地號土地一筆，地目建，面積4,453平方\n    公尺，持分611/100000，及地上房屋1969建號，門牌苓雅區\n    ○○街5巷12號4樓之3，持分全部（下稱系爭德安街房地）\n    ；3.臺灣銀行高雄分行優惠儲蓄存款新臺幣(下同)349,000\n    元；4.臺灣銀行高雄分行活期儲蓄存款850元；5.高雄市第\n    三信用合作社三多分社綜合存款7,252元；6.現金10,000元\n    。按民法第1147條、第1151條之規定，上述1.至6.之財產原\n    屬兩造與被繼承人之配偶蔣張惠咥所繼承之公同共有遺產，\n    然被告在明知原告及蔣張惠咥長年均患有嚴重精神疾病、欠\n    缺辨別事理能力之情形下，竟於89年10月間未經原告及蔣張\n    惠咥之同意，持偽造之分割協議書向地政機關辦理由其單獨\n    繼承上開二筆房地，並私吞所有款項，嗣於90年3月及94年4\n    月分別將上開二筆房地出售並換取價款予以獨占，致原告及\n    蔣張惠咥受有損害，原告自得依民法第179條、第182條第2\n    項前段不當得利之規定，請求被告給付相當於遺產三分之一\n    之利益。\n  (二)按當事人互相表示意思一致者，無論其為明示或默示，契約\n    即為成立，民法第153條第1項定有明文；次按當事人主張有\n    利於己之事實者，就其事實有舉證之責任，民事訴訟法第27\n    7條本文亦定有明文；又按解釋意思表示，應探求當事人之\n    真意，不得拘泥於所用之辭句，為民法第98條所明定，故不\n    得逕以分割協議書上蓋用原告之印鑑章，即認定兩造間確有\n    上開分割協議，且上開分割協議之最大利益者係被告而非原\n    告，況據蔡凱文代書證述本件分割協議辦理過程僅接觸到被\n    告，一切都是聽被告敘述等語，原告及訴外人蔣張惠咥是否\n    確實均已達成上開分割協議之內容，尚非無疑，揆諸前開說\n    明，被告應先就分割協議是否確實存在盡舉證之責；再者，\n    分割協議書上的印章，與原告的印鑑章看似雷同，實則經放\n    大比對後，二者字體明顯不同，印鑑證明章是遭偽造、用美\n    工刀一筆一筆刻出來的，因為筆畫沒有粗細之分，分割協議\n    書上才是真正的章。\n  (三)原告是有次看到報紙刊登愛國路附近淹大水的消息，打電話\n    問被告愛國路房子有無淹水，被告稱老早就以120萬元將房\n    子出售，當時原告德安街的戶籍還在，應是94年3月之前的\n    事，原告知道房子遭賤價出售很生氣，被告當時稱要養母親\n    蔣張惠咥，原告以為被告每月要支付2萬元照顧母親，後來\n    才知蔣錫將過世後，母親是眷屬每月可領14,000元左右；原\n    告從未對被告提告，也未以書面、存證信函等方式表示異議\n    ，係因原告從未有分家的觀念，認為二棟房子和父親的存款\n    都在，原告跟被告可以兩邊房子輪流住，而原告於94年間將\n    戶籍自高雄市○○街遷出時，固不否認已知悉房屋由被告出\n    賣，但亦不得以原告至99年間始訴請被告給付不當得利，而\n    逕認被告當時有同意分割之協議，蓋原告多年來因病居住於\n    桃園地區之療養院，原告既無能力自行訴訟，復無資力委任\n    律師為己主張權利，直至創設法律扶助制度後，原告方得以\n    透過法律扶助基金會之協助主張權利，是不得以原告多年來\n    均未主張權利，而逕認原告已默示同意分割協議。\n  (四)茲因就上開二筆房地遭被告不法變賣所生損害賠償數額，恐\n    需待鈞院鑑價或調查後始得確定，是請求鈞院允許原告就上\n    開二筆房地先以被告於89年辦理繼承登記時，主管機關所核\n    定價額列計，待鈞院鑑價或調查確定上開二筆房地之價值後\n    ，再由原告依民事訴訟法第244條第4項規定為補充聲明，以\n    作最終請求金額之確定。是原告起訴金額先以上開二筆房地\n    核定價額加上(一)3.至6.遺產遭被告侵害，原告按應繼分三分\n    之一比例計算可得主張之金額為1,581,620元。再被告係於\n    89年10月5日偽造分割協議書後，於同年10月25日及10月30\n    日分別完成二筆房地之繼承登記，至此損害(惡意不當得利)\n    已然發生，原告自得併請求損害發生時即89年10月31日起至\n    清償日止，按年息百分之五計算之利息。\n  (五)聲明：\n  1.被告應給付原告新臺幣1,581,620元，及自89年10月31日起\n    至清償日止，按年息百分之五計算之利息。\n  2.原告願供擔保請准宣告假執行。\n二、被告則辯以：\n  (一)本件被告取得遺產，係因原告自行同意放棄繼承不動產及存\n    款之權利，故被告取得遺產有正當法律上原因，自不符民法\n    不當得利之要件。\n  (二)兩造養父即被繼承人蔣錫將於89年8月5日死亡，雖留下愛國\n    路與德安街二筆房地及存款357,102元，惟亦留下多筆高雄\n    銀行之貸款債務，當時原告因積欠銀行及地下錢莊債務，擔\n    心繼承上開被繼承人之遺產後遭債權銀行及地下錢莊拍賣，\n    致影響被告及養母蔣張惠咥之權利，且被繼承人蔣錫將亦留\n    下多筆銀行貸款之債務，養母蔣張惠咥中風居往療養院，無\n    力負擔貸款利息，原告負債累累，亦無力支付多筆銀行貸款\n    本息，故協議由被告一人繼承二筆不動產及存款，當時原告\n    亦自行提供印鑑證明與印鑑章等相關資料交由被告辦理繼承\n    事宜，被告即依協議內容委託蔡凱文代書辦理繼承登記事宜\n    ，並無偽造或不法之情事。\n  (三)被繼承人蔣錫將所遺留上開二筆不動產都有貸款，系爭德安\n    街房地有公教貸款180萬元(由高雄市政府委託高雄銀行辦理\n    )及高雄銀行貸款50萬元，系爭愛國路房地則有56萬元的貸\n    款，被告所提被繼承人蔣錫將之高雄銀行授信明細查詢單記\n    載30萬元、20萬元，是第一筆50萬元換貸而來，第四筆、第\n    五筆是比較早的資料，合併之後又增貸32萬元，變成56萬元\n    ，此三筆債務均由被告以其高雄銀行帳戶000000000000轉帳\n    繳交，有高雄銀行出具之存款對帳單為證，被告為早日清償\n    蔣錫將遺留債務，先於90年3月將系爭愛國路房地賣給第三\n    人黃花，由黃花向中國信託銀行貸款清償抵押貸款426,764\n    元；嗣於94年3月間將德安街房地出售予第三人郭天順，據\n    被告所提該不動產買賣契約書第六條稅費負擔第四點，約定\n    由買方負責清償該屋之二筆抵押貸款(即180萬元公教貸款及\n    50萬元貸款)，因郭天順指定登記給郭芳廷，郭芳廷即向中\n    國信託銀行貸款並設定抵押，待中國信託銀行撥款代為清償\n    前二筆貸款餘額412,036元及1,560,027元後，再由高雄銀行\n    塗銷抵押權登記，故以上三筆貸款債務，平日係以被告帳戶\n    轉帳繳交本息，於房屋出售時，則由買主貸款以賣屋價金償\n    還。\n  (四)原告知悉被告將房地出售之事，並配合於94年3月25日將戶\n    口自德安街地址遷出，是原告起訴主張未與被告協議分割遺\n    產，協議內容係被告偽造云云，顯與事實不符，亦有違常情\n    ，印鑑證明係原告提供給被告辦理分割事宜，當時因原告積\n    欠很多卡債，名下又無財產，原告也無法照顧養母，所以原\n    告同意將不動產登記給被告，被繼承人蔣錫將過世後，原告\n    就遺產分割及由被告負擔相關貸款之繳納及清償等事均知情\n    ，卻從未表示異議，從未要求將遺產分割或出賣後分配價金\n    ，且就被告如何取得原告印鑑章，也提不出具體說法，土地\n    及房屋登記為公示資料，任何人隨時可調取，原告之戶籍更\n    先後遷入此二筆房屋，當不得諉稱不知，況被告賣出系爭德\n    安街房地時，還要求原告配合將伊戶口遷走，足證原告當時\n    同意全部遺產及債務均由被告繼承，僅因伊目前窮困潦倒，\n    無經濟來源，欲藉10年前繼承之事向被告要錢，原告多年來\n    經常向被告要錢，被告有餘力時會匯錢給原告，詎原告汙衊\n    被告偽造文書並提起本件訴訟，請鈞院明察。\n  (五)聲明：原告之訴及假執行之聲請均駁回。\n三、兩造不爭執之事實：\n  (一)原告與被告為養兄妹關係，兩造之養父即被繼承人蔣錫將於\n    89年8月5日過世，遺留有遺產：1.系爭愛國路房地；2.系爭\n    德安街房地；3.存款約357,102元。\n  (二)被繼承人蔣錫將死亡後，渠遺產由兩造及蔣錫將之配偶蔣張\n    惠咥繼承，應繼分各三分之一。\n四、得心證之理由：本件原告依不當得利之法律關係，請求被告\n    應返還相當於蔣錫將遺產三分之一之利益，主要是以被告未\n    經伊及蔣張惠咥之同意，持偽造之分割協議書向地政機關辦\n    理由被告單獨繼承遺產中之二筆房地，私吞所有款項，並於\n    90年3月及94年4月分別將上開二筆房地出售換取價款予以獨\n    占，致伊及蔣張惠咥受有損害為主張之依據，惟被告則否認\n    有偽造分割協議書之事實，並辯以：其取得遺產，係因原告\n    自行同意放棄繼承不動產及存款之權利等語，是本件原告之\n    主張是否有據，應以關於蔣錫將之遺產分割協議書是否經兩\n    造同意簽立而認定，茲審酌如下：\n  (一)查蔣錫將所遺留之系爭愛國路房地，業於89年10月25日以分\n    割繼承為原因登記予被告名下；另系爭德安街房地亦於89年\n    10月30日以分割繼承為原告登記被告名下，凡此有原告所提\n    高雄市三民地政事務所網路申領異動索引、高雄市新興地政\n    事務所網路申領異動索引各1件為證，並經本院分別向高雄\n    市政府地政局三民地政事務所、及新興地政事務所調取前開\n    之分割繼承所有權移轉登記文件，分別經三民地政事務所以\n    100年2月15日高市地民價字第1000001507號函檢附該區○○\n    段29地號土地，及其上546建號，門牌三民區○○路86巷3號\n    建物之所有權移轉登記資料，及新興地政事務所以100年2月\n    15日高市地新價字第1000001374號函檢附苓雅區○○段1435\n    地號土地，及其上苓雅區○○街5巷12號4樓之3建物之移轉\n    登記資料附卷供參。而上開二份回函中之移轉登記資料均附\n    有原告(原名蔣紹武，嗣於93年2月27日更名為蔣瑞福)、被\n    告及蔣張惠咥所簽訂之分割協議書、印鑑證明。而原告對於\n    分割協議書及印鑑證明上之印鑑章式樣相似，初亦坦承：分\n    割協議書上之印章與原告印鑑章看起來十分雷同等語，惟又\n    稱對於協議書上所蓋之章是否為伊所有沒有印象等語，可見\n    原告就分割協議書關於原告之章與印鑑證明之章為同一一事\n    初亦不否認。且核對上開地政事務所函附本院所附之分割協\n    議書、印鑑證明、土地登記申請書（均影本），其上關於原\n    告更名前蔣紹武之印文，其字形雷同，亦可見該分割協議書\n    之蔣紹文印文，與印鑑證明之印文應屬同一。至原告嗣後雖\n    於言詞辯論時始質疑印鑑證明與分割協議書之印文顯然不同\n    ，印鑑證明之章是假的等語，並提出伊自行放大印鑑證明及\n    分割協議書之印文影本附卷供參，然該放大影本既為原告自\n    行重複放大，則在多次影印過程中，其紙張有無壓平、墨水\n    濃度深淺，均可能影響最後字體之樣式，此從原告所提之其\n    上蓋有「157822」編號之印鑑證明影本，經核對與本院向前\n    開三民地政事務所所調取之印鑑證明，其中字體墨色深淺有\n    別，以致原告所提印鑑證明中「蔣」字之「寸」、及「紹」\n    字之「糸」部呈現不連續，而與本院調取之印鑑證明明顯不\n    同。以此，原告僅以伊將印鑑證明及分割協議書上之印文放\n    大比對而有差異為由，主張分割協議書上之印文非伊所有，\n    已難採信。\n  (二)且查，當初辦理分割協議登記時，除提出分割協議書外，並\n    有原告之印鑑證明，已見前述，並據證人即辦理蔣錫將移產\n    分割繼承登記之代書蔡凱文證述：「（蔣錫將所有之遺產於\n    高雄市○○區○○路86巷3號房屋及高雄市○○區○○街5巷\n    12號四樓之3房屋及土地等，當初辦理遺產分割協議，是否\n    為你處理？）是的，當時應該是被告委託我辦理的。（兩造\n    有無訂立遺產分割協議？）有。（遺產分割協議有無經過兩\n    造及其他繼承人同意？）他們各蓋印鑑章並出具印鑑證明給\n    我。（訂立分割協議書時，你有無在場？）沒有。（章是由\n    何人蓋的？）是被告當時把原告的印鑑當場拿給我，並說是\n    原告委託他拿給我辦理的。（原告是否知道你去辦理分割遺\n    產的登記？）我不確定。（當時有無聯絡原告？）當時原告\n    不在高雄，且一般情形我們認為有出具印鑑證明，並交付印\n    鑑章，我們就認為有經過本人的同意，否則不會隨便將印鑑\n    章及印鑑證明交給別人。（辦理分割遺產登記後，原告有無\n    向你表示意見？）沒有。（是否直接拿到原告的印鑑章，或\n    是文件上面已經蓋好印鑑印文？）被告直接拿原告的印鑑章\n    給我，說是原告委託他拿給我的，我是當著被告的面確認文\n    件沒有問題後，我當場蓋章並將原告的印鑑章交還給被告。\n    （該分割協議書的內容，是否為你所繕打？）是的，但我是\n    依據兩造及其他繼承人的意思所繕打，我跟三個繼承人並沒\n    有全部見面，我只有與被告接觸。」等語，依證人所述，系\n    爭分割協議書固係由渠繕打，然當初被告乃將原告印鑑章及\n    印鑑證明交付證人蓋印後將印鑑章交還被告，則系爭分割協\n    議書業據附上原告之印鑑證明，已可認定。而原告已不否認\n    該印鑑證明為伊所有，雖伊就該印鑑證明如何而來，辯稱：\n    不知道，因被告把伊從台北叫回高雄，說母親中風等語；惟\n    依卷附原告申辦印鑑證明即89年8月14日當時之有效之印鑑\n    登記辦法（嗣已於98年10月13日修正）第7條規定：「依第\n    四條第一項規定申請印鑑證明應由當事人或其受委任人填具\n    申請書(格式九)並繳驗國民身分證，申請辦理。由其受委任\n    人申請者，並應附繳委任書。」以此，關於當初辦理系爭遺\n    產分割協議所附之原告印鑑證明，無論係原告本人親辦，或\n    由原告出具國民身分證委由他人辦理，無論何者，均可認定\n    該印鑑證明乃經原告同意所申辦；衡情，以印鑑證明乃係為\n    該印文係本人所有之憑據，其關係重大，非有重要事項，一\n    般人當不至無故辦理，可見原告申辦該印鑑證明，當出於特\n    殊目的。再觀兩造被繼承人蔣錫將係於89年8月5日死亡，原\n    告之印鑑證明於89年8月14日申辦，兩造之分割協議書訂立\n    日期為89年10月5日，而前述之系爭愛國路房地係於89年10\n    月25日登記予被告名下，系爭德安街房地亦於89年10月30日\n    以分割繼承為原告登記予被告名下，凡此有原告所提高雄市\n    三民地政事務所網路申領異動索引、高雄市新興地政事務所\n    網路申領異動索引各1件為證，並經本院分別向高雄市政府\n    地政局三民地政事務所、及新興地政事務所調取前開之分割\n    繼承所有權移轉登記文件，以原告之印鑑證明申辦日期介於\n    蔣錫將死亡之後，及兩造訂立分割協議書及辦理分割繼承登\n    記之前，則依上開事件之順序，已可推論原告當係於蔣錫將\n    死亡後，為辦理分割協議，而申辦印鑑證明，再憑以交付被\n    告完成遺產繼承之事宜，是原告所辯不知印鑑如何而來等語\n    ，顯為避重就輕之詞，自不可信。\n  (三)何況被告於依繼承登記取得蔣錫將之不動產後，已分別於90\n    年3月將系爭愛國路房地出售予訴外人黃花，並於90年3月8\n    日辦理所有權移轉登記，嗣又於94年3月5日將系爭德安街房\n    地出售予訴外人郭天順，並於94年4月19日辦理所有權移轉\n    登記予郭芳廷，凡此業為原告提出高雄市三民地政事務所網\n    路申領異動索引、高雄市新興地政事務所網路申領異動索引\n    、苓雅區○○段第1435地號土地登記第二類謄本等件，及被\n    告提出之不動產買賣契約書附卷供參。而原告之戶籍原設於\n    系爭德安街房屋之上，後於94年3月25日遷移至中壢，此亦\n    有原告之戶籍謄本供參，而原告亦自承伊於戶籍仍設於德安\n    街地址時即已知悉被告將前開房地出售之事實，則對照前述\n    經過，可見原告至遲於94年3月25日以前即已知悉被告出售\n    遺產之事，乃迄至99年7月29日始起訴請求返還不當得利，\n    期間相距5年，是參照原告遲未起訴或發存證信函之事實，\n    甚且於被告將德安街房地出售之前將戶籍遷移他處，可見原\n    告對於出售房地一事，不僅知情，且有配合被告而遷移戶籍\n    之意。\n  (四)且被告另抗辯：蔣錫將留下多筆銀行貸款之債務，養母蔣張\n    惠咥中風居往療養院，無力負擔貸款利息，原告負債累累，\n    亦無力支付多筆銀行貸款本息，故協議由其一人繼承二筆不\n    動產及存款，其為早日清償蔣錫將遺留債務，先於90年3月\n    將系爭愛國路房地賣給第三人黃花，由黃花向中國信託銀行\n    貸款清償抵押貸款426,764元，嗣於94年3月間將系爭德安街\n    房地出售予第三人郭天順，約定由買方負責清償該屋之二筆\n    抵押貸款，因郭天順指定登記給郭芳廷，郭芳廷即向中國信\n    託銀行貸款並設定抵押，待中國信託銀行撥款代為清償前二\n    筆貸款餘額412,036元及1,560,027元後，再由高雄銀行塗銷\n    抵押權登記，故以上三筆貸款債務，平日係以其帳戶轉帳繳\n    交本息，於房屋出售時，則由買主貸款以賣屋價金償還等語\n    。查，蔣錫將死亡當時，遺有三筆貸款，分別為：1.積欠高\n    雄銀行大發分行金額491,652元；2.積欠高雄銀行大發分行\n    金額479,749元；此二筆貸款均由被告於高雄銀行大發分行\n    所開設帳戶扣款繳納本金及利息，並於90年3月16日由中國\n    信託三民分行匯款清償第1.筆貸款，及於94年4月20日由中\n    國信託高雄分行匯款清償第2.筆貸款；此有高雄銀行股份有\n    限公司大發分行100年3月30日高銀大發字第10000052號函附\n    卷可稽；另第3.筆為國宅貸款180萬元，並於94年4月20日由\n    中國信託帳戶匯入，償還金額為1,560,027元，此亦有高雄\n    銀行股份有限公司100年4月28日高銀營字第1000002937號函\n    可參。從上所述，其中蔣錫將所遺留之第1.、2.筆借款均係\n    由被告清償，另從系爭愛國路房地係於90年3月間出售，並\n    於3月8日移轉登記，其與第1.筆貸款完全清償之時間僅相差\n    8日；而系爭德安街之房地於94年3月5日出售，並於94年4月\n    19日移轉登記，此亦與第2.、3.筆貸款之完全清償日期94年\n    4月20日亦密切相近，則參照上開事實，可認被告所辯蔣錫\n    將所遺留債務由其負責清償，嗣後並由其將系爭愛國路、德\n    安街房地出售後以所得價金清償款項等語，亦可認定。\n  (五)綜合前述，本件從蔣錫將遺產辦理分割協議登記時，已有原\n    告之印鑑證明及印鑑章，而原告就印鑑證明之由來亦答以不\n    知情，則衡諸常情，該印鑑證明當係原告申辦或由原告授意\n    辦理，而以印鑑證明之申辦時間乃在蔣錫將死亡後數日所為\n    ，且該印鑑證明申辦後未久即經代書辦理蔣錫將遺產分割協\n    議登記，更可見該印鑑證明當係為辦理分割協議而申辦；參\n    以被告於94年3月5日將德安街房地出售後，原告隨即於同月\n    25日將原設籍於德安街之戶籍遷至中壢，並參原告自承於戶\n    籍仍設於德安街之時即知被告將房地出售之事，可見原告對\n    於被告出售蔣錫將所留遺產一事，不僅知情，且亦配合辦理\n    遷移戶籍，而從原告自該時起迄今起訴時之5年餘時間均未\n    曾異議，乃於時隔5年餘又表示被告未得伊同意變賣父親遺\n    產，自不合理。再參蔣錫將所遺留債務係由被告償還，嗣並\n    以出售愛國路、德安街房地之價金償還，益可見被告所辯當\n    初繼承人協議由其繼承不動產及存款，並將房地出售後清償\n    貸款之主張，為可採信。依上，則原告對於本件系爭分割協\n    議當已知悉並同意，伊主張被告偽造分割協議書辦理繼承登\n    記，並變賣父親遺產，殊不可信。茲被告所辦理遺產分割，\n    既係本於繼承人之協議，則伊取得蔣錫將之遺產，自非無法\n    律上原因，從而原告以被告無法律上原因而受利益，致伊及\n    共同繼承人蔣張惠咥受有損害，據以依不當得利之法律關係\n    請求被告返還相當遺產三分之一之利益，於法無據，應予駁\n    回。\n五、本件法律關係已臻明確，兩造其餘之主張、抗辯，於本件之\n    認定不生影響，爰不再一一論述；又被告聲請蔣張惠咥到庭\n    訊問，惟依渠所證，語涉：「．．．我先生現在還在，住在\n    小港，他死了是死了，但他的靈還在，他天天來看我，我還\n    弄飯給他吃，我先生現在住在小港。（有無去找妳先生？）\n    我天天看得見。（如何看見的？）我是天上聖母，我是神，\n    也是人。」等語無倫次之言語，是渠之心神狀況不佳，已難\n    為有正確證述，則渠所為其餘證詞自難採認，併此敘明。\n六、據上論結，本件原告之訴為無理由，依民事訴訟法第78條，\n    判決如主文。",
    "reason": "一、原告起訴主張︰\n  (一)原告與被告為養兄妹關係，兩造之養父即被繼承人蔣錫將於\n    民國89年8月5日過世，遺留有如下之遺產：1.座落於高雄市\n    ○○區○○段29地號土地一筆，地目建，面積57.97平方公\n    尺，持分全部，及地上房屋546建號，門牌三民區○○路86\n    巷3號，持分全部（下稱系爭愛國路房地）；2.座落高雄市\n    ○○區○○段1435地號土地一筆，地目建，面積4,453平方\n    公尺，持分611/100000，及地上房屋1969建號，門牌苓雅區\n    ○○街5巷12號4樓之3，持分全部（下稱系爭德安街房地）\n    ；3.臺灣銀行高雄分行優惠儲蓄存款新臺幣(下同)349,000\n    元；4.臺灣銀行高雄分行活期儲蓄存款850元；5.高雄市第\n    三信用合作社三多分社綜合存款7,252元；6.現金10,000元\n    。按民法第1147條、第1151條之規定，上述1.至6.之財產原\n    屬兩造與被繼承人之配偶蔣張惠咥所繼承之公同共有遺產，\n    然被告在明知原告及蔣張惠咥長年均患有嚴重精神疾病、欠\n    缺辨別事理能力之情形下，竟於89年10月間未經原告及蔣張\n    惠咥之同意，持偽造之分割協議書向地政機關辦理由其單獨\n    繼承上開二筆房地，並私吞所有款項，嗣於90年3月及94年4\n    月分別將上開二筆房地出售並換取價款予以獨占，致原告及\n    蔣張惠咥受有損害，原告自得依民法第179條、第182條第2\n    項前段不當得利之規定，請求被告給付相當於遺產三分之一\n    之利益。\n  (二)按當事人互相表示意思一致者，無論其為明示或默示，契約\n    即為成立，民法第153條第1項定有明文；次按當事人主張有\n    利於己之事實者，就其事實有舉證之責任，民事訴訟法第27\n    7條本文亦定有明文；又按解釋意思表示，應探求當事人之\n    真意，不得拘泥於所用之辭句，為民法第98條所明定，故不\n    得逕以分割協議書上蓋用原告之印鑑章，即認定兩造間確有\n    上開分割協議，且上開分割協議之最大利益者係被告而非原\n    告，況據蔡凱文代書證述本件分割協議辦理過程僅接觸到被\n    告，一切都是聽被告敘述等語，原告及訴外人蔣張惠咥是否\n    確實均已達成上開分割協議之內容，尚非無疑，揆諸前開說\n    明，被告應先就分割協議是否確實存在盡舉證之責；再者，\n    分割協議書上的印章，與原告的印鑑章看似雷同，實則經放\n    大比對後，二者字體明顯不同，印鑑證明章是遭偽造、用美\n    工刀一筆一筆刻出來的，因為筆畫沒有粗細之分，分割協議\n    書上才是真正的章。\n  (三)原告是有次看到報紙刊登愛國路附近淹大水的消息，打電話\n    問被告愛國路房子有無淹水，被告稱老早就以120萬元將房\n    子出售，當時原告德安街的戶籍還在，應是94年3月之前的\n    事，原告知道房子遭賤價出售很生氣，被告當時稱要養母親\n    蔣張惠咥，原告以為被告每月要支付2萬元照顧母親，後來\n    才知蔣錫將過世後，母親是眷屬每月可領14,000元左右；原\n    告從未對被告提告，也未以書面、存證信函等方式表示異議\n    ，係因原告從未有分家的觀念，認為二棟房子和父親的存款\n    都在，原告跟被告可以兩邊房子輪流住，而原告於94年間將\n    戶籍自高雄市○○街遷出時，固不否認已知悉房屋由被告出\n    賣，但亦不得以原告至99年間始訴請被告給付不當得利，而\n    逕認被告當時有同意分割之協議，蓋原告多年來因病居住於\n    桃園地區之療養院，原告既無能力自行訴訟，復無資力委任\n    律師為己主張權利，直至創設法律扶助制度後，原告方得以\n    透過法律扶助基金會之協助主張權利，是不得以原告多年來\n    均未主張權利，而逕認原告已默示同意分割協議。\n  (四)茲因就上開二筆房地遭被告不法變賣所生損害賠償數額，恐\n    需待鈞院鑑價或調查後始得確定，是請求鈞院允許原告就上\n    開二筆房地先以被告於89年辦理繼承登記時，主管機關所核\n    定價額列計，待鈞院鑑價或調查確定上開二筆房地之價值後\n    ，再由原告依民事訴訟法第244條第4項規定為補充聲明，以\n    作最終請求金額之確定。是原告起訴金額先以上開二筆房地\n    核定價額加上(一)3.至6.遺產遭被告侵害，原告按應繼分三分\n    之一比例計算可得主張之金額為1,581,620元。再被告係於\n    89年10月5日偽造分割協議書後，於同年10月25日及10月30\n    日分別完成二筆房地之繼承登記，至此損害(惡意不當得利)\n    已然發生，原告自得併請求損害發生時即89年10月31日起至\n    清償日止，按年息百分之五計算之利息。\n  (五)聲明：\n  1.被告應給付原告新臺幣1,581,620元，及自89年10月31日起\n    至清償日止，按年息百分之五計算之利息。\n  2.原告願供擔保請准宣告假執行。\n二、被告則辯以：\n  (一)本件被告取得遺產，係因原告自行同意放棄繼承不動產及存\n    款之權利，故被告取得遺產有正當法律上原因，自不符民法\n    不當得利之要件。\n  (二)兩造養父即被繼承人蔣錫將於89年8月5日死亡，雖留下愛國\n    路與德安街二筆房地及存款357,102元，惟亦留下多筆高雄\n    銀行之貸款債務，當時原告因積欠銀行及地下錢莊債務，擔\n    心繼承上開被繼承人之遺產後遭債權銀行及地下錢莊拍賣，\n    致影響被告及養母蔣張惠咥之權利，且被繼承人蔣錫將亦留\n    下多筆銀行貸款之債務，養母蔣張惠咥中風居往療養院，無\n    力負擔貸款利息，原告負債累累，亦無力支付多筆銀行貸款\n    本息，故協議由被告一人繼承二筆不動產及存款，當時原告\n    亦自行提供印鑑證明與印鑑章等相關資料交由被告辦理繼承\n    事宜，被告即依協議內容委託蔡凱文代書辦理繼承登記事宜\n    ，並無偽造或不法之情事。\n  (三)被繼承人蔣錫將所遺留上開二筆不動產都有貸款，系爭德安\n    街房地有公教貸款180萬元(由高雄市政府委託高雄銀行辦理\n    )及高雄銀行貸款50萬元，系爭愛國路房地則有56萬元的貸\n    款，被告所提被繼承人蔣錫將之高雄銀行授信明細查詢單記\n    載30萬元、20萬元，是第一筆50萬元換貸而來，第四筆、第\n    五筆是比較早的資料，合併之後又增貸32萬元，變成56萬元\n    ，此三筆債務均由被告以其高雄銀行帳戶000000000000轉帳\n    繳交，有高雄銀行出具之存款對帳單為證，被告為早日清償\n    蔣錫將遺留債務，先於90年3月將系爭愛國路房地賣給第三\n    人黃花，由黃花向中國信託銀行貸款清償抵押貸款426,764\n    元；嗣於94年3月間將德安街房地出售予第三人郭天順，據\n    被告所提該不動產買賣契約書第六條稅費負擔第四點，約定\n    由買方負責清償該屋之二筆抵押貸款(即180萬元公教貸款及\n    50萬元貸款)，因郭天順指定登記給郭芳廷，郭芳廷即向中\n    國信託銀行貸款並設定抵押，待中國信託銀行撥款代為清償\n    前二筆貸款餘額412,036元及1,560,027元後，再由高雄銀行\n    塗銷抵押權登記，故以上三筆貸款債務，平日係以被告帳戶\n    轉帳繳交本息，於房屋出售時，則由買主貸款以賣屋價金償\n    還。\n  (四)原告知悉被告將房地出售之事，並配合於94年3月25日將戶\n    口自德安街地址遷出，是原告起訴主張未與被告協議分割遺\n    產，協議內容係被告偽造云云，顯與事實不符，亦有違常情\n    ，印鑑證明係原告提供給被告辦理分割事宜，當時因原告積\n    欠很多卡債，名下又無財產，原告也無法照顧養母，所以原\n    告同意將不動產登記給被告，被繼承人蔣錫將過世後，原告\n    就遺產分割及由被告負擔相關貸款之繳納及清償等事均知情\n    ，卻從未表示異議，從未要求將遺產分割或出賣後分配價金\n    ，且就被告如何取得原告印鑑章，也提不出具體說法，土地\n    及房屋登記為公示資料，任何人隨時可調取，原告之戶籍更\n    先後遷入此二筆房屋，當不得諉稱不知，況被告賣出系爭德\n    安街房地時，還要求原告配合將伊戶口遷走，足證原告當時\n    同意全部遺產及債務均由被告繼承，僅因伊目前窮困潦倒，\n    無經濟來源，欲藉10年前繼承之事向被告要錢，原告多年來\n    經常向被告要錢，被告有餘力時會匯錢給原告，詎原告汙衊\n    被告偽造文書並提起本件訴訟，請鈞院明察。\n  (五)聲明：原告之訴及假執行之聲請均駁回。\n三、兩造不爭執之事實：\n  (一)原告與被告為養兄妹關係，兩造之養父即被繼承人蔣錫將於\n    89年8月5日過世，遺留有遺產：1.系爭愛國路房地；2.系爭\n    德安街房地；3.存款約357,102元。\n  (二)被繼承人蔣錫將死亡後，渠遺產由兩造及蔣錫將之配偶蔣張\n    惠咥繼承，應繼分各三分之一。\n四、得心證之理由：本件原告依不當得利之法律關係，請求被告\n    應返還相當於蔣錫將遺產三分之一之利益，主要是以被告未\n    經伊及蔣張惠咥之同意，持偽造之分割協議書向地政機關辦\n    理由被告單獨繼承遺產中之二筆房地，私吞所有款項，並於\n    90年3月及94年4月分別將上開二筆房地出售換取價款予以獨\n    占，致伊及蔣張惠咥受有損害為主張之依據，惟被告則否認\n    有偽造分割協議書之事實，並辯以：其取得遺產，係因原告\n    自行同意放棄繼承不動產及存款之權利等語，是本件原告之\n    主張是否有據，應以關於蔣錫將之遺產分割協議書是否經兩\n    造同意簽立而認定，茲審酌如下：\n  (一)查蔣錫將所遺留之系爭愛國路房地，業於89年10月25日以分\n    割繼承為原因登記予被告名下；另系爭德安街房地亦於89年\n    10月30日以分割繼承為原告登記被告名下，凡此有原告所提\n    高雄市三民地政事務所網路申領異動索引、高雄市新興地政\n    事務所網路申領異動索引各1件為證，並經本院分別向高雄\n    市政府地政局三民地政事務所、及新興地政事務所調取前開\n    之分割繼承所有權移轉登記文件，分別經三民地政事務所以\n    100年2月15日高市地民價字第1000001507號函檢附該區○○\n    段29地號土地，及其上546建號，門牌三民區○○路86巷3號\n    建物之所有權移轉登記資料，及新興地政事務所以100年2月\n    15日高市地新價字第1000001374號函檢附苓雅區○○段1435\n    地號土地，及其上苓雅區○○街5巷12號4樓之3建物之移轉\n    登記資料附卷供參。而上開二份回函中之移轉登記資料均附\n    有原告(原名蔣紹武，嗣於93年2月27日更名為蔣瑞福)、被\n    告及蔣張惠咥所簽訂之分割協議書、印鑑證明。而原告對於\n    分割協議書及印鑑證明上之印鑑章式樣相似，初亦坦承：分\n    割協議書上之印章與原告印鑑章看起來十分雷同等語，惟又\n    稱對於協議書上所蓋之章是否為伊所有沒有印象等語，可見\n    原告就分割協議書關於原告之章與印鑑證明之章為同一一事\n    初亦不否認。且核對上開地政事務所函附本院所附之分割協\n    議書、印鑑證明、土地登記申請書（均影本），其上關於原\n    告更名前蔣紹武之印文，其字形雷同，亦可見該分割協議書\n    之蔣紹文印文，與印鑑證明之印文應屬同一。至原告嗣後雖\n    於言詞辯論時始質疑印鑑證明與分割協議書之印文顯然不同\n    ，印鑑證明之章是假的等語，並提出伊自行放大印鑑證明及\n    分割協議書之印文影本附卷供參，然該放大影本既為原告自\n    行重複放大，則在多次影印過程中，其紙張有無壓平、墨水\n    濃度深淺，均可能影響最後字體之樣式，此從原告所提之其\n    上蓋有「157822」編號之印鑑證明影本，經核對與本院向前\n    開三民地政事務所所調取之印鑑證明，其中字體墨色深淺有\n    別，以致原告所提印鑑證明中「蔣」字之「寸」、及「紹」\n    字之「糸」部呈現不連續，而與本院調取之印鑑證明明顯不\n    同。以此，原告僅以伊將印鑑證明及分割協議書上之印文放\n    大比對而有差異為由，主張分割協議書上之印文非伊所有，\n    已難採信。\n  (二)且查，當初辦理分割協議登記時，除提出分割協議書外，並\n    有原告之印鑑證明，已見前述，並據證人即辦理蔣錫將移產\n    分割繼承登記之代書蔡凱文證述：「（蔣錫將所有之遺產於\n    高雄市○○區○○路86巷3號房屋及高雄市○○區○○街5巷\n    12號四樓之3房屋及土地等，當初辦理遺產分割協議，是否\n    為你處理？）是的，當時應該是被告委託我辦理的。（兩造\n    有無訂立遺產分割協議？）有。（遺產分割協議有無經過兩\n    造及其他繼承人同意？）他們各蓋印鑑章並出具印鑑證明給\n    我。（訂立分割協議書時，你有無在場？）沒有。（章是由\n    何人蓋的？）是被告當時把原告的印鑑當場拿給我，並說是\n    原告委託他拿給我辦理的。（原告是否知道你去辦理分割遺\n    產的登記？）我不確定。（當時有無聯絡原告？）當時原告\n    不在高雄，且一般情形我們認為有出具印鑑證明，並交付印\n    鑑章，我們就認為有經過本人的同意，否則不會隨便將印鑑\n    章及印鑑證明交給別人。（辦理分割遺產登記後，原告有無\n    向你表示意見？）沒有。（是否直接拿到原告的印鑑章，或\n    是文件上面已經蓋好印鑑印文？）被告直接拿原告的印鑑章\n    給我，說是原告委託他拿給我的，我是當著被告的面確認文\n    件沒有問題後，我當場蓋章並將原告的印鑑章交還給被告。\n    （該分割協議書的內容，是否為你所繕打？）是的，但我是\n    依據兩造及其他繼承人的意思所繕打，我跟三個繼承人並沒\n    有全部見面，我只有與被告接觸。」等語，依證人所述，系\n    爭分割協議書固係由渠繕打，然當初被告乃將原告印鑑章及\n    印鑑證明交付證人蓋印後將印鑑章交還被告，則系爭分割協\n    議書業據附上原告之印鑑證明，已可認定。而原告已不否認\n    該印鑑證明為伊所有，雖伊就該印鑑證明如何而來，辯稱：\n    不知道，因被告把伊從台北叫回高雄，說母親中風等語；惟\n    依卷附原告申辦印鑑證明即89年8月14日當時之有效之印鑑\n    登記辦法（嗣已於98年10月13日修正）第7條規定：「依第\n    四條第一項規定申請印鑑證明應由當事人或其受委任人填具\n    申請書(格式九)並繳驗國民身分證，申請辦理。由其受委任\n    人申請者，並應附繳委任書。」以此，關於當初辦理系爭遺\n    產分割協議所附之原告印鑑證明，無論係原告本人親辦，或\n    由原告出具國民身分證委由他人辦理，無論何者，均可認定\n    該印鑑證明乃經原告同意所申辦；衡情，以印鑑證明乃係為\n    該印文係本人所有之憑據，其關係重大，非有重要事項，一\n    般人當不至無故辦理，可見原告申辦該印鑑證明，當出於特\n    殊目的。再觀兩造被繼承人蔣錫將係於89年8月5日死亡，原\n    告之印鑑證明於89年8月14日申辦，兩造之分割協議書訂立\n    日期為89年10月5日，而前述之系爭愛國路房地係於89年10\n    月25日登記予被告名下，系爭德安街房地亦於89年10月30日\n    以分割繼承為原告登記予被告名下，凡此有原告所提高雄市\n    三民地政事務所網路申領異動索引、高雄市新興地政事務所\n    網路申領異動索引各1件為證，並經本院分別向高雄市政府\n    地政局三民地政事務所、及新興地政事務所調取前開之分割\n    繼承所有權移轉登記文件，以原告之印鑑證明申辦日期介於\n    蔣錫將死亡之後，及兩造訂立分割協議書及辦理分割繼承登\n    記之前，則依上開事件之順序，已可推論原告當係於蔣錫將\n    死亡後，為辦理分割協議，而申辦印鑑證明，再憑以交付被\n    告完成遺產繼承之事宜，是原告所辯不知印鑑如何而來等語\n    ，顯為避重就輕之詞，自不可信。\n  (三)何況被告於依繼承登記取得蔣錫將之不動產後，已分別於90\n    年3月將系爭愛國路房地出售予訴外人黃花，並於90年3月8\n    日辦理所有權移轉登記，嗣又於94年3月5日將系爭德安街房\n    地出售予訴外人郭天順，並於94年4月19日辦理所有權移轉\n    登記予郭芳廷，凡此業為原告提出高雄市三民地政事務所網\n    路申領異動索引、高雄市新興地政事務所網路申領異動索引\n    、苓雅區○○段第1435地號土地登記第二類謄本等件，及被\n    告提出之不動產買賣契約書附卷供參。而原告之戶籍原設於\n    系爭德安街房屋之上，後於94年3月25日遷移至中壢，此亦\n    有原告之戶籍謄本供參，而原告亦自承伊於戶籍仍設於德安\n    街地址時即已知悉被告將前開房地出售之事實，則對照前述\n    經過，可見原告至遲於94年3月25日以前即已知悉被告出售\n    遺產之事，乃迄至99年7月29日始起訴請求返還不當得利，\n    期間相距5年，是參照原告遲未起訴或發存證信函之事實，\n    甚且於被告將德安街房地出售之前將戶籍遷移他處，可見原\n    告對於出售房地一事，不僅知情，且有配合被告而遷移戶籍\n    之意。\n  (四)且被告另抗辯：蔣錫將留下多筆銀行貸款之債務，養母蔣張\n    惠咥中風居往療養院，無力負擔貸款利息，原告負債累累，\n    亦無力支付多筆銀行貸款本息，故協議由其一人繼承二筆不\n    動產及存款，其為早日清償蔣錫將遺留債務，先於90年3月\n    將系爭愛國路房地賣給第三人黃花，由黃花向中國信託銀行\n    貸款清償抵押貸款426,764元，嗣於94年3月間將系爭德安街\n    房地出售予第三人郭天順，約定由買方負責清償該屋之二筆\n    抵押貸款，因郭天順指定登記給郭芳廷，郭芳廷即向中國信\n    託銀行貸款並設定抵押，待中國信託銀行撥款代為清償前二\n    筆貸款餘額412,036元及1,560,027元後，再由高雄銀行塗銷\n    抵押權登記，故以上三筆貸款債務，平日係以其帳戶轉帳繳\n    交本息，於房屋出售時，則由買主貸款以賣屋價金償還等語\n    。查，蔣錫將死亡當時，遺有三筆貸款，分別為：1.積欠高\n    雄銀行大發分行金額491,652元；2.積欠高雄銀行大發分行\n    金額479,749元；此二筆貸款均由被告於高雄銀行大發分行\n    所開設帳戶扣款繳納本金及利息，並於90年3月16日由中國\n    信託三民分行匯款清償第1.筆貸款，及於94年4月20日由中\n    國信託高雄分行匯款清償第2.筆貸款；此有高雄銀行股份有\n    限公司大發分行100年3月30日高銀大發字第10000052號函附\n    卷可稽；另第3.筆為國宅貸款180萬元，並於94年4月20日由\n    中國信託帳戶匯入，償還金額為1,560,027元，此亦有高雄\n    銀行股份有限公司100年4月28日高銀營字第1000002937號函\n    可參。從上所述，其中蔣錫將所遺留之第1.、2.筆借款均係\n    由被告清償，另從系爭愛國路房地係於90年3月間出售，並\n    於3月8日移轉登記，其與第1.筆貸款完全清償之時間僅相差\n    8日；而系爭德安街之房地於94年3月5日出售，並於94年4月\n    19日移轉登記，此亦與第2.、3.筆貸款之完全清償日期94年\n    4月20日亦密切相近，則參照上開事實，可認被告所辯蔣錫\n    將所遺留債務由其負責清償，嗣後並由其將系爭愛國路、德\n    安街房地出售後以所得價金清償款項等語，亦可認定。\n  (五)綜合前述，本件從蔣錫將遺產辦理分割協議登記時，已有原\n    告之印鑑證明及印鑑章，而原告就印鑑證明之由來亦答以不\n    知情，則衡諸常情，該印鑑證明當係原告申辦或由原告授意\n    辦理，而以印鑑證明之申辦時間乃在蔣錫將死亡後數日所為\n    ，且該印鑑證明申辦後未久即經代書辦理蔣錫將遺產分割協\n    議登記，更可見該印鑑證明當係為辦理分割協議而申辦；參\n    以被告於94年3月5日將德安街房地出售後，原告隨即於同月\n    25日將原設籍於德安街之戶籍遷至中壢，並參原告自承於戶\n    籍仍設於德安街之時即知被告將房地出售之事，可見原告對\n    於被告出售蔣錫將所留遺產一事，不僅知情，且亦配合辦理\n    遷移戶籍，而從原告自該時起迄今起訴時之5年餘時間均未\n    曾異議，乃於時隔5年餘又表示被告未得伊同意變賣父親遺\n    產，自不合理。再參蔣錫將所遺留債務係由被告償還，嗣並\n    以出售愛國路、德安街房地之價金償還，益可見被告所辯當\n    初繼承人協議由其繼承不動產及存款，並將房地出售後清償\n    貸款之主張，為可採信。依上，則原告對於本件系爭分割協\n    議當已知悉並同意，伊主張被告偽造分割協議書辦理繼承登\n    記，並變賣父親遺產，殊不可信。茲被告所辦理遺產分割，\n    既係本於繼承人之協議，則伊取得蔣錫將之遺產，自非無法\n    律上原因，從而原告以被告無法律上原因而受利益，致伊及\n    共同繼承人蔣張惠咥受有損害，據以依不當得利之法律關係\n    請求被告返還相當遺產三分之一之利益，於法無據，應予駁\n    回。\n五、本件法律關係已臻明確，兩造其餘之主張、抗辯，於本件之\n    認定不生影響，爰不再一一論述；又被告聲請蔣張惠咥到庭\n    訊問，惟依渠所證，語涉：「．．．我先生現在還在，住在\n    小港，他死了是死了，但他的靈還在，他天天來看我，我還\n    弄飯給他吃，我先生現在住在小港。（有無去找妳先生？）\n    我天天看得見。（如何看見的？）我是天上聖母，我是神，\n    也是人。」等語無倫次之言語，是渠之心神狀況不佳，已難\n    為有正確證述，則渠所為其餘證詞自難採認，併此敘明。\n六、據上論結，本件原告之訴為無理由，依民事訴訟法第78條，\n    判決如主文。"
  },
  "search": "臺灣臺南地方法院民事判決100年度家訴字第27號原告蔣瑞福訴訟代理人黃郁婷律師陳建欽律師被告蔣育瑛訴訟代理人陳慈鳳律師上列當事人間請求返還不當得利事件，本院判決如下：主文原告之訴及假執行之聲請均駁回。訴訟費用由原告負擔。事實及理由一、原告起訴主張︰(一)原告與被告為養兄妹關係，兩造之養父即被繼承人蔣錫將於民國89年8月5日過世，遺留有如下之遺產：1.座落於高雄市○○區○○段29地號土地一筆，地目建，面積57.97平方公尺，持分全部，及地上房屋546建號，門牌三民區○○路86巷3號，持分全部（下稱系爭愛國路房地）；2.座落高雄市○○區○○段1435地號土地一筆，地目建，面積4,453平方公尺，持分611/100000，及地上房屋1969建號，門牌苓雅區○○街5巷12號4樓之3，持分全部（下稱系爭德安街房地）；3.臺灣銀行高雄分行優惠儲蓄存款新臺幣(下同)349,000元；4.臺灣銀行高雄分行活期儲蓄存款850元；5.高雄市第三信用合作社三多分社綜合存款7,252元；6.現金10,000元。按民法第1147條、第1151條之規定，上述1.至6.之財產原屬兩造與被繼承人之配偶蔣張惠咥所繼承之公同共有遺產，然被告在明知原告及蔣張惠咥長年均患有嚴重精神疾病、欠缺辨別事理能力之情形下，竟於89年10月間未經原告及蔣張惠咥之同意，持偽造之分割協議書向地政機關辦理由其單獨繼承上開二筆房地，並私吞所有款項，嗣於90年3月及94年4月分別將上開二筆房地出售並換取價款予以獨占，致原告及蔣張惠咥受有損害，原告自得依民法第179條、第182條第2項前段不當得利之規定，請求被告給付相當於遺產三分之一之利益。(二)按當事人互相表示意思一致者，無論其為明示或默示，契約即為成立，民法第153條第1項定有明文；次按當事人主張有利於己之事實者，就其事實有舉證之責任，民事訴訟法第277條本文亦定有明文；又按解釋意思表示，應探求當事人之真意，不得拘泥於所用之辭句，為民法第98條所明定，故不得逕以分割協議書上蓋用原告之印鑑章，即認定兩造間確有上開分割協議，且上開分割協議之最大利益者係被告而非原告，況據蔡凱文代書證述本件分割協議辦理過程僅接觸到被告，一切都是聽被告敘述等語，原告及訴外人蔣張惠咥是否確實均已達成上開分割協議之內容，尚非無疑，揆諸前開說明，被告應先就分割協議是否確實存在盡舉證之責；再者，分割協議書上的印章，與原告的印鑑章看似雷同，實則經放大比對後，二者字體明顯不同，印鑑證明章是遭偽造、用美工刀一筆一筆刻出來的，因為筆畫沒有粗細之分，分割協議書上才是真正的章。(三)原告是有次看到報紙刊登愛國路附近淹大水的消息，打電話問被告愛國路房子有無淹水，被告稱老早就以120萬元將房子出售，當時原告德安街的戶籍還在，應是94年3月之前的事，原告知道房子遭賤價出售很生氣，被告當時稱要養母親蔣張惠咥，原告以為被告每月要支付2萬元照顧母親，後來才知蔣錫將過世後，母親是眷屬每月可領14,000元左右；原告從未對被告提告，也未以書面、存證信函等方式表示異議，係因原告從未有分家的觀念，認為二棟房子和父親的存款都在，原告跟被告可以兩邊房子輪流住，而原告於94年間將戶籍自高雄市○○街遷出時，固不否認已知悉房屋由被告出賣，但亦不得以原告至99年間始訴請被告給付不當得利，而逕認被告當時有同意分割之協議，蓋原告多年來因病居住於桃園地區之療養院，原告既無能力自行訴訟，復無資力委任律師為己主張權利，直至創設法律扶助制度後，原告方得以透過法律扶助基金會之協助主張權利，是不得以原告多年來均未主張權利，而逕認原告已默示同意分割協議。(四)茲因就上開二筆房地遭被告不法變賣所生損害賠償數額，恐需待鈞院鑑價或調查後始得確定，是請求鈞院允許原告就上開二筆房地先以被告於89年辦理繼承登記時，主管機關所核定價額列計，待鈞院鑑價或調查確定上開二筆房地之價值後，再由原告依民事訴訟法第244條第4項規定為補充聲明，以作最終請求金額之確定。是原告起訴金額先以上開二筆房地核定價額加上(一)3.至6.遺產遭被告侵害，原告按應繼分三分之一比例計算可得主張之金額為1,581,620元。再被告係於89年10月5日偽造分割協議書後，於同年10月25日及10月30日分別完成二筆房地之繼承登記，至此損害(惡意不當得利)已然發生，原告自得併請求損害發生時即89年10月31日起至清償日止，按年息百分之五計算之利息。(五)聲明：1.被告應給付原告新臺幣1,581,620元，及自89年10月31日起至清償日止，按年息百分之五計算之利息。2.原告願供擔保請准宣告假執行。二、被告則辯以：(一)本件被告取得遺產，係因原告自行同意放棄繼承不動產及存款之權利，故被告取得遺產有正當法律上原因，自不符民法不當得利之要件。(二)兩造養父即被繼承人蔣錫將於89年8月5日死亡，雖留下愛國路與德安街二筆房地及存款357,102元，惟亦留下多筆高雄銀行之貸款債務，當時原告因積欠銀行及地下錢莊債務，擔心繼承上開被繼承人之遺產後遭債權銀行及地下錢莊拍賣，致影響被告及養母蔣張惠咥之權利，且被繼承人蔣錫將亦留下多筆銀行貸款之債務，養母蔣張惠咥中風居往療養院，無力負擔貸款利息，原告負債累累，亦無力支付多筆銀行貸款本息，故協議由被告一人繼承二筆不動產及存款，當時原告亦自行提供印鑑證明與印鑑章等相關資料交由被告辦理繼承事宜，被告即依協議內容委託蔡凱文代書辦理繼承登記事宜，並無偽造或不法之情事。(三)被繼承人蔣錫將所遺留上開二筆不動產都有貸款，系爭德安街房地有公教貸款180萬元(由高雄市政府委託高雄銀行辦理)及高雄銀行貸款50萬元，系爭愛國路房地則有56萬元的貸款，被告所提被繼承人蔣錫將之高雄銀行授信明細查詢單記載30萬元、20萬元，是第一筆50萬元換貸而來，第四筆、第五筆是比較早的資料，合併之後又增貸32萬元，變成56萬元，此三筆債務均由被告以其高雄銀行帳戶000000000000轉帳繳交，有高雄銀行出具之存款對帳單為證，被告為早日清償蔣錫將遺留債務，先於90年3月將系爭愛國路房地賣給第三人黃花，由黃花向中國信託銀行貸款清償抵押貸款426,764元；嗣於94年3月間將德安街房地出售予第三人郭天順，據被告所提該不動產買賣契約書第六條稅費負擔第四點，約定由買方負責清償該屋之二筆抵押貸款(即180萬元公教貸款及50萬元貸款)，因郭天順指定登記給郭芳廷，郭芳廷即向中國信託銀行貸款並設定抵押，待中國信託銀行撥款代為清償前二筆貸款餘額412,036元及1,560,027元後，再由高雄銀行塗銷抵押權登記，故以上三筆貸款債務，平日係以被告帳戶轉帳繳交本息，於房屋出售時，則由買主貸款以賣屋價金償還。(四)原告知悉被告將房地出售之事，並配合於94年3月25日將戶口自德安街地址遷出，是原告起訴主張未與被告協議分割遺產，協議內容係被告偽造云云，顯與事實不符，亦有違常情，印鑑證明係原告提供給被告辦理分割事宜，當時因原告積欠很多卡債，名下又無財產，原告也無法照顧養母，所以原告同意將不動產登記給被告，被繼承人蔣錫將過世後，原告就遺產分割及由被告負擔相關貸款之繳納及清償等事均知情，卻從未表示異議，從未要求將遺產分割或出賣後分配價金，且就被告如何取得原告印鑑章，也提不出具體說法，土地及房屋登記為公示資料，任何人隨時可調取，原告之戶籍更先後遷入此二筆房屋，當不得諉稱不知，況被告賣出系爭德安街房地時，還要求原告配合將伊戶口遷走，足證原告當時同意全部遺產及債務均由被告繼承，僅因伊目前窮困潦倒，無經濟來源，欲藉10年前繼承之事向被告要錢，原告多年來經常向被告要錢，被告有餘力時會匯錢給原告，詎原告汙衊被告偽造文書並提起本件訴訟，請鈞院明察。(五)聲明：原告之訴及假執行之聲請均駁回。三、兩造不爭執之事實：(一)原告與被告為養兄妹關係，兩造之養父即被繼承人蔣錫將於89年8月5日過世，遺留有遺產：1.系爭愛國路房地；2.系爭德安街房地；3.存款約357,102元。(二)被繼承人蔣錫將死亡後，渠遺產由兩造及蔣錫將之配偶蔣張惠咥繼承，應繼分各三分之一。四、得心證之理由：本件原告依不當得利之法律關係，請求被告應返還相當於蔣錫將遺產三分之一之利益，主要是以被告未經伊及蔣張惠咥之同意，持偽造之分割協議書向地政機關辦理由被告單獨繼承遺產中之二筆房地，私吞所有款項，並於90年3月及94年4月分別將上開二筆房地出售換取價款予以獨占，致伊及蔣張惠咥受有損害為主張之依據，惟被告則否認有偽造分割協議書之事實，並辯以：其取得遺產，係因原告自行同意放棄繼承不動產及存款之權利等語，是本件原告之主張是否有據，應以關於蔣錫將之遺產分割協議書是否經兩造同意簽立而認定，茲審酌如下：(一)查蔣錫將所遺留之系爭愛國路房地，業於89年10月25日以分割繼承為原因登記予被告名下；另系爭德安街房地亦於89年10月30日以分割繼承為原告登記被告名下，凡此有原告所提高雄市三民地政事務所網路申領異動索引、高雄市新興地政事務所網路申領異動索引各1件為證，並經本院分別向高雄市政府地政局三民地政事務所、及新興地政事務所調取前開之分割繼承所有權移轉登記文件，分別經三民地政事務所以100年2月15日高市地民價字第1000001507號函檢附該區○○段29地號土地，及其上546建號，門牌三民區○○路86巷3號建物之所有權移轉登記資料，及新興地政事務所以100年2月15日高市地新價字第1000001374號函檢附苓雅區○○段1435地號土地，及其上苓雅區○○街5巷12號4樓之3建物之移轉登記資料附卷供參。而上開二份回函中之移轉登記資料均附有原告(原名蔣紹武，嗣於93年2月27日更名為蔣瑞福)、被告及蔣張惠咥所簽訂之分割協議書、印鑑證明。而原告對於分割協議書及印鑑證明上之印鑑章式樣相似，初亦坦承：分割協議書上之印章與原告印鑑章看起來十分雷同等語，惟又稱對於協議書上所蓋之章是否為伊所有沒有印象等語，可見原告就分割協議書關於原告之章與印鑑證明之章為同一一事初亦不否認。且核對上開地政事務所函附本院所附之分割協議書、印鑑證明、土地登記申請書（均影本），其上關於原告更名前蔣紹武之印文，其字形雷同，亦可見該分割協議書之蔣紹文印文，與印鑑證明之印文應屬同一。至原告嗣後雖於言詞辯論時始質疑印鑑證明與分割協議書之印文顯然不同，印鑑證明之章是假的等語，並提出伊自行放大印鑑證明及分割協議書之印文影本附卷供參，然該放大影本既為原告自行重複放大，則在多次影印過程中，其紙張有無壓平、墨水濃度深淺，均可能影響最後字體之樣式，此從原告所提之其上蓋有「157822」編號之印鑑證明影本，經核對與本院向前開三民地政事務所所調取之印鑑證明，其中字體墨色深淺有別，以致原告所提印鑑證明中「蔣」字之「寸」、及「紹」字之「糸」部呈現不連續，而與本院調取之印鑑證明明顯不同。以此，原告僅以伊將印鑑證明及分割協議書上之印文放大比對而有差異為由，主張分割協議書上之印文非伊所有，已難採信。(二)且查，當初辦理分割協議登記時，除提出分割協議書外，並有原告之印鑑證明，已見前述，並據證人即辦理蔣錫將移產分割繼承登記之代書蔡凱文證述：「（蔣錫將所有之遺產於高雄市○○區○○路86巷3號房屋及高雄市○○區○○街5巷12號四樓之3房屋及土地等，當初辦理遺產分割協議，是否為你處理？）是的，當時應該是被告委託我辦理的。（兩造有無訂立遺產分割協議？）有。（遺產分割協議有無經過兩造及其他繼承人同意？）他們各蓋印鑑章並出具印鑑證明給我。（訂立分割協議書時，你有無在場？）沒有。（章是由何人蓋的？）是被告當時把原告的印鑑當場拿給我，並說是原告委託他拿給我辦理的。（原告是否知道你去辦理分割遺產的登記？）我不確定。（當時有無聯絡原告？）當時原告不在高雄，且一般情形我們認為有出具印鑑證明，並交付印鑑章，我們就認為有經過本人的同意，否則不會隨便將印鑑章及印鑑證明交給別人。（辦理分割遺產登記後，原告有無向你表示意見？）沒有。（是否直接拿到原告的印鑑章，或是文件上面已經蓋好印鑑印文？）被告直接拿原告的印鑑章給我，說是原告委託他拿給我的，我是當著被告的面確認文件沒有問題後，我當場蓋章並將原告的印鑑章交還給被告。（該分割協議書的內容，是否為你所繕打？）是的，但我是依據兩造及其他繼承人的意思所繕打，我跟三個繼承人並沒有全部見面，我只有與被告接觸。」等語，依證人所述，系爭分割協議書固係由渠繕打，然當初被告乃將原告印鑑章及印鑑證明交付證人蓋印後將印鑑章交還被告，則系爭分割協議書業據附上原告之印鑑證明，已可認定。而原告已不否認該印鑑證明為伊所有，雖伊就該印鑑證明如何而來，辯稱：不知道，因被告把伊從台北叫回高雄，說母親中風等語；惟依卷附原告申辦印鑑證明即89年8月14日當時之有效之印鑑登記辦法（嗣已於98年10月13日修正）第7條規定：「依第四條第一項規定申請印鑑證明應由當事人或其受委任人填具申請書(格式九)並繳驗國民身分證，申請辦理。由其受委任人申請者，並應附繳委任書。」以此，關於當初辦理系爭遺產分割協議所附之原告印鑑證明，無論係原告本人親辦，或由原告出具國民身分證委由他人辦理，無論何者，均可認定該印鑑證明乃經原告同意所申辦；衡情，以印鑑證明乃係為該印文係本人所有之憑據，其關係重大，非有重要事項，一般人當不至無故辦理，可見原告申辦該印鑑證明，當出於特殊目的。再觀兩造被繼承人蔣錫將係於89年8月5日死亡，原告之印鑑證明於89年8月14日申辦，兩造之分割協議書訂立日期為89年10月5日，而前述之系爭愛國路房地係於89年10月25日登記予被告名下，系爭德安街房地亦於89年10月30日以分割繼承為原告登記予被告名下，凡此有原告所提高雄市三民地政事務所網路申領異動索引、高雄市新興地政事務所網路申領異動索引各1件為證，並經本院分別向高雄市政府地政局三民地政事務所、及新興地政事務所調取前開之分割繼承所有權移轉登記文件，以原告之印鑑證明申辦日期介於蔣錫將死亡之後，及兩造訂立分割協議書及辦理分割繼承登記之前，則依上開事件之順序，已可推論原告當係於蔣錫將死亡後，為辦理分割協議，而申辦印鑑證明，再憑以交付被告完成遺產繼承之事宜，是原告所辯不知印鑑如何而來等語，顯為避重就輕之詞，自不可信。(三)何況被告於依繼承登記取得蔣錫將之不動產後，已分別於90年3月將系爭愛國路房地出售予訴外人黃花，並於90年3月8日辦理所有權移轉登記，嗣又於94年3月5日將系爭德安街房地出售予訴外人郭天順，並於94年4月19日辦理所有權移轉登記予郭芳廷，凡此業為原告提出高雄市三民地政事務所網路申領異動索引、高雄市新興地政事務所網路申領異動索引、苓雅區○○段第1435地號土地登記第二類謄本等件，及被告提出之不動產買賣契約書附卷供參。而原告之戶籍原設於系爭德安街房屋之上，後於94年3月25日遷移至中壢，此亦有原告之戶籍謄本供參，而原告亦自承伊於戶籍仍設於德安街地址時即已知悉被告將前開房地出售之事實，則對照前述經過，可見原告至遲於94年3月25日以前即已知悉被告出售遺產之事，乃迄至99年7月29日始起訴請求返還不當得利，期間相距5年，是參照原告遲未起訴或發存證信函之事實，甚且於被告將德安街房地出售之前將戶籍遷移他處，可見原告對於出售房地一事，不僅知情，且有配合被告而遷移戶籍之意。(四)且被告另抗辯：蔣錫將留下多筆銀行貸款之債務，養母蔣張惠咥中風居往療養院，無力負擔貸款利息，原告負債累累，亦無力支付多筆銀行貸款本息，故協議由其一人繼承二筆不動產及存款，其為早日清償蔣錫將遺留債務，先於90年3月將系爭愛國路房地賣給第三人黃花，由黃花向中國信託銀行貸款清償抵押貸款426,764元，嗣於94年3月間將系爭德安街房地出售予第三人郭天順，約定由買方負責清償該屋之二筆抵押貸款，因郭天順指定登記給郭芳廷，郭芳廷即向中國信託銀行貸款並設定抵押，待中國信託銀行撥款代為清償前二筆貸款餘額412,036元及1,560,027元後，再由高雄銀行塗銷抵押權登記，故以上三筆貸款債務，平日係以其帳戶轉帳繳交本息，於房屋出售時，則由買主貸款以賣屋價金償還等語。查，蔣錫將死亡當時，遺有三筆貸款，分別為：1.積欠高雄銀行大發分行金額491,652元；2.積欠高雄銀行大發分行金額479,749元；此二筆貸款均由被告於高雄銀行大發分行所開設帳戶扣款繳納本金及利息，並於90年3月16日由中國信託三民分行匯款清償第1.筆貸款，及於94年4月20日由中國信託高雄分行匯款清償第2.筆貸款；此有高雄銀行股份有限公司大發分行100年3月30日高銀大發字第10000052號函附卷可稽；另第3.筆為國宅貸款180萬元，並於94年4月20日由中國信託帳戶匯入，償還金額為1,560,027元，此亦有高雄銀行股份有限公司100年4月28日高銀營字第1000002937號函可參。從上所述，其中蔣錫將所遺留之第1.、2.筆借款均係由被告清償，另從系爭愛國路房地係於90年3月間出售，並於3月8日移轉登記，其與第1.筆貸款完全清償之時間僅相差8日；而系爭德安街之房地於94年3月5日出售，並於94年4月19日移轉登記，此亦與第2.、3.筆貸款之完全清償日期94年4月20日亦密切相近，則參照上開事實，可認被告所辯蔣錫將所遺留債務由其負責清償，嗣後並由其將系爭愛國路、德安街房地出售後以所得價金清償款項等語，亦可認定。(五)綜合前述，本件從蔣錫將遺產辦理分割協議登記時，已有原告之印鑑證明及印鑑章，而原告就印鑑證明之由來亦答以不知情，則衡諸常情，該印鑑證明當係原告申辦或由原告授意辦理，而以印鑑證明之申辦時間乃在蔣錫將死亡後數日所為，且該印鑑證明申辦後未久即經代書辦理蔣錫將遺產分割協議登記，更可見該印鑑證明當係為辦理分割協議而申辦；參以被告於94年3月5日將德安街房地出售後，原告隨即於同月25日將原設籍於德安街之戶籍遷至中壢，並參原告自承於戶籍仍設於德安街之時即知被告將房地出售之事，可見原告對於被告出售蔣錫將所留遺產一事，不僅知情，且亦配合辦理遷移戶籍，而從原告自該時起迄今起訴時之5年餘時間均未曾異議，乃於時隔5年餘又表示被告未得伊同意變賣父親遺產，自不合理。再參蔣錫將所遺留債務係由被告償還，嗣並以出售愛國路、德安街房地之價金償還，益可見被告所辯當初繼承人協議由其繼承不動產及存款，並將房地出售後清償貸款之主張，為可採信。依上，則原告對於本件系爭分割協議當已知悉並同意，伊主張被告偽造分割協議書辦理繼承登記，並變賣父親遺產，殊不可信。茲被告所辦理遺產分割，既係本於繼承人之協議，則伊取得蔣錫將之遺產，自非無法律上原因，從而原告以被告無法律上原因而受利益，致伊及共同繼承人蔣張惠咥受有損害，據以依不當得利之法律關係請求被告返還相當遺產三分之一之利益，於法無據，應予駁回。五、本件法律關係已臻明確，兩造其餘之主張、抗辯，於本件之認定不生影響，爰不再一一論述；又被告聲請蔣張惠咥到庭訊問，惟依渠所證，語涉：「．．．我先生現在還在，住在小港，他死了是死了，但他的靈還在，他天天來看我，我還弄飯給他吃，我先生現在住在小港。（有無去找妳先生？）我天天看得見。（如何看見的？）我是天上聖母，我是神，也是人。」等語無倫次之言語，是渠之心神狀況不佳，已難為有正確證述，則渠所為其餘證詞自難採認，併此敘明。六、據上論結，本件原告之訴為無理由，依民事訴訟法第78條，判決如主文。中華民國100年6月22日家事法庭法官林富郎以上為正本係照原本作成如對本判決上訴，須於判決送達後20日內向本院提出上訴狀（附具繕本），如委任律師提起上訴者，應一併繳納上訴審裁判費。中華民國100年6月22日書記官劉毓如",
  "characters": {
    "judges": [
      "林富郎"
    ],
    "prosecutors": [

    ],
    "lawyers": [
      "黃郁婷",
      "陳建欽",
      "陳慈鳳"
    ],
    "clerks": [

    ],
    "plaintiffs": [
      "蔣瑞福"
    ],
    "defendants": [
      "蔣育瑛"
    ],
    "prosecutor_office": [

    ],
    "creditors": [

    ],
    "debtors": [

    ],
    "judicial_associate_officer": [

    ]
  },
  "adjudged_at": "2011-06-22",
  "created_at": "2016-02-13 17:54:34",
  "updated_at": "2016-02-13 17:54:34"
}