{
  "identify": "TNH-100-上易-340-20110622-1",
  "court": {
    "name": "臺灣高等法院",
    "code": "TNH"
  },
  "division": {
    "name": "刑事",
    "code": "M"
  },
  "year": 100,
  "word": "上易",
  "number": "340",
  "jcheck": "1",
  "reason": "詐欺",
  "content": "臺灣高等法院臺南分院刑事判決        100年度上易字第340號\n上  訴  人\n即  被  告  王藏億\n上列上訴人因詐欺案件，不服臺灣臺南地方法院100 年度易字第\n294號中華民國100 年4月12日第一審判決（起訴案號：臺灣臺南\n地方法院檢察署100年度偵字第1401號；移送併辦案號：100年度\n偵字第3567號），提起上訴，本院判決如下：\n    主  文\n上訴駁回。\n    理  由\n一、按刑事訴訟法第三百五十條、第三百六十一條、第三百六十\n    二條、第三百六十七條規定，不服地方法院之第一審判決而\n    上訴者，須提出上訴書狀，並應敘述具體理由，此為上訴必\n    備之程式；如所提之書狀未敘述上訴理由，或僅曾以言詞陳\n    述上訴理由者，均應於上訴期間屆滿後二十日內補提理由書\n    於第一審法院。第一審法院經形式審查，認逾期未補提上訴\n    理由者，應定期間先命補正；逾期未補正者，為上訴不合法\n    律上之程式，應以裁定駁回。倘已提出上訴理由，但所提非\n    屬具體理由者，則由第二審法院以上訴不合法律上之程式，\n    判決駁回。而所謂具體理由，必係依據卷內既有訴訟資料或\n    提出新事證，指摘或表明第一審判決有何採證、認事、用法\n    或量刑等足以影響判決本旨之不當或違法，而構成應予撤銷\n    之具體事由，始克當之（例如：依憑證據法則具體指出所採\n    證據何以不具證據能力，或依憑卷證資料，明確指出所為證\n    據證明力之判斷如何違背經驗、論理法則）；倘僅泛言原判\n    決認定事實錯誤、違背法令、採証違法、判決不公、量刑失\n    之過重或輕縱，而未依上揭意旨指出具體事由，或形式上雖\n    已指出具體事由，然該事由縱使屬實，亦不足以認為原判決\n    有何不當或違法者（例如：對不具有調查必要性之證據，法\n    院未依聲請調查亦未說明理由，或援用證據不當，但除去該\n    證據仍應為同一事實之認定），皆難謂係具體理由，而應認\n    其上訴為不合法律上之程式（最高法院九十七年台上字第八\n    九二號判決、九十七年台上字第三二六七號判決意旨及法院\n    辦理刑事訴訟案件應行注意事項第一六二點參照）。\n二、本件上訴意旨略以：(一)按法官對於如何量定其刑，為求個案\n    裁判之妥當性，法律固賦與法官自由裁量之權。然而對於被\n    告而言，定罪固然重要，但量刑問題往往是他們更為關心的\n    。無論是實體正義還是程序正義，歸根究底都需要量刑公正\n    來體現，如果刑罰運用不能實現公正、合理的價值標準，必\n    然會使人們對司法公正產生懷疑，造成法院刑事審判的公信\n    力的下降，損害了審判權威。是故，就刑之量定而言，固屬\n    實體法上賦予法院得為自由裁量之事項，惟法院行使此項職\n    權時，仍應受比例原則與平等原則等一般法律原則之支配，\n    同時需符合法律授權之目的，且考量秩序之理念、國民法律\n    感情等，以期達成客觀上之適當性與必要性之價值要求，若\n    違反比例原則、平等原則，自有量刑失當之違法。此有最高\n    法院96年度台上字第3773號、95年度台上字第1779號、91年\n    度台上字第5317號、86年度台上字第7655號刑事判決意旨可\n    供參照。(二)次按對被告而言，其所重視的並非法庭上之攻防\n    活動，而僅在乎法官最後判刑之多寡？從而，對於判決結果\n    中刑之量定部分，法官應以罪刑相當原則、合於人民之法感\n    情作為刑罰裁量之前提，再依據各種不同之情形為刑罰之裁\n    量，量定被告應得之刑罰。是故，法官在量刑時除應站在被\n    告角度外，更應兼顧人民的法感情，綜合各種情狀，論理分\n    明且清楚而具體的於判決理由中說明，才能夠讓被告或社會\n    大眾信賴司法的透明。查被告王藏億於偵審中供出該詐騙集\n    團的其他共犯，顯見其犯後態度良好，而依刑法第57條第10\n    款之規定，應作為科刑輕重之標準，然而原審判決理由對此\n    可作為量刑事由之事項卻隻字未提。是故，原審判決自有判\n    決不備理由之違誤。(三)次查被告王藏億所為並不可取，然而\n    考量被告僅是因為一時思慮不周而誤入歧途，又被告王藏億\n    並非在該詐騙集團中擔任主腦的身分地位，而僅是在該詐騙\n    集團擔任枝微末節的車手角色地位而已，對於詐騙計畫的實\n    施並非扮演舉足輕重的角色，任何人都可以加以取代。是故\n    ，可知被告的惡性並非重大，所造成的危害並非嚴重；且其\n    犯後態度良好，於警詢、偵訊及審判程序均自白坦承犯行不\n    諱，又供出該詐騙集團的其他共犯供檢警繼續查緝，尚屬有\n    功，顯見被告已知所悔悟，而歷經此一刑事訴訟程序，應無\n    再犯之虞。核被告王藏億犯罪之情狀及犯後之態度，顯可憫\n    恕。爰此，懇請鈞院鑒核，能依刑法第59條之規定，讓被告\n    有滌蕩舊恥，勉力自新之機會云云。\n三、經查：\n  (一)本件上訴人即被告王藏億於原審一○○年三月二十九日行準\n    備程序時就檢察官起訴之犯罪事實為認罪之表示（見原審卷\n    第廿五頁背面），經原審告知簡式審判程序之旨，並經聽取\n    其與公訴人之意見後，而裁定以簡式審判程序審理（見原審\n    卷二五頁背面）。嗣被告於原審同日行審理程序時，亦坦承\n    全部犯罪事實（見原審卷第廿八頁背面），且就卷內證據資\n    料均表示無意見（見原審卷第二八頁背面至二十九頁背面）\n    ，先此敘明。\n  (二)其次，本件被告雖已敘述上訴理由，但其上訴理由，僅泛以\n    其惡性並非重大，所造成的危害並非嚴重；犯後態度良好，\n    於警詢、偵訊及審判程序均自白坦承犯行不諱，且供出該詐\n    騙集團的其他共犯供檢警繼續查緝，尚屬有功，顯見被告已\n    知所悔悟，而歷經此一刑事訴訟程序，應無再犯之虞。核被\n    告王藏億犯罪之情狀及犯後之態度，顯可憫恕，懇請能依刑\n    法第59條之規定，減輕其刑云云。惟原審判決係依被告於原\n    審準備及審理程序中之認罪陳述，已於事實及理由欄中說明\n    被告罪刑成立之理由，並於理由欄詳予說明依據之證據資料\n    。亦即上揭犯罪事實，業據被告自白在卷，且有證人楊美錞\n    所申辦行動電話號碼0000000000號自九十九年四月七日至九\n    十九年四月九日之通聯記錄，行動電話號碼0000000000（王\n    益誠）、0000000000（王藏億）使用者資料查詢單等資料均\n    在卷可憑，兼衡被告為一己之私利，加入詐騙集團參與協力\n    分工之犯罪動機、目的，價值觀念嚴重偏差，詐騙被害人之\n    財物之所為影響社會治安及金融交易安全，被害人所受損害\n    ，及被告犯後坦承犯行之態度等一切情狀，量處有期徒刑一\n    年，經核並無不當。\n  (三)原審判決既已審酌被告犯後坦承犯行之態度等情狀作為量刑\n    之參考，被告上訴意旨以：被告王藏億於偵審中供出該詐騙\n    集團的其他共犯，顯見其犯後態度良好，而依刑法第五十七\n    條第十款之規定，應作為科刑輕重之標準，然而原審判決理\n    由對此可作為量刑事由之事項卻隻字未提云云，執為上訴理\n    由，即無可採。又量刑之輕重本屬法院依職權裁量之事項，\n    而刑法第五十九條之酌量減輕其刑，必於犯罪之情狀，在客\n    觀上足以引起一般同情，認為即予宣告法定低度刑期，猶嫌\n    過重者，始有其適用，至於犯罪動機、情節輕微、素行端正\n    、家計負擔、犯後態度等情狀，僅可為法定刑內從輕科刑之\n    標準，不得據為酌量減輕之理由（最高法院五十一年台上字\n    第八九九號、二十八年上字第一○六四號等判例意旨可參）\n    。本件被告王藏億與王益誠、陳俊源等人所組之詐騙集團成\n    員相互分工合作，而由在大陸地區之陳俊源等人撥打被害人\n    電話詐騙被害人後，而被告王藏億除擔任吸收詐騙集團成員\n    之車手人員，且教導車手向被害人收受財物，並負責收取同\n    案被告王益誠所收取被害人財物後，再依詐騙集團成員指示\n    匯入特定帳戶而轉交與詐欺集團之人等行為，其屬有計劃、\n    集團性之犯罪，且依其向被害人李文池先詐得現金二萬元、\n    金項鍊一條及現金八萬元之情節，尚難謂「客觀上足以引起\n    一般同情，認為即予宣告法定低度刑期，猶嫌過重者」，原\n    判決未適用刑法第五十九條予以酌減其刑，亦難謂有何不當\n    。\n  (四)揆諸首開判決意旨，被告之上訴顯未依據卷內既有訴訟資料\n    或提出新事證，具體指摘或表明第一審判決有何認事採證不\n    當或違法之事由或其於原審之自白有何違反任意性之規定，\n    徒以上開理由指稱原判決不當，揆諸前開說明，其上訴理由\n    ，自難謂係具體理由。是上訴人即被告之上訴顯不合法律上\n    之程式，爰依刑事訴訟法第三百六十七條前段之規定，駁回\n    其上訴，並不經言詞辯論為之。\n據上論斷，應依刑事訴訟法第三百六十七條前段、第三百七十二\n條，判決如主文。\n中    華    民    國   100    年    6     月    22    日\n                  刑事第六庭    審判長法  官  董武全\n                                      法  官  林英志\n                                      法  官  孫玉文\n以上正本證明與原本無異。\n不得上訴。\n                                      書記官  王薇潔\n中    華    民    國   100    年    6     月    22    日",
  "structure": {
    "main": "上訴駁回。",
    "reason": "一、按刑事訴訟法第三百五十條、第三百六十一條、第三百六十\n    二條、第三百六十七條規定，不服地方法院之第一審判決而\n    上訴者，須提出上訴書狀，並應敘述具體理由，此為上訴必\n    備之程式；如所提之書狀未敘述上訴理由，或僅曾以言詞陳\n    述上訴理由者，均應於上訴期間屆滿後二十日內補提理由書\n    於第一審法院。第一審法院經形式審查，認逾期未補提上訴\n    理由者，應定期間先命補正；逾期未補正者，為上訴不合法\n    律上之程式，應以裁定駁回。倘已提出上訴理由，但所提非\n    屬具體理由者，則由第二審法院以上訴不合法律上之程式，\n    判決駁回。而所謂具體理由，必係依據卷內既有訴訟資料或\n    提出新事證，指摘或表明第一審判決有何採證、認事、用法\n    或量刑等足以影響判決本旨之不當或違法，而構成應予撤銷\n    之具體事由，始克當之（例如：依憑證據法則具體指出所採\n    證據何以不具證據能力，或依憑卷證資料，明確指出所為證\n    據證明力之判斷如何違背經驗、論理法則）；倘僅泛言原判\n    決認定事實錯誤、違背法令、採証違法、判決不公、量刑失\n    之過重或輕縱，而未依上揭意旨指出具體事由，或形式上雖\n    已指出具體事由，然該事由縱使屬實，亦不足以認為原判決\n    有何不當或違法者（例如：對不具有調查必要性之證據，法\n    院未依聲請調查亦未說明理由，或援用證據不當，但除去該\n    證據仍應為同一事實之認定），皆難謂係具體理由，而應認\n    其上訴為不合法律上之程式（最高法院九十七年台上字第八\n    九二號判決、九十七年台上字第三二六七號判決意旨及法院\n    辦理刑事訴訟案件應行注意事項第一六二點參照）。\n二、本件上訴意旨略以：(一)按法官對於如何量定其刑，為求個案\n    裁判之妥當性，法律固賦與法官自由裁量之權。然而對於被\n    告而言，定罪固然重要，但量刑問題往往是他們更為關心的\n    。無論是實體正義還是程序正義，歸根究底都需要量刑公正\n    來體現，如果刑罰運用不能實現公正、合理的價值標準，必\n    然會使人們對司法公正產生懷疑，造成法院刑事審判的公信\n    力的下降，損害了審判權威。是故，就刑之量定而言，固屬\n    實體法上賦予法院得為自由裁量之事項，惟法院行使此項職\n    權時，仍應受比例原則與平等原則等一般法律原則之支配，\n    同時需符合法律授權之目的，且考量秩序之理念、國民法律\n    感情等，以期達成客觀上之適當性與必要性之價值要求，若\n    違反比例原則、平等原則，自有量刑失當之違法。此有最高\n    法院96年度台上字第3773號、95年度台上字第1779號、91年\n    度台上字第5317號、86年度台上字第7655號刑事判決意旨可\n    供參照。(二)次按對被告而言，其所重視的並非法庭上之攻防\n    活動，而僅在乎法官最後判刑之多寡？從而，對於判決結果\n    中刑之量定部分，法官應以罪刑相當原則、合於人民之法感\n    情作為刑罰裁量之前提，再依據各種不同之情形為刑罰之裁\n    量，量定被告應得之刑罰。是故，法官在量刑時除應站在被\n    告角度外，更應兼顧人民的法感情，綜合各種情狀，論理分\n    明且清楚而具體的於判決理由中說明，才能夠讓被告或社會\n    大眾信賴司法的透明。查被告王藏億於偵審中供出該詐騙集\n    團的其他共犯，顯見其犯後態度良好，而依刑法第57條第10\n    款之規定，應作為科刑輕重之標準，然而原審判決理由對此\n    可作為量刑事由之事項卻隻字未提。是故，原審判決自有判\n    決不備理由之違誤。(三)次查被告王藏億所為並不可取，然而\n    考量被告僅是因為一時思慮不周而誤入歧途，又被告王藏億\n    並非在該詐騙集團中擔任主腦的身分地位，而僅是在該詐騙\n    集團擔任枝微末節的車手角色地位而已，對於詐騙計畫的實\n    施並非扮演舉足輕重的角色，任何人都可以加以取代。是故\n    ，可知被告的惡性並非重大，所造成的危害並非嚴重；且其\n    犯後態度良好，於警詢、偵訊及審判程序均自白坦承犯行不\n    諱，又供出該詐騙集團的其他共犯供檢警繼續查緝，尚屬有\n    功，顯見被告已知所悔悟，而歷經此一刑事訴訟程序，應無\n    再犯之虞。核被告王藏億犯罪之情狀及犯後之態度，顯可憫\n    恕。爰此，懇請鈞院鑒核，能依刑法第59條之規定，讓被告\n    有滌蕩舊恥，勉力自新之機會云云。\n三、經查：\n  (一)本件上訴人即被告王藏億於原審一○○年三月二十九日行準\n    備程序時就檢察官起訴之犯罪事實為認罪之表示（見原審卷\n    第廿五頁背面），經原審告知簡式審判程序之旨，並經聽取\n    其與公訴人之意見後，而裁定以簡式審判程序審理（見原審\n    卷二五頁背面）。嗣被告於原審同日行審理程序時，亦坦承\n    全部犯罪事實（見原審卷第廿八頁背面），且就卷內證據資\n    料均表示無意見（見原審卷第二八頁背面至二十九頁背面）\n    ，先此敘明。\n  (二)其次，本件被告雖已敘述上訴理由，但其上訴理由，僅泛以\n    其惡性並非重大，所造成的危害並非嚴重；犯後態度良好，\n    於警詢、偵訊及審判程序均自白坦承犯行不諱，且供出該詐\n    騙集團的其他共犯供檢警繼續查緝，尚屬有功，顯見被告已\n    知所悔悟，而歷經此一刑事訴訟程序，應無再犯之虞。核被\n    告王藏億犯罪之情狀及犯後之態度，顯可憫恕，懇請能依刑\n    法第59條之規定，減輕其刑云云。惟原審判決係依被告於原\n    審準備及審理程序中之認罪陳述，已於事實及理由欄中說明\n    被告罪刑成立之理由，並於理由欄詳予說明依據之證據資料\n    。亦即上揭犯罪事實，業據被告自白在卷，且有證人楊美錞\n    所申辦行動電話號碼0000000000號自九十九年四月七日至九\n    十九年四月九日之通聯記錄，行動電話號碼0000000000（王\n    益誠）、0000000000（王藏億）使用者資料查詢單等資料均\n    在卷可憑，兼衡被告為一己之私利，加入詐騙集團參與協力\n    分工之犯罪動機、目的，價值觀念嚴重偏差，詐騙被害人之\n    財物之所為影響社會治安及金融交易安全，被害人所受損害\n    ，及被告犯後坦承犯行之態度等一切情狀，量處有期徒刑一\n    年，經核並無不當。\n  (三)原審判決既已審酌被告犯後坦承犯行之態度等情狀作為量刑\n    之參考，被告上訴意旨以：被告王藏億於偵審中供出該詐騙\n    集團的其他共犯，顯見其犯後態度良好，而依刑法第五十七\n    條第十款之規定，應作為科刑輕重之標準，然而原審判決理\n    由對此可作為量刑事由之事項卻隻字未提云云，執為上訴理\n    由，即無可採。又量刑之輕重本屬法院依職權裁量之事項，\n    而刑法第五十九條之酌量減輕其刑，必於犯罪之情狀，在客\n    觀上足以引起一般同情，認為即予宣告法定低度刑期，猶嫌\n    過重者，始有其適用，至於犯罪動機、情節輕微、素行端正\n    、家計負擔、犯後態度等情狀，僅可為法定刑內從輕科刑之\n    標準，不得據為酌量減輕之理由（最高法院五十一年台上字\n    第八九九號、二十八年上字第一○六四號等判例意旨可參）\n    。本件被告王藏億與王益誠、陳俊源等人所組之詐騙集團成\n    員相互分工合作，而由在大陸地區之陳俊源等人撥打被害人\n    電話詐騙被害人後，而被告王藏億除擔任吸收詐騙集團成員\n    之車手人員，且教導車手向被害人收受財物，並負責收取同\n    案被告王益誠所收取被害人財物後，再依詐騙集團成員指示\n    匯入特定帳戶而轉交與詐欺集團之人等行為，其屬有計劃、\n    集團性之犯罪，且依其向被害人李文池先詐得現金二萬元、\n    金項鍊一條及現金八萬元之情節，尚難謂「客觀上足以引起\n    一般同情，認為即予宣告法定低度刑期，猶嫌過重者」，原\n    判決未適用刑法第五十九條予以酌減其刑，亦難謂有何不當\n    。\n  (四)揆諸首開判決意旨，被告之上訴顯未依據卷內既有訴訟資料\n    或提出新事證，具體指摘或表明第一審判決有何認事採證不\n    當或違法之事由或其於原審之自白有何違反任意性之規定，\n    徒以上開理由指稱原判決不當，揆諸前開說明，其上訴理由\n    ，自難謂係具體理由。是上訴人即被告之上訴顯不合法律上\n    之程式，爰依刑事訴訟法第三百六十七條前段之規定，駁回\n    其上訴，並不經言詞辯論為之。\n據上論斷，應依刑事訴訟法第三百六十七條前段、第三百七十二\n條，判決如主文。"
  },
  "search": "臺灣高等法院臺南分院刑事判決100年度上易字第340號上訴人即被告王藏億上列上訴人因詐欺案件，不服臺灣臺南地方法院100年度易字第294號中華民國100年4月12日第一審判決（起訴案號：臺灣臺南地方法院檢察署100年度偵字第1401號；移送併辦案號：100年度偵字第3567號），提起上訴，本院判決如下：主文上訴駁回。理由一、按刑事訴訟法第三百五十條、第三百六十一條、第三百六十二條、第三百六十七條規定，不服地方法院之第一審判決而上訴者，須提出上訴書狀，並應敘述具體理由，此為上訴必備之程式；如所提之書狀未敘述上訴理由，或僅曾以言詞陳述上訴理由者，均應於上訴期間屆滿後二十日內補提理由書於第一審法院。第一審法院經形式審查，認逾期未補提上訴理由者，應定期間先命補正；逾期未補正者，為上訴不合法律上之程式，應以裁定駁回。倘已提出上訴理由，但所提非屬具體理由者，則由第二審法院以上訴不合法律上之程式，判決駁回。而所謂具體理由，必係依據卷內既有訴訟資料或提出新事證，指摘或表明第一審判決有何採證、認事、用法或量刑等足以影響判決本旨之不當或違法，而構成應予撤銷之具體事由，始克當之（例如：依憑證據法則具體指出所採證據何以不具證據能力，或依憑卷證資料，明確指出所為證據證明力之判斷如何違背經驗、論理法則）；倘僅泛言原判決認定事實錯誤、違背法令、採証違法、判決不公、量刑失之過重或輕縱，而未依上揭意旨指出具體事由，或形式上雖已指出具體事由，然該事由縱使屬實，亦不足以認為原判決有何不當或違法者（例如：對不具有調查必要性之證據，法院未依聲請調查亦未說明理由，或援用證據不當，但除去該證據仍應為同一事實之認定），皆難謂係具體理由，而應認其上訴為不合法律上之程式（最高法院九十七年台上字第八九二號判決、九十七年台上字第三二六七號判決意旨及法院辦理刑事訴訟案件應行注意事項第一六二點參照）。二、本件上訴意旨略以：(一)按法官對於如何量定其刑，為求個案裁判之妥當性，法律固賦與法官自由裁量之權。然而對於被告而言，定罪固然重要，但量刑問題往往是他們更為關心的。無論是實體正義還是程序正義，歸根究底都需要量刑公正來體現，如果刑罰運用不能實現公正、合理的價值標準，必然會使人們對司法公正產生懷疑，造成法院刑事審判的公信力的下降，損害了審判權威。是故，就刑之量定而言，固屬實體法上賦予法院得為自由裁量之事項，惟法院行使此項職權時，仍應受比例原則與平等原則等一般法律原則之支配，同時需符合法律授權之目的，且考量秩序之理念、國民法律感情等，以期達成客觀上之適當性與必要性之價值要求，若違反比例原則、平等原則，自有量刑失當之違法。此有最高法院96年度台上字第3773號、95年度台上字第1779號、91年度台上字第5317號、86年度台上字第7655號刑事判決意旨可供參照。(二)次按對被告而言，其所重視的並非法庭上之攻防活動，而僅在乎法官最後判刑之多寡？從而，對於判決結果中刑之量定部分，法官應以罪刑相當原則、合於人民之法感情作為刑罰裁量之前提，再依據各種不同之情形為刑罰之裁量，量定被告應得之刑罰。是故，法官在量刑時除應站在被告角度外，更應兼顧人民的法感情，綜合各種情狀，論理分明且清楚而具體的於判決理由中說明，才能夠讓被告或社會大眾信賴司法的透明。查被告王藏億於偵審中供出該詐騙集團的其他共犯，顯見其犯後態度良好，而依刑法第57條第10款之規定，應作為科刑輕重之標準，然而原審判決理由對此可作為量刑事由之事項卻隻字未提。是故，原審判決自有判決不備理由之違誤。(三)次查被告王藏億所為並不可取，然而考量被告僅是因為一時思慮不周而誤入歧途，又被告王藏億並非在該詐騙集團中擔任主腦的身分地位，而僅是在該詐騙集團擔任枝微末節的車手角色地位而已，對於詐騙計畫的實施並非扮演舉足輕重的角色，任何人都可以加以取代。是故，可知被告的惡性並非重大，所造成的危害並非嚴重；且其犯後態度良好，於警詢、偵訊及審判程序均自白坦承犯行不諱，又供出該詐騙集團的其他共犯供檢警繼續查緝，尚屬有功，顯見被告已知所悔悟，而歷經此一刑事訴訟程序，應無再犯之虞。核被告王藏億犯罪之情狀及犯後之態度，顯可憫恕。爰此，懇請鈞院鑒核，能依刑法第59條之規定，讓被告有滌蕩舊恥，勉力自新之機會云云。三、經查：(一)本件上訴人即被告王藏億於原審一○○年三月二十九日行準備程序時就檢察官起訴之犯罪事實為認罪之表示（見原審卷第廿五頁背面），經原審告知簡式審判程序之旨，並經聽取其與公訴人之意見後，而裁定以簡式審判程序審理（見原審卷二五頁背面）。嗣被告於原審同日行審理程序時，亦坦承全部犯罪事實（見原審卷第廿八頁背面），且就卷內證據資料均表示無意見（見原審卷第二八頁背面至二十九頁背面），先此敘明。(二)其次，本件被告雖已敘述上訴理由，但其上訴理由，僅泛以其惡性並非重大，所造成的危害並非嚴重；犯後態度良好，於警詢、偵訊及審判程序均自白坦承犯行不諱，且供出該詐騙集團的其他共犯供檢警繼續查緝，尚屬有功，顯見被告已知所悔悟，而歷經此一刑事訴訟程序，應無再犯之虞。核被告王藏億犯罪之情狀及犯後之態度，顯可憫恕，懇請能依刑法第59條之規定，減輕其刑云云。惟原審判決係依被告於原審準備及審理程序中之認罪陳述，已於事實及理由欄中說明被告罪刑成立之理由，並於理由欄詳予說明依據之證據資料。亦即上揭犯罪事實，業據被告自白在卷，且有證人楊美錞所申辦行動電話號碼0000000000號自九十九年四月七日至九十九年四月九日之通聯記錄，行動電話號碼0000000000（王益誠）、0000000000（王藏億）使用者資料查詢單等資料均在卷可憑，兼衡被告為一己之私利，加入詐騙集團參與協力分工之犯罪動機、目的，價值觀念嚴重偏差，詐騙被害人之財物之所為影響社會治安及金融交易安全，被害人所受損害，及被告犯後坦承犯行之態度等一切情狀，量處有期徒刑一年，經核並無不當。(三)原審判決既已審酌被告犯後坦承犯行之態度等情狀作為量刑之參考，被告上訴意旨以：被告王藏億於偵審中供出該詐騙集團的其他共犯，顯見其犯後態度良好，而依刑法第五十七條第十款之規定，應作為科刑輕重之標準，然而原審判決理由對此可作為量刑事由之事項卻隻字未提云云，執為上訴理由，即無可採。又量刑之輕重本屬法院依職權裁量之事項，而刑法第五十九條之酌量減輕其刑，必於犯罪之情狀，在客觀上足以引起一般同情，認為即予宣告法定低度刑期，猶嫌過重者，始有其適用，至於犯罪動機、情節輕微、素行端正、家計負擔、犯後態度等情狀，僅可為法定刑內從輕科刑之標準，不得據為酌量減輕之理由（最高法院五十一年台上字第八九九號、二十八年上字第一○六四號等判例意旨可參）。本件被告王藏億與王益誠、陳俊源等人所組之詐騙集團成員相互分工合作，而由在大陸地區之陳俊源等人撥打被害人電話詐騙被害人後，而被告王藏億除擔任吸收詐騙集團成員之車手人員，且教導車手向被害人收受財物，並負責收取同案被告王益誠所收取被害人財物後，再依詐騙集團成員指示匯入特定帳戶而轉交與詐欺集團之人等行為，其屬有計劃、集團性之犯罪，且依其向被害人李文池先詐得現金二萬元、金項鍊一條及現金八萬元之情節，尚難謂「客觀上足以引起一般同情，認為即予宣告法定低度刑期，猶嫌過重者」，原判決未適用刑法第五十九條予以酌減其刑，亦難謂有何不當。(四)揆諸首開判決意旨，被告之上訴顯未依據卷內既有訴訟資料或提出新事證，具體指摘或表明第一審判決有何認事採證不當或違法之事由或其於原審之自白有何違反任意性之規定，徒以上開理由指稱原判決不當，揆諸前開說明，其上訴理由，自難謂係具體理由。是上訴人即被告之上訴顯不合法律上之程式，爰依刑事訴訟法第三百六十七條前段之規定，駁回其上訴，並不經言詞辯論為之。據上論斷，應依刑事訴訟法第三百六十七條前段、第三百七十二條，判決如主文。中華民國100年6月22日刑事第六庭審判長法官董武全法官林英志法官孫玉文以上正本證明與原本無異。不得上訴。書記官王薇潔中華民國100年6月22日",
  "characters": {
    "judges": [
      "董武全",
      "林英志",
      "孫玉文"
    ],
    "prosecutors": [

    ],
    "lawyers": [

    ],
    "clerks": [
      "王薇潔"
    ],
    "plaintiffs": [

    ],
    "defendants": [
      "王藏億"
    ],
    "prosecutor_office": [

    ],
    "creditors": [

    ],
    "debtors": [

    ],
    "judicial_associate_officer": [

    ]
  },
  "adjudged_at": "2011-06-22",
  "created_at": "2016-02-13 17:52:28",
  "updated_at": "2016-02-13 17:52:28"
}