{
  "identify": "KSD-100-交簡-823-20110321-1",
  "court": {
    "name": "臺灣高雄地方法院",
    "code": "KSD"
  },
  "division": {
    "name": "刑事",
    "code": "M"
  },
  "year": 100,
  "word": "交簡",
  "number": "823",
  "jcheck": "1",
  "reason": "公共危險",
  "content": "臺灣高雄地方法院刑事簡易判決        100年度交簡字第823號\n聲  請  人  臺灣高雄地方法院檢察署檢察官\n被      告  盧慶讚\n上列被告因公共危險案件，經檢察官聲請以簡易判決處刑（100\n年度偵字第1995號），本院判決如下：\n    主  文\n盧慶讚犯不能安全駕駛動力交通工具罪，科罰金新臺幣伍萬柒仟\n元，如易服勞役，以新臺幣壹仟元折算壹日。\n    事實及理由\n一、本件犯罪事實及證據，除犯罪事實欄一、第3 行「2 瓶」應\n    更正為「2 杯」外，均引用檢察官聲請簡易判決處刑書之記\n    載（如附件）。\n二、按刑法第185 條之3 係「抽象危險犯」，不以發生具體危險\n    為必要，另參考德國、美國之認定標準，對於酒精濃度呼氣\n    已達每公升0.55毫克(0.55MG/L)或血液濃度達0.11％以上，\n    肇事率為一般正常人之10倍，已達「不能安全駕駛」之標準\n    ，業據法務部於88年5 月18日以法88檢字第1669號函示甚明\n    。本案被告盧慶讚於接受呼氣酒精濃度檢測時，其呼氣所含\n    酒精濃度值為每公升0.89毫克，有前開酒精濃度呼氣測試報\n    告1 紙附卷可稽，依上開說明，顯已達不能安全駕駛動力交\n    通工具而駕駛之狀態，是本案事證明確，被告犯行堪以認定\n    。核被告盧慶讚所為，係犯刑法第185 條之3 之不能安全駕\n    駛動力交通工具罪。爰審酌被告酒後猶貿然駕駛動力交通工\n    具上路，危害公共安全甚鉅，惟念其無前科紀錄，素行良好\n    ，有臺灣高等法院被告前案紀錄表在卷可考，且犯後坦承犯\n    罪，態度尚稱良好，兼衡其品行、智識程度、生活狀況等一\n    切情狀，量處如主文所示之刑，並諭知易服勞役之折算標準\n    。\n三、依刑事訴訟法第449  條第1 項前段、第3 項、第454 條第2\n    項，刑法第185 條之3 、第42條第3 項前段，刑法施行法第\n    1 條之1 第1 項，逕以簡易判決處刑如主文。\n四、如不服本件判決，得自收受送達之日起10日內，向本院提起\n    上訴狀，上訴於本院管轄之第二審地方法院合議庭。\n中    華    民    國  100     年    3     月    21    日\n\n                  高雄簡易庭  法  官    沈宗興\n以上正本證明與原本無異。\n如不服本判決，應於判決送達之日起10日內向本院提出上訴書狀\n。\n中    華    民    國   100    年    3     月    21    日\n                                書記官  楊雅蘭\n附錄本判決論罪之法條：\n中華民國刑法第185條之3\n服用毒品、麻醉藥品、酒類或其他相類之物，不能安全駕駛動力\n交通工具而駕駛者，處1年以下有期徒刑、拘役或科或併科15萬\n元以下罰金。\n附件：\n臺灣高雄地方法院檢察署檢察官聲請簡易判決處刑書\n                                     100年度偵字第1995號\n    被      告  盧慶讚  男  46歲（民國○○年○月○○日生）\n                        住高雄市○○區○○街119號6樓\n                        國民身分證統一編號：Ｚ000000000號\n上列被告因公共危險案件，業經偵查終結，認宜聲請簡易判決處\n刑，茲將犯罪事實及證據並所犯法條分敘如下：\n        犯罪事實\n一、盧慶讚於民國99年12月21日12時許，先在其位於高雄市○○\n    區○○街119 號6 樓家中飲用2 杯高粱酒，又於同日16時30\n    分許，在上址飲用保力達2 瓶後，已達不能安全駕駛動力車\n    輛之程度，且明知服用酒類後，不能安全駕駛動力交通工具\n    者，不得為駕駛行為，仍於同日19時25分許，騎乘車牌號碼\n    XVK －236 號之普通重型機車離開上揭地點，欲前往附近便\n    利商店買泡麵。嗣其於同日19時35分許，行經高雄市○○區\n    ○○街84號前時，因未戴安全帽而為警攔查，而於同日19時\n    49分許對其施以酒精濃度呼氣測試，測得其呼氣中酒精濃度\n    達每公升0.89毫克，因而查悉上情。\n二、案經高雄市政府警察局三民第二分局報告偵辦。\n        證據並所犯法條\n一、前揭犯罪事實，業據被告盧慶讚於警詢及本署偵訊中均坦承\n    不諱，並有被告之酒精濃度呼氣測試紀錄單、刑法第185 條\n    之3 案件測試觀察紀錄表、高雄市政府警察局舉發違反道路\n    交通管理事件通知單各1 份附卷可資佐證。按刑法第185 條\n    之3 所謂「不能安全駕駛」，係抽象危險犯，並不以發生具\n    體危險為必要，又就醫學文獻所知，酒精對人體之影響程度\n    乃依血中酒精濃度而定，而警方測試器所測得之呼氣酒精濃\n    度乘以200 為當時之血中酒精濃度，當呼氣濃度達每公升0.\n    25毫克時，將造成輕度協調功能降低之輕度酒精中毒症狀，\n    當呼氣濃度達每公升0.55毫克時，將造成反應較慢、感覺降\n    低、影響駕駛等輕到中度之酒精中毒症狀，當呼氣濃度達每\n    公升0.75毫克時，將造成思考改變、個性行為改變等酒精中\n    毒症狀，當呼氣濃度達每公升1.0 毫克時，將造成步態不穩\n    、噁心嘔吐、精神混惑不清晰等中度酒精中毒症狀，此有行\n    政院國軍退除役官兵輔導委員會臺北榮民總醫院88年8 月5\n    日(88)北總內字第26868 號函文可參。且經統計，駕駛人於\n    飲酒後吐氣酒精濃度達每公升0.55毫克以上者，其駕車肇事\n    率為一般正常人之10倍，有法務部法88檢字第1669號函可參\n    可資參照。本件被告經攔檢後所測酒精濃度達每公升0.89毫\n    克，依前揭認定酒後不能安全駕駛一般所採標準之說明，佐\n    以卷附刑法第185條之3案件測試觀察紀錄表記載被告對員警\n    指揮無反應或遲緩，駕駛判斷力顯然欠佳等事實，足認被告\n    已因飲酒導致意識不清，操控車輛能力顯然降低，其駕車時\n    已達不能安全駕駛動力交通工具之程度。綜上所述，本件事\n    證明確，被告罪嫌已堪認定。\n二、核被告所為，係犯刑法第185條之3服用酒類不能安全駕駛動\n    力交通工具而駕駛罪嫌。\n三、依刑事訴訟法第451條第1項聲請逕以簡易判決處刑。\n    此  致\n臺灣高雄地方法院\n中    華    民    國    100   年    1     月    21    日\n                              檢  察  官  王 啟 明\n                              檢  察  官  劉 彥 君\n所犯法條：\n中華民國刑法第185條之3\n服用毒品、麻醉藥品、酒類或其他相類之物，不能安全駕駛動力\n交通工具而駕駛者，處 1 年以下有期徒刑、拘役或科或併科\n15萬元以下罰金。\n附記事項：本件係依刑事訴訟法簡易程序辦理，法院簡易庭得不\n傳喚被告、輔佐人、告訴人、告發人等出庭即以簡易判決處刑；\n被告、被害人、告訴人等對告訴乃論案件如已達成民事和解而要\n撤回告訴或對非告訴乃論案件認有受傳喚到庭陳述意見之必要時\n，請即另以書狀向簡易法庭陳述或請求傳訊。",
  "structure": {
    "main": "盧慶讚犯不能安全駕駛動力交通工具罪，科罰金新臺幣伍萬柒仟\n元，如易服勞役，以新臺幣壹仟元折算壹日。",
    "fact": "一、本件犯罪事實及證據，除犯罪事實欄一、第3 行「2 瓶」應\n    更正為「2 杯」外，均引用檢察官聲請簡易判決處刑書之記\n    載（如附件）。\n二、按刑法第185 條之3 係「抽象危險犯」，不以發生具體危險\n    為必要，另參考德國、美國之認定標準，對於酒精濃度呼氣\n    已達每公升0.55毫克(0.55MG/L)或血液濃度達0.11％以上，\n    肇事率為一般正常人之10倍，已達「不能安全駕駛」之標準\n    ，業據法務部於88年5 月18日以法88檢字第1669號函示甚明\n    。本案被告盧慶讚於接受呼氣酒精濃度檢測時，其呼氣所含\n    酒精濃度值為每公升0.89毫克，有前開酒精濃度呼氣測試報\n    告1 紙附卷可稽，依上開說明，顯已達不能安全駕駛動力交\n    通工具而駕駛之狀態，是本案事證明確，被告犯行堪以認定\n    。核被告盧慶讚所為，係犯刑法第185 條之3 之不能安全駕\n    駛動力交通工具罪。爰審酌被告酒後猶貿然駕駛動力交通工\n    具上路，危害公共安全甚鉅，惟念其無前科紀錄，素行良好\n    ，有臺灣高等法院被告前案紀錄表在卷可考，且犯後坦承犯\n    罪，態度尚稱良好，兼衡其品行、智識程度、生活狀況等一\n    切情狀，量處如主文所示之刑，並諭知易服勞役之折算標準\n    。\n三、依刑事訴訟法第449  條第1 項前段、第3 項、第454 條第2\n    項，刑法第185 條之3 、第42條第3 項前段，刑法施行法第\n    1 條之1 第1 項，逕以簡易判決處刑如主文。\n四、如不服本件判決，得自收受送達之日起10日內，向本院提起\n    上訴狀，上訴於本院管轄之第二審地方法院合議庭。",
    "reason": "一、本件犯罪事實及證據，除犯罪事實欄一、第3 行「2 瓶」應\n    更正為「2 杯」外，均引用檢察官聲請簡易判決處刑書之記\n    載（如附件）。\n二、按刑法第185 條之3 係「抽象危險犯」，不以發生具體危險\n    為必要，另參考德國、美國之認定標準，對於酒精濃度呼氣\n    已達每公升0.55毫克(0.55MG/L)或血液濃度達0.11％以上，\n    肇事率為一般正常人之10倍，已達「不能安全駕駛」之標準\n    ，業據法務部於88年5 月18日以法88檢字第1669號函示甚明\n    。本案被告盧慶讚於接受呼氣酒精濃度檢測時，其呼氣所含\n    酒精濃度值為每公升0.89毫克，有前開酒精濃度呼氣測試報\n    告1 紙附卷可稽，依上開說明，顯已達不能安全駕駛動力交\n    通工具而駕駛之狀態，是本案事證明確，被告犯行堪以認定\n    。核被告盧慶讚所為，係犯刑法第185 條之3 之不能安全駕\n    駛動力交通工具罪。爰審酌被告酒後猶貿然駕駛動力交通工\n    具上路，危害公共安全甚鉅，惟念其無前科紀錄，素行良好\n    ，有臺灣高等法院被告前案紀錄表在卷可考，且犯後坦承犯\n    罪，態度尚稱良好，兼衡其品行、智識程度、生活狀況等一\n    切情狀，量處如主文所示之刑，並諭知易服勞役之折算標準\n    。\n三、依刑事訴訟法第449  條第1 項前段、第3 項、第454 條第2\n    項，刑法第185 條之3 、第42條第3 項前段，刑法施行法第\n    1 條之1 第1 項，逕以簡易判決處刑如主文。\n四、如不服本件判決，得自收受送達之日起10日內，向本院提起\n    上訴狀，上訴於本院管轄之第二審地方法院合議庭。"
  },
  "search": "臺灣高雄地方法院刑事簡易判決100年度交簡字第823號聲請人臺灣高雄地方法院檢察署檢察官被告盧慶讚上列被告因公共危險案件，經檢察官聲請以簡易判決處刑（100年度偵字第1995號），本院判決如下：主文盧慶讚犯不能安全駕駛動力交通工具罪，科罰金新臺幣伍萬柒仟元，如易服勞役，以新臺幣壹仟元折算壹日。事實及理由一、本件犯罪事實及證據，除犯罪事實欄一、第3行「2瓶」應更正為「2杯」外，均引用檢察官聲請簡易判決處刑書之記載（如附件）。二、按刑法第185條之3係「抽象危險犯」，不以發生具體危險為必要，另參考德國、美國之認定標準，對於酒精濃度呼氣已達每公升0.55毫克(0.55MG/L)或血液濃度達0.11％以上，肇事率為一般正常人之10倍，已達「不能安全駕駛」之標準，業據法務部於88年5月18日以法88檢字第1669號函示甚明。本案被告盧慶讚於接受呼氣酒精濃度檢測時，其呼氣所含酒精濃度值為每公升0.89毫克，有前開酒精濃度呼氣測試報告1紙附卷可稽，依上開說明，顯已達不能安全駕駛動力交通工具而駕駛之狀態，是本案事證明確，被告犯行堪以認定。核被告盧慶讚所為，係犯刑法第185條之3之不能安全駕駛動力交通工具罪。爰審酌被告酒後猶貿然駕駛動力交通工具上路，危害公共安全甚鉅，惟念其無前科紀錄，素行良好，有臺灣高等法院被告前案紀錄表在卷可考，且犯後坦承犯罪，態度尚稱良好，兼衡其品行、智識程度、生活狀況等一切情狀，量處如主文所示之刑，並諭知易服勞役之折算標準。三、依刑事訴訟法第449條第1項前段、第3項、第454條第2項，刑法第185條之3、第42條第3項前段，刑法施行法第1條之1第1項，逕以簡易判決處刑如主文。四、如不服本件判決，得自收受送達之日起10日內，向本院提起上訴狀，上訴於本院管轄之第二審地方法院合議庭。中華民國100年3月21日高雄簡易庭法官沈宗興以上正本證明與原本無異。如不服本判決，應於判決送達之日起10日內向本院提出上訴書狀。中華民國100年3月21日書記官楊雅蘭附錄本判決論罪之法條：中華民國刑法第185條之3服用毒品、麻醉藥品、酒類或其他相類之物，不能安全駕駛動力交通工具而駕駛者，處1年以下有期徒刑、拘役或科或併科15萬元以下罰金。附件：臺灣高雄地方法院檢察署檢察官聲請簡易判決處刑書100年度偵字第1995號被告盧慶讚男46歲（民國○○年○月○○日生）住高雄市○○區○○街119號6樓國民身分證統一編號：Ｚ000000000號上列被告因公共危險案件，業經偵查終結，認宜聲請簡易判決處刑，茲將犯罪事實及證據並所犯法條分敘如下：犯罪事實一、盧慶讚於民國99年12月21日12時許，先在其位於高雄市○○區○○街119號6樓家中飲用2杯高粱酒，又於同日16時30分許，在上址飲用保力達2瓶後，已達不能安全駕駛動力車輛之程度，且明知服用酒類後，不能安全駕駛動力交通工具者，不得為駕駛行為，仍於同日19時25分許，騎乘車牌號碼XVK－236號之普通重型機車離開上揭地點，欲前往附近便利商店買泡麵。嗣其於同日19時35分許，行經高雄市○○區○○街84號前時，因未戴安全帽而為警攔查，而於同日19時49分許對其施以酒精濃度呼氣測試，測得其呼氣中酒精濃度達每公升0.89毫克，因而查悉上情。二、案經高雄市政府警察局三民第二分局報告偵辦。證據並所犯法條一、前揭犯罪事實，業據被告盧慶讚於警詢及本署偵訊中均坦承不諱，並有被告之酒精濃度呼氣測試紀錄單、刑法第185條之3案件測試觀察紀錄表、高雄市政府警察局舉發違反道路交通管理事件通知單各1份附卷可資佐證。按刑法第185條之3所謂「不能安全駕駛」，係抽象危險犯，並不以發生具體危險為必要，又就醫學文獻所知，酒精對人體之影響程度乃依血中酒精濃度而定，而警方測試器所測得之呼氣酒精濃度乘以200為當時之血中酒精濃度，當呼氣濃度達每公升0.25毫克時，將造成輕度協調功能降低之輕度酒精中毒症狀，當呼氣濃度達每公升0.55毫克時，將造成反應較慢、感覺降低、影響駕駛等輕到中度之酒精中毒症狀，當呼氣濃度達每公升0.75毫克時，將造成思考改變、個性行為改變等酒精中毒症狀，當呼氣濃度達每公升1.0毫克時，將造成步態不穩、噁心嘔吐、精神混惑不清晰等中度酒精中毒症狀，此有行政院國軍退除役官兵輔導委員會臺北榮民總醫院88年8月5日(88)北總內字第26868號函文可參。且經統計，駕駛人於飲酒後吐氣酒精濃度達每公升0.55毫克以上者，其駕車肇事率為一般正常人之10倍，有法務部法88檢字第1669號函可參可資參照。本件被告經攔檢後所測酒精濃度達每公升0.89毫克，依前揭認定酒後不能安全駕駛一般所採標準之說明，佐以卷附刑法第185條之3案件測試觀察紀錄表記載被告對員警指揮無反應或遲緩，駕駛判斷力顯然欠佳等事實，足認被告已因飲酒導致意識不清，操控車輛能力顯然降低，其駕車時已達不能安全駕駛動力交通工具之程度。綜上所述，本件事證明確，被告罪嫌已堪認定。二、核被告所為，係犯刑法第185條之3服用酒類不能安全駕駛動力交通工具而駕駛罪嫌。三、依刑事訴訟法第451條第1項聲請逕以簡易判決處刑。此致臺灣高雄地方法院中華民國100年1月21日檢察官王啟明檢察官劉彥君所犯法條：中華民國刑法第185條之3服用毒品、麻醉藥品、酒類或其他相類之物，不能安全駕駛動力交通工具而駕駛者，處1年以下有期徒刑、拘役或科或併科15萬元以下罰金。附記事項：本件係依刑事訴訟法簡易程序辦理，法院簡易庭得不傳喚被告、輔佐人、告訴人、告發人等出庭即以簡易判決處刑；被告、被害人、告訴人等對告訴乃論案件如已達成民事和解而要撤回告訴或對非告訴乃論案件認有受傳喚到庭陳述意見之必要時，請即另以書狀向簡易法庭陳述或請求傳訊。",
  "characters": {
    "judges": [
      "沈宗興"
    ],
    "prosecutors": [

    ],
    "lawyers": [

    ],
    "clerks": [
      "楊雅蘭"
    ],
    "plaintiffs": [

    ],
    "defendants": [
      "盧慶讚",
      "盧慶讚  男  46歲（民國○○年○月○○日生）"
    ],
    "prosecutor_office": [
      "臺灣高雄地方法院檢察署檢察官"
    ],
    "creditors": [

    ],
    "debtors": [

    ],
    "judicial_associate_officer": [

    ]
  },
  "adjudged_at": "2011-03-21",
  "created_at": "2016-02-13 21:49:33",
  "updated_at": "2016-02-13 21:49:33"
}