{
  "identify": "ULD-100-易-87-20110321-1",
  "court": {
    "name": "臺灣雲林地方法院",
    "code": "ULD"
  },
  "division": {
    "name": "刑事",
    "code": "M"
  },
  "year": 100,
  "word": "易",
  "number": "87",
  "jcheck": "1",
  "reason": "違反槍砲彈藥刀械管制條例",
  "content": "臺灣雲林地方法院刑事判決               100年度易字第87號\n公  訴  人  臺灣雲林地方法院檢察署檢察官\n被      告  汪世豐\n上列被告因違反槍砲彈藥刀械管制條例案件，經檢察官提起公訴\n（100年度偵字第23 號），於本院準備程序進行中，被告就被訴\n事實為有罪之陳述，經裁定進行簡式審判程序，判決如下：\n    主  文\n汪世豐犯非法持有刀械罪，處拘役拾日，如易科罰金，以新臺\n幣壹仟元折算壹日。扣案之手指虎壹支沒收。\n    事  實\n一、汪世豐於民國90年或91年間某日，在網路上以新臺幣200 元\n    之代價，向不詳人士購買槍砲彈藥刀械管制條例所管制之手\n    指虎刀械1 支，並自斯時起，即未經許可持有之。嗣警因另\n    案持搜索票於99年8 月8 日下午4 時50分許，在汪世豐當時\n    位於雲林縣二崙鄉永定村永定計59號電信公司電桿後方鐵皮\n    貨櫃屋之居所內，查扣前揭鐵製手指虎1 支，查悉上情。\n二、案經雲林縣警察局移送臺灣雲林地方法院檢察署檢察官偵查\n    起訴。\n    理  由\n一、本件被告汪世豐所犯之罪，非死刑、無期徒刑、最輕本刑為\n    3 年以上有期徒刑之罪或高等法院管轄第一審之案件，其於\n    準備程序進行中，就前揭被訴事實為有罪之陳述，經受命法\n    官告以簡式審判程序之旨，並聽取其與公訴人之意見後，本\n    院認無不得或不宜改依簡式審判程序進行之情事，依刑事訴\n    訟法第273 條之1 第1 項、第284 條之1 規定，裁定本件由\n    受命法官獨任進行簡式審判程序，是本件之證據調查，依刑\n    事訴訟法第273 條之2 規定，不受同法第159 條第1 項、第\n    161 條之2 、第161 條之3 、第163 條之1 及第164 條至第\n    170 條規定之限制，合先敘明。\n二、上揭犯罪事實，迭據被告汪世豐於警詢、偵查及本院審理中\n    坦承不諱（見警卷第2 頁、偵卷第11頁、本院卷第29頁、第\n    32頁反面），復有本院99年度聲搜字第386 號搜索票、雲林\n    縣警察局搜索扣押筆錄、扣押物品目錄表各1 份及蒐證照片\n    4 張附卷可稽（見警卷第9 頁至第15頁），並有扣案之手指\n    虎1 支可資佐證，足認被告上開任意性自白與事實相符，堪\n    信為真。而該手指虎為鐵製，依其形狀確係槍砲彈藥刀械管\n    制條例第4 條第1 項第3 款所指之手指虎一節，業據本院當\n    庭勘驗該手指虎並核對與上開條例所附圖例(四)手指虎相符（\n    見本院卷第29頁反面、第18頁），且經雲林縣警察局鑑定結\n    果亦持相同之認定，有該分局99年12月23日雲警保字第0990\n    200577號函暨所附之刀械鑑驗表1 份在卷足參（見偵卷第6\n    頁至第7 頁），本件事證明確，被告犯行堪以認定，自應依\n    法論科。\n三、核被告所為，係犯槍砲彈藥刀械管制條例第14條第3 項之未\n    經許可持有刀械罪。爰審酌以扣案手指虎外觀而言，可認並\n    非純供觀賞之用，被告無端持有該管制物品，實不足取，惟\n    該手指虎為警查獲時係置放於房間內而非隨身攜帶，對社會\n    之危害尚屬輕微，犯罪情節非鉅，且被告自陳是因為在網頁\n    上看到，覺得新奇才購買，購買之後未曾持之使用等語（見\n    本院卷第32頁反面、第33頁），參之被告前未曾有過傷害他\n    人身體之前科，有臺灣高等法院被告前案紀錄表1 份在卷可\n    考，可見被告之品性尚可，復衡酌被告犯後坦承犯行，態度\n    良好，具有悔意，又被告自陳現與父母、兄嫂及配偶同住，\n    並育有年僅6 、7 個月大之幼子，配偶沒有工作，自己以運\n    輸蔬菜為業，其每月約有4 、5 萬元之收入（見本院卷第33\n    頁正反面），家庭狀況小康及被告國中畢業之智識程度（見\n    警詢調查筆錄「受詢問人」欄所載）等一切情狀，量處如主\n    文所示之刑，並諭知易科罰金之折算標準。扣案之手指虎1\n    支為違禁物，爰依刑法第38條第1 項第1 款之規定，宣告沒\n    收。\n據上論斷，應依刑事訴訟法第273 條之1 第1 項、第299 條第1\n項前段，槍砲彈藥刀械管制條例第14條第3 項，刑法第11條前段\n、第41條第1 項前段、第38條第1 項第1 款，判決如主文。\n本案經檢察官江柏青到庭執行職務。\n中    華    民    國   100    年    3     月    21    日\n                  刑事第五庭    法  官  段奇琬\n以上正本證明與原本無異。\n如不服本判決應於收受判決後10日內向本院提出上訴書狀，並應\n敘述具體理由；其未敘述上訴理由者，應於上訴期間屆滿後20日\n內向本院補提理由書（均須按他造當事人之人數附繕本）。「切\n勿逕送上級法院」。\n                                書記官  高培馨\n中    華    民    國   100    年    3     月    21    日\n附錄本件論罪科刑法條全文：\n槍砲彈藥刀械管制條例第14條\n未經許可，製造、販賣或運輸刀械者，處 3 年以下有期徒刑，\n併科新台幣100 萬元以下罰金。\n意圖供自己或他人犯罪之用，而犯前項之罪者，處 6 月以上 5\n年以下有期徒刑，併科新台幣 300 萬元以下罰金。\n未經許可，持有或意圖販賣而陳列刀械者，處 1 年以下有期徒\n刑、拘役或新台幣 50 萬元以下罰金。\n第 1 項及第 2 項之未遂犯罰之。",
  "structure": {
    "main": "汪世豐犯非法持有刀械罪，處拘役拾日，如易科罰金，以新臺\n幣壹仟元折算壹日。扣案之手指虎壹支沒收。",
    "fact": "一、汪世豐於民國90年或91年間某日，在網路上以新臺幣200 元\n    之代價，向不詳人士購買槍砲彈藥刀械管制條例所管制之手\n    指虎刀械1 支，並自斯時起，即未經許可持有之。嗣警因另\n    案持搜索票於99年8 月8 日下午4 時50分許，在汪世豐當時\n    位於雲林縣二崙鄉永定村永定計59號電信公司電桿後方鐵皮\n    貨櫃屋之居所內，查扣前揭鐵製手指虎1 支，查悉上情。\n二、案經雲林縣警察局移送臺灣雲林地方法院檢察署檢察官偵查\n    起訴。",
    "reason": "一、本件被告汪世豐所犯之罪，非死刑、無期徒刑、最輕本刑為\n    3 年以上有期徒刑之罪或高等法院管轄第一審之案件，其於\n    準備程序進行中，就前揭被訴事實為有罪之陳述，經受命法\n    官告以簡式審判程序之旨，並聽取其與公訴人之意見後，本\n    院認無不得或不宜改依簡式審判程序進行之情事，依刑事訴\n    訟法第273 條之1 第1 項、第284 條之1 規定，裁定本件由\n    受命法官獨任進行簡式審判程序，是本件之證據調查，依刑\n    事訴訟法第273 條之2 規定，不受同法第159 條第1 項、第\n    161 條之2 、第161 條之3 、第163 條之1 及第164 條至第\n    170 條規定之限制，合先敘明。\n二、上揭犯罪事實，迭據被告汪世豐於警詢、偵查及本院審理中\n    坦承不諱（見警卷第2 頁、偵卷第11頁、本院卷第29頁、第\n    32頁反面），復有本院99年度聲搜字第386 號搜索票、雲林\n    縣警察局搜索扣押筆錄、扣押物品目錄表各1 份及蒐證照片\n    4 張附卷可稽（見警卷第9 頁至第15頁），並有扣案之手指\n    虎1 支可資佐證，足認被告上開任意性自白與事實相符，堪\n    信為真。而該手指虎為鐵製，依其形狀確係槍砲彈藥刀械管\n    制條例第4 條第1 項第3 款所指之手指虎一節，業據本院當\n    庭勘驗該手指虎並核對與上開條例所附圖例(四)手指虎相符（\n    見本院卷第29頁反面、第18頁），且經雲林縣警察局鑑定結\n    果亦持相同之認定，有該分局99年12月23日雲警保字第0990\n    200577號函暨所附之刀械鑑驗表1 份在卷足參（見偵卷第6\n    頁至第7 頁），本件事證明確，被告犯行堪以認定，自應依\n    法論科。\n三、核被告所為，係犯槍砲彈藥刀械管制條例第14條第3 項之未\n    經許可持有刀械罪。爰審酌以扣案手指虎外觀而言，可認並\n    非純供觀賞之用，被告無端持有該管制物品，實不足取，惟\n    該手指虎為警查獲時係置放於房間內而非隨身攜帶，對社會\n    之危害尚屬輕微，犯罪情節非鉅，且被告自陳是因為在網頁\n    上看到，覺得新奇才購買，購買之後未曾持之使用等語（見\n    本院卷第32頁反面、第33頁），參之被告前未曾有過傷害他\n    人身體之前科，有臺灣高等法院被告前案紀錄表1 份在卷可\n    考，可見被告之品性尚可，復衡酌被告犯後坦承犯行，態度\n    良好，具有悔意，又被告自陳現與父母、兄嫂及配偶同住，\n    並育有年僅6 、7 個月大之幼子，配偶沒有工作，自己以運\n    輸蔬菜為業，其每月約有4 、5 萬元之收入（見本院卷第33\n    頁正反面），家庭狀況小康及被告國中畢業之智識程度（見\n    警詢調查筆錄「受詢問人」欄所載）等一切情狀，量處如主\n    文所示之刑，並諭知易科罰金之折算標準。扣案之手指虎1\n    支為違禁物，爰依刑法第38條第1 項第1 款之規定，宣告沒\n    收。\n據上論斷，應依刑事訴訟法第273 條之1 第1 項、第299 條第1\n項前段，槍砲彈藥刀械管制條例第14條第3 項，刑法第11條前段\n、第41條第1 項前段、第38條第1 項第1 款，判決如主文。\n本案經檢察官江柏青到庭執行職務。\n中    華    民    國   100    年    3     月    21    日\n                  刑事第五庭    法  官  段奇琬\n以上正本證明與原本無異。\n如不服本判決應於收受判決後10日內向本院提出上訴書狀，並應\n敘述具體理由；其未敘述上訴理由者，應於上訴期間屆滿後20日\n內向本院補提理由書（均須按他造當事人之人數附繕本）。「切\n勿逕送上級法院」。\n                                書記官  高培馨"
  },
  "search": "臺灣雲林地方法院刑事判決100年度易字第87號公訴人臺灣雲林地方法院檢察署檢察官被告汪世豐上列被告因違反槍砲彈藥刀械管制條例案件，經檢察官提起公訴（100年度偵字第23號），於本院準備程序進行中，被告就被訴事實為有罪之陳述，經裁定進行簡式審判程序，判決如下：主文汪世豐犯非法持有刀械罪，處拘役拾日，如易科罰金，以新臺幣壹仟元折算壹日。扣案之手指虎壹支沒收。事實一、汪世豐於民國90年或91年間某日，在網路上以新臺幣200元之代價，向不詳人士購買槍砲彈藥刀械管制條例所管制之手指虎刀械1支，並自斯時起，即未經許可持有之。嗣警因另案持搜索票於99年8月8日下午4時50分許，在汪世豐當時位於雲林縣二崙鄉永定村永定計59號電信公司電桿後方鐵皮貨櫃屋之居所內，查扣前揭鐵製手指虎1支，查悉上情。二、案經雲林縣警察局移送臺灣雲林地方法院檢察署檢察官偵查起訴。理由一、本件被告汪世豐所犯之罪，非死刑、無期徒刑、最輕本刑為3年以上有期徒刑之罪或高等法院管轄第一審之案件，其於準備程序進行中，就前揭被訴事實為有罪之陳述，經受命法官告以簡式審判程序之旨，並聽取其與公訴人之意見後，本院認無不得或不宜改依簡式審判程序進行之情事，依刑事訴訟法第273條之1第1項、第284條之1規定，裁定本件由受命法官獨任進行簡式審判程序，是本件之證據調查，依刑事訴訟法第273條之2規定，不受同法第159條第1項、第161條之2、第161條之3、第163條之1及第164條至第170條規定之限制，合先敘明。二、上揭犯罪事實，迭據被告汪世豐於警詢、偵查及本院審理中坦承不諱（見警卷第2頁、偵卷第11頁、本院卷第29頁、第32頁反面），復有本院99年度聲搜字第386號搜索票、雲林縣警察局搜索扣押筆錄、扣押物品目錄表各1份及蒐證照片4張附卷可稽（見警卷第9頁至第15頁），並有扣案之手指虎1支可資佐證，足認被告上開任意性自白與事實相符，堪信為真。而該手指虎為鐵製，依其形狀確係槍砲彈藥刀械管制條例第4條第1項第3款所指之手指虎一節，業據本院當庭勘驗該手指虎並核對與上開條例所附圖例(四)手指虎相符（見本院卷第29頁反面、第18頁），且經雲林縣警察局鑑定結果亦持相同之認定，有該分局99年12月23日雲警保字第0990200577號函暨所附之刀械鑑驗表1份在卷足參（見偵卷第6頁至第7頁），本件事證明確，被告犯行堪以認定，自應依法論科。三、核被告所為，係犯槍砲彈藥刀械管制條例第14條第3項之未經許可持有刀械罪。爰審酌以扣案手指虎外觀而言，可認並非純供觀賞之用，被告無端持有該管制物品，實不足取，惟該手指虎為警查獲時係置放於房間內而非隨身攜帶，對社會之危害尚屬輕微，犯罪情節非鉅，且被告自陳是因為在網頁上看到，覺得新奇才購買，購買之後未曾持之使用等語（見本院卷第32頁反面、第33頁），參之被告前未曾有過傷害他人身體之前科，有臺灣高等法院被告前案紀錄表1份在卷可考，可見被告之品性尚可，復衡酌被告犯後坦承犯行，態度良好，具有悔意，又被告自陳現與父母、兄嫂及配偶同住，並育有年僅6、7個月大之幼子，配偶沒有工作，自己以運輸蔬菜為業，其每月約有4、5萬元之收入（見本院卷第33頁正反面），家庭狀況小康及被告國中畢業之智識程度（見警詢調查筆錄「受詢問人」欄所載）等一切情狀，量處如主文所示之刑，並諭知易科罰金之折算標準。扣案之手指虎1支為違禁物，爰依刑法第38條第1項第1款之規定，宣告沒收。據上論斷，應依刑事訴訟法第273條之1第1項、第299條第1項前段，槍砲彈藥刀械管制條例第14條第3項，刑法第11條前段、第41條第1項前段、第38條第1項第1款，判決如主文。本案經檢察官江柏青到庭執行職務。中華民國100年3月21日刑事第五庭法官段奇琬以上正本證明與原本無異。如不服本判決應於收受判決後10日內向本院提出上訴書狀，並應敘述具體理由；其未敘述上訴理由者，應於上訴期間屆滿後20日內向本院補提理由書（均須按他造當事人之人數附繕本）。「切勿逕送上級法院」。書記官高培馨中華民國100年3月21日附錄本件論罪科刑法條全文：槍砲彈藥刀械管制條例第14條未經許可，製造、販賣或運輸刀械者，處3年以下有期徒刑，併科新台幣100萬元以下罰金。意圖供自己或他人犯罪之用，而犯前項之罪者，處6月以上5年以下有期徒刑，併科新台幣300萬元以下罰金。未經許可，持有或意圖販賣而陳列刀械者，處1年以下有期徒刑、拘役或新台幣50萬元以下罰金。第1項及第2項之未遂犯罰之。",
  "characters": {
    "judges": [
      "段奇琬"
    ],
    "prosecutors": [
      "江柏青"
    ],
    "lawyers": [

    ],
    "clerks": [
      "高培馨"
    ],
    "plaintiffs": [

    ],
    "defendants": [
      "汪世豐"
    ],
    "prosecutor_office": [
      "臺灣雲林地方法院檢察署檢察官"
    ],
    "creditors": [

    ],
    "debtors": [

    ],
    "judicial_associate_officer": [

    ]
  },
  "adjudged_at": "2011-03-21",
  "created_at": "2016-02-13 21:45:36",
  "updated_at": "2016-02-13 21:45:36"
}