{
  "identify": "CHD-94-訴-1394-20051108-1",
  "court": {
    "name": "臺灣彰化地方法院",
    "code": "CHD"
  },
  "division": {
    "name": "刑事",
    "code": "M"
  },
  "year": 94,
  "word": "訴",
  "number": "1394",
  "jcheck": "1",
  "reason": "毒品危害防制條例",
  "content": "臺灣彰化地方法院刑事判決              94年度訴字第1394號\n公  訴  人  臺灣彰化地方法院檢察署檢察官\n被      告  甲○○\n上列被告因違反毒品危害防制條例案件，經檢察官提起公訴（94\n年度毒偵字第3569號），本院判決如下：\n    主  文\n本件公訴不受理。\n    理  由\n一、公訴意旨略以：被告甲○○前因施用毒品案件，由臺灣彰化\n    地方法院檢察署檢察官聲請裁定送強制戒治，於民國93年1\n    月9 日釋放出所；又因竊盜案件，經本院以90年度易字第14\n    95號判決判處有期徒刑6 月確定；另因施用毒品案件，經本\n    院以92年度訴字第265 號判決判處有期徒刑9 月確定，上開\n    2 罪刑接續執行，於93年10月6 日縮短刑期假釋付保護管束\n    ，並於93年12月25日假釋期滿未經撤銷視為徒刑執行完畢。\n    再因施用第一、二級毒品案件，由本院於94年6 月30日以94\n    年度訴字第769 號判決分別判處有期徒刑10月、3 月，定應\n    執行有期徒刑11月，甫於94年7 月25日確定。詎仍不知悔改\n    ，在上開判決宣示判決後，復基於施用第一級毒品海洛因之\n    概括犯意，自94年7 月1 日某時起，迄同年月12日晚上10時\n    許止，在彰化縣和美鎮○○路81號其住所，以將海洛因置於\n    針筒內注射之方式，連續施用第一級毒品海洛因多次；另基\n    於施用第二級毒品甲基安非他命之犯意，於94年7 月5日 某\n    時許，亦在上址以將甲基安非他命置於錫箔紙上點火燃燒吸\n    食煙氣之方式，施用第二級毒品甲基安非他命1 次。嗣於94\n    年7 月13日晚上7 時許，在彰化縣和美鎮○○路巷口，因形\n    跡可疑為警盤詰查獲，並當場扣得第一級毒品海洛因2 包（\n    毛重各為0.9 公克、0.5 公克）、第二級毒品安非他命1 包\n    （毛重0.3 公克）及其所有供施用海洛因使用之注射針筒2\n    支。因認被告涉犯毒品危害防制條例第10條第1 、2 項之施\n    用第一、二級毒品罪嫌。\n二、按被告死亡者，應諭知不受理之判決，並得不經言詞辯論為\n    之，刑事訴訟法第303條第5款、第307 條分別定有明文。經\n    查：被告甲○○業於94年10月7 日死亡，此有彰化縣警察局\n    二林分局94年10月31日林警分偵字第0940013924號函及法務\n    部戶役政連結作業系統個人基本資料各1 份附卷可稽。揆諸\n    上開說明，爰不經言詞辯論，諭知不受理之判決。\n三、至臺灣彰化地方法院檢察署以94年8 月15日彰檢榮禮94毒偵\n    3899字第32001 號、彰檢榮禮94毒偵4045字32000 號函、94\n    年10月13日彰檢榮法94毒偵4796字第40916 號函移送併辦（\n    即臺灣彰化地方法院檢察署94年度毒偵字第3899、4045、47\n    96號）之被告所涉施用第一、二級毒品罪嫌部分，因前開起\n    訴部分既經本院為不受理判決，即難認移送併辦部分與起訴\n    部分有何連續犯之裁判上一罪關係，而為起訴效力所及，本\n    院已無從併案審理，應退回由檢察官為妥適處理，附此敘明\n    。\n據上論斷，應依刑事訴訟法第303條第5款、第307 條，判決如主\n文。\n中    華    民    國    94    年    11    月    8     日\n                  刑事第一庭    審判長法  官  周淡怡\n                                      法  官  許旭聖\n                                      法  官  吳永梁\n以上正本證明與原本無異。\n如不服本判決，應於判決送達後10日內，向本院提出上訴狀（須\n附繕本）。\n中    華    民    國    94    年    11    月    10    日\n                                      書記官  陳美敏\n",
  "structure": {
    "main": "本件公訴不受理。",
    "reason": "一、公訴意旨略以：被告甲○○前因施用毒品案件，由臺灣彰化\n    地方法院檢察署檢察官聲請裁定送強制戒治，於民國93年1\n    月9 日釋放出所；又因竊盜案件，經本院以90年度易字第14\n    95號判決判處有期徒刑6 月確定；另因施用毒品案件，經本\n    院以92年度訴字第265 號判決判處有期徒刑9 月確定，上開\n    2 罪刑接續執行，於93年10月6 日縮短刑期假釋付保護管束\n    ，並於93年12月25日假釋期滿未經撤銷視為徒刑執行完畢。\n    再因施用第一、二級毒品案件，由本院於94年6 月30日以94\n    年度訴字第769 號判決分別判處有期徒刑10月、3 月，定應\n    執行有期徒刑11月，甫於94年7 月25日確定。詎仍不知悔改\n    ，在上開判決宣示判決後，復基於施用第一級毒品海洛因之\n    概括犯意，自94年7 月1 日某時起，迄同年月12日晚上10時\n    許止，在彰化縣和美鎮○○路81號其住所，以將海洛因置於\n    針筒內注射之方式，連續施用第一級毒品海洛因多次；另基\n    於施用第二級毒品甲基安非他命之犯意，於94年7 月5日 某\n    時許，亦在上址以將甲基安非他命置於錫箔紙上點火燃燒吸\n    食煙氣之方式，施用第二級毒品甲基安非他命1 次。嗣於94\n    年7 月13日晚上7 時許，在彰化縣和美鎮○○路巷口，因形\n    跡可疑為警盤詰查獲，並當場扣得第一級毒品海洛因2 包（\n    毛重各為0.9 公克、0.5 公克）、第二級毒品安非他命1 包\n    （毛重0.3 公克）及其所有供施用海洛因使用之注射針筒2\n    支。因認被告涉犯毒品危害防制條例第10條第1 、2 項之施\n    用第一、二級毒品罪嫌。\n二、按被告死亡者，應諭知不受理之判決，並得不經言詞辯論為\n    之，刑事訴訟法第303條第5款、第307 條分別定有明文。經\n    查：被告甲○○業於94年10月7 日死亡，此有彰化縣警察局\n    二林分局94年10月31日林警分偵字第0940013924號函及法務\n    部戶役政連結作業系統個人基本資料各1 份附卷可稽。揆諸\n    上開說明，爰不經言詞辯論，諭知不受理之判決。\n三、至臺灣彰化地方法院檢察署以94年8 月15日彰檢榮禮94毒偵\n    3899字第32001 號、彰檢榮禮94毒偵4045字32000 號函、94\n    年10月13日彰檢榮法94毒偵4796字第40916 號函移送併辦（\n    即臺灣彰化地方法院檢察署94年度毒偵字第3899、4045、47\n    96號）之被告所涉施用第一、二級毒品罪嫌部分，因前開起\n    訴部分既經本院為不受理判決，即難認移送併辦部分與起訴\n    部分有何連續犯之裁判上一罪關係，而為起訴效力所及，本\n    院已無從併案審理，應退回由檢察官為妥適處理，附此敘明\n    。\n據上論斷，應依刑事訴訟法第303條第5款、第307 條，判決如主\n文。"
  },
  "search": "臺灣彰化地方法院刑事判決94年度訴字第1394號公訴人臺灣彰化地方法院檢察署檢察官被告甲○○上列被告因違反毒品危害防制條例案件，經檢察官提起公訴（94年度毒偵字第3569號），本院判決如下：主文本件公訴不受理。理由一、公訴意旨略以：被告甲○○前因施用毒品案件，由臺灣彰化地方法院檢察署檢察官聲請裁定送強制戒治，於民國93年1月9日釋放出所；又因竊盜案件，經本院以90年度易字第1495號判決判處有期徒刑6月確定；另因施用毒品案件，經本院以92年度訴字第265號判決判處有期徒刑9月確定，上開2罪刑接續執行，於93年10月6日縮短刑期假釋付保護管束，並於93年12月25日假釋期滿未經撤銷視為徒刑執行完畢。再因施用第一、二級毒品案件，由本院於94年6月30日以94年度訴字第769號判決分別判處有期徒刑10月、3月，定應執行有期徒刑11月，甫於94年7月25日確定。詎仍不知悔改，在上開判決宣示判決後，復基於施用第一級毒品海洛因之概括犯意，自94年7月1日某時起，迄同年月12日晚上10時許止，在彰化縣和美鎮○○路81號其住所，以將海洛因置於針筒內注射之方式，連續施用第一級毒品海洛因多次；另基於施用第二級毒品甲基安非他命之犯意，於94年7月5日某時許，亦在上址以將甲基安非他命置於錫箔紙上點火燃燒吸食煙氣之方式，施用第二級毒品甲基安非他命1次。嗣於94年7月13日晚上7時許，在彰化縣和美鎮○○路巷口，因形跡可疑為警盤詰查獲，並當場扣得第一級毒品海洛因2包（毛重各為0.9公克、0.5公克）、第二級毒品安非他命1包（毛重0.3公克）及其所有供施用海洛因使用之注射針筒2支。因認被告涉犯毒品危害防制條例第10條第1、2項之施用第一、二級毒品罪嫌。二、按被告死亡者，應諭知不受理之判決，並得不經言詞辯論為之，刑事訴訟法第303條第5款、第307條分別定有明文。經查：被告甲○○業於94年10月7日死亡，此有彰化縣警察局二林分局94年10月31日林警分偵字第0940013924號函及法務部戶役政連結作業系統個人基本資料各1份附卷可稽。揆諸上開說明，爰不經言詞辯論，諭知不受理之判決。三、至臺灣彰化地方法院檢察署以94年8月15日彰檢榮禮94毒偵3899字第32001號、彰檢榮禮94毒偵4045字32000號函、94年10月13日彰檢榮法94毒偵4796字第40916號函移送併辦（即臺灣彰化地方法院檢察署94年度毒偵字第3899、4045、4796號）之被告所涉施用第一、二級毒品罪嫌部分，因前開起訴部分既經本院為不受理判決，即難認移送併辦部分與起訴部分有何連續犯之裁判上一罪關係，而為起訴效力所及，本院已無從併案審理，應退回由檢察官為妥適處理，附此敘明。據上論斷，應依刑事訴訟法第303條第5款、第307條，判決如主文。中華民國94年11月8日刑事第一庭審判長法官周淡怡法官許旭聖法官吳永梁以上正本證明與原本無異。如不服本判決，應於判決送達後10日內，向本院提出上訴狀（須附繕本）。中華民國94年11月10日書記官陳美敏",
  "characters": {
    "judges": [
      "周淡怡",
      "許旭聖",
      "吳永梁"
    ],
    "prosecutors": [

    ],
    "lawyers": [

    ],
    "clerks": [
      "陳美敏"
    ],
    "plaintiffs": [

    ],
    "defendants": [
      "甲○○"
    ],
    "prosecutor_office": [
      "臺灣彰化地方法院檢察署檢察官"
    ],
    "creditors": [

    ],
    "debtors": [

    ],
    "judicial_associate_officer": [

    ]
  },
  "adjudged_at": "2005-11-08",
  "created_at": "2016-02-07 00:27:01",
  "updated_at": "2016-02-07 00:27:01"
}