{
  "identify": "KSD-94-訴-2716-20051107-4",
  "court": {
    "name": "臺灣高雄地方法院",
    "code": "KSD"
  },
  "division": {
    "name": "刑事",
    "code": "M"
  },
  "year": 94,
  "word": "訴",
  "number": "2716",
  "jcheck": "4",
  "reason": "搶奪等",
  "content": "臺灣高雄地方法院刑事裁定              94年度訴字第2716號\n公  訴  人  臺灣高雄地方法院檢察署檢察官\n被      告  甲○○\n上列被告因詐欺等案件，本院裁定如下：\n    主  文\n甲○○自民國玖拾肆年拾壹月玖日起延長羈押貳月。\n    理  由\n一、被告甲○○因詐欺等案件，經本院認為所犯刑法第339 條第\n    1 項之詐欺取財罪、刑法第346 條第1 項之恐嚇取財罪之犯\n    罪嫌疑重大，且有事實足認有反覆實施同一犯罪之虞，而有\n    羈押之必要，依刑事訴訟法第101 條之1 第5 款、第7 款及\n    第8 款之規定，於民國94年8月9日執行羈押。\n二、茲本院以羈押期間，即將屆滿，其羈押原因仍然存在，且有\n    繼續羈押之必要，應自民國94年11月9 日起，再延長羈押二\n    月，爰依刑事訴訟法第108 條第1 項、第2 項裁定如主文。\n中    華    民    國    94    年    11    月    7     日\n                 刑事第14庭審判長法  官  蔡廣昇\n                                 法  官  林瑋桓\n                                 法  官  紀凱峰\n以上正本證明與原本無異。\n如不服本裁定，應於收受送達後5 日內向本院提出抗告狀。\n中    華    民    國    94    年    11    月    7     日\n                                 書記官  黃進遠\n",
  "structure": {
    "main": "甲○○自民國玖拾肆年拾壹月玖日起延長羈押貳月。",
    "reason": "一、被告甲○○因詐欺等案件，經本院認為所犯刑法第339 條第\n    1 項之詐欺取財罪、刑法第346 條第1 項之恐嚇取財罪之犯\n    罪嫌疑重大，且有事實足認有反覆實施同一犯罪之虞，而有\n    羈押之必要，依刑事訴訟法第101 條之1 第5 款、第7 款及\n    第8 款之規定，於民國94年8月9日執行羈押。\n二、茲本院以羈押期間，即將屆滿，其羈押原因仍然存在，且有\n    繼續羈押之必要，應自民國94年11月9 日起，再延長羈押二\n    月，爰依刑事訴訟法第108 條第1 項、第2 項裁定如主文。"
  },
  "search": "臺灣高雄地方法院刑事裁定94年度訴字第2716號公訴人臺灣高雄地方法院檢察署檢察官被告甲○○上列被告因詐欺等案件，本院裁定如下：主文甲○○自民國玖拾肆年拾壹月玖日起延長羈押貳月。理由一、被告甲○○因詐欺等案件，經本院認為所犯刑法第339條第1項之詐欺取財罪、刑法第346條第1項之恐嚇取財罪之犯罪嫌疑重大，且有事實足認有反覆實施同一犯罪之虞，而有羈押之必要，依刑事訴訟法第101條之1第5款、第7款及第8款之規定，於民國94年8月9日執行羈押。二、茲本院以羈押期間，即將屆滿，其羈押原因仍然存在，且有繼續羈押之必要，應自民國94年11月9日起，再延長羈押二月，爰依刑事訴訟法第108條第1項、第2項裁定如主文。中華民國94年11月7日刑事第14庭審判長法官蔡廣昇法官林瑋桓法官紀凱峰以上正本證明與原本無異。如不服本裁定，應於收受送達後5日內向本院提出抗告狀。中華民國94年11月7日書記官黃進遠",
  "characters": {
    "judges": [
      "蔡廣昇",
      "林瑋桓",
      "紀凱峰"
    ],
    "prosecutors": [

    ],
    "lawyers": [

    ],
    "clerks": [
      "黃進遠"
    ],
    "plaintiffs": [

    ],
    "defendants": [
      "甲○○"
    ],
    "prosecutor_office": [
      "臺灣高雄地方法院檢察署檢察官"
    ],
    "creditors": [

    ],
    "debtors": [

    ],
    "judicial_associate_officer": [

    ]
  },
  "adjudged_at": "2005-11-07",
  "created_at": "2016-02-07 00:21:12",
  "updated_at": "2016-02-07 00:21:12"
}