{
  "identify": "KSD-94-訴緝-117-20050823-2",
  "court": {
    "name": "臺灣高雄地方法院",
    "code": "KSD"
  },
  "division": {
    "name": "刑事",
    "code": "M"
  },
  "year": 94,
  "word": "訴緝",
  "number": "117",
  "jcheck": "2",
  "reason": "毒品危害防制條例",
  "content": "臺灣高雄地方法院刑事判決             94年度訴緝字第117號\n公  訴  人  臺灣高雄地方法院檢察署檢察官\n被      告  甲○○\n上列被告因毒品危害防制條例案件，經檢察官提起公訴（93年度\n毒偵字第4302號），本院依簡式審判程序，判決如下：\n    主  文\n甲○○連續施用第一級毒品，累犯，處有期徒刑壹年，扣案之海\n洛因壹包（淨重零點零肆公克）沒收銷燬之。\n    事  實\n一、甲○○曾於民國91年間因施用毒品案件，令入戒治處所強制\n    戒治，於91年11月14日強制戒治執行完畢釋放。復曾於90年\n    間因施用毒品案件，經本院判處有期徒刑10月確定，並於92\n    年9 月13日執行完畢。詎仍不知悔改，猶於上開強制戒治執\n    行完畢釋放後5 年內，基於施用第一級毒品海洛因之概括犯\n    意，自93年6 月間某日起至同年8 月1 日某時止，先後在高\n    雄縣林園鄉清水巖附近，以將海洛因摻入香煙內燃燒施用煙\n    氣之方式及約一星期施用一次之頻率，施用海洛因多次。嗣\n    為警於93年8 月4 日18時25分許在高雄市○○區○○路與朝\n    福街口查獲，並扣得其所有之海洛因1 包（淨重0 點04公克\n    ）。\n二、案經高雄市政府警察局小港分局報請臺灣高雄地方法院檢察\n    署檢察官偵查起訴。\n    理  由\n一、被告甲○○所犯係死刑、無期徒刑、最輕本刑為3 年以上有\n    期徒刑以外之罪，其於準備程序就前揭被訴事實為有罪之陳\n    述，經受命法官告知簡式審判程序之旨，並聽取其與公訴人\n    之意見後，本院認無不得或不宜改依簡式審判程序進行之處\n    ，爰依刑事訴訟法第273 條之1 第1 項、第284 條之1 ，裁\n    定本件由受命法官獨任進行簡式審判程序，合先敘明。\n二、訊據被告對於上揭事實均坦承不諱，且經將被告為警查獲後\n    所採取之尿液送驗結果，係呈嗎啡陽性反應，有高雄市立凱\n    旋醫院93年8 月23日00000000號濫用藥物尿液檢驗報告1 份\n    可稽，且扣案之海洛因1 包經鑑驗結果，確為海洛因無誤，\n    有法務部調查局93年12月9 日調科壹字第220018775 號鑑定\n    通知書1 份可憑，足徵被告自白核與事實相符，應堪採信。\n    又被告先前於91年間因施用毒品案件，令入戒治處所強制戒\n    治，於91年11月14日強制戒治執行完畢，有臺灣高雄地方法\n    院檢察署刑案資料查註紀錄表及臺灣高等法院被告全國前案\n    紀錄表各1 份可參，被告於強制戒治執行完畢釋放後5 年內\n    ，有施用第一級毒品之行為，堪予確認，事證明確，被告犯\n    行洵堪認定。\n三、核被告所為，係犯毒品危害防制條例第 10條第1項之施用第\n    一級毒品罪。被告持有海洛因之低度行為，為施用海洛因之\n    高度行為所吸收，不另論罪。被告先後多次施用海洛因之行\n    為，時間緊接、方法相同，犯罪構成要件亦相同，顯係基於\n    概括犯意反覆為之，為連續犯，應依刑法第56條規定論以1\n    罪，並加重其刑。再被告曾於90年間因施用毒品案件，經本\n    院判處有期徒刑10月確定，並於92年9 月13日執行完畢，有\n    上開臺灣高等法院被告全國前案紀錄表可參，其於有期徒刑\n    執行完畢後，5 年內再犯本件有期徒刑以上之罪，為累犯，\n    應依刑法第47條規定遞加重其刑。爰審酌被告被告先前業因\n    施用毒品行為遭強制戒治，竟仍未戒絕毒品，猶再施用毒品\n    ，顯見其不知悔改，意志不堅，惟念其施用毒品乃自戕一己\n    之身體健康，尚未害及他人，且犯後坦承犯行，態度尚稱良\n    好等一切情狀，分別量處如主文所示之刑，並定其應執行刑\n    。扣案之海洛因1 包（淨重0 點04公克），係屬毒品，應依\n    毒品危害防制條例第18條第1 項前段規定宣告併予沒收銷燬\n    之。\n據上論斷，應依刑事訴訟法第273 條之1 第1 項、第299 條第 1\n項前段，毒品危害防制條例第10條第1 項、第18條第1 項前段，\n刑法第11條前段、第56條、第47條，判決如主文。\n本案經檢察官林慧美到庭執行職務。\n中    華    民    國    94    年    8     月    23    日\n                        刑事第三庭  法  官  陳威龍\n以上正本證明與原本無異。\n如不服本判決，應於收受送達後10日內向本院提出上訴書狀。\n中    華    民    國    94    年    8     月    23    日\n                                    書記官  張家瑜\n附錄本案論罪科刑法條\n毒品危害防制條例第10條第1項：\n施用第一級毒品者，處6月以上5年以下有期徒刑。\n",
  "structure": {
    "main": "甲○○連續施用第一級毒品，累犯，處有期徒刑壹年，扣案之海\n洛因壹包（淨重零點零肆公克）沒收銷燬之。",
    "fact": "一、甲○○曾於民國91年間因施用毒品案件，令入戒治處所強制\n    戒治，於91年11月14日強制戒治執行完畢釋放。復曾於90年\n    間因施用毒品案件，經本院判處有期徒刑10月確定，並於92\n    年9 月13日執行完畢。詎仍不知悔改，猶於上開強制戒治執\n    行完畢釋放後5 年內，基於施用第一級毒品海洛因之概括犯\n    意，自93年6 月間某日起至同年8 月1 日某時止，先後在高\n    雄縣林園鄉清水巖附近，以將海洛因摻入香煙內燃燒施用煙\n    氣之方式及約一星期施用一次之頻率，施用海洛因多次。嗣\n    為警於93年8 月4 日18時25分許在高雄市○○區○○路與朝\n    福街口查獲，並扣得其所有之海洛因1 包（淨重0 點04公克\n    ）。\n二、案經高雄市政府警察局小港分局報請臺灣高雄地方法院檢察\n    署檢察官偵查起訴。",
    "reason": "一、被告甲○○所犯係死刑、無期徒刑、最輕本刑為3 年以上有\n    期徒刑以外之罪，其於準備程序就前揭被訴事實為有罪之陳\n    述，經受命法官告知簡式審判程序之旨，並聽取其與公訴人\n    之意見後，本院認無不得或不宜改依簡式審判程序進行之處\n    ，爰依刑事訴訟法第273 條之1 第1 項、第284 條之1 ，裁\n    定本件由受命法官獨任進行簡式審判程序，合先敘明。\n二、訊據被告對於上揭事實均坦承不諱，且經將被告為警查獲後\n    所採取之尿液送驗結果，係呈嗎啡陽性反應，有高雄市立凱\n    旋醫院93年8 月23日00000000號濫用藥物尿液檢驗報告1 份\n    可稽，且扣案之海洛因1 包經鑑驗結果，確為海洛因無誤，\n    有法務部調查局93年12月9 日調科壹字第220018775 號鑑定\n    通知書1 份可憑，足徵被告自白核與事實相符，應堪採信。\n    又被告先前於91年間因施用毒品案件，令入戒治處所強制戒\n    治，於91年11月14日強制戒治執行完畢，有臺灣高雄地方法\n    院檢察署刑案資料查註紀錄表及臺灣高等法院被告全國前案\n    紀錄表各1 份可參，被告於強制戒治執行完畢釋放後5 年內\n    ，有施用第一級毒品之行為，堪予確認，事證明確，被告犯\n    行洵堪認定。\n三、核被告所為，係犯毒品危害防制條例第 10條第1項之施用第\n    一級毒品罪。被告持有海洛因之低度行為，為施用海洛因之\n    高度行為所吸收，不另論罪。被告先後多次施用海洛因之行\n    為，時間緊接、方法相同，犯罪構成要件亦相同，顯係基於\n    概括犯意反覆為之，為連續犯，應依刑法第56條規定論以1\n    罪，並加重其刑。再被告曾於90年間因施用毒品案件，經本\n    院判處有期徒刑10月確定，並於92年9 月13日執行完畢，有\n    上開臺灣高等法院被告全國前案紀錄表可參，其於有期徒刑\n    執行完畢後，5 年內再犯本件有期徒刑以上之罪，為累犯，\n    應依刑法第47條規定遞加重其刑。爰審酌被告被告先前業因\n    施用毒品行為遭強制戒治，竟仍未戒絕毒品，猶再施用毒品\n    ，顯見其不知悔改，意志不堅，惟念其施用毒品乃自戕一己\n    之身體健康，尚未害及他人，且犯後坦承犯行，態度尚稱良\n    好等一切情狀，分別量處如主文所示之刑，並定其應執行刑\n    。扣案之海洛因1 包（淨重0 點04公克），係屬毒品，應依\n    毒品危害防制條例第18條第1 項前段規定宣告併予沒收銷燬\n    之。\n據上論斷，應依刑事訴訟法第273 條之1 第1 項、第299 條第 1\n項前段，毒品危害防制條例第10條第1 項、第18條第1 項前段，\n刑法第11條前段、第56條、第47條，判決如主文。\n本案經檢察官林慧美到庭執行職務。\n中    華    民    國    94    年    8     月    23    日\n                        刑事第三庭  法  官  陳威龍\n以上正本證明與原本無異。\n如不服本判決，應於收受送達後10日內向本院提出上訴書狀。"
  },
  "search": "臺灣高雄地方法院刑事判決94年度訴緝字第117號公訴人臺灣高雄地方法院檢察署檢察官被告甲○○上列被告因毒品危害防制條例案件，經檢察官提起公訴（93年度毒偵字第4302號），本院依簡式審判程序，判決如下：主文甲○○連續施用第一級毒品，累犯，處有期徒刑壹年，扣案之海洛因壹包（淨重零點零肆公克）沒收銷燬之。事實一、甲○○曾於民國91年間因施用毒品案件，令入戒治處所強制戒治，於91年11月14日強制戒治執行完畢釋放。復曾於90年間因施用毒品案件，經本院判處有期徒刑10月確定，並於92年9月13日執行完畢。詎仍不知悔改，猶於上開強制戒治執行完畢釋放後5年內，基於施用第一級毒品海洛因之概括犯意，自93年6月間某日起至同年8月1日某時止，先後在高雄縣林園鄉清水巖附近，以將海洛因摻入香煙內燃燒施用煙氣之方式及約一星期施用一次之頻率，施用海洛因多次。嗣為警於93年8月4日18時25分許在高雄市○○區○○路與朝福街口查獲，並扣得其所有之海洛因1包（淨重0點04公克）。二、案經高雄市政府警察局小港分局報請臺灣高雄地方法院檢察署檢察官偵查起訴。理由一、被告甲○○所犯係死刑、無期徒刑、最輕本刑為3年以上有期徒刑以外之罪，其於準備程序就前揭被訴事實為有罪之陳述，經受命法官告知簡式審判程序之旨，並聽取其與公訴人之意見後，本院認無不得或不宜改依簡式審判程序進行之處，爰依刑事訴訟法第273條之1第1項、第284條之1，裁定本件由受命法官獨任進行簡式審判程序，合先敘明。二、訊據被告對於上揭事實均坦承不諱，且經將被告為警查獲後所採取之尿液送驗結果，係呈嗎啡陽性反應，有高雄市立凱旋醫院93年8月23日00000000號濫用藥物尿液檢驗報告1份可稽，且扣案之海洛因1包經鑑驗結果，確為海洛因無誤，有法務部調查局93年12月9日調科壹字第220018775號鑑定通知書1份可憑，足徵被告自白核與事實相符，應堪採信。又被告先前於91年間因施用毒品案件，令入戒治處所強制戒治，於91年11月14日強制戒治執行完畢，有臺灣高雄地方法院檢察署刑案資料查註紀錄表及臺灣高等法院被告全國前案紀錄表各1份可參，被告於強制戒治執行完畢釋放後5年內，有施用第一級毒品之行為，堪予確認，事證明確，被告犯行洵堪認定。三、核被告所為，係犯毒品危害防制條例第10條第1項之施用第一級毒品罪。被告持有海洛因之低度行為，為施用海洛因之高度行為所吸收，不另論罪。被告先後多次施用海洛因之行為，時間緊接、方法相同，犯罪構成要件亦相同，顯係基於概括犯意反覆為之，為連續犯，應依刑法第56條規定論以1罪，並加重其刑。再被告曾於90年間因施用毒品案件，經本院判處有期徒刑10月確定，並於92年9月13日執行完畢，有上開臺灣高等法院被告全國前案紀錄表可參，其於有期徒刑執行完畢後，5年內再犯本件有期徒刑以上之罪，為累犯，應依刑法第47條規定遞加重其刑。爰審酌被告被告先前業因施用毒品行為遭強制戒治，竟仍未戒絕毒品，猶再施用毒品，顯見其不知悔改，意志不堅，惟念其施用毒品乃自戕一己之身體健康，尚未害及他人，且犯後坦承犯行，態度尚稱良好等一切情狀，分別量處如主文所示之刑，並定其應執行刑。扣案之海洛因1包（淨重0點04公克），係屬毒品，應依毒品危害防制條例第18條第1項前段規定宣告併予沒收銷燬之。據上論斷，應依刑事訴訟法第273條之1第1項、第299條第1項前段，毒品危害防制條例第10條第1項、第18條第1項前段，刑法第11條前段、第56條、第47條，判決如主文。本案經檢察官林慧美到庭執行職務。中華民國94年8月23日刑事第三庭法官陳威龍以上正本證明與原本無異。如不服本判決，應於收受送達後10日內向本院提出上訴書狀。中華民國94年8月23日書記官張家瑜附錄本案論罪科刑法條毒品危害防制條例第10條第1項：施用第一級毒品者，處6月以上5年以下有期徒刑。",
  "characters": {
    "judges": [
      "陳威龍"
    ],
    "prosecutors": [
      "林慧美"
    ],
    "lawyers": [

    ],
    "clerks": [
      "張家瑜"
    ],
    "plaintiffs": [

    ],
    "defendants": [
      "甲○○"
    ],
    "prosecutor_office": [
      "臺灣高雄地方法院檢察署檢察官"
    ],
    "creditors": [

    ],
    "debtors": [

    ],
    "judicial_associate_officer": [

    ]
  },
  "adjudged_at": "2005-08-23",
  "created_at": "2016-02-06 22:55:15",
  "updated_at": "2016-02-06 22:55:15"
}