{
  "identify": "TCD-100-易-1505-20110613-1",
  "court": {
    "name": "臺灣臺中地方法院",
    "code": "TCD"
  },
  "division": {
    "name": "刑事",
    "code": "M"
  },
  "year": 100,
  "word": "易",
  "number": "1505",
  "jcheck": "1",
  "reason": "傷害",
  "content": "臺灣臺中地方法院刑事判決             100年度易字第1505號\n公  訴  人  臺灣臺中地方法院檢察署檢察官\n被      告  陳萬特\n被      告  林崇棋\n被      告  林宗柏\n被      告  林宗賓\n上列被告等因傷害案件，經檢察官提起公訴（100年度偵字第135\n1號），本院判決如下：\n    主    文\n本件公訴不受理。\n    理    由\n一、公訴意旨意旨略以：被告林崇棋、林宗柏與林宗賓兄弟3人\n    於民國99年7月31日19時30分許，因發現被告林宗賓平日停\n    放在臺中市○里區○○路19號住處附近之汽車停車位遭鄰居\n    即被告陳萬特之車輛佔用，遂前往陳萬特位於臺中市○里區\n    ○○路22巷3號之住處敲門。陳萬特見林宗柏口氣不佳，2人\n    因而發生口角；詎林宗柏先以胸口抵住陳萬特胸口作勢挑釁\n    ，引發陳萬特不滿，乃萌生傷害之犯意，以左手出拳打向林\n    宗柏，林宗柏向後閃避，林崇棋見狀遂上前抵擋。林宗柏、\n    林宗賓、林崇棋3人與陳萬特竟均基於傷害他方身體之犯意\n    ，由拉扯肢體碰觸進而互毆，衝突中，前來勸架之陳萬特父\n    親陳枝南遭林宗柏、林宗賓、林崇棋等人推倒，受有右大拇\n    指擦挫傷及臀部挫傷，陳萬特受有頭、頸、左下胸部、背部\n    多處頓挫傷及四肢多處擦挫傷等傷害，林宗柏則受有左臉頰\n    挫傷、上唇裂傷、左拇指扭傷及右小指擦傷等傷害。因認被\n    告陳萬特、林崇棋、林宗柏、林宗賓等人涉犯刑法第277條\n    第1項之普通傷害罪。\n二、按告訴乃論之罪，其告訴經撤回者，應諭知不受理之判決，\n    為刑事訴訟法第303條第3款所明定。本件被告陳萬特、林崇\n    棋、林宗柏、林宗賓經檢察官以犯刑法第277條第1項之普通\n    傷害罪嫌提起公訴，依同法第287條前段規定係屬告訴乃論\n    之罪。茲經告訴人林宗柏、陳萬特、陳枝南於第一審辯論終\n    結前，具狀撤回告訴，有調解結果報告書、聲請撤回告訴狀\n    3紙、本院調解程序筆錄等在卷可稽，揆諸上開說明，自應\n    諭知不受理之判決，並不經言詞辯論為之。\n據上論斷，應依刑事訴訟法第303條第3款、第307條，判決如主\n文。\n中    華    民    國   100    年    6     月    13    日\n                  刑事第四庭  審判長法  官  吳進發\n                                    法  官  黃益茂\n                                    法  官  李婉玉\n以上正本證明與原本無異。\n如不服本判決應於收受判決後10日內向本院提出上訴書狀，並應\n敘述具體理由；其未敘述上訴理由者，應於上訴期間屆滿後20日\n內向本院補提理由書（均須按他造當事人之人數附繕本）「切勿\n逕送上級法院」。\n                                    書記官  林政佑\n中    華    民    國   100    年    6     月    13    日",
  "structure": {
    "main": "本件公訴不受理。",
    "reason": "一、公訴意旨意旨略以：被告林崇棋、林宗柏與林宗賓兄弟3人\n    於民國99年7月31日19時30分許，因發現被告林宗賓平日停\n    放在臺中市○里區○○路19號住處附近之汽車停車位遭鄰居\n    即被告陳萬特之車輛佔用，遂前往陳萬特位於臺中市○里區\n    ○○路22巷3號之住處敲門。陳萬特見林宗柏口氣不佳，2人\n    因而發生口角；詎林宗柏先以胸口抵住陳萬特胸口作勢挑釁\n    ，引發陳萬特不滿，乃萌生傷害之犯意，以左手出拳打向林\n    宗柏，林宗柏向後閃避，林崇棋見狀遂上前抵擋。林宗柏、\n    林宗賓、林崇棋3人與陳萬特竟均基於傷害他方身體之犯意\n    ，由拉扯肢體碰觸進而互毆，衝突中，前來勸架之陳萬特父\n    親陳枝南遭林宗柏、林宗賓、林崇棋等人推倒，受有右大拇\n    指擦挫傷及臀部挫傷，陳萬特受有頭、頸、左下胸部、背部\n    多處頓挫傷及四肢多處擦挫傷等傷害，林宗柏則受有左臉頰\n    挫傷、上唇裂傷、左拇指扭傷及右小指擦傷等傷害。因認被\n    告陳萬特、林崇棋、林宗柏、林宗賓等人涉犯刑法第277條\n    第1項之普通傷害罪。\n二、按告訴乃論之罪，其告訴經撤回者，應諭知不受理之判決，\n    為刑事訴訟法第303條第3款所明定。本件被告陳萬特、林崇\n    棋、林宗柏、林宗賓經檢察官以犯刑法第277條第1項之普通\n    傷害罪嫌提起公訴，依同法第287條前段規定係屬告訴乃論\n    之罪。茲經告訴人林宗柏、陳萬特、陳枝南於第一審辯論終\n    結前，具狀撤回告訴，有調解結果報告書、聲請撤回告訴狀\n    3紙、本院調解程序筆錄等在卷可稽，揆諸上開說明，自應\n    諭知不受理之判決，並不經言詞辯論為之。\n據上論斷，應依刑事訴訟法第303條第3款、第307條，判決如主\n文。"
  },
  "search": "臺灣臺中地方法院刑事判決100年度易字第1505號公訴人臺灣臺中地方法院檢察署檢察官被告陳萬特被告林崇棋被告林宗柏被告林宗賓上列被告等因傷害案件，經檢察官提起公訴（100年度偵字第1351號），本院判決如下：主文本件公訴不受理。理由一、公訴意旨意旨略以：被告林崇棋、林宗柏與林宗賓兄弟3人於民國99年7月31日19時30分許，因發現被告林宗賓平日停放在臺中市○里區○○路19號住處附近之汽車停車位遭鄰居即被告陳萬特之車輛佔用，遂前往陳萬特位於臺中市○里區○○路22巷3號之住處敲門。陳萬特見林宗柏口氣不佳，2人因而發生口角；詎林宗柏先以胸口抵住陳萬特胸口作勢挑釁，引發陳萬特不滿，乃萌生傷害之犯意，以左手出拳打向林宗柏，林宗柏向後閃避，林崇棋見狀遂上前抵擋。林宗柏、林宗賓、林崇棋3人與陳萬特竟均基於傷害他方身體之犯意，由拉扯肢體碰觸進而互毆，衝突中，前來勸架之陳萬特父親陳枝南遭林宗柏、林宗賓、林崇棋等人推倒，受有右大拇指擦挫傷及臀部挫傷，陳萬特受有頭、頸、左下胸部、背部多處頓挫傷及四肢多處擦挫傷等傷害，林宗柏則受有左臉頰挫傷、上唇裂傷、左拇指扭傷及右小指擦傷等傷害。因認被告陳萬特、林崇棋、林宗柏、林宗賓等人涉犯刑法第277條第1項之普通傷害罪。二、按告訴乃論之罪，其告訴經撤回者，應諭知不受理之判決，為刑事訴訟法第303條第3款所明定。本件被告陳萬特、林崇棋、林宗柏、林宗賓經檢察官以犯刑法第277條第1項之普通傷害罪嫌提起公訴，依同法第287條前段規定係屬告訴乃論之罪。茲經告訴人林宗柏、陳萬特、陳枝南於第一審辯論終結前，具狀撤回告訴，有調解結果報告書、聲請撤回告訴狀3紙、本院調解程序筆錄等在卷可稽，揆諸上開說明，自應諭知不受理之判決，並不經言詞辯論為之。據上論斷，應依刑事訴訟法第303條第3款、第307條，判決如主文。中華民國100年6月13日刑事第四庭審判長法官吳進發法官黃益茂法官李婉玉以上正本證明與原本無異。如不服本判決應於收受判決後10日內向本院提出上訴書狀，並應敘述具體理由；其未敘述上訴理由者，應於上訴期間屆滿後20日內向本院補提理由書（均須按他造當事人之人數附繕本）「切勿逕送上級法院」。書記官林政佑中華民國100年6月13日",
  "characters": {
    "judges": [
      "吳進發",
      "黃益茂",
      "李婉玉"
    ],
    "prosecutors": [

    ],
    "lawyers": [

    ],
    "clerks": [
      "林政佑"
    ],
    "plaintiffs": [

    ],
    "defendants": [
      "陳萬特",
      "被      告  林崇棋",
      "被      告  林宗柏",
      "被      告  林宗賓"
    ],
    "prosecutor_office": [
      "臺灣臺中地方法院檢察署檢察官"
    ],
    "creditors": [

    ],
    "debtors": [

    ],
    "judicial_associate_officer": [

    ]
  },
  "adjudged_at": "2011-06-13",
  "created_at": "2016-02-13 16:43:43",
  "updated_at": "2016-02-13 16:43:43"
}