{
  "identify": "TYD-100-桃簡-939-20110613-1",
  "court": {
    "name": "臺灣桃園地方法院",
    "code": "TYD"
  },
  "division": {
    "name": "刑事",
    "code": "M"
  },
  "year": 100,
  "word": "桃簡",
  "number": "939",
  "jcheck": "1",
  "reason": "詐欺",
  "content": "臺灣桃園地方法院刑事簡易判決        100年度桃簡字第939號\n聲  請  人  臺灣桃園地方法院檢察署檢察官\n被      告  黃清富\n上列被告因詐欺案件，經檢察官聲請簡易判決處刑（99年度偵字\n第24536號），本院逕以簡易判決處刑如下：\n    主  文\n黃清富幫助犯詐欺取財罪，累犯，處有期徒刑參月，如易科罰金\n，以新臺幣壹仟元折算壹日。\n    事實及理由\n一、本件犯罪事實及證據，除犯罪事實第13行「於民國99年6 月\n    26日前某日」，應更正為「於民國99年6 月26前之6 月中下\n    旬某日」；另證據部分應補充「內政部警政署反詐騙諮詢專\n    線紀錄表6 紙、受理詐騙帳戶通報警示簡便格式表6 紙、受\n    理刑事案件報案三聯單3 紙、受理各類案件紀錄表5 紙」外\n    ，餘均引用檢察官聲請簡易判決處刑書之記載（如附件）。\n二、按刑法上之幫助犯，係對於犯罪與正犯有共同之認識，而以\n    幫助之意思，對於正犯資以助力，而未參與實施犯罪之行為\n    者而言（最高法院75年度台上字第1509號、84年度台上字第\n    5998號、88年度台上字第1270號判決意旨參照）；是以，如\n    未參與實施犯罪構成要件之行為，且係出於幫助之意思提供\n    助力，即屬幫助犯，而非共同正犯。本件被告提供中華郵政\n    仁美郵局帳戶予他人使用，使他人得基於詐欺取財之犯意，\n    向被害人等施用詐術，致使被害人等陷於錯誤而匯款至被告\n    上揭帳戶內，以遂行詐欺取財之犯行，該詐騙集團成員固犯\n    刑法第339 條詐欺取財罪行，然被告單純提供帳戶供人使用\n    之行為，並不等同於向被害人等施以詐術之行為，此外，復\n    無其他證據證明被告有參與詐欺取財犯行之構成要件行為，\n    是被告提供帳戶供人使用之行為，係對於他人遂行詐欺取財\n    之犯行資以助力，應論以幫助犯。\n三、論罪科刑\n  (一)核被告黃清富所為，均係犯刑法第339 條第1 項、第30條第\n    1 項之幫助詐欺取財罪。\n  (二)被告以同時提供1 個金融帳戶之一個幫助行為，衍生上揭6\n    被害人受詐騙之結果，核屬一行為觸犯數罪名之想像競合犯\n    ，應依刑法第55條規定，從一重論以幫助詐欺罪處斷。\n  (三)被告有如附件犯罪事實欄所載犯罪科刑及執行完畢之紀錄，\n    有臺灣高等法院被告前案紀錄表1 份在卷可稽，其於有期徒\n    刑執行完畢5 年內，故意再犯本件有期徒刑以上之罪，為累\n    犯，應依刑法第47條第1 項之規定加重其刑。\n  (四)又被告以幫助之意思，參與構成要件以外之行為，為幫助犯\n    ，業如前述，爰依刑法第30條第2 項規定，依正犯之刑減輕\n    之。並依法先加後減。\n  (五)爰審酌被告有提供存摺、金融卡及密碼，幫助詐騙集團成員\n    ，使渠等方便行騙財物，助長詐騙集團詐財歪風，增加查緝\n    困難，危害財產安全及社會秩序之穩定，以及被害人等所受\n    損害、兼衡酌被告犯後坦承犯行，犯後態度良好等一切情狀\n    ，量處如主文所示之刑，並諭知易科罰金之折算標準。\n  (六)而被告提供與詐騙集團所使用之前揭帳戶存摺、金融卡，既\n    經交付他人且未扣案，現是否尚在不明，為免將來執行困難\n    與爭議，爰均不另為沒收之諭知。\n四、據上論斷，應依刑事訴訟法第449 條第1 項前段、第3 項、\n    第454 條第2 項，刑法第30條第1 項前段、第2 項、第339\n    條第1 項、第55條、第47條第1 項、第41條第1 項前段，刑\n    法施行法第1 條之1 第1 項、第2 項前段，逕以簡易判決處\n    刑如主文。\n五、如不服本判決，得於判決書送達之翌日起10日內，以書狀敘\n    述理由（須附繕本），向本院合議庭，提出上訴。\n中    華    民    國   100    年    6     月    13    日\n                  刑事第二庭  法  官  廖珮伶\n以上正本證明與原本無異。\n如不服本判決，應於判決送達後10日內向本院提出上訴狀（應附\n繕本）。\n                              書記官  張良煜\n中    華    民    國   100    年    6     月    20    日\n附錄本案論罪科刑法條全文\n中華民國刑法第339 條（普通詐欺罪）\n意圖為自己或第三人不法之所有，以詐術使人將本人或第三人之\n物交付者，處5 年以下有期徒刑、拘役或科或併科1 千元以下罰\n金。\n以前項方法得財產上不法之利益或使第三人得之者，亦同。\n前二項之未遂犯罰之。",
  "structure": {
    "main": "黃清富幫助犯詐欺取財罪，累犯，處有期徒刑參月，如易科罰金\n，以新臺幣壹仟元折算壹日。",
    "fact": "一、本件犯罪事實及證據，除犯罪事實第13行「於民國99年6 月\n    26日前某日」，應更正為「於民國99年6 月26前之6 月中下\n    旬某日」；另證據部分應補充「內政部警政署反詐騙諮詢專\n    線紀錄表6 紙、受理詐騙帳戶通報警示簡便格式表6 紙、受\n    理刑事案件報案三聯單3 紙、受理各類案件紀錄表5 紙」外\n    ，餘均引用檢察官聲請簡易判決處刑書之記載（如附件）。\n二、按刑法上之幫助犯，係對於犯罪與正犯有共同之認識，而以\n    幫助之意思，對於正犯資以助力，而未參與實施犯罪之行為\n    者而言（最高法院75年度台上字第1509號、84年度台上字第\n    5998號、88年度台上字第1270號判決意旨參照）；是以，如\n    未參與實施犯罪構成要件之行為，且係出於幫助之意思提供\n    助力，即屬幫助犯，而非共同正犯。本件被告提供中華郵政\n    仁美郵局帳戶予他人使用，使他人得基於詐欺取財之犯意，\n    向被害人等施用詐術，致使被害人等陷於錯誤而匯款至被告\n    上揭帳戶內，以遂行詐欺取財之犯行，該詐騙集團成員固犯\n    刑法第339 條詐欺取財罪行，然被告單純提供帳戶供人使用\n    之行為，並不等同於向被害人等施以詐術之行為，此外，復\n    無其他證據證明被告有參與詐欺取財犯行之構成要件行為，\n    是被告提供帳戶供人使用之行為，係對於他人遂行詐欺取財\n    之犯行資以助力，應論以幫助犯。\n三、論罪科刑\n  (一)核被告黃清富所為，均係犯刑法第339 條第1 項、第30條第\n    1 項之幫助詐欺取財罪。\n  (二)被告以同時提供1 個金融帳戶之一個幫助行為，衍生上揭6\n    被害人受詐騙之結果，核屬一行為觸犯數罪名之想像競合犯\n    ，應依刑法第55條規定，從一重論以幫助詐欺罪處斷。\n  (三)被告有如附件犯罪事實欄所載犯罪科刑及執行完畢之紀錄，\n    有臺灣高等法院被告前案紀錄表1 份在卷可稽，其於有期徒\n    刑執行完畢5 年內，故意再犯本件有期徒刑以上之罪，為累\n    犯，應依刑法第47條第1 項之規定加重其刑。\n  (四)又被告以幫助之意思，參與構成要件以外之行為，為幫助犯\n    ，業如前述，爰依刑法第30條第2 項規定，依正犯之刑減輕\n    之。並依法先加後減。\n  (五)爰審酌被告有提供存摺、金融卡及密碼，幫助詐騙集團成員\n    ，使渠等方便行騙財物，助長詐騙集團詐財歪風，增加查緝\n    困難，危害財產安全及社會秩序之穩定，以及被害人等所受\n    損害、兼衡酌被告犯後坦承犯行，犯後態度良好等一切情狀\n    ，量處如主文所示之刑，並諭知易科罰金之折算標準。\n  (六)而被告提供與詐騙集團所使用之前揭帳戶存摺、金融卡，既\n    經交付他人且未扣案，現是否尚在不明，為免將來執行困難\n    與爭議，爰均不另為沒收之諭知。\n四、據上論斷，應依刑事訴訟法第449 條第1 項前段、第3 項、\n    第454 條第2 項，刑法第30條第1 項前段、第2 項、第339\n    條第1 項、第55條、第47條第1 項、第41條第1 項前段，刑\n    法施行法第1 條之1 第1 項、第2 項前段，逕以簡易判決處\n    刑如主文。\n五、如不服本判決，得於判決書送達之翌日起10日內，以書狀敘\n    述理由（須附繕本），向本院合議庭，提出上訴。",
    "reason": "一、本件犯罪事實及證據，除犯罪事實第13行「於民國99年6 月\n    26日前某日」，應更正為「於民國99年6 月26前之6 月中下\n    旬某日」；另證據部分應補充「內政部警政署反詐騙諮詢專\n    線紀錄表6 紙、受理詐騙帳戶通報警示簡便格式表6 紙、受\n    理刑事案件報案三聯單3 紙、受理各類案件紀錄表5 紙」外\n    ，餘均引用檢察官聲請簡易判決處刑書之記載（如附件）。\n二、按刑法上之幫助犯，係對於犯罪與正犯有共同之認識，而以\n    幫助之意思，對於正犯資以助力，而未參與實施犯罪之行為\n    者而言（最高法院75年度台上字第1509號、84年度台上字第\n    5998號、88年度台上字第1270號判決意旨參照）；是以，如\n    未參與實施犯罪構成要件之行為，且係出於幫助之意思提供\n    助力，即屬幫助犯，而非共同正犯。本件被告提供中華郵政\n    仁美郵局帳戶予他人使用，使他人得基於詐欺取財之犯意，\n    向被害人等施用詐術，致使被害人等陷於錯誤而匯款至被告\n    上揭帳戶內，以遂行詐欺取財之犯行，該詐騙集團成員固犯\n    刑法第339 條詐欺取財罪行，然被告單純提供帳戶供人使用\n    之行為，並不等同於向被害人等施以詐術之行為，此外，復\n    無其他證據證明被告有參與詐欺取財犯行之構成要件行為，\n    是被告提供帳戶供人使用之行為，係對於他人遂行詐欺取財\n    之犯行資以助力，應論以幫助犯。\n三、論罪科刑\n  (一)核被告黃清富所為，均係犯刑法第339 條第1 項、第30條第\n    1 項之幫助詐欺取財罪。\n  (二)被告以同時提供1 個金融帳戶之一個幫助行為，衍生上揭6\n    被害人受詐騙之結果，核屬一行為觸犯數罪名之想像競合犯\n    ，應依刑法第55條規定，從一重論以幫助詐欺罪處斷。\n  (三)被告有如附件犯罪事實欄所載犯罪科刑及執行完畢之紀錄，\n    有臺灣高等法院被告前案紀錄表1 份在卷可稽，其於有期徒\n    刑執行完畢5 年內，故意再犯本件有期徒刑以上之罪，為累\n    犯，應依刑法第47條第1 項之規定加重其刑。\n  (四)又被告以幫助之意思，參與構成要件以外之行為，為幫助犯\n    ，業如前述，爰依刑法第30條第2 項規定，依正犯之刑減輕\n    之。並依法先加後減。\n  (五)爰審酌被告有提供存摺、金融卡及密碼，幫助詐騙集團成員\n    ，使渠等方便行騙財物，助長詐騙集團詐財歪風，增加查緝\n    困難，危害財產安全及社會秩序之穩定，以及被害人等所受\n    損害、兼衡酌被告犯後坦承犯行，犯後態度良好等一切情狀\n    ，量處如主文所示之刑，並諭知易科罰金之折算標準。\n  (六)而被告提供與詐騙集團所使用之前揭帳戶存摺、金融卡，既\n    經交付他人且未扣案，現是否尚在不明，為免將來執行困難\n    與爭議，爰均不另為沒收之諭知。\n四、據上論斷，應依刑事訴訟法第449 條第1 項前段、第3 項、\n    第454 條第2 項，刑法第30條第1 項前段、第2 項、第339\n    條第1 項、第55條、第47條第1 項、第41條第1 項前段，刑\n    法施行法第1 條之1 第1 項、第2 項前段，逕以簡易判決處\n    刑如主文。\n五、如不服本判決，得於判決書送達之翌日起10日內，以書狀敘\n    述理由（須附繕本），向本院合議庭，提出上訴。"
  },
  "search": "臺灣桃園地方法院刑事簡易判決100年度桃簡字第939號聲請人臺灣桃園地方法院檢察署檢察官被告黃清富上列被告因詐欺案件，經檢察官聲請簡易判決處刑（99年度偵字第24536號），本院逕以簡易判決處刑如下：主文黃清富幫助犯詐欺取財罪，累犯，處有期徒刑參月，如易科罰金，以新臺幣壹仟元折算壹日。事實及理由一、本件犯罪事實及證據，除犯罪事實第13行「於民國99年6月26日前某日」，應更正為「於民國99年6月26前之6月中下旬某日」；另證據部分應補充「內政部警政署反詐騙諮詢專線紀錄表6紙、受理詐騙帳戶通報警示簡便格式表6紙、受理刑事案件報案三聯單3紙、受理各類案件紀錄表5紙」外，餘均引用檢察官聲請簡易判決處刑書之記載（如附件）。二、按刑法上之幫助犯，係對於犯罪與正犯有共同之認識，而以幫助之意思，對於正犯資以助力，而未參與實施犯罪之行為者而言（最高法院75年度台上字第1509號、84年度台上字第5998號、88年度台上字第1270號判決意旨參照）；是以，如未參與實施犯罪構成要件之行為，且係出於幫助之意思提供助力，即屬幫助犯，而非共同正犯。本件被告提供中華郵政仁美郵局帳戶予他人使用，使他人得基於詐欺取財之犯意，向被害人等施用詐術，致使被害人等陷於錯誤而匯款至被告上揭帳戶內，以遂行詐欺取財之犯行，該詐騙集團成員固犯刑法第339條詐欺取財罪行，然被告單純提供帳戶供人使用之行為，並不等同於向被害人等施以詐術之行為，此外，復無其他證據證明被告有參與詐欺取財犯行之構成要件行為，是被告提供帳戶供人使用之行為，係對於他人遂行詐欺取財之犯行資以助力，應論以幫助犯。三、論罪科刑(一)核被告黃清富所為，均係犯刑法第339條第1項、第30條第1項之幫助詐欺取財罪。(二)被告以同時提供1個金融帳戶之一個幫助行為，衍生上揭6被害人受詐騙之結果，核屬一行為觸犯數罪名之想像競合犯，應依刑法第55條規定，從一重論以幫助詐欺罪處斷。(三)被告有如附件犯罪事實欄所載犯罪科刑及執行完畢之紀錄，有臺灣高等法院被告前案紀錄表1份在卷可稽，其於有期徒刑執行完畢5年內，故意再犯本件有期徒刑以上之罪，為累犯，應依刑法第47條第1項之規定加重其刑。(四)又被告以幫助之意思，參與構成要件以外之行為，為幫助犯，業如前述，爰依刑法第30條第2項規定，依正犯之刑減輕之。並依法先加後減。(五)爰審酌被告有提供存摺、金融卡及密碼，幫助詐騙集團成員，使渠等方便行騙財物，助長詐騙集團詐財歪風，增加查緝困難，危害財產安全及社會秩序之穩定，以及被害人等所受損害、兼衡酌被告犯後坦承犯行，犯後態度良好等一切情狀，量處如主文所示之刑，並諭知易科罰金之折算標準。(六)而被告提供與詐騙集團所使用之前揭帳戶存摺、金融卡，既經交付他人且未扣案，現是否尚在不明，為免將來執行困難與爭議，爰均不另為沒收之諭知。四、據上論斷，應依刑事訴訟法第449條第1項前段、第3項、第454條第2項，刑法第30條第1項前段、第2項、第339條第1項、第55條、第47條第1項、第41條第1項前段，刑法施行法第1條之1第1項、第2項前段，逕以簡易判決處刑如主文。五、如不服本判決，得於判決書送達之翌日起10日內，以書狀敘述理由（須附繕本），向本院合議庭，提出上訴。中華民國100年6月13日刑事第二庭法官廖珮伶以上正本證明與原本無異。如不服本判決，應於判決送達後10日內向本院提出上訴狀（應附繕本）。書記官張良煜中華民國100年6月20日附錄本案論罪科刑法條全文中華民國刑法第339條（普通詐欺罪）意圖為自己或第三人不法之所有，以詐術使人將本人或第三人之物交付者，處5年以下有期徒刑、拘役或科或併科1千元以下罰金。以前項方法得財產上不法之利益或使第三人得之者，亦同。前二項之未遂犯罰之。",
  "characters": {
    "judges": [
      "廖珮伶"
    ],
    "prosecutors": [

    ],
    "lawyers": [

    ],
    "clerks": [
      "張良煜"
    ],
    "plaintiffs": [

    ],
    "defendants": [
      "黃清富"
    ],
    "prosecutor_office": [
      "臺灣桃園地方法院檢察署檢察官"
    ],
    "creditors": [

    ],
    "debtors": [

    ],
    "judicial_associate_officer": [

    ]
  },
  "adjudged_at": "2011-06-13",
  "created_at": "2016-02-13 16:49:37",
  "updated_at": "2016-02-13 16:49:37"
}