{
  "identify": "KSD-91-訴-700-20020426-1",
  "court": {
    "name": "臺灣高雄地方法院",
    "code": "KSD"
  },
  "division": {
    "name": "民事",
    "code": "V"
  },
  "year": 91,
  "word": "訴",
  "number": "700",
  "jcheck": "1",
  "reason": "清償借款",
  "content": "臺灣高雄地方法院民事判決  九十一年度訴字第七○○號\n    原      告  中央信託局楠梓分局\n    法定代理人  丙○○\n    訴訟代理人  甲○○\n    被      告  乙○○\n右當事人間清償借款事件，本院判決如左：\n    主    文\n被告應給付原告新台幣伍拾伍萬仟貳佰肆拾伍元，及自民國九十年九月十二日起至\n清償日止按年息百分之八點零六計算之利息，並自民國九十年十月十三日起至清償日\n止，其逾期在六個月以內者按上開利率百分之十、超過六個月者按上開利率百分之二\n十計算之違約金。\n訴訟費用由被告負擔。\n本判決於原告以新台幣壹拾捌萬肆仟肆佰壹拾伍元為被告供擔保後得假執行。\n    事    實\n甲、原告方面：\n  一、聲明：除假執行擔保金額外，求為判決如主文所示。\n  二、陳述：\n      被告乙○○於民國八十八年十月八日與原告簽訂消費性借款契約，向原告借得\n      新臺幣（下同）七十萬元，該項借款期限七年，自借款日起按月平均攤付本息\n      ，約定利息為按原告之基本放款利率減碼年息百分之○點二九五計息，並同意\n      嗣後隨基本放款利率調整而調整，另約定借用人不依期還本者即喪失期限利益\n      而視為全部到期，且其遲延履行之本金或利息，除仍按上開利率計息外，其逾\n      期在六個月以內者，按上開利率百分之十、逾期超過六個月者，另依約定利率\n      百分之二十加計違約金。詎被告乙○○就上開借款僅清償部分本息至九十年九\n      月十一日止，餘款即未再依約繳納，按約即視為全部到期而應即將積欠之本金\n      五十五萬三千二百四十五元及其利息、違約金一次清償，為此乃依消費借貸之\n      法律關係提起本訴，請求判令被告應給付如主文第一項所示之金額及其利息、\n      違約金。\n  三、證據：提出消費性借款契約、放款帳務資料查詢單、基本放款利率變動表等件\n      為證。\n乙、被告方面：\n    被告未於言詞辯論期日到場，亦未提出書狀作何聲明或陳述。\n    理    由\n一、本件被告經合法通知未於言詞辯論期日到場，經核無民事訴訟法第三百八十六條\n    各款所列情形，爰依原告之聲請，由其一造辯論而為判決。\n二、按借用人應於約定期限內，返還與借用物種類、品質、數量相同之物，而遲延之\n    債務，以支付金錢為標的者，債權人得請求依法定利率計算之遲延利息，但約定\n    利率較高，仍從其約定利率，另當事人得約定債務人不履行債務時，應支付違約\n    金，民法第四百七十八條前段、第二百三十三條第一項、第二百五十條第一項分\n    別定有明文。本件原告主張被告於上開時日借取前開金額，嗣因遲未繳付本息而\n    視為全部到期，計欠有如主文第一項所示之金額及其利息、違約金之事實，業據\n    其提出與所述相符之消費性借款契約、放款帳務資料查詢單、基本放款利率變動\n    表等件為證，被告經合法通知，既未於言詞辯論期日到場爭執，復未提出書狀答\n    辯以供本院斟酌，應認原告之主張為真實。從而本件原告依消費借貸之法律關係\n    據以提起本訴，請求判令被告應給付如主文第一項所示之金額及其利息、違約金\n    ，依法即無不合，自應予以准許。\n三、原告陳明願供擔保請准宣告假執行，經核並無不合，爰酌定相當擔保金額准許之\n    。\n四、據上論結，本件原告之訴為有理由，依民事訴訟法第三百八十五條第一項、第七\n    十八條，判決如主文。\n中      華      民      國    九十一    年      四      月    二十六    日\n                              臺灣高雄地方法院民事庭\n~B審判長法官  沈建興\n~B法      官  廖家陽\n~B法      官  胡宜如\n右為正本係照原本作成。\n如不服本判決，應於送達後廿日內，向本院提出上訴狀並表明上訴理由，如於本判決\n宣示後送達前提起上訴者，應於判決送達後十日內補提上訴理由書（須附繕本）。\n中      華      民      國    九十一    年      四      月    二十六    日\n~B法院書記官  王世雄\n",
  "structure": {
    "main": "被告應給付原告新台幣伍拾伍萬仟貳佰肆拾伍元，及自民國九十年九月十二日起至\n清償日止按年息百分之八點零六計算之利息，並自民國九十年十月十三日起至清償日\n止，其逾期在六個月以內者按上開利率百分之十、超過六個月者按上開利率百分之二\n十計算之違約金。\n訴訟費用由被告負擔。\n本判決於原告以新台幣壹拾捌萬肆仟肆佰壹拾伍元為被告供擔保後得假執行。",
    "fact": "甲、原告方面：\n  一、聲明：除假執行擔保金額外，求為判決如主文所示。\n  二、陳述：\n      被告乙○○於民國八十八年十月八日與原告簽訂消費性借款契約，向原告借得\n      新臺幣（下同）七十萬元，該項借款期限七年，自借款日起按月平均攤付本息\n      ，約定利息為按原告之基本放款利率減碼年息百分之○點二九五計息，並同意\n      嗣後隨基本放款利率調整而調整，另約定借用人不依期還本者即喪失期限利益\n      而視為全部到期，且其遲延履行之本金或利息，除仍按上開利率計息外，其逾\n      期在六個月以內者，按上開利率百分之十、逾期超過六個月者，另依約定利率\n      百分之二十加計違約金。詎被告乙○○就上開借款僅清償部分本息至九十年九\n      月十一日止，餘款即未再依約繳納，按約即視為全部到期而應即將積欠之本金\n      五十五萬三千二百四十五元及其利息、違約金一次清償，為此乃依消費借貸之\n      法律關係提起本訴，請求判令被告應給付如主文第一項所示之金額及其利息、\n      違約金。\n  三、證據：提出消費性借款契約、放款帳務資料查詢單、基本放款利率變動表等件\n      為證。\n乙、被告方面：\n    被告未於言詞辯論期日到場，亦未提出書狀作何聲明或陳述。",
    "reason": "一、本件被告經合法通知未於言詞辯論期日到場，經核無民事訴訟法第三百八十六條\n    各款所列情形，爰依原告之聲請，由其一造辯論而為判決。\n二、按借用人應於約定期限內，返還與借用物種類、品質、數量相同之物，而遲延之\n    債務，以支付金錢為標的者，債權人得請求依法定利率計算之遲延利息，但約定\n    利率較高，仍從其約定利率，另當事人得約定債務人不履行債務時，應支付違約\n    金，民法第四百七十八條前段、第二百三十三條第一項、第二百五十條第一項分\n    別定有明文。本件原告主張被告於上開時日借取前開金額，嗣因遲未繳付本息而\n    視為全部到期，計欠有如主文第一項所示之金額及其利息、違約金之事實，業據\n    其提出與所述相符之消費性借款契約、放款帳務資料查詢單、基本放款利率變動\n    表等件為證，被告經合法通知，既未於言詞辯論期日到場爭執，復未提出書狀答\n    辯以供本院斟酌，應認原告之主張為真實。從而本件原告依消費借貸之法律關係\n    據以提起本訴，請求判令被告應給付如主文第一項所示之金額及其利息、違約金\n    ，依法即無不合，自應予以准許。\n三、原告陳明願供擔保請准宣告假執行，經核並無不合，爰酌定相當擔保金額准許之\n    。\n四、據上論結，本件原告之訴為有理由，依民事訴訟法第三百八十五條第一項、第七\n    十八條，判決如主文。\n中      華      民      國    九十一    年      四      月    二十六    日\n                              臺灣高雄地方法院民事庭\n~B審判長法官  沈建興\n~B法      官  廖家陽\n~B法      官  胡宜如\n右為正本係照原本作成。\n如不服本判決，應於送達後廿日內，向本院提出上訴狀並表明上訴理由，如於本判決\n宣示後送達前提起上訴者，應於判決送達後十日內補提上訴理由書（須附繕本）。"
  },
  "search": "臺灣高雄地方法院民事判決九十一年度訴字第七○○號原告中央信託局楠梓分局法定代理人丙○○訴訟代理人甲○○被告乙○○右當事人間清償借款事件，本院判決如左：主文被告應給付原告新台幣伍拾伍萬仟貳佰肆拾伍元，及自民國九十年九月十二日起至清償日止按年息百分之八點零六計算之利息，並自民國九十年十月十三日起至清償日止，其逾期在六個月以內者按上開利率百分之十、超過六個月者按上開利率百分之二十計算之違約金。訴訟費用由被告負擔。本判決於原告以新台幣壹拾捌萬肆仟肆佰壹拾伍元為被告供擔保後得假執行。事實甲、原告方面：一、聲明：除假執行擔保金額外，求為判決如主文所示。二、陳述：被告乙○○於民國八十八年十月八日與原告簽訂消費性借款契約，向原告借得新臺幣（下同）七十萬元，該項借款期限七年，自借款日起按月平均攤付本息，約定利息為按原告之基本放款利率減碼年息百分之○點二九五計息，並同意嗣後隨基本放款利率調整而調整，另約定借用人不依期還本者即喪失期限利益而視為全部到期，且其遲延履行之本金或利息，除仍按上開利率計息外，其逾期在六個月以內者，按上開利率百分之十、逾期超過六個月者，另依約定利率百分之二十加計違約金。詎被告乙○○就上開借款僅清償部分本息至九十年九月十一日止，餘款即未再依約繳納，按約即視為全部到期而應即將積欠之本金五十五萬三千二百四十五元及其利息、違約金一次清償，為此乃依消費借貸之法律關係提起本訴，請求判令被告應給付如主文第一項所示之金額及其利息、違約金。三、證據：提出消費性借款契約、放款帳務資料查詢單、基本放款利率變動表等件為證。乙、被告方面：被告未於言詞辯論期日到場，亦未提出書狀作何聲明或陳述。理由一、本件被告經合法通知未於言詞辯論期日到場，經核無民事訴訟法第三百八十六條各款所列情形，爰依原告之聲請，由其一造辯論而為判決。二、按借用人應於約定期限內，返還與借用物種類、品質、數量相同之物，而遲延之債務，以支付金錢為標的者，債權人得請求依法定利率計算之遲延利息，但約定利率較高，仍從其約定利率，另當事人得約定債務人不履行債務時，應支付違約金，民法第四百七十八條前段、第二百三十三條第一項、第二百五十條第一項分別定有明文。本件原告主張被告於上開時日借取前開金額，嗣因遲未繳付本息而視為全部到期，計欠有如主文第一項所示之金額及其利息、違約金之事實，業據其提出與所述相符之消費性借款契約、放款帳務資料查詢單、基本放款利率變動表等件為證，被告經合法通知，既未於言詞辯論期日到場爭執，復未提出書狀答辯以供本院斟酌，應認原告之主張為真實。從而本件原告依消費借貸之法律關係據以提起本訴，請求判令被告應給付如主文第一項所示之金額及其利息、違約金，依法即無不合，自應予以准許。三、原告陳明願供擔保請准宣告假執行，經核並無不合，爰酌定相當擔保金額准許之。四、據上論結，本件原告之訴為有理由，依民事訴訟法第三百八十五條第一項、第七十八條，判決如主文。中華民國九十一年四月二十六日臺灣高雄地方法院民事庭~B審判長法官沈建興~B法官廖家陽~B法官胡宜如右為正本係照原本作成。如不服本判決，應於送達後廿日內，向本院提出上訴狀並表明上訴理由，如於本判決宣示後送達前提起上訴者，應於判決送達後十日內補提上訴理由書（須附繕本）。中華民國九十一年四月二十六日~B法院書記官王世雄",
  "characters": {
    "judges": [
      "廖家陽",
      "胡宜如"
    ],
    "prosecutors": [

    ],
    "lawyers": [

    ],
    "clerks": [

    ],
    "plaintiffs": [
      "中央信託局楠梓分局"
    ],
    "defendants": [
      "乙○○",
      "右當事人間清償借款事件，本院判決如左："
    ],
    "prosecutor_office": [

    ],
    "creditors": [

    ],
    "debtors": [

    ],
    "judicial_associate_officer": [

    ]
  },
  "adjudged_at": "2002-04-26",
  "created_at": "2016-02-04 16:10:37",
  "updated_at": "2016-02-04 16:10:37"
}