{
  "identify": "CHD-100-侵訴-36-20111006-1",
  "court": {
    "name": "臺灣彰化地方法院",
    "code": "CHD"
  },
  "division": {
    "name": "刑事",
    "code": "M"
  },
  "year": 100,
  "word": "侵訴",
  "number": "36",
  "jcheck": "1",
  "reason": "妨害性自主",
  "content": "臺灣彰化地方法院刑事裁定             100年度侵訴字第36號\n公  訴  人  臺灣彰化地方法院檢察署檢察官\n被      告  陳○樺代號000.\n選任辯護人  劉嘉堯律師\n上列被告因加重強制性交等案件，經檢察官提起公訴（100年度\n偵字第4342、5503號），本院裁定如下：\n    主  文\n陳○樺自民國壹佰年拾月拾壹日起延長羈押貳月。\n    理  由\n一、本件被告涉犯加重強制性交及加重強制猥褻等案件，經本院\n    認有刑事訴訟法第101 條第1 項第3 款、同法第101 條之1\n    第2 款情形，而有羈押必要，於民國100 年7 月11日執行羈\n    押，因被告所犯係最輕本刑7 年以上有期徒刑之重罪及有事\n    實足認為有反覆實施同一犯罪之虞，上開羈押原因依然存在\n    ，仍有繼續羈押之必要，自100 年10月11日起延長羈押2月\n    。\n二、爰依刑事訴訟法第108 條第1 項裁定如主文。\n中    華    民    國  100     年    10    月    6    日\n                        刑事第九庭    審判長  蕭文學\n                                      法  官  吳芙如\n                                      法  官  鮑慧忠\n以上正本證明與原本無異。\n如不服本裁定，應於裁定送達後五日內向本院提出抗告狀(須附\n抗告狀繕本 )。\n中    華    民    國   100    年    10    月    6     日\n                                      書記官  林子惠",
  "structure": {
    "main": "陳○樺自民國壹佰年拾月拾壹日起延長羈押貳月。",
    "reason": "一、本件被告涉犯加重強制性交及加重強制猥褻等案件，經本院\n    認有刑事訴訟法第101 條第1 項第3 款、同法第101 條之1\n    第2 款情形，而有羈押必要，於民國100 年7 月11日執行羈\n    押，因被告所犯係最輕本刑7 年以上有期徒刑之重罪及有事\n    實足認為有反覆實施同一犯罪之虞，上開羈押原因依然存在\n    ，仍有繼續羈押之必要，自100 年10月11日起延長羈押2月\n    。\n二、爰依刑事訴訟法第108 條第1 項裁定如主文。"
  },
  "search": "臺灣彰化地方法院刑事裁定100年度侵訴字第36號公訴人臺灣彰化地方法院檢察署檢察官被告陳○樺代號000.選任辯護人劉嘉堯律師上列被告因加重強制性交等案件，經檢察官提起公訴（100年度偵字第4342、5503號），本院裁定如下：主文陳○樺自民國壹佰年拾月拾壹日起延長羈押貳月。理由一、本件被告涉犯加重強制性交及加重強制猥褻等案件，經本院認有刑事訴訟法第101條第1項第3款、同法第101條之1第2款情形，而有羈押必要，於民國100年7月11日執行羈押，因被告所犯係最輕本刑7年以上有期徒刑之重罪及有事實足認為有反覆實施同一犯罪之虞，上開羈押原因依然存在，仍有繼續羈押之必要，自100年10月11日起延長羈押2月。二、爰依刑事訴訟法第108條第1項裁定如主文。中華民國100年10月6日刑事第九庭審判長蕭文學法官吳芙如法官鮑慧忠以上正本證明與原本無異。如不服本裁定，應於裁定送達後五日內向本院提出抗告狀(須附抗告狀繕本)。中華民國100年10月6日書記官林子惠",
  "characters": {
    "judges": [
      "吳芙如",
      "鮑慧忠"
    ],
    "prosecutors": [

    ],
    "lawyers": [
      "劉嘉堯"
    ],
    "clerks": [

    ],
    "plaintiffs": [

    ],
    "defendants": [
      "陳○樺代號000."
    ],
    "prosecutor_office": [
      "臺灣彰化地方法院檢察署檢察官"
    ],
    "creditors": [

    ],
    "debtors": [

    ],
    "judicial_associate_officer": [

    ]
  },
  "adjudged_at": "2011-10-06",
  "created_at": "2016-02-14 07:14:13",
  "updated_at": "2016-02-14 07:14:13"
}