{
  "identify": "KSD-100-簡-4788-20111006-1",
  "court": {
    "name": "臺灣高雄地方法院",
    "code": "KSD"
  },
  "division": {
    "name": "刑事",
    "code": "M"
  },
  "year": 100,
  "word": "簡",
  "number": "4788",
  "jcheck": "1",
  "reason": "竊盜",
  "content": "臺灣高雄地方法院刑事簡易判決         100年度簡字第4788號\n聲  請  人  臺灣高雄地方法院檢察署檢察官\n被      告  龔順明\n上列被告因竊盜案件，經檢察官聲請以簡易判決處刑（100年度\n偵字第6466號），本院判決如下：\n    主      文\n龔順明竊盜，累犯，處有期徒刑伍月，如易科罰金，以新臺幣壹\n仟元折算壹日。\n    事實及理由\n一、本件除犯罪事實欄一、被告前科更正為「龔順明前於民國95\n    年間，因施用毒品案件，經本院以95年度訴字第2624號判處\n    有期徒刑6月確定；又因施用毒品案件，經本院以95年度訴\n    字第3762號判處有期徒刑8月、7月、4月，並定應執行有期\n    徒刑1年3月確定，上開4罪經本院96年度聲字第1474號刑事\n    裁定定其應執行之刑為有期徒刑1年7月，嗣經本院96年度聲\n    減字第404號刑事裁定減刑為有期徒刑9月15日確定，於96年\n    9月7日縮短刑期執行完畢出監。」、第11行補充為「自行車\n    1部（價值約新臺幣500元）」，犯罪事實欄二、更正為「案\n    經楊令吉訴由高雄市政府警察局三民第二分局報告偵辦。」\n    ；證據並所犯法條欄一、編號1第2頁之待證事實欄其中「酷\n    哥」應更正為「酷弟」，同欄證據清單第3頁編號5之證據名\n    稱補充「受理各類案件紀錄表及刑事案件報案三聯單各1份\n    」外，餘均引用如附件檢察官聲請簡易判決處刑書所載。\n二、被告於上揭時、地，竊取被害人楊令吉所有之自行車1部等\n    情，業據被告於警詢及偵查中，供承明確，核與證人即告訴\n    人楊令吉、被告友人吳建樺證述之情節相符，並有贓物認領\n    保管單1紙、現場照片3張、監視器畫面照片10張附卷可稽，\n    足堪認定。至被告辯稱：因伊將機車借給其綽號「酷弟」之\n    友人，「酷弟」才將上開自行車借給伊云云。惟被告於警詢\n    及偵查中雖均表示上開自行車為其友人所有，卻無法提供該\n    友人之年籍資料或聯絡方式，供警方查證，此據證人即查獲\n    警員陳溪文於偵查中證述明確。且被告將其使用之機車借與\n    友人，卻無法與該友人聯絡，被告於該友人歸還機車時，亦\n    未留下該友人之聯絡方式，顯與常情不符，則該名綽號「酷\n    弟」之友人是否實際存在，已屬有疑。另被告猶辯稱：伊誤\n    認上開自行車係綽號「酷弟」友人所有云云。然該友人僅告\n    知上開自行車未上鎖及停放地點，未說明上開自行車之外觀\n    ，亦未交付被告可供開啟上開自行車上鎖頭之鑰匙，此據被\n    告自承在卷，亦與一般徵得友人同意使用自行車之情形不符\n    。又被告於偵查中供稱伊約事發當日下午4、5時，吃完午餐\n    後即將上開自行車騎回原處停放云云。然告訴人於當日下午\n    3時20分許，發現其所有之自行車失竊，旋於當日下午6時21\n    分許向高雄市政府警察局三民第二分局陽明派出所報案，警\n    方經由現場監視器畫面得知上開自行車為被告所竊取，即循\n    線通知被告，被告接獲通知後，於當日晚間11時39分許，將\n    上開自行車停放回原處之鐵門外乙節，業據證人楊令吉指訴\n    歷歷，復有高雄市政府警察局三民第二分局陽明派出所受理\n    各類案件紀錄表、刑事案件報案三聯單各1份及當日晚間11\n    時39分之監視器畫面照片4張可資佐證，益徵被告係因警方\n    已循線查獲，始將上開自行車歸還。是被告前揭所辯，顯係\n    事後卸責之詞，要無可採。本件事證明確，被告犯行洵堪認\n    定，應予依法論科。\n三、核被告龔順明所為，係犯刑法第320條第1項之竊盜罪。又被\n    告有如聲請書所載之犯罪科刑執行情形，有臺灣高等法院被\n    告前案紀錄表1份在卷可查，其於受有期徒刑執行完畢後，5\n    年內故意再犯本件有期徒刑以上之罪，為累犯，應依刑法第\n    47條第1項規定，加重其刑。爰審酌被告正值壯年，不思以\n    正當方法謀取生活上所需，竟為貪圖不法利益，率爾竊取他\n    人財物，其犯罪之動機、手段、目的均非可取，惟念其所竊\n    財物價值尚非過鉅（約新臺幣500元），所竊財物業據告訴\n    人楊令吉領回，此有贓物認領保管單1紙可參，犯罪所生損\n    害已稍有減輕，兼衡其自稱小康之生活狀況、高職畢業之智\n    識程度等一切情狀，量處如主文所示之刑，並諭知如易科罰\n    金之折算標準。\n三、依刑事訴訟法第449條第1項前段、第3項、第454條第2項，\n    刑法第320條第1項、第47條第1項、第41條第1項前段，刑法\n    施行法第1條之1第1項、第2項前段，逕以簡易判決處刑如主\n    文。\n四、如不服本判決，應於判決送達之日起10日內，向本院提出上\n    訴狀。\n中    華    民    國   100    年    10    月    6     日\n                  高雄簡易庭  法  官  張嘉芳\n以上正本，係照原本作成，證明與原本無異。\n如不服本判決，得自收受送達之日起10日內，向本院提起上訴。\n中    華    民    國   100    年    10    月    6     日\n                              書記官  蕭永同\n附錄本案論罪科刑法條：\n刑法第320條第1項\n意圖為自己或第三人不法之所有，而竊取他人之動產者，為竊盜\n罪，處 5 年以下有期徒刑、拘役或 5 百元（新臺幣 1 萬 5 千\n元）以下罰金。\n附件：\n臺灣高雄地方法院檢察署檢察官聲請簡易判決處刑書\n                                     100年度偵字第6466號\n    被      告  龔順明  男  32歲（民國○○年○○月○日生）\n                        住高雄市○○區○○路33巷3號\n                        國民身分證統一編號：Ｚ000000000號\n上列被告因竊盜案件，已經偵查終結，認為宜以簡易判決處刑，\n茲敘述犯罪事實及證據並所犯法條如下：\n        犯罪事實\n一、龔順明前於民國95年間，因施用毒品等案件，經臺灣高雄地\n    方法院分別以95年度訴字第2624號、95年度訴字第3962號判\n    決判處有期徒刑6月、1年3月，上開2罪經同院以96年度聲字\n    第1474號裁定應執行有期徒刑1年7月，再經同院以96年度聲\n    簡字第404號裁定減刑為有期徒刑9月15日確定，95年12月14\n    日入監執行，甫於96年9月7日縮刑期滿執行完畢。竟意圖為\n    自己不法之所有，於100年1月14日15時17分許，由不知情之\n    吳建樺騎乘車號YWV-413號輕型機車搭載龔順明，至高雄市\n    三民區○○○路95巷2號旁元大證券停車場後，吳建樺即騎\n    車離去，龔順明乘四下無人之際，徒手竊取楊令吉所有停放\n    在上址之未上鎖之捷安特深色自行車1部，嗣經楊令吉報警\n    調閱監視器而循線查獲。\n二、案經高雄市政府警察局三民第二分局移送偵辦。\n        證據並所犯法條\n一、證據清單及待證事實\n┌──┬───────────┬───────────┐\n│編號│  證  據  名  稱      │  待  證  事  實      │\n├──┼───────────┼───────────┤\n│ 1  │被告龔順明於警詢及偵查│坦承有至上開地點騎乘上│\n│    │中之自白。            │開自行車離去之事實，惟│\n│    │                      │辯稱誤認該自行車為伊綽│\n│    │                      │號「酷哥」友人所有。  │\n├──┼───────────┼───────────┤\n│ 2  │證人吳建樺於警詢及偵查│當日下午2時許騎機車搭 │\n│    │中之證述              │載被告至建軍路與建榮路│\n│    │                      │口之某店家賣液晶螢幕，│\n│    │                      │之後被告要伊載他至水源│\n│    │                      │路附近之巷子牽被告友人│\n│    │                      │綽號「酷弟」之腳踏車，│\n│    │                      │伊騎車離去後有看見被告│\n│    │                      │騎走一輛腳踏車等語。  │\n├──┼───────────┼───────────┤\n│ 3  │證人陳溪文即承辦員警於│當時調閱監視器畫面，有│\n│    │偵查中之證述          │拍攝到吳建樺騎機車搭載│\n│    │                      │被告至上址，被告即騎乘│\n│    │                      │告訴人腳踏車離去，失竊│\n│    │                      │當日半夜被告到派出所說│\n│    │                      │明是向綽號「酷弟」友人│\n│    │                      │借的，但提不出該人之聯│\n│    │                      │絡方式等資料，故無從查│\n│    │                      │證。                  │\n├──┼───────────┼───────────┤\n│ 4  │告訴人楊令吉於警詢中之│上開自行車於100年1月14│\n│    │指訴                  │日15時20分許，在高雄市│\n│    │                      │三民區○○○路95巷2號 │\n│    │                      │元大證券停車場失竊，當│\n│    │                      │時該自行車未上鎖之事實│\n│    │                      │。                    │\n├──┼───────────┼───────────┤\n│ 5  │扣押物品目錄表、贓物認│上開全部犯罪事實。    │\n│    │領保管單、車輛詳細資料│                      │\n│    │報表、現場照片        │                      │\n├──┼───────────┼───────────┤\n│ 6  │楊令吉自行車失案監視畫│吳建樺於100年1月14日15│\n│    │面擷取面之照片10張    │時17分許，騎乘機車搭載│\n│    │                      │被告至九如一路與九如一│\n│    │                      │路95巷口，之後被告即下│\n│    │                      │車騎乘上開自行車離去之│\n│    │                      │事實。                │\n└──┴───────────┴───────────┘\n二、核被告龔順明所為，係犯刑法第320條第1項之竊盜罪嫌。又\n    被告曾受有期徒刑之執行完畢，有本署刑案資料查註紀錄表\n    1份附卷可參，5年以內故意再犯本件有期徒刑以上之罪，為\n    累犯，請依刑法第47條第1項之規定加重其刑。\n三、依刑事訴訟法第451條第1項聲請逕以簡易判決處刑。\n    此    致\n臺灣高雄地方法院\n中    華    民    國   100    年    7     月    21    日\n                              檢察官   羅瑞昌",
  "structure": {
    "main": "龔順明竊盜，累犯，處有期徒刑伍月，如易科罰金，以新臺幣壹\n仟元折算壹日。",
    "fact": "一、本件除犯罪事實欄一、被告前科更正為「龔順明前於民國95\n    年間，因施用毒品案件，經本院以95年度訴字第2624號判處\n    有期徒刑6月確定；又因施用毒品案件，經本院以95年度訴\n    字第3762號判處有期徒刑8月、7月、4月，並定應執行有期\n    徒刑1年3月確定，上開4罪經本院96年度聲字第1474號刑事\n    裁定定其應執行之刑為有期徒刑1年7月，嗣經本院96年度聲\n    減字第404號刑事裁定減刑為有期徒刑9月15日確定，於96年\n    9月7日縮短刑期執行完畢出監。」、第11行補充為「自行車\n    1部（價值約新臺幣500元）」，犯罪事實欄二、更正為「案\n    經楊令吉訴由高雄市政府警察局三民第二分局報告偵辦。」\n    ；證據並所犯法條欄一、編號1第2頁之待證事實欄其中「酷\n    哥」應更正為「酷弟」，同欄證據清單第3頁編號5之證據名\n    稱補充「受理各類案件紀錄表及刑事案件報案三聯單各1份\n    」外，餘均引用如附件檢察官聲請簡易判決處刑書所載。\n二、被告於上揭時、地，竊取被害人楊令吉所有之自行車1部等\n    情，業據被告於警詢及偵查中，供承明確，核與證人即告訴\n    人楊令吉、被告友人吳建樺證述之情節相符，並有贓物認領\n    保管單1紙、現場照片3張、監視器畫面照片10張附卷可稽，\n    足堪認定。至被告辯稱：因伊將機車借給其綽號「酷弟」之\n    友人，「酷弟」才將上開自行車借給伊云云。惟被告於警詢\n    及偵查中雖均表示上開自行車為其友人所有，卻無法提供該\n    友人之年籍資料或聯絡方式，供警方查證，此據證人即查獲\n    警員陳溪文於偵查中證述明確。且被告將其使用之機車借與\n    友人，卻無法與該友人聯絡，被告於該友人歸還機車時，亦\n    未留下該友人之聯絡方式，顯與常情不符，則該名綽號「酷\n    弟」之友人是否實際存在，已屬有疑。另被告猶辯稱：伊誤\n    認上開自行車係綽號「酷弟」友人所有云云。然該友人僅告\n    知上開自行車未上鎖及停放地點，未說明上開自行車之外觀\n    ，亦未交付被告可供開啟上開自行車上鎖頭之鑰匙，此據被\n    告自承在卷，亦與一般徵得友人同意使用自行車之情形不符\n    。又被告於偵查中供稱伊約事發當日下午4、5時，吃完午餐\n    後即將上開自行車騎回原處停放云云。然告訴人於當日下午\n    3時20分許，發現其所有之自行車失竊，旋於當日下午6時21\n    分許向高雄市政府警察局三民第二分局陽明派出所報案，警\n    方經由現場監視器畫面得知上開自行車為被告所竊取，即循\n    線通知被告，被告接獲通知後，於當日晚間11時39分許，將\n    上開自行車停放回原處之鐵門外乙節，業據證人楊令吉指訴\n    歷歷，復有高雄市政府警察局三民第二分局陽明派出所受理\n    各類案件紀錄表、刑事案件報案三聯單各1份及當日晚間11\n    時39分之監視器畫面照片4張可資佐證，益徵被告係因警方\n    已循線查獲，始將上開自行車歸還。是被告前揭所辯，顯係\n    事後卸責之詞，要無可採。本件事證明確，被告犯行洵堪認\n    定，應予依法論科。\n三、核被告龔順明所為，係犯刑法第320條第1項之竊盜罪。又被\n    告有如聲請書所載之犯罪科刑執行情形，有臺灣高等法院被\n    告前案紀錄表1份在卷可查，其於受有期徒刑執行完畢後，5\n    年內故意再犯本件有期徒刑以上之罪，為累犯，應依刑法第\n    47條第1項規定，加重其刑。爰審酌被告正值壯年，不思以\n    正當方法謀取生活上所需，竟為貪圖不法利益，率爾竊取他\n    人財物，其犯罪之動機、手段、目的均非可取，惟念其所竊\n    財物價值尚非過鉅（約新臺幣500元），所竊財物業據告訴\n    人楊令吉領回，此有贓物認領保管單1紙可參，犯罪所生損\n    害已稍有減輕，兼衡其自稱小康之生活狀況、高職畢業之智\n    識程度等一切情狀，量處如主文所示之刑，並諭知如易科罰\n    金之折算標準。\n三、依刑事訴訟法第449條第1項前段、第3項、第454條第2項，\n    刑法第320條第1項、第47條第1項、第41條第1項前段，刑法\n    施行法第1條之1第1項、第2項前段，逕以簡易判決處刑如主\n    文。\n四、如不服本判決，應於判決送達之日起10日內，向本院提出上\n    訴狀。",
    "reason": "一、本件除犯罪事實欄一、被告前科更正為「龔順明前於民國95\n    年間，因施用毒品案件，經本院以95年度訴字第2624號判處\n    有期徒刑6月確定；又因施用毒品案件，經本院以95年度訴\n    字第3762號判處有期徒刑8月、7月、4月，並定應執行有期\n    徒刑1年3月確定，上開4罪經本院96年度聲字第1474號刑事\n    裁定定其應執行之刑為有期徒刑1年7月，嗣經本院96年度聲\n    減字第404號刑事裁定減刑為有期徒刑9月15日確定，於96年\n    9月7日縮短刑期執行完畢出監。」、第11行補充為「自行車\n    1部（價值約新臺幣500元）」，犯罪事實欄二、更正為「案\n    經楊令吉訴由高雄市政府警察局三民第二分局報告偵辦。」\n    ；證據並所犯法條欄一、編號1第2頁之待證事實欄其中「酷\n    哥」應更正為「酷弟」，同欄證據清單第3頁編號5之證據名\n    稱補充「受理各類案件紀錄表及刑事案件報案三聯單各1份\n    」外，餘均引用如附件檢察官聲請簡易判決處刑書所載。\n二、被告於上揭時、地，竊取被害人楊令吉所有之自行車1部等\n    情，業據被告於警詢及偵查中，供承明確，核與證人即告訴\n    人楊令吉、被告友人吳建樺證述之情節相符，並有贓物認領\n    保管單1紙、現場照片3張、監視器畫面照片10張附卷可稽，\n    足堪認定。至被告辯稱：因伊將機車借給其綽號「酷弟」之\n    友人，「酷弟」才將上開自行車借給伊云云。惟被告於警詢\n    及偵查中雖均表示上開自行車為其友人所有，卻無法提供該\n    友人之年籍資料或聯絡方式，供警方查證，此據證人即查獲\n    警員陳溪文於偵查中證述明確。且被告將其使用之機車借與\n    友人，卻無法與該友人聯絡，被告於該友人歸還機車時，亦\n    未留下該友人之聯絡方式，顯與常情不符，則該名綽號「酷\n    弟」之友人是否實際存在，已屬有疑。另被告猶辯稱：伊誤\n    認上開自行車係綽號「酷弟」友人所有云云。然該友人僅告\n    知上開自行車未上鎖及停放地點，未說明上開自行車之外觀\n    ，亦未交付被告可供開啟上開自行車上鎖頭之鑰匙，此據被\n    告自承在卷，亦與一般徵得友人同意使用自行車之情形不符\n    。又被告於偵查中供稱伊約事發當日下午4、5時，吃完午餐\n    後即將上開自行車騎回原處停放云云。然告訴人於當日下午\n    3時20分許，發現其所有之自行車失竊，旋於當日下午6時21\n    分許向高雄市政府警察局三民第二分局陽明派出所報案，警\n    方經由現場監視器畫面得知上開自行車為被告所竊取，即循\n    線通知被告，被告接獲通知後，於當日晚間11時39分許，將\n    上開自行車停放回原處之鐵門外乙節，業據證人楊令吉指訴\n    歷歷，復有高雄市政府警察局三民第二分局陽明派出所受理\n    各類案件紀錄表、刑事案件報案三聯單各1份及當日晚間11\n    時39分之監視器畫面照片4張可資佐證，益徵被告係因警方\n    已循線查獲，始將上開自行車歸還。是被告前揭所辯，顯係\n    事後卸責之詞，要無可採。本件事證明確，被告犯行洵堪認\n    定，應予依法論科。\n三、核被告龔順明所為，係犯刑法第320條第1項之竊盜罪。又被\n    告有如聲請書所載之犯罪科刑執行情形，有臺灣高等法院被\n    告前案紀錄表1份在卷可查，其於受有期徒刑執行完畢後，5\n    年內故意再犯本件有期徒刑以上之罪，為累犯，應依刑法第\n    47條第1項規定，加重其刑。爰審酌被告正值壯年，不思以\n    正當方法謀取生活上所需，竟為貪圖不法利益，率爾竊取他\n    人財物，其犯罪之動機、手段、目的均非可取，惟念其所竊\n    財物價值尚非過鉅（約新臺幣500元），所竊財物業據告訴\n    人楊令吉領回，此有贓物認領保管單1紙可參，犯罪所生損\n    害已稍有減輕，兼衡其自稱小康之生活狀況、高職畢業之智\n    識程度等一切情狀，量處如主文所示之刑，並諭知如易科罰\n    金之折算標準。\n三、依刑事訴訟法第449條第1項前段、第3項、第454條第2項，\n    刑法第320條第1項、第47條第1項、第41條第1項前段，刑法\n    施行法第1條之1第1項、第2項前段，逕以簡易判決處刑如主\n    文。\n四、如不服本判決，應於判決送達之日起10日內，向本院提出上\n    訴狀。"
  },
  "search": "臺灣高雄地方法院刑事簡易判決100年度簡字第4788號聲請人臺灣高雄地方法院檢察署檢察官被告龔順明上列被告因竊盜案件，經檢察官聲請以簡易判決處刑（100年度偵字第6466號），本院判決如下：主文龔順明竊盜，累犯，處有期徒刑伍月，如易科罰金，以新臺幣壹仟元折算壹日。事實及理由一、本件除犯罪事實欄一、被告前科更正為「龔順明前於民國95年間，因施用毒品案件，經本院以95年度訴字第2624號判處有期徒刑6月確定；又因施用毒品案件，經本院以95年度訴字第3762號判處有期徒刑8月、7月、4月，並定應執行有期徒刑1年3月確定，上開4罪經本院96年度聲字第1474號刑事裁定定其應執行之刑為有期徒刑1年7月，嗣經本院96年度聲減字第404號刑事裁定減刑為有期徒刑9月15日確定，於96年9月7日縮短刑期執行完畢出監。」、第11行補充為「自行車1部（價值約新臺幣500元）」，犯罪事實欄二、更正為「案經楊令吉訴由高雄市政府警察局三民第二分局報告偵辦。」；證據並所犯法條欄一、編號1第2頁之待證事實欄其中「酷哥」應更正為「酷弟」，同欄證據清單第3頁編號5之證據名稱補充「受理各類案件紀錄表及刑事案件報案三聯單各1份」外，餘均引用如附件檢察官聲請簡易判決處刑書所載。二、被告於上揭時、地，竊取被害人楊令吉所有之自行車1部等情，業據被告於警詢及偵查中，供承明確，核與證人即告訴人楊令吉、被告友人吳建樺證述之情節相符，並有贓物認領保管單1紙、現場照片3張、監視器畫面照片10張附卷可稽，足堪認定。至被告辯稱：因伊將機車借給其綽號「酷弟」之友人，「酷弟」才將上開自行車借給伊云云。惟被告於警詢及偵查中雖均表示上開自行車為其友人所有，卻無法提供該友人之年籍資料或聯絡方式，供警方查證，此據證人即查獲警員陳溪文於偵查中證述明確。且被告將其使用之機車借與友人，卻無法與該友人聯絡，被告於該友人歸還機車時，亦未留下該友人之聯絡方式，顯與常情不符，則該名綽號「酷弟」之友人是否實際存在，已屬有疑。另被告猶辯稱：伊誤認上開自行車係綽號「酷弟」友人所有云云。然該友人僅告知上開自行車未上鎖及停放地點，未說明上開自行車之外觀，亦未交付被告可供開啟上開自行車上鎖頭之鑰匙，此據被告自承在卷，亦與一般徵得友人同意使用自行車之情形不符。又被告於偵查中供稱伊約事發當日下午4、5時，吃完午餐後即將上開自行車騎回原處停放云云。然告訴人於當日下午3時20分許，發現其所有之自行車失竊，旋於當日下午6時21分許向高雄市政府警察局三民第二分局陽明派出所報案，警方經由現場監視器畫面得知上開自行車為被告所竊取，即循線通知被告，被告接獲通知後，於當日晚間11時39分許，將上開自行車停放回原處之鐵門外乙節，業據證人楊令吉指訴歷歷，復有高雄市政府警察局三民第二分局陽明派出所受理各類案件紀錄表、刑事案件報案三聯單各1份及當日晚間11時39分之監視器畫面照片4張可資佐證，益徵被告係因警方已循線查獲，始將上開自行車歸還。是被告前揭所辯，顯係事後卸責之詞，要無可採。本件事證明確，被告犯行洵堪認定，應予依法論科。三、核被告龔順明所為，係犯刑法第320條第1項之竊盜罪。又被告有如聲請書所載之犯罪科刑執行情形，有臺灣高等法院被告前案紀錄表1份在卷可查，其於受有期徒刑執行完畢後，5年內故意再犯本件有期徒刑以上之罪，為累犯，應依刑法第47條第1項規定，加重其刑。爰審酌被告正值壯年，不思以正當方法謀取生活上所需，竟為貪圖不法利益，率爾竊取他人財物，其犯罪之動機、手段、目的均非可取，惟念其所竊財物價值尚非過鉅（約新臺幣500元），所竊財物業據告訴人楊令吉領回，此有贓物認領保管單1紙可參，犯罪所生損害已稍有減輕，兼衡其自稱小康之生活狀況、高職畢業之智識程度等一切情狀，量處如主文所示之刑，並諭知如易科罰金之折算標準。三、依刑事訴訟法第449條第1項前段、第3項、第454條第2項，刑法第320條第1項、第47條第1項、第41條第1項前段，刑法施行法第1條之1第1項、第2項前段，逕以簡易判決處刑如主文。四、如不服本判決，應於判決送達之日起10日內，向本院提出上訴狀。中華民國100年10月6日高雄簡易庭法官張嘉芳以上正本，係照原本作成，證明與原本無異。如不服本判決，得自收受送達之日起10日內，向本院提起上訴。中華民國100年10月6日書記官蕭永同附錄本案論罪科刑法條：刑法第320條第1項意圖為自己或第三人不法之所有，而竊取他人之動產者，為竊盜罪，處5年以下有期徒刑、拘役或5百元（新臺幣1萬5千元）以下罰金。附件：臺灣高雄地方法院檢察署檢察官聲請簡易判決處刑書100年度偵字第6466號被告龔順明男32歲（民國○○年○○月○日生）住高雄市○○區○○路33巷3號國民身分證統一編號：Ｚ000000000號上列被告因竊盜案件，已經偵查終結，認為宜以簡易判決處刑，茲敘述犯罪事實及證據並所犯法條如下：犯罪事實一、龔順明前於民國95年間，因施用毒品等案件，經臺灣高雄地方法院分別以95年度訴字第2624號、95年度訴字第3962號判決判處有期徒刑6月、1年3月，上開2罪經同院以96年度聲字第1474號裁定應執行有期徒刑1年7月，再經同院以96年度聲簡字第404號裁定減刑為有期徒刑9月15日確定，95年12月14日入監執行，甫於96年9月7日縮刑期滿執行完畢。竟意圖為自己不法之所有，於100年1月14日15時17分許，由不知情之吳建樺騎乘車號YWV-413號輕型機車搭載龔順明，至高雄市三民區○○○路95巷2號旁元大證券停車場後，吳建樺即騎車離去，龔順明乘四下無人之際，徒手竊取楊令吉所有停放在上址之未上鎖之捷安特深色自行車1部，嗣經楊令吉報警調閱監視器而循線查獲。二、案經高雄市政府警察局三民第二分局移送偵辦。證據並所犯法條一、證據清單及待證事實┌──┬───────────┬───────────┐│編號│證據名稱│待證事實│├──┼───────────┼───────────┤│1│被告龔順明於警詢及偵查│坦承有至上開地點騎乘上│││中之自白。│開自行車離去之事實，惟││││辯稱誤認該自行車為伊綽││││號「酷哥」友人所有。│├──┼───────────┼───────────┤│2│證人吳建樺於警詢及偵查│當日下午2時許騎機車搭│││中之證述│載被告至建軍路與建榮路││││口之某店家賣液晶螢幕，││││之後被告要伊載他至水源││││路附近之巷子牽被告友人││││綽號「酷弟」之腳踏車，││││伊騎車離去後有看見被告││││騎走一輛腳踏車等語。│├──┼───────────┼───────────┤│3│證人陳溪文即承辦員警於│當時調閱監視器畫面，有│││偵查中之證述│拍攝到吳建樺騎機車搭載││││被告至上址，被告即騎乘││││告訴人腳踏車離去，失竊││││當日半夜被告到派出所說││││明是向綽號「酷弟」友人││││借的，但提不出該人之聯││││絡方式等資料，故無從查││││證。│├──┼───────────┼───────────┤│4│告訴人楊令吉於警詢中之│上開自行車於100年1月14│││指訴│日15時20分許，在高雄市││││三民區○○○路95巷2號││││元大證券停車場失竊，當││││時該自行車未上鎖之事實││││。│├──┼───────────┼───────────┤│5│扣押物品目錄表、贓物認│上開全部犯罪事實。│││領保管單、車輛詳細資料││││報表、現場照片││├──┼───────────┼───────────┤│6│楊令吉自行車失案監視畫│吳建樺於100年1月14日15│││面擷取面之照片10張│時17分許，騎乘機車搭載││││被告至九如一路與九如一││││路95巷口，之後被告即下││││車騎乘上開自行車離去之││││事實。│└──┴───────────┴───────────┘二、核被告龔順明所為，係犯刑法第320條第1項之竊盜罪嫌。又被告曾受有期徒刑之執行完畢，有本署刑案資料查註紀錄表1份附卷可參，5年以內故意再犯本件有期徒刑以上之罪，為累犯，請依刑法第47條第1項之規定加重其刑。三、依刑事訴訟法第451條第1項聲請逕以簡易判決處刑。此致臺灣高雄地方法院中華民國100年7月21日檢察官羅瑞昌",
  "characters": {
    "judges": [
      "張嘉芳"
    ],
    "prosecutors": [

    ],
    "lawyers": [

    ],
    "clerks": [
      "蕭永同"
    ],
    "plaintiffs": [

    ],
    "defendants": [
      "龔順明",
      "龔順明  男  32歲（民國○○年○○月○日生）"
    ],
    "prosecutor_office": [
      "臺灣高雄地方法院檢察署檢察官"
    ],
    "creditors": [

    ],
    "debtors": [

    ],
    "judicial_associate_officer": [

    ]
  },
  "adjudged_at": "2011-10-06",
  "created_at": "2016-02-14 07:24:30",
  "updated_at": "2016-02-14 07:24:30"
}