{
  "identify": "MLD-100-苗簡-806-20111006-1",
  "court": {
    "name": "臺灣苗栗地方法院",
    "code": "MLD"
  },
  "division": {
    "name": "刑事",
    "code": "M"
  },
  "year": 100,
  "word": "苗簡",
  "number": "806",
  "jcheck": "1",
  "reason": "違反電業法",
  "content": "臺灣苗栗地方法院刑事簡易判決        100年度苗簡字第806號\n聲  請  人  臺灣苗栗地方法院檢察署檢察官\n被      告  黃勇強\n上列被告因違反電業法案件，經檢察官聲請簡易判決處刑（100\n年度撤緩偵字第92號），本院判決如下：\n    主    文\n黃勇強犯電業法第一百零六條第一款之竊電罪，處拘役貳拾日，\n如易科罰金，以新臺幣壹仟元折算壹日，扣案之電線貳條沒收。\n    犯罪事實及理由\n一、本件犯罪事實及證據均引用檢察官聲請簡易判決處刑書內容\n    之記載（如附件）。並就檢察官聲請簡易判決處刑書中被告\n    未繳納電費之用電地點更正為「苗栗縣公館鄉鶴山村9 鄰鶴\n    山290 號」。\n二、應適用之法條：\n    （一）刑事訴訟法第449 條第1 項、第454 條、第450 條第\n          1 項。\n    （二）電業法第106 條第1 款。\n    （三）刑法第11條前段、第41條第1 項前段、第38條第1項\n          第2 款。\n三、如不服本判決，得自收受送達之日起10日內，向本院提起上\n    訴。\n中    華    民    國   100    年    10    月    6     日\n                     苗栗簡易庭      法  官  林靜雯\n以上正本證明與原本無異。\n如不服本判決應於收受判決後10日內向本院提出上訴書狀，並應\n敘述具體理由。其未敘述上訴理由者，應於上訴期間屆滿後20\n日內向本院補提理由書（均須附繕本）「切勿逕送上級法院」。\n                                     書記官  劉千瑄\n中    華    民    國   100    年    10    月    6     日\n附錄本判決論罪科刑法條：\n電業法第106條：\n有左列行為之一者為竊電，處5年以下有期徒刑、拘役或5百元以\n下罰金：\n一、未經電業供電，而在其供電線路上私接電線者。\n二、繞越電度表或其他計電器，損壞或改動表外之線路者。\n三、損壞或改變電度表、無效電力計、其他計電器之構造，或以\n    其他方法使其失效不準者。\n四、在電價較低之線路上，私接電價較高之電器者。\n五、包燈用戶，在原定電燈盞數及瓦特數以外，私自增加盞數或\n    瓦特數者。\n六、電力用戶，在原申請馬力數、瓩數或仟伏安數以外，私自增\n    加馬力數瓩數或仟伏安數者。\n附件：\n臺灣苗栗地方法院檢察署檢察官聲請簡易判決處刑書\n                                   100年度撤緩偵字第92號\n    被      告  黃勇強  男  25歲（民國○○年○月○○日生）\n                        住苗栗縣公館鄉鶴山村9鄰鶴山291之\n                        2號\n                        國民身分證統一編號：Ｚ000000000號\n上被告黃勇強因違反電業法案件，業經偵查終結，認為宜以簡易\n判決處刑，茲將犯罪事實及證據並所犯法條分敘如左：\n        犯罪事實\n一、黃勇強因無力繳納所居住之苗栗縣公館鄉鶴山村9鄰鶴山291\n    之2號住處電費，遭臺灣電力股份有限公司（下簡稱台電公\n    司）於民國99年8月16日停止供電。詎其竟意圖為自己不法\n    所有之犯意，於99年8月29日13時許，自行將上住處之電表\n    外殼拆卸後，再由電表底座插入電線之方式，私自竊取電力\n    使用。嗣於99年9月7日上午9時許，為警會同台電公司稽查\n    員呂炳祥至現場查獲，黃勇強合計竊得電力約944度。\n二、案經台電公司訴由苗栗縣警察局苗栗分局報告偵辦，前經緩\n    起訴處分，惟黃勇強於緩起訴期間違反刑事訴訟法第253條\n    之3第1項之規定，經依職權撤銷原緩起訴處分。\n        證據並所犯法條\n一、依下列證據，被告黃勇強所涉罪嫌可堪認定：\n    (一)被告黃勇強於警詢及偵查中之自白。\n    (二)告訴代理人呂炳祥於警詢之指訴。\n    (三)台電公司實地調查書。\n    (四)現場照片4張。\n    (五)扣案之電線2條。\n二、核被告黃勇強所為，係犯犯電業法第106條第1款之竊電罪嫌\n    。扣案之電線2條，係被告犯罪所用，併請依法宣告沒收。\n三、依刑事訴訟法第451條第1項聲請逕以簡易判決處刑。\n    此    致\n臺灣苗栗地方法院\n中    華    民    國    100    年    8    月    4    日\n                              檢  察  官  蕭  慶  賢\n本件證明與原本無異\n中    華    民    國   100    年    8     月    16    日\n                              書  記  官  彭  國  恭\n電業法第106條\n（罰則（二）----竊電）\n有下列行為之一者為竊電，處 5 年以下有期徒刑、拘役或 5 百\n元以下罰金：\n一、未經電業供電，而在其供電線路上私接電線者。",
  "structure": {
    "main": "黃勇強犯電業法第一百零六條第一款之竊電罪，處拘役貳拾日，\n如易科罰金，以新臺幣壹仟元折算壹日，扣案之電線貳條沒收。",
    "fact": "一、本件犯罪事實及證據均引用檢察官聲請簡易判決處刑書內容\n    之記載（如附件）。並就檢察官聲請簡易判決處刑書中被告\n    未繳納電費之用電地點更正為「苗栗縣公館鄉鶴山村9 鄰鶴\n    山290 號」。\n二、應適用之法條：\n    （一）刑事訴訟法第449 條第1 項、第454 條、第450 條第\n          1 項。\n    （二）電業法第106 條第1 款。\n    （三）刑法第11條前段、第41條第1 項前段、第38條第1項\n          第2 款。\n三、如不服本判決，得自收受送達之日起10日內，向本院提起上\n    訴。",
    "reason": "一、本件犯罪事實及證據均引用檢察官聲請簡易判決處刑書內容\n    之記載（如附件）。並就檢察官聲請簡易判決處刑書中被告\n    未繳納電費之用電地點更正為「苗栗縣公館鄉鶴山村9 鄰鶴\n    山290 號」。\n二、應適用之法條：\n    （一）刑事訴訟法第449 條第1 項、第454 條、第450 條第\n          1 項。\n    （二）電業法第106 條第1 款。\n    （三）刑法第11條前段、第41條第1 項前段、第38條第1項\n          第2 款。\n三、如不服本判決，得自收受送達之日起10日內，向本院提起上\n    訴。"
  },
  "search": "臺灣苗栗地方法院刑事簡易判決100年度苗簡字第806號聲請人臺灣苗栗地方法院檢察署檢察官被告黃勇強上列被告因違反電業法案件，經檢察官聲請簡易判決處刑（100年度撤緩偵字第92號），本院判決如下：主文黃勇強犯電業法第一百零六條第一款之竊電罪，處拘役貳拾日，如易科罰金，以新臺幣壹仟元折算壹日，扣案之電線貳條沒收。犯罪事實及理由一、本件犯罪事實及證據均引用檢察官聲請簡易判決處刑書內容之記載（如附件）。並就檢察官聲請簡易判決處刑書中被告未繳納電費之用電地點更正為「苗栗縣公館鄉鶴山村9鄰鶴山290號」。二、應適用之法條：（一）刑事訴訟法第449條第1項、第454條、第450條第1項。（二）電業法第106條第1款。（三）刑法第11條前段、第41條第1項前段、第38條第1項第2款。三、如不服本判決，得自收受送達之日起10日內，向本院提起上訴。中華民國100年10月6日苗栗簡易庭法官林靜雯以上正本證明與原本無異。如不服本判決應於收受判決後10日內向本院提出上訴書狀，並應敘述具體理由。其未敘述上訴理由者，應於上訴期間屆滿後20日內向本院補提理由書（均須附繕本）「切勿逕送上級法院」。書記官劉千瑄中華民國100年10月6日附錄本判決論罪科刑法條：電業法第106條：有左列行為之一者為竊電，處5年以下有期徒刑、拘役或5百元以下罰金：一、未經電業供電，而在其供電線路上私接電線者。二、繞越電度表或其他計電器，損壞或改動表外之線路者。三、損壞或改變電度表、無效電力計、其他計電器之構造，或以其他方法使其失效不準者。四、在電價較低之線路上，私接電價較高之電器者。五、包燈用戶，在原定電燈盞數及瓦特數以外，私自增加盞數或瓦特數者。六、電力用戶，在原申請馬力數、瓩數或仟伏安數以外，私自增加馬力數瓩數或仟伏安數者。附件：臺灣苗栗地方法院檢察署檢察官聲請簡易判決處刑書100年度撤緩偵字第92號被告黃勇強男25歲（民國○○年○月○○日生）住苗栗縣公館鄉鶴山村9鄰鶴山291之2號國民身分證統一編號：Ｚ000000000號上被告黃勇強因違反電業法案件，業經偵查終結，認為宜以簡易判決處刑，茲將犯罪事實及證據並所犯法條分敘如左：犯罪事實一、黃勇強因無力繳納所居住之苗栗縣公館鄉鶴山村9鄰鶴山291之2號住處電費，遭臺灣電力股份有限公司（下簡稱台電公司）於民國99年8月16日停止供電。詎其竟意圖為自己不法所有之犯意，於99年8月29日13時許，自行將上住處之電表外殼拆卸後，再由電表底座插入電線之方式，私自竊取電力使用。嗣於99年9月7日上午9時許，為警會同台電公司稽查員呂炳祥至現場查獲，黃勇強合計竊得電力約944度。二、案經台電公司訴由苗栗縣警察局苗栗分局報告偵辦，前經緩起訴處分，惟黃勇強於緩起訴期間違反刑事訴訟法第253條之3第1項之規定，經依職權撤銷原緩起訴處分。證據並所犯法條一、依下列證據，被告黃勇強所涉罪嫌可堪認定：(一)被告黃勇強於警詢及偵查中之自白。(二)告訴代理人呂炳祥於警詢之指訴。(三)台電公司實地調查書。(四)現場照片4張。(五)扣案之電線2條。二、核被告黃勇強所為，係犯犯電業法第106條第1款之竊電罪嫌。扣案之電線2條，係被告犯罪所用，併請依法宣告沒收。三、依刑事訴訟法第451條第1項聲請逕以簡易判決處刑。此致臺灣苗栗地方法院中華民國100年8月4日檢察官蕭慶賢本件證明與原本無異中華民國100年8月16日書記官彭國恭電業法第106條（罰則（二）----竊電）有下列行為之一者為竊電，處5年以下有期徒刑、拘役或5百元以下罰金：一、未經電業供電，而在其供電線路上私接電線者。",
  "characters": {
    "judges": [
      "林靜雯"
    ],
    "prosecutors": [

    ],
    "lawyers": [

    ],
    "clerks": [
      "劉千瑄"
    ],
    "plaintiffs": [

    ],
    "defendants": [
      "黃勇強",
      "黃勇強  男  25歲（民國○○年○月○○日生）"
    ],
    "prosecutor_office": [
      "臺灣苗栗地方法院檢察署檢察官"
    ],
    "creditors": [

    ],
    "debtors": [

    ],
    "judicial_associate_officer": [

    ]
  },
  "adjudged_at": "2011-10-06",
  "created_at": "2016-02-14 07:33:35",
  "updated_at": "2016-02-14 07:33:35"
}