{
  "identify": "PCD-92-訴-2000-20040109-4",
  "court": {
    "name": "臺灣新北地方法院",
    "code": "PCD"
  },
  "division": {
    "name": "刑事",
    "code": "M"
  },
  "year": 92,
  "word": "訴",
  "number": "2000",
  "jcheck": "4",
  "reason": "槍砲彈藥刀械管制等",
  "content": "臺灣板橋地方法院刑事裁定                        九十二年度訴字第二號\n    公  訴  人  台灣板橋地方法院檢察署檢察官\n    被      告  乙○○\n    指定辯護人  甲○公設辯護人  吳天明\n    被      告  丙○○\n    選任辯護人  黃世瑋律師\n                楊永成律師\n                朱容辰律師\n右列被告因槍砲彈藥刀械管制等案件，甲○裁定如左：\n    主  文\n乙○○、丙○○均自民國玖拾參年貳月壹日起延長羈押貳月。\n    理  由\n被告乙○○、丙○○因違反槍砲彈藥刀械管制等案件，前經甲○訊問後，認其等犯罪\n嫌疑重大，所犯係最輕本刑五年以上有期徒刑之罪，有羈押之必要，而於民國九十二\n年九月一日依刑事訴訟法第一百零一條第一項第三款規定予以羈押，並於同年十一月\n十一日裁定自九十二年十二月一日起，延長羈押二月。茲甲○於九十三年一月二日訊\n問被告二人後，認前項羈押原因依然存在，且仍有繼續羈押之必要，應自九十三年二\n月一日起延長羈押二月，爰依刑事訴訟法第一百零八條第一項、第二項，裁定如主文\n。\n中      華      民      國    九十三    年      一      月      九      日\n                              臺灣板橋地方法院刑事第八庭\n                                    審判長法  官  樊季康\n                                          法  官  葉靜芳\n                                          法  官  劉元斐\n右正本證明與原本無異。\n如不服本裁定，應於裁定送達後五日內向甲○提出抗告狀。\n                                          書記官    郭玉芬\n中      華      民      國    九十三    年      一      月      九      日\n",
  "structure": {
    "main": "乙○○、丙○○均自民國玖拾參年貳月壹日起延長羈押貳月。",
    "reason": "被告乙○○、丙○○因違反槍砲彈藥刀械管制等案件，前經甲○訊問後，認其等犯罪\n嫌疑重大，所犯係最輕本刑五年以上有期徒刑之罪，有羈押之必要，而於民國九十二\n年九月一日依刑事訴訟法第一百零一條第一項第三款規定予以羈押，並於同年十一月\n十一日裁定自九十二年十二月一日起，延長羈押二月。茲甲○於九十三年一月二日訊\n問被告二人後，認前項羈押原因依然存在，且仍有繼續羈押之必要，應自九十三年二\n月一日起延長羈押二月，爰依刑事訴訟法第一百零八條第一項、第二項，裁定如主文\n。"
  },
  "search": "臺灣板橋地方法院刑事裁定九十二年度訴字第二號公訴人台灣板橋地方法院檢察署檢察官被告乙○○指定辯護人甲○公設辯護人吳天明被告丙○○選任辯護人黃世瑋律師楊永成律師朱容辰律師右列被告因槍砲彈藥刀械管制等案件，甲○裁定如左：主文乙○○、丙○○均自民國玖拾參年貳月壹日起延長羈押貳月。理由被告乙○○、丙○○因違反槍砲彈藥刀械管制等案件，前經甲○訊問後，認其等犯罪嫌疑重大，所犯係最輕本刑五年以上有期徒刑之罪，有羈押之必要，而於民國九十二年九月一日依刑事訴訟法第一百零一條第一項第三款規定予以羈押，並於同年十一月十一日裁定自九十二年十二月一日起，延長羈押二月。茲甲○於九十三年一月二日訊問被告二人後，認前項羈押原因依然存在，且仍有繼續羈押之必要，應自九十三年二月一日起延長羈押二月，爰依刑事訴訟法第一百零八條第一項、第二項，裁定如主文。中華民國九十三年一月九日臺灣板橋地方法院刑事第八庭審判長法官樊季康法官葉靜芳法官劉元斐右正本證明與原本無異。如不服本裁定，應於裁定送達後五日內向甲○提出抗告狀。書記官郭玉芬中華民國九十三年一月九日",
  "characters": {
    "judges": [
      "樊季康",
      "葉靜芳",
      "劉元斐"
    ],
    "prosecutors": [

    ],
    "lawyers": [
      "黃世瑋",
      "楊永成",
      "朱容辰"
    ],
    "clerks": [
      "郭玉芬"
    ],
    "plaintiffs": [

    ],
    "defendants": [
      "乙○○",
      "丙○○"
    ],
    "prosecutor_office": [
      "台灣板橋地方法院檢察署檢察官"
    ],
    "creditors": [

    ],
    "debtors": [

    ],
    "judicial_associate_officer": [

    ]
  },
  "adjudged_at": "2004-01-09",
  "created_at": "2016-02-06 05:34:32",
  "updated_at": "2016-02-06 05:34:32"
}