{
  "identify": "TPD-94-訴-2915-20050818-1",
  "court": {
    "name": "臺灣臺北地方法院",
    "code": "TPD"
  },
  "division": {
    "name": "民事",
    "code": "V"
  },
  "year": 94,
  "word": "訴",
  "number": "2915",
  "jcheck": "1",
  "reason": "清償借款",
  "content": "臺灣臺北地方法院民事判決              94年度訴字第2915號\n原      告  台北國際商業銀行股份有限公司\n法定代理人  丙○○\n訴訟代理人  甲○○\n            乙○○\n被      告  丁○○\n上列當事人間請求清償借款事件，於民國94年8月2日言詞辯論\n終結，本院判決如下：\n    主    文\n被告應給付原告新台幣伍拾柒萬玖仟肆佰伍拾壹元，及如附表所\n示之利息、違約金。\n訴訟費用由被告負擔。\n    事    實\n甲、原告方面：\n一、聲明：如主文第1項所示，並願供擔保聲請宣告假執行。\n二、陳述：被告於民國93年11月4日向原告借用新台幣（下同）\n    600,000元，約定借款期間自93年11月4日起至98年11月4日\n    止，利息自貸放日起，前3個月按週年利率2.88%，第4個月\n    至第6個月按週年利率5.88%，自第7個月起按週年利率11.88\n    ％固定計算，被告應自93年11月4日起以每1個月為1期，共\n    分60期按年金法平均攤還本金及利息，逾期清償在6個月以\n    內者，按上開利率10％，超過6個月者，按上開利率百分之\n    20％計付違約金，詎被告自94年2月4日起即未再依約繳款，\n    依約本件借款視為全部到期，尚欠本金579,451元及如主文\n    第1項所示之利息、違約金迄未清償，為此提起本件訴訟。\n三、證據：提出放款借據、放款客戶還款繳息查詢單各1件為證\n    。\n乙、被告方面：\n    被告未於言詞辯論期日到場，亦未提出書狀作何聲明或陳述\n    。\n    理    由\n甲、程序方面：\n一、原告主張兩造合意以本院為第1審管轄法院之事實，業據其\n    提出放款借據1紙為證，堪信原告之主張為真正，本院依民\n    事訴訟法第24條第1項規定有第1審管轄權。\n二、本件被告未於言詞辯論期日到場，核無民事訴訟法第386條\n    所列各款情形，應依原告之聲請，由其一造辯論而為判決。\n乙、實體方面：\n一、本件原告主張之事實，已據其提出放款借據、放款客戶還款\n    繳息查詢單各1件為證，且被告未於言詞辯論期日到場爭執\n    ，亦未提出書狀供本院審酌，自堪信原告之主張為真實。\n二、從而，原告依消費借貸之法律關係，請求被告給付579,451\n    元及如主文第1項所示之利息、違約金，為有理由，應予准\n    許。\n三、結論：本件原告之訴為有理由，依民事訴訟法第385條第1項\n    前段、第78條，判決如主文。\n中    華    民    國    94    年    8     月    18    日\n                  民事第五庭    法  官  羅富美\n以上正本係照原本作成\n如對本判決上訴，須於判決送達後20日內向本院提出上訴狀\n中    華    民    國    94    年    8     月    18    日\n                                書記官  許博為\n",
  "structure": {
    "main": "被告應給付原告新台幣伍拾柒萬玖仟肆佰伍拾壹元，及如附表所\n示之利息、違約金。\n訴訟費用由被告負擔。",
    "fact": "甲、原告方面：\n一、聲明：如主文第1項所示，並願供擔保聲請宣告假執行。\n二、陳述：被告於民國93年11月4日向原告借用新台幣（下同）\n    600,000元，約定借款期間自93年11月4日起至98年11月4日\n    止，利息自貸放日起，前3個月按週年利率2.88%，第4個月\n    至第6個月按週年利率5.88%，自第7個月起按週年利率11.88\n    ％固定計算，被告應自93年11月4日起以每1個月為1期，共\n    分60期按年金法平均攤還本金及利息，逾期清償在6個月以\n    內者，按上開利率10％，超過6個月者，按上開利率百分之\n    20％計付違約金，詎被告自94年2月4日起即未再依約繳款，\n    依約本件借款視為全部到期，尚欠本金579,451元及如主文\n    第1項所示之利息、違約金迄未清償，為此提起本件訴訟。\n三、證據：提出放款借據、放款客戶還款繳息查詢單各1件為證\n    。\n乙、被告方面：\n    被告未於言詞辯論期日到場，亦未提出書狀作何聲明或陳述\n    。",
    "reason": "甲、程序方面：\n一、原告主張兩造合意以本院為第1審管轄法院之事實，業據其\n    提出放款借據1紙為證，堪信原告之主張為真正，本院依民\n    事訴訟法第24條第1項規定有第1審管轄權。\n二、本件被告未於言詞辯論期日到場，核無民事訴訟法第386條\n    所列各款情形，應依原告之聲請，由其一造辯論而為判決。\n乙、實體方面：\n一、本件原告主張之事實，已據其提出放款借據、放款客戶還款\n    繳息查詢單各1件為證，且被告未於言詞辯論期日到場爭執\n    ，亦未提出書狀供本院審酌，自堪信原告之主張為真實。\n二、從而，原告依消費借貸之法律關係，請求被告給付579,451\n    元及如主文第1項所示之利息、違約金，為有理由，應予准\n    許。\n三、結論：本件原告之訴為有理由，依民事訴訟法第385條第1項\n    前段、第78條，判決如主文。\n中    華    民    國    94    年    8     月    18    日\n                  民事第五庭    法  官  羅富美\n以上正本係照原本作成\n如對本判決上訴，須於判決送達後20日內向本院提出上訴狀"
  },
  "search": "臺灣臺北地方法院民事判決94年度訴字第2915號原告台北國際商業銀行股份有限公司法定代理人丙○○訴訟代理人甲○○乙○○被告丁○○上列當事人間請求清償借款事件，於民國94年8月2日言詞辯論終結，本院判決如下：主文被告應給付原告新台幣伍拾柒萬玖仟肆佰伍拾壹元，及如附表所示之利息、違約金。訴訟費用由被告負擔。事實甲、原告方面：一、聲明：如主文第1項所示，並願供擔保聲請宣告假執行。二、陳述：被告於民國93年11月4日向原告借用新台幣（下同）600,000元，約定借款期間自93年11月4日起至98年11月4日止，利息自貸放日起，前3個月按週年利率2.88%，第4個月至第6個月按週年利率5.88%，自第7個月起按週年利率11.88％固定計算，被告應自93年11月4日起以每1個月為1期，共分60期按年金法平均攤還本金及利息，逾期清償在6個月以內者，按上開利率10％，超過6個月者，按上開利率百分之20％計付違約金，詎被告自94年2月4日起即未再依約繳款，依約本件借款視為全部到期，尚欠本金579,451元及如主文第1項所示之利息、違約金迄未清償，為此提起本件訴訟。三、證據：提出放款借據、放款客戶還款繳息查詢單各1件為證。乙、被告方面：被告未於言詞辯論期日到場，亦未提出書狀作何聲明或陳述。理由甲、程序方面：一、原告主張兩造合意以本院為第1審管轄法院之事實，業據其提出放款借據1紙為證，堪信原告之主張為真正，本院依民事訴訟法第24條第1項規定有第1審管轄權。二、本件被告未於言詞辯論期日到場，核無民事訴訟法第386條所列各款情形，應依原告之聲請，由其一造辯論而為判決。乙、實體方面：一、本件原告主張之事實，已據其提出放款借據、放款客戶還款繳息查詢單各1件為證，且被告未於言詞辯論期日到場爭執，亦未提出書狀供本院審酌，自堪信原告之主張為真實。二、從而，原告依消費借貸之法律關係，請求被告給付579,451元及如主文第1項所示之利息、違約金，為有理由，應予准許。三、結論：本件原告之訴為有理由，依民事訴訟法第385條第1項前段、第78條，判決如主文。中華民國94年8月18日民事第五庭法官羅富美以上正本係照原本作成如對本判決上訴，須於判決送達後20日內向本院提出上訴狀中華民國94年8月18日書記官許博為",
  "characters": {
    "judges": [
      "羅富美"
    ],
    "prosecutors": [

    ],
    "lawyers": [

    ],
    "clerks": [
      "許博為"
    ],
    "plaintiffs": [
      "台北國際商業銀行股份有限公司"
    ],
    "defendants": [
      "丁○○"
    ],
    "prosecutor_office": [

    ],
    "creditors": [

    ],
    "debtors": [

    ],
    "judicial_associate_officer": [

    ]
  },
  "adjudged_at": "2005-08-18",
  "created_at": "2016-02-06 21:30:16",
  "updated_at": "2016-02-06 21:30:16"
}