{
  "identify": "KSD-93-簡-6228-20041224-1",
  "court": {
    "name": "臺灣高雄地方法院",
    "code": "KSD"
  },
  "division": {
    "name": "刑事",
    "code": "M"
  },
  "year": 93,
  "word": "簡",
  "number": "6228",
  "jcheck": "1",
  "reason": "詐欺",
  "content": "臺灣高雄地方法院刑事簡易判決                      九十三年度簡字第六二二八號\n    聲  請  人  臺灣高雄地方法院檢察署檢察官\n    被      告  甲○○\n右列被告因詐欺案件，經檢察官聲請簡易判決處刑（九十三年度偵字第一三五二五號\n），本院判決如左：\n    主  文\n甲○○意圖為自己不法之所有，以詐術使人將本人之物交付，處有期徒刑陸月，如易\n科罰金，以參佰元折算壹日。\n    事實及理由\n一、本件犯罪事實及證據，均引用檢察官聲請簡易判決處刑書之記載（如附件）。\n二、核被告所為，係刑犯刑法第三百三十九條第一項之詐欺取財罪。被告對告訴人一\n    施用詐術行為，使告訴人接續二次交付財物，應僅論以一詐欺取財罪。爰審酌被\n    告為念告訴人與其為舊識之情而佯稱自己任職於財經管理公司，願意代被告投資\n    期貨而詐取財物，其犯罪之動機、目的、手段均不足取，而其犯罪所詐得之財物\n    價值為新台幣十萬元，犯後猶否認犯行，難認有悔悟之心等一切情狀，量處如主\n    文所示之刑，並諭知易科罰金之折算標準。\n三、如不服本判決，應於判決送達之日起十日內，向本院提出上訴狀。\n據上論斷，應依刑事訴訟法第四百四十九條第一項前段、第三項、第四百五十四條第\n二項，刑法第三百三十九條第一項、第四十一條第一項前段，罰金罰鍰提高標準條例\n第一條前段、第二條，逕以簡易判決處刑如主文。\n中      華      民      國    九十三    年     十二     月    二十四    日\n                              臺灣高雄地方法院高雄簡易庭\n                                  法  官  卓立婷\n右正本證明與原本無異。\n                                  書記官  李春慧\n中      華      民      國    九十三    年     十二     月    二十八    日\n附錄本判決論罪科刑法條】\n中華民國刑法第三百三十九條\n意圖為自己或第三人不法之所有，以詐術使人將本人或第三人之物交付者\n，處五年以下有期徒刑、拘役或科或併科一千元以下罰金。\n以前項方法得財產上不法之利益或使第三人得之者，亦同。\n前二項之未遂犯罰之。\n",
  "structure": {
    "main": "甲○○意圖為自己不法之所有，以詐術使人將本人之物交付，處有期徒刑陸月，如易\n科罰金，以參佰元折算壹日。",
    "fact": "一、本件犯罪事實及證據，均引用檢察官聲請簡易判決處刑書之記載（如附件）。\n二、核被告所為，係刑犯刑法第三百三十九條第一項之詐欺取財罪。被告對告訴人一\n    施用詐術行為，使告訴人接續二次交付財物，應僅論以一詐欺取財罪。爰審酌被\n    告為念告訴人與其為舊識之情而佯稱自己任職於財經管理公司，願意代被告投資\n    期貨而詐取財物，其犯罪之動機、目的、手段均不足取，而其犯罪所詐得之財物\n    價值為新台幣十萬元，犯後猶否認犯行，難認有悔悟之心等一切情狀，量處如主\n    文所示之刑，並諭知易科罰金之折算標準。\n三、如不服本判決，應於判決送達之日起十日內，向本院提出上訴狀。\n據上論斷，應依刑事訴訟法第四百四十九條第一項前段、第三項、第四百五十四條第\n二項，刑法第三百三十九條第一項、第四十一條第一項前段，罰金罰鍰提高標準條例\n第一條前段、第二條，逕以簡易判決處刑如主文。",
    "reason": "一、本件犯罪事實及證據，均引用檢察官聲請簡易判決處刑書之記載（如附件）。\n二、核被告所為，係刑犯刑法第三百三十九條第一項之詐欺取財罪。被告對告訴人一\n    施用詐術行為，使告訴人接續二次交付財物，應僅論以一詐欺取財罪。爰審酌被\n    告為念告訴人與其為舊識之情而佯稱自己任職於財經管理公司，願意代被告投資\n    期貨而詐取財物，其犯罪之動機、目的、手段均不足取，而其犯罪所詐得之財物\n    價值為新台幣十萬元，犯後猶否認犯行，難認有悔悟之心等一切情狀，量處如主\n    文所示之刑，並諭知易科罰金之折算標準。\n三、如不服本判決，應於判決送達之日起十日內，向本院提出上訴狀。\n據上論斷，應依刑事訴訟法第四百四十九條第一項前段、第三項、第四百五十四條第\n二項，刑法第三百三十九條第一項、第四十一條第一項前段，罰金罰鍰提高標準條例\n第一條前段、第二條，逕以簡易判決處刑如主文。"
  },
  "search": "臺灣高雄地方法院刑事簡易判決九十三年度簡字第六二二八號聲請人臺灣高雄地方法院檢察署檢察官被告甲○○右列被告因詐欺案件，經檢察官聲請簡易判決處刑（九十三年度偵字第一三五二五號），本院判決如左：主文甲○○意圖為自己不法之所有，以詐術使人將本人之物交付，處有期徒刑陸月，如易科罰金，以參佰元折算壹日。事實及理由一、本件犯罪事實及證據，均引用檢察官聲請簡易判決處刑書之記載（如附件）。二、核被告所為，係刑犯刑法第三百三十九條第一項之詐欺取財罪。被告對告訴人一施用詐術行為，使告訴人接續二次交付財物，應僅論以一詐欺取財罪。爰審酌被告為念告訴人與其為舊識之情而佯稱自己任職於財經管理公司，願意代被告投資期貨而詐取財物，其犯罪之動機、目的、手段均不足取，而其犯罪所詐得之財物價值為新台幣十萬元，犯後猶否認犯行，難認有悔悟之心等一切情狀，量處如主文所示之刑，並諭知易科罰金之折算標準。三、如不服本判決，應於判決送達之日起十日內，向本院提出上訴狀。據上論斷，應依刑事訴訟法第四百四十九條第一項前段、第三項、第四百五十四條第二項，刑法第三百三十九條第一項、第四十一條第一項前段，罰金罰鍰提高標準條例第一條前段、第二條，逕以簡易判決處刑如主文。中華民國九十三年十二月二十四日臺灣高雄地方法院高雄簡易庭法官卓立婷右正本證明與原本無異。書記官李春慧中華民國九十三年十二月二十八日附錄本判決論罪科刑法條】中華民國刑法第三百三十九條意圖為自己或第三人不法之所有，以詐術使人將本人或第三人之物交付者，處五年以下有期徒刑、拘役或科或併科一千元以下罰金。以前項方法得財產上不法之利益或使第三人得之者，亦同。前二項之未遂犯罰之。",
  "characters": {
    "judges": [
      "卓立婷"
    ],
    "prosecutors": [

    ],
    "lawyers": [

    ],
    "clerks": [
      "李春慧"
    ],
    "plaintiffs": [

    ],
    "defendants": [
      "甲○○",
      "右列被告因詐欺案件，經檢察官聲請簡易判決處刑（九十三年度偵字第一三五二五號",
      "），本院判決如左："
    ],
    "prosecutor_office": [
      "臺灣高雄地方法院檢察署檢察官"
    ],
    "creditors": [

    ],
    "debtors": [

    ],
    "judicial_associate_officer": [

    ]
  },
  "adjudged_at": "2004-12-24",
  "created_at": "2016-02-06 06:57:07",
  "updated_at": "2016-02-06 06:57:07"
}