{
  "identify": "KSD-93-訴緝-228-20050908-1",
  "court": {
    "name": "臺灣高雄地方法院",
    "code": "KSD"
  },
  "division": {
    "name": "刑事",
    "code": "M"
  },
  "year": 93,
  "word": "訴緝",
  "number": "228",
  "jcheck": "1",
  "reason": "強盜",
  "content": "臺灣高雄地方法院刑事裁定             93年度訴緝字第228號\n公  訴  人  臺灣高雄地方法院檢察署檢察官\n被      告  乙○○\n義務辯護人  李偉如律師\n上列被告因強盜案件，本院裁定如下：\n    主  文\n乙○○自民國玖拾肆年玖月拾參日起延長羈押貳月。\n    理  由\n一、按停止羈押後有經合法傳因無正當之理由不到場者，得命再\n    執行羈押；再執行羈押之期間，應與停止羈押前已經過之期\n    間合併計算。刑事訴訟法第117 條第1 項第1 款、同條第3\n    項分別定有明文。\n二、被告乙○○因涉犯刑法第330 條之加重強盜罪，有被害人甲\n    ○○於偵查中之指述，罪嫌重大，所犯為最輕本刑5 年以上\n    有期徒刑之罪，且被告經拘提到案，非予羈押，顯難進行審\n    判程序，而依刑事訴訟法第101 條第1 項第3 款之規定，經\n    本院於民國92年10月29日執行羈押；嗣本院於93年1 月12日\n    裁定准予新臺幣20,000元具保停止羈押，並限制其住居於高\n    雄市○○區○○路506 巷3 號之住所，被告即於93年1 月15\n    日具保停止羈押，共計羈押2 月18日；詎本院分別合法通知\n    被告及具保人蘇美鳳應於93年5 月24日及同年6 月28日到庭\n    ，被告及具保人均無正當理由而未到庭，復經拘提無著，而\n    經本院於同年7 月15日發布通緝，被告於93年12月24日始為\n    警緝獲而入監執行他案，並於94年8 月31日期滿執行完畢，\n    而由本院依首揭法條規定，而於94年9 月1 日逕行拘提再執\n    行羈押，併合計停止羈押前之羈押期間。\n二、茲本院以被告之羈押期間，即將屆滿，且涉犯加重強盜罪嫌\n    重大，而所犯係最輕本刑為5 年以上有期徒刑之罪，刑事訴\n    訟法第101 條第1 項第3 款之羈押原因仍然存在，且經通緝\n    到案，有事實足認有逃亡之虞，非予羈押顯難進行審判程序\n    ，仍有繼續羈押之必要，應自94年9 月13 日起再延長羈押2\n    月，爰依刑事訴訟法第108 條第1 項、第2 項、第5 項，裁\n    定如主文。\n中    華    民    國    94    年    9     月    8     日\n                  刑事第十五庭審判長  法  官 唐照明\n                                      法  官 呂憲雄\n                                      法  官 陳筱蓉\n以上正本證明與原本無異。\n如不服本裁定，應於收受送達後5 日內向本院提出抗告狀。\n中    華    民    國    94    年    9     月    8     日\n                                      書記官 梁瑜玲\n",
  "structure": {
    "main": "乙○○自民國玖拾肆年玖月拾參日起延長羈押貳月。",
    "reason": "一、按停止羈押後有經合法傳因無正當之理由不到場者，得命再\n    執行羈押；再執行羈押之期間，應與停止羈押前已經過之期\n    間合併計算。刑事訴訟法第117 條第1 項第1 款、同條第3\n    項分別定有明文。\n二、被告乙○○因涉犯刑法第330 條之加重強盜罪，有被害人甲\n    ○○於偵查中之指述，罪嫌重大，所犯為最輕本刑5 年以上\n    有期徒刑之罪，且被告經拘提到案，非予羈押，顯難進行審\n    判程序，而依刑事訴訟法第101 條第1 項第3 款之規定，經\n    本院於民國92年10月29日執行羈押；嗣本院於93年1 月12日\n    裁定准予新臺幣20,000元具保停止羈押，並限制其住居於高\n    雄市○○區○○路506 巷3 號之住所，被告即於93年1 月15\n    日具保停止羈押，共計羈押2 月18日；詎本院分別合法通知\n    被告及具保人蘇美鳳應於93年5 月24日及同年6 月28日到庭\n    ，被告及具保人均無正當理由而未到庭，復經拘提無著，而\n    經本院於同年7 月15日發布通緝，被告於93年12月24日始為\n    警緝獲而入監執行他案，並於94年8 月31日期滿執行完畢，\n    而由本院依首揭法條規定，而於94年9 月1 日逕行拘提再執\n    行羈押，併合計停止羈押前之羈押期間。\n二、茲本院以被告之羈押期間，即將屆滿，且涉犯加重強盜罪嫌\n    重大，而所犯係最輕本刑為5 年以上有期徒刑之罪，刑事訴\n    訟法第101 條第1 項第3 款之羈押原因仍然存在，且經通緝\n    到案，有事實足認有逃亡之虞，非予羈押顯難進行審判程序\n    ，仍有繼續羈押之必要，應自94年9 月13 日起再延長羈押2\n    月，爰依刑事訴訟法第108 條第1 項、第2 項、第5 項，裁\n    定如主文。"
  },
  "search": "臺灣高雄地方法院刑事裁定93年度訴緝字第228號公訴人臺灣高雄地方法院檢察署檢察官被告乙○○義務辯護人李偉如律師上列被告因強盜案件，本院裁定如下：主文乙○○自民國玖拾肆年玖月拾參日起延長羈押貳月。理由一、按停止羈押後有經合法傳因無正當之理由不到場者，得命再執行羈押；再執行羈押之期間，應與停止羈押前已經過之期間合併計算。刑事訴訟法第117條第1項第1款、同條第3項分別定有明文。二、被告乙○○因涉犯刑法第330條之加重強盜罪，有被害人甲○○於偵查中之指述，罪嫌重大，所犯為最輕本刑5年以上有期徒刑之罪，且被告經拘提到案，非予羈押，顯難進行審判程序，而依刑事訴訟法第101條第1項第3款之規定，經本院於民國92年10月29日執行羈押；嗣本院於93年1月12日裁定准予新臺幣20,000元具保停止羈押，並限制其住居於高雄市○○區○○路506巷3號之住所，被告即於93年1月15日具保停止羈押，共計羈押2月18日；詎本院分別合法通知被告及具保人蘇美鳳應於93年5月24日及同年6月28日到庭，被告及具保人均無正當理由而未到庭，復經拘提無著，而經本院於同年7月15日發布通緝，被告於93年12月24日始為警緝獲而入監執行他案，並於94年8月31日期滿執行完畢，而由本院依首揭法條規定，而於94年9月1日逕行拘提再執行羈押，併合計停止羈押前之羈押期間。二、茲本院以被告之羈押期間，即將屆滿，且涉犯加重強盜罪嫌重大，而所犯係最輕本刑為5年以上有期徒刑之罪，刑事訴訟法第101條第1項第3款之羈押原因仍然存在，且經通緝到案，有事實足認有逃亡之虞，非予羈押顯難進行審判程序，仍有繼續羈押之必要，應自94年9月13日起再延長羈押2月，爰依刑事訴訟法第108條第1項、第2項、第5項，裁定如主文。中華民國94年9月8日刑事第十五庭審判長法官唐照明法官呂憲雄法官陳筱蓉以上正本證明與原本無異。如不服本裁定，應於收受送達後5日內向本院提出抗告狀。中華民國94年9月8日書記官梁瑜玲",
  "characters": {
    "judges": [
      "唐照明",
      "呂憲雄",
      "陳筱蓉"
    ],
    "prosecutors": [

    ],
    "lawyers": [
      "李偉如"
    ],
    "clerks": [
      "梁瑜玲"
    ],
    "plaintiffs": [

    ],
    "defendants": [
      "乙○○",
      "義務辯護人  李偉如律師"
    ],
    "prosecutor_office": [
      "臺灣高雄地方法院檢察署檢察官"
    ],
    "creditors": [

    ],
    "debtors": [

    ],
    "judicial_associate_officer": [

    ]
  },
  "adjudged_at": "2005-09-08",
  "created_at": "2016-02-06 20:01:58",
  "updated_at": "2016-02-06 20:01:58"
}