{
  "identify": "TYD-94-訴-1488-20050909-2",
  "court": {
    "name": "臺灣桃園地方法院",
    "code": "TYD"
  },
  "division": {
    "name": "刑事",
    "code": "M"
  },
  "year": 94,
  "word": "訴",
  "number": "1488",
  "jcheck": "2",
  "reason": "毒品危害防制條例",
  "content": "臺灣桃園地方法院刑事裁定             94年度訴字第1488號\n公  訴  人  台灣桃園地方法院檢察署檢察官\n被      告  甲○○\n上列被告因違反毒品危害防制條例案件，本院裁定如下：\n    主  文\n本院於中華民國94 年8 月22日所為之裁定應予撤銷。\n    理  由\n一、按除被告所犯為死刑、無期徒刑、最輕本刑為3 年以上有期\n    徒刑之罪或高等法院管轄第一審案件以外之罪，被告就被訴\n    事實為有罪之陳述，審判長得告知被告簡式審判程序之旨，\n    並聽取當事人、代理人、辯護人及輔佐人之意見後裁定進行\n    審判程序。法院為前項裁定後認有不得或不宜者，應撤銷原\n    裁定，依通常程序審判之，刑事訴訟法第273 條之1 第1 項\n    、第2 項分別定有。換言之，得以簡式程序進行之案件，以\n    被告判處有罪之案件為限，若應諭知不受理之案件，不得以\n    簡式審判程序處理。\n二、查本件甲○○所犯違反毒品危害防制條例案件，經本院審理\n    後，認其涉犯施用第二級毒品安非他命部分有應為不受理判\n    決之情形，故本件不得以簡式審判程序審理，本院誤裁定進\n    行簡式審判程序，爰依刑事訴訟法第273 條之1 第2 項裁定\n    如主文。\n中    華    民    國    94    年    9     月    9    日\n                  刑事第七庭  審判長法  官  孫惠琳\n                                    法  官  林惠霞\n                                    法  官  劉為丕\n不得抗告。\n                                    書記官  方秀貞\n中    華    民    國    94    年    9     月    12    日\n",
  "structure": {
    "main": "本院於中華民國94 年8 月22日所為之裁定應予撤銷。",
    "reason": "一、按除被告所犯為死刑、無期徒刑、最輕本刑為3 年以上有期\n    徒刑之罪或高等法院管轄第一審案件以外之罪，被告就被訴\n    事實為有罪之陳述，審判長得告知被告簡式審判程序之旨，\n    並聽取當事人、代理人、辯護人及輔佐人之意見後裁定進行\n    審判程序。法院為前項裁定後認有不得或不宜者，應撤銷原\n    裁定，依通常程序審判之，刑事訴訟法第273 條之1 第1 項\n    、第2 項分別定有。換言之，得以簡式程序進行之案件，以\n    被告判處有罪之案件為限，若應諭知不受理之案件，不得以\n    簡式審判程序處理。\n二、查本件甲○○所犯違反毒品危害防制條例案件，經本院審理\n    後，認其涉犯施用第二級毒品安非他命部分有應為不受理判\n    決之情形，故本件不得以簡式審判程序審理，本院誤裁定進\n    行簡式審判程序，爰依刑事訴訟法第273 條之1 第2 項裁定\n    如主文。"
  },
  "search": "臺灣桃園地方法院刑事裁定94年度訴字第1488號公訴人台灣桃園地方法院檢察署檢察官被告甲○○上列被告因違反毒品危害防制條例案件，本院裁定如下：主文本院於中華民國94年8月22日所為之裁定應予撤銷。理由一、按除被告所犯為死刑、無期徒刑、最輕本刑為3年以上有期徒刑之罪或高等法院管轄第一審案件以外之罪，被告就被訴事實為有罪之陳述，審判長得告知被告簡式審判程序之旨，並聽取當事人、代理人、辯護人及輔佐人之意見後裁定進行審判程序。法院為前項裁定後認有不得或不宜者，應撤銷原裁定，依通常程序審判之，刑事訴訟法第273條之1第1項、第2項分別定有。換言之，得以簡式程序進行之案件，以被告判處有罪之案件為限，若應諭知不受理之案件，不得以簡式審判程序處理。二、查本件甲○○所犯違反毒品危害防制條例案件，經本院審理後，認其涉犯施用第二級毒品安非他命部分有應為不受理判決之情形，故本件不得以簡式審判程序審理，本院誤裁定進行簡式審判程序，爰依刑事訴訟法第273條之1第2項裁定如主文。中華民國94年9月9日刑事第七庭審判長法官孫惠琳法官林惠霞法官劉為丕不得抗告。書記官方秀貞中華民國94年9月12日",
  "characters": {
    "judges": [
      "孫惠琳",
      "林惠霞",
      "劉為丕"
    ],
    "prosecutors": [

    ],
    "lawyers": [

    ],
    "clerks": [
      "方秀貞"
    ],
    "plaintiffs": [

    ],
    "defendants": [
      "甲○○"
    ],
    "prosecutor_office": [
      "台灣桃園地方法院檢察署檢察官"
    ],
    "creditors": [

    ],
    "debtors": [

    ],
    "judicial_associate_officer": [

    ]
  },
  "adjudged_at": "2005-09-09",
  "created_at": "2016-02-06 19:57:15",
  "updated_at": "2016-02-06 19:57:15"
}