{
  "identify": "TPB-94-簡-547-20051110-1",
  "court": {
    "name": "臺北高等行政法院",
    "code": "TPB"
  },
  "division": {
    "name": "行政",
    "code": "A"
  },
  "year": 94,
  "word": "簡",
  "number": "547",
  "jcheck": "1",
  "reason": "就業服務法",
  "content": "臺北高等行政法院裁定\n                                     94年度簡字第00547號\n原      告  甲○○\n被      告  台北縣政府\n代  表  人  乙○○代理縣長）.\n上列當事人間因就業服務法事件，原告不服行政院勞工委員會中\n華民國94年4月27日勞訴字第0940010953號訴願決定，提起行政\n訴訟，本院裁定如下：\n    主  文\n原告之訴駁回。\n訴訟費用由原告負擔。\n    理  由\n一、按訴願之提起，應自行政處分達到或公告期滿之次日起30日\n    內為之。訴願事件，提起訴願逾法定期間或未於訴願法第57\n    條所定期間內補送訴願書者，應為不受理之決定，分別為同\n    法第14條第1項及第77條第2款所明定。\n二、本件原告因就業服務法事件，係於民國（下同）93年12月10\n    日收受被告93年12月7日北府勞動字第0930812904號之處分\n    書，此有送達證書影本附訴願卷可稽。計其提起訴願之期間\n    ，應自93年12月11日起算，因原告住居於台北縣，扣除在途\n    期間2日，至94年1月11日即已屆滿。惟原告遲至94年2月5日\n    始經由被告向行政院勞工委員會提起訴願，此有被告所屬勞\n    工局收文章蓋於訴願書可按，訴願決定以其訴願已逾法定不\n    變期間，不予受理，自無不合。原告復對之提起行政訴訟，\n    顯非合法，應予駁回。\n三、依行政訴訟法第236條、第107條第1項第10款、第104條、民\n    事訴訟法第95條、第78條，裁定如主文。\n中    華    民    國    94    年    11   月     10    日\n                            第 五 庭  法  官  張瓊文\n上為正本係照原本作成。\n本件以訴訟事件所涉及之法律見解具有原則性者為限，始得於本\n裁定送達後10日內向本院提出抗告狀（須按他造人數附繕本），\n並經最高行政法院許可後方得抗告。\n中    華    民    國    94    年    11   月     10    日\n                                      書記官  簡信滇\n",
  "structure": {
    "main": "原告之訴駁回。\n訴訟費用由原告負擔。",
    "reason": "一、按訴願之提起，應自行政處分達到或公告期滿之次日起30日\n    內為之。訴願事件，提起訴願逾法定期間或未於訴願法第57\n    條所定期間內補送訴願書者，應為不受理之決定，分別為同\n    法第14條第1項及第77條第2款所明定。\n二、本件原告因就業服務法事件，係於民國（下同）93年12月10\n    日收受被告93年12月7日北府勞動字第0930812904號之處分\n    書，此有送達證書影本附訴願卷可稽。計其提起訴願之期間\n    ，應自93年12月11日起算，因原告住居於台北縣，扣除在途\n    期間2日，至94年1月11日即已屆滿。惟原告遲至94年2月5日\n    始經由被告向行政院勞工委員會提起訴願，此有被告所屬勞\n    工局收文章蓋於訴願書可按，訴願決定以其訴願已逾法定不\n    變期間，不予受理，自無不合。原告復對之提起行政訴訟，\n    顯非合法，應予駁回。\n三、依行政訴訟法第236條、第107條第1項第10款、第104條、民\n    事訴訟法第95條、第78條，裁定如主文。"
  },
  "search": "臺北高等行政法院裁定94年度簡字第00547號原告甲○○被告台北縣政府代表人乙○○代理縣長）.上列當事人間因就業服務法事件，原告不服行政院勞工委員會中華民國94年4月27日勞訴字第0940010953號訴願決定，提起行政訴訟，本院裁定如下：主文原告之訴駁回。訴訟費用由原告負擔。理由一、按訴願之提起，應自行政處分達到或公告期滿之次日起30日內為之。訴願事件，提起訴願逾法定期間或未於訴願法第57條所定期間內補送訴願書者，應為不受理之決定，分別為同法第14條第1項及第77條第2款所明定。二、本件原告因就業服務法事件，係於民國（下同）93年12月10日收受被告93年12月7日北府勞動字第0930812904號之處分書，此有送達證書影本附訴願卷可稽。計其提起訴願之期間，應自93年12月11日起算，因原告住居於台北縣，扣除在途期間2日，至94年1月11日即已屆滿。惟原告遲至94年2月5日始經由被告向行政院勞工委員會提起訴願，此有被告所屬勞工局收文章蓋於訴願書可按，訴願決定以其訴願已逾法定不變期間，不予受理，自無不合。原告復對之提起行政訴訟，顯非合法，應予駁回。三、依行政訴訟法第236條、第107條第1項第10款、第104條、民事訴訟法第95條、第78條，裁定如主文。中華民國94年11月10日第五庭法官張瓊文上為正本係照原本作成。本件以訴訟事件所涉及之法律見解具有原則性者為限，始得於本裁定送達後10日內向本院提出抗告狀（須按他造人數附繕本），並經最高行政法院許可後方得抗告。中華民國94年11月10日書記官簡信滇",
  "characters": {
    "judges": [
      "張瓊文"
    ],
    "prosecutors": [

    ],
    "lawyers": [

    ],
    "clerks": [
      "簡信滇"
    ],
    "plaintiffs": [
      "甲○○"
    ],
    "defendants": [
      "台北縣政府",
      "代  表  人  乙○○代理縣長）."
    ],
    "prosecutor_office": [

    ],
    "creditors": [

    ],
    "debtors": [

    ],
    "judicial_associate_officer": [

    ]
  },
  "adjudged_at": "2005-11-10",
  "created_at": "2016-02-06 23:50:57",
  "updated_at": "2016-02-06 23:50:57"
}