{
  "identify": "TPH-92-上-1207-20051109-4",
  "court": {
    "name": "臺灣高等法院",
    "code": "TPH"
  },
  "division": {
    "name": "民事",
    "code": "V"
  },
  "year": 92,
  "word": "上",
  "number": "1207",
  "jcheck": "4",
  "reason": "請求辦理所有權移轉登記",
  "content": "臺灣高等法院民事裁定                  92年度上字第1207號\n    上  訴  人  丁○○\n                丙○○\n    共      同\n    訴訟代理人  溫瑞鳳律師\n    被  上訴人  甲○○○\n    追 加 被告  庚○○○\n                辛○○\n                己○○\n                戊○○\n                乙○○\n上列當事人間請求辦理所有權移轉登記事件，本院於民國94年\n10月19日所為之裁定，其原本及正本應更正如下：\n    主  文\n原裁定當事人欄內關於追加被告「鄭素枝」之記載應更正為「乙\n○○」。\n    理  由\n一按判決如有誤寫、誤算或其他類此之顯然錯誤者，法院得隨時\n  或依聲請以裁定更正之，其正本與原本不符者亦同，民事訴訟\n  法第232條第1項定有明文。\n二查本院前開裁定將追加被告乙○○誤載為鄭素枝，顯係誤寫，\n  應予更正。\n三依首開規定裁定如主文。\n中    華    民    國    94    年    11    月    9     日\n                  民事第十庭審判長法  官  黃熙嫣\n                                  法  官  呂太郎\n                                  法  官  楊力進\n正本係照原本作成。\n如不服本裁定，應於收受送達後10日內向本院提出抗告狀，並應\n繳納抗告費新台幣１千元。\n中    華    民    國    94    年    11    月    10    日\n                                  書記官  劉家聲\n",
  "structure": {
    "main": "原裁定當事人欄內關於追加被告「鄭素枝」之記載應更正為「乙\n○○」。",
    "reason": "一按判決如有誤寫、誤算或其他類此之顯然錯誤者，法院得隨時\n  或依聲請以裁定更正之，其正本與原本不符者亦同，民事訴訟\n  法第232條第1項定有明文。\n二查本院前開裁定將追加被告乙○○誤載為鄭素枝，顯係誤寫，\n  應予更正。\n三依首開規定裁定如主文。"
  },
  "search": "臺灣高等法院民事裁定92年度上字第1207號上訴人丁○○丙○○共同訴訟代理人溫瑞鳳律師被上訴人甲○○○追加被告庚○○○辛○○己○○戊○○乙○○上列當事人間請求辦理所有權移轉登記事件，本院於民國94年10月19日所為之裁定，其原本及正本應更正如下：主文原裁定當事人欄內關於追加被告「鄭素枝」之記載應更正為「乙○○」。理由一按判決如有誤寫、誤算或其他類此之顯然錯誤者，法院得隨時或依聲請以裁定更正之，其正本與原本不符者亦同，民事訴訟法第232條第1項定有明文。二查本院前開裁定將追加被告乙○○誤載為鄭素枝，顯係誤寫，應予更正。三依首開規定裁定如主文。中華民國94年11月9日民事第十庭審判長法官黃熙嫣法官呂太郎法官楊力進正本係照原本作成。如不服本裁定，應於收受送達後10日內向本院提出抗告狀，並應繳納抗告費新台幣１千元。中華民國94年11月10日書記官劉家聲",
  "characters": {
    "judges": [
      "黃熙嫣",
      "呂太郎",
      "楊力進"
    ],
    "prosecutors": [

    ],
    "lawyers": [
      "溫瑞鳳"
    ],
    "clerks": [
      "劉家聲"
    ],
    "plaintiffs": [

    ],
    "defendants": [

    ],
    "prosecutor_office": [

    ],
    "creditors": [

    ],
    "debtors": [

    ],
    "judicial_associate_officer": [

    ]
  },
  "adjudged_at": "2005-11-09",
  "created_at": "2016-02-06 23:48:37",
  "updated_at": "2016-02-06 23:48:37"
}