{
  "identify": "KLD-94-基簡-150-20050407-1",
  "court": {
    "name": "臺灣基隆地方法院",
    "code": "KLD"
  },
  "division": {
    "name": "刑事",
    "code": "M"
  },
  "year": 94,
  "word": "基簡",
  "number": "150",
  "jcheck": "1",
  "reason": "違反動產擔保交易法",
  "content": "臺灣基隆地方法院刑事簡易判決         94年度基簡字第150號\n聲  請  人  臺灣基隆地方法院檢察署檢察官\n被      告  甲○○  男  41歲.\n上列被告因違反動產擔保交易法案件，經檢察官聲請逕以簡易判\n決處刑（簡易判決處刑書聲請案號：九十四年度偵字第八０號）\n，本院判決如下：\n        主  文\n甲○○動產擔保交易之債務人，意圖不法之利益，將標的物遷移\n，致生損害於債權人，處有期徒刑參月，如易科罰金以參佰元折\n算壹日。\n        事實及理由\n一、本件犯罪之事實、證據及應適用之法條，均引用附件之聲請\n    簡易判決處刑書之記載。另補充及更正如下：(一)、被告係向\n    林錦如買受九十年十月卅一日發照（落地照）之車號三Ｎ─\n    ０二六二號中古自用小客車，該車並非新車，被告與林錦如\n    並於九十一年十二月卅一日向基隆監理站辦理過戶於被告名\n    下之手續。(二)、被告雖偵訊時辯稱其未向遠東商業銀行貸款\n    云云，然比對卷附貸款暨動產抵押契約書、動產擔保交易動\n    產抵押設定登記申請書上「甲○○」之簽名確與被告於九十\n    三年十一月十六日在偵訊筆錄上所簽姓名筆跡特性相符，其\n    於偵訊時亦自承是其簽名的，其猶否認有向遠東商業銀行貸\n    款，並稱不知簽約內容云云，均與事實不符。況被告又自承\n    前開自用小客車是其友人邱智勤以其名義購買的，因邱智勤\n    信用破產，才以其名義購買，該車尚在其之名下等語，更可\n    見其明知本件貸款暨動產抵押契約書之內容，猶出名為其友\n    人邱智勤出面貸款以購買前開自用小客車。(三)、被告又辯稱\n    本件債權由遠東商業銀行讓與告訴人匯豐汽車股份有限公司\n    並沒有通知伊云云，然本件所涉動產擔保交易法第三十八條\n    之犯罪係公訴罪，與民法上債權讓與之通知無涉，僅在匯豐\n    汽車股份有限公司於本案之地位係告訴人或告發人有所不同\n    而已；再者，民法第二百九十七條債權讓與之通知，不過使\n    債務人知悉現在債權人為何人，免於清償時發生對象錯誤，\n    而有損權益，故受讓人對於債務人主張受讓事實行使債權時\n    ，既足使債務人知有債權讓與之事實，即應認為兼有通知之\n    效力，此在最高法院二十二年上字第一一六二號、三十九年\n    台上字第四四八號判例皆著有明文，因之，檢察官於九十三\n    年十一月十六日傳喚告訴代理人林鯤進並提當時尚在服刑之\n    被告同時開庭，並使告訴代理人當庭陳述其告何人何事之時\n    ，即已係兼有債權讓與通知之性質，匯豐汽車股份有限公司\n    遲至此時即已具有適格之權債人身分（至卷附由匯豐汽車股\n    份有限公司發予被告之存證信函，因將被告之地址誤寫為基\n    隆市○○路五三二號，該存證信函尚不能發生債權通知之效\n    力）。因之，被告辯稱未受債權讓與之通知云云，亦未可採\n    。(四)、爰審酌被告尚欠債權人即告訴人匯豐汽車股份有限公\n    司之債務額、行為手段、行為產生之危害、出獄後不思與債\n    權人和解、坐令債權人之損失擴大等一切情狀，量處如主文\n    所示之刑，並諭知易科罰金之折算標準。\n二、依刑事訴訟法第四百四十九條第一項前段、第四百五十四條\n    第二項，動產擔保交易法第三十八條，刑法第十一條前段、\n    第四十一條第一項前段，罰金罰鍰提高標準條例第一條前段\n    、第二條，逕以簡易判決處刑如主文。\n三、如不服本判決，應於判決送達後十日內，向本院提出上訴書\n    狀，上訴於本院合議庭。\n中    華    民    國    94    年    4     月    7     日\n                  基隆簡易庭法    官  曾雨明\n以上正本證明與原本無異。\n如不服本判決，應於判決送達後10日內，向本院提出上訴書狀，\n上訴於本院合議庭。\n中    華    民    國    94    年    4     月    11    日\n                            書 記 官  王靜敏\n附錄論罪法條：\n動產擔保交易法第38條：\n動產擔保交易之債務人，意圖不法之利益，將標的物遷移、出賣\n、出質、移轉、抵押或為其他處分，致生損害於債權人者，處3\n年以下有期徒刑、拘役或科或併科6000元以下之罰金。\n附件：\n臺灣基隆地方法院檢察署檢察官聲請簡易判決處刑書\n                                        94年度偵字第80號\n  被    告  甲○○  男  41歲（民國○○年○○月○○日生）\n                    籍設基隆市安樂區○○○街6 巷10之4號\n                    國民身分證統一編號：Ｚ000000000號\n上列被告因違反動產擔保交易法案件，已經偵查終結，認為宜聲\n請以簡易判決處刑，茲將犯罪事實及證據並所犯法條分敘如下：\n一、犯罪事實：甲○○於民國91年12月16日，以動產擔保交易動\n    產抵押方式，將其新購之3N-0262 號小客車設定動產抵押，\n    向遠東國際商業銀行貸款33萬元，為動產擔保交易之債務人\n    。約定分36期償還貸款，每月一期，每期付款11286 元，標\n    的物存放地點為基隆市○○○街6 巷10之4 號甲○○戶籍地\n    ，債務人不得任意遷移或為其他處分。詎甲○○在取得標的\n    物後，即將之交予其友人邱智勤使用，去向不明，致債權人\n    追索無著受有損害。案經匯豐汽車股份有限公司告訴偵辦。\n二、證據：被告之供述、告訴代理人之指述、貸款暨動產抵押契\n    約書、設定登記申請書、存證信函。\n三、法條：動產擔保交易法第38條之罪嫌。\n四、依刑事訴訟法第451 條第1 項聲請逕以簡易判決處刑。\n    此致\n臺灣基隆地方法院基隆簡易庭\n中    華    民    國    94    年    2     月    27    日\n                               檢察官  張  長  樹\n本件正本證明與原本無異\n中    華    民    國    94    年    3     月    2     日\n                               書記官  葉  美  慧\n附錄所犯法條：\n動產擔保交易法第38條\n     動產擔保交易之債務人，意圖不法之利益，將標的物遷移、\n     出賣、出質、移轉、抵押或為其他處分，致生損害於債權人\n     者，處3 年以下有期徒刑、拘役或科或併科6000元以下之罰\n     金。\n附記事項：本件係依刑事訴訟法簡易程序辦理，法院簡易庭得不\n傳喚被告、輔佐人、告訴人、告發人等出庭即以簡易判決處刑；\n被告、被害人、告訴人等對告訴乃論案件如已達成民事和解而要\n撤回告訴或對非告訴乃論案件認有受傳喚到庭陳述意見之必要時\n，請即另以書狀向簡易法庭陳述或請求傳訊。\n",
  "structure": {
    "main": "甲○○動產擔保交易之債務人，意圖不法之利益，將標的物遷移\n，致生損害於債權人，處有期徒刑參月，如易科罰金以參佰元折\n算壹日。",
    "fact": "一、本件犯罪之事實、證據及應適用之法條，均引用附件之聲請\n    簡易判決處刑書之記載。另補充及更正如下：(一)、被告係向\n    林錦如買受九十年十月卅一日發照（落地照）之車號三Ｎ─\n    ０二六二號中古自用小客車，該車並非新車，被告與林錦如\n    並於九十一年十二月卅一日向基隆監理站辦理過戶於被告名\n    下之手續。(二)、被告雖偵訊時辯稱其未向遠東商業銀行貸款\n    云云，然比對卷附貸款暨動產抵押契約書、動產擔保交易動\n    產抵押設定登記申請書上「甲○○」之簽名確與被告於九十\n    三年十一月十六日在偵訊筆錄上所簽姓名筆跡特性相符，其\n    於偵訊時亦自承是其簽名的，其猶否認有向遠東商業銀行貸\n    款，並稱不知簽約內容云云，均與事實不符。況被告又自承\n    前開自用小客車是其友人邱智勤以其名義購買的，因邱智勤\n    信用破產，才以其名義購買，該車尚在其之名下等語，更可\n    見其明知本件貸款暨動產抵押契約書之內容，猶出名為其友\n    人邱智勤出面貸款以購買前開自用小客車。(三)、被告又辯稱\n    本件債權由遠東商業銀行讓與告訴人匯豐汽車股份有限公司\n    並沒有通知伊云云，然本件所涉動產擔保交易法第三十八條\n    之犯罪係公訴罪，與民法上債權讓與之通知無涉，僅在匯豐\n    汽車股份有限公司於本案之地位係告訴人或告發人有所不同\n    而已；再者，民法第二百九十七條債權讓與之通知，不過使\n    債務人知悉現在債權人為何人，免於清償時發生對象錯誤，\n    而有損權益，故受讓人對於債務人主張受讓事實行使債權時\n    ，既足使債務人知有債權讓與之事實，即應認為兼有通知之\n    效力，此在最高法院二十二年上字第一一六二號、三十九年\n    台上字第四四八號判例皆著有明文，因之，檢察官於九十三\n    年十一月十六日傳喚告訴代理人林鯤進並提當時尚在服刑之\n    被告同時開庭，並使告訴代理人當庭陳述其告何人何事之時\n    ，即已係兼有債權讓與通知之性質，匯豐汽車股份有限公司\n    遲至此時即已具有適格之權債人身分（至卷附由匯豐汽車股\n    份有限公司發予被告之存證信函，因將被告之地址誤寫為基\n    隆市○○路五三二號，該存證信函尚不能發生債權通知之效\n    力）。因之，被告辯稱未受債權讓與之通知云云，亦未可採\n    。(四)、爰審酌被告尚欠債權人即告訴人匯豐汽車股份有限公\n    司之債務額、行為手段、行為產生之危害、出獄後不思與債\n    權人和解、坐令債權人之損失擴大等一切情狀，量處如主文\n    所示之刑，並諭知易科罰金之折算標準。\n二、依刑事訴訟法第四百四十九條第一項前段、第四百五十四條\n    第二項，動產擔保交易法第三十八條，刑法第十一條前段、\n    第四十一條第一項前段，罰金罰鍰提高標準條例第一條前段\n    、第二條，逕以簡易判決處刑如主文。\n三、如不服本判決，應於判決送達後十日內，向本院提出上訴書\n    狀，上訴於本院合議庭。",
    "reason": "一、本件犯罪之事實、證據及應適用之法條，均引用附件之聲請\n    簡易判決處刑書之記載。另補充及更正如下：(一)、被告係向\n    林錦如買受九十年十月卅一日發照（落地照）之車號三Ｎ─\n    ０二六二號中古自用小客車，該車並非新車，被告與林錦如\n    並於九十一年十二月卅一日向基隆監理站辦理過戶於被告名\n    下之手續。(二)、被告雖偵訊時辯稱其未向遠東商業銀行貸款\n    云云，然比對卷附貸款暨動產抵押契約書、動產擔保交易動\n    產抵押設定登記申請書上「甲○○」之簽名確與被告於九十\n    三年十一月十六日在偵訊筆錄上所簽姓名筆跡特性相符，其\n    於偵訊時亦自承是其簽名的，其猶否認有向遠東商業銀行貸\n    款，並稱不知簽約內容云云，均與事實不符。況被告又自承\n    前開自用小客車是其友人邱智勤以其名義購買的，因邱智勤\n    信用破產，才以其名義購買，該車尚在其之名下等語，更可\n    見其明知本件貸款暨動產抵押契約書之內容，猶出名為其友\n    人邱智勤出面貸款以購買前開自用小客車。(三)、被告又辯稱\n    本件債權由遠東商業銀行讓與告訴人匯豐汽車股份有限公司\n    並沒有通知伊云云，然本件所涉動產擔保交易法第三十八條\n    之犯罪係公訴罪，與民法上債權讓與之通知無涉，僅在匯豐\n    汽車股份有限公司於本案之地位係告訴人或告發人有所不同\n    而已；再者，民法第二百九十七條債權讓與之通知，不過使\n    債務人知悉現在債權人為何人，免於清償時發生對象錯誤，\n    而有損權益，故受讓人對於債務人主張受讓事實行使債權時\n    ，既足使債務人知有債權讓與之事實，即應認為兼有通知之\n    效力，此在最高法院二十二年上字第一一六二號、三十九年\n    台上字第四四八號判例皆著有明文，因之，檢察官於九十三\n    年十一月十六日傳喚告訴代理人林鯤進並提當時尚在服刑之\n    被告同時開庭，並使告訴代理人當庭陳述其告何人何事之時\n    ，即已係兼有債權讓與通知之性質，匯豐汽車股份有限公司\n    遲至此時即已具有適格之權債人身分（至卷附由匯豐汽車股\n    份有限公司發予被告之存證信函，因將被告之地址誤寫為基\n    隆市○○路五三二號，該存證信函尚不能發生債權通知之效\n    力）。因之，被告辯稱未受債權讓與之通知云云，亦未可採\n    。(四)、爰審酌被告尚欠債權人即告訴人匯豐汽車股份有限公\n    司之債務額、行為手段、行為產生之危害、出獄後不思與債\n    權人和解、坐令債權人之損失擴大等一切情狀，量處如主文\n    所示之刑，並諭知易科罰金之折算標準。\n二、依刑事訴訟法第四百四十九條第一項前段、第四百五十四條\n    第二項，動產擔保交易法第三十八條，刑法第十一條前段、\n    第四十一條第一項前段，罰金罰鍰提高標準條例第一條前段\n    、第二條，逕以簡易判決處刑如主文。\n三、如不服本判決，應於判決送達後十日內，向本院提出上訴書\n    狀，上訴於本院合議庭。"
  },
  "search": "臺灣基隆地方法院刑事簡易判決94年度基簡字第150號聲請人臺灣基隆地方法院檢察署檢察官被告甲○○男41歲.上列被告因違反動產擔保交易法案件，經檢察官聲請逕以簡易判決處刑（簡易判決處刑書聲請案號：九十四年度偵字第八０號），本院判決如下：主文甲○○動產擔保交易之債務人，意圖不法之利益，將標的物遷移，致生損害於債權人，處有期徒刑參月，如易科罰金以參佰元折算壹日。事實及理由一、本件犯罪之事實、證據及應適用之法條，均引用附件之聲請簡易判決處刑書之記載。另補充及更正如下：(一)、被告係向林錦如買受九十年十月卅一日發照（落地照）之車號三Ｎ─０二六二號中古自用小客車，該車並非新車，被告與林錦如並於九十一年十二月卅一日向基隆監理站辦理過戶於被告名下之手續。(二)、被告雖偵訊時辯稱其未向遠東商業銀行貸款云云，然比對卷附貸款暨動產抵押契約書、動產擔保交易動產抵押設定登記申請書上「甲○○」之簽名確與被告於九十三年十一月十六日在偵訊筆錄上所簽姓名筆跡特性相符，其於偵訊時亦自承是其簽名的，其猶否認有向遠東商業銀行貸款，並稱不知簽約內容云云，均與事實不符。況被告又自承前開自用小客車是其友人邱智勤以其名義購買的，因邱智勤信用破產，才以其名義購買，該車尚在其之名下等語，更可見其明知本件貸款暨動產抵押契約書之內容，猶出名為其友人邱智勤出面貸款以購買前開自用小客車。(三)、被告又辯稱本件債權由遠東商業銀行讓與告訴人匯豐汽車股份有限公司並沒有通知伊云云，然本件所涉動產擔保交易法第三十八條之犯罪係公訴罪，與民法上債權讓與之通知無涉，僅在匯豐汽車股份有限公司於本案之地位係告訴人或告發人有所不同而已；再者，民法第二百九十七條債權讓與之通知，不過使債務人知悉現在債權人為何人，免於清償時發生對象錯誤，而有損權益，故受讓人對於債務人主張受讓事實行使債權時，既足使債務人知有債權讓與之事實，即應認為兼有通知之效力，此在最高法院二十二年上字第一一六二號、三十九年台上字第四四八號判例皆著有明文，因之，檢察官於九十三年十一月十六日傳喚告訴代理人林鯤進並提當時尚在服刑之被告同時開庭，並使告訴代理人當庭陳述其告何人何事之時，即已係兼有債權讓與通知之性質，匯豐汽車股份有限公司遲至此時即已具有適格之權債人身分（至卷附由匯豐汽車股份有限公司發予被告之存證信函，因將被告之地址誤寫為基隆市○○路五三二號，該存證信函尚不能發生債權通知之效力）。因之，被告辯稱未受債權讓與之通知云云，亦未可採。(四)、爰審酌被告尚欠債權人即告訴人匯豐汽車股份有限公司之債務額、行為手段、行為產生之危害、出獄後不思與債權人和解、坐令債權人之損失擴大等一切情狀，量處如主文所示之刑，並諭知易科罰金之折算標準。二、依刑事訴訟法第四百四十九條第一項前段、第四百五十四條第二項，動產擔保交易法第三十八條，刑法第十一條前段、第四十一條第一項前段，罰金罰鍰提高標準條例第一條前段、第二條，逕以簡易判決處刑如主文。三、如不服本判決，應於判決送達後十日內，向本院提出上訴書狀，上訴於本院合議庭。中華民國94年4月7日基隆簡易庭法官曾雨明以上正本證明與原本無異。如不服本判決，應於判決送達後10日內，向本院提出上訴書狀，上訴於本院合議庭。中華民國94年4月11日書記官王靜敏附錄論罪法條：動產擔保交易法第38條：動產擔保交易之債務人，意圖不法之利益，將標的物遷移、出賣、出質、移轉、抵押或為其他處分，致生損害於債權人者，處3年以下有期徒刑、拘役或科或併科6000元以下之罰金。附件：臺灣基隆地方法院檢察署檢察官聲請簡易判決處刑書94年度偵字第80號被告甲○○男41歲（民國○○年○○月○○日生）籍設基隆市安樂區○○○街6巷10之4號國民身分證統一編號：Ｚ000000000號上列被告因違反動產擔保交易法案件，已經偵查終結，認為宜聲請以簡易判決處刑，茲將犯罪事實及證據並所犯法條分敘如下：一、犯罪事實：甲○○於民國91年12月16日，以動產擔保交易動產抵押方式，將其新購之3N-0262號小客車設定動產抵押，向遠東國際商業銀行貸款33萬元，為動產擔保交易之債務人。約定分36期償還貸款，每月一期，每期付款11286元，標的物存放地點為基隆市○○○街6巷10之4號甲○○戶籍地，債務人不得任意遷移或為其他處分。詎甲○○在取得標的物後，即將之交予其友人邱智勤使用，去向不明，致債權人追索無著受有損害。案經匯豐汽車股份有限公司告訴偵辦。二、證據：被告之供述、告訴代理人之指述、貸款暨動產抵押契約書、設定登記申請書、存證信函。三、法條：動產擔保交易法第38條之罪嫌。四、依刑事訴訟法第451條第1項聲請逕以簡易判決處刑。此致臺灣基隆地方法院基隆簡易庭中華民國94年2月27日檢察官張長樹本件正本證明與原本無異中華民國94年3月2日書記官葉美慧附錄所犯法條：動產擔保交易法第38條動產擔保交易之債務人，意圖不法之利益，將標的物遷移、出賣、出質、移轉、抵押或為其他處分，致生損害於債權人者，處3年以下有期徒刑、拘役或科或併科6000元以下之罰金。附記事項：本件係依刑事訴訟法簡易程序辦理，法院簡易庭得不傳喚被告、輔佐人、告訴人、告發人等出庭即以簡易判決處刑；被告、被害人、告訴人等對告訴乃論案件如已達成民事和解而要撤回告訴或對非告訴乃論案件認有受傳喚到庭陳述意見之必要時，請即另以書狀向簡易法庭陳述或請求傳訊。",
  "characters": {
    "judges": [
      "曾雨明"
    ],
    "prosecutors": [

    ],
    "lawyers": [

    ],
    "clerks": [
      "葉美慧"
    ],
    "plaintiffs": [

    ],
    "defendants": [
      "甲○○  男  41歲.",
      "甲○○  男  41歲（民國○○年○○月○○日生）"
    ],
    "prosecutor_office": [
      "臺灣基隆地方法院檢察署檢察官"
    ],
    "creditors": [

    ],
    "debtors": [

    ],
    "judicial_associate_officer": [

    ]
  },
  "adjudged_at": "2005-04-07",
  "created_at": "2016-02-06 18:56:27",
  "updated_at": "2016-02-06 18:56:27"
}