{
  "identify": "TPH-94-上訴-227-20050408-1",
  "court": {
    "name": "臺灣高等法院",
    "code": "TPH"
  },
  "division": {
    "name": "刑事",
    "code": "M"
  },
  "year": 94,
  "word": "上訴",
  "number": "227",
  "jcheck": "1",
  "reason": "護照條例等",
  "content": "臺灣高等法院刑事判決                 94年度上訴字第227號\n上  訴  人  臺灣桃園地方法院檢察署檢察官\n上  訴  人\n即  被  告  甲○○\n選任辯護人  洪榮彬律師\n            陳麗玲律師\n上  訴  人\n即  被  告  丁○○\n            丙○○\n            乙○○\n被      告  己○○\n            戊○○\n上列上訴人因被告違反\n91年度訴字第686 號，中華民國93年4月15日及93年5月18日第一\n審判決（起訴案號：臺灣桃園地方法院檢察署89年度偵字第1775\n0號、90年度偵字第2512號、第3840號、第8840 號；併辦案號：\n臺灣嘉義地方法院檢察署91年度偵字第3779號、第6096號），提\n起上訴，本院判決如下：\n    主  文\n原判決關於甲○○、丁○○、丙○○、乙○○及戊○○部分撤銷\n。\n甲○○共同連續將\n刑陸月，併科罰金新臺幣捌萬元，有期徒刑如易科罰金以佰元\n折算壹日，罰金如易服勞役，以銀元佰元即新臺幣玖佰元折算\n壹日。\n丁○○共同連續將\n有期徒刑陸月，併科罰金新臺幣伍萬元，有期徒刑如易科罰金以\n佰元折算壹日，罰金如易服勞役，以銀元佰元即新臺幣玖佰\n元折算壹日。\n丙○○共同連續將\n刑伍月，併科罰金新臺幣萬元，有期徒刑如易科罰金以佰元\n折算壹日，罰金如易服勞役，以銀元佰元即新臺幣玖佰元折算\n壹日。\n乙○○共同將\n月，如易科罰金，以佰元折算壹日。\n戊○○共同將\n月，如易科罰金，以佰元折算壹日。\n其他上訴駁回。\n    事  實\n一、丁○○前有麻醉藥品管理條例等前科，其於民國（下同）八\n    十七年間所犯之竊盜案件，經臺灣高等法院台南高分院判處\n    有期徒刑三月確定，於八十八年四月十九日入監服刑，而於\n    八十八年七月十八日執行完畢。\n二、甲○○與不詳年籍名為「林永隆」之成年男子，明知\n    表彰特定人身分之證明文件，不得任意買賣，收購\n    意圖供他人冒名行使，竟為貪圖不法利益，共同基於將\n    交付他人，以供他人冒名使用之概括犯意聯絡，由名為「林\n    永隆」者囑由甲○○在臺負責收購他人之\n    。甲○○旋自八十九年二月間起以每本新台幣（下同）二萬\n    元，收購我國國民\n    有犯意聯絡之丁○○、丙○○，並告知願以每本二萬元代價\n    收購我國國民\n    人即給予五千元報酬，嗣丁○○、丙○○二人或單獨、或與\n    甲○○共同於附表所示時間、地點，收取如附表所示人員之\n    巨邦旅行社及雄獅旅行社之職員代辦\n    附表所示之人，前往臺北市○○路○段一三四巷七號「美國\n    在台協會臺北辦事處」辦理美國簽證後予以收購，再交由甲\n    ○○統籌收齊後（渠三人所蒐購之我國國民\n    間、地點、\n    永和市不詳店名簡餐店、咖啡廳，或在嘉義市不詳店名咖啡\n    廳，或持往泰國曼谷，轉售該「林永隆」者，嗣該「林永隆\n    」者將收購而來之\n    僑綽號「阿真」、「開樂」等成年男子，以換貼照片方式，\n    變造我國國民\n    成年男子及綽號「大姐」不詳年籍姓名之成年女子安排意圖\n    偷渡前往美國者持該變造之我國\n    六日及八十九年十二月六日，由大陸女子陳敏霞及董琴分別\n    自泰國曼谷及香港搭乘中華航空班機至桃園中正機場欲轉機\n    前往美國時，在登機門前，因分別持貼有陳敏霞及董琴照片\n    而署名「羅秀玉」及「王嘉鈴」之變造中華民國\n    政部警政署航空警察局（下稱航警局）證照查驗人員查驗時\n    ，旋為航警局證照查驗隊警員當場查獲，並循線查獲上情。\n三、乙○○明知\n    賣，收購\n    ，與甲○○共同基於將\n    犯意聯絡，與甲○○達成以二萬元之代價出售其\n    後，於八十九年六月間某日，在嘉義市○○路路旁，將其國\n    民身分證、退伍令、照片、印章及已過期之中華民國\n    本等物，交付同具犯意聯絡依甲○○指示前往收取之丁○○\n    ，嗣再轉交甲○○，旋甲○○即委由不知情之嘉義市巨邦旅\n    行社職員向外交部申辦乙○○之中華民國\n    月初並由丁○○搭載乙○○北上美國在臺協會辦理簽證，經\n    獲美國簽證後，乙○○即將領取之\n    戊山，再轉交甲○○領取，而甲○○即給付乙○○二萬元；\n    嗣經警於同年十一月十六日在甲○○位於嘉義市○○路一一\n    八號四樓之一住處，查獲乙○○\n四、戊○○於八十九年九、十月間某日，在其娘家嘉義縣番路鄉\n    觸口村埔尾六十號處與甲○○認識時，於言談中，經甲○○\n    表示願以每本二萬元之代價向其購買\n    係表彰特定人身分之證明文件，不得任意買賣，收購\n    係意圖供他人冒名行使，竟為貪圖不法利益，與甲○○共同\n    基於將\n    麗雲於八十九年二月十八日與己○○結婚，戊○○即以前往\n    美國度蜜月為由，於翌日取得己○○之\n    其\n    交部申辦中華民國\n    麗雲及己○○北上臺北美國在臺協會辦理簽證，經獲美國簽\n    證後，由戊○○於八十九年五月間某日，在其上揭住處，將\n    己○○之\n    甲○○即以每本\n    甲○○將之轉售該「林永隆」者再行轉供他人冒名使用。\n五、案經內政部警政署航空警察局移送台灣桃園地方法院檢察署\n    檢察官偵查起訴及台灣嘉義地方法院檢察署檢察官移送併辦\n    。\n    理  由\n一、訊據上訴人被告甲○○供承有於上揭時地受「林永隆」之委\n    託，由其本人及委由被告丁○○及丙○○以每本\n    之代價收購如附表所示之我國國民\n    」之事實，而訊據上訴人即被告丁○○及丙○○均供承有於\n    上揭時地受被告甲○○之指示，代為尋覓有意出售\n    而經分別收購如附表所示之我國國民\n    被告甲○○獲取五千元報酬等事實，經核彼等所述如何收購\n    我國國民\n    、李金獅、吳雪聘、李建益、許采薇（原名許淑媛）、蔡嘉\n    明、施明芳、蔡居安、陳美娟、張惠茱、張惠婷、侯季萩、\n    梁冬洋、詹秋純、王嘉鈴、黃宇翔、蘇昭蓉、馮振華及王木\n    村亦分別於偵審時供稱因被告甲○○、丁○○及丙○○等人\n    前來覓購\n    慶安代為辦理\n    四０號卷第一八二頁背面至第一九０頁、原審卷（四）第一\n    八七頁、第一八八頁、卷（五）第六八頁、第七十頁及臺灣\n    嘉義地方法院檢察署九十年偵字第三０九七號卷第六一頁、\n    第六二頁），並有如附表所示人員普通\n    請書影本各乙份在卷可稽，且經警於八十九年十月四日在被\n    告甲○○上揭住處查獲署名「蔡嘉明」之變造\n    可稽（被告甲○○等並未涉犯行使變造\n    ），而蔡嘉明之\n    ，亦據蔡嘉明供明在卷，依上所述，被告甲○○、丁○○及\n    丙○○上揭自白堪認與事實相符，事證明確，被告甲○○、\n    丁○○及丙○○犯行，洵堪認定。\n二、訊據上訴人即被告乙○○供承有於上揭時地將其國民\n    、退伍令、照片、印章及已過期之中華民國\n    戊山轉交甲○○，以供被告甲○○代為辦理其\n    被告丁○○帶同其北上美國在臺協會辦理簽證，而將領取護\n    照及簽證之領據交由被告丁○○轉交被告甲○○領取之事實\n    ，惟被告乙○○矢口否認有何違反\n    伊僅係委託甲○○代為辦理\n    云，然查被告乙○○於原審法院審理時供稱伊與甲○○往來\n    期間，甲○○是從事檳榔業及裝潢業，而甲○○沒有開過旅\n    行社等語（見原審卷（四）第一五四頁），則被告乙○○所\n    供委由被告甲○○辦理\n    因\n    符常情，何以被告甲○○詢以是否要辦\n    竟即將其上述證件交由被告甲○○代辦\n    山帶同北上美國在臺協會辦理簽證，且於辦完美國簽證後，\n    將領取\n    取，至被告乙○○雖辯稱於\n    銘哲聯絡取回\n    向伊催請交付\n    被告乙○○之\n    十九年十一月十六日在被告甲○○住處查獲，且依被告乙○\n    ○供稱伊辦理美國簽證時係任職於南山人壽等語，然依卷附\n    被告乙○○申請書上服務機關欄竟填載：將群資訊有限公司\n    ，此有被告乙○○之辦理美國簽證申請書乙紙在卷可考（見\n    九十年度偵字第三八四０號卷第七八頁），若被告乙○○僅\n    係因\n    填載不實資料，另查被告乙○○介紹同案被告吳雪聘與被告\n    甲○○認識等情，此據被告乙○○、甲○○及同案被告吳雪\n    聘供述在卷，而依被告丁○○於警詢時供稱：吳雪聘是乙○\n    ○介紹認識的，吳雪聘販賣\n    由乙○○交給伊處理，辦理美簽也是伊帶他們去臺北辦的等\n    語（見同上偵字第三八四０號偵查卷第十三頁背面），嗣同\n    案被告吳雪聘因而將領取之\n    情，亦據同案被告吳雪聘及被告甲○○供述在卷（見原審卷\n    （三）第一八七頁及本院卷九十四年三月三日準備程序筆錄\n    ），而同案被告吳雪聘並因販賣\n    法院同案判處罪刑確定，茲查被告乙○○與同案被告吳雪聘\n    以同一模式，委由被告甲○○代辦\n    告吳雪聘並因被告乙○○之介紹，而將其\n    銘哲，足見被告乙○○係販售其本人\n    亦介紹同案吳雪聘販賣\n    揭所辯僅是單純委由甲○○申辦\n    足取。\n三、訊據被告戊○○供承上揭將其所有與己○○所有之\n    每本二萬元之代價販售予被告甲○○之事實，核與被告甲○\n    ○供述如何向被告戊○○購買戊○○與己○○夫妻二人\n    之情節相符，而被告己○○亦供稱案發後檢察官訊問時，伊\n    才知道戊○○將伊之\n    非從事旅行社業務之被告甲○○代為辦理\n    國在臺協會辦理簽證，而被告己○○亦由被告甲○○指示被\n    告丙○○帶同北上美國在臺協會辦理簽證，茲被告戊○○亦\n    無從提出其自己及其夫己○○之\n    雲上揭自白販售其與己○○之\n    ，事證明確，被告戊○○犯行，洵堪認定。\n四、查\n    ，本不得任意買賣，或借予他人使用，是將\n    ，應得預見該收購者係意圖供他人冒名使用，是核被告甲○\n    ○、丁○○、丙○○、乙○○及戊○○所為，均係犯\n    例第二十四條第三項之將\n    罪。而查共同正犯之意思聯絡，原不以數人間直接發生者為\n    限，即有間接之聯絡者，亦無礙於其為共同正犯之成立；本\n    件被告甲○○與名為「林永隆」不詳年籍之成年男子基於共\n    同犯意聯絡，由名為「林永隆」者囑被告甲○○在臺負責收\n    購他人之\n    山及丙○○代為尋覓出售\n    被告丁○○、丙○○雖與該名為「林永隆」者未有直接犯意\n    聯絡，然被告丁○○及丙○○係經由被告甲○○居間聯絡，\n    而被告甲○○、丁○○、丙○○與該名為「林永隆」四人因\n    而基於同一犯意，則就所犯上開之罪具有犯意聯絡及行為分\n    擔，均為共同正犯；至被告甲○○、丁○○、丙○○分別向\n    附表所示之人收購\n    銘、丁○○及丙○○分別與各該出售\n    等人間（其中附表編號十己○○除外），具有犯意聯絡及行\n    為分擔，均為共同正犯。被告甲○○、丁○○、丙○○各先\n    後多次將\n    ，手段相似，觸犯構成要件相同之罪名，顯均係基於概括犯\n    意為之，均應依連續犯規定，論以一連續將\n    以供他人冒名使用罪，並加重其刑。至公訴人雖就被告甲○\n    ○、丁○○收購王木村\n    冒名使用部分犯行提起公訴，然此部分犯行與公訴人起訴而\n    經論罪之被告丁○○等人上開犯行具有連續犯之裁判上一罪\n    關係，本院自得併予審理。而查被告丁○○有上揭事實欄所\n    載之前科判決及執行情形，有本院被告全國前案紀錄表在卷\n    可參，被告丁○○於受有期徒刑執行完畢後五年內，再犯本\n    件有期徒刑以上之罪，為累犯，應依刑法四十七條規定遞加\n    重其刑。原審以被告甲○○、丁○○、丙○○及呂長未上述\n    犯行事證明確，予以論罪科刑，固非無見，惟查：（一）被\n    告甲○○、丁○○及丙○○僅係收購\n    林永隆」者，並未參與本件\n    使用之犯行，原審認被告甲○○、丁○○及丙○○除收購護\n    照外，並參與變造\n    告甲○○、丁○○及丙○○並係犯\n    項、第一項之行使變造\n    未當；（二）被告戊○○以每本二萬元之代價出售其所有及\n    己○○所有之\n    應成立\n    他人冒名使用罪，原審未詳加調查，細心勾稽，以被告戊○\n    ○係因被告甲○○為招待渠夫妻出國度蜜月，因而交付渠夫\n    妻之\n    為被告戊○○無罪之諭知，其論斷亦有未當；（三）原審就\n    被告乙○○究以若干代價與被告甲○○達成出售其\n    意，未於犯罪事實中載明，暨原審認被告乙○○究出售其護\n    照之犯行係與被告甲○○及丁○○為之，然於判決理由中認\n    被告乙○○就出售其\n    意聯絡及行為分擔，顯相矛盾，均有未洽，是被告乙○○上\n    訴意旨否認犯罪，固無理由，而上訴意旨未指摘及此，惟檢\n    察官上訴意旨指摘原審就被告戊○○部分判決無罪係屬不當\n    ，非無理由，則原判決關於被告甲○○、丁○○、丙○○、\n    乙○○及戊○○部分既有上揭可議之處，自應由本院予以撤\n    銷改判，爰審酌被告甲○○、丁○○、丙○○、乙○○及戊\n    ○○之素行，犯罪之動機、目的、手段，因而所獲得之利益\n    ，被告甲○○、丁○○及丙○○收購他人\n    區，供大陸地區人士不法利用，犯罪情節難認輕微，惟念被\n    告甲○○罹患胰臟膿瘍、腸缺血壞死及腹膜炎併敗血性休克\n    ，因而多次住院接受手術治療，其間並因而經病危通知，目\n    前仍於左腹部有引流管，引流胰臟管，仍需持續治療，有\n    財團法人佛教慈濟綜合醫院大林分院、長庚紀念醫院及嘉義\n    榮民醫院出具之甲○○診斷證明書及病危通知書一紙在卷可\n    參，為免其因入監服刑而加重病情，而被告丁○○及丙○○\n    僅係依被告甲○○指示代為尋覓販賣\n    乙○○僅係一時貪圖利益而出售\n    山、丙○○及戊○○犯後坦承犯行，已知所悔悟等一切情狀\n    ，分別量處被告甲○○、丁○○、丙○○、乙○○及戊○○\n    如主文所示第二、三、四、五、六項所示之刑；而查被告行\n    為後，刑法第四十一條業於九十年一月十日經總統公佈，並\n    於同年月十二日生效，將易科罰金適用範圍由最重本刑有期\n    徒刑三年提高為五年以下有期徒刑以下之刑之罪，經比較新\n    舊法結果，以修正後之新法對被告較為有利，依刑法第二條\n    第一項前段規定，並依修正後刑法第四十一條第一項規定，\n    爰併就被告甲○○、丁○○、丙○○、乙○○及戊○○所量\n    處之有期徒刑均諭知易科罰金之折算標準，另就被告甲○○\n    、丁○○及丙○○併科罰金部份諭知易服勞役之折算標準。\n五、公訴意旨另以：被告甲○○、丁○○及丙○○與何嘉容、許\n    進銘及大陸地區林姓等真實性名不詳男子基於共同之犯意聯\n    絡，合組人蛇集團，先由臺灣地區人民許進銘利用自己身分\n    辦理\n    被告甲○○、丙○○及丁○○等人，連同被告甲○○、丙○\n    ○及丁○○其他所收購之我國國民\n    子變造後，以美金五萬元不等之價錢，協助大陸地區人士假\n    冒臺灣地區人民，持用變造謢照，自泰國等地搭機來臺，在\n    桃園中正機場轉機前往美國，以此方式造成臺灣人民在臺灣\n    直接搭機前往美國之假象，藉以矇混入境；嗣於八十九年八\n    月十六日，大陸人士楊衛勝，自泰國曼谷搭乘華航ＣＩ０六\n    六號班機至桃園中正機場，欲轉搭華航ＣＩ００六班機前往\n    美國，於同日下午四時四十五分許，在桃園中正機場Ａ６登\n    機門前，持用變造之許進銘中華民國\n    航空警察局查驗人員行使時當場查獲，因認被告甲○○、丁\n    ○○及丙○○另涉犯\n    行使變造\n六、按犯罪事實應依證據認定之，無證據不得推定其犯罪事實，\n    刑事訴訟法第一百五十四條第二項定有明文。所謂認定犯罪\n    事實之證據，係指足以認定被告確有犯罪行為之積極證據而\n    言，該項證據自須適合於被告犯罪事實認定，始得採為斷罪\n    資料，如未能發現相當證據，或證據不足以證明，自不能以\n    推測或擬制之方法，為裁判基礎（參照最高法院二十九年度\n    上字第三一０五號、四十年台上字第八六號判例）。訊據被\n    告甲○○、丁○○及丙○○均矢口否認有參與變造\n    提供給大陸人士使用之事實，經查：\n(一)被告甲○○係與不詳年籍名為「林永隆」之成年男子達成收\n    購他人\n    臺負責蒐購我國國民\n    ，嗣被告甲○○即以每本\n    照，並另覓妥被告丁○○及丙○○代為收購有意出售其我國\n    統籌收齊後，被告甲○○分別於上揭地點轉售予該名為「林\n    永隆」者，嗣其中被告甲○○、丁○○及丙○○所收購之我\n    國國民\n    ，而由大陸地區人民冒用該變造之\n    述其僅係將收購之我國國民\n    告甲○○固供認知悉該「林永隆」者收購我國國民\n    的係為變造供大陸人士使用，然查該名為「林永隆」者將購\n    自被告甲○○之\n    「阿真」、「開樂」之成年男子，在泰國曼谷以換貼大陸人\n    士照片之方式予以變造，而並查無何積極證據足資證明被告\n    甲○○、丁○○及丙○○共同參與變造，且查被告甲○○將\n    收購之\n    理及使用該等\n    無非僅係貪圖其中轉售之差價，而被告丁○○及丙○○二人\n    並僅係依被告甲○○之指示代為尋覓有意出售\n    覓妥一人從中獲取五千元報酬而已，均無從中參與變造之行\n    為，至經警固於被告甲○○上揭住處查獲署名「蔡嘉明」變\n    造之\n    予「林永隆」之\n    國民\n    美國，並係由泰國華僑綽號「阿真」、「開樂」之成年男子\n    在泰國曼谷予以變造，則該等變造後之\n    銘哲住處之理，是被告甲○○所述該變造之「蔡嘉明」\n    係被冒名使用後，林永隆交還伊的等語，尚非無據，實難因\n    於被告甲○○住處查獲變造之\n    與該變造\n    購國國民\n    該等收購之\n    同實施犯罪行為者外，其就他人之行為負共犯之責者，以有\n    意思聯絡為要件，茲綜上所述，本件既無何證據除認被告甲\n    ○○、丁○○及丙○○有共同參與變造\n    極證據足資證明被告甲○○、丁○○及丙○○有參與謀議如\n    何收購我國國民\n    而由渠等分擔收購\n    丙○○所辯並無參與變造\n    銘哲、丁○○及丙○○此部分犯行，尚屬不能證明。\n(二)訊據被告甲○○、丁○○及丙○○均否認認識何嘉容、許進\n    銘，暨收購許進銘\n    時地，將其\n    名使用，但並未見過丁○○、丙○○等情，業據同案被告許\n    進銘於原審法院審理中及何嘉容另案被訴違反\n    （臺灣桃園地方法院九十二年度訴字第六二０號違反\n    例案件）審理時供明在卷，有該審理筆錄在卷可參，而證人\n    即另案被告何嘉容於其上揭違反\n    審法院審理時亦供稱：伊僅認識許進銘，不認識亦未見過丁\n    ○○、丙○○、甲○○等人，不知為何檢察官起訴其與丁○\n    ○等人共同合組人蛇集團變造\n    見原審卷（一）第三一一頁、第三一二頁），而證人即承辦\n    本案之航警局刑警隊偵查員吳偉秀於原審法院審理中時證稱\n    ：何嘉容沒有參與本案，當時在機場查獲許進銘、羅秀玉的\n    的，但是因為當時何嘉容都沒有回國接受訊問，所以我們都\n    無法證明是否有關係等語（見原審卷（一）第三一二頁），\n    而查同案被告許進銘之\n    用，於八十九年八月十六日自泰國曼谷搭乘華航ＣＩ０六六\n    號班機至桃園中正機場，欲轉搭華航ＣＩ００六班機前往美\n    國時，在桃園中正機場Ａ６登機門前，為警當場查獲，而證\n    人楊衛勝於警詢時證述：大約在\n    們在大陸福州時，認識一名大陸籍王姓蛇頭（年約六十歲、\n    白頭髮），要我們偷渡到美國打工，約定偷渡成功後，我們\n    要付給他五萬美元為代價，談妥後於七月二十二日先持用大\n    陸\n    拿到曼谷、臺北、洛杉磯的機票及『許進銘』的臺灣假\n    ，於翌日（十六日）即從曼谷搭機來臺北後，再轉搭中華航\n    空ＣＩ００六班機欲偷渡到美國再轉機到芝加哥，伊在泰國\n    曼谷住宿時是由一名自稱林先生的華裔泰國人（年約四十歲\n    、略懂普通話）所照料，他要了我們每人六枚相片，替我們\n    各辦理一本中華民國\n    ０號卷第十三頁背面至第十四頁），是並無積極證據足以證\n    明被告甲○○、丁○○及丙○○有參與變造許進銘\n    為，至上開署名「許進銘」\n    之合成相片，並剪貼雷射防偽國徽，塗色防偽亂碼，且\n    之膠膜內有氣泡，與以雷射版網狀相片、雷射防偽國徽密接\n    、其防偽亂碼清淡，且\n    造品乙節，有內政部警政署航空警察局證照查驗隊出具之查\n    驗隊偽變造\n    字第一七七五０號卷第十七頁），然此僅可證明楊衛勝所持\n    之\n    丁○○及丙○○有何參與變造許進銘\n    、許進銘有何犯意聯絡，合組人蛇集團，是被告甲○○、丁\n    ○○及丙○○所辯並無收購及變造許進銘\n    信，被告甲○○、丁○○及丙○○此部分犯行亦屬不能證明\n    。\n    依上所述，並無何證據足資證明被告甲○○、丁○○及丙○\n    ○有上揭變造\n    人認被告甲○○、丁○○及丙○○此部分犯行同屬被告三人\n    上開所犯實質上一罪之犯行，自不另為無罪之諭知。\n七、公訴意旨另以：被告己○○係被告戊○○之夫，於八十九年\n    三、四月間，被告甲○○以免費招待其出國旅遊之作為報酬\n    ，而被告己○○竟將本人\n    辦理謢照及美國簽證，因認被告己○○涉犯\n    四條第三項之罪嫌（起訴書贅載同條例第二十四條第二項、\n    第一項）云云。\n八、按犯罪事實應依證據認定之，無證據不得認定犯罪事實；又\n    不能證明被告犯罪者，應諭知無罪之判決，刑事訴訟法第一\n    百五十四條第二項及第三百零一條第一項分別定有明文。而\n    所謂認定犯罪事實之證據，係指足以認定被告確有犯罪行為\n    之積極證據而言，該項證據自須適合於被告犯罪事實之認定\n    ，始得採為斷罪資料，如未能發現相當證據，或證據不足以\n    證明，自不能以推測或擬制之方法，以為裁判之基礎（參照\n    最高法院二十九年上字第三一０五號、四十年臺上字第八六\n    號及三十年上字第八一六號判例）。\n九、訊據被告己○○供承被告甲○○以欲招待其夫妻前往美國度\n    蜜月，其因而將\n    帶往美國在臺協會辦理美國簽證等事實，惟矢口否認有公訴\n    人指訴之販售\n    司可招待我們夫妻出國度蜜月，報抵稅金，因而才將伊\n    交給太太辦理，伊一直到檢察官訊問時才知道伊太太將伊的\n    被告己○○二人之\n    銘哲等情，此據被告戊○○及甲○○供承在卷，並已如前述\n    ，而查被告己○○以其係為辦理前往美國旅遊而將\n    被告戊○○辦理，嗣被告戊○○以每本二萬元之代價販售予\n    被告甲○○，惟被告戊○○迭次供述被告己○○並不知情，\n    而被告江明哲於原審法院經通緝到案後即供認以每本二萬元\n    之代價收購被告己○○及戊○○二人之\n    於本院準備程序時供稱伊係於八十八年中秋節後，在戊○○\n    的娘家嘉義縣番路鄉觸口村埔尾六十號跟戊○○談買他們夫\n    妻二人的\n    辦理戊○○\n    就辦理他們夫妻二人之美國簽證，辦完簽證後，將領據交給\n    伊，伊交給戊○○四萬元（見本院卷九十四年三月三日準備\n    程序筆錄），而依卷內資料，並查無何證據足資認定被告己\n    ○○有參與本件\n    安帶往美國在臺協會辦理簽證，惟被告己○○係自行保管領\n    取美國簽證之憑據，此據被告己○○供明在卷（見原審卷（\n    四）第一二一頁），而被告丙○○於本院準備程序時亦供稱\n    伊僅係帶己○○到臺北辦理美國簽證，而己○○並未跟伊提\n    起賣\n    明若明知其辦理美國簽證係為便於出售其\n    ，，而被告丙○○並係依被告甲○○之指示帶同被告己○○\n    前往美國在臺協會辦理簽證，衡情被告己○○於辦完簽證後\n    理應將領取簽證之單據逕交予被告丙○○轉交被告甲○○，\n    又何以由被告己○○交付被告戊○○，再行交付被告甲○○\n    ，是被告戊○○所供己○○之\n    一併販售予甲○○等語，應屬事實，而被告己○○主觀上係\n    認定因被告甲○○為招待渠等夫妻出國度蜜月，始因而將其\n    竟以每本二萬元之代價販售予被告甲○○，惟並查無何證據\n    足認被告己○○事先即知情並與被告戊○○謀議如何出售護\n    照，並推由被告戊○○出面與被告甲○○接洽，是被告己○\n    ○所辯並未參與本件販賣\n    犯罪尚屬不能證明，原審因而以不能證明被告己○○犯罪，\n    而為被告己○○無罪之諭知，經核並無不合，檢察官上訴意\n    旨以被告甲○○供承有以每本二萬元之代價收購被告戊○○\n    及己○○之\n    難認有理由，檢察官就被告己○○部分之上訴，應予駁回。\n據上論斷，應依刑事訴訟法第三百六十八條、第三百六十九條第\n一項前段、第三百六十四條、第二百九十九條第一項前段，\n條例第二十四條第三項，刑法第十一條前段、第二十八條、第五\n十六條、第二條第一項前段、第四十七條、第四十一條第一項、\n第四十二條第二項，罰金罰鍰提高標準條例第二條，判決如主文\n。\n本案經檢察官鄭富銘庭執行職務。\n中    華    民    國    94    年    4     月    8     日\n                  臺灣高等法院刑事第八庭\n                                審判長法  官  吳  敦\n                                      法  官  沈宜生\n                                      法  官  張傳栗\n以上正本證明與原本無異。\n如不服本判決，應於收受送達後十日內向本院提出上訴書狀，其\n未敘述上訴之理由者並得於提起上訴後十日內向本院補提理由書\n（均須按他造當事人之人數附繕本）。\n                                      書記官  秦慧榮\n中    華    民    國    94    年    4     月    11    日\n附錄：本案論罪科刑法條全文\n護照條例第二十四條\n偽造、變造護照足以生損害於公眾或他人者，處五年以下有期徒\n刑，併科新臺幣五十萬元以下罰金。\n行使前項文書者，亦同。\n將護照交付他人或謊報遺失以供他人冒名使用者，處五年以下有\n期徒刑、拘役或科或併科新臺幣十萬元以下罰金。\n附表：\n┌───┬──────┬─────────┬───────┬──────┐\n│編號  │出售護照者之│收購時間、地點    │收購人        │備        註│\n│      │姓名、護照號│                  │              │            │\n│      │碼          │                  │              │            │\n├───┼──────┼─────────┼───────┼──────┤\n│一    │羅秀玉      │八十九年六月間    │甲○○        │經換貼大陸女│\n│      │            │                  │丁○○        │子陳敏霞照片│\n│      │一三０三二四│嘉義縣水上鄉市○街│丙○○        │，由其冒名持│\n│      │二二六      │十一號            │              │用。        │\n├───┼──────┼─────────┼───────┼──────┤\n│二    │郭岳峰      │同右              │同右          │與羅秀玉為夫│\n│      │            │                  │              │妻（起訴書誤│\n│      │Ｍ一五七七四│                  │              │載為詹秋純）│\n│      │九九九      │                  │              │。          │\n├───┼──────┼─────────┼───────┼──────┤\n│三    │李金獅      │八十九年八月初某日│丙○○        │            │\n│      │            │（起訴書誤載為同年│              │            │\n│      │一三０五三八│七月下旬）        │              │            │\n│      │三七四      │                  │              │            │\n│      │            │嘉義市○○路某不詳│              │            │\n│      │            │店名遊樂場        │              │            │\n├───┼──────┼─────────┼───────┼──────┤\n│四    │吳雪聘      │八十九年七月間    │甲○○        │            │\n│      │            │                  │              │            │\n│      │一三０五一八│嘉義市○○路「維特│              │            │\n│      │二六一      │ＰＵＢ」          │              │            │\n├───┼──────┼─────────┼───────┼──────┤\n│五    │李建益      │八十九年七月底    │甲○○        │            │\n│      │            │                  │              │            │\n│      │            │嘉義市○○街三十九│              │            │\n│      │            │號                │              │            │\n├───┼──────┼─────────┼───────┼──────┤\n│六    │許采薇      │八十九年七月間    │甲○○        │            │\n│      │（原名許淑媛│                  │              │            │\n│      │）          │嘉義市○○路「維特│              │            │\n│      │            │ＰＵＢ」          │              │            │\n│      │一三０五一一│                  │              │            │\n│      │七三０      │                  │              │            │\n├───┼──────┼─────────┼───────┼──────┤\n│七    │蔡嘉明      │八十九年八月間（起│丙○○        │於八十九年十│\n│      │            │訴書誤載為同年三  │              │一月十六日在│\n│      │一三０四六四│、四）            │              │甲○○位於嘉│\n│      │七五五      │                  │              │義市○○路一│\n│      │            │嘉義市○○路「香格│              │一四號住處，│\n│      │            │里拉ＫＴＶ」      │              │查獲換貼不詳│\n│      │            │                  │              │人士照片，載│\n│      │            │                  │              │有蔡嘉明基本│\n│      │            │                  │              │資料護照號碼│\n│      │            │                  │              │分別為一三０│\n│      │            │                  │              │四六四七五五│\n│      │            │                  │              │、一三０五三│\n│      │            │                  │              │八三七二（此│\n│      │            │                  │              │本護照並變造│\n│      │            │                  │              │出生年月日資│\n│      │            │                  │              │料為五十一年│\n│      │            │                  │              │三月二十七日│\n│      │            │                  │              │）之護照各一│\n│      │            │                  │              │本。        │\n├───┼──────┼─────────┼───────┼──────┤\n│八    │施明芳      │八十九年五月間（起│丙○○        │            │\n│      │            │訴書誤載為同年三、│              │            │\n│      │一三０一四三│四月間）          │              │            │\n│      │九二三      │                  │              │            │\n│      │            │嘉義市○○路「香格│              │            │\n│      │            │里拉ＫＴＶ」      │              │            │\n├───┼──────┼─────────┼───────┼──────┤\n│九    │戊○○      │八十九年二月間    │甲○○        │與己○○為夫│\n│      │            │                  │              │妻          │\n│      │            │嘉義縣水上鄉鎮│              │            │\n│      │            │九十六號之二      │              │            │\n├───┼──────┼─────────┼───────┼──────┤\n│十    │己○○      │八十九年二月十九日│甲○○        │與戊○○為夫│\n│      │            │                  │              │妻          │\n│      │Ｍ一四二五八│嘉義縣水上鄉鎮│              │            │\n│      │四七０      │九十六號之二      │              │            │\n├───┼──────┼─────────┼───────┼──────┤\n│十一  │蔡居安      │八十九年七月間    │丁○○        │            │\n│      │            │                  │丙○○        │            │\n│      │一三０五三八│嘉義市車店里附近  │              │            │\n│      │三七三      │                  │              │            │\n├───┼──────┼─────────┼───────┼──────┤\n│十二  │李瑪琍      │八十九年七月間    │丁○○        │            │\n│      │            │                  │              │            │\n│      │一三０一四０│台北市○○路○段一│              │            │\n│      │二四四      │三四巷七號「美國在│              │            │\n│      │            │台協會台北辦事處」│              │            │\n├───┼──────┼─────────┼───────┼──────┤\n│十三  │陳美娟      │八十九年七月間    │丁○○        │            │\n│      │            │                  │丙○○        │            │\n│      │一三０四五八│台北市○○路○段一│              │            │\n│      │五三二      │三四巷七號「美國在│              │            │\n│      │            │台協會台北辦事處」│              │            │\n│      │            │                  │              │            │\n├───┼──────┼─────────┼───────┼──────┤\n│十四  │侯季萩      │八十九年七月間    │丁○○        │            │\n│      │            │                  │丙○○        │            │\n│      │一三０三三０│台北市○○路○段一│              │            │\n│      │三一六      │三四巷七號「美國在│              │            │\n│      │            │台協會台北辦事處」│              │            │\n├───┼──────┼─────────┼───────┼──────┤\n│十五  │張惠茱      │八十九年七月間    │甲○○        │            │\n│      │            │                  │丁○○        │            │\n│      │一三０四六四│嘉義市○○路「維特│丙○○        │            │\n│      │七五一      │ＰＵＢ」          │              │            │\n├───┼──────┼─────────┼───────┼──────┤\n│十六  │張惠婷      │八十九年七月間    │甲○○        │            │\n│      │            │                  │丁○○        │            │\n│      │一三０四六四│嘉義市○○路「維特│丙○○        │            │\n│      │七四九      │ＰＵＢ」          │              │            │\n├───┼──────┼─────────┼───────┼──────┤\n│十七  │乙○○      │八十九年六月間    │甲○○        │            │\n│      │            │                  │丁○○        │            │\n│      │一三０一二四│嘉義市○○路旁    │              │            │\n│      │四八０      │                  │              │            │\n├───┼──────┼─────────┼───────┼──────┤\n│十八  │梁冬洋      │八十九年七月間    │丁○○        │            │\n│      │            │                  │丙○○        │            │\n│      │一三０三二七│嘉義市○○路「維特│              │            │\n│      │一四二      │ＰＵＢ」          │              │            │\n├───┼──────┼─────────┼───────┼──────┤\n│十九  │詹秋純      │八十九年六月中旬  │丁○○        │            │\n│      │            │                  │              │            │\n│      │一三０三三０│嘉義市○○○路「俊│              │            │\n│      │三一七      │峰通訊行」        │              │            │\n├───┼──────┼─────────┼───────┼──────┤\n│二十  │王嘉鈴      │八十九年十一月間  │丙○○        │經換貼大陸女│\n│      │            │                  │丁○○        │子董琴照片，│\n│      │一三０八五九│嘉義市「小鹿亂撞撞│              │由其冒名持用│\n│      │六二一      │球場」            │              │。          │\n├───┼──────┼─────────┼───────┼──────┤\n│二十一│黃宇翔      │八十九年十一月間  │丙○○        │            │\n│      │            │                  │丁○○        │            │\n│      │一三０八五九│嘉義市「小鹿亂撞撞│              │            │\n│      │六二三      │球場」            │              │            │\n├───┼──────┼─────────┼───────┼──────┤\n│二十二│馮振華      │八十九年十一月間  │丙○○        │            │\n│      │            │                  │丁○○        │            │\n│      │一三０八五九│嘉義市「小鹿亂撞撞│              │            │\n│      │六二四      │球場」            │              │            │\n├───┼──────┼─────────┼───────┼──────┤\n│二十三│蘇昭蓉      │八十九年十一月間  │丙○○        │            │\n│      │            │                  │丁○○        │            │\n│      │一三０八五九│嘉義市「小鹿亂撞撞│              │            │\n│      │六二二      │球場」            │              │            │\n├───┼──────┼─────────┼───────┼──────┤\n│二十四│王木村      │八十九年七月間    │丁○○        │            │\n│      │            │                  │              │            │\n│      │一三０六０七│台北市○○路○段一│              │            │\n│      │九０九      │三四巷七號「美國在│              │            │\n│      │            │台協會台北辦事處」│              │            │\n└───┴──────┴─────────┴───────┴──────┘\n",
  "structure": {
    "main": "原判決關於甲○○、丁○○、丙○○、乙○○及戊○○部分撤銷\n。\n甲○○共同連續將\n刑陸月，併科罰金新臺幣捌萬元，有期徒刑如易科罰金以佰元\n折算壹日，罰金如易服勞役，以銀元佰元即新臺幣玖佰元折算\n壹日。\n丁○○共同連續將\n有期徒刑陸月，併科罰金新臺幣伍萬元，有期徒刑如易科罰金以\n佰元折算壹日，罰金如易服勞役，以銀元佰元即新臺幣玖佰\n元折算壹日。\n丙○○共同連續將\n刑伍月，併科罰金新臺幣萬元，有期徒刑如易科罰金以佰元\n折算壹日，罰金如易服勞役，以銀元佰元即新臺幣玖佰元折算\n壹日。\n乙○○共同將\n月，如易科罰金，以佰元折算壹日。\n戊○○共同將\n月，如易科罰金，以佰元折算壹日。\n其他上訴駁回。",
    "fact": "一、丁○○前有麻醉藥品管理條例等前科，其於民國（下同）八\n    十七年間所犯之竊盜案件，經臺灣高等法院台南高分院判處\n    有期徒刑三月確定，於八十八年四月十九日入監服刑，而於\n    八十八年七月十八日執行完畢。\n二、甲○○與不詳年籍名為「林永隆」之成年男子，明知\n    表彰特定人身分之證明文件，不得任意買賣，收購\n    意圖供他人冒名行使，竟為貪圖不法利益，共同基於將\n    交付他人，以供他人冒名使用之概括犯意聯絡，由名為「林\n    永隆」者囑由甲○○在臺負責收購他人之\n    。甲○○旋自八十九年二月間起以每本新台幣（下同）二萬\n    元，收購我國國民\n    有犯意聯絡之丁○○、丙○○，並告知願以每本二萬元代價\n    收購我國國民\n    人即給予五千元報酬，嗣丁○○、丙○○二人或單獨、或與\n    甲○○共同於附表所示時間、地點，收取如附表所示人員之\n    巨邦旅行社及雄獅旅行社之職員代辦\n    附表所示之人，前往臺北市○○路○段一三四巷七號「美國\n    在台協會臺北辦事處」辦理美國簽證後予以收購，再交由甲\n    ○○統籌收齊後（渠三人所蒐購之我國國民\n    間、地點、\n    永和市不詳店名簡餐店、咖啡廳，或在嘉義市不詳店名咖啡\n    廳，或持往泰國曼谷，轉售該「林永隆」者，嗣該「林永隆\n    」者將收購而來之\n    僑綽號「阿真」、「開樂」等成年男子，以換貼照片方式，\n    變造我國國民\n    成年男子及綽號「大姐」不詳年籍姓名之成年女子安排意圖\n    偷渡前往美國者持該變造之我國\n    六日及八十九年十二月六日，由大陸女子陳敏霞及董琴分別\n    自泰國曼谷及香港搭乘中華航空班機至桃園中正機場欲轉機\n    前往美國時，在登機門前，因分別持貼有陳敏霞及董琴照片\n    而署名「羅秀玉」及「王嘉鈴」之變造中華民國\n    政部警政署航空警察局（下稱航警局）證照查驗人員查驗時\n    ，旋為航警局證照查驗隊警員當場查獲，並循線查獲上情。\n三、乙○○明知\n    賣，收購\n    ，與甲○○共同基於將\n    犯意聯絡，與甲○○達成以二萬元之代價出售其\n    後，於八十九年六月間某日，在嘉義市○○路路旁，將其國\n    民身分證、退伍令、照片、印章及已過期之中華民國\n    本等物，交付同具犯意聯絡依甲○○指示前往收取之丁○○\n    ，嗣再轉交甲○○，旋甲○○即委由不知情之嘉義市巨邦旅\n    行社職員向外交部申辦乙○○之中華民國\n    月初並由丁○○搭載乙○○北上美國在臺協會辦理簽證，經\n    獲美國簽證後，乙○○即將領取之\n    戊山，再轉交甲○○領取，而甲○○即給付乙○○二萬元；\n    嗣經警於同年十一月十六日在甲○○位於嘉義市○○路一一\n    八號四樓之一住處，查獲乙○○\n四、戊○○於八十九年九、十月間某日，在其娘家嘉義縣番路鄉\n    觸口村埔尾六十號處與甲○○認識時，於言談中，經甲○○\n    表示願以每本二萬元之代價向其購買\n    係表彰特定人身分之證明文件，不得任意買賣，收購\n    係意圖供他人冒名行使，竟為貪圖不法利益，與甲○○共同\n    基於將\n    麗雲於八十九年二月十八日與己○○結婚，戊○○即以前往\n    美國度蜜月為由，於翌日取得己○○之\n    其\n    交部申辦中華民國\n    麗雲及己○○北上臺北美國在臺協會辦理簽證，經獲美國簽\n    證後，由戊○○於八十九年五月間某日，在其上揭住處，將\n    己○○之\n    甲○○即以每本\n    甲○○將之轉售該「林永隆」者再行轉供他人冒名使用。\n五、案經內政部警政署航空警察局移送台灣桃園地方法院檢察署\n    檢察官偵查起訴及台灣嘉義地方法院檢察署檢察官移送併辦\n    。",
    "reason": "一、訊據上訴人被告甲○○供承有於上揭時地受「林永隆」之委\n    託，由其本人及委由被告丁○○及丙○○以每本\n    之代價收購如附表所示之我國國民\n    」之事實，而訊據上訴人即被告丁○○及丙○○均供承有於\n    上揭時地受被告甲○○之指示，代為尋覓有意出售\n    而經分別收購如附表所示之我國國民\n    被告甲○○獲取五千元報酬等事實，經核彼等所述如何收購\n    我國國民\n    、李金獅、吳雪聘、李建益、許采薇（原名許淑媛）、蔡嘉\n    明、施明芳、蔡居安、陳美娟、張惠茱、張惠婷、侯季萩、\n    梁冬洋、詹秋純、王嘉鈴、黃宇翔、蘇昭蓉、馮振華及王木\n    村亦分別於偵審時供稱因被告甲○○、丁○○及丙○○等人\n    前來覓購\n    慶安代為辦理\n    四０號卷第一八二頁背面至第一九０頁、原審卷（四）第一\n    八七頁、第一八八頁、卷（五）第六八頁、第七十頁及臺灣\n    嘉義地方法院檢察署九十年偵字第三０九七號卷第六一頁、\n    第六二頁），並有如附表所示人員普通\n    請書影本各乙份在卷可稽，且經警於八十九年十月四日在被\n    告甲○○上揭住處查獲署名「蔡嘉明」之變造\n    可稽（被告甲○○等並未涉犯行使變造\n    ），而蔡嘉明之\n    ，亦據蔡嘉明供明在卷，依上所述，被告甲○○、丁○○及\n    丙○○上揭自白堪認與事實相符，事證明確，被告甲○○、\n    丁○○及丙○○犯行，洵堪認定。\n二、訊據上訴人即被告乙○○供承有於上揭時地將其國民\n    、退伍令、照片、印章及已過期之中華民國\n    戊山轉交甲○○，以供被告甲○○代為辦理其\n    被告丁○○帶同其北上美國在臺協會辦理簽證，而將領取護\n    照及簽證之領據交由被告丁○○轉交被告甲○○領取之事實\n    ，惟被告乙○○矢口否認有何違反\n    伊僅係委託甲○○代為辦理\n    云，然查被告乙○○於原審法院審理時供稱伊與甲○○往來\n    期間，甲○○是從事檳榔業及裝潢業，而甲○○沒有開過旅\n    行社等語（見原審卷（四）第一五四頁），則被告乙○○所\n    供委由被告甲○○辦理\n    因\n    符常情，何以被告甲○○詢以是否要辦\n    竟即將其上述證件交由被告甲○○代辦\n    山帶同北上美國在臺協會辦理簽證，且於辦完美國簽證後，\n    將領取\n    取，至被告乙○○雖辯稱於\n    銘哲聯絡取回\n    向伊催請交付\n    被告乙○○之\n    十九年十一月十六日在被告甲○○住處查獲，且依被告乙○\n    ○供稱伊辦理美國簽證時係任職於南山人壽等語，然依卷附\n    被告乙○○申請書上服務機關欄竟填載：將群資訊有限公司\n    ，此有被告乙○○之辦理美國簽證申請書乙紙在卷可考（見\n    九十年度偵字第三八四０號卷第七八頁），若被告乙○○僅\n    係因\n    填載不實資料，另查被告乙○○介紹同案被告吳雪聘與被告\n    甲○○認識等情，此據被告乙○○、甲○○及同案被告吳雪\n    聘供述在卷，而依被告丁○○於警詢時供稱：吳雪聘是乙○\n    ○介紹認識的，吳雪聘販賣\n    由乙○○交給伊處理，辦理美簽也是伊帶他們去臺北辦的等\n    語（見同上偵字第三八四０號偵查卷第十三頁背面），嗣同\n    案被告吳雪聘因而將領取之\n    情，亦據同案被告吳雪聘及被告甲○○供述在卷（見原審卷\n    （三）第一八七頁及本院卷九十四年三月三日準備程序筆錄\n    ），而同案被告吳雪聘並因販賣\n    法院同案判處罪刑確定，茲查被告乙○○與同案被告吳雪聘\n    以同一模式，委由被告甲○○代辦\n    告吳雪聘並因被告乙○○之介紹，而將其\n    銘哲，足見被告乙○○係販售其本人\n    亦介紹同案吳雪聘販賣\n    揭所辯僅是單純委由甲○○申辦\n    足取。\n三、訊據被告戊○○供承上揭將其所有與己○○所有之\n    每本二萬元之代價販售予被告甲○○之事實，核與被告甲○\n    ○供述如何向被告戊○○購買戊○○與己○○夫妻二人\n    之情節相符，而被告己○○亦供稱案發後檢察官訊問時，伊\n    才知道戊○○將伊之\n    非從事旅行社業務之被告甲○○代為辦理\n    國在臺協會辦理簽證，而被告己○○亦由被告甲○○指示被\n    告丙○○帶同北上美國在臺協會辦理簽證，茲被告戊○○亦\n    無從提出其自己及其夫己○○之\n    雲上揭自白販售其與己○○之\n    ，事證明確，被告戊○○犯行，洵堪認定。\n四、查\n    ，本不得任意買賣，或借予他人使用，是將\n    ，應得預見該收購者係意圖供他人冒名使用，是核被告甲○\n    ○、丁○○、丙○○、乙○○及戊○○所為，均係犯\n    例第二十四條第三項之將\n    罪。而查共同正犯之意思聯絡，原不以數人間直接發生者為\n    限，即有間接之聯絡者，亦無礙於其為共同正犯之成立；本\n    件被告甲○○與名為「林永隆」不詳年籍之成年男子基於共\n    同犯意聯絡，由名為「林永隆」者囑被告甲○○在臺負責收\n    購他人之\n    山及丙○○代為尋覓出售\n    被告丁○○、丙○○雖與該名為「林永隆」者未有直接犯意\n    聯絡，然被告丁○○及丙○○係經由被告甲○○居間聯絡，\n    而被告甲○○、丁○○、丙○○與該名為「林永隆」四人因\n    而基於同一犯意，則就所犯上開之罪具有犯意聯絡及行為分\n    擔，均為共同正犯；至被告甲○○、丁○○、丙○○分別向\n    附表所示之人收購\n    銘、丁○○及丙○○分別與各該出售\n    等人間（其中附表編號十己○○除外），具有犯意聯絡及行\n    為分擔，均為共同正犯。被告甲○○、丁○○、丙○○各先\n    後多次將\n    ，手段相似，觸犯構成要件相同之罪名，顯均係基於概括犯\n    意為之，均應依連續犯規定，論以一連續將\n    以供他人冒名使用罪，並加重其刑。至公訴人雖就被告甲○\n    ○、丁○○收購王木村\n    冒名使用部分犯行提起公訴，然此部分犯行與公訴人起訴而\n    經論罪之被告丁○○等人上開犯行具有連續犯之裁判上一罪\n    關係，本院自得併予審理。而查被告丁○○有上揭事實欄所\n    載之前科判決及執行情形，有本院被告全國前案紀錄表在卷\n    可參，被告丁○○於受有期徒刑執行完畢後五年內，再犯本\n    件有期徒刑以上之罪，為累犯，應依刑法四十七條規定遞加\n    重其刑。原審以被告甲○○、丁○○、丙○○及呂長未上述\n    犯行事證明確，予以論罪科刑，固非無見，惟查：（一）被\n    告甲○○、丁○○及丙○○僅係收購\n    林永隆」者，並未參與本件\n    使用之犯行，原審認被告甲○○、丁○○及丙○○除收購護\n    照外，並參與變造\n    告甲○○、丁○○及丙○○並係犯\n    項、第一項之行使變造\n    未當；（二）被告戊○○以每本二萬元之代價出售其所有及\n    己○○所有之\n    應成立\n    他人冒名使用罪，原審未詳加調查，細心勾稽，以被告戊○\n    ○係因被告甲○○為招待渠夫妻出國度蜜月，因而交付渠夫\n    妻之\n    為被告戊○○無罪之諭知，其論斷亦有未當；（三）原審就\n    被告乙○○究以若干代價與被告甲○○達成出售其\n    意，未於犯罪事實中載明，暨原審認被告乙○○究出售其護\n    照之犯行係與被告甲○○及丁○○為之，然於判決理由中認\n    被告乙○○就出售其\n    意聯絡及行為分擔，顯相矛盾，均有未洽，是被告乙○○上\n    訴意旨否認犯罪，固無理由，而上訴意旨未指摘及此，惟檢\n    察官上訴意旨指摘原審就被告戊○○部分判決無罪係屬不當\n    ，非無理由，則原判決關於被告甲○○、丁○○、丙○○、\n    乙○○及戊○○部分既有上揭可議之處，自應由本院予以撤\n    銷改判，爰審酌被告甲○○、丁○○、丙○○、乙○○及戊\n    ○○之素行，犯罪之動機、目的、手段，因而所獲得之利益\n    ，被告甲○○、丁○○及丙○○收購他人\n    區，供大陸地區人士不法利用，犯罪情節難認輕微，惟念被\n    告甲○○罹患胰臟膿瘍、腸缺血壞死及腹膜炎併敗血性休克\n    ，因而多次住院接受手術治療，其間並因而經病危通知，目\n    前仍於左腹部有引流管，引流胰臟管，仍需持續治療，有\n    財團法人佛教慈濟綜合醫院大林分院、長庚紀念醫院及嘉義\n    榮民醫院出具之甲○○診斷證明書及病危通知書一紙在卷可\n    參，為免其因入監服刑而加重病情，而被告丁○○及丙○○\n    僅係依被告甲○○指示代為尋覓販賣\n    乙○○僅係一時貪圖利益而出售\n    山、丙○○及戊○○犯後坦承犯行，已知所悔悟等一切情狀\n    ，分別量處被告甲○○、丁○○、丙○○、乙○○及戊○○\n    如主文所示第二、三、四、五、六項所示之刑；而查被告行\n    為後，刑法第四十一條業於九十年一月十日經總統公佈，並\n    於同年月十二日生效，將易科罰金適用範圍由最重本刑有期\n    徒刑三年提高為五年以下有期徒刑以下之刑之罪，經比較新\n    舊法結果，以修正後之新法對被告較為有利，依刑法第二條\n    第一項前段規定，並依修正後刑法第四十一條第一項規定，\n    爰併就被告甲○○、丁○○、丙○○、乙○○及戊○○所量\n    處之有期徒刑均諭知易科罰金之折算標準，另就被告甲○○\n    、丁○○及丙○○併科罰金部份諭知易服勞役之折算標準。\n五、公訴意旨另以：被告甲○○、丁○○及丙○○與何嘉容、許\n    進銘及大陸地區林姓等真實性名不詳男子基於共同之犯意聯\n    絡，合組人蛇集團，先由臺灣地區人民許進銘利用自己身分\n    辦理\n    被告甲○○、丙○○及丁○○等人，連同被告甲○○、丙○\n    ○及丁○○其他所收購之我國國民\n    子變造後，以美金五萬元不等之價錢，協助大陸地區人士假\n    冒臺灣地區人民，持用變造謢照，自泰國等地搭機來臺，在\n    桃園中正機場轉機前往美國，以此方式造成臺灣人民在臺灣\n    直接搭機前往美國之假象，藉以矇混入境；嗣於八十九年八\n    月十六日，大陸人士楊衛勝，自泰國曼谷搭乘華航ＣＩ０六\n    六號班機至桃園中正機場，欲轉搭華航ＣＩ００六班機前往\n    美國，於同日下午四時四十五分許，在桃園中正機場Ａ６登\n    機門前，持用變造之許進銘中華民國\n    航空警察局查驗人員行使時當場查獲，因認被告甲○○、丁\n    ○○及丙○○另涉犯\n    行使變造\n六、按犯罪事實應依證據認定之，無證據不得推定其犯罪事實，\n    刑事訴訟法第一百五十四條第二項定有明文。所謂認定犯罪\n    事實之證據，係指足以認定被告確有犯罪行為之積極證據而\n    言，該項證據自須適合於被告犯罪事實認定，始得採為斷罪\n    資料，如未能發現相當證據，或證據不足以證明，自不能以\n    推測或擬制之方法，為裁判基礎（參照最高法院二十九年度\n    上字第三一０五號、四十年台上字第八六號判例）。訊據被\n    告甲○○、丁○○及丙○○均矢口否認有參與變造\n    提供給大陸人士使用之事實，經查：\n(一)被告甲○○係與不詳年籍名為「林永隆」之成年男子達成收\n    購他人\n    臺負責蒐購我國國民\n    ，嗣被告甲○○即以每本\n    照，並另覓妥被告丁○○及丙○○代為收購有意出售其我國\n    統籌收齊後，被告甲○○分別於上揭地點轉售予該名為「林\n    永隆」者，嗣其中被告甲○○、丁○○及丙○○所收購之我\n    國國民\n    ，而由大陸地區人民冒用該變造之\n    述其僅係將收購之我國國民\n    告甲○○固供認知悉該「林永隆」者收購我國國民\n    的係為變造供大陸人士使用，然查該名為「林永隆」者將購\n    自被告甲○○之\n    「阿真」、「開樂」之成年男子，在泰國曼谷以換貼大陸人\n    士照片之方式予以變造，而並查無何積極證據足資證明被告\n    甲○○、丁○○及丙○○共同參與變造，且查被告甲○○將\n    收購之\n    理及使用該等\n    無非僅係貪圖其中轉售之差價，而被告丁○○及丙○○二人\n    並僅係依被告甲○○之指示代為尋覓有意出售\n    覓妥一人從中獲取五千元報酬而已，均無從中參與變造之行\n    為，至經警固於被告甲○○上揭住處查獲署名「蔡嘉明」變\n    造之\n    予「林永隆」之\n    國民\n    美國，並係由泰國華僑綽號「阿真」、「開樂」之成年男子\n    在泰國曼谷予以變造，則該等變造後之\n    銘哲住處之理，是被告甲○○所述該變造之「蔡嘉明」\n    係被冒名使用後，林永隆交還伊的等語，尚非無據，實難因\n    於被告甲○○住處查獲變造之\n    與該變造\n    購國國民\n    該等收購之\n    同實施犯罪行為者外，其就他人之行為負共犯之責者，以有\n    意思聯絡為要件，茲綜上所述，本件既無何證據除認被告甲\n    ○○、丁○○及丙○○有共同參與變造\n    極證據足資證明被告甲○○、丁○○及丙○○有參與謀議如\n    何收購我國國民\n    而由渠等分擔收購\n    丙○○所辯並無參與變造\n    銘哲、丁○○及丙○○此部分犯行，尚屬不能證明。\n(二)訊據被告甲○○、丁○○及丙○○均否認認識何嘉容、許進\n    銘，暨收購許進銘\n    時地，將其\n    名使用，但並未見過丁○○、丙○○等情，業據同案被告許\n    進銘於原審法院審理中及何嘉容另案被訴違反\n    （臺灣桃園地方法院九十二年度訴字第六二０號違反\n    例案件）審理時供明在卷，有該審理筆錄在卷可參，而證人\n    即另案被告何嘉容於其上揭違反\n    審法院審理時亦供稱：伊僅認識許進銘，不認識亦未見過丁\n    ○○、丙○○、甲○○等人，不知為何檢察官起訴其與丁○\n    ○等人共同合組人蛇集團變造\n    見原審卷（一）第三一一頁、第三一二頁），而證人即承辦\n    本案之航警局刑警隊偵查員吳偉秀於原審法院審理中時證稱\n    ：何嘉容沒有參與本案，當時在機場查獲許進銘、羅秀玉的\n    的，但是因為當時何嘉容都沒有回國接受訊問，所以我們都\n    無法證明是否有關係等語（見原審卷（一）第三一二頁），\n    而查同案被告許進銘之\n    用，於八十九年八月十六日自泰國曼谷搭乘華航ＣＩ０六六\n    號班機至桃園中正機場，欲轉搭華航ＣＩ００六班機前往美\n    國時，在桃園中正機場Ａ６登機門前，為警當場查獲，而證\n    人楊衛勝於警詢時證述：大約在\n    們在大陸福州時，認識一名大陸籍王姓蛇頭（年約六十歲、\n    白頭髮），要我們偷渡到美國打工，約定偷渡成功後，我們\n    要付給他五萬美元為代價，談妥後於七月二十二日先持用大\n    陸\n    拿到曼谷、臺北、洛杉磯的機票及『許進銘』的臺灣假\n    ，於翌日（十六日）即從曼谷搭機來臺北後，再轉搭中華航\n    空ＣＩ００六班機欲偷渡到美國再轉機到芝加哥，伊在泰國\n    曼谷住宿時是由一名自稱林先生的華裔泰國人（年約四十歲\n    、略懂普通話）所照料，他要了我們每人六枚相片，替我們\n    各辦理一本中華民國\n    ０號卷第十三頁背面至第十四頁），是並無積極證據足以證\n    明被告甲○○、丁○○及丙○○有參與變造許進銘\n    為，至上開署名「許進銘」\n    之合成相片，並剪貼雷射防偽國徽，塗色防偽亂碼，且\n    之膠膜內有氣泡，與以雷射版網狀相片、雷射防偽國徽密接\n    、其防偽亂碼清淡，且\n    造品乙節，有內政部警政署航空警察局證照查驗隊出具之查\n    驗隊偽變造\n    字第一七七五０號卷第十七頁），然此僅可證明楊衛勝所持\n    之\n    丁○○及丙○○有何參與變造許進銘\n    、許進銘有何犯意聯絡，合組人蛇集團，是被告甲○○、丁\n    ○○及丙○○所辯並無收購及變造許進銘\n    信，被告甲○○、丁○○及丙○○此部分犯行亦屬不能證明\n    。\n    依上所述，並無何證據足資證明被告甲○○、丁○○及丙○\n    ○有上揭變造\n    人認被告甲○○、丁○○及丙○○此部分犯行同屬被告三人\n    上開所犯實質上一罪之犯行，自不另為無罪之諭知。\n七、公訴意旨另以：被告己○○係被告戊○○之夫，於八十九年\n    三、四月間，被告甲○○以免費招待其出國旅遊之作為報酬\n    ，而被告己○○竟將本人\n    辦理謢照及美國簽證，因認被告己○○涉犯\n    四條第三項之罪嫌（起訴書贅載同條例第二十四條第二項、\n    第一項）云云。\n八、按犯罪事實應依證據認定之，無證據不得認定犯罪事實；又\n    不能證明被告犯罪者，應諭知無罪之判決，刑事訴訟法第一\n    百五十四條第二項及第三百零一條第一項分別定有明文。而\n    所謂認定犯罪事實之證據，係指足以認定被告確有犯罪行為\n    之積極證據而言，該項證據自須適合於被告犯罪事實之認定\n    ，始得採為斷罪資料，如未能發現相當證據，或證據不足以\n    證明，自不能以推測或擬制之方法，以為裁判之基礎（參照\n    最高法院二十九年上字第三一０五號、四十年臺上字第八六\n    號及三十年上字第八一六號判例）。\n九、訊據被告己○○供承被告甲○○以欲招待其夫妻前往美國度\n    蜜月，其因而將\n    帶往美國在臺協會辦理美國簽證等事實，惟矢口否認有公訴\n    人指訴之販售\n    司可招待我們夫妻出國度蜜月，報抵稅金，因而才將伊\n    交給太太辦理，伊一直到檢察官訊問時才知道伊太太將伊的\n    被告己○○二人之\n    銘哲等情，此據被告戊○○及甲○○供承在卷，並已如前述\n    ，而查被告己○○以其係為辦理前往美國旅遊而將\n    被告戊○○辦理，嗣被告戊○○以每本二萬元之代價販售予\n    被告甲○○，惟被告戊○○迭次供述被告己○○並不知情，\n    而被告江明哲於原審法院經通緝到案後即供認以每本二萬元\n    之代價收購被告己○○及戊○○二人之\n    於本院準備程序時供稱伊係於八十八年中秋節後，在戊○○\n    的娘家嘉義縣番路鄉觸口村埔尾六十號跟戊○○談買他們夫\n    妻二人的\n    辦理戊○○\n    就辦理他們夫妻二人之美國簽證，辦完簽證後，將領據交給\n    伊，伊交給戊○○四萬元（見本院卷九十四年三月三日準備\n    程序筆錄），而依卷內資料，並查無何證據足資認定被告己\n    ○○有參與本件\n    安帶往美國在臺協會辦理簽證，惟被告己○○係自行保管領\n    取美國簽證之憑據，此據被告己○○供明在卷（見原審卷（\n    四）第一二一頁），而被告丙○○於本院準備程序時亦供稱\n    伊僅係帶己○○到臺北辦理美國簽證，而己○○並未跟伊提\n    起賣\n    明若明知其辦理美國簽證係為便於出售其\n    ，，而被告丙○○並係依被告甲○○之指示帶同被告己○○\n    前往美國在臺協會辦理簽證，衡情被告己○○於辦完簽證後\n    理應將領取簽證之單據逕交予被告丙○○轉交被告甲○○，\n    又何以由被告己○○交付被告戊○○，再行交付被告甲○○\n    ，是被告戊○○所供己○○之\n    一併販售予甲○○等語，應屬事實，而被告己○○主觀上係\n    認定因被告甲○○為招待渠等夫妻出國度蜜月，始因而將其\n    竟以每本二萬元之代價販售予被告甲○○，惟並查無何證據\n    足認被告己○○事先即知情並與被告戊○○謀議如何出售護\n    照，並推由被告戊○○出面與被告甲○○接洽，是被告己○\n    ○所辯並未參與本件販賣\n    犯罪尚屬不能證明，原審因而以不能證明被告己○○犯罪，\n    而為被告己○○無罪之諭知，經核並無不合，檢察官上訴意\n    旨以被告甲○○供承有以每本二萬元之代價收購被告戊○○\n    及己○○之\n    難認有理由，檢察官就被告己○○部分之上訴，應予駁回。\n據上論斷，應依刑事訴訟法第三百六十八條、第三百六十九條第\n一項前段、第三百六十四條、第二百九十九條第一項前段，\n條例第二十四條第三項，刑法第十一條前段、第二十八條、第五\n十六條、第二條第一項前段、第四十七條、第四十一條第一項、\n第四十二條第二項，罰金罰鍰提高標準條例第二條，判決如主文\n。\n本案經檢察官鄭富銘庭執行職務。\n中    華    民    國    94    年    4     月    8     日\n                  臺灣高等法院刑事第八庭\n                                審判長法  官  吳  敦\n                                      法  官  沈宜生\n                                      法  官  張傳栗\n以上正本證明與原本無異。\n如不服本判決，應於收受送達後十日內向本院提出上訴書狀，其\n未敘述上訴之理由者並得於提起上訴後十日內向本院補提理由書\n（均須按他造當事人之人數附繕本）。\n                                      書記官  秦慧榮"
  },
  "search": "臺灣高等法院刑事判決94年度上訴字第227號上訴人臺灣桃園地方法院檢察署檢察官上訴人即被告甲○○選任辯護人洪榮彬律師陳麗玲律師上訴人即被告丁○○丙○○乙○○被告己○○戊○○上列上訴人因被告違反91年度訴字第686號，中華民國93年4月15日及93年5月18日第一審判決（起訴案號：臺灣桃園地方法院檢察署89年度偵字第17750號、90年度偵字第2512號、第3840號、第8840號；併辦案號：臺灣嘉義地方法院檢察署91年度偵字第3779號、第6096號），提起上訴，本院判決如下：主文原判決關於甲○○、丁○○、丙○○、乙○○及戊○○部分撤銷。甲○○共同連續將刑陸月，併科罰金新臺幣捌萬元，有期徒刑如易科罰金以佰元折算壹日，罰金如易服勞役，以銀元佰元即新臺幣玖佰元折算壹日。丁○○共同連續將有期徒刑陸月，併科罰金新臺幣伍萬元，有期徒刑如易科罰金以佰元折算壹日，罰金如易服勞役，以銀元佰元即新臺幣玖佰元折算壹日。丙○○共同連續將刑伍月，併科罰金新臺幣萬元，有期徒刑如易科罰金以佰元折算壹日，罰金如易服勞役，以銀元佰元即新臺幣玖佰元折算壹日。乙○○共同將月，如易科罰金，以佰元折算壹日。戊○○共同將月，如易科罰金，以佰元折算壹日。其他上訴駁回。事實一、丁○○前有麻醉藥品管理條例等前科，其於民國（下同）八十七年間所犯之竊盜案件，經臺灣高等法院台南高分院判處有期徒刑三月確定，於八十八年四月十九日入監服刑，而於八十八年七月十八日執行完畢。二、甲○○與不詳年籍名為「林永隆」之成年男子，明知表彰特定人身分之證明文件，不得任意買賣，收購意圖供他人冒名行使，竟為貪圖不法利益，共同基於將交付他人，以供他人冒名使用之概括犯意聯絡，由名為「林永隆」者囑由甲○○在臺負責收購他人之。甲○○旋自八十九年二月間起以每本新台幣（下同）二萬元，收購我國國民有犯意聯絡之丁○○、丙○○，並告知願以每本二萬元代價收購我國國民人即給予五千元報酬，嗣丁○○、丙○○二人或單獨、或與甲○○共同於附表所示時間、地點，收取如附表所示人員之巨邦旅行社及雄獅旅行社之職員代辦附表所示之人，前往臺北市○○路○段一三四巷七號「美國在台協會臺北辦事處」辦理美國簽證後予以收購，再交由甲○○統籌收齊後（渠三人所蒐購之我國國民間、地點、永和市不詳店名簡餐店、咖啡廳，或在嘉義市不詳店名咖啡廳，或持往泰國曼谷，轉售該「林永隆」者，嗣該「林永隆」者將收購而來之僑綽號「阿真」、「開樂」等成年男子，以換貼照片方式，變造我國國民成年男子及綽號「大姐」不詳年籍姓名之成年女子安排意圖偷渡前往美國者持該變造之我國六日及八十九年十二月六日，由大陸女子陳敏霞及董琴分別自泰國曼谷及香港搭乘中華航空班機至桃園中正機場欲轉機前往美國時，在登機門前，因分別持貼有陳敏霞及董琴照片而署名「羅秀玉」及「王嘉鈴」之變造中華民國政部警政署航空警察局（下稱航警局）證照查驗人員查驗時，旋為航警局證照查驗隊警員當場查獲，並循線查獲上情。三、乙○○明知賣，收購，與甲○○共同基於將犯意聯絡，與甲○○達成以二萬元之代價出售其後，於八十九年六月間某日，在嘉義市○○路路旁，將其國民身分證、退伍令、照片、印章及已過期之中華民國本等物，交付同具犯意聯絡依甲○○指示前往收取之丁○○，嗣再轉交甲○○，旋甲○○即委由不知情之嘉義市巨邦旅行社職員向外交部申辦乙○○之中華民國月初並由丁○○搭載乙○○北上美國在臺協會辦理簽證，經獲美國簽證後，乙○○即將領取之戊山，再轉交甲○○領取，而甲○○即給付乙○○二萬元；嗣經警於同年十一月十六日在甲○○位於嘉義市○○路一一八號四樓之一住處，查獲乙○○四、戊○○於八十九年九、十月間某日，在其娘家嘉義縣番路鄉觸口村埔尾六十號處與甲○○認識時，於言談中，經甲○○表示願以每本二萬元之代價向其購買係表彰特定人身分之證明文件，不得任意買賣，收購係意圖供他人冒名行使，竟為貪圖不法利益，與甲○○共同基於將麗雲於八十九年二月十八日與己○○結婚，戊○○即以前往美國度蜜月為由，於翌日取得己○○之其交部申辦中華民國麗雲及己○○北上臺北美國在臺協會辦理簽證，經獲美國簽證後，由戊○○於八十九年五月間某日，在其上揭住處，將己○○之甲○○即以每本甲○○將之轉售該「林永隆」者再行轉供他人冒名使用。五、案經內政部警政署航空警察局移送台灣桃園地方法院檢察署檢察官偵查起訴及台灣嘉義地方法院檢察署檢察官移送併辦。理由一、訊據上訴人被告甲○○供承有於上揭時地受「林永隆」之委託，由其本人及委由被告丁○○及丙○○以每本之代價收購如附表所示之我國國民」之事實，而訊據上訴人即被告丁○○及丙○○均供承有於上揭時地受被告甲○○之指示，代為尋覓有意出售而經分別收購如附表所示之我國國民被告甲○○獲取五千元報酬等事實，經核彼等所述如何收購我國國民、李金獅、吳雪聘、李建益、許采薇（原名許淑媛）、蔡嘉明、施明芳、蔡居安、陳美娟、張惠茱、張惠婷、侯季萩、梁冬洋、詹秋純、王嘉鈴、黃宇翔、蘇昭蓉、馮振華及王木村亦分別於偵審時供稱因被告甲○○、丁○○及丙○○等人前來覓購慶安代為辦理四０號卷第一八二頁背面至第一九０頁、原審卷（四）第一八七頁、第一八八頁、卷（五）第六八頁、第七十頁及臺灣嘉義地方法院檢察署九十年偵字第三０九七號卷第六一頁、第六二頁），並有如附表所示人員普通請書影本各乙份在卷可稽，且經警於八十九年十月四日在被告甲○○上揭住處查獲署名「蔡嘉明」之變造可稽（被告甲○○等並未涉犯行使變造），而蔡嘉明之，亦據蔡嘉明供明在卷，依上所述，被告甲○○、丁○○及丙○○上揭自白堪認與事實相符，事證明確，被告甲○○、丁○○及丙○○犯行，洵堪認定。二、訊據上訴人即被告乙○○供承有於上揭時地將其國民、退伍令、照片、印章及已過期之中華民國戊山轉交甲○○，以供被告甲○○代為辦理其被告丁○○帶同其北上美國在臺協會辦理簽證，而將領取護照及簽證之領據交由被告丁○○轉交被告甲○○領取之事實，惟被告乙○○矢口否認有何違反伊僅係委託甲○○代為辦理云，然查被告乙○○於原審法院審理時供稱伊與甲○○往來期間，甲○○是從事檳榔業及裝潢業，而甲○○沒有開過旅行社等語（見原審卷（四）第一五四頁），則被告乙○○所供委由被告甲○○辦理因符常情，何以被告甲○○詢以是否要辦竟即將其上述證件交由被告甲○○代辦山帶同北上美國在臺協會辦理簽證，且於辦完美國簽證後，將領取取，至被告乙○○雖辯稱於銘哲聯絡取回向伊催請交付被告乙○○之十九年十一月十六日在被告甲○○住處查獲，且依被告乙○○供稱伊辦理美國簽證時係任職於南山人壽等語，然依卷附被告乙○○申請書上服務機關欄竟填載：將群資訊有限公司，此有被告乙○○之辦理美國簽證申請書乙紙在卷可考（見九十年度偵字第三八四０號卷第七八頁），若被告乙○○僅係因填載不實資料，另查被告乙○○介紹同案被告吳雪聘與被告甲○○認識等情，此據被告乙○○、甲○○及同案被告吳雪聘供述在卷，而依被告丁○○於警詢時供稱：吳雪聘是乙○○介紹認識的，吳雪聘販賣由乙○○交給伊處理，辦理美簽也是伊帶他們去臺北辦的等語（見同上偵字第三八四０號偵查卷第十三頁背面），嗣同案被告吳雪聘因而將領取之情，亦據同案被告吳雪聘及被告甲○○供述在卷（見原審卷（三）第一八七頁及本院卷九十四年三月三日準備程序筆錄），而同案被告吳雪聘並因販賣法院同案判處罪刑確定，茲查被告乙○○與同案被告吳雪聘以同一模式，委由被告甲○○代辦告吳雪聘並因被告乙○○之介紹，而將其銘哲，足見被告乙○○係販售其本人亦介紹同案吳雪聘販賣揭所辯僅是單純委由甲○○申辦足取。三、訊據被告戊○○供承上揭將其所有與己○○所有之每本二萬元之代價販售予被告甲○○之事實，核與被告甲○○供述如何向被告戊○○購買戊○○與己○○夫妻二人之情節相符，而被告己○○亦供稱案發後檢察官訊問時，伊才知道戊○○將伊之非從事旅行社業務之被告甲○○代為辦理國在臺協會辦理簽證，而被告己○○亦由被告甲○○指示被告丙○○帶同北上美國在臺協會辦理簽證，茲被告戊○○亦無從提出其自己及其夫己○○之雲上揭自白販售其與己○○之，事證明確，被告戊○○犯行，洵堪認定。四、查，本不得任意買賣，或借予他人使用，是將，應得預見該收購者係意圖供他人冒名使用，是核被告甲○○、丁○○、丙○○、乙○○及戊○○所為，均係犯例第二十四條第三項之將罪。而查共同正犯之意思聯絡，原不以數人間直接發生者為限，即有間接之聯絡者，亦無礙於其為共同正犯之成立；本件被告甲○○與名為「林永隆」不詳年籍之成年男子基於共同犯意聯絡，由名為「林永隆」者囑被告甲○○在臺負責收購他人之山及丙○○代為尋覓出售被告丁○○、丙○○雖與該名為「林永隆」者未有直接犯意聯絡，然被告丁○○及丙○○係經由被告甲○○居間聯絡，而被告甲○○、丁○○、丙○○與該名為「林永隆」四人因而基於同一犯意，則就所犯上開之罪具有犯意聯絡及行為分擔，均為共同正犯；至被告甲○○、丁○○、丙○○分別向附表所示之人收購銘、丁○○及丙○○分別與各該出售等人間（其中附表編號十己○○除外），具有犯意聯絡及行為分擔，均為共同正犯。被告甲○○、丁○○、丙○○各先後多次將，手段相似，觸犯構成要件相同之罪名，顯均係基於概括犯意為之，均應依連續犯規定，論以一連續將以供他人冒名使用罪，並加重其刑。至公訴人雖就被告甲○○、丁○○收購王木村冒名使用部分犯行提起公訴，然此部分犯行與公訴人起訴而經論罪之被告丁○○等人上開犯行具有連續犯之裁判上一罪關係，本院自得併予審理。而查被告丁○○有上揭事實欄所載之前科判決及執行情形，有本院被告全國前案紀錄表在卷可參，被告丁○○於受有期徒刑執行完畢後五年內，再犯本件有期徒刑以上之罪，為累犯，應依刑法四十七條規定遞加重其刑。原審以被告甲○○、丁○○、丙○○及呂長未上述犯行事證明確，予以論罪科刑，固非無見，惟查：（一）被告甲○○、丁○○及丙○○僅係收購林永隆」者，並未參與本件使用之犯行，原審認被告甲○○、丁○○及丙○○除收購護照外，並參與變造告甲○○、丁○○及丙○○並係犯項、第一項之行使變造未當；（二）被告戊○○以每本二萬元之代價出售其所有及己○○所有之應成立他人冒名使用罪，原審未詳加調查，細心勾稽，以被告戊○○係因被告甲○○為招待渠夫妻出國度蜜月，因而交付渠夫妻之為被告戊○○無罪之諭知，其論斷亦有未當；（三）原審就被告乙○○究以若干代價與被告甲○○達成出售其意，未於犯罪事實中載明，暨原審認被告乙○○究出售其護照之犯行係與被告甲○○及丁○○為之，然於判決理由中認被告乙○○就出售其意聯絡及行為分擔，顯相矛盾，均有未洽，是被告乙○○上訴意旨否認犯罪，固無理由，而上訴意旨未指摘及此，惟檢察官上訴意旨指摘原審就被告戊○○部分判決無罪係屬不當，非無理由，則原判決關於被告甲○○、丁○○、丙○○、乙○○及戊○○部分既有上揭可議之處，自應由本院予以撤銷改判，爰審酌被告甲○○、丁○○、丙○○、乙○○及戊○○之素行，犯罪之動機、目的、手段，因而所獲得之利益，被告甲○○、丁○○及丙○○收購他人區，供大陸地區人士不法利用，犯罪情節難認輕微，惟念被告甲○○罹患胰臟膿瘍、腸缺血壞死及腹膜炎併敗血性休克，因而多次住院接受手術治療，其間並因而經病危通知，目前仍於左腹部有引流管，引流胰臟管，仍需持續治療，有財團法人佛教慈濟綜合醫院大林分院、長庚紀念醫院及嘉義榮民醫院出具之甲○○診斷證明書及病危通知書一紙在卷可參，為免其因入監服刑而加重病情，而被告丁○○及丙○○僅係依被告甲○○指示代為尋覓販賣乙○○僅係一時貪圖利益而出售山、丙○○及戊○○犯後坦承犯行，已知所悔悟等一切情狀，分別量處被告甲○○、丁○○、丙○○、乙○○及戊○○如主文所示第二、三、四、五、六項所示之刑；而查被告行為後，刑法第四十一條業於九十年一月十日經總統公佈，並於同年月十二日生效，將易科罰金適用範圍由最重本刑有期徒刑三年提高為五年以下有期徒刑以下之刑之罪，經比較新舊法結果，以修正後之新法對被告較為有利，依刑法第二條第一項前段規定，並依修正後刑法第四十一條第一項規定，爰併就被告甲○○、丁○○、丙○○、乙○○及戊○○所量處之有期徒刑均諭知易科罰金之折算標準，另就被告甲○○、丁○○及丙○○併科罰金部份諭知易服勞役之折算標準。五、公訴意旨另以：被告甲○○、丁○○及丙○○與何嘉容、許進銘及大陸地區林姓等真實性名不詳男子基於共同之犯意聯絡，合組人蛇集團，先由臺灣地區人民許進銘利用自己身分辦理被告甲○○、丙○○及丁○○等人，連同被告甲○○、丙○○及丁○○其他所收購之我國國民子變造後，以美金五萬元不等之價錢，協助大陸地區人士假冒臺灣地區人民，持用變造謢照，自泰國等地搭機來臺，在桃園中正機場轉機前往美國，以此方式造成臺灣人民在臺灣直接搭機前往美國之假象，藉以矇混入境；嗣於八十九年八月十六日，大陸人士楊衛勝，自泰國曼谷搭乘華航ＣＩ０六六號班機至桃園中正機場，欲轉搭華航ＣＩ００六班機前往美國，於同日下午四時四十五分許，在桃園中正機場Ａ６登機門前，持用變造之許進銘中華民國航空警察局查驗人員行使時當場查獲，因認被告甲○○、丁○○及丙○○另涉犯行使變造六、按犯罪事實應依證據認定之，無證據不得推定其犯罪事實，刑事訴訟法第一百五十四條第二項定有明文。所謂認定犯罪事實之證據，係指足以認定被告確有犯罪行為之積極證據而言，該項證據自須適合於被告犯罪事實認定，始得採為斷罪資料，如未能發現相當證據，或證據不足以證明，自不能以推測或擬制之方法，為裁判基礎（參照最高法院二十九年度上字第三一０五號、四十年台上字第八六號判例）。訊據被告甲○○、丁○○及丙○○均矢口否認有參與變造提供給大陸人士使用之事實，經查：(一)被告甲○○係與不詳年籍名為「林永隆」之成年男子達成收購他人臺負責蒐購我國國民，嗣被告甲○○即以每本照，並另覓妥被告丁○○及丙○○代為收購有意出售其我國統籌收齊後，被告甲○○分別於上揭地點轉售予該名為「林永隆」者，嗣其中被告甲○○、丁○○及丙○○所收購之我國國民，而由大陸地區人民冒用該變造之述其僅係將收購之我國國民告甲○○固供認知悉該「林永隆」者收購我國國民的係為變造供大陸人士使用，然查該名為「林永隆」者將購自被告甲○○之「阿真」、「開樂」之成年男子，在泰國曼谷以換貼大陸人士照片之方式予以變造，而並查無何積極證據足資證明被告甲○○、丁○○及丙○○共同參與變造，且查被告甲○○將收購之理及使用該等無非僅係貪圖其中轉售之差價，而被告丁○○及丙○○二人並僅係依被告甲○○之指示代為尋覓有意出售覓妥一人從中獲取五千元報酬而已，均無從中參與變造之行為，至經警固於被告甲○○上揭住處查獲署名「蔡嘉明」變造之予「林永隆」之國民美國，並係由泰國華僑綽號「阿真」、「開樂」之成年男子在泰國曼谷予以變造，則該等變造後之銘哲住處之理，是被告甲○○所述該變造之「蔡嘉明」係被冒名使用後，林永隆交還伊的等語，尚非無據，實難因於被告甲○○住處查獲變造之與該變造購國國民該等收購之同實施犯罪行為者外，其就他人之行為負共犯之責者，以有意思聯絡為要件，茲綜上所述，本件既無何證據除認被告甲○○、丁○○及丙○○有共同參與變造極證據足資證明被告甲○○、丁○○及丙○○有參與謀議如何收購我國國民而由渠等分擔收購丙○○所辯並無參與變造銘哲、丁○○及丙○○此部分犯行，尚屬不能證明。(二)訊據被告甲○○、丁○○及丙○○均否認認識何嘉容、許進銘，暨收購許進銘時地，將其名使用，但並未見過丁○○、丙○○等情，業據同案被告許進銘於原審法院審理中及何嘉容另案被訴違反（臺灣桃園地方法院九十二年度訴字第六二０號違反例案件）審理時供明在卷，有該審理筆錄在卷可參，而證人即另案被告何嘉容於其上揭違反審法院審理時亦供稱：伊僅認識許進銘，不認識亦未見過丁○○、丙○○、甲○○等人，不知為何檢察官起訴其與丁○○等人共同合組人蛇集團變造見原審卷（一）第三一一頁、第三一二頁），而證人即承辦本案之航警局刑警隊偵查員吳偉秀於原審法院審理中時證稱：何嘉容沒有參與本案，當時在機場查獲許進銘、羅秀玉的的，但是因為當時何嘉容都沒有回國接受訊問，所以我們都無法證明是否有關係等語（見原審卷（一）第三一二頁），而查同案被告許進銘之用，於八十九年八月十六日自泰國曼谷搭乘華航ＣＩ０六六號班機至桃園中正機場，欲轉搭華航ＣＩ００六班機前往美國時，在桃園中正機場Ａ６登機門前，為警當場查獲，而證人楊衛勝於警詢時證述：大約在們在大陸福州時，認識一名大陸籍王姓蛇頭（年約六十歲、白頭髮），要我們偷渡到美國打工，約定偷渡成功後，我們要付給他五萬美元為代價，談妥後於七月二十二日先持用大陸拿到曼谷、臺北、洛杉磯的機票及『許進銘』的臺灣假，於翌日（十六日）即從曼谷搭機來臺北後，再轉搭中華航空ＣＩ００六班機欲偷渡到美國再轉機到芝加哥，伊在泰國曼谷住宿時是由一名自稱林先生的華裔泰國人（年約四十歲、略懂普通話）所照料，他要了我們每人六枚相片，替我們各辦理一本中華民國０號卷第十三頁背面至第十四頁），是並無積極證據足以證明被告甲○○、丁○○及丙○○有參與變造許進銘為，至上開署名「許進銘」之合成相片，並剪貼雷射防偽國徽，塗色防偽亂碼，且之膠膜內有氣泡，與以雷射版網狀相片、雷射防偽國徽密接、其防偽亂碼清淡，且造品乙節，有內政部警政署航空警察局證照查驗隊出具之查驗隊偽變造字第一七七五０號卷第十七頁），然此僅可證明楊衛勝所持之丁○○及丙○○有何參與變造許進銘、許進銘有何犯意聯絡，合組人蛇集團，是被告甲○○、丁○○及丙○○所辯並無收購及變造許進銘信，被告甲○○、丁○○及丙○○此部分犯行亦屬不能證明。依上所述，並無何證據足資證明被告甲○○、丁○○及丙○○有上揭變造人認被告甲○○、丁○○及丙○○此部分犯行同屬被告三人上開所犯實質上一罪之犯行，自不另為無罪之諭知。七、公訴意旨另以：被告己○○係被告戊○○之夫，於八十九年三、四月間，被告甲○○以免費招待其出國旅遊之作為報酬，而被告己○○竟將本人辦理謢照及美國簽證，因認被告己○○涉犯四條第三項之罪嫌（起訴書贅載同條例第二十四條第二項、第一項）云云。八、按犯罪事實應依證據認定之，無證據不得認定犯罪事實；又不能證明被告犯罪者，應諭知無罪之判決，刑事訴訟法第一百五十四條第二項及第三百零一條第一項分別定有明文。而所謂認定犯罪事實之證據，係指足以認定被告確有犯罪行為之積極證據而言，該項證據自須適合於被告犯罪事實之認定，始得採為斷罪資料，如未能發現相當證據，或證據不足以證明，自不能以推測或擬制之方法，以為裁判之基礎（參照最高法院二十九年上字第三一０五號、四十年臺上字第八六號及三十年上字第八一六號判例）。九、訊據被告己○○供承被告甲○○以欲招待其夫妻前往美國度蜜月，其因而將帶往美國在臺協會辦理美國簽證等事實，惟矢口否認有公訴人指訴之販售司可招待我們夫妻出國度蜜月，報抵稅金，因而才將伊交給太太辦理，伊一直到檢察官訊問時才知道伊太太將伊的被告己○○二人之銘哲等情，此據被告戊○○及甲○○供承在卷，並已如前述，而查被告己○○以其係為辦理前往美國旅遊而將被告戊○○辦理，嗣被告戊○○以每本二萬元之代價販售予被告甲○○，惟被告戊○○迭次供述被告己○○並不知情，而被告江明哲於原審法院經通緝到案後即供認以每本二萬元之代價收購被告己○○及戊○○二人之於本院準備程序時供稱伊係於八十八年中秋節後，在戊○○的娘家嘉義縣番路鄉觸口村埔尾六十號跟戊○○談買他們夫妻二人的辦理戊○○就辦理他們夫妻二人之美國簽證，辦完簽證後，將領據交給伊，伊交給戊○○四萬元（見本院卷九十四年三月三日準備程序筆錄），而依卷內資料，並查無何證據足資認定被告己○○有參與本件安帶往美國在臺協會辦理簽證，惟被告己○○係自行保管領取美國簽證之憑據，此據被告己○○供明在卷（見原審卷（四）第一二一頁），而被告丙○○於本院準備程序時亦供稱伊僅係帶己○○到臺北辦理美國簽證，而己○○並未跟伊提起賣明若明知其辦理美國簽證係為便於出售其，，而被告丙○○並係依被告甲○○之指示帶同被告己○○前往美國在臺協會辦理簽證，衡情被告己○○於辦完簽證後理應將領取簽證之單據逕交予被告丙○○轉交被告甲○○，又何以由被告己○○交付被告戊○○，再行交付被告甲○○，是被告戊○○所供己○○之一併販售予甲○○等語，應屬事實，而被告己○○主觀上係認定因被告甲○○為招待渠等夫妻出國度蜜月，始因而將其竟以每本二萬元之代價販售予被告甲○○，惟並查無何證據足認被告己○○事先即知情並與被告戊○○謀議如何出售護照，並推由被告戊○○出面與被告甲○○接洽，是被告己○○所辯並未參與本件販賣犯罪尚屬不能證明，原審因而以不能證明被告己○○犯罪，而為被告己○○無罪之諭知，經核並無不合，檢察官上訴意旨以被告甲○○供承有以每本二萬元之代價收購被告戊○○及己○○之難認有理由，檢察官就被告己○○部分之上訴，應予駁回。據上論斷，應依刑事訴訟法第三百六十八條、第三百六十九條第一項前段、第三百六十四條、第二百九十九條第一項前段，條例第二十四條第三項，刑法第十一條前段、第二十八條、第五十六條、第二條第一項前段、第四十七條、第四十一條第一項、第四十二條第二項，罰金罰鍰提高標準條例第二條，判決如主文。本案經檢察官鄭富銘庭執行職務。中華民國94年4月8日臺灣高等法院刑事第八庭審判長法官吳敦法官沈宜生法官張傳栗以上正本證明與原本無異。如不服本判決，應於收受送達後十日內向本院提出上訴書狀，其未敘述上訴之理由者並得於提起上訴後十日內向本院補提理由書（均須按他造當事人之人數附繕本）。書記官秦慧榮中華民國94年4月11日附錄：本案論罪科刑法條全文護照條例第二十四條偽造、變造護照足以生損害於公眾或他人者，處五年以下有期徒刑，併科新臺幣五十萬元以下罰金。行使前項文書者，亦同。將護照交付他人或謊報遺失以供他人冒名使用者，處五年以下有期徒刑、拘役或科或併科新臺幣十萬元以下罰金。附表：┌───┬──────┬─────────┬───────┬──────┐│編號│出售護照者之│收購時間、地點│收購人│備註│││姓名、護照號││││││碼││││├───┼──────┼─────────┼───────┼──────┤│一│羅秀玉│八十九年六月間│甲○○│經換貼大陸女│││││丁○○│子陳敏霞照片│││一三０三二四│嘉義縣水上鄉市○街│丙○○│，由其冒名持│││二二六│十一號││用。│├───┼──────┼─────────┼───────┼──────┤│二│郭岳峰│同右│同右│與羅秀玉為夫││││││妻（起訴書誤│││Ｍ一五七七四│││載為詹秋純）│││九九九│││。│├───┼──────┼─────────┼───────┼──────┤│三│李金獅│八十九年八月初某日│丙○○│││││（起訴書誤載為同年│││││一三０五三八│七月下旬）│││││三七四│││││││嘉義市○○路某不詳││││││店名遊樂場│││├───┼──────┼─────────┼───────┼──────┤│四│吳雪聘│八十九年七月間│甲○○││││││││││一三０五一八│嘉義市○○路「維特│││││二六一│ＰＵＢ」│││├───┼──────┼─────────┼───────┼──────┤│五│李建益│八十九年七月底│甲○○│││││││││││嘉義市○○街三十九││││││號│││├───┼──────┼─────────┼───────┼──────┤│六│許采薇│八十九年七月間│甲○○││││（原名許淑媛││││││）│嘉義市○○路「維特││││││ＰＵＢ」│││││一三０五一一││││││七三０││││├───┼──────┼─────────┼───────┼──────┤│七│蔡嘉明│八十九年八月間（起│丙○○│於八十九年十││││訴書誤載為同年三││一月十六日在│││一三０四六四│、四）││甲○○位於嘉│││七五五│││義市○○路一││││嘉義市○○路「香格││一四號住處，││││里拉ＫＴＶ」││查獲換貼不詳││││││人士照片，載││││││有蔡嘉明基本││││││資料護照號碼││││││分別為一三０││││││四六四七五五││││││、一三０五三││││││八三七二（此││││││本護照並變造││││││出生年月日資││││││料為五十一年││││││三月二十七日││││││）之護照各一││││││本。│├───┼──────┼─────────┼───────┼──────┤│八│施明芳│八十九年五月間（起│丙○○│││││訴書誤載為同年三、│││││一三０一四三│四月間）│││││九二三│││││││嘉義市○○路「香格││││││里拉ＫＴＶ」│││├───┼──────┼─────────┼───────┼──────┤│九│戊○○│八十九年二月間│甲○○│與己○○為夫││││││妻││││嘉義縣水上鄉鎮││││││九十六號之二│││├───┼──────┼─────────┼───────┼──────┤│十│己○○│八十九年二月十九日│甲○○│與戊○○為夫││││││妻│││Ｍ一四二五八│嘉義縣水上鄉鎮│││││四七０│九十六號之二│││├───┼──────┼─────────┼───────┼──────┤│十一│蔡居安│八十九年七月間│丁○○││││││丙○○││││一三０五三八│嘉義市車店里附近│││││三七三││││├───┼──────┼─────────┼───────┼──────┤│十二│李瑪琍│八十九年七月間│丁○○││││││││││一三０一四０│台北市○○路○段一│││││二四四│三四巷七號「美國在││││││台協會台北辦事處」│││├───┼──────┼─────────┼───────┼──────┤│十三│陳美娟│八十九年七月間│丁○○││││││丙○○││││一三０四五八│台北市○○路○段一│││││五三二│三四巷七號「美國在││││││台協會台北辦事處」│││││││││├───┼──────┼─────────┼───────┼──────┤│十四│侯季萩│八十九年七月間│丁○○││││││丙○○││││一三０三三０│台北市○○路○段一│││││三一六│三四巷七號「美國在││││││台協會台北辦事處」│││├───┼──────┼─────────┼───────┼──────┤│十五│張惠茱│八十九年七月間│甲○○││││││丁○○││││一三０四六四│嘉義市○○路「維特│丙○○││││七五一│ＰＵＢ」│││├───┼──────┼─────────┼───────┼──────┤│十六│張惠婷│八十九年七月間│甲○○││││││丁○○││││一三０四六四│嘉義市○○路「維特│丙○○││││七四九│ＰＵＢ」│││├───┼──────┼─────────┼───────┼──────┤│十七│乙○○│八十九年六月間│甲○○││││││丁○○││││一三０一二四│嘉義市○○路旁│││││四八０││││├───┼──────┼─────────┼───────┼──────┤│十八│梁冬洋│八十九年七月間│丁○○││││││丙○○││││一三０三二七│嘉義市○○路「維特│││││一四二│ＰＵＢ」│││├───┼──────┼─────────┼───────┼──────┤│十九│詹秋純│八十九年六月中旬│丁○○││││││││││一三０三三０│嘉義市○○○路「俊│││││三一七│峰通訊行」│││├───┼──────┼─────────┼───────┼──────┤│二十│王嘉鈴│八十九年十一月間│丙○○│經換貼大陸女│││││丁○○│子董琴照片，│││一三０八五九│嘉義市「小鹿亂撞撞││由其冒名持用│││六二一│球場」││。│├───┼──────┼─────────┼───────┼──────┤│二十一│黃宇翔│八十九年十一月間│丙○○││││││丁○○││││一三０八五九│嘉義市「小鹿亂撞撞│││││六二三│球場」│││├───┼──────┼─────────┼───────┼──────┤│二十二│馮振華│八十九年十一月間│丙○○││││││丁○○││││一三０八五九│嘉義市「小鹿亂撞撞│││││六二四│球場」│││├───┼──────┼─────────┼───────┼──────┤│二十三│蘇昭蓉│八十九年十一月間│丙○○││││││丁○○││││一三０八五九│嘉義市「小鹿亂撞撞│││││六二二│球場」│││├───┼──────┼─────────┼───────┼──────┤│二十四│王木村│八十九年七月間│丁○○││││││││││一三０六０七│台北市○○路○段一│││││九０九│三四巷七號「美國在││││││台協會台北辦事處」│││└───┴──────┴─────────┴───────┴──────┘",
  "characters": {
    "judges": [
      "吳敦",
      "沈宜生",
      "張傳栗"
    ],
    "prosecutors": [

    ],
    "lawyers": [
      "洪榮彬",
      "陳麗玲"
    ],
    "clerks": [
      "秦慧榮"
    ],
    "plaintiffs": [

    ],
    "defendants": [
      "己○○"
    ],
    "prosecutor_office": [

    ],
    "creditors": [

    ],
    "debtors": [

    ],
    "judicial_associate_officer": [

    ]
  },
  "adjudged_at": "2005-04-08",
  "created_at": "2016-02-06 18:54:51",
  "updated_at": "2016-02-06 18:54:51"
}