{
  "identify": "TPD-98-消債核-4277-20110103-2",
  "court": {
    "name": "臺灣臺北地方法院",
    "code": "TPD"
  },
  "division": {
    "name": "民事",
    "code": "V"
  },
  "year": 98,
  "word": "消債核",
  "number": "4277",
  "jcheck": "2",
  "reason": "消債之前置協商認可事件",
  "content": "臺灣臺北地方法院民事裁定          98年度消債核字第4277號\n聲  請  人\n即債權人    臺灣銀行股份有限公司\n法定代理人  羅澤成\n聲  請  人\n即債權人    國泰世華商業銀行股份有限公司\n法定代理人  汪國華\n聲  請  人\n即債權人    美商花旗銀行股份有限公司\n法定代理人  利明\n聲  請  人\n即債權人    荷商荷蘭銀行股份有限公司台北分公司\n法定代理人  經天瑞\n聲  請  人\n即債權人    渣打國際商業銀行股份有限公司\n法定代理人  麥侃哲\n聲  請  人\n即債權人    玉山商業銀行股份有限公司\n法定代理人  黃永仁\n聲  請  人\n即債權人    台新國際商業銀行股份有限公司\n法定代理人  蔡孟\n聲  請  人\n即債權人    大眾商業銀行股份有限公司\n法定代理人  陳建平\n相  對  人\n即債務人    陳昆龍\n上列當事人間請求消債之前置協商認可事件事件，本院於民國\n九十八年二月二十七日所為之裁定，應裁定更正如下：\n    主  文\n原裁定當事人欄中關於「聲請人即債權人」之記載，應增列如本\n裁定當事人欄所示。\n    理  由\n一、按判決如有誤寫、誤算或其他類此之顯然錯誤者，法院得隨\n    時或依聲請以裁定更正之，民事訴訟法第232條第1項定有明\n    文。此於裁定亦準用之，同法第239條亦定有明文。\n二、查本院前開之裁定有如主文所示漏載之顯然錯誤，應予更正\n    。\n三、依首開規定裁定如主文。\n中    華    民    國   100    年    1     月    3     日\n                  民事第二庭    法  官  高偉文\n以上正本係照原本作成。\n如不服本裁定應於送達後10日內向本院提出抗告狀，並繳納抗告\n費新臺幣1,000元。\n中    華    民    國   100    年    1     月    3     日\n                                書記官  駱俊勳",
  "structure": {
    "main": "原裁定當事人欄中關於「聲請人即債權人」之記載，應增列如本\n裁定當事人欄所示。",
    "reason": "一、按判決如有誤寫、誤算或其他類此之顯然錯誤者，法院得隨\n    時或依聲請以裁定更正之，民事訴訟法第232條第1項定有明\n    文。此於裁定亦準用之，同法第239條亦定有明文。\n二、查本院前開之裁定有如主文所示漏載之顯然錯誤，應予更正\n    。\n三、依首開規定裁定如主文。"
  },
  "search": "臺灣臺北地方法院民事裁定98年度消債核字第4277號聲請人即債權人臺灣銀行股份有限公司法定代理人羅澤成聲請人即債權人國泰世華商業銀行股份有限公司法定代理人汪國華聲請人即債權人美商花旗銀行股份有限公司法定代理人利明聲請人即債權人荷商荷蘭銀行股份有限公司台北分公司法定代理人經天瑞聲請人即債權人渣打國際商業銀行股份有限公司法定代理人麥侃哲聲請人即債權人玉山商業銀行股份有限公司法定代理人黃永仁聲請人即債權人台新國際商業銀行股份有限公司法定代理人蔡孟聲請人即債權人大眾商業銀行股份有限公司法定代理人陳建平相對人即債務人陳昆龍上列當事人間請求消債之前置協商認可事件事件，本院於民國九十八年二月二十七日所為之裁定，應裁定更正如下：主文原裁定當事人欄中關於「聲請人即債權人」之記載，應增列如本裁定當事人欄所示。理由一、按判決如有誤寫、誤算或其他類此之顯然錯誤者，法院得隨時或依聲請以裁定更正之，民事訴訟法第232條第1項定有明文。此於裁定亦準用之，同法第239條亦定有明文。二、查本院前開之裁定有如主文所示漏載之顯然錯誤，應予更正。三、依首開規定裁定如主文。中華民國100年1月3日民事第二庭法官高偉文以上正本係照原本作成。如不服本裁定應於送達後10日內向本院提出抗告狀，並繳納抗告費新臺幣1,000元。中華民國100年1月3日書記官駱俊勳",
  "characters": {
    "judges": [
      "高偉文"
    ],
    "prosecutors": [

    ],
    "lawyers": [

    ],
    "clerks": [

    ],
    "plaintiffs": [

    ],
    "defendants": [

    ],
    "prosecutor_office": [

    ],
    "creditors": [
      "臺灣銀行股份有限公司",
      "國泰世華商業銀行股份有限公司",
      "美商花旗銀行股份有限公司",
      "荷商荷蘭銀行股份有限公司台北分公司",
      "渣打國際商業銀行股份有限公司",
      "玉山商業銀行股份有限公司",
      "台新國際商業銀行股份有限公司",
      "大眾商業銀行股份有限公司"
    ],
    "debtors": [

    ],
    "judicial_associate_officer": [

    ]
  },
  "adjudged_at": "2011-01-03",
  "created_at": "2016-02-13 04:26:11",
  "updated_at": "2016-02-13 04:26:11"
}