{
  "identify": "KLD-93-簡上-54-20050204-1",
  "court": {
    "name": "臺灣基隆地方法院",
    "code": "KLD"
  },
  "division": {
    "name": "刑事",
    "code": "M"
  },
  "year": 93,
  "word": "簡上",
  "number": "54",
  "jcheck": "1",
  "reason": "竊盜",
  "content": "臺灣基隆地方法院刑事判決              93年度簡上字第54號\n上  訴  人  臺灣基隆地方法院檢察署檢察官\n被      告  丙○○  男  37歲（民國56年4月26日生）\n                      址）\n輔佐人即被\n告之父      乙○    男  64歲（民國29年8月2日生）\n指定辯護人  蔡文玲律師\n右上訴人因被告竊盜案件，不服本院93年度基簡字第385 號中華\n民國93年5 月13日第一審簡易判決（聲請案號：93年度偵字第17\n16號）提起上訴，及2 次移送併案辦理（93年度偵字第2094號、\n93年度偵字第4227號），本院管轄之第二審合議庭判決如下：\n    主  文\n原判決撤銷。\n丙○○連續竊盜，處拘役貳拾日，如易科罰金以佰元折算壹日\n，緩刑年。\n    事  實\n一、丙○○為慢性精神分裂症病患，於民國90年4 月27日領有中\n    度精神病之身心障礙手冊，於下列行為時為精神耗弱人，意\n    圖為自己不法之所有，並基於概括之犯意，先後3 次為下列\n    竊盜行為：\n（一）於93年4 月25日上午6 時10分許，在基隆市○○區○○街\n      368 號前，徒手竊取戊○○所有之ㄇ型5 分鐵條24支（約\n      值新台幣「下同」3,600 元），得手後騎乘車號GHX ─05\n      5 號重機車將上開鐵條運離現場，嗣於同日上午7 時30分\n      許，為警在基隆市○○區○○街224 號前巡邏發現而查獲\n      （丙○○竊得之上開財物已發還被害人戊○○）。\n（二）於93年5 月11日上午4 、5 時許，在基隆市○○區○○路\n      185 巷3 號癈鐵回收廠大門口右邊無門禁之白鐵堆料區，\n      徒手竊取丁○○所有之白鐵製癈鐵窗（約值250 元），得\n      手將上開白鐵製癈鐵窗搬離現場，嗣於同日下午1 時許，\n      為警循線查獲（丙○○竊得之上開財物已發還被害人丁○\n      ○）。\n（三）於93年9 月22日凌晨2 時55分許，在基隆市○○區○○街\n      505 號前，徒手竊取甲○○所有放置於鐵桶內之不銹鋼鐵\n      片約重15公斤（約值500 元），得手後將不銹鋼鐵片裝入\n      麻袋內並放置於其騎乘其車號GHX ─055 號重機車腳踏墊\n      處，正欲離開之際，為巡邏之員警發覺有異，而當場查獲\n      （丙○○竊得之上開財物已發還被害人甲○○）。\n二、案經基隆市警察局第三分局報告臺灣基隆地方法院檢察署檢\n    察官偵查聲請簡易判決處刑。又案經基隆市警察局第三分局\n    2 次報告臺灣基隆地方法院檢察署檢察官先後移送併案審理\n    。\n    理  由\n一、右揭事實，業據被告丙○○於本院準備程序、審判時坦承不\n    諱，核與被害人戊○○、丁○○、甲○○於警詢時指述之情\n    節相符，且有被害人戊○○、丁○○、甲○○分別立具之贓\n    物認領保管收據、照片五張附卷可稽，被告之自白與事實相\n    符，可以採信，事證明確，被告犯行至堪認定，應依法論科\n    。\n二、核被告所為，係犯刑法第320 條第1 項之竊盜罪。被告先後\n    3 次竊盜犯行，時間緊接，所犯罪名相同，顯係出於概括之\n    犯意為之，為連續犯，應依刑法第56條之規定論以1 竊盜罪\n    ，並加重其刑。再查被告於93年4 月25日警訊時提出於90年\n    4 月27日領有之中度精神病身心障礙手冊影本（附於93年度\n    偵字第1716號偵查卷第14頁），被告之指定辯護人蔡文玲律\n    師對於被告行為時之情神狀態為何，向本院聲請將被告送鑑\n    定，本院乃將被告送請財團法人長庚紀念醫院基隆分院作精\n    神鑑定，鑑定結論認「周員為慢性精神分裂症病患，經精神\n    狀態檢查及心理測驗後確認周員之腦功能有輕度受損，其智\n    力、認知功能、現實感及判斷力稍顯缺失，目前的精神狀態\n    尚未達到心神喪失，但其慢性精神疾患確已導致周員的行為\n    能力受損，在進行鑑定當下及犯案當時呈現精神耗弱，僅有\n    部分行為能力。」此有該院精神鑑定報告書一份存卷可考，\n    是以，被告行為時確處於精神耗弱之狀態，堪可認定。被告\n    行為時既有精神耗弱之情形，應依刑法第19條第2 項之規定\n    減輕其刑，並先加後減之。原審以被告罪證明確，援引刑法\n    第320 條第1 項、第19條第2 項、第42條第2 項、罰金罰鍰\n    提高標準條例第1 條前段、第2 條，量處被告罰金1000元，\n    並諭知易服勞科之折算標準，固非無據，惟被告另犯事實欄\n    一（二）、（三）二部分之刑法第320 條第1 項竊盜犯行，\n    與原審認罪科刑部分有連續犯裁判上一罪之關係，應為聲請\n    簡易判決處刑效力所及，本應併予審理，惟原審未及斟酌此\n    點，容有未洽，檢察官持此提起上訴，指摘原審判決不當，\n    非無理由，自應由本院管轄之第二審合議庭將原審判決予以\n    撤銷改判。爰審酌被告為慢性精神分裂症病患、品行，犯罪\n    之動機、目的、手段、犯罪所生之損害、所得財物價值非高\n    及犯罪後坦承犯行等一切情狀，並參酌檢察官之求刑，量處\n    如主文所示之刑，並諭知易科罰金之折算標準，以示儆懲。\n    末查被告前未曾受有期徒刑以上刑之宣告，有臺灣基隆地方\n    法院檢察署刑案資料查註紀錄表及臺灣高等法院被告全國前\n    案紀錄表各1 份附卷可佐，被告犯罪後已深知悔悟，本院認\n    其經此教訓後，當知警惕，應無再犯之虞，因認其所宣告之\n    刑，以暫不執行為適當，併予宣告緩刑3 年，以勵來茲而啟\n    自新。\n據上論斷，應依刑事訴訟法第455 條之1 第3 項、第369 條第1\n項前段、第364 條、第299 條第1 項前段，刑法第56條、第320\n條第1 項、第19條第2 項、第41條第1 項前段、第74條第1 款，\n罰金罰鍰提高標準條例第1 條前段、第2 條，判決如主文。\n本案經檢察官黃鴻達到庭執行職務\n中    華    民    國    94    年    2     月    4     日\n                  刑事第三庭審判長法  官  鄭景文\n                                  法  官  曾雨明\n                                  法  官  王美婷\n以上正本證明與原本無異。\n不得上訴。\n中    華    民    國    94    年    2     月    4     日\n                                  書記官  陸清敏\n附錄論罪科刑依據之法條：\n刑法第320條第1 項：\n意圖為自己或第三人不法之所有，而竊取他人之動產者，為竊盜\n罪，處五年以下有期徒刑、拘役或五百元以下罰金。\n",
  "structure": {
    "main": "原判決撤銷。\n丙○○連續竊盜，處拘役貳拾日，如易科罰金以佰元折算壹日\n，緩刑年。",
    "fact": "一、丙○○為慢性精神分裂症病患，於民國90年4 月27日領有中\n    度精神病之身心障礙手冊，於下列行為時為精神耗弱人，意\n    圖為自己不法之所有，並基於概括之犯意，先後3 次為下列\n    竊盜行為：\n（一）於93年4 月25日上午6 時10分許，在基隆市○○區○○街\n      368 號前，徒手竊取戊○○所有之ㄇ型5 分鐵條24支（約\n      值新台幣「下同」3,600 元），得手後騎乘車號GHX ─05\n      5 號重機車將上開鐵條運離現場，嗣於同日上午7 時30分\n      許，為警在基隆市○○區○○街224 號前巡邏發現而查獲\n      （丙○○竊得之上開財物已發還被害人戊○○）。\n（二）於93年5 月11日上午4 、5 時許，在基隆市○○區○○路\n      185 巷3 號癈鐵回收廠大門口右邊無門禁之白鐵堆料區，\n      徒手竊取丁○○所有之白鐵製癈鐵窗（約值250 元），得\n      手將上開白鐵製癈鐵窗搬離現場，嗣於同日下午1 時許，\n      為警循線查獲（丙○○竊得之上開財物已發還被害人丁○\n      ○）。\n（三）於93年9 月22日凌晨2 時55分許，在基隆市○○區○○街\n      505 號前，徒手竊取甲○○所有放置於鐵桶內之不銹鋼鐵\n      片約重15公斤（約值500 元），得手後將不銹鋼鐵片裝入\n      麻袋內並放置於其騎乘其車號GHX ─055 號重機車腳踏墊\n      處，正欲離開之際，為巡邏之員警發覺有異，而當場查獲\n      （丙○○竊得之上開財物已發還被害人甲○○）。\n二、案經基隆市警察局第三分局報告臺灣基隆地方法院檢察署檢\n    察官偵查聲請簡易判決處刑。又案經基隆市警察局第三分局\n    2 次報告臺灣基隆地方法院檢察署檢察官先後移送併案審理\n    。",
    "reason": "一、右揭事實，業據被告丙○○於本院準備程序、審判時坦承不\n    諱，核與被害人戊○○、丁○○、甲○○於警詢時指述之情\n    節相符，且有被害人戊○○、丁○○、甲○○分別立具之贓\n    物認領保管收據、照片五張附卷可稽，被告之自白與事實相\n    符，可以採信，事證明確，被告犯行至堪認定，應依法論科\n    。\n二、核被告所為，係犯刑法第320 條第1 項之竊盜罪。被告先後\n    3 次竊盜犯行，時間緊接，所犯罪名相同，顯係出於概括之\n    犯意為之，為連續犯，應依刑法第56條之規定論以1 竊盜罪\n    ，並加重其刑。再查被告於93年4 月25日警訊時提出於90年\n    4 月27日領有之中度精神病身心障礙手冊影本（附於93年度\n    偵字第1716號偵查卷第14頁），被告之指定辯護人蔡文玲律\n    師對於被告行為時之情神狀態為何，向本院聲請將被告送鑑\n    定，本院乃將被告送請財團法人長庚紀念醫院基隆分院作精\n    神鑑定，鑑定結論認「周員為慢性精神分裂症病患，經精神\n    狀態檢查及心理測驗後確認周員之腦功能有輕度受損，其智\n    力、認知功能、現實感及判斷力稍顯缺失，目前的精神狀態\n    尚未達到心神喪失，但其慢性精神疾患確已導致周員的行為\n    能力受損，在進行鑑定當下及犯案當時呈現精神耗弱，僅有\n    部分行為能力。」此有該院精神鑑定報告書一份存卷可考，\n    是以，被告行為時確處於精神耗弱之狀態，堪可認定。被告\n    行為時既有精神耗弱之情形，應依刑法第19條第2 項之規定\n    減輕其刑，並先加後減之。原審以被告罪證明確，援引刑法\n    第320 條第1 項、第19條第2 項、第42條第2 項、罰金罰鍰\n    提高標準條例第1 條前段、第2 條，量處被告罰金1000元，\n    並諭知易服勞科之折算標準，固非無據，惟被告另犯事實欄\n    一（二）、（三）二部分之刑法第320 條第1 項竊盜犯行，\n    與原審認罪科刑部分有連續犯裁判上一罪之關係，應為聲請\n    簡易判決處刑效力所及，本應併予審理，惟原審未及斟酌此\n    點，容有未洽，檢察官持此提起上訴，指摘原審判決不當，\n    非無理由，自應由本院管轄之第二審合議庭將原審判決予以\n    撤銷改判。爰審酌被告為慢性精神分裂症病患、品行，犯罪\n    之動機、目的、手段、犯罪所生之損害、所得財物價值非高\n    及犯罪後坦承犯行等一切情狀，並參酌檢察官之求刑，量處\n    如主文所示之刑，並諭知易科罰金之折算標準，以示儆懲。\n    末查被告前未曾受有期徒刑以上刑之宣告，有臺灣基隆地方\n    法院檢察署刑案資料查註紀錄表及臺灣高等法院被告全國前\n    案紀錄表各1 份附卷可佐，被告犯罪後已深知悔悟，本院認\n    其經此教訓後，當知警惕，應無再犯之虞，因認其所宣告之\n    刑，以暫不執行為適當，併予宣告緩刑3 年，以勵來茲而啟\n    自新。\n據上論斷，應依刑事訴訟法第455 條之1 第3 項、第369 條第1\n項前段、第364 條、第299 條第1 項前段，刑法第56條、第320\n條第1 項、第19條第2 項、第41條第1 項前段、第74條第1 款，\n罰金罰鍰提高標準條例第1 條前段、第2 條，判決如主文。\n本案經檢察官黃鴻達到庭執行職務\n中    華    民    國    94    年    2     月    4     日\n                  刑事第三庭審判長法  官  鄭景文\n                                  法  官  曾雨明\n                                  法  官  王美婷\n以上正本證明與原本無異。\n不得上訴。"
  },
  "search": "臺灣基隆地方法院刑事判決93年度簡上字第54號上訴人臺灣基隆地方法院檢察署檢察官被告丙○○男37歲（民國56年4月26日生）址）輔佐人即被告之父乙○男64歲（民國29年8月2日生）指定辯護人蔡文玲律師右上訴人因被告竊盜案件，不服本院93年度基簡字第385號中華民國93年5月13日第一審簡易判決（聲請案號：93年度偵字第1716號）提起上訴，及2次移送併案辦理（93年度偵字第2094號、93年度偵字第4227號），本院管轄之第二審合議庭判決如下：主文原判決撤銷。丙○○連續竊盜，處拘役貳拾日，如易科罰金以佰元折算壹日，緩刑年。事實一、丙○○為慢性精神分裂症病患，於民國90年4月27日領有中度精神病之身心障礙手冊，於下列行為時為精神耗弱人，意圖為自己不法之所有，並基於概括之犯意，先後3次為下列竊盜行為：（一）於93年4月25日上午6時10分許，在基隆市○○區○○街368號前，徒手竊取戊○○所有之ㄇ型5分鐵條24支（約值新台幣「下同」3,600元），得手後騎乘車號GHX─055號重機車將上開鐵條運離現場，嗣於同日上午7時30分許，為警在基隆市○○區○○街224號前巡邏發現而查獲（丙○○竊得之上開財物已發還被害人戊○○）。（二）於93年5月11日上午4、5時許，在基隆市○○區○○路185巷3號癈鐵回收廠大門口右邊無門禁之白鐵堆料區，徒手竊取丁○○所有之白鐵製癈鐵窗（約值250元），得手將上開白鐵製癈鐵窗搬離現場，嗣於同日下午1時許，為警循線查獲（丙○○竊得之上開財物已發還被害人丁○○）。（三）於93年9月22日凌晨2時55分許，在基隆市○○區○○街505號前，徒手竊取甲○○所有放置於鐵桶內之不銹鋼鐵片約重15公斤（約值500元），得手後將不銹鋼鐵片裝入麻袋內並放置於其騎乘其車號GHX─055號重機車腳踏墊處，正欲離開之際，為巡邏之員警發覺有異，而當場查獲（丙○○竊得之上開財物已發還被害人甲○○）。二、案經基隆市警察局第三分局報告臺灣基隆地方法院檢察署檢察官偵查聲請簡易判決處刑。又案經基隆市警察局第三分局2次報告臺灣基隆地方法院檢察署檢察官先後移送併案審理。理由一、右揭事實，業據被告丙○○於本院準備程序、審判時坦承不諱，核與被害人戊○○、丁○○、甲○○於警詢時指述之情節相符，且有被害人戊○○、丁○○、甲○○分別立具之贓物認領保管收據、照片五張附卷可稽，被告之自白與事實相符，可以採信，事證明確，被告犯行至堪認定，應依法論科。二、核被告所為，係犯刑法第320條第1項之竊盜罪。被告先後3次竊盜犯行，時間緊接，所犯罪名相同，顯係出於概括之犯意為之，為連續犯，應依刑法第56條之規定論以1竊盜罪，並加重其刑。再查被告於93年4月25日警訊時提出於90年4月27日領有之中度精神病身心障礙手冊影本（附於93年度偵字第1716號偵查卷第14頁），被告之指定辯護人蔡文玲律師對於被告行為時之情神狀態為何，向本院聲請將被告送鑑定，本院乃將被告送請財團法人長庚紀念醫院基隆分院作精神鑑定，鑑定結論認「周員為慢性精神分裂症病患，經精神狀態檢查及心理測驗後確認周員之腦功能有輕度受損，其智力、認知功能、現實感及判斷力稍顯缺失，目前的精神狀態尚未達到心神喪失，但其慢性精神疾患確已導致周員的行為能力受損，在進行鑑定當下及犯案當時呈現精神耗弱，僅有部分行為能力。」此有該院精神鑑定報告書一份存卷可考，是以，被告行為時確處於精神耗弱之狀態，堪可認定。被告行為時既有精神耗弱之情形，應依刑法第19條第2項之規定減輕其刑，並先加後減之。原審以被告罪證明確，援引刑法第320條第1項、第19條第2項、第42條第2項、罰金罰鍰提高標準條例第1條前段、第2條，量處被告罰金1000元，並諭知易服勞科之折算標準，固非無據，惟被告另犯事實欄一（二）、（三）二部分之刑法第320條第1項竊盜犯行，與原審認罪科刑部分有連續犯裁判上一罪之關係，應為聲請簡易判決處刑效力所及，本應併予審理，惟原審未及斟酌此點，容有未洽，檢察官持此提起上訴，指摘原審判決不當，非無理由，自應由本院管轄之第二審合議庭將原審判決予以撤銷改判。爰審酌被告為慢性精神分裂症病患、品行，犯罪之動機、目的、手段、犯罪所生之損害、所得財物價值非高及犯罪後坦承犯行等一切情狀，並參酌檢察官之求刑，量處如主文所示之刑，並諭知易科罰金之折算標準，以示儆懲。末查被告前未曾受有期徒刑以上刑之宣告，有臺灣基隆地方法院檢察署刑案資料查註紀錄表及臺灣高等法院被告全國前案紀錄表各1份附卷可佐，被告犯罪後已深知悔悟，本院認其經此教訓後，當知警惕，應無再犯之虞，因認其所宣告之刑，以暫不執行為適當，併予宣告緩刑3年，以勵來茲而啟自新。據上論斷，應依刑事訴訟法第455條之1第3項、第369條第1項前段、第364條、第299條第1項前段，刑法第56條、第320條第1項、第19條第2項、第41條第1項前段、第74條第1款，罰金罰鍰提高標準條例第1條前段、第2條，判決如主文。本案經檢察官黃鴻達到庭執行職務中華民國94年2月4日刑事第三庭審判長法官鄭景文法官曾雨明法官王美婷以上正本證明與原本無異。不得上訴。中華民國94年2月4日書記官陸清敏附錄論罪科刑依據之法條：刑法第320條第1項：意圖為自己或第三人不法之所有，而竊取他人之動產者，為竊盜罪，處五年以下有期徒刑、拘役或五百元以下罰金。",
  "characters": {
    "judges": [
      "鄭景文",
      "曾雨明",
      "王美婷"
    ],
    "prosecutors": [
      "黃鴻達"
    ],
    "lawyers": [
      "蔡文玲"
    ],
    "clerks": [
      "陸清敏"
    ],
    "plaintiffs": [

    ],
    "defendants": [
      "丙○○  男  37歲（民國56年4月26日生）"
    ],
    "prosecutor_office": [

    ],
    "creditors": [

    ],
    "debtors": [

    ],
    "judicial_associate_officer": [

    ]
  },
  "adjudged_at": "2005-02-04",
  "created_at": "2016-02-06 16:52:50",
  "updated_at": "2016-02-06 16:52:50"
}