{
  "identify": "TPD-100-重訴-1-20110401-1",
  "court": {
    "name": "臺灣臺北地方法院",
    "code": "TPD"
  },
  "division": {
    "name": "刑事",
    "code": "M"
  },
  "year": 100,
  "word": "重訴",
  "number": "1",
  "jcheck": "1",
  "reason": "殺人",
  "content": "臺灣臺北地方法院刑事裁定              100年度重訴字第1號\n公  訴  人  臺灣臺北地方法院檢察署檢察官\n被      告  程浩威\n選任辯護人  陳長甫律師\n上列被告因殺人案件，本院裁定如下：\n    主  文\n程浩威自民國壹百年肆月柒日起延長羈押貳月。\n    理  由\n一、本件被告程浩威因殺人案件，前經本院訊問後認其所涉刑法\n    第271 條第1 項之殺人罪、同法第271 條第2 項、第1 項之\n    殺人未遂罪，犯罪嫌疑重大，所犯為最輕本刑十年以上有期\n    徒刑之重罪，且被告連續砍殺被害人四人，危害社會治安重\n    大，復於案發後有往南部逃避警方查緝之舉動，顯有逃亡之\n    虞，並有羈押之必要，爰依刑事訴訟法第101 條第1 項第1\n    款、第3 款規定，將被告於民國100 年1 月7 日羈押在案。\n二、茲本院以被告之羈押期間即將屆滿，且經本院訊問後認其羈\n    押事由仍然存在，且有繼續羈押之必要，故應自100 年4 月\n    7 日起延長羈押2 月。爰依刑事訴訟法第108 條第1 項、第\n    5 項規定，裁定如主文。\n中    華    民    國   100    年    4     月    1     日\n                  刑事第十六庭審判長法  官  吳俊龍\n                                    法  官  羅立德\n                                    法  官  葉藍鸚\n上正本證明與原本無異。\n如不服本裁定，應於送達後5日內向本院提出抗告狀。\n                                    書記官  劉俊源\n中    華    民    國   100    年    4     月    1     日",
  "structure": {
    "main": "程浩威自民國壹百年肆月柒日起延長羈押貳月。",
    "reason": "一、本件被告程浩威因殺人案件，前經本院訊問後認其所涉刑法\n    第271 條第1 項之殺人罪、同法第271 條第2 項、第1 項之\n    殺人未遂罪，犯罪嫌疑重大，所犯為最輕本刑十年以上有期\n    徒刑之重罪，且被告連續砍殺被害人四人，危害社會治安重\n    大，復於案發後有往南部逃避警方查緝之舉動，顯有逃亡之\n    虞，並有羈押之必要，爰依刑事訴訟法第101 條第1 項第1\n    款、第3 款規定，將被告於民國100 年1 月7 日羈押在案。\n二、茲本院以被告之羈押期間即將屆滿，且經本院訊問後認其羈\n    押事由仍然存在，且有繼續羈押之必要，故應自100 年4 月\n    7 日起延長羈押2 月。爰依刑事訴訟法第108 條第1 項、第\n    5 項規定，裁定如主文。"
  },
  "search": "臺灣臺北地方法院刑事裁定100年度重訴字第1號公訴人臺灣臺北地方法院檢察署檢察官被告程浩威選任辯護人陳長甫律師上列被告因殺人案件，本院裁定如下：主文程浩威自民國壹百年肆月柒日起延長羈押貳月。理由一、本件被告程浩威因殺人案件，前經本院訊問後認其所涉刑法第271條第1項之殺人罪、同法第271條第2項、第1項之殺人未遂罪，犯罪嫌疑重大，所犯為最輕本刑十年以上有期徒刑之重罪，且被告連續砍殺被害人四人，危害社會治安重大，復於案發後有往南部逃避警方查緝之舉動，顯有逃亡之虞，並有羈押之必要，爰依刑事訴訟法第101條第1項第1款、第3款規定，將被告於民國100年1月7日羈押在案。二、茲本院以被告之羈押期間即將屆滿，且經本院訊問後認其羈押事由仍然存在，且有繼續羈押之必要，故應自100年4月7日起延長羈押2月。爰依刑事訴訟法第108條第1項、第5項規定，裁定如主文。中華民國100年4月1日刑事第十六庭審判長法官吳俊龍法官羅立德法官葉藍鸚上正本證明與原本無異。如不服本裁定，應於送達後5日內向本院提出抗告狀。書記官劉俊源中華民國100年4月1日",
  "characters": {
    "judges": [
      "吳俊龍",
      "羅立德",
      "葉藍鸚"
    ],
    "prosecutors": [

    ],
    "lawyers": [
      "陳長甫"
    ],
    "clerks": [
      "劉俊源"
    ],
    "plaintiffs": [

    ],
    "defendants": [
      "程浩威"
    ],
    "prosecutor_office": [
      "臺灣臺北地方法院檢察署檢察官"
    ],
    "creditors": [

    ],
    "debtors": [

    ],
    "judicial_associate_officer": [

    ]
  },
  "adjudged_at": "2011-04-01",
  "created_at": "2016-02-12 09:57:00",
  "updated_at": "2016-02-12 09:57:00"
}