{
  "identify": "PTD-94-易-30-20050526-2",
  "court": {
    "name": "臺灣屏東地方法院",
    "code": "PTD"
  },
  "division": {
    "name": "刑事",
    "code": "M"
  },
  "year": 94,
  "word": "易",
  "number": "30",
  "jcheck": "2",
  "reason": "詐欺",
  "content": "臺灣屏東地方法院刑事判決                94年度易字第30號\n公  訴  人  臺灣屏東地方法院檢察署檢察官\n被      告  乙○○  男  25歲.\n上列被告因詐欺案件，經檢察官提起公訴（93年度偵字第6215號\n），本院裁定以簡式審判程序審理，判決如下：\n    主  文\n乙○○意圖為自己不法之所有，而侵占自己持有他人之物，處有\n期徒刑肆月，如易科罰金，以佰元折算壹日。\n    事  實\n一、乙○○係甲○○之堂弟，二人為鄰居，乙○○竟意圖為自己\n    不法之所有，本於侵占之犯意，於民國93年8 月24日，在屏\n    東縣萬丹鄉○○村○○路797 巷78號代收甲○○所申請之玉\n    山商業銀行股份有限公司（下稱玉山銀行）現金卡（帳號為\n    0000000000000 號）及密碼函後，予以侵占入己。\n二、乙○○侵占上開甲○○玉山銀行現金卡後，竟意圖為自己不\n    法之所有，本於利用不正方法由自動付款設備詐得財物之概\n    括犯意，持上開現金卡，於下列時地連續為詐欺行為：\n  (一)於93年8 月26日12時11分許，先至屏東市○○路43號中國信\n    託商業銀行股份有限公司永吉分行，以玉山銀行現金卡插入\n    自動提款機，並輸入該現金卡密碼之不正方法，詐領新台幣\n    （下同）20000 元。\n  (二)於同年月26日12時39分許，再至屏東縣萬丹鄉社口村43之1\n    號農民銀行社皮辦事處，持玉山銀行現金卡，以前述不正方\n    法，從該行自動提款機詐領19000 元。\n  (三)同年月29日16時許，至屏東縣萬丹鄉社口村43之1 號農民銀\n    行社皮辦事處，持玉山銀行現金卡，以前述不正方法，從該\n    行自動提款機詐領700 元。\n    共計以不正方法從自動提款機詐領現金39700 元。乙○○得\n    款後花用費失，並將上開現金卡丟棄於屏東縣萬丹鄉○○路\n    旁水溝內。嗣經甲○○遲未收到上開現金卡而以電話向玉山\n    銀行查詢，始知前開現金卡遭人詐領而報警處理，經警調取\n    農民銀行社皮辦事處提款機之提款畫面錄影帶，翻拍成照片\n    供甲○○指認，因而循線查獲。\n三、案經甲○○訴由屏東縣警察局屏東分局報請臺灣屏東地方法\n    院檢察署檢察官偵查起訴。\n      理  由\n一、上開犯罪事實，業據被告乙○○於警詢及本院審理時坦承不\n    諱，核與告訴人甲○○於警詢、偵查中指訴之情節相符，並\n    有玉山銀行綜存戶交易資料查詢單、萬丹郵局掛號郵件區段\n    投遞簽收清單各1 紙、自動櫃員機監視錄影帶翻拍照片4 幀\n    在卷可參，足見被告之自白與事實相符，堪予採信，本件事\n    證明確，被告犯行應可認定。\n二、核被告侵占告訴人甲○○所有之玉山銀行現金卡1 張之行為\n    ，係犯刑法第335 第1 項之普通侵占罪。被告上開以玉山銀\n    行現金卡從自動提款機詐領現金既遂之行為，則係犯刑法第\n    33 9條之2 第1 項之詐欺既遂罪。其先後於93年8 月26日及\n    同年月29日3 次以不正方法由自動付款設備詐欺取財既遂，\n    時間緊接，所犯罪名相同，顯係出於概括之犯意為之，為連\n    續犯，應依刑法第56條之規定以一罪論，並加重其刑。又被\n    告所犯普通侵占罪及以不正方法由自動付款設備詐欺取財既\n    遂罪間，有目的及手段之牽連關係，為牽連犯，應從一重之\n    以普通侵占罪處斷。爰審酌被告之素行（見前科表），冒用\n    他人現金卡，危害消費金融秩序，冒用之金額，犯後坦承犯\n    行，態度尚稱良好等一切情狀，量處如主文所示之刑，並諭\n    知易科罰金之折算標準。\n據上論斷，依刑事訴訟法第273 條之1 第1 項、第299 條第1 項\n前段，刑法第56條、第335 條第1 項、第339 條之2 第1 項、第\n41條第1 項前段，罰金罰鍰提高標準條例第1 條前段、第2 條，\n判決如主文。\n本案經檢察官黃莉琄到庭執行職務。\n中    華    民    國    94    年    5     月    26    日\n                  刑事第二庭    法  官  余德正\n以上正本證明與原本無異。\n如不服本判決應於收受本判決送達後十日內向本院提出上訴書狀，\n其未敘述上訴理由者，並得於提起上訴後十日內向本院補提理由\n書狀（均須按他造當事人之人數附繕本）「切勿逕送上級法院」\n                                書記官  潘美碧\n中    華    民    國    94    年    5     月    26    日\n附錄論罪科刑法條：\n刑法第335條第1 項\n意圖為自己或第三人不法之所有，而侵占自己持有他人之物者，\n處五年以下有期徒刑、拘役或科或併科一千元以下罰金。\n刑法第339條之2 第1 項\n意圖為自己或第三人不法之所有，以不正方法由自動付款設備取\n得他人之物者，處三年以下有期徒刑、拘役或一萬元以下罰金。\n",
  "structure": {
    "main": "乙○○意圖為自己不法之所有，而侵占自己持有他人之物，處有\n期徒刑肆月，如易科罰金，以佰元折算壹日。",
    "fact": "一、乙○○係甲○○之堂弟，二人為鄰居，乙○○竟意圖為自己\n    不法之所有，本於侵占之犯意，於民國93年8 月24日，在屏\n    東縣萬丹鄉○○村○○路797 巷78號代收甲○○所申請之玉\n    山商業銀行股份有限公司（下稱玉山銀行）現金卡（帳號為\n    0000000000000 號）及密碼函後，予以侵占入己。\n二、乙○○侵占上開甲○○玉山銀行現金卡後，竟意圖為自己不\n    法之所有，本於利用不正方法由自動付款設備詐得財物之概\n    括犯意，持上開現金卡，於下列時地連續為詐欺行為：\n  (一)於93年8 月26日12時11分許，先至屏東市○○路43號中國信\n    託商業銀行股份有限公司永吉分行，以玉山銀行現金卡插入\n    自動提款機，並輸入該現金卡密碼之不正方法，詐領新台幣\n    （下同）20000 元。\n  (二)於同年月26日12時39分許，再至屏東縣萬丹鄉社口村43之1\n    號農民銀行社皮辦事處，持玉山銀行現金卡，以前述不正方\n    法，從該行自動提款機詐領19000 元。\n  (三)同年月29日16時許，至屏東縣萬丹鄉社口村43之1 號農民銀\n    行社皮辦事處，持玉山銀行現金卡，以前述不正方法，從該\n    行自動提款機詐領700 元。\n    共計以不正方法從自動提款機詐領現金39700 元。乙○○得\n    款後花用費失，並將上開現金卡丟棄於屏東縣萬丹鄉○○路\n    旁水溝內。嗣經甲○○遲未收到上開現金卡而以電話向玉山\n    銀行查詢，始知前開現金卡遭人詐領而報警處理，經警調取\n    農民銀行社皮辦事處提款機之提款畫面錄影帶，翻拍成照片\n    供甲○○指認，因而循線查獲。\n三、案經甲○○訴由屏東縣警察局屏東分局報請臺灣屏東地方法\n    院檢察署檢察官偵查起訴。",
    "reason": "一、上開犯罪事實，業據被告乙○○於警詢及本院審理時坦承不\n    諱，核與告訴人甲○○於警詢、偵查中指訴之情節相符，並\n    有玉山銀行綜存戶交易資料查詢單、萬丹郵局掛號郵件區段\n    投遞簽收清單各1 紙、自動櫃員機監視錄影帶翻拍照片4 幀\n    在卷可參，足見被告之自白與事實相符，堪予採信，本件事\n    證明確，被告犯行應可認定。\n二、核被告侵占告訴人甲○○所有之玉山銀行現金卡1 張之行為\n    ，係犯刑法第335 第1 項之普通侵占罪。被告上開以玉山銀\n    行現金卡從自動提款機詐領現金既遂之行為，則係犯刑法第\n    33 9條之2 第1 項之詐欺既遂罪。其先後於93年8 月26日及\n    同年月29日3 次以不正方法由自動付款設備詐欺取財既遂，\n    時間緊接，所犯罪名相同，顯係出於概括之犯意為之，為連\n    續犯，應依刑法第56條之規定以一罪論，並加重其刑。又被\n    告所犯普通侵占罪及以不正方法由自動付款設備詐欺取財既\n    遂罪間，有目的及手段之牽連關係，為牽連犯，應從一重之\n    以普通侵占罪處斷。爰審酌被告之素行（見前科表），冒用\n    他人現金卡，危害消費金融秩序，冒用之金額，犯後坦承犯\n    行，態度尚稱良好等一切情狀，量處如主文所示之刑，並諭\n    知易科罰金之折算標準。\n據上論斷，依刑事訴訟法第273 條之1 第1 項、第299 條第1 項\n前段，刑法第56條、第335 條第1 項、第339 條之2 第1 項、第\n41條第1 項前段，罰金罰鍰提高標準條例第1 條前段、第2 條，\n判決如主文。\n本案經檢察官黃莉琄到庭執行職務。\n中    華    民    國    94    年    5     月    26    日\n                  刑事第二庭    法  官  余德正\n以上正本證明與原本無異。\n如不服本判決應於收受本判決送達後十日內向本院提出上訴書狀，\n其未敘述上訴理由者，並得於提起上訴後十日內向本院補提理由\n書狀（均須按他造當事人之人數附繕本）「切勿逕送上級法院」\n                                書記官  潘美碧"
  },
  "search": "臺灣屏東地方法院刑事判決94年度易字第30號公訴人臺灣屏東地方法院檢察署檢察官被告乙○○男25歲.上列被告因詐欺案件，經檢察官提起公訴（93年度偵字第6215號），本院裁定以簡式審判程序審理，判決如下：主文乙○○意圖為自己不法之所有，而侵占自己持有他人之物，處有期徒刑肆月，如易科罰金，以佰元折算壹日。事實一、乙○○係甲○○之堂弟，二人為鄰居，乙○○竟意圖為自己不法之所有，本於侵占之犯意，於民國93年8月24日，在屏東縣萬丹鄉○○村○○路797巷78號代收甲○○所申請之玉山商業銀行股份有限公司（下稱玉山銀行）現金卡（帳號為0000000000000號）及密碼函後，予以侵占入己。二、乙○○侵占上開甲○○玉山銀行現金卡後，竟意圖為自己不法之所有，本於利用不正方法由自動付款設備詐得財物之概括犯意，持上開現金卡，於下列時地連續為詐欺行為：(一)於93年8月26日12時11分許，先至屏東市○○路43號中國信託商業銀行股份有限公司永吉分行，以玉山銀行現金卡插入自動提款機，並輸入該現金卡密碼之不正方法，詐領新台幣（下同）20000元。(二)於同年月26日12時39分許，再至屏東縣萬丹鄉社口村43之1號農民銀行社皮辦事處，持玉山銀行現金卡，以前述不正方法，從該行自動提款機詐領19000元。(三)同年月29日16時許，至屏東縣萬丹鄉社口村43之1號農民銀行社皮辦事處，持玉山銀行現金卡，以前述不正方法，從該行自動提款機詐領700元。共計以不正方法從自動提款機詐領現金39700元。乙○○得款後花用費失，並將上開現金卡丟棄於屏東縣萬丹鄉○○路旁水溝內。嗣經甲○○遲未收到上開現金卡而以電話向玉山銀行查詢，始知前開現金卡遭人詐領而報警處理，經警調取農民銀行社皮辦事處提款機之提款畫面錄影帶，翻拍成照片供甲○○指認，因而循線查獲。三、案經甲○○訴由屏東縣警察局屏東分局報請臺灣屏東地方法院檢察署檢察官偵查起訴。理由一、上開犯罪事實，業據被告乙○○於警詢及本院審理時坦承不諱，核與告訴人甲○○於警詢、偵查中指訴之情節相符，並有玉山銀行綜存戶交易資料查詢單、萬丹郵局掛號郵件區段投遞簽收清單各1紙、自動櫃員機監視錄影帶翻拍照片4幀在卷可參，足見被告之自白與事實相符，堪予採信，本件事證明確，被告犯行應可認定。二、核被告侵占告訴人甲○○所有之玉山銀行現金卡1張之行為，係犯刑法第335第1項之普通侵占罪。被告上開以玉山銀行現金卡從自動提款機詐領現金既遂之行為，則係犯刑法第339條之2第1項之詐欺既遂罪。其先後於93年8月26日及同年月29日3次以不正方法由自動付款設備詐欺取財既遂，時間緊接，所犯罪名相同，顯係出於概括之犯意為之，為連續犯，應依刑法第56條之規定以一罪論，並加重其刑。又被告所犯普通侵占罪及以不正方法由自動付款設備詐欺取財既遂罪間，有目的及手段之牽連關係，為牽連犯，應從一重之以普通侵占罪處斷。爰審酌被告之素行（見前科表），冒用他人現金卡，危害消費金融秩序，冒用之金額，犯後坦承犯行，態度尚稱良好等一切情狀，量處如主文所示之刑，並諭知易科罰金之折算標準。據上論斷，依刑事訴訟法第273條之1第1項、第299條第1項前段，刑法第56條、第335條第1項、第339條之2第1項、第41條第1項前段，罰金罰鍰提高標準條例第1條前段、第2條，判決如主文。本案經檢察官黃莉琄到庭執行職務。中華民國94年5月26日刑事第二庭法官余德正以上正本證明與原本無異。如不服本判決應於收受本判決送達後十日內向本院提出上訴書狀，其未敘述上訴理由者，並得於提起上訴後十日內向本院補提理由書狀（均須按他造當事人之人數附繕本）「切勿逕送上級法院」書記官潘美碧中華民國94年5月26日附錄論罪科刑法條：刑法第335條第1項意圖為自己或第三人不法之所有，而侵占自己持有他人之物者，處五年以下有期徒刑、拘役或科或併科一千元以下罰金。刑法第339條之2第1項意圖為自己或第三人不法之所有，以不正方法由自動付款設備取得他人之物者，處三年以下有期徒刑、拘役或一萬元以下罰金。",
  "characters": {
    "judges": [
      "余德正"
    ],
    "prosecutors": [
      "黃莉琄"
    ],
    "lawyers": [

    ],
    "clerks": [
      "潘美碧"
    ],
    "plaintiffs": [

    ],
    "defendants": [
      "乙○○  男  25歲."
    ],
    "prosecutor_office": [
      "臺灣屏東地方法院檢察署檢察官"
    ],
    "creditors": [

    ],
    "debtors": [

    ],
    "judicial_associate_officer": [

    ]
  },
  "adjudged_at": "2005-05-26",
  "created_at": "2016-02-06 15:56:38",
  "updated_at": "2016-02-06 15:56:38"
}