{
  "identify": "SCD-94-竹交簡-767-20050920-1",
  "court": {
    "name": "臺灣新竹地方法院",
    "code": "SCD"
  },
  "division": {
    "name": "刑事",
    "code": "M"
  },
  "year": 94,
  "word": "竹交簡",
  "number": "767",
  "jcheck": "1",
  "reason": "公共危險",
  "content": "臺灣新竹地方法院刑事簡易判決       94年度竹交簡字第767號\n聲  請  人  臺灣新竹地方法院檢察署檢察官\n被      告  甲○○\n上列被告因公共危險案件，經檢察官聲請簡易判決處刑（94年度\n速偵字第1307號），本院判決如下：\n    主  文\n甲○○服用酒類，不能安全駕駛動力交通工具而駕駛，處拘役肆\n拾日，如易科罰金，以參佰元折算壹日。\n    事實及理由\n一、甲○○明知飲酒後駕車將導致其注意能力減低、反應能力變\n    慢，在此時仍駕車行駛於馬路上，隨時有致他人於死、傷之\n    危險，且道路交通管理處罰條例定有於飲酒後呼氣之酒精濃\n    度達每公升空氣含0點25毫克時即不得駕車之規定，竟仍於\n    民國94年8月19日13時許，在彰化縣某檳榔攤飲用維士比約\n    半瓶後，於同日13時30分許酒後（未達心神喪失或精神耗弱\n    之程度）不能安全駕駛動力交通工具之狀況下，猶自該處駕\n    駛山隆通運股份有限公司所有之車牌號碼FG－031號營業貨\n    運曳引車欲前往新竹市，迨於同日17時5分許，行經新竹市\n    ○○路、東西向快速道路口時，因飲酒過量而精神不集中，\n    判斷力、操控車輛之能力均不及於平時未飲酒時之狀況，轉\n    彎時車輛失控而翻覆。嗣經警據報前往處理，並於同日17時\n    8分許以酒精測定器當場測試其呼氣之酒精濃度，竟高達每\n    公升空氣含0點76毫克之濃度。\n二、證據：\n（一）被告於警詢、偵查中之供述（見偵查卷第6頁至第7頁、第\n      29頁）。\n（二）道路交通事故現場圖、道路交通事故調查報告表（一）、\n      （二）、新竹市警察局舉發違反道路交通管理事件通知單\n      、酒精濃度測試單、刑法第185條之3案件測試觀察紀錄表\n      、汽機車駕駛人酒後生理協調平衡檢測紀錄表各乙份及照\n      片6張在卷可稽（見偵查卷第8至10頁、第17頁至第23頁）\n      。\n（三）按對於酒精濃度呼氣已達每公升0點55毫克時，肇事率為\n      一般正常人之10倍，認已達不能安全駕駛之標準，有法務\n      部88年5月18日所發之88年度法檢字第001669號函1份在卷\n      足憑，而被告於員警測試時呼氣酒精濃度每公升高達0點7\n      6毫克，超過每公升0點55毫克之標準值甚高，有上開酒精\n      濃度測試單1紙足參，且經警當場對被告施作閉雙眼，30\n      秒內朗誦阿拉伯數字，由1001到1030之檢測結果不合格，\n      有前述汽車駕駛人酒後生理協調平衡檢測紀錄表可考。從\n      而，被告顯已達酒醉而不能安全駕駛之程度，堪予認定。\n三、核被告所為，係犯刑法第185條之3之服用酒類不能安全駕駛\n    動力交通工具而駕駛罪。爰審酌被告於服用酒類不能安全駕\n    駛動力交通工具之情形下，仍駕駛車身龐大之營業貨運曳引\n    車上路，對公眾行的安全已構成相當危害，參以其反應能力\n    減損之程度，如撞及其他用路人，後果殊難想像，而近年政\n    府行政部門迭經透過傳播媒體大力宣導酒醉後不得開車之政\n    令及法律知識，傳播媒體更時時透過影像、文字描繪傳達出\n    因酒醉後駕車所造成之用路人受傷、死亡及損害公共設施等\n    情形，被告為一有相當智識經驗之成年人，當能知曉酒醉後\n    駕車對所有用路人之安全有相當程度之危險性，竟不知戒慎\n    ；惟幸未造成其他人員傷亡等一切情狀，量處如主文所示之\n    刑，並諭知易科罰金之折算標準。\n四、據上論斷，應依刑事訴訟法第449條第1項前段，刑法第185\n    條之3、第41條第1項，罰金罰鍰提高標準條例第2條，逕以\n    簡易判決處如主文所示之刑。\n五、如不服本判決，得自收受送達之日起10日內，向本院提起上\n    訴。\n中    華    民    國    94    年    9     月    20    日\n                  新竹簡易庭    法  官  鄭子俊\n以上正本證明與原本無異。\n如不服本判決，應於判決送達後10日內向本院提出上訴狀。\n中    華    民    國    94    年    9     月    20    日\n                                書記官  沈藝珠\n附錄本院論罪科刑法條：\n刑法第185條之3\n服用毒品、麻醉藥品、酒類或其他相類似之物，不能安全駕駛動\n力交通工具而駕駛者，處一年以下有期徒刑、拘役或三萬元以下\n罰金。\n",
  "structure": {
    "main": "甲○○服用酒類，不能安全駕駛動力交通工具而駕駛，處拘役肆\n拾日，如易科罰金，以參佰元折算壹日。",
    "fact": "一、甲○○明知飲酒後駕車將導致其注意能力減低、反應能力變\n    慢，在此時仍駕車行駛於馬路上，隨時有致他人於死、傷之\n    危險，且道路交通管理處罰條例定有於飲酒後呼氣之酒精濃\n    度達每公升空氣含0點25毫克時即不得駕車之規定，竟仍於\n    民國94年8月19日13時許，在彰化縣某檳榔攤飲用維士比約\n    半瓶後，於同日13時30分許酒後（未達心神喪失或精神耗弱\n    之程度）不能安全駕駛動力交通工具之狀況下，猶自該處駕\n    駛山隆通運股份有限公司所有之車牌號碼FG－031號營業貨\n    運曳引車欲前往新竹市，迨於同日17時5分許，行經新竹市\n    ○○路、東西向快速道路口時，因飲酒過量而精神不集中，\n    判斷力、操控車輛之能力均不及於平時未飲酒時之狀況，轉\n    彎時車輛失控而翻覆。嗣經警據報前往處理，並於同日17時\n    8分許以酒精測定器當場測試其呼氣之酒精濃度，竟高達每\n    公升空氣含0點76毫克之濃度。\n二、證據：\n（一）被告於警詢、偵查中之供述（見偵查卷第6頁至第7頁、第\n      29頁）。\n（二）道路交通事故現場圖、道路交通事故調查報告表（一）、\n      （二）、新竹市警察局舉發違反道路交通管理事件通知單\n      、酒精濃度測試單、刑法第185條之3案件測試觀察紀錄表\n      、汽機車駕駛人酒後生理協調平衡檢測紀錄表各乙份及照\n      片6張在卷可稽（見偵查卷第8至10頁、第17頁至第23頁）\n      。\n（三）按對於酒精濃度呼氣已達每公升0點55毫克時，肇事率為\n      一般正常人之10倍，認已達不能安全駕駛之標準，有法務\n      部88年5月18日所發之88年度法檢字第001669號函1份在卷\n      足憑，而被告於員警測試時呼氣酒精濃度每公升高達0點7\n      6毫克，超過每公升0點55毫克之標準值甚高，有上開酒精\n      濃度測試單1紙足參，且經警當場對被告施作閉雙眼，30\n      秒內朗誦阿拉伯數字，由1001到1030之檢測結果不合格，\n      有前述汽車駕駛人酒後生理協調平衡檢測紀錄表可考。從\n      而，被告顯已達酒醉而不能安全駕駛之程度，堪予認定。\n三、核被告所為，係犯刑法第185條之3之服用酒類不能安全駕駛\n    動力交通工具而駕駛罪。爰審酌被告於服用酒類不能安全駕\n    駛動力交通工具之情形下，仍駕駛車身龐大之營業貨運曳引\n    車上路，對公眾行的安全已構成相當危害，參以其反應能力\n    減損之程度，如撞及其他用路人，後果殊難想像，而近年政\n    府行政部門迭經透過傳播媒體大力宣導酒醉後不得開車之政\n    令及法律知識，傳播媒體更時時透過影像、文字描繪傳達出\n    因酒醉後駕車所造成之用路人受傷、死亡及損害公共設施等\n    情形，被告為一有相當智識經驗之成年人，當能知曉酒醉後\n    駕車對所有用路人之安全有相當程度之危險性，竟不知戒慎\n    ；惟幸未造成其他人員傷亡等一切情狀，量處如主文所示之\n    刑，並諭知易科罰金之折算標準。\n四、據上論斷，應依刑事訴訟法第449條第1項前段，刑法第185\n    條之3、第41條第1項，罰金罰鍰提高標準條例第2條，逕以\n    簡易判決處如主文所示之刑。\n五、如不服本判決，得自收受送達之日起10日內，向本院提起上\n    訴。",
    "reason": "一、甲○○明知飲酒後駕車將導致其注意能力減低、反應能力變\n    慢，在此時仍駕車行駛於馬路上，隨時有致他人於死、傷之\n    危險，且道路交通管理處罰條例定有於飲酒後呼氣之酒精濃\n    度達每公升空氣含0點25毫克時即不得駕車之規定，竟仍於\n    民國94年8月19日13時許，在彰化縣某檳榔攤飲用維士比約\n    半瓶後，於同日13時30分許酒後（未達心神喪失或精神耗弱\n    之程度）不能安全駕駛動力交通工具之狀況下，猶自該處駕\n    駛山隆通運股份有限公司所有之車牌號碼FG－031號營業貨\n    運曳引車欲前往新竹市，迨於同日17時5分許，行經新竹市\n    ○○路、東西向快速道路口時，因飲酒過量而精神不集中，\n    判斷力、操控車輛之能力均不及於平時未飲酒時之狀況，轉\n    彎時車輛失控而翻覆。嗣經警據報前往處理，並於同日17時\n    8分許以酒精測定器當場測試其呼氣之酒精濃度，竟高達每\n    公升空氣含0點76毫克之濃度。\n二、證據：\n（一）被告於警詢、偵查中之供述（見偵查卷第6頁至第7頁、第\n      29頁）。\n（二）道路交通事故現場圖、道路交通事故調查報告表（一）、\n      （二）、新竹市警察局舉發違反道路交通管理事件通知單\n      、酒精濃度測試單、刑法第185條之3案件測試觀察紀錄表\n      、汽機車駕駛人酒後生理協調平衡檢測紀錄表各乙份及照\n      片6張在卷可稽（見偵查卷第8至10頁、第17頁至第23頁）\n      。\n（三）按對於酒精濃度呼氣已達每公升0點55毫克時，肇事率為\n      一般正常人之10倍，認已達不能安全駕駛之標準，有法務\n      部88年5月18日所發之88年度法檢字第001669號函1份在卷\n      足憑，而被告於員警測試時呼氣酒精濃度每公升高達0點7\n      6毫克，超過每公升0點55毫克之標準值甚高，有上開酒精\n      濃度測試單1紙足參，且經警當場對被告施作閉雙眼，30\n      秒內朗誦阿拉伯數字，由1001到1030之檢測結果不合格，\n      有前述汽車駕駛人酒後生理協調平衡檢測紀錄表可考。從\n      而，被告顯已達酒醉而不能安全駕駛之程度，堪予認定。\n三、核被告所為，係犯刑法第185條之3之服用酒類不能安全駕駛\n    動力交通工具而駕駛罪。爰審酌被告於服用酒類不能安全駕\n    駛動力交通工具之情形下，仍駕駛車身龐大之營業貨運曳引\n    車上路，對公眾行的安全已構成相當危害，參以其反應能力\n    減損之程度，如撞及其他用路人，後果殊難想像，而近年政\n    府行政部門迭經透過傳播媒體大力宣導酒醉後不得開車之政\n    令及法律知識，傳播媒體更時時透過影像、文字描繪傳達出\n    因酒醉後駕車所造成之用路人受傷、死亡及損害公共設施等\n    情形，被告為一有相當智識經驗之成年人，當能知曉酒醉後\n    駕車對所有用路人之安全有相當程度之危險性，竟不知戒慎\n    ；惟幸未造成其他人員傷亡等一切情狀，量處如主文所示之\n    刑，並諭知易科罰金之折算標準。\n四、據上論斷，應依刑事訴訟法第449條第1項前段，刑法第185\n    條之3、第41條第1項，罰金罰鍰提高標準條例第2條，逕以\n    簡易判決處如主文所示之刑。\n五、如不服本判決，得自收受送達之日起10日內，向本院提起上\n    訴。"
  },
  "search": "臺灣新竹地方法院刑事簡易判決94年度竹交簡字第767號聲請人臺灣新竹地方法院檢察署檢察官被告甲○○上列被告因公共危險案件，經檢察官聲請簡易判決處刑（94年度速偵字第1307號），本院判決如下：主文甲○○服用酒類，不能安全駕駛動力交通工具而駕駛，處拘役肆拾日，如易科罰金，以參佰元折算壹日。事實及理由一、甲○○明知飲酒後駕車將導致其注意能力減低、反應能力變慢，在此時仍駕車行駛於馬路上，隨時有致他人於死、傷之危險，且道路交通管理處罰條例定有於飲酒後呼氣之酒精濃度達每公升空氣含0點25毫克時即不得駕車之規定，竟仍於民國94年8月19日13時許，在彰化縣某檳榔攤飲用維士比約半瓶後，於同日13時30分許酒後（未達心神喪失或精神耗弱之程度）不能安全駕駛動力交通工具之狀況下，猶自該處駕駛山隆通運股份有限公司所有之車牌號碼FG－031號營業貨運曳引車欲前往新竹市，迨於同日17時5分許，行經新竹市○○路、東西向快速道路口時，因飲酒過量而精神不集中，判斷力、操控車輛之能力均不及於平時未飲酒時之狀況，轉彎時車輛失控而翻覆。嗣經警據報前往處理，並於同日17時8分許以酒精測定器當場測試其呼氣之酒精濃度，竟高達每公升空氣含0點76毫克之濃度。二、證據：（一）被告於警詢、偵查中之供述（見偵查卷第6頁至第7頁、第29頁）。（二）道路交通事故現場圖、道路交通事故調查報告表（一）、（二）、新竹市警察局舉發違反道路交通管理事件通知單、酒精濃度測試單、刑法第185條之3案件測試觀察紀錄表、汽機車駕駛人酒後生理協調平衡檢測紀錄表各乙份及照片6張在卷可稽（見偵查卷第8至10頁、第17頁至第23頁）。（三）按對於酒精濃度呼氣已達每公升0點55毫克時，肇事率為一般正常人之10倍，認已達不能安全駕駛之標準，有法務部88年5月18日所發之88年度法檢字第001669號函1份在卷足憑，而被告於員警測試時呼氣酒精濃度每公升高達0點76毫克，超過每公升0點55毫克之標準值甚高，有上開酒精濃度測試單1紙足參，且經警當場對被告施作閉雙眼，30秒內朗誦阿拉伯數字，由1001到1030之檢測結果不合格，有前述汽車駕駛人酒後生理協調平衡檢測紀錄表可考。從而，被告顯已達酒醉而不能安全駕駛之程度，堪予認定。三、核被告所為，係犯刑法第185條之3之服用酒類不能安全駕駛動力交通工具而駕駛罪。爰審酌被告於服用酒類不能安全駕駛動力交通工具之情形下，仍駕駛車身龐大之營業貨運曳引車上路，對公眾行的安全已構成相當危害，參以其反應能力減損之程度，如撞及其他用路人，後果殊難想像，而近年政府行政部門迭經透過傳播媒體大力宣導酒醉後不得開車之政令及法律知識，傳播媒體更時時透過影像、文字描繪傳達出因酒醉後駕車所造成之用路人受傷、死亡及損害公共設施等情形，被告為一有相當智識經驗之成年人，當能知曉酒醉後駕車對所有用路人之安全有相當程度之危險性，竟不知戒慎；惟幸未造成其他人員傷亡等一切情狀，量處如主文所示之刑，並諭知易科罰金之折算標準。四、據上論斷，應依刑事訴訟法第449條第1項前段，刑法第185條之3、第41條第1項，罰金罰鍰提高標準條例第2條，逕以簡易判決處如主文所示之刑。五、如不服本判決，得自收受送達之日起10日內，向本院提起上訴。中華民國94年9月20日新竹簡易庭法官鄭子俊以上正本證明與原本無異。如不服本判決，應於判決送達後10日內向本院提出上訴狀。中華民國94年9月20日書記官沈藝珠附錄本院論罪科刑法條：刑法第185條之3服用毒品、麻醉藥品、酒類或其他相類似之物，不能安全駕駛動力交通工具而駕駛者，處一年以下有期徒刑、拘役或三萬元以下罰金。",
  "characters": {
    "judges": [
      "鄭子俊"
    ],
    "prosecutors": [

    ],
    "lawyers": [

    ],
    "clerks": [
      "沈藝珠"
    ],
    "plaintiffs": [

    ],
    "defendants": [
      "甲○○"
    ],
    "prosecutor_office": [
      "臺灣新竹地方法院檢察署檢察官"
    ],
    "creditors": [

    ],
    "debtors": [

    ],
    "judicial_associate_officer": [

    ]
  },
  "adjudged_at": "2005-09-20",
  "created_at": "2016-02-06 20:33:47",
  "updated_at": "2016-02-06 20:33:47"
}