{
  "identify": "TCH-94-上易-288-20050920-1",
  "court": {
    "name": "臺灣高等法院",
    "code": "TCH"
  },
  "division": {
    "name": "民事",
    "code": "V"
  },
  "year": 94,
  "word": "上易",
  "number": "288",
  "jcheck": "1",
  "reason": "清償借款",
  "content": "臺灣高等法院臺中分院民事判決         94年度上易字第288號\n      上  訴  人  甲○○\n      被  上訴人  乙○○\n      訴訟代理人  黃耀南律師\n上列當事人間請求清償借款事件，上訴人對於中華民國94年6月6\n日臺灣彰化地方法院94年度訴字第160號第一審判決提起上訴，\n本院於94年9月6日言詞辯論終結，茲判決如下：\n    主      文\n上訴駁回。\n第二審訴訟費用由上訴人負擔。\n    事實及理由\n一、上訴人主張：伊於民國85年7月間，委託被上訴人代為收取\n    訴外人江文傑積欠伊之借款新臺幣（下同）150萬元，經江\n    文傑將借款匯入被上訴人帳戶後，伊於同月13日要求被上訴\n    人交付上開款項，被上訴人即簽發付款人為彰化市第六信用\n    合作社、票面金額150萬元、發票日85年3月30日、支票號碼\n    FA0000000號之支票交付予伊，嗣因被上訴人要求延期清償\n    ，再將系爭支票發票日塗改為85年8月23日，此有系爭更改\n    到期日並重新蓋章認證之支票、江文傑付款收據、匯入世華\n    聯合商業銀行彰化分行被上訴人0000000000-0帳號帳戶內之\n    入帳記錄等資料可證，即被上訴人於原審法院91年度字第43\n    6號清償借款事件審理中亦自承系爭支票為其向伊借款150萬\n    元所開無訛，僅以其已清償借款置辯而已，此有該案審判筆\n    錄可稽。而該件因兩造合意停止後，經原法院以視同撤回終\n    結，乃因伊不諳法律程序延誤所致，伊非有撤回訴訟之意。\n    被上訴人確已將所收款項存入世華聯合商業銀行彰化分行帳\n    號0000000000-0之帳戶內，被上訴人推說該筆款項轉借訴外\n    人陳永卿，惟查伊並未出具同意及委託書同意轉借，上訴人\n    所提出以抵償陳永卿欠款之房屋買賣契約書乃係出於偽造，\n    並非真實等情，爰依消費借貸之法律關係，提起本件訴訟，\n    求為命被上訴人給付伊150萬元元及自支付命令繕本送達翌\n    日起至清償日止按週年利率百分之五加計遲延利息之判決。\n二、被上訴人則以：(一)上訴人確曾委託伊代為收取江文傑積欠上\n    訴人之借款本金150萬元與利息11萬零250元，惟伊於85年7\n    月9日取得上開款項後，即經上訴人同意以其名義將其中150\n    萬元借貸予訴外人陳永卿，此經原法院86年度自字第136號\n    刑事判決、本院92年度重上更(二)字第270號刑事判決確定在\n    案，可見消費借貸之法律關係應係存在於上訴人與陳永卿之\n    間，與伊無涉。(二)又系爭支票係因伊仲介上訴人借貸上開15\n    0萬元予江文傑，始由伊簽發作為保證之用。且上訴人另於\n    91年3月4日、8 日，以系爭支票作為證據，主張伊於88年間\n    各向其借款50 萬元、150萬元為由，聲請核發支付命令，經\n    原法院分別核發91年度促字第5026號、91年度促字第5778號\n    支付命令後，伊聲明異議，否認兩造間存有消費借貸之法律\n    關係，復經原法院彰化簡易庭91年度彰簡字第196號、同院\n    91年度訴字第436號受理在案，並分別因上訴人當庭撤回訴\n    訟而終結。現上訴人再以系爭支票作為證據，主張伊於85年\n    間向上訴人借款150萬元，與聲請前開二件支付命令時所為\n    係於88年間向上訴人分別借款50萬元、150萬元時主張之借\n    貸原因、事實、時間，顯不相符。(三)上訴人具狀告訴伊涉嫌\n    侵占訴外人江文傑交付之150萬元及利息11萬零250元等情，\n    業經原法院86年偵字第3249號案檢察官為不起訴處分；嗣上\n    訴人改提自訴，亦經原法院以86年自訴字第136號案受理，\n    上訴人於該案審理中並未主張兩造係金錢借貸關係，並於該\n    案中自承系爭支票係以擔保伊仲介上訴人借款予江文傑之用\n    ，此有原法院該案86年9月25日訊問筆錄、86年11月4日訊問\n    筆錄、86年11月21日訊問筆錄可稽，而上訴人轉貸予江文傑\n    150萬元部分，業經上揭刑事判決認定係經上訴人同意再轉\n    借予信和建設公司之負責人陳永卿，而陳永卿未如期清償，\n    上訴人依法應向其求償，卻再三向伊請求清償借款，顯屬無\n    據。末查，關於於上訴附證三之建物謄本乙節，係因上訴人\n    事後毀約不同意以轉借予陳永卿150萬元當作訂金購買該屋\n    ，而訴外人陳永卿於89年10月5日將該屋移轉登記予他人名\n    義，乃謀貸款週轉之用，與上開事件無涉，亦與系爭支票借\n    款事件無關等語，資為抗辯。\n三、原審法院審理後，斟酌兩造之主張及攻擊防禦方法之結果，\n    認上訴人之訴為無理由，為其敗訴之判決，駁回上訴人在原\n    審之訴及假執行之聲請。上訴人不服，提起上訴，聲明求為\n    判決：(一)原判決廢棄；(二)被上訴人應給付伊150萬元及本件\n    支付命令繕本送達翌日起至清償日止按週年利率百分之五計\n    算之利息；(三)第一、二審訴訟費用均由被上訴人負擔。\n    被上訴人則答辯聲明求為判決駁回上訴人之上訴。\n四、兩造不爭執之事實：\n  (一)被上訴人曾簽發，付款人為彰化市第六信用合作社，票面金\n    額150萬元，發票日期為85年3月30日，支票號碼為0000000\n    號之支票予上訴人收執。\n  (二)上訴人曾委託被上訴人代為收取江文傑積欠上訴人之借款15\n    0萬元，江文傑已將借款本金150萬元與利息11萬零250元交\n    付予被上訴人。\n五、本件爭點：上訴人與被上訴人間是否因簽發交付系爭支票而\n    成立消費借貸契約，而使被上訴人應負150萬元之借款返還\n    義務。茲分析如下：\n  (一)按稱消費借貸者，謂當事人一方移轉金錢或其他代替物之所\n    有權於他方，而約定他方以種類、品質、數量相同之物返還\n    之契約，民法第474條第1項定有明文。次按，當事人主張有\n    金錢借貸關係存在，須就其發生所須具備之特別要件即金錢\n    之交付及借貸意思表示互相一致負舉證之責任，若僅證明有\n    金錢之交付，未證明借貸意思表示互相一致者，尚不能認為\n    有金錢借貸關係存在 (最高法院81年度台上字第2372號判決\n    意旨參照)；又支票為無因證券，簽發支票之原因實有多端\n    ，非必因借貸關係始簽發，故簽發支票交付他人提領尚不足\n    以證明與他人訂立借貸契約，貸款與他人而成立借貸關係。\n    最高法院86年度台上字第2031號判決亦明揭斯旨。而當事人\n    主張有利於己之事實，就其事實有舉證責任，民事訴訟法第\n    277條有明文規定。從而當事人如主張有金錢借貸關係存在\n    ，自須就已交付金錢及雙方借貸意思表示互相一致等有利於\n    己之事實，負舉證之責任。\n  (二)經查，本件上訴人係基於消費借貸之法律關係，訴請被上訴\n    人返還借款150萬元，則依上揭說明，上訴人應就該消費借\n    貸法律關係所須具備之要件，即消費借貸意思表示相互一致\n    ，以及交付150萬元兩項事實負舉證責任。本件被上訴人固\n    不爭執確曾受上訴人委託代為收取江文傑積欠上訴人之借款\n    150萬元，以及江文傑已將該借款本金與利息交付予被上訴\n    人之事實，然否認係基於兩造間具有消費借貸之法律關係存\n    在，故關於兩造間確有消費借貸意思表示相互一致之有利於\n    上訴人之事實，自仍應由上訴人負舉證責任。又，被上訴人\n    雖自承簽發系爭150萬元支票交付上訴人，惟辯稱：「系爭\n    支票係因伊仲介上訴人借貸上開150萬元予江文傑，始由伊\n    簽發作為保證之用」等語。此為上訴人於原法院上開刑事案\n    件審理時所自承（見原法院上開刑事卷宗第22、52頁）。按\n    簽發支票，非必因借貸關係始簽發，尚不足以證明與他人訂\n    立借貸契約，前已說明。且上訴人係於85年7月始委託被上\n    訴人代為收取江文傑積欠上訴人之借款，而系爭支票塗改前\n    之發票日則為85年3月30日，顯係於上訴人委託被上訴人代\n    為收取借款以前所簽發，則上訴人所主張伊於85年7月13日\n    要求被上訴人交付向江文傑所收取之借款時，被上訴人即簽\n    發系爭支票交付上訴人等語，即難憑採，被上訴人上開辯詞\n    ，應屬可信。依上訴人所提出台灣台中地方法院91年度訴字\n    第436號清償借款事件91年5月20日筆錄所示，被上訴人固先\n    稱系爭支票係其向上訴人借款150萬元所開無訛，然其隨即\n    更正陳述其乃經上訴人之同意，將受託向江文傑收取之150\n    萬元轉借給陳永卿，被告因而提起刑事訴訟等語，因之兩造\n    合意停止訴訟，以俟刑事案件之調查審認，以釐清其糾葛。\n    是依被上訴人一貫所辯，足見其就其上開錯誤之自認已為撤\n    銷更正。次查，就被上訴人更正陳述所陳相關刑事案件，為\n    上訴人前於86年4月7日具狀，以被上訴人受託代為收取江文\n    傑積欠伊之借款150萬元及利息11萬零250元後，將該款項侵\n    占為己有，並冒用伊之名義，與訴外人信和建設股份有限公\n    司偽簽預定房屋買賣契約書，涉犯侵占、偽造文書等罪嫌為\n    由，向臺灣彰化地方法院檢察署提出告訴，經該署以86年度\n    偵字第3249號受理在案；上訴人復於86年8月2日再以同一事\n    由，向原法院提起自訴，經該院以86年度自字第136號刑事\n    判決被上訴人無罪；上訴人不服該刑事判決復提起上訴，經\n    本院92年度重上更(二)字第270號刑事判決，於93年3月3日駁\n    回上訴人上訴並確定在案；此經本院調取上開刑事案件卷宗\n    ，核閱無訛。依上開刑事案件卷宗資料所示，上訴人於該刑\n    事案件將近7年之偵審期間，僅堅稱：被上訴人受託代為收\n    取江文傑積欠伊之借款150萬元及利息11萬零250元後，即將\n    該款項侵占為己有等語，並未主張兩造就該筆款項具有消費\n    借貸法律關係存在之情事，故兩造間是否確有消費借貸之法\n    律關係存在，已非無疑。況且，上訴人於85年9月11日、同\n    年10月21日，先後向被上訴人寄發彰化永安街郵局存證信函\n    第129號、第153號，其內容僅要求被上訴人將受託向江文傑\n    收取之借款交付予上訴人，全無兩造間曾就該筆款項成立消\n    費借貸法律關係之任何記載，此有存證信函影本可稽（見上\n    開偵查卷宗第4、5頁）。從而，上訴人所主張兩造間具有消\n    費借貸之法律關係存在等語，實難遽信。被上訴人另辯稱：\n    「伊受託代為收取江文傑積欠上訴人之借款後，係經上訴人\n    同意以上訴人之名義將其中150萬元借貸予陳永卿」等語，\n    此業經陳永卿及其會計曹馨方於上開刑事案件審理時證述明\n    確（見本院89年度上更(一)字第337號刑事卷宗第97、98、164\n    、166頁，本院92年度重上更(二)字第270號刑事卷宗第114、\n    12頁），自堪信為真實；此外，上訴人復未能提出其他證據\n    ，足資證明兩造間就系爭150萬元成立消費借貸之法律關係\n    確已意思表示相互一致。則被上訴人辯稱兩造間並無消費借\n    貸關係存在之陳述，應為可採。從而，上訴人基於消費借貸\n    之法律關係，請求被上訴人給付150萬元，及自支付命令繕\n    本送達被上訴人翌日起至清償日止，按週年利率5%計算之利\n    息，即無理由。\n  (三)綜上所述，本件上訴人主張基於消費借貸之法律關係，請求\n    被上訴人給付150萬元，及自支付命令繕本送達被告翌日起\n    至清償日止，按週年利率5%計算之利息，即無理由。原審因\n    而為被上訴人勝訴之判決，駁回上訴人在原審之訴及假執行\n    之聲請，依法並無不合。上訴意旨仍執陳詞，指摘原判決不\n    當，聲明求予廢棄改判，為無理由，應予駁回。\n六、兩造其餘攻擊防禦方法，經本院斟酌後，認為均不足以影響\n    本件判決結果，爰不一一論列，併此敘明。\n七、據上論結，本件上訴為無理由，依民事訴訟法第449條第1項\n    、第78條，判決如主文。\n中    華    民    國    94    年    9     月    20    日\n                      民事第五庭審判長法  官  陳滿賢\n                                      法  官  古金男\n                                      法  官  朱  樑\n以上正本係照原本作成。\n兩造均不得上訴。\n                                      書記官  陳俞豪\n中    華    民    國    94    年    9     月    22    日\n                                                      Ｈ\n",
  "structure": {
    "main": "上訴駁回。\n第二審訴訟費用由上訴人負擔。",
    "fact": "一、上訴人主張：伊於民國85年7月間，委託被上訴人代為收取\n    訴外人江文傑積欠伊之借款新臺幣（下同）150萬元，經江\n    文傑將借款匯入被上訴人帳戶後，伊於同月13日要求被上訴\n    人交付上開款項，被上訴人即簽發付款人為彰化市第六信用\n    合作社、票面金額150萬元、發票日85年3月30日、支票號碼\n    FA0000000號之支票交付予伊，嗣因被上訴人要求延期清償\n    ，再將系爭支票發票日塗改為85年8月23日，此有系爭更改\n    到期日並重新蓋章認證之支票、江文傑付款收據、匯入世華\n    聯合商業銀行彰化分行被上訴人0000000000-0帳號帳戶內之\n    入帳記錄等資料可證，即被上訴人於原審法院91年度字第43\n    6號清償借款事件審理中亦自承系爭支票為其向伊借款150萬\n    元所開無訛，僅以其已清償借款置辯而已，此有該案審判筆\n    錄可稽。而該件因兩造合意停止後，經原法院以視同撤回終\n    結，乃因伊不諳法律程序延誤所致，伊非有撤回訴訟之意。\n    被上訴人確已將所收款項存入世華聯合商業銀行彰化分行帳\n    號0000000000-0之帳戶內，被上訴人推說該筆款項轉借訴外\n    人陳永卿，惟查伊並未出具同意及委託書同意轉借，上訴人\n    所提出以抵償陳永卿欠款之房屋買賣契約書乃係出於偽造，\n    並非真實等情，爰依消費借貸之法律關係，提起本件訴訟，\n    求為命被上訴人給付伊150萬元元及自支付命令繕本送達翌\n    日起至清償日止按週年利率百分之五加計遲延利息之判決。\n二、被上訴人則以：(一)上訴人確曾委託伊代為收取江文傑積欠上\n    訴人之借款本金150萬元與利息11萬零250元，惟伊於85年7\n    月9日取得上開款項後，即經上訴人同意以其名義將其中150\n    萬元借貸予訴外人陳永卿，此經原法院86年度自字第136號\n    刑事判決、本院92年度重上更(二)字第270號刑事判決確定在\n    案，可見消費借貸之法律關係應係存在於上訴人與陳永卿之\n    間，與伊無涉。(二)又系爭支票係因伊仲介上訴人借貸上開15\n    0萬元予江文傑，始由伊簽發作為保證之用。且上訴人另於\n    91年3月4日、8 日，以系爭支票作為證據，主張伊於88年間\n    各向其借款50 萬元、150萬元為由，聲請核發支付命令，經\n    原法院分別核發91年度促字第5026號、91年度促字第5778號\n    支付命令後，伊聲明異議，否認兩造間存有消費借貸之法律\n    關係，復經原法院彰化簡易庭91年度彰簡字第196號、同院\n    91年度訴字第436號受理在案，並分別因上訴人當庭撤回訴\n    訟而終結。現上訴人再以系爭支票作為證據，主張伊於85年\n    間向上訴人借款150萬元，與聲請前開二件支付命令時所為\n    係於88年間向上訴人分別借款50萬元、150萬元時主張之借\n    貸原因、事實、時間，顯不相符。(三)上訴人具狀告訴伊涉嫌\n    侵占訴外人江文傑交付之150萬元及利息11萬零250元等情，\n    業經原法院86年偵字第3249號案檢察官為不起訴處分；嗣上\n    訴人改提自訴，亦經原法院以86年自訴字第136號案受理，\n    上訴人於該案審理中並未主張兩造係金錢借貸關係，並於該\n    案中自承系爭支票係以擔保伊仲介上訴人借款予江文傑之用\n    ，此有原法院該案86年9月25日訊問筆錄、86年11月4日訊問\n    筆錄、86年11月21日訊問筆錄可稽，而上訴人轉貸予江文傑\n    150萬元部分，業經上揭刑事判決認定係經上訴人同意再轉\n    借予信和建設公司之負責人陳永卿，而陳永卿未如期清償，\n    上訴人依法應向其求償，卻再三向伊請求清償借款，顯屬無\n    據。末查，關於於上訴附證三之建物謄本乙節，係因上訴人\n    事後毀約不同意以轉借予陳永卿150萬元當作訂金購買該屋\n    ，而訴外人陳永卿於89年10月5日將該屋移轉登記予他人名\n    義，乃謀貸款週轉之用，與上開事件無涉，亦與系爭支票借\n    款事件無關等語，資為抗辯。\n三、原審法院審理後，斟酌兩造之主張及攻擊防禦方法之結果，\n    認上訴人之訴為無理由，為其敗訴之判決，駁回上訴人在原\n    審之訴及假執行之聲請。上訴人不服，提起上訴，聲明求為\n    判決：(一)原判決廢棄；(二)被上訴人應給付伊150萬元及本件\n    支付命令繕本送達翌日起至清償日止按週年利率百分之五計\n    算之利息；(三)第一、二審訴訟費用均由被上訴人負擔。\n    被上訴人則答辯聲明求為判決駁回上訴人之上訴。\n四、兩造不爭執之事實：\n  (一)被上訴人曾簽發，付款人為彰化市第六信用合作社，票面金\n    額150萬元，發票日期為85年3月30日，支票號碼為0000000\n    號之支票予上訴人收執。\n  (二)上訴人曾委託被上訴人代為收取江文傑積欠上訴人之借款15\n    0萬元，江文傑已將借款本金150萬元與利息11萬零250元交\n    付予被上訴人。\n五、本件爭點：上訴人與被上訴人間是否因簽發交付系爭支票而\n    成立消費借貸契約，而使被上訴人應負150萬元之借款返還\n    義務。茲分析如下：\n  (一)按稱消費借貸者，謂當事人一方移轉金錢或其他代替物之所\n    有權於他方，而約定他方以種類、品質、數量相同之物返還\n    之契約，民法第474條第1項定有明文。次按，當事人主張有\n    金錢借貸關係存在，須就其發生所須具備之特別要件即金錢\n    之交付及借貸意思表示互相一致負舉證之責任，若僅證明有\n    金錢之交付，未證明借貸意思表示互相一致者，尚不能認為\n    有金錢借貸關係存在 (最高法院81年度台上字第2372號判決\n    意旨參照)；又支票為無因證券，簽發支票之原因實有多端\n    ，非必因借貸關係始簽發，故簽發支票交付他人提領尚不足\n    以證明與他人訂立借貸契約，貸款與他人而成立借貸關係。\n    最高法院86年度台上字第2031號判決亦明揭斯旨。而當事人\n    主張有利於己之事實，就其事實有舉證責任，民事訴訟法第\n    277條有明文規定。從而當事人如主張有金錢借貸關係存在\n    ，自須就已交付金錢及雙方借貸意思表示互相一致等有利於\n    己之事實，負舉證之責任。\n  (二)經查，本件上訴人係基於消費借貸之法律關係，訴請被上訴\n    人返還借款150萬元，則依上揭說明，上訴人應就該消費借\n    貸法律關係所須具備之要件，即消費借貸意思表示相互一致\n    ，以及交付150萬元兩項事實負舉證責任。本件被上訴人固\n    不爭執確曾受上訴人委託代為收取江文傑積欠上訴人之借款\n    150萬元，以及江文傑已將該借款本金與利息交付予被上訴\n    人之事實，然否認係基於兩造間具有消費借貸之法律關係存\n    在，故關於兩造間確有消費借貸意思表示相互一致之有利於\n    上訴人之事實，自仍應由上訴人負舉證責任。又，被上訴人\n    雖自承簽發系爭150萬元支票交付上訴人，惟辯稱：「系爭\n    支票係因伊仲介上訴人借貸上開150萬元予江文傑，始由伊\n    簽發作為保證之用」等語。此為上訴人於原法院上開刑事案\n    件審理時所自承（見原法院上開刑事卷宗第22、52頁）。按\n    簽發支票，非必因借貸關係始簽發，尚不足以證明與他人訂\n    立借貸契約，前已說明。且上訴人係於85年7月始委託被上\n    訴人代為收取江文傑積欠上訴人之借款，而系爭支票塗改前\n    之發票日則為85年3月30日，顯係於上訴人委託被上訴人代\n    為收取借款以前所簽發，則上訴人所主張伊於85年7月13日\n    要求被上訴人交付向江文傑所收取之借款時，被上訴人即簽\n    發系爭支票交付上訴人等語，即難憑採，被上訴人上開辯詞\n    ，應屬可信。依上訴人所提出台灣台中地方法院91年度訴字\n    第436號清償借款事件91年5月20日筆錄所示，被上訴人固先\n    稱系爭支票係其向上訴人借款150萬元所開無訛，然其隨即\n    更正陳述其乃經上訴人之同意，將受託向江文傑收取之150\n    萬元轉借給陳永卿，被告因而提起刑事訴訟等語，因之兩造\n    合意停止訴訟，以俟刑事案件之調查審認，以釐清其糾葛。\n    是依被上訴人一貫所辯，足見其就其上開錯誤之自認已為撤\n    銷更正。次查，就被上訴人更正陳述所陳相關刑事案件，為\n    上訴人前於86年4月7日具狀，以被上訴人受託代為收取江文\n    傑積欠伊之借款150萬元及利息11萬零250元後，將該款項侵\n    占為己有，並冒用伊之名義，與訴外人信和建設股份有限公\n    司偽簽預定房屋買賣契約書，涉犯侵占、偽造文書等罪嫌為\n    由，向臺灣彰化地方法院檢察署提出告訴，經該署以86年度\n    偵字第3249號受理在案；上訴人復於86年8月2日再以同一事\n    由，向原法院提起自訴，經該院以86年度自字第136號刑事\n    判決被上訴人無罪；上訴人不服該刑事判決復提起上訴，經\n    本院92年度重上更(二)字第270號刑事判決，於93年3月3日駁\n    回上訴人上訴並確定在案；此經本院調取上開刑事案件卷宗\n    ，核閱無訛。依上開刑事案件卷宗資料所示，上訴人於該刑\n    事案件將近7年之偵審期間，僅堅稱：被上訴人受託代為收\n    取江文傑積欠伊之借款150萬元及利息11萬零250元後，即將\n    該款項侵占為己有等語，並未主張兩造就該筆款項具有消費\n    借貸法律關係存在之情事，故兩造間是否確有消費借貸之法\n    律關係存在，已非無疑。況且，上訴人於85年9月11日、同\n    年10月21日，先後向被上訴人寄發彰化永安街郵局存證信函\n    第129號、第153號，其內容僅要求被上訴人將受託向江文傑\n    收取之借款交付予上訴人，全無兩造間曾就該筆款項成立消\n    費借貸法律關係之任何記載，此有存證信函影本可稽（見上\n    開偵查卷宗第4、5頁）。從而，上訴人所主張兩造間具有消\n    費借貸之法律關係存在等語，實難遽信。被上訴人另辯稱：\n    「伊受託代為收取江文傑積欠上訴人之借款後，係經上訴人\n    同意以上訴人之名義將其中150萬元借貸予陳永卿」等語，\n    此業經陳永卿及其會計曹馨方於上開刑事案件審理時證述明\n    確（見本院89年度上更(一)字第337號刑事卷宗第97、98、164\n    、166頁，本院92年度重上更(二)字第270號刑事卷宗第114、\n    12頁），自堪信為真實；此外，上訴人復未能提出其他證據\n    ，足資證明兩造間就系爭150萬元成立消費借貸之法律關係\n    確已意思表示相互一致。則被上訴人辯稱兩造間並無消費借\n    貸關係存在之陳述，應為可採。從而，上訴人基於消費借貸\n    之法律關係，請求被上訴人給付150萬元，及自支付命令繕\n    本送達被上訴人翌日起至清償日止，按週年利率5%計算之利\n    息，即無理由。\n  (三)綜上所述，本件上訴人主張基於消費借貸之法律關係，請求\n    被上訴人給付150萬元，及自支付命令繕本送達被告翌日起\n    至清償日止，按週年利率5%計算之利息，即無理由。原審因\n    而為被上訴人勝訴之判決，駁回上訴人在原審之訴及假執行\n    之聲請，依法並無不合。上訴意旨仍執陳詞，指摘原判決不\n    當，聲明求予廢棄改判，為無理由，應予駁回。\n六、兩造其餘攻擊防禦方法，經本院斟酌後，認為均不足以影響\n    本件判決結果，爰不一一論列，併此敘明。\n七、據上論結，本件上訴為無理由，依民事訴訟法第449條第1項\n    、第78條，判決如主文。",
    "reason": "一、上訴人主張：伊於民國85年7月間，委託被上訴人代為收取\n    訴外人江文傑積欠伊之借款新臺幣（下同）150萬元，經江\n    文傑將借款匯入被上訴人帳戶後，伊於同月13日要求被上訴\n    人交付上開款項，被上訴人即簽發付款人為彰化市第六信用\n    合作社、票面金額150萬元、發票日85年3月30日、支票號碼\n    FA0000000號之支票交付予伊，嗣因被上訴人要求延期清償\n    ，再將系爭支票發票日塗改為85年8月23日，此有系爭更改\n    到期日並重新蓋章認證之支票、江文傑付款收據、匯入世華\n    聯合商業銀行彰化分行被上訴人0000000000-0帳號帳戶內之\n    入帳記錄等資料可證，即被上訴人於原審法院91年度字第43\n    6號清償借款事件審理中亦自承系爭支票為其向伊借款150萬\n    元所開無訛，僅以其已清償借款置辯而已，此有該案審判筆\n    錄可稽。而該件因兩造合意停止後，經原法院以視同撤回終\n    結，乃因伊不諳法律程序延誤所致，伊非有撤回訴訟之意。\n    被上訴人確已將所收款項存入世華聯合商業銀行彰化分行帳\n    號0000000000-0之帳戶內，被上訴人推說該筆款項轉借訴外\n    人陳永卿，惟查伊並未出具同意及委託書同意轉借，上訴人\n    所提出以抵償陳永卿欠款之房屋買賣契約書乃係出於偽造，\n    並非真實等情，爰依消費借貸之法律關係，提起本件訴訟，\n    求為命被上訴人給付伊150萬元元及自支付命令繕本送達翌\n    日起至清償日止按週年利率百分之五加計遲延利息之判決。\n二、被上訴人則以：(一)上訴人確曾委託伊代為收取江文傑積欠上\n    訴人之借款本金150萬元與利息11萬零250元，惟伊於85年7\n    月9日取得上開款項後，即經上訴人同意以其名義將其中150\n    萬元借貸予訴外人陳永卿，此經原法院86年度自字第136號\n    刑事判決、本院92年度重上更(二)字第270號刑事判決確定在\n    案，可見消費借貸之法律關係應係存在於上訴人與陳永卿之\n    間，與伊無涉。(二)又系爭支票係因伊仲介上訴人借貸上開15\n    0萬元予江文傑，始由伊簽發作為保證之用。且上訴人另於\n    91年3月4日、8 日，以系爭支票作為證據，主張伊於88年間\n    各向其借款50 萬元、150萬元為由，聲請核發支付命令，經\n    原法院分別核發91年度促字第5026號、91年度促字第5778號\n    支付命令後，伊聲明異議，否認兩造間存有消費借貸之法律\n    關係，復經原法院彰化簡易庭91年度彰簡字第196號、同院\n    91年度訴字第436號受理在案，並分別因上訴人當庭撤回訴\n    訟而終結。現上訴人再以系爭支票作為證據，主張伊於85年\n    間向上訴人借款150萬元，與聲請前開二件支付命令時所為\n    係於88年間向上訴人分別借款50萬元、150萬元時主張之借\n    貸原因、事實、時間，顯不相符。(三)上訴人具狀告訴伊涉嫌\n    侵占訴外人江文傑交付之150萬元及利息11萬零250元等情，\n    業經原法院86年偵字第3249號案檢察官為不起訴處分；嗣上\n    訴人改提自訴，亦經原法院以86年自訴字第136號案受理，\n    上訴人於該案審理中並未主張兩造係金錢借貸關係，並於該\n    案中自承系爭支票係以擔保伊仲介上訴人借款予江文傑之用\n    ，此有原法院該案86年9月25日訊問筆錄、86年11月4日訊問\n    筆錄、86年11月21日訊問筆錄可稽，而上訴人轉貸予江文傑\n    150萬元部分，業經上揭刑事判決認定係經上訴人同意再轉\n    借予信和建設公司之負責人陳永卿，而陳永卿未如期清償，\n    上訴人依法應向其求償，卻再三向伊請求清償借款，顯屬無\n    據。末查，關於於上訴附證三之建物謄本乙節，係因上訴人\n    事後毀約不同意以轉借予陳永卿150萬元當作訂金購買該屋\n    ，而訴外人陳永卿於89年10月5日將該屋移轉登記予他人名\n    義，乃謀貸款週轉之用，與上開事件無涉，亦與系爭支票借\n    款事件無關等語，資為抗辯。\n三、原審法院審理後，斟酌兩造之主張及攻擊防禦方法之結果，\n    認上訴人之訴為無理由，為其敗訴之判決，駁回上訴人在原\n    審之訴及假執行之聲請。上訴人不服，提起上訴，聲明求為\n    判決：(一)原判決廢棄；(二)被上訴人應給付伊150萬元及本件\n    支付命令繕本送達翌日起至清償日止按週年利率百分之五計\n    算之利息；(三)第一、二審訴訟費用均由被上訴人負擔。\n    被上訴人則答辯聲明求為判決駁回上訴人之上訴。\n四、兩造不爭執之事實：\n  (一)被上訴人曾簽發，付款人為彰化市第六信用合作社，票面金\n    額150萬元，發票日期為85年3月30日，支票號碼為0000000\n    號之支票予上訴人收執。\n  (二)上訴人曾委託被上訴人代為收取江文傑積欠上訴人之借款15\n    0萬元，江文傑已將借款本金150萬元與利息11萬零250元交\n    付予被上訴人。\n五、本件爭點：上訴人與被上訴人間是否因簽發交付系爭支票而\n    成立消費借貸契約，而使被上訴人應負150萬元之借款返還\n    義務。茲分析如下：\n  (一)按稱消費借貸者，謂當事人一方移轉金錢或其他代替物之所\n    有權於他方，而約定他方以種類、品質、數量相同之物返還\n    之契約，民法第474條第1項定有明文。次按，當事人主張有\n    金錢借貸關係存在，須就其發生所須具備之特別要件即金錢\n    之交付及借貸意思表示互相一致負舉證之責任，若僅證明有\n    金錢之交付，未證明借貸意思表示互相一致者，尚不能認為\n    有金錢借貸關係存在 (最高法院81年度台上字第2372號判決\n    意旨參照)；又支票為無因證券，簽發支票之原因實有多端\n    ，非必因借貸關係始簽發，故簽發支票交付他人提領尚不足\n    以證明與他人訂立借貸契約，貸款與他人而成立借貸關係。\n    最高法院86年度台上字第2031號判決亦明揭斯旨。而當事人\n    主張有利於己之事實，就其事實有舉證責任，民事訴訟法第\n    277條有明文規定。從而當事人如主張有金錢借貸關係存在\n    ，自須就已交付金錢及雙方借貸意思表示互相一致等有利於\n    己之事實，負舉證之責任。\n  (二)經查，本件上訴人係基於消費借貸之法律關係，訴請被上訴\n    人返還借款150萬元，則依上揭說明，上訴人應就該消費借\n    貸法律關係所須具備之要件，即消費借貸意思表示相互一致\n    ，以及交付150萬元兩項事實負舉證責任。本件被上訴人固\n    不爭執確曾受上訴人委託代為收取江文傑積欠上訴人之借款\n    150萬元，以及江文傑已將該借款本金與利息交付予被上訴\n    人之事實，然否認係基於兩造間具有消費借貸之法律關係存\n    在，故關於兩造間確有消費借貸意思表示相互一致之有利於\n    上訴人之事實，自仍應由上訴人負舉證責任。又，被上訴人\n    雖自承簽發系爭150萬元支票交付上訴人，惟辯稱：「系爭\n    支票係因伊仲介上訴人借貸上開150萬元予江文傑，始由伊\n    簽發作為保證之用」等語。此為上訴人於原法院上開刑事案\n    件審理時所自承（見原法院上開刑事卷宗第22、52頁）。按\n    簽發支票，非必因借貸關係始簽發，尚不足以證明與他人訂\n    立借貸契約，前已說明。且上訴人係於85年7月始委託被上\n    訴人代為收取江文傑積欠上訴人之借款，而系爭支票塗改前\n    之發票日則為85年3月30日，顯係於上訴人委託被上訴人代\n    為收取借款以前所簽發，則上訴人所主張伊於85年7月13日\n    要求被上訴人交付向江文傑所收取之借款時，被上訴人即簽\n    發系爭支票交付上訴人等語，即難憑採，被上訴人上開辯詞\n    ，應屬可信。依上訴人所提出台灣台中地方法院91年度訴字\n    第436號清償借款事件91年5月20日筆錄所示，被上訴人固先\n    稱系爭支票係其向上訴人借款150萬元所開無訛，然其隨即\n    更正陳述其乃經上訴人之同意，將受託向江文傑收取之150\n    萬元轉借給陳永卿，被告因而提起刑事訴訟等語，因之兩造\n    合意停止訴訟，以俟刑事案件之調查審認，以釐清其糾葛。\n    是依被上訴人一貫所辯，足見其就其上開錯誤之自認已為撤\n    銷更正。次查，就被上訴人更正陳述所陳相關刑事案件，為\n    上訴人前於86年4月7日具狀，以被上訴人受託代為收取江文\n    傑積欠伊之借款150萬元及利息11萬零250元後，將該款項侵\n    占為己有，並冒用伊之名義，與訴外人信和建設股份有限公\n    司偽簽預定房屋買賣契約書，涉犯侵占、偽造文書等罪嫌為\n    由，向臺灣彰化地方法院檢察署提出告訴，經該署以86年度\n    偵字第3249號受理在案；上訴人復於86年8月2日再以同一事\n    由，向原法院提起自訴，經該院以86年度自字第136號刑事\n    判決被上訴人無罪；上訴人不服該刑事判決復提起上訴，經\n    本院92年度重上更(二)字第270號刑事判決，於93年3月3日駁\n    回上訴人上訴並確定在案；此經本院調取上開刑事案件卷宗\n    ，核閱無訛。依上開刑事案件卷宗資料所示，上訴人於該刑\n    事案件將近7年之偵審期間，僅堅稱：被上訴人受託代為收\n    取江文傑積欠伊之借款150萬元及利息11萬零250元後，即將\n    該款項侵占為己有等語，並未主張兩造就該筆款項具有消費\n    借貸法律關係存在之情事，故兩造間是否確有消費借貸之法\n    律關係存在，已非無疑。況且，上訴人於85年9月11日、同\n    年10月21日，先後向被上訴人寄發彰化永安街郵局存證信函\n    第129號、第153號，其內容僅要求被上訴人將受託向江文傑\n    收取之借款交付予上訴人，全無兩造間曾就該筆款項成立消\n    費借貸法律關係之任何記載，此有存證信函影本可稽（見上\n    開偵查卷宗第4、5頁）。從而，上訴人所主張兩造間具有消\n    費借貸之法律關係存在等語，實難遽信。被上訴人另辯稱：\n    「伊受託代為收取江文傑積欠上訴人之借款後，係經上訴人\n    同意以上訴人之名義將其中150萬元借貸予陳永卿」等語，\n    此業經陳永卿及其會計曹馨方於上開刑事案件審理時證述明\n    確（見本院89年度上更(一)字第337號刑事卷宗第97、98、164\n    、166頁，本院92年度重上更(二)字第270號刑事卷宗第114、\n    12頁），自堪信為真實；此外，上訴人復未能提出其他證據\n    ，足資證明兩造間就系爭150萬元成立消費借貸之法律關係\n    確已意思表示相互一致。則被上訴人辯稱兩造間並無消費借\n    貸關係存在之陳述，應為可採。從而，上訴人基於消費借貸\n    之法律關係，請求被上訴人給付150萬元，及自支付命令繕\n    本送達被上訴人翌日起至清償日止，按週年利率5%計算之利\n    息，即無理由。\n  (三)綜上所述，本件上訴人主張基於消費借貸之法律關係，請求\n    被上訴人給付150萬元，及自支付命令繕本送達被告翌日起\n    至清償日止，按週年利率5%計算之利息，即無理由。原審因\n    而為被上訴人勝訴之判決，駁回上訴人在原審之訴及假執行\n    之聲請，依法並無不合。上訴意旨仍執陳詞，指摘原判決不\n    當，聲明求予廢棄改判，為無理由，應予駁回。\n六、兩造其餘攻擊防禦方法，經本院斟酌後，認為均不足以影響\n    本件判決結果，爰不一一論列，併此敘明。\n七、據上論結，本件上訴為無理由，依民事訴訟法第449條第1項\n    、第78條，判決如主文。"
  },
  "search": "臺灣高等法院臺中分院民事判決94年度上易字第288號上訴人甲○○被上訴人乙○○訴訟代理人黃耀南律師上列當事人間請求清償借款事件，上訴人對於中華民國94年6月6日臺灣彰化地方法院94年度訴字第160號第一審判決提起上訴，本院於94年9月6日言詞辯論終結，茲判決如下：主文上訴駁回。第二審訴訟費用由上訴人負擔。事實及理由一、上訴人主張：伊於民國85年7月間，委託被上訴人代為收取訴外人江文傑積欠伊之借款新臺幣（下同）150萬元，經江文傑將借款匯入被上訴人帳戶後，伊於同月13日要求被上訴人交付上開款項，被上訴人即簽發付款人為彰化市第六信用合作社、票面金額150萬元、發票日85年3月30日、支票號碼FA0000000號之支票交付予伊，嗣因被上訴人要求延期清償，再將系爭支票發票日塗改為85年8月23日，此有系爭更改到期日並重新蓋章認證之支票、江文傑付款收據、匯入世華聯合商業銀行彰化分行被上訴人0000000000-0帳號帳戶內之入帳記錄等資料可證，即被上訴人於原審法院91年度字第436號清償借款事件審理中亦自承系爭支票為其向伊借款150萬元所開無訛，僅以其已清償借款置辯而已，此有該案審判筆錄可稽。而該件因兩造合意停止後，經原法院以視同撤回終結，乃因伊不諳法律程序延誤所致，伊非有撤回訴訟之意。被上訴人確已將所收款項存入世華聯合商業銀行彰化分行帳號0000000000-0之帳戶內，被上訴人推說該筆款項轉借訴外人陳永卿，惟查伊並未出具同意及委託書同意轉借，上訴人所提出以抵償陳永卿欠款之房屋買賣契約書乃係出於偽造，並非真實等情，爰依消費借貸之法律關係，提起本件訴訟，求為命被上訴人給付伊150萬元元及自支付命令繕本送達翌日起至清償日止按週年利率百分之五加計遲延利息之判決。二、被上訴人則以：(一)上訴人確曾委託伊代為收取江文傑積欠上訴人之借款本金150萬元與利息11萬零250元，惟伊於85年7月9日取得上開款項後，即經上訴人同意以其名義將其中150萬元借貸予訴外人陳永卿，此經原法院86年度自字第136號刑事判決、本院92年度重上更(二)字第270號刑事判決確定在案，可見消費借貸之法律關係應係存在於上訴人與陳永卿之間，與伊無涉。(二)又系爭支票係因伊仲介上訴人借貸上開150萬元予江文傑，始由伊簽發作為保證之用。且上訴人另於91年3月4日、8日，以系爭支票作為證據，主張伊於88年間各向其借款50萬元、150萬元為由，聲請核發支付命令，經原法院分別核發91年度促字第5026號、91年度促字第5778號支付命令後，伊聲明異議，否認兩造間存有消費借貸之法律關係，復經原法院彰化簡易庭91年度彰簡字第196號、同院91年度訴字第436號受理在案，並分別因上訴人當庭撤回訴訟而終結。現上訴人再以系爭支票作為證據，主張伊於85年間向上訴人借款150萬元，與聲請前開二件支付命令時所為係於88年間向上訴人分別借款50萬元、150萬元時主張之借貸原因、事實、時間，顯不相符。(三)上訴人具狀告訴伊涉嫌侵占訴外人江文傑交付之150萬元及利息11萬零250元等情，業經原法院86年偵字第3249號案檢察官為不起訴處分；嗣上訴人改提自訴，亦經原法院以86年自訴字第136號案受理，上訴人於該案審理中並未主張兩造係金錢借貸關係，並於該案中自承系爭支票係以擔保伊仲介上訴人借款予江文傑之用，此有原法院該案86年9月25日訊問筆錄、86年11月4日訊問筆錄、86年11月21日訊問筆錄可稽，而上訴人轉貸予江文傑150萬元部分，業經上揭刑事判決認定係經上訴人同意再轉借予信和建設公司之負責人陳永卿，而陳永卿未如期清償，上訴人依法應向其求償，卻再三向伊請求清償借款，顯屬無據。末查，關於於上訴附證三之建物謄本乙節，係因上訴人事後毀約不同意以轉借予陳永卿150萬元當作訂金購買該屋，而訴外人陳永卿於89年10月5日將該屋移轉登記予他人名義，乃謀貸款週轉之用，與上開事件無涉，亦與系爭支票借款事件無關等語，資為抗辯。三、原審法院審理後，斟酌兩造之主張及攻擊防禦方法之結果，認上訴人之訴為無理由，為其敗訴之判決，駁回上訴人在原審之訴及假執行之聲請。上訴人不服，提起上訴，聲明求為判決：(一)原判決廢棄；(二)被上訴人應給付伊150萬元及本件支付命令繕本送達翌日起至清償日止按週年利率百分之五計算之利息；(三)第一、二審訴訟費用均由被上訴人負擔。被上訴人則答辯聲明求為判決駁回上訴人之上訴。四、兩造不爭執之事實：(一)被上訴人曾簽發，付款人為彰化市第六信用合作社，票面金額150萬元，發票日期為85年3月30日，支票號碼為0000000號之支票予上訴人收執。(二)上訴人曾委託被上訴人代為收取江文傑積欠上訴人之借款150萬元，江文傑已將借款本金150萬元與利息11萬零250元交付予被上訴人。五、本件爭點：上訴人與被上訴人間是否因簽發交付系爭支票而成立消費借貸契約，而使被上訴人應負150萬元之借款返還義務。茲分析如下：(一)按稱消費借貸者，謂當事人一方移轉金錢或其他代替物之所有權於他方，而約定他方以種類、品質、數量相同之物返還之契約，民法第474條第1項定有明文。次按，當事人主張有金錢借貸關係存在，須就其發生所須具備之特別要件即金錢之交付及借貸意思表示互相一致負舉證之責任，若僅證明有金錢之交付，未證明借貸意思表示互相一致者，尚不能認為有金錢借貸關係存在(最高法院81年度台上字第2372號判決意旨參照)；又支票為無因證券，簽發支票之原因實有多端，非必因借貸關係始簽發，故簽發支票交付他人提領尚不足以證明與他人訂立借貸契約，貸款與他人而成立借貸關係。最高法院86年度台上字第2031號判決亦明揭斯旨。而當事人主張有利於己之事實，就其事實有舉證責任，民事訴訟法第277條有明文規定。從而當事人如主張有金錢借貸關係存在，自須就已交付金錢及雙方借貸意思表示互相一致等有利於己之事實，負舉證之責任。(二)經查，本件上訴人係基於消費借貸之法律關係，訴請被上訴人返還借款150萬元，則依上揭說明，上訴人應就該消費借貸法律關係所須具備之要件，即消費借貸意思表示相互一致，以及交付150萬元兩項事實負舉證責任。本件被上訴人固不爭執確曾受上訴人委託代為收取江文傑積欠上訴人之借款150萬元，以及江文傑已將該借款本金與利息交付予被上訴人之事實，然否認係基於兩造間具有消費借貸之法律關係存在，故關於兩造間確有消費借貸意思表示相互一致之有利於上訴人之事實，自仍應由上訴人負舉證責任。又，被上訴人雖自承簽發系爭150萬元支票交付上訴人，惟辯稱：「系爭支票係因伊仲介上訴人借貸上開150萬元予江文傑，始由伊簽發作為保證之用」等語。此為上訴人於原法院上開刑事案件審理時所自承（見原法院上開刑事卷宗第22、52頁）。按簽發支票，非必因借貸關係始簽發，尚不足以證明與他人訂立借貸契約，前已說明。且上訴人係於85年7月始委託被上訴人代為收取江文傑積欠上訴人之借款，而系爭支票塗改前之發票日則為85年3月30日，顯係於上訴人委託被上訴人代為收取借款以前所簽發，則上訴人所主張伊於85年7月13日要求被上訴人交付向江文傑所收取之借款時，被上訴人即簽發系爭支票交付上訴人等語，即難憑採，被上訴人上開辯詞，應屬可信。依上訴人所提出台灣台中地方法院91年度訴字第436號清償借款事件91年5月20日筆錄所示，被上訴人固先稱系爭支票係其向上訴人借款150萬元所開無訛，然其隨即更正陳述其乃經上訴人之同意，將受託向江文傑收取之150萬元轉借給陳永卿，被告因而提起刑事訴訟等語，因之兩造合意停止訴訟，以俟刑事案件之調查審認，以釐清其糾葛。是依被上訴人一貫所辯，足見其就其上開錯誤之自認已為撤銷更正。次查，就被上訴人更正陳述所陳相關刑事案件，為上訴人前於86年4月7日具狀，以被上訴人受託代為收取江文傑積欠伊之借款150萬元及利息11萬零250元後，將該款項侵占為己有，並冒用伊之名義，與訴外人信和建設股份有限公司偽簽預定房屋買賣契約書，涉犯侵占、偽造文書等罪嫌為由，向臺灣彰化地方法院檢察署提出告訴，經該署以86年度偵字第3249號受理在案；上訴人復於86年8月2日再以同一事由，向原法院提起自訴，經該院以86年度自字第136號刑事判決被上訴人無罪；上訴人不服該刑事判決復提起上訴，經本院92年度重上更(二)字第270號刑事判決，於93年3月3日駁回上訴人上訴並確定在案；此經本院調取上開刑事案件卷宗，核閱無訛。依上開刑事案件卷宗資料所示，上訴人於該刑事案件將近7年之偵審期間，僅堅稱：被上訴人受託代為收取江文傑積欠伊之借款150萬元及利息11萬零250元後，即將該款項侵占為己有等語，並未主張兩造就該筆款項具有消費借貸法律關係存在之情事，故兩造間是否確有消費借貸之法律關係存在，已非無疑。況且，上訴人於85年9月11日、同年10月21日，先後向被上訴人寄發彰化永安街郵局存證信函第129號、第153號，其內容僅要求被上訴人將受託向江文傑收取之借款交付予上訴人，全無兩造間曾就該筆款項成立消費借貸法律關係之任何記載，此有存證信函影本可稽（見上開偵查卷宗第4、5頁）。從而，上訴人所主張兩造間具有消費借貸之法律關係存在等語，實難遽信。被上訴人另辯稱：「伊受託代為收取江文傑積欠上訴人之借款後，係經上訴人同意以上訴人之名義將其中150萬元借貸予陳永卿」等語，此業經陳永卿及其會計曹馨方於上開刑事案件審理時證述明確（見本院89年度上更(一)字第337號刑事卷宗第97、98、164、166頁，本院92年度重上更(二)字第270號刑事卷宗第114、12頁），自堪信為真實；此外，上訴人復未能提出其他證據，足資證明兩造間就系爭150萬元成立消費借貸之法律關係確已意思表示相互一致。則被上訴人辯稱兩造間並無消費借貸關係存在之陳述，應為可採。從而，上訴人基於消費借貸之法律關係，請求被上訴人給付150萬元，及自支付命令繕本送達被上訴人翌日起至清償日止，按週年利率5%計算之利息，即無理由。(三)綜上所述，本件上訴人主張基於消費借貸之法律關係，請求被上訴人給付150萬元，及自支付命令繕本送達被告翌日起至清償日止，按週年利率5%計算之利息，即無理由。原審因而為被上訴人勝訴之判決，駁回上訴人在原審之訴及假執行之聲請，依法並無不合。上訴意旨仍執陳詞，指摘原判決不當，聲明求予廢棄改判，為無理由，應予駁回。六、兩造其餘攻擊防禦方法，經本院斟酌後，認為均不足以影響本件判決結果，爰不一一論列，併此敘明。七、據上論結，本件上訴為無理由，依民事訴訟法第449條第1項、第78條，判決如主文。中華民國94年9月20日民事第五庭審判長法官陳滿賢法官古金男法官朱樑以上正本係照原本作成。兩造均不得上訴。書記官陳俞豪中華民國94年9月22日Ｈ",
  "characters": {
    "judges": [
      "陳滿賢",
      "古金男",
      "朱樑"
    ],
    "prosecutors": [

    ],
    "lawyers": [
      "黃耀南"
    ],
    "clerks": [
      "陳俞豪"
    ],
    "plaintiffs": [

    ],
    "defendants": [

    ],
    "prosecutor_office": [

    ],
    "creditors": [

    ],
    "debtors": [

    ],
    "judicial_associate_officer": [

    ]
  },
  "adjudged_at": "2005-09-20",
  "created_at": "2016-02-06 20:36:48",
  "updated_at": "2016-02-06 20:36:48"
}