{
  "identify": "TYD-93-訴-1246-20050418-1",
  "court": {
    "name": "臺灣桃園地方法院",
    "code": "TYD"
  },
  "division": {
    "name": "刑事",
    "code": "M"
  },
  "year": 93,
  "word": "訴",
  "number": "1246",
  "jcheck": "1",
  "reason": "毒品危害防制條例",
  "content": "臺灣桃園地方法院刑事判決              93年度訴字第1246號\n公  訴  人  臺灣桃園地方法院檢察署檢察官\n被      告  甲○○  男  26歲.\n                      號\n指定辯護人  本院公設辯護人  彭詩雯\n上列被告因毒品危害防制條例案件，經檢察官提起公訴（九十三\n年度毒偵字第二一○四號），被告自白犯罪，經本院合議庭裁定\n認由受命法官獨任進行簡式審判程序，檢察官聲請改依協商程序\n而為判決，本院判決如下：\n    主  文\n甲○○連續施用第一級毒品，處有期徒刑捌月，扣案之海洛因肆\n拾陸包（驗餘淨重壹捌點貳陸公克，包裝重玖點壹捌公克）均沒\n收銷毀之；又連續施用第二級毒品，處有期徒刑陸月，扣案之安\n非他命拾肆包（毛重柒公克）均沒收銷燬之。有期徒刑部分，應\n執行有期徒刑壹年。\n    事實及理由\n一、犯罪事實：\n    甲○○前因施用毒品案件，經觀察、勒戒後，認無繼續施用\n    毒品之傾向，由臺灣桃園地方法院檢察署檢察官於民國八十\n    八年十月十一日，以八十八年度偵緝字第九六三號為不起訴\n    處分確定，復因施用毒品案件，經送強制戒治，於九十二年\n    八月七日停止戒治出所。詎賴文龍又分別基於施用第一級毒\n    品海洛因及第二級毒品安非他命之概括犯意，自五年內之九\n    十三年二月間某日起至同年九十三年五月十日止及九十二年\n    十一月間起至九十三年五月十日止，在其桃園縣桃園市○○\n    路六六二號住處，連續分別施用海洛因、安非他命多次，嗣\n    為警於九十三年五月十日十四時許，在桃園縣桃園市○○街\n    二八三號前查獲，並扣得毒品海洛因四十六包（驗餘淨重一\n    八．二六公克，包裝重九．一八公克）、安非他命十四包（\n    毛重七公克）。\n二、證據：\n  (一)被告於警訊、偵訊及本院調查、審理中之自白。\n  (二)桃園縣衛生局不法藥物尿液檢定書、法務部調查局鑑定通知\n    書、台灣高等法院被告全國前案紀錄表及不起訴處分書抄本\n    各一份。\n  (三)前述海洛因、安非他命等毒品扣案。\n三、本件經檢察官與被告、辯護人於審判外達成協商之合意且被\n    告已認罪，其合意內容為如主文所示。經查前述協商合意並\n    無刑事訴訟法第四百五十五條之四第一項所列情形之一，檢\n    察官聲請改依協商程序而為判決，本院爰不經言詞辯論，於\n    協商合意範圍內為協商判決。\n四、應適用之法條：刑事訴訟法第二百九十九條第一項前段，毒\n    品危害防制條例毒品危害防制條例第十條第一項、第二項、\n    第十八條第一項前段、刑法第十一條前段、第五十六條、第\n    五十一條第五款。\n五、本判決除有刑事訴訟法第四百五十五條之四第一項第一款、\n    第二款、第四款、第六款、第七款所定情形之一，或違反同\n    條第二項規定者外，不得上訴。\n六、如有前述例外得上訴之情形，又不服本件判決，得自判決送\n    達之日起十日內，向本院提出上訴書狀，上訴於第二審法院\n    。\n中    華    民    國    94    年    4     月    18    日\n                      刑事第二庭法  官  潘進順\n以上正本證明與原本無異。\n如不服本判決，應於判決送達後10日內向本院提出上訴狀（應附\n繕本)，上訴於第二審法院。\n                                書記官  陳玉芬\n中    華    民    國    94    年    4     月    18    日\n附錄本件論罪科刑依據法條：\n毒品危害防制條例第十條\n施用第一級毒品者，處六月以上五年以下有期徒刑。\n施用第二級毒品者，處三年以下有期徒刑。\n",
  "structure": {
    "main": "甲○○連續施用第一級毒品，處有期徒刑捌月，扣案之海洛因肆\n拾陸包（驗餘淨重壹捌點貳陸公克，包裝重玖點壹捌公克）均沒\n收銷毀之；又連續施用第二級毒品，處有期徒刑陸月，扣案之安\n非他命拾肆包（毛重柒公克）均沒收銷燬之。有期徒刑部分，應\n執行有期徒刑壹年。",
    "fact": "一、犯罪事實：\n    甲○○前因施用毒品案件，經觀察、勒戒後，認無繼續施用\n    毒品之傾向，由臺灣桃園地方法院檢察署檢察官於民國八十\n    八年十月十一日，以八十八年度偵緝字第九六三號為不起訴\n    處分確定，復因施用毒品案件，經送強制戒治，於九十二年\n    八月七日停止戒治出所。詎賴文龍又分別基於施用第一級毒\n    品海洛因及第二級毒品安非他命之概括犯意，自五年內之九\n    十三年二月間某日起至同年九十三年五月十日止及九十二年\n    十一月間起至九十三年五月十日止，在其桃園縣桃園市○○\n    路六六二號住處，連續分別施用海洛因、安非他命多次，嗣\n    為警於九十三年五月十日十四時許，在桃園縣桃園市○○街\n    二八三號前查獲，並扣得毒品海洛因四十六包（驗餘淨重一\n    八．二六公克，包裝重九．一八公克）、安非他命十四包（\n    毛重七公克）。\n二、證據：\n  (一)被告於警訊、偵訊及本院調查、審理中之自白。\n  (二)桃園縣衛生局不法藥物尿液檢定書、法務部調查局鑑定通知\n    書、台灣高等法院被告全國前案紀錄表及不起訴處分書抄本\n    各一份。\n  (三)前述海洛因、安非他命等毒品扣案。\n三、本件經檢察官與被告、辯護人於審判外達成協商之合意且被\n    告已認罪，其合意內容為如主文所示。經查前述協商合意並\n    無刑事訴訟法第四百五十五條之四第一項所列情形之一，檢\n    察官聲請改依協商程序而為判決，本院爰不經言詞辯論，於\n    協商合意範圍內為協商判決。\n四、應適用之法條：刑事訴訟法第二百九十九條第一項前段，毒\n    品危害防制條例毒品危害防制條例第十條第一項、第二項、\n    第十八條第一項前段、刑法第十一條前段、第五十六條、第\n    五十一條第五款。\n五、本判決除有刑事訴訟法第四百五十五條之四第一項第一款、\n    第二款、第四款、第六款、第七款所定情形之一，或違反同\n    條第二項規定者外，不得上訴。\n六、如有前述例外得上訴之情形，又不服本件判決，得自判決送\n    達之日起十日內，向本院提出上訴書狀，上訴於第二審法院\n    。",
    "reason": "一、犯罪事實：\n    甲○○前因施用毒品案件，經觀察、勒戒後，認無繼續施用\n    毒品之傾向，由臺灣桃園地方法院檢察署檢察官於民國八十\n    八年十月十一日，以八十八年度偵緝字第九六三號為不起訴\n    處分確定，復因施用毒品案件，經送強制戒治，於九十二年\n    八月七日停止戒治出所。詎賴文龍又分別基於施用第一級毒\n    品海洛因及第二級毒品安非他命之概括犯意，自五年內之九\n    十三年二月間某日起至同年九十三年五月十日止及九十二年\n    十一月間起至九十三年五月十日止，在其桃園縣桃園市○○\n    路六六二號住處，連續分別施用海洛因、安非他命多次，嗣\n    為警於九十三年五月十日十四時許，在桃園縣桃園市○○街\n    二八三號前查獲，並扣得毒品海洛因四十六包（驗餘淨重一\n    八．二六公克，包裝重九．一八公克）、安非他命十四包（\n    毛重七公克）。\n二、證據：\n  (一)被告於警訊、偵訊及本院調查、審理中之自白。\n  (二)桃園縣衛生局不法藥物尿液檢定書、法務部調查局鑑定通知\n    書、台灣高等法院被告全國前案紀錄表及不起訴處分書抄本\n    各一份。\n  (三)前述海洛因、安非他命等毒品扣案。\n三、本件經檢察官與被告、辯護人於審判外達成協商之合意且被\n    告已認罪，其合意內容為如主文所示。經查前述協商合意並\n    無刑事訴訟法第四百五十五條之四第一項所列情形之一，檢\n    察官聲請改依協商程序而為判決，本院爰不經言詞辯論，於\n    協商合意範圍內為協商判決。\n四、應適用之法條：刑事訴訟法第二百九十九條第一項前段，毒\n    品危害防制條例毒品危害防制條例第十條第一項、第二項、\n    第十八條第一項前段、刑法第十一條前段、第五十六條、第\n    五十一條第五款。\n五、本判決除有刑事訴訟法第四百五十五條之四第一項第一款、\n    第二款、第四款、第六款、第七款所定情形之一，或違反同\n    條第二項規定者外，不得上訴。\n六、如有前述例外得上訴之情形，又不服本件判決，得自判決送\n    達之日起十日內，向本院提出上訴書狀，上訴於第二審法院\n    。"
  },
  "search": "臺灣桃園地方法院刑事判決93年度訴字第1246號公訴人臺灣桃園地方法院檢察署檢察官被告甲○○男26歲.號指定辯護人本院公設辯護人彭詩雯上列被告因毒品危害防制條例案件，經檢察官提起公訴（九十三年度毒偵字第二一○四號），被告自白犯罪，經本院合議庭裁定認由受命法官獨任進行簡式審判程序，檢察官聲請改依協商程序而為判決，本院判決如下：主文甲○○連續施用第一級毒品，處有期徒刑捌月，扣案之海洛因肆拾陸包（驗餘淨重壹捌點貳陸公克，包裝重玖點壹捌公克）均沒收銷毀之；又連續施用第二級毒品，處有期徒刑陸月，扣案之安非他命拾肆包（毛重柒公克）均沒收銷燬之。有期徒刑部分，應執行有期徒刑壹年。事實及理由一、犯罪事實：甲○○前因施用毒品案件，經觀察、勒戒後，認無繼續施用毒品之傾向，由臺灣桃園地方法院檢察署檢察官於民國八十八年十月十一日，以八十八年度偵緝字第九六三號為不起訴處分確定，復因施用毒品案件，經送強制戒治，於九十二年八月七日停止戒治出所。詎賴文龍又分別基於施用第一級毒品海洛因及第二級毒品安非他命之概括犯意，自五年內之九十三年二月間某日起至同年九十三年五月十日止及九十二年十一月間起至九十三年五月十日止，在其桃園縣桃園市○○路六六二號住處，連續分別施用海洛因、安非他命多次，嗣為警於九十三年五月十日十四時許，在桃園縣桃園市○○街二八三號前查獲，並扣得毒品海洛因四十六包（驗餘淨重一八．二六公克，包裝重九．一八公克）、安非他命十四包（毛重七公克）。二、證據：(一)被告於警訊、偵訊及本院調查、審理中之自白。(二)桃園縣衛生局不法藥物尿液檢定書、法務部調查局鑑定通知書、台灣高等法院被告全國前案紀錄表及不起訴處分書抄本各一份。(三)前述海洛因、安非他命等毒品扣案。三、本件經檢察官與被告、辯護人於審判外達成協商之合意且被告已認罪，其合意內容為如主文所示。經查前述協商合意並無刑事訴訟法第四百五十五條之四第一項所列情形之一，檢察官聲請改依協商程序而為判決，本院爰不經言詞辯論，於協商合意範圍內為協商判決。四、應適用之法條：刑事訴訟法第二百九十九條第一項前段，毒品危害防制條例毒品危害防制條例第十條第一項、第二項、第十八條第一項前段、刑法第十一條前段、第五十六條、第五十一條第五款。五、本判決除有刑事訴訟法第四百五十五條之四第一項第一款、第二款、第四款、第六款、第七款所定情形之一，或違反同條第二項規定者外，不得上訴。六、如有前述例外得上訴之情形，又不服本件判決，得自判決送達之日起十日內，向本院提出上訴書狀，上訴於第二審法院。中華民國94年4月18日刑事第二庭法官潘進順以上正本證明與原本無異。如不服本判決，應於判決送達後10日內向本院提出上訴狀（應附繕本)，上訴於第二審法院。書記官陳玉芬中華民國94年4月18日附錄本件論罪科刑依據法條：毒品危害防制條例第十條施用第一級毒品者，處六月以上五年以下有期徒刑。施用第二級毒品者，處三年以下有期徒刑。",
  "characters": {
    "judges": [
      "潘進順"
    ],
    "prosecutors": [

    ],
    "lawyers": [

    ],
    "clerks": [
      "陳玉芬"
    ],
    "plaintiffs": [

    ],
    "defendants": [
      "甲○○  男  26歲."
    ],
    "prosecutor_office": [
      "臺灣桃園地方法院檢察署檢察官"
    ],
    "creditors": [

    ],
    "debtors": [

    ],
    "judicial_associate_officer": [

    ]
  },
  "adjudged_at": "2005-04-18",
  "created_at": "2016-02-06 18:12:17",
  "updated_at": "2016-02-06 18:12:17"
}