{
  "identify": "KLD-100-基交簡-810-20111208-1",
  "court": {
    "name": "臺灣基隆地方法院",
    "code": "KLD"
  },
  "division": {
    "name": "刑事",
    "code": "M"
  },
  "year": 100,
  "word": "基交簡",
  "number": "810",
  "jcheck": "1",
  "reason": "公共危險",
  "content": "臺灣基隆地方法院刑事簡易判決      100年度基交簡字第810號\n聲  請  人  臺灣基隆地方法院檢察署檢察官\n被      告  蕭建菲\n上列被告因公共危險案件，經檢察官聲請以簡易判決處刑（100\n年度偵字第5249號），本院判決如下：\n    主      文\n蕭建菲服用酒類，不能安全駕駛動力交通工具而駕駛，處有期徒\n刑月，如易科罰金，以新臺幣壹仟元折算壹日。\n    事實及理由\n一、本件犯罪事實、證據，均引用檢察官聲請簡易判決處刑書（\n    以下簡稱「聲請書」）之記載（詳如附件），並補充如下：\n  (一)被告蕭建菲前於民國90年間，即曾因「服用酒類，不能安全\n    駕駛動力交通工具而駕駛」，經本院於民國90年11月28日，\n    以90年度基交簡字第720 號判決拘役50日、緩刑二年確定（\n    不構成累犯）；其後，又再因「服用酒類，不能安全駕駛動\n    力交通工具而駕駛」，經本院於93年9 月29日，以93年度基\n    交簡字第414 號判決拘役50日確定，93年12月28日易科罰金\n    執行完畢（不構成累犯）。此除有臺灣高等法院被告前案紀\n    錄表在卷可考，並據本院職權查核上開判決所載內容無訛。\n  (二)按汽車駕駛人飲酒後，其吐氣所含酒精成分超過0.25mg/L者\n    ，不得駕車，道路交通安全規則第一百十四條第二款定有明\n    文。參以相關醫學文獻之所載，亦可知酒精對人體之影響程\n    度，係依血中酒精濃度而定，經換算結果，呼氣濃度達0.25\n    mg/L（即血液中酒精濃度為50mg/dl ）時，將造成輕度協調\n    功能降低之輕度中毒症狀；呼氣濃度達0.5 mg/L（即血液中\n    酒精濃度為100mg/dl）時，將造成反應較慢、感覺減低、影\n    響駕駛等輕到中度之中毒症狀；呼氣濃度達0.75mg/L（即血\n    液中酒精濃度為150mg/dl）時，將造成思考改變、個性行為\n    改變；呼氣濃度達1 mg/L（即血液中酒精濃度為200mg/dl）\n    時，將造成步態不穩、噁心嘔吐、精神混惑不清晰等中度酒\n    精中毒症狀。此觀行政院國軍退除役官兵輔導委員會臺北榮\n    民總醫院以88年8 月5 日北總內字第26868 號函釋之內容\n    即明。尤以酒精使用後對身體之影響，除自主神經系統亢奮\n    與認知功能之暫時性缺損外，與駕駛能力有關而將受影響者\n    ，亦包括：對移動景物之追蹤能力。經強光照射後恢復\n    視力。監視四周之注意力。許多人常因飲酒後無可自覺之\n    生理反應，以致頭部功能已缺損，仍不自知而照常開車；雖\n    每人飲酒後之自覺生理反應不一，然而同種族間之酒精清除\n    率係相近，故一般而言，飲用同量酒精後對每個人身體之影\n    響應類似，且酒精濃度與肇事率之關係為呼氣酒精濃度達0.\n    25mg/L時，肇事率為未飲酒者之兩倍。此亦有臺北醫學院、\n    中央警察大學製作之相關研究文獻資料可資參佐。據此對照\n    本案被告為警查獲後，經施以酒精濃度測試之結果，其呼氣\n    酒精濃度值達0.79mg/L（即血液中酒精濃度為158mg/dl）之\n    情節；兼衡量被告果因酒後注意力下降而肇致如聲請書所載\n    之車禍實害，此除經被告敘明在卷，並據證人陳光亮證述明\n    確，且有基隆市○○○道路交通事故現場草圖1 紙、車禍現\n    場暨車損照片16張附卷足考。則被告飲用酒類以後，確已處\n    於不能安全駕駛之狀態，當亦殆無可疑。\n二、論罪科刑：\n  (一)查被告服用酒類，不能安全駕駛動力交通工具，猶駕駛動力\n    交通工具行駛道路致為警查獲（100 年9 月15日）以後，刑\n    法第一百八十五條之三業於100 年11月30日修正公布，並自\n    100 年12月2 日開始施行（總統令100 年11月30日華一總字\n    第10000263911 號）。茲刑法第一百八十五條之三於「修正\n    前」，原係規定：「服用毒品、麻醉藥品、酒類或其他相類\n    之物，不能安全駕駛動力交通工具而駕駛者，處一年以下有\n    期徒刑、拘役或科或併科（新臺幣）十五萬元以下罰金。」\n    本次修正則增列第二項加重結果犯之規定，併將原條文移列\n    為同條第一項而規定「服用毒品、麻醉藥品、酒類或其他相\n    類之物，不能安全駕駛動力交通工具而駕駛者，處二年以下\n    有期徒刑、拘役或科或併科（新臺幣）二十萬元以下罰金。\n    」細繹修正前、後法律規定，有關「服用酒類，不能安全駕\n    駛動力交通工具，猶駕駛動力交通工具行駛道路」之犯罪構\n    成要件雖未更異，然其法律效果則有不同；亦即，修正後之\n    刑法第一百八十五條之三第一項，除將原「一年以下有期徒\n    刑」之刑度提高為「二年以下有期徒刑」，併將「新臺幣十\n    五萬元以下（刑法施行法第一條之一第一項規定參照）」之\n    罰金數額提高為「新臺幣二十萬元以下（刑法施行法第一條\n    之一第一項規定參照）」。是依修正前、後法律規定而為比\n    較適用，本案顯以修正前之舊法，較有利於被告，按諸刑法\n    第二條第一項所揭櫫之「從舊從輕」原則，本院自應以100\n    年11月30日修正公布前之刑法第一百八十五條之三，為本案\n    所應適用、處斷之法條罪名。\n  (二)是核被告如聲請書犯罪事實欄之所為，係犯100 年11月30日\n    修正公布前之刑法第一百八十五條之三之服用酒類不能安全\n    駕駛罪。\n  (三)本院審酌被告明知酒後駕車在道路上行駛，對一般往來之公\n    眾及駕駛人自身具有高度危險性，仍執意酒後駕車，既漠視\n    自身安危，更枉顧公眾安全；並考量被告為警依法施測所得\n    之酒精濃度值達0.79mg/L、本次復已致生交通實害（詳如聲\n    請書所載），兼衡量被告前即曾因酒後不能安全駕駛，而遭\n    法院判處罪刑確定，詳如本判決一(一)之所述，猶再犯本案而\n    未見改悔，暨其犯後態度等一切情狀，量處如主文所示之刑\n    ，併諭知易科罰金之折算標準。\n三、依刑事訴訟法第四百四十九條第一項前段、第四百五十四條\n    第二項，100 年11月30日修正公布前之刑法第一百八十五條\n    之三，刑法第二條第一項、第四十一條第一項前段，刑法施\n    行法第一條之一，逕以簡易判決處刑如主文。\n如不服本判決，得自收受送達之日起10日內，向本院提起上訴。\n中    華    民    國   100    年    12    月    8     日\n                  基隆簡易庭法  官  王慧惠\n以上正本證明與原本無異。\n如不服本判決，應於判決送達後10日內，向本院提出上訴書狀，\n敘述上訴理由，上訴於本院合議庭，並按他造當事人之人數附具\n繕本。\n中    華    民    國   100    年    12    月    8     日\n                            書記官  王一芳\n附錄論罪法條：\n100 年11月30日修正公布前刑法第185 條之3\n服用毒品、麻醉藥品、酒類或其他相類之物，不能安全駕駛動力\n交通工具而駕駛者，處1 年以下有期徒刑、拘役或科或併科15萬\n元以下罰金。\n附件：\n臺灣基隆地方法院檢察署檢察官聲請簡易判決處刑書\n                                     100年度偵字第5249號\n    被      告  蕭建菲  男  61歲（民國○○年○月○日生）\n                        住新北市萬里區雙興里豐廩14號\n                        居基隆市信義區○○○街7號2樓\n                        （指定送達處所）\n                        國民身分證統一編號：Ｚ000000000號\n上列被告因公共危險案件，業經偵查終結，認為宜聲請以簡易判\n決處刑，茲將犯罪事實及證據並所犯法條分敘如下：\n        犯罪事實\n一、蕭建菲明知服用酒類過量會導致反應遲鈍、注意力減低之結\n    果，此時若駕駛動力交通工具行駛於道路上，肇事之機率及\n    危險性均遠較正常人為高，於民國100年9月15日傍晚在新北\n    市萬里區雙興里豐廩14號戶籍地飲用2杯藥酒，雖稍事休息\n    ，惟尚呈反應遲緩、注意能力減低，而不能安全駕駛動力交\n    通工具之程度，猶於晚間駕駛車牌號碼DH-1990號自小客車\n    欲前往居所，於同日22時許途經基隆市○○區○○路與壽山\n    路口時，不慎與陳光亮駕駛車牌號碼HF-1686號自小客車發\n    生擦撞，警方到場處理，經測試蕭建菲呼氣中酒精含量為每\n    公升0.79毫克\n二、案經基隆市警察局第二分局報告偵辦。\n        證據並所犯法條\n一、上開犯罪事實，業據被告蕭建菲坦承不諱，復有呼氣測試紀\n    錄、刑法第185條之3案件測試觀察紀錄表及現場照片附卷足\n    資對照。本件事證明確，被告犯行已堪認定。\n二、核被告所為，係犯刑法第185條之3公共危險罪嫌。\n三、依刑事訴訟法第451條第1項聲請逕以簡易判決處刑。\n    此  致\n臺灣基隆地方法院基隆簡易庭\n中    華    民    國   100    年    11    月    25    日\n                              檢  察  官  王亞樵\n本件正本證明與原本無異\n中    華    民    國   100    年    11    月    30    日\n                              書  記  官  趙立慧\n附錄本案所犯法條全文\n中華民國刑法第185條之3\n服用毒品、麻醉藥品、酒類或其他相類之物，不能安全駕駛動力\n交通工具而駕駛者，處 1 年以下有期徒刑、拘役或科或併科 15\n萬元以下罰金。\n附記事項：\n本件係依刑事訴訟法簡易程序辦理，法院簡易庭得不傳喚被告、\n輔佐人、告訴人、告發人等出庭即以簡易判決處刑；被告、被害\n人、告訴人等對於告訴乃論案件如已達成民事和解而要撤回告訴\n或對非告訴乃論案件認有受傳喚到庭陳述意見之必要時，請即另\n以書狀向簡易法庭陳述或請求傳訊。",
  "structure": {
    "main": "蕭建菲服用酒類，不能安全駕駛動力交通工具而駕駛，處有期徒\n刑月，如易科罰金，以新臺幣壹仟元折算壹日。",
    "fact": "一、本件犯罪事實、證據，均引用檢察官聲請簡易判決處刑書（\n    以下簡稱「聲請書」）之記載（詳如附件），並補充如下：\n  (一)被告蕭建菲前於民國90年間，即曾因「服用酒類，不能安全\n    駕駛動力交通工具而駕駛」，經本院於民國90年11月28日，\n    以90年度基交簡字第720 號判決拘役50日、緩刑二年確定（\n    不構成累犯）；其後，又再因「服用酒類，不能安全駕駛動\n    力交通工具而駕駛」，經本院於93年9 月29日，以93年度基\n    交簡字第414 號判決拘役50日確定，93年12月28日易科罰金\n    執行完畢（不構成累犯）。此除有臺灣高等法院被告前案紀\n    錄表在卷可考，並據本院職權查核上開判決所載內容無訛。\n  (二)按汽車駕駛人飲酒後，其吐氣所含酒精成分超過0.25mg/L者\n    ，不得駕車，道路交通安全規則第一百十四條第二款定有明\n    文。參以相關醫學文獻之所載，亦可知酒精對人體之影響程\n    度，係依血中酒精濃度而定，經換算結果，呼氣濃度達0.25\n    mg/L（即血液中酒精濃度為50mg/dl ）時，將造成輕度協調\n    功能降低之輕度中毒症狀；呼氣濃度達0.5 mg/L（即血液中\n    酒精濃度為100mg/dl）時，將造成反應較慢、感覺減低、影\n    響駕駛等輕到中度之中毒症狀；呼氣濃度達0.75mg/L（即血\n    液中酒精濃度為150mg/dl）時，將造成思考改變、個性行為\n    改變；呼氣濃度達1 mg/L（即血液中酒精濃度為200mg/dl）\n    時，將造成步態不穩、噁心嘔吐、精神混惑不清晰等中度酒\n    精中毒症狀。此觀行政院國軍退除役官兵輔導委員會臺北榮\n    民總醫院以88年8 月5 日北總內字第26868 號函釋之內容\n    即明。尤以酒精使用後對身體之影響，除自主神經系統亢奮\n    與認知功能之暫時性缺損外，與駕駛能力有關而將受影響者\n    ，亦包括：對移動景物之追蹤能力。經強光照射後恢復\n    視力。監視四周之注意力。許多人常因飲酒後無可自覺之\n    生理反應，以致頭部功能已缺損，仍不自知而照常開車；雖\n    每人飲酒後之自覺生理反應不一，然而同種族間之酒精清除\n    率係相近，故一般而言，飲用同量酒精後對每個人身體之影\n    響應類似，且酒精濃度與肇事率之關係為呼氣酒精濃度達0.\n    25mg/L時，肇事率為未飲酒者之兩倍。此亦有臺北醫學院、\n    中央警察大學製作之相關研究文獻資料可資參佐。據此對照\n    本案被告為警查獲後，經施以酒精濃度測試之結果，其呼氣\n    酒精濃度值達0.79mg/L（即血液中酒精濃度為158mg/dl）之\n    情節；兼衡量被告果因酒後注意力下降而肇致如聲請書所載\n    之車禍實害，此除經被告敘明在卷，並據證人陳光亮證述明\n    確，且有基隆市○○○道路交通事故現場草圖1 紙、車禍現\n    場暨車損照片16張附卷足考。則被告飲用酒類以後，確已處\n    於不能安全駕駛之狀態，當亦殆無可疑。\n二、論罪科刑：\n  (一)查被告服用酒類，不能安全駕駛動力交通工具，猶駕駛動力\n    交通工具行駛道路致為警查獲（100 年9 月15日）以後，刑\n    法第一百八十五條之三業於100 年11月30日修正公布，並自\n    100 年12月2 日開始施行（總統令100 年11月30日華一總字\n    第10000263911 號）。茲刑法第一百八十五條之三於「修正\n    前」，原係規定：「服用毒品、麻醉藥品、酒類或其他相類\n    之物，不能安全駕駛動力交通工具而駕駛者，處一年以下有\n    期徒刑、拘役或科或併科（新臺幣）十五萬元以下罰金。」\n    本次修正則增列第二項加重結果犯之規定，併將原條文移列\n    為同條第一項而規定「服用毒品、麻醉藥品、酒類或其他相\n    類之物，不能安全駕駛動力交通工具而駕駛者，處二年以下\n    有期徒刑、拘役或科或併科（新臺幣）二十萬元以下罰金。\n    」細繹修正前、後法律規定，有關「服用酒類，不能安全駕\n    駛動力交通工具，猶駕駛動力交通工具行駛道路」之犯罪構\n    成要件雖未更異，然其法律效果則有不同；亦即，修正後之\n    刑法第一百八十五條之三第一項，除將原「一年以下有期徒\n    刑」之刑度提高為「二年以下有期徒刑」，併將「新臺幣十\n    五萬元以下（刑法施行法第一條之一第一項規定參照）」之\n    罰金數額提高為「新臺幣二十萬元以下（刑法施行法第一條\n    之一第一項規定參照）」。是依修正前、後法律規定而為比\n    較適用，本案顯以修正前之舊法，較有利於被告，按諸刑法\n    第二條第一項所揭櫫之「從舊從輕」原則，本院自應以100\n    年11月30日修正公布前之刑法第一百八十五條之三，為本案\n    所應適用、處斷之法條罪名。\n  (二)是核被告如聲請書犯罪事實欄之所為，係犯100 年11月30日\n    修正公布前之刑法第一百八十五條之三之服用酒類不能安全\n    駕駛罪。\n  (三)本院審酌被告明知酒後駕車在道路上行駛，對一般往來之公\n    眾及駕駛人自身具有高度危險性，仍執意酒後駕車，既漠視\n    自身安危，更枉顧公眾安全；並考量被告為警依法施測所得\n    之酒精濃度值達0.79mg/L、本次復已致生交通實害（詳如聲\n    請書所載），兼衡量被告前即曾因酒後不能安全駕駛，而遭\n    法院判處罪刑確定，詳如本判決一(一)之所述，猶再犯本案而\n    未見改悔，暨其犯後態度等一切情狀，量處如主文所示之刑\n    ，併諭知易科罰金之折算標準。\n三、依刑事訴訟法第四百四十九條第一項前段、第四百五十四條\n    第二項，100 年11月30日修正公布前之刑法第一百八十五條\n    之三，刑法第二條第一項、第四十一條第一項前段，刑法施\n    行法第一條之一，逕以簡易判決處刑如主文。\n如不服本判決，得自收受送達之日起10日內，向本院提起上訴。",
    "reason": "一、本件犯罪事實、證據，均引用檢察官聲請簡易判決處刑書（\n    以下簡稱「聲請書」）之記載（詳如附件），並補充如下：\n  (一)被告蕭建菲前於民國90年間，即曾因「服用酒類，不能安全\n    駕駛動力交通工具而駕駛」，經本院於民國90年11月28日，\n    以90年度基交簡字第720 號判決拘役50日、緩刑二年確定（\n    不構成累犯）；其後，又再因「服用酒類，不能安全駕駛動\n    力交通工具而駕駛」，經本院於93年9 月29日，以93年度基\n    交簡字第414 號判決拘役50日確定，93年12月28日易科罰金\n    執行完畢（不構成累犯）。此除有臺灣高等法院被告前案紀\n    錄表在卷可考，並據本院職權查核上開判決所載內容無訛。\n  (二)按汽車駕駛人飲酒後，其吐氣所含酒精成分超過0.25mg/L者\n    ，不得駕車，道路交通安全規則第一百十四條第二款定有明\n    文。參以相關醫學文獻之所載，亦可知酒精對人體之影響程\n    度，係依血中酒精濃度而定，經換算結果，呼氣濃度達0.25\n    mg/L（即血液中酒精濃度為50mg/dl ）時，將造成輕度協調\n    功能降低之輕度中毒症狀；呼氣濃度達0.5 mg/L（即血液中\n    酒精濃度為100mg/dl）時，將造成反應較慢、感覺減低、影\n    響駕駛等輕到中度之中毒症狀；呼氣濃度達0.75mg/L（即血\n    液中酒精濃度為150mg/dl）時，將造成思考改變、個性行為\n    改變；呼氣濃度達1 mg/L（即血液中酒精濃度為200mg/dl）\n    時，將造成步態不穩、噁心嘔吐、精神混惑不清晰等中度酒\n    精中毒症狀。此觀行政院國軍退除役官兵輔導委員會臺北榮\n    民總醫院以88年8 月5 日北總內字第26868 號函釋之內容\n    即明。尤以酒精使用後對身體之影響，除自主神經系統亢奮\n    與認知功能之暫時性缺損外，與駕駛能力有關而將受影響者\n    ，亦包括：對移動景物之追蹤能力。經強光照射後恢復\n    視力。監視四周之注意力。許多人常因飲酒後無可自覺之\n    生理反應，以致頭部功能已缺損，仍不自知而照常開車；雖\n    每人飲酒後之自覺生理反應不一，然而同種族間之酒精清除\n    率係相近，故一般而言，飲用同量酒精後對每個人身體之影\n    響應類似，且酒精濃度與肇事率之關係為呼氣酒精濃度達0.\n    25mg/L時，肇事率為未飲酒者之兩倍。此亦有臺北醫學院、\n    中央警察大學製作之相關研究文獻資料可資參佐。據此對照\n    本案被告為警查獲後，經施以酒精濃度測試之結果，其呼氣\n    酒精濃度值達0.79mg/L（即血液中酒精濃度為158mg/dl）之\n    情節；兼衡量被告果因酒後注意力下降而肇致如聲請書所載\n    之車禍實害，此除經被告敘明在卷，並據證人陳光亮證述明\n    確，且有基隆市○○○道路交通事故現場草圖1 紙、車禍現\n    場暨車損照片16張附卷足考。則被告飲用酒類以後，確已處\n    於不能安全駕駛之狀態，當亦殆無可疑。\n二、論罪科刑：\n  (一)查被告服用酒類，不能安全駕駛動力交通工具，猶駕駛動力\n    交通工具行駛道路致為警查獲（100 年9 月15日）以後，刑\n    法第一百八十五條之三業於100 年11月30日修正公布，並自\n    100 年12月2 日開始施行（總統令100 年11月30日華一總字\n    第10000263911 號）。茲刑法第一百八十五條之三於「修正\n    前」，原係規定：「服用毒品、麻醉藥品、酒類或其他相類\n    之物，不能安全駕駛動力交通工具而駕駛者，處一年以下有\n    期徒刑、拘役或科或併科（新臺幣）十五萬元以下罰金。」\n    本次修正則增列第二項加重結果犯之規定，併將原條文移列\n    為同條第一項而規定「服用毒品、麻醉藥品、酒類或其他相\n    類之物，不能安全駕駛動力交通工具而駕駛者，處二年以下\n    有期徒刑、拘役或科或併科（新臺幣）二十萬元以下罰金。\n    」細繹修正前、後法律規定，有關「服用酒類，不能安全駕\n    駛動力交通工具，猶駕駛動力交通工具行駛道路」之犯罪構\n    成要件雖未更異，然其法律效果則有不同；亦即，修正後之\n    刑法第一百八十五條之三第一項，除將原「一年以下有期徒\n    刑」之刑度提高為「二年以下有期徒刑」，併將「新臺幣十\n    五萬元以下（刑法施行法第一條之一第一項規定參照）」之\n    罰金數額提高為「新臺幣二十萬元以下（刑法施行法第一條\n    之一第一項規定參照）」。是依修正前、後法律規定而為比\n    較適用，本案顯以修正前之舊法，較有利於被告，按諸刑法\n    第二條第一項所揭櫫之「從舊從輕」原則，本院自應以100\n    年11月30日修正公布前之刑法第一百八十五條之三，為本案\n    所應適用、處斷之法條罪名。\n  (二)是核被告如聲請書犯罪事實欄之所為，係犯100 年11月30日\n    修正公布前之刑法第一百八十五條之三之服用酒類不能安全\n    駕駛罪。\n  (三)本院審酌被告明知酒後駕車在道路上行駛，對一般往來之公\n    眾及駕駛人自身具有高度危險性，仍執意酒後駕車，既漠視\n    自身安危，更枉顧公眾安全；並考量被告為警依法施測所得\n    之酒精濃度值達0.79mg/L、本次復已致生交通實害（詳如聲\n    請書所載），兼衡量被告前即曾因酒後不能安全駕駛，而遭\n    法院判處罪刑確定，詳如本判決一(一)之所述，猶再犯本案而\n    未見改悔，暨其犯後態度等一切情狀，量處如主文所示之刑\n    ，併諭知易科罰金之折算標準。\n三、依刑事訴訟法第四百四十九條第一項前段、第四百五十四條\n    第二項，100 年11月30日修正公布前之刑法第一百八十五條\n    之三，刑法第二條第一項、第四十一條第一項前段，刑法施\n    行法第一條之一，逕以簡易判決處刑如主文。\n如不服本判決，得自收受送達之日起10日內，向本院提起上訴。"
  },
  "search": "臺灣基隆地方法院刑事簡易判決100年度基交簡字第810號聲請人臺灣基隆地方法院檢察署檢察官被告蕭建菲上列被告因公共危險案件，經檢察官聲請以簡易判決處刑（100年度偵字第5249號），本院判決如下：主文蕭建菲服用酒類，不能安全駕駛動力交通工具而駕駛，處有期徒刑月，如易科罰金，以新臺幣壹仟元折算壹日。事實及理由一、本件犯罪事實、證據，均引用檢察官聲請簡易判決處刑書（以下簡稱「聲請書」）之記載（詳如附件），並補充如下：(一)被告蕭建菲前於民國90年間，即曾因「服用酒類，不能安全駕駛動力交通工具而駕駛」，經本院於民國90年11月28日，以90年度基交簡字第720號判決拘役50日、緩刑二年確定（不構成累犯）；其後，又再因「服用酒類，不能安全駕駛動力交通工具而駕駛」，經本院於93年9月29日，以93年度基交簡字第414號判決拘役50日確定，93年12月28日易科罰金執行完畢（不構成累犯）。此除有臺灣高等法院被告前案紀錄表在卷可考，並據本院職權查核上開判決所載內容無訛。(二)按汽車駕駛人飲酒後，其吐氣所含酒精成分超過0.25mg/L者，不得駕車，道路交通安全規則第一百十四條第二款定有明文。參以相關醫學文獻之所載，亦可知酒精對人體之影響程度，係依血中酒精濃度而定，經換算結果，呼氣濃度達0.25mg/L（即血液中酒精濃度為50mg/dl）時，將造成輕度協調功能降低之輕度中毒症狀；呼氣濃度達0.5mg/L（即血液中酒精濃度為100mg/dl）時，將造成反應較慢、感覺減低、影響駕駛等輕到中度之中毒症狀；呼氣濃度達0.75mg/L（即血液中酒精濃度為150mg/dl）時，將造成思考改變、個性行為改變；呼氣濃度達1mg/L（即血液中酒精濃度為200mg/dl）時，將造成步態不穩、噁心嘔吐、精神混惑不清晰等中度酒精中毒症狀。此觀行政院國軍退除役官兵輔導委員會臺北榮民總醫院以88年8月5日北總內字第26868號函釋之內容即明。尤以酒精使用後對身體之影響，除自主神經系統亢奮與認知功能之暫時性缺損外，與駕駛能力有關而將受影響者，亦包括：對移動景物之追蹤能力。經強光照射後恢復視力。監視四周之注意力。許多人常因飲酒後無可自覺之生理反應，以致頭部功能已缺損，仍不自知而照常開車；雖每人飲酒後之自覺生理反應不一，然而同種族間之酒精清除率係相近，故一般而言，飲用同量酒精後對每個人身體之影響應類似，且酒精濃度與肇事率之關係為呼氣酒精濃度達0.25mg/L時，肇事率為未飲酒者之兩倍。此亦有臺北醫學院、中央警察大學製作之相關研究文獻資料可資參佐。據此對照本案被告為警查獲後，經施以酒精濃度測試之結果，其呼氣酒精濃度值達0.79mg/L（即血液中酒精濃度為158mg/dl）之情節；兼衡量被告果因酒後注意力下降而肇致如聲請書所載之車禍實害，此除經被告敘明在卷，並據證人陳光亮證述明確，且有基隆市○○○道路交通事故現場草圖1紙、車禍現場暨車損照片16張附卷足考。則被告飲用酒類以後，確已處於不能安全駕駛之狀態，當亦殆無可疑。二、論罪科刑：(一)查被告服用酒類，不能安全駕駛動力交通工具，猶駕駛動力交通工具行駛道路致為警查獲（100年9月15日）以後，刑法第一百八十五條之三業於100年11月30日修正公布，並自100年12月2日開始施行（總統令100年11月30日華一總字第10000263911號）。茲刑法第一百八十五條之三於「修正前」，原係規定：「服用毒品、麻醉藥品、酒類或其他相類之物，不能安全駕駛動力交通工具而駕駛者，處一年以下有期徒刑、拘役或科或併科（新臺幣）十五萬元以下罰金。」本次修正則增列第二項加重結果犯之規定，併將原條文移列為同條第一項而規定「服用毒品、麻醉藥品、酒類或其他相類之物，不能安全駕駛動力交通工具而駕駛者，處二年以下有期徒刑、拘役或科或併科（新臺幣）二十萬元以下罰金。」細繹修正前、後法律規定，有關「服用酒類，不能安全駕駛動力交通工具，猶駕駛動力交通工具行駛道路」之犯罪構成要件雖未更異，然其法律效果則有不同；亦即，修正後之刑法第一百八十五條之三第一項，除將原「一年以下有期徒刑」之刑度提高為「二年以下有期徒刑」，併將「新臺幣十五萬元以下（刑法施行法第一條之一第一項規定參照）」之罰金數額提高為「新臺幣二十萬元以下（刑法施行法第一條之一第一項規定參照）」。是依修正前、後法律規定而為比較適用，本案顯以修正前之舊法，較有利於被告，按諸刑法第二條第一項所揭櫫之「從舊從輕」原則，本院自應以100年11月30日修正公布前之刑法第一百八十五條之三，為本案所應適用、處斷之法條罪名。(二)是核被告如聲請書犯罪事實欄之所為，係犯100年11月30日修正公布前之刑法第一百八十五條之三之服用酒類不能安全駕駛罪。(三)本院審酌被告明知酒後駕車在道路上行駛，對一般往來之公眾及駕駛人自身具有高度危險性，仍執意酒後駕車，既漠視自身安危，更枉顧公眾安全；並考量被告為警依法施測所得之酒精濃度值達0.79mg/L、本次復已致生交通實害（詳如聲請書所載），兼衡量被告前即曾因酒後不能安全駕駛，而遭法院判處罪刑確定，詳如本判決一(一)之所述，猶再犯本案而未見改悔，暨其犯後態度等一切情狀，量處如主文所示之刑，併諭知易科罰金之折算標準。三、依刑事訴訟法第四百四十九條第一項前段、第四百五十四條第二項，100年11月30日修正公布前之刑法第一百八十五條之三，刑法第二條第一項、第四十一條第一項前段，刑法施行法第一條之一，逕以簡易判決處刑如主文。如不服本判決，得自收受送達之日起10日內，向本院提起上訴。中華民國100年12月8日基隆簡易庭法官王慧惠以上正本證明與原本無異。如不服本判決，應於判決送達後10日內，向本院提出上訴書狀，敘述上訴理由，上訴於本院合議庭，並按他造當事人之人數附具繕本。中華民國100年12月8日書記官王一芳附錄論罪法條：100年11月30日修正公布前刑法第185條之3服用毒品、麻醉藥品、酒類或其他相類之物，不能安全駕駛動力交通工具而駕駛者，處1年以下有期徒刑、拘役或科或併科15萬元以下罰金。附件：臺灣基隆地方法院檢察署檢察官聲請簡易判決處刑書100年度偵字第5249號被告蕭建菲男61歲（民國○○年○月○日生）住新北市萬里區雙興里豐廩14號居基隆市信義區○○○街7號2樓（指定送達處所）國民身分證統一編號：Ｚ000000000號上列被告因公共危險案件，業經偵查終結，認為宜聲請以簡易判決處刑，茲將犯罪事實及證據並所犯法條分敘如下：犯罪事實一、蕭建菲明知服用酒類過量會導致反應遲鈍、注意力減低之結果，此時若駕駛動力交通工具行駛於道路上，肇事之機率及危險性均遠較正常人為高，於民國100年9月15日傍晚在新北市萬里區雙興里豐廩14號戶籍地飲用2杯藥酒，雖稍事休息，惟尚呈反應遲緩、注意能力減低，而不能安全駕駛動力交通工具之程度，猶於晚間駕駛車牌號碼DH-1990號自小客車欲前往居所，於同日22時許途經基隆市○○區○○路與壽山路口時，不慎與陳光亮駕駛車牌號碼HF-1686號自小客車發生擦撞，警方到場處理，經測試蕭建菲呼氣中酒精含量為每公升0.79毫克二、案經基隆市警察局第二分局報告偵辦。證據並所犯法條一、上開犯罪事實，業據被告蕭建菲坦承不諱，復有呼氣測試紀錄、刑法第185條之3案件測試觀察紀錄表及現場照片附卷足資對照。本件事證明確，被告犯行已堪認定。二、核被告所為，係犯刑法第185條之3公共危險罪嫌。三、依刑事訴訟法第451條第1項聲請逕以簡易判決處刑。此致臺灣基隆地方法院基隆簡易庭中華民國100年11月25日檢察官王亞樵本件正本證明與原本無異中華民國100年11月30日書記官趙立慧附錄本案所犯法條全文中華民國刑法第185條之3服用毒品、麻醉藥品、酒類或其他相類之物，不能安全駕駛動力交通工具而駕駛者，處1年以下有期徒刑、拘役或科或併科15萬元以下罰金。附記事項：本件係依刑事訴訟法簡易程序辦理，法院簡易庭得不傳喚被告、輔佐人、告訴人、告發人等出庭即以簡易判決處刑；被告、被害人、告訴人等對於告訴乃論案件如已達成民事和解而要撤回告訴或對非告訴乃論案件認有受傳喚到庭陳述意見之必要時，請即另以書狀向簡易法庭陳述或請求傳訊。",
  "characters": {
    "judges": [
      "王慧惠"
    ],
    "prosecutors": [

    ],
    "lawyers": [

    ],
    "clerks": [
      "王一芳"
    ],
    "plaintiffs": [

    ],
    "defendants": [
      "蕭建菲",
      "蕭建菲  男  61歲（民國○○年○月○日生）"
    ],
    "prosecutor_office": [
      "臺灣基隆地方法院檢察署檢察官"
    ],
    "creditors": [

    ],
    "debtors": [

    ],
    "judicial_associate_officer": [

    ]
  },
  "adjudged_at": "2011-12-08",
  "created_at": "2016-02-13 13:06:45",
  "updated_at": "2016-02-13 13:06:45"
}