{
  "identify": "PCD-100-聲-5730-20111208-1",
  "court": {
    "name": "臺灣新北地方法院",
    "code": "PCD"
  },
  "division": {
    "name": "刑事",
    "code": "M"
  },
  "year": 100,
  "word": "聲",
  "number": "5730",
  "jcheck": "1",
  "reason": "聲請宣告沒收違禁物",
  "content": "臺灣板橋地方法院刑事裁定             100年度聲字第5730號\n聲  請  人  臺灣板橋地方法院檢察署檢察官\n被      告  陳建畯\n上列聲請人因聲請宣告沒收違禁物案件（100 年度聲沒字第899\n號），本院裁定如下：\n    主  文\n扣案之第二級毒品甲基安非他命壹袋（驗餘淨重零點玖陸柒捌公\n克）沒收銷燬之。\n    理  由\n一、聲請意旨略以：臺北市政府警察局萬華分局於民國100 年6\n    月9 日以北市警萬分刑字第10031257503 號移送書，移送被\n    告陳建畯涉犯施用第二級毒品甲基安非他命案件，業經臺灣\n    板橋地方法院檢察署檢察官以100 年度毒偵字第4152號為不\n    起訴處分確定，有該不起訴處分書1 份存卷可參。惟查，扣\n    案之白色結晶1 袋（驗餘淨重0.9678公克），經鑑驗含有第\n    二級毒品甲基安非他命成分，此有交通部民用航空局航空醫\n    務中心於100 年6 月22日出具航藥鑑字第1003486 號之毒品\n    鑑定書在卷足憑，因屬違禁物，爰依法聲請宣告沒收銷燬之\n    等語。\n二、按違禁物得單獨宣告沒收，且違禁物不問屬於犯罪行為人與\n    否沒收之，刑法第38條第1 項第1 款、第2 項、第40條第2\n    項定有明文；又甲基安非他命業經毒品危害防制條例第2 條\n    第2 項第2 款列為第二級毒品，並禁止製造、運輸、販賣、\n    施用、持有，而第二級毒品依同法第18條第1 項前段規定，\n    應予沒收銷燬之，毒品危害防制條例第2 條第2 項第2 款、\n    第4 條第2 項、第10條第2 項、第11條第2 項及第18條第1\n    項前段，亦定有明文。\n三、經查，扣案之白色透明結晶1 袋，經送交通部民用航空局航\n    空醫務中心檢驗結果確含有甲基安非他命成分，實稱毛重1.\n    1680公克，淨重0.9680公克，取樣0.0002公克，餘重0.9678\n    公克，有該中心100 年6 月22日出具之毒品鑑定書1 紙存卷\n    可稽。故上開扣案物自屬毒品危害防制條例第2 條第2 項第\n    2 款所列之第二級毒品，為違禁物，是除檢驗用罄部分業已\n    滅失毋庸宣告沒收銷燬外，驗餘淨重0.9678公克，聲請人依\n    法聲請宣告沒收銷燬之，經核於法尚無不合，爰依毒品危害\n    防制條例第18條第1 項前段，刑法第40條第2 項規定，裁定\n    如主文。\n中    華    民    國   100    年    12    月    8     日\n                  刑事第九庭    法  官  王士珮\n以上正本證明與原本無異。\n如不服本裁定應於送達後5 日內向本院提出抗告狀。\n                                書記官  金和國\n中    華    民    國   100    年    12    月    8     日",
  "structure": {
    "main": "扣案之第二級毒品甲基安非他命壹袋（驗餘淨重零點玖陸柒捌公\n克）沒收銷燬之。",
    "reason": "一、聲請意旨略以：臺北市政府警察局萬華分局於民國100 年6\n    月9 日以北市警萬分刑字第10031257503 號移送書，移送被\n    告陳建畯涉犯施用第二級毒品甲基安非他命案件，業經臺灣\n    板橋地方法院檢察署檢察官以100 年度毒偵字第4152號為不\n    起訴處分確定，有該不起訴處分書1 份存卷可參。惟查，扣\n    案之白色結晶1 袋（驗餘淨重0.9678公克），經鑑驗含有第\n    二級毒品甲基安非他命成分，此有交通部民用航空局航空醫\n    務中心於100 年6 月22日出具航藥鑑字第1003486 號之毒品\n    鑑定書在卷足憑，因屬違禁物，爰依法聲請宣告沒收銷燬之\n    等語。\n二、按違禁物得單獨宣告沒收，且違禁物不問屬於犯罪行為人與\n    否沒收之，刑法第38條第1 項第1 款、第2 項、第40條第2\n    項定有明文；又甲基安非他命業經毒品危害防制條例第2 條\n    第2 項第2 款列為第二級毒品，並禁止製造、運輸、販賣、\n    施用、持有，而第二級毒品依同法第18條第1 項前段規定，\n    應予沒收銷燬之，毒品危害防制條例第2 條第2 項第2 款、\n    第4 條第2 項、第10條第2 項、第11條第2 項及第18條第1\n    項前段，亦定有明文。\n三、經查，扣案之白色透明結晶1 袋，經送交通部民用航空局航\n    空醫務中心檢驗結果確含有甲基安非他命成分，實稱毛重1.\n    1680公克，淨重0.9680公克，取樣0.0002公克，餘重0.9678\n    公克，有該中心100 年6 月22日出具之毒品鑑定書1 紙存卷\n    可稽。故上開扣案物自屬毒品危害防制條例第2 條第2 項第\n    2 款所列之第二級毒品，為違禁物，是除檢驗用罄部分業已\n    滅失毋庸宣告沒收銷燬外，驗餘淨重0.9678公克，聲請人依\n    法聲請宣告沒收銷燬之，經核於法尚無不合，爰依毒品危害\n    防制條例第18條第1 項前段，刑法第40條第2 項規定，裁定\n    如主文。"
  },
  "search": "臺灣板橋地方法院刑事裁定100年度聲字第5730號聲請人臺灣板橋地方法院檢察署檢察官被告陳建畯上列聲請人因聲請宣告沒收違禁物案件（100年度聲沒字第899號），本院裁定如下：主文扣案之第二級毒品甲基安非他命壹袋（驗餘淨重零點玖陸柒捌公克）沒收銷燬之。理由一、聲請意旨略以：臺北市政府警察局萬華分局於民國100年6月9日以北市警萬分刑字第10031257503號移送書，移送被告陳建畯涉犯施用第二級毒品甲基安非他命案件，業經臺灣板橋地方法院檢察署檢察官以100年度毒偵字第4152號為不起訴處分確定，有該不起訴處分書1份存卷可參。惟查，扣案之白色結晶1袋（驗餘淨重0.9678公克），經鑑驗含有第二級毒品甲基安非他命成分，此有交通部民用航空局航空醫務中心於100年6月22日出具航藥鑑字第1003486號之毒品鑑定書在卷足憑，因屬違禁物，爰依法聲請宣告沒收銷燬之等語。二、按違禁物得單獨宣告沒收，且違禁物不問屬於犯罪行為人與否沒收之，刑法第38條第1項第1款、第2項、第40條第2項定有明文；又甲基安非他命業經毒品危害防制條例第2條第2項第2款列為第二級毒品，並禁止製造、運輸、販賣、施用、持有，而第二級毒品依同法第18條第1項前段規定，應予沒收銷燬之，毒品危害防制條例第2條第2項第2款、第4條第2項、第10條第2項、第11條第2項及第18條第1項前段，亦定有明文。三、經查，扣案之白色透明結晶1袋，經送交通部民用航空局航空醫務中心檢驗結果確含有甲基安非他命成分，實稱毛重1.1680公克，淨重0.9680公克，取樣0.0002公克，餘重0.9678公克，有該中心100年6月22日出具之毒品鑑定書1紙存卷可稽。故上開扣案物自屬毒品危害防制條例第2條第2項第2款所列之第二級毒品，為違禁物，是除檢驗用罄部分業已滅失毋庸宣告沒收銷燬外，驗餘淨重0.9678公克，聲請人依法聲請宣告沒收銷燬之，經核於法尚無不合，爰依毒品危害防制條例第18條第1項前段，刑法第40條第2項規定，裁定如主文。中華民國100年12月8日刑事第九庭法官王士珮以上正本證明與原本無異。如不服本裁定應於送達後5日內向本院提出抗告狀。書記官金和國中華民國100年12月8日",
  "characters": {
    "judges": [
      "王士珮"
    ],
    "prosecutors": [

    ],
    "lawyers": [

    ],
    "clerks": [
      "金和國"
    ],
    "plaintiffs": [

    ],
    "defendants": [
      "陳建畯"
    ],
    "prosecutor_office": [
      "臺灣板橋地方法院檢察署檢察官"
    ],
    "creditors": [

    ],
    "debtors": [

    ],
    "judicial_associate_officer": [

    ]
  },
  "adjudged_at": "2011-12-08",
  "created_at": "2016-02-13 12:52:58",
  "updated_at": "2016-02-13 12:52:58"
}