{
  "identify": "PCD-100-聲-5667-20111207-1",
  "court": {
    "name": "臺灣新北地方法院",
    "code": "PCD"
  },
  "division": {
    "name": "刑事",
    "code": "M"
  },
  "year": 100,
  "word": "聲",
  "number": "5667",
  "jcheck": "1",
  "reason": "沒入保證金",
  "content": "臺灣板橋地方法院刑事裁定             100年度聲字第5667號\n聲  請  人  臺灣板橋地方法院檢察署檢察官\n具  保  人  王蔡柳枝\n被      告  楊    立\n上列聲請人因被告犯賭博案件，聲請沒入保證金（100年度執聲\n沒字第768號），本院裁定如下：\n    主  文\n聲請駁回。\n    理  由\n一、本件聲請意旨略以：具保人王蔡柳枝因被告楊立犯賭博案件\n    ，經依臺灣板橋地方法院檢察署檢察官指定之保證金額新臺\n    幣1萬元，出具現金保證後，將被告釋放，茲因該被告逃匿\n    ，依刑事訴訟法第118條之規定，應沒入具保人繳納之保證\n    金（刑保字第10001275號，聲請書誤載為「100刑保字第100\n    01275號」），爰依同法第121條第1項規定聲請沒入具保人\n    繳納之保證金等語。\n二、按具保之被告逃匿者，應命具保人繳納指定之保證金額，並\n    沒入之；不繳納者，強制執行；保證金已繳納者，以法院裁\n    定沒入之，刑事訴訟法第118 條第1 項、第121 條第1 項分\n    別定有明文。又具保證書或繳納保證金之第三人，將被告預\n    備逃匿情形，於得以防止之際報告法院、檢察官或司法警察\n    官而聲請退保者，得准其退保，同法第119條第2項前段亦定\n    有明文，是以因具保停止羈押之被告，經依法傳拘未獲，固\n    得裁定沒入保證金，但若於為裁定沒入前，先行通知具保人\n    限期命將被告送案，於無效果時，再為沒入之裁定，一方面\n    可明瞭被告是否果真逃匿，一方面可使具保人對於沒入保證\n    金之裁定更加信服（參照司法院民國70年10月28日〈70〉廳\n    刑一字第1104號函文意旨）。\n三、經查本件具保人王蔡柳枝因被告楊立犯賭博案件，經依臺灣\n    板橋地方法院檢察署檢察官指定之保證金額1萬元，出具現\n    金保證後，將被告釋放，嗣該案經本院以100年度簡字第386\n    2號判處有期徒刑2月，如易科罰金以新臺幣1,000元折算1日\n    確定。被告於執行階段經同署檢察官依法傳喚，並通知具保\n    人帶同被告到案接受執行，嗣被告於100年8月11日到案請求\n    易科罰金分期付款，經聲請人諭知被告准予分3期繳納罰金\n    ，未按時繳納者，將逕行撤銷易科罰金之易刑處分而直接執\n    行本刑，並得逕行拘提，惟被告雖於同日繳納第1期罰金1萬\n    元，但未如期於同年9月11日、10月11日到案繳納剩餘2期之\n    罰金2萬1千元、3萬元，且經拘提、傳喚亦不到案執行等情\n    ，固有保證金收據、被告及具保人之戶役政連結作業系統查\n    詢資料各1份、通知書、通知送達證書、執行傳票送達證書\n    各2 份、訊問筆錄、執行案件分期繳納罰金執行進行表、自\n    行收納款項收據各1份、拘票暨拘提報告書各4份、執行傳票\n    送達證書2份、執行案件資料表、臺灣高等法院在監在押全\n    國紀錄表各1份附卷可稽。然觀諸卷附資料，就被告嗣後應\n    遵期到案繳納罰金，卻逾期未到案執行部分，聲請人並未另\n    行通知具保人上開事項，並令其攜同被告如期到案執行，故\n    本件具保人在未受合法通知之情形下，自無從得知前已到案\n    執行之被告，嗣後未遵期執行之情形，難期具保人得以履行\n    其保證人之責任，以促被告到庭，或將被告預備逃匿之情形\n    報告法院而免除其具保責任，揆諸前開說明，本件聲請人聲\n    請沒入具保人所繳納之保證金，尚有未合，應予駁回。\n四、應依刑事訴訟法第220 條，裁定如主文。\n中    華    民    國   100    年    12    月    7     日\n                  刑事第十庭    法  官    陳昭筠\n以上正本證明與原本無異。\n如不服本裁定應於送達後5日內向本院提出抗告狀。\n                                書記官    黃文儀\n中    華    民    國   100    年    12    月    12    日",
  "structure": {
    "main": "聲請駁回。",
    "reason": "一、本件聲請意旨略以：具保人王蔡柳枝因被告楊立犯賭博案件\n    ，經依臺灣板橋地方法院檢察署檢察官指定之保證金額新臺\n    幣1萬元，出具現金保證後，將被告釋放，茲因該被告逃匿\n    ，依刑事訴訟法第118條之規定，應沒入具保人繳納之保證\n    金（刑保字第10001275號，聲請書誤載為「100刑保字第100\n    01275號」），爰依同法第121條第1項規定聲請沒入具保人\n    繳納之保證金等語。\n二、按具保之被告逃匿者，應命具保人繳納指定之保證金額，並\n    沒入之；不繳納者，強制執行；保證金已繳納者，以法院裁\n    定沒入之，刑事訴訟法第118 條第1 項、第121 條第1 項分\n    別定有明文。又具保證書或繳納保證金之第三人，將被告預\n    備逃匿情形，於得以防止之際報告法院、檢察官或司法警察\n    官而聲請退保者，得准其退保，同法第119條第2項前段亦定\n    有明文，是以因具保停止羈押之被告，經依法傳拘未獲，固\n    得裁定沒入保證金，但若於為裁定沒入前，先行通知具保人\n    限期命將被告送案，於無效果時，再為沒入之裁定，一方面\n    可明瞭被告是否果真逃匿，一方面可使具保人對於沒入保證\n    金之裁定更加信服（參照司法院民國70年10月28日〈70〉廳\n    刑一字第1104號函文意旨）。\n三、經查本件具保人王蔡柳枝因被告楊立犯賭博案件，經依臺灣\n    板橋地方法院檢察署檢察官指定之保證金額1萬元，出具現\n    金保證後，將被告釋放，嗣該案經本院以100年度簡字第386\n    2號判處有期徒刑2月，如易科罰金以新臺幣1,000元折算1日\n    確定。被告於執行階段經同署檢察官依法傳喚，並通知具保\n    人帶同被告到案接受執行，嗣被告於100年8月11日到案請求\n    易科罰金分期付款，經聲請人諭知被告准予分3期繳納罰金\n    ，未按時繳納者，將逕行撤銷易科罰金之易刑處分而直接執\n    行本刑，並得逕行拘提，惟被告雖於同日繳納第1期罰金1萬\n    元，但未如期於同年9月11日、10月11日到案繳納剩餘2期之\n    罰金2萬1千元、3萬元，且經拘提、傳喚亦不到案執行等情\n    ，固有保證金收據、被告及具保人之戶役政連結作業系統查\n    詢資料各1份、通知書、通知送達證書、執行傳票送達證書\n    各2 份、訊問筆錄、執行案件分期繳納罰金執行進行表、自\n    行收納款項收據各1份、拘票暨拘提報告書各4份、執行傳票\n    送達證書2份、執行案件資料表、臺灣高等法院在監在押全\n    國紀錄表各1份附卷可稽。然觀諸卷附資料，就被告嗣後應\n    遵期到案繳納罰金，卻逾期未到案執行部分，聲請人並未另\n    行通知具保人上開事項，並令其攜同被告如期到案執行，故\n    本件具保人在未受合法通知之情形下，自無從得知前已到案\n    執行之被告，嗣後未遵期執行之情形，難期具保人得以履行\n    其保證人之責任，以促被告到庭，或將被告預備逃匿之情形\n    報告法院而免除其具保責任，揆諸前開說明，本件聲請人聲\n    請沒入具保人所繳納之保證金，尚有未合，應予駁回。\n四、應依刑事訴訟法第220 條，裁定如主文。"
  },
  "search": "臺灣板橋地方法院刑事裁定100年度聲字第5667號聲請人臺灣板橋地方法院檢察署檢察官具保人王蔡柳枝被告楊立上列聲請人因被告犯賭博案件，聲請沒入保證金（100年度執聲沒字第768號），本院裁定如下：主文聲請駁回。理由一、本件聲請意旨略以：具保人王蔡柳枝因被告楊立犯賭博案件，經依臺灣板橋地方法院檢察署檢察官指定之保證金額新臺幣1萬元，出具現金保證後，將被告釋放，茲因該被告逃匿，依刑事訴訟法第118條之規定，應沒入具保人繳納之保證金（刑保字第10001275號，聲請書誤載為「100刑保字第10001275號」），爰依同法第121條第1項規定聲請沒入具保人繳納之保證金等語。二、按具保之被告逃匿者，應命具保人繳納指定之保證金額，並沒入之；不繳納者，強制執行；保證金已繳納者，以法院裁定沒入之，刑事訴訟法第118條第1項、第121條第1項分別定有明文。又具保證書或繳納保證金之第三人，將被告預備逃匿情形，於得以防止之際報告法院、檢察官或司法警察官而聲請退保者，得准其退保，同法第119條第2項前段亦定有明文，是以因具保停止羈押之被告，經依法傳拘未獲，固得裁定沒入保證金，但若於為裁定沒入前，先行通知具保人限期命將被告送案，於無效果時，再為沒入之裁定，一方面可明瞭被告是否果真逃匿，一方面可使具保人對於沒入保證金之裁定更加信服（參照司法院民國70年10月28日〈70〉廳刑一字第1104號函文意旨）。三、經查本件具保人王蔡柳枝因被告楊立犯賭博案件，經依臺灣板橋地方法院檢察署檢察官指定之保證金額1萬元，出具現金保證後，將被告釋放，嗣該案經本院以100年度簡字第3862號判處有期徒刑2月，如易科罰金以新臺幣1,000元折算1日確定。被告於執行階段經同署檢察官依法傳喚，並通知具保人帶同被告到案接受執行，嗣被告於100年8月11日到案請求易科罰金分期付款，經聲請人諭知被告准予分3期繳納罰金，未按時繳納者，將逕行撤銷易科罰金之易刑處分而直接執行本刑，並得逕行拘提，惟被告雖於同日繳納第1期罰金1萬元，但未如期於同年9月11日、10月11日到案繳納剩餘2期之罰金2萬1千元、3萬元，且經拘提、傳喚亦不到案執行等情，固有保證金收據、被告及具保人之戶役政連結作業系統查詢資料各1份、通知書、通知送達證書、執行傳票送達證書各2份、訊問筆錄、執行案件分期繳納罰金執行進行表、自行收納款項收據各1份、拘票暨拘提報告書各4份、執行傳票送達證書2份、執行案件資料表、臺灣高等法院在監在押全國紀錄表各1份附卷可稽。然觀諸卷附資料，就被告嗣後應遵期到案繳納罰金，卻逾期未到案執行部分，聲請人並未另行通知具保人上開事項，並令其攜同被告如期到案執行，故本件具保人在未受合法通知之情形下，自無從得知前已到案執行之被告，嗣後未遵期執行之情形，難期具保人得以履行其保證人之責任，以促被告到庭，或將被告預備逃匿之情形報告法院而免除其具保責任，揆諸前開說明，本件聲請人聲請沒入具保人所繳納之保證金，尚有未合，應予駁回。四、應依刑事訴訟法第220條，裁定如主文。中華民國100年12月7日刑事第十庭法官陳昭筠以上正本證明與原本無異。如不服本裁定應於送達後5日內向本院提出抗告狀。書記官黃文儀中華民國100年12月12日",
  "characters": {
    "judges": [
      "陳昭筠"
    ],
    "prosecutors": [

    ],
    "lawyers": [

    ],
    "clerks": [
      "黃文儀"
    ],
    "plaintiffs": [

    ],
    "defendants": [
      "楊    立"
    ],
    "prosecutor_office": [
      "臺灣板橋地方法院檢察署檢察官"
    ],
    "creditors": [

    ],
    "debtors": [

    ],
    "judicial_associate_officer": [

    ]
  },
  "adjudged_at": "2011-12-07",
  "created_at": "2016-02-13 13:01:24",
  "updated_at": "2016-02-13 13:01:24"
}