{
  "identify": "PCD-100-訴-2592-20111208-1",
  "court": {
    "name": "臺灣新北地方法院",
    "code": "PCD"
  },
  "division": {
    "name": "民事",
    "code": "V"
  },
  "year": 100,
  "word": "訴",
  "number": "2592",
  "jcheck": "1",
  "reason": "侵權行為損害賠償等",
  "content": "臺灣板橋地方法院民事裁定             100年度訴字第2592號\n原      告  林介立\n被      告  蕭羽茹\n被      告  汪君惠\n上列當事人間請求侵權行為損害賠償等事件，本院裁定如下：\n    主  文\n本件移送臺灣澎湖地方法院。\n    理  由\n一、按訴訟之全部或一部，法院認為無管轄權者，依原告聲請或\n    依職權以裁定移送其管轄法院，民事訴訟法第28條第1項定\n    有明文。\n二、本件原告起訴時（民國100年11月23日）被告之住、居所地\n    均係在澎湖縣，有被告戶籍查詢資料及被告汪君惠在監、在\n    押全國紀錄表（被告汪惠君於100年9月5日解還澎湖監獄）\n    在卷可佐，依民事訴訟第1條第1項之規定，自應由臺灣澎湖\n    地方法院管轄。玆原告向無管轄權之本院起訴，顯係違誤，\n    爰依職權將本件移送於該管轄法院。\n三、依首開法條裁定如主文。\n中    華    民    國   100    年    12    月    8     日\n                  民事第一庭    法  官  黃信滿\n以上正本係照原本作成\n如對本裁定抗告須於裁定送達後10日內向本院提出抗告狀，並應\n繳納抗告費新台幣1,000元整。\n中    華    民    國   100    年    12    月    8     日\n                                書記官  莊琬婷",
  "structure": {
    "main": "本件移送臺灣澎湖地方法院。",
    "reason": "一、按訴訟之全部或一部，法院認為無管轄權者，依原告聲請或\n    依職權以裁定移送其管轄法院，民事訴訟法第28條第1項定\n    有明文。\n二、本件原告起訴時（民國100年11月23日）被告之住、居所地\n    均係在澎湖縣，有被告戶籍查詢資料及被告汪君惠在監、在\n    押全國紀錄表（被告汪惠君於100年9月5日解還澎湖監獄）\n    在卷可佐，依民事訴訟第1條第1項之規定，自應由臺灣澎湖\n    地方法院管轄。玆原告向無管轄權之本院起訴，顯係違誤，\n    爰依職權將本件移送於該管轄法院。\n三、依首開法條裁定如主文。"
  },
  "search": "臺灣板橋地方法院民事裁定100年度訴字第2592號原告林介立被告蕭羽茹被告汪君惠上列當事人間請求侵權行為損害賠償等事件，本院裁定如下：主文本件移送臺灣澎湖地方法院。理由一、按訴訟之全部或一部，法院認為無管轄權者，依原告聲請或依職權以裁定移送其管轄法院，民事訴訟法第28條第1項定有明文。二、本件原告起訴時（民國100年11月23日）被告之住、居所地均係在澎湖縣，有被告戶籍查詢資料及被告汪君惠在監、在押全國紀錄表（被告汪惠君於100年9月5日解還澎湖監獄）在卷可佐，依民事訴訟第1條第1項之規定，自應由臺灣澎湖地方法院管轄。玆原告向無管轄權之本院起訴，顯係違誤，爰依職權將本件移送於該管轄法院。三、依首開法條裁定如主文。中華民國100年12月8日民事第一庭法官黃信滿以上正本係照原本作成如對本裁定抗告須於裁定送達後10日內向本院提出抗告狀，並應繳納抗告費新台幣1,000元整。中華民國100年12月8日書記官莊琬婷",
  "characters": {
    "judges": [
      "黃信滿"
    ],
    "prosecutors": [

    ],
    "lawyers": [

    ],
    "clerks": [

    ],
    "plaintiffs": [
      "林介立"
    ],
    "defendants": [
      "蕭羽茹",
      "被      告  汪君惠"
    ],
    "prosecutor_office": [

    ],
    "creditors": [

    ],
    "debtors": [

    ],
    "judicial_associate_officer": [

    ]
  },
  "adjudged_at": "2011-12-08",
  "created_at": "2016-02-13 12:50:39",
  "updated_at": "2016-02-13 12:50:39"
}