{
  "identify": "CYD-100-交訴-12-20111031-1",
  "court": {
    "name": "臺灣嘉義地方法院",
    "code": "CYD"
  },
  "division": {
    "name": "刑事",
    "code": "M"
  },
  "year": 100,
  "word": "交訴",
  "number": "12",
  "jcheck": "1",
  "reason": "公共危險等",
  "content": "臺灣嘉義地方法院刑事判決             100年度交訴字第12號\n公  訴  人  臺灣嘉義地方法院檢察署檢察官\n被      告  王金竹\n選任辯護人  黃曜春律師\n上列被告因公共危險等案件，經檢察官提起公訴（99年度偵字第\n8015號），本院就過失傷害部份，判決如下：\n    主  文\n王金竹被訴業務過失傷害部分公訴不受理。\n    理  由\n一、公訴意旨略以，被告王金竹任職其胞姐所開設之公司擔任司\n    機，平日駕駛車輛載送貨物予顧客，以從事駕駛為業，為從\n    事業務之人，於民國99年9 月12日駕駛車牌號碼910-TP號自\n    用大貨車送貨至雲林縣北港鎮予客戶後，欲返回臺南市，於\n    同日凌晨5 時40分許，沿嘉義縣六腳鄉○○○○○路北往南方\n    向行駛，途經嘉義縣六腳鄉○○○○○路80.8公里處時，本應\n    注意行車速度，依速限標誌或標線之規定，且汽車在同一車\n    道行駛時，除擬超越前車外，後車與前車之間應保持隨時可\n    以煞停之距離，並應注意車前狀況及兩車併行之間隔，隨時\n    採取必要之安全措施，而當地速限為每小時60公里，又當時\n    天候晴、早晨有暮光、柏油路面乾燥、無缺陷、無障礙物、\n    視距良好，別無不能注意之情事，王金竹竟以每小時70至80\n    公里之速度超速行駛，亦疏未注意與前車保持隨時可以煞停\n    之距離及車前狀況，而自後方追撞同向前方由吳美珠所騎乘\n    之腳踏車，致吳美珠人、車倒地，因而受有腦震盪、左側第\n    五蹠骨閉鎖性骨折、頭皮撕裂傷3 公分、腰腹部至臀部挫傷\n    約2010公分瘀血、擦傷122  公分、102 公分、6 1\n    公分、左肩挫傷併擦傷6  6 公分、左手第五指挫傷2 2\n    公分等傷害，因認被告涉犯刑法第284 條第2 項前段業務過\n    失傷害罪嫌。\n二、按告訴乃論之罪，告訴人於第一審辯論終結前得撤回其告訴\n    ，又告訴經撤回者，應諭知不受理之判決，刑事訴訟法第23\n    8 條第1 項、第303 條第3 款分別定有明文。\n三、經查，公訴意旨認被告王金竹所犯刑法第284 條第2 項前段\n    之業務過失傷害罪嫌，依同法第287 條前段之規定，須告訴\n    乃論。茲告訴人吳美珠已與被告王金竹達成調解，並具狀撤\n    回本件告訴，有撤回告訴狀乙份附卷可稽，依上揭規定，自\n    應諭知不受理之判決，並不經言詞辯論為之，至被告所涉公\n    共危險部分，另行判決。\n四、依刑事訴訟法第303 條第3 款、第307 條，判決如主文。\n中    華    民    國  100     年    10    月    31    日\n                  刑事第三庭    審判長法  官  陳仁智\n                                      法  官  鄭雅文\n                                      法  官  李秋瑩\n以上正本證明與原本無異。\n如不服本判決應於收受判決後10日內向本院提出上訴書狀，並應\n敘述具體理由；其未敘述上訴理由者，應於上訴期間屆滿後20日\n內向本院補提理由書（均須按他造當事人之人數附繕本）「切勿\n逕送上級法院」。告訴人或被害人如對於本判決不服者，應具備\n理由請求檢察官上訴，其上訴期間之計算係以檢察官收受判決正\n本之日期為準。\n中    華    民    國  100     年    10    月    31    日\n                                      書記官  劉英芬",
  "structure": {
    "main": "王金竹被訴業務過失傷害部分公訴不受理。",
    "reason": "一、公訴意旨略以，被告王金竹任職其胞姐所開設之公司擔任司\n    機，平日駕駛車輛載送貨物予顧客，以從事駕駛為業，為從\n    事業務之人，於民國99年9 月12日駕駛車牌號碼910-TP號自\n    用大貨車送貨至雲林縣北港鎮予客戶後，欲返回臺南市，於\n    同日凌晨5 時40分許，沿嘉義縣六腳鄉○○○○○路北往南方\n    向行駛，途經嘉義縣六腳鄉○○○○○路80.8公里處時，本應\n    注意行車速度，依速限標誌或標線之規定，且汽車在同一車\n    道行駛時，除擬超越前車外，後車與前車之間應保持隨時可\n    以煞停之距離，並應注意車前狀況及兩車併行之間隔，隨時\n    採取必要之安全措施，而當地速限為每小時60公里，又當時\n    天候晴、早晨有暮光、柏油路面乾燥、無缺陷、無障礙物、\n    視距良好，別無不能注意之情事，王金竹竟以每小時70至80\n    公里之速度超速行駛，亦疏未注意與前車保持隨時可以煞停\n    之距離及車前狀況，而自後方追撞同向前方由吳美珠所騎乘\n    之腳踏車，致吳美珠人、車倒地，因而受有腦震盪、左側第\n    五蹠骨閉鎖性骨折、頭皮撕裂傷3 公分、腰腹部至臀部挫傷\n    約2010公分瘀血、擦傷122  公分、102 公分、6 1\n    公分、左肩挫傷併擦傷6  6 公分、左手第五指挫傷2 2\n    公分等傷害，因認被告涉犯刑法第284 條第2 項前段業務過\n    失傷害罪嫌。\n二、按告訴乃論之罪，告訴人於第一審辯論終結前得撤回其告訴\n    ，又告訴經撤回者，應諭知不受理之判決，刑事訴訟法第23\n    8 條第1 項、第303 條第3 款分別定有明文。\n三、經查，公訴意旨認被告王金竹所犯刑法第284 條第2 項前段\n    之業務過失傷害罪嫌，依同法第287 條前段之規定，須告訴\n    乃論。茲告訴人吳美珠已與被告王金竹達成調解，並具狀撤\n    回本件告訴，有撤回告訴狀乙份附卷可稽，依上揭規定，自\n    應諭知不受理之判決，並不經言詞辯論為之，至被告所涉公\n    共危險部分，另行判決。\n四、依刑事訴訟法第303 條第3 款、第307 條，判決如主文。"
  },
  "search": "臺灣嘉義地方法院刑事判決100年度交訴字第12號公訴人臺灣嘉義地方法院檢察署檢察官被告王金竹選任辯護人黃曜春律師上列被告因公共危險等案件，經檢察官提起公訴（99年度偵字第8015號），本院就過失傷害部份，判決如下：主文王金竹被訴業務過失傷害部分公訴不受理。理由一、公訴意旨略以，被告王金竹任職其胞姐所開設之公司擔任司機，平日駕駛車輛載送貨物予顧客，以從事駕駛為業，為從事業務之人，於民國99年9月12日駕駛車牌號碼910-TP號自用大貨車送貨至雲林縣北港鎮予客戶後，欲返回臺南市，於同日凌晨5時40分許，沿嘉義縣六腳鄉○○○○○路北往南方向行駛，途經嘉義縣六腳鄉○○○○○路80.8公里處時，本應注意行車速度，依速限標誌或標線之規定，且汽車在同一車道行駛時，除擬超越前車外，後車與前車之間應保持隨時可以煞停之距離，並應注意車前狀況及兩車併行之間隔，隨時採取必要之安全措施，而當地速限為每小時60公里，又當時天候晴、早晨有暮光、柏油路面乾燥、無缺陷、無障礙物、視距良好，別無不能注意之情事，王金竹竟以每小時70至80公里之速度超速行駛，亦疏未注意與前車保持隨時可以煞停之距離及車前狀況，而自後方追撞同向前方由吳美珠所騎乘之腳踏車，致吳美珠人、車倒地，因而受有腦震盪、左側第五蹠骨閉鎖性骨折、頭皮撕裂傷3公分、腰腹部至臀部挫傷約2010公分瘀血、擦傷122公分、102公分、61公分、左肩挫傷併擦傷66公分、左手第五指挫傷22公分等傷害，因認被告涉犯刑法第284條第2項前段業務過失傷害罪嫌。二、按告訴乃論之罪，告訴人於第一審辯論終結前得撤回其告訴，又告訴經撤回者，應諭知不受理之判決，刑事訴訟法第238條第1項、第303條第3款分別定有明文。三、經查，公訴意旨認被告王金竹所犯刑法第284條第2項前段之業務過失傷害罪嫌，依同法第287條前段之規定，須告訴乃論。茲告訴人吳美珠已與被告王金竹達成調解，並具狀撤回本件告訴，有撤回告訴狀乙份附卷可稽，依上揭規定，自應諭知不受理之判決，並不經言詞辯論為之，至被告所涉公共危險部分，另行判決。四、依刑事訴訟法第303條第3款、第307條，判決如主文。中華民國100年10月31日刑事第三庭審判長法官陳仁智法官鄭雅文法官李秋瑩以上正本證明與原本無異。如不服本判決應於收受判決後10日內向本院提出上訴書狀，並應敘述具體理由；其未敘述上訴理由者，應於上訴期間屆滿後20日內向本院補提理由書（均須按他造當事人之人數附繕本）「切勿逕送上級法院」。告訴人或被害人如對於本判決不服者，應具備理由請求檢察官上訴，其上訴期間之計算係以檢察官收受判決正本之日期為準。中華民國100年10月31日書記官劉英芬",
  "characters": {
    "judges": [
      "陳仁智",
      "鄭雅文",
      "李秋瑩"
    ],
    "prosecutors": [

    ],
    "lawyers": [
      "黃曜春"
    ],
    "clerks": [

    ],
    "plaintiffs": [

    ],
    "defendants": [
      "王金竹"
    ],
    "prosecutor_office": [
      "臺灣嘉義地方法院檢察署檢察官"
    ],
    "creditors": [

    ],
    "debtors": [

    ],
    "judicial_associate_officer": [

    ]
  },
  "adjudged_at": "2011-10-31",
  "created_at": "2016-02-14 08:44:43",
  "updated_at": "2016-02-14 08:44:43"
}