{
  "identify": "IPC-100-行商訴-61-20111031-2",
  "court": {
    "name": "智慧財產法院",
    "code": "IPC"
  },
  "division": {
    "name": "行政",
    "code": "A"
  },
  "year": 100,
  "word": "行商訴",
  "number": "61",
  "jcheck": "2",
  "reason": "商標異議",
  "content": "智慧財產法院行政判決\n                                   100年度行商訴字第61號\n                                    100年10月6日辯論終結\n原      告  艾凘克企業股份有限公司\n代  表  人  吳皇明         \n訴訟代理人  黃照律師\n被      告  經濟部智慧財產局設臺北市大安區辛亥路二段185\n代  表  人  王美花（局長） \n訴訟代理人  林政憓        \n上列當事人間因商標異議事件，原告不服經濟部中華民國100 年\n3 月16日經訴字第10006097290 號訴願決定，提起行政訴訟，並\n經本院裁定命參加人獨立參加本件被告之訴訟，本院判決如下：\n    主  文\n原告之訴駁回。\n訴訟費用由原告負擔。\n    事實及理由\n一、事實概要：訴外人耐吉斯實業股份有限公司（下稱耐吉斯公\n    司）於民國98年1 月15日以「OPTI-PRO」商標，指定使用於\n    商標法施行細則第13條所定修正前商品及服務分類表第31類\n    之「寵物飼料、非醫用飼料添加物、非醫用飼料添加劑、動\n    物用奶粉、狗飼料、貓飼料、狗餅乾、寵物用食品、動物用\n    飼養劑、動物可食用咀嚼物、寵物用飲料」商品，向被告申\n    請註冊，嗣於98年8 月13日變更申請人為原告。經被告審查\n    ，准列為註冊第1378519 號商標（下稱系爭商標）。嗣參加\n    人美商瑪斯公司以系爭商標與據以異議之註冊第842395號「\n    OPTIMA」商標（下稱據以異議商標）構成近似為由，主張系\n    爭商標違反商標法第23條第1 項第12款及第13款規定，對之\n    提起異議。經被告審查，認系爭商標與據以異議商標構成近\n    似，復均指定使用於寵物飼料等類似商品，且系爭商標之註\n    冊申請難謂為善意，有致相關消費者混淆誤認之虞，而以99\n    年11月29日中台異字第981033號商標異議審定書為系爭商標\n    之註冊應予撤銷之處分。原告不服，提起訴願，經訴願機關\n    決定駁回，原告猶未甘服，遂向本院提起行政訴訟。本院因\n    認本件訴訟之結果對於參加人之權利或利益將有影響，乃依\n    行政訴訟法第42條第1 項規定，依職權裁定命參加人獨立參\n    加本件被告之訴訟。\n二、本件原告主張：\n  (一)有關兩造商標並未構成近似之判斷部分：\n  1.就外觀而言：系爭商標係由「OPTI」及「PRO 」二組外文字\n    母及於中間加入「－」符號所組合，乃不可分割之整體，而\n    據以異議商標僅為由五個英文字母「OPTIMA」併列組成，就\n    外觀而言，二商標之整體排列組合及字數多寡等形態皆迥然\n    有別，縱使二商標之字首皆為「OPTI」，惟判斷是否混淆誤\n    認係應以各項因素交叉審酌，而不得以單一因素為最終判斷\n    近似之依歸。\n  2.就讀音而言：系爭商標與據以異議商標雖均有外文「OPTI」\n    ，惟整體之於連貫唱呼之際，後者除「OPTI」及「PRO 」之\n    外文，其中尚有「－」之斷句得以區分，且「PRO 」之發音\n    與據以異議商標「MA」之發音差距甚遠，於交易時連貫唱呼\n    之際，無論「OPTI-PRO」或「OPTIMA」均未產生有混同誤認\n    之情事，是二商標於讀音上仍不屬近似。\n  3.就意匠而言：據以異議商標「OPTIMA」係外文「OPTIMUM 」\n    之複數形，即「最適宜的」之中文釋意，此為參加人所熟知\n    。而系爭商標之「OPTI」並未有其他釋意，其結合「PRO 」\n    （專門、內行）後形成一獨立之字義或一標語者，且極具強\n    烈之識別性，即不宜再將其割裂而取其中一、二字詞為比對\n    ，依商標審查基準5.2.6.5 規定，可知拼音性之外文對於整\n    體字詞給予消費者之印象有極重要之影響，判斷近似時應賦\n    予比重較重之考量。至訴願機關所為其他中文解釋，係屬個\n    人主觀意見，不得據此為訴願決定駁回之依據。\n  4.外文「OPTI」結合其他文字，指定使用於相同或類似本案之\n    商品或服務而取得註冊之商標併存案例，不勝枚舉。且據以\n    異議商標與註冊第590242號「OPTIPRO 」商標係指定於相同\n    或類似之商品，且專用期間重疊，而註冊第590242號「OPTI\n    PRO 」商標之專用期限為92年3 月15日，該商標取得註冊之\n    期限內，仍不得排除曾與據以異議商標併存之事實，足見二\n    商標實因非屬近似而得以核准審定且併存在案。又據以異議\n    商標與註冊第1126038 號「OPTIMUN 」商標係指定於相同或\n    類似之商品，且專用期間重疊，而註冊第1126038 號商標係\n    於98年8 月1 日另案撤銷註冊在案，惟該商標於審查當時，\n    仍依法審定核准，並未因據以異議商標註冊在先而予以駁回\n    處分，足見二商標因非屬近似而得以核准併存在案。\n  (二)有關系爭商標之註冊申請是否善意部分：系爭商標之產品包\n    裝係經由原著作權人同意而合法使用之行為，並未有任何不\n    妥之處。另由國內PChome線上購物網站資料可知，該拍賣網\n    站係屬銷售者之個人行為，並非原告所為，至被告認為原告\n    提出之公司網站資料顯示查詢日期為西元2010年7 月29日，\n    故不得作為有利事證，惟參加人提出商標異議時並未證明原\n    告有違法情事，上開資料不足以作為參酌依據。至原告於98\n    年3 月25日向消費者發出品牌更名通知係屬商業習慣行為，\n    且係避免引發之商業糾紛，進而影響原告之商譽，故決議以\n    公開並誠實告知消費者二商標己切割之事實，且公告系爭商\n    標係為全新之產品規格，以避免消費者認為據以異議商標之\n    商品仍為原告所代為販售之產品，進而因信任原告所推出之\n    產品而誤購已出現瑕疵具爭議之舊品牌商品，導致因其品質\n    不佳而衍生其他相關爭議問題，是該通知係屬善意且誠實之\n    行為。\n  (三)系爭商標並無違反商標法第23條第1 項第13款規定，原處分\n    及訴願決定顯有違法不當之處。並聲明求為判決：1.撤銷訴\n    願決定及原處分。2.被告就原告註冊第1378519 號商標異議\n    事件，應為「異議不成立」之處分。\n三、被告則以：\n  (一)有關商標是否近似暨其近似之程度部分：系爭商標「OPTI-P\n    RO」係由外文「OPTI」結合符號「－」及外文「PRO 」所組\n    成，其中外文「PRO 」有「專業的」之意，識別性本較薄弱\n    ，是系爭商標引人注意之顯著部分應為起首字母「OPTI」。\n    系爭商標與據以異議商標相較，兩者皆有引人注意之起首字\n    母「OPTI」，以具有普通知識經驗之消費者，於購買時施以\n    普通之注意，可能會誤認二商標之商品來自同一來源或雖不\n    相同但有關聯之來源，應屬構成近似之商標，惟近似之程度\n    不高。\n  (二)有關商品是否類似暨其類似之程度部分：系爭商標指定使用\n    之「寵物飼料、非醫用飼料添加物、非醫用飼料添加劑、動\n    物用奶粉、狗飼料、貓飼料」等商品，與據以異議商標指定\n    使用之「寵物飼料」商品相較，二商標之商品之性質及用途\n    雷同，通常經由相同之行銷管道，於同一販賣場所併同銷售\n    ，如果標上相同或近似的商標，依一般社會通念及市場交易\n    情形，易使商品消費者誤認其為來自相同或雖不相同但有關\n    聯之來源，應屬構成同一或高度類似之商品。\n  (三)有關商標識別性之強弱部分：據以異議商標之外文「OPTIMA\n    」固非參加人所獨創，惟其指定使用於寵物飼料商品上，並\n    非直接明顯之說明文字，依被告所公告之「混淆誤認之虞」\n    審查基準5.1 規定，應具有相當之識別性。\n  (四)有關系爭商標之註冊申請是否善意部分：參加人及原告主張\n    據以異議商標係參加人之關係企業即訴外人美商當恩公司於\n    西元1998年所創寵物食品之品牌，乃由原告之關係企業即訴\n    外人耐吉斯公司獨家引進台灣市場，透過該公司大量行銷廣\n    告，使據以異議商標之商品已在台灣及中國大陸有相當地位\n    ，嗣因中國大陸發生狗糧遭污染事件，雙方遂停止長達10年\n    之合作關係，原告乃以自創之「OPTI-PRO」申請系爭商標註\n    冊。然原告於98年3 月25日發布之品牌更名通知所載「OPTI\n    MA優格寵物食譜正式更名為OPTI-PRO優格寵物食譜，以全新\n    的產品規格，繼續為消費者提供美味健康的犬貓乾糧」及國\n    內PChome線上購物網站資料展示寵物飼料商品之外包裝盒上\n    雖標示有「OPTI-PRO」字樣，惟標題及商品介紹仍指向據以\n    異議商標「OPTIMA」，或標題雖為「OPTI-PRO」，然商品圖\n    片卻展示據以異議商標之產品，依系爭商標實際使用之整體\n    態樣，客觀上易使相關消費者產生二商標之商品係來自相同\n    產製主體之聯想，而有混淆誤認之虞，足見系爭商標之註冊\n    申請應非出於善意。至原告主張其未以相同之包裝及近似商\n    標標示銷售而獲利，且參加人提出購物網站資料之商品係銷\n    售者之個人行為，非原告所為，復以原告之公司網站資料並\n    無販售及陳列據以異議商標商品之訊息，惟上開購物網站資\n    料所載商品資訊，縱非原告所為，消費者瀏覽相關資訊時，\n    仍極易將二造商標之來源產生聯想，況原告之公司網站資料\n    顯示查詢日期為西元2010年7 月29日，僅得認定於查詢日時\n    之網站網頁情形，尚難據此作為有利事證。\n  (五)原告主張外文「OPTI」結合其他文字，指定使用於相同或類\n    似本案之商品或服務而取得註冊之商標併存案例，不勝枚舉\n    ，且據以異議商標與註冊第590242號「OPTIPRO 」商標、第\n    1126038 號「OPTIMUN 」商標之併存情形，與本案案情更為\n    雷同，難謂系爭商標與據爭商標有構成混淆誤認之情事。惟\n    上開註冊第590242號商標已屆專用期限，而註冊第1126038\n    號商標已經另案廢止其註冊在案，況渠等商標均與本件不盡\n    相同，案情自屬有別，依商標個案審查拘束原則，尚難比附\n    援引執為本件有利之論據。又系爭商標既應依商標法第23條\n    第1 項第13款規定，撤銷其註冊，則其是否尚有違反同條項\n    第12款規定，即毋庸審究。並聲明駁回原告之訴。\n四、參酌兩造上開說明，本件兩造之爭點主要為：系爭商標是否\n    具有識別性，足以使相關消費者認識其為表彰商品來源、品\n    質、信譽之識別標識，而無商標法第23條第1 項13款規定之\n    適用？茲分述如下：\n  (一)按商標相同或近似於他人同一或類似商品或服務之註冊商標\n    或申請在先之商標，有致相關消費者混淆誤認之虞者，不得\n    註冊，商標法第23條第1 項第13款定有明文。上開規定所謂\n    「有致相關消費者混淆誤認之虞」者，係指兩商標因相同或\n    構成近似，致使同一或類似商品或服務之相關消費者誤認二\n    商標為同一商標，或雖不致誤認二商標為同一商標，但極有\n    可能誤認二商標之商品或服務為同一來源之系列商品或服務\n    ，或誤認二商標之使用人間存在關係企業、授權關係、加盟\n    關係或其他類似關係而言。而判斷有無混淆誤認之虞，則應\n    參酌商標識別性之強弱、商標之近似及商品或服務類似等相\n    關因素之強弱程度、相互影響關係及各因素等綜合認定是否\n    已達有致相關消費者產生混淆誤認之虞。\n  (二)本件訴外人耐吉斯公司於98年1 月15日以「OPTI-PRO」商標\n    ，指定使用於商標法施行細則第13條所定修正前商品及服務\n    分類表第31類之「寵物飼料、非醫用飼料添加物、非醫用飼\n    料添加劑、動物用奶粉、狗飼料、貓飼料、狗餅乾、寵物用\n    食品、動物用飼養劑、動物可食用咀嚼物、寵物用飲料」商\n    品，向被告申請註冊，嗣於98年8 月13日變更申請人為原告\n    ，經被告審查，准列為註冊第1378519 號商標。經查，原告\n    系爭商標乃以單純未經特殊設計之外文字體所組成，商標文\n    字分為前後段，前段文字為「OPTI」，後段文字為「PRO 」\n    ，中間以「- 」符號連接。按系爭商標後段之「PRO 」外文\n    ，乃指「專業的、內行的」，台灣口語用法為「撲囉（普囉\n    ）」，為國人習知習用之用語，其引人注意之識別性較低；\n    而系爭商標前段之「OPTI」外文，則因其使用之場所不同而\n    有不同意義，該文字常被作為光學、視覺（OPTICAL ）之縮\n    詞，雖鏡片業者多習用該文字，然對一般人而言，該文字較\n    之「PRO 」一字仍屬較罕用字，是以，對一般消費者而言，\n    比較注意者乃該「OPTI」前段文字，換言之，系爭商標之文\n    字，仍以前段「OPTI」文字較具識別性。消費者於見聞系爭\n    商標時，比較容易產生「某某（OPTI）專家（PRO ）」之聯\n    想。反觀據以異議商標，亦係由未經任何特殊設計之外文「\n    OPTIMA」構成，據以異議商標之文字乃外文「OPTIMUM 」之\n    複數形，即「最適宜的」之中文釋意，然因此文字較罕見，\n    且非習用字，對一般消費者而言，應更具識別性。茲比較系\n    爭商標與據以異議商標，兩者均有相同之外文字「OPTI」為\n    前導，僅系爭商標在上開前導文字之後，另以「- 」符號連\n    接後段之「PRO 」文字，而據以異議商標則在上開前導文字\n    之後緊接「MA」，是以，就系爭商標與據以異議商標二者比\n    較，在拼字上，兩者略有相同，而讀音上，亦非完全相似，\n    應係近似程度中等之商標。\n  (三)承上所述，原告系爭商標係指定使用在商標法施行細則第13\n    條所定修正前商品及服務分類表第31類之「寵物飼料、非醫\n    用飼料添加物、非醫用飼料添加劑、動物用奶粉、狗飼料、\n    貓飼料、狗餅乾、寵物用食品、動物用飼養劑、動物可食用\n    咀嚼物、寵物用飲料」商品，而據以異議商標則係指定使用\n    在「寵物飼料」商品，兩者相較，不論係商品之性質及用途\n    均屬高度類似，且其銷售之場所及銷售之對象均相同，消費\n    者在相同之場所目睹相同或類似之產品並列，確有可能誤認\n    二商標為同一商標，或雖不致誤認二商標為同一商標，但極\n    有可能誤認二商標之商品或服務為同一來源之系列商品或服\n    務，或誤認二商標之使用人間存在關係企業、授權關係、加\n    盟關係或其他類似關係。此在異時異地隔離觀察時，造成誤\n    認之可能性將更高。\n  (四)按本件據以異議商標原係參加人之關係企業即訴外人美商當\n    恩公司於西元1998年所創寵物食品之品牌，由原告之關係企\n    業即訴外人耐吉斯公司獨家引進台灣市場後行銷多年，嗣因\n    中國大陸發生狗糧遭污染事件，雙方遂停止長達10年之合作\n    關係。是以，廣義而言，原告與參加人之間曾有業務往來關\n    係，原告亦明知據以異議商標之存在，且係指定使用在「寵\n    物飼料」商品。而原告在雙方終止合作關係後，乃以系爭「\n    OPTI-PRO」商標申請註冊，指定使用在相同或類似之商品。\n    茲有爭議者，乃原告以系爭商標申請註冊後，竟於98年3 月\n    25日發布品牌更名通知，告知消費者及下游經銷商謂「OPTI\n    MA優格寵物食譜正式更名為OPTI-PRO優格寵物食譜，以全新\n    的產品規格，繼續為消費者提供美味健康的犬貓乾糧」云云\n    ，依據上開通知內容意旨，乃係在告知消費者及經銷商謂原\n    來名為「OPTIMA」商標之產品，已經改名為「OPTI-PRO」，\n    亦即兩者名稱雖有不同，然來源相同，產品內容相同，品質\n    相同，原來購買「OPTIMA」商標商品之消費者，其後可以購\n    買「OPTI-PRO」。原告此舉，不惟意欲接收原為購買參加人\n    商品之客戶，且使相關消費者對於產品來源產生不當之聯想\n    ，蓋實際上參加人據以異議商標之商品於國內寵物市場仍然\n    繼續銷售，消費者在銷售寵物飼料之場所，仍有可能看到具\n    有據以異議商標之商品與系爭商標商品同時陳列於貨架上，\n    倘消費者基於原告上開通知之內容印象，極有可能會認為此\n    二不同商標之商品其生產來源實為同一，而所以會有二商標\n    商品同時存在貨架上，有可能係因「舊」商標商品尚未售罄\n    緣故。換言之，原告之行止，不僅未降低系爭商標與據以異\n    議商標使消費者產生混淆誤認之可能性，反提高其致使相關\n    消費者產生混淆誤認之程度，同時益證原告以系爭商標申請\n    註冊，指定使用在商標法施行細則第13條所定修正前商品及\n    服務分類表第31類之「寵物飼料、非醫用飼料添加物、非醫\n    用飼料添加劑、動物用奶粉、狗飼料、貓飼料、狗餅乾、寵\n    物用食品、動物用飼養劑、動物可食用咀嚼物、寵物用飲料\n    」商品，其目的在於混淆消費者對於其所銷售之商品與據以\n    異議商標商品之來源。\n  (五)況依國內PChome線上購物網站資料展示寵物飼料商品之外包\n    裝盒上雖標示有「OPTI-PRO」字樣，惟標題及商品介紹仍指\n    向據以異議商標「OPTIMA」，或標題雖為「OPTI-PRO」，然\n    商品圖片卻展示據以異議商標之產品，依系爭商標實際使用\n    之整體態樣，客觀上易使相關消費者產生二商標之商品係來\n    自相同產製主體之聯想，而有混淆誤認之虞。原告雖主張其\n    未以相同之包裝及近似商標標示銷售而獲利，且上開購物網\n    站資料之商品係銷售者之個人行為，非其所為，復以其公司\n    網站資料並無販售及陳列據以異議商標商品之訊息云云。惟\n    查，上開購物網站資料所載商品資訊，縱非原告所為，然其\n    內容仍不違背原告上開公告通知之意旨，消費者瀏覽相關資\n    訊時，仍極易將二造商標商品之來源產生聯想。是以，縱使\n    上開網路訊息並非原告親為，然其商品確係以此種方式於市\n    場上販售，且此種銷售方式亦符合原告上開通知意旨（即原\n    「OPTIMA」商標已改為「OPTI-PRO」）。本院審酌上開證據\n    事實，以及參酌據以異議商標商品早於系爭商標商品進入國\n    內市場，其商標識別性較之系爭商標為強、以及系爭商標與\n    據以異議商標兩者雖屬中度近似，惟二商標指定使用之商品\n    或服務卻屬相同或高度類似等相關因素、相互影響關係及各\n    因素等綜合判斷，認為系爭商標使用近似於據以異議商標之\n    文字，且指定使用在相同或高度類似之商品或服務，確已達\n    有致相關消費者產生混淆誤認之虞程度，顯已違反商標法第\n    23條第1 項第13款規定，應不許其註冊。\n五、綜上所述，被告依首揭規定，為系爭商標之註冊應予撤銷之\n    處分，並無不合。訴願決定予駁回，亦無違誤，均應予以維\n    持。本件原告請求撤銷原處分及訴願決定，為無理由，應予\n    駁回。\n六、本件事證已明，兩造其餘主張或答辯，已與本院判決結果無\n    影響，爰毋庸一一論列，併此敘明。\n據上論結，本件原告之訴為無理由，爰依智慧財產案件審理法第\n1 條、行政訴訟法第98條第1 項前段，判決如主文。\n中    華    民    國    100   年    10    月    31    日\n                    智慧財產法院第一庭\n                          審判長法  官  李得灶\n                                法  官  林欣蓉\n                                法  官  汪漢卿\n以上正本係照原本作成。\n如不服本判決，應於送達後20日內，向本院提出上訴狀並表明上\n訴理由（須按他造人數附繕本）。\n如於本判決宣示後送達前提起上訴者，應於判決送達後20日內補\n提上訴理由書（須按他造人數附繕本）。\n中    華    民    國    100   年    11    月     2    日\n                                書記官  邱于婷",
  "structure": {
    "main": "原告之訴駁回。\n訴訟費用由原告負擔。",
    "fact": "一、事實概要：訴外人耐吉斯實業股份有限公司（下稱耐吉斯公\n    司）於民國98年1 月15日以「OPTI-PRO」商標，指定使用於\n    商標法施行細則第13條所定修正前商品及服務分類表第31類\n    之「寵物飼料、非醫用飼料添加物、非醫用飼料添加劑、動\n    物用奶粉、狗飼料、貓飼料、狗餅乾、寵物用食品、動物用\n    飼養劑、動物可食用咀嚼物、寵物用飲料」商品，向被告申\n    請註冊，嗣於98年8 月13日變更申請人為原告。經被告審查\n    ，准列為註冊第1378519 號商標（下稱系爭商標）。嗣參加\n    人美商瑪斯公司以系爭商標與據以異議之註冊第842395號「\n    OPTIMA」商標（下稱據以異議商標）構成近似為由，主張系\n    爭商標違反商標法第23條第1 項第12款及第13款規定，對之\n    提起異議。經被告審查，認系爭商標與據以異議商標構成近\n    似，復均指定使用於寵物飼料等類似商品，且系爭商標之註\n    冊申請難謂為善意，有致相關消費者混淆誤認之虞，而以99\n    年11月29日中台異字第981033號商標異議審定書為系爭商標\n    之註冊應予撤銷之處分。原告不服，提起訴願，經訴願機關\n    決定駁回，原告猶未甘服，遂向本院提起行政訴訟。本院因\n    認本件訴訟之結果對於參加人之權利或利益將有影響，乃依\n    行政訴訟法第42條第1 項規定，依職權裁定命參加人獨立參\n    加本件被告之訴訟。\n二、本件原告主張：\n  (一)有關兩造商標並未構成近似之判斷部分：\n  1.就外觀而言：系爭商標係由「OPTI」及「PRO 」二組外文字\n    母及於中間加入「－」符號所組合，乃不可分割之整體，而\n    據以異議商標僅為由五個英文字母「OPTIMA」併列組成，就\n    外觀而言，二商標之整體排列組合及字數多寡等形態皆迥然\n    有別，縱使二商標之字首皆為「OPTI」，惟判斷是否混淆誤\n    認係應以各項因素交叉審酌，而不得以單一因素為最終判斷\n    近似之依歸。\n  2.就讀音而言：系爭商標與據以異議商標雖均有外文「OPTI」\n    ，惟整體之於連貫唱呼之際，後者除「OPTI」及「PRO 」之\n    外文，其中尚有「－」之斷句得以區分，且「PRO 」之發音\n    與據以異議商標「MA」之發音差距甚遠，於交易時連貫唱呼\n    之際，無論「OPTI-PRO」或「OPTIMA」均未產生有混同誤認\n    之情事，是二商標於讀音上仍不屬近似。\n  3.就意匠而言：據以異議商標「OPTIMA」係外文「OPTIMUM 」\n    之複數形，即「最適宜的」之中文釋意，此為參加人所熟知\n    。而系爭商標之「OPTI」並未有其他釋意，其結合「PRO 」\n    （專門、內行）後形成一獨立之字義或一標語者，且極具強\n    烈之識別性，即不宜再將其割裂而取其中一、二字詞為比對\n    ，依商標審查基準5.2.6.5 規定，可知拼音性之外文對於整\n    體字詞給予消費者之印象有極重要之影響，判斷近似時應賦\n    予比重較重之考量。至訴願機關所為其他中文解釋，係屬個\n    人主觀意見，不得據此為訴願決定駁回之依據。\n  4.外文「OPTI」結合其他文字，指定使用於相同或類似本案之\n    商品或服務而取得註冊之商標併存案例，不勝枚舉。且據以\n    異議商標與註冊第590242號「OPTIPRO 」商標係指定於相同\n    或類似之商品，且專用期間重疊，而註冊第590242號「OPTI\n    PRO 」商標之專用期限為92年3 月15日，該商標取得註冊之\n    期限內，仍不得排除曾與據以異議商標併存之事實，足見二\n    商標實因非屬近似而得以核准審定且併存在案。又據以異議\n    商標與註冊第1126038 號「OPTIMUN 」商標係指定於相同或\n    類似之商品，且專用期間重疊，而註冊第1126038 號商標係\n    於98年8 月1 日另案撤銷註冊在案，惟該商標於審查當時，\n    仍依法審定核准，並未因據以異議商標註冊在先而予以駁回\n    處分，足見二商標因非屬近似而得以核准併存在案。\n  (二)有關系爭商標之註冊申請是否善意部分：系爭商標之產品包\n    裝係經由原著作權人同意而合法使用之行為，並未有任何不\n    妥之處。另由國內PChome線上購物網站資料可知，該拍賣網\n    站係屬銷售者之個人行為，並非原告所為，至被告認為原告\n    提出之公司網站資料顯示查詢日期為西元2010年7 月29日，\n    故不得作為有利事證，惟參加人提出商標異議時並未證明原\n    告有違法情事，上開資料不足以作為參酌依據。至原告於98\n    年3 月25日向消費者發出品牌更名通知係屬商業習慣行為，\n    且係避免引發之商業糾紛，進而影響原告之商譽，故決議以\n    公開並誠實告知消費者二商標己切割之事實，且公告系爭商\n    標係為全新之產品規格，以避免消費者認為據以異議商標之\n    商品仍為原告所代為販售之產品，進而因信任原告所推出之\n    產品而誤購已出現瑕疵具爭議之舊品牌商品，導致因其品質\n    不佳而衍生其他相關爭議問題，是該通知係屬善意且誠實之\n    行為。\n  (三)系爭商標並無違反商標法第23條第1 項第13款規定，原處分\n    及訴願決定顯有違法不當之處。並聲明求為判決：1.撤銷訴\n    願決定及原處分。2.被告就原告註冊第1378519 號商標異議\n    事件，應為「異議不成立」之處分。\n三、被告則以：\n  (一)有關商標是否近似暨其近似之程度部分：系爭商標「OPTI-P\n    RO」係由外文「OPTI」結合符號「－」及外文「PRO 」所組\n    成，其中外文「PRO 」有「專業的」之意，識別性本較薄弱\n    ，是系爭商標引人注意之顯著部分應為起首字母「OPTI」。\n    系爭商標與據以異議商標相較，兩者皆有引人注意之起首字\n    母「OPTI」，以具有普通知識經驗之消費者，於購買時施以\n    普通之注意，可能會誤認二商標之商品來自同一來源或雖不\n    相同但有關聯之來源，應屬構成近似之商標，惟近似之程度\n    不高。\n  (二)有關商品是否類似暨其類似之程度部分：系爭商標指定使用\n    之「寵物飼料、非醫用飼料添加物、非醫用飼料添加劑、動\n    物用奶粉、狗飼料、貓飼料」等商品，與據以異議商標指定\n    使用之「寵物飼料」商品相較，二商標之商品之性質及用途\n    雷同，通常經由相同之行銷管道，於同一販賣場所併同銷售\n    ，如果標上相同或近似的商標，依一般社會通念及市場交易\n    情形，易使商品消費者誤認其為來自相同或雖不相同但有關\n    聯之來源，應屬構成同一或高度類似之商品。\n  (三)有關商標識別性之強弱部分：據以異議商標之外文「OPTIMA\n    」固非參加人所獨創，惟其指定使用於寵物飼料商品上，並\n    非直接明顯之說明文字，依被告所公告之「混淆誤認之虞」\n    審查基準5.1 規定，應具有相當之識別性。\n  (四)有關系爭商標之註冊申請是否善意部分：參加人及原告主張\n    據以異議商標係參加人之關係企業即訴外人美商當恩公司於\n    西元1998年所創寵物食品之品牌，乃由原告之關係企業即訴\n    外人耐吉斯公司獨家引進台灣市場，透過該公司大量行銷廣\n    告，使據以異議商標之商品已在台灣及中國大陸有相當地位\n    ，嗣因中國大陸發生狗糧遭污染事件，雙方遂停止長達10年\n    之合作關係，原告乃以自創之「OPTI-PRO」申請系爭商標註\n    冊。然原告於98年3 月25日發布之品牌更名通知所載「OPTI\n    MA優格寵物食譜正式更名為OPTI-PRO優格寵物食譜，以全新\n    的產品規格，繼續為消費者提供美味健康的犬貓乾糧」及國\n    內PChome線上購物網站資料展示寵物飼料商品之外包裝盒上\n    雖標示有「OPTI-PRO」字樣，惟標題及商品介紹仍指向據以\n    異議商標「OPTIMA」，或標題雖為「OPTI-PRO」，然商品圖\n    片卻展示據以異議商標之產品，依系爭商標實際使用之整體\n    態樣，客觀上易使相關消費者產生二商標之商品係來自相同\n    產製主體之聯想，而有混淆誤認之虞，足見系爭商標之註冊\n    申請應非出於善意。至原告主張其未以相同之包裝及近似商\n    標標示銷售而獲利，且參加人提出購物網站資料之商品係銷\n    售者之個人行為，非原告所為，復以原告之公司網站資料並\n    無販售及陳列據以異議商標商品之訊息，惟上開購物網站資\n    料所載商品資訊，縱非原告所為，消費者瀏覽相關資訊時，\n    仍極易將二造商標之來源產生聯想，況原告之公司網站資料\n    顯示查詢日期為西元2010年7 月29日，僅得認定於查詢日時\n    之網站網頁情形，尚難據此作為有利事證。\n  (五)原告主張外文「OPTI」結合其他文字，指定使用於相同或類\n    似本案之商品或服務而取得註冊之商標併存案例，不勝枚舉\n    ，且據以異議商標與註冊第590242號「OPTIPRO 」商標、第\n    1126038 號「OPTIMUN 」商標之併存情形，與本案案情更為\n    雷同，難謂系爭商標與據爭商標有構成混淆誤認之情事。惟\n    上開註冊第590242號商標已屆專用期限，而註冊第1126038\n    號商標已經另案廢止其註冊在案，況渠等商標均與本件不盡\n    相同，案情自屬有別，依商標個案審查拘束原則，尚難比附\n    援引執為本件有利之論據。又系爭商標既應依商標法第23條\n    第1 項第13款規定，撤銷其註冊，則其是否尚有違反同條項\n    第12款規定，即毋庸審究。並聲明駁回原告之訴。\n四、參酌兩造上開說明，本件兩造之爭點主要為：系爭商標是否\n    具有識別性，足以使相關消費者認識其為表彰商品來源、品\n    質、信譽之識別標識，而無商標法第23條第1 項13款規定之\n    適用？茲分述如下：\n  (一)按商標相同或近似於他人同一或類似商品或服務之註冊商標\n    或申請在先之商標，有致相關消費者混淆誤認之虞者，不得\n    註冊，商標法第23條第1 項第13款定有明文。上開規定所謂\n    「有致相關消費者混淆誤認之虞」者，係指兩商標因相同或\n    構成近似，致使同一或類似商品或服務之相關消費者誤認二\n    商標為同一商標，或雖不致誤認二商標為同一商標，但極有\n    可能誤認二商標之商品或服務為同一來源之系列商品或服務\n    ，或誤認二商標之使用人間存在關係企業、授權關係、加盟\n    關係或其他類似關係而言。而判斷有無混淆誤認之虞，則應\n    參酌商標識別性之強弱、商標之近似及商品或服務類似等相\n    關因素之強弱程度、相互影響關係及各因素等綜合認定是否\n    已達有致相關消費者產生混淆誤認之虞。\n  (二)本件訴外人耐吉斯公司於98年1 月15日以「OPTI-PRO」商標\n    ，指定使用於商標法施行細則第13條所定修正前商品及服務\n    分類表第31類之「寵物飼料、非醫用飼料添加物、非醫用飼\n    料添加劑、動物用奶粉、狗飼料、貓飼料、狗餅乾、寵物用\n    食品、動物用飼養劑、動物可食用咀嚼物、寵物用飲料」商\n    品，向被告申請註冊，嗣於98年8 月13日變更申請人為原告\n    ，經被告審查，准列為註冊第1378519 號商標。經查，原告\n    系爭商標乃以單純未經特殊設計之外文字體所組成，商標文\n    字分為前後段，前段文字為「OPTI」，後段文字為「PRO 」\n    ，中間以「- 」符號連接。按系爭商標後段之「PRO 」外文\n    ，乃指「專業的、內行的」，台灣口語用法為「撲囉（普囉\n    ）」，為國人習知習用之用語，其引人注意之識別性較低；\n    而系爭商標前段之「OPTI」外文，則因其使用之場所不同而\n    有不同意義，該文字常被作為光學、視覺（OPTICAL ）之縮\n    詞，雖鏡片業者多習用該文字，然對一般人而言，該文字較\n    之「PRO 」一字仍屬較罕用字，是以，對一般消費者而言，\n    比較注意者乃該「OPTI」前段文字，換言之，系爭商標之文\n    字，仍以前段「OPTI」文字較具識別性。消費者於見聞系爭\n    商標時，比較容易產生「某某（OPTI）專家（PRO ）」之聯\n    想。反觀據以異議商標，亦係由未經任何特殊設計之外文「\n    OPTIMA」構成，據以異議商標之文字乃外文「OPTIMUM 」之\n    複數形，即「最適宜的」之中文釋意，然因此文字較罕見，\n    且非習用字，對一般消費者而言，應更具識別性。茲比較系\n    爭商標與據以異議商標，兩者均有相同之外文字「OPTI」為\n    前導，僅系爭商標在上開前導文字之後，另以「- 」符號連\n    接後段之「PRO 」文字，而據以異議商標則在上開前導文字\n    之後緊接「MA」，是以，就系爭商標與據以異議商標二者比\n    較，在拼字上，兩者略有相同，而讀音上，亦非完全相似，\n    應係近似程度中等之商標。\n  (三)承上所述，原告系爭商標係指定使用在商標法施行細則第13\n    條所定修正前商品及服務分類表第31類之「寵物飼料、非醫\n    用飼料添加物、非醫用飼料添加劑、動物用奶粉、狗飼料、\n    貓飼料、狗餅乾、寵物用食品、動物用飼養劑、動物可食用\n    咀嚼物、寵物用飲料」商品，而據以異議商標則係指定使用\n    在「寵物飼料」商品，兩者相較，不論係商品之性質及用途\n    均屬高度類似，且其銷售之場所及銷售之對象均相同，消費\n    者在相同之場所目睹相同或類似之產品並列，確有可能誤認\n    二商標為同一商標，或雖不致誤認二商標為同一商標，但極\n    有可能誤認二商標之商品或服務為同一來源之系列商品或服\n    務，或誤認二商標之使用人間存在關係企業、授權關係、加\n    盟關係或其他類似關係。此在異時異地隔離觀察時，造成誤\n    認之可能性將更高。\n  (四)按本件據以異議商標原係參加人之關係企業即訴外人美商當\n    恩公司於西元1998年所創寵物食品之品牌，由原告之關係企\n    業即訴外人耐吉斯公司獨家引進台灣市場後行銷多年，嗣因\n    中國大陸發生狗糧遭污染事件，雙方遂停止長達10年之合作\n    關係。是以，廣義而言，原告與參加人之間曾有業務往來關\n    係，原告亦明知據以異議商標之存在，且係指定使用在「寵\n    物飼料」商品。而原告在雙方終止合作關係後，乃以系爭「\n    OPTI-PRO」商標申請註冊，指定使用在相同或類似之商品。\n    茲有爭議者，乃原告以系爭商標申請註冊後，竟於98年3 月\n    25日發布品牌更名通知，告知消費者及下游經銷商謂「OPTI\n    MA優格寵物食譜正式更名為OPTI-PRO優格寵物食譜，以全新\n    的產品規格，繼續為消費者提供美味健康的犬貓乾糧」云云\n    ，依據上開通知內容意旨，乃係在告知消費者及經銷商謂原\n    來名為「OPTIMA」商標之產品，已經改名為「OPTI-PRO」，\n    亦即兩者名稱雖有不同，然來源相同，產品內容相同，品質\n    相同，原來購買「OPTIMA」商標商品之消費者，其後可以購\n    買「OPTI-PRO」。原告此舉，不惟意欲接收原為購買參加人\n    商品之客戶，且使相關消費者對於產品來源產生不當之聯想\n    ，蓋實際上參加人據以異議商標之商品於國內寵物市場仍然\n    繼續銷售，消費者在銷售寵物飼料之場所，仍有可能看到具\n    有據以異議商標之商品與系爭商標商品同時陳列於貨架上，\n    倘消費者基於原告上開通知之內容印象，極有可能會認為此\n    二不同商標之商品其生產來源實為同一，而所以會有二商標\n    商品同時存在貨架上，有可能係因「舊」商標商品尚未售罄\n    緣故。換言之，原告之行止，不僅未降低系爭商標與據以異\n    議商標使消費者產生混淆誤認之可能性，反提高其致使相關\n    消費者產生混淆誤認之程度，同時益證原告以系爭商標申請\n    註冊，指定使用在商標法施行細則第13條所定修正前商品及\n    服務分類表第31類之「寵物飼料、非醫用飼料添加物、非醫\n    用飼料添加劑、動物用奶粉、狗飼料、貓飼料、狗餅乾、寵\n    物用食品、動物用飼養劑、動物可食用咀嚼物、寵物用飲料\n    」商品，其目的在於混淆消費者對於其所銷售之商品與據以\n    異議商標商品之來源。\n  (五)況依國內PChome線上購物網站資料展示寵物飼料商品之外包\n    裝盒上雖標示有「OPTI-PRO」字樣，惟標題及商品介紹仍指\n    向據以異議商標「OPTIMA」，或標題雖為「OPTI-PRO」，然\n    商品圖片卻展示據以異議商標之產品，依系爭商標實際使用\n    之整體態樣，客觀上易使相關消費者產生二商標之商品係來\n    自相同產製主體之聯想，而有混淆誤認之虞。原告雖主張其\n    未以相同之包裝及近似商標標示銷售而獲利，且上開購物網\n    站資料之商品係銷售者之個人行為，非其所為，復以其公司\n    網站資料並無販售及陳列據以異議商標商品之訊息云云。惟\n    查，上開購物網站資料所載商品資訊，縱非原告所為，然其\n    內容仍不違背原告上開公告通知之意旨，消費者瀏覽相關資\n    訊時，仍極易將二造商標商品之來源產生聯想。是以，縱使\n    上開網路訊息並非原告親為，然其商品確係以此種方式於市\n    場上販售，且此種銷售方式亦符合原告上開通知意旨（即原\n    「OPTIMA」商標已改為「OPTI-PRO」）。本院審酌上開證據\n    事實，以及參酌據以異議商標商品早於系爭商標商品進入國\n    內市場，其商標識別性較之系爭商標為強、以及系爭商標與\n    據以異議商標兩者雖屬中度近似，惟二商標指定使用之商品\n    或服務卻屬相同或高度類似等相關因素、相互影響關係及各\n    因素等綜合判斷，認為系爭商標使用近似於據以異議商標之\n    文字，且指定使用在相同或高度類似之商品或服務，確已達\n    有致相關消費者產生混淆誤認之虞程度，顯已違反商標法第\n    23條第1 項第13款規定，應不許其註冊。\n五、綜上所述，被告依首揭規定，為系爭商標之註冊應予撤銷之\n    處分，並無不合。訴願決定予駁回，亦無違誤，均應予以維\n    持。本件原告請求撤銷原處分及訴願決定，為無理由，應予\n    駁回。\n六、本件事證已明，兩造其餘主張或答辯，已與本院判決結果無\n    影響，爰毋庸一一論列，併此敘明。\n據上論結，本件原告之訴為無理由，爰依智慧財產案件審理法第\n1 條、行政訴訟法第98條第1 項前段，判決如主文。",
    "reason": "一、事實概要：訴外人耐吉斯實業股份有限公司（下稱耐吉斯公\n    司）於民國98年1 月15日以「OPTI-PRO」商標，指定使用於\n    商標法施行細則第13條所定修正前商品及服務分類表第31類\n    之「寵物飼料、非醫用飼料添加物、非醫用飼料添加劑、動\n    物用奶粉、狗飼料、貓飼料、狗餅乾、寵物用食品、動物用\n    飼養劑、動物可食用咀嚼物、寵物用飲料」商品，向被告申\n    請註冊，嗣於98年8 月13日變更申請人為原告。經被告審查\n    ，准列為註冊第1378519 號商標（下稱系爭商標）。嗣參加\n    人美商瑪斯公司以系爭商標與據以異議之註冊第842395號「\n    OPTIMA」商標（下稱據以異議商標）構成近似為由，主張系\n    爭商標違反商標法第23條第1 項第12款及第13款規定，對之\n    提起異議。經被告審查，認系爭商標與據以異議商標構成近\n    似，復均指定使用於寵物飼料等類似商品，且系爭商標之註\n    冊申請難謂為善意，有致相關消費者混淆誤認之虞，而以99\n    年11月29日中台異字第981033號商標異議審定書為系爭商標\n    之註冊應予撤銷之處分。原告不服，提起訴願，經訴願機關\n    決定駁回，原告猶未甘服，遂向本院提起行政訴訟。本院因\n    認本件訴訟之結果對於參加人之權利或利益將有影響，乃依\n    行政訴訟法第42條第1 項規定，依職權裁定命參加人獨立參\n    加本件被告之訴訟。\n二、本件原告主張：\n  (一)有關兩造商標並未構成近似之判斷部分：\n  1.就外觀而言：系爭商標係由「OPTI」及「PRO 」二組外文字\n    母及於中間加入「－」符號所組合，乃不可分割之整體，而\n    據以異議商標僅為由五個英文字母「OPTIMA」併列組成，就\n    外觀而言，二商標之整體排列組合及字數多寡等形態皆迥然\n    有別，縱使二商標之字首皆為「OPTI」，惟判斷是否混淆誤\n    認係應以各項因素交叉審酌，而不得以單一因素為最終判斷\n    近似之依歸。\n  2.就讀音而言：系爭商標與據以異議商標雖均有外文「OPTI」\n    ，惟整體之於連貫唱呼之際，後者除「OPTI」及「PRO 」之\n    外文，其中尚有「－」之斷句得以區分，且「PRO 」之發音\n    與據以異議商標「MA」之發音差距甚遠，於交易時連貫唱呼\n    之際，無論「OPTI-PRO」或「OPTIMA」均未產生有混同誤認\n    之情事，是二商標於讀音上仍不屬近似。\n  3.就意匠而言：據以異議商標「OPTIMA」係外文「OPTIMUM 」\n    之複數形，即「最適宜的」之中文釋意，此為參加人所熟知\n    。而系爭商標之「OPTI」並未有其他釋意，其結合「PRO 」\n    （專門、內行）後形成一獨立之字義或一標語者，且極具強\n    烈之識別性，即不宜再將其割裂而取其中一、二字詞為比對\n    ，依商標審查基準5.2.6.5 規定，可知拼音性之外文對於整\n    體字詞給予消費者之印象有極重要之影響，判斷近似時應賦\n    予比重較重之考量。至訴願機關所為其他中文解釋，係屬個\n    人主觀意見，不得據此為訴願決定駁回之依據。\n  4.外文「OPTI」結合其他文字，指定使用於相同或類似本案之\n    商品或服務而取得註冊之商標併存案例，不勝枚舉。且據以\n    異議商標與註冊第590242號「OPTIPRO 」商標係指定於相同\n    或類似之商品，且專用期間重疊，而註冊第590242號「OPTI\n    PRO 」商標之專用期限為92年3 月15日，該商標取得註冊之\n    期限內，仍不得排除曾與據以異議商標併存之事實，足見二\n    商標實因非屬近似而得以核准審定且併存在案。又據以異議\n    商標與註冊第1126038 號「OPTIMUN 」商標係指定於相同或\n    類似之商品，且專用期間重疊，而註冊第1126038 號商標係\n    於98年8 月1 日另案撤銷註冊在案，惟該商標於審查當時，\n    仍依法審定核准，並未因據以異議商標註冊在先而予以駁回\n    處分，足見二商標因非屬近似而得以核准併存在案。\n  (二)有關系爭商標之註冊申請是否善意部分：系爭商標之產品包\n    裝係經由原著作權人同意而合法使用之行為，並未有任何不\n    妥之處。另由國內PChome線上購物網站資料可知，該拍賣網\n    站係屬銷售者之個人行為，並非原告所為，至被告認為原告\n    提出之公司網站資料顯示查詢日期為西元2010年7 月29日，\n    故不得作為有利事證，惟參加人提出商標異議時並未證明原\n    告有違法情事，上開資料不足以作為參酌依據。至原告於98\n    年3 月25日向消費者發出品牌更名通知係屬商業習慣行為，\n    且係避免引發之商業糾紛，進而影響原告之商譽，故決議以\n    公開並誠實告知消費者二商標己切割之事實，且公告系爭商\n    標係為全新之產品規格，以避免消費者認為據以異議商標之\n    商品仍為原告所代為販售之產品，進而因信任原告所推出之\n    產品而誤購已出現瑕疵具爭議之舊品牌商品，導致因其品質\n    不佳而衍生其他相關爭議問題，是該通知係屬善意且誠實之\n    行為。\n  (三)系爭商標並無違反商標法第23條第1 項第13款規定，原處分\n    及訴願決定顯有違法不當之處。並聲明求為判決：1.撤銷訴\n    願決定及原處分。2.被告就原告註冊第1378519 號商標異議\n    事件，應為「異議不成立」之處分。\n三、被告則以：\n  (一)有關商標是否近似暨其近似之程度部分：系爭商標「OPTI-P\n    RO」係由外文「OPTI」結合符號「－」及外文「PRO 」所組\n    成，其中外文「PRO 」有「專業的」之意，識別性本較薄弱\n    ，是系爭商標引人注意之顯著部分應為起首字母「OPTI」。\n    系爭商標與據以異議商標相較，兩者皆有引人注意之起首字\n    母「OPTI」，以具有普通知識經驗之消費者，於購買時施以\n    普通之注意，可能會誤認二商標之商品來自同一來源或雖不\n    相同但有關聯之來源，應屬構成近似之商標，惟近似之程度\n    不高。\n  (二)有關商品是否類似暨其類似之程度部分：系爭商標指定使用\n    之「寵物飼料、非醫用飼料添加物、非醫用飼料添加劑、動\n    物用奶粉、狗飼料、貓飼料」等商品，與據以異議商標指定\n    使用之「寵物飼料」商品相較，二商標之商品之性質及用途\n    雷同，通常經由相同之行銷管道，於同一販賣場所併同銷售\n    ，如果標上相同或近似的商標，依一般社會通念及市場交易\n    情形，易使商品消費者誤認其為來自相同或雖不相同但有關\n    聯之來源，應屬構成同一或高度類似之商品。\n  (三)有關商標識別性之強弱部分：據以異議商標之外文「OPTIMA\n    」固非參加人所獨創，惟其指定使用於寵物飼料商品上，並\n    非直接明顯之說明文字，依被告所公告之「混淆誤認之虞」\n    審查基準5.1 規定，應具有相當之識別性。\n  (四)有關系爭商標之註冊申請是否善意部分：參加人及原告主張\n    據以異議商標係參加人之關係企業即訴外人美商當恩公司於\n    西元1998年所創寵物食品之品牌，乃由原告之關係企業即訴\n    外人耐吉斯公司獨家引進台灣市場，透過該公司大量行銷廣\n    告，使據以異議商標之商品已在台灣及中國大陸有相當地位\n    ，嗣因中國大陸發生狗糧遭污染事件，雙方遂停止長達10年\n    之合作關係，原告乃以自創之「OPTI-PRO」申請系爭商標註\n    冊。然原告於98年3 月25日發布之品牌更名通知所載「OPTI\n    MA優格寵物食譜正式更名為OPTI-PRO優格寵物食譜，以全新\n    的產品規格，繼續為消費者提供美味健康的犬貓乾糧」及國\n    內PChome線上購物網站資料展示寵物飼料商品之外包裝盒上\n    雖標示有「OPTI-PRO」字樣，惟標題及商品介紹仍指向據以\n    異議商標「OPTIMA」，或標題雖為「OPTI-PRO」，然商品圖\n    片卻展示據以異議商標之產品，依系爭商標實際使用之整體\n    態樣，客觀上易使相關消費者產生二商標之商品係來自相同\n    產製主體之聯想，而有混淆誤認之虞，足見系爭商標之註冊\n    申請應非出於善意。至原告主張其未以相同之包裝及近似商\n    標標示銷售而獲利，且參加人提出購物網站資料之商品係銷\n    售者之個人行為，非原告所為，復以原告之公司網站資料並\n    無販售及陳列據以異議商標商品之訊息，惟上開購物網站資\n    料所載商品資訊，縱非原告所為，消費者瀏覽相關資訊時，\n    仍極易將二造商標之來源產生聯想，況原告之公司網站資料\n    顯示查詢日期為西元2010年7 月29日，僅得認定於查詢日時\n    之網站網頁情形，尚難據此作為有利事證。\n  (五)原告主張外文「OPTI」結合其他文字，指定使用於相同或類\n    似本案之商品或服務而取得註冊之商標併存案例，不勝枚舉\n    ，且據以異議商標與註冊第590242號「OPTIPRO 」商標、第\n    1126038 號「OPTIMUN 」商標之併存情形，與本案案情更為\n    雷同，難謂系爭商標與據爭商標有構成混淆誤認之情事。惟\n    上開註冊第590242號商標已屆專用期限，而註冊第1126038\n    號商標已經另案廢止其註冊在案，況渠等商標均與本件不盡\n    相同，案情自屬有別，依商標個案審查拘束原則，尚難比附\n    援引執為本件有利之論據。又系爭商標既應依商標法第23條\n    第1 項第13款規定，撤銷其註冊，則其是否尚有違反同條項\n    第12款規定，即毋庸審究。並聲明駁回原告之訴。\n四、參酌兩造上開說明，本件兩造之爭點主要為：系爭商標是否\n    具有識別性，足以使相關消費者認識其為表彰商品來源、品\n    質、信譽之識別標識，而無商標法第23條第1 項13款規定之\n    適用？茲分述如下：\n  (一)按商標相同或近似於他人同一或類似商品或服務之註冊商標\n    或申請在先之商標，有致相關消費者混淆誤認之虞者，不得\n    註冊，商標法第23條第1 項第13款定有明文。上開規定所謂\n    「有致相關消費者混淆誤認之虞」者，係指兩商標因相同或\n    構成近似，致使同一或類似商品或服務之相關消費者誤認二\n    商標為同一商標，或雖不致誤認二商標為同一商標，但極有\n    可能誤認二商標之商品或服務為同一來源之系列商品或服務\n    ，或誤認二商標之使用人間存在關係企業、授權關係、加盟\n    關係或其他類似關係而言。而判斷有無混淆誤認之虞，則應\n    參酌商標識別性之強弱、商標之近似及商品或服務類似等相\n    關因素之強弱程度、相互影響關係及各因素等綜合認定是否\n    已達有致相關消費者產生混淆誤認之虞。\n  (二)本件訴外人耐吉斯公司於98年1 月15日以「OPTI-PRO」商標\n    ，指定使用於商標法施行細則第13條所定修正前商品及服務\n    分類表第31類之「寵物飼料、非醫用飼料添加物、非醫用飼\n    料添加劑、動物用奶粉、狗飼料、貓飼料、狗餅乾、寵物用\n    食品、動物用飼養劑、動物可食用咀嚼物、寵物用飲料」商\n    品，向被告申請註冊，嗣於98年8 月13日變更申請人為原告\n    ，經被告審查，准列為註冊第1378519 號商標。經查，原告\n    系爭商標乃以單純未經特殊設計之外文字體所組成，商標文\n    字分為前後段，前段文字為「OPTI」，後段文字為「PRO 」\n    ，中間以「- 」符號連接。按系爭商標後段之「PRO 」外文\n    ，乃指「專業的、內行的」，台灣口語用法為「撲囉（普囉\n    ）」，為國人習知習用之用語，其引人注意之識別性較低；\n    而系爭商標前段之「OPTI」外文，則因其使用之場所不同而\n    有不同意義，該文字常被作為光學、視覺（OPTICAL ）之縮\n    詞，雖鏡片業者多習用該文字，然對一般人而言，該文字較\n    之「PRO 」一字仍屬較罕用字，是以，對一般消費者而言，\n    比較注意者乃該「OPTI」前段文字，換言之，系爭商標之文\n    字，仍以前段「OPTI」文字較具識別性。消費者於見聞系爭\n    商標時，比較容易產生「某某（OPTI）專家（PRO ）」之聯\n    想。反觀據以異議商標，亦係由未經任何特殊設計之外文「\n    OPTIMA」構成，據以異議商標之文字乃外文「OPTIMUM 」之\n    複數形，即「最適宜的」之中文釋意，然因此文字較罕見，\n    且非習用字，對一般消費者而言，應更具識別性。茲比較系\n    爭商標與據以異議商標，兩者均有相同之外文字「OPTI」為\n    前導，僅系爭商標在上開前導文字之後，另以「- 」符號連\n    接後段之「PRO 」文字，而據以異議商標則在上開前導文字\n    之後緊接「MA」，是以，就系爭商標與據以異議商標二者比\n    較，在拼字上，兩者略有相同，而讀音上，亦非完全相似，\n    應係近似程度中等之商標。\n  (三)承上所述，原告系爭商標係指定使用在商標法施行細則第13\n    條所定修正前商品及服務分類表第31類之「寵物飼料、非醫\n    用飼料添加物、非醫用飼料添加劑、動物用奶粉、狗飼料、\n    貓飼料、狗餅乾、寵物用食品、動物用飼養劑、動物可食用\n    咀嚼物、寵物用飲料」商品，而據以異議商標則係指定使用\n    在「寵物飼料」商品，兩者相較，不論係商品之性質及用途\n    均屬高度類似，且其銷售之場所及銷售之對象均相同，消費\n    者在相同之場所目睹相同或類似之產品並列，確有可能誤認\n    二商標為同一商標，或雖不致誤認二商標為同一商標，但極\n    有可能誤認二商標之商品或服務為同一來源之系列商品或服\n    務，或誤認二商標之使用人間存在關係企業、授權關係、加\n    盟關係或其他類似關係。此在異時異地隔離觀察時，造成誤\n    認之可能性將更高。\n  (四)按本件據以異議商標原係參加人之關係企業即訴外人美商當\n    恩公司於西元1998年所創寵物食品之品牌，由原告之關係企\n    業即訴外人耐吉斯公司獨家引進台灣市場後行銷多年，嗣因\n    中國大陸發生狗糧遭污染事件，雙方遂停止長達10年之合作\n    關係。是以，廣義而言，原告與參加人之間曾有業務往來關\n    係，原告亦明知據以異議商標之存在，且係指定使用在「寵\n    物飼料」商品。而原告在雙方終止合作關係後，乃以系爭「\n    OPTI-PRO」商標申請註冊，指定使用在相同或類似之商品。\n    茲有爭議者，乃原告以系爭商標申請註冊後，竟於98年3 月\n    25日發布品牌更名通知，告知消費者及下游經銷商謂「OPTI\n    MA優格寵物食譜正式更名為OPTI-PRO優格寵物食譜，以全新\n    的產品規格，繼續為消費者提供美味健康的犬貓乾糧」云云\n    ，依據上開通知內容意旨，乃係在告知消費者及經銷商謂原\n    來名為「OPTIMA」商標之產品，已經改名為「OPTI-PRO」，\n    亦即兩者名稱雖有不同，然來源相同，產品內容相同，品質\n    相同，原來購買「OPTIMA」商標商品之消費者，其後可以購\n    買「OPTI-PRO」。原告此舉，不惟意欲接收原為購買參加人\n    商品之客戶，且使相關消費者對於產品來源產生不當之聯想\n    ，蓋實際上參加人據以異議商標之商品於國內寵物市場仍然\n    繼續銷售，消費者在銷售寵物飼料之場所，仍有可能看到具\n    有據以異議商標之商品與系爭商標商品同時陳列於貨架上，\n    倘消費者基於原告上開通知之內容印象，極有可能會認為此\n    二不同商標之商品其生產來源實為同一，而所以會有二商標\n    商品同時存在貨架上，有可能係因「舊」商標商品尚未售罄\n    緣故。換言之，原告之行止，不僅未降低系爭商標與據以異\n    議商標使消費者產生混淆誤認之可能性，反提高其致使相關\n    消費者產生混淆誤認之程度，同時益證原告以系爭商標申請\n    註冊，指定使用在商標法施行細則第13條所定修正前商品及\n    服務分類表第31類之「寵物飼料、非醫用飼料添加物、非醫\n    用飼料添加劑、動物用奶粉、狗飼料、貓飼料、狗餅乾、寵\n    物用食品、動物用飼養劑、動物可食用咀嚼物、寵物用飲料\n    」商品，其目的在於混淆消費者對於其所銷售之商品與據以\n    異議商標商品之來源。\n  (五)況依國內PChome線上購物網站資料展示寵物飼料商品之外包\n    裝盒上雖標示有「OPTI-PRO」字樣，惟標題及商品介紹仍指\n    向據以異議商標「OPTIMA」，或標題雖為「OPTI-PRO」，然\n    商品圖片卻展示據以異議商標之產品，依系爭商標實際使用\n    之整體態樣，客觀上易使相關消費者產生二商標之商品係來\n    自相同產製主體之聯想，而有混淆誤認之虞。原告雖主張其\n    未以相同之包裝及近似商標標示銷售而獲利，且上開購物網\n    站資料之商品係銷售者之個人行為，非其所為，復以其公司\n    網站資料並無販售及陳列據以異議商標商品之訊息云云。惟\n    查，上開購物網站資料所載商品資訊，縱非原告所為，然其\n    內容仍不違背原告上開公告通知之意旨，消費者瀏覽相關資\n    訊時，仍極易將二造商標商品之來源產生聯想。是以，縱使\n    上開網路訊息並非原告親為，然其商品確係以此種方式於市\n    場上販售，且此種銷售方式亦符合原告上開通知意旨（即原\n    「OPTIMA」商標已改為「OPTI-PRO」）。本院審酌上開證據\n    事實，以及參酌據以異議商標商品早於系爭商標商品進入國\n    內市場，其商標識別性較之系爭商標為強、以及系爭商標與\n    據以異議商標兩者雖屬中度近似，惟二商標指定使用之商品\n    或服務卻屬相同或高度類似等相關因素、相互影響關係及各\n    因素等綜合判斷，認為系爭商標使用近似於據以異議商標之\n    文字，且指定使用在相同或高度類似之商品或服務，確已達\n    有致相關消費者產生混淆誤認之虞程度，顯已違反商標法第\n    23條第1 項第13款規定，應不許其註冊。\n五、綜上所述，被告依首揭規定，為系爭商標之註冊應予撤銷之\n    處分，並無不合。訴願決定予駁回，亦無違誤，均應予以維\n    持。本件原告請求撤銷原處分及訴願決定，為無理由，應予\n    駁回。\n六、本件事證已明，兩造其餘主張或答辯，已與本院判決結果無\n    影響，爰毋庸一一論列，併此敘明。\n據上論結，本件原告之訴為無理由，爰依智慧財產案件審理法第\n1 條、行政訴訟法第98條第1 項前段，判決如主文。"
  },
  "search": "智慧財產法院行政判決100年度行商訴字第61號100年10月6日辯論終結原告艾凘克企業股份有限公司代表人吳皇明訴訟代理人黃照律師被告經濟部智慧財產局設臺北市大安區辛亥路二段185代表人王美花（局長）訴訟代理人林政憓上列當事人間因商標異議事件，原告不服經濟部中華民國100年3月16日經訴字第10006097290號訴願決定，提起行政訴訟，並經本院裁定命參加人獨立參加本件被告之訴訟，本院判決如下：主文原告之訴駁回。訴訟費用由原告負擔。事實及理由一、事實概要：訴外人耐吉斯實業股份有限公司（下稱耐吉斯公司）於民國98年1月15日以「OPTI-PRO」商標，指定使用於商標法施行細則第13條所定修正前商品及服務分類表第31類之「寵物飼料、非醫用飼料添加物、非醫用飼料添加劑、動物用奶粉、狗飼料、貓飼料、狗餅乾、寵物用食品、動物用飼養劑、動物可食用咀嚼物、寵物用飲料」商品，向被告申請註冊，嗣於98年8月13日變更申請人為原告。經被告審查，准列為註冊第1378519號商標（下稱系爭商標）。嗣參加人美商瑪斯公司以系爭商標與據以異議之註冊第842395號「OPTIMA」商標（下稱據以異議商標）構成近似為由，主張系爭商標違反商標法第23條第1項第12款及第13款規定，對之提起異議。經被告審查，認系爭商標與據以異議商標構成近似，復均指定使用於寵物飼料等類似商品，且系爭商標之註冊申請難謂為善意，有致相關消費者混淆誤認之虞，而以99年11月29日中台異字第981033號商標異議審定書為系爭商標之註冊應予撤銷之處分。原告不服，提起訴願，經訴願機關決定駁回，原告猶未甘服，遂向本院提起行政訴訟。本院因認本件訴訟之結果對於參加人之權利或利益將有影響，乃依行政訴訟法第42條第1項規定，依職權裁定命參加人獨立參加本件被告之訴訟。二、本件原告主張：(一)有關兩造商標並未構成近似之判斷部分：1.就外觀而言：系爭商標係由「OPTI」及「PRO」二組外文字母及於中間加入「－」符號所組合，乃不可分割之整體，而據以異議商標僅為由五個英文字母「OPTIMA」併列組成，就外觀而言，二商標之整體排列組合及字數多寡等形態皆迥然有別，縱使二商標之字首皆為「OPTI」，惟判斷是否混淆誤認係應以各項因素交叉審酌，而不得以單一因素為最終判斷近似之依歸。2.就讀音而言：系爭商標與據以異議商標雖均有外文「OPTI」，惟整體之於連貫唱呼之際，後者除「OPTI」及「PRO」之外文，其中尚有「－」之斷句得以區分，且「PRO」之發音與據以異議商標「MA」之發音差距甚遠，於交易時連貫唱呼之際，無論「OPTI-PRO」或「OPTIMA」均未產生有混同誤認之情事，是二商標於讀音上仍不屬近似。3.就意匠而言：據以異議商標「OPTIMA」係外文「OPTIMUM」之複數形，即「最適宜的」之中文釋意，此為參加人所熟知。而系爭商標之「OPTI」並未有其他釋意，其結合「PRO」（專門、內行）後形成一獨立之字義或一標語者，且極具強烈之識別性，即不宜再將其割裂而取其中一、二字詞為比對，依商標審查基準5.2.6.5規定，可知拼音性之外文對於整體字詞給予消費者之印象有極重要之影響，判斷近似時應賦予比重較重之考量。至訴願機關所為其他中文解釋，係屬個人主觀意見，不得據此為訴願決定駁回之依據。4.外文「OPTI」結合其他文字，指定使用於相同或類似本案之商品或服務而取得註冊之商標併存案例，不勝枚舉。且據以異議商標與註冊第590242號「OPTIPRO」商標係指定於相同或類似之商品，且專用期間重疊，而註冊第590242號「OPTIPRO」商標之專用期限為92年3月15日，該商標取得註冊之期限內，仍不得排除曾與據以異議商標併存之事實，足見二商標實因非屬近似而得以核准審定且併存在案。又據以異議商標與註冊第1126038號「OPTIMUN」商標係指定於相同或類似之商品，且專用期間重疊，而註冊第1126038號商標係於98年8月1日另案撤銷註冊在案，惟該商標於審查當時，仍依法審定核准，並未因據以異議商標註冊在先而予以駁回處分，足見二商標因非屬近似而得以核准併存在案。(二)有關系爭商標之註冊申請是否善意部分：系爭商標之產品包裝係經由原著作權人同意而合法使用之行為，並未有任何不妥之處。另由國內PChome線上購物網站資料可知，該拍賣網站係屬銷售者之個人行為，並非原告所為，至被告認為原告提出之公司網站資料顯示查詢日期為西元2010年7月29日，故不得作為有利事證，惟參加人提出商標異議時並未證明原告有違法情事，上開資料不足以作為參酌依據。至原告於98年3月25日向消費者發出品牌更名通知係屬商業習慣行為，且係避免引發之商業糾紛，進而影響原告之商譽，故決議以公開並誠實告知消費者二商標己切割之事實，且公告系爭商標係為全新之產品規格，以避免消費者認為據以異議商標之商品仍為原告所代為販售之產品，進而因信任原告所推出之產品而誤購已出現瑕疵具爭議之舊品牌商品，導致因其品質不佳而衍生其他相關爭議問題，是該通知係屬善意且誠實之行為。(三)系爭商標並無違反商標法第23條第1項第13款規定，原處分及訴願決定顯有違法不當之處。並聲明求為判決：1.撤銷訴願決定及原處分。2.被告就原告註冊第1378519號商標異議事件，應為「異議不成立」之處分。三、被告則以：(一)有關商標是否近似暨其近似之程度部分：系爭商標「OPTI-PRO」係由外文「OPTI」結合符號「－」及外文「PRO」所組成，其中外文「PRO」有「專業的」之意，識別性本較薄弱，是系爭商標引人注意之顯著部分應為起首字母「OPTI」。系爭商標與據以異議商標相較，兩者皆有引人注意之起首字母「OPTI」，以具有普通知識經驗之消費者，於購買時施以普通之注意，可能會誤認二商標之商品來自同一來源或雖不相同但有關聯之來源，應屬構成近似之商標，惟近似之程度不高。(二)有關商品是否類似暨其類似之程度部分：系爭商標指定使用之「寵物飼料、非醫用飼料添加物、非醫用飼料添加劑、動物用奶粉、狗飼料、貓飼料」等商品，與據以異議商標指定使用之「寵物飼料」商品相較，二商標之商品之性質及用途雷同，通常經由相同之行銷管道，於同一販賣場所併同銷售，如果標上相同或近似的商標，依一般社會通念及市場交易情形，易使商品消費者誤認其為來自相同或雖不相同但有關聯之來源，應屬構成同一或高度類似之商品。(三)有關商標識別性之強弱部分：據以異議商標之外文「OPTIMA」固非參加人所獨創，惟其指定使用於寵物飼料商品上，並非直接明顯之說明文字，依被告所公告之「混淆誤認之虞」審查基準5.1規定，應具有相當之識別性。(四)有關系爭商標之註冊申請是否善意部分：參加人及原告主張據以異議商標係參加人之關係企業即訴外人美商當恩公司於西元1998年所創寵物食品之品牌，乃由原告之關係企業即訴外人耐吉斯公司獨家引進台灣市場，透過該公司大量行銷廣告，使據以異議商標之商品已在台灣及中國大陸有相當地位，嗣因中國大陸發生狗糧遭污染事件，雙方遂停止長達10年之合作關係，原告乃以自創之「OPTI-PRO」申請系爭商標註冊。然原告於98年3月25日發布之品牌更名通知所載「OPTIMA優格寵物食譜正式更名為OPTI-PRO優格寵物食譜，以全新的產品規格，繼續為消費者提供美味健康的犬貓乾糧」及國內PChome線上購物網站資料展示寵物飼料商品之外包裝盒上雖標示有「OPTI-PRO」字樣，惟標題及商品介紹仍指向據以異議商標「OPTIMA」，或標題雖為「OPTI-PRO」，然商品圖片卻展示據以異議商標之產品，依系爭商標實際使用之整體態樣，客觀上易使相關消費者產生二商標之商品係來自相同產製主體之聯想，而有混淆誤認之虞，足見系爭商標之註冊申請應非出於善意。至原告主張其未以相同之包裝及近似商標標示銷售而獲利，且參加人提出購物網站資料之商品係銷售者之個人行為，非原告所為，復以原告之公司網站資料並無販售及陳列據以異議商標商品之訊息，惟上開購物網站資料所載商品資訊，縱非原告所為，消費者瀏覽相關資訊時，仍極易將二造商標之來源產生聯想，況原告之公司網站資料顯示查詢日期為西元2010年7月29日，僅得認定於查詢日時之網站網頁情形，尚難據此作為有利事證。(五)原告主張外文「OPTI」結合其他文字，指定使用於相同或類似本案之商品或服務而取得註冊之商標併存案例，不勝枚舉，且據以異議商標與註冊第590242號「OPTIPRO」商標、第1126038號「OPTIMUN」商標之併存情形，與本案案情更為雷同，難謂系爭商標與據爭商標有構成混淆誤認之情事。惟上開註冊第590242號商標已屆專用期限，而註冊第1126038號商標已經另案廢止其註冊在案，況渠等商標均與本件不盡相同，案情自屬有別，依商標個案審查拘束原則，尚難比附援引執為本件有利之論據。又系爭商標既應依商標法第23條第1項第13款規定，撤銷其註冊，則其是否尚有違反同條項第12款規定，即毋庸審究。並聲明駁回原告之訴。四、參酌兩造上開說明，本件兩造之爭點主要為：系爭商標是否具有識別性，足以使相關消費者認識其為表彰商品來源、品質、信譽之識別標識，而無商標法第23條第1項13款規定之適用？茲分述如下：(一)按商標相同或近似於他人同一或類似商品或服務之註冊商標或申請在先之商標，有致相關消費者混淆誤認之虞者，不得註冊，商標法第23條第1項第13款定有明文。上開規定所謂「有致相關消費者混淆誤認之虞」者，係指兩商標因相同或構成近似，致使同一或類似商品或服務之相關消費者誤認二商標為同一商標，或雖不致誤認二商標為同一商標，但極有可能誤認二商標之商品或服務為同一來源之系列商品或服務，或誤認二商標之使用人間存在關係企業、授權關係、加盟關係或其他類似關係而言。而判斷有無混淆誤認之虞，則應參酌商標識別性之強弱、商標之近似及商品或服務類似等相關因素之強弱程度、相互影響關係及各因素等綜合認定是否已達有致相關消費者產生混淆誤認之虞。(二)本件訴外人耐吉斯公司於98年1月15日以「OPTI-PRO」商標，指定使用於商標法施行細則第13條所定修正前商品及服務分類表第31類之「寵物飼料、非醫用飼料添加物、非醫用飼料添加劑、動物用奶粉、狗飼料、貓飼料、狗餅乾、寵物用食品、動物用飼養劑、動物可食用咀嚼物、寵物用飲料」商品，向被告申請註冊，嗣於98年8月13日變更申請人為原告，經被告審查，准列為註冊第1378519號商標。經查，原告系爭商標乃以單純未經特殊設計之外文字體所組成，商標文字分為前後段，前段文字為「OPTI」，後段文字為「PRO」，中間以「-」符號連接。按系爭商標後段之「PRO」外文，乃指「專業的、內行的」，台灣口語用法為「撲囉（普囉）」，為國人習知習用之用語，其引人注意之識別性較低；而系爭商標前段之「OPTI」外文，則因其使用之場所不同而有不同意義，該文字常被作為光學、視覺（OPTICAL）之縮詞，雖鏡片業者多習用該文字，然對一般人而言，該文字較之「PRO」一字仍屬較罕用字，是以，對一般消費者而言，比較注意者乃該「OPTI」前段文字，換言之，系爭商標之文字，仍以前段「OPTI」文字較具識別性。消費者於見聞系爭商標時，比較容易產生「某某（OPTI）專家（PRO）」之聯想。反觀據以異議商標，亦係由未經任何特殊設計之外文「OPTIMA」構成，據以異議商標之文字乃外文「OPTIMUM」之複數形，即「最適宜的」之中文釋意，然因此文字較罕見，且非習用字，對一般消費者而言，應更具識別性。茲比較系爭商標與據以異議商標，兩者均有相同之外文字「OPTI」為前導，僅系爭商標在上開前導文字之後，另以「-」符號連接後段之「PRO」文字，而據以異議商標則在上開前導文字之後緊接「MA」，是以，就系爭商標與據以異議商標二者比較，在拼字上，兩者略有相同，而讀音上，亦非完全相似，應係近似程度中等之商標。(三)承上所述，原告系爭商標係指定使用在商標法施行細則第13條所定修正前商品及服務分類表第31類之「寵物飼料、非醫用飼料添加物、非醫用飼料添加劑、動物用奶粉、狗飼料、貓飼料、狗餅乾、寵物用食品、動物用飼養劑、動物可食用咀嚼物、寵物用飲料」商品，而據以異議商標則係指定使用在「寵物飼料」商品，兩者相較，不論係商品之性質及用途均屬高度類似，且其銷售之場所及銷售之對象均相同，消費者在相同之場所目睹相同或類似之產品並列，確有可能誤認二商標為同一商標，或雖不致誤認二商標為同一商標，但極有可能誤認二商標之商品或服務為同一來源之系列商品或服務，或誤認二商標之使用人間存在關係企業、授權關係、加盟關係或其他類似關係。此在異時異地隔離觀察時，造成誤認之可能性將更高。(四)按本件據以異議商標原係參加人之關係企業即訴外人美商當恩公司於西元1998年所創寵物食品之品牌，由原告之關係企業即訴外人耐吉斯公司獨家引進台灣市場後行銷多年，嗣因中國大陸發生狗糧遭污染事件，雙方遂停止長達10年之合作關係。是以，廣義而言，原告與參加人之間曾有業務往來關係，原告亦明知據以異議商標之存在，且係指定使用在「寵物飼料」商品。而原告在雙方終止合作關係後，乃以系爭「OPTI-PRO」商標申請註冊，指定使用在相同或類似之商品。茲有爭議者，乃原告以系爭商標申請註冊後，竟於98年3月25日發布品牌更名通知，告知消費者及下游經銷商謂「OPTIMA優格寵物食譜正式更名為OPTI-PRO優格寵物食譜，以全新的產品規格，繼續為消費者提供美味健康的犬貓乾糧」云云，依據上開通知內容意旨，乃係在告知消費者及經銷商謂原來名為「OPTIMA」商標之產品，已經改名為「OPTI-PRO」，亦即兩者名稱雖有不同，然來源相同，產品內容相同，品質相同，原來購買「OPTIMA」商標商品之消費者，其後可以購買「OPTI-PRO」。原告此舉，不惟意欲接收原為購買參加人商品之客戶，且使相關消費者對於產品來源產生不當之聯想，蓋實際上參加人據以異議商標之商品於國內寵物市場仍然繼續銷售，消費者在銷售寵物飼料之場所，仍有可能看到具有據以異議商標之商品與系爭商標商品同時陳列於貨架上，倘消費者基於原告上開通知之內容印象，極有可能會認為此二不同商標之商品其生產來源實為同一，而所以會有二商標商品同時存在貨架上，有可能係因「舊」商標商品尚未售罄緣故。換言之，原告之行止，不僅未降低系爭商標與據以異議商標使消費者產生混淆誤認之可能性，反提高其致使相關消費者產生混淆誤認之程度，同時益證原告以系爭商標申請註冊，指定使用在商標法施行細則第13條所定修正前商品及服務分類表第31類之「寵物飼料、非醫用飼料添加物、非醫用飼料添加劑、動物用奶粉、狗飼料、貓飼料、狗餅乾、寵物用食品、動物用飼養劑、動物可食用咀嚼物、寵物用飲料」商品，其目的在於混淆消費者對於其所銷售之商品與據以異議商標商品之來源。(五)況依國內PChome線上購物網站資料展示寵物飼料商品之外包裝盒上雖標示有「OPTI-PRO」字樣，惟標題及商品介紹仍指向據以異議商標「OPTIMA」，或標題雖為「OPTI-PRO」，然商品圖片卻展示據以異議商標之產品，依系爭商標實際使用之整體態樣，客觀上易使相關消費者產生二商標之商品係來自相同產製主體之聯想，而有混淆誤認之虞。原告雖主張其未以相同之包裝及近似商標標示銷售而獲利，且上開購物網站資料之商品係銷售者之個人行為，非其所為，復以其公司網站資料並無販售及陳列據以異議商標商品之訊息云云。惟查，上開購物網站資料所載商品資訊，縱非原告所為，然其內容仍不違背原告上開公告通知之意旨，消費者瀏覽相關資訊時，仍極易將二造商標商品之來源產生聯想。是以，縱使上開網路訊息並非原告親為，然其商品確係以此種方式於市場上販售，且此種銷售方式亦符合原告上開通知意旨（即原「OPTIMA」商標已改為「OPTI-PRO」）。本院審酌上開證據事實，以及參酌據以異議商標商品早於系爭商標商品進入國內市場，其商標識別性較之系爭商標為強、以及系爭商標與據以異議商標兩者雖屬中度近似，惟二商標指定使用之商品或服務卻屬相同或高度類似等相關因素、相互影響關係及各因素等綜合判斷，認為系爭商標使用近似於據以異議商標之文字，且指定使用在相同或高度類似之商品或服務，確已達有致相關消費者產生混淆誤認之虞程度，顯已違反商標法第23條第1項第13款規定，應不許其註冊。五、綜上所述，被告依首揭規定，為系爭商標之註冊應予撤銷之處分，並無不合。訴願決定予駁回，亦無違誤，均應予以維持。本件原告請求撤銷原處分及訴願決定，為無理由，應予駁回。六、本件事證已明，兩造其餘主張或答辯，已與本院判決結果無影響，爰毋庸一一論列，併此敘明。據上論結，本件原告之訴為無理由，爰依智慧財產案件審理法第1條、行政訴訟法第98條第1項前段，判決如主文。中華民國100年10月31日智慧財產法院第一庭審判長法官李得灶法官林欣蓉法官汪漢卿以上正本係照原本作成。如不服本判決，應於送達後20日內，向本院提出上訴狀並表明上訴理由（須按他造人數附繕本）。如於本判決宣示後送達前提起上訴者，應於判決送達後20日內補提上訴理由書（須按他造人數附繕本）。中華民國100年11月2日書記官邱于婷",
  "characters": {
    "judges": [
      "李得灶",
      "林欣蓉",
      "汪漢卿"
    ],
    "prosecutors": [

    ],
    "lawyers": [

    ],
    "clerks": [

    ],
    "plaintiffs": [
      "艾凘克企業股份有限公司"
    ],
    "defendants": [
      "經濟部智慧財產局設臺北市大安區辛亥路二段185",
      "代  表  人  王美花（局長）"
    ],
    "prosecutor_office": [

    ],
    "creditors": [

    ],
    "debtors": [

    ],
    "judicial_associate_officer": [

    ]
  },
  "adjudged_at": "2011-10-31",
  "created_at": "2016-02-14 08:41:49",
  "updated_at": "2016-02-14 08:41:49"
}