{
  "identify": "KSD-100-聲-5119-20111031-1",
  "court": {
    "name": "臺灣高雄地方法院",
    "code": "KSD"
  },
  "division": {
    "name": "刑事",
    "code": "M"
  },
  "year": 100,
  "word": "聲",
  "number": "5119",
  "jcheck": "1",
  "reason": "聲請具保停止羈押",
  "content": "臺灣高雄地方法院刑事裁定             100年度聲字第5119號\n聲 請 人即  郭正鵬律師\n選任辯護人\n被      告  鄧天生\n上列聲請人因被告涉嫌犯偽造信用卡等案件，聲請具保停止羈押\n，本院裁定如下：\n    主  文\n聲請駁回。\n    理  由\n一、聲請意旨略以：被告鄧天生對於檢察官起訴之事實均坦承不\n    諱，核被告所為係犯刑法第第339條之2第1項之非法由自動\n    付款設備取財罪，並非刑事訴訟法第101條之1第1項第7款之\n    罪，自不能以被告有反覆實施同一犯罪之虞之羈押原因，予\n    以羈押；且被告既對起訴書所載事實，均坦承不諱，自無勾\n    串共犯、湮滅證據之虞；又本件縱有羈押原因，亦應無羈押\n    之必要，爰請求具保停止羈押云云。\n二、經查：被告前經法官訊問後認被告坦承犯行，足認涉犯詐欺\n    取財罪及非法以電腦製作不實財產紀錄罪及行使偽造有價證\n    券罪嫌疑重大，且本案尚有共犯「豆仔」、「二尺」在逃尚\n    未歸案，有事實足認被告有勾串共犯、湮滅證據之虞，且被\n    告盜領款項多次，有反覆實施同一犯罪之虞，非於羈押顯難\n    進行審判，而依刑事訴訟法第101條第1項第2款、第101條之\n    1第1項第7款，予以羈押。聲請人雖以前揭理由聲請具保停\n    止羈押。惟查：縱經本院審理後，認被告所為應係犯刑法第\n    第339條之2第1項之非法由自動付款設備取財罪，並非刑事\n    訴訟法第101條之1第1項第7款之罪，而無反覆實施同一犯罪\n    之虞之羈押原因；且被告對於本案已坦承不諱。惟本案既仍\n    有共犯「豆仔」、「二尺」在逃尚未歸案，且被告所盜領之\n    金額約0000000元，均尚未追回，被告自仍有勾串共犯及湮\n    滅證據（包括贓款0000000元）之虞。即被告所盜領而尚未\n    追回之贓款甚鉅，倘被告未受羈押，依一般常情，自有極高\n    之可能性，被告自行或與其他共犯共同處分或隱匿該鉅額贓\n    款，而有羈押之必要性，且該羈押之必要性，顯無法以責付\n    、限制住居、具保或其他方式代替之。從而，聲請人以上開\n    事由聲請具保停止羈押，尚難准許，是應予駁回。\n三、依刑事訴訟法第220 條，裁定如主文。\n中    華    民    國   100    年    10    月    31    日\n                 刑事第二庭審判長法  官  李政庭\n                                 法  官  洪韻婷\n                                 法  官  施盈志\n以上正本證明與原本無異。\n如不服本裁定，應於收受送達後5 日內向本院提出抗告狀。\n中    華    民    國   100    年    10    月    31    日\n                                 書記官  吳和卿",
  "structure": {
    "main": "聲請駁回。",
    "reason": "一、聲請意旨略以：被告鄧天生對於檢察官起訴之事實均坦承不\n    諱，核被告所為係犯刑法第第339條之2第1項之非法由自動\n    付款設備取財罪，並非刑事訴訟法第101條之1第1項第7款之\n    罪，自不能以被告有反覆實施同一犯罪之虞之羈押原因，予\n    以羈押；且被告既對起訴書所載事實，均坦承不諱，自無勾\n    串共犯、湮滅證據之虞；又本件縱有羈押原因，亦應無羈押\n    之必要，爰請求具保停止羈押云云。\n二、經查：被告前經法官訊問後認被告坦承犯行，足認涉犯詐欺\n    取財罪及非法以電腦製作不實財產紀錄罪及行使偽造有價證\n    券罪嫌疑重大，且本案尚有共犯「豆仔」、「二尺」在逃尚\n    未歸案，有事實足認被告有勾串共犯、湮滅證據之虞，且被\n    告盜領款項多次，有反覆實施同一犯罪之虞，非於羈押顯難\n    進行審判，而依刑事訴訟法第101條第1項第2款、第101條之\n    1第1項第7款，予以羈押。聲請人雖以前揭理由聲請具保停\n    止羈押。惟查：縱經本院審理後，認被告所為應係犯刑法第\n    第339條之2第1項之非法由自動付款設備取財罪，並非刑事\n    訴訟法第101條之1第1項第7款之罪，而無反覆實施同一犯罪\n    之虞之羈押原因；且被告對於本案已坦承不諱。惟本案既仍\n    有共犯「豆仔」、「二尺」在逃尚未歸案，且被告所盜領之\n    金額約0000000元，均尚未追回，被告自仍有勾串共犯及湮\n    滅證據（包括贓款0000000元）之虞。即被告所盜領而尚未\n    追回之贓款甚鉅，倘被告未受羈押，依一般常情，自有極高\n    之可能性，被告自行或與其他共犯共同處分或隱匿該鉅額贓\n    款，而有羈押之必要性，且該羈押之必要性，顯無法以責付\n    、限制住居、具保或其他方式代替之。從而，聲請人以上開\n    事由聲請具保停止羈押，尚難准許，是應予駁回。\n三、依刑事訴訟法第220 條，裁定如主文。"
  },
  "search": "臺灣高雄地方法院刑事裁定100年度聲字第5119號聲請人即郭正鵬律師選任辯護人被告鄧天生上列聲請人因被告涉嫌犯偽造信用卡等案件，聲請具保停止羈押，本院裁定如下：主文聲請駁回。理由一、聲請意旨略以：被告鄧天生對於檢察官起訴之事實均坦承不諱，核被告所為係犯刑法第第339條之2第1項之非法由自動付款設備取財罪，並非刑事訴訟法第101條之1第1項第7款之罪，自不能以被告有反覆實施同一犯罪之虞之羈押原因，予以羈押；且被告既對起訴書所載事實，均坦承不諱，自無勾串共犯、湮滅證據之虞；又本件縱有羈押原因，亦應無羈押之必要，爰請求具保停止羈押云云。二、經查：被告前經法官訊問後認被告坦承犯行，足認涉犯詐欺取財罪及非法以電腦製作不實財產紀錄罪及行使偽造有價證券罪嫌疑重大，且本案尚有共犯「豆仔」、「二尺」在逃尚未歸案，有事實足認被告有勾串共犯、湮滅證據之虞，且被告盜領款項多次，有反覆實施同一犯罪之虞，非於羈押顯難進行審判，而依刑事訴訟法第101條第1項第2款、第101條之1第1項第7款，予以羈押。聲請人雖以前揭理由聲請具保停止羈押。惟查：縱經本院審理後，認被告所為應係犯刑法第第339條之2第1項之非法由自動付款設備取財罪，並非刑事訴訟法第101條之1第1項第7款之罪，而無反覆實施同一犯罪之虞之羈押原因；且被告對於本案已坦承不諱。惟本案既仍有共犯「豆仔」、「二尺」在逃尚未歸案，且被告所盜領之金額約0000000元，均尚未追回，被告自仍有勾串共犯及湮滅證據（包括贓款0000000元）之虞。即被告所盜領而尚未追回之贓款甚鉅，倘被告未受羈押，依一般常情，自有極高之可能性，被告自行或與其他共犯共同處分或隱匿該鉅額贓款，而有羈押之必要性，且該羈押之必要性，顯無法以責付、限制住居、具保或其他方式代替之。從而，聲請人以上開事由聲請具保停止羈押，尚難准許，是應予駁回。三、依刑事訴訟法第220條，裁定如主文。中華民國100年10月31日刑事第二庭審判長法官李政庭法官洪韻婷法官施盈志以上正本證明與原本無異。如不服本裁定，應於收受送達後5日內向本院提出抗告狀。中華民國100年10月31日書記官吳和卿",
  "characters": {
    "judges": [
      "李政庭",
      "洪韻婷",
      "施盈志"
    ],
    "prosecutors": [

    ],
    "lawyers": [
      "郭正鵬"
    ],
    "clerks": [

    ],
    "plaintiffs": [

    ],
    "defendants": [
      "鄧天生"
    ],
    "prosecutor_office": [

    ],
    "creditors": [

    ],
    "debtors": [

    ],
    "judicial_associate_officer": [

    ]
  },
  "adjudged_at": "2011-10-31",
  "created_at": "2016-02-14 08:16:50",
  "updated_at": "2016-02-14 08:16:50"
}