{
  "identify": "KSD-100-交簡-3815-20111031-1",
  "court": {
    "name": "臺灣高雄地方法院",
    "code": "KSD"
  },
  "division": {
    "name": "刑事",
    "code": "M"
  },
  "year": 100,
  "word": "交簡",
  "number": "3815",
  "jcheck": "1",
  "reason": "公共危險",
  "content": "臺灣高雄地方法院刑事簡易判決       100年度交簡字第3815號\n聲  請  人  臺灣高雄地方法院檢察署檢察官\n被      告  江清分\n上列被告因公共危險案件，經檢察官聲請以簡易判決處刑（100\n年度偵字第22523號），本院判決如下：\n    主      文\n江清分犯不能安全駕駛動力交通工具罪，累犯，處有期徒刑肆月\n，如易科罰金，以新臺幣壹仟元折算壹日。\n    事實及理由\n一、本件犯罪事實及證據，除犯罪事實欄一第7 ～8 行「追撞同\n    向在前由尤辛梅騎乘之車牌YYW-046 號機車」應補充為「追\n    撞同向在前由尤辛梅騎乘之車牌號碼YYW-046 號輕型機車（\n    過失傷害部分未據告訴）」；證據部分另補充「舉發違反道\n    路交通管理事件通知單」外，餘均引用附件檢察官聲請簡易\n    判決處刑書之記載。\n二、核被告江清分所為，係犯刑法第185 條之3 之不能安全駕駛\n    動力交通工具罪。又被告有如聲請簡易判決處刑書所載之曾\n    受有期徒刑之宣告及執行完畢乙節，有臺灣高等法院被告前\n    案紀錄表1 份在卷可參，其於有期徒刑執行完畢後，5 年內\n    故意再犯本件有期徒刑以上之罪，為累犯，應依刑法第47條\n    第1 項規定，加重其刑。爰審酌被告於飲用啤酒後猶貿然駕\n    駛自用小貨車行駛於一般道路等犯罪之動機、目的及手段，\n    且呼氣酒精濃度達每公升0.85毫克，危害公共安全甚鉅，並\n    業已肇事致傷產生實害，且其前甫因公共危險案件，經法院\n    判處有期徒刑2 月確定，此品行資料有上開前案紀錄表可考\n    ，復衡酌其犯後坦承犯罪之態度及其國小肄業之智識程度、\n    家境小康等經濟暨生活狀況等上開被告個人具體之行為人責\n    任基礎之一切情狀，量處如主文所示之刑，並參酌前開犯罪\n    情狀，諭知易科罰金之折算標準，以資警惕。\n三、依刑事訴訟法第449  條第1 項前段、第3 項、第454 條第2\n    項，刑法第185 條之3 、第47條第1 項、第41條第1 項前段\n    ，刑法施行法第1 條之1 第1 項，逕以簡易判決處刑如主文\n    。\n四、如不服本判決，得自判決送達之日起 10 日內，向本院提起\n    上訴。\n中    華    民    國   100    年    10    月    31    日\n                  高雄簡易庭  法  官  陳薏\n以上正本證明與原本無異。\n如不服本判決，應於送達之日起10日內向本院提出上訴書狀。\n中    華    民    國   100    年    10    月    31    日\n                              書記官  戴金龍\n附錄本案論罪科刑法條：\n刑法第185條之3\n服用毒品、麻醉藥品、酒類或其他相類之物，不能安全駕駛動力\n交通工具而駕駛者，處1年以下有期徒刑、拘役或科或併科15 萬\n元以下罰金。\n附件：\n臺灣高雄地方法院檢察署檢察官聲請簡易判決處刑書\n                                    100年度偵字第22523號\n    被      告  江清分  男  57歲（民國○○年○○月○○日生）\n                        住高雄市仁武區○○○街317之2號\n                        國民身分證統一編號：Ｚ000000000號\n上列被告因公共危險案件，業經偵查終結，認為宜以簡易判決處\n刑，茲將犯罪事實及證據並所犯法條分敘如下：\n        犯罪事實\n一、江清分前因公共危險案件，經臺灣臺東地方法院以99年度東\n    交簡字第212號判處有期徒刑2月確定，於民國100年1月31日\n    易科罰金執行完畢。竟猶不知悔改，於100年7月13日下午，\n    因飲用酒類後，已不能安全駕駛動力交通工具，猶駕駛車牌\n    F5-2748號自小貨車，沿高雄市三民區○○○路由西往東方\n    向行駛，於同日下午7時23分許，行經大中一路147巷口時，\n    因不慎酒力致注意力無法集中，追撞同向在前由尤辛梅騎乘\n    之車牌YYW-046號機車，尤辛梅之機車再追撞停放在旁之自\n    小客車，經警據報到場處理，並於同日下午7時53分許以酒\n    精測定器對其實施檢測吹氣，其吐氣所含酒精成份仍達每公\n    升0.85毫克而查獲。\n二、案經高雄市政府警察局三民第二分局移送偵辦。\n        證據並所犯法條\n一、上揭酒後駕車肇事之事實，業據被告江清分於警詢及偵訊時\n    坦承不諱，核與被害人尤辛梅於警詢中之指述相符，並有酒\n    精濃度測試表暨警製測試觀察紀錄表、生理平衡檢測紀錄表\n    、道路交通事故現場圖、道路交通事故調查報告表(一)、(二)各\n    1紙、交通事故談話紀錄表、現場蒐證照片7張附卷可稽，核\n    被告自白與事實相符，堪予採信。按汽車駕駛人飲酒後其吐\n    氣所含酒精成分超過每公升0.25毫克以上者，即不得駕車，\n    道路交通安全規則第114條第2款定有明文；次按刑法第185\n    條之3規定所謂「不能安全駕駛」，係抽象危險犯，並不以\n    發生具體危險為必要，對呼氣酒精濃度已達每公升0.55毫克\n    以上，肇事率為一般正常人之10倍，認為已達不能安全駕車\n    之標準，至於上揭數值以下之行為，如輔以其他客觀事實得\n    作為「不能安全駕駛」之判斷時，亦應依刑法第185條之3之\n    規定移送法辦處以刑罰，此業經法務部88年5月18日以法88\n    檢字第001669號函告週知。被告為警查獲時其吐氣所含酒精\n    成份測試，達每公升0.85毫克，則其發生肇事之危險性，已\n    高出一般人甚多，況其復且駕車疏失而至肇事，依前揭說明\n    ，足認被告已達不能安全駕駛之情狀。本件事證明確，被告\n    犯嫌洵堪認定。\n二、核被告所為，係犯刑法第185條之3公共危險罪嫌。被告前曾\n    犯如犯罪事實欄所載之罪，此有本署刑案資料查註紀錄表在\n    卷可憑，於刑執行完畢後5年內故意再犯本罪，請依累犯規\n    定加重其刑論處。\n三、依刑事訴訟法第451條第1項聲請逕以簡易判決處刑。\n    此  致\n臺灣高雄地方法院\n中    華    民    國   100    年    9     月    30    日\n                              檢察官  黃雯麗\n上正本證明與原本無異\n中    華    民    國   100    年    10    月    5     日\n                              書記官  李元正\n所犯法條：\n中華民國刑法第185條之3\n服用毒品、麻醉藥品、酒類或其他相類之物，不能安全駕駛動力\n交通工具而駕駛者，處1年以下有期徒刑、拘役或科或併科15萬\n元以下罰金。\n附記事項：本件係依刑事訴訟法簡易程序辦理，法院簡易庭得不\n傳喚被告、輔佐人、告訴人、告發人等出庭即以簡易判決處刑；\n被告、被害人、告訴人等對告訴乃論案件如已達成民事和解而要\n撤回告訴或對非告訴乃論案件認有受傳喚到庭陳述意見之必要時\n，請即另以書狀向簡易法庭陳述或請求傳訊。",
  "structure": {
    "main": "江清分犯不能安全駕駛動力交通工具罪，累犯，處有期徒刑肆月\n，如易科罰金，以新臺幣壹仟元折算壹日。",
    "fact": "一、本件犯罪事實及證據，除犯罪事實欄一第7 ～8 行「追撞同\n    向在前由尤辛梅騎乘之車牌YYW-046 號機車」應補充為「追\n    撞同向在前由尤辛梅騎乘之車牌號碼YYW-046 號輕型機車（\n    過失傷害部分未據告訴）」；證據部分另補充「舉發違反道\n    路交通管理事件通知單」外，餘均引用附件檢察官聲請簡易\n    判決處刑書之記載。\n二、核被告江清分所為，係犯刑法第185 條之3 之不能安全駕駛\n    動力交通工具罪。又被告有如聲請簡易判決處刑書所載之曾\n    受有期徒刑之宣告及執行完畢乙節，有臺灣高等法院被告前\n    案紀錄表1 份在卷可參，其於有期徒刑執行完畢後，5 年內\n    故意再犯本件有期徒刑以上之罪，為累犯，應依刑法第47條\n    第1 項規定，加重其刑。爰審酌被告於飲用啤酒後猶貿然駕\n    駛自用小貨車行駛於一般道路等犯罪之動機、目的及手段，\n    且呼氣酒精濃度達每公升0.85毫克，危害公共安全甚鉅，並\n    業已肇事致傷產生實害，且其前甫因公共危險案件，經法院\n    判處有期徒刑2 月確定，此品行資料有上開前案紀錄表可考\n    ，復衡酌其犯後坦承犯罪之態度及其國小肄業之智識程度、\n    家境小康等經濟暨生活狀況等上開被告個人具體之行為人責\n    任基礎之一切情狀，量處如主文所示之刑，並參酌前開犯罪\n    情狀，諭知易科罰金之折算標準，以資警惕。\n三、依刑事訴訟法第449  條第1 項前段、第3 項、第454 條第2\n    項，刑法第185 條之3 、第47條第1 項、第41條第1 項前段\n    ，刑法施行法第1 條之1 第1 項，逕以簡易判決處刑如主文\n    。\n四、如不服本判決，得自判決送達之日起 10 日內，向本院提起\n    上訴。",
    "reason": "一、本件犯罪事實及證據，除犯罪事實欄一第7 ～8 行「追撞同\n    向在前由尤辛梅騎乘之車牌YYW-046 號機車」應補充為「追\n    撞同向在前由尤辛梅騎乘之車牌號碼YYW-046 號輕型機車（\n    過失傷害部分未據告訴）」；證據部分另補充「舉發違反道\n    路交通管理事件通知單」外，餘均引用附件檢察官聲請簡易\n    判決處刑書之記載。\n二、核被告江清分所為，係犯刑法第185 條之3 之不能安全駕駛\n    動力交通工具罪。又被告有如聲請簡易判決處刑書所載之曾\n    受有期徒刑之宣告及執行完畢乙節，有臺灣高等法院被告前\n    案紀錄表1 份在卷可參，其於有期徒刑執行完畢後，5 年內\n    故意再犯本件有期徒刑以上之罪，為累犯，應依刑法第47條\n    第1 項規定，加重其刑。爰審酌被告於飲用啤酒後猶貿然駕\n    駛自用小貨車行駛於一般道路等犯罪之動機、目的及手段，\n    且呼氣酒精濃度達每公升0.85毫克，危害公共安全甚鉅，並\n    業已肇事致傷產生實害，且其前甫因公共危險案件，經法院\n    判處有期徒刑2 月確定，此品行資料有上開前案紀錄表可考\n    ，復衡酌其犯後坦承犯罪之態度及其國小肄業之智識程度、\n    家境小康等經濟暨生活狀況等上開被告個人具體之行為人責\n    任基礎之一切情狀，量處如主文所示之刑，並參酌前開犯罪\n    情狀，諭知易科罰金之折算標準，以資警惕。\n三、依刑事訴訟法第449  條第1 項前段、第3 項、第454 條第2\n    項，刑法第185 條之3 、第47條第1 項、第41條第1 項前段\n    ，刑法施行法第1 條之1 第1 項，逕以簡易判決處刑如主文\n    。\n四、如不服本判決，得自判決送達之日起 10 日內，向本院提起\n    上訴。"
  },
  "search": "臺灣高雄地方法院刑事簡易判決100年度交簡字第3815號聲請人臺灣高雄地方法院檢察署檢察官被告江清分上列被告因公共危險案件，經檢察官聲請以簡易判決處刑（100年度偵字第22523號），本院判決如下：主文江清分犯不能安全駕駛動力交通工具罪，累犯，處有期徒刑肆月，如易科罰金，以新臺幣壹仟元折算壹日。事實及理由一、本件犯罪事實及證據，除犯罪事實欄一第7～8行「追撞同向在前由尤辛梅騎乘之車牌YYW-046號機車」應補充為「追撞同向在前由尤辛梅騎乘之車牌號碼YYW-046號輕型機車（過失傷害部分未據告訴）」；證據部分另補充「舉發違反道路交通管理事件通知單」外，餘均引用附件檢察官聲請簡易判決處刑書之記載。二、核被告江清分所為，係犯刑法第185條之3之不能安全駕駛動力交通工具罪。又被告有如聲請簡易判決處刑書所載之曾受有期徒刑之宣告及執行完畢乙節，有臺灣高等法院被告前案紀錄表1份在卷可參，其於有期徒刑執行完畢後，5年內故意再犯本件有期徒刑以上之罪，為累犯，應依刑法第47條第1項規定，加重其刑。爰審酌被告於飲用啤酒後猶貿然駕駛自用小貨車行駛於一般道路等犯罪之動機、目的及手段，且呼氣酒精濃度達每公升0.85毫克，危害公共安全甚鉅，並業已肇事致傷產生實害，且其前甫因公共危險案件，經法院判處有期徒刑2月確定，此品行資料有上開前案紀錄表可考，復衡酌其犯後坦承犯罪之態度及其國小肄業之智識程度、家境小康等經濟暨生活狀況等上開被告個人具體之行為人責任基礎之一切情狀，量處如主文所示之刑，並參酌前開犯罪情狀，諭知易科罰金之折算標準，以資警惕。三、依刑事訴訟法第449條第1項前段、第3項、第454條第2項，刑法第185條之3、第47條第1項、第41條第1項前段，刑法施行法第1條之1第1項，逕以簡易判決處刑如主文。四、如不服本判決，得自判決送達之日起10日內，向本院提起上訴。中華民國100年10月31日高雄簡易庭法官陳薏以上正本證明與原本無異。如不服本判決，應於送達之日起10日內向本院提出上訴書狀。中華民國100年10月31日書記官戴金龍附錄本案論罪科刑法條：刑法第185條之3服用毒品、麻醉藥品、酒類或其他相類之物，不能安全駕駛動力交通工具而駕駛者，處1年以下有期徒刑、拘役或科或併科15萬元以下罰金。附件：臺灣高雄地方法院檢察署檢察官聲請簡易判決處刑書100年度偵字第22523號被告江清分男57歲（民國○○年○○月○○日生）住高雄市仁武區○○○街317之2號國民身分證統一編號：Ｚ000000000號上列被告因公共危險案件，業經偵查終結，認為宜以簡易判決處刑，茲將犯罪事實及證據並所犯法條分敘如下：犯罪事實一、江清分前因公共危險案件，經臺灣臺東地方法院以99年度東交簡字第212號判處有期徒刑2月確定，於民國100年1月31日易科罰金執行完畢。竟猶不知悔改，於100年7月13日下午，因飲用酒類後，已不能安全駕駛動力交通工具，猶駕駛車牌F5-2748號自小貨車，沿高雄市三民區○○○路由西往東方向行駛，於同日下午7時23分許，行經大中一路147巷口時，因不慎酒力致注意力無法集中，追撞同向在前由尤辛梅騎乘之車牌YYW-046號機車，尤辛梅之機車再追撞停放在旁之自小客車，經警據報到場處理，並於同日下午7時53分許以酒精測定器對其實施檢測吹氣，其吐氣所含酒精成份仍達每公升0.85毫克而查獲。二、案經高雄市政府警察局三民第二分局移送偵辦。證據並所犯法條一、上揭酒後駕車肇事之事實，業據被告江清分於警詢及偵訊時坦承不諱，核與被害人尤辛梅於警詢中之指述相符，並有酒精濃度測試表暨警製測試觀察紀錄表、生理平衡檢測紀錄表、道路交通事故現場圖、道路交通事故調查報告表(一)、(二)各1紙、交通事故談話紀錄表、現場蒐證照片7張附卷可稽，核被告自白與事實相符，堪予採信。按汽車駕駛人飲酒後其吐氣所含酒精成分超過每公升0.25毫克以上者，即不得駕車，道路交通安全規則第114條第2款定有明文；次按刑法第185條之3規定所謂「不能安全駕駛」，係抽象危險犯，並不以發生具體危險為必要，對呼氣酒精濃度已達每公升0.55毫克以上，肇事率為一般正常人之10倍，認為已達不能安全駕車之標準，至於上揭數值以下之行為，如輔以其他客觀事實得作為「不能安全駕駛」之判斷時，亦應依刑法第185條之3之規定移送法辦處以刑罰，此業經法務部88年5月18日以法88檢字第001669號函告週知。被告為警查獲時其吐氣所含酒精成份測試，達每公升0.85毫克，則其發生肇事之危險性，已高出一般人甚多，況其復且駕車疏失而至肇事，依前揭說明，足認被告已達不能安全駕駛之情狀。本件事證明確，被告犯嫌洵堪認定。二、核被告所為，係犯刑法第185條之3公共危險罪嫌。被告前曾犯如犯罪事實欄所載之罪，此有本署刑案資料查註紀錄表在卷可憑，於刑執行完畢後5年內故意再犯本罪，請依累犯規定加重其刑論處。三、依刑事訴訟法第451條第1項聲請逕以簡易判決處刑。此致臺灣高雄地方法院中華民國100年9月30日檢察官黃雯麗上正本證明與原本無異中華民國100年10月5日書記官李元正所犯法條：中華民國刑法第185條之3服用毒品、麻醉藥品、酒類或其他相類之物，不能安全駕駛動力交通工具而駕駛者，處1年以下有期徒刑、拘役或科或併科15萬元以下罰金。附記事項：本件係依刑事訴訟法簡易程序辦理，法院簡易庭得不傳喚被告、輔佐人、告訴人、告發人等出庭即以簡易判決處刑；被告、被害人、告訴人等對告訴乃論案件如已達成民事和解而要撤回告訴或對非告訴乃論案件認有受傳喚到庭陳述意見之必要時，請即另以書狀向簡易法庭陳述或請求傳訊。",
  "characters": {
    "judges": [
      "陳薏"
    ],
    "prosecutors": [

    ],
    "lawyers": [

    ],
    "clerks": [
      "戴金龍",
      "李元正"
    ],
    "plaintiffs": [

    ],
    "defendants": [
      "江清分",
      "江清分  男  57歲（民國○○年○○月○○日生）"
    ],
    "prosecutor_office": [
      "臺灣高雄地方法院檢察署檢察官"
    ],
    "creditors": [

    ],
    "debtors": [

    ],
    "judicial_associate_officer": [

    ]
  },
  "adjudged_at": "2011-10-31",
  "created_at": "2016-02-14 08:33:12",
  "updated_at": "2016-02-14 08:33:12"
}