{
  "identify": "PCD-100-簡上-359-20111031-1",
  "court": {
    "name": "臺灣新北地方法院",
    "code": "PCD"
  },
  "division": {
    "name": "刑事",
    "code": "M"
  },
  "year": 100,
  "word": "簡上",
  "number": "359",
  "jcheck": "1",
  "reason": "妨害風化",
  "content": "臺灣板橋地方法院刑事判決            100年度簡上字第359號\n上  訴  人\n即  被  告  王民益\n上列上訴人即被告因妨害風化案件，不服本院中華民國100 年4\n月11日100 年度簡字第2471號第一審簡易判決（聲請簡易判決處\n刑案號：臺灣板橋地方法院檢察署100 年度速偵字第1487號）提\n起上訴，本院管轄之第二審合議庭判決如下：\n    主  文\n原判決撤銷。\n王民益共同意圖使女子與他人為性交之行為，而媒介以營利，處\n有期徒刑月，如易科罰金，以新臺幣壹仟元折算壹日，扣案之\n行動電話SIM 卡壹枚（門號0000000000號）、現金新臺幣貳仟伍\n佰元，均沒收之。\n    事  實                                              \n一、王民益與真實姓名年籍不詳綽號「阿正」之成年男子共同基\n    於意圖使女子與他人為性交易行為而媒介以營利之犯意聯絡\n    ，自民國100 年2 月8 日起，以日薪新臺幣（下同）2,200\n    元之代價，受僱於「阿正」，擔任接送女子與不特定男客從\n    事性交易之司機工作，並負責於性交易完成後，向該女子收\n    取性交易所得，轉交「阿正」，於扣除其薪資後，餘款繳交\n    與「阿正」。嗣於100 年3 月1 日某時，接獲「阿正」電話\n    指示後，即駕駛車牌號碼CD-7272 號自用小客車，搭載成年\n    女子彭玉芳（違反社會秩序維護法部分另由警移送本院三重\n    簡易庭裁處），前往位在新北市○○區○○路3 段8 號「雅\n    緹汽車旅館」205 號房處，由彭玉芳以5000元之價碼，與男\n    客劉奇欣從事性交易。嗣於同日20時40分許，為警在位在新\n    北市○○區○○路與化成路11巷口「雅緹汽車旅館」停車場\n    內查獲，並扣得王民益所持用之門號0000000000號及彭玉芳\n    所持用之門號0000000000號行動電話SIM 卡各1 枚、性交易\n    所得50 00 元，始查悉上情。\n二、案經新北市政府警察局新莊分局移送臺灣板橋地方法院檢察\n    署檢察官聲請簡易判決處刑。\n    理  由                                                                \n一、按刑事訴訟法第159 條第1 項雖規定，被告以外之人於審判\n    外之言詞或書面陳述，除法律有規定者外，不得作為證據。\n    惟同法第159 條之5 第1 、2 項已規定，經當事人於審判程\n    序同意作為證據，法院審酌該言詞陳述或書面陳述作成時之\n    情況，認為適當者，亦得為證據。當事人、代理人或辯護人\n    於法院調查證據時，知有第159 條第1 項不得為證據之情形\n    ，而未於言詞辯論終結前聲明異議者，視為有前項之同意（\n    指同條第1 項之同意作為證據），此乃第159 條第1 項所容\n    許，得作為證據之例外規定之一。經查，本案被告王民益及\n    檢察官於言詞辯論終結前，均未就判決所引用之各該被告以\n    外之人於審判外之陳述（含共同被告基於被告以外之人身分\n    所為陳述）及所調查之證據主張有刑事訴訟法第159 條第1\n    項不得為證據之情形，本院復審酌各該證據作成時並無違法\n    及證明力明顯過低之瑕疵等情況，認為適當，是本案經調查\n    之證據均有證據能力。至以下所引其餘非屬供述證據部分，\n    既不適用傳聞法則，復查無違法取得之情事存在，自應認同\n    具證據能力。\n二、前揭事實，業據被告王民益於偵查及本院審理中均坦承不諱\n    ，核與證人彭玉芳、劉奇欣於警詢之證述情節相符，復有搜\n    索扣押筆錄、扣押物品目錄表、現場蒐證照片2 張附卷可稽\n    ，並扣得王民益所持用之門號0000000000號及彭玉芳所持用\n    之門號0000000000號行動電話SIM 卡各1 枚、性交易所得財\n    物5,00 0元等物，足認被告上開所為不利於己之自白與事實\n    相符，堪信為真實。據此，本案事證明確，被告上開妨害風\n    化犯行，堪以認定。\n三、核被告所為，係犯刑法第231 條第1 項前段之意圖使女子與\n    他人為性交之行為，而媒介以營利罪。又被告與真實姓名年\n    籍不詳綽號「阿正」之成年男子就上開犯行間，有犯意聯絡\n    及行為分擔，應論以共同正犯。另按刑事法若干本質上具有\n    反覆、延續實行特徵之行為，因立法時既予特別歸類，定為\n    犯罪構成要件之行為要素，故行為人基於概括之犯意，在密\n    切接近之一定時、地持續實行之複次行為，倘依社會通念，\n    於客觀上認為符合一個反覆、延續性之行為觀念者，於刑法\n    評價上，即應僅成立一罪，俾免有重複評價、刑度超過罪責\n    與不法內涵之疑慮，學理上所稱「集合犯」之職業性、營業\n    性或收集性等具有重複特質之犯罪均屬之，例如經營、從事\n    業務、收集、販賣、製造、散布等行為概念者是，最高法院\n    95年台上字第1079號判決要旨可資參照。是故，本件被告受\n    僱於應召站，負責載送女子至旅館與男客為性交易，而媒介\n    女子與他人為性交而營利，其行為具有反覆實施之特性，應\n    屬集合犯之包括一罪。\n四、撤銷改判之理由及科刑：\n  (一)原審認被告犯罪事證明確，而予以論罪科刑，固非無見，惟\n    查，被告並無任何前科犯行，此有臺灣高等法院被告前案紀\n    錄表1 份在卷可佐，是本院認原審以被告前因妨害風化案件\n    受刑之宣告，猶不知悔改之情，而量處有期徒刑4 月，如易\n    科罰金，以新臺幣1000元折算一日，則有違誤，被告執此提\n    起本件上訴，即有理由，自應由本院管轄之第二審合議庭將\n    原判決予以撤銷。\n  (二)爰審酌被告之素行尚佳，此有前開之被告前案紀錄表1 份在\n    卷可按，惟衡其不思以合法手段謀求生計，竟媒介女子賣淫\n    以營利，所為非是，兼衡其犯罪動機、目的、手段、犯後態\n    度等一切情狀，爰量處如主文第二項所示之刑，並諭知易科\n    罰金之折算標準，以資懲儆。另扣案之門號0000000000號行\n    動電話SIM 卡1 枚，為被告所有供本件犯罪所用之物；另媒\n    介性交易所得新臺幣2,500 元，為被告所有因本件犯罪所得\n    之物，業據被告供承在卷，爰分別依刑法第38條第1 項第2\n    、3 款宣告沒收之；另其餘2500元則係彭玉芳因該次性交易\n    所得之財物，非本件被告所有，再門號0000000000號行動電\n    話SIM 卡1 枚，係證人彭玉芳所有，核其性質亦非屬違禁物\n    ，爰均不予宣告沒收，附此說明。\n據上論斷，依刑事訴訟法第455 條之1 第1 項、第3 項、第369\n條第1 項前段、第364 條、第299 條第1 項前段，刑法第28條、\n第231 條第1 項、第41條第1 項前段、第38條第1 項第2 款、第\n3款，刑法施行法第1 條之1第1項、第2項前段 ，判決如主文。\n本案經檢察官王乙軒到庭執行職務。\n中    華    民    國    100   年    10    月    31    日\n                    刑事第一庭審判長  法  官 李釱任\n                          \n                                      法  官 戴嘉清\n\n                                      法  官 陳正偉\n上列正本證明與原本無異。\n不得上訴。\n\n                                      書記官 許慧禎\n\n中    華    民    國    100   年    10    月    31    日\n附錄本案論罪科刑法條全文：\n中華民國刑法第231條\n意圖使男女與他人為性交或猥褻之行為，而引誘、容留或媒介以\n營利者，處5 年以下有期徒刑，得併科10萬元以下罰金。以詐術\n犯之者，亦同。\n公務員包庇他人犯前項之罪者，依前項之規定加重其刑至二分之\n一。",
  "structure": {
    "main": "原判決撤銷。\n王民益共同意圖使女子與他人為性交之行為，而媒介以營利，處\n有期徒刑月，如易科罰金，以新臺幣壹仟元折算壹日，扣案之\n行動電話SIM 卡壹枚（門號0000000000號）、現金新臺幣貳仟伍\n佰元，均沒收之。",
    "fact": "一、王民益與真實姓名年籍不詳綽號「阿正」之成年男子共同基\n    於意圖使女子與他人為性交易行為而媒介以營利之犯意聯絡\n    ，自民國100 年2 月8 日起，以日薪新臺幣（下同）2,200\n    元之代價，受僱於「阿正」，擔任接送女子與不特定男客從\n    事性交易之司機工作，並負責於性交易完成後，向該女子收\n    取性交易所得，轉交「阿正」，於扣除其薪資後，餘款繳交\n    與「阿正」。嗣於100 年3 月1 日某時，接獲「阿正」電話\n    指示後，即駕駛車牌號碼CD-7272 號自用小客車，搭載成年\n    女子彭玉芳（違反社會秩序維護法部分另由警移送本院三重\n    簡易庭裁處），前往位在新北市○○區○○路3 段8 號「雅\n    緹汽車旅館」205 號房處，由彭玉芳以5000元之價碼，與男\n    客劉奇欣從事性交易。嗣於同日20時40分許，為警在位在新\n    北市○○區○○路與化成路11巷口「雅緹汽車旅館」停車場\n    內查獲，並扣得王民益所持用之門號0000000000號及彭玉芳\n    所持用之門號0000000000號行動電話SIM 卡各1 枚、性交易\n    所得50 00 元，始查悉上情。\n二、案經新北市政府警察局新莊分局移送臺灣板橋地方法院檢察\n    署檢察官聲請簡易判決處刑。",
    "reason": "一、按刑事訴訟法第159 條第1 項雖規定，被告以外之人於審判\n    外之言詞或書面陳述，除法律有規定者外，不得作為證據。\n    惟同法第159 條之5 第1 、2 項已規定，經當事人於審判程\n    序同意作為證據，法院審酌該言詞陳述或書面陳述作成時之\n    情況，認為適當者，亦得為證據。當事人、代理人或辯護人\n    於法院調查證據時，知有第159 條第1 項不得為證據之情形\n    ，而未於言詞辯論終結前聲明異議者，視為有前項之同意（\n    指同條第1 項之同意作為證據），此乃第159 條第1 項所容\n    許，得作為證據之例外規定之一。經查，本案被告王民益及\n    檢察官於言詞辯論終結前，均未就判決所引用之各該被告以\n    外之人於審判外之陳述（含共同被告基於被告以外之人身分\n    所為陳述）及所調查之證據主張有刑事訴訟法第159 條第1\n    項不得為證據之情形，本院復審酌各該證據作成時並無違法\n    及證明力明顯過低之瑕疵等情況，認為適當，是本案經調查\n    之證據均有證據能力。至以下所引其餘非屬供述證據部分，\n    既不適用傳聞法則，復查無違法取得之情事存在，自應認同\n    具證據能力。\n二、前揭事實，業據被告王民益於偵查及本院審理中均坦承不諱\n    ，核與證人彭玉芳、劉奇欣於警詢之證述情節相符，復有搜\n    索扣押筆錄、扣押物品目錄表、現場蒐證照片2 張附卷可稽\n    ，並扣得王民益所持用之門號0000000000號及彭玉芳所持用\n    之門號0000000000號行動電話SIM 卡各1 枚、性交易所得財\n    物5,00 0元等物，足認被告上開所為不利於己之自白與事實\n    相符，堪信為真實。據此，本案事證明確，被告上開妨害風\n    化犯行，堪以認定。\n三、核被告所為，係犯刑法第231 條第1 項前段之意圖使女子與\n    他人為性交之行為，而媒介以營利罪。又被告與真實姓名年\n    籍不詳綽號「阿正」之成年男子就上開犯行間，有犯意聯絡\n    及行為分擔，應論以共同正犯。另按刑事法若干本質上具有\n    反覆、延續實行特徵之行為，因立法時既予特別歸類，定為\n    犯罪構成要件之行為要素，故行為人基於概括之犯意，在密\n    切接近之一定時、地持續實行之複次行為，倘依社會通念，\n    於客觀上認為符合一個反覆、延續性之行為觀念者，於刑法\n    評價上，即應僅成立一罪，俾免有重複評價、刑度超過罪責\n    與不法內涵之疑慮，學理上所稱「集合犯」之職業性、營業\n    性或收集性等具有重複特質之犯罪均屬之，例如經營、從事\n    業務、收集、販賣、製造、散布等行為概念者是，最高法院\n    95年台上字第1079號判決要旨可資參照。是故，本件被告受\n    僱於應召站，負責載送女子至旅館與男客為性交易，而媒介\n    女子與他人為性交而營利，其行為具有反覆實施之特性，應\n    屬集合犯之包括一罪。\n四、撤銷改判之理由及科刑：\n  (一)原審認被告犯罪事證明確，而予以論罪科刑，固非無見，惟\n    查，被告並無任何前科犯行，此有臺灣高等法院被告前案紀\n    錄表1 份在卷可佐，是本院認原審以被告前因妨害風化案件\n    受刑之宣告，猶不知悔改之情，而量處有期徒刑4 月，如易\n    科罰金，以新臺幣1000元折算一日，則有違誤，被告執此提\n    起本件上訴，即有理由，自應由本院管轄之第二審合議庭將\n    原判決予以撤銷。\n  (二)爰審酌被告之素行尚佳，此有前開之被告前案紀錄表1 份在\n    卷可按，惟衡其不思以合法手段謀求生計，竟媒介女子賣淫\n    以營利，所為非是，兼衡其犯罪動機、目的、手段、犯後態\n    度等一切情狀，爰量處如主文第二項所示之刑，並諭知易科\n    罰金之折算標準，以資懲儆。另扣案之門號0000000000號行\n    動電話SIM 卡1 枚，為被告所有供本件犯罪所用之物；另媒\n    介性交易所得新臺幣2,500 元，為被告所有因本件犯罪所得\n    之物，業據被告供承在卷，爰分別依刑法第38條第1 項第2\n    、3 款宣告沒收之；另其餘2500元則係彭玉芳因該次性交易\n    所得之財物，非本件被告所有，再門號0000000000號行動電\n    話SIM 卡1 枚，係證人彭玉芳所有，核其性質亦非屬違禁物\n    ，爰均不予宣告沒收，附此說明。\n據上論斷，依刑事訴訟法第455 條之1 第1 項、第3 項、第369\n條第1 項前段、第364 條、第299 條第1 項前段，刑法第28條、\n第231 條第1 項、第41條第1 項前段、第38條第1 項第2 款、第\n3款，刑法施行法第1 條之1第1項、第2項前段 ，判決如主文。\n本案經檢察官王乙軒到庭執行職務。\n中    華    民    國    100   年    10    月    31    日\n                    刑事第一庭審判長  法  官 李釱任\n                          \n                                      法  官 戴嘉清\n\n                                      法  官 陳正偉\n上列正本證明與原本無異。\n不得上訴。\n\n                                      書記官 許慧禎"
  },
  "search": "臺灣板橋地方法院刑事判決100年度簡上字第359號上訴人即被告王民益上列上訴人即被告因妨害風化案件，不服本院中華民國100年4月11日100年度簡字第2471號第一審簡易判決（聲請簡易判決處刑案號：臺灣板橋地方法院檢察署100年度速偵字第1487號）提起上訴，本院管轄之第二審合議庭判決如下：主文原判決撤銷。王民益共同意圖使女子與他人為性交之行為，而媒介以營利，處有期徒刑月，如易科罰金，以新臺幣壹仟元折算壹日，扣案之行動電話SIM卡壹枚（門號0000000000號）、現金新臺幣貳仟伍佰元，均沒收之。事實一、王民益與真實姓名年籍不詳綽號「阿正」之成年男子共同基於意圖使女子與他人為性交易行為而媒介以營利之犯意聯絡，自民國100年2月8日起，以日薪新臺幣（下同）2,200元之代價，受僱於「阿正」，擔任接送女子與不特定男客從事性交易之司機工作，並負責於性交易完成後，向該女子收取性交易所得，轉交「阿正」，於扣除其薪資後，餘款繳交與「阿正」。嗣於100年3月1日某時，接獲「阿正」電話指示後，即駕駛車牌號碼CD-7272號自用小客車，搭載成年女子彭玉芳（違反社會秩序維護法部分另由警移送本院三重簡易庭裁處），前往位在新北市○○區○○路3段8號「雅緹汽車旅館」205號房處，由彭玉芳以5000元之價碼，與男客劉奇欣從事性交易。嗣於同日20時40分許，為警在位在新北市○○區○○路與化成路11巷口「雅緹汽車旅館」停車場內查獲，並扣得王民益所持用之門號0000000000號及彭玉芳所持用之門號0000000000號行動電話SIM卡各1枚、性交易所得5000元，始查悉上情。二、案經新北市政府警察局新莊分局移送臺灣板橋地方法院檢察署檢察官聲請簡易判決處刑。理由一、按刑事訴訟法第159條第1項雖規定，被告以外之人於審判外之言詞或書面陳述，除法律有規定者外，不得作為證據。惟同法第159條之5第1、2項已規定，經當事人於審判程序同意作為證據，法院審酌該言詞陳述或書面陳述作成時之情況，認為適當者，亦得為證據。當事人、代理人或辯護人於法院調查證據時，知有第159條第1項不得為證據之情形，而未於言詞辯論終結前聲明異議者，視為有前項之同意（指同條第1項之同意作為證據），此乃第159條第1項所容許，得作為證據之例外規定之一。經查，本案被告王民益及檢察官於言詞辯論終結前，均未就判決所引用之各該被告以外之人於審判外之陳述（含共同被告基於被告以外之人身分所為陳述）及所調查之證據主張有刑事訴訟法第159條第1項不得為證據之情形，本院復審酌各該證據作成時並無違法及證明力明顯過低之瑕疵等情況，認為適當，是本案經調查之證據均有證據能力。至以下所引其餘非屬供述證據部分，既不適用傳聞法則，復查無違法取得之情事存在，自應認同具證據能力。二、前揭事實，業據被告王民益於偵查及本院審理中均坦承不諱，核與證人彭玉芳、劉奇欣於警詢之證述情節相符，復有搜索扣押筆錄、扣押物品目錄表、現場蒐證照片2張附卷可稽，並扣得王民益所持用之門號0000000000號及彭玉芳所持用之門號0000000000號行動電話SIM卡各1枚、性交易所得財物5,000元等物，足認被告上開所為不利於己之自白與事實相符，堪信為真實。據此，本案事證明確，被告上開妨害風化犯行，堪以認定。三、核被告所為，係犯刑法第231條第1項前段之意圖使女子與他人為性交之行為，而媒介以營利罪。又被告與真實姓名年籍不詳綽號「阿正」之成年男子就上開犯行間，有犯意聯絡及行為分擔，應論以共同正犯。另按刑事法若干本質上具有反覆、延續實行特徵之行為，因立法時既予特別歸類，定為犯罪構成要件之行為要素，故行為人基於概括之犯意，在密切接近之一定時、地持續實行之複次行為，倘依社會通念，於客觀上認為符合一個反覆、延續性之行為觀念者，於刑法評價上，即應僅成立一罪，俾免有重複評價、刑度超過罪責與不法內涵之疑慮，學理上所稱「集合犯」之職業性、營業性或收集性等具有重複特質之犯罪均屬之，例如經營、從事業務、收集、販賣、製造、散布等行為概念者是，最高法院95年台上字第1079號判決要旨可資參照。是故，本件被告受僱於應召站，負責載送女子至旅館與男客為性交易，而媒介女子與他人為性交而營利，其行為具有反覆實施之特性，應屬集合犯之包括一罪。四、撤銷改判之理由及科刑：(一)原審認被告犯罪事證明確，而予以論罪科刑，固非無見，惟查，被告並無任何前科犯行，此有臺灣高等法院被告前案紀錄表1份在卷可佐，是本院認原審以被告前因妨害風化案件受刑之宣告，猶不知悔改之情，而量處有期徒刑4月，如易科罰金，以新臺幣1000元折算一日，則有違誤，被告執此提起本件上訴，即有理由，自應由本院管轄之第二審合議庭將原判決予以撤銷。(二)爰審酌被告之素行尚佳，此有前開之被告前案紀錄表1份在卷可按，惟衡其不思以合法手段謀求生計，竟媒介女子賣淫以營利，所為非是，兼衡其犯罪動機、目的、手段、犯後態度等一切情狀，爰量處如主文第二項所示之刑，並諭知易科罰金之折算標準，以資懲儆。另扣案之門號0000000000號行動電話SIM卡1枚，為被告所有供本件犯罪所用之物；另媒介性交易所得新臺幣2,500元，為被告所有因本件犯罪所得之物，業據被告供承在卷，爰分別依刑法第38條第1項第2、3款宣告沒收之；另其餘2500元則係彭玉芳因該次性交易所得之財物，非本件被告所有，再門號0000000000號行動電話SIM卡1枚，係證人彭玉芳所有，核其性質亦非屬違禁物，爰均不予宣告沒收，附此說明。據上論斷，依刑事訴訟法第455條之1第1項、第3項、第369條第1項前段、第364條、第299條第1項前段，刑法第28條、第231條第1項、第41條第1項前段、第38條第1項第2款、第3款，刑法施行法第1條之1第1項、第2項前段，判決如主文。本案經檢察官王乙軒到庭執行職務。中華民國100年10月31日刑事第一庭審判長法官李釱任法官戴嘉清法官陳正偉上列正本證明與原本無異。不得上訴。書記官許慧禎中華民國100年10月31日附錄本案論罪科刑法條全文：中華民國刑法第231條意圖使男女與他人為性交或猥褻之行為，而引誘、容留或媒介以營利者，處5年以下有期徒刑，得併科10萬元以下罰金。以詐術犯之者，亦同。公務員包庇他人犯前項之罪者，依前項之規定加重其刑至二分之一。",
  "characters": {
    "judges": [
      "李釱任",
      "戴嘉清",
      "陳正偉"
    ],
    "prosecutors": [
      "王乙軒"
    ],
    "lawyers": [

    ],
    "clerks": [
      "許慧禎"
    ],
    "plaintiffs": [

    ],
    "defendants": [
      "王民益"
    ],
    "prosecutor_office": [

    ],
    "creditors": [

    ],
    "debtors": [

    ],
    "judicial_associate_officer": [

    ]
  },
  "adjudged_at": "2011-10-31",
  "created_at": "2016-02-14 08:44:56",
  "updated_at": "2016-02-14 08:44:56"
}