{
  "identify": "TCD-100-聲-3779-20111031-1",
  "court": {
    "name": "臺灣臺中地方法院",
    "code": "TCD"
  },
  "division": {
    "name": "刑事",
    "code": "M"
  },
  "year": 100,
  "word": "聲",
  "number": "3779",
  "jcheck": "1",
  "reason": "聲請單獨宣告沒收",
  "content": "臺灣臺中地方法院刑事裁定          100 年度聲字第3779號\n聲  請  人  臺灣臺中地方法院檢察署檢察官\n被      告  PEACE WU  .\n上開聲請人聲請單獨宣告沒收違禁物案件（100年度聲沒字第199\n號），本院裁定如下：\n    主  文\n扣案之第二級毒品大麻貳包( 合計驗餘淨重貳拾點伍陸公克，含\n空包裝袋貳只) 沒收銷燬之。\n    理  由\n一、本件聲請意旨略以：財政部臺北關稅局於民國( 下同)99 年\n    3 月11日查獲一起來自荷蘭郵件。該郵件收件人為：PEACE\n    WU，收件地址為臺中市○區○○路300 號，內含疑似大麻煙\n    草2 包( 合計淨重20.60 公克，驗餘淨重20.56 公克，空包\n    裝總重3.58公克) ，經將內容物送鑑結果，確含第二級毒品\n    大麻成分，有法務部調查局濫用藥物實驗室鑑定書1 份在卷\n    可按，是上開查扣物係屬違禁物，爰依毒品危害防制條例第\n    18條第1 項前段（聲請書漏載，應予補充）、刑法第40條第\n    2 項、第38條第1 項第1 款、第2 項規定聲請宣告沒收銷燬\n    等語。\n二、按違禁物，不問屬於犯罪行為人與否，沒收之，且得單獨宣\n    告沒收；又查獲之第一、二級毒品，不問屬於犯人與否，均\n    沒收銷燬之，刑法第38條第1項第1款、第2項、第40條第2項\n    ，毒品危害防制條例第18條第1項前段分別定有明文。\n三、經查，扣案疑似第二級毒品大麻煙草2 包，經送法務部調查\n    局鑑定結果，均檢出含有大麻成分( 合計驗餘淨重20.56 公\n    克) ，有法務部調查局100 年6 月7 日調科壹字第10023013\n    000 號濫用藥物實驗室鑑定書在卷可憑。扣案之大麻係毒品\n    危害防制條例第2 條第2 項第2 款規定之第二級毒品，依同\n    條例之規定，不得製造、販賣、運輸、轉讓、持有，屬違禁\n    物。依首揭說明，聲請人聲請單獨宣告沒收並銷燬上開第二\n    級毒品，核無不合，應予准許( 其外包裝袋，與附著其上之\n    毒品無從析離，應視同毒品為違禁物併予沒收銷燬) 。至於\n    鑑驗耗損之第二級毒品大麻，既已滅失，爰不另行諭知沒收\n    銷燬，附此敘明。至本件檢察官雖僅引刑法第40條第2 項、\n    第38條第1 項第1 款、第2 項作為聲請依據，而漏引毒品危\n    害防制條例第18條第1 項前段，惟因該等物品本即屬應宣告\n    沒收且得單獨聲請法院宣告沒收之物，法院仍得裁定宣告沒\n    收銷燬之，並自行援引適當之規定，不受檢察官聲請書所載\n    法條之限制（臺灣高等法院暨所屬法院98年法律座談會刑事\n    類提案第39號研討結果參照），附此敘明。\n三、另扣案之郵件外包裝1件，已由臺灣臺中地方法院檢察署檢\n    察官於100年9月14日以中檢輝履字第118848號為廢棄處分命\n    令在案，爰不宣告沒收，併此敘明。\n四、爰依毒品危害防制條例第18條第1項前段、刑法第40條第2項\n    ，裁定如主文。\n中    華    民    國    100     年   10    月    31   日\n                  刑事第六庭    法  官  李立傑\n上正本証明與原本無異。\n如不服本裁定應於送達後五日內向本院提出抗告狀。\n                                書記官  陳怡臻\n中    華    民    國    100     年   10    月    31   日",
  "structure": {
    "main": "扣案之第二級毒品大麻貳包( 合計驗餘淨重貳拾點伍陸公克，含\n空包裝袋貳只) 沒收銷燬之。",
    "reason": "一、本件聲請意旨略以：財政部臺北關稅局於民國( 下同)99 年\n    3 月11日查獲一起來自荷蘭郵件。該郵件收件人為：PEACE\n    WU，收件地址為臺中市○區○○路300 號，內含疑似大麻煙\n    草2 包( 合計淨重20.60 公克，驗餘淨重20.56 公克，空包\n    裝總重3.58公克) ，經將內容物送鑑結果，確含第二級毒品\n    大麻成分，有法務部調查局濫用藥物實驗室鑑定書1 份在卷\n    可按，是上開查扣物係屬違禁物，爰依毒品危害防制條例第\n    18條第1 項前段（聲請書漏載，應予補充）、刑法第40條第\n    2 項、第38條第1 項第1 款、第2 項規定聲請宣告沒收銷燬\n    等語。\n二、按違禁物，不問屬於犯罪行為人與否，沒收之，且得單獨宣\n    告沒收；又查獲之第一、二級毒品，不問屬於犯人與否，均\n    沒收銷燬之，刑法第38條第1項第1款、第2項、第40條第2項\n    ，毒品危害防制條例第18條第1項前段分別定有明文。\n三、經查，扣案疑似第二級毒品大麻煙草2 包，經送法務部調查\n    局鑑定結果，均檢出含有大麻成分( 合計驗餘淨重20.56 公\n    克) ，有法務部調查局100 年6 月7 日調科壹字第10023013\n    000 號濫用藥物實驗室鑑定書在卷可憑。扣案之大麻係毒品\n    危害防制條例第2 條第2 項第2 款規定之第二級毒品，依同\n    條例之規定，不得製造、販賣、運輸、轉讓、持有，屬違禁\n    物。依首揭說明，聲請人聲請單獨宣告沒收並銷燬上開第二\n    級毒品，核無不合，應予准許( 其外包裝袋，與附著其上之\n    毒品無從析離，應視同毒品為違禁物併予沒收銷燬) 。至於\n    鑑驗耗損之第二級毒品大麻，既已滅失，爰不另行諭知沒收\n    銷燬，附此敘明。至本件檢察官雖僅引刑法第40條第2 項、\n    第38條第1 項第1 款、第2 項作為聲請依據，而漏引毒品危\n    害防制條例第18條第1 項前段，惟因該等物品本即屬應宣告\n    沒收且得單獨聲請法院宣告沒收之物，法院仍得裁定宣告沒\n    收銷燬之，並自行援引適當之規定，不受檢察官聲請書所載\n    法條之限制（臺灣高等法院暨所屬法院98年法律座談會刑事\n    類提案第39號研討結果參照），附此敘明。\n三、另扣案之郵件外包裝1件，已由臺灣臺中地方法院檢察署檢\n    察官於100年9月14日以中檢輝履字第118848號為廢棄處分命\n    令在案，爰不宣告沒收，併此敘明。\n四、爰依毒品危害防制條例第18條第1項前段、刑法第40條第2項\n    ，裁定如主文。"
  },
  "search": "臺灣臺中地方法院刑事裁定100年度聲字第3779號聲請人臺灣臺中地方法院檢察署檢察官被告PEACEWU.上開聲請人聲請單獨宣告沒收違禁物案件（100年度聲沒字第199號），本院裁定如下：主文扣案之第二級毒品大麻貳包(合計驗餘淨重貳拾點伍陸公克，含空包裝袋貳只)沒收銷燬之。理由一、本件聲請意旨略以：財政部臺北關稅局於民國(下同)99年3月11日查獲一起來自荷蘭郵件。該郵件收件人為：PEACEWU，收件地址為臺中市○區○○路300號，內含疑似大麻煙草2包(合計淨重20.60公克，驗餘淨重20.56公克，空包裝總重3.58公克)，經將內容物送鑑結果，確含第二級毒品大麻成分，有法務部調查局濫用藥物實驗室鑑定書1份在卷可按，是上開查扣物係屬違禁物，爰依毒品危害防制條例第18條第1項前段（聲請書漏載，應予補充）、刑法第40條第2項、第38條第1項第1款、第2項規定聲請宣告沒收銷燬等語。二、按違禁物，不問屬於犯罪行為人與否，沒收之，且得單獨宣告沒收；又查獲之第一、二級毒品，不問屬於犯人與否，均沒收銷燬之，刑法第38條第1項第1款、第2項、第40條第2項，毒品危害防制條例第18條第1項前段分別定有明文。三、經查，扣案疑似第二級毒品大麻煙草2包，經送法務部調查局鑑定結果，均檢出含有大麻成分(合計驗餘淨重20.56公克)，有法務部調查局100年6月7日調科壹字第10023013000號濫用藥物實驗室鑑定書在卷可憑。扣案之大麻係毒品危害防制條例第2條第2項第2款規定之第二級毒品，依同條例之規定，不得製造、販賣、運輸、轉讓、持有，屬違禁物。依首揭說明，聲請人聲請單獨宣告沒收並銷燬上開第二級毒品，核無不合，應予准許(其外包裝袋，與附著其上之毒品無從析離，應視同毒品為違禁物併予沒收銷燬)。至於鑑驗耗損之第二級毒品大麻，既已滅失，爰不另行諭知沒收銷燬，附此敘明。至本件檢察官雖僅引刑法第40條第2項、第38條第1項第1款、第2項作為聲請依據，而漏引毒品危害防制條例第18條第1項前段，惟因該等物品本即屬應宣告沒收且得單獨聲請法院宣告沒收之物，法院仍得裁定宣告沒收銷燬之，並自行援引適當之規定，不受檢察官聲請書所載法條之限制（臺灣高等法院暨所屬法院98年法律座談會刑事類提案第39號研討結果參照），附此敘明。三、另扣案之郵件外包裝1件，已由臺灣臺中地方法院檢察署檢察官於100年9月14日以中檢輝履字第118848號為廢棄處分命令在案，爰不宣告沒收，併此敘明。四、爰依毒品危害防制條例第18條第1項前段、刑法第40條第2項，裁定如主文。中華民國100年10月31日刑事第六庭法官李立傑上正本証明與原本無異。如不服本裁定應於送達後五日內向本院提出抗告狀。書記官陳怡臻中華民國100年10月31日",
  "characters": {
    "judges": [
      "李立傑"
    ],
    "prosecutors": [

    ],
    "lawyers": [

    ],
    "clerks": [
      "陳怡臻"
    ],
    "plaintiffs": [

    ],
    "defendants": [
      "PEACE WU  ."
    ],
    "prosecutor_office": [
      "臺灣臺中地方法院檢察署檢察官"
    ],
    "creditors": [

    ],
    "debtors": [

    ],
    "judicial_associate_officer": [

    ]
  },
  "adjudged_at": "2011-10-31",
  "created_at": "2016-02-14 08:26:05",
  "updated_at": "2016-02-14 08:26:05"
}