{
  "identify": "TYD-100-壢交簡-1966-20111031-1",
  "court": {
    "name": "臺灣桃園地方法院",
    "code": "TYD"
  },
  "division": {
    "name": "刑事",
    "code": "M"
  },
  "year": 100,
  "word": "壢交簡",
  "number": "1966",
  "jcheck": "1",
  "reason": "過失傷害",
  "content": "臺灣桃園地方法院刑事簡易判決     100年度壢交簡字第1966號\n    聲  請  人  臺灣桃園地方法院檢察署檢察官\n    被      告  王延招\n上列被告因過失傷害案件，經檢察官聲請以簡易判決處刑（100\n年度偵字第13086 號），本院判決如下：\n    主      文\n王延招犯過失傷害罪，處有期徒刑月，如易科罰金，以新臺幣\n壹仟元折算壹日。\n    事實及理由\n一、王延招於民國99年11月25日下午4 時17分許，駕駛車牌號碼\n    8288-UT 號自用小客貨車，自桃園縣平鎮市○○路41號前對\n    面車道路邊線外起駛，起步後車頭旋左迴轉，欲迴轉至對向\n    車道行駛，王延招本應注意汽車迴車前，應暫停並顯示左轉\n    燈光或手勢，看清有無來往車輛，始得迴轉，而依當時道路\n    型態為雙向二線車道、直路、柏油路面乾燥、無缺陷、無障\n    礙物、視距良好等情形，並無不能注意之情事，竟疏未注意\n    左後方來車，讓直駛行進中之車輛優先通行，即貿然迴轉，\n    適陳慶安騎乘車牌號碼L7K-650 號重型機車沿該路段同方向\n    （即龍德路往龍南路方向）自其左後方正常直行行進而來，\n    陳慶安發現王延招突然迴轉時已避煞不及，遂撞擊王延招駕\n    駛之車輛左後車門後，人車倒地，致陳慶安受有上顎骨骨折\n    、顏面撕裂傷、頭部外傷等傷害。王延招在有偵查犯罪權限\n    之人知悉犯罪人之前，向到場處理員警自首為肇事人表示願\n    接受裁判。案經告訴人陳慶安訴由桃園縣政府警察局平鎮分\n    局移送臺灣桃園地方法院檢察署檢察官偵查後聲請簡易判決\n    處刑。\n二、上開犯罪事實，業據被告王延招於警詢及偵查中坦白承認，\n    核與告訴人陳慶安之指訴情節相符，復有壢新醫院診斷證明\n    書2 張、道路交通事故現場圖、道路交通事故調查報告表(一)\n    (二)與現場照片14幀附卷可稽，足認被告自白與事實相符。按\n    汽車迴車前，應暫停並顯示左轉燈光或手勢，看清無來往車\n    輛，始得迴轉，道路交通安全規則第106 條第5 款訂有明文\n    。被告駕駛車輛自應注意上述道路交通安全規定，以確保行\n    車安全。且依當時道路型態為雙向二線車道、直路、柏油路\n    面乾燥、無缺陷、無障礙物、視距良好等情形，又無不能注\n    意之情形，竟應注意能注意而疏未注意即貿然迴轉，以致肇\n    事，被告顯有過失。又本件車禍經臺灣省桃園縣區車輛行車\n    事故鑑定委員會鑑定，鑑定結果亦認定被告駕駛自小客貨車\n    由路旁起駛左迴轉未看清來往車輛且未讓車道上直行行進中\n    之車輛先行為肇事原因，告訴人陳慶安無肇事因素，此有該\n    委員會之鑑定意見書1 份在卷為憑。又告訴人因本件車禍受\n    傷，與被告之過失行為間，具有相當因果關係，自不待言。\n    本件事證明確，被告犯行洵以認定，應依法論科。\n三、核被告所為，係犯刑法第284 條第1 項前段之過失傷害罪。\n    查被告於肇事後於警員到場處理時自承犯行，表示願接受裁\n    判，有其警訊筆錄記載暨自首情形紀錄表乙紙附卷可稽，應\n    依刑法第62條前段自首之規定減輕其刑。爰審酌被告過失之\n    程度極高，告訴人並未與有過失，暨告訴人所受傷勢甚重，\n    迄今尚未康癒，被告行為所生損害容屬非輕，雖被告犯後坦\n    承過失態度良好已受警惕，但未能與告訴人達成和解賠償（\n    雙方差距過大）獲取諒宥，兼衡被告之品行、智識程度及其\n    資力等一切情狀，量處如主文所示之刑，以資懲儆，併諭知\n    易科罰金之折算標準。\n四、據上論斷，應依刑事訴訟法第449 條第1 項前段、第3 項，\n    刑法第284 條第1 項前段、第62條前段、第41條第1 項前段\n    ，刑法施行法第1 條之1 第1 項、第2 項前段，逕以簡易判\n    決處刑如主文。\n五、如不服本判決，得於判決書送達之翌日起10日內，以書狀敘\n    述理由，向本院提出上訴。\n中    華    民    國   100    年    10    月    31    日\n                  中壢簡易庭    法  官  江德民\n以上正本證明與原本無異。\n如不服本判決，應於送達後10日內，向本院提出上訴狀（應附繕\n本）。\n                                書記官  黃子祝\n中    華    民    國  100     年    11    月    7     日\n附論罪科刑依據之法條：\n刑法第284 條（過失傷害罪）\n因過失傷害人者，處6 月以下有期徒刑、拘役或（新臺幣）5 百\n元（經提高為新臺幣1 萬5 千元）以下罰金，致重傷者，處1 年\n以下有期徒刑、拘役或（新臺幣）5 百元（經提高為新臺幣1 萬\n5 千元）以下罰金。",
  "structure": {
    "main": "王延招犯過失傷害罪，處有期徒刑月，如易科罰金，以新臺幣\n壹仟元折算壹日。",
    "fact": "一、王延招於民國99年11月25日下午4 時17分許，駕駛車牌號碼\n    8288-UT 號自用小客貨車，自桃園縣平鎮市○○路41號前對\n    面車道路邊線外起駛，起步後車頭旋左迴轉，欲迴轉至對向\n    車道行駛，王延招本應注意汽車迴車前，應暫停並顯示左轉\n    燈光或手勢，看清有無來往車輛，始得迴轉，而依當時道路\n    型態為雙向二線車道、直路、柏油路面乾燥、無缺陷、無障\n    礙物、視距良好等情形，並無不能注意之情事，竟疏未注意\n    左後方來車，讓直駛行進中之車輛優先通行，即貿然迴轉，\n    適陳慶安騎乘車牌號碼L7K-650 號重型機車沿該路段同方向\n    （即龍德路往龍南路方向）自其左後方正常直行行進而來，\n    陳慶安發現王延招突然迴轉時已避煞不及，遂撞擊王延招駕\n    駛之車輛左後車門後，人車倒地，致陳慶安受有上顎骨骨折\n    、顏面撕裂傷、頭部外傷等傷害。王延招在有偵查犯罪權限\n    之人知悉犯罪人之前，向到場處理員警自首為肇事人表示願\n    接受裁判。案經告訴人陳慶安訴由桃園縣政府警察局平鎮分\n    局移送臺灣桃園地方法院檢察署檢察官偵查後聲請簡易判決\n    處刑。\n二、上開犯罪事實，業據被告王延招於警詢及偵查中坦白承認，\n    核與告訴人陳慶安之指訴情節相符，復有壢新醫院診斷證明\n    書2 張、道路交通事故現場圖、道路交通事故調查報告表(一)\n    (二)與現場照片14幀附卷可稽，足認被告自白與事實相符。按\n    汽車迴車前，應暫停並顯示左轉燈光或手勢，看清無來往車\n    輛，始得迴轉，道路交通安全規則第106 條第5 款訂有明文\n    。被告駕駛車輛自應注意上述道路交通安全規定，以確保行\n    車安全。且依當時道路型態為雙向二線車道、直路、柏油路\n    面乾燥、無缺陷、無障礙物、視距良好等情形，又無不能注\n    意之情形，竟應注意能注意而疏未注意即貿然迴轉，以致肇\n    事，被告顯有過失。又本件車禍經臺灣省桃園縣區車輛行車\n    事故鑑定委員會鑑定，鑑定結果亦認定被告駕駛自小客貨車\n    由路旁起駛左迴轉未看清來往車輛且未讓車道上直行行進中\n    之車輛先行為肇事原因，告訴人陳慶安無肇事因素，此有該\n    委員會之鑑定意見書1 份在卷為憑。又告訴人因本件車禍受\n    傷，與被告之過失行為間，具有相當因果關係，自不待言。\n    本件事證明確，被告犯行洵以認定，應依法論科。\n三、核被告所為，係犯刑法第284 條第1 項前段之過失傷害罪。\n    查被告於肇事後於警員到場處理時自承犯行，表示願接受裁\n    判，有其警訊筆錄記載暨自首情形紀錄表乙紙附卷可稽，應\n    依刑法第62條前段自首之規定減輕其刑。爰審酌被告過失之\n    程度極高，告訴人並未與有過失，暨告訴人所受傷勢甚重，\n    迄今尚未康癒，被告行為所生損害容屬非輕，雖被告犯後坦\n    承過失態度良好已受警惕，但未能與告訴人達成和解賠償（\n    雙方差距過大）獲取諒宥，兼衡被告之品行、智識程度及其\n    資力等一切情狀，量處如主文所示之刑，以資懲儆，併諭知\n    易科罰金之折算標準。\n四、據上論斷，應依刑事訴訟法第449 條第1 項前段、第3 項，\n    刑法第284 條第1 項前段、第62條前段、第41條第1 項前段\n    ，刑法施行法第1 條之1 第1 項、第2 項前段，逕以簡易判\n    決處刑如主文。\n五、如不服本判決，得於判決書送達之翌日起10日內，以書狀敘\n    述理由，向本院提出上訴。",
    "reason": "一、王延招於民國99年11月25日下午4 時17分許，駕駛車牌號碼\n    8288-UT 號自用小客貨車，自桃園縣平鎮市○○路41號前對\n    面車道路邊線外起駛，起步後車頭旋左迴轉，欲迴轉至對向\n    車道行駛，王延招本應注意汽車迴車前，應暫停並顯示左轉\n    燈光或手勢，看清有無來往車輛，始得迴轉，而依當時道路\n    型態為雙向二線車道、直路、柏油路面乾燥、無缺陷、無障\n    礙物、視距良好等情形，並無不能注意之情事，竟疏未注意\n    左後方來車，讓直駛行進中之車輛優先通行，即貿然迴轉，\n    適陳慶安騎乘車牌號碼L7K-650 號重型機車沿該路段同方向\n    （即龍德路往龍南路方向）自其左後方正常直行行進而來，\n    陳慶安發現王延招突然迴轉時已避煞不及，遂撞擊王延招駕\n    駛之車輛左後車門後，人車倒地，致陳慶安受有上顎骨骨折\n    、顏面撕裂傷、頭部外傷等傷害。王延招在有偵查犯罪權限\n    之人知悉犯罪人之前，向到場處理員警自首為肇事人表示願\n    接受裁判。案經告訴人陳慶安訴由桃園縣政府警察局平鎮分\n    局移送臺灣桃園地方法院檢察署檢察官偵查後聲請簡易判決\n    處刑。\n二、上開犯罪事實，業據被告王延招於警詢及偵查中坦白承認，\n    核與告訴人陳慶安之指訴情節相符，復有壢新醫院診斷證明\n    書2 張、道路交通事故現場圖、道路交通事故調查報告表(一)\n    (二)與現場照片14幀附卷可稽，足認被告自白與事實相符。按\n    汽車迴車前，應暫停並顯示左轉燈光或手勢，看清無來往車\n    輛，始得迴轉，道路交通安全規則第106 條第5 款訂有明文\n    。被告駕駛車輛自應注意上述道路交通安全規定，以確保行\n    車安全。且依當時道路型態為雙向二線車道、直路、柏油路\n    面乾燥、無缺陷、無障礙物、視距良好等情形，又無不能注\n    意之情形，竟應注意能注意而疏未注意即貿然迴轉，以致肇\n    事，被告顯有過失。又本件車禍經臺灣省桃園縣區車輛行車\n    事故鑑定委員會鑑定，鑑定結果亦認定被告駕駛自小客貨車\n    由路旁起駛左迴轉未看清來往車輛且未讓車道上直行行進中\n    之車輛先行為肇事原因，告訴人陳慶安無肇事因素，此有該\n    委員會之鑑定意見書1 份在卷為憑。又告訴人因本件車禍受\n    傷，與被告之過失行為間，具有相當因果關係，自不待言。\n    本件事證明確，被告犯行洵以認定，應依法論科。\n三、核被告所為，係犯刑法第284 條第1 項前段之過失傷害罪。\n    查被告於肇事後於警員到場處理時自承犯行，表示願接受裁\n    判，有其警訊筆錄記載暨自首情形紀錄表乙紙附卷可稽，應\n    依刑法第62條前段自首之規定減輕其刑。爰審酌被告過失之\n    程度極高，告訴人並未與有過失，暨告訴人所受傷勢甚重，\n    迄今尚未康癒，被告行為所生損害容屬非輕，雖被告犯後坦\n    承過失態度良好已受警惕，但未能與告訴人達成和解賠償（\n    雙方差距過大）獲取諒宥，兼衡被告之品行、智識程度及其\n    資力等一切情狀，量處如主文所示之刑，以資懲儆，併諭知\n    易科罰金之折算標準。\n四、據上論斷，應依刑事訴訟法第449 條第1 項前段、第3 項，\n    刑法第284 條第1 項前段、第62條前段、第41條第1 項前段\n    ，刑法施行法第1 條之1 第1 項、第2 項前段，逕以簡易判\n    決處刑如主文。\n五、如不服本判決，得於判決書送達之翌日起10日內，以書狀敘\n    述理由，向本院提出上訴。"
  },
  "search": "臺灣桃園地方法院刑事簡易判決100年度壢交簡字第1966號聲請人臺灣桃園地方法院檢察署檢察官被告王延招上列被告因過失傷害案件，經檢察官聲請以簡易判決處刑（100年度偵字第13086號），本院判決如下：主文王延招犯過失傷害罪，處有期徒刑月，如易科罰金，以新臺幣壹仟元折算壹日。事實及理由一、王延招於民國99年11月25日下午4時17分許，駕駛車牌號碼8288-UT號自用小客貨車，自桃園縣平鎮市○○路41號前對面車道路邊線外起駛，起步後車頭旋左迴轉，欲迴轉至對向車道行駛，王延招本應注意汽車迴車前，應暫停並顯示左轉燈光或手勢，看清有無來往車輛，始得迴轉，而依當時道路型態為雙向二線車道、直路、柏油路面乾燥、無缺陷、無障礙物、視距良好等情形，並無不能注意之情事，竟疏未注意左後方來車，讓直駛行進中之車輛優先通行，即貿然迴轉，適陳慶安騎乘車牌號碼L7K-650號重型機車沿該路段同方向（即龍德路往龍南路方向）自其左後方正常直行行進而來，陳慶安發現王延招突然迴轉時已避煞不及，遂撞擊王延招駕駛之車輛左後車門後，人車倒地，致陳慶安受有上顎骨骨折、顏面撕裂傷、頭部外傷等傷害。王延招在有偵查犯罪權限之人知悉犯罪人之前，向到場處理員警自首為肇事人表示願接受裁判。案經告訴人陳慶安訴由桃園縣政府警察局平鎮分局移送臺灣桃園地方法院檢察署檢察官偵查後聲請簡易判決處刑。二、上開犯罪事實，業據被告王延招於警詢及偵查中坦白承認，核與告訴人陳慶安之指訴情節相符，復有壢新醫院診斷證明書2張、道路交通事故現場圖、道路交通事故調查報告表(一)(二)與現場照片14幀附卷可稽，足認被告自白與事實相符。按汽車迴車前，應暫停並顯示左轉燈光或手勢，看清無來往車輛，始得迴轉，道路交通安全規則第106條第5款訂有明文。被告駕駛車輛自應注意上述道路交通安全規定，以確保行車安全。且依當時道路型態為雙向二線車道、直路、柏油路面乾燥、無缺陷、無障礙物、視距良好等情形，又無不能注意之情形，竟應注意能注意而疏未注意即貿然迴轉，以致肇事，被告顯有過失。又本件車禍經臺灣省桃園縣區車輛行車事故鑑定委員會鑑定，鑑定結果亦認定被告駕駛自小客貨車由路旁起駛左迴轉未看清來往車輛且未讓車道上直行行進中之車輛先行為肇事原因，告訴人陳慶安無肇事因素，此有該委員會之鑑定意見書1份在卷為憑。又告訴人因本件車禍受傷，與被告之過失行為間，具有相當因果關係，自不待言。本件事證明確，被告犯行洵以認定，應依法論科。三、核被告所為，係犯刑法第284條第1項前段之過失傷害罪。查被告於肇事後於警員到場處理時自承犯行，表示願接受裁判，有其警訊筆錄記載暨自首情形紀錄表乙紙附卷可稽，應依刑法第62條前段自首之規定減輕其刑。爰審酌被告過失之程度極高，告訴人並未與有過失，暨告訴人所受傷勢甚重，迄今尚未康癒，被告行為所生損害容屬非輕，雖被告犯後坦承過失態度良好已受警惕，但未能與告訴人達成和解賠償（雙方差距過大）獲取諒宥，兼衡被告之品行、智識程度及其資力等一切情狀，量處如主文所示之刑，以資懲儆，併諭知易科罰金之折算標準。四、據上論斷，應依刑事訴訟法第449條第1項前段、第3項，刑法第284條第1項前段、第62條前段、第41條第1項前段，刑法施行法第1條之1第1項、第2項前段，逕以簡易判決處刑如主文。五、如不服本判決，得於判決書送達之翌日起10日內，以書狀敘述理由，向本院提出上訴。中華民國100年10月31日中壢簡易庭法官江德民以上正本證明與原本無異。如不服本判決，應於送達後10日內，向本院提出上訴狀（應附繕本）。書記官黃子祝中華民國100年11月7日附論罪科刑依據之法條：刑法第284條（過失傷害罪）因過失傷害人者，處6月以下有期徒刑、拘役或（新臺幣）5百元（經提高為新臺幣1萬5千元）以下罰金，致重傷者，處1年以下有期徒刑、拘役或（新臺幣）5百元（經提高為新臺幣1萬5千元）以下罰金。",
  "characters": {
    "judges": [
      "江德民"
    ],
    "prosecutors": [

    ],
    "lawyers": [

    ],
    "clerks": [
      "黃子祝"
    ],
    "plaintiffs": [

    ],
    "defendants": [
      "王延招"
    ],
    "prosecutor_office": [
      "臺灣桃園地方法院檢察署檢察官"
    ],
    "creditors": [

    ],
    "debtors": [

    ],
    "judicial_associate_officer": [

    ]
  },
  "adjudged_at": "2011-10-31",
  "created_at": "2016-02-14 08:28:12",
  "updated_at": "2016-02-14 08:28:12"
}