{
  "identify": "TYD-100-訴-1171-20111031-1",
  "court": {
    "name": "臺灣桃園地方法院",
    "code": "TYD"
  },
  "division": {
    "name": "民事",
    "code": "V"
  },
  "year": 100,
  "word": "訴",
  "number": "1171",
  "jcheck": "1",
  "reason": "履行契約",
  "content": "臺灣桃園地方法院民事判決             100年度訴字第1171號\n原      告  李奕興\n訴訟代理人  陳志律師\n            陳孟彥律師\n            黃佩琦律師\n被      告  李治維\n上列當事人間請求履行契約事件，本院於民國100 年10月27日言\n詞辯論終結，判決如下：\n    主      文\n被告應協同原告共同申報坐落於桃園縣桃園市○○段埔子小段第\n一三二三之二三及第一三二三之二四地號土地上之建物（門牌號\n碼為桃園縣桃園市○○路九八九號）之契稅後，再將上開房屋稅\n籍納稅義務人辦理變更為原告名義。\n訴訟費用由被告負擔。\n    事實及理由\n一、本件被告經合法通知，無正當理由未於言詞辯論期日到場，\n    核無民事訴訟法第386 條所列各款情形，爰依原告之聲請，\n    由其一造辯論而為判決。\n二、按訴狀送達後，原告不得將原訴變更或追加他訴。但請求之\n    基礎事實同一者，不在此限。民事訴訟法第255 條第1 項但\n    書第2 款定有明文。次按所謂請求之基礎事實同一，係指變\n    更或追加之訴與原訴之主要爭點有其共同性，各請求利益之\n    主張在社會生活上可認為同一或關連，而就原請求之訴訟及\n    證據資料，於審理繼續進行在相當程度範圍內具有同一性或\n    一體性，得期待於後請求之審理予以利用，俾先後兩請求在\n    同一程序得加以解決，避免重複審理，進而為統一解決紛爭\n    者，即屬之，此有最高法院95年度台上字第1573號判決可資\n    參照。本件原告起訴聲明原為被告應將坐落於桃園縣桃園市\n    ○○段埔子小段第1323之23及第1323之24地號土地（下稱系\n    爭土地）上之建物（門牌號碼為桃園縣桃園市○○路989 號\n    ，下稱系爭房屋）之稅籍，辦理變更為被告名義。嗣於本院\n    審理中，將上開聲明變更為被告應協同原告共同申報坐落於\n    系爭土地上系爭房屋之契稅後，再將系爭房屋稅籍納稅義務\n    人辦理變更為原告名義。經核原訴與追加之訴間有相當之關\n    連性，且原訴之證據資料得於追加之訴審理時予以利用，揆\n    諸前開規定，可認原訴與追加之訴之請求基礎事實係屬同一\n    ，原告所為訴之追加，於法有據，應予准許。\n三、本件原告主張：\n  (一)兩造於民國93年12月18日簽訂土地租賃契約書（下稱系爭租\n    賃契約），約明原告將其所有坐落於桃園縣桃園市○○段埔\n    子小段第1323之23及第1323之24地號2 筆土地（下稱系爭土\n    地），租予被告搭建鐵皮屋，被告則應依約支付原告每月新\n    臺幣12,000元之租金，租賃期間自94年1 月1 日至99年12月\n    31日止，並在系爭土地上興建鐵皮屋（門牌號碼為桃園縣桃\n    園市○○路989 號，下稱系爭房屋）作為鋼鐵工廠之用。依\n    系爭租賃契約附註條款約定：「乙方（即被告）於承租處搭\n    建鐵皮屋，租約期滿後建物歸甲方（即原告）所有。」另按\n    房屋稅條例第4 條第1 項規定，「房屋稅向房屋所有人徵收\n    之。」系爭房屋係屬未辦理保存登記之建物，原告本於系爭\n    租賃契約附註條款，於租賃期限屆至後取得系爭房屋之事實\n    上處分權，而稅籍變更雖不生法律上產權變動之效果，然因\n    系爭房屋無法為所有權移轉登記，原告僅得為事實上處分權\n    人，故系爭房屋之房屋稅應向原告徵收較為正確，則稅籍登\n    記應得作為其事實上處分權某程度之表徵，被告基於系爭租\n    賃契約附註條款之法律關係，自有配合將系爭房屋納稅義務\n    人變更為被告之義務。\n  (二)爰依系爭租賃契約附註條之法律關係，求為判決並聲明：被\n    告應將坐落於系爭土地上之系爭房屋之稅籍，辦理變更為被\n    告名義。\n四、被告經合法通知，未於言詞辯論期日到庭辯論，亦未提出任\n    何準備書狀為何聲明或陳述。\n五、經查，原告主張之前揭事實，業據其提出系爭租賃契約1件\n    為證（參見本院100 年度桃簡字第711 號卷第9 至11頁），\n    核與其所述情節相符，而被告已於相當時期受合法之通知，\n    於言辯論期日不到場，亦未提出準備書狀爭執，是原告主張\n    之前揭事實，自堪信為真實。\n六、從而，原告依系爭租賃契約附註條之法律關係，請求被告將\n    坐落於系爭土地上之系爭房屋之稅籍，辦理變更為被告名義\n    ，為有理由，應予准許。\n七、訴訟費用負擔之依據：民事訴訟法第78條。\n中    華    民    國   100    年    10    月    31    日\n                  民事第一庭    法  官  林哲賢\n以上正本證明與原本無異\n如對本判決上訴，須於判決送達後 20 日內向本院提出上訴狀。\n如委任律師提起上訴者，應一併繳納上訴審裁判費。\n中    華    民    國   100    年    10    月    31    日\n                                書記官  陳佳彬",
  "structure": {
    "main": "被告應協同原告共同申報坐落於桃園縣桃園市○○段埔子小段第\n一三二三之二三及第一三二三之二四地號土地上之建物（門牌號\n碼為桃園縣桃園市○○路九八九號）之契稅後，再將上開房屋稅\n籍納稅義務人辦理變更為原告名義。\n訴訟費用由被告負擔。",
    "fact": "一、本件被告經合法通知，無正當理由未於言詞辯論期日到場，\n    核無民事訴訟法第386 條所列各款情形，爰依原告之聲請，\n    由其一造辯論而為判決。\n二、按訴狀送達後，原告不得將原訴變更或追加他訴。但請求之\n    基礎事實同一者，不在此限。民事訴訟法第255 條第1 項但\n    書第2 款定有明文。次按所謂請求之基礎事實同一，係指變\n    更或追加之訴與原訴之主要爭點有其共同性，各請求利益之\n    主張在社會生活上可認為同一或關連，而就原請求之訴訟及\n    證據資料，於審理繼續進行在相當程度範圍內具有同一性或\n    一體性，得期待於後請求之審理予以利用，俾先後兩請求在\n    同一程序得加以解決，避免重複審理，進而為統一解決紛爭\n    者，即屬之，此有最高法院95年度台上字第1573號判決可資\n    參照。本件原告起訴聲明原為被告應將坐落於桃園縣桃園市\n    ○○段埔子小段第1323之23及第1323之24地號土地（下稱系\n    爭土地）上之建物（門牌號碼為桃園縣桃園市○○路989 號\n    ，下稱系爭房屋）之稅籍，辦理變更為被告名義。嗣於本院\n    審理中，將上開聲明變更為被告應協同原告共同申報坐落於\n    系爭土地上系爭房屋之契稅後，再將系爭房屋稅籍納稅義務\n    人辦理變更為原告名義。經核原訴與追加之訴間有相當之關\n    連性，且原訴之證據資料得於追加之訴審理時予以利用，揆\n    諸前開規定，可認原訴與追加之訴之請求基礎事實係屬同一\n    ，原告所為訴之追加，於法有據，應予准許。\n三、本件原告主張：\n  (一)兩造於民國93年12月18日簽訂土地租賃契約書（下稱系爭租\n    賃契約），約明原告將其所有坐落於桃園縣桃園市○○段埔\n    子小段第1323之23及第1323之24地號2 筆土地（下稱系爭土\n    地），租予被告搭建鐵皮屋，被告則應依約支付原告每月新\n    臺幣12,000元之租金，租賃期間自94年1 月1 日至99年12月\n    31日止，並在系爭土地上興建鐵皮屋（門牌號碼為桃園縣桃\n    園市○○路989 號，下稱系爭房屋）作為鋼鐵工廠之用。依\n    系爭租賃契約附註條款約定：「乙方（即被告）於承租處搭\n    建鐵皮屋，租約期滿後建物歸甲方（即原告）所有。」另按\n    房屋稅條例第4 條第1 項規定，「房屋稅向房屋所有人徵收\n    之。」系爭房屋係屬未辦理保存登記之建物，原告本於系爭\n    租賃契約附註條款，於租賃期限屆至後取得系爭房屋之事實\n    上處分權，而稅籍變更雖不生法律上產權變動之效果，然因\n    系爭房屋無法為所有權移轉登記，原告僅得為事實上處分權\n    人，故系爭房屋之房屋稅應向原告徵收較為正確，則稅籍登\n    記應得作為其事實上處分權某程度之表徵，被告基於系爭租\n    賃契約附註條款之法律關係，自有配合將系爭房屋納稅義務\n    人變更為被告之義務。\n  (二)爰依系爭租賃契約附註條之法律關係，求為判決並聲明：被\n    告應將坐落於系爭土地上之系爭房屋之稅籍，辦理變更為被\n    告名義。\n四、被告經合法通知，未於言詞辯論期日到庭辯論，亦未提出任\n    何準備書狀為何聲明或陳述。\n五、經查，原告主張之前揭事實，業據其提出系爭租賃契約1件\n    為證（參見本院100 年度桃簡字第711 號卷第9 至11頁），\n    核與其所述情節相符，而被告已於相當時期受合法之通知，\n    於言辯論期日不到場，亦未提出準備書狀爭執，是原告主張\n    之前揭事實，自堪信為真實。\n六、從而，原告依系爭租賃契約附註條之法律關係，請求被告將\n    坐落於系爭土地上之系爭房屋之稅籍，辦理變更為被告名義\n    ，為有理由，應予准許。\n七、訴訟費用負擔之依據：民事訴訟法第78條。",
    "reason": "一、本件被告經合法通知，無正當理由未於言詞辯論期日到場，\n    核無民事訴訟法第386 條所列各款情形，爰依原告之聲請，\n    由其一造辯論而為判決。\n二、按訴狀送達後，原告不得將原訴變更或追加他訴。但請求之\n    基礎事實同一者，不在此限。民事訴訟法第255 條第1 項但\n    書第2 款定有明文。次按所謂請求之基礎事實同一，係指變\n    更或追加之訴與原訴之主要爭點有其共同性，各請求利益之\n    主張在社會生活上可認為同一或關連，而就原請求之訴訟及\n    證據資料，於審理繼續進行在相當程度範圍內具有同一性或\n    一體性，得期待於後請求之審理予以利用，俾先後兩請求在\n    同一程序得加以解決，避免重複審理，進而為統一解決紛爭\n    者，即屬之，此有最高法院95年度台上字第1573號判決可資\n    參照。本件原告起訴聲明原為被告應將坐落於桃園縣桃園市\n    ○○段埔子小段第1323之23及第1323之24地號土地（下稱系\n    爭土地）上之建物（門牌號碼為桃園縣桃園市○○路989 號\n    ，下稱系爭房屋）之稅籍，辦理變更為被告名義。嗣於本院\n    審理中，將上開聲明變更為被告應協同原告共同申報坐落於\n    系爭土地上系爭房屋之契稅後，再將系爭房屋稅籍納稅義務\n    人辦理變更為原告名義。經核原訴與追加之訴間有相當之關\n    連性，且原訴之證據資料得於追加之訴審理時予以利用，揆\n    諸前開規定，可認原訴與追加之訴之請求基礎事實係屬同一\n    ，原告所為訴之追加，於法有據，應予准許。\n三、本件原告主張：\n  (一)兩造於民國93年12月18日簽訂土地租賃契約書（下稱系爭租\n    賃契約），約明原告將其所有坐落於桃園縣桃園市○○段埔\n    子小段第1323之23及第1323之24地號2 筆土地（下稱系爭土\n    地），租予被告搭建鐵皮屋，被告則應依約支付原告每月新\n    臺幣12,000元之租金，租賃期間自94年1 月1 日至99年12月\n    31日止，並在系爭土地上興建鐵皮屋（門牌號碼為桃園縣桃\n    園市○○路989 號，下稱系爭房屋）作為鋼鐵工廠之用。依\n    系爭租賃契約附註條款約定：「乙方（即被告）於承租處搭\n    建鐵皮屋，租約期滿後建物歸甲方（即原告）所有。」另按\n    房屋稅條例第4 條第1 項規定，「房屋稅向房屋所有人徵收\n    之。」系爭房屋係屬未辦理保存登記之建物，原告本於系爭\n    租賃契約附註條款，於租賃期限屆至後取得系爭房屋之事實\n    上處分權，而稅籍變更雖不生法律上產權變動之效果，然因\n    系爭房屋無法為所有權移轉登記，原告僅得為事實上處分權\n    人，故系爭房屋之房屋稅應向原告徵收較為正確，則稅籍登\n    記應得作為其事實上處分權某程度之表徵，被告基於系爭租\n    賃契約附註條款之法律關係，自有配合將系爭房屋納稅義務\n    人變更為被告之義務。\n  (二)爰依系爭租賃契約附註條之法律關係，求為判決並聲明：被\n    告應將坐落於系爭土地上之系爭房屋之稅籍，辦理變更為被\n    告名義。\n四、被告經合法通知，未於言詞辯論期日到庭辯論，亦未提出任\n    何準備書狀為何聲明或陳述。\n五、經查，原告主張之前揭事實，業據其提出系爭租賃契約1件\n    為證（參見本院100 年度桃簡字第711 號卷第9 至11頁），\n    核與其所述情節相符，而被告已於相當時期受合法之通知，\n    於言辯論期日不到場，亦未提出準備書狀爭執，是原告主張\n    之前揭事實，自堪信為真實。\n六、從而，原告依系爭租賃契約附註條之法律關係，請求被告將\n    坐落於系爭土地上之系爭房屋之稅籍，辦理變更為被告名義\n    ，為有理由，應予准許。\n七、訴訟費用負擔之依據：民事訴訟法第78條。"
  },
  "search": "臺灣桃園地方法院民事判決100年度訴字第1171號原告李奕興訴訟代理人陳志律師陳孟彥律師黃佩琦律師被告李治維上列當事人間請求履行契約事件，本院於民國100年10月27日言詞辯論終結，判決如下：主文被告應協同原告共同申報坐落於桃園縣桃園市○○段埔子小段第一三二三之二三及第一三二三之二四地號土地上之建物（門牌號碼為桃園縣桃園市○○路九八九號）之契稅後，再將上開房屋稅籍納稅義務人辦理變更為原告名義。訴訟費用由被告負擔。事實及理由一、本件被告經合法通知，無正當理由未於言詞辯論期日到場，核無民事訴訟法第386條所列各款情形，爰依原告之聲請，由其一造辯論而為判決。二、按訴狀送達後，原告不得將原訴變更或追加他訴。但請求之基礎事實同一者，不在此限。民事訴訟法第255條第1項但書第2款定有明文。次按所謂請求之基礎事實同一，係指變更或追加之訴與原訴之主要爭點有其共同性，各請求利益之主張在社會生活上可認為同一或關連，而就原請求之訴訟及證據資料，於審理繼續進行在相當程度範圍內具有同一性或一體性，得期待於後請求之審理予以利用，俾先後兩請求在同一程序得加以解決，避免重複審理，進而為統一解決紛爭者，即屬之，此有最高法院95年度台上字第1573號判決可資參照。本件原告起訴聲明原為被告應將坐落於桃園縣桃園市○○段埔子小段第1323之23及第1323之24地號土地（下稱系爭土地）上之建物（門牌號碼為桃園縣桃園市○○路989號，下稱系爭房屋）之稅籍，辦理變更為被告名義。嗣於本院審理中，將上開聲明變更為被告應協同原告共同申報坐落於系爭土地上系爭房屋之契稅後，再將系爭房屋稅籍納稅義務人辦理變更為原告名義。經核原訴與追加之訴間有相當之關連性，且原訴之證據資料得於追加之訴審理時予以利用，揆諸前開規定，可認原訴與追加之訴之請求基礎事實係屬同一，原告所為訴之追加，於法有據，應予准許。三、本件原告主張：(一)兩造於民國93年12月18日簽訂土地租賃契約書（下稱系爭租賃契約），約明原告將其所有坐落於桃園縣桃園市○○段埔子小段第1323之23及第1323之24地號2筆土地（下稱系爭土地），租予被告搭建鐵皮屋，被告則應依約支付原告每月新臺幣12,000元之租金，租賃期間自94年1月1日至99年12月31日止，並在系爭土地上興建鐵皮屋（門牌號碼為桃園縣桃園市○○路989號，下稱系爭房屋）作為鋼鐵工廠之用。依系爭租賃契約附註條款約定：「乙方（即被告）於承租處搭建鐵皮屋，租約期滿後建物歸甲方（即原告）所有。」另按房屋稅條例第4條第1項規定，「房屋稅向房屋所有人徵收之。」系爭房屋係屬未辦理保存登記之建物，原告本於系爭租賃契約附註條款，於租賃期限屆至後取得系爭房屋之事實上處分權，而稅籍變更雖不生法律上產權變動之效果，然因系爭房屋無法為所有權移轉登記，原告僅得為事實上處分權人，故系爭房屋之房屋稅應向原告徵收較為正確，則稅籍登記應得作為其事實上處分權某程度之表徵，被告基於系爭租賃契約附註條款之法律關係，自有配合將系爭房屋納稅義務人變更為被告之義務。(二)爰依系爭租賃契約附註條之法律關係，求為判決並聲明：被告應將坐落於系爭土地上之系爭房屋之稅籍，辦理變更為被告名義。四、被告經合法通知，未於言詞辯論期日到庭辯論，亦未提出任何準備書狀為何聲明或陳述。五、經查，原告主張之前揭事實，業據其提出系爭租賃契約1件為證（參見本院100年度桃簡字第711號卷第9至11頁），核與其所述情節相符，而被告已於相當時期受合法之通知，於言辯論期日不到場，亦未提出準備書狀爭執，是原告主張之前揭事實，自堪信為真實。六、從而，原告依系爭租賃契約附註條之法律關係，請求被告將坐落於系爭土地上之系爭房屋之稅籍，辦理變更為被告名義，為有理由，應予准許。七、訴訟費用負擔之依據：民事訴訟法第78條。中華民國100年10月31日民事第一庭法官林哲賢以上正本證明與原本無異如對本判決上訴，須於判決送達後20日內向本院提出上訴狀。如委任律師提起上訴者，應一併繳納上訴審裁判費。中華民國100年10月31日書記官陳佳彬",
  "characters": {
    "judges": [
      "林哲賢"
    ],
    "prosecutors": [

    ],
    "lawyers": [
      "陳孟彥",
      "黃佩琦",
      "如委任"
    ],
    "clerks": [

    ],
    "plaintiffs": [
      "李奕興"
    ],
    "defendants": [
      "李治維"
    ],
    "prosecutor_office": [

    ],
    "creditors": [

    ],
    "debtors": [

    ],
    "judicial_associate_officer": [

    ]
  },
  "adjudged_at": "2011-10-31",
  "created_at": "2016-02-14 08:26:58",
  "updated_at": "2016-02-14 08:26:58"
}