{
  "identify": "TCD-100-中交簡-2586-20111213-1",
  "court": {
    "name": "臺灣臺中地方法院",
    "code": "TCD"
  },
  "division": {
    "name": "刑事",
    "code": "M"
  },
  "year": 100,
  "word": "中交簡",
  "number": "2586",
  "jcheck": "1",
  "reason": "公共危險",
  "content": "臺灣臺中地方法院刑事簡易判決     100年度中交簡字第2586號\n聲  請  人  臺灣臺中地方法院檢察署檢察官\n被      告  陳隆杰\n上列被告因公共危險案件，經檢察官聲請以簡易判決處刑（100\n年度速偵字第5123號），本院判決如下：\n    主  文\n陳隆杰服用酒類，不能安全駕駛動力交通工具而駕駛，累犯，處\n有期徒刑陸月，如易科罰金，以新臺幣壹仟元折算壹日。\n    犯罪事實及理由\n一、陳隆杰曾因公共危險案件，經本院判處有期徒刑3月確定，\n    於民國98年10月11日執行完畢，復於99年間，再因公共危險\n    案件，經本院判處有期徒刑5月確定，於99年9月14日執行完\n    畢。詎其仍不知悔改，復於100年11月9日下午5時許，在不\n    詳處所飲用酒類後，已達不能安全駕駛動力交通工具之程度\n    ，仍於同日下午6時30分許，騎乘車牌號碼TAH-351號輕型機\n    車上路。嗣於同日晚間7時25分許，行經臺中市○里區○○\n    街358號前時，因不勝酒力，不慎與曾麗泥所騎乘車牌號碼\n    OBT-976號重型機車發生碰撞（過失傷害部分未據告訴），\n    經警據報前往處理，發現陳隆杰酒氣甚濃，遂對其施以呼氣\n    酒精濃度測試，測得其呼氣酒精濃度達每公升1.27毫克，始\n    悉上情。案經臺中市政府警察局霧峰分局報請臺灣臺中地方\n    法院檢察署檢察官偵查後聲請以簡易判決處刑。\n二、上揭犯罪事實，業據被告陳隆杰於警詢時及偵查中坦承不諱\n    ，核與證人曾麗泥於警詢證述情節相符，並有酒精濃度測定\n    紀錄表、員警職務報告書、刑法第185條之3案件測試觀察紀\n    錄表、汽機車駕駛人酒後生理協調平衡檢測紀錄表、刑案現\n    場測繪圖、道路交通事故調查報告表（一）（二）、臺中市\n    政府警察局舉發違反道路交通管理事件通知單各1紙及照片9\n    張等附卷可稽。按刑法第185條之3之公共危險罪，係「抽象\n    危險犯」，不以發生具體危險為必要，參考德國、美國之認\n    定標準，對於呼氣酒精濃度已達每公升0.55MG/L或血液濃度\n    達0.11%以上，肇事率為一般正常人之10倍，認已達「不能\n    安全駕駛」之標準（法務部88年5月18日法88檢字第001669\n    號函參照）。本件被告呼氣酒精濃度測試值為每公升1.27毫\n    克，顯見其已不能安全駕駛動力交通工具，故本件事證明確\n    ，被告犯行堪以認定。\n三、查，被告行為後，刑法第185條之3業經修正，並經總統於\n    100年11月30日以華總一義字第10000263911號公布，於同年\n    12月2日施行。修正前法第185條之3規定：「服用毒品、麻\n    醉藥品、酒類或其他相類之物，不能安全駕駛動力交通工具\n    而駕駛者，處1年以下有期徒刑、拘役或科或併科15萬元以\n    下罰金。」修正後則規定為：「「服用毒品、麻醉藥品、酒\n    類或其他相類之物，不能安全駕駛動力交通工具而駕駛者，\n    處2年以下有期徒刑、拘役或科或併科20萬元以下罰金（第\n    一項）。因而致人於死者，處1年以上7年以下有期徒刑；致\n    重傷者，處6月以上5年以下有期徒刑（第二項）。」亦即提\n    高服用酒類駕車之刑責，比較新舊法之規定，自以舊法之規\n    定較有利於被告，依刑法第2條第1項：「行為後法律有變更\n    者，適用行為時之法律。但行為後之法律有利於行為人者，\n    適用最有利於行為人之法律。」本案自應適用被告行為時之\n    舊法。故核被告陳隆杰所為，係犯修正前刑法第185條之3之\n    公共危險罪。又被告曾因公共危險案件，經本院判處有期徒\n    刑5月確定，而於99年9月14日執行完畢，有臺灣高等法院被\n    告前案紀錄表附卷可按，其於5年內故意再犯本件有期徒刑\n    以上之罪，為累犯，應依刑法第47條第1項規定加重其刑。\n    爰審酌被告曾有多次公共危險（服用酒類駕車）紀錄，仍不\n    知警惕，犯後雖能坦承犯行，惟本件又肇致事故，及檢察官\n    具體求處有期徒刑6月等一切情狀，量處如主文所示之刑，\n    並諭知易科罰金之折算標準。\n四、爰依刑事訴訟法第449條第1項前段，刑法第2條第1項前段、\n    （修正前）第185條之3、第47條第1項、第41條第1項前段，\n    刑法施行法第1條之1第1項、第2項但書，逕以簡易判決處刑\n    如主文。\n中    華    民    國    100  年     12  月     13     日\n                  臺中簡易庭  法  官  郭瑞祥\n上正本證明與原本無異。\n如不服本判決，應於收受送達後10日內向本院提出上訴書狀（應\n附繕本）。\n                              書記官  黃雅青\n中    華    民    國    100  年     12  月     13     日\n修正前刑法第185條之3\n服用毒品、麻醉藥品、酒類或其他相類之物，不能安全駕駛動力\n交通工具而駕駛者，處1年以下有期徒刑、拘役或科或併科15萬\n元以下罰金。",
  "structure": {
    "main": "陳隆杰服用酒類，不能安全駕駛動力交通工具而駕駛，累犯，處\n有期徒刑陸月，如易科罰金，以新臺幣壹仟元折算壹日。",
    "fact": "一、陳隆杰曾因公共危險案件，經本院判處有期徒刑3月確定，\n    於民國98年10月11日執行完畢，復於99年間，再因公共危險\n    案件，經本院判處有期徒刑5月確定，於99年9月14日執行完\n    畢。詎其仍不知悔改，復於100年11月9日下午5時許，在不\n    詳處所飲用酒類後，已達不能安全駕駛動力交通工具之程度\n    ，仍於同日下午6時30分許，騎乘車牌號碼TAH-351號輕型機\n    車上路。嗣於同日晚間7時25分許，行經臺中市○里區○○\n    街358號前時，因不勝酒力，不慎與曾麗泥所騎乘車牌號碼\n    OBT-976號重型機車發生碰撞（過失傷害部分未據告訴），\n    經警據報前往處理，發現陳隆杰酒氣甚濃，遂對其施以呼氣\n    酒精濃度測試，測得其呼氣酒精濃度達每公升1.27毫克，始\n    悉上情。案經臺中市政府警察局霧峰分局報請臺灣臺中地方\n    法院檢察署檢察官偵查後聲請以簡易判決處刑。\n二、上揭犯罪事實，業據被告陳隆杰於警詢時及偵查中坦承不諱\n    ，核與證人曾麗泥於警詢證述情節相符，並有酒精濃度測定\n    紀錄表、員警職務報告書、刑法第185條之3案件測試觀察紀\n    錄表、汽機車駕駛人酒後生理協調平衡檢測紀錄表、刑案現\n    場測繪圖、道路交通事故調查報告表（一）（二）、臺中市\n    政府警察局舉發違反道路交通管理事件通知單各1紙及照片9\n    張等附卷可稽。按刑法第185條之3之公共危險罪，係「抽象\n    危險犯」，不以發生具體危險為必要，參考德國、美國之認\n    定標準，對於呼氣酒精濃度已達每公升0.55MG/L或血液濃度\n    達0.11%以上，肇事率為一般正常人之10倍，認已達「不能\n    安全駕駛」之標準（法務部88年5月18日法88檢字第001669\n    號函參照）。本件被告呼氣酒精濃度測試值為每公升1.27毫\n    克，顯見其已不能安全駕駛動力交通工具，故本件事證明確\n    ，被告犯行堪以認定。\n三、查，被告行為後，刑法第185條之3業經修正，並經總統於\n    100年11月30日以華總一義字第10000263911號公布，於同年\n    12月2日施行。修正前法第185條之3規定：「服用毒品、麻\n    醉藥品、酒類或其他相類之物，不能安全駕駛動力交通工具\n    而駕駛者，處1年以下有期徒刑、拘役或科或併科15萬元以\n    下罰金。」修正後則規定為：「「服用毒品、麻醉藥品、酒\n    類或其他相類之物，不能安全駕駛動力交通工具而駕駛者，\n    處2年以下有期徒刑、拘役或科或併科20萬元以下罰金（第\n    一項）。因而致人於死者，處1年以上7年以下有期徒刑；致\n    重傷者，處6月以上5年以下有期徒刑（第二項）。」亦即提\n    高服用酒類駕車之刑責，比較新舊法之規定，自以舊法之規\n    定較有利於被告，依刑法第2條第1項：「行為後法律有變更\n    者，適用行為時之法律。但行為後之法律有利於行為人者，\n    適用最有利於行為人之法律。」本案自應適用被告行為時之\n    舊法。故核被告陳隆杰所為，係犯修正前刑法第185條之3之\n    公共危險罪。又被告曾因公共危險案件，經本院判處有期徒\n    刑5月確定，而於99年9月14日執行完畢，有臺灣高等法院被\n    告前案紀錄表附卷可按，其於5年內故意再犯本件有期徒刑\n    以上之罪，為累犯，應依刑法第47條第1項規定加重其刑。\n    爰審酌被告曾有多次公共危險（服用酒類駕車）紀錄，仍不\n    知警惕，犯後雖能坦承犯行，惟本件又肇致事故，及檢察官\n    具體求處有期徒刑6月等一切情狀，量處如主文所示之刑，\n    並諭知易科罰金之折算標準。\n四、爰依刑事訴訟法第449條第1項前段，刑法第2條第1項前段、\n    （修正前）第185條之3、第47條第1項、第41條第1項前段，\n    刑法施行法第1條之1第1項、第2項但書，逕以簡易判決處刑\n    如主文。",
    "reason": "一、陳隆杰曾因公共危險案件，經本院判處有期徒刑3月確定，\n    於民國98年10月11日執行完畢，復於99年間，再因公共危險\n    案件，經本院判處有期徒刑5月確定，於99年9月14日執行完\n    畢。詎其仍不知悔改，復於100年11月9日下午5時許，在不\n    詳處所飲用酒類後，已達不能安全駕駛動力交通工具之程度\n    ，仍於同日下午6時30分許，騎乘車牌號碼TAH-351號輕型機\n    車上路。嗣於同日晚間7時25分許，行經臺中市○里區○○\n    街358號前時，因不勝酒力，不慎與曾麗泥所騎乘車牌號碼\n    OBT-976號重型機車發生碰撞（過失傷害部分未據告訴），\n    經警據報前往處理，發現陳隆杰酒氣甚濃，遂對其施以呼氣\n    酒精濃度測試，測得其呼氣酒精濃度達每公升1.27毫克，始\n    悉上情。案經臺中市政府警察局霧峰分局報請臺灣臺中地方\n    法院檢察署檢察官偵查後聲請以簡易判決處刑。\n二、上揭犯罪事實，業據被告陳隆杰於警詢時及偵查中坦承不諱\n    ，核與證人曾麗泥於警詢證述情節相符，並有酒精濃度測定\n    紀錄表、員警職務報告書、刑法第185條之3案件測試觀察紀\n    錄表、汽機車駕駛人酒後生理協調平衡檢測紀錄表、刑案現\n    場測繪圖、道路交通事故調查報告表（一）（二）、臺中市\n    政府警察局舉發違反道路交通管理事件通知單各1紙及照片9\n    張等附卷可稽。按刑法第185條之3之公共危險罪，係「抽象\n    危險犯」，不以發生具體危險為必要，參考德國、美國之認\n    定標準，對於呼氣酒精濃度已達每公升0.55MG/L或血液濃度\n    達0.11%以上，肇事率為一般正常人之10倍，認已達「不能\n    安全駕駛」之標準（法務部88年5月18日法88檢字第001669\n    號函參照）。本件被告呼氣酒精濃度測試值為每公升1.27毫\n    克，顯見其已不能安全駕駛動力交通工具，故本件事證明確\n    ，被告犯行堪以認定。\n三、查，被告行為後，刑法第185條之3業經修正，並經總統於\n    100年11月30日以華總一義字第10000263911號公布，於同年\n    12月2日施行。修正前法第185條之3規定：「服用毒品、麻\n    醉藥品、酒類或其他相類之物，不能安全駕駛動力交通工具\n    而駕駛者，處1年以下有期徒刑、拘役或科或併科15萬元以\n    下罰金。」修正後則規定為：「「服用毒品、麻醉藥品、酒\n    類或其他相類之物，不能安全駕駛動力交通工具而駕駛者，\n    處2年以下有期徒刑、拘役或科或併科20萬元以下罰金（第\n    一項）。因而致人於死者，處1年以上7年以下有期徒刑；致\n    重傷者，處6月以上5年以下有期徒刑（第二項）。」亦即提\n    高服用酒類駕車之刑責，比較新舊法之規定，自以舊法之規\n    定較有利於被告，依刑法第2條第1項：「行為後法律有變更\n    者，適用行為時之法律。但行為後之法律有利於行為人者，\n    適用最有利於行為人之法律。」本案自應適用被告行為時之\n    舊法。故核被告陳隆杰所為，係犯修正前刑法第185條之3之\n    公共危險罪。又被告曾因公共危險案件，經本院判處有期徒\n    刑5月確定，而於99年9月14日執行完畢，有臺灣高等法院被\n    告前案紀錄表附卷可按，其於5年內故意再犯本件有期徒刑\n    以上之罪，為累犯，應依刑法第47條第1項規定加重其刑。\n    爰審酌被告曾有多次公共危險（服用酒類駕車）紀錄，仍不\n    知警惕，犯後雖能坦承犯行，惟本件又肇致事故，及檢察官\n    具體求處有期徒刑6月等一切情狀，量處如主文所示之刑，\n    並諭知易科罰金之折算標準。\n四、爰依刑事訴訟法第449條第1項前段，刑法第2條第1項前段、\n    （修正前）第185條之3、第47條第1項、第41條第1項前段，\n    刑法施行法第1條之1第1項、第2項但書，逕以簡易判決處刑\n    如主文。"
  },
  "search": "臺灣臺中地方法院刑事簡易判決100年度中交簡字第2586號聲請人臺灣臺中地方法院檢察署檢察官被告陳隆杰上列被告因公共危險案件，經檢察官聲請以簡易判決處刑（100年度速偵字第5123號），本院判決如下：主文陳隆杰服用酒類，不能安全駕駛動力交通工具而駕駛，累犯，處有期徒刑陸月，如易科罰金，以新臺幣壹仟元折算壹日。犯罪事實及理由一、陳隆杰曾因公共危險案件，經本院判處有期徒刑3月確定，於民國98年10月11日執行完畢，復於99年間，再因公共危險案件，經本院判處有期徒刑5月確定，於99年9月14日執行完畢。詎其仍不知悔改，復於100年11月9日下午5時許，在不詳處所飲用酒類後，已達不能安全駕駛動力交通工具之程度，仍於同日下午6時30分許，騎乘車牌號碼TAH-351號輕型機車上路。嗣於同日晚間7時25分許，行經臺中市○里區○○街358號前時，因不勝酒力，不慎與曾麗泥所騎乘車牌號碼OBT-976號重型機車發生碰撞（過失傷害部分未據告訴），經警據報前往處理，發現陳隆杰酒氣甚濃，遂對其施以呼氣酒精濃度測試，測得其呼氣酒精濃度達每公升1.27毫克，始悉上情。案經臺中市政府警察局霧峰分局報請臺灣臺中地方法院檢察署檢察官偵查後聲請以簡易判決處刑。二、上揭犯罪事實，業據被告陳隆杰於警詢時及偵查中坦承不諱，核與證人曾麗泥於警詢證述情節相符，並有酒精濃度測定紀錄表、員警職務報告書、刑法第185條之3案件測試觀察紀錄表、汽機車駕駛人酒後生理協調平衡檢測紀錄表、刑案現場測繪圖、道路交通事故調查報告表（一）（二）、臺中市政府警察局舉發違反道路交通管理事件通知單各1紙及照片9張等附卷可稽。按刑法第185條之3之公共危險罪，係「抽象危險犯」，不以發生具體危險為必要，參考德國、美國之認定標準，對於呼氣酒精濃度已達每公升0.55MG/L或血液濃度達0.11%以上，肇事率為一般正常人之10倍，認已達「不能安全駕駛」之標準（法務部88年5月18日法88檢字第001669號函參照）。本件被告呼氣酒精濃度測試值為每公升1.27毫克，顯見其已不能安全駕駛動力交通工具，故本件事證明確，被告犯行堪以認定。三、查，被告行為後，刑法第185條之3業經修正，並經總統於100年11月30日以華總一義字第10000263911號公布，於同年12月2日施行。修正前法第185條之3規定：「服用毒品、麻醉藥品、酒類或其他相類之物，不能安全駕駛動力交通工具而駕駛者，處1年以下有期徒刑、拘役或科或併科15萬元以下罰金。」修正後則規定為：「「服用毒品、麻醉藥品、酒類或其他相類之物，不能安全駕駛動力交通工具而駕駛者，處2年以下有期徒刑、拘役或科或併科20萬元以下罰金（第一項）。因而致人於死者，處1年以上7年以下有期徒刑；致重傷者，處6月以上5年以下有期徒刑（第二項）。」亦即提高服用酒類駕車之刑責，比較新舊法之規定，自以舊法之規定較有利於被告，依刑法第2條第1項：「行為後法律有變更者，適用行為時之法律。但行為後之法律有利於行為人者，適用最有利於行為人之法律。」本案自應適用被告行為時之舊法。故核被告陳隆杰所為，係犯修正前刑法第185條之3之公共危險罪。又被告曾因公共危險案件，經本院判處有期徒刑5月確定，而於99年9月14日執行完畢，有臺灣高等法院被告前案紀錄表附卷可按，其於5年內故意再犯本件有期徒刑以上之罪，為累犯，應依刑法第47條第1項規定加重其刑。爰審酌被告曾有多次公共危險（服用酒類駕車）紀錄，仍不知警惕，犯後雖能坦承犯行，惟本件又肇致事故，及檢察官具體求處有期徒刑6月等一切情狀，量處如主文所示之刑，並諭知易科罰金之折算標準。四、爰依刑事訴訟法第449條第1項前段，刑法第2條第1項前段、（修正前）第185條之3、第47條第1項、第41條第1項前段，刑法施行法第1條之1第1項、第2項但書，逕以簡易判決處刑如主文。中華民國100年12月13日臺中簡易庭法官郭瑞祥上正本證明與原本無異。如不服本判決，應於收受送達後10日內向本院提出上訴書狀（應附繕本）。書記官黃雅青中華民國100年12月13日修正前刑法第185條之3服用毒品、麻醉藥品、酒類或其他相類之物，不能安全駕駛動力交通工具而駕駛者，處1年以下有期徒刑、拘役或科或併科15萬元以下罰金。",
  "characters": {
    "judges": [
      "郭瑞祥"
    ],
    "prosecutors": [

    ],
    "lawyers": [

    ],
    "clerks": [
      "黃雅青"
    ],
    "plaintiffs": [

    ],
    "defendants": [
      "陳隆杰"
    ],
    "prosecutor_office": [
      "臺灣臺中地方法院檢察署檢察官"
    ],
    "creditors": [

    ],
    "debtors": [

    ],
    "judicial_associate_officer": [

    ]
  },
  "adjudged_at": "2011-12-13",
  "created_at": "2016-02-13 09:43:44",
  "updated_at": "2016-02-13 09:43:44"
}