{
  "identify": "TPH-100-上訴-2954-20111214-1",
  "court": {
    "name": "臺灣高等法院",
    "code": "TPH"
  },
  "division": {
    "name": "刑事",
    "code": "M"
  },
  "year": 100,
  "word": "上訴",
  "number": "2954",
  "jcheck": "1",
  "reason": "毒品危害防制條例等",
  "content": "臺灣高等法院刑事裁定               100年度上訴字第2954號\n上  訴  人  臺灣新竹地方法院檢察署檢察官\n上  訴  人\n即  被  告  黃啟明\n選任辯護人  李志雄律師\n上列被告因毒品危害防制條例等上訴案件，本院裁定如下：\n    主  文\n黃啟明羈押期間，自民國101年1月6日起，延長貳月。\n    理  由\n一、上訴人即被告黃啟明前經本院認為犯毒品危害防制條例等罪\n    嫌疑重大，有刑事訴訟法第101條第1項第1、3款情形，非予\n    羈押，顯難進行審判，於民國100年10月6日執行羈押，至民\n    國101年1月5日止，3個月羈押期間即將屆滿。\n二、茲本院於100年12月8日訊問被告後，以前項原因依然存在，\n    認有繼續羈押之必要，應自民國101年1月6日起，延長羈押\n    貳月，爰依刑事訴訟法第108條第1項、第5項，裁定如主文\n    。\n中    華    民    國   100    年    12    月    14    日\n                  刑事第七庭審判長法  官  溫耀源\n                                  法  官  張傳栗\n                                  法  官  朱瑞娟\n以上正本證明與原本無異。\n如不服本裁定，應於收受送達後五日內向本院提出抗告狀。\n                                  書記官  郭家慧\n中    華    民    國   100    年    12    月    15    日",
  "structure": {
    "main": "黃啟明羈押期間，自民國101年1月6日起，延長貳月。",
    "reason": "一、上訴人即被告黃啟明前經本院認為犯毒品危害防制條例等罪\n    嫌疑重大，有刑事訴訟法第101條第1項第1、3款情形，非予\n    羈押，顯難進行審判，於民國100年10月6日執行羈押，至民\n    國101年1月5日止，3個月羈押期間即將屆滿。\n二、茲本院於100年12月8日訊問被告後，以前項原因依然存在，\n    認有繼續羈押之必要，應自民國101年1月6日起，延長羈押\n    貳月，爰依刑事訴訟法第108條第1項、第5項，裁定如主文\n    。"
  },
  "search": "臺灣高等法院刑事裁定100年度上訴字第2954號上訴人臺灣新竹地方法院檢察署檢察官上訴人即被告黃啟明選任辯護人李志雄律師上列被告因毒品危害防制條例等上訴案件，本院裁定如下：主文黃啟明羈押期間，自民國101年1月6日起，延長貳月。理由一、上訴人即被告黃啟明前經本院認為犯毒品危害防制條例等罪嫌疑重大，有刑事訴訟法第101條第1項第1、3款情形，非予羈押，顯難進行審判，於民國100年10月6日執行羈押，至民國101年1月5日止，3個月羈押期間即將屆滿。二、茲本院於100年12月8日訊問被告後，以前項原因依然存在，認有繼續羈押之必要，應自民國101年1月6日起，延長羈押貳月，爰依刑事訴訟法第108條第1項、第5項，裁定如主文。中華民國100年12月14日刑事第七庭審判長法官溫耀源法官張傳栗法官朱瑞娟以上正本證明與原本無異。如不服本裁定，應於收受送達後五日內向本院提出抗告狀。書記官郭家慧中華民國100年12月15日",
  "characters": {
    "judges": [
      "溫耀源",
      "張傳栗",
      "朱瑞娟"
    ],
    "prosecutors": [

    ],
    "lawyers": [
      "李志雄"
    ],
    "clerks": [
      "郭家慧"
    ],
    "plaintiffs": [

    ],
    "defendants": [
      "黃啟明"
    ],
    "prosecutor_office": [

    ],
    "creditors": [

    ],
    "debtors": [

    ],
    "judicial_associate_officer": [

    ]
  },
  "adjudged_at": "2011-12-14",
  "created_at": "2016-02-13 09:44:19",
  "updated_at": "2016-02-13 09:44:19"
}