{
  "identify": "KSH-99-上易-1200-20110224-1",
  "court": {
    "name": "臺灣高等法院",
    "code": "KSH"
  },
  "division": {
    "name": "刑事",
    "code": "M"
  },
  "year": 99,
  "word": "上易",
  "number": "1200",
  "jcheck": "1",
  "reason": "竊盜",
  "content": "臺灣高等法院高雄分院刑事判決        99年度上易字第1200號\n上  訴  人  臺灣屏東地方法院檢察署檢察官\n被      告  楊金峰\n            許進豐\n            洪天文\n            李培貴\n            林志雄\n共      同\n選任辯護人  蔡將葳律師\n上列上訴人因被告竊盜案件，不服臺灣屏東地方法院98年度易字\n第1229號中華民國98年9 月28日第一審判決（起訴案號：臺灣屏\n東地方法院檢察署98年度偵字第1201號），提起上訴，本院判決\n如下：\n    主  文\n上訴駁回。\n    理  由\n一、公訴意旨以：被告楊金峰受鼎信營造有限公司（下稱鼎信公\n    司）委託，施作由鼎信公司向屏東縣政府承包之「屏東加工\n    出口區○○道路（週邊設施改善工程）」（下稱系爭工程）\n    ，其中A1工區○○○○路段側邊背填土工程，C 工區係施作\n    擋土牆工程，被告許進豐、洪天文、李培貴、林志雄則均係\n    被告楊金峰雇用之員工。渠等均明知系爭工程C 工區即屏東\n    縣萬丹鄉萬丹堤防尾之砂石，係屬公有財產，未經申請許可\n    ，不得擅自盜採，竟仍共同意圖為自己不法之所有，基於結\n    夥三人以上竊盜之犯意聯絡，由被告楊金峰指示被告許進豐\n    等人，於民國98年2 月3 日14時許，假藉將系爭工程C 工區\n    砂石暫置A1工區名義，行回填A1工區之實，以減少A1工區購\n    置回填土之費用，共竊得290 立方公尺（長約58公尺、寬約\n    2.5 公尺、深約2 公尺）。嗣經屏東縣政府警察局及高屏溪\n    流域管理委員會人員執行巡邏勤務，查獲上情，並扣得砂石\n    60立方公尺、挖土機1 臺、營業用大貨車2 臺。因認被告楊\n    金峰、許進豐、洪天文、李培貴、林志雄均涉犯刑法第321\n    條第1 項第4 款結夥三人以上而竊盜之罪嫌。\n二、公訴人認被告楊金峰、許進豐、洪天文、李培貴、林志雄涉\n    犯結夥竊盜之犯行，係以被告5 人之供述及證人曹俊彥、曾\n    智鴻之證述，並有現場勘查紀錄表、扣押物品清單、車輛及\n    現場照片30張扣案可佐，為其論據。\n三、訊據被告楊金峰、許進豐、洪天文、李培貴、林志雄均否認\n    有結夥竊盜犯行，被告楊金峰辯稱因C 工區挖出之土方無地\n    方堆放，其乃指示將C 工區挖出之土方運到A1工區暫放，俟\n    C 工區需回填土方時，再將暫放A1工區之土方運回，其不知\n    道C 工區是河川公地，亦無竊盜土方之犯意等語；被告許進\n    豐、洪天文、李培貴、林志雄均辯稱其等係受被告楊金峰僱\n    用而依指示而為，不知C 工區是河川公地，亦無竊盜土方之\n    犯意等語。\n四、經查：\n    (一)系爭工程係由鼎信公司承攬後，由被告楊金峰負責施工，\n      被告許進豐、洪天文、李培貴、林志雄則受雇被告楊金峰\n      ；又系爭工程分為A 、B 、C 、D 、E 、F 共6 個工區，\n      其中C 工區係屬河川公地；98年2 月3 日，被告許進豐依\n      被告楊金峰之指示，令被告洪天文駕駛怪手在C 工區挖掘\n      土方（挖掘處GPS 座標為X ：192603，Y ：0000000 ），\n      並令被告李培貴、林志雄各自駕駛砂石車將挖出之土方載\n      運至A1工區放置（堆置處GPS 座標為X ：193471，Y ：00\n      00000 ），迄同日（98年2 月3 日）下午2 時許遭查獲時\n      ，C 工區共挖掘長約58公尺、寬約2.5 公尺、深約2 公尺\n      之土方；上開事實業經證人即高屏溪流域管理委員會稽查\n      大隊人員尤冠偉、朱韓義於原審審理中結證在卷（見原審\n      卷第108 －111 頁），復有工程契約、系爭工程圖、高屏\n      溪流域管理委員會現場勘查紀錄表、現場照片30張、河川\n      圖籍套繪圖、地形套繪圖在卷可佐（見警卷第73、85－99\n      頁、偵卷第117 、118 頁及卷外書證2 冊）；再被告楊金\n      峰、許進豐、洪天文、李培貴、林志雄亦坦承上情在卷，\n      核與上開證據相符，此部分情節即堪認定。\n    (二)被告楊金峰、許進豐、洪天文、李培貴、林志雄固有將C\n      工區挖出之土方運到A1工區放置，惟被告5 人均否認有竊\n      取土方之故意及行為，被告楊金峰辯稱因C 工區挖出之土\n      方無地方堆放，其乃指示將C 工區挖出之土方運到A1工區\n      暫放等語。再參諸下述：\n      1.證人曾智鴻於偵查及原審審理中結證稱其任職立洲工程\n        顧問有限公司（下稱立洲公司），立洲公司因承攬系爭\n        工程之設計及監造，乃指派其擔任系爭工程現場監工，\n        工程開挖之土方堆放旁邊即可，若開挖之土方放置地點\n        不在工區內，即需提出暫置計畫包括地主同意書，經立\n        洲公司同意後轉屏東縣政府備查，C 工區旁因都是農地\n        ，需要休耕或土地所有人同意始可放置土方，故C 工區\n        無空地可以放置開挖之土方，系爭工程之A2工區距C 工\n        區最近，因A2工區正施作其他工程，不能暫置土方，A1\n        工區沒有施作工程，僅有該處可堆置土方，98年2 月3\n        日前一天，系爭工程有提暫置計畫，但立洲公司尚未審\n        核，98年2 月3 日上午，被告楊金峰亦有告知系爭工程\n        C 工區開挖土方欲暫置之位置，嗣於98年2 月3 日遭查\n        獲後，始知悉C 工區係河川公地，土方不得外運，故暫\n        置計畫其後未經核准，另向經濟部水利署第七河川局申\n        請放置在農民休耕之土地上等語（見偵查卷第113 、\n        114 頁、原審卷第74頁、第75頁反面、第76頁、第78頁\n        反面－第79頁反面）。\n      2.證人即屏東縣政府公務處土木課職員陳青宏於原審審理\n        中結證稱系爭工程是針對整條路及附近村里道路修繕，\n        大部分工區○○村里○○道路，堆置土方都有困難，被\n        告等將土方放置在A 工區的A1工區，因為那個地方是道\n        路的旁邊，是要施作草皮，放置土方較為適當，其他工\n        區○○○○道路、水溝，放置土方會對交通造成影響等\n        語（見原審卷第126 －127 頁）。\n      3.另證人曾智鴻於偵查中結證稱一般工程回填土方需要二\n        部怪手，一部用挖土方，一部用來回填，回填需要分層\n        回填，依現場照片所示，C 工區之土方係屬堆置A1工區\n        ，因為土方非在A1工區裡，且A1工區尚未施工達回填工\n        程等語（見偵查卷第114 頁原審卷第75頁反面、第79頁\n        反面）；證人即高屏溪流域管理委員會稽查大隊人員尤\n        冠偉、朱韓義於原審審理中亦結證稱其等據報後至A1工\n        區察看，現場有六堆土堆，並未見有怪手、堆土機等機\n        具或卡車在場施工等語（見原審卷第108 －111 頁）。\n      綜上各情以觀，系爭工程C 工區旁確有無法堆置挖出土方\n      之情形，且被告楊金峰事先亦確有提出暫置計畫及向系爭\n      工程現場監工曾智鴻提出暫置地點，而參以A1工區並未見\n      有怪手、堆土機等機具在場施工，是被告楊金峰辯稱因C\n      工區挖出之土方無地方堆放，乃指示將C 工區挖出之土方\n      運到A1工區暫放等語，應非屬虛構。至證人即員警曹俊彥\n      於偵查中固結證稱A1工區距C 工區有七公里，被告等係為\n      節省購買回填A1區土石之成本，因而挖C 工區之土方回填\n      A1工區等語（見偵查卷第108 頁），然證人曹俊彥於原審\n      審理中復結證稱其係依移送書記載及嫌疑人所述，足見證\n      人曹俊彥上開所述尚非本於其親自見聞或本身學識經驗，\n      尚難據為不利被告等之判斷。\n    此外，復查無其他積極證據足資證明被告等有結夥三人以上\n    竊盜之犯行，被告等犯罪自屬不能證明。\n五、原審因而以不能證明被告等犯罪，而為被告等無罪之諭知，\n    核無違誤。檢察官上訴意旨，指摘原判決不當，為無理由，\n    應予駁回。\n據上論斷，應依刑事訴訟法第368 條，判決如主文。\n本案經檢察官劉玲興到庭執行職務。\n中    華    民    國  100     年    2     月    24    日\n                    刑事第八庭  審判長法  官  洪兆隆\n                                      法  官  張盛喜\n                                      法  官  郭玫利\n以上正本證明與原本無異。\n不得上訴。\n中    華    民    國  100     年    2     月    24    日\n                                      書記官  梁美姿",
  "structure": {
    "main": "上訴駁回。",
    "reason": "一、公訴意旨以：被告楊金峰受鼎信營造有限公司（下稱鼎信公\n    司）委託，施作由鼎信公司向屏東縣政府承包之「屏東加工\n    出口區○○道路（週邊設施改善工程）」（下稱系爭工程）\n    ，其中A1工區○○○○路段側邊背填土工程，C 工區係施作\n    擋土牆工程，被告許進豐、洪天文、李培貴、林志雄則均係\n    被告楊金峰雇用之員工。渠等均明知系爭工程C 工區即屏東\n    縣萬丹鄉萬丹堤防尾之砂石，係屬公有財產，未經申請許可\n    ，不得擅自盜採，竟仍共同意圖為自己不法之所有，基於結\n    夥三人以上竊盜之犯意聯絡，由被告楊金峰指示被告許進豐\n    等人，於民國98年2 月3 日14時許，假藉將系爭工程C 工區\n    砂石暫置A1工區名義，行回填A1工區之實，以減少A1工區購\n    置回填土之費用，共竊得290 立方公尺（長約58公尺、寬約\n    2.5 公尺、深約2 公尺）。嗣經屏東縣政府警察局及高屏溪\n    流域管理委員會人員執行巡邏勤務，查獲上情，並扣得砂石\n    60立方公尺、挖土機1 臺、營業用大貨車2 臺。因認被告楊\n    金峰、許進豐、洪天文、李培貴、林志雄均涉犯刑法第321\n    條第1 項第4 款結夥三人以上而竊盜之罪嫌。\n二、公訴人認被告楊金峰、許進豐、洪天文、李培貴、林志雄涉\n    犯結夥竊盜之犯行，係以被告5 人之供述及證人曹俊彥、曾\n    智鴻之證述，並有現場勘查紀錄表、扣押物品清單、車輛及\n    現場照片30張扣案可佐，為其論據。\n三、訊據被告楊金峰、許進豐、洪天文、李培貴、林志雄均否認\n    有結夥竊盜犯行，被告楊金峰辯稱因C 工區挖出之土方無地\n    方堆放，其乃指示將C 工區挖出之土方運到A1工區暫放，俟\n    C 工區需回填土方時，再將暫放A1工區之土方運回，其不知\n    道C 工區是河川公地，亦無竊盜土方之犯意等語；被告許進\n    豐、洪天文、李培貴、林志雄均辯稱其等係受被告楊金峰僱\n    用而依指示而為，不知C 工區是河川公地，亦無竊盜土方之\n    犯意等語。\n四、經查：\n    (一)系爭工程係由鼎信公司承攬後，由被告楊金峰負責施工，\n      被告許進豐、洪天文、李培貴、林志雄則受雇被告楊金峰\n      ；又系爭工程分為A 、B 、C 、D 、E 、F 共6 個工區，\n      其中C 工區係屬河川公地；98年2 月3 日，被告許進豐依\n      被告楊金峰之指示，令被告洪天文駕駛怪手在C 工區挖掘\n      土方（挖掘處GPS 座標為X ：192603，Y ：0000000 ），\n      並令被告李培貴、林志雄各自駕駛砂石車將挖出之土方載\n      運至A1工區放置（堆置處GPS 座標為X ：193471，Y ：00\n      00000 ），迄同日（98年2 月3 日）下午2 時許遭查獲時\n      ，C 工區共挖掘長約58公尺、寬約2.5 公尺、深約2 公尺\n      之土方；上開事實業經證人即高屏溪流域管理委員會稽查\n      大隊人員尤冠偉、朱韓義於原審審理中結證在卷（見原審\n      卷第108 －111 頁），復有工程契約、系爭工程圖、高屏\n      溪流域管理委員會現場勘查紀錄表、現場照片30張、河川\n      圖籍套繪圖、地形套繪圖在卷可佐（見警卷第73、85－99\n      頁、偵卷第117 、118 頁及卷外書證2 冊）；再被告楊金\n      峰、許進豐、洪天文、李培貴、林志雄亦坦承上情在卷，\n      核與上開證據相符，此部分情節即堪認定。\n    (二)被告楊金峰、許進豐、洪天文、李培貴、林志雄固有將C\n      工區挖出之土方運到A1工區放置，惟被告5 人均否認有竊\n      取土方之故意及行為，被告楊金峰辯稱因C 工區挖出之土\n      方無地方堆放，其乃指示將C 工區挖出之土方運到A1工區\n      暫放等語。再參諸下述：\n      1.證人曾智鴻於偵查及原審審理中結證稱其任職立洲工程\n        顧問有限公司（下稱立洲公司），立洲公司因承攬系爭\n        工程之設計及監造，乃指派其擔任系爭工程現場監工，\n        工程開挖之土方堆放旁邊即可，若開挖之土方放置地點\n        不在工區內，即需提出暫置計畫包括地主同意書，經立\n        洲公司同意後轉屏東縣政府備查，C 工區旁因都是農地\n        ，需要休耕或土地所有人同意始可放置土方，故C 工區\n        無空地可以放置開挖之土方，系爭工程之A2工區距C 工\n        區最近，因A2工區正施作其他工程，不能暫置土方，A1\n        工區沒有施作工程，僅有該處可堆置土方，98年2 月3\n        日前一天，系爭工程有提暫置計畫，但立洲公司尚未審\n        核，98年2 月3 日上午，被告楊金峰亦有告知系爭工程\n        C 工區開挖土方欲暫置之位置，嗣於98年2 月3 日遭查\n        獲後，始知悉C 工區係河川公地，土方不得外運，故暫\n        置計畫其後未經核准，另向經濟部水利署第七河川局申\n        請放置在農民休耕之土地上等語（見偵查卷第113 、\n        114 頁、原審卷第74頁、第75頁反面、第76頁、第78頁\n        反面－第79頁反面）。\n      2.證人即屏東縣政府公務處土木課職員陳青宏於原審審理\n        中結證稱系爭工程是針對整條路及附近村里道路修繕，\n        大部分工區○○村里○○道路，堆置土方都有困難，被\n        告等將土方放置在A 工區的A1工區，因為那個地方是道\n        路的旁邊，是要施作草皮，放置土方較為適當，其他工\n        區○○○○道路、水溝，放置土方會對交通造成影響等\n        語（見原審卷第126 －127 頁）。\n      3.另證人曾智鴻於偵查中結證稱一般工程回填土方需要二\n        部怪手，一部用挖土方，一部用來回填，回填需要分層\n        回填，依現場照片所示，C 工區之土方係屬堆置A1工區\n        ，因為土方非在A1工區裡，且A1工區尚未施工達回填工\n        程等語（見偵查卷第114 頁原審卷第75頁反面、第79頁\n        反面）；證人即高屏溪流域管理委員會稽查大隊人員尤\n        冠偉、朱韓義於原審審理中亦結證稱其等據報後至A1工\n        區察看，現場有六堆土堆，並未見有怪手、堆土機等機\n        具或卡車在場施工等語（見原審卷第108 －111 頁）。\n      綜上各情以觀，系爭工程C 工區旁確有無法堆置挖出土方\n      之情形，且被告楊金峰事先亦確有提出暫置計畫及向系爭\n      工程現場監工曾智鴻提出暫置地點，而參以A1工區並未見\n      有怪手、堆土機等機具在場施工，是被告楊金峰辯稱因C\n      工區挖出之土方無地方堆放，乃指示將C 工區挖出之土方\n      運到A1工區暫放等語，應非屬虛構。至證人即員警曹俊彥\n      於偵查中固結證稱A1工區距C 工區有七公里，被告等係為\n      節省購買回填A1區土石之成本，因而挖C 工區之土方回填\n      A1工區等語（見偵查卷第108 頁），然證人曹俊彥於原審\n      審理中復結證稱其係依移送書記載及嫌疑人所述，足見證\n      人曹俊彥上開所述尚非本於其親自見聞或本身學識經驗，\n      尚難據為不利被告等之判斷。\n    此外，復查無其他積極證據足資證明被告等有結夥三人以上\n    竊盜之犯行，被告等犯罪自屬不能證明。\n五、原審因而以不能證明被告等犯罪，而為被告等無罪之諭知，\n    核無違誤。檢察官上訴意旨，指摘原判決不當，為無理由，\n    應予駁回。\n據上論斷，應依刑事訴訟法第368 條，判決如主文。\n本案經檢察官劉玲興到庭執行職務。"
  },
  "search": "臺灣高等法院高雄分院刑事判決99年度上易字第1200號上訴人臺灣屏東地方法院檢察署檢察官被告楊金峰許進豐洪天文李培貴林志雄共同選任辯護人蔡將葳律師上列上訴人因被告竊盜案件，不服臺灣屏東地方法院98年度易字第1229號中華民國98年9月28日第一審判決（起訴案號：臺灣屏東地方法院檢察署98年度偵字第1201號），提起上訴，本院判決如下：主文上訴駁回。理由一、公訴意旨以：被告楊金峰受鼎信營造有限公司（下稱鼎信公司）委託，施作由鼎信公司向屏東縣政府承包之「屏東加工出口區○○道路（週邊設施改善工程）」（下稱系爭工程），其中A1工區○○○○路段側邊背填土工程，C工區係施作擋土牆工程，被告許進豐、洪天文、李培貴、林志雄則均係被告楊金峰雇用之員工。渠等均明知系爭工程C工區即屏東縣萬丹鄉萬丹堤防尾之砂石，係屬公有財產，未經申請許可，不得擅自盜採，竟仍共同意圖為自己不法之所有，基於結夥三人以上竊盜之犯意聯絡，由被告楊金峰指示被告許進豐等人，於民國98年2月3日14時許，假藉將系爭工程C工區砂石暫置A1工區名義，行回填A1工區之實，以減少A1工區購置回填土之費用，共竊得290立方公尺（長約58公尺、寬約2.5公尺、深約2公尺）。嗣經屏東縣政府警察局及高屏溪流域管理委員會人員執行巡邏勤務，查獲上情，並扣得砂石60立方公尺、挖土機1臺、營業用大貨車2臺。因認被告楊金峰、許進豐、洪天文、李培貴、林志雄均涉犯刑法第321條第1項第4款結夥三人以上而竊盜之罪嫌。二、公訴人認被告楊金峰、許進豐、洪天文、李培貴、林志雄涉犯結夥竊盜之犯行，係以被告5人之供述及證人曹俊彥、曾智鴻之證述，並有現場勘查紀錄表、扣押物品清單、車輛及現場照片30張扣案可佐，為其論據。三、訊據被告楊金峰、許進豐、洪天文、李培貴、林志雄均否認有結夥竊盜犯行，被告楊金峰辯稱因C工區挖出之土方無地方堆放，其乃指示將C工區挖出之土方運到A1工區暫放，俟C工區需回填土方時，再將暫放A1工區之土方運回，其不知道C工區是河川公地，亦無竊盜土方之犯意等語；被告許進豐、洪天文、李培貴、林志雄均辯稱其等係受被告楊金峰僱用而依指示而為，不知C工區是河川公地，亦無竊盜土方之犯意等語。四、經查：(一)系爭工程係由鼎信公司承攬後，由被告楊金峰負責施工，被告許進豐、洪天文、李培貴、林志雄則受雇被告楊金峰；又系爭工程分為A、B、C、D、E、F共6個工區，其中C工區係屬河川公地；98年2月3日，被告許進豐依被告楊金峰之指示，令被告洪天文駕駛怪手在C工區挖掘土方（挖掘處GPS座標為X：192603，Y：0000000），並令被告李培貴、林志雄各自駕駛砂石車將挖出之土方載運至A1工區放置（堆置處GPS座標為X：193471，Y：0000000），迄同日（98年2月3日）下午2時許遭查獲時，C工區共挖掘長約58公尺、寬約2.5公尺、深約2公尺之土方；上開事實業經證人即高屏溪流域管理委員會稽查大隊人員尤冠偉、朱韓義於原審審理中結證在卷（見原審卷第108－111頁），復有工程契約、系爭工程圖、高屏溪流域管理委員會現場勘查紀錄表、現場照片30張、河川圖籍套繪圖、地形套繪圖在卷可佐（見警卷第73、85－99頁、偵卷第117、118頁及卷外書證2冊）；再被告楊金峰、許進豐、洪天文、李培貴、林志雄亦坦承上情在卷，核與上開證據相符，此部分情節即堪認定。(二)被告楊金峰、許進豐、洪天文、李培貴、林志雄固有將C工區挖出之土方運到A1工區放置，惟被告5人均否認有竊取土方之故意及行為，被告楊金峰辯稱因C工區挖出之土方無地方堆放，其乃指示將C工區挖出之土方運到A1工區暫放等語。再參諸下述：1.證人曾智鴻於偵查及原審審理中結證稱其任職立洲工程顧問有限公司（下稱立洲公司），立洲公司因承攬系爭工程之設計及監造，乃指派其擔任系爭工程現場監工，工程開挖之土方堆放旁邊即可，若開挖之土方放置地點不在工區內，即需提出暫置計畫包括地主同意書，經立洲公司同意後轉屏東縣政府備查，C工區旁因都是農地，需要休耕或土地所有人同意始可放置土方，故C工區無空地可以放置開挖之土方，系爭工程之A2工區距C工區最近，因A2工區正施作其他工程，不能暫置土方，A1工區沒有施作工程，僅有該處可堆置土方，98年2月3日前一天，系爭工程有提暫置計畫，但立洲公司尚未審核，98年2月3日上午，被告楊金峰亦有告知系爭工程C工區開挖土方欲暫置之位置，嗣於98年2月3日遭查獲後，始知悉C工區係河川公地，土方不得外運，故暫置計畫其後未經核准，另向經濟部水利署第七河川局申請放置在農民休耕之土地上等語（見偵查卷第113、114頁、原審卷第74頁、第75頁反面、第76頁、第78頁反面－第79頁反面）。2.證人即屏東縣政府公務處土木課職員陳青宏於原審審理中結證稱系爭工程是針對整條路及附近村里道路修繕，大部分工區○○村里○○道路，堆置土方都有困難，被告等將土方放置在A工區的A1工區，因為那個地方是道路的旁邊，是要施作草皮，放置土方較為適當，其他工區○○○○道路、水溝，放置土方會對交通造成影響等語（見原審卷第126－127頁）。3.另證人曾智鴻於偵查中結證稱一般工程回填土方需要二部怪手，一部用挖土方，一部用來回填，回填需要分層回填，依現場照片所示，C工區之土方係屬堆置A1工區，因為土方非在A1工區裡，且A1工區尚未施工達回填工程等語（見偵查卷第114頁原審卷第75頁反面、第79頁反面）；證人即高屏溪流域管理委員會稽查大隊人員尤冠偉、朱韓義於原審審理中亦結證稱其等據報後至A1工區察看，現場有六堆土堆，並未見有怪手、堆土機等機具或卡車在場施工等語（見原審卷第108－111頁）。綜上各情以觀，系爭工程C工區旁確有無法堆置挖出土方之情形，且被告楊金峰事先亦確有提出暫置計畫及向系爭工程現場監工曾智鴻提出暫置地點，而參以A1工區並未見有怪手、堆土機等機具在場施工，是被告楊金峰辯稱因C工區挖出之土方無地方堆放，乃指示將C工區挖出之土方運到A1工區暫放等語，應非屬虛構。至證人即員警曹俊彥於偵查中固結證稱A1工區距C工區有七公里，被告等係為節省購買回填A1區土石之成本，因而挖C工區之土方回填A1工區等語（見偵查卷第108頁），然證人曹俊彥於原審審理中復結證稱其係依移送書記載及嫌疑人所述，足見證人曹俊彥上開所述尚非本於其親自見聞或本身學識經驗，尚難據為不利被告等之判斷。此外，復查無其他積極證據足資證明被告等有結夥三人以上竊盜之犯行，被告等犯罪自屬不能證明。五、原審因而以不能證明被告等犯罪，而為被告等無罪之諭知，核無違誤。檢察官上訴意旨，指摘原判決不當，為無理由，應予駁回。據上論斷，應依刑事訴訟法第368條，判決如主文。本案經檢察官劉玲興到庭執行職務。中華民國100年2月24日刑事第八庭審判長法官洪兆隆法官張盛喜法官郭玫利以上正本證明與原本無異。不得上訴。中華民國100年2月24日書記官梁美姿",
  "characters": {
    "judges": [
      "洪兆隆",
      "張盛喜",
      "郭玫利"
    ],
    "prosecutors": [
      "劉玲興"
    ],
    "lawyers": [
      "蔡將葳"
    ],
    "clerks": [

    ],
    "plaintiffs": [

    ],
    "defendants": [
      "楊金峰"
    ],
    "prosecutor_office": [

    ],
    "creditors": [

    ],
    "debtors": [

    ],
    "judicial_associate_officer": [

    ]
  },
  "adjudged_at": "2011-02-24",
  "created_at": "2016-02-12 06:03:41",
  "updated_at": "2016-02-12 06:03:41"
}