{
  "identify": "TPD-100-除-451-20110225-1",
  "court": {
    "name": "臺灣臺北地方法院",
    "code": "TPD"
  },
  "division": {
    "name": "民事",
    "code": "V"
  },
  "year": 100,
  "word": "除",
  "number": "451",
  "jcheck": "1",
  "reason": "除權判決（股票）",
  "content": "臺灣臺北地方法院民事判決              100年度除字第451號\n聲  請  人  陳傳政\n上列聲請人聲請除權判決事件，本院判決如下：\n    主  文\n如附表所示之證券無效。\n訴訟費用新臺幣壹仟元由聲請人負擔。\n    理  由\n一、上開證券，經本院以99年度司催字第2481號公示催告。\n二、所定申報權利期間，已於民國100年1月11日屆滿，迄今無人\n    申報權利。\n三、依民事訴訟法第564條第1項、第549條之1、第87條第1項之\n    規定，判決如主文。\n中    華    民    國   100    年    2     月    25    日\n                  民事第三庭    法  官  曾益盛\n以上正本係照原本作成。\n本判決不得上訴。\n中    華    民    國   100    年    2     月    25    日\n                                書記官  蔡月女\n┌───────────────────────────────┐\n│附表：                                      100年度除字第451號│\n├──┬──────────┬────────┬──┬──┬──┤\n│編號│發    行    公    司│股  票  號  碼  │種類│張數│股數│\n├──┼──────────┼────────┼──┼──┼──┤\n│001 │中國電器股份有限公司│0080ND0000000-0 │股票│1   │1000│\n├──┼──────────┼────────┼──┼──┼──┤\n│002 │中國電器股份有限公司│0080ND0000000-0 │股票│1   │1000│\n└──┴──────────┴────────┴──┴──┴──┘",
  "structure": {
    "main": "如附表所示之證券無效。\n訴訟費用新臺幣壹仟元由聲請人負擔。",
    "reason": "一、上開證券，經本院以99年度司催字第2481號公示催告。\n二、所定申報權利期間，已於民國100年1月11日屆滿，迄今無人\n    申報權利。\n三、依民事訴訟法第564條第1項、第549條之1、第87條第1項之\n    規定，判決如主文。"
  },
  "search": "臺灣臺北地方法院民事判決100年度除字第451號聲請人陳傳政上列聲請人聲請除權判決事件，本院判決如下：主文如附表所示之證券無效。訴訟費用新臺幣壹仟元由聲請人負擔。理由一、上開證券，經本院以99年度司催字第2481號公示催告。二、所定申報權利期間，已於民國100年1月11日屆滿，迄今無人申報權利。三、依民事訴訟法第564條第1項、第549條之1、第87條第1項之規定，判決如主文。中華民國100年2月25日民事第三庭法官曾益盛以上正本係照原本作成。本判決不得上訴。中華民國100年2月25日書記官蔡月女┌───────────────────────────────┐│附表：100年度除字第451號│├──┬──────────┬────────┬──┬──┬──┤│編號│發行公司│股票號碼│種類│張數│股數│├──┼──────────┼────────┼──┼──┼──┤│001│中國電器股份有限公司│0080ND0000000-0│股票│1│1000│├──┼──────────┼────────┼──┼──┼──┤│002│中國電器股份有限公司│0080ND0000000-0│股票│1│1000│└──┴──────────┴────────┴──┴──┴──┘",
  "characters": {
    "judges": [
      "曾益盛"
    ],
    "prosecutors": [

    ],
    "lawyers": [

    ],
    "clerks": [
      "蔡月女"
    ],
    "plaintiffs": [

    ],
    "defendants": [

    ],
    "prosecutor_office": [
      "陳傳政"
    ],
    "creditors": [

    ],
    "debtors": [

    ],
    "judicial_associate_officer": [

    ]
  },
  "adjudged_at": "2011-02-25",
  "created_at": "2016-02-12 05:45:23",
  "updated_at": "2016-02-12 05:45:23"
}