{
  "identify": "KSD-90-易-3735-20020117-1",
  "court": {
    "name": "臺灣高雄地方法院",
    "code": "KSD"
  },
  "division": {
    "name": "刑事",
    "code": "M"
  },
  "year": 90,
  "word": "易",
  "number": "3735",
  "jcheck": "1",
  "reason": "毒品危害防制條例",
  "content": "臺灣高雄地方法院刑事判決                          九十年度易字第三七三五號\n    公  訴  人  臺灣高雄地方法院檢察署檢察官\n    被      告  甲○○\n右列被告因毒品危害防制條例案件，經檢察官提起公訴（九十年度毒偵字第三九六四\n號），本院判決如左：\n    主  文\n甲○○施用第二級毒品，處有期徒刑月，如易科罰金，以佰元折算壹日。\n扣案之第二級毒品安非他命壹包（驗後毛重零點公克），沒收銷燬之。\n    事  實\n一、甲○○前因施用毒品案件，經台灣屏東地方法院以八十九年度毒聲字第七七一號\n    裁定送觀察、勒戒後，認有繼續施用毒品之傾向，經送強制戒治及交付保護管束\n    期滿後，業經台灣屏東地方法院檢察署檢察官於九十年五月三日以九十年戒毒偵\n    字第一二八號不起訴處分確定，猶不知悔改，復基於施用第二級毒品之犯意，於\n    九十年八月二十七日上午十時許，在屏東縣屏東市屏東公園廁所內，以將安非他\n    命置於鋁箔紙上，下端以火燒烤加熱，使安非他命汽化產生煙霧吸用之方式，施\n    用第二級毒品安非他命一次，為警於同日晚間八時許，在高雄市○○區○○路與\n    七賢路口查獲，並扣得其所有之第二級毒品安非他命一包（驗前毛重零點四七公\n    克、驗後毛重零點三公克）。\n二、案經高雄市政府警察局移送台灣高雄地方法院檢察署檢察官偵查起訴。\n    理  由\n一、右揭事實，業據被告甲○○於本院審理時坦承不諱，且被告經警查獲之時所採集\n    之尿液，經送高雄市政府衛生局檢驗之結果，呈甲基安非他命之陽性反應，有該\n    醫院九十年九月六日高衛試煙字第Ｌ—三二號煙毒尿液檢驗成績書乙紙附卷可稽\n    ，另扣案之晶體一包經送驗後確定為第二級毒品甲基安非他命，此有高雄醫學院\n    附設中和紀念醫院檢驗報告（編號０九一一—一０九號）在卷可憑。又被告前因\n    施用毒品案件，經依台灣屏東地方法院以八十九年度毒聲字第七七一號裁定送觀\n    察、勒戒後，認有繼續施用毒品之傾向，經送強制戒治及交付保護管束期滿後，\n    業經台灣屏東地方法院檢察署檢察官於九十年五月三日以九十年戒毒偵字第一二\n    八號不起訴處分確定，有台灣高等法院被告全國前案紀錄表可按。被告於五年內\n    再犯第十條之罪，由檢察官向本院聲請強制戒治，即應進入訴訟程序審理，毒品\n    危害防制條例第二十三條第二項定有明文，是本件事證已臻明確，被告犯行應堪\n    認定。\n二、按安非他命係屬第二級毒品，毒品危害防制條例第二條第二項規定甚明，核被告\n    甲○○所為，係犯同條例第十條第二項之施用第二級毒品罪。其持有安非他命後\n    ，進而施用，其持有行為應被其施用之行為所吸收，不另論罪。爰審酌被告曾因\n    施用毒品案件，經強制戒治交付保護管束期滿，仍不知悔改、警惕，猶繼續施用\n    毒品，本不宜寬貸，惟其施用毒品僅戕害己身，未危及他人等一切情狀，量處如\n    主文所示之刑，並諭知易科罰金之折算標準，以資懲儆。扣案之第二級毒品安非\n    他命一包（驗前毛重零點四七公克、驗後毛重零點三公克），應依毒品危害防制\n    條例第十八條第一項前段之規定，宣告沒收銷燬之。又送鑑耗損之安非他命晶體\n    ，既已滅失，自無庸再予宣告沒收銷燬之必要，附此敘明。\n據上論斷，應依刑事訴訟法第二百九十九條第一項前段，毒品危害防制條例第十條第\n二項、第十八條第一項前段，刑法第十一條、第四十一條第一項，罰金罰鍰提高標準\n條例第二條，判決如主文。\n中    華    民    國      九十一年      一      月      十七      日\n                                  臺灣高雄地方法院刑事第四庭\n                                      審判長法  官  黃建榮\n                                            法  官  莊珮君\n                                            法  官  盧怡秀\n右正本證明與原本無異。\n如不服本判決，應於判決送達後十日內，向本院提出上訴狀。\n                                            書記官  林宜正\n中    華    民    國      九十一      年      一      月     二十一     日\n附錄論罪科刑法條：\n毒品危害防制條例第十條第二項：\n施用第二級毒品者，處三年以下有期徒刑。\n毒品危害防制條例第十八條第一項前段：\n查獲之毒品及專供製造或施用毒品之器具，不問屬於犯人與否，均沒收銷燬之。\n",
  "structure": {
    "main": "甲○○施用第二級毒品，處有期徒刑月，如易科罰金，以佰元折算壹日。\n扣案之第二級毒品安非他命壹包（驗後毛重零點公克），沒收銷燬之。",
    "fact": "一、甲○○前因施用毒品案件，經台灣屏東地方法院以八十九年度毒聲字第七七一號\n    裁定送觀察、勒戒後，認有繼續施用毒品之傾向，經送強制戒治及交付保護管束\n    期滿後，業經台灣屏東地方法院檢察署檢察官於九十年五月三日以九十年戒毒偵\n    字第一二八號不起訴處分確定，猶不知悔改，復基於施用第二級毒品之犯意，於\n    九十年八月二十七日上午十時許，在屏東縣屏東市屏東公園廁所內，以將安非他\n    命置於鋁箔紙上，下端以火燒烤加熱，使安非他命汽化產生煙霧吸用之方式，施\n    用第二級毒品安非他命一次，為警於同日晚間八時許，在高雄市○○區○○路與\n    七賢路口查獲，並扣得其所有之第二級毒品安非他命一包（驗前毛重零點四七公\n    克、驗後毛重零點三公克）。\n二、案經高雄市政府警察局移送台灣高雄地方法院檢察署檢察官偵查起訴。",
    "reason": "一、右揭事實，業據被告甲○○於本院審理時坦承不諱，且被告經警查獲之時所採集\n    之尿液，經送高雄市政府衛生局檢驗之結果，呈甲基安非他命之陽性反應，有該\n    醫院九十年九月六日高衛試煙字第Ｌ—三二號煙毒尿液檢驗成績書乙紙附卷可稽\n    ，另扣案之晶體一包經送驗後確定為第二級毒品甲基安非他命，此有高雄醫學院\n    附設中和紀念醫院檢驗報告（編號０九一一—一０九號）在卷可憑。又被告前因\n    施用毒品案件，經依台灣屏東地方法院以八十九年度毒聲字第七七一號裁定送觀\n    察、勒戒後，認有繼續施用毒品之傾向，經送強制戒治及交付保護管束期滿後，\n    業經台灣屏東地方法院檢察署檢察官於九十年五月三日以九十年戒毒偵字第一二\n    八號不起訴處分確定，有台灣高等法院被告全國前案紀錄表可按。被告於五年內\n    再犯第十條之罪，由檢察官向本院聲請強制戒治，即應進入訴訟程序審理，毒品\n    危害防制條例第二十三條第二項定有明文，是本件事證已臻明確，被告犯行應堪\n    認定。\n二、按安非他命係屬第二級毒品，毒品危害防制條例第二條第二項規定甚明，核被告\n    甲○○所為，係犯同條例第十條第二項之施用第二級毒品罪。其持有安非他命後\n    ，進而施用，其持有行為應被其施用之行為所吸收，不另論罪。爰審酌被告曾因\n    施用毒品案件，經強制戒治交付保護管束期滿，仍不知悔改、警惕，猶繼續施用\n    毒品，本不宜寬貸，惟其施用毒品僅戕害己身，未危及他人等一切情狀，量處如\n    主文所示之刑，並諭知易科罰金之折算標準，以資懲儆。扣案之第二級毒品安非\n    他命一包（驗前毛重零點四七公克、驗後毛重零點三公克），應依毒品危害防制\n    條例第十八條第一項前段之規定，宣告沒收銷燬之。又送鑑耗損之安非他命晶體\n    ，既已滅失，自無庸再予宣告沒收銷燬之必要，附此敘明。\n據上論斷，應依刑事訴訟法第二百九十九條第一項前段，毒品危害防制條例第十條第\n二項、第十八條第一項前段，刑法第十一條、第四十一條第一項，罰金罰鍰提高標準\n條例第二條，判決如主文。\n中    華    民    國      九十一年      一      月      十七      日\n                                  臺灣高雄地方法院刑事第四庭\n                                      審判長法  官  黃建榮\n                                            法  官  莊珮君\n                                            法  官  盧怡秀\n右正本證明與原本無異。\n如不服本判決，應於判決送達後十日內，向本院提出上訴狀。\n                                            書記官  林宜正"
  },
  "search": "臺灣高雄地方法院刑事判決九十年度易字第三七三五號公訴人臺灣高雄地方法院檢察署檢察官被告甲○○右列被告因毒品危害防制條例案件，經檢察官提起公訴（九十年度毒偵字第三九六四號），本院判決如左：主文甲○○施用第二級毒品，處有期徒刑月，如易科罰金，以佰元折算壹日。扣案之第二級毒品安非他命壹包（驗後毛重零點公克），沒收銷燬之。事實一、甲○○前因施用毒品案件，經台灣屏東地方法院以八十九年度毒聲字第七七一號裁定送觀察、勒戒後，認有繼續施用毒品之傾向，經送強制戒治及交付保護管束期滿後，業經台灣屏東地方法院檢察署檢察官於九十年五月三日以九十年戒毒偵字第一二八號不起訴處分確定，猶不知悔改，復基於施用第二級毒品之犯意，於九十年八月二十七日上午十時許，在屏東縣屏東市屏東公園廁所內，以將安非他命置於鋁箔紙上，下端以火燒烤加熱，使安非他命汽化產生煙霧吸用之方式，施用第二級毒品安非他命一次，為警於同日晚間八時許，在高雄市○○區○○路與七賢路口查獲，並扣得其所有之第二級毒品安非他命一包（驗前毛重零點四七公克、驗後毛重零點三公克）。二、案經高雄市政府警察局移送台灣高雄地方法院檢察署檢察官偵查起訴。理由一、右揭事實，業據被告甲○○於本院審理時坦承不諱，且被告經警查獲之時所採集之尿液，經送高雄市政府衛生局檢驗之結果，呈甲基安非他命之陽性反應，有該醫院九十年九月六日高衛試煙字第Ｌ—三二號煙毒尿液檢驗成績書乙紙附卷可稽，另扣案之晶體一包經送驗後確定為第二級毒品甲基安非他命，此有高雄醫學院附設中和紀念醫院檢驗報告（編號０九一一—一０九號）在卷可憑。又被告前因施用毒品案件，經依台灣屏東地方法院以八十九年度毒聲字第七七一號裁定送觀察、勒戒後，認有繼續施用毒品之傾向，經送強制戒治及交付保護管束期滿後，業經台灣屏東地方法院檢察署檢察官於九十年五月三日以九十年戒毒偵字第一二八號不起訴處分確定，有台灣高等法院被告全國前案紀錄表可按。被告於五年內再犯第十條之罪，由檢察官向本院聲請強制戒治，即應進入訴訟程序審理，毒品危害防制條例第二十三條第二項定有明文，是本件事證已臻明確，被告犯行應堪認定。二、按安非他命係屬第二級毒品，毒品危害防制條例第二條第二項規定甚明，核被告甲○○所為，係犯同條例第十條第二項之施用第二級毒品罪。其持有安非他命後，進而施用，其持有行為應被其施用之行為所吸收，不另論罪。爰審酌被告曾因施用毒品案件，經強制戒治交付保護管束期滿，仍不知悔改、警惕，猶繼續施用毒品，本不宜寬貸，惟其施用毒品僅戕害己身，未危及他人等一切情狀，量處如主文所示之刑，並諭知易科罰金之折算標準，以資懲儆。扣案之第二級毒品安非他命一包（驗前毛重零點四七公克、驗後毛重零點三公克），應依毒品危害防制條例第十八條第一項前段之規定，宣告沒收銷燬之。又送鑑耗損之安非他命晶體，既已滅失，自無庸再予宣告沒收銷燬之必要，附此敘明。據上論斷，應依刑事訴訟法第二百九十九條第一項前段，毒品危害防制條例第十條第二項、第十八條第一項前段，刑法第十一條、第四十一條第一項，罰金罰鍰提高標準條例第二條，判決如主文。中華民國九十一年一月十七日臺灣高雄地方法院刑事第四庭審判長法官黃建榮法官莊珮君法官盧怡秀右正本證明與原本無異。如不服本判決，應於判決送達後十日內，向本院提出上訴狀。書記官林宜正中華民國九十一年一月二十一日附錄論罪科刑法條：毒品危害防制條例第十條第二項：施用第二級毒品者，處三年以下有期徒刑。毒品危害防制條例第十八條第一項前段：查獲之毒品及專供製造或施用毒品之器具，不問屬於犯人與否，均沒收銷燬之。",
  "characters": {
    "judges": [
      "黃建榮",
      "莊珮君",
      "盧怡秀"
    ],
    "prosecutors": [

    ],
    "lawyers": [

    ],
    "clerks": [
      "林宜正"
    ],
    "plaintiffs": [

    ],
    "defendants": [
      "甲○○",
      "右列被告因毒品危害防制條例案件，經檢察官提起公訴（九十年度毒偵字第三九六四",
      "號），本院判決如左："
    ],
    "prosecutor_office": [
      "臺灣高雄地方法院檢察署檢察官"
    ],
    "creditors": [

    ],
    "debtors": [

    ],
    "judicial_associate_officer": [

    ]
  },
  "adjudged_at": "2002-01-17",
  "created_at": "2016-02-05 03:22:49",
  "updated_at": "2016-02-05 03:22:49"
}