{
  "identify": "TCH-88-訴-171-20020219-1",
  "court": {
    "name": "臺灣高等法院",
    "code": "TCH"
  },
  "division": {
    "name": "民事",
    "code": "V"
  },
  "year": 88,
  "word": "訴",
  "number": "171",
  "jcheck": "1",
  "reason": "侵權行為損害賠償",
  "content": "臺灣高等法院臺中分院民事裁定      八十八年度訴字第一七一號\n      原      告  壬○○\n                  戊○○\n                  庚○○○\n                  乙○○\n                  丁○○\n      法定代理人  丙○○\n      原      告  辛○○\n                  己  ○\n      被      告  甲○○\n                  王邱園妹\n右當事人間侵權行為損害賠償事件，本院裁定如左：\n      主    文\n本件於被告甲○○刑事訴訟終結前，停止訴訟程序。\n      理    由\n一、查本件被告甲○○涉有偽造文書犯罪嫌疑，經本院刑事庭判處有期徒刑壹年肆月\n    ，現在最高法院審理中，該犯罪嫌疑，確有影響於本件民事訴訟之裁判，非俟刑\n    事訴訟終結，本件民事訴訟即難於判斷，認有裁定停止訴訟之必要。\n二、依民事訴訟法第一百八十三條，裁定如主文。\n中      華      民      國    九十一    年      二      月     十九     日\n~B1民事第三庭審判長法  官  陳照德\n~B2                法  官  蔡王金全\n~B3                法  官  陳成泉\n右為正本係照原本作成。\n如不服本裁定應於裁定送達後十日內向本院提出抗告理由狀（須按他造人數附具繕本\n），並繳納抗告裁判費新台幣肆拾伍元及送達用雙掛號郵票拾份（每份拾肆元）。\n~B                書記官  劉恒宏\n中      華      民      國    九十一    年      二      月    二十一    日\n                                                                        Ｂ\n",
  "structure": {
    "main": "本件於被告甲○○刑事訴訟終結前，停止訴訟程序。",
    "reason": "一、查本件被告甲○○涉有偽造文書犯罪嫌疑，經本院刑事庭判處有期徒刑壹年肆月\n    ，現在最高法院審理中，該犯罪嫌疑，確有影響於本件民事訴訟之裁判，非俟刑\n    事訴訟終結，本件民事訴訟即難於判斷，認有裁定停止訴訟之必要。\n二、依民事訴訟法第一百八十三條，裁定如主文。"
  },
  "search": "臺灣高等法院臺中分院民事裁定八十八年度訴字第一七一號原告壬○○戊○○庚○○○乙○○丁○○法定代理人丙○○原告辛○○己○被告甲○○王邱園妹右當事人間侵權行為損害賠償事件，本院裁定如左：主文本件於被告甲○○刑事訴訟終結前，停止訴訟程序。理由一、查本件被告甲○○涉有偽造文書犯罪嫌疑，經本院刑事庭判處有期徒刑壹年肆月，現在最高法院審理中，該犯罪嫌疑，確有影響於本件民事訴訟之裁判，非俟刑事訴訟終結，本件民事訴訟即難於判斷，認有裁定停止訴訟之必要。二、依民事訴訟法第一百八十三條，裁定如主文。中華民國九十一年二月十九日~B1民事第三庭審判長法官陳照德~B2法官蔡王金全~B3法官陳成泉右為正本係照原本作成。如不服本裁定應於裁定送達後十日內向本院提出抗告理由狀（須按他造人數附具繕本），並繳納抗告裁判費新台幣肆拾伍元及送達用雙掛號郵票拾份（每份拾肆元）。~B書記官劉恒宏中華民國九十一年二月二十一日Ｂ",
  "characters": {
    "judges": [
      "陳照德",
      "蔡王金全",
      "陳成泉"
    ],
    "prosecutors": [

    ],
    "lawyers": [

    ],
    "clerks": [

    ],
    "plaintiffs": [
      "壬",
      "辛"
    ],
    "defendants": [
      "甲○○"
    ],
    "prosecutor_office": [

    ],
    "creditors": [

    ],
    "debtors": [

    ],
    "judicial_associate_officer": [

    ]
  },
  "adjudged_at": "2002-02-19",
  "created_at": "2016-02-04 14:33:00",
  "updated_at": "2016-02-04 14:33:00"
}