{
  "identify": "KSD-94-簡-6213-20051031-1",
  "court": {
    "name": "臺灣高雄地方法院",
    "code": "KSD"
  },
  "division": {
    "name": "刑事",
    "code": "M"
  },
  "year": 94,
  "word": "簡",
  "number": "6213",
  "jcheck": "1",
  "reason": "違反動產擔保交易法",
  "content": "臺灣高雄地方法院刑事簡易判決          94年度簡字第6213號\n聲  請  人  臺灣高雄地方法院檢察署檢察官\n被      告  甲○○○\n上列被告因違反動產擔保交易法案件，經檢察官聲請以簡易判決\n處刑（94年度偵字第19612 號），本院判決如下：\n    主  文\n甲○○○動產擔保交易之債務人，意圖不法之利益，將標的物遷\n移，致生損害於債權人，處拘役伍拾日，如易科罰金，以佰元\n折算壹日。緩刑貳年。\n    事實及理由\n一、本件除事實欄補充：「甲○○○尚積欠貸款本金新臺幣（下\n    同）349,187 元」外，其餘犯罪事實及證據均引用檢察官聲\n    請簡易判決處刑書之記載（如附件）。\n二、核被告甲○○○所為，係違反動產擔保交易法第38條動產擔\n    保交易之債務人，意圖不法之利益，將標的物遷移，致生損\n    害於債權人罪。爰審酌被告在價金未付清前，即將標的物遷\n    移，致告訴人台新國際商業銀行股份有限公司追索無著，且\n    尚積欠告訴人349,187 元，金額非微，迄今尚未與告訴人達\n    成和解，賠償告訴人之損失，惟念及被告並無前科，有臺灣\n    高等法院被告前案紀錄表在卷可憑，素行良好等一切情狀，\n    量處如主文所示之刑，並諭知易科罰金之折算標準。末查被\n    告前未曾受有期徒刑以上刑之宣告，有臺灣高等法院被告前\n    案紀錄表在卷可憑，其因一時失慮，致觸犯本案犯行，經此\n    次偵審之教訓，應無再犯之虞，本院認前開所宣告之刑，以\n    暫不執行為適當，爰宣告緩刑2 年，以啟自新。\n三、依刑事訴訟法第449 條第1 項前段、第3 項、第454 條第2\n    項，動產擔保交易法第38條、刑法第11條前段、第41條第1\n    項前段、第74條第1 款，罰金罰鍰提高標準條例第1 條前段\n    、第2 條，逕以簡易判決處如主文所示之刑。\n四、如不服本判決，得於判決書送達之日起10日內，以書狀敘明\n    理由，向本院提出上訴。\n中    華    民    國    94    年    10    月    31    日\n                  高雄簡易庭  法  官  洪能超\n以上正本，係照原本作成，證明與原本無異。\n中    華    民    國    94    年    10    月    31    日\n                              書記官  曾小玲\n附錄本判決論罪之法條：\n動產擔保交易法第38條\n動產擔保交易之債務人，意圖不法之利益，將標的物遷移、出賣\n、出質、移轉、抵押或為其他處分，致生損害於債權人者，處3\n年以下有期徒刑、拘役或科或併科6000元以下之罰金。\n",
  "structure": {
    "main": "甲○○○動產擔保交易之債務人，意圖不法之利益，將標的物遷\n移，致生損害於債權人，處拘役伍拾日，如易科罰金，以佰元\n折算壹日。緩刑貳年。",
    "fact": "一、本件除事實欄補充：「甲○○○尚積欠貸款本金新臺幣（下\n    同）349,187 元」外，其餘犯罪事實及證據均引用檢察官聲\n    請簡易判決處刑書之記載（如附件）。\n二、核被告甲○○○所為，係違反動產擔保交易法第38條動產擔\n    保交易之債務人，意圖不法之利益，將標的物遷移，致生損\n    害於債權人罪。爰審酌被告在價金未付清前，即將標的物遷\n    移，致告訴人台新國際商業銀行股份有限公司追索無著，且\n    尚積欠告訴人349,187 元，金額非微，迄今尚未與告訴人達\n    成和解，賠償告訴人之損失，惟念及被告並無前科，有臺灣\n    高等法院被告前案紀錄表在卷可憑，素行良好等一切情狀，\n    量處如主文所示之刑，並諭知易科罰金之折算標準。末查被\n    告前未曾受有期徒刑以上刑之宣告，有臺灣高等法院被告前\n    案紀錄表在卷可憑，其因一時失慮，致觸犯本案犯行，經此\n    次偵審之教訓，應無再犯之虞，本院認前開所宣告之刑，以\n    暫不執行為適當，爰宣告緩刑2 年，以啟自新。\n三、依刑事訴訟法第449 條第1 項前段、第3 項、第454 條第2\n    項，動產擔保交易法第38條、刑法第11條前段、第41條第1\n    項前段、第74條第1 款，罰金罰鍰提高標準條例第1 條前段\n    、第2 條，逕以簡易判決處如主文所示之刑。\n四、如不服本判決，得於判決書送達之日起10日內，以書狀敘明\n    理由，向本院提出上訴。",
    "reason": "一、本件除事實欄補充：「甲○○○尚積欠貸款本金新臺幣（下\n    同）349,187 元」外，其餘犯罪事實及證據均引用檢察官聲\n    請簡易判決處刑書之記載（如附件）。\n二、核被告甲○○○所為，係違反動產擔保交易法第38條動產擔\n    保交易之債務人，意圖不法之利益，將標的物遷移，致生損\n    害於債權人罪。爰審酌被告在價金未付清前，即將標的物遷\n    移，致告訴人台新國際商業銀行股份有限公司追索無著，且\n    尚積欠告訴人349,187 元，金額非微，迄今尚未與告訴人達\n    成和解，賠償告訴人之損失，惟念及被告並無前科，有臺灣\n    高等法院被告前案紀錄表在卷可憑，素行良好等一切情狀，\n    量處如主文所示之刑，並諭知易科罰金之折算標準。末查被\n    告前未曾受有期徒刑以上刑之宣告，有臺灣高等法院被告前\n    案紀錄表在卷可憑，其因一時失慮，致觸犯本案犯行，經此\n    次偵審之教訓，應無再犯之虞，本院認前開所宣告之刑，以\n    暫不執行為適當，爰宣告緩刑2 年，以啟自新。\n三、依刑事訴訟法第449 條第1 項前段、第3 項、第454 條第2\n    項，動產擔保交易法第38條、刑法第11條前段、第41條第1\n    項前段、第74條第1 款，罰金罰鍰提高標準條例第1 條前段\n    、第2 條，逕以簡易判決處如主文所示之刑。\n四、如不服本判決，得於判決書送達之日起10日內，以書狀敘明\n    理由，向本院提出上訴。"
  },
  "search": "臺灣高雄地方法院刑事簡易判決94年度簡字第6213號聲請人臺灣高雄地方法院檢察署檢察官被告甲○○○上列被告因違反動產擔保交易法案件，經檢察官聲請以簡易判決處刑（94年度偵字第19612號），本院判決如下：主文甲○○○動產擔保交易之債務人，意圖不法之利益，將標的物遷移，致生損害於債權人，處拘役伍拾日，如易科罰金，以佰元折算壹日。緩刑貳年。事實及理由一、本件除事實欄補充：「甲○○○尚積欠貸款本金新臺幣（下同）349,187元」外，其餘犯罪事實及證據均引用檢察官聲請簡易判決處刑書之記載（如附件）。二、核被告甲○○○所為，係違反動產擔保交易法第38條動產擔保交易之債務人，意圖不法之利益，將標的物遷移，致生損害於債權人罪。爰審酌被告在價金未付清前，即將標的物遷移，致告訴人台新國際商業銀行股份有限公司追索無著，且尚積欠告訴人349,187元，金額非微，迄今尚未與告訴人達成和解，賠償告訴人之損失，惟念及被告並無前科，有臺灣高等法院被告前案紀錄表在卷可憑，素行良好等一切情狀，量處如主文所示之刑，並諭知易科罰金之折算標準。末查被告前未曾受有期徒刑以上刑之宣告，有臺灣高等法院被告前案紀錄表在卷可憑，其因一時失慮，致觸犯本案犯行，經此次偵審之教訓，應無再犯之虞，本院認前開所宣告之刑，以暫不執行為適當，爰宣告緩刑2年，以啟自新。三、依刑事訴訟法第449條第1項前段、第3項、第454條第2項，動產擔保交易法第38條、刑法第11條前段、第41條第1項前段、第74條第1款，罰金罰鍰提高標準條例第1條前段、第2條，逕以簡易判決處如主文所示之刑。四、如不服本判決，得於判決書送達之日起10日內，以書狀敘明理由，向本院提出上訴。中華民國94年10月31日高雄簡易庭法官洪能超以上正本，係照原本作成，證明與原本無異。中華民國94年10月31日書記官曾小玲附錄本判決論罪之法條：動產擔保交易法第38條動產擔保交易之債務人，意圖不法之利益，將標的物遷移、出賣、出質、移轉、抵押或為其他處分，致生損害於債權人者，處3年以下有期徒刑、拘役或科或併科6000元以下之罰金。",
  "characters": {
    "judges": [
      "洪能超"
    ],
    "prosecutors": [

    ],
    "lawyers": [

    ],
    "clerks": [
      "曾小玲"
    ],
    "plaintiffs": [

    ],
    "defendants": [
      "甲○○○"
    ],
    "prosecutor_office": [
      "臺灣高雄地方法院檢察署檢察官"
    ],
    "creditors": [

    ],
    "debtors": [

    ],
    "judicial_associate_officer": [

    ]
  },
  "adjudged_at": "2005-10-31",
  "created_at": "2016-02-07 11:37:59",
  "updated_at": "2016-02-07 11:37:59"
}