{
  "identify": "PTD-94-交簡-609-20051031-1",
  "court": {
    "name": "臺灣屏東地方法院",
    "code": "PTD"
  },
  "division": {
    "name": "刑事",
    "code": "M"
  },
  "year": 94,
  "word": "交簡",
  "number": "609",
  "jcheck": "1",
  "reason": "公共危險",
  "content": "臺灣屏東地方法院刑事簡易判決         94年度交簡字第609號\n聲  請  人  臺灣屏東地方法院檢察署檢察官\n被      告  甲○○\n上列被告因公共危險案件，經檢察官聲請以簡易判決處刑（94年\n度偵字第3978號），本院判決如下：\n    主      文\n甲○○服用酒類，不能安全駕駛動力交通工具而駕駛，處有期徒\n刑月，如易科罰金，以佰元折算壹日。車號JY-2899 號（車\n身號碼UZZZ8CZSA079478 號）自用小客車沒收。\n    事實及理由\n一、甲○○明知酒精對人體中樞神經有抑制作用，酒後駕車極易\n    因身體協調功能降低、對突發狀況之反應能力減緩而發生危\n    險。其前於民國92年8 月23日凌晨，甫因酒後吐氣中酒精濃\n    度達每公升1.12毫克（1.12mg/L），已不能安全駕駛動力交\n    通工具而駕駛其所有之車號JY-2899 號自用小客車，在高雄\n    市○○區○○路、五福三路口肇事而遭查獲，經臺灣高雄地\n    方法院檢察署檢察官於92年9 月17日以92年度偵字第17743\n    號作成期間1 年之緩起訴處分確定，竟不知警惕，復於94年\n    6 月20日晚間8 時許，在屏東市某PUB 店內飲用瓶裝啤酒10\n    瓶以上後，仍駕駛其所有上開同一自用小客車上路，欲返回\n    位在高雄縣林園鄉之住處，旋於94年6 月21日凌晨1 時55分\n    許，由北往南沿屏東市○○路行經該路103 號，林明芳所有\n    之房屋前方時，因體內酒精作用致無法有效操控所駕車輛，\n    竟衝出路面邊線，自後方強力衝撞林明芳之女林美鳳所有並\n    停放該址門口路旁之車號Y7-0097 號自用小客車，旋又撞及\n    該址鐵捲門及大門牆柱後始停止，造成林美鳳所有上開自用\n    小客車向前彈出數公尺、車尾嚴重變形，林明芳所有上開房\n    屋大門牆柱受損、鐵捲門損壞不能使用。甲○○隨即向到場\n    處理之員警自首接受調查，並經測得吐氣中酒精濃度高達每\n    公升1.04毫克（1.04mg/L），顯已達不能安全駕駛動力交通\n    工具之程度。案經屏東縣警察局屏東分局報告臺灣屏東地方\n    法院檢察署檢察官偵查起訴。\n二、前揭酒後駕車失控衝撞路旁車輛及房屋之事實，除據被告甲\n    ○○於警詢及本院調查時自白不諱，並經證人林美鳳於警詢\n    中證述綦詳，復有道路交通事故調查報告(一)、(二)表、現場圖\n    、酒精濃度檢測單、刑法第185 條之3 案件測試觀察紀錄表\n    各1 份、現場及車損照片12幀在卷可稽，堪信為真。按酒精\n    對人體所生影響，於吐氣中酒精濃度達每公升0.25毫克時，\n    即已輕微中毒，而有輕度協調功能降低，是依道路交通安全\n    規則第114 條第2 款規定，汽車駕駛人飲酒後，吐氣中所含\n    酒精濃度逾每公升0.25毫克者，即不得駕車；若進而其濃度\n    達每公升0.55毫克、0.75毫克、0.85毫克以上者，肇事率猶\n    分別達到一般正常人之10倍、25倍、50倍之譜，此觀卷附臺\n    灣高等法院88年10月26日院賓文廉字第13407 號致所屬各\n    級法院函檢附法務部88年10月1 日法檢字第3641號函暨附\n    件研究報告及中央警察大學蔡中志教授製作之「酒精濃度與\n    肇事率之關係表」自明。被告甲○○為前揭駕駛行為後，不\n    僅經測得吐氣中酒精濃度達每公升1.04毫克，遠逾前述肇事\n    率為一般正常人50倍之標準，危險極高。其經承辦員警進行\n    行為測試觀察，亦呈現腳步不穩、手腳搖晃、語無倫次、含\n    糊不清、意識模糊等現象，有前引測試觀察紀錄表在卷可參\n    。今依卷附道路交通事故調查報告表、肇事現場圖、現場及\n    車損照片所示，上開事故發生時間固為雨天夜晚，然現場為\n    有照明、雙向各有3.5 公尺寬車道及1.5 公尺寬路肩各1 線\n    ，以柏油鋪設之市區道路○路面無缺陷、無障礙、光線、視\n    距良好之路段，詎被告甲○○行經現場時，竟衝出路面邊線\n    ，並穿越有相當寬度以為緩衝之路肩地帶而衝撞順向停放路\n    旁之自用小客車，猶強力撞及民宅大門及牆柱，然其在歷此\n    一連串狀況後，所駕上開車輛竟未遺留任何剎車、制動之痕\n    跡，是被告甲○○當時反應顯與一般正常人之駕駛作為迥異\n    ，其為前揭駕駛行為時，因體內酒精濃度作用致不能有效操\n    控所駕車輛，已達不能安全駕駛動力交通工具之程度等情，\n    堪予認定。今查，酒精對於人體中樞神經系統有抑制作用，\n    酒後從事駕駛行為極易因體內酒精作用致身體協調機能及對\n    外界事物之反應能力減弱而發生危險，每每造成重大交通事\n    故，嚴重危害公眾往來交通安全，乃政府近年來大力宣導禁\n    止並取締酒後駕車之行為，此依卷附個人資料為63年7 月16\n    日出生、具備大學畢業教育程度，並已進入社會工作多年，\n    以從事不動產仲介為業，且1 年多前甫因重醉駕車肇事，涉\n    犯公共危險罪嫌而經檢察官予以緩起訴處分之被告甲○○所\n    知之甚明者，是本件被告犯罪事證已臻明確，應依法論科。\n三、查汽車係以汽油內燃機為動力，並以行駛公共道路為主要功\n    能之車輛，為刑法第185 條之3 規定之動力交通工具。核被\n    告甲○○所為，係犯刑法第185 條之3 服用酒類致不能安全\n    駕駛動力交通工具而駕駛之公共危險罪。又被告甲○○犯罪\n    後於員警到場處理時，主動向警方自首並接受裁判，有屏東\n    縣警察局道路交通事故肇事人自首情形紀錄表在卷可憑，應\n    依刑法第62條前段規定，減輕其刑。爰審酌被告甲○○之年\n    齡、品行、智識程度、犯罪時體內酒精濃度之數值、犯罪所\n    生之損害，對於公共安全造成危害之程度：被告甲○○為63\n    年7 月16日出生、具備大學畢業教育程度、現從事不動產仲\n    介為業之人，有年籍資料在卷可按，並據其於本院訊問時自\n    承在卷，前揭行為時已逾而立；其前於92年8 月23日凌晨，\n    因酒後吐氣中酒精濃度達每公升1.12毫克，已不能安全駕駛\n    動力交通工具而駕駛車輛肇事，甫經臺灣高雄地方法院檢察\n    署檢察官於92年9 月17日以92年度偵字第17743 號作成期間\n    1 年之緩起訴處分確定，有臺灣高等法院被告前案紀錄表、\n    臺灣屏東地方法院檢察署刑案資料查註紀錄表及臺灣高雄地\n    方法院檢察署檢察官緩起訴處分書各1 份在卷可按，竟不知\n    警惕，於本件犯罪前飲用瓶裝啤酒10瓶以上，吐氣中酒精濃\n    度高達1.04毫克，竟仍輕率駕駛車輛上路，欲前往之目的地\n    猶在數10公里外之高雄縣林園鄉，影響之大，足徵其目無法\n    紀、全不在乎他人生命、身體及公共交通往來安全之態度；\n    又其所駕動力交通工具為機械推力良好之自用小客車，犯罪\n    時間為雨天夜晚，地點為市區時有人車往來之路段，對於法\n    益產生危險之程度，與其犯罪除形成公眾交通往來之危險，\n    並已衍生事故，對法益造成實害，及其犯罪後尚能坦承犯行\n    ，態度尚可等一切情狀，量處如主文所示之刑，並諭知易科\n    罰金之折算標準，以資儆懲。\n四、按刑法第185 條之3 所規定公共危險罪，係以行為人在服用\n    毒品、麻醉藥品、酒類或其他相類之物致不能安全駕駛動力\n    交通工具之情狀下，有駕駛動力交通工具之行為為其構成要\n    件。學說上固有以此為「原因自由行為」之規定者，惟查，\n    學理上所稱「原因自由行為」，係針對傳統理論面對犯罪行\n    為之成立必須行為人於行為時具備責任能力為前提，無法解\n    決因故意或過失使自己陷於無責任能力或減輕責任能力狀態\n    下實現構成要件等犯罪類型之窘境，而提出歸責之基礎，認\n    為行為人因可歸責於自己之事由，致自陷於精神障礙狀態，\n    進而在心神喪失或精神耗弱狀態中實現不法構成要件者，應\n    將其行為之評價提前至造成其嗣後陷於責任能力有欠缺狀態\n    之原因行為階段，亦即，認為此種犯罪類型實含有前後相續\n    而不可分之「原因階段」與「行為階段」，刑法對於此等行\n    為之評價，不應只限於行為階段，而應同時兼顧原因階段。\n    然原因自由行為之態樣，其「行為階段」所實施者，原屬刑\n    法分則所規定獨立之犯罪類型，僅因特定個案中，行為人稍\n    早另有自陷於心神喪失或精神耗弱狀態之行為，乃將該「原\n    因行為」一併納入評價其罪責之依據，尚非在原條文外創設\n    另一刑罰規範，遑論將其前行為當然評價為犯罪構成要件行\n    為。刑法第185 條之3 ，就其條文結構之形式而言，固亦有\n    自陷於不能安全駕駛動力交通工具之原因階段，及駕駛動力\n    交通工具等先後兩部分之要件，惟姑不論其前階段所稱「不\n    能安全駕駛動力交通工具」是否等同於心神喪失或精神耗弱\n    等責任能力有欠缺之狀態，已非無疑；而行為人單有後階段\n    所規定即單純駕駛汽車之舉，亦非刑法所規定之犯罪行為，\n    與前開「原因自由行為」之類型迥然有別。縱依原因自由行\n    為之理論，原僅在於解決行為人為後階段行為時，客觀上係\n    處於欠缺完全責任能力之狀態，乃提前將其先前之行為一併\n    納入評價，亦非逕以其自陷於心神喪失或精神耗弱狀態之行\n    為為犯罪構成要件之行為，矧刑法第185 條之3 公共危險罪\n    之規定，原不以服用酒類等行為為其歸責之本旨，蓋以飲用\n    酒類原屬法律所容許之社會行為，而服用毒品、麻醉藥品等\n    行為，縱為法所禁止，其不法內涵要亦已為毒品危害防制條\n    例等相關刑罰法律所規範、處罰，均非本條規範目的所評價\n    、非難之對象，猶非居於本條構成要件行為之地位，而屬法\n    定構成要件特別行為情狀之一部。申言之，刑法第185 條之\n    3 係以行為人處於因服用毒品、麻醉藥品、酒類或其他相類\n    之物所造成不能安全駕駛動力交通工具之「特別行為情狀」\n    下，而有駕駛動力交通工具之「構成要件行為」者，為其規\n    範之內涵。從而，本條既以特定情狀下所為駕駛行為為犯罪\n    構成要件行為，則行為人在該情狀下用以供駕駛行為使用之\n    動力交通工具，即為其實施本條犯罪行為所用之物。茲前揭\n    車號JY-2899 號自用小客車為被告甲○○所有、自83年3 月\n    30 日 發照至前揭事故發生時出廠已逾10年之老舊車輛，除\n    據被告甲○○自承在卷（詳本院卷94年10月5 日訊問筆錄）\n    ，復有公路監理查註紀錄表、車籍作業系統查詢認可資料各\n    1 紙附卷可參，依前開論述並為被告甲○○供本件犯罪所用\n    之物，自屬刑法第38條第1 項第2 款所規定得為沒收之物，\n    本院90年度3 月份刑庭會議決議同此意旨，殊堪贊同。今以\n    被告甲○○在本件犯行前，於92年8 月23日凌晨，因酒後吐\n    氣中酒精濃度達每公升1.12毫克，已不能安全駕駛動力交通\n    工具而駕駛前開其所有之車號JY-2899 號自用小客車，在高\n    雄市○○街道前金區○○路、五福三路口肇事而遭查獲，雖\n    經臺灣高雄地方法院檢察署檢察官於92年9 月17日以92年度\n    偵字第17743 號作成期間1 年之緩起訴處分確定，竟無動於\n    衷，於前開緩起訴處分期間甫屆滿未及1 年，旋又固態復萌\n    ，以同一車輛即車齡逾10年以上，依一般耐用年限、折舊公\n    式計算幾無殘值之自用小客車再犯本件犯行，酒精濃度之高\n    ，行駛路段之交通情形及計劃前往目的地之遠，甚至已嚴重\n    衝撞其他車輛及民宅，對公眾往來秩序及不特定用路人之生\n    命、財產安全所構成之威脅甚鉅，是依其前揭犯行對法益侵\n    害之強度、其反覆實施同類犯行之主觀惡性及素行對法益隱\n    存之危險性，考量刑法一般預防及特別預防之效果，審酌諭\n    知從刑之適當性、必要性及權衡法益之合比例性，併就其所\n    有供前揭犯罪使用之車號JY-2899 號自用小客車（車身號碼\n    UZZZ8CZSA079478號）為沒收之諭知。\n五、據上論斷，應依刑事訴訟法第273 條之1 第1 項、第299 條\n    第1 項前段，刑法第185 條之3 、第62條前段、第41條第1\n    項前段、第38條第1 項第2 款，罰金罰鍰提高標準條例第2\n    條，逕以簡易判決判處如主文所示之刑。\n六、如不服本判決，得自收受送達之日起10日內，向本院提起上\n    訴。\n中    華    民    國    94    年    10    月    31    日\n                  交通法庭    法  官  陳松檀\n以上正本證明與原本無異。\n如不服本判決應於收受本判決送達後十日內向本院提出上訴書狀\n，其未敘述上訴理由者，並得於提起上訴後十日內向本院補提理\n由書狀（均須按他造當事人之人數附繕本）「切勿逕送上級法院\n」\n中    華    民    國    94    年    11    月    3     日\n                              書記官  魏慧夷\n附錄本判決論罪科刑法條全文\n刑法第185條之3\n服用毒品、麻醉藥品、酒類或其他相類之物，不能安全駕駛動力\n交通工具而駕駛者，處一年以下有期徒刑、拘役或三萬元以下罰\n金。\n",
  "structure": {
    "main": "甲○○服用酒類，不能安全駕駛動力交通工具而駕駛，處有期徒\n刑月，如易科罰金，以佰元折算壹日。車號JY-2899 號（車\n身號碼UZZZ8CZSA079478 號）自用小客車沒收。",
    "fact": "一、甲○○明知酒精對人體中樞神經有抑制作用，酒後駕車極易\n    因身體協調功能降低、對突發狀況之反應能力減緩而發生危\n    險。其前於民國92年8 月23日凌晨，甫因酒後吐氣中酒精濃\n    度達每公升1.12毫克（1.12mg/L），已不能安全駕駛動力交\n    通工具而駕駛其所有之車號JY-2899 號自用小客車，在高雄\n    市○○區○○路、五福三路口肇事而遭查獲，經臺灣高雄地\n    方法院檢察署檢察官於92年9 月17日以92年度偵字第17743\n    號作成期間1 年之緩起訴處分確定，竟不知警惕，復於94年\n    6 月20日晚間8 時許，在屏東市某PUB 店內飲用瓶裝啤酒10\n    瓶以上後，仍駕駛其所有上開同一自用小客車上路，欲返回\n    位在高雄縣林園鄉之住處，旋於94年6 月21日凌晨1 時55分\n    許，由北往南沿屏東市○○路行經該路103 號，林明芳所有\n    之房屋前方時，因體內酒精作用致無法有效操控所駕車輛，\n    竟衝出路面邊線，自後方強力衝撞林明芳之女林美鳳所有並\n    停放該址門口路旁之車號Y7-0097 號自用小客車，旋又撞及\n    該址鐵捲門及大門牆柱後始停止，造成林美鳳所有上開自用\n    小客車向前彈出數公尺、車尾嚴重變形，林明芳所有上開房\n    屋大門牆柱受損、鐵捲門損壞不能使用。甲○○隨即向到場\n    處理之員警自首接受調查，並經測得吐氣中酒精濃度高達每\n    公升1.04毫克（1.04mg/L），顯已達不能安全駕駛動力交通\n    工具之程度。案經屏東縣警察局屏東分局報告臺灣屏東地方\n    法院檢察署檢察官偵查起訴。\n二、前揭酒後駕車失控衝撞路旁車輛及房屋之事實，除據被告甲\n    ○○於警詢及本院調查時自白不諱，並經證人林美鳳於警詢\n    中證述綦詳，復有道路交通事故調查報告(一)、(二)表、現場圖\n    、酒精濃度檢測單、刑法第185 條之3 案件測試觀察紀錄表\n    各1 份、現場及車損照片12幀在卷可稽，堪信為真。按酒精\n    對人體所生影響，於吐氣中酒精濃度達每公升0.25毫克時，\n    即已輕微中毒，而有輕度協調功能降低，是依道路交通安全\n    規則第114 條第2 款規定，汽車駕駛人飲酒後，吐氣中所含\n    酒精濃度逾每公升0.25毫克者，即不得駕車；若進而其濃度\n    達每公升0.55毫克、0.75毫克、0.85毫克以上者，肇事率猶\n    分別達到一般正常人之10倍、25倍、50倍之譜，此觀卷附臺\n    灣高等法院88年10月26日院賓文廉字第13407 號致所屬各\n    級法院函檢附法務部88年10月1 日法檢字第3641號函暨附\n    件研究報告及中央警察大學蔡中志教授製作之「酒精濃度與\n    肇事率之關係表」自明。被告甲○○為前揭駕駛行為後，不\n    僅經測得吐氣中酒精濃度達每公升1.04毫克，遠逾前述肇事\n    率為一般正常人50倍之標準，危險極高。其經承辦員警進行\n    行為測試觀察，亦呈現腳步不穩、手腳搖晃、語無倫次、含\n    糊不清、意識模糊等現象，有前引測試觀察紀錄表在卷可參\n    。今依卷附道路交通事故調查報告表、肇事現場圖、現場及\n    車損照片所示，上開事故發生時間固為雨天夜晚，然現場為\n    有照明、雙向各有3.5 公尺寬車道及1.5 公尺寬路肩各1 線\n    ，以柏油鋪設之市區道路○路面無缺陷、無障礙、光線、視\n    距良好之路段，詎被告甲○○行經現場時，竟衝出路面邊線\n    ，並穿越有相當寬度以為緩衝之路肩地帶而衝撞順向停放路\n    旁之自用小客車，猶強力撞及民宅大門及牆柱，然其在歷此\n    一連串狀況後，所駕上開車輛竟未遺留任何剎車、制動之痕\n    跡，是被告甲○○當時反應顯與一般正常人之駕駛作為迥異\n    ，其為前揭駕駛行為時，因體內酒精濃度作用致不能有效操\n    控所駕車輛，已達不能安全駕駛動力交通工具之程度等情，\n    堪予認定。今查，酒精對於人體中樞神經系統有抑制作用，\n    酒後從事駕駛行為極易因體內酒精作用致身體協調機能及對\n    外界事物之反應能力減弱而發生危險，每每造成重大交通事\n    故，嚴重危害公眾往來交通安全，乃政府近年來大力宣導禁\n    止並取締酒後駕車之行為，此依卷附個人資料為63年7 月16\n    日出生、具備大學畢業教育程度，並已進入社會工作多年，\n    以從事不動產仲介為業，且1 年多前甫因重醉駕車肇事，涉\n    犯公共危險罪嫌而經檢察官予以緩起訴處分之被告甲○○所\n    知之甚明者，是本件被告犯罪事證已臻明確，應依法論科。\n三、查汽車係以汽油內燃機為動力，並以行駛公共道路為主要功\n    能之車輛，為刑法第185 條之3 規定之動力交通工具。核被\n    告甲○○所為，係犯刑法第185 條之3 服用酒類致不能安全\n    駕駛動力交通工具而駕駛之公共危險罪。又被告甲○○犯罪\n    後於員警到場處理時，主動向警方自首並接受裁判，有屏東\n    縣警察局道路交通事故肇事人自首情形紀錄表在卷可憑，應\n    依刑法第62條前段規定，減輕其刑。爰審酌被告甲○○之年\n    齡、品行、智識程度、犯罪時體內酒精濃度之數值、犯罪所\n    生之損害，對於公共安全造成危害之程度：被告甲○○為63\n    年7 月16日出生、具備大學畢業教育程度、現從事不動產仲\n    介為業之人，有年籍資料在卷可按，並據其於本院訊問時自\n    承在卷，前揭行為時已逾而立；其前於92年8 月23日凌晨，\n    因酒後吐氣中酒精濃度達每公升1.12毫克，已不能安全駕駛\n    動力交通工具而駕駛車輛肇事，甫經臺灣高雄地方法院檢察\n    署檢察官於92年9 月17日以92年度偵字第17743 號作成期間\n    1 年之緩起訴處分確定，有臺灣高等法院被告前案紀錄表、\n    臺灣屏東地方法院檢察署刑案資料查註紀錄表及臺灣高雄地\n    方法院檢察署檢察官緩起訴處分書各1 份在卷可按，竟不知\n    警惕，於本件犯罪前飲用瓶裝啤酒10瓶以上，吐氣中酒精濃\n    度高達1.04毫克，竟仍輕率駕駛車輛上路，欲前往之目的地\n    猶在數10公里外之高雄縣林園鄉，影響之大，足徵其目無法\n    紀、全不在乎他人生命、身體及公共交通往來安全之態度；\n    又其所駕動力交通工具為機械推力良好之自用小客車，犯罪\n    時間為雨天夜晚，地點為市區時有人車往來之路段，對於法\n    益產生危險之程度，與其犯罪除形成公眾交通往來之危險，\n    並已衍生事故，對法益造成實害，及其犯罪後尚能坦承犯行\n    ，態度尚可等一切情狀，量處如主文所示之刑，並諭知易科\n    罰金之折算標準，以資儆懲。\n四、按刑法第185 條之3 所規定公共危險罪，係以行為人在服用\n    毒品、麻醉藥品、酒類或其他相類之物致不能安全駕駛動力\n    交通工具之情狀下，有駕駛動力交通工具之行為為其構成要\n    件。學說上固有以此為「原因自由行為」之規定者，惟查，\n    學理上所稱「原因自由行為」，係針對傳統理論面對犯罪行\n    為之成立必須行為人於行為時具備責任能力為前提，無法解\n    決因故意或過失使自己陷於無責任能力或減輕責任能力狀態\n    下實現構成要件等犯罪類型之窘境，而提出歸責之基礎，認\n    為行為人因可歸責於自己之事由，致自陷於精神障礙狀態，\n    進而在心神喪失或精神耗弱狀態中實現不法構成要件者，應\n    將其行為之評價提前至造成其嗣後陷於責任能力有欠缺狀態\n    之原因行為階段，亦即，認為此種犯罪類型實含有前後相續\n    而不可分之「原因階段」與「行為階段」，刑法對於此等行\n    為之評價，不應只限於行為階段，而應同時兼顧原因階段。\n    然原因自由行為之態樣，其「行為階段」所實施者，原屬刑\n    法分則所規定獨立之犯罪類型，僅因特定個案中，行為人稍\n    早另有自陷於心神喪失或精神耗弱狀態之行為，乃將該「原\n    因行為」一併納入評價其罪責之依據，尚非在原條文外創設\n    另一刑罰規範，遑論將其前行為當然評價為犯罪構成要件行\n    為。刑法第185 條之3 ，就其條文結構之形式而言，固亦有\n    自陷於不能安全駕駛動力交通工具之原因階段，及駕駛動力\n    交通工具等先後兩部分之要件，惟姑不論其前階段所稱「不\n    能安全駕駛動力交通工具」是否等同於心神喪失或精神耗弱\n    等責任能力有欠缺之狀態，已非無疑；而行為人單有後階段\n    所規定即單純駕駛汽車之舉，亦非刑法所規定之犯罪行為，\n    與前開「原因自由行為」之類型迥然有別。縱依原因自由行\n    為之理論，原僅在於解決行為人為後階段行為時，客觀上係\n    處於欠缺完全責任能力之狀態，乃提前將其先前之行為一併\n    納入評價，亦非逕以其自陷於心神喪失或精神耗弱狀態之行\n    為為犯罪構成要件之行為，矧刑法第185 條之3 公共危險罪\n    之規定，原不以服用酒類等行為為其歸責之本旨，蓋以飲用\n    酒類原屬法律所容許之社會行為，而服用毒品、麻醉藥品等\n    行為，縱為法所禁止，其不法內涵要亦已為毒品危害防制條\n    例等相關刑罰法律所規範、處罰，均非本條規範目的所評價\n    、非難之對象，猶非居於本條構成要件行為之地位，而屬法\n    定構成要件特別行為情狀之一部。申言之，刑法第185 條之\n    3 係以行為人處於因服用毒品、麻醉藥品、酒類或其他相類\n    之物所造成不能安全駕駛動力交通工具之「特別行為情狀」\n    下，而有駕駛動力交通工具之「構成要件行為」者，為其規\n    範之內涵。從而，本條既以特定情狀下所為駕駛行為為犯罪\n    構成要件行為，則行為人在該情狀下用以供駕駛行為使用之\n    動力交通工具，即為其實施本條犯罪行為所用之物。茲前揭\n    車號JY-2899 號自用小客車為被告甲○○所有、自83年3 月\n    30 日 發照至前揭事故發生時出廠已逾10年之老舊車輛，除\n    據被告甲○○自承在卷（詳本院卷94年10月5 日訊問筆錄）\n    ，復有公路監理查註紀錄表、車籍作業系統查詢認可資料各\n    1 紙附卷可參，依前開論述並為被告甲○○供本件犯罪所用\n    之物，自屬刑法第38條第1 項第2 款所規定得為沒收之物，\n    本院90年度3 月份刑庭會議決議同此意旨，殊堪贊同。今以\n    被告甲○○在本件犯行前，於92年8 月23日凌晨，因酒後吐\n    氣中酒精濃度達每公升1.12毫克，已不能安全駕駛動力交通\n    工具而駕駛前開其所有之車號JY-2899 號自用小客車，在高\n    雄市○○街道前金區○○路、五福三路口肇事而遭查獲，雖\n    經臺灣高雄地方法院檢察署檢察官於92年9 月17日以92年度\n    偵字第17743 號作成期間1 年之緩起訴處分確定，竟無動於\n    衷，於前開緩起訴處分期間甫屆滿未及1 年，旋又固態復萌\n    ，以同一車輛即車齡逾10年以上，依一般耐用年限、折舊公\n    式計算幾無殘值之自用小客車再犯本件犯行，酒精濃度之高\n    ，行駛路段之交通情形及計劃前往目的地之遠，甚至已嚴重\n    衝撞其他車輛及民宅，對公眾往來秩序及不特定用路人之生\n    命、財產安全所構成之威脅甚鉅，是依其前揭犯行對法益侵\n    害之強度、其反覆實施同類犯行之主觀惡性及素行對法益隱\n    存之危險性，考量刑法一般預防及特別預防之效果，審酌諭\n    知從刑之適當性、必要性及權衡法益之合比例性，併就其所\n    有供前揭犯罪使用之車號JY-2899 號自用小客車（車身號碼\n    UZZZ8CZSA079478號）為沒收之諭知。\n五、據上論斷，應依刑事訴訟法第273 條之1 第1 項、第299 條\n    第1 項前段，刑法第185 條之3 、第62條前段、第41條第1\n    項前段、第38條第1 項第2 款，罰金罰鍰提高標準條例第2\n    條，逕以簡易判決判處如主文所示之刑。\n六、如不服本判決，得自收受送達之日起10日內，向本院提起上\n    訴。",
    "reason": "一、甲○○明知酒精對人體中樞神經有抑制作用，酒後駕車極易\n    因身體協調功能降低、對突發狀況之反應能力減緩而發生危\n    險。其前於民國92年8 月23日凌晨，甫因酒後吐氣中酒精濃\n    度達每公升1.12毫克（1.12mg/L），已不能安全駕駛動力交\n    通工具而駕駛其所有之車號JY-2899 號自用小客車，在高雄\n    市○○區○○路、五福三路口肇事而遭查獲，經臺灣高雄地\n    方法院檢察署檢察官於92年9 月17日以92年度偵字第17743\n    號作成期間1 年之緩起訴處分確定，竟不知警惕，復於94年\n    6 月20日晚間8 時許，在屏東市某PUB 店內飲用瓶裝啤酒10\n    瓶以上後，仍駕駛其所有上開同一自用小客車上路，欲返回\n    位在高雄縣林園鄉之住處，旋於94年6 月21日凌晨1 時55分\n    許，由北往南沿屏東市○○路行經該路103 號，林明芳所有\n    之房屋前方時，因體內酒精作用致無法有效操控所駕車輛，\n    竟衝出路面邊線，自後方強力衝撞林明芳之女林美鳳所有並\n    停放該址門口路旁之車號Y7-0097 號自用小客車，旋又撞及\n    該址鐵捲門及大門牆柱後始停止，造成林美鳳所有上開自用\n    小客車向前彈出數公尺、車尾嚴重變形，林明芳所有上開房\n    屋大門牆柱受損、鐵捲門損壞不能使用。甲○○隨即向到場\n    處理之員警自首接受調查，並經測得吐氣中酒精濃度高達每\n    公升1.04毫克（1.04mg/L），顯已達不能安全駕駛動力交通\n    工具之程度。案經屏東縣警察局屏東分局報告臺灣屏東地方\n    法院檢察署檢察官偵查起訴。\n二、前揭酒後駕車失控衝撞路旁車輛及房屋之事實，除據被告甲\n    ○○於警詢及本院調查時自白不諱，並經證人林美鳳於警詢\n    中證述綦詳，復有道路交通事故調查報告(一)、(二)表、現場圖\n    、酒精濃度檢測單、刑法第185 條之3 案件測試觀察紀錄表\n    各1 份、現場及車損照片12幀在卷可稽，堪信為真。按酒精\n    對人體所生影響，於吐氣中酒精濃度達每公升0.25毫克時，\n    即已輕微中毒，而有輕度協調功能降低，是依道路交通安全\n    規則第114 條第2 款規定，汽車駕駛人飲酒後，吐氣中所含\n    酒精濃度逾每公升0.25毫克者，即不得駕車；若進而其濃度\n    達每公升0.55毫克、0.75毫克、0.85毫克以上者，肇事率猶\n    分別達到一般正常人之10倍、25倍、50倍之譜，此觀卷附臺\n    灣高等法院88年10月26日院賓文廉字第13407 號致所屬各\n    級法院函檢附法務部88年10月1 日法檢字第3641號函暨附\n    件研究報告及中央警察大學蔡中志教授製作之「酒精濃度與\n    肇事率之關係表」自明。被告甲○○為前揭駕駛行為後，不\n    僅經測得吐氣中酒精濃度達每公升1.04毫克，遠逾前述肇事\n    率為一般正常人50倍之標準，危險極高。其經承辦員警進行\n    行為測試觀察，亦呈現腳步不穩、手腳搖晃、語無倫次、含\n    糊不清、意識模糊等現象，有前引測試觀察紀錄表在卷可參\n    。今依卷附道路交通事故調查報告表、肇事現場圖、現場及\n    車損照片所示，上開事故發生時間固為雨天夜晚，然現場為\n    有照明、雙向各有3.5 公尺寬車道及1.5 公尺寬路肩各1 線\n    ，以柏油鋪設之市區道路○路面無缺陷、無障礙、光線、視\n    距良好之路段，詎被告甲○○行經現場時，竟衝出路面邊線\n    ，並穿越有相當寬度以為緩衝之路肩地帶而衝撞順向停放路\n    旁之自用小客車，猶強力撞及民宅大門及牆柱，然其在歷此\n    一連串狀況後，所駕上開車輛竟未遺留任何剎車、制動之痕\n    跡，是被告甲○○當時反應顯與一般正常人之駕駛作為迥異\n    ，其為前揭駕駛行為時，因體內酒精濃度作用致不能有效操\n    控所駕車輛，已達不能安全駕駛動力交通工具之程度等情，\n    堪予認定。今查，酒精對於人體中樞神經系統有抑制作用，\n    酒後從事駕駛行為極易因體內酒精作用致身體協調機能及對\n    外界事物之反應能力減弱而發生危險，每每造成重大交通事\n    故，嚴重危害公眾往來交通安全，乃政府近年來大力宣導禁\n    止並取締酒後駕車之行為，此依卷附個人資料為63年7 月16\n    日出生、具備大學畢業教育程度，並已進入社會工作多年，\n    以從事不動產仲介為業，且1 年多前甫因重醉駕車肇事，涉\n    犯公共危險罪嫌而經檢察官予以緩起訴處分之被告甲○○所\n    知之甚明者，是本件被告犯罪事證已臻明確，應依法論科。\n三、查汽車係以汽油內燃機為動力，並以行駛公共道路為主要功\n    能之車輛，為刑法第185 條之3 規定之動力交通工具。核被\n    告甲○○所為，係犯刑法第185 條之3 服用酒類致不能安全\n    駕駛動力交通工具而駕駛之公共危險罪。又被告甲○○犯罪\n    後於員警到場處理時，主動向警方自首並接受裁判，有屏東\n    縣警察局道路交通事故肇事人自首情形紀錄表在卷可憑，應\n    依刑法第62條前段規定，減輕其刑。爰審酌被告甲○○之年\n    齡、品行、智識程度、犯罪時體內酒精濃度之數值、犯罪所\n    生之損害，對於公共安全造成危害之程度：被告甲○○為63\n    年7 月16日出生、具備大學畢業教育程度、現從事不動產仲\n    介為業之人，有年籍資料在卷可按，並據其於本院訊問時自\n    承在卷，前揭行為時已逾而立；其前於92年8 月23日凌晨，\n    因酒後吐氣中酒精濃度達每公升1.12毫克，已不能安全駕駛\n    動力交通工具而駕駛車輛肇事，甫經臺灣高雄地方法院檢察\n    署檢察官於92年9 月17日以92年度偵字第17743 號作成期間\n    1 年之緩起訴處分確定，有臺灣高等法院被告前案紀錄表、\n    臺灣屏東地方法院檢察署刑案資料查註紀錄表及臺灣高雄地\n    方法院檢察署檢察官緩起訴處分書各1 份在卷可按，竟不知\n    警惕，於本件犯罪前飲用瓶裝啤酒10瓶以上，吐氣中酒精濃\n    度高達1.04毫克，竟仍輕率駕駛車輛上路，欲前往之目的地\n    猶在數10公里外之高雄縣林園鄉，影響之大，足徵其目無法\n    紀、全不在乎他人生命、身體及公共交通往來安全之態度；\n    又其所駕動力交通工具為機械推力良好之自用小客車，犯罪\n    時間為雨天夜晚，地點為市區時有人車往來之路段，對於法\n    益產生危險之程度，與其犯罪除形成公眾交通往來之危險，\n    並已衍生事故，對法益造成實害，及其犯罪後尚能坦承犯行\n    ，態度尚可等一切情狀，量處如主文所示之刑，並諭知易科\n    罰金之折算標準，以資儆懲。\n四、按刑法第185 條之3 所規定公共危險罪，係以行為人在服用\n    毒品、麻醉藥品、酒類或其他相類之物致不能安全駕駛動力\n    交通工具之情狀下，有駕駛動力交通工具之行為為其構成要\n    件。學說上固有以此為「原因自由行為」之規定者，惟查，\n    學理上所稱「原因自由行為」，係針對傳統理論面對犯罪行\n    為之成立必須行為人於行為時具備責任能力為前提，無法解\n    決因故意或過失使自己陷於無責任能力或減輕責任能力狀態\n    下實現構成要件等犯罪類型之窘境，而提出歸責之基礎，認\n    為行為人因可歸責於自己之事由，致自陷於精神障礙狀態，\n    進而在心神喪失或精神耗弱狀態中實現不法構成要件者，應\n    將其行為之評價提前至造成其嗣後陷於責任能力有欠缺狀態\n    之原因行為階段，亦即，認為此種犯罪類型實含有前後相續\n    而不可分之「原因階段」與「行為階段」，刑法對於此等行\n    為之評價，不應只限於行為階段，而應同時兼顧原因階段。\n    然原因自由行為之態樣，其「行為階段」所實施者，原屬刑\n    法分則所規定獨立之犯罪類型，僅因特定個案中，行為人稍\n    早另有自陷於心神喪失或精神耗弱狀態之行為，乃將該「原\n    因行為」一併納入評價其罪責之依據，尚非在原條文外創設\n    另一刑罰規範，遑論將其前行為當然評價為犯罪構成要件行\n    為。刑法第185 條之3 ，就其條文結構之形式而言，固亦有\n    自陷於不能安全駕駛動力交通工具之原因階段，及駕駛動力\n    交通工具等先後兩部分之要件，惟姑不論其前階段所稱「不\n    能安全駕駛動力交通工具」是否等同於心神喪失或精神耗弱\n    等責任能力有欠缺之狀態，已非無疑；而行為人單有後階段\n    所規定即單純駕駛汽車之舉，亦非刑法所規定之犯罪行為，\n    與前開「原因自由行為」之類型迥然有別。縱依原因自由行\n    為之理論，原僅在於解決行為人為後階段行為時，客觀上係\n    處於欠缺完全責任能力之狀態，乃提前將其先前之行為一併\n    納入評價，亦非逕以其自陷於心神喪失或精神耗弱狀態之行\n    為為犯罪構成要件之行為，矧刑法第185 條之3 公共危險罪\n    之規定，原不以服用酒類等行為為其歸責之本旨，蓋以飲用\n    酒類原屬法律所容許之社會行為，而服用毒品、麻醉藥品等\n    行為，縱為法所禁止，其不法內涵要亦已為毒品危害防制條\n    例等相關刑罰法律所規範、處罰，均非本條規範目的所評價\n    、非難之對象，猶非居於本條構成要件行為之地位，而屬法\n    定構成要件特別行為情狀之一部。申言之，刑法第185 條之\n    3 係以行為人處於因服用毒品、麻醉藥品、酒類或其他相類\n    之物所造成不能安全駕駛動力交通工具之「特別行為情狀」\n    下，而有駕駛動力交通工具之「構成要件行為」者，為其規\n    範之內涵。從而，本條既以特定情狀下所為駕駛行為為犯罪\n    構成要件行為，則行為人在該情狀下用以供駕駛行為使用之\n    動力交通工具，即為其實施本條犯罪行為所用之物。茲前揭\n    車號JY-2899 號自用小客車為被告甲○○所有、自83年3 月\n    30 日 發照至前揭事故發生時出廠已逾10年之老舊車輛，除\n    據被告甲○○自承在卷（詳本院卷94年10月5 日訊問筆錄）\n    ，復有公路監理查註紀錄表、車籍作業系統查詢認可資料各\n    1 紙附卷可參，依前開論述並為被告甲○○供本件犯罪所用\n    之物，自屬刑法第38條第1 項第2 款所規定得為沒收之物，\n    本院90年度3 月份刑庭會議決議同此意旨，殊堪贊同。今以\n    被告甲○○在本件犯行前，於92年8 月23日凌晨，因酒後吐\n    氣中酒精濃度達每公升1.12毫克，已不能安全駕駛動力交通\n    工具而駕駛前開其所有之車號JY-2899 號自用小客車，在高\n    雄市○○街道前金區○○路、五福三路口肇事而遭查獲，雖\n    經臺灣高雄地方法院檢察署檢察官於92年9 月17日以92年度\n    偵字第17743 號作成期間1 年之緩起訴處分確定，竟無動於\n    衷，於前開緩起訴處分期間甫屆滿未及1 年，旋又固態復萌\n    ，以同一車輛即車齡逾10年以上，依一般耐用年限、折舊公\n    式計算幾無殘值之自用小客車再犯本件犯行，酒精濃度之高\n    ，行駛路段之交通情形及計劃前往目的地之遠，甚至已嚴重\n    衝撞其他車輛及民宅，對公眾往來秩序及不特定用路人之生\n    命、財產安全所構成之威脅甚鉅，是依其前揭犯行對法益侵\n    害之強度、其反覆實施同類犯行之主觀惡性及素行對法益隱\n    存之危險性，考量刑法一般預防及特別預防之效果，審酌諭\n    知從刑之適當性、必要性及權衡法益之合比例性，併就其所\n    有供前揭犯罪使用之車號JY-2899 號自用小客車（車身號碼\n    UZZZ8CZSA079478號）為沒收之諭知。\n五、據上論斷，應依刑事訴訟法第273 條之1 第1 項、第299 條\n    第1 項前段，刑法第185 條之3 、第62條前段、第41條第1\n    項前段、第38條第1 項第2 款，罰金罰鍰提高標準條例第2\n    條，逕以簡易判決判處如主文所示之刑。\n六、如不服本判決，得自收受送達之日起10日內，向本院提起上\n    訴。"
  },
  "search": "臺灣屏東地方法院刑事簡易判決94年度交簡字第609號聲請人臺灣屏東地方法院檢察署檢察官被告甲○○上列被告因公共危險案件，經檢察官聲請以簡易判決處刑（94年度偵字第3978號），本院判決如下：主文甲○○服用酒類，不能安全駕駛動力交通工具而駕駛，處有期徒刑月，如易科罰金，以佰元折算壹日。車號JY-2899號（車身號碼UZZZ8CZSA079478號）自用小客車沒收。事實及理由一、甲○○明知酒精對人體中樞神經有抑制作用，酒後駕車極易因身體協調功能降低、對突發狀況之反應能力減緩而發生危險。其前於民國92年8月23日凌晨，甫因酒後吐氣中酒精濃度達每公升1.12毫克（1.12mg/L），已不能安全駕駛動力交通工具而駕駛其所有之車號JY-2899號自用小客車，在高雄市○○區○○路、五福三路口肇事而遭查獲，經臺灣高雄地方法院檢察署檢察官於92年9月17日以92年度偵字第17743號作成期間1年之緩起訴處分確定，竟不知警惕，復於94年6月20日晚間8時許，在屏東市某PUB店內飲用瓶裝啤酒10瓶以上後，仍駕駛其所有上開同一自用小客車上路，欲返回位在高雄縣林園鄉之住處，旋於94年6月21日凌晨1時55分許，由北往南沿屏東市○○路行經該路103號，林明芳所有之房屋前方時，因體內酒精作用致無法有效操控所駕車輛，竟衝出路面邊線，自後方強力衝撞林明芳之女林美鳳所有並停放該址門口路旁之車號Y7-0097號自用小客車，旋又撞及該址鐵捲門及大門牆柱後始停止，造成林美鳳所有上開自用小客車向前彈出數公尺、車尾嚴重變形，林明芳所有上開房屋大門牆柱受損、鐵捲門損壞不能使用。甲○○隨即向到場處理之員警自首接受調查，並經測得吐氣中酒精濃度高達每公升1.04毫克（1.04mg/L），顯已達不能安全駕駛動力交通工具之程度。案經屏東縣警察局屏東分局報告臺灣屏東地方法院檢察署檢察官偵查起訴。二、前揭酒後駕車失控衝撞路旁車輛及房屋之事實，除據被告甲○○於警詢及本院調查時自白不諱，並經證人林美鳳於警詢中證述綦詳，復有道路交通事故調查報告(一)、(二)表、現場圖、酒精濃度檢測單、刑法第185條之3案件測試觀察紀錄表各1份、現場及車損照片12幀在卷可稽，堪信為真。按酒精對人體所生影響，於吐氣中酒精濃度達每公升0.25毫克時，即已輕微中毒，而有輕度協調功能降低，是依道路交通安全規則第114條第2款規定，汽車駕駛人飲酒後，吐氣中所含酒精濃度逾每公升0.25毫克者，即不得駕車；若進而其濃度達每公升0.55毫克、0.75毫克、0.85毫克以上者，肇事率猶分別達到一般正常人之10倍、25倍、50倍之譜，此觀卷附臺灣高等法院88年10月26日院賓文廉字第13407號致所屬各級法院函檢附法務部88年10月1日法檢字第3641號函暨附件研究報告及中央警察大學蔡中志教授製作之「酒精濃度與肇事率之關係表」自明。被告甲○○為前揭駕駛行為後，不僅經測得吐氣中酒精濃度達每公升1.04毫克，遠逾前述肇事率為一般正常人50倍之標準，危險極高。其經承辦員警進行行為測試觀察，亦呈現腳步不穩、手腳搖晃、語無倫次、含糊不清、意識模糊等現象，有前引測試觀察紀錄表在卷可參。今依卷附道路交通事故調查報告表、肇事現場圖、現場及車損照片所示，上開事故發生時間固為雨天夜晚，然現場為有照明、雙向各有3.5公尺寬車道及1.5公尺寬路肩各1線，以柏油鋪設之市區道路○路面無缺陷、無障礙、光線、視距良好之路段，詎被告甲○○行經現場時，竟衝出路面邊線，並穿越有相當寬度以為緩衝之路肩地帶而衝撞順向停放路旁之自用小客車，猶強力撞及民宅大門及牆柱，然其在歷此一連串狀況後，所駕上開車輛竟未遺留任何剎車、制動之痕跡，是被告甲○○當時反應顯與一般正常人之駕駛作為迥異，其為前揭駕駛行為時，因體內酒精濃度作用致不能有效操控所駕車輛，已達不能安全駕駛動力交通工具之程度等情，堪予認定。今查，酒精對於人體中樞神經系統有抑制作用，酒後從事駕駛行為極易因體內酒精作用致身體協調機能及對外界事物之反應能力減弱而發生危險，每每造成重大交通事故，嚴重危害公眾往來交通安全，乃政府近年來大力宣導禁止並取締酒後駕車之行為，此依卷附個人資料為63年7月16日出生、具備大學畢業教育程度，並已進入社會工作多年，以從事不動產仲介為業，且1年多前甫因重醉駕車肇事，涉犯公共危險罪嫌而經檢察官予以緩起訴處分之被告甲○○所知之甚明者，是本件被告犯罪事證已臻明確，應依法論科。三、查汽車係以汽油內燃機為動力，並以行駛公共道路為主要功能之車輛，為刑法第185條之3規定之動力交通工具。核被告甲○○所為，係犯刑法第185條之3服用酒類致不能安全駕駛動力交通工具而駕駛之公共危險罪。又被告甲○○犯罪後於員警到場處理時，主動向警方自首並接受裁判，有屏東縣警察局道路交通事故肇事人自首情形紀錄表在卷可憑，應依刑法第62條前段規定，減輕其刑。爰審酌被告甲○○之年齡、品行、智識程度、犯罪時體內酒精濃度之數值、犯罪所生之損害，對於公共安全造成危害之程度：被告甲○○為63年7月16日出生、具備大學畢業教育程度、現從事不動產仲介為業之人，有年籍資料在卷可按，並據其於本院訊問時自承在卷，前揭行為時已逾而立；其前於92年8月23日凌晨，因酒後吐氣中酒精濃度達每公升1.12毫克，已不能安全駕駛動力交通工具而駕駛車輛肇事，甫經臺灣高雄地方法院檢察署檢察官於92年9月17日以92年度偵字第17743號作成期間1年之緩起訴處分確定，有臺灣高等法院被告前案紀錄表、臺灣屏東地方法院檢察署刑案資料查註紀錄表及臺灣高雄地方法院檢察署檢察官緩起訴處分書各1份在卷可按，竟不知警惕，於本件犯罪前飲用瓶裝啤酒10瓶以上，吐氣中酒精濃度高達1.04毫克，竟仍輕率駕駛車輛上路，欲前往之目的地猶在數10公里外之高雄縣林園鄉，影響之大，足徵其目無法紀、全不在乎他人生命、身體及公共交通往來安全之態度；又其所駕動力交通工具為機械推力良好之自用小客車，犯罪時間為雨天夜晚，地點為市區時有人車往來之路段，對於法益產生危險之程度，與其犯罪除形成公眾交通往來之危險，並已衍生事故，對法益造成實害，及其犯罪後尚能坦承犯行，態度尚可等一切情狀，量處如主文所示之刑，並諭知易科罰金之折算標準，以資儆懲。四、按刑法第185條之3所規定公共危險罪，係以行為人在服用毒品、麻醉藥品、酒類或其他相類之物致不能安全駕駛動力交通工具之情狀下，有駕駛動力交通工具之行為為其構成要件。學說上固有以此為「原因自由行為」之規定者，惟查，學理上所稱「原因自由行為」，係針對傳統理論面對犯罪行為之成立必須行為人於行為時具備責任能力為前提，無法解決因故意或過失使自己陷於無責任能力或減輕責任能力狀態下實現構成要件等犯罪類型之窘境，而提出歸責之基礎，認為行為人因可歸責於自己之事由，致自陷於精神障礙狀態，進而在心神喪失或精神耗弱狀態中實現不法構成要件者，應將其行為之評價提前至造成其嗣後陷於責任能力有欠缺狀態之原因行為階段，亦即，認為此種犯罪類型實含有前後相續而不可分之「原因階段」與「行為階段」，刑法對於此等行為之評價，不應只限於行為階段，而應同時兼顧原因階段。然原因自由行為之態樣，其「行為階段」所實施者，原屬刑法分則所規定獨立之犯罪類型，僅因特定個案中，行為人稍早另有自陷於心神喪失或精神耗弱狀態之行為，乃將該「原因行為」一併納入評價其罪責之依據，尚非在原條文外創設另一刑罰規範，遑論將其前行為當然評價為犯罪構成要件行為。刑法第185條之3，就其條文結構之形式而言，固亦有自陷於不能安全駕駛動力交通工具之原因階段，及駕駛動力交通工具等先後兩部分之要件，惟姑不論其前階段所稱「不能安全駕駛動力交通工具」是否等同於心神喪失或精神耗弱等責任能力有欠缺之狀態，已非無疑；而行為人單有後階段所規定即單純駕駛汽車之舉，亦非刑法所規定之犯罪行為，與前開「原因自由行為」之類型迥然有別。縱依原因自由行為之理論，原僅在於解決行為人為後階段行為時，客觀上係處於欠缺完全責任能力之狀態，乃提前將其先前之行為一併納入評價，亦非逕以其自陷於心神喪失或精神耗弱狀態之行為為犯罪構成要件之行為，矧刑法第185條之3公共危險罪之規定，原不以服用酒類等行為為其歸責之本旨，蓋以飲用酒類原屬法律所容許之社會行為，而服用毒品、麻醉藥品等行為，縱為法所禁止，其不法內涵要亦已為毒品危害防制條例等相關刑罰法律所規範、處罰，均非本條規範目的所評價、非難之對象，猶非居於本條構成要件行為之地位，而屬法定構成要件特別行為情狀之一部。申言之，刑法第185條之3係以行為人處於因服用毒品、麻醉藥品、酒類或其他相類之物所造成不能安全駕駛動力交通工具之「特別行為情狀」下，而有駕駛動力交通工具之「構成要件行為」者，為其規範之內涵。從而，本條既以特定情狀下所為駕駛行為為犯罪構成要件行為，則行為人在該情狀下用以供駕駛行為使用之動力交通工具，即為其實施本條犯罪行為所用之物。茲前揭車號JY-2899號自用小客車為被告甲○○所有、自83年3月30日發照至前揭事故發生時出廠已逾10年之老舊車輛，除據被告甲○○自承在卷（詳本院卷94年10月5日訊問筆錄），復有公路監理查註紀錄表、車籍作業系統查詢認可資料各1紙附卷可參，依前開論述並為被告甲○○供本件犯罪所用之物，自屬刑法第38條第1項第2款所規定得為沒收之物，本院90年度3月份刑庭會議決議同此意旨，殊堪贊同。今以被告甲○○在本件犯行前，於92年8月23日凌晨，因酒後吐氣中酒精濃度達每公升1.12毫克，已不能安全駕駛動力交通工具而駕駛前開其所有之車號JY-2899號自用小客車，在高雄市○○街道前金區○○路、五福三路口肇事而遭查獲，雖經臺灣高雄地方法院檢察署檢察官於92年9月17日以92年度偵字第17743號作成期間1年之緩起訴處分確定，竟無動於衷，於前開緩起訴處分期間甫屆滿未及1年，旋又固態復萌，以同一車輛即車齡逾10年以上，依一般耐用年限、折舊公式計算幾無殘值之自用小客車再犯本件犯行，酒精濃度之高，行駛路段之交通情形及計劃前往目的地之遠，甚至已嚴重衝撞其他車輛及民宅，對公眾往來秩序及不特定用路人之生命、財產安全所構成之威脅甚鉅，是依其前揭犯行對法益侵害之強度、其反覆實施同類犯行之主觀惡性及素行對法益隱存之危險性，考量刑法一般預防及特別預防之效果，審酌諭知從刑之適當性、必要性及權衡法益之合比例性，併就其所有供前揭犯罪使用之車號JY-2899號自用小客車（車身號碼UZZZ8CZSA079478號）為沒收之諭知。五、據上論斷，應依刑事訴訟法第273條之1第1項、第299條第1項前段，刑法第185條之3、第62條前段、第41條第1項前段、第38條第1項第2款，罰金罰鍰提高標準條例第2條，逕以簡易判決判處如主文所示之刑。六、如不服本判決，得自收受送達之日起10日內，向本院提起上訴。中華民國94年10月31日交通法庭法官陳松檀以上正本證明與原本無異。如不服本判決應於收受本判決送達後十日內向本院提出上訴書狀，其未敘述上訴理由者，並得於提起上訴後十日內向本院補提理由書狀（均須按他造當事人之人數附繕本）「切勿逕送上級法院」中華民國94年11月3日書記官魏慧夷附錄本判決論罪科刑法條全文刑法第185條之3服用毒品、麻醉藥品、酒類或其他相類之物，不能安全駕駛動力交通工具而駕駛者，處一年以下有期徒刑、拘役或三萬元以下罰金。",
  "characters": {
    "judges": [
      "陳松檀"
    ],
    "prosecutors": [

    ],
    "lawyers": [

    ],
    "clerks": [
      "魏慧夷"
    ],
    "plaintiffs": [

    ],
    "defendants": [
      "甲○○"
    ],
    "prosecutor_office": [
      "臺灣屏東地方法院檢察署檢察官"
    ],
    "creditors": [

    ],
    "debtors": [

    ],
    "judicial_associate_officer": [

    ]
  },
  "adjudged_at": "2005-10-31",
  "created_at": "2016-02-07 11:26:50",
  "updated_at": "2016-02-07 11:26:50"
}