{
  "identify": "TPD-94-易-1433-20051031-1",
  "court": {
    "name": "臺灣臺北地方法院",
    "code": "TPD"
  },
  "division": {
    "name": "刑事",
    "code": "M"
  },
  "year": 94,
  "word": "易",
  "number": "1433",
  "jcheck": "1",
  "reason": "毀棄損壞",
  "content": "臺灣臺北地方法院刑事判決              94年度易字第1433號\n公  訴  人  臺灣臺北地方法院檢察署檢察官\n被      告  乙○○\n上列被告因偽造文書案件，經檢察官提起公訴（九十三年度偵字\n第一○○六七號），本院判決如下：\n    主  文\n本件公訴不受理。\n    理  由\n一、公訴意旨略稱：被告乙○○明知臺北市○○區○○街一一八\n    號三層樓房屋及所坐落之臺北市○○區○○段三小段地號土\n    地均係其父徐春芳贈與甲○○，因不滿甲○○在前揭房屋一\n    樓裝設不鏽鋼門，竟基於毀損之故意，於民國九十二年十一\n    月十六日午間十二時三十七分，持鐵鎚敲打臺北市○○區○\n    ○街一一八號一樓之不鏽鋼門，致該門門把與門框之鉸鍊遭\n    破壞變形，喪失正常啟閉之效用，因認被告涉有刑法第三百\n    五十四條之毀損罪嫌等語。\n二、按被告死亡者，應諭知不受理之判決，刑事訴訟法第三百零\n    三條第五款定有明文。\n三、經查，本件被告業於九十四年四月二十日推定死亡，此有個\n    人基本資料查詢結果各一份在卷可稽，揆諸上開說明，本件\n    爰不經言詞辯論，逕為不受理之判決。\n據上論斷，應依刑事訴訟法第三百零三條第五款、第三百零七條\n，判決如主文。\n中    華    民    國   九十四  年   十    月  三十一  日\n                    臺灣臺北地方法院刑事第二庭\n                        審判長法  官  吳孟良\n                              法  官  沈君玲\n                              法  官  雷淑雯\n右正本證明與原本無異。\n如不服本判決，應於判決送達後十日內向本院提出上訴狀（應抄\n附繕本）。\n                              書記官  林碧華\n中    華    民    國   九十四  年   十    月  三十一  日\n",
  "structure": {
    "main": "本件公訴不受理。",
    "reason": "一、公訴意旨略稱：被告乙○○明知臺北市○○區○○街一一八\n    號三層樓房屋及所坐落之臺北市○○區○○段三小段地號土\n    地均係其父徐春芳贈與甲○○，因不滿甲○○在前揭房屋一\n    樓裝設不鏽鋼門，竟基於毀損之故意，於民國九十二年十一\n    月十六日午間十二時三十七分，持鐵鎚敲打臺北市○○區○\n    ○街一一八號一樓之不鏽鋼門，致該門門把與門框之鉸鍊遭\n    破壞變形，喪失正常啟閉之效用，因認被告涉有刑法第三百\n    五十四條之毀損罪嫌等語。\n二、按被告死亡者，應諭知不受理之判決，刑事訴訟法第三百零\n    三條第五款定有明文。\n三、經查，本件被告業於九十四年四月二十日推定死亡，此有個\n    人基本資料查詢結果各一份在卷可稽，揆諸上開說明，本件\n    爰不經言詞辯論，逕為不受理之判決。\n據上論斷，應依刑事訴訟法第三百零三條第五款、第三百零七條\n，判決如主文。"
  },
  "search": "臺灣臺北地方法院刑事判決94年度易字第1433號公訴人臺灣臺北地方法院檢察署檢察官被告乙○○上列被告因偽造文書案件，經檢察官提起公訴（九十三年度偵字第一○○六七號），本院判決如下：主文本件公訴不受理。理由一、公訴意旨略稱：被告乙○○明知臺北市○○區○○街一一八號三層樓房屋及所坐落之臺北市○○區○○段三小段地號土地均係其父徐春芳贈與甲○○，因不滿甲○○在前揭房屋一樓裝設不鏽鋼門，竟基於毀損之故意，於民國九十二年十一月十六日午間十二時三十七分，持鐵鎚敲打臺北市○○區○○街一一八號一樓之不鏽鋼門，致該門門把與門框之鉸鍊遭破壞變形，喪失正常啟閉之效用，因認被告涉有刑法第三百五十四條之毀損罪嫌等語。二、按被告死亡者，應諭知不受理之判決，刑事訴訟法第三百零三條第五款定有明文。三、經查，本件被告業於九十四年四月二十日推定死亡，此有個人基本資料查詢結果各一份在卷可稽，揆諸上開說明，本件爰不經言詞辯論，逕為不受理之判決。據上論斷，應依刑事訴訟法第三百零三條第五款、第三百零七條，判決如主文。中華民國九十四年十月三十一日臺灣臺北地方法院刑事第二庭審判長法官吳孟良法官沈君玲法官雷淑雯右正本證明與原本無異。如不服本判決，應於判決送達後十日內向本院提出上訴狀（應抄附繕本）。書記官林碧華中華民國九十四年十月三十一日",
  "characters": {
    "judges": [
      "吳孟良",
      "沈君玲",
      "雷淑雯"
    ],
    "prosecutors": [

    ],
    "lawyers": [

    ],
    "clerks": [
      "林碧華"
    ],
    "plaintiffs": [

    ],
    "defendants": [
      "乙○○"
    ],
    "prosecutor_office": [
      "臺灣臺北地方法院檢察署檢察官"
    ],
    "creditors": [

    ],
    "debtors": [

    ],
    "judicial_associate_officer": [

    ]
  },
  "adjudged_at": "2005-10-31",
  "created_at": "2016-02-07 11:28:19",
  "updated_at": "2016-02-07 11:28:19"
}