{
  "identify": "MLD-100-司票-384-20111101-1",
  "court": {
    "name": "臺灣苗栗地方法院",
    "code": "MLD"
  },
  "division": {
    "name": "民事",
    "code": "V"
  },
  "year": 100,
  "word": "司票",
  "number": "384",
  "jcheck": "1",
  "reason": "本票裁定",
  "content": "臺灣苗栗地方法院民事裁定            100年度司票字第384號\n聲  請  人  蘇美珍\n相  對  人  徐東呈\n上列當事人間聲請對本票准許強制執行事件，本院裁定如下：\n    主  文\n相對人於如附表所示發票日簽發之本票，內載憑票支付聲請人各\n如附表所示之金額，及自各如附表所示利息起算日起，均至清償\n日止，按年息百分之六計算之利息，得為強制執行。\n程序費用新臺幣壹仟元由相對人負擔。\n    理  由\n一、聲請意旨略以：聲請人執有相對人簽發如附表所示之本票，\n    並免除作成拒絕證書，詎於到期後提示均未獲付款，為此提\n    出本票原本44紙，聲請裁定准許強制執行等語。\n二、本件聲請核與票據法第123條之規定相符，應予准許。\n三、依非訟事件法第21條第2 項、24條第1 項、民事訴訟法第78\n    條，裁定如主文。\n中    華    民    國   100    年    11    月    1     日\n                  民事庭司法事務官  侯美滿\n┌────────────────────────────────────────────────────────────┐\n│本票附表：                                                                                          100年度司票字第384號│\n├──┬───────────┬─────────┬───────────┬───────────┬────────┬──┤\n│編號│發        票        日│  票  面  金  額  │到        期        日│  利  息  起  算  日  │ 票  據  號  碼 │備考│\n│    │                      │  （新  台  幣）  │                      │                      │                │    │\n├──┼───────────┼─────────┼───────────┼───────────┼────────┼──┤\n│001 │98年1月1日            │5,000元           │      未載到期日      │98年1月1日            │WG00000000      │    │\n├──┼───────────┼─────────┼───────────┼───────────┼────────┼──┤\n│002 │98年1月1日            │5,000元           │      未載到期日      │98年1月1日            │WG00000000      │    │\n├──┼───────────┼─────────┼───────────┼───────────┼────────┼──┤\n│003 │98年1月1日            │5,000元           │      未載到期日      │98年1月1日            │WG00000000      │    │\n├──┼───────────┼─────────┼───────────┼───────────┼────────┼──┤\n│004 │98年1月1日            │5,000元           │      未載到期日      │98年1月1日            │WG00000000      │    │\n├──┼───────────┼─────────┼───────────┼───────────┼────────┼──┤\n│005 │98年1月1日            │5,000元           │      未載到期日      │98年1月1日            │WG00000000      │    │\n├──┼───────────┼─────────┼───────────┼───────────┼────────┼──┤\n│006 │98年1月1日            │5,000元           │      未載到期日      │98年1月1日            │WG00000000      │    │\n├──┼───────────┼─────────┼───────────┼───────────┼────────┼──┤\n│007 │98年1月1日            │5,000元           │      未載到期日      │98年1月1日            │WG00000000      │    │\n├──┼───────────┼─────────┼───────────┼───────────┼────────┼──┤\n│008 │98年1月1日            │10,000元          │      未載到期日      │98年1月1日            │WG00000000      │    │\n├──┼───────────┼─────────┼───────────┼───────────┼────────┼──┤\n│009 │98年1月1日            │10,000元          │      未載到期日      │98年1月1日            │WG00000000      │    │\n├──┼───────────┼─────────┼───────────┼───────────┼────────┼──┤\n│010 │98年1月1日            │10,000元          │      未載到期日      │98年1月1日            │WG00000000      │    │\n├──┼───────────┼─────────┼───────────┼───────────┼────────┼──┤\n│011 │98年1月1日            │10,000元          │      未載到期日      │98年1月1日            │WG00000000      │    │\n├──┼───────────┼─────────┼───────────┼───────────┼────────┼──┤\n│012 │98年1月1日            │10,000元          │      未載到期日      │98年1月1日            │WG00000000      │    │\n├──┼───────────┼─────────┼───────────┼───────────┼────────┼──┤\n│013 │98年1月1日            │10,000元          │      未載到期日      │98年1月1日            │WG00000000      │    │\n├──┼───────────┼─────────┼───────────┼───────────┼────────┼──┤\n│014 │98年1月1日            │10,000元          │      未載到期日      │98年1月1日            │WG00000000      │    │\n├──┼───────────┼─────────┼───────────┼───────────┼────────┼──┤\n│015 │98年1月1日            │5,000元           │      未載到期日      │98年1月1日            │WG00000000      │    │\n├──┼───────────┼─────────┼───────────┼───────────┼────────┼──┤\n│016 │98年1月1日            │5,000元           │      未載到期日      │98年1月1日            │WG00000000      │    │\n├──┼───────────┼─────────┼───────────┼───────────┼────────┼──┤\n│017 │98年1月1日            │5,000元           │      未載到期日      │98年1月1日            │WG00000000      │    │\n├──┼───────────┼─────────┼───────────┼───────────┼────────┼──┤\n│018 │98年1月1日            │5,000元           │      未載到期日      │98年1月1日            │WG00000000      │    │\n├──┼───────────┼─────────┼───────────┼───────────┼────────┼──┤\n│019 │98年1月1日            │5,000元           │      未載到期日      │98年1月1日            │WG00000000      │    │\n├──┼───────────┼─────────┼───────────┼───────────┼────────┼──┤\n│020 │98年1月1日            │5,000元           │      未載到期日      │98年1月1日            │WG00000000      │    │\n├──┼───────────┼─────────┼───────────┼───────────┼────────┼──┤\n│021 │98年1月1日            │5,000元           │      未載到期日      │98年1月1日            │WG00000000      │    │\n├──┼───────────┼─────────┼───────────┼───────────┼────────┼──┤\n│022 │98年1月1日            │5,000元           │      未載到期日      │98年1月1日            │WG00000000      │    │\n├──┼───────────┼─────────┼───────────┼───────────┼────────┼──┤\n│023 │98年1月1日            │5,000元           │      未載到期日      │98年1月1日            │WG00000000      │    │\n├──┼───────────┼─────────┼───────────┼───────────┼────────┼──┤\n│024 │98年1月1日            │5,000元           │      未載到期日      │98年1月1日            │WG00000000      │    │\n├──┼───────────┼─────────┼───────────┼───────────┼────────┼──┤\n│025 │98年1月1日            │10,000元          │      未載到期日      │98年1月1日            │WG00000000      │    │\n├──┼───────────┼─────────┼───────────┼───────────┼────────┼──┤\n│026 │98年1月1日            │10,000元          │      未載到期日      │98年1月1日            │WG00000000      │    │\n├──┼───────────┼─────────┼───────────┼───────────┼────────┼──┤\n│027 │98年1月1日            │10,000元          │      未載到期日      │98年1月1日            │WG00000000      │    │\n├──┼───────────┼─────────┼───────────┼───────────┼────────┼──┤\n│028 │98年1月1日            │10,000元          │      未載到期日      │98年1月1日            │WG00000000      │    │\n├──┼───────────┼─────────┼───────────┼───────────┼────────┼──┤\n│029 │98年1月1日            │10,000元          │      未載到期日      │98年1月1日            │WG00000000      │    │\n├──┼───────────┼─────────┼───────────┼───────────┼────────┼──┤\n│030 │98年1月1日            │10,000元          │      未載到期日      │98年1月1日            │WG00000000      │    │\n├──┼───────────┼─────────┼───────────┼───────────┼────────┼──┤\n│031 │98年1月1日            │10,000元          │      未載到期日      │98年1月1日            │WG00000000      │    │\n├──┼───────────┼─────────┼───────────┼───────────┼────────┼──┤\n│032 │98年1月1日            │10,000元          │      未載到期日      │98年1月1日            │WG00000000      │    │\n├──┼───────────┼─────────┼───────────┼───────────┼────────┼──┤\n│033 │98年1月1日            │10,000元          │      未載到期日      │98年1月1日            │WG00000000      │    │\n├──┼───────────┼─────────┼───────────┼───────────┼────────┼──┤\n│034 │98年1月1日            │10,000元          │      未載到期日      │98年1月1日            │WG00000000      │    │\n├──┼───────────┼─────────┼───────────┼───────────┼────────┼──┤\n│035 │98年1月1日            │5,000元           │      未載到期日      │98年1月1日            │WG00000000      │    │\n├──┼───────────┼─────────┼───────────┼───────────┼────────┼──┤\n│036 │98年1月1日            │5,000元           │      未載到期日      │98年1月1日            │WG00000000      │    │\n├──┼───────────┼─────────┼───────────┼───────────┼────────┼──┤\n│037 │98年1月1日            │5,000元           │      未載到期日      │98年1月1日            │WG00000000      │    │\n├──┼───────────┼─────────┼───────────┼───────────┼────────┼──┤\n│038 │98年1月1日            │5,000元           │      未載到期日      │98年1月1日            │WG00000000      │    │\n├──┼───────────┼─────────┼───────────┼───────────┼────────┼──┤\n│039 │98年1月1日            │10,000元          │      未載到期日      │98年1月1日            │WG00000000      │    │\n├──┼───────────┼─────────┼───────────┼───────────┼────────┼──┤\n│040 │98年1月1日            │10,000元          │      未載到期日      │98年1月1日            │WG00000000      │    │\n├──┼───────────┼─────────┼───────────┼───────────┼────────┼──┤\n│041 │98年1月1日            │10,000元          │      未載到期日      │98年1月1日            │WG00000000      │    │\n├──┼───────────┼─────────┼───────────┼───────────┼────────┼──┤\n│042 │98年1月1日            │10,000元          │      未載到期日      │98年1月1日            │WG00000000      │    │\n├──┼───────────┼─────────┼───────────┼───────────┼────────┼──┤\n│043 │98年1月1日            │10,000元          │      未載到期日      │98年1月1日            │WG00000000      │    │\n├──┼───────────┼─────────┼───────────┼───────────┼────────┼──┤\n│044 │98年1月1日            │10,000元          │      未載到期日      │98年1月1日            │WG00000000      │    │\n└──┴───────────┴─────────┴───────────┴───────────┴────────┴──┘\n一、以上正本係照原本作成\n二、如不服本裁定應於送達後10日內向本院提出抗告狀，並繳納\n    抗告費新臺幣1,000 元。\n三、發票人如主張本票係偽造、變造者，得於接到本裁定後20日\n    內，對執票人向本院另行提起確認債權不存在之訴。\n附註：\n一、聲請人、相對人嗣後遞狀時均請註明案號、股別。\n二、案件一經確定，本院即依職權核發確定證明書，聲請人勿庸\n    另行聲請。\n                        書記官  李學詩\n中    華    民    國   100    年    11    月    1     日",
  "structure": {
    "main": "相對人於如附表所示發票日簽發之本票，內載憑票支付聲請人各\n如附表所示之金額，及自各如附表所示利息起算日起，均至清償\n日止，按年息百分之六計算之利息，得為強制執行。\n程序費用新臺幣壹仟元由相對人負擔。",
    "reason": "一、聲請意旨略以：聲請人執有相對人簽發如附表所示之本票，\n    並免除作成拒絕證書，詎於到期後提示均未獲付款，為此提\n    出本票原本44紙，聲請裁定准許強制執行等語。\n二、本件聲請核與票據法第123條之規定相符，應予准許。\n三、依非訟事件法第21條第2 項、24條第1 項、民事訴訟法第78\n    條，裁定如主文。"
  },
  "search": "臺灣苗栗地方法院民事裁定100年度司票字第384號聲請人蘇美珍相對人徐東呈上列當事人間聲請對本票准許強制執行事件，本院裁定如下：主文相對人於如附表所示發票日簽發之本票，內載憑票支付聲請人各如附表所示之金額，及自各如附表所示利息起算日起，均至清償日止，按年息百分之六計算之利息，得為強制執行。程序費用新臺幣壹仟元由相對人負擔。理由一、聲請意旨略以：聲請人執有相對人簽發如附表所示之本票，並免除作成拒絕證書，詎於到期後提示均未獲付款，為此提出本票原本44紙，聲請裁定准許強制執行等語。二、本件聲請核與票據法第123條之規定相符，應予准許。三、依非訟事件法第21條第2項、24條第1項、民事訴訟法第78條，裁定如主文。中華民國100年11月1日民事庭司法事務官侯美滿┌────────────────────────────────────────────────────────────┐│本票附表：100年度司票字第384號│├──┬───────────┬─────────┬───────────┬───────────┬────────┬──┤│編號│發票日│票面金額│到期日│利息起算日│票據號碼│備考││││（新台幣）│││││├──┼───────────┼─────────┼───────────┼───────────┼────────┼──┤│001│98年1月1日│5,000元│未載到期日│98年1月1日│WG00000000││├──┼───────────┼─────────┼───────────┼───────────┼────────┼──┤│002│98年1月1日│5,000元│未載到期日│98年1月1日│WG00000000││├──┼───────────┼─────────┼───────────┼───────────┼────────┼──┤│003│98年1月1日│5,000元│未載到期日│98年1月1日│WG00000000││├──┼───────────┼─────────┼───────────┼───────────┼────────┼──┤│004│98年1月1日│5,000元│未載到期日│98年1月1日│WG00000000││├──┼───────────┼─────────┼───────────┼───────────┼────────┼──┤│005│98年1月1日│5,000元│未載到期日│98年1月1日│WG00000000││├──┼───────────┼─────────┼───────────┼───────────┼────────┼──┤│006│98年1月1日│5,000元│未載到期日│98年1月1日│WG00000000││├──┼───────────┼─────────┼───────────┼───────────┼────────┼──┤│007│98年1月1日│5,000元│未載到期日│98年1月1日│WG00000000││├──┼───────────┼─────────┼───────────┼───────────┼────────┼──┤│008│98年1月1日│10,000元│未載到期日│98年1月1日│WG00000000││├──┼───────────┼─────────┼───────────┼───────────┼────────┼──┤│009│98年1月1日│10,000元│未載到期日│98年1月1日│WG00000000││├──┼───────────┼─────────┼───────────┼───────────┼────────┼──┤│010│98年1月1日│10,000元│未載到期日│98年1月1日│WG00000000││├──┼───────────┼─────────┼───────────┼───────────┼────────┼──┤│011│98年1月1日│10,000元│未載到期日│98年1月1日│WG00000000││├──┼───────────┼─────────┼───────────┼───────────┼────────┼──┤│012│98年1月1日│10,000元│未載到期日│98年1月1日│WG00000000││├──┼───────────┼─────────┼───────────┼───────────┼────────┼──┤│013│98年1月1日│10,000元│未載到期日│98年1月1日│WG00000000││├──┼───────────┼─────────┼───────────┼───────────┼────────┼──┤│014│98年1月1日│10,000元│未載到期日│98年1月1日│WG00000000││├──┼───────────┼─────────┼───────────┼───────────┼────────┼──┤│015│98年1月1日│5,000元│未載到期日│98年1月1日│WG00000000││├──┼───────────┼─────────┼───────────┼───────────┼────────┼──┤│016│98年1月1日│5,000元│未載到期日│98年1月1日│WG00000000││├──┼───────────┼─────────┼───────────┼───────────┼────────┼──┤│017│98年1月1日│5,000元│未載到期日│98年1月1日│WG00000000││├──┼───────────┼─────────┼───────────┼───────────┼────────┼──┤│018│98年1月1日│5,000元│未載到期日│98年1月1日│WG00000000││├──┼───────────┼─────────┼───────────┼───────────┼────────┼──┤│019│98年1月1日│5,000元│未載到期日│98年1月1日│WG00000000││├──┼───────────┼─────────┼───────────┼───────────┼────────┼──┤│020│98年1月1日│5,000元│未載到期日│98年1月1日│WG00000000││├──┼───────────┼─────────┼───────────┼───────────┼────────┼──┤│021│98年1月1日│5,000元│未載到期日│98年1月1日│WG00000000││├──┼───────────┼─────────┼───────────┼───────────┼────────┼──┤│022│98年1月1日│5,000元│未載到期日│98年1月1日│WG00000000││├──┼───────────┼─────────┼───────────┼───────────┼────────┼──┤│023│98年1月1日│5,000元│未載到期日│98年1月1日│WG00000000││├──┼───────────┼─────────┼───────────┼───────────┼────────┼──┤│024│98年1月1日│5,000元│未載到期日│98年1月1日│WG00000000││├──┼───────────┼─────────┼───────────┼───────────┼────────┼──┤│025│98年1月1日│10,000元│未載到期日│98年1月1日│WG00000000││├──┼───────────┼─────────┼───────────┼───────────┼────────┼──┤│026│98年1月1日│10,000元│未載到期日│98年1月1日│WG00000000││├──┼───────────┼─────────┼───────────┼───────────┼────────┼──┤│027│98年1月1日│10,000元│未載到期日│98年1月1日│WG00000000││├──┼───────────┼─────────┼───────────┼───────────┼────────┼──┤│028│98年1月1日│10,000元│未載到期日│98年1月1日│WG00000000││├──┼───────────┼─────────┼───────────┼───────────┼────────┼──┤│029│98年1月1日│10,000元│未載到期日│98年1月1日│WG00000000││├──┼───────────┼─────────┼───────────┼───────────┼────────┼──┤│030│98年1月1日│10,000元│未載到期日│98年1月1日│WG00000000││├──┼───────────┼─────────┼───────────┼───────────┼────────┼──┤│031│98年1月1日│10,000元│未載到期日│98年1月1日│WG00000000││├──┼───────────┼─────────┼───────────┼───────────┼────────┼──┤│032│98年1月1日│10,000元│未載到期日│98年1月1日│WG00000000││├──┼───────────┼─────────┼───────────┼───────────┼────────┼──┤│033│98年1月1日│10,000元│未載到期日│98年1月1日│WG00000000││├──┼───────────┼─────────┼───────────┼───────────┼────────┼──┤│034│98年1月1日│10,000元│未載到期日│98年1月1日│WG00000000││├──┼───────────┼─────────┼───────────┼───────────┼────────┼──┤│035│98年1月1日│5,000元│未載到期日│98年1月1日│WG00000000││├──┼───────────┼─────────┼───────────┼───────────┼────────┼──┤│036│98年1月1日│5,000元│未載到期日│98年1月1日│WG00000000││├──┼───────────┼─────────┼───────────┼───────────┼────────┼──┤│037│98年1月1日│5,000元│未載到期日│98年1月1日│WG00000000││├──┼───────────┼─────────┼───────────┼───────────┼────────┼──┤│038│98年1月1日│5,000元│未載到期日│98年1月1日│WG00000000││├──┼───────────┼─────────┼───────────┼───────────┼────────┼──┤│039│98年1月1日│10,000元│未載到期日│98年1月1日│WG00000000││├──┼───────────┼─────────┼───────────┼───────────┼────────┼──┤│040│98年1月1日│10,000元│未載到期日│98年1月1日│WG00000000││├──┼───────────┼─────────┼───────────┼───────────┼────────┼──┤│041│98年1月1日│10,000元│未載到期日│98年1月1日│WG00000000││├──┼───────────┼─────────┼───────────┼───────────┼────────┼──┤│042│98年1月1日│10,000元│未載到期日│98年1月1日│WG00000000││├──┼───────────┼─────────┼───────────┼───────────┼────────┼──┤│043│98年1月1日│10,000元│未載到期日│98年1月1日│WG00000000││├──┼───────────┼─────────┼───────────┼───────────┼────────┼──┤│044│98年1月1日│10,000元│未載到期日│98年1月1日│WG00000000││└──┴───────────┴─────────┴───────────┴───────────┴────────┴──┘一、以上正本係照原本作成二、如不服本裁定應於送達後10日內向本院提出抗告狀，並繳納抗告費新臺幣1,000元。三、發票人如主張本票係偽造、變造者，得於接到本裁定後20日內，對執票人向本院另行提起確認債權不存在之訴。附註：一、聲請人、相對人嗣後遞狀時均請註明案號、股別。二、案件一經確定，本院即依職權核發確定證明書，聲請人勿庸另行聲請。書記官李學詩中華民國100年11月1日",
  "characters": {
    "judges": [

    ],
    "prosecutors": [

    ],
    "lawyers": [

    ],
    "clerks": [
      "李學詩"
    ],
    "plaintiffs": [

    ],
    "defendants": [

    ],
    "prosecutor_office": [
      "蘇美珍"
    ],
    "creditors": [

    ],
    "debtors": [

    ],
    "judicial_associate_officer": [
      "侯美滿"
    ]
  },
  "adjudged_at": "2011-11-01",
  "created_at": "2016-02-12 23:48:15",
  "updated_at": "2016-02-12 23:48:15"
}