{
  "identify": "CYD-100-朴簡-294-20110907-1",
  "court": {
    "name": "臺灣嘉義地方法院",
    "code": "CYD"
  },
  "division": {
    "name": "刑事",
    "code": "M"
  },
  "year": 100,
  "word": "朴簡",
  "number": "294",
  "jcheck": "1",
  "reason": "違反毒品危害防制條例",
  "content": "臺灣嘉義地方法院刑事簡易判決        100年度朴簡字第294號\n聲  請  人  臺灣嘉義地方法院檢察署檢察官\n被      告  林坤鋒\n上列被告因毒品危害防制條例案件，經檢察官聲請以簡易判決處\n刑（100年度毒偵字第1071號），本院判決如下：\n    主  文\n林坤鋒施用第二級毒品，處有期徒刑貳月，如易科罰金，以新臺\n幣壹仟元折算壹日。\n    犯罪事實及理由\n一、本件除聲請簡易判決處刑書（如附件）犯罪事實欄第4行之\n    「晚間9時20分許」更正為「22時26分許」外，其餘犯罪事\n    實及證據均引用聲請簡易判決處刑書之記載。\n二、爰審酌被告林坤鋒前因施用毒品犯行，經觀察、勒戒執行完\n    畢，猶不思藉機徹底戒除施用毒品之惡習，仍再次施用毒品\n    ，惟其施用毒品係自戕行為，施用毒品之手段，及犯後坦承\n    犯行等一切情狀，量處如主文所示之刑，並諭知易科罰金之\n    折算標準。\n三、依刑事訴訟法第449條第1項前段、第454條第2項，毒品危害\n    防制條例第10條第2項，刑法第11條前段、第41條第1項前段\n    ，逕以簡易判決量處如主文所示之刑。\n四、如不服本判決，得於判決書送達之日起10日內，以書狀敘述\n    理由，向本院提出上訴（須附繕本）。\n中    華    民    國   100    年    9     月    7     日\n                      朴子簡易庭  法  官  卓春慧\n上列正本證明與原本無異。\n如不服本判決，應於判決送達後10日內向本院提出上訴狀（應附\n繕本）。\n中    華    民    國   100    年    9     月    7     日\n                                  書記官  李玫娜\n附錄本案論罪科刑法條全文：\n毒品危害防制條例第10條第2項：\n施用第二級毒品者，處3年以下有期徒刑。",
  "structure": {
    "main": "林坤鋒施用第二級毒品，處有期徒刑貳月，如易科罰金，以新臺\n幣壹仟元折算壹日。",
    "fact": "一、本件除聲請簡易判決處刑書（如附件）犯罪事實欄第4行之\n    「晚間9時20分許」更正為「22時26分許」外，其餘犯罪事\n    實及證據均引用聲請簡易判決處刑書之記載。\n二、爰審酌被告林坤鋒前因施用毒品犯行，經觀察、勒戒執行完\n    畢，猶不思藉機徹底戒除施用毒品之惡習，仍再次施用毒品\n    ，惟其施用毒品係自戕行為，施用毒品之手段，及犯後坦承\n    犯行等一切情狀，量處如主文所示之刑，並諭知易科罰金之\n    折算標準。\n三、依刑事訴訟法第449條第1項前段、第454條第2項，毒品危害\n    防制條例第10條第2項，刑法第11條前段、第41條第1項前段\n    ，逕以簡易判決量處如主文所示之刑。\n四、如不服本判決，得於判決書送達之日起10日內，以書狀敘述\n    理由，向本院提出上訴（須附繕本）。",
    "reason": "一、本件除聲請簡易判決處刑書（如附件）犯罪事實欄第4行之\n    「晚間9時20分許」更正為「22時26分許」外，其餘犯罪事\n    實及證據均引用聲請簡易判決處刑書之記載。\n二、爰審酌被告林坤鋒前因施用毒品犯行，經觀察、勒戒執行完\n    畢，猶不思藉機徹底戒除施用毒品之惡習，仍再次施用毒品\n    ，惟其施用毒品係自戕行為，施用毒品之手段，及犯後坦承\n    犯行等一切情狀，量處如主文所示之刑，並諭知易科罰金之\n    折算標準。\n三、依刑事訴訟法第449條第1項前段、第454條第2項，毒品危害\n    防制條例第10條第2項，刑法第11條前段、第41條第1項前段\n    ，逕以簡易判決量處如主文所示之刑。\n四、如不服本判決，得於判決書送達之日起10日內，以書狀敘述\n    理由，向本院提出上訴（須附繕本）。"
  },
  "search": "臺灣嘉義地方法院刑事簡易判決100年度朴簡字第294號聲請人臺灣嘉義地方法院檢察署檢察官被告林坤鋒上列被告因毒品危害防制條例案件，經檢察官聲請以簡易判決處刑（100年度毒偵字第1071號），本院判決如下：主文林坤鋒施用第二級毒品，處有期徒刑貳月，如易科罰金，以新臺幣壹仟元折算壹日。犯罪事實及理由一、本件除聲請簡易判決處刑書（如附件）犯罪事實欄第4行之「晚間9時20分許」更正為「22時26分許」外，其餘犯罪事實及證據均引用聲請簡易判決處刑書之記載。二、爰審酌被告林坤鋒前因施用毒品犯行，經觀察、勒戒執行完畢，猶不思藉機徹底戒除施用毒品之惡習，仍再次施用毒品，惟其施用毒品係自戕行為，施用毒品之手段，及犯後坦承犯行等一切情狀，量處如主文所示之刑，並諭知易科罰金之折算標準。三、依刑事訴訟法第449條第1項前段、第454條第2項，毒品危害防制條例第10條第2項，刑法第11條前段、第41條第1項前段，逕以簡易判決量處如主文所示之刑。四、如不服本判決，得於判決書送達之日起10日內，以書狀敘述理由，向本院提出上訴（須附繕本）。中華民國100年9月7日朴子簡易庭法官卓春慧上列正本證明與原本無異。如不服本判決，應於判決送達後10日內向本院提出上訴狀（應附繕本）。中華民國100年9月7日書記官李玫娜附錄本案論罪科刑法條全文：毒品危害防制條例第10條第2項：施用第二級毒品者，處3年以下有期徒刑。",
  "characters": {
    "judges": [
      "卓春慧"
    ],
    "prosecutors": [

    ],
    "lawyers": [

    ],
    "clerks": [
      "李玫娜"
    ],
    "plaintiffs": [

    ],
    "defendants": [
      "林坤鋒"
    ],
    "prosecutor_office": [
      "臺灣嘉義地方法院檢察署檢察官"
    ],
    "creditors": [

    ],
    "debtors": [

    ],
    "judicial_associate_officer": [

    ]
  },
  "adjudged_at": "2011-09-07",
  "created_at": "2016-02-12 14:23:28",
  "updated_at": "2016-02-12 14:23:28"
}