{
  "identify": "TPD-100-簡-2599-20110906-1",
  "court": {
    "name": "臺灣臺北地方法院",
    "code": "TPD"
  },
  "division": {
    "name": "刑事",
    "code": "M"
  },
  "year": 100,
  "word": "簡",
  "number": "2599",
  "jcheck": "1",
  "reason": "毒品危害防制條例",
  "content": "臺灣臺北地方法院刑事簡易判決         100年度簡字第2599號\n聲  請  人  臺灣臺北地方法院檢察署檢察官\n被      告  顏育科\n上列被告因違反毒品危害防制條例案件，經檢察官聲請以簡易判\n決處刑（一○○年度毒偵字第一七六四號），本院判決如下：\n    主  文\n顏育科施用第二級毒品，處有期徒刑伍月，如易科罰金，以新臺\n幣壹仟元折算壹日。\n    事實及理由\n一、本件犯罪事實及證據，均引用如附件檢察官聲請簡易判決處\n    刑書之記載。\n二、按安非他命、甲基安非他命為毒品危害防制條例第二條第二\n    項第二款所明定之第二級毒品。核被告所為，係犯毒品危害\n    防制條例第十條第二項之施用第二級毒品罪。被告於施用前\n    後持有第二級毒品之低度行為，為其施用之高度行為所吸收\n    ，不另論罪。爰審酌被告前曾經觀察勒戒，猶不能戒絕施用\n    毒品而觸犯施用毒品罪，顯未衷心悛悔，漠視法令之禁制，\n    恣意濫用毒品，惟兼衡酌其施用毒品所生危害僅自戕健康，\n    於他人法益無重大危害，及犯後坦承犯行，態度尚佳等一切\n    情狀，量處如主文所示之刑，並諭知易科罰金之折算標準，\n    以資懲儆。至被告犯罪所用之玻璃球吸食器，並未扣案，且\n    亦無法證明為被告所有之物，故不予宣告沒收，併此敘明。\n三、據上論斷，應依刑事訴訟法第四百四十九條第一項前段、第\n    三項，毒品危害防制條例第十條第二項，刑法第十一條前段\n    、第四十一條第一項前段，逕以簡易判決處刑如主文。\n中    華    民    國   100    年    9     月    6     日\n                  刑事第九庭    法  官  徐淑芬\n以上正本證明與原本無異。\n如不服本判決應於收受送達後十日內向本院提出上訴書狀，並應\n敘述具體理由；其未敘述上訴理由者，應於上訴期間屆滿後二十\n日內向本院補提理由書（均須按他造當事人之人數附繕本）「切\n勿逕送上級法院」。\n                                書記官  劉郅享\n中    華    民    國   100    年    9     月    6     日\n附錄本案論罪科刑法條全文：\n毒品危害防制條例第十條\n施用第一級毒品者，處六月以上五年以下有期徒刑。\n施用第二級毒品者，處三年以下有期徒刑。\n臺灣臺北地方法院檢察署檢察官聲請簡易判決處刑書\n                                   100年度毒偵字第1764號\n    被      告  顏育科  男  35歲（民國○○年○月○日生）\n                        住臺北市○○區○○街３７號\n                        居臺北市○○區○○街３７號３樓\n                        國民身分證統一編號：Ｚ000000000號\n                        （現在臺北監獄執行中）\n上列被告因毒品危害防制條例案件，業經偵查終結，認宜聲請以\n簡易判決處刑，茲將犯罪事實及證據並所犯法條分敘如下：\n      犯罪事實\n一、顏育科於民國97年間因施用毒品案件，經臺灣臺北地方法院\n    以98年度毒聲字第50號裁定令入勒戒處所觀察、勒戒，因\n    認無繼續施用傾向，於98年4月23日執行完畢釋放，並經本\n    署檢察官以97年度毒偵字第3518號案為不起訴處分確定，詎\n    猶不知悔改，5年內復基於施用第二級毒品之犯意，於100年\n    4月24日晚間10時許，在臺北市○○區○○街37號3樓居所，\n    以將甲基安非他命放置在玻璃球吸食器內，再以打火機加熱\n    後吸食其煙霧之方式，施用第二級毒品甲基安非他命，嗣因\n    顏育科另案遭發佈通緝，為警於同年月26日上午11時30分許\n    ，在臺北市○○區○○街３７號前，當場緝獲，並經警採尿\n    送驗後而查悉上情。\n二、案經臺北市政府警察局大安分局報告偵辦。\n      證據並所犯法條\n一、上揭犯罪事實，業據被告顏育科坦承不諱，且被告為警查獲\n    後採尿送驗之結果，確呈甲基安非他命及安非他命陽性反應\n    ，有台灣尖端先進生技醫藥股份有限公司100年5月10日濫用\n    藥物檢驗報告1份在卷足參，被告犯嫌已堪認定。\n二、核被告顏育科所為，係犯毒品危害防制條例第10條第2項之\n    施用第二級毒品罪嫌。\n三、依刑事訴訟法第451條第1項聲請逕以簡易判決處刑。\n      此  致\n臺灣臺北地方法院\n中    華    民    國   100    年    6     月    21    日\n                              檢  察  官  張  銘  珠\n本件正本證明與原本無異\n中    華    民    國   100    年    6     月    29    日\n                              書  記  官  陳  勇  在\n附錄本案所犯法條全文：\n毒品危害防制條例第10條\n施用第一級毒品者，處 6 月以上 5 年以下有期徒刑。\n施用第二級毒品者，處 3 年以下有期徒刑。\n本件係依刑事訴訟法簡易程序辦理，法院簡易庭得不傳喚被告、\n輔佐人、告訴人、告發人等出庭即以簡易判決處刑；被告、被害\n人、告訴人等對告訴乃論案件如已達成民事和解而要撤回告訴或\n對非告訴乃論案件認有受傳喚到庭陳述意見之必要時，請即另以\n書狀向簡易法庭陳述或請求傳訊。",
  "structure": {
    "main": "顏育科施用第二級毒品，處有期徒刑伍月，如易科罰金，以新臺\n幣壹仟元折算壹日。",
    "fact": "一、本件犯罪事實及證據，均引用如附件檢察官聲請簡易判決處\n    刑書之記載。\n二、按安非他命、甲基安非他命為毒品危害防制條例第二條第二\n    項第二款所明定之第二級毒品。核被告所為，係犯毒品危害\n    防制條例第十條第二項之施用第二級毒品罪。被告於施用前\n    後持有第二級毒品之低度行為，為其施用之高度行為所吸收\n    ，不另論罪。爰審酌被告前曾經觀察勒戒，猶不能戒絕施用\n    毒品而觸犯施用毒品罪，顯未衷心悛悔，漠視法令之禁制，\n    恣意濫用毒品，惟兼衡酌其施用毒品所生危害僅自戕健康，\n    於他人法益無重大危害，及犯後坦承犯行，態度尚佳等一切\n    情狀，量處如主文所示之刑，並諭知易科罰金之折算標準，\n    以資懲儆。至被告犯罪所用之玻璃球吸食器，並未扣案，且\n    亦無法證明為被告所有之物，故不予宣告沒收，併此敘明。\n三、據上論斷，應依刑事訴訟法第四百四十九條第一項前段、第\n    三項，毒品危害防制條例第十條第二項，刑法第十一條前段\n    、第四十一條第一項前段，逕以簡易判決處刑如主文。",
    "reason": "一、本件犯罪事實及證據，均引用如附件檢察官聲請簡易判決處\n    刑書之記載。\n二、按安非他命、甲基安非他命為毒品危害防制條例第二條第二\n    項第二款所明定之第二級毒品。核被告所為，係犯毒品危害\n    防制條例第十條第二項之施用第二級毒品罪。被告於施用前\n    後持有第二級毒品之低度行為，為其施用之高度行為所吸收\n    ，不另論罪。爰審酌被告前曾經觀察勒戒，猶不能戒絕施用\n    毒品而觸犯施用毒品罪，顯未衷心悛悔，漠視法令之禁制，\n    恣意濫用毒品，惟兼衡酌其施用毒品所生危害僅自戕健康，\n    於他人法益無重大危害，及犯後坦承犯行，態度尚佳等一切\n    情狀，量處如主文所示之刑，並諭知易科罰金之折算標準，\n    以資懲儆。至被告犯罪所用之玻璃球吸食器，並未扣案，且\n    亦無法證明為被告所有之物，故不予宣告沒收，併此敘明。\n三、據上論斷，應依刑事訴訟法第四百四十九條第一項前段、第\n    三項，毒品危害防制條例第十條第二項，刑法第十一條前段\n    、第四十一條第一項前段，逕以簡易判決處刑如主文。"
  },
  "search": "臺灣臺北地方法院刑事簡易判決100年度簡字第2599號聲請人臺灣臺北地方法院檢察署檢察官被告顏育科上列被告因違反毒品危害防制條例案件，經檢察官聲請以簡易判決處刑（一○○年度毒偵字第一七六四號），本院判決如下：主文顏育科施用第二級毒品，處有期徒刑伍月，如易科罰金，以新臺幣壹仟元折算壹日。事實及理由一、本件犯罪事實及證據，均引用如附件檢察官聲請簡易判決處刑書之記載。二、按安非他命、甲基安非他命為毒品危害防制條例第二條第二項第二款所明定之第二級毒品。核被告所為，係犯毒品危害防制條例第十條第二項之施用第二級毒品罪。被告於施用前後持有第二級毒品之低度行為，為其施用之高度行為所吸收，不另論罪。爰審酌被告前曾經觀察勒戒，猶不能戒絕施用毒品而觸犯施用毒品罪，顯未衷心悛悔，漠視法令之禁制，恣意濫用毒品，惟兼衡酌其施用毒品所生危害僅自戕健康，於他人法益無重大危害，及犯後坦承犯行，態度尚佳等一切情狀，量處如主文所示之刑，並諭知易科罰金之折算標準，以資懲儆。至被告犯罪所用之玻璃球吸食器，並未扣案，且亦無法證明為被告所有之物，故不予宣告沒收，併此敘明。三、據上論斷，應依刑事訴訟法第四百四十九條第一項前段、第三項，毒品危害防制條例第十條第二項，刑法第十一條前段、第四十一條第一項前段，逕以簡易判決處刑如主文。中華民國100年9月6日刑事第九庭法官徐淑芬以上正本證明與原本無異。如不服本判決應於收受送達後十日內向本院提出上訴書狀，並應敘述具體理由；其未敘述上訴理由者，應於上訴期間屆滿後二十日內向本院補提理由書（均須按他造當事人之人數附繕本）「切勿逕送上級法院」。書記官劉郅享中華民國100年9月6日附錄本案論罪科刑法條全文：毒品危害防制條例第十條施用第一級毒品者，處六月以上五年以下有期徒刑。施用第二級毒品者，處三年以下有期徒刑。臺灣臺北地方法院檢察署檢察官聲請簡易判決處刑書100年度毒偵字第1764號被告顏育科男35歲（民國○○年○月○日生）住臺北市○○區○○街３７號居臺北市○○區○○街３７號３樓國民身分證統一編號：Ｚ000000000號（現在臺北監獄執行中）上列被告因毒品危害防制條例案件，業經偵查終結，認宜聲請以簡易判決處刑，茲將犯罪事實及證據並所犯法條分敘如下：犯罪事實一、顏育科於民國97年間因施用毒品案件，經臺灣臺北地方法院以98年度毒聲字第50號裁定令入勒戒處所觀察、勒戒，因認無繼續施用傾向，於98年4月23日執行完畢釋放，並經本署檢察官以97年度毒偵字第3518號案為不起訴處分確定，詎猶不知悔改，5年內復基於施用第二級毒品之犯意，於100年4月24日晚間10時許，在臺北市○○區○○街37號3樓居所，以將甲基安非他命放置在玻璃球吸食器內，再以打火機加熱後吸食其煙霧之方式，施用第二級毒品甲基安非他命，嗣因顏育科另案遭發佈通緝，為警於同年月26日上午11時30分許，在臺北市○○區○○街３７號前，當場緝獲，並經警採尿送驗後而查悉上情。二、案經臺北市政府警察局大安分局報告偵辦。證據並所犯法條一、上揭犯罪事實，業據被告顏育科坦承不諱，且被告為警查獲後採尿送驗之結果，確呈甲基安非他命及安非他命陽性反應，有台灣尖端先進生技醫藥股份有限公司100年5月10日濫用藥物檢驗報告1份在卷足參，被告犯嫌已堪認定。二、核被告顏育科所為，係犯毒品危害防制條例第10條第2項之施用第二級毒品罪嫌。三、依刑事訴訟法第451條第1項聲請逕以簡易判決處刑。此致臺灣臺北地方法院中華民國100年6月21日檢察官張銘珠本件正本證明與原本無異中華民國100年6月29日書記官陳勇在附錄本案所犯法條全文：毒品危害防制條例第10條施用第一級毒品者，處6月以上5年以下有期徒刑。施用第二級毒品者，處3年以下有期徒刑。本件係依刑事訴訟法簡易程序辦理，法院簡易庭得不傳喚被告、輔佐人、告訴人、告發人等出庭即以簡易判決處刑；被告、被害人、告訴人等對告訴乃論案件如已達成民事和解而要撤回告訴或對非告訴乃論案件認有受傳喚到庭陳述意見之必要時，請即另以書狀向簡易法庭陳述或請求傳訊。",
  "characters": {
    "judges": [
      "徐淑芬"
    ],
    "prosecutors": [

    ],
    "lawyers": [

    ],
    "clerks": [
      "劉郅享"
    ],
    "plaintiffs": [

    ],
    "defendants": [
      "顏育科",
      "顏育科  男  35歲（民國○○年○月○日生）"
    ],
    "prosecutor_office": [
      "臺灣臺北地方法院檢察署檢察官"
    ],
    "creditors": [

    ],
    "debtors": [

    ],
    "judicial_associate_officer": [

    ]
  },
  "adjudged_at": "2011-09-06",
  "created_at": "2016-02-12 14:30:55",
  "updated_at": "2016-02-12 14:30:55"
}