{
  "identify": "TCH-100-抗-204-20110530-1",
  "court": {
    "name": "臺灣高等法院",
    "code": "TCH"
  },
  "division": {
    "name": "民事",
    "code": "V"
  },
  "year": 100,
  "word": "抗",
  "number": "204",
  "jcheck": "1",
  "reason": "聲明異議",
  "content": "臺灣高等法院臺中分院民事裁定  100年度抗字第204號\n抗  告  人  蔡元仁\n相  對  人  張豐猷\n上列抗告人因與相對人間確定執行費用額事件，對於中華民國\n100年3月29日臺灣彰化地方法院100年度事聲字第32號裁定提起\n抗告，本院裁定如下：\n    主  文\n抗告駁回。\n抗告程序費用由抗告人負擔。\n    理  由\n一、原裁定意旨略以：原審法院99年度司執字第43637號強制執\n    行事件，相對人聲請抗告人遷讓房屋之執行費用70,131元，\n    已有自行收納款項統一收據附於前揭執行卷宗可查。又兩造\n    於99年10月28日於原審法院99年度訴字第800號遷讓房屋事\n    件成立訴訟上和解時，和解筆錄所記載「訴訟費用各自分擔\n    」，係指該訴訟事件所產生之訴訟費用各自分擔，並不包含\n    將來之執行費用，故抗告人以當初和解契約約定訴訟費用各\n    自分擔，即認本件執行費用亦應各自負擔，顯然有誤。再兩\n    造雖成立前揭訴訟上和解，然因抗告人並未依和解契約內容\n    自動履行拆遷義務，經相對人聲請強制執行，而支出強制執\n    行費用70,131元，則此強制執行費用70,131元，自應由抗告\n    人負擔。至抗告人雖又主張電線、大燈及鐵架非其所有云云\n    ，惟查，前揭和解筆錄內已記載抗告人願將其所有電線、大\n    燈及鐵架遷出，故抗告人事後又翻稱電線、大燈及鐵架非其\n    所有云云，顯然無據，故抗告人本件聲明異議為無理由，應\n    予駁回等語。\n二、本院審酌原審裁定理由，並無不當。又按提起抗告，應表明\n    抗告理由，民事訴訟法第488條第3項定有明文。本件抗告人\n    前雖提出抗告狀，對於原裁定聲明不服，惟經本院於100年5\n    月9日函命抗告人補正抗告理由後，抗告人迄未補具任何不\n    服原裁定之抗告理由，致本院無從予以審酌，應認其抗告為\n    無理由，應予駁回。\n三、據上論結，本件抗告為無理由，依強制執行法第30條之1，\n    民事訴訟法第495條之1第1項、第449條第1項、第95條、第7\n    8條，裁定如主文。\n中    華    民    國   100    年    5     月    30    日\n                民事第七庭    審判長法  官  饒鴻鵬\n                                    法  官  張瑞蘭\n                                    法  官  陳毓秀\n以上正本係照原本作成。\n再為抗告應以適用法規顯有錯誤為理由。\n如提起再抗告者應於裁定送達後10日內向本院提出抗告理由狀（\n須按照他造人數附具繕本）並繳納抗告裁判費新臺幣1,000元，\n同時委任律師或具有律師資格之關係人為代理人。\n                                    書記官  高勳楠\n中    華    民    國   100    年    5     月    31    日\n                                                      Ｓ",
  "structure": {
    "main": "抗告駁回。\n抗告程序費用由抗告人負擔。",
    "reason": "一、原裁定意旨略以：原審法院99年度司執字第43637號強制執\n    行事件，相對人聲請抗告人遷讓房屋之執行費用70,131元，\n    已有自行收納款項統一收據附於前揭執行卷宗可查。又兩造\n    於99年10月28日於原審法院99年度訴字第800號遷讓房屋事\n    件成立訴訟上和解時，和解筆錄所記載「訴訟費用各自分擔\n    」，係指該訴訟事件所產生之訴訟費用各自分擔，並不包含\n    將來之執行費用，故抗告人以當初和解契約約定訴訟費用各\n    自分擔，即認本件執行費用亦應各自負擔，顯然有誤。再兩\n    造雖成立前揭訴訟上和解，然因抗告人並未依和解契約內容\n    自動履行拆遷義務，經相對人聲請強制執行，而支出強制執\n    行費用70,131元，則此強制執行費用70,131元，自應由抗告\n    人負擔。至抗告人雖又主張電線、大燈及鐵架非其所有云云\n    ，惟查，前揭和解筆錄內已記載抗告人願將其所有電線、大\n    燈及鐵架遷出，故抗告人事後又翻稱電線、大燈及鐵架非其\n    所有云云，顯然無據，故抗告人本件聲明異議為無理由，應\n    予駁回等語。\n二、本院審酌原審裁定理由，並無不當。又按提起抗告，應表明\n    抗告理由，民事訴訟法第488條第3項定有明文。本件抗告人\n    前雖提出抗告狀，對於原裁定聲明不服，惟經本院於100年5\n    月9日函命抗告人補正抗告理由後，抗告人迄未補具任何不\n    服原裁定之抗告理由，致本院無從予以審酌，應認其抗告為\n    無理由，應予駁回。\n三、據上論結，本件抗告為無理由，依強制執行法第30條之1，\n    民事訴訟法第495條之1第1項、第449條第1項、第95條、第7\n    8條，裁定如主文。"
  },
  "search": "臺灣高等法院臺中分院民事裁定100年度抗字第204號抗告人蔡元仁相對人張豐猷上列抗告人因與相對人間確定執行費用額事件，對於中華民國100年3月29日臺灣彰化地方法院100年度事聲字第32號裁定提起抗告，本院裁定如下：主文抗告駁回。抗告程序費用由抗告人負擔。理由一、原裁定意旨略以：原審法院99年度司執字第43637號強制執行事件，相對人聲請抗告人遷讓房屋之執行費用70,131元，已有自行收納款項統一收據附於前揭執行卷宗可查。又兩造於99年10月28日於原審法院99年度訴字第800號遷讓房屋事件成立訴訟上和解時，和解筆錄所記載「訴訟費用各自分擔」，係指該訴訟事件所產生之訴訟費用各自分擔，並不包含將來之執行費用，故抗告人以當初和解契約約定訴訟費用各自分擔，即認本件執行費用亦應各自負擔，顯然有誤。再兩造雖成立前揭訴訟上和解，然因抗告人並未依和解契約內容自動履行拆遷義務，經相對人聲請強制執行，而支出強制執行費用70,131元，則此強制執行費用70,131元，自應由抗告人負擔。至抗告人雖又主張電線、大燈及鐵架非其所有云云，惟查，前揭和解筆錄內已記載抗告人願將其所有電線、大燈及鐵架遷出，故抗告人事後又翻稱電線、大燈及鐵架非其所有云云，顯然無據，故抗告人本件聲明異議為無理由，應予駁回等語。二、本院審酌原審裁定理由，並無不當。又按提起抗告，應表明抗告理由，民事訴訟法第488條第3項定有明文。本件抗告人前雖提出抗告狀，對於原裁定聲明不服，惟經本院於100年5月9日函命抗告人補正抗告理由後，抗告人迄未補具任何不服原裁定之抗告理由，致本院無從予以審酌，應認其抗告為無理由，應予駁回。三、據上論結，本件抗告為無理由，依強制執行法第30條之1，民事訴訟法第495條之1第1項、第449條第1項、第95條、第78條，裁定如主文。中華民國100年5月30日民事第七庭審判長法官饒鴻鵬法官張瑞蘭法官陳毓秀以上正本係照原本作成。再為抗告應以適用法規顯有錯誤為理由。如提起再抗告者應於裁定送達後10日內向本院提出抗告理由狀（須按照他造人數附具繕本）並繳納抗告裁判費新臺幣1,000元，同時委任律師或具有律師資格之關係人為代理人。書記官高勳楠中華民國100年5月31日Ｓ",
  "characters": {
    "judges": [
      "饒鴻鵬",
      "張瑞蘭",
      "陳毓秀"
    ],
    "prosecutors": [

    ],
    "lawyers": [
      "同時委任律師或具有"
    ],
    "clerks": [
      "高勳楠"
    ],
    "plaintiffs": [

    ],
    "defendants": [

    ],
    "prosecutor_office": [

    ],
    "creditors": [

    ],
    "debtors": [

    ],
    "judicial_associate_officer": [

    ]
  },
  "adjudged_at": "2011-05-30",
  "created_at": "2016-02-12 02:39:26",
  "updated_at": "2016-02-12 02:39:26"
}