{
  "identify": "TYD-100-易-362-20110530-1",
  "court": {
    "name": "臺灣桃園地方法院",
    "code": "TYD"
  },
  "division": {
    "name": "刑事",
    "code": "M"
  },
  "year": 100,
  "word": "易",
  "number": "362",
  "jcheck": "1",
  "reason": "毀損",
  "content": "臺灣桃園地方法院刑事判決              100年度易字第362號\n公  訴  人  臺灣桃園地方法院檢察署檢察官\n被      告  袁明昌\n選任辯護人  陳俊隆律師\n            林永祥律師\n上列被告因毀損案件，經檢察官提起公訴（99年度偵字第25603號\n），本院判決如下：\n    主  文\n本件公訴不受理。\n    理  由\n一、本件公訴意旨略以：被告袁明昌因不滿其前妻曾馨誼於民國\n    96 年10 月30日過戶出賣曾馨誼所有座落在桃園縣桃園市○\n    ○路○ 段121 之3 號3 樓房地予黎萬雄，明知上開房屋所有\n    權人為他人，竟基於毀損他人所有物之犯意，於99年7 月15\n    日交屋前不詳時間，接續在上址房屋內，以朱紅色、藍灰色\n    、白色等油漆潑灑在該房屋內之牆壁、地板、插座、電源開\n    關、手把、衛浴設備、衣櫥、大門及窗戶等處所，致令上開\n    物品外形、效用發生顯著不良之改變，且遭受污損而不堪使\n    用，足生損害於黎萬雄。嗣於99年7 月15日被告袁明昌依法\n    院調解意旨，將前揭房屋之鑰匙寄送與曾馨誼實際交易之楊\n    勝發，經楊勝發到場查看，始悉上情。因認被告涉犯刑法第\n    354 條之毀損罪嫌等語。\n二、惟按告訴乃論之罪，告訴人於第一審言詞辯論終結前得撤回\n    其告訴，告訴經撤回者，法院應諭知不受理之判決，並得不\n    經言詞辯論為之，刑事訴訟法第238 條第1 項、第303 條第\n    3 款及第307 條分別定有明文。經查，本件被告被訴涉犯刑\n    法第354 條之毀損罪，依同法第357 條之規定，須告訴乃論\n    ，而被告與告訴人黎萬雄業已於100 年5 月20日於本院調解\n    成立，告訴人並於同日具狀撤回告訴，有訊問筆錄及調解單\n    各1 份、刑事撤回告訴狀1 紙在卷可參，揆諸前開法律規定\n    ，本件爰不經言詞辯論，逕行諭知不受理之判決。\n三、據上論斷，應依刑事訴訟法第303 條第3 款、第307 條，判\n    決如主文。\n中    華    民    國    100     年    5     月   30    日\n                  刑事第十二庭審判長法  官  許雅婷\n                                    法  官  陳威帆\n                                    法  官  黃裕民\n以上正本證明與原本無異。\n如不服本判決應於收受判決後10日內向本院提出上訴書狀，並應\n敘述具體理由。其未敘述上訴理由者，應於上訴期間屆滿後20日\n內向本院補提理由書( 均須按他造當事人之人數附繕本) 「切勿\n逕送上級法院」。\n                                    書記官  蕭秀蓉\n中    華    民    國   100    年    5     月    30    日",
  "structure": {
    "main": "本件公訴不受理。",
    "reason": "一、本件公訴意旨略以：被告袁明昌因不滿其前妻曾馨誼於民國\n    96 年10 月30日過戶出賣曾馨誼所有座落在桃園縣桃園市○\n    ○路○ 段121 之3 號3 樓房地予黎萬雄，明知上開房屋所有\n    權人為他人，竟基於毀損他人所有物之犯意，於99年7 月15\n    日交屋前不詳時間，接續在上址房屋內，以朱紅色、藍灰色\n    、白色等油漆潑灑在該房屋內之牆壁、地板、插座、電源開\n    關、手把、衛浴設備、衣櫥、大門及窗戶等處所，致令上開\n    物品外形、效用發生顯著不良之改變，且遭受污損而不堪使\n    用，足生損害於黎萬雄。嗣於99年7 月15日被告袁明昌依法\n    院調解意旨，將前揭房屋之鑰匙寄送與曾馨誼實際交易之楊\n    勝發，經楊勝發到場查看，始悉上情。因認被告涉犯刑法第\n    354 條之毀損罪嫌等語。\n二、惟按告訴乃論之罪，告訴人於第一審言詞辯論終結前得撤回\n    其告訴，告訴經撤回者，法院應諭知不受理之判決，並得不\n    經言詞辯論為之，刑事訴訟法第238 條第1 項、第303 條第\n    3 款及第307 條分別定有明文。經查，本件被告被訴涉犯刑\n    法第354 條之毀損罪，依同法第357 條之規定，須告訴乃論\n    ，而被告與告訴人黎萬雄業已於100 年5 月20日於本院調解\n    成立，告訴人並於同日具狀撤回告訴，有訊問筆錄及調解單\n    各1 份、刑事撤回告訴狀1 紙在卷可參，揆諸前開法律規定\n    ，本件爰不經言詞辯論，逕行諭知不受理之判決。\n三、據上論斷，應依刑事訴訟法第303 條第3 款、第307 條，判\n    決如主文。"
  },
  "search": "臺灣桃園地方法院刑事判決100年度易字第362號公訴人臺灣桃園地方法院檢察署檢察官被告袁明昌選任辯護人陳俊隆律師林永祥律師上列被告因毀損案件，經檢察官提起公訴（99年度偵字第25603號），本院判決如下：主文本件公訴不受理。理由一、本件公訴意旨略以：被告袁明昌因不滿其前妻曾馨誼於民國96年10月30日過戶出賣曾馨誼所有座落在桃園縣桃園市○○路○段121之3號3樓房地予黎萬雄，明知上開房屋所有權人為他人，竟基於毀損他人所有物之犯意，於99年7月15日交屋前不詳時間，接續在上址房屋內，以朱紅色、藍灰色、白色等油漆潑灑在該房屋內之牆壁、地板、插座、電源開關、手把、衛浴設備、衣櫥、大門及窗戶等處所，致令上開物品外形、效用發生顯著不良之改變，且遭受污損而不堪使用，足生損害於黎萬雄。嗣於99年7月15日被告袁明昌依法院調解意旨，將前揭房屋之鑰匙寄送與曾馨誼實際交易之楊勝發，經楊勝發到場查看，始悉上情。因認被告涉犯刑法第354條之毀損罪嫌等語。二、惟按告訴乃論之罪，告訴人於第一審言詞辯論終結前得撤回其告訴，告訴經撤回者，法院應諭知不受理之判決，並得不經言詞辯論為之，刑事訴訟法第238條第1項、第303條第3款及第307條分別定有明文。經查，本件被告被訴涉犯刑法第354條之毀損罪，依同法第357條之規定，須告訴乃論，而被告與告訴人黎萬雄業已於100年5月20日於本院調解成立，告訴人並於同日具狀撤回告訴，有訊問筆錄及調解單各1份、刑事撤回告訴狀1紙在卷可參，揆諸前開法律規定，本件爰不經言詞辯論，逕行諭知不受理之判決。三、據上論斷，應依刑事訴訟法第303條第3款、第307條，判決如主文。中華民國100年5月30日刑事第十二庭審判長法官許雅婷法官陳威帆法官黃裕民以上正本證明與原本無異。如不服本判決應於收受判決後10日內向本院提出上訴書狀，並應敘述具體理由。其未敘述上訴理由者，應於上訴期間屆滿後20日內向本院補提理由書(均須按他造當事人之人數附繕本)「切勿逕送上級法院」。書記官蕭秀蓉中華民國100年5月30日",
  "characters": {
    "judges": [
      "許雅婷",
      "陳威帆",
      "黃裕民"
    ],
    "prosecutors": [

    ],
    "lawyers": [
      "陳俊隆",
      "林永祥"
    ],
    "clerks": [
      "蕭秀蓉"
    ],
    "plaintiffs": [

    ],
    "defendants": [
      "袁明昌"
    ],
    "prosecutor_office": [
      "臺灣桃園地方法院檢察署檢察官"
    ],
    "creditors": [

    ],
    "debtors": [

    ],
    "judicial_associate_officer": [

    ]
  },
  "adjudged_at": "2011-05-30",
  "created_at": "2016-02-12 02:38:40",
  "updated_at": "2016-02-12 02:38:40"
}