{
  "identify": "CYD-92-易-449-20040324-1",
  "court": {
    "name": "臺灣嘉義地方法院",
    "code": "CYD"
  },
  "division": {
    "name": "刑事",
    "code": "M"
  },
  "year": 92,
  "word": "易",
  "number": "449",
  "jcheck": "1",
  "reason": "詐欺",
  "content": "臺灣嘉義地方法院刑事裁定                          九十二年度易字第四四九號\n    公  訴  人  臺灣嘉義地方法院檢察署檢察官\n    被      告  甲○○\n右列被告因詐欺案件，本院裁定如左：\n    主  文\n甲○○自民國玖拾年月貳拾玖日起，延長羈押貳月。\n    理  由\n被告甲○○因詐欺案件，經本院認為罪嫌重大，有並有羈押之必要，依刑事訴訟法第\n一百零一條第一項第一款規定，於民國九十二年十二月二十九日執行羈押，茲本院以\n羈押期間，即將屆滿，羈押原因仍然存在，認有繼續羈押之必要，應自民國九十三年\n三月二十九日起，再予延長羈押二月，爰依刑事訴訟法第一百零八條第一項、第二項\n，裁定如主文。\n中      華      民      國    九十三    年      三      月    二十四    日\n                            臺灣嘉義地方法院刑事第五庭\n                                審判長  法  官  黃國益\n                                        法  官  黃義成\n                                        法  官  黃仁勇\n右正本証明與原本無異。\n如不服本裁定，應於送達後五日內，向本院提出抗告狀。\n中      華      民      國    九十三    年      三      月    二十四    日\n                                        書記官  呂權芳\n",
  "structure": {
    "main": "甲○○自民國玖拾年月貳拾玖日起，延長羈押貳月。",
    "reason": "被告甲○○因詐欺案件，經本院認為罪嫌重大，有並有羈押之必要，依刑事訴訟法第\n一百零一條第一項第一款規定，於民國九十二年十二月二十九日執行羈押，茲本院以\n羈押期間，即將屆滿，羈押原因仍然存在，認有繼續羈押之必要，應自民國九十三年\n三月二十九日起，再予延長羈押二月，爰依刑事訴訟法第一百零八條第一項、第二項\n，裁定如主文。"
  },
  "search": "臺灣嘉義地方法院刑事裁定九十二年度易字第四四九號公訴人臺灣嘉義地方法院檢察署檢察官被告甲○○右列被告因詐欺案件，本院裁定如左：主文甲○○自民國玖拾年月貳拾玖日起，延長羈押貳月。理由被告甲○○因詐欺案件，經本院認為罪嫌重大，有並有羈押之必要，依刑事訴訟法第一百零一條第一項第一款規定，於民國九十二年十二月二十九日執行羈押，茲本院以羈押期間，即將屆滿，羈押原因仍然存在，認有繼續羈押之必要，應自民國九十三年三月二十九日起，再予延長羈押二月，爰依刑事訴訟法第一百零八條第一項、第二項，裁定如主文。中華民國九十三年三月二十四日臺灣嘉義地方法院刑事第五庭審判長法官黃國益法官黃義成法官黃仁勇右正本証明與原本無異。如不服本裁定，應於送達後五日內，向本院提出抗告狀。中華民國九十三年三月二十四日書記官呂權芳",
  "characters": {
    "judges": [
      "黃國益",
      "黃義成",
      "黃仁勇"
    ],
    "prosecutors": [

    ],
    "lawyers": [

    ],
    "clerks": [
      "呂權芳"
    ],
    "plaintiffs": [

    ],
    "defendants": [
      "甲○○",
      "右列被告因詐欺案件，本院裁定如左："
    ],
    "prosecutor_office": [
      "臺灣嘉義地方法院檢察署檢察官"
    ],
    "creditors": [

    ],
    "debtors": [

    ],
    "judicial_associate_officer": [

    ]
  },
  "adjudged_at": "2004-03-24",
  "created_at": "2016-02-06 11:25:09",
  "updated_at": "2016-02-06 11:25:09"
}