{
  "identify": "KSD-94-易-349-20050331-1",
  "court": {
    "name": "臺灣高雄地方法院",
    "code": "KSD"
  },
  "division": {
    "name": "刑事",
    "code": "M"
  },
  "year": 94,
  "word": "易",
  "number": "349",
  "jcheck": "1",
  "reason": "毒品危害防制條例",
  "content": "臺灣高雄地方法院刑事判決               94年度易字第349號\n公  訴  人  臺灣高雄地方法院檢察署檢察官李廷輝\n被      告  甲○○  男  41歲.\n上列被告因毒品危害防制條例案件，經檢察官提起公訴（93年度\n毒偵字第7607號），被告於準備程序進行中就被訴事實為有罪之\n陳述，本院聽取當事人之意見後，裁定改以簡式審判程序審理，\n本院判決如左：\n    主  文\n甲○○持有第一級毒品，累犯，處有期徒刑伍月，如易科罰金，\n以參佰元折算壹日。\n扣案第一級毒品海洛因伍包（驗後淨重合計陸點玖陸公克，包裝\n重合計肆點貳肆公克），沒收銷燬之。\n    事  實\n一、甲○○前曾於民國85年1月間因違反麻醉藥品管理條例等案\n    件，經法院各判處有期徒刑8月、2年8月確定，嗣合併執行\n    有期徒刑3年，於91年4月26日執行完畢。詎甲○○仍未悔改\n    ，復基於持有第一級毒品海洛因之犯意，於93年3月18日上\n    午某時，在高雄縣鳳山市○○街91號住處，受友人真實年籍\n    不詳之成年男子綽號「白目榮」之託，代為保管第一級毒品\n    海洛因粉末五包（驗後淨重合計陸點玖陸公克，包裝重合計\n    肆點貳肆公克）而非法持有之，並藏置於高雄縣鳳山市○○\n    街91號住處房間桌子及小皮包內，嗣為警於93年3月18日下\n    午2時30分許，在高雄縣鳳山市○○街91號住處查獲，並扣\n    得第一級毒品海洛因粉末五包（驗後淨重合計陸點玖陸公克\n    ，包裝重合計肆點貳肆公克）。\n二、案經內政部警政署保安警察隊報告臺灣高雄地方法院檢察署\n    檢察官偵查起訴。\n    理  由\n壹、程序部分：\n    本件被告甲○○所犯係死刑、無期徒刑、最輕本刑為三年以\n    上有期徒刑以外之罪，其於準備程序中就被訴事實為有罪之\n    陳述，經法官告知簡式審判程序之旨，並聽取公訴人、被告\n    之意見後，本院認為適宜獨任進行簡式審判程序，故本件適\n    用簡式審判程序審理，合先敘明。\n貳、\n  一、右揭犯罪事實，業據被告於本院審理時坦承不諱（參見本\n      院審理卷第30頁），復有扣案疑似海洛因粉末五包（驗\n      後淨重合計陸點玖陸公克，包裝重合計肆點貳肆公克）經\n      局93 年5月6日編號000000000號鑑定通知書一紙附卷可憑\n      （參見偵查卷第21頁），被告自白與事實相符，堪信為真\n      實。本件事證相確，被告持有第一級毒品海洛因之犯行應\n      依法論科。\n  二、查海洛因為毒品危害防制條例第二條第二項第一款明定之\n      第一級毒品，本件被告持有海洛因粉末五小包之行為，係\n      犯毒品危害防制條例第十一條第一項之持有第一級毒品罪\n      。末查，被告曾於八十五年一月間因違反麻醉藥品管理條\n      例等案件，經法院各判處有期徒刑八月、二年八月確定，\n      嗣合併執行有期徒刑三年，於九十一年四月二十六日執行\n      完畢，有臺灣高等法院被告全國前案紀錄表可參，其於執\n      行完畢後五年內再犯本件犯行，為累犯，應依刑法第四十\n      七條之規定加重其刑。又修正後毒品危害防制條例於第十\n      一條增列第四項規定持有毒品達一定數量者，加重其刑至\n      二分之一，其標準由行政院定之。行政院嗣於九十三年一\n      月七日依前揭授權訂定公布持有第一級毒品淨重（指除去\n      包裝後之毒品重量）五公克以上者，需加重其刑至二分之\n      一，被告今持有海洛因五小包，驗後淨重合計達陸點玖陸\n      公克，有上開法務部調查局鑑定通知書一分在卷可查，爰\n      依上開規定遞加重之。爰審酌被告明知不得擅自持有毒品\n      仍持有之，行為誠屬不當，惟念及所犯情節尚輕，並未危\n      害他人且犯後坦承犯行等一切情狀，量處如主文所示之刑\n      ，並諭知易科罰金之折算標準。扣案之第一級毒品海洛因\n      粉五小包（驗後淨重合計陸點玖陸公克，包裝重合計肆點\n      貳肆公克）應依毒品危害防制條例第十八條第一項前段之\n      規定，沒收銷燬之。\n據上論斷，應依刑事訴訟法第二百九十九條第一項前段，毒品危\n害防制條例第十一條條第一項、第四項、第十八條第一項前段，\n刑法第十一條、第四十七條，罰金罰鍰提高標準條例第一條前段\n、第二條，判決如主文。\n本案經檢察官李廷輝到庭執行職務\n中      華      民      國    94  年   3   月   31    日\n                           鳳山刑事第二庭\n                           法  官  廖建瑜\n以上正本證明與原本無異。\n如不服本判決，應於收受送達後10日內向本院提出上訴書狀。\n                           書記官  王世雄\n中      華      民      國    94  年   3   月   31    日\n附錄本判決論罪法條\n毒品危害防制條例第10條\n施用第一級毒品者，處 6 月以上 5 年以下有期徒刑。\n",
  "structure": {
    "main": "甲○○持有第一級毒品，累犯，處有期徒刑伍月，如易科罰金，\n以參佰元折算壹日。\n扣案第一級毒品海洛因伍包（驗後淨重合計陸點玖陸公克，包裝\n重合計肆點貳肆公克），沒收銷燬之。",
    "fact": "一、甲○○前曾於民國85年1月間因違反麻醉藥品管理條例等案\n    件，經法院各判處有期徒刑8月、2年8月確定，嗣合併執行\n    有期徒刑3年，於91年4月26日執行完畢。詎甲○○仍未悔改\n    ，復基於持有第一級毒品海洛因之犯意，於93年3月18日上\n    午某時，在高雄縣鳳山市○○街91號住處，受友人真實年籍\n    不詳之成年男子綽號「白目榮」之託，代為保管第一級毒品\n    海洛因粉末五包（驗後淨重合計陸點玖陸公克，包裝重合計\n    肆點貳肆公克）而非法持有之，並藏置於高雄縣鳳山市○○\n    街91號住處房間桌子及小皮包內，嗣為警於93年3月18日下\n    午2時30分許，在高雄縣鳳山市○○街91號住處查獲，並扣\n    得第一級毒品海洛因粉末五包（驗後淨重合計陸點玖陸公克\n    ，包裝重合計肆點貳肆公克）。\n二、案經內政部警政署保安警察隊報告臺灣高雄地方法院檢察署\n    檢察官偵查起訴。",
    "reason": "壹、程序部分：\n    本件被告甲○○所犯係死刑、無期徒刑、最輕本刑為三年以\n    上有期徒刑以外之罪，其於準備程序中就被訴事實為有罪之\n    陳述，經法官告知簡式審判程序之旨，並聽取公訴人、被告\n    之意見後，本院認為適宜獨任進行簡式審判程序，故本件適\n    用簡式審判程序審理，合先敘明。\n貳、\n  一、右揭犯罪事實，業據被告於本院審理時坦承不諱（參見本\n      院審理卷第30頁），復有扣案疑似海洛因粉末五包（驗\n      後淨重合計陸點玖陸公克，包裝重合計肆點貳肆公克）經\n      局93 年5月6日編號000000000號鑑定通知書一紙附卷可憑\n      （參見偵查卷第21頁），被告自白與事實相符，堪信為真\n      實。本件事證相確，被告持有第一級毒品海洛因之犯行應\n      依法論科。\n  二、查海洛因為毒品危害防制條例第二條第二項第一款明定之\n      第一級毒品，本件被告持有海洛因粉末五小包之行為，係\n      犯毒品危害防制條例第十一條第一項之持有第一級毒品罪\n      。末查，被告曾於八十五年一月間因違反麻醉藥品管理條\n      例等案件，經法院各判處有期徒刑八月、二年八月確定，\n      嗣合併執行有期徒刑三年，於九十一年四月二十六日執行\n      完畢，有臺灣高等法院被告全國前案紀錄表可參，其於執\n      行完畢後五年內再犯本件犯行，為累犯，應依刑法第四十\n      七條之規定加重其刑。又修正後毒品危害防制條例於第十\n      一條增列第四項規定持有毒品達一定數量者，加重其刑至\n      二分之一，其標準由行政院定之。行政院嗣於九十三年一\n      月七日依前揭授權訂定公布持有第一級毒品淨重（指除去\n      包裝後之毒品重量）五公克以上者，需加重其刑至二分之\n      一，被告今持有海洛因五小包，驗後淨重合計達陸點玖陸\n      公克，有上開法務部調查局鑑定通知書一分在卷可查，爰\n      依上開規定遞加重之。爰審酌被告明知不得擅自持有毒品\n      仍持有之，行為誠屬不當，惟念及所犯情節尚輕，並未危\n      害他人且犯後坦承犯行等一切情狀，量處如主文所示之刑\n      ，並諭知易科罰金之折算標準。扣案之第一級毒品海洛因\n      粉五小包（驗後淨重合計陸點玖陸公克，包裝重合計肆點\n      貳肆公克）應依毒品危害防制條例第十八條第一項前段之\n      規定，沒收銷燬之。\n據上論斷，應依刑事訴訟法第二百九十九條第一項前段，毒品危\n害防制條例第十一條條第一項、第四項、第十八條第一項前段，\n刑法第十一條、第四十七條，罰金罰鍰提高標準條例第一條前段\n、第二條，判決如主文。\n本案經檢察官李廷輝到庭執行職務\n中      華      民      國    94  年   3   月   31    日\n                           鳳山刑事第二庭\n                           法  官  廖建瑜\n以上正本證明與原本無異。\n如不服本判決，應於收受送達後10日內向本院提出上訴書狀。\n                           書記官  王世雄"
  },
  "search": "臺灣高雄地方法院刑事判決94年度易字第349號公訴人臺灣高雄地方法院檢察署檢察官李廷輝被告甲○○男41歲.上列被告因毒品危害防制條例案件，經檢察官提起公訴（93年度毒偵字第7607號），被告於準備程序進行中就被訴事實為有罪之陳述，本院聽取當事人之意見後，裁定改以簡式審判程序審理，本院判決如左：主文甲○○持有第一級毒品，累犯，處有期徒刑伍月，如易科罰金，以參佰元折算壹日。扣案第一級毒品海洛因伍包（驗後淨重合計陸點玖陸公克，包裝重合計肆點貳肆公克），沒收銷燬之。事實一、甲○○前曾於民國85年1月間因違反麻醉藥品管理條例等案件，經法院各判處有期徒刑8月、2年8月確定，嗣合併執行有期徒刑3年，於91年4月26日執行完畢。詎甲○○仍未悔改，復基於持有第一級毒品海洛因之犯意，於93年3月18日上午某時，在高雄縣鳳山市○○街91號住處，受友人真實年籍不詳之成年男子綽號「白目榮」之託，代為保管第一級毒品海洛因粉末五包（驗後淨重合計陸點玖陸公克，包裝重合計肆點貳肆公克）而非法持有之，並藏置於高雄縣鳳山市○○街91號住處房間桌子及小皮包內，嗣為警於93年3月18日下午2時30分許，在高雄縣鳳山市○○街91號住處查獲，並扣得第一級毒品海洛因粉末五包（驗後淨重合計陸點玖陸公克，包裝重合計肆點貳肆公克）。二、案經內政部警政署保安警察隊報告臺灣高雄地方法院檢察署檢察官偵查起訴。理由壹、程序部分：本件被告甲○○所犯係死刑、無期徒刑、最輕本刑為三年以上有期徒刑以外之罪，其於準備程序中就被訴事實為有罪之陳述，經法官告知簡式審判程序之旨，並聽取公訴人、被告之意見後，本院認為適宜獨任進行簡式審判程序，故本件適用簡式審判程序審理，合先敘明。貳、一、右揭犯罪事實，業據被告於本院審理時坦承不諱（參見本院審理卷第30頁），復有扣案疑似海洛因粉末五包（驗後淨重合計陸點玖陸公克，包裝重合計肆點貳肆公克）經局93年5月6日編號000000000號鑑定通知書一紙附卷可憑（參見偵查卷第21頁），被告自白與事實相符，堪信為真實。本件事證相確，被告持有第一級毒品海洛因之犯行應依法論科。二、查海洛因為毒品危害防制條例第二條第二項第一款明定之第一級毒品，本件被告持有海洛因粉末五小包之行為，係犯毒品危害防制條例第十一條第一項之持有第一級毒品罪。末查，被告曾於八十五年一月間因違反麻醉藥品管理條例等案件，經法院各判處有期徒刑八月、二年八月確定，嗣合併執行有期徒刑三年，於九十一年四月二十六日執行完畢，有臺灣高等法院被告全國前案紀錄表可參，其於執行完畢後五年內再犯本件犯行，為累犯，應依刑法第四十七條之規定加重其刑。又修正後毒品危害防制條例於第十一條增列第四項規定持有毒品達一定數量者，加重其刑至二分之一，其標準由行政院定之。行政院嗣於九十三年一月七日依前揭授權訂定公布持有第一級毒品淨重（指除去包裝後之毒品重量）五公克以上者，需加重其刑至二分之一，被告今持有海洛因五小包，驗後淨重合計達陸點玖陸公克，有上開法務部調查局鑑定通知書一分在卷可查，爰依上開規定遞加重之。爰審酌被告明知不得擅自持有毒品仍持有之，行為誠屬不當，惟念及所犯情節尚輕，並未危害他人且犯後坦承犯行等一切情狀，量處如主文所示之刑，並諭知易科罰金之折算標準。扣案之第一級毒品海洛因粉五小包（驗後淨重合計陸點玖陸公克，包裝重合計肆點貳肆公克）應依毒品危害防制條例第十八條第一項前段之規定，沒收銷燬之。據上論斷，應依刑事訴訟法第二百九十九條第一項前段，毒品危害防制條例第十一條條第一項、第四項、第十八條第一項前段，刑法第十一條、第四十七條，罰金罰鍰提高標準條例第一條前段、第二條，判決如主文。本案經檢察官李廷輝到庭執行職務中華民國94年3月31日鳳山刑事第二庭法官廖建瑜以上正本證明與原本無異。如不服本判決，應於收受送達後10日內向本院提出上訴書狀。書記官王世雄中華民國94年3月31日附錄本判決論罪法條毒品危害防制條例第10條施用第一級毒品者，處6月以上5年以下有期徒刑。",
  "characters": {
    "judges": [
      "廖建瑜"
    ],
    "prosecutors": [
      "李廷輝"
    ],
    "lawyers": [

    ],
    "clerks": [
      "王世雄"
    ],
    "plaintiffs": [

    ],
    "defendants": [
      "甲○○  男  41歲."
    ],
    "prosecutor_office": [
      "臺灣高雄地方法院檢察署檢察官李廷輝"
    ],
    "creditors": [

    ],
    "debtors": [

    ],
    "judicial_associate_officer": [

    ]
  },
  "adjudged_at": "2005-03-31",
  "created_at": "2016-02-07 07:55:20",
  "updated_at": "2016-02-07 07:55:20"
}