{
  "identify": "SCD-94-易-165-20050331-1",
  "court": {
    "name": "臺灣新竹地方法院",
    "code": "SCD"
  },
  "division": {
    "name": "刑事",
    "code": "M"
  },
  "year": 94,
  "word": "易",
  "number": "165",
  "jcheck": "1",
  "reason": "妨害婚姻",
  "content": "臺灣新竹地方法院刑事判決               94年度易字第165號\n公  訴  人  臺灣新竹地方法院檢察署檢察官\n被      告  乙○○  男  54歲.\n上列被告因妨害婚姻案件，經檢察官聲請簡易判決處刑（93年度\n調偵字第101號），本院改依通常程序審理並判決如下：\n    主   文\n本件公訴不受理。\n    理  由\n一、按告訴乃論之罪，告訴人於第一審辯論終結前得撤回其告訴\n    ，又告訴經撤回者，應諭知不受理之判決，並得不經言詞辯\n    論為之，刑事訴訟法第238條第1項、第303條第3款、第307\n    條定有明文。\n二、公訴意旨略以：被告乙○○係告訴人甲○○之夫，為有配偶\n    之人，於民國92年5月間，經由友人尹瑞英介紹而認識程慧\n    蘋，兩人遂於同年6月間開始交往，乙○○基於通姦之概括\n    犯意，自92年6月間起至同年7月間止，連續與不知情之程慧\n    蘋（程慧蘋涉相姦部分業經檢察官為不起訴處分確定），在\n    程慧蘋位於新竹縣竹東鎮○○路62號7樓住處內通姦二次，\n    甲○○旋於93年1月底發現程慧蘋對乙○○聲請之保護令而\n    知悉上情，因認被告乙○○涉犯刑法第239條前段之通姦罪\n    嫌等語。\n三、查本件告訴人甲○○告訴被告妨害婚姻案件，公訴人認係觸\n    犯刑法第239條前段之通姦罪，依同法第245條第1項之規定\n    ，須告訴乃論。茲據告訴人甲○○撤回其告訴，有撤回告訴\n    狀一件在卷可稽（見93年度調偵字第101號偵查卷第72頁）\n    ，依照首開說明，本件爰不經言詞辯論，逕為諭知不受理之\n    判決。\n四、據上論斷，應依刑事訴訟法第452條、第303條第3款、第307\n    條，判決如主文。\n中    華    民    國    94    年    3     月    31    日\n                  刑事第六庭審判長法  官  遲中慧\n                                  法  官  林昌義\n                                  法  官  魏瑞紅\n以上正本證明與原本無異。\n如不服本判決，應於判決送達後10日內向本院提出上訴狀（應附\n繕本），上訴於臺灣高等法院。\n中    華    民    國    94    年    4     月     1    日\n                                  書記官  陳凰榆\n",
  "structure": {
    "main": "本件公訴不受理。",
    "reason": "一、按告訴乃論之罪，告訴人於第一審辯論終結前得撤回其告訴\n    ，又告訴經撤回者，應諭知不受理之判決，並得不經言詞辯\n    論為之，刑事訴訟法第238條第1項、第303條第3款、第307\n    條定有明文。\n二、公訴意旨略以：被告乙○○係告訴人甲○○之夫，為有配偶\n    之人，於民國92年5月間，經由友人尹瑞英介紹而認識程慧\n    蘋，兩人遂於同年6月間開始交往，乙○○基於通姦之概括\n    犯意，自92年6月間起至同年7月間止，連續與不知情之程慧\n    蘋（程慧蘋涉相姦部分業經檢察官為不起訴處分確定），在\n    程慧蘋位於新竹縣竹東鎮○○路62號7樓住處內通姦二次，\n    甲○○旋於93年1月底發現程慧蘋對乙○○聲請之保護令而\n    知悉上情，因認被告乙○○涉犯刑法第239條前段之通姦罪\n    嫌等語。\n三、查本件告訴人甲○○告訴被告妨害婚姻案件，公訴人認係觸\n    犯刑法第239條前段之通姦罪，依同法第245條第1項之規定\n    ，須告訴乃論。茲據告訴人甲○○撤回其告訴，有撤回告訴\n    狀一件在卷可稽（見93年度調偵字第101號偵查卷第72頁）\n    ，依照首開說明，本件爰不經言詞辯論，逕為諭知不受理之\n    判決。\n四、據上論斷，應依刑事訴訟法第452條、第303條第3款、第307\n    條，判決如主文。"
  },
  "search": "臺灣新竹地方法院刑事判決94年度易字第165號公訴人臺灣新竹地方法院檢察署檢察官被告乙○○男54歲.上列被告因妨害婚姻案件，經檢察官聲請簡易判決處刑（93年度調偵字第101號），本院改依通常程序審理並判決如下：主文本件公訴不受理。理由一、按告訴乃論之罪，告訴人於第一審辯論終結前得撤回其告訴，又告訴經撤回者，應諭知不受理之判決，並得不經言詞辯論為之，刑事訴訟法第238條第1項、第303條第3款、第307條定有明文。二、公訴意旨略以：被告乙○○係告訴人甲○○之夫，為有配偶之人，於民國92年5月間，經由友人尹瑞英介紹而認識程慧蘋，兩人遂於同年6月間開始交往，乙○○基於通姦之概括犯意，自92年6月間起至同年7月間止，連續與不知情之程慧蘋（程慧蘋涉相姦部分業經檢察官為不起訴處分確定），在程慧蘋位於新竹縣竹東鎮○○路62號7樓住處內通姦二次，甲○○旋於93年1月底發現程慧蘋對乙○○聲請之保護令而知悉上情，因認被告乙○○涉犯刑法第239條前段之通姦罪嫌等語。三、查本件告訴人甲○○告訴被告妨害婚姻案件，公訴人認係觸犯刑法第239條前段之通姦罪，依同法第245條第1項之規定，須告訴乃論。茲據告訴人甲○○撤回其告訴，有撤回告訴狀一件在卷可稽（見93年度調偵字第101號偵查卷第72頁），依照首開說明，本件爰不經言詞辯論，逕為諭知不受理之判決。四、據上論斷，應依刑事訴訟法第452條、第303條第3款、第307條，判決如主文。中華民國94年3月31日刑事第六庭審判長法官遲中慧法官林昌義法官魏瑞紅以上正本證明與原本無異。如不服本判決，應於判決送達後10日內向本院提出上訴狀（應附繕本），上訴於臺灣高等法院。中華民國94年4月1日書記官陳凰榆",
  "characters": {
    "judges": [
      "遲中慧",
      "林昌義",
      "魏瑞紅"
    ],
    "prosecutors": [

    ],
    "lawyers": [

    ],
    "clerks": [
      "陳凰榆"
    ],
    "plaintiffs": [

    ],
    "defendants": [
      "乙○○  男  54歲."
    ],
    "prosecutor_office": [
      "臺灣新竹地方法院檢察署檢察官"
    ],
    "creditors": [

    ],
    "debtors": [

    ],
    "judicial_associate_officer": [

    ]
  },
  "adjudged_at": "2005-03-31",
  "created_at": "2016-02-07 08:06:10",
  "updated_at": "2016-02-07 08:06:10"
}