{
  "identify": "TCD-94-訴-2-20050331-1",
  "court": {
    "name": "臺灣臺中地方法院",
    "code": "TCD"
  },
  "division": {
    "name": "民事",
    "code": "V"
  },
  "year": 94,
  "word": "訴",
  "number": "2",
  "jcheck": "1",
  "reason": "清償借款",
  "content": "臺灣臺中地方法院民事判決  九十四年度訴字第二號\n    原      告  三信商業銀行股份有限公司\n    法定代理人  甲○○\n    訴訟代理人  丙○○\n    被      告  乙○○\n當事人間清償借款事件，本院於九十年三月十四日言詞辯論終結，判決如下：\n    主    文\n被告應給付原告新台幣壹佰壹拾萬零柒仟陸佰玖拾肆元，及自民國八十八年四月二十九日起\n至清償日止，按年息百分之九．六七計算之利息，並自民國八十八年五月三十日起至清償日\n止，其逾期在六個月以內者，按上開利率百分之十，逾期超過六個月以上者，按上開利率百\n分之二十計算之違約金。\n訴訟費用由被告負擔。\n    事實及理由\n一、依卷附兩造間授信約定書第十一條之約定，兩造已合意本件消費借貸之法律訟爭事件，\n    由本院為第一審管轄法院。又本件被告均未於言詞辯論期日到場，核無民事訴訟法第三\n    百八十六條各款所列情形，爰依原告之聲請，由其一造辯論而為判決，合先敘明。\n二、原告主張：訴外人尚品建設股份有限公司邀同訴外人李坤秀、李振昌及被告擔任連帶保\n    證人，於民國（下同）八十七年七月二十九日向原告借款新台幣（下同）一百五十萬元\n    ，約定到期日為九十年七月二十九日止，利息按年息百分之九．七五計付，並依原告之\n    基本放款利率變動而機動調整，每月按期付息，如有一次未依約履行，全部借款即視為\n    到期，除仍須支付利息外，逾期清償在六個月以內者，按上開利率百分之十，超過六個\n    月以上者，按上開利率百分之二十計付之違約金，訴外人尚品建設股份有限公司自八十\n    八年四月二十九日起即未再依約繳息，，迄今尚欠本金一百一十萬七千六百九十四元及\n    利息、違約金未為清償，爰依連帶保證之法律關係提起本件訴訟。並聲明：如主文第一\n    項所示。\n三、被告未於言詞辯論期日到場，亦未提出書狀作何聲明或陳述。\n四、得心證之理由：\n  (一)按當事人對於他造主張之事實，於言詞辯論時不爭執者，視同自認；當事人對於他造主\n    張之事實，已於相當時期受合法之通知，而於言詞辯論期日不到場，亦未提出準備書狀\n    爭執者，準用第一項之規定，民事訴訟法第二百八十條第一項、第三項分別定有明文。\n    本件原告主張之事實，已據其提出與所述相符之授信約定書、借據、連帶保證書及呆帳\n    登記簿各一紙等為證，被告經合法通知，既不於最後言詞辯論期日到庭爭執，復未提出\n    書狀以供本院斟酌，故原告上開主張，自堪信為真實。\n  (二)綜上所述，原告依連帶保證之法律關係請求被告給付一百一十萬七千六百九十四元，及\n    自八十八年四月二十九日起，至清償日止，按年息百分之九．六七計算之利息，並自民\n    國八十八年五月三十日起，至清償日止，其逾期在六個月以內者，按上開利率百分之十\n    ，逾期超過六個月以上者，按上開利率百分之二十計算之違約金，為有理由，應予准許\n    。\n五、訴訟費用負擔之依據：民事訴訟法第三百八十五條第一項前段、第七十八條。\n中        華        民        國   九十四   年      三       月    三十一     日\n                                        臺灣臺中地方法院民事第一庭\n~B法      官  吳蕙玟\n正本係照原本作成如對本判決上訴，須於判決送達後廿日內向本院提出上訴狀\n中        華        民        國   九十四   年      三       月    三十一     日\n~B法院書記官  黃鴻鑑\n",
  "structure": {
    "main": "被告應給付原告新台幣壹佰壹拾萬零柒仟陸佰玖拾肆元，及自民國八十八年四月二十九日起\n至清償日止，按年息百分之九．六七計算之利息，並自民國八十八年五月三十日起至清償日\n止，其逾期在六個月以內者，按上開利率百分之十，逾期超過六個月以上者，按上開利率百\n分之二十計算之違約金。\n訴訟費用由被告負擔。",
    "fact": "一、依卷附兩造間授信約定書第十一條之約定，兩造已合意本件消費借貸之法律訟爭事件，\n    由本院為第一審管轄法院。又本件被告均未於言詞辯論期日到場，核無民事訴訟法第三\n    百八十六條各款所列情形，爰依原告之聲請，由其一造辯論而為判決，合先敘明。\n二、原告主張：訴外人尚品建設股份有限公司邀同訴外人李坤秀、李振昌及被告擔任連帶保\n    證人，於民國（下同）八十七年七月二十九日向原告借款新台幣（下同）一百五十萬元\n    ，約定到期日為九十年七月二十九日止，利息按年息百分之九．七五計付，並依原告之\n    基本放款利率變動而機動調整，每月按期付息，如有一次未依約履行，全部借款即視為\n    到期，除仍須支付利息外，逾期清償在六個月以內者，按上開利率百分之十，超過六個\n    月以上者，按上開利率百分之二十計付之違約金，訴外人尚品建設股份有限公司自八十\n    八年四月二十九日起即未再依約繳息，，迄今尚欠本金一百一十萬七千六百九十四元及\n    利息、違約金未為清償，爰依連帶保證之法律關係提起本件訴訟。並聲明：如主文第一\n    項所示。\n三、被告未於言詞辯論期日到場，亦未提出書狀作何聲明或陳述。\n四、得心證之理由：\n  (一)按當事人對於他造主張之事實，於言詞辯論時不爭執者，視同自認；當事人對於他造主\n    張之事實，已於相當時期受合法之通知，而於言詞辯論期日不到場，亦未提出準備書狀\n    爭執者，準用第一項之規定，民事訴訟法第二百八十條第一項、第三項分別定有明文。\n    本件原告主張之事實，已據其提出與所述相符之授信約定書、借據、連帶保證書及呆帳\n    登記簿各一紙等為證，被告經合法通知，既不於最後言詞辯論期日到庭爭執，復未提出\n    書狀以供本院斟酌，故原告上開主張，自堪信為真實。\n  (二)綜上所述，原告依連帶保證之法律關係請求被告給付一百一十萬七千六百九十四元，及\n    自八十八年四月二十九日起，至清償日止，按年息百分之九．六七計算之利息，並自民\n    國八十八年五月三十日起，至清償日止，其逾期在六個月以內者，按上開利率百分之十\n    ，逾期超過六個月以上者，按上開利率百分之二十計算之違約金，為有理由，應予准許\n    。\n五、訴訟費用負擔之依據：民事訴訟法第三百八十五條第一項前段、第七十八條。",
    "reason": "一、依卷附兩造間授信約定書第十一條之約定，兩造已合意本件消費借貸之法律訟爭事件，\n    由本院為第一審管轄法院。又本件被告均未於言詞辯論期日到場，核無民事訴訟法第三\n    百八十六條各款所列情形，爰依原告之聲請，由其一造辯論而為判決，合先敘明。\n二、原告主張：訴外人尚品建設股份有限公司邀同訴外人李坤秀、李振昌及被告擔任連帶保\n    證人，於民國（下同）八十七年七月二十九日向原告借款新台幣（下同）一百五十萬元\n    ，約定到期日為九十年七月二十九日止，利息按年息百分之九．七五計付，並依原告之\n    基本放款利率變動而機動調整，每月按期付息，如有一次未依約履行，全部借款即視為\n    到期，除仍須支付利息外，逾期清償在六個月以內者，按上開利率百分之十，超過六個\n    月以上者，按上開利率百分之二十計付之違約金，訴外人尚品建設股份有限公司自八十\n    八年四月二十九日起即未再依約繳息，，迄今尚欠本金一百一十萬七千六百九十四元及\n    利息、違約金未為清償，爰依連帶保證之法律關係提起本件訴訟。並聲明：如主文第一\n    項所示。\n三、被告未於言詞辯論期日到場，亦未提出書狀作何聲明或陳述。\n四、得心證之理由：\n  (一)按當事人對於他造主張之事實，於言詞辯論時不爭執者，視同自認；當事人對於他造主\n    張之事實，已於相當時期受合法之通知，而於言詞辯論期日不到場，亦未提出準備書狀\n    爭執者，準用第一項之規定，民事訴訟法第二百八十條第一項、第三項分別定有明文。\n    本件原告主張之事實，已據其提出與所述相符之授信約定書、借據、連帶保證書及呆帳\n    登記簿各一紙等為證，被告經合法通知，既不於最後言詞辯論期日到庭爭執，復未提出\n    書狀以供本院斟酌，故原告上開主張，自堪信為真實。\n  (二)綜上所述，原告依連帶保證之法律關係請求被告給付一百一十萬七千六百九十四元，及\n    自八十八年四月二十九日起，至清償日止，按年息百分之九．六七計算之利息，並自民\n    國八十八年五月三十日起，至清償日止，其逾期在六個月以內者，按上開利率百分之十\n    ，逾期超過六個月以上者，按上開利率百分之二十計算之違約金，為有理由，應予准許\n    。\n五、訴訟費用負擔之依據：民事訴訟法第三百八十五條第一項前段、第七十八條。"
  },
  "search": "臺灣臺中地方法院民事判決九十四年度訴字第二號原告三信商業銀行股份有限公司法定代理人甲○○訴訟代理人丙○○被告乙○○當事人間清償借款事件，本院於九十年三月十四日言詞辯論終結，判決如下：主文被告應給付原告新台幣壹佰壹拾萬零柒仟陸佰玖拾肆元，及自民國八十八年四月二十九日起至清償日止，按年息百分之九．六七計算之利息，並自民國八十八年五月三十日起至清償日止，其逾期在六個月以內者，按上開利率百分之十，逾期超過六個月以上者，按上開利率百分之二十計算之違約金。訴訟費用由被告負擔。事實及理由一、依卷附兩造間授信約定書第十一條之約定，兩造已合意本件消費借貸之法律訟爭事件，由本院為第一審管轄法院。又本件被告均未於言詞辯論期日到場，核無民事訴訟法第三百八十六條各款所列情形，爰依原告之聲請，由其一造辯論而為判決，合先敘明。二、原告主張：訴外人尚品建設股份有限公司邀同訴外人李坤秀、李振昌及被告擔任連帶保證人，於民國（下同）八十七年七月二十九日向原告借款新台幣（下同）一百五十萬元，約定到期日為九十年七月二十九日止，利息按年息百分之九．七五計付，並依原告之基本放款利率變動而機動調整，每月按期付息，如有一次未依約履行，全部借款即視為到期，除仍須支付利息外，逾期清償在六個月以內者，按上開利率百分之十，超過六個月以上者，按上開利率百分之二十計付之違約金，訴外人尚品建設股份有限公司自八十八年四月二十九日起即未再依約繳息，，迄今尚欠本金一百一十萬七千六百九十四元及利息、違約金未為清償，爰依連帶保證之法律關係提起本件訴訟。並聲明：如主文第一項所示。三、被告未於言詞辯論期日到場，亦未提出書狀作何聲明或陳述。四、得心證之理由：(一)按當事人對於他造主張之事實，於言詞辯論時不爭執者，視同自認；當事人對於他造主張之事實，已於相當時期受合法之通知，而於言詞辯論期日不到場，亦未提出準備書狀爭執者，準用第一項之規定，民事訴訟法第二百八十條第一項、第三項分別定有明文。本件原告主張之事實，已據其提出與所述相符之授信約定書、借據、連帶保證書及呆帳登記簿各一紙等為證，被告經合法通知，既不於最後言詞辯論期日到庭爭執，復未提出書狀以供本院斟酌，故原告上開主張，自堪信為真實。(二)綜上所述，原告依連帶保證之法律關係請求被告給付一百一十萬七千六百九十四元，及自八十八年四月二十九日起，至清償日止，按年息百分之九．六七計算之利息，並自民國八十八年五月三十日起，至清償日止，其逾期在六個月以內者，按上開利率百分之十，逾期超過六個月以上者，按上開利率百分之二十計算之違約金，為有理由，應予准許。五、訴訟費用負擔之依據：民事訴訟法第三百八十五條第一項前段、第七十八條。中華民國九十四年三月三十一日臺灣臺中地方法院民事第一庭~B法官吳蕙玟正本係照原本作成如對本判決上訴，須於判決送達後廿日內向本院提出上訴狀中華民國九十四年三月三十一日~B法院書記官黃鴻鑑",
  "characters": {
    "judges": [
      "吳蕙玟"
    ],
    "prosecutors": [

    ],
    "lawyers": [

    ],
    "clerks": [

    ],
    "plaintiffs": [
      "三信商業銀行股份有限公司"
    ],
    "defendants": [
      "乙○○",
      "當事人間清償借款事件，本院於九十年三月十四日言詞辯論終結，判決如下："
    ],
    "prosecutor_office": [

    ],
    "creditors": [

    ],
    "debtors": [

    ],
    "judicial_associate_officer": [

    ]
  },
  "adjudged_at": "2005-03-31",
  "created_at": "2016-02-07 07:52:25",
  "updated_at": "2016-02-07 07:52:25"
}