{
  "identify": "PTD-93-訴-570-20040831-4",
  "court": {
    "name": "臺灣屏東地方法院",
    "code": "PTD"
  },
  "division": {
    "name": "刑事",
    "code": "M"
  },
  "year": 93,
  "word": "訴",
  "number": "570",
  "jcheck": "4",
  "reason": "搶奪等",
  "content": "臺灣屏東地方法院刑事判決                          九十三年度訴字第五七號\n    公  訴  人  臺灣屏東地方法院檢察署檢察官\n    被      告  亥○○\n    選任辯護人  鍾治漢\n    被      告  巳○○\n右列被告因搶奪等案件，經檢察官提起公訴（九十三年度核退偵字第五一號、九十三\n年度偵字第二五七二、二九０八、三０二四號），及移\n九五四、四一０一號），本院裁定改以簡式審判程序審理，茲判決如左：\n     主  文\n亥○○共同連續意圖為自己不法之所有，而搶奪他人之動產，處有期徒刑貳年。鑰匙\n壹支沒收。\n巳○○共同連續意圖為自己不法之所有，而搶奪他人之動產，累犯，處有期徒刑玖月\n；又連續收受贓物，累犯，處有期徒刑肆月。應執行有期徒刑壹年。\n     事  實\n一、巳○○曾於民國八十五、八十六年間，因犯妨害家庭、竊盜、違反麻醉藥品管理\n    條例、詐欺、恐嚇等罪，經法院分別判處有期徒刑二月、一年六月、五月、三年\n    、三月、十月確定，經定執行刑及接續執行，於九十二年十一月八日執行完畢，\n    仍不知悔改。\n二、亥○○、巳○○二人意圖為自己不法之所有，本於搶奪之概括犯意聯絡，或各自\n    單獨一人，或夥同彼此，於如附表一、二所示時地，騎乘機車，趁如附表一、二\n    所列被害人未及防備之際，以腕力徒手搶奪該被害人等所有之皮包（內有現金、\n    證件、行動電話等物），得手後，將搶得之現金各自單獨或朋分花用完畢；亥○\n    ○單獨行搶所得之行動電話則部分交予知情之巳○○收受（詳後述），部分借予\n    不知情之潘國淵，部分由亥○○留存，另被害人之證件等物則予以丟棄或燒毀。\n    嗣為警循線查獲，並扣得部分被害人所有之證件及行動電話（部分已發還）。\n三、亥○○、巳○○二人為掩人耳目，以遂行其等搶奪之犯行，竟意圖為自己不法之\n    所有，本於竊盜之犯意聯絡，於九十三年六月一日凌晨三時許，在屏東縣潮州鎮\n    ○○路八十號前，見蕭秀華所有之車號ＰＧＵ─三七九號機車鑰匙忘記取走，即\n    推由巳○○徒手竊取該部機車，二人並於同日凌晨五時二十分許，騎乘該部贓車\n    ，共同對如附表一編號十九號之被害人丁○○為搶奪行為（即附表二編號二）。\n    又亥○○承前述竊盜之概括犯意，單獨於九十三年六月三日凌晨一、二時許，在\n    屏東縣潮州鎮○○路二四號之二前，以其所有之鑰匙一支，竊取洪甘桃所有車號\n    ＯＭＪ─九一０號機車，得手後即於同年六月三、四日，單獨騎乘該機車，為附\n    表一編號二十至二二號之搶奪犯行。嗣為警循線分別在屏東縣潮州鎮茂榮骨科醫\n    院後方空地，查獲車號ＯＭＪ─九一０號機車，及在屏東縣潮州鎮○○路愛彌兒\n    幼稚園前，扣得車號ＰＧＵ─三七九號機車（均已發還）。\n四、巳○○明知亥○○於九十三年五、六月間所持有之型號為摩托羅拉小海豚、諾基\n    亞八三一０、諾基亞、三星等四支手機，為亥○○自癸○○、午○○等被害人處\n    搶得之贓物，竟另基於收受贓物之概括犯意，連續於上述時間，在其位於屏東縣\n    潮州鎮○○路六一巷三四號住處，收受上述四支手機，並將其中型號為摩托羅拉\n    小海豚、諾基亞八三一０二支手機，轉借予不知情之潘國淵，為警於九十三年六\n    月七日，分別在巳○○上址住處及潘國淵位於屏東縣潮州鎮○○路二七八號之住\n    處查獲。\n五、案經屏東縣警察局屏東分局、潮州分局、內埔分局報告臺灣屏東地方法院檢察署\n    檢察官偵查起訴及移送併辦。\n     理  由\n一、訊據被告亥○○、巳○○二人，對附表一、二所示之搶奪犯行，及事實欄三所述\n    之竊盜犯行均坦承不諱，核與附表一、二所示被害人及被竊機車車主蕭秀華、洪\n    甘桃於警、偵訊指訴情節相符，並經證人謝元興於警訊證述明確，此外，復有刑\n    案通報單、車輛竊盜查詢表、贓物認領收據、現場照片、扣押物品照片等資料附\n    卷可稽。是被告二人之自白，與事實相符，應可採信，本件事證明確，被告二人\n    之搶奪、竊盜犯行，應可認定。\n二、訊據被告巳○○雖坦承有於上述時地自被告亥○○處拿取四支手機，惟否認自始\n    知悉該等手機為贓物，辯稱：「亥○○拿給我的時候我不知道手機從哪裡來，後\n    來我跟他一起搶奪時才知道手機是搶來的」等語。然查，\n（一）在被告巳○○上址住處扣得之諾基亞、三星手機各一支，分別為被害人癸○○\n      、午○○所有一節，業據被害人癸○○、午○○於警訊指訴明確，並有贓物認\n      領收據、搜索扣押筆錄等附卷可稽。又被告亥○○已於偵訊及本院審理時供稱\n      ：「在潘國淵住處扣得五支手機都是我搶來的」等語明確，核與證人潘國淵於\n      警訊證述：「摩托羅拉小海豚、諾基亞八三一０二支手機，是我分別於五月底\n      及六月初向巳○○借的，其他三支是向亥○○借的」等語相符，有搜索扣押筆\n      錄在卷可憑，足證被告巳○○收受之四支手機，確為贓物無誤。\n（二）被告巳○○已於本院審理時供稱：「我常常跟亥○○見面，他的職業是修理車\n      子，收受手機時我覺得怪怪的，有問他來源，但他沒有回答，我就沒再追問」\n      等語，顯見其對被告亥○○之經濟狀況知之甚詳，被告亥○○既非富有，又非\n      以經營手機買賣或維修為業，竟持有多支手機，並任意借予他人，自有可疑。\n      參以被告巳○○有多項前科，非涉世未深之人，其於數日之間多次收受手機，\n      豈有不知來源有異之理？是被告巳○○上開辯稱即非實在，難以採信。綜上，\n      被告巳○○收受贓物事證明確，其贓物犯行應可認定。\n三、核被告亥○○所為，係犯刑法第三百二十五條第一項之搶奪罪，及同法第三百二\n    十條第一項之竊盜罪。被告巳○○所為，則係犯刑法第三百二十五條第一項搶奪\n    罪、第三百二十條第一項之竊盜罪、第三百四十九條第一項之收受贓物罪。被告\n    二人就附表一編號十九（即附表二編號二）之搶奪犯行，及竊取被害人蕭秀華機\n    車之犯行，均有犯意聯絡及行為分擔，皆為共同正犯。被告亥○○先後多次搶奪\n    犯行、二次竊盜犯行；被告巳○○先後二次搶奪犯行、四次收受贓物犯行，均時\n    間緊接，方法相同，觸犯構成要件相同之罪名，顯均基於概括犯意而為之，均應\n    依刑法第五十六條之規定，分別以一罪論，並加重其刑。被告二人竊取蕭秀華機\n    車後，及被告亥○○竊得洪甘桃機車後，即為搶奪犯行，顯見二人竊盜之目的，\n    在遂其搶奪犯行，所犯搶奪、竊盜二罪間，有方法結果之牽連關係，應均從一重\n    之搶奪罪論處。被告巳○○所犯搶奪、收受贓物二罪，犯意各別，罪名不同，應\n    分開論罪，合併處罰。又被告亥○○附表一編號一、七、十、十八、二十、二一\n    號部分，雖未據公訴人起訴，然此部分犯行，業據被告亥○○坦承不諱，並經被\n    害人指訴明確，本院認與上述起訴論罪之搶奪部分，有連續犯之裁判上一罪關係\n    ，為起訴效力所及，應併予審理。被告巳○○前於八十五、八十六年間，因犯妨\n    害家庭、竊盜、違反麻醉藥品管理條例、詐欺、恐嚇等罪，經法院分別判處有期\n    徒刑二月、一年六月、五月、三年、三月、十月確定，經定執行刑及接續執行，\n    於九十二年十一月八日執行完畢，有台灣高等法院被告全國前案記錄表在卷可按\n    ，其於有期徒刑執行完畢後五年內再犯本件有期徒刑以上之上述二罪，皆為累犯\n    ，應依刑法第四十七條之規定，分別加重其刑，其有二種刑之加重事由，均應遞\n    加重之。爰審酌被告亥○○並無前科，被告巳○○之素行（見前科表），其二人\n    犯罪之動機、目的、手段，被告亥○○搶奪次數多達二二次，造成被害人損失不\n    貲，被告巳○○搶奪次數二次，損失較小，收受贓物不利執法機關追查犯罪，二\n    人犯後均坦認犯行，態度尚可等一切情狀，分別量處如主文所示之刑，並就被告\n    巳○○部分定應執行之刑。被告亥○○所有，用以行竊洪甘桃所有機車之鑰匙一\n    支，尚在被告亥○○住處，業據其自承在卷，應依刑法第三十八條第一項第二款\n    之規定，宣告沒收。\n四、公訴意旨另以：被告巳○○多次收受被告亥○○搶得之被害人證件（附表一編號\n    十一、十三、十六、十九、二二號），尚涉有收受贓物罪嫌等語。訊據被告巳○\n    ○堅決否認有何收受被害人證件之贓物犯行，辯稱：「我和亥○○一起在羅玉枝\n    家的豬舍養鬥雞，證件是亥○○丟在豬舍的，我去養雞時才看到，不是我叫他丟\n    的，我也沒有留下證件的意思，如果要留就不會亂丟」等語。經查，同案被告亥\n    ○○於偵訊及本院審理時證稱：「被害人的證件是我丟在巳○○女友羅玉枝家的\n    豬舍，並沒有交給巳○○，是我在燒被害人證件時，巳○○看到，他才知道我丟\n    在這裡的」等語相符。衡諸常情，被告巳○○如有收受被害人證件準備供作他用\n    之意思，其自應妥為保存、收藏，豈有隨便棄置於豬舍之理？是被告巳○○上開\n    辯稱，應屬可採。此外，復查無其他證據足證被告巳○○有收受被害人證件之犯\n    行，本應為無罪之諭知，惟公訴意旨認此部分與收受被害人手機部分有連續犯之\n    裁判上一罪關係，爰不另為無罪之諭知。\n據上論斷，應依刑事訴訟法第二百九十九條第一項前段、第二百七十三條之一第一項\n，刑法第二十八條、第五十六條、第三百二十條第一項、第三百二十五條第一項、第\n三百四十九條第一項、第五十五條、第四十七條、第五十一條第五款、第三十八條第\n一項第二款、罰金罰鍰提高標準條例第一條前段，判決如主文。\n本案經檢察官黃莉琄到庭執行職務\n中      華      民      國     九十三     年     八     月    三十一    日\n                                      臺灣屏東地方法院刑事第二庭\n                           法  官    翁世容\n右正本證明與原本無異。\n如不服本判決應於收受本判決送達後十日內向本院提出上訴書狀，其未敘述上訴理由\n者，並得於提起上訴後十日內向本院補提理由書狀（均須按他造當事人之人數附繕本\n ）「切勿逕送上級法院」\n                                           書記官    王秋淑\n中    華    民    國     九十三      年      九      月       一       日\n附錄：\n刑法第三百二十五條第一項：\n意圖為自己或第三人不法之所有，而搶奪他人之動產者，處六月以上五年以下有期徒\n刑。\n刑法第三百二十條第一項：\n意圖為自己或第三人不法之所有，而竊取他人之動產者，為竊盜罪，處五年以下有期\n徒刑、拘役或五百元以下罰金。\n刑法第三百四十九條第一項：\n收受贓物者，處三年以下有期徒刑、拘役或五百元以下罰金。\n附表一：（亥○○搶奪部分）\n┌──┬───┬──────┬───────┬────┬────────┬─────────┐\n│編號│行為人│犯罪時間    │  犯罪地點    │ 被害人 │ 犯罪所得       │備註              │\n├──┼───┼──────┼───────┼────┼────────┼─────────┤\n│一  │亥○○│92年10月28日│屏東市○○路上│卯○○  │咖啡色皮包，內有│併案。            │\n│    │      │4時許       │              │        │現金、證件、手機│                  │\n│    │      │            │              │        │一支。          │                  │\n├──┼───┼──────┼───────┼────┼────────┼─────────┤\n│二  │亥○○│93年2月17日 │屏東市○○路師│己○○  │咖啡色皮包，內有│                  │\n│    │      │2時50分許   │範學院前      │        │現金五千元、證件│                  │\n│    │      │            │              │        │、手機一支。    │                  │\n├──┼───┼──────┼───────┼────┼────────┼─────────┤\n│三  │亥○○│93年2月24日 │屏東縣潮州鎮福│戊○○  │黑色皮包，內有現│                  │\n│    │      │0時50分許   │康街與光華路一│        │金七千元、證件、│                  │\n│    │      │            │二二巷口      │        │手機一支。      │                  │\n├──┼───┼──────┼───────┼────┼────────┼─────────┤\n│四  │亥○○│93年3月19日 │屏東縣潮州鎮南│戌○○  │黑色皮包，內有現│                  │\n│    │      │21時許      │進路二七號前  │        │金五千元、證件、│                  │\n│    │      │            │              │        │手機一支。      │                  │\n├──┼───┼──────┼───────┼────┼────────┼─────────┤\n│五  │亥○○│93年3月19日 │屏東縣潮州鎮延│辛○○○│黑色皮包，內有現│                  │\n│    │      │21時50分許  │平路與朝昇路口│        │金三千一百元、證│                  │\n│    │      │            │              │        │件、手機一支。  │                  │\n├──┼───┼──────┼───────┼────┼────────┼─────────┤\n│六  │亥○○│93年3月20日 │屏東縣東港鎮明│酉○○  │皮包一個，內有現│                  │\n│    ││23時10分許  │德街          │        │金一千三百元、證│                  │\n│    │      │            │              │        │件、手機一支。  │                  │\n├──┼───┼──────┼───────┼────┼────────┼─────────┤\n│七  │亥○○│93年3月25日 │屏東市○○路、│壬○○  │皮包一個，內有證│併案。            │\n│    │      │1時30分許   │公園路口      │        │件、提款卡。    │                  │\n│    │      │            │              │        │                │                  │\n├──┼───┼──────┼───────┼────┼────────┼─────────┤\n│八  │亥○○│93年4月5日  │屏東市○○路國│寅○○  │背包一個，內有現│                  │\n│    │      │2時30分許   │光客運站前    │        │金五十元、證件。│                  │\n│    │      │            │              │        │                │                  │\n├──┼───┼──────┼───────┼────┼────────┼─────────┤\n│九  │亥○○│93年4月5日  │屏東縣潮州鎮永│申○○  │皮包一個，內有現│                  │\n│    │      │22時20分許  │昌路三一號前  │        │金二萬五千元、證│                  │\n│    │      │            │              │        │件、手機一支。  │                  │\n├──┼───┼──────┼───────┼────┼────────┼─────────┤\n│十  │亥○○│93年4月6日  │屏東市○○路上│庚○○  │皮包一個，內有現│併案。            │\n│    │      │2時許       │              │        │金二千元、證件。│                  │\n│    │      │            │              │        │                │                  │\n├──┼───┼──────┼───────┼────┼────────┼─────────┤\n│十一│亥○○│93年5月21日 │屏東縣潮州鎮興│宇○○  │皮包一個，內有現│宇○○證件在羅玉枝│\n│    │      │21時40分許  │隆路八一四超商│        │金二萬六千五百元│家中查獲，已領回。│\n│    │      │            │前            │        │、證件、手機一支│                  │\n│    │      │            │              │        │。              │                  │\n├──┼───┼──────┼───────┼────┼────────┼─────────┤\n│十二│亥○○│93年5月25日 │屏東縣潮州鎮新│辰○○  │皮包一個，內有現│手機在不知情之潘國│\n│    │      │8時10分許   │生路麥當勞前  │        │金二千元、證件、│淵住處查獲，已領回│\n│    │      │            │              │        │手機一支。      │。                │\n├──┼───┼──────┼───────┼────┼────────┼─────────┤\n│十三│亥○○│93年5月25日 │屏東市中央市場│天○○  │紅色皮包，內有現│手機在不知情之潘國│\n│    │      │9時10分許   │前            │        │金二萬元、證件、│淵住處查獲；證件在│\n│    │      │            │              │        │手機一支。      │不知情之羅玉枝住處│\n│    │      │            │              │        │                │查獲，均已領回。  │\n├──┼───┼──────┼───────┼────┼────────┼─────────┤\n│十四│亥○○│93年5月25日 │屏東縣內埔鄉文│甲○○  │皮包一個，內有現│手機在不知情之潘國│\n│    │      │18時50分許  │化路三七四號前│        │金一萬三千元、證│淵住處查獲，已領回│\n│    │      │            │              │        │件、手機一支。  │。                │\n├──┼───┼──────┼───────┼────┼────────┼─────────┤\n│十五│亥○○│93年5月27日 │屏東市○○路、│丑○○  │黑色皮包，內有現│                  │\n│    │      │6時40分許   │光復路口      │        │金五千元、證件、│                  │\n│    │      │            │              │        │手機一支。      │                  │\n├──┼───┼──────┼───────┼────┼────────┼─────────┤\n│十六│亥○○│93年5月28日 │屏東縣內埔鄉仁│地○○  │皮包一個，內有現│證件在不知情之羅玉│\n│    │      │16時10分許  │和路、廣田路口│        │金一萬八千元、證│枝住處查獲，已領回│\n│    │      │            │              │        │件、手機一支。  │。                │\n├──┼───┼──────┼───────┼────┼────────┼─────────┤\n│十七│亥○○│93年5月29日 │屏東縣東港鎮光│癸○○  │皮包一個，內有現│手機在巳○○住處查│\n│    │      │23時許      │復路一段      │        │金七百元、證件、│獲，已領回。      │\n│    │      │            │              │        │手機一支。      │                  │\n├──┼───┼──────┼───────┼────┼────────┼─────────┤\n│十八│亥○○│93年5月30日 │屏東市○○路二│乙○○○│皮包一個，內有現│併案。            │\n│    │      │9時許       │三九號前      │        │金一千三百元、證│                  │\n│    │      │            │              │        │件、手機一支。  │                  │\n├──┼───┼──────┼───────┼────┼────────┼─────────┤\n│十九│亥○○│93年6月1日  │屏東縣潮州鎮朝│丁○○  │皮包一個，內有現│共騎竊得之車號ＰＵ│\n│    │巳○○│5時20分許   │昇東路        │        │金五百元、證件、│Ｇ─三七九號機車行│\n│    │      │            │              │        │手機一支。      │搶。證件在不知情之│\n│    │      │            │              │        │                │羅玉枝住處查獲，已│\n│    │      │            │              │        │                │領回。            │\n├──┼───┼──────┼───────┼────┼────────┼─────────┤\n│二十│亥○○│93年6月3日  │屏東市○○路、│子○○  │皮包一個，內有現│併案。            │\n│    │      │7時許       │杭州街口      │        │金二千元、證件、│騎乘竊得之車號ＯＭ│\n│    │      │            │              │        │手機一支。      │Ｊ─九一０號機車行│\n│    │      │            │              │        │                │搶。              │\n├──┼───┼──────┼───────┼────┼────────┼─────────┤\n│二一│亥○○│93年6月3日  │屏東市○○路一│未○○  │皮包一個，內有現│併案。            │\n│    │      │7時40分許   │六六之一號前  │        │金三千元、證件、│騎乘竊得之車號ＯＭ│\n│    │      │            │              │        │手機一支。      │Ｊ─九一０號機車行│\n│    │      │            │              │        │                │搶。              │\n├──┼───┼──────┼───────┼────┼────────┼─────────┤\n│二二│亥○○│93年6月4日  │屏東縣內埔鄉文│午○○  │咖啡色皮包，內有│騎乘竊得之車號ＯＭ│\n│    │      │18時10分許  │化路八九號前  │        │現金八千五百元、│Ｊ─九一０號機車行│\n│    │      │            │              │        │證件、手機一支。│搶。手機在巳○○住│\n│    │      │            │              │        │                │處查扣；證件在不知│\n│    │      │            │              │        │                │情之羅玉枝住處查獲│\n│    │      │            │              │        │                │，均已領回。      │\n└──┴───┴──────┴───────┴────┴────────┴─────────┘\n附表二：（巳○○搶奪部分）\n┌──┬───┬──────┬───────┬────┬────────┬─────────┐\n│編號│行為人│犯罪時間    │  犯罪地點    │ 被害人 │ 犯罪所得       │備註              │\n├──┼───┼──────┼───────┼────┼────────┼─────────┤\n│一  │巳○○│93年5月03日 │屏東縣潮州鎮公│丙○○○│皮包一個，內有現│                  │\n│    │      │10時許      │園路四一號前  │        │金三千七百元、戒│                  │\n│    │      │            │              │        │指、耳環、手機一│                  │\n│    │      │            │              │        │支。            │                  │\n├──┼───┼──────┼───────┼────┼────────┼─────────┤\n│二  │巳○○│93年6月1日  │屏東縣潮州鎮朝│丁○○  │皮包一個，內有現│共騎竊得之車號ＰＵ│\n│    │亥○○│5時20分許   │昇東路        │        │金五百元、證件、│Ｇ─三七九號機車行│\n│    │      │            │              │        │手機一支。      │搶。證件在不知情之│\n│    │      │            │              │        │                │羅玉枝住處查獲，已│\n│    │      │            │              │        │                │領回。            │\n└──┴───┴──────┴───────┴────┴────────┴─────────┘\n",
  "structure": {
    "main": "亥○○共同連續意圖為自己不法之所有，而搶奪他人之動產，處有期徒刑貳年。鑰匙\n壹支沒收。\n巳○○共同連續意圖為自己不法之所有，而搶奪他人之動產，累犯，處有期徒刑玖月\n；又連續收受贓物，累犯，處有期徒刑肆月。應執行有期徒刑壹年。",
    "fact": "一、巳○○曾於民國八十五、八十六年間，因犯妨害家庭、竊盜、違反麻醉藥品管理\n    條例、詐欺、恐嚇等罪，經法院分別判處有期徒刑二月、一年六月、五月、三年\n    、三月、十月確定，經定執行刑及接續執行，於九十二年十一月八日執行完畢，\n    仍不知悔改。\n二、亥○○、巳○○二人意圖為自己不法之所有，本於搶奪之概括犯意聯絡，或各自\n    單獨一人，或夥同彼此，於如附表一、二所示時地，騎乘機車，趁如附表一、二\n    所列被害人未及防備之際，以腕力徒手搶奪該被害人等所有之皮包（內有現金、\n    證件、行動電話等物），得手後，將搶得之現金各自單獨或朋分花用完畢；亥○\n    ○單獨行搶所得之行動電話則部分交予知情之巳○○收受（詳後述），部分借予\n    不知情之潘國淵，部分由亥○○留存，另被害人之證件等物則予以丟棄或燒毀。\n    嗣為警循線查獲，並扣得部分被害人所有之證件及行動電話（部分已發還）。\n三、亥○○、巳○○二人為掩人耳目，以遂行其等搶奪之犯行，竟意圖為自己不法之\n    所有，本於竊盜之犯意聯絡，於九十三年六月一日凌晨三時許，在屏東縣潮州鎮\n    ○○路八十號前，見蕭秀華所有之車號ＰＧＵ─三七九號機車鑰匙忘記取走，即\n    推由巳○○徒手竊取該部機車，二人並於同日凌晨五時二十分許，騎乘該部贓車\n    ，共同對如附表一編號十九號之被害人丁○○為搶奪行為（即附表二編號二）。\n    又亥○○承前述竊盜之概括犯意，單獨於九十三年六月三日凌晨一、二時許，在\n    屏東縣潮州鎮○○路二四號之二前，以其所有之鑰匙一支，竊取洪甘桃所有車號\n    ＯＭＪ─九一０號機車，得手後即於同年六月三、四日，單獨騎乘該機車，為附\n    表一編號二十至二二號之搶奪犯行。嗣為警循線分別在屏東縣潮州鎮茂榮骨科醫\n    院後方空地，查獲車號ＯＭＪ─九一０號機車，及在屏東縣潮州鎮○○路愛彌兒\n    幼稚園前，扣得車號ＰＧＵ─三七九號機車（均已發還）。\n四、巳○○明知亥○○於九十三年五、六月間所持有之型號為摩托羅拉小海豚、諾基\n    亞八三一０、諾基亞、三星等四支手機，為亥○○自癸○○、午○○等被害人處\n    搶得之贓物，竟另基於收受贓物之概括犯意，連續於上述時間，在其位於屏東縣\n    潮州鎮○○路六一巷三四號住處，收受上述四支手機，並將其中型號為摩托羅拉\n    小海豚、諾基亞八三一０二支手機，轉借予不知情之潘國淵，為警於九十三年六\n    月七日，分別在巳○○上址住處及潘國淵位於屏東縣潮州鎮○○路二七八號之住\n    處查獲。\n五、案經屏東縣警察局屏東分局、潮州分局、內埔分局報告臺灣屏東地方法院檢察署\n    檢察官偵查起訴及移送併辦。",
    "reason": "一、訊據被告亥○○、巳○○二人，對附表一、二所示之搶奪犯行，及事實欄三所述\n    之竊盜犯行均坦承不諱，核與附表一、二所示被害人及被竊機車車主蕭秀華、洪\n    甘桃於警、偵訊指訴情節相符，並經證人謝元興於警訊證述明確，此外，復有刑\n    案通報單、車輛竊盜查詢表、贓物認領收據、現場照片、扣押物品照片等資料附\n    卷可稽。是被告二人之自白，與事實相符，應可採信，本件事證明確，被告二人\n    之搶奪、竊盜犯行，應可認定。\n二、訊據被告巳○○雖坦承有於上述時地自被告亥○○處拿取四支手機，惟否認自始\n    知悉該等手機為贓物，辯稱：「亥○○拿給我的時候我不知道手機從哪裡來，後\n    來我跟他一起搶奪時才知道手機是搶來的」等語。然查，\n（一）在被告巳○○上址住處扣得之諾基亞、三星手機各一支，分別為被害人癸○○\n      、午○○所有一節，業據被害人癸○○、午○○於警訊指訴明確，並有贓物認\n      領收據、搜索扣押筆錄等附卷可稽。又被告亥○○已於偵訊及本院審理時供稱\n      ：「在潘國淵住處扣得五支手機都是我搶來的」等語明確，核與證人潘國淵於\n      警訊證述：「摩托羅拉小海豚、諾基亞八三一０二支手機，是我分別於五月底\n      及六月初向巳○○借的，其他三支是向亥○○借的」等語相符，有搜索扣押筆\n      錄在卷可憑，足證被告巳○○收受之四支手機，確為贓物無誤。\n（二）被告巳○○已於本院審理時供稱：「我常常跟亥○○見面，他的職業是修理車\n      子，收受手機時我覺得怪怪的，有問他來源，但他沒有回答，我就沒再追問」\n      等語，顯見其對被告亥○○之經濟狀況知之甚詳，被告亥○○既非富有，又非\n      以經營手機買賣或維修為業，竟持有多支手機，並任意借予他人，自有可疑。\n      參以被告巳○○有多項前科，非涉世未深之人，其於數日之間多次收受手機，\n      豈有不知來源有異之理？是被告巳○○上開辯稱即非實在，難以採信。綜上，\n      被告巳○○收受贓物事證明確，其贓物犯行應可認定。\n三、核被告亥○○所為，係犯刑法第三百二十五條第一項之搶奪罪，及同法第三百二\n    十條第一項之竊盜罪。被告巳○○所為，則係犯刑法第三百二十五條第一項搶奪\n    罪、第三百二十條第一項之竊盜罪、第三百四十九條第一項之收受贓物罪。被告\n    二人就附表一編號十九（即附表二編號二）之搶奪犯行，及竊取被害人蕭秀華機\n    車之犯行，均有犯意聯絡及行為分擔，皆為共同正犯。被告亥○○先後多次搶奪\n    犯行、二次竊盜犯行；被告巳○○先後二次搶奪犯行、四次收受贓物犯行，均時\n    間緊接，方法相同，觸犯構成要件相同之罪名，顯均基於概括犯意而為之，均應\n    依刑法第五十六條之規定，分別以一罪論，並加重其刑。被告二人竊取蕭秀華機\n    車後，及被告亥○○竊得洪甘桃機車後，即為搶奪犯行，顯見二人竊盜之目的，\n    在遂其搶奪犯行，所犯搶奪、竊盜二罪間，有方法結果之牽連關係，應均從一重\n    之搶奪罪論處。被告巳○○所犯搶奪、收受贓物二罪，犯意各別，罪名不同，應\n    分開論罪，合併處罰。又被告亥○○附表一編號一、七、十、十八、二十、二一\n    號部分，雖未據公訴人起訴，然此部分犯行，業據被告亥○○坦承不諱，並經被\n    害人指訴明確，本院認與上述起訴論罪之搶奪部分，有連續犯之裁判上一罪關係\n    ，為起訴效力所及，應併予審理。被告巳○○前於八十五、八十六年間，因犯妨\n    害家庭、竊盜、違反麻醉藥品管理條例、詐欺、恐嚇等罪，經法院分別判處有期\n    徒刑二月、一年六月、五月、三年、三月、十月確定，經定執行刑及接續執行，\n    於九十二年十一月八日執行完畢，有台灣高等法院被告全國前案記錄表在卷可按\n    ，其於有期徒刑執行完畢後五年內再犯本件有期徒刑以上之上述二罪，皆為累犯\n    ，應依刑法第四十七條之規定，分別加重其刑，其有二種刑之加重事由，均應遞\n    加重之。爰審酌被告亥○○並無前科，被告巳○○之素行（見前科表），其二人\n    犯罪之動機、目的、手段，被告亥○○搶奪次數多達二二次，造成被害人損失不\n    貲，被告巳○○搶奪次數二次，損失較小，收受贓物不利執法機關追查犯罪，二\n    人犯後均坦認犯行，態度尚可等一切情狀，分別量處如主文所示之刑，並就被告\n    巳○○部分定應執行之刑。被告亥○○所有，用以行竊洪甘桃所有機車之鑰匙一\n    支，尚在被告亥○○住處，業據其自承在卷，應依刑法第三十八條第一項第二款\n    之規定，宣告沒收。\n四、公訴意旨另以：被告巳○○多次收受被告亥○○搶得之被害人證件（附表一編號\n    十一、十三、十六、十九、二二號），尚涉有收受贓物罪嫌等語。訊據被告巳○\n    ○堅決否認有何收受被害人證件之贓物犯行，辯稱：「我和亥○○一起在羅玉枝\n    家的豬舍養鬥雞，證件是亥○○丟在豬舍的，我去養雞時才看到，不是我叫他丟\n    的，我也沒有留下證件的意思，如果要留就不會亂丟」等語。經查，同案被告亥\n    ○○於偵訊及本院審理時證稱：「被害人的證件是我丟在巳○○女友羅玉枝家的\n    豬舍，並沒有交給巳○○，是我在燒被害人證件時，巳○○看到，他才知道我丟\n    在這裡的」等語相符。衡諸常情，被告巳○○如有收受被害人證件準備供作他用\n    之意思，其自應妥為保存、收藏，豈有隨便棄置於豬舍之理？是被告巳○○上開\n    辯稱，應屬可採。此外，復查無其他證據足證被告巳○○有收受被害人證件之犯\n    行，本應為無罪之諭知，惟公訴意旨認此部分與收受被害人手機部分有連續犯之\n    裁判上一罪關係，爰不另為無罪之諭知。\n據上論斷，應依刑事訴訟法第二百九十九條第一項前段、第二百七十三條之一第一項\n，刑法第二十八條、第五十六條、第三百二十條第一項、第三百二十五條第一項、第\n三百四十九條第一項、第五十五條、第四十七條、第五十一條第五款、第三十八條第\n一項第二款、罰金罰鍰提高標準條例第一條前段，判決如主文。\n本案經檢察官黃莉琄到庭執行職務\n中      華      民      國     九十三     年     八     月    三十一    日\n                                      臺灣屏東地方法院刑事第二庭\n                           法  官    翁世容\n右正本證明與原本無異。\n如不服本判決應於收受本判決送達後十日內向本院提出上訴書狀，其未敘述上訴理由\n者，並得於提起上訴後十日內向本院補提理由書狀（均須按他造當事人之人數附繕本\n ）「切勿逕送上級法院」\n                                           書記官    王秋淑"
  },
  "search": "臺灣屏東地方法院刑事判決九十三年度訴字第五七號公訴人臺灣屏東地方法院檢察署檢察官被告亥○○選任辯護人鍾治漢被告巳○○右列被告因搶奪等案件，經檢察官提起公訴（九十三年度核退偵字第五一號、九十三年度偵字第二五七二、二九０八、三０二四號），及移九五四、四一０一號），本院裁定改以簡式審判程序審理，茲判決如左：主文亥○○共同連續意圖為自己不法之所有，而搶奪他人之動產，處有期徒刑貳年。鑰匙壹支沒收。巳○○共同連續意圖為自己不法之所有，而搶奪他人之動產，累犯，處有期徒刑玖月；又連續收受贓物，累犯，處有期徒刑肆月。應執行有期徒刑壹年。事實一、巳○○曾於民國八十五、八十六年間，因犯妨害家庭、竊盜、違反麻醉藥品管理條例、詐欺、恐嚇等罪，經法院分別判處有期徒刑二月、一年六月、五月、三年、三月、十月確定，經定執行刑及接續執行，於九十二年十一月八日執行完畢，仍不知悔改。二、亥○○、巳○○二人意圖為自己不法之所有，本於搶奪之概括犯意聯絡，或各自單獨一人，或夥同彼此，於如附表一、二所示時地，騎乘機車，趁如附表一、二所列被害人未及防備之際，以腕力徒手搶奪該被害人等所有之皮包（內有現金、證件、行動電話等物），得手後，將搶得之現金各自單獨或朋分花用完畢；亥○○單獨行搶所得之行動電話則部分交予知情之巳○○收受（詳後述），部分借予不知情之潘國淵，部分由亥○○留存，另被害人之證件等物則予以丟棄或燒毀。嗣為警循線查獲，並扣得部分被害人所有之證件及行動電話（部分已發還）。三、亥○○、巳○○二人為掩人耳目，以遂行其等搶奪之犯行，竟意圖為自己不法之所有，本於竊盜之犯意聯絡，於九十三年六月一日凌晨三時許，在屏東縣潮州鎮○○路八十號前，見蕭秀華所有之車號ＰＧＵ─三七九號機車鑰匙忘記取走，即推由巳○○徒手竊取該部機車，二人並於同日凌晨五時二十分許，騎乘該部贓車，共同對如附表一編號十九號之被害人丁○○為搶奪行為（即附表二編號二）。又亥○○承前述竊盜之概括犯意，單獨於九十三年六月三日凌晨一、二時許，在屏東縣潮州鎮○○路二四號之二前，以其所有之鑰匙一支，竊取洪甘桃所有車號ＯＭＪ─九一０號機車，得手後即於同年六月三、四日，單獨騎乘該機車，為附表一編號二十至二二號之搶奪犯行。嗣為警循線分別在屏東縣潮州鎮茂榮骨科醫院後方空地，查獲車號ＯＭＪ─九一０號機車，及在屏東縣潮州鎮○○路愛彌兒幼稚園前，扣得車號ＰＧＵ─三七九號機車（均已發還）。四、巳○○明知亥○○於九十三年五、六月間所持有之型號為摩托羅拉小海豚、諾基亞八三一０、諾基亞、三星等四支手機，為亥○○自癸○○、午○○等被害人處搶得之贓物，竟另基於收受贓物之概括犯意，連續於上述時間，在其位於屏東縣潮州鎮○○路六一巷三四號住處，收受上述四支手機，並將其中型號為摩托羅拉小海豚、諾基亞八三一０二支手機，轉借予不知情之潘國淵，為警於九十三年六月七日，分別在巳○○上址住處及潘國淵位於屏東縣潮州鎮○○路二七八號之住處查獲。五、案經屏東縣警察局屏東分局、潮州分局、內埔分局報告臺灣屏東地方法院檢察署檢察官偵查起訴及移送併辦。理由一、訊據被告亥○○、巳○○二人，對附表一、二所示之搶奪犯行，及事實欄三所述之竊盜犯行均坦承不諱，核與附表一、二所示被害人及被竊機車車主蕭秀華、洪甘桃於警、偵訊指訴情節相符，並經證人謝元興於警訊證述明確，此外，復有刑案通報單、車輛竊盜查詢表、贓物認領收據、現場照片、扣押物品照片等資料附卷可稽。是被告二人之自白，與事實相符，應可採信，本件事證明確，被告二人之搶奪、竊盜犯行，應可認定。二、訊據被告巳○○雖坦承有於上述時地自被告亥○○處拿取四支手機，惟否認自始知悉該等手機為贓物，辯稱：「亥○○拿給我的時候我不知道手機從哪裡來，後來我跟他一起搶奪時才知道手機是搶來的」等語。然查，（一）在被告巳○○上址住處扣得之諾基亞、三星手機各一支，分別為被害人癸○○、午○○所有一節，業據被害人癸○○、午○○於警訊指訴明確，並有贓物認領收據、搜索扣押筆錄等附卷可稽。又被告亥○○已於偵訊及本院審理時供稱：「在潘國淵住處扣得五支手機都是我搶來的」等語明確，核與證人潘國淵於警訊證述：「摩托羅拉小海豚、諾基亞八三一０二支手機，是我分別於五月底及六月初向巳○○借的，其他三支是向亥○○借的」等語相符，有搜索扣押筆錄在卷可憑，足證被告巳○○收受之四支手機，確為贓物無誤。（二）被告巳○○已於本院審理時供稱：「我常常跟亥○○見面，他的職業是修理車子，收受手機時我覺得怪怪的，有問他來源，但他沒有回答，我就沒再追問」等語，顯見其對被告亥○○之經濟狀況知之甚詳，被告亥○○既非富有，又非以經營手機買賣或維修為業，竟持有多支手機，並任意借予他人，自有可疑。參以被告巳○○有多項前科，非涉世未深之人，其於數日之間多次收受手機，豈有不知來源有異之理？是被告巳○○上開辯稱即非實在，難以採信。綜上，被告巳○○收受贓物事證明確，其贓物犯行應可認定。三、核被告亥○○所為，係犯刑法第三百二十五條第一項之搶奪罪，及同法第三百二十條第一項之竊盜罪。被告巳○○所為，則係犯刑法第三百二十五條第一項搶奪罪、第三百二十條第一項之竊盜罪、第三百四十九條第一項之收受贓物罪。被告二人就附表一編號十九（即附表二編號二）之搶奪犯行，及竊取被害人蕭秀華機車之犯行，均有犯意聯絡及行為分擔，皆為共同正犯。被告亥○○先後多次搶奪犯行、二次竊盜犯行；被告巳○○先後二次搶奪犯行、四次收受贓物犯行，均時間緊接，方法相同，觸犯構成要件相同之罪名，顯均基於概括犯意而為之，均應依刑法第五十六條之規定，分別以一罪論，並加重其刑。被告二人竊取蕭秀華機車後，及被告亥○○竊得洪甘桃機車後，即為搶奪犯行，顯見二人竊盜之目的，在遂其搶奪犯行，所犯搶奪、竊盜二罪間，有方法結果之牽連關係，應均從一重之搶奪罪論處。被告巳○○所犯搶奪、收受贓物二罪，犯意各別，罪名不同，應分開論罪，合併處罰。又被告亥○○附表一編號一、七、十、十八、二十、二一號部分，雖未據公訴人起訴，然此部分犯行，業據被告亥○○坦承不諱，並經被害人指訴明確，本院認與上述起訴論罪之搶奪部分，有連續犯之裁判上一罪關係，為起訴效力所及，應併予審理。被告巳○○前於八十五、八十六年間，因犯妨害家庭、竊盜、違反麻醉藥品管理條例、詐欺、恐嚇等罪，經法院分別判處有期徒刑二月、一年六月、五月、三年、三月、十月確定，經定執行刑及接續執行，於九十二年十一月八日執行完畢，有台灣高等法院被告全國前案記錄表在卷可按，其於有期徒刑執行完畢後五年內再犯本件有期徒刑以上之上述二罪，皆為累犯，應依刑法第四十七條之規定，分別加重其刑，其有二種刑之加重事由，均應遞加重之。爰審酌被告亥○○並無前科，被告巳○○之素行（見前科表），其二人犯罪之動機、目的、手段，被告亥○○搶奪次數多達二二次，造成被害人損失不貲，被告巳○○搶奪次數二次，損失較小，收受贓物不利執法機關追查犯罪，二人犯後均坦認犯行，態度尚可等一切情狀，分別量處如主文所示之刑，並就被告巳○○部分定應執行之刑。被告亥○○所有，用以行竊洪甘桃所有機車之鑰匙一支，尚在被告亥○○住處，業據其自承在卷，應依刑法第三十八條第一項第二款之規定，宣告沒收。四、公訴意旨另以：被告巳○○多次收受被告亥○○搶得之被害人證件（附表一編號十一、十三、十六、十九、二二號），尚涉有收受贓物罪嫌等語。訊據被告巳○○堅決否認有何收受被害人證件之贓物犯行，辯稱：「我和亥○○一起在羅玉枝家的豬舍養鬥雞，證件是亥○○丟在豬舍的，我去養雞時才看到，不是我叫他丟的，我也沒有留下證件的意思，如果要留就不會亂丟」等語。經查，同案被告亥○○於偵訊及本院審理時證稱：「被害人的證件是我丟在巳○○女友羅玉枝家的豬舍，並沒有交給巳○○，是我在燒被害人證件時，巳○○看到，他才知道我丟在這裡的」等語相符。衡諸常情，被告巳○○如有收受被害人證件準備供作他用之意思，其自應妥為保存、收藏，豈有隨便棄置於豬舍之理？是被告巳○○上開辯稱，應屬可採。此外，復查無其他證據足證被告巳○○有收受被害人證件之犯行，本應為無罪之諭知，惟公訴意旨認此部分與收受被害人手機部分有連續犯之裁判上一罪關係，爰不另為無罪之諭知。據上論斷，應依刑事訴訟法第二百九十九條第一項前段、第二百七十三條之一第一項，刑法第二十八條、第五十六條、第三百二十條第一項、第三百二十五條第一項、第三百四十九條第一項、第五十五條、第四十七條、第五十一條第五款、第三十八條第一項第二款、罰金罰鍰提高標準條例第一條前段，判決如主文。本案經檢察官黃莉琄到庭執行職務中華民國九十三年八月三十一日臺灣屏東地方法院刑事第二庭法官翁世容右正本證明與原本無異。如不服本判決應於收受本判決送達後十日內向本院提出上訴書狀，其未敘述上訴理由者，並得於提起上訴後十日內向本院補提理由書狀（均須按他造當事人之人數附繕本）「切勿逕送上級法院」書記官王秋淑中華民國九十三年九月一日附錄：刑法第三百二十五條第一項：意圖為自己或第三人不法之所有，而搶奪他人之動產者，處六月以上五年以下有期徒刑。刑法第三百二十條第一項：意圖為自己或第三人不法之所有，而竊取他人之動產者，為竊盜罪，處五年以下有期徒刑、拘役或五百元以下罰金。刑法第三百四十九條第一項：收受贓物者，處三年以下有期徒刑、拘役或五百元以下罰金。附表一：（亥○○搶奪部分）┌──┬───┬──────┬───────┬────┬────────┬─────────┐│編號│行為人│犯罪時間│犯罪地點│被害人│犯罪所得│備註│├──┼───┼──────┼───────┼────┼────────┼─────────┤│一│亥○○│92年10月28日│屏東市○○路上│卯○○│咖啡色皮包，內有│併案。││││4時許│││現金、證件、手機││││││││一支。││├──┼───┼──────┼───────┼────┼────────┼─────────┤│二│亥○○│93年2月17日│屏東市○○路師│己○○│咖啡色皮包，內有│││││2時50分許│範學院前││現金五千元、證件││││││││、手機一支。││├──┼───┼──────┼───────┼────┼────────┼─────────┤│三│亥○○│93年2月24日│屏東縣潮州鎮福│戊○○│黑色皮包，內有現│││││0時50分許│康街與光華路一││金七千元、證件、││││││二二巷口││手機一支。││├──┼───┼──────┼───────┼────┼────────┼─────────┤│四│亥○○│93年3月19日│屏東縣潮州鎮南│戌○○│黑色皮包，內有現│││││21時許│進路二七號前││金五千元、證件、││││││││手機一支。││├──┼───┼──────┼───────┼────┼────────┼─────────┤│五│亥○○│93年3月19日│屏東縣潮州鎮延│辛○○○│黑色皮包，內有現│││││21時50分許│平路與朝昇路口││金三千一百元、證││││││││件、手機一支。││├──┼───┼──────┼───────┼────┼────────┼─────────┤│六│亥○○│93年3月20日│屏東縣東港鎮明│酉○○│皮包一個，內有現│││││23時10分許│德街││金一千三百元、證││││││││件、手機一支。││├──┼───┼──────┼───────┼────┼────────┼─────────┤│七│亥○○│93年3月25日│屏東市○○路、│壬○○│皮包一個，內有證│併案。││││1時30分許│公園路口││件、提款卡。││││││││││├──┼───┼──────┼───────┼────┼────────┼─────────┤│八│亥○○│93年4月5日│屏東市○○路國│寅○○│背包一個，內有現│││││2時30分許│光客運站前││金五十元、證件。││││││││││├──┼───┼──────┼───────┼────┼────────┼─────────┤│九│亥○○│93年4月5日│屏東縣潮州鎮永│申○○│皮包一個，內有現│││││22時20分許│昌路三一號前││金二萬五千元、證││││││││件、手機一支。││├──┼───┼──────┼───────┼────┼────────┼─────────┤│十│亥○○│93年4月6日│屏東市○○路上│庚○○│皮包一個，內有現│併案。││││2時許│││金二千元、證件。││││││││││├──┼───┼──────┼───────┼────┼────────┼─────────┤│十一│亥○○│93年5月21日│屏東縣潮州鎮興│宇○○│皮包一個，內有現│宇○○證件在羅玉枝││││21時40分許│隆路八一四超商││金二萬六千五百元│家中查獲，已領回。│││││前││、證件、手機一支││││││││。││├──┼───┼──────┼───────┼────┼────────┼─────────┤│十二│亥○○│93年5月25日│屏東縣潮州鎮新│辰○○│皮包一個，內有現│手機在不知情之潘國││││8時10分許│生路麥當勞前││金二千元、證件、│淵住處查獲，已領回│││││││手機一支。│。│├──┼───┼──────┼───────┼────┼────────┼─────────┤│十三│亥○○│93年5月25日│屏東市中央市場│天○○│紅色皮包，內有現│手機在不知情之潘國││││9時10分許│前││金二萬元、證件、│淵住處查獲；證件在│││││││手機一支。│不知情之羅玉枝住處││││││││查獲，均已領回。│├──┼───┼──────┼───────┼────┼────────┼─────────┤│十四│亥○○│93年5月25日│屏東縣內埔鄉文│甲○○│皮包一個，內有現│手機在不知情之潘國││││18時50分許│化路三七四號前││金一萬三千元、證│淵住處查獲，已領回│││││││件、手機一支。│。│├──┼───┼──────┼───────┼────┼────────┼─────────┤│十五│亥○○│93年5月27日│屏東市○○路、│丑○○│黑色皮包，內有現│││││6時40分許│光復路口││金五千元、證件、││││││││手機一支。││├──┼───┼──────┼───────┼────┼────────┼─────────┤│十六│亥○○│93年5月28日│屏東縣內埔鄉仁│地○○│皮包一個，內有現│證件在不知情之羅玉││││16時10分許│和路、廣田路口││金一萬八千元、證│枝住處查獲，已領回│││││││件、手機一支。│。│├──┼───┼──────┼───────┼────┼────────┼─────────┤│十七│亥○○│93年5月29日│屏東縣東港鎮光│癸○○│皮包一個，內有現│手機在巳○○住處查││││23時許│復路一段││金七百元、證件、│獲，已領回。│││││││手機一支。││├──┼───┼──────┼───────┼────┼────────┼─────────┤│十八│亥○○│93年5月30日│屏東市○○路二│乙○○○│皮包一個，內有現│併案。││││9時許│三九號前││金一千三百元、證││││││││件、手機一支。││├──┼───┼──────┼───────┼────┼────────┼─────────┤│十九│亥○○│93年6月1日│屏東縣潮州鎮朝│丁○○│皮包一個，內有現│共騎竊得之車號ＰＵ│││巳○○│5時20分許│昇東路││金五百元、證件、│Ｇ─三七九號機車行│││││││手機一支。│搶。證件在不知情之││││││││羅玉枝住處查獲，已││││││││領回。│├──┼───┼──────┼───────┼────┼────────┼─────────┤│二十│亥○○│93年6月3日│屏東市○○路、│子○○│皮包一個，內有現│併案。││││7時許│杭州街口││金二千元、證件、│騎乘竊得之車號ＯＭ│││││││手機一支。│Ｊ─九一０號機車行││││││││搶。│├──┼───┼──────┼───────┼────┼────────┼─────────┤│二一│亥○○│93年6月3日│屏東市○○路一│未○○│皮包一個，內有現│併案。││││7時40分許│六六之一號前││金三千元、證件、│騎乘竊得之車號ＯＭ│││││││手機一支。│Ｊ─九一０號機車行││││││││搶。│├──┼───┼──────┼───────┼────┼────────┼─────────┤│二二│亥○○│93年6月4日│屏東縣內埔鄉文│午○○│咖啡色皮包，內有│騎乘竊得之車號ＯＭ││││18時10分許│化路八九號前││現金八千五百元、│Ｊ─九一０號機車行│││││││證件、手機一支。│搶。手機在巳○○住││││││││處查扣；證件在不知││││││││情之羅玉枝住處查獲││││││││，均已領回。│└──┴───┴──────┴───────┴────┴────────┴─────────┘附表二：（巳○○搶奪部分）┌──┬───┬──────┬───────┬────┬────────┬─────────┐│編號│行為人│犯罪時間│犯罪地點│被害人│犯罪所得│備註│├──┼───┼──────┼───────┼────┼────────┼─────────┤│一│巳○○│93年5月03日│屏東縣潮州鎮公│丙○○○│皮包一個，內有現│││││10時許│園路四一號前││金三千七百元、戒││││││││指、耳環、手機一││││││││支。││├──┼───┼──────┼───────┼────┼────────┼─────────┤│二│巳○○│93年6月1日│屏東縣潮州鎮朝│丁○○│皮包一個，內有現│共騎竊得之車號ＰＵ│││亥○○│5時20分許│昇東路││金五百元、證件、│Ｇ─三七九號機車行│││││││手機一支。│搶。證件在不知情之││││││││羅玉枝住處查獲，已││││││││領回。│└──┴───┴──────┴───────┴────┴────────┴─────────┘",
  "characters": {
    "judges": [
      "翁世容"
    ],
    "prosecutors": [
      "黃莉琄"
    ],
    "lawyers": [

    ],
    "clerks": [
      "王秋淑"
    ],
    "plaintiffs": [

    ],
    "defendants": [
      "亥○○",
      "巳○○",
      "右列被告因搶奪等案件，經檢察官提起公訴（九十三年度核退偵字第五一號、九十三",
      "年度偵字第二五七二、二九０八、三０二四號），及移",
      "九五四、四一０一號），本院裁定改以簡式審判程序審理，茲判決如左："
    ],
    "prosecutor_office": [
      "臺灣屏東地方法院檢察署檢察官"
    ],
    "creditors": [

    ],
    "debtors": [

    ],
    "judicial_associate_officer": [

    ]
  },
  "adjudged_at": "2004-08-31",
  "created_at": "2016-02-06 02:56:58",
  "updated_at": "2016-02-06 02:56:58"
}