{
  "identify": "TYD-100-聲-3077-20110823-1",
  "court": {
    "name": "臺灣桃園地方法院",
    "code": "TYD"
  },
  "division": {
    "name": "刑事",
    "code": "M"
  },
  "year": 100,
  "word": "聲",
  "number": "3077",
  "jcheck": "1",
  "reason": "聲請沒收",
  "content": "臺灣桃園地方法院刑事裁定             100年度聲字第3077號\n聲  請  人  臺灣桃園地方法院檢察署檢察官\n被      告  詹侑庭\n上列被告因違犯商標法案件，經聲請人聲請沒收（100 年度聲沒\n字第108號），本院裁定如下：\n    主  文\n扣案之仿冒GUCCI註冊商標圖樣之側背包壹個沒收之。\n    事  實\n一、聲請意旨略以：被告詹侑庭涉犯違反商標法案件，業經98年\n    度偵字第21423 號緩起訴處分確定，而扣案之側背包1 個，\n    係仿冒GUCCI 註冊商標圖樣之商品，爰依商標法第83條規定\n    聲請沒收等語。\n二、按犯商標法第81條、第82條之罪所製造、販賣、陳列、輸出\n    或輸入之商品，或所提供於服務使用之物品或文書，不問屬\n    於犯人與否，均沒收之，商標法第83條定有明文。\n三、經查，被告前因違反商標法案件，經臺灣桃園地方法院檢察\n    署檢察官偵查結果，認被告犯商標法第82條之罪，以緩起訴\n    處分為適當，乃以98年度偵字第21423 號為緩起訴處分確定\n    在案，有該緩起訴處分書、臺灣高等法院被告前案紀錄表各\n    1 紙在卷可稽。而警佯為買家，向被告購入之扣案仿冒GUCC\n    I 註冊商標圖樣之側背包1 個，係未經商標權人授權使用之\n    仿冒商品乙節，亦有鑑定證明書1 份、經濟部智慧財產局商\n    標資料檢索服務1 紙存卷足憑（見偵卷第33、58頁），係本\n    件犯罪所販賣之商品，依上說明，不問屬於犯人與否，應沒\n    收之，本件聲請應予准許。\n四、爰依商標法第83條，刑事訴訟法第220 條，裁定如主文。\n中    華    民    國    100   年    8     月    23    日\n                  刑事第九庭  法  官  蘇琬能\n以上正本證明與原本無異。\n如不服本裁定，應於裁定送達後5 日內向本院提出抗告狀。\n                              書記官  黃惠鈴\n中    華    民    國   100    年    8     月    24    日",
  "structure": {
    "main": "扣案之仿冒GUCCI註冊商標圖樣之側背包壹個沒收之。",
    "fact": "一、聲請意旨略以：被告詹侑庭涉犯違反商標法案件，業經98年\n    度偵字第21423 號緩起訴處分確定，而扣案之側背包1 個，\n    係仿冒GUCCI 註冊商標圖樣之商品，爰依商標法第83條規定\n    聲請沒收等語。\n二、按犯商標法第81條、第82條之罪所製造、販賣、陳列、輸出\n    或輸入之商品，或所提供於服務使用之物品或文書，不問屬\n    於犯人與否，均沒收之，商標法第83條定有明文。\n三、經查，被告前因違反商標法案件，經臺灣桃園地方法院檢察\n    署檢察官偵查結果，認被告犯商標法第82條之罪，以緩起訴\n    處分為適當，乃以98年度偵字第21423 號為緩起訴處分確定\n    在案，有該緩起訴處分書、臺灣高等法院被告前案紀錄表各\n    1 紙在卷可稽。而警佯為買家，向被告購入之扣案仿冒GUCC\n    I 註冊商標圖樣之側背包1 個，係未經商標權人授權使用之\n    仿冒商品乙節，亦有鑑定證明書1 份、經濟部智慧財產局商\n    標資料檢索服務1 紙存卷足憑（見偵卷第33、58頁），係本\n    件犯罪所販賣之商品，依上說明，不問屬於犯人與否，應沒\n    收之，本件聲請應予准許。\n四、爰依商標法第83條，刑事訴訟法第220 條，裁定如主文。"
  },
  "search": "臺灣桃園地方法院刑事裁定100年度聲字第3077號聲請人臺灣桃園地方法院檢察署檢察官被告詹侑庭上列被告因違犯商標法案件，經聲請人聲請沒收（100年度聲沒字第108號），本院裁定如下：主文扣案之仿冒GUCCI註冊商標圖樣之側背包壹個沒收之。事實一、聲請意旨略以：被告詹侑庭涉犯違反商標法案件，業經98年度偵字第21423號緩起訴處分確定，而扣案之側背包1個，係仿冒GUCCI註冊商標圖樣之商品，爰依商標法第83條規定聲請沒收等語。二、按犯商標法第81條、第82條之罪所製造、販賣、陳列、輸出或輸入之商品，或所提供於服務使用之物品或文書，不問屬於犯人與否，均沒收之，商標法第83條定有明文。三、經查，被告前因違反商標法案件，經臺灣桃園地方法院檢察署檢察官偵查結果，認被告犯商標法第82條之罪，以緩起訴處分為適當，乃以98年度偵字第21423號為緩起訴處分確定在案，有該緩起訴處分書、臺灣高等法院被告前案紀錄表各1紙在卷可稽。而警佯為買家，向被告購入之扣案仿冒GUCCI註冊商標圖樣之側背包1個，係未經商標權人授權使用之仿冒商品乙節，亦有鑑定證明書1份、經濟部智慧財產局商標資料檢索服務1紙存卷足憑（見偵卷第33、58頁），係本件犯罪所販賣之商品，依上說明，不問屬於犯人與否，應沒收之，本件聲請應予准許。四、爰依商標法第83條，刑事訴訟法第220條，裁定如主文。中華民國100年8月23日刑事第九庭法官蘇琬能以上正本證明與原本無異。如不服本裁定，應於裁定送達後5日內向本院提出抗告狀。書記官黃惠鈴中華民國100年8月24日",
  "characters": {
    "judges": [
      "蘇琬能"
    ],
    "prosecutors": [

    ],
    "lawyers": [

    ],
    "clerks": [
      "黃惠鈴"
    ],
    "plaintiffs": [

    ],
    "defendants": [
      "詹侑庭"
    ],
    "prosecutor_office": [
      "臺灣桃園地方法院檢察署檢察官"
    ],
    "creditors": [

    ],
    "debtors": [

    ],
    "judicial_associate_officer": [

    ]
  },
  "adjudged_at": "2011-08-23",
  "created_at": "2016-02-12 20:46:19",
  "updated_at": "2016-02-12 20:46:19"
}