{
  "identify": "TCD-100-中簡-631-20110310-1",
  "court": {
    "name": "臺灣臺中地方法院",
    "code": "TCD"
  },
  "division": {
    "name": "刑事",
    "code": "M"
  },
  "year": 100,
  "word": "中簡",
  "number": "631",
  "jcheck": "1",
  "reason": "賭博",
  "content": "臺灣臺中地方法院刑事簡易判決        100年度中簡字第631號\n聲  請  人  臺灣臺中地方法院檢察署檢察官\n被      告  林皇昇\n            陸自豪\n上列被告因賭博案件，經檢察官聲請以簡易判決處刑（99年度偵\n字第25888號），本院判決如下：\n    主    文\n林皇昇共同犯圖利聚眾賭博罪，處有期徒刑肆月，如易科罰金，\n以新臺幣壹仟元折算壹日。\n陸自豪犯賭博罪，處罰金新臺幣陸仟元，如易服勞役，以新臺幣\n壹仟元折算壹日。\n    犯罪事實及理由\n一、本案犯罪事實、證據及理由均引用處刑書之記載（詳附件）\n    。\n二、依刑事訴訟法第449條第1項、第454條第2項，刑法第28條、\n    第266條第1項、第268條、第55條前段、第41條第1項前段、\n    第42條第3 項前段，刑法施行法第1條之1，逕以簡易判決處\n    如主文所示之刑。\n三、如不服本判決應於收受判決後10日內向本院提出上訴書狀，\n    並應敘述具體理由；其未敘述上訴理由者，應於上訴期間屆\n    滿後20日內向本院補提理由書（均須按他造當事人之人數附\n    繕本）「切勿逕送上級法院」。\n中    華    民    國   100    年    3     月    10    日\n                  臺中簡易庭  法  官  林慧英\n上正本證明與原本無異。\n                              書記官  陳玲誼\n中    華    民    國   100    年    3     月    10    日\n附錄論罪科刑法條\n刑法第266條第1項\n在公共場所或公眾得出入之場所賭博財物者，處1 千元以下罰金\n。但以供人暫時娛樂之物為賭者，不在此限。\n刑法第268條\n意圖營利，供給賭博場所或聚眾賭博者，處3 年以下有期徒刑，\n得併科3千元以下罰金。",
  "structure": {
    "main": "林皇昇共同犯圖利聚眾賭博罪，處有期徒刑肆月，如易科罰金，\n以新臺幣壹仟元折算壹日。\n陸自豪犯賭博罪，處罰金新臺幣陸仟元，如易服勞役，以新臺幣\n壹仟元折算壹日。",
    "fact": "一、本案犯罪事實、證據及理由均引用處刑書之記載（詳附件）\n    。\n二、依刑事訴訟法第449條第1項、第454條第2項，刑法第28條、\n    第266條第1項、第268條、第55條前段、第41條第1項前段、\n    第42條第3 項前段，刑法施行法第1條之1，逕以簡易判決處\n    如主文所示之刑。\n三、如不服本判決應於收受判決後10日內向本院提出上訴書狀，\n    並應敘述具體理由；其未敘述上訴理由者，應於上訴期間屆\n    滿後20日內向本院補提理由書（均須按他造當事人之人數附\n    繕本）「切勿逕送上級法院」。",
    "reason": "一、本案犯罪事實、證據及理由均引用處刑書之記載（詳附件）\n    。\n二、依刑事訴訟法第449條第1項、第454條第2項，刑法第28條、\n    第266條第1項、第268條、第55條前段、第41條第1項前段、\n    第42條第3 項前段，刑法施行法第1條之1，逕以簡易判決處\n    如主文所示之刑。\n三、如不服本判決應於收受判決後10日內向本院提出上訴書狀，\n    並應敘述具體理由；其未敘述上訴理由者，應於上訴期間屆\n    滿後20日內向本院補提理由書（均須按他造當事人之人數附\n    繕本）「切勿逕送上級法院」。"
  },
  "search": "臺灣臺中地方法院刑事簡易判決100年度中簡字第631號聲請人臺灣臺中地方法院檢察署檢察官被告林皇昇陸自豪上列被告因賭博案件，經檢察官聲請以簡易判決處刑（99年度偵字第25888號），本院判決如下：主文林皇昇共同犯圖利聚眾賭博罪，處有期徒刑肆月，如易科罰金，以新臺幣壹仟元折算壹日。陸自豪犯賭博罪，處罰金新臺幣陸仟元，如易服勞役，以新臺幣壹仟元折算壹日。犯罪事實及理由一、本案犯罪事實、證據及理由均引用處刑書之記載（詳附件）。二、依刑事訴訟法第449條第1項、第454條第2項，刑法第28條、第266條第1項、第268條、第55條前段、第41條第1項前段、第42條第3項前段，刑法施行法第1條之1，逕以簡易判決處如主文所示之刑。三、如不服本判決應於收受判決後10日內向本院提出上訴書狀，並應敘述具體理由；其未敘述上訴理由者，應於上訴期間屆滿後20日內向本院補提理由書（均須按他造當事人之人數附繕本）「切勿逕送上級法院」。中華民國100年3月10日臺中簡易庭法官林慧英上正本證明與原本無異。書記官陳玲誼中華民國100年3月10日附錄論罪科刑法條刑法第266條第1項在公共場所或公眾得出入之場所賭博財物者，處1千元以下罰金。但以供人暫時娛樂之物為賭者，不在此限。刑法第268條意圖營利，供給賭博場所或聚眾賭博者，處3年以下有期徒刑，得併科3千元以下罰金。",
  "characters": {
    "judges": [
      "林慧英"
    ],
    "prosecutors": [

    ],
    "lawyers": [

    ],
    "clerks": [
      "陳玲誼"
    ],
    "plaintiffs": [

    ],
    "defendants": [
      "林皇昇"
    ],
    "prosecutor_office": [
      "臺灣臺中地方法院檢察署檢察官"
    ],
    "creditors": [

    ],
    "debtors": [

    ],
    "judicial_associate_officer": [

    ]
  },
  "adjudged_at": "2011-03-10",
  "created_at": "2016-02-13 22:05:48",
  "updated_at": "2016-02-13 22:05:48"
}