{
  "identify": "TPD-100-除-627-20110311-1",
  "court": {
    "name": "臺灣臺北地方法院",
    "code": "TPD"
  },
  "division": {
    "name": "民事",
    "code": "V"
  },
  "year": 100,
  "word": "除",
  "number": "627",
  "jcheck": "1",
  "reason": "除權判決（股票）",
  "content": "臺灣臺北地方法院民事判決              100年度除字第627號\n聲  請  人  方重雄\n上列聲請人聲請除權判決事件，本院判決如下：\n    主  文\n如附表所示之證券無效。\n訴訟費用由聲請人負擔。\n    理  由\n一、上開證券，經本院以99年度司催字第2997號公示催告。\n二、所定申報權利期間，已於民國100年2月21日屆滿，迄今無人\n    申報權利。\n三、依民事訴訟法第564條第1項，判決如主文。\n中    華    民    國    100   年    3     月    11    日\n                  民事第一庭        法  官  熊志強\n本判決不得上訴。\n以上正本證明係照原本作成。\n中    華    民    國    100   年    3     月    11    日\n                                    書記官  謝盈敏\n┌────────────────────────────┐\n│附表：                                100年度除字第627號│\n├──┬──────────┬───────┬───┬──┤\n│編號│發    行    公    司│股  票  號  碼│張  數│股數│\n├──┼──────────┼───────┼───┼──┤\n│001 │新光紡織股份有限公司│83NX 000000-0 │1     │100 │\n├──┼──────────┼───────┼───┼──┤\n│002 │新光紡織股份有限公司│84NX 000000-0 │1     │210 │\n└──┴──────────┴───────┴───┴──┘",
  "structure": {
    "main": "如附表所示之證券無效。\n訴訟費用由聲請人負擔。",
    "reason": "一、上開證券，經本院以99年度司催字第2997號公示催告。\n二、所定申報權利期間，已於民國100年2月21日屆滿，迄今無人\n    申報權利。\n三、依民事訴訟法第564條第1項，判決如主文。"
  },
  "search": "臺灣臺北地方法院民事判決100年度除字第627號聲請人方重雄上列聲請人聲請除權判決事件，本院判決如下：主文如附表所示之證券無效。訴訟費用由聲請人負擔。理由一、上開證券，經本院以99年度司催字第2997號公示催告。二、所定申報權利期間，已於民國100年2月21日屆滿，迄今無人申報權利。三、依民事訴訟法第564條第1項，判決如主文。中華民國100年3月11日民事第一庭法官熊志強本判決不得上訴。以上正本證明係照原本作成。中華民國100年3月11日書記官謝盈敏┌────────────────────────────┐│附表：100年度除字第627號│├──┬──────────┬───────┬───┬──┤│編號│發行公司│股票號碼│張數│股數│├──┼──────────┼───────┼───┼──┤│001│新光紡織股份有限公司│83NX000000-0│1│100│├──┼──────────┼───────┼───┼──┤│002│新光紡織股份有限公司│84NX000000-0│1│210│└──┴──────────┴───────┴───┴──┘",
  "characters": {
    "judges": [
      "熊志強"
    ],
    "prosecutors": [

    ],
    "lawyers": [

    ],
    "clerks": [
      "謝盈敏"
    ],
    "plaintiffs": [

    ],
    "defendants": [

    ],
    "prosecutor_office": [
      "方重雄"
    ],
    "creditors": [

    ],
    "debtors": [

    ],
    "judicial_associate_officer": [

    ]
  },
  "adjudged_at": "2011-03-11",
  "created_at": "2016-02-13 21:53:32",
  "updated_at": "2016-02-13 21:53:32"
}