{
  "identify": "PCD-92-智-54-20040430-1",
  "court": {
    "name": "臺灣新北地方法院",
    "code": "PCD"
  },
  "division": {
    "name": "民事",
    "code": "V"
  },
  "year": 92,
  "word": "智",
  "number": "54",
  "jcheck": "1",
  "reason": "侵權行為損害賠償",
  "content": "臺灣板橋地方法院民事裁定                            九十二年度智字第五四號\n    原      告  龍達塑膠股份有限公司\n    法定代理人  甲○○\n    訴訟代理人  李耀馨律師\n    被      告  洋皓實業有限公司\n    法定代理人  乙○○\n    訴訟代理人  吳慶隆律師\n右當事人間請求侵權行為損害賠償事件，本院裁定如左：\n    主      文\n本件於經濟部民國九十三年三月十九日經訴字第○九三○六二一五一○○號訴願決定\n行政爭訟事件訟終結前，停止訴訟程序。\n    理      由\n一、按訴訟全部或一部之裁判，以他訴訟之法律關係是否成立為據者，法院得在他訴\n    訟終結前，以裁定停止訴訟程序。前項規定，於應依行政爭訟程序確定法律關係\n    是否成立者準用之，但法律別有規定者，依其規定；關於發明專利之民事或刑事\n    訴訟，申請案、異議案、舉發案、撤銷案確定前，得止偵查或審判；新型專利準\n    用之，民事訴訟法第一百八十二條、專利法第九十條、第一百零五條分別定有明\n    文。\n二、查本件民事訴訟之裁判，以經濟部民國九十三年三月十九日經訴字第○九三○六\n    二一五一○○號訴願決定行政爭訟事件（關於新型第一六二二七○號專利舉發案\n    ）之處分結果為據，本院認有裁定停止本件民事訴訟程序之必要。\n三、依首開法條裁定如主文。\n中      華      民      國    九十三    年      四      月     三十     日\n                                臺灣板橋地方法院民一庭\n                                                法  官  黃信滿\n右正本證明與原本無異\n如不服本裁定應於送達後十日內向本院提出抗告狀。\n中      華      民      國    九十三    年      四      月     三十     日\n                                                書記官  吳美瑤\n",
  "structure": {
    "main": "本件於經濟部民國九十三年三月十九日經訴字第○九三○六二一五一○○號訴願決定\n行政爭訟事件訟終結前，停止訴訟程序。",
    "reason": "一、按訴訟全部或一部之裁判，以他訴訟之法律關係是否成立為據者，法院得在他訴\n    訟終結前，以裁定停止訴訟程序。前項規定，於應依行政爭訟程序確定法律關係\n    是否成立者準用之，但法律別有規定者，依其規定；關於發明專利之民事或刑事\n    訴訟，申請案、異議案、舉發案、撤銷案確定前，得止偵查或審判；新型專利準\n    用之，民事訴訟法第一百八十二條、專利法第九十條、第一百零五條分別定有明\n    文。\n二、查本件民事訴訟之裁判，以經濟部民國九十三年三月十九日經訴字第○九三○六\n    二一五一○○號訴願決定行政爭訟事件（關於新型第一六二二七○號專利舉發案\n    ）之處分結果為據，本院認有裁定停止本件民事訴訟程序之必要。\n三、依首開法條裁定如主文。"
  },
  "search": "臺灣板橋地方法院民事裁定九十二年度智字第五四號原告龍達塑膠股份有限公司法定代理人甲○○訴訟代理人李耀馨律師被告洋皓實業有限公司法定代理人乙○○訴訟代理人吳慶隆律師右當事人間請求侵權行為損害賠償事件，本院裁定如左：主文本件於經濟部民國九十三年三月十九日經訴字第○九三○六二一五一○○號訴願決定行政爭訟事件訟終結前，停止訴訟程序。理由一、按訴訟全部或一部之裁判，以他訴訟之法律關係是否成立為據者，法院得在他訴訟終結前，以裁定停止訴訟程序。前項規定，於應依行政爭訟程序確定法律關係是否成立者準用之，但法律別有規定者，依其規定；關於發明專利之民事或刑事訴訟，申請案、異議案、舉發案、撤銷案確定前，得止偵查或審判；新型專利準用之，民事訴訟法第一百八十二條、專利法第九十條、第一百零五條分別定有明文。二、查本件民事訴訟之裁判，以經濟部民國九十三年三月十九日經訴字第○九三○六二一五一○○號訴願決定行政爭訟事件（關於新型第一六二二七○號專利舉發案）之處分結果為據，本院認有裁定停止本件民事訴訟程序之必要。三、依首開法條裁定如主文。中華民國九十三年四月三十日臺灣板橋地方法院民一庭法官黃信滿右正本證明與原本無異如不服本裁定應於送達後十日內向本院提出抗告狀。中華民國九十三年四月三十日書記官吳美瑤",
  "characters": {
    "judges": [
      "黃信滿"
    ],
    "prosecutors": [

    ],
    "lawyers": [
      "李耀馨",
      "吳慶隆"
    ],
    "clerks": [
      "吳美瑤"
    ],
    "plaintiffs": [
      "龍達塑膠股份有限公司"
    ],
    "defendants": [
      "洋皓實業有限公司"
    ],
    "prosecutor_office": [

    ],
    "creditors": [

    ],
    "debtors": [

    ],
    "judicial_associate_officer": [

    ]
  },
  "adjudged_at": "2004-04-30",
  "created_at": "2016-02-06 00:02:50",
  "updated_at": "2016-02-06 00:02:50"
}