{
  "identify": "ILD-100-侵訴-4-20110607-1",
  "court": {
    "name": "臺灣宜蘭地方法院",
    "code": "ILD"
  },
  "division": {
    "name": "刑事",
    "code": "M"
  },
  "year": 100,
  "word": "侵訴",
  "number": "4",
  "jcheck": "1",
  "reason": "妨害性自主罪",
  "content": "臺灣宜蘭地方法院刑事判決              100年度侵訴字第4號\n公  訴  人  臺灣宜蘭地方法院檢察署檢察官\n被      告  林保全\n公設辯護人  本院公設辯護人黃之中  \n上列被告因妨害性自主罪案件，經檢察官提起公訴（98年度偵字\n第4835號），本院判決如下：\n    主  文\n林保全無罪。\n    理  由\n壹、程序部分：\n一、被告林保全與被害人甲女（代號：00000000，79年10月生，\n    姓名年籍詳卷）為鄰居，為避免因揭露被告住居所及犯罪行\n    為地等資料，因此而揭露足資識別甲女身分之資訊，爰依性\n    侵害犯罪防治法第12條第2項之規定，將被告住處地址略稱\n    為「宜蘭縣蘇澳鎮」，被害人部分以「甲女」代之；至於犯\n    罪行為地即為被告住處，亦僅略稱「宜蘭縣蘇澳鎮」。\n二、被告以外之人於審判外之言詞或書面陳述，除法律有規定者\n    外，不得作為證據（刑事訴訟法第159條第1項參照）；查甲\n    女之警詢筆錄，為被告以外之人於審判外之陳述，核屬傳聞\n    證據，被告之辯護人既已爭執前開傳聞證據之證據能力（見\n    本院卷第33頁），揆諸前開所述，甲女之警詢筆錄自無證據\n    能力。\n三、按當事人、代理人或辯護人於法院調查證據時，知有第159\n    條第1項不得為證據之情形，而未於言詞辯論終結前聲明異\n    議者，視為有前項之同意，同法第159條之5亦有明文。本件\n    當事人對於本判決下列所引用之供述證據之證據能力，於本\n    院審理時均表示無意見而不予爭執，且迄至言詞辯論終結前\n    亦未再聲明異議，本院審酌上開證據資料製作時之情況，尚\n    無違法不當及證明力明顯過低之瑕疵之情形，爰依刑事訴訟\n    法第159條之5規定，認均具有證據能力。又本院下列所引用\n    卷內之文書證據之證據能力部分，並無證據證明係公務員違\n    背法定程序所取得，且當事人等於本院亦均未主張排除其證\n    據能力，且迄本院言詞辯論終結前均未表示異議，本院審酌\n    前揭文書證據並無顯不可信之情況與不得作為證據之情形，\n    依刑事訴訟法第158條之4反面解釋及第159條之4之規定，亦\n    應認均有證據能力。 \n貳、實體部分：\n一、公訴意旨：被告林保全為自甲女年幼時，即看甲女成長之長\n    輩，明知甲女係智能障礙之人，竟於民國97年年底、98年1\n    月下旬及98年3月間，利用甲女智能障礙不知如何抗拒以及\n    酒後不能抗拒之情形，在其宜蘭縣蘇澳鎮住處，分別三次與\n    甲女為性交行為。因認被告係犯刑法第225條第1項對於女子\n    利用其心智缺陷不知抗拒而為性交罪嫌。\n二、公訴人認被告涉有前揭罪嫌，係以：被告之供述、被害人甲\n    女之指訴、羅東博愛醫院出具之受理疑似性侵害事件驗傷診\n    斷書、羅東聖母醫院99年12月9日天羅民字第1055號函附之\n    精神鑑定報告書各1份等，為主要論據。訊據被告就其於上\n    開時間、地點曾與甲女發生性交行為之事實，固不爭執，惟\n    堅決否認有利用甲女心智缺陷不知抗拒之際，乘機而為性交\n    之犯行，辯稱：伊不知甲女領有身心障礙手冊，於來往期間\n    也不知甲女與一般正常人有何不同之處，甲女常喝了酒來找\n    伊，為向伊要錢，主動與伊為性交3次，伊性交完後都有給\n    甲女錢，每次約一千元或數百元不等等語。\n三、按犯罪事實應依證據認定之，無證據不得認定犯罪事實；不\n    能證明被告犯罪者，應諭知無罪之判決，刑事訴訟法第154\n    條第2項、第301條第1項定有明文。犯罪事實之認定，應憑\n    真實之證據，倘證據是否真實尚欠明確，自難以擬制推測之\n    方法，為其判斷之基礎；而認定犯罪事實之證據係指足以認\n    定被告確有犯罪行為之積極證據而言，該項證據自須適合於\n    被告犯罪事實之認定，始得採為斷罪資料（最高法院53年台\n    上字第656號、29年上字第3105號判例意旨參照）。又按刑\n    法第225條第1項之乘機性交罪，係以行為人對於男女利用其\n    精神、身體障礙、心智缺陷或其他相類之情形，不能或不知\n    抗拒而為性交，為其成立要件；其所謂不能或不知抗拒而為\n    性交，係指被害人因上開情形，致無同意性交之理解，或無\n    抗拒性交之能力者而言（臺灣高等法院99年度上訴字第423\n    號判決意旨參照）。次按刑法第225條第1項乘機性交罪，僅\n    處罰故意犯，因此行為人就被害人有精神、身體障礙、心智\n    缺陷或其他相類之情形，雖不以明知為必要，然至少應有知\n    悉或預見被害人有該等情形，仍予利用，並容任其發生性交\n    之意欲，始足成立本罪（最高法院99年度台上字第1155號判\n    決意旨參照）。再按刑法第225條之立法理由，有關被害人\n    狀態之認定，並不以被害人是否領有身心障礙手冊為判斷之\n    依據，而係以被害人身心之客觀狀態作為認定之標準，以與\n    保護被害人之意旨相呼應（最高法院94年度台上字第7213號\n    判決意旨參照）。\n四、查被告有於上揭時地與被害人甲女為三次性交行為之事實，\n    業據其坦承不諱，核與被害人甲女於檢察官偵訊及本院審理\n    時所述大致相符，堪認屬實。惟被告是否構成刑法第225條\n    第1項之乘機性交罪，端視被告與甲女為性交時，甲女是否\n    有不能或不知抗拒而為性交，致無同意性交之理解，或無抗\n    拒性交之能力？如是，則被告是否事先知悉甲女係屬心智缺\n    陷之人，及有無利用Ａ女心智缺陷，不知抗拒之機會，對之\n    為性交行為？經查：\n  (一)被害人甲女於本案偵查中，經檢察官送請羅東聖母醫院進行\n    精神鑑定，其中進行身心及精神狀態檢查面談時，甲女意識\n    清楚，外觀整潔，態度合作，對答切題，語言的理解和表達\n    能力尚可，能自在地回答日常生活情境相關問題，描述雖簡\n    短，但具體且清楚，鑑定結論則認為：甲女屬輕度至中度智\n    能障礙之人，就一般生活能力而論，約與輕度智能障礙者相\n    近，由於家庭功能不良，甲女在真實生活中的感情支持薄弱\n    ，使其易將溫情的渴望投射於男女情愛，又對男女情愛與男\n    歡女愛混淆不清，期待經由性行為感受親密和溫馨，其對於\n    性交行為雖不是「不能或不知抗拒」，但就性自主表達所需\n    的現實判斷和思考能力而言，甲女仍有能力上的障礙，不應\n    視為有完全的自主表達能力，此種考慮正如「兒童少年性交\n    易保護法」對於兒童少年性自主表達能力的考慮一樣等情，\n    有羅東聖母醫院99年12月9日天羅聖民字第1055號函覆之精\n    神鑑定報告書在卷可。復稽之被害人甲女於檢察官偵訊時另\n    指述伊曾與案外人雷文彬（業據檢察官為不起訴處分在案）\n    於98年1至3月間為性交，並供稱：伊知道可以拒絕與雷文彬\n    發生性行為，伊願意並想要跟雷文彬發生性行為等語（偵卷\n    第93-96頁），於本院審理時亦稱：伊如果不願意與他人為\n    性交，自己會拒絕，伊與被告為性交前有喝酒，伊沒有錢吃\n    飯就會跟被告要，之後就跟被告發生性行為，伊係自願與被\n    告性交，於性交時知道自己在做什麼，但伊不喜歡等語（本\n    院卷第34頁以下）。再從甲女之認知層面，其於97年底首次\n    與被告發生性行為後，即可知此行為不應發生，卻仍於其後\n    二次繼續與被告發生性關係，復徵以甲女於本院審理時，對\n    於與被告發生性交之原因及內心感受等，亦能清楚、明確地\n    答覆訊問，而就檢察官與公設辯護人之詰問，尚能切題回答\n    所詢問之問題，足認其理解力正常無礙。據上，被害人甲女\n    於智能上雖為輕度至中度智能障礙之人，但於日常生活能力\n    則較近為輕度智能障礙，雖心理上因對溫情的渴望而投射於\n    男女情愛並混淆情愛與性交之意義，但對於是否為性交行為\n    顯非不能或不知抗拒，洵堪認定。則被告與被害人甲女為性\n    交時，即難認有何利用被害人甲女有不知或不能抗拒為性交\n    行為之情形。\n  (二)至被害人甲女於檢察官偵訊時雖指稱：每次被告與伊性交，\n    伊都有跟被告說不要，但被告都一直騙伊，跟伊說沒關係，\n    伊不喜歡被告，不想與被告性交云云（偵卷第93-96頁），\n    惟此與被害人甲女於本院審理時之供述伊係自願與被告為性\n    交一情不符，況觀諸被害人甲女於檢察官偵訊時所為供述內\n    容，甲女對於案外人雷文彬之供述，忽而稱不想與他發生性\n    行為，忽而稱發生性行為是自願的，又改稱想要和他發生性\n    行為，喜歡他但他有老婆等語（偵卷第93-96頁），可見被\n    害人甲女於接受檢察官偵訊時，對於伊是否「喜歡」性交之\n    對象、是否「願意」發生性行為、是否「想要」發生性行為\n    之詢問並未確切釐清，始生前揭看似矛盾之證述，則甲女於\n    檢察官偵訊時之證述是否可採，頗有疑義。且稽之上開精神\n    鑑定報告書及被害人甲女前揭供述顯示，被害人甲女對於性\n    交行為並非不能或不知抗拒，故縱使被害人甲女情感上不喜\n    歡被告，但男女間為性交行為之原因所在多有，或因情感，\n    或因金錢等其他原因，自不能因為甲女不喜歡被告即推認甲\n    女不願意與被告為性交，亦不能因為甲女不喜歡被告卻與被\n    告為性交即遽論甲女與被告為性交行為時不知或不能抗拒。\n    是被害人甲女於檢察官偵訊時之供述，尚難據為不利於被告\n    之認定。\n五、綜上所述，本件依檢察官所提全部證據，尚不足為被告涉犯\n    上揭乘機性交罪之積極證明，無從說服本院形成被告有罪之\n    心證，本院就檢察官所指述被告之犯行仍有合理懷疑存在，\n    未達有罪之確信，基於無罪推定之原則，自應為被告無罪判\n    決之諭知。\n據上論斷，應依刑事訴訟法第301條第1項前段判決如主文。\n本案經檢察官陳錦雯到庭執行職務\n中    華    民    國   100    年    6     月    7     日\n                  刑事第四庭審判長法  官  林楨森  \n                                  法  官  辜漢忠      \n                                  法  官  陳雪玉       \n以上正本證明與原本無異。\n如不服本判決應於收受送達後十日內向本院提出上訴書狀，並應\n敘述具體理由；其未敘述上述理由者，應於上訴期間屆滿後二十\n日內向本院補提理由書(均須按他造當事人之人數附繕本)「切勿\n逕送上級法院」。\n                                  書記官  陳建宇\n中    華    民    國   100    年    6     月    7     日",
  "structure": {
    "main": "林保全無罪。",
    "reason": "壹、程序部分：\n一、被告林保全與被害人甲女（代號：00000000，79年10月生，\n    姓名年籍詳卷）為鄰居，為避免因揭露被告住居所及犯罪行\n    為地等資料，因此而揭露足資識別甲女身分之資訊，爰依性\n    侵害犯罪防治法第12條第2項之規定，將被告住處地址略稱\n    為「宜蘭縣蘇澳鎮」，被害人部分以「甲女」代之；至於犯\n    罪行為地即為被告住處，亦僅略稱「宜蘭縣蘇澳鎮」。\n二、被告以外之人於審判外之言詞或書面陳述，除法律有規定者\n    外，不得作為證據（刑事訴訟法第159條第1項參照）；查甲\n    女之警詢筆錄，為被告以外之人於審判外之陳述，核屬傳聞\n    證據，被告之辯護人既已爭執前開傳聞證據之證據能力（見\n    本院卷第33頁），揆諸前開所述，甲女之警詢筆錄自無證據\n    能力。\n三、按當事人、代理人或辯護人於法院調查證據時，知有第159\n    條第1項不得為證據之情形，而未於言詞辯論終結前聲明異\n    議者，視為有前項之同意，同法第159條之5亦有明文。本件\n    當事人對於本判決下列所引用之供述證據之證據能力，於本\n    院審理時均表示無意見而不予爭執，且迄至言詞辯論終結前\n    亦未再聲明異議，本院審酌上開證據資料製作時之情況，尚\n    無違法不當及證明力明顯過低之瑕疵之情形，爰依刑事訴訟\n    法第159條之5規定，認均具有證據能力。又本院下列所引用\n    卷內之文書證據之證據能力部分，並無證據證明係公務員違\n    背法定程序所取得，且當事人等於本院亦均未主張排除其證\n    據能力，且迄本院言詞辯論終結前均未表示異議，本院審酌\n    前揭文書證據並無顯不可信之情況與不得作為證據之情形，\n    依刑事訴訟法第158條之4反面解釋及第159條之4之規定，亦\n    應認均有證據能力。 \n貳、實體部分：\n一、公訴意旨：被告林保全為自甲女年幼時，即看甲女成長之長\n    輩，明知甲女係智能障礙之人，竟於民國97年年底、98年1\n    月下旬及98年3月間，利用甲女智能障礙不知如何抗拒以及\n    酒後不能抗拒之情形，在其宜蘭縣蘇澳鎮住處，分別三次與\n    甲女為性交行為。因認被告係犯刑法第225條第1項對於女子\n    利用其心智缺陷不知抗拒而為性交罪嫌。\n二、公訴人認被告涉有前揭罪嫌，係以：被告之供述、被害人甲\n    女之指訴、羅東博愛醫院出具之受理疑似性侵害事件驗傷診\n    斷書、羅東聖母醫院99年12月9日天羅民字第1055號函附之\n    精神鑑定報告書各1份等，為主要論據。訊據被告就其於上\n    開時間、地點曾與甲女發生性交行為之事實，固不爭執，惟\n    堅決否認有利用甲女心智缺陷不知抗拒之際，乘機而為性交\n    之犯行，辯稱：伊不知甲女領有身心障礙手冊，於來往期間\n    也不知甲女與一般正常人有何不同之處，甲女常喝了酒來找\n    伊，為向伊要錢，主動與伊為性交3次，伊性交完後都有給\n    甲女錢，每次約一千元或數百元不等等語。\n三、按犯罪事實應依證據認定之，無證據不得認定犯罪事實；不\n    能證明被告犯罪者，應諭知無罪之判決，刑事訴訟法第154\n    條第2項、第301條第1項定有明文。犯罪事實之認定，應憑\n    真實之證據，倘證據是否真實尚欠明確，自難以擬制推測之\n    方法，為其判斷之基礎；而認定犯罪事實之證據係指足以認\n    定被告確有犯罪行為之積極證據而言，該項證據自須適合於\n    被告犯罪事實之認定，始得採為斷罪資料（最高法院53年台\n    上字第656號、29年上字第3105號判例意旨參照）。又按刑\n    法第225條第1項之乘機性交罪，係以行為人對於男女利用其\n    精神、身體障礙、心智缺陷或其他相類之情形，不能或不知\n    抗拒而為性交，為其成立要件；其所謂不能或不知抗拒而為\n    性交，係指被害人因上開情形，致無同意性交之理解，或無\n    抗拒性交之能力者而言（臺灣高等法院99年度上訴字第423\n    號判決意旨參照）。次按刑法第225條第1項乘機性交罪，僅\n    處罰故意犯，因此行為人就被害人有精神、身體障礙、心智\n    缺陷或其他相類之情形，雖不以明知為必要，然至少應有知\n    悉或預見被害人有該等情形，仍予利用，並容任其發生性交\n    之意欲，始足成立本罪（最高法院99年度台上字第1155號判\n    決意旨參照）。再按刑法第225條之立法理由，有關被害人\n    狀態之認定，並不以被害人是否領有身心障礙手冊為判斷之\n    依據，而係以被害人身心之客觀狀態作為認定之標準，以與\n    保護被害人之意旨相呼應（最高法院94年度台上字第7213號\n    判決意旨參照）。\n四、查被告有於上揭時地與被害人甲女為三次性交行為之事實，\n    業據其坦承不諱，核與被害人甲女於檢察官偵訊及本院審理\n    時所述大致相符，堪認屬實。惟被告是否構成刑法第225條\n    第1項之乘機性交罪，端視被告與甲女為性交時，甲女是否\n    有不能或不知抗拒而為性交，致無同意性交之理解，或無抗\n    拒性交之能力？如是，則被告是否事先知悉甲女係屬心智缺\n    陷之人，及有無利用Ａ女心智缺陷，不知抗拒之機會，對之\n    為性交行為？經查：\n  (一)被害人甲女於本案偵查中，經檢察官送請羅東聖母醫院進行\n    精神鑑定，其中進行身心及精神狀態檢查面談時，甲女意識\n    清楚，外觀整潔，態度合作，對答切題，語言的理解和表達\n    能力尚可，能自在地回答日常生活情境相關問題，描述雖簡\n    短，但具體且清楚，鑑定結論則認為：甲女屬輕度至中度智\n    能障礙之人，就一般生活能力而論，約與輕度智能障礙者相\n    近，由於家庭功能不良，甲女在真實生活中的感情支持薄弱\n    ，使其易將溫情的渴望投射於男女情愛，又對男女情愛與男\n    歡女愛混淆不清，期待經由性行為感受親密和溫馨，其對於\n    性交行為雖不是「不能或不知抗拒」，但就性自主表達所需\n    的現實判斷和思考能力而言，甲女仍有能力上的障礙，不應\n    視為有完全的自主表達能力，此種考慮正如「兒童少年性交\n    易保護法」對於兒童少年性自主表達能力的考慮一樣等情，\n    有羅東聖母醫院99年12月9日天羅聖民字第1055號函覆之精\n    神鑑定報告書在卷可。復稽之被害人甲女於檢察官偵訊時另\n    指述伊曾與案外人雷文彬（業據檢察官為不起訴處分在案）\n    於98年1至3月間為性交，並供稱：伊知道可以拒絕與雷文彬\n    發生性行為，伊願意並想要跟雷文彬發生性行為等語（偵卷\n    第93-96頁），於本院審理時亦稱：伊如果不願意與他人為\n    性交，自己會拒絕，伊與被告為性交前有喝酒，伊沒有錢吃\n    飯就會跟被告要，之後就跟被告發生性行為，伊係自願與被\n    告性交，於性交時知道自己在做什麼，但伊不喜歡等語（本\n    院卷第34頁以下）。再從甲女之認知層面，其於97年底首次\n    與被告發生性行為後，即可知此行為不應發生，卻仍於其後\n    二次繼續與被告發生性關係，復徵以甲女於本院審理時，對\n    於與被告發生性交之原因及內心感受等，亦能清楚、明確地\n    答覆訊問，而就檢察官與公設辯護人之詰問，尚能切題回答\n    所詢問之問題，足認其理解力正常無礙。據上，被害人甲女\n    於智能上雖為輕度至中度智能障礙之人，但於日常生活能力\n    則較近為輕度智能障礙，雖心理上因對溫情的渴望而投射於\n    男女情愛並混淆情愛與性交之意義，但對於是否為性交行為\n    顯非不能或不知抗拒，洵堪認定。則被告與被害人甲女為性\n    交時，即難認有何利用被害人甲女有不知或不能抗拒為性交\n    行為之情形。\n  (二)至被害人甲女於檢察官偵訊時雖指稱：每次被告與伊性交，\n    伊都有跟被告說不要，但被告都一直騙伊，跟伊說沒關係，\n    伊不喜歡被告，不想與被告性交云云（偵卷第93-96頁），\n    惟此與被害人甲女於本院審理時之供述伊係自願與被告為性\n    交一情不符，況觀諸被害人甲女於檢察官偵訊時所為供述內\n    容，甲女對於案外人雷文彬之供述，忽而稱不想與他發生性\n    行為，忽而稱發生性行為是自願的，又改稱想要和他發生性\n    行為，喜歡他但他有老婆等語（偵卷第93-96頁），可見被\n    害人甲女於接受檢察官偵訊時，對於伊是否「喜歡」性交之\n    對象、是否「願意」發生性行為、是否「想要」發生性行為\n    之詢問並未確切釐清，始生前揭看似矛盾之證述，則甲女於\n    檢察官偵訊時之證述是否可採，頗有疑義。且稽之上開精神\n    鑑定報告書及被害人甲女前揭供述顯示，被害人甲女對於性\n    交行為並非不能或不知抗拒，故縱使被害人甲女情感上不喜\n    歡被告，但男女間為性交行為之原因所在多有，或因情感，\n    或因金錢等其他原因，自不能因為甲女不喜歡被告即推認甲\n    女不願意與被告為性交，亦不能因為甲女不喜歡被告卻與被\n    告為性交即遽論甲女與被告為性交行為時不知或不能抗拒。\n    是被害人甲女於檢察官偵訊時之供述，尚難據為不利於被告\n    之認定。\n五、綜上所述，本件依檢察官所提全部證據，尚不足為被告涉犯\n    上揭乘機性交罪之積極證明，無從說服本院形成被告有罪之\n    心證，本院就檢察官所指述被告之犯行仍有合理懷疑存在，\n    未達有罪之確信，基於無罪推定之原則，自應為被告無罪判\n    決之諭知。\n據上論斷，應依刑事訴訟法第301條第1項前段判決如主文。\n本案經檢察官陳錦雯到庭執行職務"
  },
  "search": "臺灣宜蘭地方法院刑事判決100年度侵訴字第4號公訴人臺灣宜蘭地方法院檢察署檢察官被告林保全公設辯護人本院公設辯護人黃之中上列被告因妨害性自主罪案件，經檢察官提起公訴（98年度偵字第4835號），本院判決如下：主文林保全無罪。理由壹、程序部分：一、被告林保全與被害人甲女（代號：00000000，79年10月生，姓名年籍詳卷）為鄰居，為避免因揭露被告住居所及犯罪行為地等資料，因此而揭露足資識別甲女身分之資訊，爰依性侵害犯罪防治法第12條第2項之規定，將被告住處地址略稱為「宜蘭縣蘇澳鎮」，被害人部分以「甲女」代之；至於犯罪行為地即為被告住處，亦僅略稱「宜蘭縣蘇澳鎮」。二、被告以外之人於審判外之言詞或書面陳述，除法律有規定者外，不得作為證據（刑事訴訟法第159條第1項參照）；查甲女之警詢筆錄，為被告以外之人於審判外之陳述，核屬傳聞證據，被告之辯護人既已爭執前開傳聞證據之證據能力（見本院卷第33頁），揆諸前開所述，甲女之警詢筆錄自無證據能力。三、按當事人、代理人或辯護人於法院調查證據時，知有第159條第1項不得為證據之情形，而未於言詞辯論終結前聲明異議者，視為有前項之同意，同法第159條之5亦有明文。本件當事人對於本判決下列所引用之供述證據之證據能力，於本院審理時均表示無意見而不予爭執，且迄至言詞辯論終結前亦未再聲明異議，本院審酌上開證據資料製作時之情況，尚無違法不當及證明力明顯過低之瑕疵之情形，爰依刑事訴訟法第159條之5規定，認均具有證據能力。又本院下列所引用卷內之文書證據之證據能力部分，並無證據證明係公務員違背法定程序所取得，且當事人等於本院亦均未主張排除其證據能力，且迄本院言詞辯論終結前均未表示異議，本院審酌前揭文書證據並無顯不可信之情況與不得作為證據之情形，依刑事訴訟法第158條之4反面解釋及第159條之4之規定，亦應認均有證據能力。貳、實體部分：一、公訴意旨：被告林保全為自甲女年幼時，即看甲女成長之長輩，明知甲女係智能障礙之人，竟於民國97年年底、98年1月下旬及98年3月間，利用甲女智能障礙不知如何抗拒以及酒後不能抗拒之情形，在其宜蘭縣蘇澳鎮住處，分別三次與甲女為性交行為。因認被告係犯刑法第225條第1項對於女子利用其心智缺陷不知抗拒而為性交罪嫌。二、公訴人認被告涉有前揭罪嫌，係以：被告之供述、被害人甲女之指訴、羅東博愛醫院出具之受理疑似性侵害事件驗傷診斷書、羅東聖母醫院99年12月9日天羅民字第1055號函附之精神鑑定報告書各1份等，為主要論據。訊據被告就其於上開時間、地點曾與甲女發生性交行為之事實，固不爭執，惟堅決否認有利用甲女心智缺陷不知抗拒之際，乘機而為性交之犯行，辯稱：伊不知甲女領有身心障礙手冊，於來往期間也不知甲女與一般正常人有何不同之處，甲女常喝了酒來找伊，為向伊要錢，主動與伊為性交3次，伊性交完後都有給甲女錢，每次約一千元或數百元不等等語。三、按犯罪事實應依證據認定之，無證據不得認定犯罪事實；不能證明被告犯罪者，應諭知無罪之判決，刑事訴訟法第154條第2項、第301條第1項定有明文。犯罪事實之認定，應憑真實之證據，倘證據是否真實尚欠明確，自難以擬制推測之方法，為其判斷之基礎；而認定犯罪事實之證據係指足以認定被告確有犯罪行為之積極證據而言，該項證據自須適合於被告犯罪事實之認定，始得採為斷罪資料（最高法院53年台上字第656號、29年上字第3105號判例意旨參照）。又按刑法第225條第1項之乘機性交罪，係以行為人對於男女利用其精神、身體障礙、心智缺陷或其他相類之情形，不能或不知抗拒而為性交，為其成立要件；其所謂不能或不知抗拒而為性交，係指被害人因上開情形，致無同意性交之理解，或無抗拒性交之能力者而言（臺灣高等法院99年度上訴字第423號判決意旨參照）。次按刑法第225條第1項乘機性交罪，僅處罰故意犯，因此行為人就被害人有精神、身體障礙、心智缺陷或其他相類之情形，雖不以明知為必要，然至少應有知悉或預見被害人有該等情形，仍予利用，並容任其發生性交之意欲，始足成立本罪（最高法院99年度台上字第1155號判決意旨參照）。再按刑法第225條之立法理由，有關被害人狀態之認定，並不以被害人是否領有身心障礙手冊為判斷之依據，而係以被害人身心之客觀狀態作為認定之標準，以與保護被害人之意旨相呼應（最高法院94年度台上字第7213號判決意旨參照）。四、查被告有於上揭時地與被害人甲女為三次性交行為之事實，業據其坦承不諱，核與被害人甲女於檢察官偵訊及本院審理時所述大致相符，堪認屬實。惟被告是否構成刑法第225條第1項之乘機性交罪，端視被告與甲女為性交時，甲女是否有不能或不知抗拒而為性交，致無同意性交之理解，或無抗拒性交之能力？如是，則被告是否事先知悉甲女係屬心智缺陷之人，及有無利用Ａ女心智缺陷，不知抗拒之機會，對之為性交行為？經查：(一)被害人甲女於本案偵查中，經檢察官送請羅東聖母醫院進行精神鑑定，其中進行身心及精神狀態檢查面談時，甲女意識清楚，外觀整潔，態度合作，對答切題，語言的理解和表達能力尚可，能自在地回答日常生活情境相關問題，描述雖簡短，但具體且清楚，鑑定結論則認為：甲女屬輕度至中度智能障礙之人，就一般生活能力而論，約與輕度智能障礙者相近，由於家庭功能不良，甲女在真實生活中的感情支持薄弱，使其易將溫情的渴望投射於男女情愛，又對男女情愛與男歡女愛混淆不清，期待經由性行為感受親密和溫馨，其對於性交行為雖不是「不能或不知抗拒」，但就性自主表達所需的現實判斷和思考能力而言，甲女仍有能力上的障礙，不應視為有完全的自主表達能力，此種考慮正如「兒童少年性交易保護法」對於兒童少年性自主表達能力的考慮一樣等情，有羅東聖母醫院99年12月9日天羅聖民字第1055號函覆之精神鑑定報告書在卷可。復稽之被害人甲女於檢察官偵訊時另指述伊曾與案外人雷文彬（業據檢察官為不起訴處分在案）於98年1至3月間為性交，並供稱：伊知道可以拒絕與雷文彬發生性行為，伊願意並想要跟雷文彬發生性行為等語（偵卷第93-96頁），於本院審理時亦稱：伊如果不願意與他人為性交，自己會拒絕，伊與被告為性交前有喝酒，伊沒有錢吃飯就會跟被告要，之後就跟被告發生性行為，伊係自願與被告性交，於性交時知道自己在做什麼，但伊不喜歡等語（本院卷第34頁以下）。再從甲女之認知層面，其於97年底首次與被告發生性行為後，即可知此行為不應發生，卻仍於其後二次繼續與被告發生性關係，復徵以甲女於本院審理時，對於與被告發生性交之原因及內心感受等，亦能清楚、明確地答覆訊問，而就檢察官與公設辯護人之詰問，尚能切題回答所詢問之問題，足認其理解力正常無礙。據上，被害人甲女於智能上雖為輕度至中度智能障礙之人，但於日常生活能力則較近為輕度智能障礙，雖心理上因對溫情的渴望而投射於男女情愛並混淆情愛與性交之意義，但對於是否為性交行為顯非不能或不知抗拒，洵堪認定。則被告與被害人甲女為性交時，即難認有何利用被害人甲女有不知或不能抗拒為性交行為之情形。(二)至被害人甲女於檢察官偵訊時雖指稱：每次被告與伊性交，伊都有跟被告說不要，但被告都一直騙伊，跟伊說沒關係，伊不喜歡被告，不想與被告性交云云（偵卷第93-96頁），惟此與被害人甲女於本院審理時之供述伊係自願與被告為性交一情不符，況觀諸被害人甲女於檢察官偵訊時所為供述內容，甲女對於案外人雷文彬之供述，忽而稱不想與他發生性行為，忽而稱發生性行為是自願的，又改稱想要和他發生性行為，喜歡他但他有老婆等語（偵卷第93-96頁），可見被害人甲女於接受檢察官偵訊時，對於伊是否「喜歡」性交之對象、是否「願意」發生性行為、是否「想要」發生性行為之詢問並未確切釐清，始生前揭看似矛盾之證述，則甲女於檢察官偵訊時之證述是否可採，頗有疑義。且稽之上開精神鑑定報告書及被害人甲女前揭供述顯示，被害人甲女對於性交行為並非不能或不知抗拒，故縱使被害人甲女情感上不喜歡被告，但男女間為性交行為之原因所在多有，或因情感，或因金錢等其他原因，自不能因為甲女不喜歡被告即推認甲女不願意與被告為性交，亦不能因為甲女不喜歡被告卻與被告為性交即遽論甲女與被告為性交行為時不知或不能抗拒。是被害人甲女於檢察官偵訊時之供述，尚難據為不利於被告之認定。五、綜上所述，本件依檢察官所提全部證據，尚不足為被告涉犯上揭乘機性交罪之積極證明，無從說服本院形成被告有罪之心證，本院就檢察官所指述被告之犯行仍有合理懷疑存在，未達有罪之確信，基於無罪推定之原則，自應為被告無罪判決之諭知。據上論斷，應依刑事訴訟法第301條第1項前段判決如主文。本案經檢察官陳錦雯到庭執行職務中華民國100年6月7日刑事第四庭審判長法官林楨森法官辜漢忠法官陳雪玉以上正本證明與原本無異。如不服本判決應於收受送達後十日內向本院提出上訴書狀，並應敘述具體理由；其未敘述上述理由者，應於上訴期間屆滿後二十日內向本院補提理由書(均須按他造當事人之人數附繕本)「切勿逕送上級法院」。書記官陳建宇中華民國100年6月7日",
  "characters": {
    "judges": [
      "林楨森",
      "辜漢忠",
      "陳雪玉"
    ],
    "prosecutors": [
      "陳錦雯"
    ],
    "lawyers": [

    ],
    "clerks": [
      "陳建宇"
    ],
    "plaintiffs": [

    ],
    "defendants": [
      "林保全",
      "公設辯護人  本院公設辯護人黃之中"
    ],
    "prosecutor_office": [
      "臺灣宜蘭地方法院檢察署檢察官"
    ],
    "creditors": [

    ],
    "debtors": [

    ],
    "judicial_associate_officer": [

    ]
  },
  "adjudged_at": "2011-06-07",
  "created_at": "2016-02-13 17:01:12",
  "updated_at": "2016-02-13 17:01:12"
}