{
  "identify": "KSD-100-訴-1843-20111228-1",
  "court": {
    "name": "臺灣高雄地方法院",
    "code": "KSD"
  },
  "division": {
    "name": "民事",
    "code": "V"
  },
  "year": 100,
  "word": "訴",
  "number": "1843",
  "jcheck": "1",
  "reason": "債務人異議之訴",
  "content": "臺灣高雄地方法院民事判決             100年度訴字第1843號\n原      告  莊國士\n被      告  板信商業銀行股份有限公司\n法定代理人  劉炳輝\n訴訟代理人  楊林澂律師\n上列當事人間債務人異議之訴事件，本院民國100 年12月14日言\n詞辯論終結，判決如下：\n    主      文\n原告之訴駁回。\n訴訟費用由原告負擔。\n   事實及理由\n一、原告主張：被告以本院83年度執字第12175 號強制執行事件\n    執行無結果而於民國84年2 月17日核發之債權憑證為執行名\n    義（下稱系爭執行名義），聲請對原告為強制執行，經本院\n    於民國100 年1 月20日以雄院高100 司執字第11484 號（下\n    稱系爭強制執行）執行命令，禁止原告取回本院98年度存字\n    第3692號提存事件為第三人彭美鳳提存之擔保金新台幣（下\n    同）709,042 元。惟按請求權因15年間不行使而消滅，時效\n    完成後，債務人得拒絕給付，系爭執行名義自84年2 月17日\n    算至99年2 月16日，已屆滿15年，期間被告雖曾聲請本院以\n    88年度執字第32156 號、93年度執字第5766號強制執行，然\n    均未提出債權憑證記載執行結果，可見被告已撤回或被駁回\n    聲請，依民法第136 條第2 項，時效視為不中斷，原告得以\n    罹於時效為由拒絕給付消費借款，被告前於99年12月間聲請\n    本院99年度民司執字第16 0319 號強制執行已罹於時效，茲\n    於100 年1 月14日聲請系爭強制執行，亦罹於時效；又上開\n    提存金債權另經97年度司執字第50341 號強制執行事件扣押\n    命令禁止取回，經本院民事執行處命與系爭強制執行合併執\n    行中，尚難謂執行程序終結，為此爰依強制執行法第14條第\n    1 項規定提起本訴等語。並聲明：系爭強制執行程序應予撤\n    銷。\n二、被告則以：(一)系爭強制執行程序之標的因與97年度司執字第\n    50341 號強制執行事件同一，經本院民事執行處於100 年3\n    月28日以雄院高100 司執字第11484 號通知合併執行而終結\n    ，原告不得提起異議之訴；(二)又被告於88年10月1 日及93年\n    2 月6 日均曾向本院聲請強制執行，並未撤回，嗣均因執行\n    無結果，經本院註記在債權憑證上後發還，已中斷時效進行\n    ，並未罹於時效等語置辯。並聲明如主文第1 項所示。\n三、兩造不爭執事項：\n  (一)第三人即原債權人高雄市第五信用合作社請求原告給付1 億\n    5,860 萬元及利息、違約金，獲本院81年度重訴字第48號確\n    定勝訴判決，消費借貸債權時效為15年，嗣以本院83年度執\n    字第12175 號對原告執行無結果，經本院於84年2 月17日核\n    發債權憑證即本件系爭執行名義；被告於86年9 月29日承受\n    債權。\n  (二)被告以系爭執行名義，分別於88年9 月30日聲請本院88年度\n    執字第32156 號，於93年2 月5 日聲請本院93年度民執字第\n    5766號，於99年間聲請本院99年度民司執字第160319號強制\n    執行（以上見本院93年度執字第5766號卷第4 頁債權憑證、\n    100 年度司執字第11484 號卷第4 頁補發之債權憑證之記載\n    ）。\n四、本件爭點：(一)系爭執行程序是否已經終結而不得提起異議之\n    訴？(二)被告於88年、93年間聲請強制執行後有無撤回？對原\n    告之債權，有無罹於時效？本院得心證之理由如下：\n  (一)按債務人異議之訴，係以排除執行名義之執行力為目的，應\n    限於強制執行程序終結前提起，始得為之，如強制執行程序\n    業已終結，已無阻止強制執行之實益，不得提起本訴，強制\n    執行法第14條第1 項定有明文。所謂強制執行程序終結，係\n    指執行名義之強制執行程序終結而言，執行名義之強制執行\n    程序，進行至執行名義所載債權全部達其目的時，始為終結\n    （司法院院字第2776號解釋參照）。查系爭強制執行程序中\n    ，本院民事執行處曾於100 年1 月31日核發移轉命令，准原\n    告於本院98年度存字第3692號提存事件，對提存所之709,04\n    2 元債權移轉予被告，惟經本院提存所函覆表示：受擔保利\n    益人彭美鳳有與質權人同一之權利，且該筆債權另經本院97\n    年度司執字第50341 號扣押在案，故無法准由被告領取等語\n    ，本院民事執行處乃於100 年3 月28日撤銷先前之移轉命令\n    ，並將系爭執行程序併入97年度司執字第50341 號強制執行\n    事件合併執行，俟將來原告得取回上開提存擔保金後，再由\n    被告及其他債權人領取等情，有本院民事執行處100 年1 月\n    31日雄院高100 司執逸字第11484 號執行命令、本院提存所\n    100 年3 月10日98存字第3692號函及本院民事執行處100 年\n    3 月28日雄院高100 司執逸字第11484 號執行通知各1 紙附\n    卷可稽，故系爭強制執行程序案號雖行政報結，然實已併入\n    另案執行中，將來原告得領回之條件成就後，始得由被告領\n    取，自難謂被告之債權已實現或已執行而無效果，揆諸前揭\n    說明，系爭強制執行程序尚未終結，原告提起本件異議之訴\n    ，於法有據，被告此項辯解不足憑採。\n  (二)按強制執行法第14條第1 項規定之債務人異議之訴，須執行\n    名義成立後，有消滅或妨礙債權人請求之事由發生，始得提\n    起。所謂消滅債權人請求之事由，例如清償、提存、抵銷、\n    免除、混同、債權讓與、債務承擔、更改、消滅時效完成、\n    解除條件成就、契約解除或撤銷、另訂和解契約，或其他類\n    此之情形（最高法院98年台上字第1899號判決意旨參照）。\n    而按請求權，因15年間不行使而消滅；消滅時效因開始執行\n    行為或聲請強制執行而中斷；且時效中斷者，自中斷之事由\n    終止時，重行起算，民法第125 條前段、第129 條第2 項第\n    5 款及第137 條第1 項分別定有明文。又債務人無財產可供\n    強制執行，或雖有財產經強制執行後所得之數額仍不足清償\n    債務時，執行法院應命債權人於一個月內查報債務人財產，\n    債權人到期不為報告或查報無財產者，應發給憑證，交債權\n    人收執，載明俟發見有財產時，再予強制執行，債權人聲請\n    執行，而陳明債務人現無財產可供執行者，執行法院得逕行\n    發給憑證，強制執行法第27條定有明文。執行法院發予債權\n    憑證交債權人收執時，執行行為即為終結，因開始執行行為\n    而中斷之時效，應由此重行起算（最高法院89年度台上字第\n    2544號判決要旨參照）。查本件被告承受債權後，於88年9\n    月30日以系爭執行名義聲請聲請本院88年度執字第32156 號\n    強制執行，嗣併入本院87年度執字第32355 號另案執行，執\n    行無結果；復於93年間以系爭執行名義聲請本院93年度民執\n    字第5766號對原告強制執行，經本院於93年2 月9 日在債權\n    憑證上註記「執行無結果」後寄還被告；又於99年間以系爭\n    執行名義聲請本院99年度民司執字第160319號強制執行，經\n    本院於99年12月30日註記「執行無結果」後發還，此有債權\n    憑證及補發之債權憑證、93年2 月9 日執行審理單及送達回\n    證各1 份附卷可考（見本院93年度執字第5766號卷第4 頁、\n    100 年度司執字第11484 號卷第4 頁及本院100 年度訴字第\n    1843號卷第38、54至55頁），未有何撤回或被駁回聲請之情\n    形，自無民法第136 條第2 項時效視為不中斷規定之適用，\n    足見被告債權消滅時效分別於88年、93年間均有中斷進行，\n    迄今顯未罹於15年消滅時效，原告主張委無可採。\n  (三)綜上，原告主張系爭執行名義已罹於時效無可憑採，其提起\n    本件債務人異議之訴，請求撤銷本院100 年度司執字第1148\n    4 號強制執行程序，為無理由，應予駁回。\n五、據上論結，原告之訴為無理由，依民事訴訟法第78條，判決\n    如主文。\n中    華    民    國  100     年    12    月    28    日\n                      民事第四庭    法  官  李俊霖\n以上正本係照原本製成。\n如對本判決上訴，須於判決送達後20日內向本院提出上訴狀。如\n委任律師提起上訴者，應一併繳納上訴審裁判費。\n中    華    民    國  100     年    12    月    28    日\n                                    書記官  邱上一",
  "structure": {
    "main": "原告之訴駁回。\n訴訟費用由原告負擔。",
    "fact": "一、原告主張：被告以本院83年度執字第12175 號強制執行事件\n    執行無結果而於民國84年2 月17日核發之債權憑證為執行名\n    義（下稱系爭執行名義），聲請對原告為強制執行，經本院\n    於民國100 年1 月20日以雄院高100 司執字第11484 號（下\n    稱系爭強制執行）執行命令，禁止原告取回本院98年度存字\n    第3692號提存事件為第三人彭美鳳提存之擔保金新台幣（下\n    同）709,042 元。惟按請求權因15年間不行使而消滅，時效\n    完成後，債務人得拒絕給付，系爭執行名義自84年2 月17日\n    算至99年2 月16日，已屆滿15年，期間被告雖曾聲請本院以\n    88年度執字第32156 號、93年度執字第5766號強制執行，然\n    均未提出債權憑證記載執行結果，可見被告已撤回或被駁回\n    聲請，依民法第136 條第2 項，時效視為不中斷，原告得以\n    罹於時效為由拒絕給付消費借款，被告前於99年12月間聲請\n    本院99年度民司執字第16 0319 號強制執行已罹於時效，茲\n    於100 年1 月14日聲請系爭強制執行，亦罹於時效；又上開\n    提存金債權另經97年度司執字第50341 號強制執行事件扣押\n    命令禁止取回，經本院民事執行處命與系爭強制執行合併執\n    行中，尚難謂執行程序終結，為此爰依強制執行法第14條第\n    1 項規定提起本訴等語。並聲明：系爭強制執行程序應予撤\n    銷。\n二、被告則以：(一)系爭強制執行程序之標的因與97年度司執字第\n    50341 號強制執行事件同一，經本院民事執行處於100 年3\n    月28日以雄院高100 司執字第11484 號通知合併執行而終結\n    ，原告不得提起異議之訴；(二)又被告於88年10月1 日及93年\n    2 月6 日均曾向本院聲請強制執行，並未撤回，嗣均因執行\n    無結果，經本院註記在債權憑證上後發還，已中斷時效進行\n    ，並未罹於時效等語置辯。並聲明如主文第1 項所示。\n三、兩造不爭執事項：\n  (一)第三人即原債權人高雄市第五信用合作社請求原告給付1 億\n    5,860 萬元及利息、違約金，獲本院81年度重訴字第48號確\n    定勝訴判決，消費借貸債權時效為15年，嗣以本院83年度執\n    字第12175 號對原告執行無結果，經本院於84年2 月17日核\n    發債權憑證即本件系爭執行名義；被告於86年9 月29日承受\n    債權。\n  (二)被告以系爭執行名義，分別於88年9 月30日聲請本院88年度\n    執字第32156 號，於93年2 月5 日聲請本院93年度民執字第\n    5766號，於99年間聲請本院99年度民司執字第160319號強制\n    執行（以上見本院93年度執字第5766號卷第4 頁債權憑證、\n    100 年度司執字第11484 號卷第4 頁補發之債權憑證之記載\n    ）。\n四、本件爭點：(一)系爭執行程序是否已經終結而不得提起異議之\n    訴？(二)被告於88年、93年間聲請強制執行後有無撤回？對原\n    告之債權，有無罹於時效？本院得心證之理由如下：\n  (一)按債務人異議之訴，係以排除執行名義之執行力為目的，應\n    限於強制執行程序終結前提起，始得為之，如強制執行程序\n    業已終結，已無阻止強制執行之實益，不得提起本訴，強制\n    執行法第14條第1 項定有明文。所謂強制執行程序終結，係\n    指執行名義之強制執行程序終結而言，執行名義之強制執行\n    程序，進行至執行名義所載債權全部達其目的時，始為終結\n    （司法院院字第2776號解釋參照）。查系爭強制執行程序中\n    ，本院民事執行處曾於100 年1 月31日核發移轉命令，准原\n    告於本院98年度存字第3692號提存事件，對提存所之709,04\n    2 元債權移轉予被告，惟經本院提存所函覆表示：受擔保利\n    益人彭美鳳有與質權人同一之權利，且該筆債權另經本院97\n    年度司執字第50341 號扣押在案，故無法准由被告領取等語\n    ，本院民事執行處乃於100 年3 月28日撤銷先前之移轉命令\n    ，並將系爭執行程序併入97年度司執字第50341 號強制執行\n    事件合併執行，俟將來原告得取回上開提存擔保金後，再由\n    被告及其他債權人領取等情，有本院民事執行處100 年1 月\n    31日雄院高100 司執逸字第11484 號執行命令、本院提存所\n    100 年3 月10日98存字第3692號函及本院民事執行處100 年\n    3 月28日雄院高100 司執逸字第11484 號執行通知各1 紙附\n    卷可稽，故系爭強制執行程序案號雖行政報結，然實已併入\n    另案執行中，將來原告得領回之條件成就後，始得由被告領\n    取，自難謂被告之債權已實現或已執行而無效果，揆諸前揭\n    說明，系爭強制執行程序尚未終結，原告提起本件異議之訴\n    ，於法有據，被告此項辯解不足憑採。\n  (二)按強制執行法第14條第1 項規定之債務人異議之訴，須執行\n    名義成立後，有消滅或妨礙債權人請求之事由發生，始得提\n    起。所謂消滅債權人請求之事由，例如清償、提存、抵銷、\n    免除、混同、債權讓與、債務承擔、更改、消滅時效完成、\n    解除條件成就、契約解除或撤銷、另訂和解契約，或其他類\n    此之情形（最高法院98年台上字第1899號判決意旨參照）。\n    而按請求權，因15年間不行使而消滅；消滅時效因開始執行\n    行為或聲請強制執行而中斷；且時效中斷者，自中斷之事由\n    終止時，重行起算，民法第125 條前段、第129 條第2 項第\n    5 款及第137 條第1 項分別定有明文。又債務人無財產可供\n    強制執行，或雖有財產經強制執行後所得之數額仍不足清償\n    債務時，執行法院應命債權人於一個月內查報債務人財產，\n    債權人到期不為報告或查報無財產者，應發給憑證，交債權\n    人收執，載明俟發見有財產時，再予強制執行，債權人聲請\n    執行，而陳明債務人現無財產可供執行者，執行法院得逕行\n    發給憑證，強制執行法第27條定有明文。執行法院發予債權\n    憑證交債權人收執時，執行行為即為終結，因開始執行行為\n    而中斷之時效，應由此重行起算（最高法院89年度台上字第\n    2544號判決要旨參照）。查本件被告承受債權後，於88年9\n    月30日以系爭執行名義聲請聲請本院88年度執字第32156 號\n    強制執行，嗣併入本院87年度執字第32355 號另案執行，執\n    行無結果；復於93年間以系爭執行名義聲請本院93年度民執\n    字第5766號對原告強制執行，經本院於93年2 月9 日在債權\n    憑證上註記「執行無結果」後寄還被告；又於99年間以系爭\n    執行名義聲請本院99年度民司執字第160319號強制執行，經\n    本院於99年12月30日註記「執行無結果」後發還，此有債權\n    憑證及補發之債權憑證、93年2 月9 日執行審理單及送達回\n    證各1 份附卷可考（見本院93年度執字第5766號卷第4 頁、\n    100 年度司執字第11484 號卷第4 頁及本院100 年度訴字第\n    1843號卷第38、54至55頁），未有何撤回或被駁回聲請之情\n    形，自無民法第136 條第2 項時效視為不中斷規定之適用，\n    足見被告債權消滅時效分別於88年、93年間均有中斷進行，\n    迄今顯未罹於15年消滅時效，原告主張委無可採。\n  (三)綜上，原告主張系爭執行名義已罹於時效無可憑採，其提起\n    本件債務人異議之訴，請求撤銷本院100 年度司執字第1148\n    4 號強制執行程序，為無理由，應予駁回。\n五、據上論結，原告之訴為無理由，依民事訴訟法第78條，判決\n    如主文。",
    "reason": "一、原告主張：被告以本院83年度執字第12175 號強制執行事件\n    執行無結果而於民國84年2 月17日核發之債權憑證為執行名\n    義（下稱系爭執行名義），聲請對原告為強制執行，經本院\n    於民國100 年1 月20日以雄院高100 司執字第11484 號（下\n    稱系爭強制執行）執行命令，禁止原告取回本院98年度存字\n    第3692號提存事件為第三人彭美鳳提存之擔保金新台幣（下\n    同）709,042 元。惟按請求權因15年間不行使而消滅，時效\n    完成後，債務人得拒絕給付，系爭執行名義自84年2 月17日\n    算至99年2 月16日，已屆滿15年，期間被告雖曾聲請本院以\n    88年度執字第32156 號、93年度執字第5766號強制執行，然\n    均未提出債權憑證記載執行結果，可見被告已撤回或被駁回\n    聲請，依民法第136 條第2 項，時效視為不中斷，原告得以\n    罹於時效為由拒絕給付消費借款，被告前於99年12月間聲請\n    本院99年度民司執字第16 0319 號強制執行已罹於時效，茲\n    於100 年1 月14日聲請系爭強制執行，亦罹於時效；又上開\n    提存金債權另經97年度司執字第50341 號強制執行事件扣押\n    命令禁止取回，經本院民事執行處命與系爭強制執行合併執\n    行中，尚難謂執行程序終結，為此爰依強制執行法第14條第\n    1 項規定提起本訴等語。並聲明：系爭強制執行程序應予撤\n    銷。\n二、被告則以：(一)系爭強制執行程序之標的因與97年度司執字第\n    50341 號強制執行事件同一，經本院民事執行處於100 年3\n    月28日以雄院高100 司執字第11484 號通知合併執行而終結\n    ，原告不得提起異議之訴；(二)又被告於88年10月1 日及93年\n    2 月6 日均曾向本院聲請強制執行，並未撤回，嗣均因執行\n    無結果，經本院註記在債權憑證上後發還，已中斷時效進行\n    ，並未罹於時效等語置辯。並聲明如主文第1 項所示。\n三、兩造不爭執事項：\n  (一)第三人即原債權人高雄市第五信用合作社請求原告給付1 億\n    5,860 萬元及利息、違約金，獲本院81年度重訴字第48號確\n    定勝訴判決，消費借貸債權時效為15年，嗣以本院83年度執\n    字第12175 號對原告執行無結果，經本院於84年2 月17日核\n    發債權憑證即本件系爭執行名義；被告於86年9 月29日承受\n    債權。\n  (二)被告以系爭執行名義，分別於88年9 月30日聲請本院88年度\n    執字第32156 號，於93年2 月5 日聲請本院93年度民執字第\n    5766號，於99年間聲請本院99年度民司執字第160319號強制\n    執行（以上見本院93年度執字第5766號卷第4 頁債權憑證、\n    100 年度司執字第11484 號卷第4 頁補發之債權憑證之記載\n    ）。\n四、本件爭點：(一)系爭執行程序是否已經終結而不得提起異議之\n    訴？(二)被告於88年、93年間聲請強制執行後有無撤回？對原\n    告之債權，有無罹於時效？本院得心證之理由如下：\n  (一)按債務人異議之訴，係以排除執行名義之執行力為目的，應\n    限於強制執行程序終結前提起，始得為之，如強制執行程序\n    業已終結，已無阻止強制執行之實益，不得提起本訴，強制\n    執行法第14條第1 項定有明文。所謂強制執行程序終結，係\n    指執行名義之強制執行程序終結而言，執行名義之強制執行\n    程序，進行至執行名義所載債權全部達其目的時，始為終結\n    （司法院院字第2776號解釋參照）。查系爭強制執行程序中\n    ，本院民事執行處曾於100 年1 月31日核發移轉命令，准原\n    告於本院98年度存字第3692號提存事件，對提存所之709,04\n    2 元債權移轉予被告，惟經本院提存所函覆表示：受擔保利\n    益人彭美鳳有與質權人同一之權利，且該筆債權另經本院97\n    年度司執字第50341 號扣押在案，故無法准由被告領取等語\n    ，本院民事執行處乃於100 年3 月28日撤銷先前之移轉命令\n    ，並將系爭執行程序併入97年度司執字第50341 號強制執行\n    事件合併執行，俟將來原告得取回上開提存擔保金後，再由\n    被告及其他債權人領取等情，有本院民事執行處100 年1 月\n    31日雄院高100 司執逸字第11484 號執行命令、本院提存所\n    100 年3 月10日98存字第3692號函及本院民事執行處100 年\n    3 月28日雄院高100 司執逸字第11484 號執行通知各1 紙附\n    卷可稽，故系爭強制執行程序案號雖行政報結，然實已併入\n    另案執行中，將來原告得領回之條件成就後，始得由被告領\n    取，自難謂被告之債權已實現或已執行而無效果，揆諸前揭\n    說明，系爭強制執行程序尚未終結，原告提起本件異議之訴\n    ，於法有據，被告此項辯解不足憑採。\n  (二)按強制執行法第14條第1 項規定之債務人異議之訴，須執行\n    名義成立後，有消滅或妨礙債權人請求之事由發生，始得提\n    起。所謂消滅債權人請求之事由，例如清償、提存、抵銷、\n    免除、混同、債權讓與、債務承擔、更改、消滅時效完成、\n    解除條件成就、契約解除或撤銷、另訂和解契約，或其他類\n    此之情形（最高法院98年台上字第1899號判決意旨參照）。\n    而按請求權，因15年間不行使而消滅；消滅時效因開始執行\n    行為或聲請強制執行而中斷；且時效中斷者，自中斷之事由\n    終止時，重行起算，民法第125 條前段、第129 條第2 項第\n    5 款及第137 條第1 項分別定有明文。又債務人無財產可供\n    強制執行，或雖有財產經強制執行後所得之數額仍不足清償\n    債務時，執行法院應命債權人於一個月內查報債務人財產，\n    債權人到期不為報告或查報無財產者，應發給憑證，交債權\n    人收執，載明俟發見有財產時，再予強制執行，債權人聲請\n    執行，而陳明債務人現無財產可供執行者，執行法院得逕行\n    發給憑證，強制執行法第27條定有明文。執行法院發予債權\n    憑證交債權人收執時，執行行為即為終結，因開始執行行為\n    而中斷之時效，應由此重行起算（最高法院89年度台上字第\n    2544號判決要旨參照）。查本件被告承受債權後，於88年9\n    月30日以系爭執行名義聲請聲請本院88年度執字第32156 號\n    強制執行，嗣併入本院87年度執字第32355 號另案執行，執\n    行無結果；復於93年間以系爭執行名義聲請本院93年度民執\n    字第5766號對原告強制執行，經本院於93年2 月9 日在債權\n    憑證上註記「執行無結果」後寄還被告；又於99年間以系爭\n    執行名義聲請本院99年度民司執字第160319號強制執行，經\n    本院於99年12月30日註記「執行無結果」後發還，此有債權\n    憑證及補發之債權憑證、93年2 月9 日執行審理單及送達回\n    證各1 份附卷可考（見本院93年度執字第5766號卷第4 頁、\n    100 年度司執字第11484 號卷第4 頁及本院100 年度訴字第\n    1843號卷第38、54至55頁），未有何撤回或被駁回聲請之情\n    形，自無民法第136 條第2 項時效視為不中斷規定之適用，\n    足見被告債權消滅時效分別於88年、93年間均有中斷進行，\n    迄今顯未罹於15年消滅時效，原告主張委無可採。\n  (三)綜上，原告主張系爭執行名義已罹於時效無可憑採，其提起\n    本件債務人異議之訴，請求撤銷本院100 年度司執字第1148\n    4 號強制執行程序，為無理由，應予駁回。\n五、據上論結，原告之訴為無理由，依民事訴訟法第78條，判決\n    如主文。"
  },
  "search": "臺灣高雄地方法院民事判決100年度訴字第1843號原告莊國士被告板信商業銀行股份有限公司法定代理人劉炳輝訴訟代理人楊林澂律師上列當事人間債務人異議之訴事件，本院民國100年12月14日言詞辯論終結，判決如下：主文原告之訴駁回。訴訟費用由原告負擔。事實及理由一、原告主張：被告以本院83年度執字第12175號強制執行事件執行無結果而於民國84年2月17日核發之債權憑證為執行名義（下稱系爭執行名義），聲請對原告為強制執行，經本院於民國100年1月20日以雄院高100司執字第11484號（下稱系爭強制執行）執行命令，禁止原告取回本院98年度存字第3692號提存事件為第三人彭美鳳提存之擔保金新台幣（下同）709,042元。惟按請求權因15年間不行使而消滅，時效完成後，債務人得拒絕給付，系爭執行名義自84年2月17日算至99年2月16日，已屆滿15年，期間被告雖曾聲請本院以88年度執字第32156號、93年度執字第5766號強制執行，然均未提出債權憑證記載執行結果，可見被告已撤回或被駁回聲請，依民法第136條第2項，時效視為不中斷，原告得以罹於時效為由拒絕給付消費借款，被告前於99年12月間聲請本院99年度民司執字第160319號強制執行已罹於時效，茲於100年1月14日聲請系爭強制執行，亦罹於時效；又上開提存金債權另經97年度司執字第50341號強制執行事件扣押命令禁止取回，經本院民事執行處命與系爭強制執行合併執行中，尚難謂執行程序終結，為此爰依強制執行法第14條第1項規定提起本訴等語。並聲明：系爭強制執行程序應予撤銷。二、被告則以：(一)系爭強制執行程序之標的因與97年度司執字第50341號強制執行事件同一，經本院民事執行處於100年3月28日以雄院高100司執字第11484號通知合併執行而終結，原告不得提起異議之訴；(二)又被告於88年10月1日及93年2月6日均曾向本院聲請強制執行，並未撤回，嗣均因執行無結果，經本院註記在債權憑證上後發還，已中斷時效進行，並未罹於時效等語置辯。並聲明如主文第1項所示。三、兩造不爭執事項：(一)第三人即原債權人高雄市第五信用合作社請求原告給付1億5,860萬元及利息、違約金，獲本院81年度重訴字第48號確定勝訴判決，消費借貸債權時效為15年，嗣以本院83年度執字第12175號對原告執行無結果，經本院於84年2月17日核發債權憑證即本件系爭執行名義；被告於86年9月29日承受債權。(二)被告以系爭執行名義，分別於88年9月30日聲請本院88年度執字第32156號，於93年2月5日聲請本院93年度民執字第5766號，於99年間聲請本院99年度民司執字第160319號強制執行（以上見本院93年度執字第5766號卷第4頁債權憑證、100年度司執字第11484號卷第4頁補發之債權憑證之記載）。四、本件爭點：(一)系爭執行程序是否已經終結而不得提起異議之訴？(二)被告於88年、93年間聲請強制執行後有無撤回？對原告之債權，有無罹於時效？本院得心證之理由如下：(一)按債務人異議之訴，係以排除執行名義之執行力為目的，應限於強制執行程序終結前提起，始得為之，如強制執行程序業已終結，已無阻止強制執行之實益，不得提起本訴，強制執行法第14條第1項定有明文。所謂強制執行程序終結，係指執行名義之強制執行程序終結而言，執行名義之強制執行程序，進行至執行名義所載債權全部達其目的時，始為終結（司法院院字第2776號解釋參照）。查系爭強制執行程序中，本院民事執行處曾於100年1月31日核發移轉命令，准原告於本院98年度存字第3692號提存事件，對提存所之709,042元債權移轉予被告，惟經本院提存所函覆表示：受擔保利益人彭美鳳有與質權人同一之權利，且該筆債權另經本院97年度司執字第50341號扣押在案，故無法准由被告領取等語，本院民事執行處乃於100年3月28日撤銷先前之移轉命令，並將系爭執行程序併入97年度司執字第50341號強制執行事件合併執行，俟將來原告得取回上開提存擔保金後，再由被告及其他債權人領取等情，有本院民事執行處100年1月31日雄院高100司執逸字第11484號執行命令、本院提存所100年3月10日98存字第3692號函及本院民事執行處100年3月28日雄院高100司執逸字第11484號執行通知各1紙附卷可稽，故系爭強制執行程序案號雖行政報結，然實已併入另案執行中，將來原告得領回之條件成就後，始得由被告領取，自難謂被告之債權已實現或已執行而無效果，揆諸前揭說明，系爭強制執行程序尚未終結，原告提起本件異議之訴，於法有據，被告此項辯解不足憑採。(二)按強制執行法第14條第1項規定之債務人異議之訴，須執行名義成立後，有消滅或妨礙債權人請求之事由發生，始得提起。所謂消滅債權人請求之事由，例如清償、提存、抵銷、免除、混同、債權讓與、債務承擔、更改、消滅時效完成、解除條件成就、契約解除或撤銷、另訂和解契約，或其他類此之情形（最高法院98年台上字第1899號判決意旨參照）。而按請求權，因15年間不行使而消滅；消滅時效因開始執行行為或聲請強制執行而中斷；且時效中斷者，自中斷之事由終止時，重行起算，民法第125條前段、第129條第2項第5款及第137條第1項分別定有明文。又債務人無財產可供強制執行，或雖有財產經強制執行後所得之數額仍不足清償債務時，執行法院應命債權人於一個月內查報債務人財產，債權人到期不為報告或查報無財產者，應發給憑證，交債權人收執，載明俟發見有財產時，再予強制執行，債權人聲請執行，而陳明債務人現無財產可供執行者，執行法院得逕行發給憑證，強制執行法第27條定有明文。執行法院發予債權憑證交債權人收執時，執行行為即為終結，因開始執行行為而中斷之時效，應由此重行起算（最高法院89年度台上字第2544號判決要旨參照）。查本件被告承受債權後，於88年9月30日以系爭執行名義聲請聲請本院88年度執字第32156號強制執行，嗣併入本院87年度執字第32355號另案執行，執行無結果；復於93年間以系爭執行名義聲請本院93年度民執字第5766號對原告強制執行，經本院於93年2月9日在債權憑證上註記「執行無結果」後寄還被告；又於99年間以系爭執行名義聲請本院99年度民司執字第160319號強制執行，經本院於99年12月30日註記「執行無結果」後發還，此有債權憑證及補發之債權憑證、93年2月9日執行審理單及送達回證各1份附卷可考（見本院93年度執字第5766號卷第4頁、100年度司執字第11484號卷第4頁及本院100年度訴字第1843號卷第38、54至55頁），未有何撤回或被駁回聲請之情形，自無民法第136條第2項時效視為不中斷規定之適用，足見被告債權消滅時效分別於88年、93年間均有中斷進行，迄今顯未罹於15年消滅時效，原告主張委無可採。(三)綜上，原告主張系爭執行名義已罹於時效無可憑採，其提起本件債務人異議之訴，請求撤銷本院100年度司執字第11484號強制執行程序，為無理由，應予駁回。五、據上論結，原告之訴為無理由，依民事訴訟法第78條，判決如主文。中華民國100年12月28日民事第四庭法官李俊霖以上正本係照原本製成。如對本判決上訴，須於判決送達後20日內向本院提出上訴狀。如委任律師提起上訴者，應一併繳納上訴審裁判費。中華民國100年12月28日書記官邱上一",
  "characters": {
    "judges": [
      "李俊霖"
    ],
    "prosecutors": [

    ],
    "lawyers": [
      "楊林澂",
      "委任"
    ],
    "clerks": [

    ],
    "plaintiffs": [
      "莊國士"
    ],
    "defendants": [
      "板信商業銀行股份有限公司"
    ],
    "prosecutor_office": [

    ],
    "creditors": [

    ],
    "debtors": [

    ],
    "judicial_associate_officer": [

    ]
  },
  "adjudged_at": "2011-12-28",
  "created_at": "2016-02-13 11:34:45",
  "updated_at": "2016-02-13 11:34:45"
}