{
  "identify": "PCD-100-交簡-4039-20111228-1",
  "court": {
    "name": "臺灣新北地方法院",
    "code": "PCD"
  },
  "division": {
    "name": "刑事",
    "code": "M"
  },
  "year": 100,
  "word": "交簡",
  "number": "4039",
  "jcheck": "1",
  "reason": "過失傷害",
  "content": "臺灣板橋地方法院刑事簡易判決       100年度交簡字第4039號\n聲  請  人  臺灣板橋地方法院檢察署檢察官\n被      告  楊  園\n上列被告因過失傷害案件，經檢察官聲請以簡易判決處刑（一百\n年度調偵字第一八九四號），本院判決如下：\n    主  文\n楊園從事業務之人，因業務上之過失傷害人，處有期徒刑參月，\n如易科罰金，以新臺幣壹仟元折算壹日。\n    事實及理由\n一、本件犯罪事實及證據，除下列事項應予更正或補充外，其餘\n    均引用如附件檢察官聲請簡易判決處刑書之記載：\n（一）犯罪事實欄一第二行犯罪時間「一百年二月二十九日」之\n      記載，應更正為「一百年二月九日」。\n（二）犯罪事實欄一第四行之「按當時情形」後，應補充「天候\n      晴朗、日間自然光線，且該處為乾燥、無缺陷、無障礙物\n      之柏油路面」。\n（三）犯罪事實欄一第七至八行「擦撞停放在路邊之車牌號碼Ｆ\n      Ｔ－１６２５號自用小客車，致該車再擦撞站在車旁之陳\n      信良」之記載，應更正為「擦撞適時正站在車牌號碼ＦＴ\n      －１６２５號自用小客車後車尾之陳信良」。\n（四）犯罪事實欄一最末行應補充「楊園於肇事後留待現場，於\n      有偵查犯罪職權之機關或公務員僅知悉犯罪事實，尚不知\n      犯罪人為何人前，向前來處理之新北市政府警察局交通大\n      隊中和第一分隊警員黃錦誠坦承肇事。」\n（五）證據並所犯法條欄一證據（三）「現場及車損照片數張」\n      之記載，應補充為「現場及車損照片十六張」。\n（六）證據並所犯法條欄一證據，應補充「（六）臺北縣詠春拳\n      國術委員會保生堂國術管損傷接骨說明書、證號查詢汽車\n      駕駛人、新北市政府警察局中和一分局道路交通事故肇事\n      人自首情形記錄表各一份，及監視器翻拍照片六張」。\n二、查被告楊園於警詢中固供稱：伊當日係前往三重向友人借款\n    ，因所騎乘之機車故障，始臨時向友人借用計程車代步，並\n    非以駕駛計程車為業云云。惟其於偵查中已供承：平日偶爾\n    會開計程車，當日已開了五、六小時，在回程路上才撞到等\n    語，顯見其並非一時代步之用。又所謂「業務」，係指個人\n    基於社會地位繼續反覆執行之事務而言，被告事實上有駕駛\n    計程車營業之行為，自屬以駕駛為業務之人。被告楊園於執\n    行業務時駕車肇事致被害人陳信良受傷，核其所為，係犯刑\n    法第二百八十四條第二項前段之業務過失傷害罪。又被告於\n    本件事故發生時未領有汽車駕駛執照乙節，有證號查詢汽車\n    駕駛人列印畫面一紙在卷足憑，被告無照駕駛汽車，因而致\n    告訴人陳信良受傷，應依道路交通管理處罰條例第八十六條\n    第一項之規定，加重其刑。又本件車禍事故乃經報案人或勤\n    指中心轉來資料未報明肇事人資料，處理員警前往現場時，\n    被告在場並當場承認為肇事人，有新北市政府警察局中和一\n    分局道路交通事故肇事人自首情形記錄表一份在卷可稽，堪\n    認被告符合自首之要件，應依刑法第六十二條前段規定減輕\n    其刑，並依先加後減之。爰審酌被告以駕駛計程車為業，且\n    其無照駕車已有不該，又不知小心謹慎，疏未檢查車輛零件\n    狀況而肇事，使被害人陳信良受有上開傷害，行為應予非難\n    ，兼衡迄未能與告訴人達成和解，賠償告訴人之損失，及其\n    犯罪後坦承犯行之態度等一切情狀，量處如主文所示之刑，\n    並諭知易科罰金之折算標準，以資懲儆。\n三、依刑事訴訟法第四百四十九條第一項前段、第三項、第四百\n    五十四條第二項，道路交通管理處罰條例第八十六條第一項\n    ，刑法第二百八十四條第二項前段、第六十二條前段、第四\n    十一條第一項前段，刑法施行法第一條之一，逕以簡易判決\n    處刑如主文。\n四、如不服本判決，得自收受送達之日起十日內向本院提出上訴\n    狀，上訴於本院第二審合議庭（須附繕本）。\n中    華    民    國   100    年    12    月    28    日\n                  刑事第二十三庭  法  官  鄭水銓\n上列正本證明與原本無異。\n                                  書記官  蔡佩珊\n中    華    民    國   100    年    12    月    28    日\n附錄本罪論罪科刑法條全文：\n刑法第二百八十四條\n因過失傷害人者，處六月以下有期徒刑、拘役或五百元以下罰金\n；致重傷者，處一年以下有期徒刑、拘役或五百元以下罰金。\n從事業務之人，因業務上之過失傷害人者，處一年以下有期徒刑\n、拘役或一千元以下罰金；致重傷者，處三年以下有期徒刑、拘\n役或二千元以下罰金。\n附  件：\n臺灣板橋地方法院檢察署檢察官聲請簡易判決處刑書\n                                   100年度調偵字第1894號\n    被      告  楊園    男  59歲（民國○○年○月○日生）\n                        住新北市○○區○○路10巷1弄11號\n                        國民身分證統一編號：Ｚ000000000號\n上列被告因業務過失傷害案件，業經偵查終結，認為宜聲請以簡\n易判決處刑，茲將犯罪事實及證據並所犯法條分敘如下：\n        犯罪事實\n一、楊園明知無駕駛執照不得駕駛車輛，仍駕駛計程車為業，為\n    從事業務之人，其於民國100年2月29日8時16分許，駕駛車\n    牌號碼607-B2號營業用小客車營業時，本應注意行車前應詳\n    細檢查車輛各項零件之狀況，且依當時情形並無不能注意之\n    情形，竟疏未注意，貿然駕駛上開車輛沿新北市○○區○○\n    路往福祥路方向行駛，行至永和路70號前，因方向盤卡住致\n    車輛失控，擦撞停放在路邊之車牌號碼FT-1625號自用小客\n    車，致該車再擦撞站在車旁之陳信良，使陳信良因而受右側\n    下肢挫擦傷、左手掌及手指開放性傷口、膝蓋、小腿、腳腕\n    嚴重挫傷之傷害。\n二、案經陳信良訴由新北市政府警察局中和第一分局移送偵辦。\n        證據並所犯法條\n一、證據：\n（一）被告楊園之自白。\n（二）告訴人陳信良之指訴。\n（三）現場及車損照片數張。\n（四）告訴人之行政院衛生署雙和醫院診斷證明書1紙。\n（五）道路交通事故現場圖、道路交通事故調查報告表(一)(二)各1\n      份等在卷可資佐證，被告犯嫌已堪認定。\n二、核被告楊園所為，係犯刑法第284條第2項前段過失傷害罪嫌\n    。又被告無駕駛執照駕駛車輛致人受傷，請依道路交通管理\n    處罰條例第86條第1項規定加重其刑至二分之一。\n三、依刑事訴訟法第451條第1項聲請逕以簡易判決處刑。\n    此    致\n臺灣板橋地方法院\n中    華    民    國   100    年    8     月    8     日\n                              檢察官  蔡景聖\n本件正本證明與原本無異\n中    華    民    國   100    年    8     月    17    日\n                              書記官  余秋桂",
  "structure": {
    "main": "楊園從事業務之人，因業務上之過失傷害人，處有期徒刑參月，\n如易科罰金，以新臺幣壹仟元折算壹日。",
    "fact": "一、本件犯罪事實及證據，除下列事項應予更正或補充外，其餘\n    均引用如附件檢察官聲請簡易判決處刑書之記載：\n（一）犯罪事實欄一第二行犯罪時間「一百年二月二十九日」之\n      記載，應更正為「一百年二月九日」。\n（二）犯罪事實欄一第四行之「按當時情形」後，應補充「天候\n      晴朗、日間自然光線，且該處為乾燥、無缺陷、無障礙物\n      之柏油路面」。\n（三）犯罪事實欄一第七至八行「擦撞停放在路邊之車牌號碼Ｆ\n      Ｔ－１６２５號自用小客車，致該車再擦撞站在車旁之陳\n      信良」之記載，應更正為「擦撞適時正站在車牌號碼ＦＴ\n      －１６２５號自用小客車後車尾之陳信良」。\n（四）犯罪事實欄一最末行應補充「楊園於肇事後留待現場，於\n      有偵查犯罪職權之機關或公務員僅知悉犯罪事實，尚不知\n      犯罪人為何人前，向前來處理之新北市政府警察局交通大\n      隊中和第一分隊警員黃錦誠坦承肇事。」\n（五）證據並所犯法條欄一證據（三）「現場及車損照片數張」\n      之記載，應補充為「現場及車損照片十六張」。\n（六）證據並所犯法條欄一證據，應補充「（六）臺北縣詠春拳\n      國術委員會保生堂國術管損傷接骨說明書、證號查詢汽車\n      駕駛人、新北市政府警察局中和一分局道路交通事故肇事\n      人自首情形記錄表各一份，及監視器翻拍照片六張」。\n二、查被告楊園於警詢中固供稱：伊當日係前往三重向友人借款\n    ，因所騎乘之機車故障，始臨時向友人借用計程車代步，並\n    非以駕駛計程車為業云云。惟其於偵查中已供承：平日偶爾\n    會開計程車，當日已開了五、六小時，在回程路上才撞到等\n    語，顯見其並非一時代步之用。又所謂「業務」，係指個人\n    基於社會地位繼續反覆執行之事務而言，被告事實上有駕駛\n    計程車營業之行為，自屬以駕駛為業務之人。被告楊園於執\n    行業務時駕車肇事致被害人陳信良受傷，核其所為，係犯刑\n    法第二百八十四條第二項前段之業務過失傷害罪。又被告於\n    本件事故發生時未領有汽車駕駛執照乙節，有證號查詢汽車\n    駕駛人列印畫面一紙在卷足憑，被告無照駕駛汽車，因而致\n    告訴人陳信良受傷，應依道路交通管理處罰條例第八十六條\n    第一項之規定，加重其刑。又本件車禍事故乃經報案人或勤\n    指中心轉來資料未報明肇事人資料，處理員警前往現場時，\n    被告在場並當場承認為肇事人，有新北市政府警察局中和一\n    分局道路交通事故肇事人自首情形記錄表一份在卷可稽，堪\n    認被告符合自首之要件，應依刑法第六十二條前段規定減輕\n    其刑，並依先加後減之。爰審酌被告以駕駛計程車為業，且\n    其無照駕車已有不該，又不知小心謹慎，疏未檢查車輛零件\n    狀況而肇事，使被害人陳信良受有上開傷害，行為應予非難\n    ，兼衡迄未能與告訴人達成和解，賠償告訴人之損失，及其\n    犯罪後坦承犯行之態度等一切情狀，量處如主文所示之刑，\n    並諭知易科罰金之折算標準，以資懲儆。\n三、依刑事訴訟法第四百四十九條第一項前段、第三項、第四百\n    五十四條第二項，道路交通管理處罰條例第八十六條第一項\n    ，刑法第二百八十四條第二項前段、第六十二條前段、第四\n    十一條第一項前段，刑法施行法第一條之一，逕以簡易判決\n    處刑如主文。\n四、如不服本判決，得自收受送達之日起十日內向本院提出上訴\n    狀，上訴於本院第二審合議庭（須附繕本）。",
    "reason": "一、本件犯罪事實及證據，除下列事項應予更正或補充外，其餘\n    均引用如附件檢察官聲請簡易判決處刑書之記載：\n（一）犯罪事實欄一第二行犯罪時間「一百年二月二十九日」之\n      記載，應更正為「一百年二月九日」。\n（二）犯罪事實欄一第四行之「按當時情形」後，應補充「天候\n      晴朗、日間自然光線，且該處為乾燥、無缺陷、無障礙物\n      之柏油路面」。\n（三）犯罪事實欄一第七至八行「擦撞停放在路邊之車牌號碼Ｆ\n      Ｔ－１６２５號自用小客車，致該車再擦撞站在車旁之陳\n      信良」之記載，應更正為「擦撞適時正站在車牌號碼ＦＴ\n      －１６２５號自用小客車後車尾之陳信良」。\n（四）犯罪事實欄一最末行應補充「楊園於肇事後留待現場，於\n      有偵查犯罪職權之機關或公務員僅知悉犯罪事實，尚不知\n      犯罪人為何人前，向前來處理之新北市政府警察局交通大\n      隊中和第一分隊警員黃錦誠坦承肇事。」\n（五）證據並所犯法條欄一證據（三）「現場及車損照片數張」\n      之記載，應補充為「現場及車損照片十六張」。\n（六）證據並所犯法條欄一證據，應補充「（六）臺北縣詠春拳\n      國術委員會保生堂國術管損傷接骨說明書、證號查詢汽車\n      駕駛人、新北市政府警察局中和一分局道路交通事故肇事\n      人自首情形記錄表各一份，及監視器翻拍照片六張」。\n二、查被告楊園於警詢中固供稱：伊當日係前往三重向友人借款\n    ，因所騎乘之機車故障，始臨時向友人借用計程車代步，並\n    非以駕駛計程車為業云云。惟其於偵查中已供承：平日偶爾\n    會開計程車，當日已開了五、六小時，在回程路上才撞到等\n    語，顯見其並非一時代步之用。又所謂「業務」，係指個人\n    基於社會地位繼續反覆執行之事務而言，被告事實上有駕駛\n    計程車營業之行為，自屬以駕駛為業務之人。被告楊園於執\n    行業務時駕車肇事致被害人陳信良受傷，核其所為，係犯刑\n    法第二百八十四條第二項前段之業務過失傷害罪。又被告於\n    本件事故發生時未領有汽車駕駛執照乙節，有證號查詢汽車\n    駕駛人列印畫面一紙在卷足憑，被告無照駕駛汽車，因而致\n    告訴人陳信良受傷，應依道路交通管理處罰條例第八十六條\n    第一項之規定，加重其刑。又本件車禍事故乃經報案人或勤\n    指中心轉來資料未報明肇事人資料，處理員警前往現場時，\n    被告在場並當場承認為肇事人，有新北市政府警察局中和一\n    分局道路交通事故肇事人自首情形記錄表一份在卷可稽，堪\n    認被告符合自首之要件，應依刑法第六十二條前段規定減輕\n    其刑，並依先加後減之。爰審酌被告以駕駛計程車為業，且\n    其無照駕車已有不該，又不知小心謹慎，疏未檢查車輛零件\n    狀況而肇事，使被害人陳信良受有上開傷害，行為應予非難\n    ，兼衡迄未能與告訴人達成和解，賠償告訴人之損失，及其\n    犯罪後坦承犯行之態度等一切情狀，量處如主文所示之刑，\n    並諭知易科罰金之折算標準，以資懲儆。\n三、依刑事訴訟法第四百四十九條第一項前段、第三項、第四百\n    五十四條第二項，道路交通管理處罰條例第八十六條第一項\n    ，刑法第二百八十四條第二項前段、第六十二條前段、第四\n    十一條第一項前段，刑法施行法第一條之一，逕以簡易判決\n    處刑如主文。\n四、如不服本判決，得自收受送達之日起十日內向本院提出上訴\n    狀，上訴於本院第二審合議庭（須附繕本）。"
  },
  "search": "臺灣板橋地方法院刑事簡易判決100年度交簡字第4039號聲請人臺灣板橋地方法院檢察署檢察官被告楊園上列被告因過失傷害案件，經檢察官聲請以簡易判決處刑（一百年度調偵字第一八九四號），本院判決如下：主文楊園從事業務之人，因業務上之過失傷害人，處有期徒刑參月，如易科罰金，以新臺幣壹仟元折算壹日。事實及理由一、本件犯罪事實及證據，除下列事項應予更正或補充外，其餘均引用如附件檢察官聲請簡易判決處刑書之記載：（一）犯罪事實欄一第二行犯罪時間「一百年二月二十九日」之記載，應更正為「一百年二月九日」。（二）犯罪事實欄一第四行之「按當時情形」後，應補充「天候晴朗、日間自然光線，且該處為乾燥、無缺陷、無障礙物之柏油路面」。（三）犯罪事實欄一第七至八行「擦撞停放在路邊之車牌號碼ＦＴ－１６２５號自用小客車，致該車再擦撞站在車旁之陳信良」之記載，應更正為「擦撞適時正站在車牌號碼ＦＴ－１６２５號自用小客車後車尾之陳信良」。（四）犯罪事實欄一最末行應補充「楊園於肇事後留待現場，於有偵查犯罪職權之機關或公務員僅知悉犯罪事實，尚不知犯罪人為何人前，向前來處理之新北市政府警察局交通大隊中和第一分隊警員黃錦誠坦承肇事。」（五）證據並所犯法條欄一證據（三）「現場及車損照片數張」之記載，應補充為「現場及車損照片十六張」。（六）證據並所犯法條欄一證據，應補充「（六）臺北縣詠春拳國術委員會保生堂國術管損傷接骨說明書、證號查詢汽車駕駛人、新北市政府警察局中和一分局道路交通事故肇事人自首情形記錄表各一份，及監視器翻拍照片六張」。二、查被告楊園於警詢中固供稱：伊當日係前往三重向友人借款，因所騎乘之機車故障，始臨時向友人借用計程車代步，並非以駕駛計程車為業云云。惟其於偵查中已供承：平日偶爾會開計程車，當日已開了五、六小時，在回程路上才撞到等語，顯見其並非一時代步之用。又所謂「業務」，係指個人基於社會地位繼續反覆執行之事務而言，被告事實上有駕駛計程車營業之行為，自屬以駕駛為業務之人。被告楊園於執行業務時駕車肇事致被害人陳信良受傷，核其所為，係犯刑法第二百八十四條第二項前段之業務過失傷害罪。又被告於本件事故發生時未領有汽車駕駛執照乙節，有證號查詢汽車駕駛人列印畫面一紙在卷足憑，被告無照駕駛汽車，因而致告訴人陳信良受傷，應依道路交通管理處罰條例第八十六條第一項之規定，加重其刑。又本件車禍事故乃經報案人或勤指中心轉來資料未報明肇事人資料，處理員警前往現場時，被告在場並當場承認為肇事人，有新北市政府警察局中和一分局道路交通事故肇事人自首情形記錄表一份在卷可稽，堪認被告符合自首之要件，應依刑法第六十二條前段規定減輕其刑，並依先加後減之。爰審酌被告以駕駛計程車為業，且其無照駕車已有不該，又不知小心謹慎，疏未檢查車輛零件狀況而肇事，使被害人陳信良受有上開傷害，行為應予非難，兼衡迄未能與告訴人達成和解，賠償告訴人之損失，及其犯罪後坦承犯行之態度等一切情狀，量處如主文所示之刑，並諭知易科罰金之折算標準，以資懲儆。三、依刑事訴訟法第四百四十九條第一項前段、第三項、第四百五十四條第二項，道路交通管理處罰條例第八十六條第一項，刑法第二百八十四條第二項前段、第六十二條前段、第四十一條第一項前段，刑法施行法第一條之一，逕以簡易判決處刑如主文。四、如不服本判決，得自收受送達之日起十日內向本院提出上訴狀，上訴於本院第二審合議庭（須附繕本）。中華民國100年12月28日刑事第二十三庭法官鄭水銓上列正本證明與原本無異。書記官蔡佩珊中華民國100年12月28日附錄本罪論罪科刑法條全文：刑法第二百八十四條因過失傷害人者，處六月以下有期徒刑、拘役或五百元以下罰金；致重傷者，處一年以下有期徒刑、拘役或五百元以下罰金。從事業務之人，因業務上之過失傷害人者，處一年以下有期徒刑、拘役或一千元以下罰金；致重傷者，處三年以下有期徒刑、拘役或二千元以下罰金。附件：臺灣板橋地方法院檢察署檢察官聲請簡易判決處刑書100年度調偵字第1894號被告楊園男59歲（民國○○年○月○日生）住新北市○○區○○路10巷1弄11號國民身分證統一編號：Ｚ000000000號上列被告因業務過失傷害案件，業經偵查終結，認為宜聲請以簡易判決處刑，茲將犯罪事實及證據並所犯法條分敘如下：犯罪事實一、楊園明知無駕駛執照不得駕駛車輛，仍駕駛計程車為業，為從事業務之人，其於民國100年2月29日8時16分許，駕駛車牌號碼607-B2號營業用小客車營業時，本應注意行車前應詳細檢查車輛各項零件之狀況，且依當時情形並無不能注意之情形，竟疏未注意，貿然駕駛上開車輛沿新北市○○區○○路往福祥路方向行駛，行至永和路70號前，因方向盤卡住致車輛失控，擦撞停放在路邊之車牌號碼FT-1625號自用小客車，致該車再擦撞站在車旁之陳信良，使陳信良因而受右側下肢挫擦傷、左手掌及手指開放性傷口、膝蓋、小腿、腳腕嚴重挫傷之傷害。二、案經陳信良訴由新北市政府警察局中和第一分局移送偵辦。證據並所犯法條一、證據：（一）被告楊園之自白。（二）告訴人陳信良之指訴。（三）現場及車損照片數張。（四）告訴人之行政院衛生署雙和醫院診斷證明書1紙。（五）道路交通事故現場圖、道路交通事故調查報告表(一)(二)各1份等在卷可資佐證，被告犯嫌已堪認定。二、核被告楊園所為，係犯刑法第284條第2項前段過失傷害罪嫌。又被告無駕駛執照駕駛車輛致人受傷，請依道路交通管理處罰條例第86條第1項規定加重其刑至二分之一。三、依刑事訴訟法第451條第1項聲請逕以簡易判決處刑。此致臺灣板橋地方法院中華民國100年8月8日檢察官蔡景聖本件正本證明與原本無異中華民國100年8月17日書記官余秋桂",
  "characters": {
    "judges": [
      "鄭水銓"
    ],
    "prosecutors": [

    ],
    "lawyers": [

    ],
    "clerks": [
      "蔡佩珊"
    ],
    "plaintiffs": [

    ],
    "defendants": [
      "楊  園",
      "楊園    男  59歲（民國○○年○月○日生）"
    ],
    "prosecutor_office": [
      "臺灣板橋地方法院檢察署檢察官"
    ],
    "creditors": [

    ],
    "debtors": [

    ],
    "judicial_associate_officer": [

    ]
  },
  "adjudged_at": "2011-12-28",
  "created_at": "2016-02-13 11:33:20",
  "updated_at": "2016-02-13 11:33:20"
}