{
  "identify": "PTD-94-簡-1465-20051125-1",
  "court": {
    "name": "臺灣屏東地方法院",
    "code": "PTD"
  },
  "division": {
    "name": "刑事",
    "code": "M"
  },
  "year": 94,
  "word": "簡",
  "number": "1465",
  "jcheck": "1",
  "reason": "竊盜",
  "content": "臺灣屏東地方法院刑事簡易判決          94年度簡字第1465號\n聲  請  人  臺灣屏東地方法院檢察署檢察官\n被      告  甲○○\n                      號\n上列被告因竊盜案件，經檢察官聲請以簡易判決處刑（94年度速\n偵字第134 號），本院判決如下：\n    主  文\n甲○○竊盜，處罰金伍佰元，如易服勞役，以佰元折算壹日。\n緩刑貳年。扣案之漁網壹張、紅色塑膠桶壹個均沒收。\n    理  由\n一、本院認定被告之犯罪事實、證據及應適用之法條，與檢察官\n    聲請簡易判決處刑書之記載相同，茲引用之（如附件）。\n二、爰審酌被告之素行、犯罪動機、手段，犯罪所得、所生危害\n    ，及犯後坦承犯行，態度尚佳，並返還所竊物品等一切情狀\n    ，量處如所示之刑，並諭知易科罰金之折算標準。又被告前\n    未曾受有期徒刑以上刑之宣告，有臺灣高等法院被告前案紀\n    錄表可徵，因一時失慮致罹刑典，信其經此論罪科刑之教訓\n    ，應知警惕而無再犯之虞，本院認前開對其宣告之刑以暫不\n    執行為適當，併予宣告緩刑2 年，用啟自新。\n三、依刑事訴訟法第449 條第1 項前段、第3 項、第454 條第2\n    項，刑法第320 條第1 項、第42 條第2 項前段、第74條第1\n    款、第38條第1 項第2 款，罰金罰鍰提高標準條例第1 條前\n    段、第2 條，逕以簡易判決判處如主文所示之刑。\n中    華    民    國    94    年    11    月    25    日\n                  刑事第三庭    法  官  柯雅惠\n以上正本證明與原本無異。\n如不服本判決，得於判決書送達之翌日起十日內，以書狀敘述理\n由，向本庭提出上訴。\n中    華    民    國    94    年    11    月    25    日\n                                書記官  葉祝君\n附錄本判決論罪科刑法條全文\n刑法第320條第1項：\n意圖為自己或第三人不法之所有，而竊取他人之動產者，為竊盜\n罪，處五年以下有期徒刑、拘役或五百元以下罰金。\n",
  "structure": {
    "main": "甲○○竊盜，處罰金伍佰元，如易服勞役，以佰元折算壹日。\n緩刑貳年。扣案之漁網壹張、紅色塑膠桶壹個均沒收。",
    "reason": "一、本院認定被告之犯罪事實、證據及應適用之法條，與檢察官\n    聲請簡易判決處刑書之記載相同，茲引用之（如附件）。\n二、爰審酌被告之素行、犯罪動機、手段，犯罪所得、所生危害\n    ，及犯後坦承犯行，態度尚佳，並返還所竊物品等一切情狀\n    ，量處如所示之刑，並諭知易科罰金之折算標準。又被告前\n    未曾受有期徒刑以上刑之宣告，有臺灣高等法院被告前案紀\n    錄表可徵，因一時失慮致罹刑典，信其經此論罪科刑之教訓\n    ，應知警惕而無再犯之虞，本院認前開對其宣告之刑以暫不\n    執行為適當，併予宣告緩刑2 年，用啟自新。\n三、依刑事訴訟法第449 條第1 項前段、第3 項、第454 條第2\n    項，刑法第320 條第1 項、第42 條第2 項前段、第74條第1\n    款、第38條第1 項第2 款，罰金罰鍰提高標準條例第1 條前\n    段、第2 條，逕以簡易判決判處如主文所示之刑。"
  },
  "search": "臺灣屏東地方法院刑事簡易判決94年度簡字第1465號聲請人臺灣屏東地方法院檢察署檢察官被告甲○○號上列被告因竊盜案件，經檢察官聲請以簡易判決處刑（94年度速偵字第134號），本院判決如下：主文甲○○竊盜，處罰金伍佰元，如易服勞役，以佰元折算壹日。緩刑貳年。扣案之漁網壹張、紅色塑膠桶壹個均沒收。理由一、本院認定被告之犯罪事實、證據及應適用之法條，與檢察官聲請簡易判決處刑書之記載相同，茲引用之（如附件）。二、爰審酌被告之素行、犯罪動機、手段，犯罪所得、所生危害，及犯後坦承犯行，態度尚佳，並返還所竊物品等一切情狀，量處如所示之刑，並諭知易科罰金之折算標準。又被告前未曾受有期徒刑以上刑之宣告，有臺灣高等法院被告前案紀錄表可徵，因一時失慮致罹刑典，信其經此論罪科刑之教訓，應知警惕而無再犯之虞，本院認前開對其宣告之刑以暫不執行為適當，併予宣告緩刑2年，用啟自新。三、依刑事訴訟法第449條第1項前段、第3項、第454條第2項，刑法第320條第1項、第42條第2項前段、第74條第1款、第38條第1項第2款，罰金罰鍰提高標準條例第1條前段、第2條，逕以簡易判決判處如主文所示之刑。中華民國94年11月25日刑事第三庭法官柯雅惠以上正本證明與原本無異。如不服本判決，得於判決書送達之翌日起十日內，以書狀敘述理由，向本庭提出上訴。中華民國94年11月25日書記官葉祝君附錄本判決論罪科刑法條全文刑法第320條第1項：意圖為自己或第三人不法之所有，而竊取他人之動產者，為竊盜罪，處五年以下有期徒刑、拘役或五百元以下罰金。",
  "characters": {
    "judges": [
      "柯雅惠"
    ],
    "prosecutors": [

    ],
    "lawyers": [

    ],
    "clerks": [
      "葉祝君"
    ],
    "plaintiffs": [

    ],
    "defendants": [
      "甲○○"
    ],
    "prosecutor_office": [
      "臺灣屏東地方法院檢察署檢察官"
    ],
    "creditors": [

    ],
    "debtors": [

    ],
    "judicial_associate_officer": [

    ]
  },
  "adjudged_at": "2005-11-25",
  "created_at": "2016-02-07 00:11:28",
  "updated_at": "2016-02-07 00:11:28"
}