{
  "identify": "TPD-94-簡-460-20050321-1",
  "court": {
    "name": "臺灣臺北地方法院",
    "code": "TPD"
  },
  "division": {
    "name": "刑事",
    "code": "M"
  },
  "year": 94,
  "word": "簡",
  "number": "460",
  "jcheck": "1",
  "reason": "竊盜",
  "content": "臺灣臺北地方法院刑事簡易判決           94年度簡字第460號\n聲 請 人  臺灣臺北地方法院檢察署檢察官\n被    告  甲○○\n          乙○○\n上列被告等因竊盜案件，經檢察官聲請以簡易判決處刑（九十四\n年度偵字第二五二六號），本院判決如下：\n    主  文\n甲○○、乙○○共同竊盜，各處拘役貳拾日，如易科罰金，均以\n佰元折算壹日，均緩刑貳年。\n    事實及理由\n一、本件犯罪事實及證據均引用檢察官聲請簡易判決處刑書（如\n    附件）之記載。\n二、被告甲○○、乙○○均未曾受有期徒刑以上刑之宣告，此有\n    臺灣高等法院被告全國前案紀錄表在卷可稽，其係因所有之\n    安全帽遭竊，為騎乘機車，始順手竊取他人所有之安全帽，\n    為圖一時便利，而犯本件罪行，經此次起訴審判後，當能知\n    所警惕，而無再犯之虞，本院因認所宣告之刑，以暫不執行\n    為適當，爰併宣告緩刑二年，以啟自新。\n三、依刑事訴訟法第四百四十九條第一項、第三項、第四百五十\n    四條第二項，刑法第二十八條、第五十六條、第三百二十條\n    第一項、第四十一條第一項、第七十四條第一款，罰金罰鍰\n    提高標準條例第一條前段、第二條，逕以簡易判決處刑如主\n    文，並諭知易科罰金之折算標準。\n四、如不服本判決，應於判決送達後十日內，向本院提出上訴狀。\n中  華  民   國  九十四     年    三    月   二十一   日\n               臺灣臺北地方法院刑事第十四庭\n                         法  官  王綽光\n右正本證明與原本無異。\n                         書記官  蔡梅蓮\n中  華  民   國  九十四     年    三    月   二十八   日\n附錄論罪科刑法條:\n中華民國刑法第320條\n (普通竊盜罪、竊佔罪)\n意圖為自己或第 3 人不法之所有，而竊取他人之動產者，為竊盜\n罪，處五\n年以下有期徒刑、拘役或五百元以下罰金。\n意圖為自己或第 3 人不法之利益，而竊佔他人之不動產者，依前\n項之規定\n處斷。\n前二項之未遂犯罰之。\n",
  "structure": {
    "main": "甲○○、乙○○共同竊盜，各處拘役貳拾日，如易科罰金，均以\n佰元折算壹日，均緩刑貳年。",
    "fact": "一、本件犯罪事實及證據均引用檢察官聲請簡易判決處刑書（如\n    附件）之記載。\n二、被告甲○○、乙○○均未曾受有期徒刑以上刑之宣告，此有\n    臺灣高等法院被告全國前案紀錄表在卷可稽，其係因所有之\n    安全帽遭竊，為騎乘機車，始順手竊取他人所有之安全帽，\n    為圖一時便利，而犯本件罪行，經此次起訴審判後，當能知\n    所警惕，而無再犯之虞，本院因認所宣告之刑，以暫不執行\n    為適當，爰併宣告緩刑二年，以啟自新。\n三、依刑事訴訟法第四百四十九條第一項、第三項、第四百五十\n    四條第二項，刑法第二十八條、第五十六條、第三百二十條\n    第一項、第四十一條第一項、第七十四條第一款，罰金罰鍰\n    提高標準條例第一條前段、第二條，逕以簡易判決處刑如主\n    文，並諭知易科罰金之折算標準。\n四、如不服本判決，應於判決送達後十日內，向本院提出上訴狀。",
    "reason": "一、本件犯罪事實及證據均引用檢察官聲請簡易判決處刑書（如\n    附件）之記載。\n二、被告甲○○、乙○○均未曾受有期徒刑以上刑之宣告，此有\n    臺灣高等法院被告全國前案紀錄表在卷可稽，其係因所有之\n    安全帽遭竊，為騎乘機車，始順手竊取他人所有之安全帽，\n    為圖一時便利，而犯本件罪行，經此次起訴審判後，當能知\n    所警惕，而無再犯之虞，本院因認所宣告之刑，以暫不執行\n    為適當，爰併宣告緩刑二年，以啟自新。\n三、依刑事訴訟法第四百四十九條第一項、第三項、第四百五十\n    四條第二項，刑法第二十八條、第五十六條、第三百二十條\n    第一項、第四十一條第一項、第七十四條第一款，罰金罰鍰\n    提高標準條例第一條前段、第二條，逕以簡易判決處刑如主\n    文，並諭知易科罰金之折算標準。\n四、如不服本判決，應於判決送達後十日內，向本院提出上訴狀。"
  },
  "search": "臺灣臺北地方法院刑事簡易判決94年度簡字第460號聲請人臺灣臺北地方法院檢察署檢察官被告甲○○乙○○上列被告等因竊盜案件，經檢察官聲請以簡易判決處刑（九十四年度偵字第二五二六號），本院判決如下：主文甲○○、乙○○共同竊盜，各處拘役貳拾日，如易科罰金，均以佰元折算壹日，均緩刑貳年。事實及理由一、本件犯罪事實及證據均引用檢察官聲請簡易判決處刑書（如附件）之記載。二、被告甲○○、乙○○均未曾受有期徒刑以上刑之宣告，此有臺灣高等法院被告全國前案紀錄表在卷可稽，其係因所有之安全帽遭竊，為騎乘機車，始順手竊取他人所有之安全帽，為圖一時便利，而犯本件罪行，經此次起訴審判後，當能知所警惕，而無再犯之虞，本院因認所宣告之刑，以暫不執行為適當，爰併宣告緩刑二年，以啟自新。三、依刑事訴訟法第四百四十九條第一項、第三項、第四百五十四條第二項，刑法第二十八條、第五十六條、第三百二十條第一項、第四十一條第一項、第七十四條第一款，罰金罰鍰提高標準條例第一條前段、第二條，逕以簡易判決處刑如主文，並諭知易科罰金之折算標準。四、如不服本判決，應於判決送達後十日內，向本院提出上訴狀。中華民國九十四年三月二十一日臺灣臺北地方法院刑事第十四庭法官王綽光右正本證明與原本無異。書記官蔡梅蓮中華民國九十四年三月二十八日附錄論罪科刑法條:中華民國刑法第320條(普通竊盜罪、竊佔罪)意圖為自己或第3人不法之所有，而竊取他人之動產者，為竊盜罪，處五年以下有期徒刑、拘役或五百元以下罰金。意圖為自己或第3人不法之利益，而竊佔他人之不動產者，依前項之規定處斷。前二項之未遂犯罰之。",
  "characters": {
    "judges": [
      "王綽光"
    ],
    "prosecutors": [

    ],
    "lawyers": [

    ],
    "clerks": [
      "蔡梅蓮"
    ],
    "plaintiffs": [

    ],
    "defendants": [
      "甲○○"
    ],
    "prosecutor_office": [
      "臺灣臺北地方法院檢察署檢察官"
    ],
    "creditors": [

    ],
    "debtors": [

    ],
    "judicial_associate_officer": [

    ]
  },
  "adjudged_at": "2005-03-21",
  "created_at": "2016-02-07 07:29:10",
  "updated_at": "2016-02-07 07:29:10"
}