{
  "identify": "TPD-93-簡-3046-20041223-1",
  "court": {
    "name": "臺灣臺北地方法院",
    "code": "TPD"
  },
  "division": {
    "name": "刑事",
    "code": "M"
  },
  "year": 93,
  "word": "簡",
  "number": "3046",
  "jcheck": "1",
  "reason": "違反替代役實施條例",
  "content": "臺灣臺北地方法院刑事簡易判決                    九十三年度簡字第三０四六號\n      聲  請  人  臺灣臺北地方法院檢察署檢察官\n      被      告  甲○○\n右列被告因違反替代役實施條例案件，經檢察官聲請以簡易判決處刑（九十三年度偵\n緝字第一五八九號），本院判決如左：\n    主  文\n甲○○替代役役男無故不就指定之替代役職役，處拘役拾日，如易科罰金，以佰元\n折算壹日。\n    事實及理由\n一、本件犯罪事實及證據均引用檢察官聲請簡易判決處刑書之記載（如附件）。惟證\n    據部分補充記載如下：依卷附台灣台北地方法院法務部在監\n    甲○○並無任何在監\n二、核被告所為，係犯替代役實施條例第五十二條之無故不就指定之替代役職役罪。\n    爰審酌被告並無任何前科紀錄，素行良好，此有台灣高等法院被告全國前案紀錄\n    表一份在卷可稽，其未依規定辦理請假手續，即無故不入營服役，造成服役單位\n    管理上之困擾，且有違職役所付與之社會責任，惟情節尚屬輕微，對於國防所生\n    之危害非鉅及事後坦承犯行，態度良好等一切情狀，量處如主文所示之刑，並諭\n    知如易科罰金之折算標準。\n三、結論：依刑事訴訟法第四百四十九條第一項前段、第三項、第四百五十四條第二\n    項，替代役實施條例第五十二條，刑法第十一條前段、第四十一條第一項前段，\n    罰金罰鍰提高標準條例第二條，逕以簡易判決處如主文所示之刑。\n中      華      民      國    九十三    年     十二     月    二十三    日\n                            臺灣臺北地方法院刑事第十三庭\n                                法  官  鍾素鳳\n右正本證明與原本無異。\n如不服本件判決，得自收受送達之日起十日內，向本院提起上訴。\n                                書記官  朱良燦\n中      華      民      國    九十三    年     十二     月    二十三    日\n附錄本判決論罪之法條：\n替代役實施條例第五十二條\n    替代役役男無故不就指定之替代役職役、擅離職役累計逾七日者，處二年以下有\n    期徒刑、拘役或科或併科新臺幣二十萬元以下罰金。\n",
  "structure": {
    "main": "甲○○替代役役男無故不就指定之替代役職役，處拘役拾日，如易科罰金，以佰元\n折算壹日。",
    "fact": "一、本件犯罪事實及證據均引用檢察官聲請簡易判決處刑書之記載（如附件）。惟證\n    據部分補充記載如下：依卷附台灣台北地方法院法務部在監\n    甲○○並無任何在監\n二、核被告所為，係犯替代役實施條例第五十二條之無故不就指定之替代役職役罪。\n    爰審酌被告並無任何前科紀錄，素行良好，此有台灣高等法院被告全國前案紀錄\n    表一份在卷可稽，其未依規定辦理請假手續，即無故不入營服役，造成服役單位\n    管理上之困擾，且有違職役所付與之社會責任，惟情節尚屬輕微，對於國防所生\n    之危害非鉅及事後坦承犯行，態度良好等一切情狀，量處如主文所示之刑，並諭\n    知如易科罰金之折算標準。\n三、結論：依刑事訴訟法第四百四十九條第一項前段、第三項、第四百五十四條第二\n    項，替代役實施條例第五十二條，刑法第十一條前段、第四十一條第一項前段，\n    罰金罰鍰提高標準條例第二條，逕以簡易判決處如主文所示之刑。",
    "reason": "一、本件犯罪事實及證據均引用檢察官聲請簡易判決處刑書之記載（如附件）。惟證\n    據部分補充記載如下：依卷附台灣台北地方法院法務部在監\n    甲○○並無任何在監\n二、核被告所為，係犯替代役實施條例第五十二條之無故不就指定之替代役職役罪。\n    爰審酌被告並無任何前科紀錄，素行良好，此有台灣高等法院被告全國前案紀錄\n    表一份在卷可稽，其未依規定辦理請假手續，即無故不入營服役，造成服役單位\n    管理上之困擾，且有違職役所付與之社會責任，惟情節尚屬輕微，對於國防所生\n    之危害非鉅及事後坦承犯行，態度良好等一切情狀，量處如主文所示之刑，並諭\n    知如易科罰金之折算標準。\n三、結論：依刑事訴訟法第四百四十九條第一項前段、第三項、第四百五十四條第二\n    項，替代役實施條例第五十二條，刑法第十一條前段、第四十一條第一項前段，\n    罰金罰鍰提高標準條例第二條，逕以簡易判決處如主文所示之刑。"
  },
  "search": "臺灣臺北地方法院刑事簡易判決九十三年度簡字第三０四六號聲請人臺灣臺北地方法院檢察署檢察官被告甲○○右列被告因違反替代役實施條例案件，經檢察官聲請以簡易判決處刑（九十三年度偵緝字第一五八九號），本院判決如左：主文甲○○替代役役男無故不就指定之替代役職役，處拘役拾日，如易科罰金，以佰元折算壹日。事實及理由一、本件犯罪事實及證據均引用檢察官聲請簡易判決處刑書之記載（如附件）。惟證據部分補充記載如下：依卷附台灣台北地方法院法務部在監甲○○並無任何在監二、核被告所為，係犯替代役實施條例第五十二條之無故不就指定之替代役職役罪。爰審酌被告並無任何前科紀錄，素行良好，此有台灣高等法院被告全國前案紀錄表一份在卷可稽，其未依規定辦理請假手續，即無故不入營服役，造成服役單位管理上之困擾，且有違職役所付與之社會責任，惟情節尚屬輕微，對於國防所生之危害非鉅及事後坦承犯行，態度良好等一切情狀，量處如主文所示之刑，並諭知如易科罰金之折算標準。三、結論：依刑事訴訟法第四百四十九條第一項前段、第三項、第四百五十四條第二項，替代役實施條例第五十二條，刑法第十一條前段、第四十一條第一項前段，罰金罰鍰提高標準條例第二條，逕以簡易判決處如主文所示之刑。中華民國九十三年十二月二十三日臺灣臺北地方法院刑事第十三庭法官鍾素鳳右正本證明與原本無異。如不服本件判決，得自收受送達之日起十日內，向本院提起上訴。書記官朱良燦中華民國九十三年十二月二十三日附錄本判決論罪之法條：替代役實施條例第五十二條替代役役男無故不就指定之替代役職役、擅離職役累計逾七日者，處二年以下有期徒刑、拘役或科或併科新臺幣二十萬元以下罰金。",
  "characters": {
    "judges": [
      "鍾素鳳"
    ],
    "prosecutors": [

    ],
    "lawyers": [

    ],
    "clerks": [
      "朱良燦"
    ],
    "plaintiffs": [

    ],
    "defendants": [
      "甲○○",
      "右列被告因違反替代役實施條例案件，經檢察官聲請以簡易判決處刑（九十三年度偵",
      "緝字第一五八九號），本院判決如左："
    ],
    "prosecutor_office": [
      "臺灣臺北地方法院檢察署檢察官"
    ],
    "creditors": [

    ],
    "debtors": [

    ],
    "judicial_associate_officer": [

    ]
  },
  "adjudged_at": "2004-12-23",
  "created_at": "2016-02-06 07:25:08",
  "updated_at": "2016-02-06 07:25:08"
}