{
  "identify": "TPD-92-重訴-1438-20041222-1",
  "court": {
    "name": "臺灣臺北地方法院",
    "code": "TPD"
  },
  "division": {
    "name": "民事",
    "code": "V"
  },
  "year": 92,
  "word": "重訴",
  "number": "1438",
  "jcheck": "1",
  "reason": "給付違約金等",
  "content": "臺灣臺北地方法院民事裁定                      九十二年度重訴字第一四三八號\n    原      告  龍雲建設開發有限公司\n    法定代理人  甲○○\n    訴訟代理人  蔡奮鯨律師\n                徐秀鳳律師\n    被      告  丑○\n                庚○○\n                辛○○\n                壬○○\n                己○○\n                戊○○\n                丙○○\n                癸○○○○○○.\n                子○○○○○○.\n                乙○○○○○○.\n    共      同\n    訴訟代理人  黃丁風律師\n    被      告  丁○○\n右當事人間請求給付違約金等事件，本院裁定如左：\n        主  文\n本件應再開言詞辯論，並指定民國九十三年十二月三十日下午三時三十分，在本院第\n第二十六法庭行言詞辯論。\n中      華      民      國    九十三    年     十二     月    二十二    日\n                              民事第六庭  法  官    姜悌文\n正本係照原本作成\n本件不得抗告\n中      華      民      國    九十三    年     十二     月    二十二    日\n                                          書記官    陳鳳瀴\n",
  "structure": {
  },
  "search": "臺灣臺北地方法院民事裁定九十二年度重訴字第一四三八號原告龍雲建設開發有限公司法定代理人甲○○訴訟代理人蔡奮鯨律師徐秀鳳律師被告丑○庚○○辛○○壬○○己○○戊○○丙○○癸○○○○○○.子○○○○○○.乙○○○○○○.共同訴訟代理人黃丁風律師被告丁○○右當事人間請求給付違約金等事件，本院裁定如左：主文本件應再開言詞辯論，並指定民國九十三年十二月三十日下午三時三十分，在本院第第二十六法庭行言詞辯論。中華民國九十三年十二月二十二日民事第六庭法官姜悌文正本係照原本作成本件不得抗告中華民國九十三年十二月二十二日書記官陳鳳瀴",
  "characters": {
    "judges": [
      "姜悌文"
    ],
    "prosecutors": [

    ],
    "lawyers": [
      "蔡奮鯨",
      "徐秀鳳",
      "黃丁風"
    ],
    "clerks": [
      "陳鳳瀴"
    ],
    "plaintiffs": [
      "龍雲建設開發有限公司"
    ],
    "defendants": [
      "丑○",
      "丁○○",
      "右當事人間請求給付違約金等事件，本院裁定如左："
    ],
    "prosecutor_office": [

    ],
    "creditors": [

    ],
    "debtors": [

    ],
    "judicial_associate_officer": [

    ]
  },
  "adjudged_at": "2004-12-22",
  "created_at": "2016-02-06 07:29:26",
  "updated_at": "2016-02-06 07:29:26"
}