{
  "identify": "PCD-100-重訴-200-20110527-1",
  "court": {
    "name": "臺灣新北地方法院",
    "code": "PCD"
  },
  "division": {
    "name": "民事",
    "code": "V"
  },
  "year": 100,
  "word": "重訴",
  "number": "200",
  "jcheck": "1",
  "reason": "塗銷所有權登記等",
  "content": "臺灣板橋地方法院民事裁定            100年度重訴字第200號\n原      告  京城商業銀行股份有限公司\n法定代理人  戴誠志\n被      告  蔡武男\n被      告  余國憲\n上列當事人間請求塗銷所有權登記等事件，本院裁定如下：\n    主  文\n本件移送臺灣桃園地方法院。\n    理  由\n一、按訴訟之全部或一部，法院認為無管轄權者，依原告聲請或\n    依職權以裁定移送其管轄法院，民事訴訟法第28條第1項定\n    有明文。\n二、本件原告請求塗銷不動產所有權登記，係基於代位所有物除\n    去妨害請求權為主張，依民事訴訟法第十條第一項規定，專\n    屬不動產所在地之法院即臺灣桃園地方法院管轄，原告向無\n    管轄權之本院起訴，顯係違誤。\n三、依職權將本件移送於該管轄法院。\n四、依首開法條裁定如主文。\n中    華    民    國   100    年    5     月    27    日\n                  民事第三庭    法  官  陳映如\n以上正本係照原本作成\n如對本裁定抗告須於裁定送達後10日內向本院提出抗告狀，並應\n繳納抗告費新台幣1,000元整。\n中    華    民    國   100    年    5     月    27    日\n                            書記官  林勁丞",
  "structure": {
    "main": "本件移送臺灣桃園地方法院。",
    "reason": "一、按訴訟之全部或一部，法院認為無管轄權者，依原告聲請或\n    依職權以裁定移送其管轄法院，民事訴訟法第28條第1項定\n    有明文。\n二、本件原告請求塗銷不動產所有權登記，係基於代位所有物除\n    去妨害請求權為主張，依民事訴訟法第十條第一項規定，專\n    屬不動產所在地之法院即臺灣桃園地方法院管轄，原告向無\n    管轄權之本院起訴，顯係違誤。\n三、依職權將本件移送於該管轄法院。\n四、依首開法條裁定如主文。"
  },
  "search": "臺灣板橋地方法院民事裁定100年度重訴字第200號原告京城商業銀行股份有限公司法定代理人戴誠志被告蔡武男被告余國憲上列當事人間請求塗銷所有權登記等事件，本院裁定如下：主文本件移送臺灣桃園地方法院。理由一、按訴訟之全部或一部，法院認為無管轄權者，依原告聲請或依職權以裁定移送其管轄法院，民事訴訟法第28條第1項定有明文。二、本件原告請求塗銷不動產所有權登記，係基於代位所有物除去妨害請求權為主張，依民事訴訟法第十條第一項規定，專屬不動產所在地之法院即臺灣桃園地方法院管轄，原告向無管轄權之本院起訴，顯係違誤。三、依職權將本件移送於該管轄法院。四、依首開法條裁定如主文。中華民國100年5月27日民事第三庭法官陳映如以上正本係照原本作成如對本裁定抗告須於裁定送達後10日內向本院提出抗告狀，並應繳納抗告費新台幣1,000元整。中華民國100年5月27日書記官林勁丞",
  "characters": {
    "judges": [
      "陳映如"
    ],
    "prosecutors": [

    ],
    "lawyers": [

    ],
    "clerks": [

    ],
    "plaintiffs": [
      "京城商業銀行股份有限公司"
    ],
    "defendants": [
      "蔡武男",
      "被      告  余國憲"
    ],
    "prosecutor_office": [

    ],
    "creditors": [

    ],
    "debtors": [

    ],
    "judicial_associate_officer": [

    ]
  },
  "adjudged_at": "2011-05-27",
  "created_at": "2016-02-12 00:09:12",
  "updated_at": "2016-02-12 00:09:12"
}