{
  "identify": "TYD-100-家訴-109-20110527-1",
  "court": {
    "name": "臺灣桃園地方法院",
    "code": "TYD"
  },
  "division": {
    "name": "民事",
    "code": "V"
  },
  "year": 100,
  "word": "家訴",
  "number": "109",
  "jcheck": "1",
  "reason": "返還遺產",
  "content": "臺灣桃園地方法院民事裁定            100年度家訴字第109號\n原      告  鄭宇婷\n被      告  劉淑靜\n被      告  劉國慶\n被      告  劉淑女\n被      告  劉淑惠\n被      告  施淑媛\n上列當事人間請求返還遺產事件，本院裁定如下：\n    主  文\n原告之訴駁回。\n訴訟費用由原告負擔。\n    理  由\n一、按原告因財產權而提起民事訴訟，應依民事訴訟法第77條之\n    13規定繳納裁判費；又依同法第116 條第1 項規定，當事人\n    書狀應記載「應為之聲明或陳述」，此均為必須具備之程式\n    。\n二、本件原告起訴，未據於書狀上記載應受判決事項之聲明、請\n    求權之依據，經本院於民國100 年5 月17日當庭裁定命原告\n    5 日內為補正，此有言詞辯論筆錄在附卷可憑。惟原告已逾\n    期未為上列補正，則其訴顯難認為合法，應予駁回。\n三、依民事訴訟法第249 條第1 項第6 款、第95條、第78條，裁\n    定如主文。\n中    華    民    國   100    年    5     月    27    日\n                  家事法庭法  官  陳添喜\n以上正本係照原本作成。\n中    華    民    國    100     年    5     月  27    日\n                          書記官  楊慧伶",
  "structure": {
    "main": "原告之訴駁回。\n訴訟費用由原告負擔。",
    "reason": "一、按原告因財產權而提起民事訴訟，應依民事訴訟法第77條之\n    13規定繳納裁判費；又依同法第116 條第1 項規定，當事人\n    書狀應記載「應為之聲明或陳述」，此均為必須具備之程式\n    。\n二、本件原告起訴，未據於書狀上記載應受判決事項之聲明、請\n    求權之依據，經本院於民國100 年5 月17日當庭裁定命原告\n    5 日內為補正，此有言詞辯論筆錄在附卷可憑。惟原告已逾\n    期未為上列補正，則其訴顯難認為合法，應予駁回。\n三、依民事訴訟法第249 條第1 項第6 款、第95條、第78條，裁\n    定如主文。"
  },
  "search": "臺灣桃園地方法院民事裁定100年度家訴字第109號原告鄭宇婷被告劉淑靜被告劉國慶被告劉淑女被告劉淑惠被告施淑媛上列當事人間請求返還遺產事件，本院裁定如下：主文原告之訴駁回。訴訟費用由原告負擔。理由一、按原告因財產權而提起民事訴訟，應依民事訴訟法第77條之13規定繳納裁判費；又依同法第116條第1項規定，當事人書狀應記載「應為之聲明或陳述」，此均為必須具備之程式。二、本件原告起訴，未據於書狀上記載應受判決事項之聲明、請求權之依據，經本院於民國100年5月17日當庭裁定命原告5日內為補正，此有言詞辯論筆錄在附卷可憑。惟原告已逾期未為上列補正，則其訴顯難認為合法，應予駁回。三、依民事訴訟法第249條第1項第6款、第95條、第78條，裁定如主文。中華民國100年5月27日家事法庭法官陳添喜以上正本係照原本作成。中華民國100年5月27日書記官楊慧伶",
  "characters": {
    "judges": [
      "陳添喜"
    ],
    "prosecutors": [

    ],
    "lawyers": [

    ],
    "clerks": [

    ],
    "plaintiffs": [
      "鄭宇婷"
    ],
    "defendants": [
      "劉淑靜",
      "被      告  劉國慶",
      "被      告  劉淑女",
      "被      告  劉淑惠",
      "被      告  施淑媛"
    ],
    "prosecutor_office": [

    ],
    "creditors": [

    ],
    "debtors": [

    ],
    "judicial_associate_officer": [

    ]
  },
  "adjudged_at": "2011-05-27",
  "created_at": "2016-02-12 00:07:09",
  "updated_at": "2016-02-12 00:07:09"
}