{
  "identify": "KSD-99-審交簡-3740-20110322-1",
  "court": {
    "name": "臺灣高雄地方法院",
    "code": "KSD"
  },
  "division": {
    "name": "刑事",
    "code": "M"
  },
  "year": 99,
  "word": "審交簡",
  "number": "3740",
  "jcheck": "1",
  "reason": "公共危險",
  "content": "臺灣高雄地方法院刑事簡易判決      99年度審交簡字第3740號\n公  訴  人  臺灣高雄地方法院檢察署檢察官\n被      告  林榮華\n上列被告因公共危險案件，經檢察官提起公訴（99年度偵字第33\n417 號），被告自白犯罪，本院認宜以簡易判決處刑，裁定改依\n簡易判決處刑，判決如下：\n    主  文\n林榮華犯不能安全駕駛動力交通工具罪，累犯，處有期徒刑伍月\n，如易科罰金，以新臺幣壹仟元折算壹日。\n    事實及理由\n一、本件犯罪事實及證據，除證據部分另補充：「被告林榮華於\n    本院審理時之自白」、「被告之證號查詢機車駕駛人資料」\n    外，餘均引用檢察官起訴書之記載（詳如附件）。\n二、核被告所為，係犯刑法第185 條之3 之不能安全駕駛動力交\n    通工具罪。又被告前因酒後駕車案件，經本院以99年度審交\n    簡字第1068號判處有期徒刑2 月，於99年8 月27日易科罰金\n    執行完畢之事實，有臺灣高等法院被告前案紀錄表附卷可參\n    ，其受徒刑之執行完畢，5 年內故意再犯本件有期徒刑以上\n    之罪，為累犯，應依刑法第47條第1 項規定，加重其刑。爰\n    審酌被告前有酒駕前科紀錄，經臺灣高雄地方法院檢察署以\n    98年度偵字第24371 號為緩起訴處分，緩起訴期間為98年10\n    月6 日至99年10月5 日，嗣又犯上開酒後駕車案件，經本院\n    判處有期徒刑2 月，緩起訴因而遭撤銷，並經本院以99年度\n    審交簡字第2485號判處罰金新臺幣（下同）5 萬5,000 元，\n    有上開臺灣高等法院被告前案紀錄表及各該確定判決書附卷\n    可按，竟猶不知悔改，復於酒後貿然騎車上路，顯見前案所\n    宣示之刑罰顯不足令被告心生警惕，亦未能促其戒除酒後駕\n    車之惡習，且本件呼氣酒精濃度每公升高達0.61毫克，被告\n    又未考領有普通重型機車駕照，經其陳明在卷，並有被告之\n    證號查詢機車駕駛人資料附卷可查（見警卷第9 頁、本院審\n    交簡卷第6 頁），其無照騎乘普通重型機車再犯本件酒後駕\n    車案件，不僅漠視自己安危，更罔顧公眾行之安全，嚴重危\n    害其他參與道路交通之不特定人之生命、身體及財產之安全\n    ，顯無警惕、悔改之意，所為實有不該，本應嚴懲，惟念及\n    其於本院審理時尚能坦承犯行，並考量本件犯罪情節，被告\n    及早為警查獲，幸未釀成事故，及被告犯罪之動機、目的、\n    所生危害，暨其自稱家庭經濟狀況貧寒、高中畢業、現從事\n    水電工作、月薪3 、4 萬元等一切情狀（見偵卷第8 頁調查\n    筆錄受詢問人欄、本院審交易字卷第13頁），量處如主文所\n    示之刑，併諭知如主文所示易科罰金之折算標準，以示懲儆\n    。\n三、依刑事訴訟法第449 條第2 項、第3 項、第454 條第2 項，\n    刑法第185 條之3 、第47條第1 項、第41條第1 項前段，逕\n    以簡易判決處刑如主文。\n四、如不服本判決，應於判決送達之日起10日內，向本院提出上\n    訴（須附繕本）。\n中    華    民    國    100   年    3    月    22     日\n                      高雄簡易庭     法  官  周佳佩\n以上正本證明與原本無異。\n中    華    民    國    100   年    3    月    22     日\n                                     書記官  李承悌\n附錄本案論罪科刑法條：\n刑法第185 條之3\n服用毒品、麻醉藥品、酒類或其他相類之物，不能安全駕駛動力\n交通工具而駕駛者，處1 年以下有期徒刑、拘役或科或併科15萬\n元以下罰金。\n附件：\n臺灣高雄地方法院檢察署檢察官起訴書\n                                     99年度偵字第33417號\n    被      告  林榮華  男  52歲（民國○○年○○月○○日生）\n                        身分證統一編號：Ｚ000000000號\n                        住臺南縣佳里鎮下26號\n                        居高雄市○○區○○街600號4樓\n上列被告因公共危險案件，業經偵查終結，認應提起公訴，茲將\n犯罪事實及證據並所犯法條分敘如下：\n        犯  罪  事  實\n一、林榮華曾犯服用酒類不能安全駕駛動力交通工具而駕駛罪，\n    經臺灣高雄地方法院於民國99年 4月19日，以99年度審交簡\n    字第1068號判處有期徒刑2月確定，甫於99年8月27日易科罰\n    金執行完畢。猶不知悔改，復於99年10月 4日20時55分許，\n    在高雄市○○區○○街某海產店與友人飲酒完畢後，已達不\n    能安全駕駛動力交通工具之狀態，竟仍騎乘車牌號碼XNG-60\n    5號普通重型機車返回高雄市○○區○○街600號 4樓居所，\n    於抵達高雄市○○區○○街 600號前之際，為警攔查，並發\n    現身上有酒味，嗣於同日21時19分許，測得其呼氣所含酒精\n    濃度仍高達0.61MG/L。\n二、案經高雄市政府警察局三民第二分局報告偵辦。\n        證  據  並  所  犯  法  條\n一、證據名稱暨待證事實：\n  ┌──┬───────────┬───────────┐\n  │編號│    證  據  名  稱    │    待  證  事  實    │\n  ├──┼───────────┼───────────┤\n  │ 一 │被告林榮華於警詢時及本│被告有於前揭時、地，酒│\n  │    │署偵查中的自白。      │後騎乘機車等全部犯罪事│\n  │    │                      │實。                  │\n  ├──┼───────────┼───────────┤\n  │ 二 │高雄市○○○○○道路交│被告於前揭時、地，酒後│\n  │    │通事故當事人酒精測定紀│騎乘機車，經檢測結果，│\n  │    │錄表。                │呼氣酒測值高達0.61MG/L│\n  │    │                      │等事實。              │\n  ├──┼───────────┼───────────┤\n  │ 三 │（一）行政院國軍退除役│就醫學實驗所得之經驗法│\n  │    │      官兵輔導委員會臺│則可知，酒精對人體的影│\n  │    │      北榮民總醫院88年│響程度乃依血中酒精濃度│\n  │    │      8月5日（88）北總│而定，又警方測試器所測│\n  │    │      內字第 26868號函│得之呼氣酒精濃度乘以20│\n  │    │      。              │0 為當時血中酒精濃度。│\n  │    │（二）法務部88年 5月18│當呼氣酒精濃度達0.25MG│\n  │    │      日（88）法檢字第│/L時，造成輕度協調功能│\n  │    │      001669號函。    │降低之輕度酒精中毒症狀│\n  │    │（三）司法院第46期司法│，當呼氣酒精濃度達 0.5│\n  │    │      業務研究會研究專│MG/L時將造成反應較慢、│\n  │    │      輯（蔡中志著，對│感覺減低、影響駕駛等輕│\n  │    │      飲酒不能安全駕駛│到中度之酒精中毒症狀，│\n  │    │      之執法研究）。  │當呼氣酒精濃度達0.75MG│\n  │    │                      │/L時，將造成思考改變、│\n  │    │                      │個性行為變等酒精中毒症│\n  │    │                      │狀，當呼氣酒精濃度達1.│\n  │    │                      │0 MG/L時，將造成步態不│\n  │    │                      │穩、噁心嘔吐、精神混惑│\n  │    │                      │不清晰之中度酒精中毒症│\n  │    │                      │狀，故被告酒測值既已高│\n  │    │                      │達0.61MG/L，當已不能安│\n  │    │                      │全駕駛動力交通工具之事│\n  │    │                      │實。                  │\n  ├──┼───────────┼───────────┤\n  │ 四 │（一）勾選駕駛人林榮華│被告違反道路交通安全規│\n  │    │      車輛行徑偏離常軌│則第114條第2款之規定酒│\n  │    │      ，時而加速，時而│後騎乘機車，並有異常行│\n  │    │      突停，顯無法正常│為狀況，足認其已不能安│\n  │    │      操控等情之刑法第│全駕駛動力交通工具等事│\n  │    │      185條之3案件測試│實。                  │\n  │    │      觀察紀錄表。    │                      │\n  │    │（二）高雄市政府警察局│                      │\n  │    │      舉發違反道路交通│                      │\n  │    │      管理事件通知單。│                      │\n  ├──┼───────────┼───────────┤\n  │ 五 │（一）法務部被告全國刑│（一）被告曾受有期徒刑│\n  │    │      案資料查註表。  │      之執行完畢， 5年│\n  │    │（二）本署99年度偵字第│      以內故意再犯本件│\n  │    │      226 號、撤緩偵字│      有期徒刑以上之罪│\n  │    │      第109 號聲請簡易│      ，為累犯等事實。│\n  │    │      判決處刑書。    │（二）被告係第三度酒後│\n  │    │（三）臺灣高雄地方法院│      駕駛動力交通工具│\n  │    │      99年度審交簡字第│      而遭查獲等事實。│\n  │    │      1068號、第2485號│                      │\n  │    │      判決書。        │                      │\n  └──┴───────────┴───────────┘\n二、所犯法條：\n    核被告林榮華所為，係犯刑法第185條之3服用酒類不能安全\n    駕駛動力交通工具而駕駛罪嫌。又被告曾受有期徒刑之執行\n    完畢，此有法務部被告全國刑案資料查註表在卷可參， 5年\n    以內故意再犯本件有期徒刑以上之罪，為累犯，請依刑法第\n    47條第 1項規定加重其刑。爰審酌被告前於98年間，兩度因\n    服用酒類不能安全駕駛動力交通工具而駕駛案件，經臺灣高\n    雄地方法院分以99年度審交簡字第2485號、99年度審交簡字\n    第1068號判決，判處罰金新臺幣 55,000元及有期徒刑2月，\n    此有法務部被告全國刑案資料查註表及前揭判決書等在卷可\n    稽，本次竟第三度為酒後駕車行為，自制力顯然欠佳，請依\n    法量處有期徒刑4個月以上，以資警惕。\n三、依刑事訴訟法第251條第1項提起公訴。\n    此    致\n臺灣高雄地方法院\n中    華    民    國    99    年    11    月    16    日\n                              檢  察  官  李  政  達\n上正本證明與原本無異\n中    華    民    國    99    年    11    月    25    日\n                              書  記  官  莊  惠  鈞\n附錄本案所犯法條全文\n中華民國刑法第185條之3\n服用毒品、麻醉藥品、酒類或其他相類之物，不能安全駕駛動力\n交通工具而駕駛者，處 1 年以下有期徒刑、拘役或科或併科 15\n萬元以下罰金。",
  "structure": {
    "main": "林榮華犯不能安全駕駛動力交通工具罪，累犯，處有期徒刑伍月\n，如易科罰金，以新臺幣壹仟元折算壹日。\n    事實及理由\n一、本件犯罪事實及證據，除證據部分另補充：「被告林榮華於\n    本院審理時之自白」、「被告之證號查詢機車駕駛人資料」\n    外，餘均引用檢察官起訴書之記載（詳如附件）。\n二、核被告所為，係犯刑法第185 條之3 之不能安全駕駛動力交\n    通工具罪。又被告前因酒後駕車案件，經本院以99年度審交\n    簡字第1068號判處有期徒刑2 月，於99年8 月27日易科罰金\n    執行完畢之事實，有臺灣高等法院被告前案紀錄表附卷可參\n    ，其受徒刑之執行完畢，5 年內故意再犯本件有期徒刑以上\n    之罪，為累犯，應依刑法第47條第1 項規定，加重其刑。爰\n    審酌被告前有酒駕前科紀錄，經臺灣高雄地方法院檢察署以\n    98年度偵字第24371 號為緩起訴處分，緩起訴期間為98年10\n    月6 日至99年10月5 日，嗣又犯上開酒後駕車案件，經本院\n    判處有期徒刑2 月，緩起訴因而遭撤銷，並經本院以99年度\n    審交簡字第2485號判處罰金新臺幣（下同）5 萬5,000 元，\n    有上開臺灣高等法院被告前案紀錄表及各該確定判決書附卷\n    可按，竟猶不知悔改，復於酒後貿然騎車上路，顯見前案所\n    宣示之刑罰顯不足令被告心生警惕，亦未能促其戒除酒後駕\n    車之惡習，且本件呼氣酒精濃度每公升高達0.61毫克，被告\n    又未考領有普通重型機車駕照，經其陳明在卷，並有被告之\n    證號查詢機車駕駛人資料附卷可查（見警卷第9 頁、本院審\n    交簡卷第6 頁），其無照騎乘普通重型機車再犯本件酒後駕\n    車案件，不僅漠視自己安危，更罔顧公眾行之安全，嚴重危\n    害其他參與道路交通之不特定人之生命、身體及財產之安全\n    ，顯無警惕、悔改之意，所為實有不該，本應嚴懲，惟念及\n    其於本院審理時尚能坦承犯行，並考量本件犯罪情節，被告\n    及早為警查獲，幸未釀成事故，及被告犯罪之動機、目的、\n    所生危害，暨其自稱家庭經濟狀況貧寒、高中畢業、現從事\n    水電工作、月薪3 、4 萬元等一切情狀（見偵卷第8 頁調查\n    筆錄受詢問人欄、本院審交易字卷第13頁），量處如主文所\n    示之刑，併諭知如主文所示易科罰金之折算標準，以示懲儆\n    。\n三、依刑事訴訟法第449 條第2 項、第3 項、第454 條第2 項，\n    刑法第185 條之3 、第47條第1 項、第41條第1 項前段，逕\n    以簡易判決處刑如主文。\n四、如不服本判決，應於判決送達之日起10日內，向本院提出上\n    訴（須附繕本）。\n中    華    民    國    100   年    3    月    22     日\n                      高雄簡易庭     法  官  周佳佩\n以上正本證明與原本無異。\n中    華    民    國    100   年    3    月    22     日\n                                     書記官  李承悌\n附錄本案論罪科刑法條：\n刑法第185 條之3\n服用毒品、麻醉藥品、酒類或其他相類之物，不能安全駕駛動力\n交通工具而駕駛者，處1 年以下有期徒刑、拘役或科或併科15萬\n元以下罰金。\n附件：\n臺灣高雄地方法院檢察署檢察官起訴書\n                                     99年度偵字第33417號\n    被      告  林榮華  男  52歲（民國○○年○○月○○日生）\n                        身分證統一編號：Ｚ000000000號\n                        住臺南縣佳里鎮下26號\n                        居高雄市○○區○○街600號4樓\n上列被告因公共危險案件，業經偵查終結，認應提起公訴，茲將\n犯罪事實及證據並所犯法條分敘如下：\n        犯  罪",
    "fact": "一、本件犯罪事實及證據，除證據部分另補充：「被告林榮華於\n    本院審理時之自白」、「被告之證號查詢機車駕駛人資料」\n    外，餘均引用檢察官起訴書之記載（詳如附件）。\n二、核被告所為，係犯刑法第185 條之3 之不能安全駕駛動力交\n    通工具罪。又被告前因酒後駕車案件，經本院以99年度審交\n    簡字第1068號判處有期徒刑2 月，於99年8 月27日易科罰金\n    執行完畢之事實，有臺灣高等法院被告前案紀錄表附卷可參\n    ，其受徒刑之執行完畢，5 年內故意再犯本件有期徒刑以上\n    之罪，為累犯，應依刑法第47條第1 項規定，加重其刑。爰\n    審酌被告前有酒駕前科紀錄，經臺灣高雄地方法院檢察署以\n    98年度偵字第24371 號為緩起訴處分，緩起訴期間為98年10\n    月6 日至99年10月5 日，嗣又犯上開酒後駕車案件，經本院\n    判處有期徒刑2 月，緩起訴因而遭撤銷，並經本院以99年度\n    審交簡字第2485號判處罰金新臺幣（下同）5 萬5,000 元，\n    有上開臺灣高等法院被告前案紀錄表及各該確定判決書附卷\n    可按，竟猶不知悔改，復於酒後貿然騎車上路，顯見前案所\n    宣示之刑罰顯不足令被告心生警惕，亦未能促其戒除酒後駕\n    車之惡習，且本件呼氣酒精濃度每公升高達0.61毫克，被告\n    又未考領有普通重型機車駕照，經其陳明在卷，並有被告之\n    證號查詢機車駕駛人資料附卷可查（見警卷第9 頁、本院審\n    交簡卷第6 頁），其無照騎乘普通重型機車再犯本件酒後駕\n    車案件，不僅漠視自己安危，更罔顧公眾行之安全，嚴重危\n    害其他參與道路交通之不特定人之生命、身體及財產之安全\n    ，顯無警惕、悔改之意，所為實有不該，本應嚴懲，惟念及\n    其於本院審理時尚能坦承犯行，並考量本件犯罪情節，被告\n    及早為警查獲，幸未釀成事故，及被告犯罪之動機、目的、\n    所生危害，暨其自稱家庭經濟狀況貧寒、高中畢業、現從事\n    水電工作、月薪3 、4 萬元等一切情狀（見偵卷第8 頁調查\n    筆錄受詢問人欄、本院審交易字卷第13頁），量處如主文所\n    示之刑，併諭知如主文所示易科罰金之折算標準，以示懲儆\n    。\n三、依刑事訴訟法第449 條第2 項、第3 項、第454 條第2 項，\n    刑法第185 條之3 、第47條第1 項、第41條第1 項前段，逕\n    以簡易判決處刑如主文。\n四、如不服本判決，應於判決送達之日起10日內，向本院提出上\n    訴（須附繕本）。",
    "reason": "一、本件犯罪事實及證據，除證據部分另補充：「被告林榮華於\n    本院審理時之自白」、「被告之證號查詢機車駕駛人資料」\n    外，餘均引用檢察官起訴書之記載（詳如附件）。\n二、核被告所為，係犯刑法第185 條之3 之不能安全駕駛動力交\n    通工具罪。又被告前因酒後駕車案件，經本院以99年度審交\n    簡字第1068號判處有期徒刑2 月，於99年8 月27日易科罰金\n    執行完畢之事實，有臺灣高等法院被告前案紀錄表附卷可參\n    ，其受徒刑之執行完畢，5 年內故意再犯本件有期徒刑以上\n    之罪，為累犯，應依刑法第47條第1 項規定，加重其刑。爰\n    審酌被告前有酒駕前科紀錄，經臺灣高雄地方法院檢察署以\n    98年度偵字第24371 號為緩起訴處分，緩起訴期間為98年10\n    月6 日至99年10月5 日，嗣又犯上開酒後駕車案件，經本院\n    判處有期徒刑2 月，緩起訴因而遭撤銷，並經本院以99年度\n    審交簡字第2485號判處罰金新臺幣（下同）5 萬5,000 元，\n    有上開臺灣高等法院被告前案紀錄表及各該確定判決書附卷\n    可按，竟猶不知悔改，復於酒後貿然騎車上路，顯見前案所\n    宣示之刑罰顯不足令被告心生警惕，亦未能促其戒除酒後駕\n    車之惡習，且本件呼氣酒精濃度每公升高達0.61毫克，被告\n    又未考領有普通重型機車駕照，經其陳明在卷，並有被告之\n    證號查詢機車駕駛人資料附卷可查（見警卷第9 頁、本院審\n    交簡卷第6 頁），其無照騎乘普通重型機車再犯本件酒後駕\n    車案件，不僅漠視自己安危，更罔顧公眾行之安全，嚴重危\n    害其他參與道路交通之不特定人之生命、身體及財產之安全\n    ，顯無警惕、悔改之意，所為實有不該，本應嚴懲，惟念及\n    其於本院審理時尚能坦承犯行，並考量本件犯罪情節，被告\n    及早為警查獲，幸未釀成事故，及被告犯罪之動機、目的、\n    所生危害，暨其自稱家庭經濟狀況貧寒、高中畢業、現從事\n    水電工作、月薪3 、4 萬元等一切情狀（見偵卷第8 頁調查\n    筆錄受詢問人欄、本院審交易字卷第13頁），量處如主文所\n    示之刑，併諭知如主文所示易科罰金之折算標準，以示懲儆\n    。\n三、依刑事訴訟法第449 條第2 項、第3 項、第454 條第2 項，\n    刑法第185 條之3 、第47條第1 項、第41條第1 項前段，逕\n    以簡易判決處刑如主文。\n四、如不服本判決，應於判決送達之日起10日內，向本院提出上\n    訴（須附繕本）。"
  },
  "search": "臺灣高雄地方法院刑事簡易判決99年度審交簡字第3740號公訴人臺灣高雄地方法院檢察署檢察官被告林榮華上列被告因公共危險案件，經檢察官提起公訴（99年度偵字第33417號），被告自白犯罪，本院認宜以簡易判決處刑，裁定改依簡易判決處刑，判決如下：主文林榮華犯不能安全駕駛動力交通工具罪，累犯，處有期徒刑伍月，如易科罰金，以新臺幣壹仟元折算壹日。事實及理由一、本件犯罪事實及證據，除證據部分另補充：「被告林榮華於本院審理時之自白」、「被告之證號查詢機車駕駛人資料」外，餘均引用檢察官起訴書之記載（詳如附件）。二、核被告所為，係犯刑法第185條之3之不能安全駕駛動力交通工具罪。又被告前因酒後駕車案件，經本院以99年度審交簡字第1068號判處有期徒刑2月，於99年8月27日易科罰金執行完畢之事實，有臺灣高等法院被告前案紀錄表附卷可參，其受徒刑之執行完畢，5年內故意再犯本件有期徒刑以上之罪，為累犯，應依刑法第47條第1項規定，加重其刑。爰審酌被告前有酒駕前科紀錄，經臺灣高雄地方法院檢察署以98年度偵字第24371號為緩起訴處分，緩起訴期間為98年10月6日至99年10月5日，嗣又犯上開酒後駕車案件，經本院判處有期徒刑2月，緩起訴因而遭撤銷，並經本院以99年度審交簡字第2485號判處罰金新臺幣（下同）5萬5,000元，有上開臺灣高等法院被告前案紀錄表及各該確定判決書附卷可按，竟猶不知悔改，復於酒後貿然騎車上路，顯見前案所宣示之刑罰顯不足令被告心生警惕，亦未能促其戒除酒後駕車之惡習，且本件呼氣酒精濃度每公升高達0.61毫克，被告又未考領有普通重型機車駕照，經其陳明在卷，並有被告之證號查詢機車駕駛人資料附卷可查（見警卷第9頁、本院審交簡卷第6頁），其無照騎乘普通重型機車再犯本件酒後駕車案件，不僅漠視自己安危，更罔顧公眾行之安全，嚴重危害其他參與道路交通之不特定人之生命、身體及財產之安全，顯無警惕、悔改之意，所為實有不該，本應嚴懲，惟念及其於本院審理時尚能坦承犯行，並考量本件犯罪情節，被告及早為警查獲，幸未釀成事故，及被告犯罪之動機、目的、所生危害，暨其自稱家庭經濟狀況貧寒、高中畢業、現從事水電工作、月薪3、4萬元等一切情狀（見偵卷第8頁調查筆錄受詢問人欄、本院審交易字卷第13頁），量處如主文所示之刑，併諭知如主文所示易科罰金之折算標準，以示懲儆。三、依刑事訴訟法第449條第2項、第3項、第454條第2項，刑法第185條之3、第47條第1項、第41條第1項前段，逕以簡易判決處刑如主文。四、如不服本判決，應於判決送達之日起10日內，向本院提出上訴（須附繕本）。中華民國100年3月22日高雄簡易庭法官周佳佩以上正本證明與原本無異。中華民國100年3月22日書記官李承悌附錄本案論罪科刑法條：刑法第185條之3服用毒品、麻醉藥品、酒類或其他相類之物，不能安全駕駛動力交通工具而駕駛者，處1年以下有期徒刑、拘役或科或併科15萬元以下罰金。附件：臺灣高雄地方法院檢察署檢察官起訴書99年度偵字第33417號被告林榮華男52歲（民國○○年○○月○○日生）身分證統一編號：Ｚ000000000號住臺南縣佳里鎮下26號居高雄市○○區○○街600號4樓上列被告因公共危險案件，業經偵查終結，認應提起公訴，茲將犯罪事實及證據並所犯法條分敘如下：犯罪事實一、林榮華曾犯服用酒類不能安全駕駛動力交通工具而駕駛罪，經臺灣高雄地方法院於民國99年4月19日，以99年度審交簡字第1068號判處有期徒刑2月確定，甫於99年8月27日易科罰金執行完畢。猶不知悔改，復於99年10月4日20時55分許，在高雄市○○區○○街某海產店與友人飲酒完畢後，已達不能安全駕駛動力交通工具之狀態，竟仍騎乘車牌號碼XNG-605號普通重型機車返回高雄市○○區○○街600號4樓居所，於抵達高雄市○○區○○街600號前之際，為警攔查，並發現身上有酒味，嗣於同日21時19分許，測得其呼氣所含酒精濃度仍高達0.61MG/L。二、案經高雄市政府警察局三民第二分局報告偵辦。證據並所犯法條一、證據名稱暨待證事實：┌──┬───────────┬───────────┐│編號│證據名稱│待證事實│├──┼───────────┼───────────┤│一│被告林榮華於警詢時及本│被告有於前揭時、地，酒│││署偵查中的自白。│後騎乘機車等全部犯罪事││││實。│├──┼───────────┼───────────┤│二│高雄市○○○○○道路交│被告於前揭時、地，酒後│││通事故當事人酒精測定紀│騎乘機車，經檢測結果，│││錄表。│呼氣酒測值高達0.61MG/L││││等事實。│├──┼───────────┼───────────┤│三│（一）行政院國軍退除役│就醫學實驗所得之經驗法│││官兵輔導委員會臺│則可知，酒精對人體的影│││北榮民總醫院88年│響程度乃依血中酒精濃度│││8月5日（88）北總│而定，又警方測試器所測│││內字第26868號函│得之呼氣酒精濃度乘以20│││。│0為當時血中酒精濃度。│││（二）法務部88年5月18│當呼氣酒精濃度達0.25MG│││日（88）法檢字第│/L時，造成輕度協調功能│││001669號函。│降低之輕度酒精中毒症狀│││（三）司法院第46期司法│，當呼氣酒精濃度達0.5│││業務研究會研究專│MG/L時將造成反應較慢、│││輯（蔡中志著，對│感覺減低、影響駕駛等輕│││飲酒不能安全駕駛│到中度之酒精中毒症狀，│││之執法研究）。│當呼氣酒精濃度達0.75MG││││/L時，將造成思考改變、││││個性行為變等酒精中毒症││││狀，當呼氣酒精濃度達1.││││0MG/L時，將造成步態不││││穩、噁心嘔吐、精神混惑││││不清晰之中度酒精中毒症││││狀，故被告酒測值既已高││││達0.61MG/L，當已不能安││││全駕駛動力交通工具之事││││實。│├──┼───────────┼───────────┤│四│（一）勾選駕駛人林榮華│被告違反道路交通安全規│││車輛行徑偏離常軌│則第114條第2款之規定酒│││，時而加速，時而│後騎乘機車，並有異常行│││突停，顯無法正常│為狀況，足認其已不能安│││操控等情之刑法第│全駕駛動力交通工具等事│││185條之3案件測試│實。│││觀察紀錄表。││││（二）高雄市政府警察局││││舉發違反道路交通││││管理事件通知單。││├──┼───────────┼───────────┤│五│（一）法務部被告全國刑│（一）被告曾受有期徒刑│││案資料查註表。│之執行完畢，5年│││（二）本署99年度偵字第│以內故意再犯本件│││226號、撤緩偵字│有期徒刑以上之罪│││第109號聲請簡易│，為累犯等事實。│││判決處刑書。│（二）被告係第三度酒後│││（三）臺灣高雄地方法院│駕駛動力交通工具│││99年度審交簡字第│而遭查獲等事實。│││1068號、第2485號││││判決書。││└──┴───────────┴───────────┘二、所犯法條：核被告林榮華所為，係犯刑法第185條之3服用酒類不能安全駕駛動力交通工具而駕駛罪嫌。又被告曾受有期徒刑之執行完畢，此有法務部被告全國刑案資料查註表在卷可參，5年以內故意再犯本件有期徒刑以上之罪，為累犯，請依刑法第47條第1項規定加重其刑。爰審酌被告前於98年間，兩度因服用酒類不能安全駕駛動力交通工具而駕駛案件，經臺灣高雄地方法院分以99年度審交簡字第2485號、99年度審交簡字第1068號判決，判處罰金新臺幣55,000元及有期徒刑2月，此有法務部被告全國刑案資料查註表及前揭判決書等在卷可稽，本次竟第三度為酒後駕車行為，自制力顯然欠佳，請依法量處有期徒刑4個月以上，以資警惕。三、依刑事訴訟法第251條第1項提起公訴。此致臺灣高雄地方法院中華民國99年11月16日檢察官李政達上正本證明與原本無異中華民國99年11月25日書記官莊惠鈞附錄本案所犯法條全文中華民國刑法第185條之3服用毒品、麻醉藥品、酒類或其他相類之物，不能安全駕駛動力交通工具而駕駛者，處1年以下有期徒刑、拘役或科或併科15萬元以下罰金。",
  "characters": {
    "judges": [
      "周佳佩"
    ],
    "prosecutors": [

    ],
    "lawyers": [

    ],
    "clerks": [
      "李承悌"
    ],
    "plaintiffs": [

    ],
    "defendants": [
      "林榮華",
      "林榮華  男  52歲（民國○○年○○月○○日生）"
    ],
    "prosecutor_office": [
      "臺灣高雄地方法院檢察署檢察官"
    ],
    "creditors": [

    ],
    "debtors": [

    ],
    "judicial_associate_officer": [

    ]
  },
  "adjudged_at": "2011-03-22",
  "created_at": "2016-02-13 22:28:39",
  "updated_at": "2016-02-13 22:28:39"
}