{
  "identify": "TND-100-交簡-602-20110322-1",
  "court": {
    "name": "臺灣臺南地方法院",
    "code": "TND"
  },
  "division": {
    "name": "刑事",
    "code": "M"
  },
  "year": 100,
  "word": "交簡",
  "number": "602",
  "jcheck": "1",
  "reason": "過失傷害",
  "content": "臺灣臺南地方法院刑事簡易判決        100年度交簡字第602號\n聲  請  人  臺灣臺南地方法院檢察署檢察官\n被      告  鄭竹喜\n上列被告因過失傷害案件，經檢察官聲請以簡易判決處刑（99年\n度偵字第18033 號），本院判決如下：\n    主  文\n鄭竹喜犯過失傷害罪，處有期徒刑參月，如易科罰金，以新臺幣\n壹仟元折算壹日。\n    事實及理由\n一、鄭竹喜於民國99年7 月28日晚上7 時15分許，駕駛車牌號碼\n    0528－UV號自小客車，沿臺南市○○區○○路1 段2 巷堤岸\n    道路由南往北方向行駛時，本應注意車前狀況，並隨時採取\n    必要之安全措施，以避免危險之發生，而依當時雖係夜間，\n    惟有照明、路面乾燥無缺陷、無障礙物及視距良好等情形觀\n    之，客觀上並無不能注意之情事，竟疏未注意及此，適有蔡\n    惠珍騎乘車牌號碼366-ENB 號普通重型機車自該路對向行駛\n    而來，亦未注意車前狀況，雙方見狀閃避不及，兩車碰撞後\n    ，蔡惠珍人車倒地，並受有頭部外傷、顱骨骨折併顱內出血\n    、右側脛骨、腓骨開放性骨折併皮膚壞死及腹部挫傷等傷害\n    。鄭竹喜肇事後，停留於肇事現場等待員警到場處理，並於\n    員警尚不知何人為本件車禍肇事人前，主動表明其為肇事車\n    輛駕駛人，自首而接受裁判。案經蔡惠珍訴由臺南市警察局\n    第三分局報請臺灣臺南地方法院檢察署檢察官偵查後聲請簡\n    易判決處刑。\n二、前項犯罪事實，有下列事證足資證明：\n  (一)被告於警詢、偵查中所為之自白。\n  (二)告訴人蔡惠珍於警詢、偵查中所為之指訴。\n  (三)臺南市警察局第三分局道路交通事故初步分析研判表1張。\n  (四)財團法人奇美醫院診斷證明書4張。\n  (五)交通事故現場勘驗圖1張。\n  (六)臺南市警察局處理交通事故紀錄表1張。\n  (七)道路交通事故現場圖1張。\n  (八)道路交通事故調查報告表（一）、（二）。\n  (九)現場照片22張。\n  (十)臺南市警察局第三分局道路交通事故肇事人自首情形紀錄表\n    1張。\n三、核被告所為，係犯刑法第284 條第1 項前段之過失傷害罪。\n    被告於肇事後，犯罪未被有偵查權之公務員或機關發覺前，\n    立即報警，留在事故現場並當場承認為肇事人，向到場處理\n    之警員自首，坦承犯行進而接受裁判，此有臺南市警察局第\n    三分局道路交通事故肇事人自首情形紀錄表附卷可稽（見警\n    卷第35頁），被告行為合乎自首之要件，爰依刑法第62條規\n    定減輕其刑。爰審酌被告因過失肇事，因而致告訴人受有頭\n    部外傷、顱骨骨折併顱內出血、右側脛骨、腓骨開放性骨折\n    併皮膚壞死及腹部挫傷等傷害，被告之過失程度，暨衡量告\n    訴人未注意車前狀況，亦與有過失，並考量被告尚未賠償告\n    訴人等一切情狀，量處如主文所示之刑，並諭知易科罰金之\n    折算標準，以資儆懲。\n四、依刑事訴訟法第449 條第1 項前段、第3 項、第454 條第1\n    項，刑法第284 條第1 項前段、第62條前段、第41條第1 項\n    前段，刑法施行法第1 條之1 ，逕以簡易判決處刑如主文。\n五、如不服本件判決，得自收受送達後10日內，向本院提出上訴\n    狀（附繕本），上訴於本院管轄之第二審地方法院合議庭。\n中    華    民    國  100    年    3    月    22    日\n                  刑事第十庭    法  官  羅郁棣\n以上正本證明與原本無異。\n                                書記官  黃玉秀\n中    華    民    國  100    年    3    月    22    日\n附錄所犯法條：\n刑法第284條第1項前段\n因過失傷害人者，處 6 月以下有期徒刑、拘役或 5 百元以下罰\n金，致重傷者，處 1 年以下有期徒刑、拘役或 5 百元以下罰金\n。\n從事業務之人，因業務上之過失傷害人者，處 1 年以下有期徒\n刑、拘役或 1 千元以下罰金，致重傷者，處 3 年以下有期徒刑\n、拘役或 2 千元以下罰金。",
  "structure": {
    "main": "鄭竹喜犯過失傷害罪，處有期徒刑參月，如易科罰金，以新臺幣\n壹仟元折算壹日。",
    "fact": "一、鄭竹喜於民國99年7 月28日晚上7 時15分許，駕駛車牌號碼\n    0528－UV號自小客車，沿臺南市○○區○○路1 段2 巷堤岸\n    道路由南往北方向行駛時，本應注意車前狀況，並隨時採取\n    必要之安全措施，以避免危險之發生，而依當時雖係夜間，\n    惟有照明、路面乾燥無缺陷、無障礙物及視距良好等情形觀\n    之，客觀上並無不能注意之情事，竟疏未注意及此，適有蔡\n    惠珍騎乘車牌號碼366-ENB 號普通重型機車自該路對向行駛\n    而來，亦未注意車前狀況，雙方見狀閃避不及，兩車碰撞後\n    ，蔡惠珍人車倒地，並受有頭部外傷、顱骨骨折併顱內出血\n    、右側脛骨、腓骨開放性骨折併皮膚壞死及腹部挫傷等傷害\n    。鄭竹喜肇事後，停留於肇事現場等待員警到場處理，並於\n    員警尚不知何人為本件車禍肇事人前，主動表明其為肇事車\n    輛駕駛人，自首而接受裁判。案經蔡惠珍訴由臺南市警察局\n    第三分局報請臺灣臺南地方法院檢察署檢察官偵查後聲請簡\n    易判決處刑。\n二、前項犯罪事實，有下列事證足資證明：\n  (一)被告於警詢、偵查中所為之自白。\n  (二)告訴人蔡惠珍於警詢、偵查中所為之指訴。\n  (三)臺南市警察局第三分局道路交通事故初步分析研判表1張。\n  (四)財團法人奇美醫院診斷證明書4張。\n  (五)交通事故現場勘驗圖1張。\n  (六)臺南市警察局處理交通事故紀錄表1張。\n  (七)道路交通事故現場圖1張。\n  (八)道路交通事故調查報告表（一）、（二）。\n  (九)現場照片22張。\n  (十)臺南市警察局第三分局道路交通事故肇事人自首情形紀錄表\n    1張。\n三、核被告所為，係犯刑法第284 條第1 項前段之過失傷害罪。\n    被告於肇事後，犯罪未被有偵查權之公務員或機關發覺前，\n    立即報警，留在事故現場並當場承認為肇事人，向到場處理\n    之警員自首，坦承犯行進而接受裁判，此有臺南市警察局第\n    三分局道路交通事故肇事人自首情形紀錄表附卷可稽（見警\n    卷第35頁），被告行為合乎自首之要件，爰依刑法第62條規\n    定減輕其刑。爰審酌被告因過失肇事，因而致告訴人受有頭\n    部外傷、顱骨骨折併顱內出血、右側脛骨、腓骨開放性骨折\n    併皮膚壞死及腹部挫傷等傷害，被告之過失程度，暨衡量告\n    訴人未注意車前狀況，亦與有過失，並考量被告尚未賠償告\n    訴人等一切情狀，量處如主文所示之刑，並諭知易科罰金之\n    折算標準，以資儆懲。\n四、依刑事訴訟法第449 條第1 項前段、第3 項、第454 條第1\n    項，刑法第284 條第1 項前段、第62條前段、第41條第1 項\n    前段，刑法施行法第1 條之1 ，逕以簡易判決處刑如主文。\n五、如不服本件判決，得自收受送達後10日內，向本院提出上訴\n    狀（附繕本），上訴於本院管轄之第二審地方法院合議庭。",
    "reason": "一、鄭竹喜於民國99年7 月28日晚上7 時15分許，駕駛車牌號碼\n    0528－UV號自小客車，沿臺南市○○區○○路1 段2 巷堤岸\n    道路由南往北方向行駛時，本應注意車前狀況，並隨時採取\n    必要之安全措施，以避免危險之發生，而依當時雖係夜間，\n    惟有照明、路面乾燥無缺陷、無障礙物及視距良好等情形觀\n    之，客觀上並無不能注意之情事，竟疏未注意及此，適有蔡\n    惠珍騎乘車牌號碼366-ENB 號普通重型機車自該路對向行駛\n    而來，亦未注意車前狀況，雙方見狀閃避不及，兩車碰撞後\n    ，蔡惠珍人車倒地，並受有頭部外傷、顱骨骨折併顱內出血\n    、右側脛骨、腓骨開放性骨折併皮膚壞死及腹部挫傷等傷害\n    。鄭竹喜肇事後，停留於肇事現場等待員警到場處理，並於\n    員警尚不知何人為本件車禍肇事人前，主動表明其為肇事車\n    輛駕駛人，自首而接受裁判。案經蔡惠珍訴由臺南市警察局\n    第三分局報請臺灣臺南地方法院檢察署檢察官偵查後聲請簡\n    易判決處刑。\n二、前項犯罪事實，有下列事證足資證明：\n  (一)被告於警詢、偵查中所為之自白。\n  (二)告訴人蔡惠珍於警詢、偵查中所為之指訴。\n  (三)臺南市警察局第三分局道路交通事故初步分析研判表1張。\n  (四)財團法人奇美醫院診斷證明書4張。\n  (五)交通事故現場勘驗圖1張。\n  (六)臺南市警察局處理交通事故紀錄表1張。\n  (七)道路交通事故現場圖1張。\n  (八)道路交通事故調查報告表（一）、（二）。\n  (九)現場照片22張。\n  (十)臺南市警察局第三分局道路交通事故肇事人自首情形紀錄表\n    1張。\n三、核被告所為，係犯刑法第284 條第1 項前段之過失傷害罪。\n    被告於肇事後，犯罪未被有偵查權之公務員或機關發覺前，\n    立即報警，留在事故現場並當場承認為肇事人，向到場處理\n    之警員自首，坦承犯行進而接受裁判，此有臺南市警察局第\n    三分局道路交通事故肇事人自首情形紀錄表附卷可稽（見警\n    卷第35頁），被告行為合乎自首之要件，爰依刑法第62條規\n    定減輕其刑。爰審酌被告因過失肇事，因而致告訴人受有頭\n    部外傷、顱骨骨折併顱內出血、右側脛骨、腓骨開放性骨折\n    併皮膚壞死及腹部挫傷等傷害，被告之過失程度，暨衡量告\n    訴人未注意車前狀況，亦與有過失，並考量被告尚未賠償告\n    訴人等一切情狀，量處如主文所示之刑，並諭知易科罰金之\n    折算標準，以資儆懲。\n四、依刑事訴訟法第449 條第1 項前段、第3 項、第454 條第1\n    項，刑法第284 條第1 項前段、第62條前段、第41條第1 項\n    前段，刑法施行法第1 條之1 ，逕以簡易判決處刑如主文。\n五、如不服本件判決，得自收受送達後10日內，向本院提出上訴\n    狀（附繕本），上訴於本院管轄之第二審地方法院合議庭。"
  },
  "search": "臺灣臺南地方法院刑事簡易判決100年度交簡字第602號聲請人臺灣臺南地方法院檢察署檢察官被告鄭竹喜上列被告因過失傷害案件，經檢察官聲請以簡易判決處刑（99年度偵字第18033號），本院判決如下：主文鄭竹喜犯過失傷害罪，處有期徒刑參月，如易科罰金，以新臺幣壹仟元折算壹日。事實及理由一、鄭竹喜於民國99年7月28日晚上7時15分許，駕駛車牌號碼0528－UV號自小客車，沿臺南市○○區○○路1段2巷堤岸道路由南往北方向行駛時，本應注意車前狀況，並隨時採取必要之安全措施，以避免危險之發生，而依當時雖係夜間，惟有照明、路面乾燥無缺陷、無障礙物及視距良好等情形觀之，客觀上並無不能注意之情事，竟疏未注意及此，適有蔡惠珍騎乘車牌號碼366-ENB號普通重型機車自該路對向行駛而來，亦未注意車前狀況，雙方見狀閃避不及，兩車碰撞後，蔡惠珍人車倒地，並受有頭部外傷、顱骨骨折併顱內出血、右側脛骨、腓骨開放性骨折併皮膚壞死及腹部挫傷等傷害。鄭竹喜肇事後，停留於肇事現場等待員警到場處理，並於員警尚不知何人為本件車禍肇事人前，主動表明其為肇事車輛駕駛人，自首而接受裁判。案經蔡惠珍訴由臺南市警察局第三分局報請臺灣臺南地方法院檢察署檢察官偵查後聲請簡易判決處刑。二、前項犯罪事實，有下列事證足資證明：(一)被告於警詢、偵查中所為之自白。(二)告訴人蔡惠珍於警詢、偵查中所為之指訴。(三)臺南市警察局第三分局道路交通事故初步分析研判表1張。(四)財團法人奇美醫院診斷證明書4張。(五)交通事故現場勘驗圖1張。(六)臺南市警察局處理交通事故紀錄表1張。(七)道路交通事故現場圖1張。(八)道路交通事故調查報告表（一）、（二）。(九)現場照片22張。(十)臺南市警察局第三分局道路交通事故肇事人自首情形紀錄表1張。三、核被告所為，係犯刑法第284條第1項前段之過失傷害罪。被告於肇事後，犯罪未被有偵查權之公務員或機關發覺前，立即報警，留在事故現場並當場承認為肇事人，向到場處理之警員自首，坦承犯行進而接受裁判，此有臺南市警察局第三分局道路交通事故肇事人自首情形紀錄表附卷可稽（見警卷第35頁），被告行為合乎自首之要件，爰依刑法第62條規定減輕其刑。爰審酌被告因過失肇事，因而致告訴人受有頭部外傷、顱骨骨折併顱內出血、右側脛骨、腓骨開放性骨折併皮膚壞死及腹部挫傷等傷害，被告之過失程度，暨衡量告訴人未注意車前狀況，亦與有過失，並考量被告尚未賠償告訴人等一切情狀，量處如主文所示之刑，並諭知易科罰金之折算標準，以資儆懲。四、依刑事訴訟法第449條第1項前段、第3項、第454條第1項，刑法第284條第1項前段、第62條前段、第41條第1項前段，刑法施行法第1條之1，逕以簡易判決處刑如主文。五、如不服本件判決，得自收受送達後10日內，向本院提出上訴狀（附繕本），上訴於本院管轄之第二審地方法院合議庭。中華民國100年3月22日刑事第十庭法官羅郁棣以上正本證明與原本無異。書記官黃玉秀中華民國100年3月22日附錄所犯法條：刑法第284條第1項前段因過失傷害人者，處6月以下有期徒刑、拘役或5百元以下罰金，致重傷者，處1年以下有期徒刑、拘役或5百元以下罰金。從事業務之人，因業務上之過失傷害人者，處1年以下有期徒刑、拘役或1千元以下罰金，致重傷者，處3年以下有期徒刑、拘役或2千元以下罰金。",
  "characters": {
    "judges": [
      "羅郁棣"
    ],
    "prosecutors": [

    ],
    "lawyers": [

    ],
    "clerks": [
      "黃玉秀"
    ],
    "plaintiffs": [

    ],
    "defendants": [
      "鄭竹喜"
    ],
    "prosecutor_office": [
      "臺灣臺南地方法院檢察署檢察官"
    ],
    "creditors": [

    ],
    "debtors": [

    ],
    "judicial_associate_officer": [

    ]
  },
  "adjudged_at": "2011-03-22",
  "created_at": "2016-02-13 22:29:48",
  "updated_at": "2016-02-13 22:29:48"
}