{
  "identify": "KSD-93-訴-1519-20041019-1",
  "court": {
    "name": "臺灣高雄地方法院",
    "code": "KSD"
  },
  "division": {
    "name": "刑事",
    "code": "M"
  },
  "year": 93,
  "word": "訴",
  "number": "1519",
  "jcheck": "1",
  "reason": "毒品危害防制條例",
  "content": "臺灣高雄地方法院刑事判決                        九十三年度訴字第一五一九號\n    公  訴  人  臺灣高雄地方法院檢察署檢察官\n    被      告  甲○○\n右列被告因違反毒品危害防制條例案件，經檢察官提起公訴（九十三年度核退毒偵字\n第六○號），及移\n經本院合議庭裁定改依簡式審判程序審理，判決如左：\n    主  文\n甲○○連續施用第一級毒品，累犯，處有期徒刑壹年，扣案之第一級毒品海洛因壹小\n包（淨重零點零捌公克，包裝重零點參公克）沒收銷燬之。\n    事  實\n一、甲○○曾於民國八十九年間，因毒品危害防制條例案件，經法院分別判處有期徒\n    刑一年二月確定，於九十二年七月九日縮刑期滿執行完畢。復因施用毒品案件，\n    經法院裁定送強制戒治，於九十年五月三十日停止戒治付保護管束，而於九十一\n    年九月十八日保護管束期滿，經臺灣高雄地方法院檢察署以九十一年度戒毒偵字\n    第八三九號不起訴處分確定。詎仍不知悔改，明知海洛因業經公告列為毒品危害\n    防制條例第二條第二項第一款之第一級毒品，不得非法持有、施用，竟於距上開\n    強制戒治執行完畢釋放後五年內，基於施用第一級毒品海洛因之概括犯意，自九\n    十三年三月十二日起至同年六月十日十六時許回溯二十四小時內之不詳時間，在\n    高雄市前金區某公共廁所內、高雄市○○區○○路二一巷四號五樓之住處及其他\n    不詳處所等地，以將海洛因摻水置入注射針筒施打於皮膚方式，連續非法施用第\n    一級毒品海洛因多次，約每二到三日即施用一次。嗣甲○○先後（一）於同年三\n    月十七日二十時十五分許，在高雄市○○區○○街與中正路口，為警查獲，並扣\n    得第一級毒品海洛因（淨重零點零八公克），（二）於同年六月十日，在高雄市\n    ○○○路與四維路口旁公園內，為警查獲。\n二、案經高雄市政府警察局苓雅分局報請臺灣高雄地方法院檢察署檢察官偵查起訴及\n    移送併辦。\n    理  由\n一、右開犯罪事實，業據被告甲○○於本院審理時坦承不諱，且被告先後查獲後所採\n    尿液，經分別送請高雄市立凱旋醫院檢驗結果確均呈嗎啡陽性反應，此有該院九\n    十三年三月二十九日、同年六月二十日高市凱醫字第○一七三五、第○一七五八\n    號煙毒尿液檢驗成績書、尿液採證代碼對照表及扣押物品清單各二紙在卷可證。\n    至扣案之毒品一小包，為供被告施用之毒品，業經被告於警詢中供稱無訛，且係\n    經警當場查獲，由臺灣尖端先進生技醫藥股份有限公司制造之煙毒檢驗包試劑初\n    步鑑驗結果，呈嗎啡海洛因反應，有高雄市政府警察局苓雅分局初步鑑驗報告單\n    在卷可按，復經送請法務部調查局鑑定，結果確認係第一級毒品海洛因（淨重零\n    點零八公克、包裝重零點三公克），此有該局鑑定通知書在卷可憑。再被告復因\n    施用毒品案件，經法院裁定送強制戒治後，經停止戒治並付保護管束，而於九十\n    一年一月四日保護管束期滿，而執行完畢，又於五年內再犯本件毒品危害防制條\n    例第十條第一項之罪等情，有臺灣高雄地方法院檢察署刑案資料查註紀錄表、九\n    十一年度戒毒偵字第八三九號不起書處分書及臺灣高等法院被告全國前案紀錄表\n    在卷可參。綜上，本件事證明確，被告犯行，堪以認定，應依法論科。\n二、核被告所為，係犯毒品危害防制條例第十條第一項之施用第一級毒品罪。其施用\n    第一級毒品海洛因前後非法持有第一級毒品海洛因之低度行為，為其施用第一級\n    毒品海洛因之高度行為所吸收，不另論罪。被告先後多次非法施用第一級毒品海\n    洛因之行為，時間緊接，罪名相同，顯係基於概括犯意反覆為之，依連續犯之規\n    定論以一罪，並加重其刑。又被告曾於八十九年間，因違反毒品危害防制條例案\n    ，經法院判處有期徒刑一年二月確定，甫於九十二年七月九日縮刑期滿執行完畢\n    ，有卷附前述之臺灣高等法院被告全國前案紀錄表在卷可按，其受有期徒刑之執\n    行完畢，五年以內再犯本件有期徒刑以上之罪，為累犯，應依法遞加重其刑。公\n    訴人雖僅就被告九十三年三月十二日至同年月十七日期間、及九十三年六月十日\n    十六時回溯二十四小時內一次施用第一級毒品海洛因部分之犯行提起公訴，然檢\n    察官就犯罪事實一部起訴者，效力及於全部，本件被告其餘多次施用第一級毒品\n    海洛因部分之犯行，與前揭論罪科刑部分，有連續犯之裁判上一罪關係，已如前\n    述，本院自應就此部分一併加以裁判。爰審酌被告屢次施用第一級毒品海洛因而\n    觸法，顯見其無悔改之意，意志不堅，一犯再犯，有失政府制定毒品危害防制條\n    例之立法美意，本不宜寬貸，惟念其施用毒品乃自戕一己之身體健康，尚未害及\n    他人，所生危害非大，及犯後態度等一切情狀，量處如主文所示之刑。至扣案之\n    第一級毒品海洛因一小包（淨重零點零八公克、包裝重零點三公克），應依毒品\n    危害防制條例第十八條第一項前段規定，不問屬於犯人與否，沒收銷燬之。\n據上論斷，應依刑事訴訟法第二百七十三條之一第一項、第二百九十九條第一項前段\n，毒品危害防制條例第十條第一項、第十八條第一項前段，刑法第十一條、第五十六\n條、第四十七條，判決如主文。\n本案經檢察官乙○○到庭執行職務。\n中      華      民      國    九十三    年      十      月     十九     日\n                              臺灣高雄地方法院刑事第九庭\n                                  法  官  陳筱蓉\n右正本證明與原本無異。\n如不服本判決，應於判決送達後十日內，向本院提出上訴狀。\n                                  書記官   梁瑜玲\n中    華    民    國      九十三      年      十      月      二十      日\n附錄本案論罪科刑法條：\n毒品危害防制條例第十條\n施用第一級毒品者，處六月以上五年以下有期徒刑。\n施用第二級毒品者，處三年以下有期徒刑。\n",
  "structure": {
    "main": "甲○○連續施用第一級毒品，累犯，處有期徒刑壹年，扣案之第一級毒品海洛因壹小\n包（淨重零點零捌公克，包裝重零點參公克）沒收銷燬之。",
    "fact": "一、甲○○曾於民國八十九年間，因毒品危害防制條例案件，經法院分別判處有期徒\n    刑一年二月確定，於九十二年七月九日縮刑期滿執行完畢。復因施用毒品案件，\n    經法院裁定送強制戒治，於九十年五月三十日停止戒治付保護管束，而於九十一\n    年九月十八日保護管束期滿，經臺灣高雄地方法院檢察署以九十一年度戒毒偵字\n    第八三九號不起訴處分確定。詎仍不知悔改，明知海洛因業經公告列為毒品危害\n    防制條例第二條第二項第一款之第一級毒品，不得非法持有、施用，竟於距上開\n    強制戒治執行完畢釋放後五年內，基於施用第一級毒品海洛因之概括犯意，自九\n    十三年三月十二日起至同年六月十日十六時許回溯二十四小時內之不詳時間，在\n    高雄市前金區某公共廁所內、高雄市○○區○○路二一巷四號五樓之住處及其他\n    不詳處所等地，以將海洛因摻水置入注射針筒施打於皮膚方式，連續非法施用第\n    一級毒品海洛因多次，約每二到三日即施用一次。嗣甲○○先後（一）於同年三\n    月十七日二十時十五分許，在高雄市○○區○○街與中正路口，為警查獲，並扣\n    得第一級毒品海洛因（淨重零點零八公克），（二）於同年六月十日，在高雄市\n    ○○○路與四維路口旁公園內，為警查獲。\n二、案經高雄市政府警察局苓雅分局報請臺灣高雄地方法院檢察署檢察官偵查起訴及\n    移送併辦。",
    "reason": "一、右開犯罪事實，業據被告甲○○於本院審理時坦承不諱，且被告先後查獲後所採\n    尿液，經分別送請高雄市立凱旋醫院檢驗結果確均呈嗎啡陽性反應，此有該院九\n    十三年三月二十九日、同年六月二十日高市凱醫字第○一七三五、第○一七五八\n    號煙毒尿液檢驗成績書、尿液採證代碼對照表及扣押物品清單各二紙在卷可證。\n    至扣案之毒品一小包，為供被告施用之毒品，業經被告於警詢中供稱無訛，且係\n    經警當場查獲，由臺灣尖端先進生技醫藥股份有限公司制造之煙毒檢驗包試劑初\n    步鑑驗結果，呈嗎啡海洛因反應，有高雄市政府警察局苓雅分局初步鑑驗報告單\n    在卷可按，復經送請法務部調查局鑑定，結果確認係第一級毒品海洛因（淨重零\n    點零八公克、包裝重零點三公克），此有該局鑑定通知書在卷可憑。再被告復因\n    施用毒品案件，經法院裁定送強制戒治後，經停止戒治並付保護管束，而於九十\n    一年一月四日保護管束期滿，而執行完畢，又於五年內再犯本件毒品危害防制條\n    例第十條第一項之罪等情，有臺灣高雄地方法院檢察署刑案資料查註紀錄表、九\n    十一年度戒毒偵字第八三九號不起書處分書及臺灣高等法院被告全國前案紀錄表\n    在卷可參。綜上，本件事證明確，被告犯行，堪以認定，應依法論科。\n二、核被告所為，係犯毒品危害防制條例第十條第一項之施用第一級毒品罪。其施用\n    第一級毒品海洛因前後非法持有第一級毒品海洛因之低度行為，為其施用第一級\n    毒品海洛因之高度行為所吸收，不另論罪。被告先後多次非法施用第一級毒品海\n    洛因之行為，時間緊接，罪名相同，顯係基於概括犯意反覆為之，依連續犯之規\n    定論以一罪，並加重其刑。又被告曾於八十九年間，因違反毒品危害防制條例案\n    ，經法院判處有期徒刑一年二月確定，甫於九十二年七月九日縮刑期滿執行完畢\n    ，有卷附前述之臺灣高等法院被告全國前案紀錄表在卷可按，其受有期徒刑之執\n    行完畢，五年以內再犯本件有期徒刑以上之罪，為累犯，應依法遞加重其刑。公\n    訴人雖僅就被告九十三年三月十二日至同年月十七日期間、及九十三年六月十日\n    十六時回溯二十四小時內一次施用第一級毒品海洛因部分之犯行提起公訴，然檢\n    察官就犯罪事實一部起訴者，效力及於全部，本件被告其餘多次施用第一級毒品\n    海洛因部分之犯行，與前揭論罪科刑部分，有連續犯之裁判上一罪關係，已如前\n    述，本院自應就此部分一併加以裁判。爰審酌被告屢次施用第一級毒品海洛因而\n    觸法，顯見其無悔改之意，意志不堅，一犯再犯，有失政府制定毒品危害防制條\n    例之立法美意，本不宜寬貸，惟念其施用毒品乃自戕一己之身體健康，尚未害及\n    他人，所生危害非大，及犯後態度等一切情狀，量處如主文所示之刑。至扣案之\n    第一級毒品海洛因一小包（淨重零點零八公克、包裝重零點三公克），應依毒品\n    危害防制條例第十八條第一項前段規定，不問屬於犯人與否，沒收銷燬之。\n據上論斷，應依刑事訴訟法第二百七十三條之一第一項、第二百九十九條第一項前段\n，毒品危害防制條例第十條第一項、第十八條第一項前段，刑法第十一條、第五十六\n條、第四十七條，判決如主文。\n本案經檢察官乙○○到庭執行職務。\n中      華      民      國    九十三    年      十      月     十九     日\n                              臺灣高雄地方法院刑事第九庭\n                                  法  官  陳筱蓉\n右正本證明與原本無異。\n如不服本判決，應於判決送達後十日內，向本院提出上訴狀。\n                                  書記官   梁瑜玲"
  },
  "search": "臺灣高雄地方法院刑事判決九十三年度訴字第一五一九號公訴人臺灣高雄地方法院檢察署檢察官被告甲○○右列被告因違反毒品危害防制條例案件，經檢察官提起公訴（九十三年度核退毒偵字第六○號），及移經本院合議庭裁定改依簡式審判程序審理，判決如左：主文甲○○連續施用第一級毒品，累犯，處有期徒刑壹年，扣案之第一級毒品海洛因壹小包（淨重零點零捌公克，包裝重零點參公克）沒收銷燬之。事實一、甲○○曾於民國八十九年間，因毒品危害防制條例案件，經法院分別判處有期徒刑一年二月確定，於九十二年七月九日縮刑期滿執行完畢。復因施用毒品案件，經法院裁定送強制戒治，於九十年五月三十日停止戒治付保護管束，而於九十一年九月十八日保護管束期滿，經臺灣高雄地方法院檢察署以九十一年度戒毒偵字第八三九號不起訴處分確定。詎仍不知悔改，明知海洛因業經公告列為毒品危害防制條例第二條第二項第一款之第一級毒品，不得非法持有、施用，竟於距上開強制戒治執行完畢釋放後五年內，基於施用第一級毒品海洛因之概括犯意，自九十三年三月十二日起至同年六月十日十六時許回溯二十四小時內之不詳時間，在高雄市前金區某公共廁所內、高雄市○○區○○路二一巷四號五樓之住處及其他不詳處所等地，以將海洛因摻水置入注射針筒施打於皮膚方式，連續非法施用第一級毒品海洛因多次，約每二到三日即施用一次。嗣甲○○先後（一）於同年三月十七日二十時十五分許，在高雄市○○區○○街與中正路口，為警查獲，並扣得第一級毒品海洛因（淨重零點零八公克），（二）於同年六月十日，在高雄市○○○路與四維路口旁公園內，為警查獲。二、案經高雄市政府警察局苓雅分局報請臺灣高雄地方法院檢察署檢察官偵查起訴及移送併辦。理由一、右開犯罪事實，業據被告甲○○於本院審理時坦承不諱，且被告先後查獲後所採尿液，經分別送請高雄市立凱旋醫院檢驗結果確均呈嗎啡陽性反應，此有該院九十三年三月二十九日、同年六月二十日高市凱醫字第○一七三五、第○一七五八號煙毒尿液檢驗成績書、尿液採證代碼對照表及扣押物品清單各二紙在卷可證。至扣案之毒品一小包，為供被告施用之毒品，業經被告於警詢中供稱無訛，且係經警當場查獲，由臺灣尖端先進生技醫藥股份有限公司制造之煙毒檢驗包試劑初步鑑驗結果，呈嗎啡海洛因反應，有高雄市政府警察局苓雅分局初步鑑驗報告單在卷可按，復經送請法務部調查局鑑定，結果確認係第一級毒品海洛因（淨重零點零八公克、包裝重零點三公克），此有該局鑑定通知書在卷可憑。再被告復因施用毒品案件，經法院裁定送強制戒治後，經停止戒治並付保護管束，而於九十一年一月四日保護管束期滿，而執行完畢，又於五年內再犯本件毒品危害防制條例第十條第一項之罪等情，有臺灣高雄地方法院檢察署刑案資料查註紀錄表、九十一年度戒毒偵字第八三九號不起書處分書及臺灣高等法院被告全國前案紀錄表在卷可參。綜上，本件事證明確，被告犯行，堪以認定，應依法論科。二、核被告所為，係犯毒品危害防制條例第十條第一項之施用第一級毒品罪。其施用第一級毒品海洛因前後非法持有第一級毒品海洛因之低度行為，為其施用第一級毒品海洛因之高度行為所吸收，不另論罪。被告先後多次非法施用第一級毒品海洛因之行為，時間緊接，罪名相同，顯係基於概括犯意反覆為之，依連續犯之規定論以一罪，並加重其刑。又被告曾於八十九年間，因違反毒品危害防制條例案，經法院判處有期徒刑一年二月確定，甫於九十二年七月九日縮刑期滿執行完畢，有卷附前述之臺灣高等法院被告全國前案紀錄表在卷可按，其受有期徒刑之執行完畢，五年以內再犯本件有期徒刑以上之罪，為累犯，應依法遞加重其刑。公訴人雖僅就被告九十三年三月十二日至同年月十七日期間、及九十三年六月十日十六時回溯二十四小時內一次施用第一級毒品海洛因部分之犯行提起公訴，然檢察官就犯罪事實一部起訴者，效力及於全部，本件被告其餘多次施用第一級毒品海洛因部分之犯行，與前揭論罪科刑部分，有連續犯之裁判上一罪關係，已如前述，本院自應就此部分一併加以裁判。爰審酌被告屢次施用第一級毒品海洛因而觸法，顯見其無悔改之意，意志不堅，一犯再犯，有失政府制定毒品危害防制條例之立法美意，本不宜寬貸，惟念其施用毒品乃自戕一己之身體健康，尚未害及他人，所生危害非大，及犯後態度等一切情狀，量處如主文所示之刑。至扣案之第一級毒品海洛因一小包（淨重零點零八公克、包裝重零點三公克），應依毒品危害防制條例第十八條第一項前段規定，不問屬於犯人與否，沒收銷燬之。據上論斷，應依刑事訴訟法第二百七十三條之一第一項、第二百九十九條第一項前段，毒品危害防制條例第十條第一項、第十八條第一項前段，刑法第十一條、第五十六條、第四十七條，判決如主文。本案經檢察官乙○○到庭執行職務。中華民國九十三年十月十九日臺灣高雄地方法院刑事第九庭法官陳筱蓉右正本證明與原本無異。如不服本判決，應於判決送達後十日內，向本院提出上訴狀。書記官梁瑜玲中華民國九十三年十月二十日附錄本案論罪科刑法條：毒品危害防制條例第十條施用第一級毒品者，處六月以上五年以下有期徒刑。施用第二級毒品者，處三年以下有期徒刑。",
  "characters": {
    "judges": [
      "陳筱蓉"
    ],
    "prosecutors": [

    ],
    "lawyers": [

    ],
    "clerks": [
      "梁瑜玲"
    ],
    "plaintiffs": [

    ],
    "defendants": [
      "甲○○",
      "右列被告因違反毒品危害防制條例案件，經檢察官提起公訴（九十三年度核退毒偵字",
      "第六○號），及移",
      "經本院合議庭裁定改依簡式審判程序審理，判決如左："
    ],
    "prosecutor_office": [
      "臺灣高雄地方法院檢察署檢察官"
    ],
    "creditors": [

    ],
    "debtors": [

    ],
    "judicial_associate_officer": [

    ]
  },
  "adjudged_at": "2004-10-19",
  "created_at": "2016-02-06 14:34:21",
  "updated_at": "2016-02-06 14:34:21"
}