{
  "identify": "CHD-100-交簡-1765-20110831-1",
  "court": {
    "name": "臺灣彰化地方法院",
    "code": "CHD"
  },
  "division": {
    "name": "刑事",
    "code": "M"
  },
  "year": 100,
  "word": "交簡",
  "number": "1765",
  "jcheck": "1",
  "reason": "公共危險",
  "content": "臺灣彰化地方法院刑事簡易判決       100年度交簡字第1765號\n聲  請  人  臺灣彰化地方法院檢察署檢察官\n被      告  鄭世傑\n上列被告因公共危險案件，經檢察官聲請以簡易判決處刑（100\n年度速偵字第1582號），本院判決如下：\n    主    文\n鄭世傑服用酒類，不能安全駕駛動力交通工具而駕駛，累犯，處\n罰金新臺幣伍萬元，如易科罰金以新臺幣壹仟元折算壹日。\n    事實及理由\n一、鄭世傑曾於民國96年間，因妨害自由案件，經臺灣南投地方\n    法院以95年度訴字第978號判決判處有期徒刑2月，如易科罰\n    金以銀元3百元折算1日確定，甫於96年11月15日易科罰金執\n    行完畢。詎其仍不知悔改，明知服用酒類或其他相類之物，\n    將使其駕駛車輛時之注意力減低，反應能力趨緩，而危及其\n    他用路人之行車往來安全，自100年8月10日晚上10時許起，\n    迄100年8月11日凌晨0時許止，在其位於彰化縣鹿港鎮○○\n    路70號之居所，飲用保力達酒加啤酒後，已達不能安全駕駛\n    動力交通工具之程度，竟酒後駕駛車牌號碼9655—LN號自用\n    小貨車，自上址出發，欲前往彰濱工業區。嗣於同日凌晨0\n    時30分許，途經彰化縣鹿港鎮○○路與鹿和路路口時，為警\n    攔檢稽查，當場發現其酒氣甚濃，對其施以呼氣式酒精濃度\n    測試，測得其呼氣酒精濃度為每公升0.63毫克，始查悉上情\n    。案經彰化縣警察局鹿港分局報告臺灣彰化地方法院檢察署\n    檢察官偵查並聲請簡易判決處刑。\n二、上揭犯罪事實，業據被告鄭世傑於警詢及偵訊時均坦承不諱\n    ，並有酒精濃度檢測單、刑法第185條之3案件測試觀察紀錄\n    表、汽車駕駛人酒後生理協調平衡檢測記錄表，及彰化縣警\n    察局舉發違反道路交通管理事件通知單各一紙在卷可稽，而\n    所謂不能安全駕駛，並無一定之數值可供界定，係由法院以\n    一般社會通念之客觀標準，足生公共危險時即足。目前行政\n    機關取締酒後駕車之參考標準，係參考美國、德國及日本等\n    國家所進行之酒精濃度與精神狀態之測試實驗，各項實驗均\n    發現凡呼氣中酒精濃度達每公升0.55毫克時，就人之生理方\n    面，已產生視覺反應遲鈍、影像不能集中、同時不能看清前\n    方路況及車旁照後鏡等狀況，及駕駛能力已受有影響、肇事\n    率已為一般人正常人10倍之事實。被告於警方查獲時，測得\n    其呼氣中酒精濃度已逾每公升0.63毫克，依一般社會通念，\n    已達不能安全駕駛之程度。被告服用酒類不能安全駕駛動力\n    交通工具而駕駛之犯行，足堪認定。\n三、核被告所為，係犯刑法第185條之3之服用酒類不能安全駕駛\n    動力交通工具而駕駛罪。又被告曾於96年間，因妨害自由案\n    件，經臺灣南投地方法院以95年度訴字第978號判決判處有\n    期徒刑2月，如易科罰金以銀元3百元折算1日確定，甫於96\n    年11月15日易科罰金執行完畢等情，此有臺灣彰化地方法院\n    檢察署刑案資料查註紀錄表及臺灣高等法院被告前案紀錄表\n    各1份在卷可稽，其於5年內故意再犯本件有期徒刑以上之罪\n    ，為累犯，應依刑法第47條第1項規定，加重其刑。爰審酌\n    被告明知酒精成分對人之意識能力具有不良影響，飲酒後會\n    導致對周遭事務之辨識及反應能力較平常狀況薄弱，且酒後\n    不能駕駛車輛業經政府三申五令宣導，詎仍不知警惕，復在\n    飲酒後已達不能安全駕駛之情況下執意駕駛動力交通工具上\n    路，對一般往來之人車均生高度危險性，更罔顧自己及他人\n    生命、身體、健康、財產安全，惟念其犯後坦承犯行，非無\n    悔意等一切情狀，量處如主文所示之刑，並諭知如易服勞役\n    之折算標準，以資懲儆。\n四、據上論斷，應依刑事訴訟法第449條第1項前段、第454條第1\n    項，刑法第185條之3、第47條第1項、第42條第3項、刑法施\n    行法第1條之1第1項，逕以簡易判決處刑如主文。\n五、如不服本簡易判決，得於簡易判決書送達之日起10日內，以\n    書狀敘述理由，向本院提出上訴（須附繕本）。\n中    華    民    國   100    年    8     月    31    日\n                            交通法庭  法  官  郭玄義\n以上正本證明與原本無異。\n如不服本件判決，得自收受送達之日起10日內，表明上訴理由，\n向本院提起上訴狀（須附繕本）。\n中    華    民    國   100    年    8     月    31    日\n                                      書記官  林婷儀\n【附錄本案論罪科刑法條全文】：\n中華民國刑法第185 條之3\n服用毒品、麻醉藥品、酒類或其他相類之物，不能安全駕駛動力\n交通工具而駕駛者，處1 年以下有期徒刑、拘役或科或併科15萬\n元以下罰金。",
  "structure": {
    "main": "鄭世傑服用酒類，不能安全駕駛動力交通工具而駕駛，累犯，處\n罰金新臺幣伍萬元，如易科罰金以新臺幣壹仟元折算壹日。",
    "fact": "一、鄭世傑曾於民國96年間，因妨害自由案件，經臺灣南投地方\n    法院以95年度訴字第978號判決判處有期徒刑2月，如易科罰\n    金以銀元3百元折算1日確定，甫於96年11月15日易科罰金執\n    行完畢。詎其仍不知悔改，明知服用酒類或其他相類之物，\n    將使其駕駛車輛時之注意力減低，反應能力趨緩，而危及其\n    他用路人之行車往來安全，自100年8月10日晚上10時許起，\n    迄100年8月11日凌晨0時許止，在其位於彰化縣鹿港鎮○○\n    路70號之居所，飲用保力達酒加啤酒後，已達不能安全駕駛\n    動力交通工具之程度，竟酒後駕駛車牌號碼9655—LN號自用\n    小貨車，自上址出發，欲前往彰濱工業區。嗣於同日凌晨0\n    時30分許，途經彰化縣鹿港鎮○○路與鹿和路路口時，為警\n    攔檢稽查，當場發現其酒氣甚濃，對其施以呼氣式酒精濃度\n    測試，測得其呼氣酒精濃度為每公升0.63毫克，始查悉上情\n    。案經彰化縣警察局鹿港分局報告臺灣彰化地方法院檢察署\n    檢察官偵查並聲請簡易判決處刑。\n二、上揭犯罪事實，業據被告鄭世傑於警詢及偵訊時均坦承不諱\n    ，並有酒精濃度檢測單、刑法第185條之3案件測試觀察紀錄\n    表、汽車駕駛人酒後生理協調平衡檢測記錄表，及彰化縣警\n    察局舉發違反道路交通管理事件通知單各一紙在卷可稽，而\n    所謂不能安全駕駛，並無一定之數值可供界定，係由法院以\n    一般社會通念之客觀標準，足生公共危險時即足。目前行政\n    機關取締酒後駕車之參考標準，係參考美國、德國及日本等\n    國家所進行之酒精濃度與精神狀態之測試實驗，各項實驗均\n    發現凡呼氣中酒精濃度達每公升0.55毫克時，就人之生理方\n    面，已產生視覺反應遲鈍、影像不能集中、同時不能看清前\n    方路況及車旁照後鏡等狀況，及駕駛能力已受有影響、肇事\n    率已為一般人正常人10倍之事實。被告於警方查獲時，測得\n    其呼氣中酒精濃度已逾每公升0.63毫克，依一般社會通念，\n    已達不能安全駕駛之程度。被告服用酒類不能安全駕駛動力\n    交通工具而駕駛之犯行，足堪認定。\n三、核被告所為，係犯刑法第185條之3之服用酒類不能安全駕駛\n    動力交通工具而駕駛罪。又被告曾於96年間，因妨害自由案\n    件，經臺灣南投地方法院以95年度訴字第978號判決判處有\n    期徒刑2月，如易科罰金以銀元3百元折算1日確定，甫於96\n    年11月15日易科罰金執行完畢等情，此有臺灣彰化地方法院\n    檢察署刑案資料查註紀錄表及臺灣高等法院被告前案紀錄表\n    各1份在卷可稽，其於5年內故意再犯本件有期徒刑以上之罪\n    ，為累犯，應依刑法第47條第1項規定，加重其刑。爰審酌\n    被告明知酒精成分對人之意識能力具有不良影響，飲酒後會\n    導致對周遭事務之辨識及反應能力較平常狀況薄弱，且酒後\n    不能駕駛車輛業經政府三申五令宣導，詎仍不知警惕，復在\n    飲酒後已達不能安全駕駛之情況下執意駕駛動力交通工具上\n    路，對一般往來之人車均生高度危險性，更罔顧自己及他人\n    生命、身體、健康、財產安全，惟念其犯後坦承犯行，非無\n    悔意等一切情狀，量處如主文所示之刑，並諭知如易服勞役\n    之折算標準，以資懲儆。\n四、據上論斷，應依刑事訴訟法第449條第1項前段、第454條第1\n    項，刑法第185條之3、第47條第1項、第42條第3項、刑法施\n    行法第1條之1第1項，逕以簡易判決處刑如主文。\n五、如不服本簡易判決，得於簡易判決書送達之日起10日內，以\n    書狀敘述理由，向本院提出上訴（須附繕本）。",
    "reason": "一、鄭世傑曾於民國96年間，因妨害自由案件，經臺灣南投地方\n    法院以95年度訴字第978號判決判處有期徒刑2月，如易科罰\n    金以銀元3百元折算1日確定，甫於96年11月15日易科罰金執\n    行完畢。詎其仍不知悔改，明知服用酒類或其他相類之物，\n    將使其駕駛車輛時之注意力減低，反應能力趨緩，而危及其\n    他用路人之行車往來安全，自100年8月10日晚上10時許起，\n    迄100年8月11日凌晨0時許止，在其位於彰化縣鹿港鎮○○\n    路70號之居所，飲用保力達酒加啤酒後，已達不能安全駕駛\n    動力交通工具之程度，竟酒後駕駛車牌號碼9655—LN號自用\n    小貨車，自上址出發，欲前往彰濱工業區。嗣於同日凌晨0\n    時30分許，途經彰化縣鹿港鎮○○路與鹿和路路口時，為警\n    攔檢稽查，當場發現其酒氣甚濃，對其施以呼氣式酒精濃度\n    測試，測得其呼氣酒精濃度為每公升0.63毫克，始查悉上情\n    。案經彰化縣警察局鹿港分局報告臺灣彰化地方法院檢察署\n    檢察官偵查並聲請簡易判決處刑。\n二、上揭犯罪事實，業據被告鄭世傑於警詢及偵訊時均坦承不諱\n    ，並有酒精濃度檢測單、刑法第185條之3案件測試觀察紀錄\n    表、汽車駕駛人酒後生理協調平衡檢測記錄表，及彰化縣警\n    察局舉發違反道路交通管理事件通知單各一紙在卷可稽，而\n    所謂不能安全駕駛，並無一定之數值可供界定，係由法院以\n    一般社會通念之客觀標準，足生公共危險時即足。目前行政\n    機關取締酒後駕車之參考標準，係參考美國、德國及日本等\n    國家所進行之酒精濃度與精神狀態之測試實驗，各項實驗均\n    發現凡呼氣中酒精濃度達每公升0.55毫克時，就人之生理方\n    面，已產生視覺反應遲鈍、影像不能集中、同時不能看清前\n    方路況及車旁照後鏡等狀況，及駕駛能力已受有影響、肇事\n    率已為一般人正常人10倍之事實。被告於警方查獲時，測得\n    其呼氣中酒精濃度已逾每公升0.63毫克，依一般社會通念，\n    已達不能安全駕駛之程度。被告服用酒類不能安全駕駛動力\n    交通工具而駕駛之犯行，足堪認定。\n三、核被告所為，係犯刑法第185條之3之服用酒類不能安全駕駛\n    動力交通工具而駕駛罪。又被告曾於96年間，因妨害自由案\n    件，經臺灣南投地方法院以95年度訴字第978號判決判處有\n    期徒刑2月，如易科罰金以銀元3百元折算1日確定，甫於96\n    年11月15日易科罰金執行完畢等情，此有臺灣彰化地方法院\n    檢察署刑案資料查註紀錄表及臺灣高等法院被告前案紀錄表\n    各1份在卷可稽，其於5年內故意再犯本件有期徒刑以上之罪\n    ，為累犯，應依刑法第47條第1項規定，加重其刑。爰審酌\n    被告明知酒精成分對人之意識能力具有不良影響，飲酒後會\n    導致對周遭事務之辨識及反應能力較平常狀況薄弱，且酒後\n    不能駕駛車輛業經政府三申五令宣導，詎仍不知警惕，復在\n    飲酒後已達不能安全駕駛之情況下執意駕駛動力交通工具上\n    路，對一般往來之人車均生高度危險性，更罔顧自己及他人\n    生命、身體、健康、財產安全，惟念其犯後坦承犯行，非無\n    悔意等一切情狀，量處如主文所示之刑，並諭知如易服勞役\n    之折算標準，以資懲儆。\n四、據上論斷，應依刑事訴訟法第449條第1項前段、第454條第1\n    項，刑法第185條之3、第47條第1項、第42條第3項、刑法施\n    行法第1條之1第1項，逕以簡易判決處刑如主文。\n五、如不服本簡易判決，得於簡易判決書送達之日起10日內，以\n    書狀敘述理由，向本院提出上訴（須附繕本）。"
  },
  "search": "臺灣彰化地方法院刑事簡易判決100年度交簡字第1765號聲請人臺灣彰化地方法院檢察署檢察官被告鄭世傑上列被告因公共危險案件，經檢察官聲請以簡易判決處刑（100年度速偵字第1582號），本院判決如下：主文鄭世傑服用酒類，不能安全駕駛動力交通工具而駕駛，累犯，處罰金新臺幣伍萬元，如易科罰金以新臺幣壹仟元折算壹日。事實及理由一、鄭世傑曾於民國96年間，因妨害自由案件，經臺灣南投地方法院以95年度訴字第978號判決判處有期徒刑2月，如易科罰金以銀元3百元折算1日確定，甫於96年11月15日易科罰金執行完畢。詎其仍不知悔改，明知服用酒類或其他相類之物，將使其駕駛車輛時之注意力減低，反應能力趨緩，而危及其他用路人之行車往來安全，自100年8月10日晚上10時許起，迄100年8月11日凌晨0時許止，在其位於彰化縣鹿港鎮○○路70號之居所，飲用保力達酒加啤酒後，已達不能安全駕駛動力交通工具之程度，竟酒後駕駛車牌號碼9655—LN號自用小貨車，自上址出發，欲前往彰濱工業區。嗣於同日凌晨0時30分許，途經彰化縣鹿港鎮○○路與鹿和路路口時，為警攔檢稽查，當場發現其酒氣甚濃，對其施以呼氣式酒精濃度測試，測得其呼氣酒精濃度為每公升0.63毫克，始查悉上情。案經彰化縣警察局鹿港分局報告臺灣彰化地方法院檢察署檢察官偵查並聲請簡易判決處刑。二、上揭犯罪事實，業據被告鄭世傑於警詢及偵訊時均坦承不諱，並有酒精濃度檢測單、刑法第185條之3案件測試觀察紀錄表、汽車駕駛人酒後生理協調平衡檢測記錄表，及彰化縣警察局舉發違反道路交通管理事件通知單各一紙在卷可稽，而所謂不能安全駕駛，並無一定之數值可供界定，係由法院以一般社會通念之客觀標準，足生公共危險時即足。目前行政機關取締酒後駕車之參考標準，係參考美國、德國及日本等國家所進行之酒精濃度與精神狀態之測試實驗，各項實驗均發現凡呼氣中酒精濃度達每公升0.55毫克時，就人之生理方面，已產生視覺反應遲鈍、影像不能集中、同時不能看清前方路況及車旁照後鏡等狀況，及駕駛能力已受有影響、肇事率已為一般人正常人10倍之事實。被告於警方查獲時，測得其呼氣中酒精濃度已逾每公升0.63毫克，依一般社會通念，已達不能安全駕駛之程度。被告服用酒類不能安全駕駛動力交通工具而駕駛之犯行，足堪認定。三、核被告所為，係犯刑法第185條之3之服用酒類不能安全駕駛動力交通工具而駕駛罪。又被告曾於96年間，因妨害自由案件，經臺灣南投地方法院以95年度訴字第978號判決判處有期徒刑2月，如易科罰金以銀元3百元折算1日確定，甫於96年11月15日易科罰金執行完畢等情，此有臺灣彰化地方法院檢察署刑案資料查註紀錄表及臺灣高等法院被告前案紀錄表各1份在卷可稽，其於5年內故意再犯本件有期徒刑以上之罪，為累犯，應依刑法第47條第1項規定，加重其刑。爰審酌被告明知酒精成分對人之意識能力具有不良影響，飲酒後會導致對周遭事務之辨識及反應能力較平常狀況薄弱，且酒後不能駕駛車輛業經政府三申五令宣導，詎仍不知警惕，復在飲酒後已達不能安全駕駛之情況下執意駕駛動力交通工具上路，對一般往來之人車均生高度危險性，更罔顧自己及他人生命、身體、健康、財產安全，惟念其犯後坦承犯行，非無悔意等一切情狀，量處如主文所示之刑，並諭知如易服勞役之折算標準，以資懲儆。四、據上論斷，應依刑事訴訟法第449條第1項前段、第454條第1項，刑法第185條之3、第47條第1項、第42條第3項、刑法施行法第1條之1第1項，逕以簡易判決處刑如主文。五、如不服本簡易判決，得於簡易判決書送達之日起10日內，以書狀敘述理由，向本院提出上訴（須附繕本）。中華民國100年8月31日交通法庭法官郭玄義以上正本證明與原本無異。如不服本件判決，得自收受送達之日起10日內，表明上訴理由，向本院提起上訴狀（須附繕本）。中華民國100年8月31日書記官林婷儀【附錄本案論罪科刑法條全文】：中華民國刑法第185條之3服用毒品、麻醉藥品、酒類或其他相類之物，不能安全駕駛動力交通工具而駕駛者，處1年以下有期徒刑、拘役或科或併科15萬元以下罰金。",
  "characters": {
    "judges": [
      "郭玄義"
    ],
    "prosecutors": [

    ],
    "lawyers": [

    ],
    "clerks": [
      "林婷儀"
    ],
    "plaintiffs": [

    ],
    "defendants": [
      "鄭世傑"
    ],
    "prosecutor_office": [
      "臺灣彰化地方法院檢察署檢察官"
    ],
    "creditors": [

    ],
    "debtors": [

    ],
    "judicial_associate_officer": [

    ]
  },
  "adjudged_at": "2011-08-31",
  "created_at": "2016-02-12 18:08:42",
  "updated_at": "2016-02-12 18:08:42"
}