{
  "identify": "PCD-100-聲判-104-20110831-1",
  "court": {
    "name": "臺灣新北地方法院",
    "code": "PCD"
  },
  "division": {
    "name": "刑事",
    "code": "M"
  },
  "year": 100,
  "word": "聲判",
  "number": "104",
  "jcheck": "1",
  "reason": "聲請交付審判",
  "content": "臺灣板橋地方法院刑事裁定            100年度聲判字第104號\n聲  請  人  蔡誌哲\n被      告  新莊分局及分駐所莊荿文及家人和親人\n上列聲請人向本院聲請交付審判，本院裁定如下：\n    主  文\n聲請駁回。\n    理  由\n一、按告訴人於接受不起訴、緩起訴處分書後，得於7 日內以書\n    狀敘述不服之理由，經原檢察官向直接上級法院檢察署檢察\n    長或檢察總長聲請再議。告訴人不服上級法院檢察署檢察長\n    或檢察總長認為再議無理由而駁回之處分者，得於接受處分\n    書後10日內委任律師提出理由狀，向該管第一審法院聲請交\n    付審判，刑事訴訟法第256 條第1 項前段、第258 條之1 第\n    1 項分別定有明文。故合於聲請交付審判之對象，乃係曾經\n    上級法院檢察署檢察長或檢察總長駁回再議之不起訴或緩起\n    訴處分，而聲請交付審判之適格當事人，亦當然係指經駁回\n    再議之不起訴或緩起訴處分中之告訴人無疑。又法院認為交\n    付審判之聲請不合法或無理由者，應駁回之，同法第258 條\n    之3 第2 項前段亦規定明確。\n二、經查，本件聲請人於民國100 年8 月19日向本院提出「刑事\n    聲請」狀，聲請意旨載明係依刑事訴訟法（刑事聲請狀誤載\n    為刑法）第258 條之3 相關法條提出聲請，惟聲請人所指情\n    事，查無檢察官所為不起訴或緩起訴處分書之存在，更無駁\n    回再議之處分，顯不存在合於聲請交付審判之對象。又聲請\n    人非屬前經駁回再議之不起訴或緩起訴處分中之告訴人，亦\n    不具聲請交付審判之資格，是揆諸前揭說明，本件交付審判\n    之聲請於法顯有未合，應予駁回。至聲請人如認「莊荿文」\n    等人有犯罪嫌疑，得向司法警察機關或偵查機關提出告發，\n    併此敘明。\n據上論斷，應依刑事訴訟法第258 條之3 第2 項前段，裁定如主\n文。\n中    華    民    國   100    年    8     月    31    日\n                  刑事第十庭  審判長法  官  楊志雄\n                                    法  官  劉景宜\n                                    法  官  陳海寧\n以上正本證明與原本無異。\n不得抗告。\n                                    書記官  馮得弟\n中    華    民    國   100    年    9     月    5     日",
  "structure": {
    "main": "聲請駁回。",
    "reason": "一、按告訴人於接受不起訴、緩起訴處分書後，得於7 日內以書\n    狀敘述不服之理由，經原檢察官向直接上級法院檢察署檢察\n    長或檢察總長聲請再議。告訴人不服上級法院檢察署檢察長\n    或檢察總長認為再議無理由而駁回之處分者，得於接受處分\n    書後10日內委任律師提出理由狀，向該管第一審法院聲請交\n    付審判，刑事訴訟法第256 條第1 項前段、第258 條之1 第\n    1 項分別定有明文。故合於聲請交付審判之對象，乃係曾經\n    上級法院檢察署檢察長或檢察總長駁回再議之不起訴或緩起\n    訴處分，而聲請交付審判之適格當事人，亦當然係指經駁回\n    再議之不起訴或緩起訴處分中之告訴人無疑。又法院認為交\n    付審判之聲請不合法或無理由者，應駁回之，同法第258 條\n    之3 第2 項前段亦規定明確。\n二、經查，本件聲請人於民國100 年8 月19日向本院提出「刑事\n    聲請」狀，聲請意旨載明係依刑事訴訟法（刑事聲請狀誤載\n    為刑法）第258 條之3 相關法條提出聲請，惟聲請人所指情\n    事，查無檢察官所為不起訴或緩起訴處分書之存在，更無駁\n    回再議之處分，顯不存在合於聲請交付審判之對象。又聲請\n    人非屬前經駁回再議之不起訴或緩起訴處分中之告訴人，亦\n    不具聲請交付審判之資格，是揆諸前揭說明，本件交付審判\n    之聲請於法顯有未合，應予駁回。至聲請人如認「莊荿文」\n    等人有犯罪嫌疑，得向司法警察機關或偵查機關提出告發，\n    併此敘明。\n據上論斷，應依刑事訴訟法第258 條之3 第2 項前段，裁定如主\n文。"
  },
  "search": "臺灣板橋地方法院刑事裁定100年度聲判字第104號聲請人蔡誌哲被告新莊分局及分駐所莊荿文及家人和親人上列聲請人向本院聲請交付審判，本院裁定如下：主文聲請駁回。理由一、按告訴人於接受不起訴、緩起訴處分書後，得於7日內以書狀敘述不服之理由，經原檢察官向直接上級法院檢察署檢察長或檢察總長聲請再議。告訴人不服上級法院檢察署檢察長或檢察總長認為再議無理由而駁回之處分者，得於接受處分書後10日內委任律師提出理由狀，向該管第一審法院聲請交付審判，刑事訴訟法第256條第1項前段、第258條之1第1項分別定有明文。故合於聲請交付審判之對象，乃係曾經上級法院檢察署檢察長或檢察總長駁回再議之不起訴或緩起訴處分，而聲請交付審判之適格當事人，亦當然係指經駁回再議之不起訴或緩起訴處分中之告訴人無疑。又法院認為交付審判之聲請不合法或無理由者，應駁回之，同法第258條之3第2項前段亦規定明確。二、經查，本件聲請人於民國100年8月19日向本院提出「刑事聲請」狀，聲請意旨載明係依刑事訴訟法（刑事聲請狀誤載為刑法）第258條之3相關法條提出聲請，惟聲請人所指情事，查無檢察官所為不起訴或緩起訴處分書之存在，更無駁回再議之處分，顯不存在合於聲請交付審判之對象。又聲請人非屬前經駁回再議之不起訴或緩起訴處分中之告訴人，亦不具聲請交付審判之資格，是揆諸前揭說明，本件交付審判之聲請於法顯有未合，應予駁回。至聲請人如認「莊荿文」等人有犯罪嫌疑，得向司法警察機關或偵查機關提出告發，併此敘明。據上論斷，應依刑事訴訟法第258條之3第2項前段，裁定如主文。中華民國100年8月31日刑事第十庭審判長法官楊志雄法官劉景宜法官陳海寧以上正本證明與原本無異。不得抗告。書記官馮得弟中華民國100年9月5日",
  "characters": {
    "judges": [
      "楊志雄",
      "劉景宜",
      "陳海寧"
    ],
    "prosecutors": [

    ],
    "lawyers": [
      "書後10日內委任"
    ],
    "clerks": [
      "馮得弟"
    ],
    "plaintiffs": [

    ],
    "defendants": [
      "新莊分局及分駐所莊荿文及家人和親人"
    ],
    "prosecutor_office": [
      "蔡誌哲"
    ],
    "creditors": [

    ],
    "debtors": [

    ],
    "judicial_associate_officer": [

    ]
  },
  "adjudged_at": "2011-08-31",
  "created_at": "2016-02-12 18:40:29",
  "updated_at": "2016-02-12 18:40:29"
}