{
  "identify": "TPD-100-訴-2463-20110901-1",
  "court": {
    "name": "臺灣臺北地方法院",
    "code": "TPD"
  },
  "division": {
    "name": "民事",
    "code": "V"
  },
  "year": 100,
  "word": "訴",
  "number": "2463",
  "jcheck": "1",
  "reason": "清償借款",
  "content": "臺灣臺北地方法院民事判決             100年度訴字第2463號\n原      告  台新國際商業銀行股份有限公司\n法定代理人  蔡榮棟\n訴訟代理人  黃堯\n            邵士庭\n被      告  徐禮萍\n當事人間請求清償借款事件，經本院於中華民國100 年8 月18日\n言詞辯論終結，判決如下：\n    主      文\n被告應給付原告新台幣壹佰零柒萬肆仟柒佰零壹元，及其中新台\n幣肆拾玖萬玖仟捌佰壹拾陸元部分自民國一百年六月一日起至清\n償日止，按年息百分之二十計算之利息。\n訴訟費用新台幣壹萬壹仟陸佰玖拾貳元由被告負擔。\n    事實及理由\n甲、程序方面：\n一、兩造業於信用貸款約定書第二十三條約定合意以本院為第一\n    審管轄法院，有信用貸款約定書在卷可稽，故本院自有管轄\n    權，合先敘明。\n二、本件被告經合法通知，未於最後言詞辯論期日到場，核無民\n    事訴訟法第三百八十六條所列各款情形，應依原告之聲請，\n    由其一造辯論而為判決。\n乙、得心證之理由：\n一、原告主張：被告於民國92年8 月29日向原告申請現金卡信用\n    貸款，依信用貸款約定書第一條約定，被告得以金融卡提款\n    或轉帳方式動用貸款額度內之現金，另依信用貸款約定書第\n    五條約定，被告應於每月繳款截止日依約繳納每月應還款之\n    金額。詎被告自92年8 月29日核撥貸款起至100 年5 月31日\n    期間止（最後繳款截止日為94年9 月28日），借款尚餘新台\n    幣（下同）1,074,701 元未按期給付（其中本金為499,816\n    元、利息為574,885 元）。依信用貸款約定書第二條約定，\n    利息本按年息18.25%按日固定計算，但因被告未依約繳款，\n    依信用貸款約定書第八條約定，原告得自應付還本日或付息\n    日之翌日起至清償日止，改按年息20% 計算延滯利息。茲被\n    告未於繳款日繳款，依信用貸款約定書第九條第一款約定，\n    被告已喪失期限利益，應立即清償所有未償還之全部款項。\n    屢向被告催討，均置之不理，為此本於現金卡信用貸款契約\n    之法律關係，起訴請求被告返還借款本息等語。並聲明：如\n    主文所示。\n二、被告未於言詞辯論期日到場，亦未提出書狀作何聲明或陳述\n    。\n三、兩造不爭執之事實：\n    本件原告主張如前一所述之事實，已據其提出信用貸款約定\n    書、現金卡申請書、帳務明細、現金卡交易紀錄為證。被告\n    經於相當時期受合法之通知，而於言詞辯論期日不到場，亦\n    未提出準備書狀爭執，依民事訴訟法第二百八十條第三項準\n    用第一項規定，視同對原告主張之前述事實為自認，自堪信\n    原告主張為真實。\n四、從而，原告依現金卡信用貸款契約請求被告給付借款如主文\n    第一項所示，為有理由，應予准許。\n五、訴訟費用之負擔：本件第一審裁判費為11,692元，應由被告\n    負擔，爰確定如主文第二項所載。\n丙、結論：原告之訴為有理由，並依民事訴訟法第三百八十五條\n    第一項前段、第七十八條，判決如主文。\n中    華    民    國   100    年    9     月    1     日\n                  民事第七庭    法  官  賴錦華\n以上正本係照原本作成。\n如對本判決上訴，須於判決送達後20日內向本院提出上訴狀。如\n委任律師提起上訴者，應一併繳納上訴審裁判費。\n中    華    民    國   100    年    9     月    1     日\n                                書記官  沈世儒",
  "structure": {
    "main": "被告應給付原告新台幣壹佰零柒萬肆仟柒佰零壹元，及其中新台\n幣肆拾玖萬玖仟捌佰壹拾陸元部分自民國一百年六月一日起至清\n償日止，按年息百分之二十計算之利息。\n訴訟費用新台幣壹萬壹仟陸佰玖拾貳元由被告負擔。",
    "fact": "甲、程序方面：\n一、兩造業於信用貸款約定書第二十三條約定合意以本院為第一\n    審管轄法院，有信用貸款約定書在卷可稽，故本院自有管轄\n    權，合先敘明。\n二、本件被告經合法通知，未於最後言詞辯論期日到場，核無民\n    事訴訟法第三百八十六條所列各款情形，應依原告之聲請，\n    由其一造辯論而為判決。\n乙、得心證之理由：\n一、原告主張：被告於民國92年8 月29日向原告申請現金卡信用\n    貸款，依信用貸款約定書第一條約定，被告得以金融卡提款\n    或轉帳方式動用貸款額度內之現金，另依信用貸款約定書第\n    五條約定，被告應於每月繳款截止日依約繳納每月應還款之\n    金額。詎被告自92年8 月29日核撥貸款起至100 年5 月31日\n    期間止（最後繳款截止日為94年9 月28日），借款尚餘新台\n    幣（下同）1,074,701 元未按期給付（其中本金為499,816\n    元、利息為574,885 元）。依信用貸款約定書第二條約定，\n    利息本按年息18.25%按日固定計算，但因被告未依約繳款，\n    依信用貸款約定書第八條約定，原告得自應付還本日或付息\n    日之翌日起至清償日止，改按年息20% 計算延滯利息。茲被\n    告未於繳款日繳款，依信用貸款約定書第九條第一款約定，\n    被告已喪失期限利益，應立即清償所有未償還之全部款項。\n    屢向被告催討，均置之不理，為此本於現金卡信用貸款契約\n    之法律關係，起訴請求被告返還借款本息等語。並聲明：如\n    主文所示。\n二、被告未於言詞辯論期日到場，亦未提出書狀作何聲明或陳述\n    。\n三、兩造不爭執之事實：\n    本件原告主張如前一所述之事實，已據其提出信用貸款約定\n    書、現金卡申請書、帳務明細、現金卡交易紀錄為證。被告\n    經於相當時期受合法之通知，而於言詞辯論期日不到場，亦\n    未提出準備書狀爭執，依民事訴訟法第二百八十條第三項準\n    用第一項規定，視同對原告主張之前述事實為自認，自堪信\n    原告主張為真實。\n四、從而，原告依現金卡信用貸款契約請求被告給付借款如主文\n    第一項所示，為有理由，應予准許。\n五、訴訟費用之負擔：本件第一審裁判費為11,692元，應由被告\n    負擔，爰確定如主文第二項所載。\n丙、結論：原告之訴為有理由，並依民事訴訟法第三百八十五條\n    第一項前段、第七十八條，判決如主文。",
    "reason": "甲、程序方面：\n一、兩造業於信用貸款約定書第二十三條約定合意以本院為第一\n    審管轄法院，有信用貸款約定書在卷可稽，故本院自有管轄\n    權，合先敘明。\n二、本件被告經合法通知，未於最後言詞辯論期日到場，核無民\n    事訴訟法第三百八十六條所列各款情形，應依原告之聲請，\n    由其一造辯論而為判決。\n乙、得心證之理由：\n一、原告主張：被告於民國92年8 月29日向原告申請現金卡信用\n    貸款，依信用貸款約定書第一條約定，被告得以金融卡提款\n    或轉帳方式動用貸款額度內之現金，另依信用貸款約定書第\n    五條約定，被告應於每月繳款截止日依約繳納每月應還款之\n    金額。詎被告自92年8 月29日核撥貸款起至100 年5 月31日\n    期間止（最後繳款截止日為94年9 月28日），借款尚餘新台\n    幣（下同）1,074,701 元未按期給付（其中本金為499,816\n    元、利息為574,885 元）。依信用貸款約定書第二條約定，\n    利息本按年息18.25%按日固定計算，但因被告未依約繳款，\n    依信用貸款約定書第八條約定，原告得自應付還本日或付息\n    日之翌日起至清償日止，改按年息20% 計算延滯利息。茲被\n    告未於繳款日繳款，依信用貸款約定書第九條第一款約定，\n    被告已喪失期限利益，應立即清償所有未償還之全部款項。\n    屢向被告催討，均置之不理，為此本於現金卡信用貸款契約\n    之法律關係，起訴請求被告返還借款本息等語。並聲明：如\n    主文所示。\n二、被告未於言詞辯論期日到場，亦未提出書狀作何聲明或陳述\n    。\n三、兩造不爭執之事實：\n    本件原告主張如前一所述之事實，已據其提出信用貸款約定\n    書、現金卡申請書、帳務明細、現金卡交易紀錄為證。被告\n    經於相當時期受合法之通知，而於言詞辯論期日不到場，亦\n    未提出準備書狀爭執，依民事訴訟法第二百八十條第三項準\n    用第一項規定，視同對原告主張之前述事實為自認，自堪信\n    原告主張為真實。\n四、從而，原告依現金卡信用貸款契約請求被告給付借款如主文\n    第一項所示，為有理由，應予准許。\n五、訴訟費用之負擔：本件第一審裁判費為11,692元，應由被告\n    負擔，爰確定如主文第二項所載。\n丙、結論：原告之訴為有理由，並依民事訴訟法第三百八十五條\n    第一項前段、第七十八條，判決如主文。"
  },
  "search": "臺灣臺北地方法院民事判決100年度訴字第2463號原告台新國際商業銀行股份有限公司法定代理人蔡榮棟訴訟代理人黃堯邵士庭被告徐禮萍當事人間請求清償借款事件，經本院於中華民國100年8月18日言詞辯論終結，判決如下：主文被告應給付原告新台幣壹佰零柒萬肆仟柒佰零壹元，及其中新台幣肆拾玖萬玖仟捌佰壹拾陸元部分自民國一百年六月一日起至清償日止，按年息百分之二十計算之利息。訴訟費用新台幣壹萬壹仟陸佰玖拾貳元由被告負擔。事實及理由甲、程序方面：一、兩造業於信用貸款約定書第二十三條約定合意以本院為第一審管轄法院，有信用貸款約定書在卷可稽，故本院自有管轄權，合先敘明。二、本件被告經合法通知，未於最後言詞辯論期日到場，核無民事訴訟法第三百八十六條所列各款情形，應依原告之聲請，由其一造辯論而為判決。乙、得心證之理由：一、原告主張：被告於民國92年8月29日向原告申請現金卡信用貸款，依信用貸款約定書第一條約定，被告得以金融卡提款或轉帳方式動用貸款額度內之現金，另依信用貸款約定書第五條約定，被告應於每月繳款截止日依約繳納每月應還款之金額。詎被告自92年8月29日核撥貸款起至100年5月31日期間止（最後繳款截止日為94年9月28日），借款尚餘新台幣（下同）1,074,701元未按期給付（其中本金為499,816元、利息為574,885元）。依信用貸款約定書第二條約定，利息本按年息18.25%按日固定計算，但因被告未依約繳款，依信用貸款約定書第八條約定，原告得自應付還本日或付息日之翌日起至清償日止，改按年息20%計算延滯利息。茲被告未於繳款日繳款，依信用貸款約定書第九條第一款約定，被告已喪失期限利益，應立即清償所有未償還之全部款項。屢向被告催討，均置之不理，為此本於現金卡信用貸款契約之法律關係，起訴請求被告返還借款本息等語。並聲明：如主文所示。二、被告未於言詞辯論期日到場，亦未提出書狀作何聲明或陳述。三、兩造不爭執之事實：本件原告主張如前一所述之事實，已據其提出信用貸款約定書、現金卡申請書、帳務明細、現金卡交易紀錄為證。被告經於相當時期受合法之通知，而於言詞辯論期日不到場，亦未提出準備書狀爭執，依民事訴訟法第二百八十條第三項準用第一項規定，視同對原告主張之前述事實為自認，自堪信原告主張為真實。四、從而，原告依現金卡信用貸款契約請求被告給付借款如主文第一項所示，為有理由，應予准許。五、訴訟費用之負擔：本件第一審裁判費為11,692元，應由被告負擔，爰確定如主文第二項所載。丙、結論：原告之訴為有理由，並依民事訴訟法第三百八十五條第一項前段、第七十八條，判決如主文。中華民國100年9月1日民事第七庭法官賴錦華以上正本係照原本作成。如對本判決上訴，須於判決送達後20日內向本院提出上訴狀。如委任律師提起上訴者，應一併繳納上訴審裁判費。中華民國100年9月1日書記官沈世儒",
  "characters": {
    "judges": [
      "賴錦華"
    ],
    "prosecutors": [

    ],
    "lawyers": [
      "委任"
    ],
    "clerks": [

    ],
    "plaintiffs": [
      "台新國際商業銀行股份有限公司"
    ],
    "defendants": [
      "徐禮萍",
      "當事人間請求清償借款事件，經本院於中華民國100 年8 月18日",
      "言詞辯論終結，判決如下："
    ],
    "prosecutor_office": [

    ],
    "creditors": [

    ],
    "debtors": [

    ],
    "judicial_associate_officer": [

    ]
  },
  "adjudged_at": "2011-09-01",
  "created_at": "2016-02-12 18:24:11",
  "updated_at": "2016-02-12 18:24:11"
}