{
  "identify": "TPD-100-簡-2831-20110831-1",
  "court": {
    "name": "臺灣臺北地方法院",
    "code": "TPD"
  },
  "division": {
    "name": "刑事",
    "code": "M"
  },
  "year": 100,
  "word": "簡",
  "number": "2831",
  "jcheck": "1",
  "reason": "竊盜",
  "content": "臺灣臺北地方法院刑事簡易判決         100年度簡字第2831號\n聲  請  人  臺灣臺北地方法院檢察署檢察官\n被      告  孫兆麟\n上列被告因竊盜案件，經檢察官聲請以簡易判決處刑（100年度\n偵字第11759號），本院判決如下：\n    主          文\n孫兆麟竊盜，處拘役貳拾日，如易科罰金，以新臺幣壹仟元折算\n壹日。\n    犯罪事實及理由\n一、本件犯罪事實、證據及應適用之法條，均引用檢察官聲請簡\n    易判決處刑書（如附件）之記載。\n二、論罪科刑之理由：\n  (一)核被告孫兆麟所為，係犯刑法第320條第1項之竊盜罪。\n  (二)被告雖陳述其精神狀況不佳，並提出中華民國身心障礙手冊\n    1紙（影本見偵查卷第14頁）。惟本院參酌被告於警詢中就\n    竊盜之細節能詳為描述：本件竊盜罪是臨時起意，且該處為\n    快餐店，故得以直接進入，進去後復見無人在場，遂繞至櫃\n    檯裡面，見到現金紙鈔就隨手拿取，之後即離開現場等語（\n    參見偵查卷第11頁），且此與監視器錄影帶畫面所示亦互核\n    相符。再徵諸被告於竊盜時，明確知悉一般快餐店將所收取\n    之款項置於何處，更趁無人注意之際繞至櫃檯後方竊取。此\n    實已堪認被告於本件竊盜犯行時，並無出現精神障礙或心智\n    缺陷或無法控制其行為之情形，而與常人無異，附此敘明。\n  (三)爰審酌被告因一時貪念，竊取他人所有之金錢，所為不該，\n    兼衡其係徒手竊取，所竊之金錢為新臺幣4千元，被害人王\n    威霖所受損害非鉅，暨考量被告為高中畢業之智識程度，家\n    庭經濟勉持之生活狀況（見警詢筆錄之受詢問人欄），且犯\n    後坦承犯行，犯後態度良好等一切情狀，量處如主文所示之\n    刑，並諭知易科罰金之折算標準，以資懲儆。\n三、依刑事訴訟法第449條第1項前段、第3項、第454條第2項，\n    刑法第320條第1項、第41條第1項前段，刑法施行法第1條之\n    1第1項、第2項前段 ，逕以簡易判決處刑如主文。\n四、如不服本判決，應於判決送達後10日內，向本院提出上訴狀\n    （應附繕本），上訴於本院合議庭。\n中    華    民    國   100    年    8     月    31    日\n                  臺灣臺北地方法院刑事第八庭\n                              法  官  古瑞君\n以上正本證明與原本無異。\n如不服本判決應於判決送達後10日內向本院提出上訴狀，（均須\n按他造當事人之數附繕本）「切勿逕送上級法院」。\n告訴人或被害人如對於本判決不服者，應具備理由請求檢察官上\n訴，其上訴期間之計算係以檢察官收受判決正本之日期為準。\n                              書記官  莊宜諳\n中    華    民    國   100    年    8     月    31    日\n附錄本案論罪科刑法條全文：\n刑法第320條\n意圖為自己或第三人不法之所有，而竊取他人之動產者，為竊盜\n罪，處5  年以下有期徒刑、拘役或 5 百元以下罰金。\n意圖為自己或第三人不法之利益，而竊佔他人之不動產者，依前\n項之規定處斷。\n前二項之未遂犯罰之。\n附件：\n臺灣臺北地方法院檢察署檢察官聲請簡易判決處刑書\n                                    100年度偵字第11759號\n    被      告  孫兆麟  女  48歲（民國○○年○○月○日生）\n                        住臺北市○○區○○街120號2樓\n                        國民身分證統一編號：Ｚ000000000號\n    選任辯護人  孫大龍律師\n上列被告因竊盜案件，業經偵查終結，認為宜以簡易判決處刑，\n茲敘述犯罪事實及證據並所犯法條如下：\n           犯罪事實\n一、孫兆麟前於民國96年間因竊盜案件，經臺灣士林地方法院判\n    處拘役20日、緩刑2 年（非累犯）。詎仍不知警惕，意圖為\n    自己不法之所有，於民國100年4月27日下午17時21分許，在\n    臺北市○○區○○街181號 東園自助餐店內，趁該店負責人\n    王威霖暫離櫃檯而疏於注意之際，徒手開取櫃檯抽屜，竊取\n    店內存放之現金新臺幣4 千元，得手後旋離去逃逸無蹤。嗣\n    經調閱上開店內監視器畫面，始循線悉上情。\n二、案經王威霖訴由臺北市政府警察局萬華分局報告偵辦。\n         證據並所犯法條\n一、上揭犯罪事實，業據被告坦承不諱，核與證人王威霖指述情\n    節相符，並有上開東園自助餐店內所設監視器翻拍畫面照片\n    2張存卷可佐，其犯嫌洵堪認定。\n二、核被告所為，係犯刑法第320條第1項之竊盜罪嫌。\n三、依刑事訴訟法第451條第1項聲請逕以簡易判決處刑。\n    此    致\n臺灣臺北地方法院\n中    華    民    國   100    年    6    月    28    日\n                            檢  察  官  林  禎  瑩\n本件正本證明與原本無異\n中    華    民    國   100    年    7     月    15    日\n                            書  記  官  林  雪  芬\n本件係依刑事訴訟法簡易程序辦理，法院簡易庭得不傳喚被告、\n輔佐人、告訴人、告發人等出庭即以簡易判決處刑；被告、被害\n人、告訴人等對告訴乃論案件如已達成民事和解而要撤回告訴或\n對非告訴乃論案件認有受傳喚到庭陳述意見之必要時，請即另以\n書狀向簡易法庭陳述或請求傳訊。\n附錄本案所犯法條全文\n中華民國刑法第320條\n（普通竊盜罪、竊佔罪）\n意圖為自己或第三人不法之所有，而竊取他人之動產者，為竊盜\n罪，處5  年以下有期徒刑、拘役或 5 百元以下罰金。\n意圖為自己或第三人不法之利益，而竊佔他人之不動產者，依前\n項之規定處斷。\n前二項之未遂犯罰之。",
  "structure": {
    "main": "孫兆麟竊盜，處拘役貳拾日，如易科罰金，以新臺幣壹仟元折算\n壹日。",
    "fact": "一、本件犯罪事實、證據及應適用之法條，均引用檢察官聲請簡\n    易判決處刑書（如附件）之記載。\n二、論罪科刑之理由：\n  (一)核被告孫兆麟所為，係犯刑法第320條第1項之竊盜罪。\n  (二)被告雖陳述其精神狀況不佳，並提出中華民國身心障礙手冊\n    1紙（影本見偵查卷第14頁）。惟本院參酌被告於警詢中就\n    竊盜之細節能詳為描述：本件竊盜罪是臨時起意，且該處為\n    快餐店，故得以直接進入，進去後復見無人在場，遂繞至櫃\n    檯裡面，見到現金紙鈔就隨手拿取，之後即離開現場等語（\n    參見偵查卷第11頁），且此與監視器錄影帶畫面所示亦互核\n    相符。再徵諸被告於竊盜時，明確知悉一般快餐店將所收取\n    之款項置於何處，更趁無人注意之際繞至櫃檯後方竊取。此\n    實已堪認被告於本件竊盜犯行時，並無出現精神障礙或心智\n    缺陷或無法控制其行為之情形，而與常人無異，附此敘明。\n  (三)爰審酌被告因一時貪念，竊取他人所有之金錢，所為不該，\n    兼衡其係徒手竊取，所竊之金錢為新臺幣4千元，被害人王\n    威霖所受損害非鉅，暨考量被告為高中畢業之智識程度，家\n    庭經濟勉持之生活狀況（見警詢筆錄之受詢問人欄），且犯\n    後坦承犯行，犯後態度良好等一切情狀，量處如主文所示之\n    刑，並諭知易科罰金之折算標準，以資懲儆。\n三、依刑事訴訟法第449條第1項前段、第3項、第454條第2項，\n    刑法第320條第1項、第41條第1項前段，刑法施行法第1條之\n    1第1項、第2項前段 ，逕以簡易判決處刑如主文。\n四、如不服本判決，應於判決送達後10日內，向本院提出上訴狀\n    （應附繕本），上訴於本院合議庭。",
    "reason": "一、本件犯罪事實、證據及應適用之法條，均引用檢察官聲請簡\n    易判決處刑書（如附件）之記載。\n二、論罪科刑之理由：\n  (一)核被告孫兆麟所為，係犯刑法第320條第1項之竊盜罪。\n  (二)被告雖陳述其精神狀況不佳，並提出中華民國身心障礙手冊\n    1紙（影本見偵查卷第14頁）。惟本院參酌被告於警詢中就\n    竊盜之細節能詳為描述：本件竊盜罪是臨時起意，且該處為\n    快餐店，故得以直接進入，進去後復見無人在場，遂繞至櫃\n    檯裡面，見到現金紙鈔就隨手拿取，之後即離開現場等語（\n    參見偵查卷第11頁），且此與監視器錄影帶畫面所示亦互核\n    相符。再徵諸被告於竊盜時，明確知悉一般快餐店將所收取\n    之款項置於何處，更趁無人注意之際繞至櫃檯後方竊取。此\n    實已堪認被告於本件竊盜犯行時，並無出現精神障礙或心智\n    缺陷或無法控制其行為之情形，而與常人無異，附此敘明。\n  (三)爰審酌被告因一時貪念，竊取他人所有之金錢，所為不該，\n    兼衡其係徒手竊取，所竊之金錢為新臺幣4千元，被害人王\n    威霖所受損害非鉅，暨考量被告為高中畢業之智識程度，家\n    庭經濟勉持之生活狀況（見警詢筆錄之受詢問人欄），且犯\n    後坦承犯行，犯後態度良好等一切情狀，量處如主文所示之\n    刑，並諭知易科罰金之折算標準，以資懲儆。\n三、依刑事訴訟法第449條第1項前段、第3項、第454條第2項，\n    刑法第320條第1項、第41條第1項前段，刑法施行法第1條之\n    1第1項、第2項前段 ，逕以簡易判決處刑如主文。\n四、如不服本判決，應於判決送達後10日內，向本院提出上訴狀\n    （應附繕本），上訴於本院合議庭。"
  },
  "search": "臺灣臺北地方法院刑事簡易判決100年度簡字第2831號聲請人臺灣臺北地方法院檢察署檢察官被告孫兆麟上列被告因竊盜案件，經檢察官聲請以簡易判決處刑（100年度偵字第11759號），本院判決如下：主文孫兆麟竊盜，處拘役貳拾日，如易科罰金，以新臺幣壹仟元折算壹日。犯罪事實及理由一、本件犯罪事實、證據及應適用之法條，均引用檢察官聲請簡易判決處刑書（如附件）之記載。二、論罪科刑之理由：(一)核被告孫兆麟所為，係犯刑法第320條第1項之竊盜罪。(二)被告雖陳述其精神狀況不佳，並提出中華民國身心障礙手冊1紙（影本見偵查卷第14頁）。惟本院參酌被告於警詢中就竊盜之細節能詳為描述：本件竊盜罪是臨時起意，且該處為快餐店，故得以直接進入，進去後復見無人在場，遂繞至櫃檯裡面，見到現金紙鈔就隨手拿取，之後即離開現場等語（參見偵查卷第11頁），且此與監視器錄影帶畫面所示亦互核相符。再徵諸被告於竊盜時，明確知悉一般快餐店將所收取之款項置於何處，更趁無人注意之際繞至櫃檯後方竊取。此實已堪認被告於本件竊盜犯行時，並無出現精神障礙或心智缺陷或無法控制其行為之情形，而與常人無異，附此敘明。(三)爰審酌被告因一時貪念，竊取他人所有之金錢，所為不該，兼衡其係徒手竊取，所竊之金錢為新臺幣4千元，被害人王威霖所受損害非鉅，暨考量被告為高中畢業之智識程度，家庭經濟勉持之生活狀況（見警詢筆錄之受詢問人欄），且犯後坦承犯行，犯後態度良好等一切情狀，量處如主文所示之刑，並諭知易科罰金之折算標準，以資懲儆。三、依刑事訴訟法第449條第1項前段、第3項、第454條第2項，刑法第320條第1項、第41條第1項前段，刑法施行法第1條之1第1項、第2項前段，逕以簡易判決處刑如主文。四、如不服本判決，應於判決送達後10日內，向本院提出上訴狀（應附繕本），上訴於本院合議庭。中華民國100年8月31日臺灣臺北地方法院刑事第八庭法官古瑞君以上正本證明與原本無異。如不服本判決應於判決送達後10日內向本院提出上訴狀，（均須按他造當事人之數附繕本）「切勿逕送上級法院」。告訴人或被害人如對於本判決不服者，應具備理由請求檢察官上訴，其上訴期間之計算係以檢察官收受判決正本之日期為準。書記官莊宜諳中華民國100年8月31日附錄本案論罪科刑法條全文：刑法第320條意圖為自己或第三人不法之所有，而竊取他人之動產者，為竊盜罪，處5年以下有期徒刑、拘役或5百元以下罰金。意圖為自己或第三人不法之利益，而竊佔他人之不動產者，依前項之規定處斷。前二項之未遂犯罰之。附件：臺灣臺北地方法院檢察署檢察官聲請簡易判決處刑書100年度偵字第11759號被告孫兆麟女48歲（民國○○年○○月○日生）住臺北市○○區○○街120號2樓國民身分證統一編號：Ｚ000000000號選任辯護人孫大龍律師上列被告因竊盜案件，業經偵查終結，認為宜以簡易判決處刑，茲敘述犯罪事實及證據並所犯法條如下：犯罪事實一、孫兆麟前於民國96年間因竊盜案件，經臺灣士林地方法院判處拘役20日、緩刑2年（非累犯）。詎仍不知警惕，意圖為自己不法之所有，於民國100年4月27日下午17時21分許，在臺北市○○區○○街181號東園自助餐店內，趁該店負責人王威霖暫離櫃檯而疏於注意之際，徒手開取櫃檯抽屜，竊取店內存放之現金新臺幣4千元，得手後旋離去逃逸無蹤。嗣經調閱上開店內監視器畫面，始循線悉上情。二、案經王威霖訴由臺北市政府警察局萬華分局報告偵辦。證據並所犯法條一、上揭犯罪事實，業據被告坦承不諱，核與證人王威霖指述情節相符，並有上開東園自助餐店內所設監視器翻拍畫面照片2張存卷可佐，其犯嫌洵堪認定。二、核被告所為，係犯刑法第320條第1項之竊盜罪嫌。三、依刑事訴訟法第451條第1項聲請逕以簡易判決處刑。此致臺灣臺北地方法院中華民國100年6月28日檢察官林禎瑩本件正本證明與原本無異中華民國100年7月15日書記官林雪芬本件係依刑事訴訟法簡易程序辦理，法院簡易庭得不傳喚被告、輔佐人、告訴人、告發人等出庭即以簡易判決處刑；被告、被害人、告訴人等對告訴乃論案件如已達成民事和解而要撤回告訴或對非告訴乃論案件認有受傳喚到庭陳述意見之必要時，請即另以書狀向簡易法庭陳述或請求傳訊。附錄本案所犯法條全文中華民國刑法第320條（普通竊盜罪、竊佔罪）意圖為自己或第三人不法之所有，而竊取他人之動產者，為竊盜罪，處5年以下有期徒刑、拘役或5百元以下罰金。意圖為自己或第三人不法之利益，而竊佔他人之不動產者，依前項之規定處斷。前二項之未遂犯罰之。",
  "characters": {
    "judges": [
      "古瑞君"
    ],
    "prosecutors": [

    ],
    "lawyers": [
      "孫大龍"
    ],
    "clerks": [
      "莊宜諳"
    ],
    "plaintiffs": [

    ],
    "defendants": [
      "孫兆麟",
      "孫兆麟  女  48歲（民國○○年○○月○日生）"
    ],
    "prosecutor_office": [
      "臺灣臺北地方法院檢察署檢察官"
    ],
    "creditors": [

    ],
    "debtors": [

    ],
    "judicial_associate_officer": [

    ]
  },
  "adjudged_at": "2011-08-31",
  "created_at": "2016-02-12 18:19:21",
  "updated_at": "2016-02-12 18:19:21"
}