{
  "identify": "TYD-99-壢簡-2468-20110831-1",
  "court": {
    "name": "臺灣桃園地方法院",
    "code": "TYD"
  },
  "division": {
    "name": "刑事",
    "code": "M"
  },
  "year": 99,
  "word": "壢簡",
  "number": "2468",
  "jcheck": "1",
  "reason": "詐欺",
  "content": "臺灣桃園地方法院刑事簡易判決        99年度壢簡字第2468號\n聲  請  人  臺灣桃園地方法院檢察署檢察官\n被      告  湯玉霞\n上列被告因詐欺案件，經檢察官聲請以簡易判決處刑（99年度偵\n緝字第1539號），本院判決如下：\n    主      文\n湯玉霞共同意圖為自己不法之所有，以詐術使人將本人之物交付\n，處有期徒刑參月，如易科罰金，以新臺幣壹仟元折算壹日。\n    事實及理由\n一、本件犯罪事實及證據，除檢察官聲請簡易判決處刑書犯罪事\n    實欄一文末「而未遂」3 字應刪除；證據部分補充「證人即\n    告訴人白鯉鳳於本院調查中之證述、被告於本院調查中之供\n    述」外，其餘均引用檢察署檢察官聲請簡易判決處刑書之記\n    載（如附件）。\n二、核被告所為，係犯刑法第339 條第1 項之詐欺取財罪。本件\n    詐欺集團成員施用詐術，致被害人陷於錯誤而匯款至指定之\n    帳戶後，因詐騙成員已處於隨時可領取該款項之狀態，對該\n    匯款已有事實之管領力，此時應已成立詐欺取財既遂，縱嗣\n    後帳戶被列為警示帳戶而詐欺集團成員未及提領亦不生影響\n    。被告與真實姓名年籍不詳之成年人綽號「阿貴」、「李凱\n    瀚」等人就上開犯行有犯意聯絡及行為分擔，應論共同正犯\n    。爰審酌被告非但提供其所有之帳戶以利詐騙，又於明知該\n    帳戶列為警示帳戶之情形下，出面為上開詐欺集團之人提領\n    款項，且犯後否認犯行，甚一再狡稱認識被害人云云，態度\n    不佳，又其犯罪情節非輕，併考量其犯罪手段、本件被害人\n    所受之損失及犯罪所造成之危害程度等一切情狀，量處如主\n    文所示之刑，並諭知易科罰金之折算標準，以示懲儆。至本\n    件被告所有用以詐騙被害人之帳戶提款卡等物，並未扣案而\n    查無證據可證明現仍存在未滅失，爰不予宣告沒收，附此敘\n    明。\n三、據上論斷，應依刑事訴訟法第449 條第1 項前段、第454 條\n    第2 項，刑法第28條、第339 條第1 項、第41條第1 項前段\n    ，刑法施行法第1 條之1 第1 項、第2 項前段，逕以簡易判\n    決處刑如主文。\n四、如不服本判決，應於判決送達後10日內，向本院提出上訴狀\n    （應附繕本），上訴於本院合議庭。\n中    華    民    國    100     年    8     月  31    日\n                              刑事第二庭  法  官  李麗珍\n以上正本證明與原本無異。\n如不服本判決，得於判決書送達之翌日起10日內，以書狀敘述理\n由，向本庭提出上訴（應附繕本）。\n                                          書記官  李靜華\n中    華    民    國   100    年    9     月  5     日\n附錄論罪科刑法條:\n刑法第339條第1項\n意圖為自己或第三人不法之所有，以詐術使人將本人或第三人之\n物交付者，處 5 年以下有期徒刑、拘役或科或併科 1 千元以下\n罰金。",
  "structure": {
    "main": "湯玉霞共同意圖為自己不法之所有，以詐術使人將本人之物交付\n，處有期徒刑參月，如易科罰金，以新臺幣壹仟元折算壹日。",
    "fact": "一、本件犯罪事實及證據，除檢察官聲請簡易判決處刑書犯罪事\n    實欄一文末「而未遂」3 字應刪除；證據部分補充「證人即\n    告訴人白鯉鳳於本院調查中之證述、被告於本院調查中之供\n    述」外，其餘均引用檢察署檢察官聲請簡易判決處刑書之記\n    載（如附件）。\n二、核被告所為，係犯刑法第339 條第1 項之詐欺取財罪。本件\n    詐欺集團成員施用詐術，致被害人陷於錯誤而匯款至指定之\n    帳戶後，因詐騙成員已處於隨時可領取該款項之狀態，對該\n    匯款已有事實之管領力，此時應已成立詐欺取財既遂，縱嗣\n    後帳戶被列為警示帳戶而詐欺集團成員未及提領亦不生影響\n    。被告與真實姓名年籍不詳之成年人綽號「阿貴」、「李凱\n    瀚」等人就上開犯行有犯意聯絡及行為分擔，應論共同正犯\n    。爰審酌被告非但提供其所有之帳戶以利詐騙，又於明知該\n    帳戶列為警示帳戶之情形下，出面為上開詐欺集團之人提領\n    款項，且犯後否認犯行，甚一再狡稱認識被害人云云，態度\n    不佳，又其犯罪情節非輕，併考量其犯罪手段、本件被害人\n    所受之損失及犯罪所造成之危害程度等一切情狀，量處如主\n    文所示之刑，並諭知易科罰金之折算標準，以示懲儆。至本\n    件被告所有用以詐騙被害人之帳戶提款卡等物，並未扣案而\n    查無證據可證明現仍存在未滅失，爰不予宣告沒收，附此敘\n    明。\n三、據上論斷，應依刑事訴訟法第449 條第1 項前段、第454 條\n    第2 項，刑法第28條、第339 條第1 項、第41條第1 項前段\n    ，刑法施行法第1 條之1 第1 項、第2 項前段，逕以簡易判\n    決處刑如主文。\n四、如不服本判決，應於判決送達後10日內，向本院提出上訴狀\n    （應附繕本），上訴於本院合議庭。",
    "reason": "一、本件犯罪事實及證據，除檢察官聲請簡易判決處刑書犯罪事\n    實欄一文末「而未遂」3 字應刪除；證據部分補充「證人即\n    告訴人白鯉鳳於本院調查中之證述、被告於本院調查中之供\n    述」外，其餘均引用檢察署檢察官聲請簡易判決處刑書之記\n    載（如附件）。\n二、核被告所為，係犯刑法第339 條第1 項之詐欺取財罪。本件\n    詐欺集團成員施用詐術，致被害人陷於錯誤而匯款至指定之\n    帳戶後，因詐騙成員已處於隨時可領取該款項之狀態，對該\n    匯款已有事實之管領力，此時應已成立詐欺取財既遂，縱嗣\n    後帳戶被列為警示帳戶而詐欺集團成員未及提領亦不生影響\n    。被告與真實姓名年籍不詳之成年人綽號「阿貴」、「李凱\n    瀚」等人就上開犯行有犯意聯絡及行為分擔，應論共同正犯\n    。爰審酌被告非但提供其所有之帳戶以利詐騙，又於明知該\n    帳戶列為警示帳戶之情形下，出面為上開詐欺集團之人提領\n    款項，且犯後否認犯行，甚一再狡稱認識被害人云云，態度\n    不佳，又其犯罪情節非輕，併考量其犯罪手段、本件被害人\n    所受之損失及犯罪所造成之危害程度等一切情狀，量處如主\n    文所示之刑，並諭知易科罰金之折算標準，以示懲儆。至本\n    件被告所有用以詐騙被害人之帳戶提款卡等物，並未扣案而\n    查無證據可證明現仍存在未滅失，爰不予宣告沒收，附此敘\n    明。\n三、據上論斷，應依刑事訴訟法第449 條第1 項前段、第454 條\n    第2 項，刑法第28條、第339 條第1 項、第41條第1 項前段\n    ，刑法施行法第1 條之1 第1 項、第2 項前段，逕以簡易判\n    決處刑如主文。\n四、如不服本判決，應於判決送達後10日內，向本院提出上訴狀\n    （應附繕本），上訴於本院合議庭。"
  },
  "search": "臺灣桃園地方法院刑事簡易判決99年度壢簡字第2468號聲請人臺灣桃園地方法院檢察署檢察官被告湯玉霞上列被告因詐欺案件，經檢察官聲請以簡易判決處刑（99年度偵緝字第1539號），本院判決如下：主文湯玉霞共同意圖為自己不法之所有，以詐術使人將本人之物交付，處有期徒刑參月，如易科罰金，以新臺幣壹仟元折算壹日。事實及理由一、本件犯罪事實及證據，除檢察官聲請簡易判決處刑書犯罪事實欄一文末「而未遂」3字應刪除；證據部分補充「證人即告訴人白鯉鳳於本院調查中之證述、被告於本院調查中之供述」外，其餘均引用檢察署檢察官聲請簡易判決處刑書之記載（如附件）。二、核被告所為，係犯刑法第339條第1項之詐欺取財罪。本件詐欺集團成員施用詐術，致被害人陷於錯誤而匯款至指定之帳戶後，因詐騙成員已處於隨時可領取該款項之狀態，對該匯款已有事實之管領力，此時應已成立詐欺取財既遂，縱嗣後帳戶被列為警示帳戶而詐欺集團成員未及提領亦不生影響。被告與真實姓名年籍不詳之成年人綽號「阿貴」、「李凱瀚」等人就上開犯行有犯意聯絡及行為分擔，應論共同正犯。爰審酌被告非但提供其所有之帳戶以利詐騙，又於明知該帳戶列為警示帳戶之情形下，出面為上開詐欺集團之人提領款項，且犯後否認犯行，甚一再狡稱認識被害人云云，態度不佳，又其犯罪情節非輕，併考量其犯罪手段、本件被害人所受之損失及犯罪所造成之危害程度等一切情狀，量處如主文所示之刑，並諭知易科罰金之折算標準，以示懲儆。至本件被告所有用以詐騙被害人之帳戶提款卡等物，並未扣案而查無證據可證明現仍存在未滅失，爰不予宣告沒收，附此敘明。三、據上論斷，應依刑事訴訟法第449條第1項前段、第454條第2項，刑法第28條、第339條第1項、第41條第1項前段，刑法施行法第1條之1第1項、第2項前段，逕以簡易判決處刑如主文。四、如不服本判決，應於判決送達後10日內，向本院提出上訴狀（應附繕本），上訴於本院合議庭。中華民國100年8月31日刑事第二庭法官李麗珍以上正本證明與原本無異。如不服本判決，得於判決書送達之翌日起10日內，以書狀敘述理由，向本庭提出上訴（應附繕本）。書記官李靜華中華民國100年9月5日附錄論罪科刑法條:刑法第339條第1項意圖為自己或第三人不法之所有，以詐術使人將本人或第三人之物交付者，處5年以下有期徒刑、拘役或科或併科1千元以下罰金。",
  "characters": {
    "judges": [
      "李麗珍"
    ],
    "prosecutors": [

    ],
    "lawyers": [

    ],
    "clerks": [
      "李靜華"
    ],
    "plaintiffs": [

    ],
    "defendants": [
      "湯玉霞"
    ],
    "prosecutor_office": [
      "臺灣桃園地方法院檢察署檢察官"
    ],
    "creditors": [

    ],
    "debtors": [

    ],
    "judicial_associate_officer": [

    ]
  },
  "adjudged_at": "2011-08-31",
  "created_at": "2016-02-12 18:26:35",
  "updated_at": "2016-02-12 18:26:35"
}