{
  "identify": "KSD-100-聲-1797-20110427-1",
  "court": {
    "name": "臺灣高雄地方法院",
    "code": "KSD"
  },
  "division": {
    "name": "刑事",
    "code": "M"
  },
  "year": 100,
  "word": "聲",
  "number": "1797",
  "jcheck": "1",
  "reason": "聲請具保停止羈押",
  "content": "臺灣高雄地方法院刑事裁定             100年度聲字第1797號\n公  訴  人  臺灣高雄地方法院檢察署檢察官\n被      告  林明賢\n聲請人  即\n選任辯護人  王仁聰律師\n            蔡桓文律師\n上列聲請人因被告所犯恐嚇取財等案件，聲請具保停止羈押，本\n院裁定如下：\n    主  文\n聲請駁回。\n    理  由\n一、聲請人即被告林明賢之辯護人聲請意旨略以：被告已坦承全\n    部犯行，而被告育有分別就讀大學二年級及高中一年級之2\n    名子女，因被告之行為大幅影響2 名子女之心情，被告之配\n    偶亦與被告離婚，原本和樂之家庭因被告行為大受影響，甚\n    導致同事及其家人陷於恐懼，被告對己身行為後悔莫及，已\n    深切悔悟，並有服刑之心理準備，然請求准予被告具保，使\n    被告有機會親自與家人溝通、說明所犯罪行，讓被告之家人\n    坦然面對，並使被告於判決確定後能安心服刑。據此，聲請\n    具保停止羈押等語。\n二、按被告及得為其輔佐人之人或辯護人，得隨時具保，向法院\n    聲請停止羈押，刑事訴訟法第110 條第1 項定有明文。次按\n    被告經法官訊問後，認為犯刑法第305 條之恐嚇罪、第346\n    條恐嚇取財罪，其嫌疑重大，有事實足認為有反覆實施同一\n    犯罪之虞，而有羈押之必要者，得羈押之，刑事訴訟法第10\n    1 條之1 第1 項第4 款、第8 款亦可參照。而羈押乃確定判\n    決前之拘禁處分，與有罪判決後之徒刑執行固有不同，但在\n    法律所定要件下，仍得羈押被告，以保全被告使刑事訴訟程\n    序得以順利進行、保全證據、確保嗣後刑罰權之執行、或俾\n    免危險繼續擴大發生，藉以維護社會秩序。是法院關於羈押\n    與否之審查，其目的僅在判斷有無實施羈押強制處分之必要\n    ，並非認定被告有無犯罪之實體審判程序，故關於羈押之要\n    件，無須經嚴格之證明，而以經釋明得以自由證明為已足，\n    至於被告是否成立犯罪，乃本案實體上應予判斷之問題，執\n    行羈押後有無繼續之必要，仍許由法院就具體個案，依職權\n    斟酌訴訟進行程度及其他一切情事而為認定。\n三、經查，被告前因恐嚇、恐嚇取財等案件，經本院訊問後，認\n    其涉犯刑法第305 條恐嚇罪、第346 條第1 項恐嚇取財罪，\n    嫌疑重大，並有事實足認有反覆實施同一犯罪之虞，有羈押\n    必要，爰依刑事訴訟法第101 條之1 第1 項第4 款、第8 款\n    規定，於民國100 年4 月1 日裁定執行羈押。次查，本件甫\n    經起訴，尚待本院進行調查、審理，且審酌被告被訴自98年\n    7 月間某日起至99年11月18日止，長期騷擾、恐嚇其先前任\n    職公司之同事，並曾2 度恐嚇該公司負責人交付鉅額款項，\n    且於98年8 月10日因此得手新臺幣1,200 萬元後，仍未罷手\n    ，恐嚇之對象多達5 人，甚至包含該公司同事之家人，有本\n    案卷證可參，足認被告有反覆實施同一犯罪之虞，為保全被\n    告得以進行審判程序，並預防其於本院審理期間再犯，以維\n    護社會安全，認原羈押原因及必要性均仍存在，不能因具保\n    而使之消滅。\n四、聲請人固以上開理由聲請准予被告具保停止羈押，惟本院係\n    依刑事訴訟法第101 條之1 第1 項第4 款、第8 款有事實足\n    認有反覆實施恐嚇、恐嚇取財罪嫌之規定，裁定羈押被告，\n    則被告是否坦承犯行乙節，核與本件羈押原因是否消滅無涉\n    。至聲請人所指被告之家庭因素等狀況，並非本院准否具保\n    停止羈押之應行審酌事項。此外，上開聲請意旨核均與刑事\n    訴訟法第114 條所定各款事由不相符合。綜上，聲請人以前\n    開事由聲請准予被告具保，於法無據，本件具保停止羈押之\n    聲請，難以准許，應予駁回。\n五、爰依刑事訴訟法第220 條，裁定如主文。\n中    華    民    國   100    年    4     月    27    日\n                  刑事第十七庭  審判長法  官  陳培維\n                                      法  官  余銘軒\n                                      法  官  毛妍懿\n以上正本證明與原本無異。\n如不服本裁定，應於收受送達後5 日內向本院提出抗告狀。\n中    華    民    國   100    年    5     月    2     日\n                                      書記官  林晏光",
  "structure": {
    "main": "聲請駁回。",
    "reason": "一、聲請人即被告林明賢之辯護人聲請意旨略以：被告已坦承全\n    部犯行，而被告育有分別就讀大學二年級及高中一年級之2\n    名子女，因被告之行為大幅影響2 名子女之心情，被告之配\n    偶亦與被告離婚，原本和樂之家庭因被告行為大受影響，甚\n    導致同事及其家人陷於恐懼，被告對己身行為後悔莫及，已\n    深切悔悟，並有服刑之心理準備，然請求准予被告具保，使\n    被告有機會親自與家人溝通、說明所犯罪行，讓被告之家人\n    坦然面對，並使被告於判決確定後能安心服刑。據此，聲請\n    具保停止羈押等語。\n二、按被告及得為其輔佐人之人或辯護人，得隨時具保，向法院\n    聲請停止羈押，刑事訴訟法第110 條第1 項定有明文。次按\n    被告經法官訊問後，認為犯刑法第305 條之恐嚇罪、第346\n    條恐嚇取財罪，其嫌疑重大，有事實足認為有反覆實施同一\n    犯罪之虞，而有羈押之必要者，得羈押之，刑事訴訟法第10\n    1 條之1 第1 項第4 款、第8 款亦可參照。而羈押乃確定判\n    決前之拘禁處分，與有罪判決後之徒刑執行固有不同，但在\n    法律所定要件下，仍得羈押被告，以保全被告使刑事訴訟程\n    序得以順利進行、保全證據、確保嗣後刑罰權之執行、或俾\n    免危險繼續擴大發生，藉以維護社會秩序。是法院關於羈押\n    與否之審查，其目的僅在判斷有無實施羈押強制處分之必要\n    ，並非認定被告有無犯罪之實體審判程序，故關於羈押之要\n    件，無須經嚴格之證明，而以經釋明得以自由證明為已足，\n    至於被告是否成立犯罪，乃本案實體上應予判斷之問題，執\n    行羈押後有無繼續之必要，仍許由法院就具體個案，依職權\n    斟酌訴訟進行程度及其他一切情事而為認定。\n三、經查，被告前因恐嚇、恐嚇取財等案件，經本院訊問後，認\n    其涉犯刑法第305 條恐嚇罪、第346 條第1 項恐嚇取財罪，\n    嫌疑重大，並有事實足認有反覆實施同一犯罪之虞，有羈押\n    必要，爰依刑事訴訟法第101 條之1 第1 項第4 款、第8 款\n    規定，於民國100 年4 月1 日裁定執行羈押。次查，本件甫\n    經起訴，尚待本院進行調查、審理，且審酌被告被訴自98年\n    7 月間某日起至99年11月18日止，長期騷擾、恐嚇其先前任\n    職公司之同事，並曾2 度恐嚇該公司負責人交付鉅額款項，\n    且於98年8 月10日因此得手新臺幣1,200 萬元後，仍未罷手\n    ，恐嚇之對象多達5 人，甚至包含該公司同事之家人，有本\n    案卷證可參，足認被告有反覆實施同一犯罪之虞，為保全被\n    告得以進行審判程序，並預防其於本院審理期間再犯，以維\n    護社會安全，認原羈押原因及必要性均仍存在，不能因具保\n    而使之消滅。\n四、聲請人固以上開理由聲請准予被告具保停止羈押，惟本院係\n    依刑事訴訟法第101 條之1 第1 項第4 款、第8 款有事實足\n    認有反覆實施恐嚇、恐嚇取財罪嫌之規定，裁定羈押被告，\n    則被告是否坦承犯行乙節，核與本件羈押原因是否消滅無涉\n    。至聲請人所指被告之家庭因素等狀況，並非本院准否具保\n    停止羈押之應行審酌事項。此外，上開聲請意旨核均與刑事\n    訴訟法第114 條所定各款事由不相符合。綜上，聲請人以前\n    開事由聲請准予被告具保，於法無據，本件具保停止羈押之\n    聲請，難以准許，應予駁回。\n五、爰依刑事訴訟法第220 條，裁定如主文。"
  },
  "search": "臺灣高雄地方法院刑事裁定100年度聲字第1797號公訴人臺灣高雄地方法院檢察署檢察官被告林明賢聲請人即選任辯護人王仁聰律師蔡桓文律師上列聲請人因被告所犯恐嚇取財等案件，聲請具保停止羈押，本院裁定如下：主文聲請駁回。理由一、聲請人即被告林明賢之辯護人聲請意旨略以：被告已坦承全部犯行，而被告育有分別就讀大學二年級及高中一年級之2名子女，因被告之行為大幅影響2名子女之心情，被告之配偶亦與被告離婚，原本和樂之家庭因被告行為大受影響，甚導致同事及其家人陷於恐懼，被告對己身行為後悔莫及，已深切悔悟，並有服刑之心理準備，然請求准予被告具保，使被告有機會親自與家人溝通、說明所犯罪行，讓被告之家人坦然面對，並使被告於判決確定後能安心服刑。據此，聲請具保停止羈押等語。二、按被告及得為其輔佐人之人或辯護人，得隨時具保，向法院聲請停止羈押，刑事訴訟法第110條第1項定有明文。次按被告經法官訊問後，認為犯刑法第305條之恐嚇罪、第346條恐嚇取財罪，其嫌疑重大，有事實足認為有反覆實施同一犯罪之虞，而有羈押之必要者，得羈押之，刑事訴訟法第101條之1第1項第4款、第8款亦可參照。而羈押乃確定判決前之拘禁處分，與有罪判決後之徒刑執行固有不同，但在法律所定要件下，仍得羈押被告，以保全被告使刑事訴訟程序得以順利進行、保全證據、確保嗣後刑罰權之執行、或俾免危險繼續擴大發生，藉以維護社會秩序。是法院關於羈押與否之審查，其目的僅在判斷有無實施羈押強制處分之必要，並非認定被告有無犯罪之實體審判程序，故關於羈押之要件，無須經嚴格之證明，而以經釋明得以自由證明為已足，至於被告是否成立犯罪，乃本案實體上應予判斷之問題，執行羈押後有無繼續之必要，仍許由法院就具體個案，依職權斟酌訴訟進行程度及其他一切情事而為認定。三、經查，被告前因恐嚇、恐嚇取財等案件，經本院訊問後，認其涉犯刑法第305條恐嚇罪、第346條第1項恐嚇取財罪，嫌疑重大，並有事實足認有反覆實施同一犯罪之虞，有羈押必要，爰依刑事訴訟法第101條之1第1項第4款、第8款規定，於民國100年4月1日裁定執行羈押。次查，本件甫經起訴，尚待本院進行調查、審理，且審酌被告被訴自98年7月間某日起至99年11月18日止，長期騷擾、恐嚇其先前任職公司之同事，並曾2度恐嚇該公司負責人交付鉅額款項，且於98年8月10日因此得手新臺幣1,200萬元後，仍未罷手，恐嚇之對象多達5人，甚至包含該公司同事之家人，有本案卷證可參，足認被告有反覆實施同一犯罪之虞，為保全被告得以進行審判程序，並預防其於本院審理期間再犯，以維護社會安全，認原羈押原因及必要性均仍存在，不能因具保而使之消滅。四、聲請人固以上開理由聲請准予被告具保停止羈押，惟本院係依刑事訴訟法第101條之1第1項第4款、第8款有事實足認有反覆實施恐嚇、恐嚇取財罪嫌之規定，裁定羈押被告，則被告是否坦承犯行乙節，核與本件羈押原因是否消滅無涉。至聲請人所指被告之家庭因素等狀況，並非本院准否具保停止羈押之應行審酌事項。此外，上開聲請意旨核均與刑事訴訟法第114條所定各款事由不相符合。綜上，聲請人以前開事由聲請准予被告具保，於法無據，本件具保停止羈押之聲請，難以准許，應予駁回。五、爰依刑事訴訟法第220條，裁定如主文。中華民國100年4月27日刑事第十七庭審判長法官陳培維法官余銘軒法官毛妍懿以上正本證明與原本無異。如不服本裁定，應於收受送達後5日內向本院提出抗告狀。中華民國100年5月2日書記官林晏光",
  "characters": {
    "judges": [
      "陳培維",
      "余銘軒",
      "毛妍懿"
    ],
    "prosecutors": [

    ],
    "lawyers": [
      "王仁聰",
      "蔡桓文"
    ],
    "clerks": [

    ],
    "plaintiffs": [

    ],
    "defendants": [
      "林明賢",
      "聲請人  即"
    ],
    "prosecutor_office": [
      "臺灣高雄地方法院檢察署檢察官"
    ],
    "creditors": [

    ],
    "debtors": [

    ],
    "judicial_associate_officer": [

    ]
  },
  "adjudged_at": "2011-04-27",
  "created_at": "2016-02-12 09:24:02",
  "updated_at": "2016-02-12 09:24:02"
}