{
  "identify": "TPD-100-簡-1126-20110428-1",
  "court": {
    "name": "臺灣臺北地方法院",
    "code": "TPD"
  },
  "division": {
    "name": "刑事",
    "code": "M"
  },
  "year": 100,
  "word": "簡",
  "number": "1126",
  "jcheck": "1",
  "reason": "違反公司法等",
  "content": "臺灣臺北地方法院刑事簡易判決         100年度簡字第1126號\n聲  請  人  臺灣臺北地方法院檢察署檢察官\n被      告  謝承芳\n上列被告因違反公司法等案件，經檢察官聲請簡易判決處刑（99\n年度偵字第22613 號），本院判決如下：\n主  文\n謝承芳共同公司負責人，公司應收之股款，股東並未實際繳納，\n而以申請文件表明收足，處有期徒刑肆月，如易科罰金，以新臺\n幣壹仟元折算壹日；減為有期徒刑貳月，如易科罰金，以新臺幣\n壹仟元折算壹日。\n    事實及理由\n一、謝承芳係百騏工程有限公司（下稱百騏公司）負責人，於民\n    國95年12月間，委託記帳業者張秀禎（業經檢察官另案起訴\n    ）辦理百騏公司資本額新臺幣（下同）1,000 萬元之增資登\n    記，其明知辦理增資之上開公司股東並未實際繳納股款，竟\n    與張秀禎、洪英哲基於以申請文件表明收足股東未實際繳納\n    之應收股款、以不正當方法致使財務報表發生不實結果、使\n    公務員登載不實之犯意聯絡，透過張秀禎向「英哲企管顧問\n    社」之洪英哲（業經另案起訴）短期借款作為驗資之資金證\n    明，由謝承芳將百麒工程公司之基本資料交付予張秀禎，再\n    依指示至合作金庫銀行敦化分行（址設臺北市松山區○○○\n    路○ 段88號），開設百騏公司之活期存款帳戶，張秀禎將開\n    立之存摺轉交「英哲企管顧問社」洪英哲，由洪英哲於95年\n    12月20日，辦理資金轉帳手續，自洪英哲自所使用之帳戶提\n    出現金後，再以謝承芳名義轉帳1,000 萬元存入百騏公司帳\n    戶後，旋將存摺帶回影印，作為股款業經股東繳納之存款證\n    明，並製作不實之百騏公司存款1,000 萬元之股東繳納股款\n    明細表、資產負債表及公司增資登記資本額查核報告書，嗣\n    於各項會計報表上蓋用代刻之公司及負責人印章，將資本額\n    查核報告書工作底稿交給不知情之會計師姚維世簽章，完成\n    公司法第7 條授權會計師查核簽證資本額之作業，旋於95年\n    12月22日將上開存入百騏公司帳戶之1,000 萬元資金轉出至\n    洪英哲所使用之帳戶內，而未用於百騏公司之經營。嗣後謝\n    承芳委由張秀禎填載公司增資登記申請書，並以上開存摺影\n    本、資產負債表及公司增資登記資本額查核報告書等申請文\n    件，表明百騏公司應收股款均已收足，向主管機關經濟部中\n    部辦公室申請增資登記，使該管承辦公務員審查認為形式要\n    件均已具備，而於95年12月26日核准百騏公司之增資登記，\n    足以生損害於主管機關對於公司管理之正確性。\n二、訊據被告對於上開犯罪事實均坦承不諱，復有經濟部95年12\n    月26日經授中字第09533378590 號核准公司增資登記函文、\n    百麒工程公司之變更登記申請書、股東同意書、委託書、變\n    更登記資本額查核報告書、試算表、95年12月20日資產負債\n    表、股東繳納股款明細表、合作金庫銀行敦化分行帳號0000\n    000000000 號帳戶之存摺交易明細、交易明細表、開戶基本\n    資料、百麒公司95年12月26日變更登記表、阪信商業銀行95\n    年12月20日存摺類取款憑證、匯出匯款申請書、合作金庫銀\n    行客戶往來傑清帳戶查詢清單等件影本在卷足憑，足認被告\n    之自白與事實相符，得為認定其犯罪之依據。本案事證明確\n    ，被告犯行堪予認定，應予依法論科。\n三、論罪科刑部分：\n  (一)被告為百騏工程公司之登記負責人，屬公司法第8 條之負責\n    人，亦為商業會計法第4 條規定之商業負責人；又按資產負\n    債表，係屬商業會計法第28條第1 項第1 款之財務報表；再\n    公司之申請登記，主管機關僅需形式審查（最高法院96年度\n    第5 次刑事庭會議決議可資參照) 。是核被告所為，係犯公\n    司法第9 條第1 項之未繳納股款罪、修正前商業會計法第71\n    條第5款 之使財務報表發生不實之結果罪、刑法第214 條使\n    公務員登載不實文書罪。被告與共犯洪英哲間，就上開犯行\n    ，有犯意聯絡及行為分擔，為共同正犯（關於公司法第9 條\n    第1 項、修正前商業會計法第71條第5 款之部分，洪英哲並\n    不具公司負責人或商業負責人之身分，惟依刑法第28條、第\n    31條第1 項之規定，仍論以共同正犯）。又公司負責人明知\n    公司應收股款，股東並未實際繳納，而將之均列作公司之流\n    動資產之銀行存款項目，登載於公司之資產負債表上，嗣向\n    主管機關提出申請文件，表明已收足股款，使公務員登載於\n    職務上所掌公文書，足以生損害於公眾或他人，其所犯公司\n    法第9 條第1 項、商業會計法第71條第5 款、刑法第214 條\n    3 罪，就行為人而言，係基於一個意思決定而著手實施，目\n    的均在為不實之公司資本登記，且上開行為既係行為人一個\n    犯罪計畫內接續實施，客觀上即難以強行分割，應評價為一\n    個犯罪行為，而各罪犯罪構成要件不同，為一行為觸犯數罪\n    名，應依刑法第55條想像競合犯規定，從較重之公司法第9\n    條第1 項處斷（最高法院96年度臺上字第6356號判決、96年\n    度第7 次刑事庭會議決議意旨參照）。\n  (二)爰審酌被告有詐欺、違反票據法等犯罪前科（有臺灣高等法\n    院被告前案紀錄表在卷可憑），其為求增加公司資本以加強\n    公司信用，而便宜行事，以上開不實方式辦理虛偽之增資登\n    記，影響國家對於公司行號之監督管理，所為自屬非是，惟\n    念及其非藉此從事其他不法犯罪，亦非藉虛設之公司，與他\n    人交易往來，尚無重大危害社會經濟秩序之情事，惡性輕微\n    ，兼衡被告犯罪之動機、目的、手段、生活狀況、智識程度\n    、虛增或設立資本額多寡，及犯後均坦承犯行，知所悔悟，\n    態度尚稱良好等一切情狀，量處如主文所示之刑，並依刑法\n    第41條第1 項前段之規定，諭知易科罰金之折算標準。又被\n    告所為本案犯行，其犯罪時間在96年4 月24日之減刑基準日\n    以前，且所犯之罪核與中華民國九十六年罪犯減刑條例第2\n    條第1 項之規定相符，復無同條例第3 條限制減刑之除外情\n    形，是應依中華民國九十六年罪犯減刑條例第2 條第1 項第\n    3 款之規定，減其上開宣告刑期2 分之1 ，及就被告所減得\n    之刑諭知如主文所示之易科罰金折算標準。\n四、應依刑事訴訟法第449 條第1 項前段、第3 項，公司法第9\n    條第1 項，商業會計法第71條第5 款，刑法第11條前段、第\n    28條、第31條第1 項、第214 條、第55條、第41條第1 項前\n    段，刑法施行法第1 條之1 ，中華民國九十六年罪犯減刑條\n    例第2 條第1 項第3 款、第7 條，逕以簡易判決處如主文所\n    示之刑。\n中    華    民    國   100    年     4    月    28    日\n                  刑事第十八庭  法  官  陳思帆\n上正本證明與原本無異。\n如不服本判決應於收受送達後10日內向本院提出上訴書狀，並應\n敘述具體理由；其未敘述上訴理由者，應於上訴期間屆滿後20日\n內向本院補提理由書（均須按他造當事人之人數附繕本）「切勿\n逕送上級法院」。告訴人或被害人如對於本判決不服者，應具備\n理由請求檢察官上訴，其上訴期間之計算係以檢察官收受判決正\n本之日期為準。\n                                書記官   林素霜\n中    華    民    國    100   年     4    月    28    日\n附錄本案論罪科刑所適用之法條全文：\n公司法第9 條\n公司應收之股款，股東並未實際繳納，而以申請文件表明收足，\n或股東雖已繳納而於登記後將股款發還股東，或任由股東收回者\n，公司負責人各處5 年以下有期徒刑、拘役或科或併科新臺幣50\n萬元以上250 萬元以下罰金。\n有前項情事時，公司負責人應與各該股東連帶賠償公司或第三人\n因此所受之損害。\n第1 項裁判確定後，由檢察機關通知中央主管機關撤銷或廢止其\n登記。但裁判確定前，已為補正或經主管機關限期補正已補正者\n，不在此限。\n公司之設立或其他登記事項有偽造、變造文書，經裁判確定後，\n由檢察機關通知中央主管機關撤銷或廢止其登記。\n商業會計法第71條\n商業負責人、主辦及經辦會計人員或依法受託代他人處理會計事\n務之人員有下列情事之一者，處5 年以下有期徒刑、拘役或科或\n併科新臺幣60萬元以下罰金：\n一、以明知為不實之事項，而填製會計憑證或記入帳冊。\n二、故意使應保存之會計憑證、會計帳簿報表滅失毀損。\n三、偽造或變造會計憑證、會計帳簿報表內容或毀損其頁數。\n四、故意遺漏會計事項不為記錄，致使財務報表發生不實之結果\n    。\n五、其他利用不正當方法，致使會計事項或財務報表發生不實之\n    結果。\n中華民國刑法第214條\n明知為不實之事項，而使公務員登載於職務上所掌之公文書，足\n以生損害於公眾或他人者，處3 年以下有期徒刑、拘役或5 百元\n以下罰金。",
  "structure": {
    "main": "謝承芳共同公司負責人，公司應收之股款，股東並未實際繳納，\n而以申請文件表明收足，處有期徒刑肆月，如易科罰金，以新臺\n幣壹仟元折算壹日；減為有期徒刑貳月，如易科罰金，以新臺幣\n壹仟元折算壹日。",
    "fact": "一、謝承芳係百騏工程有限公司（下稱百騏公司）負責人，於民\n    國95年12月間，委託記帳業者張秀禎（業經檢察官另案起訴\n    ）辦理百騏公司資本額新臺幣（下同）1,000 萬元之增資登\n    記，其明知辦理增資之上開公司股東並未實際繳納股款，竟\n    與張秀禎、洪英哲基於以申請文件表明收足股東未實際繳納\n    之應收股款、以不正當方法致使財務報表發生不實結果、使\n    公務員登載不實之犯意聯絡，透過張秀禎向「英哲企管顧問\n    社」之洪英哲（業經另案起訴）短期借款作為驗資之資金證\n    明，由謝承芳將百麒工程公司之基本資料交付予張秀禎，再\n    依指示至合作金庫銀行敦化分行（址設臺北市松山區○○○\n    路○ 段88號），開設百騏公司之活期存款帳戶，張秀禎將開\n    立之存摺轉交「英哲企管顧問社」洪英哲，由洪英哲於95年\n    12月20日，辦理資金轉帳手續，自洪英哲自所使用之帳戶提\n    出現金後，再以謝承芳名義轉帳1,000 萬元存入百騏公司帳\n    戶後，旋將存摺帶回影印，作為股款業經股東繳納之存款證\n    明，並製作不實之百騏公司存款1,000 萬元之股東繳納股款\n    明細表、資產負債表及公司增資登記資本額查核報告書，嗣\n    於各項會計報表上蓋用代刻之公司及負責人印章，將資本額\n    查核報告書工作底稿交給不知情之會計師姚維世簽章，完成\n    公司法第7 條授權會計師查核簽證資本額之作業，旋於95年\n    12月22日將上開存入百騏公司帳戶之1,000 萬元資金轉出至\n    洪英哲所使用之帳戶內，而未用於百騏公司之經營。嗣後謝\n    承芳委由張秀禎填載公司增資登記申請書，並以上開存摺影\n    本、資產負債表及公司增資登記資本額查核報告書等申請文\n    件，表明百騏公司應收股款均已收足，向主管機關經濟部中\n    部辦公室申請增資登記，使該管承辦公務員審查認為形式要\n    件均已具備，而於95年12月26日核准百騏公司之增資登記，\n    足以生損害於主管機關對於公司管理之正確性。\n二、訊據被告對於上開犯罪事實均坦承不諱，復有經濟部95年12\n    月26日經授中字第09533378590 號核准公司增資登記函文、\n    百麒工程公司之變更登記申請書、股東同意書、委託書、變\n    更登記資本額查核報告書、試算表、95年12月20日資產負債\n    表、股東繳納股款明細表、合作金庫銀行敦化分行帳號0000\n    000000000 號帳戶之存摺交易明細、交易明細表、開戶基本\n    資料、百麒公司95年12月26日變更登記表、阪信商業銀行95\n    年12月20日存摺類取款憑證、匯出匯款申請書、合作金庫銀\n    行客戶往來傑清帳戶查詢清單等件影本在卷足憑，足認被告\n    之自白與事實相符，得為認定其犯罪之依據。本案事證明確\n    ，被告犯行堪予認定，應予依法論科。\n三、論罪科刑部分：\n  (一)被告為百騏工程公司之登記負責人，屬公司法第8 條之負責\n    人，亦為商業會計法第4 條規定之商業負責人；又按資產負\n    債表，係屬商業會計法第28條第1 項第1 款之財務報表；再\n    公司之申請登記，主管機關僅需形式審查（最高法院96年度\n    第5 次刑事庭會議決議可資參照) 。是核被告所為，係犯公\n    司法第9 條第1 項之未繳納股款罪、修正前商業會計法第71\n    條第5款 之使財務報表發生不實之結果罪、刑法第214 條使\n    公務員登載不實文書罪。被告與共犯洪英哲間，就上開犯行\n    ，有犯意聯絡及行為分擔，為共同正犯（關於公司法第9 條\n    第1 項、修正前商業會計法第71條第5 款之部分，洪英哲並\n    不具公司負責人或商業負責人之身分，惟依刑法第28條、第\n    31條第1 項之規定，仍論以共同正犯）。又公司負責人明知\n    公司應收股款，股東並未實際繳納，而將之均列作公司之流\n    動資產之銀行存款項目，登載於公司之資產負債表上，嗣向\n    主管機關提出申請文件，表明已收足股款，使公務員登載於\n    職務上所掌公文書，足以生損害於公眾或他人，其所犯公司\n    法第9 條第1 項、商業會計法第71條第5 款、刑法第214 條\n    3 罪，就行為人而言，係基於一個意思決定而著手實施，目\n    的均在為不實之公司資本登記，且上開行為既係行為人一個\n    犯罪計畫內接續實施，客觀上即難以強行分割，應評價為一\n    個犯罪行為，而各罪犯罪構成要件不同，為一行為觸犯數罪\n    名，應依刑法第55條想像競合犯規定，從較重之公司法第9\n    條第1 項處斷（最高法院96年度臺上字第6356號判決、96年\n    度第7 次刑事庭會議決議意旨參照）。\n  (二)爰審酌被告有詐欺、違反票據法等犯罪前科（有臺灣高等法\n    院被告前案紀錄表在卷可憑），其為求增加公司資本以加強\n    公司信用，而便宜行事，以上開不實方式辦理虛偽之增資登\n    記，影響國家對於公司行號之監督管理，所為自屬非是，惟\n    念及其非藉此從事其他不法犯罪，亦非藉虛設之公司，與他\n    人交易往來，尚無重大危害社會經濟秩序之情事，惡性輕微\n    ，兼衡被告犯罪之動機、目的、手段、生活狀況、智識程度\n    、虛增或設立資本額多寡，及犯後均坦承犯行，知所悔悟，\n    態度尚稱良好等一切情狀，量處如主文所示之刑，並依刑法\n    第41條第1 項前段之規定，諭知易科罰金之折算標準。又被\n    告所為本案犯行，其犯罪時間在96年4 月24日之減刑基準日\n    以前，且所犯之罪核與中華民國九十六年罪犯減刑條例第2\n    條第1 項之規定相符，復無同條例第3 條限制減刑之除外情\n    形，是應依中華民國九十六年罪犯減刑條例第2 條第1 項第\n    3 款之規定，減其上開宣告刑期2 分之1 ，及就被告所減得\n    之刑諭知如主文所示之易科罰金折算標準。\n四、應依刑事訴訟法第449 條第1 項前段、第3 項，公司法第9\n    條第1 項，商業會計法第71條第5 款，刑法第11條前段、第\n    28條、第31條第1 項、第214 條、第55條、第41條第1 項前\n    段，刑法施行法第1 條之1 ，中華民國九十六年罪犯減刑條\n    例第2 條第1 項第3 款、第7 條，逕以簡易判決處如主文所\n    示之刑。",
    "reason": "一、謝承芳係百騏工程有限公司（下稱百騏公司）負責人，於民\n    國95年12月間，委託記帳業者張秀禎（業經檢察官另案起訴\n    ）辦理百騏公司資本額新臺幣（下同）1,000 萬元之增資登\n    記，其明知辦理增資之上開公司股東並未實際繳納股款，竟\n    與張秀禎、洪英哲基於以申請文件表明收足股東未實際繳納\n    之應收股款、以不正當方法致使財務報表發生不實結果、使\n    公務員登載不實之犯意聯絡，透過張秀禎向「英哲企管顧問\n    社」之洪英哲（業經另案起訴）短期借款作為驗資之資金證\n    明，由謝承芳將百麒工程公司之基本資料交付予張秀禎，再\n    依指示至合作金庫銀行敦化分行（址設臺北市松山區○○○\n    路○ 段88號），開設百騏公司之活期存款帳戶，張秀禎將開\n    立之存摺轉交「英哲企管顧問社」洪英哲，由洪英哲於95年\n    12月20日，辦理資金轉帳手續，自洪英哲自所使用之帳戶提\n    出現金後，再以謝承芳名義轉帳1,000 萬元存入百騏公司帳\n    戶後，旋將存摺帶回影印，作為股款業經股東繳納之存款證\n    明，並製作不實之百騏公司存款1,000 萬元之股東繳納股款\n    明細表、資產負債表及公司增資登記資本額查核報告書，嗣\n    於各項會計報表上蓋用代刻之公司及負責人印章，將資本額\n    查核報告書工作底稿交給不知情之會計師姚維世簽章，完成\n    公司法第7 條授權會計師查核簽證資本額之作業，旋於95年\n    12月22日將上開存入百騏公司帳戶之1,000 萬元資金轉出至\n    洪英哲所使用之帳戶內，而未用於百騏公司之經營。嗣後謝\n    承芳委由張秀禎填載公司增資登記申請書，並以上開存摺影\n    本、資產負債表及公司增資登記資本額查核報告書等申請文\n    件，表明百騏公司應收股款均已收足，向主管機關經濟部中\n    部辦公室申請增資登記，使該管承辦公務員審查認為形式要\n    件均已具備，而於95年12月26日核准百騏公司之增資登記，\n    足以生損害於主管機關對於公司管理之正確性。\n二、訊據被告對於上開犯罪事實均坦承不諱，復有經濟部95年12\n    月26日經授中字第09533378590 號核准公司增資登記函文、\n    百麒工程公司之變更登記申請書、股東同意書、委託書、變\n    更登記資本額查核報告書、試算表、95年12月20日資產負債\n    表、股東繳納股款明細表、合作金庫銀行敦化分行帳號0000\n    000000000 號帳戶之存摺交易明細、交易明細表、開戶基本\n    資料、百麒公司95年12月26日變更登記表、阪信商業銀行95\n    年12月20日存摺類取款憑證、匯出匯款申請書、合作金庫銀\n    行客戶往來傑清帳戶查詢清單等件影本在卷足憑，足認被告\n    之自白與事實相符，得為認定其犯罪之依據。本案事證明確\n    ，被告犯行堪予認定，應予依法論科。\n三、論罪科刑部分：\n  (一)被告為百騏工程公司之登記負責人，屬公司法第8 條之負責\n    人，亦為商業會計法第4 條規定之商業負責人；又按資產負\n    債表，係屬商業會計法第28條第1 項第1 款之財務報表；再\n    公司之申請登記，主管機關僅需形式審查（最高法院96年度\n    第5 次刑事庭會議決議可資參照) 。是核被告所為，係犯公\n    司法第9 條第1 項之未繳納股款罪、修正前商業會計法第71\n    條第5款 之使財務報表發生不實之結果罪、刑法第214 條使\n    公務員登載不實文書罪。被告與共犯洪英哲間，就上開犯行\n    ，有犯意聯絡及行為分擔，為共同正犯（關於公司法第9 條\n    第1 項、修正前商業會計法第71條第5 款之部分，洪英哲並\n    不具公司負責人或商業負責人之身分，惟依刑法第28條、第\n    31條第1 項之規定，仍論以共同正犯）。又公司負責人明知\n    公司應收股款，股東並未實際繳納，而將之均列作公司之流\n    動資產之銀行存款項目，登載於公司之資產負債表上，嗣向\n    主管機關提出申請文件，表明已收足股款，使公務員登載於\n    職務上所掌公文書，足以生損害於公眾或他人，其所犯公司\n    法第9 條第1 項、商業會計法第71條第5 款、刑法第214 條\n    3 罪，就行為人而言，係基於一個意思決定而著手實施，目\n    的均在為不實之公司資本登記，且上開行為既係行為人一個\n    犯罪計畫內接續實施，客觀上即難以強行分割，應評價為一\n    個犯罪行為，而各罪犯罪構成要件不同，為一行為觸犯數罪\n    名，應依刑法第55條想像競合犯規定，從較重之公司法第9\n    條第1 項處斷（最高法院96年度臺上字第6356號判決、96年\n    度第7 次刑事庭會議決議意旨參照）。\n  (二)爰審酌被告有詐欺、違反票據法等犯罪前科（有臺灣高等法\n    院被告前案紀錄表在卷可憑），其為求增加公司資本以加強\n    公司信用，而便宜行事，以上開不實方式辦理虛偽之增資登\n    記，影響國家對於公司行號之監督管理，所為自屬非是，惟\n    念及其非藉此從事其他不法犯罪，亦非藉虛設之公司，與他\n    人交易往來，尚無重大危害社會經濟秩序之情事，惡性輕微\n    ，兼衡被告犯罪之動機、目的、手段、生活狀況、智識程度\n    、虛增或設立資本額多寡，及犯後均坦承犯行，知所悔悟，\n    態度尚稱良好等一切情狀，量處如主文所示之刑，並依刑法\n    第41條第1 項前段之規定，諭知易科罰金之折算標準。又被\n    告所為本案犯行，其犯罪時間在96年4 月24日之減刑基準日\n    以前，且所犯之罪核與中華民國九十六年罪犯減刑條例第2\n    條第1 項之規定相符，復無同條例第3 條限制減刑之除外情\n    形，是應依中華民國九十六年罪犯減刑條例第2 條第1 項第\n    3 款之規定，減其上開宣告刑期2 分之1 ，及就被告所減得\n    之刑諭知如主文所示之易科罰金折算標準。\n四、應依刑事訴訟法第449 條第1 項前段、第3 項，公司法第9\n    條第1 項，商業會計法第71條第5 款，刑法第11條前段、第\n    28條、第31條第1 項、第214 條、第55條、第41條第1 項前\n    段，刑法施行法第1 條之1 ，中華民國九十六年罪犯減刑條\n    例第2 條第1 項第3 款、第7 條，逕以簡易判決處如主文所\n    示之刑。"
  },
  "search": "臺灣臺北地方法院刑事簡易判決100年度簡字第1126號聲請人臺灣臺北地方法院檢察署檢察官被告謝承芳上列被告因違反公司法等案件，經檢察官聲請簡易判決處刑（99年度偵字第22613號），本院判決如下：主文謝承芳共同公司負責人，公司應收之股款，股東並未實際繳納，而以申請文件表明收足，處有期徒刑肆月，如易科罰金，以新臺幣壹仟元折算壹日；減為有期徒刑貳月，如易科罰金，以新臺幣壹仟元折算壹日。事實及理由一、謝承芳係百騏工程有限公司（下稱百騏公司）負責人，於民國95年12月間，委託記帳業者張秀禎（業經檢察官另案起訴）辦理百騏公司資本額新臺幣（下同）1,000萬元之增資登記，其明知辦理增資之上開公司股東並未實際繳納股款，竟與張秀禎、洪英哲基於以申請文件表明收足股東未實際繳納之應收股款、以不正當方法致使財務報表發生不實結果、使公務員登載不實之犯意聯絡，透過張秀禎向「英哲企管顧問社」之洪英哲（業經另案起訴）短期借款作為驗資之資金證明，由謝承芳將百麒工程公司之基本資料交付予張秀禎，再依指示至合作金庫銀行敦化分行（址設臺北市松山區○○○路○段88號），開設百騏公司之活期存款帳戶，張秀禎將開立之存摺轉交「英哲企管顧問社」洪英哲，由洪英哲於95年12月20日，辦理資金轉帳手續，自洪英哲自所使用之帳戶提出現金後，再以謝承芳名義轉帳1,000萬元存入百騏公司帳戶後，旋將存摺帶回影印，作為股款業經股東繳納之存款證明，並製作不實之百騏公司存款1,000萬元之股東繳納股款明細表、資產負債表及公司增資登記資本額查核報告書，嗣於各項會計報表上蓋用代刻之公司及負責人印章，將資本額查核報告書工作底稿交給不知情之會計師姚維世簽章，完成公司法第7條授權會計師查核簽證資本額之作業，旋於95年12月22日將上開存入百騏公司帳戶之1,000萬元資金轉出至洪英哲所使用之帳戶內，而未用於百騏公司之經營。嗣後謝承芳委由張秀禎填載公司增資登記申請書，並以上開存摺影本、資產負債表及公司增資登記資本額查核報告書等申請文件，表明百騏公司應收股款均已收足，向主管機關經濟部中部辦公室申請增資登記，使該管承辦公務員審查認為形式要件均已具備，而於95年12月26日核准百騏公司之增資登記，足以生損害於主管機關對於公司管理之正確性。二、訊據被告對於上開犯罪事實均坦承不諱，復有經濟部95年12月26日經授中字第09533378590號核准公司增資登記函文、百麒工程公司之變更登記申請書、股東同意書、委託書、變更登記資本額查核報告書、試算表、95年12月20日資產負債表、股東繳納股款明細表、合作金庫銀行敦化分行帳號0000000000000號帳戶之存摺交易明細、交易明細表、開戶基本資料、百麒公司95年12月26日變更登記表、阪信商業銀行95年12月20日存摺類取款憑證、匯出匯款申請書、合作金庫銀行客戶往來傑清帳戶查詢清單等件影本在卷足憑，足認被告之自白與事實相符，得為認定其犯罪之依據。本案事證明確，被告犯行堪予認定，應予依法論科。三、論罪科刑部分：(一)被告為百騏工程公司之登記負責人，屬公司法第8條之負責人，亦為商業會計法第4條規定之商業負責人；又按資產負債表，係屬商業會計法第28條第1項第1款之財務報表；再公司之申請登記，主管機關僅需形式審查（最高法院96年度第5次刑事庭會議決議可資參照)。是核被告所為，係犯公司法第9條第1項之未繳納股款罪、修正前商業會計法第71條第5款之使財務報表發生不實之結果罪、刑法第214條使公務員登載不實文書罪。被告與共犯洪英哲間，就上開犯行，有犯意聯絡及行為分擔，為共同正犯（關於公司法第9條第1項、修正前商業會計法第71條第5款之部分，洪英哲並不具公司負責人或商業負責人之身分，惟依刑法第28條、第31條第1項之規定，仍論以共同正犯）。又公司負責人明知公司應收股款，股東並未實際繳納，而將之均列作公司之流動資產之銀行存款項目，登載於公司之資產負債表上，嗣向主管機關提出申請文件，表明已收足股款，使公務員登載於職務上所掌公文書，足以生損害於公眾或他人，其所犯公司法第9條第1項、商業會計法第71條第5款、刑法第214條3罪，就行為人而言，係基於一個意思決定而著手實施，目的均在為不實之公司資本登記，且上開行為既係行為人一個犯罪計畫內接續實施，客觀上即難以強行分割，應評價為一個犯罪行為，而各罪犯罪構成要件不同，為一行為觸犯數罪名，應依刑法第55條想像競合犯規定，從較重之公司法第9條第1項處斷（最高法院96年度臺上字第6356號判決、96年度第7次刑事庭會議決議意旨參照）。(二)爰審酌被告有詐欺、違反票據法等犯罪前科（有臺灣高等法院被告前案紀錄表在卷可憑），其為求增加公司資本以加強公司信用，而便宜行事，以上開不實方式辦理虛偽之增資登記，影響國家對於公司行號之監督管理，所為自屬非是，惟念及其非藉此從事其他不法犯罪，亦非藉虛設之公司，與他人交易往來，尚無重大危害社會經濟秩序之情事，惡性輕微，兼衡被告犯罪之動機、目的、手段、生活狀況、智識程度、虛增或設立資本額多寡，及犯後均坦承犯行，知所悔悟，態度尚稱良好等一切情狀，量處如主文所示之刑，並依刑法第41條第1項前段之規定，諭知易科罰金之折算標準。又被告所為本案犯行，其犯罪時間在96年4月24日之減刑基準日以前，且所犯之罪核與中華民國九十六年罪犯減刑條例第2條第1項之規定相符，復無同條例第3條限制減刑之除外情形，是應依中華民國九十六年罪犯減刑條例第2條第1項第3款之規定，減其上開宣告刑期2分之1，及就被告所減得之刑諭知如主文所示之易科罰金折算標準。四、應依刑事訴訟法第449條第1項前段、第3項，公司法第9條第1項，商業會計法第71條第5款，刑法第11條前段、第28條、第31條第1項、第214條、第55條、第41條第1項前段，刑法施行法第1條之1，中華民國九十六年罪犯減刑條例第2條第1項第3款、第7條，逕以簡易判決處如主文所示之刑。中華民國100年4月28日刑事第十八庭法官陳思帆上正本證明與原本無異。如不服本判決應於收受送達後10日內向本院提出上訴書狀，並應敘述具體理由；其未敘述上訴理由者，應於上訴期間屆滿後20日內向本院補提理由書（均須按他造當事人之人數附繕本）「切勿逕送上級法院」。告訴人或被害人如對於本判決不服者，應具備理由請求檢察官上訴，其上訴期間之計算係以檢察官收受判決正本之日期為準。書記官林素霜中華民國100年4月28日附錄本案論罪科刑所適用之法條全文：公司法第9條公司應收之股款，股東並未實際繳納，而以申請文件表明收足，或股東雖已繳納而於登記後將股款發還股東，或任由股東收回者，公司負責人各處5年以下有期徒刑、拘役或科或併科新臺幣50萬元以上250萬元以下罰金。有前項情事時，公司負責人應與各該股東連帶賠償公司或第三人因此所受之損害。第1項裁判確定後，由檢察機關通知中央主管機關撤銷或廢止其登記。但裁判確定前，已為補正或經主管機關限期補正已補正者，不在此限。公司之設立或其他登記事項有偽造、變造文書，經裁判確定後，由檢察機關通知中央主管機關撤銷或廢止其登記。商業會計法第71條商業負責人、主辦及經辦會計人員或依法受託代他人處理會計事務之人員有下列情事之一者，處5年以下有期徒刑、拘役或科或併科新臺幣60萬元以下罰金：一、以明知為不實之事項，而填製會計憑證或記入帳冊。二、故意使應保存之會計憑證、會計帳簿報表滅失毀損。三、偽造或變造會計憑證、會計帳簿報表內容或毀損其頁數。四、故意遺漏會計事項不為記錄，致使財務報表發生不實之結果。五、其他利用不正當方法，致使會計事項或財務報表發生不實之結果。中華民國刑法第214條明知為不實之事項，而使公務員登載於職務上所掌之公文書，足以生損害於公眾或他人者，處3年以下有期徒刑、拘役或5百元以下罰金。",
  "characters": {
    "judges": [
      "陳思帆"
    ],
    "prosecutors": [

    ],
    "lawyers": [

    ],
    "clerks": [
      "林素霜"
    ],
    "plaintiffs": [

    ],
    "defendants": [
      "謝承芳"
    ],
    "prosecutor_office": [
      "臺灣臺北地方法院檢察署檢察官"
    ],
    "creditors": [

    ],
    "debtors": [

    ],
    "judicial_associate_officer": [

    ]
  },
  "adjudged_at": "2011-04-28",
  "created_at": "2016-02-12 09:13:09",
  "updated_at": "2016-02-12 09:13:09"
}