{
  "identify": "TYD-100-壢簡-824-20110427-1",
  "court": {
    "name": "臺灣桃園地方法院",
    "code": "TYD"
  },
  "division": {
    "name": "刑事",
    "code": "M"
  },
  "year": 100,
  "word": "壢簡",
  "number": "824",
  "jcheck": "1",
  "reason": "竊盜",
  "content": "臺灣桃園地方法院刑事簡易判決        100年度壢簡字第824號\n聲  請  人  臺灣桃園地方法院檢察署檢察官\n被      告  武維揚\n上列被告因竊盜案件，經檢察官聲請以簡易判決處刑（100 年度\n偵字第6579號），本院判決如下：\n    主      文\n武維揚竊盜，累犯，處有期徒刑月，如易科罰金，以新臺幣壹\n仟元折算壹日。\n    事實及理由\n一、本件犯罪事實及證據，除就犯罪事實部分補充：「被告武維\n    揚前因違反毒品危害防制條例案件，經本院以96年度壢簡字\n    第729 號、97年度審易字第1582號判決判處有期徒刑6 月、\n    4 月確定，前開有期徒刑6 月再經本院以96年度聲減字第99\n    35號裁定減為有期徒刑3 月確定，復經本院以98年度聲字第\n    3853號裁定就上開有期徒刑3 月、4 月定應執行有期徒刑6\n    月確定；另因竊盜、違反毒品危害防制條例案件，經本院以\n    97年度審易緝字第11號、96年度壢簡字第2550號、96年度桃\n    簡字第3191號、97年度審簡字第151 號判決判處有期徒刑7\n    月、4 月、5 月、5 月確定，上開4 罪再經本院以97年度聲\n    字第2140號裁定定應執行有期徒刑1 年8 月確定；又因違反\n    毒品危害防制條例案件，經本院以97年度審易字第1117號判\n    決判處有期徒刑6 月15日確定，上開有期徒刑6 月、1 年8\n    月、6 月15日於民國97年5 月21日入監執行，99年6 月30日\n    假釋出監並交付保護管束，於99年10月21日假釋期滿未經撤\n    銷假釋，未執行之刑以已執行完畢論（構成累犯）」外，其\n    餘均引用檢察官聲請簡易判決處刑書之記載（如附件）。\n二、核被告所為，係犯刑法第320 條第1 項之竊盜罪。又被告前\n    曾受有如事實欄所述之犯罪科刑及執行情形，有臺灣高等法\n    院被告全國前案紀錄表1 份在卷可稽，其5 年內故意再犯本\n    件有期徒刑以上之罪，為累犯，依法加重其刑。爰審酌被告\n    不思循正當途徑獲取財物，僅因一時貪念，竟恣意竊取他人\n    財物，對他人財產安全顯然已生危害，所為誠屬不該，惟念\n    及被告坦承犯行，態度尚可等一切情狀，量處如主文所示之\n    刑，並諭知如主文所示之易科罰金折算標準，以資懲戒。\n三、依刑事訴訟法第449 條第1 項前段、第454 條第2 項，刑法\n    第320 條第1 項、第47條第1 項、第41條第1 項前段，刑法\n    施行法第1 條之1 第1 項、第2 項前段，逕以簡易判決處刑\n    。\n四、如不服本判決，應於判決送達後10日內，向本院提出上訴狀\n    （應附繕本），上訴於本院合議庭。\n中    華    民    國    100  年    4     月    27     日\n                  刑事第四庭  法  官  張淑華\n以上正本證明與原本無異\n如不服本判決，應於判決送達後10日內，向本院提出上訴狀。\n                              書記官  沈秀珍\n中    華    民    國  100    年    4      月    27    日\n附錄論罪科刑依據之法條：\n中華民國刑法第320條\n（普通竊盜罪、竊佔罪）\n意圖為自己或第三人不法之所有，而竊取他人之動產者，為竊盜\n罪，處5  年以下有期徒刑、拘役或 5 百元以下罰金。\n意圖為自己或第三人不法之利益，而竊佔他人之不動產者，依前\n項之規定處斷。\n前二項之未遂犯罰之。",
  "structure": {
    "main": "武維揚竊盜，累犯，處有期徒刑月，如易科罰金，以新臺幣壹\n仟元折算壹日。",
    "fact": "一、本件犯罪事實及證據，除就犯罪事實部分補充：「被告武維\n    揚前因違反毒品危害防制條例案件，經本院以96年度壢簡字\n    第729 號、97年度審易字第1582號判決判處有期徒刑6 月、\n    4 月確定，前開有期徒刑6 月再經本院以96年度聲減字第99\n    35號裁定減為有期徒刑3 月確定，復經本院以98年度聲字第\n    3853號裁定就上開有期徒刑3 月、4 月定應執行有期徒刑6\n    月確定；另因竊盜、違反毒品危害防制條例案件，經本院以\n    97年度審易緝字第11號、96年度壢簡字第2550號、96年度桃\n    簡字第3191號、97年度審簡字第151 號判決判處有期徒刑7\n    月、4 月、5 月、5 月確定，上開4 罪再經本院以97年度聲\n    字第2140號裁定定應執行有期徒刑1 年8 月確定；又因違反\n    毒品危害防制條例案件，經本院以97年度審易字第1117號判\n    決判處有期徒刑6 月15日確定，上開有期徒刑6 月、1 年8\n    月、6 月15日於民國97年5 月21日入監執行，99年6 月30日\n    假釋出監並交付保護管束，於99年10月21日假釋期滿未經撤\n    銷假釋，未執行之刑以已執行完畢論（構成累犯）」外，其\n    餘均引用檢察官聲請簡易判決處刑書之記載（如附件）。\n二、核被告所為，係犯刑法第320 條第1 項之竊盜罪。又被告前\n    曾受有如事實欄所述之犯罪科刑及執行情形，有臺灣高等法\n    院被告全國前案紀錄表1 份在卷可稽，其5 年內故意再犯本\n    件有期徒刑以上之罪，為累犯，依法加重其刑。爰審酌被告\n    不思循正當途徑獲取財物，僅因一時貪念，竟恣意竊取他人\n    財物，對他人財產安全顯然已生危害，所為誠屬不該，惟念\n    及被告坦承犯行，態度尚可等一切情狀，量處如主文所示之\n    刑，並諭知如主文所示之易科罰金折算標準，以資懲戒。\n三、依刑事訴訟法第449 條第1 項前段、第454 條第2 項，刑法\n    第320 條第1 項、第47條第1 項、第41條第1 項前段，刑法\n    施行法第1 條之1 第1 項、第2 項前段，逕以簡易判決處刑\n    。\n四、如不服本判決，應於判決送達後10日內，向本院提出上訴狀\n    （應附繕本），上訴於本院合議庭。",
    "reason": "一、本件犯罪事實及證據，除就犯罪事實部分補充：「被告武維\n    揚前因違反毒品危害防制條例案件，經本院以96年度壢簡字\n    第729 號、97年度審易字第1582號判決判處有期徒刑6 月、\n    4 月確定，前開有期徒刑6 月再經本院以96年度聲減字第99\n    35號裁定減為有期徒刑3 月確定，復經本院以98年度聲字第\n    3853號裁定就上開有期徒刑3 月、4 月定應執行有期徒刑6\n    月確定；另因竊盜、違反毒品危害防制條例案件，經本院以\n    97年度審易緝字第11號、96年度壢簡字第2550號、96年度桃\n    簡字第3191號、97年度審簡字第151 號判決判處有期徒刑7\n    月、4 月、5 月、5 月確定，上開4 罪再經本院以97年度聲\n    字第2140號裁定定應執行有期徒刑1 年8 月確定；又因違反\n    毒品危害防制條例案件，經本院以97年度審易字第1117號判\n    決判處有期徒刑6 月15日確定，上開有期徒刑6 月、1 年8\n    月、6 月15日於民國97年5 月21日入監執行，99年6 月30日\n    假釋出監並交付保護管束，於99年10月21日假釋期滿未經撤\n    銷假釋，未執行之刑以已執行完畢論（構成累犯）」外，其\n    餘均引用檢察官聲請簡易判決處刑書之記載（如附件）。\n二、核被告所為，係犯刑法第320 條第1 項之竊盜罪。又被告前\n    曾受有如事實欄所述之犯罪科刑及執行情形，有臺灣高等法\n    院被告全國前案紀錄表1 份在卷可稽，其5 年內故意再犯本\n    件有期徒刑以上之罪，為累犯，依法加重其刑。爰審酌被告\n    不思循正當途徑獲取財物，僅因一時貪念，竟恣意竊取他人\n    財物，對他人財產安全顯然已生危害，所為誠屬不該，惟念\n    及被告坦承犯行，態度尚可等一切情狀，量處如主文所示之\n    刑，並諭知如主文所示之易科罰金折算標準，以資懲戒。\n三、依刑事訴訟法第449 條第1 項前段、第454 條第2 項，刑法\n    第320 條第1 項、第47條第1 項、第41條第1 項前段，刑法\n    施行法第1 條之1 第1 項、第2 項前段，逕以簡易判決處刑\n    。\n四、如不服本判決，應於判決送達後10日內，向本院提出上訴狀\n    （應附繕本），上訴於本院合議庭。"
  },
  "search": "臺灣桃園地方法院刑事簡易判決100年度壢簡字第824號聲請人臺灣桃園地方法院檢察署檢察官被告武維揚上列被告因竊盜案件，經檢察官聲請以簡易判決處刑（100年度偵字第6579號），本院判決如下：主文武維揚竊盜，累犯，處有期徒刑月，如易科罰金，以新臺幣壹仟元折算壹日。事實及理由一、本件犯罪事實及證據，除就犯罪事實部分補充：「被告武維揚前因違反毒品危害防制條例案件，經本院以96年度壢簡字第729號、97年度審易字第1582號判決判處有期徒刑6月、4月確定，前開有期徒刑6月再經本院以96年度聲減字第9935號裁定減為有期徒刑3月確定，復經本院以98年度聲字第3853號裁定就上開有期徒刑3月、4月定應執行有期徒刑6月確定；另因竊盜、違反毒品危害防制條例案件，經本院以97年度審易緝字第11號、96年度壢簡字第2550號、96年度桃簡字第3191號、97年度審簡字第151號判決判處有期徒刑7月、4月、5月、5月確定，上開4罪再經本院以97年度聲字第2140號裁定定應執行有期徒刑1年8月確定；又因違反毒品危害防制條例案件，經本院以97年度審易字第1117號判決判處有期徒刑6月15日確定，上開有期徒刑6月、1年8月、6月15日於民國97年5月21日入監執行，99年6月30日假釋出監並交付保護管束，於99年10月21日假釋期滿未經撤銷假釋，未執行之刑以已執行完畢論（構成累犯）」外，其餘均引用檢察官聲請簡易判決處刑書之記載（如附件）。二、核被告所為，係犯刑法第320條第1項之竊盜罪。又被告前曾受有如事實欄所述之犯罪科刑及執行情形，有臺灣高等法院被告全國前案紀錄表1份在卷可稽，其5年內故意再犯本件有期徒刑以上之罪，為累犯，依法加重其刑。爰審酌被告不思循正當途徑獲取財物，僅因一時貪念，竟恣意竊取他人財物，對他人財產安全顯然已生危害，所為誠屬不該，惟念及被告坦承犯行，態度尚可等一切情狀，量處如主文所示之刑，並諭知如主文所示之易科罰金折算標準，以資懲戒。三、依刑事訴訟法第449條第1項前段、第454條第2項，刑法第320條第1項、第47條第1項、第41條第1項前段，刑法施行法第1條之1第1項、第2項前段，逕以簡易判決處刑。四、如不服本判決，應於判決送達後10日內，向本院提出上訴狀（應附繕本），上訴於本院合議庭。中華民國100年4月27日刑事第四庭法官張淑華以上正本證明與原本無異如不服本判決，應於判決送達後10日內，向本院提出上訴狀。書記官沈秀珍中華民國100年4月27日附錄論罪科刑依據之法條：中華民國刑法第320條（普通竊盜罪、竊佔罪）意圖為自己或第三人不法之所有，而竊取他人之動產者，為竊盜罪，處5年以下有期徒刑、拘役或5百元以下罰金。意圖為自己或第三人不法之利益，而竊佔他人之不動產者，依前項之規定處斷。前二項之未遂犯罰之。",
  "characters": {
    "judges": [
      "張淑華"
    ],
    "prosecutors": [

    ],
    "lawyers": [

    ],
    "clerks": [
      "沈秀珍"
    ],
    "plaintiffs": [

    ],
    "defendants": [
      "武維揚"
    ],
    "prosecutor_office": [
      "臺灣桃園地方法院檢察署檢察官"
    ],
    "creditors": [

    ],
    "debtors": [

    ],
    "judicial_associate_officer": [

    ]
  },
  "adjudged_at": "2011-04-27",
  "created_at": "2016-02-12 09:05:38",
  "updated_at": "2016-02-12 09:05:38"
}