{
  "identify": "TYD-93-簡-77-20040318-1",
  "court": {
    "name": "臺灣桃園地方法院",
    "code": "TYD"
  },
  "division": {
    "name": "刑事",
    "code": "M"
  },
  "year": 93,
  "word": "簡",
  "number": "77",
  "jcheck": "1",
  "reason": "詐欺",
  "content": "臺灣桃園地方法院刑事簡易判決                   九十三年度簡字第七七號\n    公  訴  人  臺灣桃園地方法院檢察署檢察官\n    被      告  甲○○○\n右列被告因妨害風化案件，檢察官以通常程序起訴（八十七年度偵字第三五三一號）\n，本院認為宜以簡易判決處刑，茲判決如左：\n    主  文\n甲○○○連續意圖為自己不法之所有，以詐術使人將本人之物交付，累犯，處有期徒\n刑陸月，如易科罰金，以參佰元折算壹日。\n    事  實\n一、甲○○○前因懲治盜匪條例案件，經臺灣高雄地方法院於民國七十九年六月十四\n    日，以七十九年少訴字第四一號判決判處有期徒刑七年三月，同年七月二十三日\n    確定，嗣減刑為有期徒刑六年七月，八十一年十二月十八日假釋出監，假釋期間\n    付保護管束，八十五年六月二十八日期滿，假釋未經撤銷，所處徒刑以已執行完\n    畢論而執行完畢。其明知自己已無清償貨款之資力，竟為償還賭債新台幣（下同\n    ）二百多萬元，仍基於意圖為自己不法所有之概括犯意，於八十六年十二月期間\n    ，先後向正利實業股份有限公司（下稱正利公司）、祥邁企業有限公司（下稱祥\n    邁公司）、及廖本淵購買塑膠原料，使正利公司之業務員、祥邁公司之承辦人楊\n    詔雄及廖本淵等人陷於錯誤，分別依約陸續交付價值一百二十萬元、四十萬元、\n    十餘萬元之塑膠原料予甲○○○。嗣因甲○○○給付之支票均未獲兌現，又行蹤\n    不明，正利公司等始知受騙。\n二、案經被害人正利公司、祥邁公司及廖本淵訴由臺灣桃園地方法院檢察署檢察官偵\n    查起訴。\n    理  由\n一、認定事實所憑之證據及理由\n（一）事實欄所載之犯罪事實，除被告甲○○○於本院審理時之自白外，另有正利公\n      司、祥邁公司及廖本淵分別提出之送貨單、帳冊、支票影本等可證，並與正利\n      公司、祥邁公司及廖本淵告訴之內容，及正利公司負責人鄭子儀、祥邁公司承\n      辦人楊詔雄於檢察官訊問之陳述相符，已足擔保被告自白之真實性。\n（二）被告雖稱給付予祥邁公司之支票票面金額之所以記載為四十萬元，是因為當時\n      已經沒有錢支付，就請朋友彭美玲隨便開一張支票轉交給楊詔雄，但購買之原\n      料應該只有二十八萬元等語；然一般人從事交易時，為支付應付債務而簽發支\n      票，其票面金額應與應付債務之金額相同，實無超額支付之可能，被告此部份\n      辯解不足採信。又廖本淵雖於檢察官偵訊時稱被告向其訂購四十萬元之塑膠原\n      料，然並未提出任何收據或憑證，依罪疑為輕之原則，應認為被告詐騙廖本淵\n      之塑膠原料價值約十多萬元。\n（三）綜合以上證據，足認被告連續向正利公司、祥邁公司及廖本淵詐騙價值共約一\n      百七十多萬元之塑膠原料，本件事證明確，已足以認定被告確有事實欄所載犯\n      行。\n二、論罪科刑之依據\n（一）被告甲○○○所為，犯刑法第三百三十九條第一項詐欺取財罪，其先後數次詐\n      欺行為，時間緊接，方法相同，觸犯構成要件相同之罪名，顯是基於概括犯意\n      反覆而為，應依連續犯之規定以一罪論，並依法加重其刑。又被告前因懲治盜\n      匪條例案件，經臺灣高雄地方法院以七十九年少訴字第四一號判決判處有期徒\n      刑七年三月確定，嗣減刑為有期徒刑六年七月，嗣執行中於八十一年十二月十\n      八日假釋出監，八十五年六月二十八日期滿，假釋未經撤銷，所處徒刑以已執\n      行完畢論而執行完畢等情，有臺灣高等法院被告全國前案紀錄表可參，其於有\n      期徒刑執行完畢後，五年內再犯有期徒刑以上之罪，為累犯，應依法加重其刑\n      ，並遞加重之。\n（二）本院審酌被告甲○○○因沉溺賭博，為償賭債而為本件犯行，不僅未主動與正\n      利公司等商談清償事宜，甚而逃匿無蹤，本應從重量刑；但念其犯後態度良好\n      ，坦承犯行等一切情狀，量處如主文所示之刑。又被告於行為後，刑法第四十\n      一條於九十年一月十日修正公布，同月十二日生效施行，修正後條文規定：「\n      犯最重本刑為五年以下有期徒刑之罪，而受六月以下有期徒刑或拘役之宣告，\n      因身體、教育、職業或家庭之關係或因其他正當事由，執行顯有困難者，得以\n      一元以上三元以下折算一日，易科罰金。但確因不執行所宣告之刑，難收矯正\n      之效或難以維持法秩序者，不在此限」，較諸修正前舊法，以犯最重本刑為三\n      年以下有期徒刑之罪，而受六月以下有期徒刑之宣告，始得易科罰金之規定，\n      新法顯然對被告較為有利，依刑法第二條第一項前段，應適用裁判時法即修正\n      後刑法第四十一條第一項前段，諭知易科罰金之折算標準。\n三、本件檢察官原依通常程序起訴，經本院合議庭認為符合刑事訴訟法第四百四十九\n    條第二項所定之情形，因此逕以簡易判決處刑。又被告於本院審理時表示願受有\n    期徒刑六月之刑度，經檢察官當庭同意，向本院為相同之求刑，本院因而於檢察\n    官求刑之範圍為判決，依刑事訴訟法第四百五十五條之一第二項規定，檢察官及\n    被告對本判決均不得上訴，附此敘明。\n四、適用之法條：刑事訴訟法第四百四十九條第二項、第四百五十一條之一第四項前\n    段，刑法第二條第一項前段、第五十六條、第三百三十九條第一項、第四十七條\n    、修正後刑法第四十一條第一項前段，罰金罰鍰提高標準條例第一條前段、第二\n    條。\n本案經檢察官崔秉君到庭執行職務\n中      華      民      國      九十三    年      三      月    十八    日\n                                臺灣桃園地方法院刑事第十一庭\n                                    法  官  邱蓮華\n右正本證明與原本無異。\n不得上訴。\n                                    書記官  何慧娟\n中      華      民      國      九十三     年      三     月   二十四   日\n附錄論罪科刑法條\n刑法第三百三十九條第一項\n意圖為自己或第三人不法之所有，以詐術使人將本人或第三人之物交付者，處五年以\n下有期徒刑、拘役或科、或併科一千元以下罰金。\n",
  "structure": {
    "main": "甲○○○連續意圖為自己不法之所有，以詐術使人將本人之物交付，累犯，處有期徒\n刑陸月，如易科罰金，以參佰元折算壹日。",
    "fact": "一、甲○○○前因懲治盜匪條例案件，經臺灣高雄地方法院於民國七十九年六月十四\n    日，以七十九年少訴字第四一號判決判處有期徒刑七年三月，同年七月二十三日\n    確定，嗣減刑為有期徒刑六年七月，八十一年十二月十八日假釋出監，假釋期間\n    付保護管束，八十五年六月二十八日期滿，假釋未經撤銷，所處徒刑以已執行完\n    畢論而執行完畢。其明知自己已無清償貨款之資力，竟為償還賭債新台幣（下同\n    ）二百多萬元，仍基於意圖為自己不法所有之概括犯意，於八十六年十二月期間\n    ，先後向正利實業股份有限公司（下稱正利公司）、祥邁企業有限公司（下稱祥\n    邁公司）、及廖本淵購買塑膠原料，使正利公司之業務員、祥邁公司之承辦人楊\n    詔雄及廖本淵等人陷於錯誤，分別依約陸續交付價值一百二十萬元、四十萬元、\n    十餘萬元之塑膠原料予甲○○○。嗣因甲○○○給付之支票均未獲兌現，又行蹤\n    不明，正利公司等始知受騙。\n二、案經被害人正利公司、祥邁公司及廖本淵訴由臺灣桃園地方法院檢察署檢察官偵\n    查起訴。",
    "reason": "一、認定事實所憑之證據及理由\n（一）事實欄所載之犯罪事實，除被告甲○○○於本院審理時之自白外，另有正利公\n      司、祥邁公司及廖本淵分別提出之送貨單、帳冊、支票影本等可證，並與正利\n      公司、祥邁公司及廖本淵告訴之內容，及正利公司負責人鄭子儀、祥邁公司承\n      辦人楊詔雄於檢察官訊問之陳述相符，已足擔保被告自白之真實性。\n（二）被告雖稱給付予祥邁公司之支票票面金額之所以記載為四十萬元，是因為當時\n      已經沒有錢支付，就請朋友彭美玲隨便開一張支票轉交給楊詔雄，但購買之原\n      料應該只有二十八萬元等語；然一般人從事交易時，為支付應付債務而簽發支\n      票，其票面金額應與應付債務之金額相同，實無超額支付之可能，被告此部份\n      辯解不足採信。又廖本淵雖於檢察官偵訊時稱被告向其訂購四十萬元之塑膠原\n      料，然並未提出任何收據或憑證，依罪疑為輕之原則，應認為被告詐騙廖本淵\n      之塑膠原料價值約十多萬元。\n（三）綜合以上證據，足認被告連續向正利公司、祥邁公司及廖本淵詐騙價值共約一\n      百七十多萬元之塑膠原料，本件事證明確，已足以認定被告確有事實欄所載犯\n      行。\n二、論罪科刑之依據\n（一）被告甲○○○所為，犯刑法第三百三十九條第一項詐欺取財罪，其先後數次詐\n      欺行為，時間緊接，方法相同，觸犯構成要件相同之罪名，顯是基於概括犯意\n      反覆而為，應依連續犯之規定以一罪論，並依法加重其刑。又被告前因懲治盜\n      匪條例案件，經臺灣高雄地方法院以七十九年少訴字第四一號判決判處有期徒\n      刑七年三月確定，嗣減刑為有期徒刑六年七月，嗣執行中於八十一年十二月十\n      八日假釋出監，八十五年六月二十八日期滿，假釋未經撤銷，所處徒刑以已執\n      行完畢論而執行完畢等情，有臺灣高等法院被告全國前案紀錄表可參，其於有\n      期徒刑執行完畢後，五年內再犯有期徒刑以上之罪，為累犯，應依法加重其刑\n      ，並遞加重之。\n（二）本院審酌被告甲○○○因沉溺賭博，為償賭債而為本件犯行，不僅未主動與正\n      利公司等商談清償事宜，甚而逃匿無蹤，本應從重量刑；但念其犯後態度良好\n      ，坦承犯行等一切情狀，量處如主文所示之刑。又被告於行為後，刑法第四十\n      一條於九十年一月十日修正公布，同月十二日生效施行，修正後條文規定：「\n      犯最重本刑為五年以下有期徒刑之罪，而受六月以下有期徒刑或拘役之宣告，\n      因身體、教育、職業或家庭之關係或因其他正當事由，執行顯有困難者，得以\n      一元以上三元以下折算一日，易科罰金。但確因不執行所宣告之刑，難收矯正\n      之效或難以維持法秩序者，不在此限」，較諸修正前舊法，以犯最重本刑為三\n      年以下有期徒刑之罪，而受六月以下有期徒刑之宣告，始得易科罰金之規定，\n      新法顯然對被告較為有利，依刑法第二條第一項前段，應適用裁判時法即修正\n      後刑法第四十一條第一項前段，諭知易科罰金之折算標準。\n三、本件檢察官原依通常程序起訴，經本院合議庭認為符合刑事訴訟法第四百四十九\n    條第二項所定之情形，因此逕以簡易判決處刑。又被告於本院審理時表示願受有\n    期徒刑六月之刑度，經檢察官當庭同意，向本院為相同之求刑，本院因而於檢察\n    官求刑之範圍為判決，依刑事訴訟法第四百五十五條之一第二項規定，檢察官及\n    被告對本判決均不得上訴，附此敘明。\n四、適用之法條：刑事訴訟法第四百四十九條第二項、第四百五十一條之一第四項前\n    段，刑法第二條第一項前段、第五十六條、第三百三十九條第一項、第四十七條\n    、修正後刑法第四十一條第一項前段，罰金罰鍰提高標準條例第一條前段、第二\n    條。\n本案經檢察官崔秉君到庭執行職務\n中      華      民      國      九十三    年      三      月    十八    日\n                                臺灣桃園地方法院刑事第十一庭\n                                    法  官  邱蓮華\n右正本證明與原本無異。\n不得上訴。\n                                    書記官  何慧娟"
  },
  "search": "臺灣桃園地方法院刑事簡易判決九十三年度簡字第七七號公訴人臺灣桃園地方法院檢察署檢察官被告甲○○○右列被告因妨害風化案件，檢察官以通常程序起訴（八十七年度偵字第三五三一號），本院認為宜以簡易判決處刑，茲判決如左：主文甲○○○連續意圖為自己不法之所有，以詐術使人將本人之物交付，累犯，處有期徒刑陸月，如易科罰金，以參佰元折算壹日。事實一、甲○○○前因懲治盜匪條例案件，經臺灣高雄地方法院於民國七十九年六月十四日，以七十九年少訴字第四一號判決判處有期徒刑七年三月，同年七月二十三日確定，嗣減刑為有期徒刑六年七月，八十一年十二月十八日假釋出監，假釋期間付保護管束，八十五年六月二十八日期滿，假釋未經撤銷，所處徒刑以已執行完畢論而執行完畢。其明知自己已無清償貨款之資力，竟為償還賭債新台幣（下同）二百多萬元，仍基於意圖為自己不法所有之概括犯意，於八十六年十二月期間，先後向正利實業股份有限公司（下稱正利公司）、祥邁企業有限公司（下稱祥邁公司）、及廖本淵購買塑膠原料，使正利公司之業務員、祥邁公司之承辦人楊詔雄及廖本淵等人陷於錯誤，分別依約陸續交付價值一百二十萬元、四十萬元、十餘萬元之塑膠原料予甲○○○。嗣因甲○○○給付之支票均未獲兌現，又行蹤不明，正利公司等始知受騙。二、案經被害人正利公司、祥邁公司及廖本淵訴由臺灣桃園地方法院檢察署檢察官偵查起訴。理由一、認定事實所憑之證據及理由（一）事實欄所載之犯罪事實，除被告甲○○○於本院審理時之自白外，另有正利公司、祥邁公司及廖本淵分別提出之送貨單、帳冊、支票影本等可證，並與正利公司、祥邁公司及廖本淵告訴之內容，及正利公司負責人鄭子儀、祥邁公司承辦人楊詔雄於檢察官訊問之陳述相符，已足擔保被告自白之真實性。（二）被告雖稱給付予祥邁公司之支票票面金額之所以記載為四十萬元，是因為當時已經沒有錢支付，就請朋友彭美玲隨便開一張支票轉交給楊詔雄，但購買之原料應該只有二十八萬元等語；然一般人從事交易時，為支付應付債務而簽發支票，其票面金額應與應付債務之金額相同，實無超額支付之可能，被告此部份辯解不足採信。又廖本淵雖於檢察官偵訊時稱被告向其訂購四十萬元之塑膠原料，然並未提出任何收據或憑證，依罪疑為輕之原則，應認為被告詐騙廖本淵之塑膠原料價值約十多萬元。（三）綜合以上證據，足認被告連續向正利公司、祥邁公司及廖本淵詐騙價值共約一百七十多萬元之塑膠原料，本件事證明確，已足以認定被告確有事實欄所載犯行。二、論罪科刑之依據（一）被告甲○○○所為，犯刑法第三百三十九條第一項詐欺取財罪，其先後數次詐欺行為，時間緊接，方法相同，觸犯構成要件相同之罪名，顯是基於概括犯意反覆而為，應依連續犯之規定以一罪論，並依法加重其刑。又被告前因懲治盜匪條例案件，經臺灣高雄地方法院以七十九年少訴字第四一號判決判處有期徒刑七年三月確定，嗣減刑為有期徒刑六年七月，嗣執行中於八十一年十二月十八日假釋出監，八十五年六月二十八日期滿，假釋未經撤銷，所處徒刑以已執行完畢論而執行完畢等情，有臺灣高等法院被告全國前案紀錄表可參，其於有期徒刑執行完畢後，五年內再犯有期徒刑以上之罪，為累犯，應依法加重其刑，並遞加重之。（二）本院審酌被告甲○○○因沉溺賭博，為償賭債而為本件犯行，不僅未主動與正利公司等商談清償事宜，甚而逃匿無蹤，本應從重量刑；但念其犯後態度良好，坦承犯行等一切情狀，量處如主文所示之刑。又被告於行為後，刑法第四十一條於九十年一月十日修正公布，同月十二日生效施行，修正後條文規定：「犯最重本刑為五年以下有期徒刑之罪，而受六月以下有期徒刑或拘役之宣告，因身體、教育、職業或家庭之關係或因其他正當事由，執行顯有困難者，得以一元以上三元以下折算一日，易科罰金。但確因不執行所宣告之刑，難收矯正之效或難以維持法秩序者，不在此限」，較諸修正前舊法，以犯最重本刑為三年以下有期徒刑之罪，而受六月以下有期徒刑之宣告，始得易科罰金之規定，新法顯然對被告較為有利，依刑法第二條第一項前段，應適用裁判時法即修正後刑法第四十一條第一項前段，諭知易科罰金之折算標準。三、本件檢察官原依通常程序起訴，經本院合議庭認為符合刑事訴訟法第四百四十九條第二項所定之情形，因此逕以簡易判決處刑。又被告於本院審理時表示願受有期徒刑六月之刑度，經檢察官當庭同意，向本院為相同之求刑，本院因而於檢察官求刑之範圍為判決，依刑事訴訟法第四百五十五條之一第二項規定，檢察官及被告對本判決均不得上訴，附此敘明。四、適用之法條：刑事訴訟法第四百四十九條第二項、第四百五十一條之一第四項前段，刑法第二條第一項前段、第五十六條、第三百三十九條第一項、第四十七條、修正後刑法第四十一條第一項前段，罰金罰鍰提高標準條例第一條前段、第二條。本案經檢察官崔秉君到庭執行職務中華民國九十三年三月十八日臺灣桃園地方法院刑事第十一庭法官邱蓮華右正本證明與原本無異。不得上訴。書記官何慧娟中華民國九十三年三月二十四日附錄論罪科刑法條刑法第三百三十九條第一項意圖為自己或第三人不法之所有，以詐術使人將本人或第三人之物交付者，處五年以下有期徒刑、拘役或科、或併科一千元以下罰金。",
  "characters": {
    "judges": [
      "邱蓮華"
    ],
    "prosecutors": [
      "崔秉君"
    ],
    "lawyers": [

    ],
    "clerks": [
      "何慧娟"
    ],
    "plaintiffs": [

    ],
    "defendants": [
      "甲○○○",
      "右列被告因妨害風化案件，檢察官以通常程序起訴（八十七年度偵字第三五三一號）",
      "，本院認為宜以簡易判決處刑，茲判決如左："
    ],
    "prosecutor_office": [
      "臺灣桃園地方法院檢察署檢察官"
    ],
    "creditors": [

    ],
    "debtors": [

    ],
    "judicial_associate_officer": [

    ]
  },
  "adjudged_at": "2004-03-18",
  "created_at": "2016-02-06 10:01:29",
  "updated_at": "2016-02-06 10:01:29"
}