{
  "identify": "MLD-94-苗簡-870-20051111-1",
  "court": {
    "name": "臺灣苗栗地方法院",
    "code": "MLD"
  },
  "division": {
    "name": "刑事",
    "code": "M"
  },
  "year": 94,
  "word": "苗簡",
  "number": "870",
  "jcheck": "1",
  "reason": "竊盜",
  "content": "臺灣苗栗地方法院刑事簡易判決         94年度苗簡字第870號\n聲  請  人  臺灣苗栗地方法院檢察署檢察官\n被      告  乙○○\n上列被告因竊盜案件，經檢察官聲請以簡易判決處刑（94年度速\n偵字第533號），本院判決如下：\n    主  文\n乙○○竊盜，處有期徒刑肆月，如易科罰金，以參佰元折算壹日\n。\n    理  由\n一、犯罪事實：乙○○為變賣現金花用，竟意圖為自己不法之所\n    有，於民國94年10月9 日5 時50分許，駕駛其母親所有車牌\n    號碼JR-5686 號之自小客車，前往苗栗縣頭份鎮上興里臺灣\n    高鐵91公里處臺灣高速鐵路公司所有價值約新台幣（下同）\n    115,000 元，現由甲○○保管之高鐵電纜線2 條（分別為批\n    號：R4104 0 、600V、VVR 暗綠色接地線、長18米；及批號\n    ：600U、NH-IE 綠色電纜線、長34米），其中1 條電纜線放\n    置地上，另1 條則以徒手拉扯錫製接頭扯斷之方式予以竊取\n    後，逕以上開自小客車載往苗栗縣頭份鎮○○里○○路河堤\n    旁，拿其在家中外甥所有之美工刀剝除纜線外皮，嗣於同日\n    6 時40分許，在上揭河堤處為警當場查獲，並扣得其竊取之\n    上開電纜線，再循線查悉上情。\n二、證據名稱：\n  （一）被告乙○○於警詢及偵訊中之自白。\n  （二）告訴人甲○○於警詢中之指述。\n  （三）查獲之現場照片4張。\n  （四）贓物認領保管單1紙。\n三、論罪科刑部分：\n  （一）核被告乙○○所為，係犯刑法第320條第1項之竊盜罪。\n  （二）審酌被告之犯罪動機、目的、手段係為變賣現金花用、\n        而以拉扯之方式徒手竊取、所竊取財物為電纜線2 條、\n        價值具被害人稱約115,000 元、業經被害人領回所生之\n        危害、犯後坦承犯行之態度，併參酌被告於94年10月9\n        日在檢察官訊問中表示同意聲請以簡易判決處刑有期徒\n        刑4 月等一切情狀，及本件無刑事訴訟法第451 條之1\n        第4 項但書之情形，是本院於聲請人求刑之範圍內判處\n        如主文所示之刑，併諭知易科罰金之折算標準。\n四、應適用法條：\n（一）刑事訴訟法第449條第1項。\n（二）刑法第320條第1項、第41條第1項前段。\n（三）罰金罰鍰提高標準條例第1條前段、第2條。\n五、本判決係依刑事訴訟法第451 條之1 第4 項所為之判決，依\n    同法第455 條之1 第2 項之規定不得上訴。\n中    華    民    國    94    年    11    月    11    日\n                  苗栗簡易庭    法  官  張珈禎\n以上正本證明與原本無異。\n                                書記官  黃雅琦\n中    華    民    國    94    年    11    月    21    日\n附錄本判決論罪科刑法條全文：\n刑法第320條第1項\n意圖為自己或第三人不法之所有，而竊取他人之動產者，為竊盜\n罪，處五年以下有期徒刑、拘役或五百元以下罰金。\n",
  "structure": {
    "main": "乙○○竊盜，處有期徒刑肆月，如易科罰金，以參佰元折算壹日\n。",
    "reason": "一、犯罪事實：乙○○為變賣現金花用，竟意圖為自己不法之所\n    有，於民國94年10月9 日5 時50分許，駕駛其母親所有車牌\n    號碼JR-5686 號之自小客車，前往苗栗縣頭份鎮上興里臺灣\n    高鐵91公里處臺灣高速鐵路公司所有價值約新台幣（下同）\n    115,000 元，現由甲○○保管之高鐵電纜線2 條（分別為批\n    號：R4104 0 、600V、VVR 暗綠色接地線、長18米；及批號\n    ：600U、NH-IE 綠色電纜線、長34米），其中1 條電纜線放\n    置地上，另1 條則以徒手拉扯錫製接頭扯斷之方式予以竊取\n    後，逕以上開自小客車載往苗栗縣頭份鎮○○里○○路河堤\n    旁，拿其在家中外甥所有之美工刀剝除纜線外皮，嗣於同日\n    6 時40分許，在上揭河堤處為警當場查獲，並扣得其竊取之\n    上開電纜線，再循線查悉上情。\n二、證據名稱：\n  （一）被告乙○○於警詢及偵訊中之自白。\n  （二）告訴人甲○○於警詢中之指述。\n  （三）查獲之現場照片4張。\n  （四）贓物認領保管單1紙。\n三、論罪科刑部分：\n  （一）核被告乙○○所為，係犯刑法第320條第1項之竊盜罪。\n  （二）審酌被告之犯罪動機、目的、手段係為變賣現金花用、\n        而以拉扯之方式徒手竊取、所竊取財物為電纜線2 條、\n        價值具被害人稱約115,000 元、業經被害人領回所生之\n        危害、犯後坦承犯行之態度，併參酌被告於94年10月9\n        日在檢察官訊問中表示同意聲請以簡易判決處刑有期徒\n        刑4 月等一切情狀，及本件無刑事訴訟法第451 條之1\n        第4 項但書之情形，是本院於聲請人求刑之範圍內判處\n        如主文所示之刑，併諭知易科罰金之折算標準。\n四、應適用法條：\n（一）刑事訴訟法第449條第1項。\n（二）刑法第320條第1項、第41條第1項前段。\n（三）罰金罰鍰提高標準條例第1條前段、第2條。\n五、本判決係依刑事訴訟法第451 條之1 第4 項所為之判決，依\n    同法第455 條之1 第2 項之規定不得上訴。"
  },
  "search": "臺灣苗栗地方法院刑事簡易判決94年度苗簡字第870號聲請人臺灣苗栗地方法院檢察署檢察官被告乙○○上列被告因竊盜案件，經檢察官聲請以簡易判決處刑（94年度速偵字第533號），本院判決如下：主文乙○○竊盜，處有期徒刑肆月，如易科罰金，以參佰元折算壹日。理由一、犯罪事實：乙○○為變賣現金花用，竟意圖為自己不法之所有，於民國94年10月9日5時50分許，駕駛其母親所有車牌號碼JR-5686號之自小客車，前往苗栗縣頭份鎮上興里臺灣高鐵91公里處臺灣高速鐵路公司所有價值約新台幣（下同）115,000元，現由甲○○保管之高鐵電纜線2條（分別為批號：R41040、600V、VVR暗綠色接地線、長18米；及批號：600U、NH-IE綠色電纜線、長34米），其中1條電纜線放置地上，另1條則以徒手拉扯錫製接頭扯斷之方式予以竊取後，逕以上開自小客車載往苗栗縣頭份鎮○○里○○路河堤旁，拿其在家中外甥所有之美工刀剝除纜線外皮，嗣於同日6時40分許，在上揭河堤處為警當場查獲，並扣得其竊取之上開電纜線，再循線查悉上情。二、證據名稱：（一）被告乙○○於警詢及偵訊中之自白。（二）告訴人甲○○於警詢中之指述。（三）查獲之現場照片4張。（四）贓物認領保管單1紙。三、論罪科刑部分：（一）核被告乙○○所為，係犯刑法第320條第1項之竊盜罪。（二）審酌被告之犯罪動機、目的、手段係為變賣現金花用、而以拉扯之方式徒手竊取、所竊取財物為電纜線2條、價值具被害人稱約115,000元、業經被害人領回所生之危害、犯後坦承犯行之態度，併參酌被告於94年10月9日在檢察官訊問中表示同意聲請以簡易判決處刑有期徒刑4月等一切情狀，及本件無刑事訴訟法第451條之1第4項但書之情形，是本院於聲請人求刑之範圍內判處如主文所示之刑，併諭知易科罰金之折算標準。四、應適用法條：（一）刑事訴訟法第449條第1項。（二）刑法第320條第1項、第41條第1項前段。（三）罰金罰鍰提高標準條例第1條前段、第2條。五、本判決係依刑事訴訟法第451條之1第4項所為之判決，依同法第455條之1第2項之規定不得上訴。中華民國94年11月11日苗栗簡易庭法官張珈禎以上正本證明與原本無異。書記官黃雅琦中華民國94年11月21日附錄本判決論罪科刑法條全文：刑法第320條第1項意圖為自己或第三人不法之所有，而竊取他人之動產者，為竊盜罪，處五年以下有期徒刑、拘役或五百元以下罰金。",
  "characters": {
    "judges": [
      "張珈禎"
    ],
    "prosecutors": [

    ],
    "lawyers": [

    ],
    "clerks": [
      "黃雅琦"
    ],
    "plaintiffs": [

    ],
    "defendants": [
      "乙○○"
    ],
    "prosecutor_office": [
      "臺灣苗栗地方法院檢察署檢察官"
    ],
    "creditors": [

    ],
    "debtors": [

    ],
    "judicial_associate_officer": [

    ]
  },
  "adjudged_at": "2005-11-11",
  "created_at": "2016-02-07 00:00:04",
  "updated_at": "2016-02-07 00:00:04"
}