{
  "identify": "TPD-94-訴-992-20051111-1",
  "court": {
    "name": "臺灣臺北地方法院",
    "code": "TPD"
  },
  "division": {
    "name": "刑事",
    "code": "M"
  },
  "year": 94,
  "word": "訴",
  "number": "992",
  "jcheck": "1",
  "reason": "違反稅捐稽徵法等",
  "content": "臺灣臺北地方法院刑事判決               94年度訴字第992號\n公  訴  人  臺灣臺北地方法院檢察署檢察官\n被      告  乙○○\n上列被告因違反稅捐稽徵法等案件，經檢察官聲請簡易判決處刑\n（九十四年度偵續字第一六九號），本院認為不宜以簡易判決處\n刑，改依通常程序審理，經被告於本院準備程序時時自白犯罪，\n本院合議庭裁定改依簡式審判程序審理，本院判決如下：\n    主  文\n乙○○納稅義務人以詐術逃漏稅捐，處有期徒刑期肆月，如易科\n罰金以參佰元折算壹日；緩刑貳年。\n    事  實\n一、乙○○於民國八十九年間，在位於臺北市中山區○○○路四\n    ００號三樓慶耀營造有限公司（下稱慶耀公司）擔任臨時性\n    工頭，為逃漏個人綜合所得稅之繳納，明知甲○○於八十九\n    年間並未受僱於慶耀公司，亦未領取任何薪資或報酬，竟利\n    用係甲○○前雇主身分，曾取得甲○○之身分證影本及印章\n    未歸還之機會，於八十九年底某日，在台北縣樹林市某處工\n    地，盜蓋甲○○之印章押蓋於慶耀公司工資清冊上盜用甲○\n    ○之印章一次，連同將甲○○之身分證影本交付與不知情之\n    慶耀公司負責人陳耀騰，受領薪資新台幣（下同）四十萬元\n    ，足生損害於甲○○及慶耀公司，陳耀騰因而將甲○○八十\n    九年間自慶耀公司受領薪資四十萬元之事項登載於各類所得\n    扣繳暨免扣繳憑單上，並於九十年間，據以向財政部臺灣省\n    北區國稅局中和稽徵所申報扣抵營利事業所得稅。乙○○於\n    九十年年四月四日，據以向財政部臺灣省北區國稅局中和稽\n    徵所申報八十九年度個人綜合所得稅之際，明知前開虛偽向\n    慶耀公司所領取甲○○四十萬元之工資，為其所領取，應列\n    入其薪資所得內，竟於偽以前開甲○○已向其領走工資之詐\n    術，於申報單上漏報前開四十萬之薪資所得，計逃漏八十九\n    年度個人綜合所得稅十二萬八千四百零三元。\n二、案經甲○○訴由臺北縣政府警察局永和分局報請台灣台北地\n    方法院檢察署檢察官聲請簡易判決處刑，經本院認為不宜以\n    簡易判決處刑，改依通常程序審理，經被告於本院準備程序\n    時時自白犯罪，本院合議庭裁定改依簡式審判程序審理。\n    理  由\n一、右揭事實，業據被告乙○○於本院審訊中坦承不諱，核與告\n    訴人甲○○之指訴相符，復有各類所得扣繳憑單、切結書、\n    財政部台灣省北區國稅局中和稽徵所九十四年四月七日函及\n    財政部台灣省北區國稅局代收移送行政執行處滯納綜合所得\n    稅稅款及財務罰鍰繳款書等件在卷可稽，被告自白經前開證\n    據補強，應與事實相符，本件事證明確，被告犯行應堪認定\n    。\n二、核被告所為，係犯刑法第二百十七條第二項盜用印章罪及稅\n    捐稽徵法第四十一條之為納稅義務人以詐術逃漏稅捐罪。起\n    訴書就被告前開盜蓋甲○○之印章於工資清冊之之行為，認\n    係被告涉犯刑法第二百十條、第二百十六條行使偽造私文書\n    ，業經蒞庭檢察官於九十四年十月二十一日到庭更正，係被\n    告涉犯盜用印章罪所為，並據以論告（見本院當日筆錄），\n    依檢察一體原則，應以蒞庭檢察官到庭更正者為檢察官所引\n    應適用之法條，此部分已無變更起訴法條之問題。又被告之\n    盜蓋印章與以詐術逃漏稅捐間，有方法結果之牽連關係，為\n    牽連犯，應從一重之以詐術逃漏稅捐罪處斷。爰審酌被告之\n    素行、動機、不法目的、手段、領取工資及逃漏稅捐之數額\n    與犯後坦承犯行等一切情狀，量處如主文所示之刑，並諭知\n    易科罰金之折算標準。又按被告犯罪後刑法第四十一條業經\n    立法院於九十年一月四日修正，於同年一月十二日生效，將\n    易科罰金之適用範圍擴大為「最重本刑五年以下有期徒刑之\n    罪，而受六月以下有期徒刑或拘役之宣告」規定，爰依刑法\n    第二條第一項前段之規定，自應適用新修正之刑法四十一條\n    第一項定其易科罰金之折算標準，附此敘明。末查被告前未\n    曾受有期徒刑以上刑之宣告，有台灣高等法院被告前案紀錄\n    表乙紙附卷可稽，其犯罪後，已深知悔悟，且被告已將逃漏\n    之稅額繳納，此亦有財政部台灣省北區國稅局代收移送行政\n    執行處滯納綜合所得稅稅款及財務罰鍰繳款書二紙在卷可稽\n    ，本院認其經此教訓後，當知警惕，應無再犯之虞，因認其\n    所宣告之刑，以暫不執行為適當，併予宣告緩刑二年，以勵\n    來茲而啟自新。\n據上論斷，應依刑事訴訟法第四百五十二條、第二百七十三條之\n一、第二百九十九條第一項前段，稅捐稽徵法第第四十一條，刑\n法第二條第一項前段、第十一條第一項前段、第二百十七條第二\n項、第一項、第五十五條、第四十一條第一項前段、第七十四條\n第一款，罰金罰鍰提高標準條例第一條前段、第二條，判決如主\n文。\n本案經檢察官林良蓉到庭執行職務\n中    華    民    國    94    年    11    月    11    日\n                          刑事第八庭法  官  陳德民\n上正本證明與原本無異。\n如不服本判決，應於判決送達後10日內，向本院提出上訴狀。\n                                    書記官  張漪蕙\n中    華    民    國    94    年    11    月    11    日\n附錄本案論罪科刑法條全文\n中華民國刑法第二百十七條\n(偽造盜用印章印文或署押罪)\n偽造印章、印文或署押，足以生損害於公眾或他人者，處3年以\n下有期徒刑。\n盜用印章、印文或署押，足以生損害於公眾或他人者，亦同。\n稅捐稽徵法第四十一條\n納稅義務人以詐術或其他不正當方法逃漏稅捐者，處五年以下有\n期徒刑、拘役或科或併科新台幣六萬元以下罰金。\n",
  "structure": {
    "main": "乙○○納稅義務人以詐術逃漏稅捐，處有期徒刑期肆月，如易科\n罰金以參佰元折算壹日；緩刑貳年。",
    "fact": "一、乙○○於民國八十九年間，在位於臺北市中山區○○○路四\n    ００號三樓慶耀營造有限公司（下稱慶耀公司）擔任臨時性\n    工頭，為逃漏個人綜合所得稅之繳納，明知甲○○於八十九\n    年間並未受僱於慶耀公司，亦未領取任何薪資或報酬，竟利\n    用係甲○○前雇主身分，曾取得甲○○之身分證影本及印章\n    未歸還之機會，於八十九年底某日，在台北縣樹林市某處工\n    地，盜蓋甲○○之印章押蓋於慶耀公司工資清冊上盜用甲○\n    ○之印章一次，連同將甲○○之身分證影本交付與不知情之\n    慶耀公司負責人陳耀騰，受領薪資新台幣（下同）四十萬元\n    ，足生損害於甲○○及慶耀公司，陳耀騰因而將甲○○八十\n    九年間自慶耀公司受領薪資四十萬元之事項登載於各類所得\n    扣繳暨免扣繳憑單上，並於九十年間，據以向財政部臺灣省\n    北區國稅局中和稽徵所申報扣抵營利事業所得稅。乙○○於\n    九十年年四月四日，據以向財政部臺灣省北區國稅局中和稽\n    徵所申報八十九年度個人綜合所得稅之際，明知前開虛偽向\n    慶耀公司所領取甲○○四十萬元之工資，為其所領取，應列\n    入其薪資所得內，竟於偽以前開甲○○已向其領走工資之詐\n    術，於申報單上漏報前開四十萬之薪資所得，計逃漏八十九\n    年度個人綜合所得稅十二萬八千四百零三元。\n二、案經甲○○訴由臺北縣政府警察局永和分局報請台灣台北地\n    方法院檢察署檢察官聲請簡易判決處刑，經本院認為不宜以\n    簡易判決處刑，改依通常程序審理，經被告於本院準備程序\n    時時自白犯罪，本院合議庭裁定改依簡式審判程序審理。",
    "reason": "一、右揭事實，業據被告乙○○於本院審訊中坦承不諱，核與告\n    訴人甲○○之指訴相符，復有各類所得扣繳憑單、切結書、\n    財政部台灣省北區國稅局中和稽徵所九十四年四月七日函及\n    財政部台灣省北區國稅局代收移送行政執行處滯納綜合所得\n    稅稅款及財務罰鍰繳款書等件在卷可稽，被告自白經前開證\n    據補強，應與事實相符，本件事證明確，被告犯行應堪認定\n    。\n二、核被告所為，係犯刑法第二百十七條第二項盜用印章罪及稅\n    捐稽徵法第四十一條之為納稅義務人以詐術逃漏稅捐罪。起\n    訴書就被告前開盜蓋甲○○之印章於工資清冊之之行為，認\n    係被告涉犯刑法第二百十條、第二百十六條行使偽造私文書\n    ，業經蒞庭檢察官於九十四年十月二十一日到庭更正，係被\n    告涉犯盜用印章罪所為，並據以論告（見本院當日筆錄），\n    依檢察一體原則，應以蒞庭檢察官到庭更正者為檢察官所引\n    應適用之法條，此部分已無變更起訴法條之問題。又被告之\n    盜蓋印章與以詐術逃漏稅捐間，有方法結果之牽連關係，為\n    牽連犯，應從一重之以詐術逃漏稅捐罪處斷。爰審酌被告之\n    素行、動機、不法目的、手段、領取工資及逃漏稅捐之數額\n    與犯後坦承犯行等一切情狀，量處如主文所示之刑，並諭知\n    易科罰金之折算標準。又按被告犯罪後刑法第四十一條業經\n    立法院於九十年一月四日修正，於同年一月十二日生效，將\n    易科罰金之適用範圍擴大為「最重本刑五年以下有期徒刑之\n    罪，而受六月以下有期徒刑或拘役之宣告」規定，爰依刑法\n    第二條第一項前段之規定，自應適用新修正之刑法四十一條\n    第一項定其易科罰金之折算標準，附此敘明。末查被告前未\n    曾受有期徒刑以上刑之宣告，有台灣高等法院被告前案紀錄\n    表乙紙附卷可稽，其犯罪後，已深知悔悟，且被告已將逃漏\n    之稅額繳納，此亦有財政部台灣省北區國稅局代收移送行政\n    執行處滯納綜合所得稅稅款及財務罰鍰繳款書二紙在卷可稽\n    ，本院認其經此教訓後，當知警惕，應無再犯之虞，因認其\n    所宣告之刑，以暫不執行為適當，併予宣告緩刑二年，以勵\n    來茲而啟自新。\n據上論斷，應依刑事訴訟法第四百五十二條、第二百七十三條之\n一、第二百九十九條第一項前段，稅捐稽徵法第第四十一條，刑\n法第二條第一項前段、第十一條第一項前段、第二百十七條第二\n項、第一項、第五十五條、第四十一條第一項前段、第七十四條\n第一款，罰金罰鍰提高標準條例第一條前段、第二條，判決如主\n文。\n本案經檢察官林良蓉到庭執行職務\n中    華    民    國    94    年    11    月    11    日\n                          刑事第八庭法  官  陳德民\n上正本證明與原本無異。\n如不服本判決，應於判決送達後10日內，向本院提出上訴狀。\n                                    書記官  張漪蕙"
  },
  "search": "臺灣臺北地方法院刑事判決94年度訴字第992號公訴人臺灣臺北地方法院檢察署檢察官被告乙○○上列被告因違反稅捐稽徵法等案件，經檢察官聲請簡易判決處刑（九十四年度偵續字第一六九號），本院認為不宜以簡易判決處刑，改依通常程序審理，經被告於本院準備程序時時自白犯罪，本院合議庭裁定改依簡式審判程序審理，本院判決如下：主文乙○○納稅義務人以詐術逃漏稅捐，處有期徒刑期肆月，如易科罰金以參佰元折算壹日；緩刑貳年。事實一、乙○○於民國八十九年間，在位於臺北市中山區○○○路四００號三樓慶耀營造有限公司（下稱慶耀公司）擔任臨時性工頭，為逃漏個人綜合所得稅之繳納，明知甲○○於八十九年間並未受僱於慶耀公司，亦未領取任何薪資或報酬，竟利用係甲○○前雇主身分，曾取得甲○○之身分證影本及印章未歸還之機會，於八十九年底某日，在台北縣樹林市某處工地，盜蓋甲○○之印章押蓋於慶耀公司工資清冊上盜用甲○○之印章一次，連同將甲○○之身分證影本交付與不知情之慶耀公司負責人陳耀騰，受領薪資新台幣（下同）四十萬元，足生損害於甲○○及慶耀公司，陳耀騰因而將甲○○八十九年間自慶耀公司受領薪資四十萬元之事項登載於各類所得扣繳暨免扣繳憑單上，並於九十年間，據以向財政部臺灣省北區國稅局中和稽徵所申報扣抵營利事業所得稅。乙○○於九十年年四月四日，據以向財政部臺灣省北區國稅局中和稽徵所申報八十九年度個人綜合所得稅之際，明知前開虛偽向慶耀公司所領取甲○○四十萬元之工資，為其所領取，應列入其薪資所得內，竟於偽以前開甲○○已向其領走工資之詐術，於申報單上漏報前開四十萬之薪資所得，計逃漏八十九年度個人綜合所得稅十二萬八千四百零三元。二、案經甲○○訴由臺北縣政府警察局永和分局報請台灣台北地方法院檢察署檢察官聲請簡易判決處刑，經本院認為不宜以簡易判決處刑，改依通常程序審理，經被告於本院準備程序時時自白犯罪，本院合議庭裁定改依簡式審判程序審理。理由一、右揭事實，業據被告乙○○於本院審訊中坦承不諱，核與告訴人甲○○之指訴相符，復有各類所得扣繳憑單、切結書、財政部台灣省北區國稅局中和稽徵所九十四年四月七日函及財政部台灣省北區國稅局代收移送行政執行處滯納綜合所得稅稅款及財務罰鍰繳款書等件在卷可稽，被告自白經前開證據補強，應與事實相符，本件事證明確，被告犯行應堪認定。二、核被告所為，係犯刑法第二百十七條第二項盜用印章罪及稅捐稽徵法第四十一條之為納稅義務人以詐術逃漏稅捐罪。起訴書就被告前開盜蓋甲○○之印章於工資清冊之之行為，認係被告涉犯刑法第二百十條、第二百十六條行使偽造私文書，業經蒞庭檢察官於九十四年十月二十一日到庭更正，係被告涉犯盜用印章罪所為，並據以論告（見本院當日筆錄），依檢察一體原則，應以蒞庭檢察官到庭更正者為檢察官所引應適用之法條，此部分已無變更起訴法條之問題。又被告之盜蓋印章與以詐術逃漏稅捐間，有方法結果之牽連關係，為牽連犯，應從一重之以詐術逃漏稅捐罪處斷。爰審酌被告之素行、動機、不法目的、手段、領取工資及逃漏稅捐之數額與犯後坦承犯行等一切情狀，量處如主文所示之刑，並諭知易科罰金之折算標準。又按被告犯罪後刑法第四十一條業經立法院於九十年一月四日修正，於同年一月十二日生效，將易科罰金之適用範圍擴大為「最重本刑五年以下有期徒刑之罪，而受六月以下有期徒刑或拘役之宣告」規定，爰依刑法第二條第一項前段之規定，自應適用新修正之刑法四十一條第一項定其易科罰金之折算標準，附此敘明。末查被告前未曾受有期徒刑以上刑之宣告，有台灣高等法院被告前案紀錄表乙紙附卷可稽，其犯罪後，已深知悔悟，且被告已將逃漏之稅額繳納，此亦有財政部台灣省北區國稅局代收移送行政執行處滯納綜合所得稅稅款及財務罰鍰繳款書二紙在卷可稽，本院認其經此教訓後，當知警惕，應無再犯之虞，因認其所宣告之刑，以暫不執行為適當，併予宣告緩刑二年，以勵來茲而啟自新。據上論斷，應依刑事訴訟法第四百五十二條、第二百七十三條之一、第二百九十九條第一項前段，稅捐稽徵法第第四十一條，刑法第二條第一項前段、第十一條第一項前段、第二百十七條第二項、第一項、第五十五條、第四十一條第一項前段、第七十四條第一款，罰金罰鍰提高標準條例第一條前段、第二條，判決如主文。本案經檢察官林良蓉到庭執行職務中華民國94年11月11日刑事第八庭法官陳德民上正本證明與原本無異。如不服本判決，應於判決送達後10日內，向本院提出上訴狀。書記官張漪蕙中華民國94年11月11日附錄本案論罪科刑法條全文中華民國刑法第二百十七條(偽造盜用印章印文或署押罪)偽造印章、印文或署押，足以生損害於公眾或他人者，處3年以下有期徒刑。盜用印章、印文或署押，足以生損害於公眾或他人者，亦同。稅捐稽徵法第四十一條納稅義務人以詐術或其他不正當方法逃漏稅捐者，處五年以下有期徒刑、拘役或科或併科新台幣六萬元以下罰金。",
  "characters": {
    "judges": [
      "陳德民"
    ],
    "prosecutors": [
      "林良蓉"
    ],
    "lawyers": [

    ],
    "clerks": [
      "張漪蕙"
    ],
    "plaintiffs": [

    ],
    "defendants": [
      "乙○○"
    ],
    "prosecutor_office": [
      "臺灣臺北地方法院檢察署檢察官"
    ],
    "creditors": [

    ],
    "debtors": [

    ],
    "judicial_associate_officer": [

    ]
  },
  "adjudged_at": "2005-11-11",
  "created_at": "2016-02-06 23:57:55",
  "updated_at": "2016-02-06 23:57:55"
}