{
  "identify": "TPD-100-簡-2907-20111005-1",
  "court": {
    "name": "臺灣臺北地方法院",
    "code": "TPD"
  },
  "division": {
    "name": "刑事",
    "code": "M"
  },
  "year": 100,
  "word": "簡",
  "number": "2907",
  "jcheck": "1",
  "reason": "毒品危害防制條例",
  "content": "臺灣臺北地方法院刑事簡易判決         100年度簡字第2907號\n公  訴  人  臺灣臺北地方法院檢察署檢察官\n被      告  張輔元\n上列被告因毒品危害防制條例案件，經檢察官提起公訴（100 年\n度毒偵字第1465號），本院訊問被告後，被告自白犯罪，改以簡\n易判決處刑如下：\n    主  文\n張輔元施用第二級毒品，累犯，處有期徒刑肆月，如易科罰金，\n以新臺幣壹仟元折算壹日。\n    事實及理由\n一、本件犯罪事實及證據均援引檢察官起訴書之記載（如附件）\n    ，惟犯罪事實欄所載：(1)「98年度毒聲字第718 號裁定」應\n    更正為「96年度毒聲字第718 號裁定」。(2)「在不詳地點，\n    施用安非他命、甲基安非他命」應更正為「在新北市板橋區\n    某賓館，以吸食器燒烤方式施用甲基安非他命1 次，並於施\n    用後將吸食器丟棄滅失」。另並於證據欄增補：被告張輔元\n    於本院訊問時之自白。\n二、是核被告所為，係犯毒品危害防制條例第10條第2 項之施用\n    第二級毒品罪。其持有第二級毒品之低度行為，為施用之高\n    度行為所吸收，不另論罪。查被告有如犯罪事實欄所載之前\n    案及執行紀錄之事實，有臺灣高等法院被告前案紀錄表在卷\n    可徵，其於受有期徒刑執行完畢5 年以內，故意再犯本件有\n    期徒刑以上之罪，應依刑法第47條第1 項規定加重其刑。爰\n    審酌被告之品性、平日素行、犯罪之動機、施用毒品戕害己\n    身之犯罪手段、目的、施用次數及犯罪後尚知坦認犯行之態\n    度等一切情狀，量處如主文所示之刑，並諭知易科罰金折算\n    之標準。\n三、應依刑事訴訟法第449 條第2 項、第3 項、第454 條第2項\n    ，毒品危害防制條例第10條第2 項，刑法第11條、第47 條\n    第1 項、第41條第1 項前段，逕以簡易判決處如主文所示之\n    刑。\n四、對於本件判決如有不服，應於收受送達10日內，向本院提出\n    上訴書狀。\n中    華    民    國     100   年    10    月    5    日\n                               刑事第十三庭法  官 劉煌基\n上正本證明與原本無異。\n如不服本判決應於收受送達後10日內向本院提出上訴書狀，並應\n敘述具體理由；其未敘述上訴理由者，應於上訴期間屆滿後20日\n內向本院補提理由書（均須按他造當事人之人數附繕本）「切勿\n逕送上級法院」。\n                                           書記官 莊文茹\n中    華    民    國   100    年    10    月    5     日\n附錄本案論罪科刑法條：\n毒品危害防制條例第10條\n施用第一級毒品者，處 6 月以上 5 年以下有期徒刑。\n施用第二級毒品者，處 3 年以下有期徒刑。\n附件\n臺灣臺北地方法院檢察署檢察官起訴書\n                                   100年度毒偵字第1465號\n    被      告  張輔元  男  36歲（民國○○年○○月○○日生）\n                        住臺北市○○區○○路四段68號11樓\n                        之7\n                        居新北市○○區○○街58號3樓\n                        國民身分證統一編號：Ｚ000000000號\n上列被告因違反毒品危害防制條例案件，已經偵查終結，認應該\n提起公訴，茲將犯罪事實及證據並所犯法條分敘如下：\n        犯罪事實\n一、張輔元前因施用毒品案件，經臺灣板橋地方法院以98年度毒\n    聲字第718號裁定送臺灣臺北看守所附設勒戒處所觀察、勒\n    戒後，認無繼續施用毒品之傾向，於民國98年7月30日釋放\n    出所，並經臺灣板橋地方法院檢察署檢察官以98年度毒偵緝\n    字第340號案件為不起訴處分確定。復因違反藥事法等案件\n    ，經同法院以98年度訴緝字第198號判決處有期徒刑9月、4\n    月，並分別減刑為4月又15日、2月，應執行有期徒刑5月確\n    定，甫於99年4月1日縮刑期滿執行完畢。詎仍不知悔改，基\n    於施用第二級毒品之犯意，於100年1月7日下午1時許為警採\n    尿前回溯96小時內之某時，在不詳地點，施用第二級毒品安\n    非他命、甲基安非他命。嗣於100年1月7日，因毒品列管人\n    口，經警通知到場，並採驗尿液呈安非他命類陽性反應，始\n    知上情。\n二、案經新北市政府警察局板橋分局報告臺灣板橋地方法院檢察\n    署呈請臺灣高等法院檢察署檢察長令轉本署偵辦。\n        證據並所犯法條\n一、訊據被告張輔元矢口否認有何上揭施用毒品之犯嫌，惟查，\n    被告經警查獲後所採集之尿液經送鑑，呈第二級毒品安非他\n    命類之陽性反應，此有台灣檢驗科技股份有限公司之濫用藥\n    物檢驗報告1紙附卷可稽。又被告前因施用毒品案件，經臺\n    灣板橋地方法院以98年度毒聲字第718號裁定送臺灣臺北看\n    守所附設勒戒處所觀察、勒戒後，認無繼續施用毒品之傾向\n    ，於98年7月30日釋放出所，並經臺灣板橋地方法院檢察署\n    檢察官以98年度毒偵緝字第340號案件為不起訴處分確定，\n    此有本署刑事資料查註紀錄表1份在卷可憑，是被告於強制\n    戒治執行完畢後5年內，再犯施用第二級毒品之犯嫌應堪認\n    定。\n二、核被告所為，係違反毒品危害防制條例第10條第2項之施用\n    第二級毒品罪嫌。被告曾有如犯罪事實欄所載之前科，有本\n    署刑案資料查註紀錄表1份可參，其於有期徒刑執行完畢後\n    ，5年內再犯本件有期徒刑以上之罪，為累犯，請依法加重\n    其刑。\n三、依刑事訴訟法第251條第1項提起公訴。\n    此    致\n臺灣臺北地方法院\n中    華    民    國   100    年    5     月    22    日\n                              檢  察  官   鄭  東  峰",
  "structure": {
    "main": "張輔元施用第二級毒品，累犯，處有期徒刑肆月，如易科罰金，\n以新臺幣壹仟元折算壹日。",
    "fact": "一、本件犯罪事實及證據均援引檢察官起訴書之記載（如附件）\n    ，惟犯罪事實欄所載：(1)「98年度毒聲字第718 號裁定」應\n    更正為「96年度毒聲字第718 號裁定」。(2)「在不詳地點，\n    施用安非他命、甲基安非他命」應更正為「在新北市板橋區\n    某賓館，以吸食器燒烤方式施用甲基安非他命1 次，並於施\n    用後將吸食器丟棄滅失」。另並於證據欄增補：被告張輔元\n    於本院訊問時之自白。\n二、是核被告所為，係犯毒品危害防制條例第10條第2 項之施用\n    第二級毒品罪。其持有第二級毒品之低度行為，為施用之高\n    度行為所吸收，不另論罪。查被告有如犯罪事實欄所載之前\n    案及執行紀錄之事實，有臺灣高等法院被告前案紀錄表在卷\n    可徵，其於受有期徒刑執行完畢5 年以內，故意再犯本件有\n    期徒刑以上之罪，應依刑法第47條第1 項規定加重其刑。爰\n    審酌被告之品性、平日素行、犯罪之動機、施用毒品戕害己\n    身之犯罪手段、目的、施用次數及犯罪後尚知坦認犯行之態\n    度等一切情狀，量處如主文所示之刑，並諭知易科罰金折算\n    之標準。\n三、應依刑事訴訟法第449 條第2 項、第3 項、第454 條第2項\n    ，毒品危害防制條例第10條第2 項，刑法第11條、第47 條\n    第1 項、第41條第1 項前段，逕以簡易判決處如主文所示之\n    刑。\n四、對於本件判決如有不服，應於收受送達10日內，向本院提出\n    上訴書狀。",
    "reason": "一、本件犯罪事實及證據均援引檢察官起訴書之記載（如附件）\n    ，惟犯罪事實欄所載：(1)「98年度毒聲字第718 號裁定」應\n    更正為「96年度毒聲字第718 號裁定」。(2)「在不詳地點，\n    施用安非他命、甲基安非他命」應更正為「在新北市板橋區\n    某賓館，以吸食器燒烤方式施用甲基安非他命1 次，並於施\n    用後將吸食器丟棄滅失」。另並於證據欄增補：被告張輔元\n    於本院訊問時之自白。\n二、是核被告所為，係犯毒品危害防制條例第10條第2 項之施用\n    第二級毒品罪。其持有第二級毒品之低度行為，為施用之高\n    度行為所吸收，不另論罪。查被告有如犯罪事實欄所載之前\n    案及執行紀錄之事實，有臺灣高等法院被告前案紀錄表在卷\n    可徵，其於受有期徒刑執行完畢5 年以內，故意再犯本件有\n    期徒刑以上之罪，應依刑法第47條第1 項規定加重其刑。爰\n    審酌被告之品性、平日素行、犯罪之動機、施用毒品戕害己\n    身之犯罪手段、目的、施用次數及犯罪後尚知坦認犯行之態\n    度等一切情狀，量處如主文所示之刑，並諭知易科罰金折算\n    之標準。\n三、應依刑事訴訟法第449 條第2 項、第3 項、第454 條第2項\n    ，毒品危害防制條例第10條第2 項，刑法第11條、第47 條\n    第1 項、第41條第1 項前段，逕以簡易判決處如主文所示之\n    刑。\n四、對於本件判決如有不服，應於收受送達10日內，向本院提出\n    上訴書狀。"
  },
  "search": "臺灣臺北地方法院刑事簡易判決100年度簡字第2907號公訴人臺灣臺北地方法院檢察署檢察官被告張輔元上列被告因毒品危害防制條例案件，經檢察官提起公訴（100年度毒偵字第1465號），本院訊問被告後，被告自白犯罪，改以簡易判決處刑如下：主文張輔元施用第二級毒品，累犯，處有期徒刑肆月，如易科罰金，以新臺幣壹仟元折算壹日。事實及理由一、本件犯罪事實及證據均援引檢察官起訴書之記載（如附件），惟犯罪事實欄所載：(1)「98年度毒聲字第718號裁定」應更正為「96年度毒聲字第718號裁定」。(2)「在不詳地點，施用安非他命、甲基安非他命」應更正為「在新北市板橋區某賓館，以吸食器燒烤方式施用甲基安非他命1次，並於施用後將吸食器丟棄滅失」。另並於證據欄增補：被告張輔元於本院訊問時之自白。二、是核被告所為，係犯毒品危害防制條例第10條第2項之施用第二級毒品罪。其持有第二級毒品之低度行為，為施用之高度行為所吸收，不另論罪。查被告有如犯罪事實欄所載之前案及執行紀錄之事實，有臺灣高等法院被告前案紀錄表在卷可徵，其於受有期徒刑執行完畢5年以內，故意再犯本件有期徒刑以上之罪，應依刑法第47條第1項規定加重其刑。爰審酌被告之品性、平日素行、犯罪之動機、施用毒品戕害己身之犯罪手段、目的、施用次數及犯罪後尚知坦認犯行之態度等一切情狀，量處如主文所示之刑，並諭知易科罰金折算之標準。三、應依刑事訴訟法第449條第2項、第3項、第454條第2項，毒品危害防制條例第10條第2項，刑法第11條、第47條第1項、第41條第1項前段，逕以簡易判決處如主文所示之刑。四、對於本件判決如有不服，應於收受送達10日內，向本院提出上訴書狀。中華民國100年10月5日刑事第十三庭法官劉煌基上正本證明與原本無異。如不服本判決應於收受送達後10日內向本院提出上訴書狀，並應敘述具體理由；其未敘述上訴理由者，應於上訴期間屆滿後20日內向本院補提理由書（均須按他造當事人之人數附繕本）「切勿逕送上級法院」。書記官莊文茹中華民國100年10月5日附錄本案論罪科刑法條：毒品危害防制條例第10條施用第一級毒品者，處6月以上5年以下有期徒刑。施用第二級毒品者，處3年以下有期徒刑。附件臺灣臺北地方法院檢察署檢察官起訴書100年度毒偵字第1465號被告張輔元男36歲（民國○○年○○月○○日生）住臺北市○○區○○路四段68號11樓之7居新北市○○區○○街58號3樓國民身分證統一編號：Ｚ000000000號上列被告因違反毒品危害防制條例案件，已經偵查終結，認應該提起公訴，茲將犯罪事實及證據並所犯法條分敘如下：犯罪事實一、張輔元前因施用毒品案件，經臺灣板橋地方法院以98年度毒聲字第718號裁定送臺灣臺北看守所附設勒戒處所觀察、勒戒後，認無繼續施用毒品之傾向，於民國98年7月30日釋放出所，並經臺灣板橋地方法院檢察署檢察官以98年度毒偵緝字第340號案件為不起訴處分確定。復因違反藥事法等案件，經同法院以98年度訴緝字第198號判決處有期徒刑9月、4月，並分別減刑為4月又15日、2月，應執行有期徒刑5月確定，甫於99年4月1日縮刑期滿執行完畢。詎仍不知悔改，基於施用第二級毒品之犯意，於100年1月7日下午1時許為警採尿前回溯96小時內之某時，在不詳地點，施用第二級毒品安非他命、甲基安非他命。嗣於100年1月7日，因毒品列管人口，經警通知到場，並採驗尿液呈安非他命類陽性反應，始知上情。二、案經新北市政府警察局板橋分局報告臺灣板橋地方法院檢察署呈請臺灣高等法院檢察署檢察長令轉本署偵辦。證據並所犯法條一、訊據被告張輔元矢口否認有何上揭施用毒品之犯嫌，惟查，被告經警查獲後所採集之尿液經送鑑，呈第二級毒品安非他命類之陽性反應，此有台灣檢驗科技股份有限公司之濫用藥物檢驗報告1紙附卷可稽。又被告前因施用毒品案件，經臺灣板橋地方法院以98年度毒聲字第718號裁定送臺灣臺北看守所附設勒戒處所觀察、勒戒後，認無繼續施用毒品之傾向，於98年7月30日釋放出所，並經臺灣板橋地方法院檢察署檢察官以98年度毒偵緝字第340號案件為不起訴處分確定，此有本署刑事資料查註紀錄表1份在卷可憑，是被告於強制戒治執行完畢後5年內，再犯施用第二級毒品之犯嫌應堪認定。二、核被告所為，係違反毒品危害防制條例第10條第2項之施用第二級毒品罪嫌。被告曾有如犯罪事實欄所載之前科，有本署刑案資料查註紀錄表1份可參，其於有期徒刑執行完畢後，5年內再犯本件有期徒刑以上之罪，為累犯，請依法加重其刑。三、依刑事訴訟法第251條第1項提起公訴。此致臺灣臺北地方法院中華民國100年5月22日檢察官鄭東峰",
  "characters": {
    "judges": [
      "劉煌基"
    ],
    "prosecutors": [

    ],
    "lawyers": [

    ],
    "clerks": [
      "莊文茹"
    ],
    "plaintiffs": [

    ],
    "defendants": [
      "張輔元",
      "張輔元  男  36歲（民國○○年○○月○○日生）"
    ],
    "prosecutor_office": [
      "臺灣臺北地方法院檢察署檢察官"
    ],
    "creditors": [

    ],
    "debtors": [

    ],
    "judicial_associate_officer": [

    ]
  },
  "adjudged_at": "2011-10-05",
  "created_at": "2016-02-14 05:56:31",
  "updated_at": "2016-02-14 05:56:31"
}