{
  "identify": "TTD-91-重訴-1-20020315-1",
  "court": {
    "name": "臺灣臺東地方法院",
    "code": "TTD"
  },
  "division": {
    "name": "民事",
    "code": "V"
  },
  "year": 91,
  "word": "重訴",
  "number": "1",
  "jcheck": "1",
  "reason": "清償借款",
  "content": "臺灣臺東地方法院民事判決  九十一年度重訴字第一號\n    原      告  中國農民銀行股份有限公司\n    法定代理人  丁○○\n    訴訟代理人  乙○○\n    被      告  甲○○\n                丙○○\n右當事人間請求清償借款事件，本院判決如左：\n    主      文\n被告應連帶給付原告新臺幣陸佰零捌萬玖仟佰肆拾肆元，及自民國九十年七月四日\n起至清償日止，按年息百分之八點三二五計算之利息，暨自民國九十年八月五日起至\n清償日止，逾期在六個月以內部分按上開利率百分之十，逾期超過六個月部分按上開\n利率百分之二十計算之違約金。\n訴訟費用由被告連帶負擔。\n    事實及理由\n壹、原告主張：被告甲○○於民國（下同）八十八年十月四日，邀同被告丙○○為連\n    帶保證人，向伊借得新臺幣（下同）六百八十萬元，借款期間自八十八年十月四\n    日起至九十九年十月四日止，利息按年息百分之八點四，採機動利率計付，約定\n    自借款日起每月平均攤還本息，如未按期攤還本息時，被告即喪失期限利益，應\n    即全部償還，逾期六個月以內部分並按上開利率百分之十，逾期超過六個月部分\n    按上開利率百分之二十加付違約金。詎被告甲○○自九十年七月四日起即未依約\n    履行，迭經催討仍不給付，爰依消費借貸及連帶保證之法律關係提起本件訴訟等\n    語。並聲明：如主文第一項所示。\n貳、被告未於言詞辯論期日到場，亦未提出書狀作何聲明或陳述。\n參、程序方面：被告經合法通知，未於言詞辯論期日到場，核無民事訴訟法第三百八\n    十六條各款所列情形，爰依原告之聲請由其一造辯論而為判決。\n肆、得心證之理由：\n  一、原告主張之事實，業據其提出借據、約定書、一般支出傳票、轉帳收入傳票、\n      繳款明細表及利率變動表等件為證，被告既未到場爭執，亦未提出書狀以為抗\n      辯，應認原告主張為真正。\n  二、從而原告依消費借貸及連帶保證之法律關係，訴請被告連帶給付如主文第一項\n      所示之金額、利息及違約金，為有理由，應予准許。\n伍、據上論結，本件原告之訴為有理由，依民事訟法第三百八十五條第一項前段、第\n    八十五條第二項，判決如主文。\n中      華      民      國    九十一    年      三      月     十五     日\n                                        臺灣臺東地方法院民事庭\n~B審判長法    官  李昆曄\n~B      法    官  柯姿佐\n~B      法    官  魏于傑\n右為正本係照原本作成\n如不服本判決，須於判決送達後二十日內向本院提出上訴狀\n中      華      民      國    九十一    年      三      月     十五     日\n~B法院書記官    李春菊\n",
  "structure": {
    "main": "被告應連帶給付原告新臺幣陸佰零捌萬玖仟佰肆拾肆元，及自民國九十年七月四日\n起至清償日止，按年息百分之八點三二五計算之利息，暨自民國九十年八月五日起至\n清償日止，逾期在六個月以內部分按上開利率百分之十，逾期超過六個月部分按上開\n利率百分之二十計算之違約金。\n訴訟費用由被告連帶負擔。",
    "fact": "壹、原告主張：被告甲○○於民國（下同）八十八年十月四日，邀同被告丙○○為連\n    帶保證人，向伊借得新臺幣（下同）六百八十萬元，借款期間自八十八年十月四\n    日起至九十九年十月四日止，利息按年息百分之八點四，採機動利率計付，約定\n    自借款日起每月平均攤還本息，如未按期攤還本息時，被告即喪失期限利益，應\n    即全部償還，逾期六個月以內部分並按上開利率百分之十，逾期超過六個月部分\n    按上開利率百分之二十加付違約金。詎被告甲○○自九十年七月四日起即未依約\n    履行，迭經催討仍不給付，爰依消費借貸及連帶保證之法律關係提起本件訴訟等\n    語。並聲明：如主文第一項所示。\n貳、被告未於言詞辯論期日到場，亦未提出書狀作何聲明或陳述。\n參、程序方面：被告經合法通知，未於言詞辯論期日到場，核無民事訴訟法第三百八\n    十六條各款所列情形，爰依原告之聲請由其一造辯論而為判決。\n肆、得心證之理由：\n  一、原告主張之事實，業據其提出借據、約定書、一般支出傳票、轉帳收入傳票、\n      繳款明細表及利率變動表等件為證，被告既未到場爭執，亦未提出書狀以為抗\n      辯，應認原告主張為真正。\n  二、從而原告依消費借貸及連帶保證之法律關係，訴請被告連帶給付如主文第一項\n      所示之金額、利息及違約金，為有理由，應予准許。\n伍、據上論結，本件原告之訴為有理由，依民事訟法第三百八十五條第一項前段、第\n    八十五條第二項，判決如主文。",
    "reason": "壹、原告主張：被告甲○○於民國（下同）八十八年十月四日，邀同被告丙○○為連\n    帶保證人，向伊借得新臺幣（下同）六百八十萬元，借款期間自八十八年十月四\n    日起至九十九年十月四日止，利息按年息百分之八點四，採機動利率計付，約定\n    自借款日起每月平均攤還本息，如未按期攤還本息時，被告即喪失期限利益，應\n    即全部償還，逾期六個月以內部分並按上開利率百分之十，逾期超過六個月部分\n    按上開利率百分之二十加付違約金。詎被告甲○○自九十年七月四日起即未依約\n    履行，迭經催討仍不給付，爰依消費借貸及連帶保證之法律關係提起本件訴訟等\n    語。並聲明：如主文第一項所示。\n貳、被告未於言詞辯論期日到場，亦未提出書狀作何聲明或陳述。\n參、程序方面：被告經合法通知，未於言詞辯論期日到場，核無民事訴訟法第三百八\n    十六條各款所列情形，爰依原告之聲請由其一造辯論而為判決。\n肆、得心證之理由：\n  一、原告主張之事實，業據其提出借據、約定書、一般支出傳票、轉帳收入傳票、\n      繳款明細表及利率變動表等件為證，被告既未到場爭執，亦未提出書狀以為抗\n      辯，應認原告主張為真正。\n  二、從而原告依消費借貸及連帶保證之法律關係，訴請被告連帶給付如主文第一項\n      所示之金額、利息及違約金，為有理由，應予准許。\n伍、據上論結，本件原告之訴為有理由，依民事訟法第三百八十五條第一項前段、第\n    八十五條第二項，判決如主文。"
  },
  "search": "臺灣臺東地方法院民事判決九十一年度重訴字第一號原告中國農民銀行股份有限公司法定代理人丁○○訴訟代理人乙○○被告甲○○丙○○右當事人間請求清償借款事件，本院判決如左：主文被告應連帶給付原告新臺幣陸佰零捌萬玖仟佰肆拾肆元，及自民國九十年七月四日起至清償日止，按年息百分之八點三二五計算之利息，暨自民國九十年八月五日起至清償日止，逾期在六個月以內部分按上開利率百分之十，逾期超過六個月部分按上開利率百分之二十計算之違約金。訴訟費用由被告連帶負擔。事實及理由壹、原告主張：被告甲○○於民國（下同）八十八年十月四日，邀同被告丙○○為連帶保證人，向伊借得新臺幣（下同）六百八十萬元，借款期間自八十八年十月四日起至九十九年十月四日止，利息按年息百分之八點四，採機動利率計付，約定自借款日起每月平均攤還本息，如未按期攤還本息時，被告即喪失期限利益，應即全部償還，逾期六個月以內部分並按上開利率百分之十，逾期超過六個月部分按上開利率百分之二十加付違約金。詎被告甲○○自九十年七月四日起即未依約履行，迭經催討仍不給付，爰依消費借貸及連帶保證之法律關係提起本件訴訟等語。並聲明：如主文第一項所示。貳、被告未於言詞辯論期日到場，亦未提出書狀作何聲明或陳述。參、程序方面：被告經合法通知，未於言詞辯論期日到場，核無民事訴訟法第三百八十六條各款所列情形，爰依原告之聲請由其一造辯論而為判決。肆、得心證之理由：一、原告主張之事實，業據其提出借據、約定書、一般支出傳票、轉帳收入傳票、繳款明細表及利率變動表等件為證，被告既未到場爭執，亦未提出書狀以為抗辯，應認原告主張為真正。二、從而原告依消費借貸及連帶保證之法律關係，訴請被告連帶給付如主文第一項所示之金額、利息及違約金，為有理由，應予准許。伍、據上論結，本件原告之訴為有理由，依民事訟法第三百八十五條第一項前段、第八十五條第二項，判決如主文。中華民國九十一年三月十五日臺灣臺東地方法院民事庭~B審判長法官李昆曄~B法官柯姿佐~B法官魏于傑右為正本係照原本作成如不服本判決，須於判決送達後二十日內向本院提出上訴狀中華民國九十一年三月十五日~B法院書記官李春菊",
  "characters": {
    "judges": [
      "李昆曄",
      "柯姿佐",
      "魏于傑"
    ],
    "prosecutors": [

    ],
    "lawyers": [

    ],
    "clerks": [

    ],
    "plaintiffs": [
      "中國農民銀行股份有限公司"
    ],
    "defendants": [
      "甲○○"
    ],
    "prosecutor_office": [

    ],
    "creditors": [

    ],
    "debtors": [

    ],
    "judicial_associate_officer": [

    ]
  },
  "adjudged_at": "2002-03-15",
  "created_at": "2016-02-05 08:08:23",
  "updated_at": "2016-02-05 08:08:23"
}