{
  "identify": "TPD-100-簡-3611-20111014-1",
  "court": {
    "name": "臺灣臺北地方法院",
    "code": "TPD"
  },
  "division": {
    "name": "刑事",
    "code": "M"
  },
  "year": 100,
  "word": "簡",
  "number": "3611",
  "jcheck": "1",
  "reason": "妨害風化",
  "content": "臺灣臺北地方法院刑事簡易判決         100年度簡字第3611號\n聲  請  人  臺灣臺北地方法院檢察署檢察官\n被      告  夏祐豪\n上列被告因妨害風化案件，經檢察官聲請簡易判決處刑（100 年\n度速偵字第219 號），本院判決如下：\n    主  文\n夏祐豪販賣猥褻之影音光碟片，累犯，處有期徒刑伍月，如易科\n罰金，以新臺幣壹仟元折算壹日。扣案之猥褻影音光碟肆仟零伍\n拾柒片均沒收。\n    事實及理由\n一、夏祐豪前於民國96年間，因詐欺案件，經臺灣臺中地方法院\n    以96年度易字第5129號判決處有期徒刑8 月，減為有期徒刑\n    4 月確定；於98年間，因詐欺案件，經同法院以98年度中簡\n    字第1171號判決處有期徒刑2 月確定，上揭2 案件，經同法\n    院以98年度聲字第2628號裁定定應執行有期徒刑6 月確定，\n    於98年9 月1 日縮刑期滿執行完畢出監。詎其猶不知悔改，\n    為址設臺北市○○區○○路1 段43巷12號1 樓「東京熱便利\n    屋」負責人，明知真實姓名、年籍不詳，綽號「阿興」之成\n    年男子（下稱「阿興」）所兜售之影音光碟均為含有暴力、\n    性虐待等內容，而無藝術性、醫學性或教育性價值之猥褻資\n    訊或物品，是不問有無採取適當之安全隔絕措施（例如附加\n    封套、警告標示或限於依法令特定之場所等），均一律禁止\n    散布、播送或販賣，竟仍基於販賣猥褻影音光碟之犯意，自\n    100 年3 至4 月間，向「阿興」以每片新臺幣（下同) 20元\n    之價格購入前開猥褻無碼影音光碟後，公開陳列在上址營業\n    店面，並以每片40元之價格販售與不特定人以營利。嗣於同\n    年9 月20日下午7 時40分許，為警持法院核發之搜索票在上\n    址搜索查獲，並扣得販售所剩餘之猥褻影音光碟4,057 片。\n    案經臺北市政府警察局中山分局報告臺灣臺北地方法院檢察\n    署檢察官偵查後聲請簡易判決處刑。\n二、上揭犯罪事實，業據被告夏祐豪於警詢、偵查中坦承不諱（\n    見臺灣臺北地方法院檢察署100 度速偵字第219 號卷〈下稱\n    偵卷〉第5 至8 、29至30頁），且有本院核發之搜索票、自\n    願受搜索同意書、搜索扣押筆錄、扣押物品目錄表各1 份、\n    查獲現場、扣案猥褻影音光碟內容節錄照片共19張存卷可查\n    （見偵卷第9 至13、19至22頁），足認被告之前開任意性自\n    白與事實相符，應堪採信。本案事證明確，被告犯行堪以認\n    定，應予依法論科。\n三、按刑法上之販賣罪，並不以販入之後復行賣出為構成要件，\n    只須以營利為目的而購入或賣出，有一於此，罪即成立，有\n    最高法院67年台上字第2500號判例意旨可資參照，故不論是\n    否已賣出，均無影響犯罪之成立。次按，所謂猥褻，指客觀\n    上足以刺激或滿足性慾，其內容可與性器官、性行為及性文\n    化之描繪與論述聯結，且須以引起普通一般人羞恥或厭惡感\n    而侵害性的道德感情，有礙於社會風化者為限，司法院釋字\n    第407 號解釋意旨參照。又按刑法第231 條第1 項規定所謂\n    散布、播送、販賣、公然陳列猥褻之資訊或物品，或以他法\n    供人觀覽、聽聞之行為，係指對含有暴力、性虐待或人獸性\n    交等而無藝術性、醫學性或教育性價值之猥褻資訊或物品為\n    傳布，或對其他客觀上足以刺激或滿足性慾，而令一般人感\n    覺不堪呈現於眾或不能忍受而排拒之猥褻資訊或物品，未採\n    取適當之安全隔絕措施而傳布，使一般人得以見聞之行為；\n    同條第2 項規定所謂意圖散布、播送、販賣而製造、持有猥\n    褻資訊、物品之行為，亦僅指意圖傳布含有暴力、性虐待或\n    人獸性交等而無藝術性、醫學性或教育性價值之猥褻資訊或\n    物品而製造、持有之行為，或對其他客觀上足以刺激或滿足\n    性慾，而令一般人感覺不堪呈現於眾或不能忍受而排拒之猥\n    褻資訊或物品，意圖不採取適當安全隔絕措施之傳布，使一\n    般人得以見聞而製造或持有該等猥褻資訊、物品之情形，司\n    法院釋字第617 號解釋意旨亦可參照。是司法院釋字第617\n    號解釋認定刑法第235 條所欲規範之猥褻出版品，應限於兩\n    類猥褻出版品，其中一類係所謂「含有暴力、性虐待或人獸\n    性交等而無藝術性、醫學性或教育性價值」之所謂硬蕊（ha\n    rd core ）猥褻資訊或物品；另一類則為「客觀上足以刺激\n    或滿足性慾，而令一般人感覺不堪呈現於眾或不能忍受而排\n    拒」之非硬蕊之一般猥褻資訊或物品，後者則必須該「資訊\n    未採取適當之安全隔絕措施而傳布，使一般人得以見聞之行\n    為」。查被告基於販賣猥褻影音光碟之犯意，自100 年3 至\n    4 月間購入上開猥褻影音光碟，該等光碟影像內含暴力、性\n    虐待等情形，無藝術性、醫學性或教育性價值，有扣案猥褻\n    影音光碟內容節錄照片在卷足憑，堪認扣案之光碟均屬猥褻\n    影音光碟甚明。\n四、核被告所為，係犯刑法第235 條第1 項之販賣猥褻影音光碟\n    罪。聲請簡易判決書雖載係犯同條項之「散布猥褻物品罪」\n    ，然聲請簡易判決處刑書既已就被告有購入、販出及其販售\n    價格具體敘明，則此部分論罪罪名應屬誤載，併予陳明。再\n    按刑事法若干犯罪行為態樣，本質上原具有反覆、延續實行\n    之特徵，立法時既予特別歸類，定為犯罪構成要件之行為要\n    素，則行為人基於概括之犯意，在密切接近之一定時、地持\n    續實行之複次行為，倘依社會通念，於客觀上認為符合一個\n    反覆、延續性之行為觀念者，於刑法評價上，即應僅成立一\n    罪，俾免有重複評價、刑度超過罪責與不法內涵之疑慮；學\n    理上所稱「集合犯」之職業性、營業性或收集性等具有重複\n    特質之犯罪均屬之，例如經營、從事業務、收集、販賣、製\n    造、散布等行為概念者是，最高法院95年度台上字第1079號\n    判決意旨參照。查被告自100 年3 月起至同年9 月20日下午\n    7 時40分許為警查獲時止，在上址「東京熱便利屋」內多次\n    反覆持續販賣猥褻影音光碟而未曾間斷，是其販賣猥褻漫畫\n    書籍之營業性行為，於概念上應評價為包括一罪之集合犯，\n    而僅論以一販賣猥褻漫畫書籍罪。其公然陳列、意圖販賣而\n    持有猥褻漫畫書籍之低度行為，均為販賣之高度行為所吸收\n    ，均不另論罪。又被告前因事實及理由一所載案件，經論處\n    徒刑後，於98年9 月1 日縮刑期滿執行完畢出監等節，有臺\n    灣高等法院被告前案紀錄表1 份在卷可按，其受有期徒刑執\n    行完畢後，5 年內故意再犯有期徒刑以上之上開之罪，為累\n    犯，應依刑法第47條第1 項規定，加重其刑。爰審酌被告販\n    售含有暴力、性虐待之影音光碟，危害社會善良風俗，迄至\n    為警查獲之時，尚仍扣得4,057 片猥褻影音光碟，數量龐大\n    ，對社會善良風俗產生不良影響甚鉅，惟念被告犯後坦承犯\n    行，態度後尚可，暨衡諸其教育程度為國中肄業，以自營商\n    為業，犯罪動機、素行、智識程度、生活狀況等一切情狀，\n    量處如主文所示之刑，並諭知易科罰金之折算標準。至扣案\n    之猥褻影音光碟4,057 片，內容含有猥褻之影音，均屬猥褻\n    物品，依刑法第235 條第3 項之規定，不問屬於犯人與否，\n    沒收之。\n五、依刑事訴訟法第449 條第1 項前段、第3 項、第450 條第1\n    項，刑法第235 條第1 項、第3 項、第47條第1 項、第41條\n    第1 項前段，刑法施行法第1 條之1 第1 項、第2 項但書，\n    逕以簡易判決處刑如主文。\n六、如不服本判決，得於判決書送達之翌日起10日內，以書狀敘\n    述理由，向本院提出上訴。\n中    華    民    國   100    年    10    月    14    日\n                        刑事第八庭法  官  湯千慧\n以上正本證明與原本無異。\n如不服本判決，應於收受送達後10日內向本院提出上訴書狀，並\n應敘述具體理由；其未敘述上訴理由者，應於上訴期間屆滿後20\n日內向本院補提理由書（均須按他造當事人之人數附繕）「切勿\n逕送上級法院」。\n                                  書記官  游雅鈞\n中    華    民    國   100    年    10    月    14    日\n附錄本案論罪科刑法條全文：\n中華民國刑法第235條\n（散布、販賣猥褻物品及製造持有罪）\n散布、播送或販賣猥褻之文字、圖畫、聲音、影像或其他物品，\n或公然陳列，或以他法供人觀覽、聽聞者，處2 年以下有期徒刑\n、拘役或科或併科3 萬元以下罰金。\n意圖散布、播送、販賣而製造、持有前項文字、圖畫、聲音、影\n像及其附著物或其他物品者，亦同。\n前二項之文字、圖畫、聲音或影像之附著物及物品，不問屬於犯\n人與否，沒收之。",
  "structure": {
    "main": "夏祐豪販賣猥褻之影音光碟片，累犯，處有期徒刑伍月，如易科\n罰金，以新臺幣壹仟元折算壹日。扣案之猥褻影音光碟肆仟零伍\n拾柒片均沒收。",
    "fact": "一、夏祐豪前於民國96年間，因詐欺案件，經臺灣臺中地方法院\n    以96年度易字第5129號判決處有期徒刑8 月，減為有期徒刑\n    4 月確定；於98年間，因詐欺案件，經同法院以98年度中簡\n    字第1171號判決處有期徒刑2 月確定，上揭2 案件，經同法\n    院以98年度聲字第2628號裁定定應執行有期徒刑6 月確定，\n    於98年9 月1 日縮刑期滿執行完畢出監。詎其猶不知悔改，\n    為址設臺北市○○區○○路1 段43巷12號1 樓「東京熱便利\n    屋」負責人，明知真實姓名、年籍不詳，綽號「阿興」之成\n    年男子（下稱「阿興」）所兜售之影音光碟均為含有暴力、\n    性虐待等內容，而無藝術性、醫學性或教育性價值之猥褻資\n    訊或物品，是不問有無採取適當之安全隔絕措施（例如附加\n    封套、警告標示或限於依法令特定之場所等），均一律禁止\n    散布、播送或販賣，竟仍基於販賣猥褻影音光碟之犯意，自\n    100 年3 至4 月間，向「阿興」以每片新臺幣（下同) 20元\n    之價格購入前開猥褻無碼影音光碟後，公開陳列在上址營業\n    店面，並以每片40元之價格販售與不特定人以營利。嗣於同\n    年9 月20日下午7 時40分許，為警持法院核發之搜索票在上\n    址搜索查獲，並扣得販售所剩餘之猥褻影音光碟4,057 片。\n    案經臺北市政府警察局中山分局報告臺灣臺北地方法院檢察\n    署檢察官偵查後聲請簡易判決處刑。\n二、上揭犯罪事實，業據被告夏祐豪於警詢、偵查中坦承不諱（\n    見臺灣臺北地方法院檢察署100 度速偵字第219 號卷〈下稱\n    偵卷〉第5 至8 、29至30頁），且有本院核發之搜索票、自\n    願受搜索同意書、搜索扣押筆錄、扣押物品目錄表各1 份、\n    查獲現場、扣案猥褻影音光碟內容節錄照片共19張存卷可查\n    （見偵卷第9 至13、19至22頁），足認被告之前開任意性自\n    白與事實相符，應堪採信。本案事證明確，被告犯行堪以認\n    定，應予依法論科。\n三、按刑法上之販賣罪，並不以販入之後復行賣出為構成要件，\n    只須以營利為目的而購入或賣出，有一於此，罪即成立，有\n    最高法院67年台上字第2500號判例意旨可資參照，故不論是\n    否已賣出，均無影響犯罪之成立。次按，所謂猥褻，指客觀\n    上足以刺激或滿足性慾，其內容可與性器官、性行為及性文\n    化之描繪與論述聯結，且須以引起普通一般人羞恥或厭惡感\n    而侵害性的道德感情，有礙於社會風化者為限，司法院釋字\n    第407 號解釋意旨參照。又按刑法第231 條第1 項規定所謂\n    散布、播送、販賣、公然陳列猥褻之資訊或物品，或以他法\n    供人觀覽、聽聞之行為，係指對含有暴力、性虐待或人獸性\n    交等而無藝術性、醫學性或教育性價值之猥褻資訊或物品為\n    傳布，或對其他客觀上足以刺激或滿足性慾，而令一般人感\n    覺不堪呈現於眾或不能忍受而排拒之猥褻資訊或物品，未採\n    取適當之安全隔絕措施而傳布，使一般人得以見聞之行為；\n    同條第2 項規定所謂意圖散布、播送、販賣而製造、持有猥\n    褻資訊、物品之行為，亦僅指意圖傳布含有暴力、性虐待或\n    人獸性交等而無藝術性、醫學性或教育性價值之猥褻資訊或\n    物品而製造、持有之行為，或對其他客觀上足以刺激或滿足\n    性慾，而令一般人感覺不堪呈現於眾或不能忍受而排拒之猥\n    褻資訊或物品，意圖不採取適當安全隔絕措施之傳布，使一\n    般人得以見聞而製造或持有該等猥褻資訊、物品之情形，司\n    法院釋字第617 號解釋意旨亦可參照。是司法院釋字第617\n    號解釋認定刑法第235 條所欲規範之猥褻出版品，應限於兩\n    類猥褻出版品，其中一類係所謂「含有暴力、性虐待或人獸\n    性交等而無藝術性、醫學性或教育性價值」之所謂硬蕊（ha\n    rd core ）猥褻資訊或物品；另一類則為「客觀上足以刺激\n    或滿足性慾，而令一般人感覺不堪呈現於眾或不能忍受而排\n    拒」之非硬蕊之一般猥褻資訊或物品，後者則必須該「資訊\n    未採取適當之安全隔絕措施而傳布，使一般人得以見聞之行\n    為」。查被告基於販賣猥褻影音光碟之犯意，自100 年3 至\n    4 月間購入上開猥褻影音光碟，該等光碟影像內含暴力、性\n    虐待等情形，無藝術性、醫學性或教育性價值，有扣案猥褻\n    影音光碟內容節錄照片在卷足憑，堪認扣案之光碟均屬猥褻\n    影音光碟甚明。\n四、核被告所為，係犯刑法第235 條第1 項之販賣猥褻影音光碟\n    罪。聲請簡易判決書雖載係犯同條項之「散布猥褻物品罪」\n    ，然聲請簡易判決處刑書既已就被告有購入、販出及其販售\n    價格具體敘明，則此部分論罪罪名應屬誤載，併予陳明。再\n    按刑事法若干犯罪行為態樣，本質上原具有反覆、延續實行\n    之特徵，立法時既予特別歸類，定為犯罪構成要件之行為要\n    素，則行為人基於概括之犯意，在密切接近之一定時、地持\n    續實行之複次行為，倘依社會通念，於客觀上認為符合一個\n    反覆、延續性之行為觀念者，於刑法評價上，即應僅成立一\n    罪，俾免有重複評價、刑度超過罪責與不法內涵之疑慮；學\n    理上所稱「集合犯」之職業性、營業性或收集性等具有重複\n    特質之犯罪均屬之，例如經營、從事業務、收集、販賣、製\n    造、散布等行為概念者是，最高法院95年度台上字第1079號\n    判決意旨參照。查被告自100 年3 月起至同年9 月20日下午\n    7 時40分許為警查獲時止，在上址「東京熱便利屋」內多次\n    反覆持續販賣猥褻影音光碟而未曾間斷，是其販賣猥褻漫畫\n    書籍之營業性行為，於概念上應評價為包括一罪之集合犯，\n    而僅論以一販賣猥褻漫畫書籍罪。其公然陳列、意圖販賣而\n    持有猥褻漫畫書籍之低度行為，均為販賣之高度行為所吸收\n    ，均不另論罪。又被告前因事實及理由一所載案件，經論處\n    徒刑後，於98年9 月1 日縮刑期滿執行完畢出監等節，有臺\n    灣高等法院被告前案紀錄表1 份在卷可按，其受有期徒刑執\n    行完畢後，5 年內故意再犯有期徒刑以上之上開之罪，為累\n    犯，應依刑法第47條第1 項規定，加重其刑。爰審酌被告販\n    售含有暴力、性虐待之影音光碟，危害社會善良風俗，迄至\n    為警查獲之時，尚仍扣得4,057 片猥褻影音光碟，數量龐大\n    ，對社會善良風俗產生不良影響甚鉅，惟念被告犯後坦承犯\n    行，態度後尚可，暨衡諸其教育程度為國中肄業，以自營商\n    為業，犯罪動機、素行、智識程度、生活狀況等一切情狀，\n    量處如主文所示之刑，並諭知易科罰金之折算標準。至扣案\n    之猥褻影音光碟4,057 片，內容含有猥褻之影音，均屬猥褻\n    物品，依刑法第235 條第3 項之規定，不問屬於犯人與否，\n    沒收之。\n五、依刑事訴訟法第449 條第1 項前段、第3 項、第450 條第1\n    項，刑法第235 條第1 項、第3 項、第47條第1 項、第41條\n    第1 項前段，刑法施行法第1 條之1 第1 項、第2 項但書，\n    逕以簡易判決處刑如主文。\n六、如不服本判決，得於判決書送達之翌日起10日內，以書狀敘\n    述理由，向本院提出上訴。",
    "reason": "一、夏祐豪前於民國96年間，因詐欺案件，經臺灣臺中地方法院\n    以96年度易字第5129號判決處有期徒刑8 月，減為有期徒刑\n    4 月確定；於98年間，因詐欺案件，經同法院以98年度中簡\n    字第1171號判決處有期徒刑2 月確定，上揭2 案件，經同法\n    院以98年度聲字第2628號裁定定應執行有期徒刑6 月確定，\n    於98年9 月1 日縮刑期滿執行完畢出監。詎其猶不知悔改，\n    為址設臺北市○○區○○路1 段43巷12號1 樓「東京熱便利\n    屋」負責人，明知真實姓名、年籍不詳，綽號「阿興」之成\n    年男子（下稱「阿興」）所兜售之影音光碟均為含有暴力、\n    性虐待等內容，而無藝術性、醫學性或教育性價值之猥褻資\n    訊或物品，是不問有無採取適當之安全隔絕措施（例如附加\n    封套、警告標示或限於依法令特定之場所等），均一律禁止\n    散布、播送或販賣，竟仍基於販賣猥褻影音光碟之犯意，自\n    100 年3 至4 月間，向「阿興」以每片新臺幣（下同) 20元\n    之價格購入前開猥褻無碼影音光碟後，公開陳列在上址營業\n    店面，並以每片40元之價格販售與不特定人以營利。嗣於同\n    年9 月20日下午7 時40分許，為警持法院核發之搜索票在上\n    址搜索查獲，並扣得販售所剩餘之猥褻影音光碟4,057 片。\n    案經臺北市政府警察局中山分局報告臺灣臺北地方法院檢察\n    署檢察官偵查後聲請簡易判決處刑。\n二、上揭犯罪事實，業據被告夏祐豪於警詢、偵查中坦承不諱（\n    見臺灣臺北地方法院檢察署100 度速偵字第219 號卷〈下稱\n    偵卷〉第5 至8 、29至30頁），且有本院核發之搜索票、自\n    願受搜索同意書、搜索扣押筆錄、扣押物品目錄表各1 份、\n    查獲現場、扣案猥褻影音光碟內容節錄照片共19張存卷可查\n    （見偵卷第9 至13、19至22頁），足認被告之前開任意性自\n    白與事實相符，應堪採信。本案事證明確，被告犯行堪以認\n    定，應予依法論科。\n三、按刑法上之販賣罪，並不以販入之後復行賣出為構成要件，\n    只須以營利為目的而購入或賣出，有一於此，罪即成立，有\n    最高法院67年台上字第2500號判例意旨可資參照，故不論是\n    否已賣出，均無影響犯罪之成立。次按，所謂猥褻，指客觀\n    上足以刺激或滿足性慾，其內容可與性器官、性行為及性文\n    化之描繪與論述聯結，且須以引起普通一般人羞恥或厭惡感\n    而侵害性的道德感情，有礙於社會風化者為限，司法院釋字\n    第407 號解釋意旨參照。又按刑法第231 條第1 項規定所謂\n    散布、播送、販賣、公然陳列猥褻之資訊或物品，或以他法\n    供人觀覽、聽聞之行為，係指對含有暴力、性虐待或人獸性\n    交等而無藝術性、醫學性或教育性價值之猥褻資訊或物品為\n    傳布，或對其他客觀上足以刺激或滿足性慾，而令一般人感\n    覺不堪呈現於眾或不能忍受而排拒之猥褻資訊或物品，未採\n    取適當之安全隔絕措施而傳布，使一般人得以見聞之行為；\n    同條第2 項規定所謂意圖散布、播送、販賣而製造、持有猥\n    褻資訊、物品之行為，亦僅指意圖傳布含有暴力、性虐待或\n    人獸性交等而無藝術性、醫學性或教育性價值之猥褻資訊或\n    物品而製造、持有之行為，或對其他客觀上足以刺激或滿足\n    性慾，而令一般人感覺不堪呈現於眾或不能忍受而排拒之猥\n    褻資訊或物品，意圖不採取適當安全隔絕措施之傳布，使一\n    般人得以見聞而製造或持有該等猥褻資訊、物品之情形，司\n    法院釋字第617 號解釋意旨亦可參照。是司法院釋字第617\n    號解釋認定刑法第235 條所欲規範之猥褻出版品，應限於兩\n    類猥褻出版品，其中一類係所謂「含有暴力、性虐待或人獸\n    性交等而無藝術性、醫學性或教育性價值」之所謂硬蕊（ha\n    rd core ）猥褻資訊或物品；另一類則為「客觀上足以刺激\n    或滿足性慾，而令一般人感覺不堪呈現於眾或不能忍受而排\n    拒」之非硬蕊之一般猥褻資訊或物品，後者則必須該「資訊\n    未採取適當之安全隔絕措施而傳布，使一般人得以見聞之行\n    為」。查被告基於販賣猥褻影音光碟之犯意，自100 年3 至\n    4 月間購入上開猥褻影音光碟，該等光碟影像內含暴力、性\n    虐待等情形，無藝術性、醫學性或教育性價值，有扣案猥褻\n    影音光碟內容節錄照片在卷足憑，堪認扣案之光碟均屬猥褻\n    影音光碟甚明。\n四、核被告所為，係犯刑法第235 條第1 項之販賣猥褻影音光碟\n    罪。聲請簡易判決書雖載係犯同條項之「散布猥褻物品罪」\n    ，然聲請簡易判決處刑書既已就被告有購入、販出及其販售\n    價格具體敘明，則此部分論罪罪名應屬誤載，併予陳明。再\n    按刑事法若干犯罪行為態樣，本質上原具有反覆、延續實行\n    之特徵，立法時既予特別歸類，定為犯罪構成要件之行為要\n    素，則行為人基於概括之犯意，在密切接近之一定時、地持\n    續實行之複次行為，倘依社會通念，於客觀上認為符合一個\n    反覆、延續性之行為觀念者，於刑法評價上，即應僅成立一\n    罪，俾免有重複評價、刑度超過罪責與不法內涵之疑慮；學\n    理上所稱「集合犯」之職業性、營業性或收集性等具有重複\n    特質之犯罪均屬之，例如經營、從事業務、收集、販賣、製\n    造、散布等行為概念者是，最高法院95年度台上字第1079號\n    判決意旨參照。查被告自100 年3 月起至同年9 月20日下午\n    7 時40分許為警查獲時止，在上址「東京熱便利屋」內多次\n    反覆持續販賣猥褻影音光碟而未曾間斷，是其販賣猥褻漫畫\n    書籍之營業性行為，於概念上應評價為包括一罪之集合犯，\n    而僅論以一販賣猥褻漫畫書籍罪。其公然陳列、意圖販賣而\n    持有猥褻漫畫書籍之低度行為，均為販賣之高度行為所吸收\n    ，均不另論罪。又被告前因事實及理由一所載案件，經論處\n    徒刑後，於98年9 月1 日縮刑期滿執行完畢出監等節，有臺\n    灣高等法院被告前案紀錄表1 份在卷可按，其受有期徒刑執\n    行完畢後，5 年內故意再犯有期徒刑以上之上開之罪，為累\n    犯，應依刑法第47條第1 項規定，加重其刑。爰審酌被告販\n    售含有暴力、性虐待之影音光碟，危害社會善良風俗，迄至\n    為警查獲之時，尚仍扣得4,057 片猥褻影音光碟，數量龐大\n    ，對社會善良風俗產生不良影響甚鉅，惟念被告犯後坦承犯\n    行，態度後尚可，暨衡諸其教育程度為國中肄業，以自營商\n    為業，犯罪動機、素行、智識程度、生活狀況等一切情狀，\n    量處如主文所示之刑，並諭知易科罰金之折算標準。至扣案\n    之猥褻影音光碟4,057 片，內容含有猥褻之影音，均屬猥褻\n    物品，依刑法第235 條第3 項之規定，不問屬於犯人與否，\n    沒收之。\n五、依刑事訴訟法第449 條第1 項前段、第3 項、第450 條第1\n    項，刑法第235 條第1 項、第3 項、第47條第1 項、第41條\n    第1 項前段，刑法施行法第1 條之1 第1 項、第2 項但書，\n    逕以簡易判決處刑如主文。\n六、如不服本判決，得於判決書送達之翌日起10日內，以書狀敘\n    述理由，向本院提出上訴。"
  },
  "search": "臺灣臺北地方法院刑事簡易判決100年度簡字第3611號聲請人臺灣臺北地方法院檢察署檢察官被告夏祐豪上列被告因妨害風化案件，經檢察官聲請簡易判決處刑（100年度速偵字第219號），本院判決如下：主文夏祐豪販賣猥褻之影音光碟片，累犯，處有期徒刑伍月，如易科罰金，以新臺幣壹仟元折算壹日。扣案之猥褻影音光碟肆仟零伍拾柒片均沒收。事實及理由一、夏祐豪前於民國96年間，因詐欺案件，經臺灣臺中地方法院以96年度易字第5129號判決處有期徒刑8月，減為有期徒刑4月確定；於98年間，因詐欺案件，經同法院以98年度中簡字第1171號判決處有期徒刑2月確定，上揭2案件，經同法院以98年度聲字第2628號裁定定應執行有期徒刑6月確定，於98年9月1日縮刑期滿執行完畢出監。詎其猶不知悔改，為址設臺北市○○區○○路1段43巷12號1樓「東京熱便利屋」負責人，明知真實姓名、年籍不詳，綽號「阿興」之成年男子（下稱「阿興」）所兜售之影音光碟均為含有暴力、性虐待等內容，而無藝術性、醫學性或教育性價值之猥褻資訊或物品，是不問有無採取適當之安全隔絕措施（例如附加封套、警告標示或限於依法令特定之場所等），均一律禁止散布、播送或販賣，竟仍基於販賣猥褻影音光碟之犯意，自100年3至4月間，向「阿興」以每片新臺幣（下同)20元之價格購入前開猥褻無碼影音光碟後，公開陳列在上址營業店面，並以每片40元之價格販售與不特定人以營利。嗣於同年9月20日下午7時40分許，為警持法院核發之搜索票在上址搜索查獲，並扣得販售所剩餘之猥褻影音光碟4,057片。案經臺北市政府警察局中山分局報告臺灣臺北地方法院檢察署檢察官偵查後聲請簡易判決處刑。二、上揭犯罪事實，業據被告夏祐豪於警詢、偵查中坦承不諱（見臺灣臺北地方法院檢察署100度速偵字第219號卷〈下稱偵卷〉第5至8、29至30頁），且有本院核發之搜索票、自願受搜索同意書、搜索扣押筆錄、扣押物品目錄表各1份、查獲現場、扣案猥褻影音光碟內容節錄照片共19張存卷可查（見偵卷第9至13、19至22頁），足認被告之前開任意性自白與事實相符，應堪採信。本案事證明確，被告犯行堪以認定，應予依法論科。三、按刑法上之販賣罪，並不以販入之後復行賣出為構成要件，只須以營利為目的而購入或賣出，有一於此，罪即成立，有最高法院67年台上字第2500號判例意旨可資參照，故不論是否已賣出，均無影響犯罪之成立。次按，所謂猥褻，指客觀上足以刺激或滿足性慾，其內容可與性器官、性行為及性文化之描繪與論述聯結，且須以引起普通一般人羞恥或厭惡感而侵害性的道德感情，有礙於社會風化者為限，司法院釋字第407號解釋意旨參照。又按刑法第231條第1項規定所謂散布、播送、販賣、公然陳列猥褻之資訊或物品，或以他法供人觀覽、聽聞之行為，係指對含有暴力、性虐待或人獸性交等而無藝術性、醫學性或教育性價值之猥褻資訊或物品為傳布，或對其他客觀上足以刺激或滿足性慾，而令一般人感覺不堪呈現於眾或不能忍受而排拒之猥褻資訊或物品，未採取適當之安全隔絕措施而傳布，使一般人得以見聞之行為；同條第2項規定所謂意圖散布、播送、販賣而製造、持有猥褻資訊、物品之行為，亦僅指意圖傳布含有暴力、性虐待或人獸性交等而無藝術性、醫學性或教育性價值之猥褻資訊或物品而製造、持有之行為，或對其他客觀上足以刺激或滿足性慾，而令一般人感覺不堪呈現於眾或不能忍受而排拒之猥褻資訊或物品，意圖不採取適當安全隔絕措施之傳布，使一般人得以見聞而製造或持有該等猥褻資訊、物品之情形，司法院釋字第617號解釋意旨亦可參照。是司法院釋字第617號解釋認定刑法第235條所欲規範之猥褻出版品，應限於兩類猥褻出版品，其中一類係所謂「含有暴力、性虐待或人獸性交等而無藝術性、醫學性或教育性價值」之所謂硬蕊（hardcore）猥褻資訊或物品；另一類則為「客觀上足以刺激或滿足性慾，而令一般人感覺不堪呈現於眾或不能忍受而排拒」之非硬蕊之一般猥褻資訊或物品，後者則必須該「資訊未採取適當之安全隔絕措施而傳布，使一般人得以見聞之行為」。查被告基於販賣猥褻影音光碟之犯意，自100年3至4月間購入上開猥褻影音光碟，該等光碟影像內含暴力、性虐待等情形，無藝術性、醫學性或教育性價值，有扣案猥褻影音光碟內容節錄照片在卷足憑，堪認扣案之光碟均屬猥褻影音光碟甚明。四、核被告所為，係犯刑法第235條第1項之販賣猥褻影音光碟罪。聲請簡易判決書雖載係犯同條項之「散布猥褻物品罪」，然聲請簡易判決處刑書既已就被告有購入、販出及其販售價格具體敘明，則此部分論罪罪名應屬誤載，併予陳明。再按刑事法若干犯罪行為態樣，本質上原具有反覆、延續實行之特徵，立法時既予特別歸類，定為犯罪構成要件之行為要素，則行為人基於概括之犯意，在密切接近之一定時、地持續實行之複次行為，倘依社會通念，於客觀上認為符合一個反覆、延續性之行為觀念者，於刑法評價上，即應僅成立一罪，俾免有重複評價、刑度超過罪責與不法內涵之疑慮；學理上所稱「集合犯」之職業性、營業性或收集性等具有重複特質之犯罪均屬之，例如經營、從事業務、收集、販賣、製造、散布等行為概念者是，最高法院95年度台上字第1079號判決意旨參照。查被告自100年3月起至同年9月20日下午7時40分許為警查獲時止，在上址「東京熱便利屋」內多次反覆持續販賣猥褻影音光碟而未曾間斷，是其販賣猥褻漫畫書籍之營業性行為，於概念上應評價為包括一罪之集合犯，而僅論以一販賣猥褻漫畫書籍罪。其公然陳列、意圖販賣而持有猥褻漫畫書籍之低度行為，均為販賣之高度行為所吸收，均不另論罪。又被告前因事實及理由一所載案件，經論處徒刑後，於98年9月1日縮刑期滿執行完畢出監等節，有臺灣高等法院被告前案紀錄表1份在卷可按，其受有期徒刑執行完畢後，5年內故意再犯有期徒刑以上之上開之罪，為累犯，應依刑法第47條第1項規定，加重其刑。爰審酌被告販售含有暴力、性虐待之影音光碟，危害社會善良風俗，迄至為警查獲之時，尚仍扣得4,057片猥褻影音光碟，數量龐大，對社會善良風俗產生不良影響甚鉅，惟念被告犯後坦承犯行，態度後尚可，暨衡諸其教育程度為國中肄業，以自營商為業，犯罪動機、素行、智識程度、生活狀況等一切情狀，量處如主文所示之刑，並諭知易科罰金之折算標準。至扣案之猥褻影音光碟4,057片，內容含有猥褻之影音，均屬猥褻物品，依刑法第235條第3項之規定，不問屬於犯人與否，沒收之。五、依刑事訴訟法第449條第1項前段、第3項、第450條第1項，刑法第235條第1項、第3項、第47條第1項、第41條第1項前段，刑法施行法第1條之1第1項、第2項但書，逕以簡易判決處刑如主文。六、如不服本判決，得於判決書送達之翌日起10日內，以書狀敘述理由，向本院提出上訴。中華民國100年10月14日刑事第八庭法官湯千慧以上正本證明與原本無異。如不服本判決，應於收受送達後10日內向本院提出上訴書狀，並應敘述具體理由；其未敘述上訴理由者，應於上訴期間屆滿後20日內向本院補提理由書（均須按他造當事人之人數附繕）「切勿逕送上級法院」。書記官游雅鈞中華民國100年10月14日附錄本案論罪科刑法條全文：中華民國刑法第235條（散布、販賣猥褻物品及製造持有罪）散布、播送或販賣猥褻之文字、圖畫、聲音、影像或其他物品，或公然陳列，或以他法供人觀覽、聽聞者，處2年以下有期徒刑、拘役或科或併科3萬元以下罰金。意圖散布、播送、販賣而製造、持有前項文字、圖畫、聲音、影像及其附著物或其他物品者，亦同。前二項之文字、圖畫、聲音或影像之附著物及物品，不問屬於犯人與否，沒收之。",
  "characters": {
    "judges": [
      "湯千慧"
    ],
    "prosecutors": [

    ],
    "lawyers": [

    ],
    "clerks": [
      "游雅鈞"
    ],
    "plaintiffs": [

    ],
    "defendants": [
      "夏祐豪"
    ],
    "prosecutor_office": [
      "臺灣臺北地方法院檢察署檢察官"
    ],
    "creditors": [

    ],
    "debtors": [

    ],
    "judicial_associate_officer": [

    ]
  },
  "adjudged_at": "2011-10-14",
  "created_at": "2016-02-14 04:47:30",
  "updated_at": "2016-02-14 04:47:30"
}