{
  "identify": "TPD-100-簡-3744-20111014-1",
  "court": {
    "name": "臺灣臺北地方法院",
    "code": "TPD"
  },
  "division": {
    "name": "刑事",
    "code": "M"
  },
  "year": 100,
  "word": "簡",
  "number": "3744",
  "jcheck": "1",
  "reason": "詐欺",
  "content": "臺灣臺北地方法院刑事簡易判決         100年度簡字第3744號\n聲  請  人  臺灣臺北地方法院檢察署檢察官\n被      告  許政新\n上列被告因詐欺案件，經檢察官聲請以簡易判決處刑（100年度\n偵字第17966號），本院判決如下：\n    主  文\n許政新幫助意圖為自己不法之所有，以詐術使人將本人之物交付\n，處拘役伍拾日，如易科罰金，以新臺幣壹仟元折算壹日。\n    事  實\n一、許政新可預見其提供提款卡及密碼等帳戶資料予他人使用，\n    將為其等持之遂行財產上犯罪之用，竟仍以縱有人以其金融\n    帳戶實施詐欺取財犯行，亦不違背其本意之幫助犯意，於民\n    國100年7月14日14時許，在臺北火車站東三門，將其本人名\n    義所申辦之中華郵政股份有限公司新店復興郵局（下稱新店\n    復興郵局）帳號000-00000000 000000號帳戶之存摺影本及\n    提款卡，交付給真實姓名年籍不詳之成年男子，之後再於電\n    話中將該提款卡之密碼告知對方。而該男子所屬詐欺集團之\n    成員取得許政新上開新店復興郵局帳戶資料後，即基於意圖\n    為自己不法所有之詐欺犯意，(一)於100年7月14日21時許致電\n    黃莉雯，佯稱其先前網路購物時之結標方式設定錯誤，必須\n    至提款機前取消扣款設定云云，致使黃莉雯陷於錯誤，於同\n    日21時19分許及21時44分許，在設於桃園縣龍潭鄉○○路之\n    郵局自動櫃員機前，依該詐欺集團成員指示操作，共匯款新\n    臺幣（下同）5萬9978元至許政新上開新店復興郵局帳戶內\n    ；(二)於100年7月14日21時45分許致電黃郁涵，佯稱其先前網\n    路購物時之匯款帳戶有誤，必須至提款機依指示操作以進行\n    轉帳云云，致使黃郁涵陷於錯誤，於同日22時8分及22時15\n    分許，在設於新北市○○區○○路3段與永平街口全家便利\n    商店內之自動櫃員機前，依該詐欺集團成員指示操作，共匯\n    款2萬2800元至許政新上開新店復興郵局帳戶內。嗣因黃莉\n    雯、黃郁涵查覺有異，因而報警查悉上情。\n    理  由\n一、訊據被告許政新固坦承有於事實欄所述時、地將其提款卡及\n    密碼交付並告知予不明人士之情，惟矢口否認有何幫助詐欺\n    之犯行，辯稱：伊沒有賣，也沒有借人家使用帳戶；伊在\n    518 網站求職，在100年7月12日時接到電話，對方問伊要不\n    要接受面試，便約同年月14日在台北車站東三門面試，當天\n    有一男子來面試，問伊有無欠錢，要伊提供存摺、提款卡，\n    伊便將上開文件及履歷表交給對方，對方稱會再請主管打電\n    話給伊，後來有一個主管與其聯絡，問其隔天能否上班，並\n    且向伊要提款卡密碼，說要匯錢進去看能不能提領，伊便將\n    密碼告訴該主管，但伊後來沒接到電話，才至郵局掛失云云\n    。經查：\n(一)被告有將其申辦之上開帳戶提款卡、存摺影本交付予不明人士\n  ，並告知提款卡密碼，嗣被害人黃莉雯、黃郁涵旋遭詐欺集團\n  成員以上述手法詐騙，因而陷於錯誤，先後將前述3筆金額匯\n  款至被告上開郵局帳戶，該帳戶並經被害人報案通報列管為警\n  示帳戶等情，業為被告所不爭執，並據被害人黃莉雯、黃郁涵\n  於警詢指述綦詳，復有前揭新店復興郵局帳戶之開戶資料及歷\n  史交易清單、被害人黃莉雯於桃園縣政府警察局龍潭分局龍潭\n  派出所受理各類案件紀錄表、受理詐騙帳戶通報警示簡便格式\n  表、金融機構聯防機制通報單、受理刑事案件報案三聯單、內\n  政部警政署反詐騙諮詢專線紀錄表、郵政自動櫃員機交易明細\n  表；被害人黃郁涵於新北市政府警察局新店分局安和派出所受\n  理詐騙帳戶通報警示簡便格式表、金融機構聯防機制通報單、\n  受理刑事案件報案三聯單、內政部警政署反詐騙諮詢專線紀錄\n  表、台新銀行自動櫃員機交易明細表等在卷可稽，此部分事實\n  ，堪以認定。\n(二)被告雖以前詞置辯，惟按刑法之故意犯，可分為直接故意與不\n  確定故意，所謂不確定故意即指行為人對於構成犯罪之事實，\n  預見其發生而其發生並不違反其本意，刑法第13條第2項定有\n  明文。是被告若對於他人可能以其所交付之帳戶，進行詐欺取\n  財之犯罪行為，已預見其發生而其發生並不違反其本意，則其\n  自仍應負相關之罪責。而社會之常態，應徵工作者於應徵工作\n  時，除非係臨性點工，若係正式工作，應徵者應備相關履歷，\n  至徵人之公司或行號面試，雙方見面談妥工作時間、工作報酬\n  、工作內容等關係個人權益之重要事項，再交付個人未來領取\n  薪資之帳戶號碼，作為薪資匯款之用，而不會於第一次面試時\n  ，即要求應徵者交出提領帳戶款項用之提款卡及密碼。且應徵\n  者須陳明個人基本資料，俾利申報薪資所得。查被告於偵查中\n  自承：之前找的工作，都是在公司面試；這次在火車站面試，\n  會覺得有點奇怪等語（見100年度偵字第17966號卷第48-49頁\n  ），且被告亦稱，密碼是透過電話跟主管講的等語，是被告非\n  但未在對方的公司所在地接受應徵、面試，且所交付者並非僅\n  是帳戶號碼，而是上開帳戶用以提領款項用之提款卡、密碼，\n  不僅有違上開應徵常規，亦迥異於被告先前應徵之經驗。且邇\n  來利用電話或報紙刊登廣告詐欺取財之犯罪類型層出不窮，該\n  等犯罪多數均係利用人頭帳戶作為出入帳戶，並經媒體廣為披\n  載，此應為一般人本於一般認知能力所易於意會者，況被告既\n  曾應徵過其他工作，則已有相當之社會歷練，對此顯然知之甚\n  詳。是被告對提供帳戶資料與他人，該人將持其帳戶資料，用\n  於詐欺取財之不法用途自有所認識，被告具幫助詐欺取財之不\n  確定故意亦至臻明確。是被告前揭所辯，為卸責之詞，不足採\n  信。綜上所述，本件事證明確，被告幫助詐欺犯行，堪以認定\n  ，應依法論科。\n二、核被告所為，係犯刑法第30條第1項前段、第339條第1項之\n    幫助詐欺取財罪。被害人黃莉雯雖分2次匯款，惟係遭詐欺\n    取財行為後之接續匯款動作，故被告此部分僅係一次幫助詐\n    欺取財之行為。被告以一交付上開帳戶之行為，幫助該詐欺\n    集團2個詐欺取財犯行，為想像競合犯，應依刑法第55條規\n    定，從一重處斷。被告係屬幫助犯，其提供帳戶資料予詐欺\n    集團成員，對被害人財產損害之造成，較諸具犯罪支配力之\n    正犯有明顯之差異，爰依刑法第30條第2項之規定，減輕其\n    刑。爰審酌被告年紀尚輕，無前科，素行良好，犯罪手段尚\n    稱平和，被害人所受損害非鉅等一切情狀，爰量處如主文所\n    示之刑，並諭知易科罰金之折算標準。\n據上論斷，應依刑事訴訟法第449條第1項前段、第3項、第454\n條第1項，刑法第339條第1項、第30條第1項前段、第2項、第41\n條第1項前段、第55條，刑法施行法第1條之1，逕以簡易判決處\n刑如主文。\n中    華    民    國   100    年    10    月    14    日\n                  刑事第十一庭  法  官  蕭涵勻\n以上正本證明與原本無異。\n如不服本判決應於收受送達後10日內向本院提出上訴書狀，並應\n敘述具體理由；其未敘述上訴理由者，應於上訴期間屆滿後20日\n內向本院補提理由書（均須按他造當事人之人數附繕）「切勿逕\n送上級法院」。\n                                書記官  陳育君\n中    華    民    國   100    年    10    月    14    日\n附錄本案論罪法條：\n中華民國刑法第339 條\n意圖為自己或第三人不法之所有，以詐術使人將本人或第三人之\n物交付者，處 5 年以下有期徒刑、拘役或科或併科 1 千元以下\n罰金。\n以前項方法得財產上不法之利益或使第三人得之者，亦同。\n前二項之未遂犯罰之。",
  "structure": {
    "main": "許政新幫助意圖為自己不法之所有，以詐術使人將本人之物交付\n，處拘役伍拾日，如易科罰金，以新臺幣壹仟元折算壹日。",
    "fact": "一、許政新可預見其提供提款卡及密碼等帳戶資料予他人使用，\n    將為其等持之遂行財產上犯罪之用，竟仍以縱有人以其金融\n    帳戶實施詐欺取財犯行，亦不違背其本意之幫助犯意，於民\n    國100年7月14日14時許，在臺北火車站東三門，將其本人名\n    義所申辦之中華郵政股份有限公司新店復興郵局（下稱新店\n    復興郵局）帳號000-00000000 000000號帳戶之存摺影本及\n    提款卡，交付給真實姓名年籍不詳之成年男子，之後再於電\n    話中將該提款卡之密碼告知對方。而該男子所屬詐欺集團之\n    成員取得許政新上開新店復興郵局帳戶資料後，即基於意圖\n    為自己不法所有之詐欺犯意，(一)於100年7月14日21時許致電\n    黃莉雯，佯稱其先前網路購物時之結標方式設定錯誤，必須\n    至提款機前取消扣款設定云云，致使黃莉雯陷於錯誤，於同\n    日21時19分許及21時44分許，在設於桃園縣龍潭鄉○○路之\n    郵局自動櫃員機前，依該詐欺集團成員指示操作，共匯款新\n    臺幣（下同）5萬9978元至許政新上開新店復興郵局帳戶內\n    ；(二)於100年7月14日21時45分許致電黃郁涵，佯稱其先前網\n    路購物時之匯款帳戶有誤，必須至提款機依指示操作以進行\n    轉帳云云，致使黃郁涵陷於錯誤，於同日22時8分及22時15\n    分許，在設於新北市○○區○○路3段與永平街口全家便利\n    商店內之自動櫃員機前，依該詐欺集團成員指示操作，共匯\n    款2萬2800元至許政新上開新店復興郵局帳戶內。嗣因黃莉\n    雯、黃郁涵查覺有異，因而報警查悉上情。",
    "reason": "一、訊據被告許政新固坦承有於事實欄所述時、地將其提款卡及\n    密碼交付並告知予不明人士之情，惟矢口否認有何幫助詐欺\n    之犯行，辯稱：伊沒有賣，也沒有借人家使用帳戶；伊在\n    518 網站求職，在100年7月12日時接到電話，對方問伊要不\n    要接受面試，便約同年月14日在台北車站東三門面試，當天\n    有一男子來面試，問伊有無欠錢，要伊提供存摺、提款卡，\n    伊便將上開文件及履歷表交給對方，對方稱會再請主管打電\n    話給伊，後來有一個主管與其聯絡，問其隔天能否上班，並\n    且向伊要提款卡密碼，說要匯錢進去看能不能提領，伊便將\n    密碼告訴該主管，但伊後來沒接到電話，才至郵局掛失云云\n    。經查：\n(一)被告有將其申辦之上開帳戶提款卡、存摺影本交付予不明人士\n  ，並告知提款卡密碼，嗣被害人黃莉雯、黃郁涵旋遭詐欺集團\n  成員以上述手法詐騙，因而陷於錯誤，先後將前述3筆金額匯\n  款至被告上開郵局帳戶，該帳戶並經被害人報案通報列管為警\n  示帳戶等情，業為被告所不爭執，並據被害人黃莉雯、黃郁涵\n  於警詢指述綦詳，復有前揭新店復興郵局帳戶之開戶資料及歷\n  史交易清單、被害人黃莉雯於桃園縣政府警察局龍潭分局龍潭\n  派出所受理各類案件紀錄表、受理詐騙帳戶通報警示簡便格式\n  表、金融機構聯防機制通報單、受理刑事案件報案三聯單、內\n  政部警政署反詐騙諮詢專線紀錄表、郵政自動櫃員機交易明細\n  表；被害人黃郁涵於新北市政府警察局新店分局安和派出所受\n  理詐騙帳戶通報警示簡便格式表、金融機構聯防機制通報單、\n  受理刑事案件報案三聯單、內政部警政署反詐騙諮詢專線紀錄\n  表、台新銀行自動櫃員機交易明細表等在卷可稽，此部分事實\n  ，堪以認定。\n(二)被告雖以前詞置辯，惟按刑法之故意犯，可分為直接故意與不\n  確定故意，所謂不確定故意即指行為人對於構成犯罪之事實，\n  預見其發生而其發生並不違反其本意，刑法第13條第2項定有\n  明文。是被告若對於他人可能以其所交付之帳戶，進行詐欺取\n  財之犯罪行為，已預見其發生而其發生並不違反其本意，則其\n  自仍應負相關之罪責。而社會之常態，應徵工作者於應徵工作\n  時，除非係臨性點工，若係正式工作，應徵者應備相關履歷，\n  至徵人之公司或行號面試，雙方見面談妥工作時間、工作報酬\n  、工作內容等關係個人權益之重要事項，再交付個人未來領取\n  薪資之帳戶號碼，作為薪資匯款之用，而不會於第一次面試時\n  ，即要求應徵者交出提領帳戶款項用之提款卡及密碼。且應徵\n  者須陳明個人基本資料，俾利申報薪資所得。查被告於偵查中\n  自承：之前找的工作，都是在公司面試；這次在火車站面試，\n  會覺得有點奇怪等語（見100年度偵字第17966號卷第48-49頁\n  ），且被告亦稱，密碼是透過電話跟主管講的等語，是被告非\n  但未在對方的公司所在地接受應徵、面試，且所交付者並非僅\n  是帳戶號碼，而是上開帳戶用以提領款項用之提款卡、密碼，\n  不僅有違上開應徵常規，亦迥異於被告先前應徵之經驗。且邇\n  來利用電話或報紙刊登廣告詐欺取財之犯罪類型層出不窮，該\n  等犯罪多數均係利用人頭帳戶作為出入帳戶，並經媒體廣為披\n  載，此應為一般人本於一般認知能力所易於意會者，況被告既\n  曾應徵過其他工作，則已有相當之社會歷練，對此顯然知之甚\n  詳。是被告對提供帳戶資料與他人，該人將持其帳戶資料，用\n  於詐欺取財之不法用途自有所認識，被告具幫助詐欺取財之不\n  確定故意亦至臻明確。是被告前揭所辯，為卸責之詞，不足採\n  信。綜上所述，本件事證明確，被告幫助詐欺犯行，堪以認定\n  ，應依法論科。\n二、核被告所為，係犯刑法第30條第1項前段、第339條第1項之\n    幫助詐欺取財罪。被害人黃莉雯雖分2次匯款，惟係遭詐欺\n    取財行為後之接續匯款動作，故被告此部分僅係一次幫助詐\n    欺取財之行為。被告以一交付上開帳戶之行為，幫助該詐欺\n    集團2個詐欺取財犯行，為想像競合犯，應依刑法第55條規\n    定，從一重處斷。被告係屬幫助犯，其提供帳戶資料予詐欺\n    集團成員，對被害人財產損害之造成，較諸具犯罪支配力之\n    正犯有明顯之差異，爰依刑法第30條第2項之規定，減輕其\n    刑。爰審酌被告年紀尚輕，無前科，素行良好，犯罪手段尚\n    稱平和，被害人所受損害非鉅等一切情狀，爰量處如主文所\n    示之刑，並諭知易科罰金之折算標準。\n據上論斷，應依刑事訴訟法第449條第1項前段、第3項、第454\n條第1項，刑法第339條第1項、第30條第1項前段、第2項、第41\n條第1項前段、第55條，刑法施行法第1條之1，逕以簡易判決處\n刑如主文。\n中    華    民    國   100    年    10    月    14    日\n                  刑事第十一庭  法  官  蕭涵勻\n以上正本證明與原本無異。\n如不服本判決應於收受送達後10日內向本院提出上訴書狀，並應\n敘述具體理由；其未敘述上訴理由者，應於上訴期間屆滿後20日\n內向本院補提理由書（均須按他造當事人之人數附繕）「切勿逕\n送上級法院」。\n                                書記官  陳育君"
  },
  "search": "臺灣臺北地方法院刑事簡易判決100年度簡字第3744號聲請人臺灣臺北地方法院檢察署檢察官被告許政新上列被告因詐欺案件，經檢察官聲請以簡易判決處刑（100年度偵字第17966號），本院判決如下：主文許政新幫助意圖為自己不法之所有，以詐術使人將本人之物交付，處拘役伍拾日，如易科罰金，以新臺幣壹仟元折算壹日。事實一、許政新可預見其提供提款卡及密碼等帳戶資料予他人使用，將為其等持之遂行財產上犯罪之用，竟仍以縱有人以其金融帳戶實施詐欺取財犯行，亦不違背其本意之幫助犯意，於民國100年7月14日14時許，在臺北火車站東三門，將其本人名義所申辦之中華郵政股份有限公司新店復興郵局（下稱新店復興郵局）帳號000-00000000000000號帳戶之存摺影本及提款卡，交付給真實姓名年籍不詳之成年男子，之後再於電話中將該提款卡之密碼告知對方。而該男子所屬詐欺集團之成員取得許政新上開新店復興郵局帳戶資料後，即基於意圖為自己不法所有之詐欺犯意，(一)於100年7月14日21時許致電黃莉雯，佯稱其先前網路購物時之結標方式設定錯誤，必須至提款機前取消扣款設定云云，致使黃莉雯陷於錯誤，於同日21時19分許及21時44分許，在設於桃園縣龍潭鄉○○路之郵局自動櫃員機前，依該詐欺集團成員指示操作，共匯款新臺幣（下同）5萬9978元至許政新上開新店復興郵局帳戶內；(二)於100年7月14日21時45分許致電黃郁涵，佯稱其先前網路購物時之匯款帳戶有誤，必須至提款機依指示操作以進行轉帳云云，致使黃郁涵陷於錯誤，於同日22時8分及22時15分許，在設於新北市○○區○○路3段與永平街口全家便利商店內之自動櫃員機前，依該詐欺集團成員指示操作，共匯款2萬2800元至許政新上開新店復興郵局帳戶內。嗣因黃莉雯、黃郁涵查覺有異，因而報警查悉上情。理由一、訊據被告許政新固坦承有於事實欄所述時、地將其提款卡及密碼交付並告知予不明人士之情，惟矢口否認有何幫助詐欺之犯行，辯稱：伊沒有賣，也沒有借人家使用帳戶；伊在518網站求職，在100年7月12日時接到電話，對方問伊要不要接受面試，便約同年月14日在台北車站東三門面試，當天有一男子來面試，問伊有無欠錢，要伊提供存摺、提款卡，伊便將上開文件及履歷表交給對方，對方稱會再請主管打電話給伊，後來有一個主管與其聯絡，問其隔天能否上班，並且向伊要提款卡密碼，說要匯錢進去看能不能提領，伊便將密碼告訴該主管，但伊後來沒接到電話，才至郵局掛失云云。經查：(一)被告有將其申辦之上開帳戶提款卡、存摺影本交付予不明人士，並告知提款卡密碼，嗣被害人黃莉雯、黃郁涵旋遭詐欺集團成員以上述手法詐騙，因而陷於錯誤，先後將前述3筆金額匯款至被告上開郵局帳戶，該帳戶並經被害人報案通報列管為警示帳戶等情，業為被告所不爭執，並據被害人黃莉雯、黃郁涵於警詢指述綦詳，復有前揭新店復興郵局帳戶之開戶資料及歷史交易清單、被害人黃莉雯於桃園縣政府警察局龍潭分局龍潭派出所受理各類案件紀錄表、受理詐騙帳戶通報警示簡便格式表、金融機構聯防機制通報單、受理刑事案件報案三聯單、內政部警政署反詐騙諮詢專線紀錄表、郵政自動櫃員機交易明細表；被害人黃郁涵於新北市政府警察局新店分局安和派出所受理詐騙帳戶通報警示簡便格式表、金融機構聯防機制通報單、受理刑事案件報案三聯單、內政部警政署反詐騙諮詢專線紀錄表、台新銀行自動櫃員機交易明細表等在卷可稽，此部分事實，堪以認定。(二)被告雖以前詞置辯，惟按刑法之故意犯，可分為直接故意與不確定故意，所謂不確定故意即指行為人對於構成犯罪之事實，預見其發生而其發生並不違反其本意，刑法第13條第2項定有明文。是被告若對於他人可能以其所交付之帳戶，進行詐欺取財之犯罪行為，已預見其發生而其發生並不違反其本意，則其自仍應負相關之罪責。而社會之常態，應徵工作者於應徵工作時，除非係臨性點工，若係正式工作，應徵者應備相關履歷，至徵人之公司或行號面試，雙方見面談妥工作時間、工作報酬、工作內容等關係個人權益之重要事項，再交付個人未來領取薪資之帳戶號碼，作為薪資匯款之用，而不會於第一次面試時，即要求應徵者交出提領帳戶款項用之提款卡及密碼。且應徵者須陳明個人基本資料，俾利申報薪資所得。查被告於偵查中自承：之前找的工作，都是在公司面試；這次在火車站面試，會覺得有點奇怪等語（見100年度偵字第17966號卷第48-49頁），且被告亦稱，密碼是透過電話跟主管講的等語，是被告非但未在對方的公司所在地接受應徵、面試，且所交付者並非僅是帳戶號碼，而是上開帳戶用以提領款項用之提款卡、密碼，不僅有違上開應徵常規，亦迥異於被告先前應徵之經驗。且邇來利用電話或報紙刊登廣告詐欺取財之犯罪類型層出不窮，該等犯罪多數均係利用人頭帳戶作為出入帳戶，並經媒體廣為披載，此應為一般人本於一般認知能力所易於意會者，況被告既曾應徵過其他工作，則已有相當之社會歷練，對此顯然知之甚詳。是被告對提供帳戶資料與他人，該人將持其帳戶資料，用於詐欺取財之不法用途自有所認識，被告具幫助詐欺取財之不確定故意亦至臻明確。是被告前揭所辯，為卸責之詞，不足採信。綜上所述，本件事證明確，被告幫助詐欺犯行，堪以認定，應依法論科。二、核被告所為，係犯刑法第30條第1項前段、第339條第1項之幫助詐欺取財罪。被害人黃莉雯雖分2次匯款，惟係遭詐欺取財行為後之接續匯款動作，故被告此部分僅係一次幫助詐欺取財之行為。被告以一交付上開帳戶之行為，幫助該詐欺集團2個詐欺取財犯行，為想像競合犯，應依刑法第55條規定，從一重處斷。被告係屬幫助犯，其提供帳戶資料予詐欺集團成員，對被害人財產損害之造成，較諸具犯罪支配力之正犯有明顯之差異，爰依刑法第30條第2項之規定，減輕其刑。爰審酌被告年紀尚輕，無前科，素行良好，犯罪手段尚稱平和，被害人所受損害非鉅等一切情狀，爰量處如主文所示之刑，並諭知易科罰金之折算標準。據上論斷，應依刑事訴訟法第449條第1項前段、第3項、第454條第1項，刑法第339條第1項、第30條第1項前段、第2項、第41條第1項前段、第55條，刑法施行法第1條之1，逕以簡易判決處刑如主文。中華民國100年10月14日刑事第十一庭法官蕭涵勻以上正本證明與原本無異。如不服本判決應於收受送達後10日內向本院提出上訴書狀，並應敘述具體理由；其未敘述上訴理由者，應於上訴期間屆滿後20日內向本院補提理由書（均須按他造當事人之人數附繕）「切勿逕送上級法院」。書記官陳育君中華民國100年10月14日附錄本案論罪法條：中華民國刑法第339條意圖為自己或第三人不法之所有，以詐術使人將本人或第三人之物交付者，處5年以下有期徒刑、拘役或科或併科1千元以下罰金。以前項方法得財產上不法之利益或使第三人得之者，亦同。前二項之未遂犯罰之。",
  "characters": {
    "judges": [
      "蕭涵勻"
    ],
    "prosecutors": [

    ],
    "lawyers": [

    ],
    "clerks": [
      "陳育君"
    ],
    "plaintiffs": [

    ],
    "defendants": [
      "許政新"
    ],
    "prosecutor_office": [
      "臺灣臺北地方法院檢察署檢察官"
    ],
    "creditors": [

    ],
    "debtors": [

    ],
    "judicial_associate_officer": [

    ]
  },
  "adjudged_at": "2011-10-14",
  "created_at": "2016-02-14 04:50:13",
  "updated_at": "2016-02-14 04:50:13"
}