{
  "identify": "TPD-100-易-1812-20111014-1",
  "court": {
    "name": "臺灣臺北地方法院",
    "code": "TPD"
  },
  "division": {
    "name": "刑事",
    "code": "M"
  },
  "year": 100,
  "word": "易",
  "number": "1812",
  "jcheck": "1",
  "reason": "傷害",
  "content": "臺灣臺北地方法院刑事判決             100年度易字第1812號\n公  訴  人  臺灣臺北地方法院檢察署檢察官\n被      告  陳昱銘\n選任辯護人  阮祺祥律師\n上列被告因過失傷害案件，經檢察官提起公訴（一○○年度調偵\n字第六二四號），判決如下：\n    主  文\n本件公訴不受理。\n    理  由\n一、公訴意旨略以：被告陳昱銘於民國九十九年十一月二十五日\n    下午九時許，在神戶通商貿易企業有限公司（址設臺北市大\n    安區○○○路○段十二號五樓之五）內，因故與告訴人蘆澤\n    洋太郎發生爭執，竟基於傷害之故意，出手抓告訴人之衣領\n    推撞牆壁，致告訴人受有頭部外傷、左前額鈍擦傷二乘二公\n    分、右手擦傷一乘一公分、左耳垂擦傷○點五乘○點五公分\n    之傷害。因認被告涉犯刑法第二百七十七條第一項之傷害罪\n    嫌等語。\n二、按告訴乃論之罪，告訴人於第一審辯論終結前得撤回其告訴\n    ，又告訴經撤回者，應諭知不受理之判決，刑事訴訟法第二\n    百三十八條第一項、第三百零三條第三款分別定有明文。\n三、查本件告訴人告訴被告傷害案件，起訴書認被告係觸犯刑法\n    第二百七十七條第一項之傷害罪嫌，依同法第二百八十七條\n    前段之規定，須告訴乃論。茲因告訴人與被告於一○○年十\n    月五日達成和解，告訴人並於同日具狀撤回告訴，有刑事撤\n    回告訴狀在卷足憑（本院卷第三十三頁頁參照），依照首開\n    說明，本件爰不經言詞辯論，逕為諭知不受理之判決。\n據上論斷，應依刑事訴訟法第三百零三條第三款、第三百零七條\n，判決如主文。\n中    華    民    國   100    年    10    月    14    日\n                  刑事第九庭    法  官  鄭富城\n以上正本證明與原本無異。\n如不服本判決應於收受送達後10日內向本院提出上訴書狀，並應\n敘述具體理由；其未敘述上訴理由者，應於上訴期間屆滿後20日\n內向本院補提理由書（均須按他造當事人之人數附繕）「切勿逕\n送上級法院」。\n                                書記官  顏淑華\n中    華    民    國   100    年    10    月    14    日",
  "structure": {
    "main": "本件公訴不受理。",
    "reason": "一、公訴意旨略以：被告陳昱銘於民國九十九年十一月二十五日\n    下午九時許，在神戶通商貿易企業有限公司（址設臺北市大\n    安區○○○路○段十二號五樓之五）內，因故與告訴人蘆澤\n    洋太郎發生爭執，竟基於傷害之故意，出手抓告訴人之衣領\n    推撞牆壁，致告訴人受有頭部外傷、左前額鈍擦傷二乘二公\n    分、右手擦傷一乘一公分、左耳垂擦傷○點五乘○點五公分\n    之傷害。因認被告涉犯刑法第二百七十七條第一項之傷害罪\n    嫌等語。\n二、按告訴乃論之罪，告訴人於第一審辯論終結前得撤回其告訴\n    ，又告訴經撤回者，應諭知不受理之判決，刑事訴訟法第二\n    百三十八條第一項、第三百零三條第三款分別定有明文。\n三、查本件告訴人告訴被告傷害案件，起訴書認被告係觸犯刑法\n    第二百七十七條第一項之傷害罪嫌，依同法第二百八十七條\n    前段之規定，須告訴乃論。茲因告訴人與被告於一○○年十\n    月五日達成和解，告訴人並於同日具狀撤回告訴，有刑事撤\n    回告訴狀在卷足憑（本院卷第三十三頁頁參照），依照首開\n    說明，本件爰不經言詞辯論，逕為諭知不受理之判決。\n據上論斷，應依刑事訴訟法第三百零三條第三款、第三百零七條\n，判決如主文。"
  },
  "search": "臺灣臺北地方法院刑事判決100年度易字第1812號公訴人臺灣臺北地方法院檢察署檢察官被告陳昱銘選任辯護人阮祺祥律師上列被告因過失傷害案件，經檢察官提起公訴（一○○年度調偵字第六二四號），判決如下：主文本件公訴不受理。理由一、公訴意旨略以：被告陳昱銘於民國九十九年十一月二十五日下午九時許，在神戶通商貿易企業有限公司（址設臺北市大安區○○○路○段十二號五樓之五）內，因故與告訴人蘆澤洋太郎發生爭執，竟基於傷害之故意，出手抓告訴人之衣領推撞牆壁，致告訴人受有頭部外傷、左前額鈍擦傷二乘二公分、右手擦傷一乘一公分、左耳垂擦傷○點五乘○點五公分之傷害。因認被告涉犯刑法第二百七十七條第一項之傷害罪嫌等語。二、按告訴乃論之罪，告訴人於第一審辯論終結前得撤回其告訴，又告訴經撤回者，應諭知不受理之判決，刑事訴訟法第二百三十八條第一項、第三百零三條第三款分別定有明文。三、查本件告訴人告訴被告傷害案件，起訴書認被告係觸犯刑法第二百七十七條第一項之傷害罪嫌，依同法第二百八十七條前段之規定，須告訴乃論。茲因告訴人與被告於一○○年十月五日達成和解，告訴人並於同日具狀撤回告訴，有刑事撤回告訴狀在卷足憑（本院卷第三十三頁頁參照），依照首開說明，本件爰不經言詞辯論，逕為諭知不受理之判決。據上論斷，應依刑事訴訟法第三百零三條第三款、第三百零七條，判決如主文。中華民國100年10月14日刑事第九庭法官鄭富城以上正本證明與原本無異。如不服本判決應於收受送達後10日內向本院提出上訴書狀，並應敘述具體理由；其未敘述上訴理由者，應於上訴期間屆滿後20日內向本院補提理由書（均須按他造當事人之人數附繕）「切勿逕送上級法院」。書記官顏淑華中華民國100年10月14日",
  "characters": {
    "judges": [
      "鄭富城"
    ],
    "prosecutors": [

    ],
    "lawyers": [
      "阮祺祥"
    ],
    "clerks": [
      "顏淑華"
    ],
    "plaintiffs": [

    ],
    "defendants": [
      "陳昱銘"
    ],
    "prosecutor_office": [
      "臺灣臺北地方法院檢察署檢察官"
    ],
    "creditors": [

    ],
    "debtors": [

    ],
    "judicial_associate_officer": [

    ]
  },
  "adjudged_at": "2011-10-14",
  "created_at": "2016-02-14 04:49:11",
  "updated_at": "2016-02-14 04:49:11"
}