{
  "identify": "TYD-100-審訴-1856-20111014-1",
  "court": {
    "name": "臺灣桃園地方法院",
    "code": "TYD"
  },
  "division": {
    "name": "刑事",
    "code": "M"
  },
  "year": 100,
  "word": "審訴",
  "number": "1856",
  "jcheck": "1",
  "reason": "毒品危害防制條例",
  "content": "臺灣桃園地方法院刑事判決           100年度審訴字第1856號\n公  訴  人  臺灣桃園地方法院檢察署檢察官\n被      告  楊華林\n上列被告因毒品危害防制條例案件，經檢察官提起公訴（100 年\n度毒偵字第2894號），嗣於本院準備程序進行中，被告就被訴事\n實為有罪之陳述，經本院告知簡式審判程序意旨，並聽取公訴人\n及被告之意見後，本院合議庭裁定改由受命法官獨任依簡式審判\n程序審理，並判決如下：\n    主  文\n楊華林施用第一級毒品，處有期徒刑柒月；又施用第二級毒品，\n處有期徒刑參月。應執行有期徒刑玖月。\n    事  實\n一、楊華林前於民國97年間因施用毒品案件，經本院以97年度毒\n    聲字第1006號裁定送觀察、勒戒後，認有繼續施用毒品之傾\n    向，再由本院以98年度毒聲字第55號裁定令入戒治處所施以\n    強制戒治，因其戒治成效經評定為合格，於98年9 月15日停\n    止戒治依法釋放，該次施用毒品犯行，並經臺灣桃園地方法\n    院檢察署檢察官以98年度戒毒偵字第261 號為不起訴處分確\n    定。復於99年間（即前開強制戒治執行完畢釋放後5 年內）\n    因施用第一、二級毒品案件，經本院以99年度審訴字第2768\n    號判決分別判處有期徒刑6 月、2 月，並定應執行有期徒刑\n    7 月確定（於本案不構成累犯）。詎其猶不知悛悔，再分別\n    基於施用第一級毒品海洛因、第二級毒品甲基安非他命之犯\n    意，於100 年3 月28日上午8 時許，在其桃園縣大溪鎮○○\n    路63巷68號之住處內，分別以針筒注射之方式施用第一級毒\n    品海洛因及以玻璃球燒烤之方式施用第二級毒品甲基安非他\n    命各1 次。嗣於100 年3 月28日晚間9 時15分許，在新北市\n    ○○區○○路二段148 巷51號前，為警攔檢查獲，並經其同\n    意採集尿液送驗後，結果呈嗎啡、甲基安非他命陽性反應。\n二、案經新北市政府警察局板橋分局報請臺灣桃園地方法院檢察\n    署檢察官偵查起訴。\n    理  由\n一、本案被告所犯之罪，均非法定刑為死刑、無期徒刑或最輕本\n    刑3 年以上有期徒刑之罪，亦非高等法院管轄第一審之案件\n    ，而被告於準備程序中就被訴事實已為有罪之陳述，經本院\n    告知簡式審判程序之旨，並聽取公訴人及被告之意見後，本\n    院合議庭乃依刑事訴訟法第273 條之1 第1 項規定，裁定由\n    受命法官獨任進行簡式審判程序，合先敘明。\n二、又本件既經本院裁定改依簡式審判程序審理，則依刑事訴訟\n    法第273 條之2 、同法第159 條第2 項之規定，不適用傳聞\n    法則有關限制證據能力及證據調查之相關規定。\n三、上揭犯罪事實，業據被告於檢察官訊問及本院準備程序、審\n    理時均自白不諱，復有新北市政府警察局板橋分局偵辦毒品\n    危害防制條例案被移送人姓名及代碼對照表、台灣檢驗科技\n    股份有限公司濫用藥物檢驗報告、臺灣高等法院被告前案紀\n    錄表各1 紙等在卷可稽，足認被告前揭自白核與事實相符，\n    可以採信。綜上，本案事證明確，被告上揭犯行洵堪認定，\n    應予依法論科。\n三、核被告所為，係犯毒品危害防制條例第10條第1 項之施用第\n    一級毒品罪及同條第2 項之施用第二級毒品罪。被告施用第\n    一、二級毒品前非法持有第一、二級毒品之低度行為，皆為\n    施用之高度行為所吸收，均不另論罪。被告所犯上開2 罪間\n    ，犯意各別，行為互殊，應予分論併罰。爰審酌被告前已因\n    施用毒品案件經觀察、勒戒完畢，本應徹底戒除毒癮，詎其\n    仍未能自新、戒斷毒癮，竟一再施用足以導致人體機能發生\n    依賴性、成癮性及抗藥性等障礙之第一、二級毒品，戕害自\n    身健康，漠視法令禁制，實不宜寬縱，並兼衡其智識程度、\n    犯罪之動機、目的、手段及其犯罪後坦承犯行，態度尚可等\n    一切情狀，分別量處如主文所示之刑，並定其應執行之刑，\n    以示懲儆。\n據上論斷，應依刑事訴訟法第273 條之1 第1 項、第299 條第1\n項前段，毒品危害防制條例第10條第1 項、第2 項，刑法第11條\n前段、第51條第5 款，判決如主文。\n本案經檢察官白勝文到庭執行職務。\n中    華    民    國  100   年      10    月    14    日\n                      刑事庭法  官  羅國鴻\n以上正本證明與原本無異。\n如不服本判決，得自收受送達之翌日起10日內向本院提出上訴狀\n（應附繕本），其未敘述上訴理由者，應於上訴期間屆滿後20日\n內補提理由書狀於本院，上訴於臺灣高等法院。\n                            書記官  張筆隆\n中    華    民    國  100   年      10    月    14    日\n附錄本案論罪科刑法條：\n毒品危害防制條例第10條\n施用第一級毒品者，處六月以上五年以下有期徒刑。\n施用第二級毒品者，處三年以下有期徒刑。",
  "structure": {
    "main": "楊華林施用第一級毒品，處有期徒刑柒月；又施用第二級毒品，\n處有期徒刑參月。應執行有期徒刑玖月。",
    "fact": "一、楊華林前於民國97年間因施用毒品案件，經本院以97年度毒\n    聲字第1006號裁定送觀察、勒戒後，認有繼續施用毒品之傾\n    向，再由本院以98年度毒聲字第55號裁定令入戒治處所施以\n    強制戒治，因其戒治成效經評定為合格，於98年9 月15日停\n    止戒治依法釋放，該次施用毒品犯行，並經臺灣桃園地方法\n    院檢察署檢察官以98年度戒毒偵字第261 號為不起訴處分確\n    定。復於99年間（即前開強制戒治執行完畢釋放後5 年內）\n    因施用第一、二級毒品案件，經本院以99年度審訴字第2768\n    號判決分別判處有期徒刑6 月、2 月，並定應執行有期徒刑\n    7 月確定（於本案不構成累犯）。詎其猶不知悛悔，再分別\n    基於施用第一級毒品海洛因、第二級毒品甲基安非他命之犯\n    意，於100 年3 月28日上午8 時許，在其桃園縣大溪鎮○○\n    路63巷68號之住處內，分別以針筒注射之方式施用第一級毒\n    品海洛因及以玻璃球燒烤之方式施用第二級毒品甲基安非他\n    命各1 次。嗣於100 年3 月28日晚間9 時15分許，在新北市\n    ○○區○○路二段148 巷51號前，為警攔檢查獲，並經其同\n    意採集尿液送驗後，結果呈嗎啡、甲基安非他命陽性反應。\n二、案經新北市政府警察局板橋分局報請臺灣桃園地方法院檢察\n    署檢察官偵查起訴。",
    "reason": "一、本案被告所犯之罪，均非法定刑為死刑、無期徒刑或最輕本\n    刑3 年以上有期徒刑之罪，亦非高等法院管轄第一審之案件\n    ，而被告於準備程序中就被訴事實已為有罪之陳述，經本院\n    告知簡式審判程序之旨，並聽取公訴人及被告之意見後，本\n    院合議庭乃依刑事訴訟法第273 條之1 第1 項規定，裁定由\n    受命法官獨任進行簡式審判程序，合先敘明。\n二、又本件既經本院裁定改依簡式審判程序審理，則依刑事訴訟\n    法第273 條之2 、同法第159 條第2 項之規定，不適用傳聞\n    法則有關限制證據能力及證據調查之相關規定。\n三、上揭犯罪事實，業據被告於檢察官訊問及本院準備程序、審\n    理時均自白不諱，復有新北市政府警察局板橋分局偵辦毒品\n    危害防制條例案被移送人姓名及代碼對照表、台灣檢驗科技\n    股份有限公司濫用藥物檢驗報告、臺灣高等法院被告前案紀\n    錄表各1 紙等在卷可稽，足認被告前揭自白核與事實相符，\n    可以採信。綜上，本案事證明確，被告上揭犯行洵堪認定，\n    應予依法論科。\n三、核被告所為，係犯毒品危害防制條例第10條第1 項之施用第\n    一級毒品罪及同條第2 項之施用第二級毒品罪。被告施用第\n    一、二級毒品前非法持有第一、二級毒品之低度行為，皆為\n    施用之高度行為所吸收，均不另論罪。被告所犯上開2 罪間\n    ，犯意各別，行為互殊，應予分論併罰。爰審酌被告前已因\n    施用毒品案件經觀察、勒戒完畢，本應徹底戒除毒癮，詎其\n    仍未能自新、戒斷毒癮，竟一再施用足以導致人體機能發生\n    依賴性、成癮性及抗藥性等障礙之第一、二級毒品，戕害自\n    身健康，漠視法令禁制，實不宜寬縱，並兼衡其智識程度、\n    犯罪之動機、目的、手段及其犯罪後坦承犯行，態度尚可等\n    一切情狀，分別量處如主文所示之刑，並定其應執行之刑，\n    以示懲儆。\n據上論斷，應依刑事訴訟法第273 條之1 第1 項、第299 條第1\n項前段，毒品危害防制條例第10條第1 項、第2 項，刑法第11條\n前段、第51條第5 款，判決如主文。\n本案經檢察官白勝文到庭執行職務。\n中    華    民    國  100   年      10    月    14    日\n                      刑事庭法  官  羅國鴻\n以上正本證明與原本無異。\n如不服本判決，得自收受送達之翌日起10日內向本院提出上訴狀\n（應附繕本），其未敘述上訴理由者，應於上訴期間屆滿後20日\n內補提理由書狀於本院，上訴於臺灣高等法院。\n                            書記官  張筆隆"
  },
  "search": "臺灣桃園地方法院刑事判決100年度審訴字第1856號公訴人臺灣桃園地方法院檢察署檢察官被告楊華林上列被告因毒品危害防制條例案件，經檢察官提起公訴（100年度毒偵字第2894號），嗣於本院準備程序進行中，被告就被訴事實為有罪之陳述，經本院告知簡式審判程序意旨，並聽取公訴人及被告之意見後，本院合議庭裁定改由受命法官獨任依簡式審判程序審理，並判決如下：主文楊華林施用第一級毒品，處有期徒刑柒月；又施用第二級毒品，處有期徒刑參月。應執行有期徒刑玖月。事實一、楊華林前於民國97年間因施用毒品案件，經本院以97年度毒聲字第1006號裁定送觀察、勒戒後，認有繼續施用毒品之傾向，再由本院以98年度毒聲字第55號裁定令入戒治處所施以強制戒治，因其戒治成效經評定為合格，於98年9月15日停止戒治依法釋放，該次施用毒品犯行，並經臺灣桃園地方法院檢察署檢察官以98年度戒毒偵字第261號為不起訴處分確定。復於99年間（即前開強制戒治執行完畢釋放後5年內）因施用第一、二級毒品案件，經本院以99年度審訴字第2768號判決分別判處有期徒刑6月、2月，並定應執行有期徒刑7月確定（於本案不構成累犯）。詎其猶不知悛悔，再分別基於施用第一級毒品海洛因、第二級毒品甲基安非他命之犯意，於100年3月28日上午8時許，在其桃園縣大溪鎮○○路63巷68號之住處內，分別以針筒注射之方式施用第一級毒品海洛因及以玻璃球燒烤之方式施用第二級毒品甲基安非他命各1次。嗣於100年3月28日晚間9時15分許，在新北市○○區○○路二段148巷51號前，為警攔檢查獲，並經其同意採集尿液送驗後，結果呈嗎啡、甲基安非他命陽性反應。二、案經新北市政府警察局板橋分局報請臺灣桃園地方法院檢察署檢察官偵查起訴。理由一、本案被告所犯之罪，均非法定刑為死刑、無期徒刑或最輕本刑3年以上有期徒刑之罪，亦非高等法院管轄第一審之案件，而被告於準備程序中就被訴事實已為有罪之陳述，經本院告知簡式審判程序之旨，並聽取公訴人及被告之意見後，本院合議庭乃依刑事訴訟法第273條之1第1項規定，裁定由受命法官獨任進行簡式審判程序，合先敘明。二、又本件既經本院裁定改依簡式審判程序審理，則依刑事訴訟法第273條之2、同法第159條第2項之規定，不適用傳聞法則有關限制證據能力及證據調查之相關規定。三、上揭犯罪事實，業據被告於檢察官訊問及本院準備程序、審理時均自白不諱，復有新北市政府警察局板橋分局偵辦毒品危害防制條例案被移送人姓名及代碼對照表、台灣檢驗科技股份有限公司濫用藥物檢驗報告、臺灣高等法院被告前案紀錄表各1紙等在卷可稽，足認被告前揭自白核與事實相符，可以採信。綜上，本案事證明確，被告上揭犯行洵堪認定，應予依法論科。三、核被告所為，係犯毒品危害防制條例第10條第1項之施用第一級毒品罪及同條第2項之施用第二級毒品罪。被告施用第一、二級毒品前非法持有第一、二級毒品之低度行為，皆為施用之高度行為所吸收，均不另論罪。被告所犯上開2罪間，犯意各別，行為互殊，應予分論併罰。爰審酌被告前已因施用毒品案件經觀察、勒戒完畢，本應徹底戒除毒癮，詎其仍未能自新、戒斷毒癮，竟一再施用足以導致人體機能發生依賴性、成癮性及抗藥性等障礙之第一、二級毒品，戕害自身健康，漠視法令禁制，實不宜寬縱，並兼衡其智識程度、犯罪之動機、目的、手段及其犯罪後坦承犯行，態度尚可等一切情狀，分別量處如主文所示之刑，並定其應執行之刑，以示懲儆。據上論斷，應依刑事訴訟法第273條之1第1項、第299條第1項前段，毒品危害防制條例第10條第1項、第2項，刑法第11條前段、第51條第5款，判決如主文。本案經檢察官白勝文到庭執行職務。中華民國100年10月14日刑事庭法官羅國鴻以上正本證明與原本無異。如不服本判決，得自收受送達之翌日起10日內向本院提出上訴狀（應附繕本），其未敘述上訴理由者，應於上訴期間屆滿後20日內補提理由書狀於本院，上訴於臺灣高等法院。書記官張筆隆中華民國100年10月14日附錄本案論罪科刑法條：毒品危害防制條例第10條施用第一級毒品者，處六月以上五年以下有期徒刑。施用第二級毒品者，處三年以下有期徒刑。",
  "characters": {
    "judges": [
      "羅國鴻"
    ],
    "prosecutors": [
      "白勝文"
    ],
    "lawyers": [

    ],
    "clerks": [
      "張筆隆"
    ],
    "plaintiffs": [

    ],
    "defendants": [
      "楊華林"
    ],
    "prosecutor_office": [
      "臺灣桃園地方法院檢察署檢察官"
    ],
    "creditors": [

    ],
    "debtors": [

    ],
    "judicial_associate_officer": [

    ]
  },
  "adjudged_at": "2011-10-14",
  "created_at": "2016-02-14 04:49:59",
  "updated_at": "2016-02-14 04:49:59"
}