{
  "identify": "KLD-94-訴-1012-20051228-1",
  "court": {
    "name": "臺灣基隆地方法院",
    "code": "KLD"
  },
  "division": {
    "name": "刑事",
    "code": "M"
  },
  "year": 94,
  "word": "訴",
  "number": "1012",
  "jcheck": "1",
  "reason": "毒品危害防制條例",
  "content": "臺灣基隆地方法院刑事判決              94年度訴字第1012號\n公  訴  人  臺灣基隆地方法院檢察署檢察官\n被      告  乙○○\n上列被告因違反毒品危害防制條例案件，經檢察官提起公訴（94\n年度毒偵字第2958號），被告為有罪之陳述，本院合議庭裁定由\n受命法官獨任以簡式審判程序進行審理，並判決如下：\n    主  文\n乙○○施用第一級毒品，處有期徒刑陸月，如易科罰金，以佰\n元折算壹日。扣案之注射針筒壹支，沒收。\n    事  實\n一、乙○○前因施用第二級毒品案件，經送觀察、勒戒後，認無\n    繼續施用毒品之傾向，由臺灣基隆地方法院檢察署檢察官於\n    民國92年4月23日，以92年度毒偵字第101號為不起訴處分確\n    定，並於同年月25日釋放出所。\n二、乙○○不思戒除毒癮，猶於94年10月26日晚間某時，在其胞\n    弟位於基隆市○○○路121巷22之3號4 樓之租住處，以注射\n    針筒施打手臂皮下組織之方式，施用第一級毒品海洛因一次\n    。嗣為警於94年10月28日晚間11時10分許，在上址搜索查獲\n    ，並扣得其所有供施用海洛因所用之注射針筒1 支。經警採\n    集其尿液送驗，結果呈海洛因之嗎啡陽性反應，而悉上情。\n三、案經基隆市警察局第四分局報告臺灣基隆地方法院檢察署檢\n    察官偵查起訴。\n    理  由\n壹、程序事項\n    查本件被告乙○○所犯者非為死刑、無期徒刑、最輕本刑為\n    3 年以上有期徒刑之罪或高等法院管轄第一審案件，其於準\n    備程序進行中，先就被訴事實為有罪之陳述，經告知其簡式\n    審判程序之旨，並聽取公訴人、被告之意見後，本院業已依\n    刑事訴訟法第273條之1第1 項之規定，裁定由受命法官獨任\n    以簡式審判程序進行本案之審理。\n貳、實體事項\n一、前揭事實業據被告於本院審理時坦承不諱，並有扣案之注射\n    針筒1 支可憑。而被告為警查獲後所採集之尿液檢體，經送\n    請檢驗，結果呈海洛因之嗎啡陽性反應（由於海洛因在人體\n    內會代謝成嗎啡，因此涉嫌海洛因之吸食者，係檢驗其尿液\n    中之嗎啡反應），有臺灣尖端先進生技醫藥股份有限公司94\n    年11月4 日濫用藥物檢驗報告附卷可稽，足見被告自白施用\n    第一級毒品海洛因之情節，與事實相符，應可採信。又被告\n    前因施用第二級毒品案件，經送觀察、勒戒後，認無繼續施\n    用毒品之傾向，由臺灣基隆地方法院檢察署檢察官於92年4\n    月23日，以92年度毒偵字第101 號為不起訴處分確定，並於\n    同年月25日釋放出所等情，亦有臺灣高等法院被告前案紀錄\n    表、前揭不起訴處分書附卷足佐。綜上所陳，本案事證明確\n    ，被告於觀察、勒戒執行完畢後，5 年以內再犯施用毒品之\n    犯行，堪可認定，應依法論科。\n二、論罪科刑：\n    (一)查海洛因係毒品危害防制條例所列管之第一級毒品，此\n        為該條例第2條第2項第1 款所明定；又犯毒品危害防制\n        條例第10條施用毒品之罪者，檢察官應聲請法院裁定，\n        令被告入勒戒處所觀察、勒戒，經觀察、勒戒後，無繼\n        續施用毒品之傾向者，應即釋放，並由檢察官為不起訴\n        處分，有繼續施用毒品之傾向者，則由檢察官先聲請法\n        院裁定令入戒治處所施以強制戒治，俟強制戒治期滿，\n        再行釋放，並由檢察官為不起訴處分；而依前開規定觀\n        察勒戒或強制戒治執行完畢釋放後，5 年內再犯施用毒\n        品之罪者，檢察官應依法追訴，毒品危害防制條例第20\n        條第1項、第2項、第23條第2項分別定有明文。\n    (二)核被告於觀察、勒戒執行完畢後，5 年以內再犯施用第\n        一級毒品海洛因之行為，係犯毒品危害防制條例第10條\n        第1 項之施用第一級毒品罪。被告持有第一級毒品海洛\n        因之低度行為，應為施用毒品之高度行為所吸收，不另\n        論罪。本院審酌被告犯罪之動機、吸食頻率僅一次、曾\n        有施用毒品之前科仍不知戒除，惟犯罪後坦承犯行，且\n        所犯之施用毒品犯行乃戕害自己身心健康，並未危及他\n        人等一切情狀，量處如主文所示之刑，併諭知易科罰金\n        之折算標準。\n    (三)末查，扣案之注射針筒1 支為市售一般藥用之物，雖非\n        專供施用毒品之器具，此業據本院當庭勘驗無訛（94年\n        12月14日審判筆錄參照），然屬被告所有供施打海洛因\n        所用之物，業據被告供明無誤，爰依刑法第38條第1 項\n        第2款之規定宣告沒收。至扣案之玻璃球吸食器2組，核\n        與本案施用海洛因之行為無關，且被告涉嫌施用第二級\n        毒品安非他命案件，業經檢察官為不起訴處分，有偵查\n        卷附不起訴處分書可稽，自無在本案宣告沒收之問題，\n        附此說明。\n據上論斷，應依刑事訴訟法第273條之1第1項、第299條第1 項前\n段，毒品危害防制條例第10條第1 項，刑法第11條前段、第41條\n第1項前段、第38條第1項第2款，罰金罰鍰提高標準條例第2條，\n判決如主文。\n本案經檢察官甲○○到庭執行職務。\n中    華    民    國    94    年    12    月    28    日\n                  刑事第五庭法  官  楊皓清\n以上正本證明與原本無異。\n對於本件判決如有不服，應於收受送達後10日內，向本院提出上\n訴書狀，上訴於臺灣高等法院，並按他造當事人之人數附具繕本\n。\n中    華    民    國    94    年    12    月    28    日\n                            書記官  王月娥\n附錄論罪法條：\n毒品危害防制條例第10條第1項：\n施用第一級毒品者，處6月以上5年以下有期徒刑。\n",
  "structure": {
    "main": "乙○○施用第一級毒品，處有期徒刑陸月，如易科罰金，以佰\n元折算壹日。扣案之注射針筒壹支，沒收。",
    "fact": "一、乙○○前因施用第二級毒品案件，經送觀察、勒戒後，認無\n    繼續施用毒品之傾向，由臺灣基隆地方法院檢察署檢察官於\n    民國92年4月23日，以92年度毒偵字第101號為不起訴處分確\n    定，並於同年月25日釋放出所。\n二、乙○○不思戒除毒癮，猶於94年10月26日晚間某時，在其胞\n    弟位於基隆市○○○路121巷22之3號4 樓之租住處，以注射\n    針筒施打手臂皮下組織之方式，施用第一級毒品海洛因一次\n    。嗣為警於94年10月28日晚間11時10分許，在上址搜索查獲\n    ，並扣得其所有供施用海洛因所用之注射針筒1 支。經警採\n    集其尿液送驗，結果呈海洛因之嗎啡陽性反應，而悉上情。\n三、案經基隆市警察局第四分局報告臺灣基隆地方法院檢察署檢\n    察官偵查起訴。",
    "reason": "壹、程序事項\n    查本件被告乙○○所犯者非為死刑、無期徒刑、最輕本刑為\n    3 年以上有期徒刑之罪或高等法院管轄第一審案件，其於準\n    備程序進行中，先就被訴事實為有罪之陳述，經告知其簡式\n    審判程序之旨，並聽取公訴人、被告之意見後，本院業已依\n    刑事訴訟法第273條之1第1 項之規定，裁定由受命法官獨任\n    以簡式審判程序進行本案之審理。\n貳、實體事項\n一、前揭事實業據被告於本院審理時坦承不諱，並有扣案之注射\n    針筒1 支可憑。而被告為警查獲後所採集之尿液檢體，經送\n    請檢驗，結果呈海洛因之嗎啡陽性反應（由於海洛因在人體\n    內會代謝成嗎啡，因此涉嫌海洛因之吸食者，係檢驗其尿液\n    中之嗎啡反應），有臺灣尖端先進生技醫藥股份有限公司94\n    年11月4 日濫用藥物檢驗報告附卷可稽，足見被告自白施用\n    第一級毒品海洛因之情節，與事實相符，應可採信。又被告\n    前因施用第二級毒品案件，經送觀察、勒戒後，認無繼續施\n    用毒品之傾向，由臺灣基隆地方法院檢察署檢察官於92年4\n    月23日，以92年度毒偵字第101 號為不起訴處分確定，並於\n    同年月25日釋放出所等情，亦有臺灣高等法院被告前案紀錄\n    表、前揭不起訴處分書附卷足佐。綜上所陳，本案事證明確\n    ，被告於觀察、勒戒執行完畢後，5 年以內再犯施用毒品之\n    犯行，堪可認定，應依法論科。\n二、論罪科刑：\n    (一)查海洛因係毒品危害防制條例所列管之第一級毒品，此\n        為該條例第2條第2項第1 款所明定；又犯毒品危害防制\n        條例第10條施用毒品之罪者，檢察官應聲請法院裁定，\n        令被告入勒戒處所觀察、勒戒，經觀察、勒戒後，無繼\n        續施用毒品之傾向者，應即釋放，並由檢察官為不起訴\n        處分，有繼續施用毒品之傾向者，則由檢察官先聲請法\n        院裁定令入戒治處所施以強制戒治，俟強制戒治期滿，\n        再行釋放，並由檢察官為不起訴處分；而依前開規定觀\n        察勒戒或強制戒治執行完畢釋放後，5 年內再犯施用毒\n        品之罪者，檢察官應依法追訴，毒品危害防制條例第20\n        條第1項、第2項、第23條第2項分別定有明文。\n    (二)核被告於觀察、勒戒執行完畢後，5 年以內再犯施用第\n        一級毒品海洛因之行為，係犯毒品危害防制條例第10條\n        第1 項之施用第一級毒品罪。被告持有第一級毒品海洛\n        因之低度行為，應為施用毒品之高度行為所吸收，不另\n        論罪。本院審酌被告犯罪之動機、吸食頻率僅一次、曾\n        有施用毒品之前科仍不知戒除，惟犯罪後坦承犯行，且\n        所犯之施用毒品犯行乃戕害自己身心健康，並未危及他\n        人等一切情狀，量處如主文所示之刑，併諭知易科罰金\n        之折算標準。\n    (三)末查，扣案之注射針筒1 支為市售一般藥用之物，雖非\n        專供施用毒品之器具，此業據本院當庭勘驗無訛（94年\n        12月14日審判筆錄參照），然屬被告所有供施打海洛因\n        所用之物，業據被告供明無誤，爰依刑法第38條第1 項\n        第2款之規定宣告沒收。至扣案之玻璃球吸食器2組，核\n        與本案施用海洛因之行為無關，且被告涉嫌施用第二級\n        毒品安非他命案件，業經檢察官為不起訴處分，有偵查\n        卷附不起訴處分書可稽，自無在本案宣告沒收之問題，\n        附此說明。\n據上論斷，應依刑事訴訟法第273條之1第1項、第299條第1 項前\n段，毒品危害防制條例第10條第1 項，刑法第11條前段、第41條\n第1項前段、第38條第1項第2款，罰金罰鍰提高標準條例第2條，\n判決如主文。\n本案經檢察官甲○○到庭執行職務。\n中    華    民    國    94    年    12    月    28    日\n                  刑事第五庭法  官  楊皓清\n以上正本證明與原本無異。\n對於本件判決如有不服，應於收受送達後10日內，向本院提出上\n訴書狀，上訴於臺灣高等法院，並按他造當事人之人數附具繕本\n。"
  },
  "search": "臺灣基隆地方法院刑事判決94年度訴字第1012號公訴人臺灣基隆地方法院檢察署檢察官被告乙○○上列被告因違反毒品危害防制條例案件，經檢察官提起公訴（94年度毒偵字第2958號），被告為有罪之陳述，本院合議庭裁定由受命法官獨任以簡式審判程序進行審理，並判決如下：主文乙○○施用第一級毒品，處有期徒刑陸月，如易科罰金，以佰元折算壹日。扣案之注射針筒壹支，沒收。事實一、乙○○前因施用第二級毒品案件，經送觀察、勒戒後，認無繼續施用毒品之傾向，由臺灣基隆地方法院檢察署檢察官於民國92年4月23日，以92年度毒偵字第101號為不起訴處分確定，並於同年月25日釋放出所。二、乙○○不思戒除毒癮，猶於94年10月26日晚間某時，在其胞弟位於基隆市○○○路121巷22之3號4樓之租住處，以注射針筒施打手臂皮下組織之方式，施用第一級毒品海洛因一次。嗣為警於94年10月28日晚間11時10分許，在上址搜索查獲，並扣得其所有供施用海洛因所用之注射針筒1支。經警採集其尿液送驗，結果呈海洛因之嗎啡陽性反應，而悉上情。三、案經基隆市警察局第四分局報告臺灣基隆地方法院檢察署檢察官偵查起訴。理由壹、程序事項查本件被告乙○○所犯者非為死刑、無期徒刑、最輕本刑為3年以上有期徒刑之罪或高等法院管轄第一審案件，其於準備程序進行中，先就被訴事實為有罪之陳述，經告知其簡式審判程序之旨，並聽取公訴人、被告之意見後，本院業已依刑事訴訟法第273條之1第1項之規定，裁定由受命法官獨任以簡式審判程序進行本案之審理。貳、實體事項一、前揭事實業據被告於本院審理時坦承不諱，並有扣案之注射針筒1支可憑。而被告為警查獲後所採集之尿液檢體，經送請檢驗，結果呈海洛因之嗎啡陽性反應（由於海洛因在人體內會代謝成嗎啡，因此涉嫌海洛因之吸食者，係檢驗其尿液中之嗎啡反應），有臺灣尖端先進生技醫藥股份有限公司94年11月4日濫用藥物檢驗報告附卷可稽，足見被告自白施用第一級毒品海洛因之情節，與事實相符，應可採信。又被告前因施用第二級毒品案件，經送觀察、勒戒後，認無繼續施用毒品之傾向，由臺灣基隆地方法院檢察署檢察官於92年4月23日，以92年度毒偵字第101號為不起訴處分確定，並於同年月25日釋放出所等情，亦有臺灣高等法院被告前案紀錄表、前揭不起訴處分書附卷足佐。綜上所陳，本案事證明確，被告於觀察、勒戒執行完畢後，5年以內再犯施用毒品之犯行，堪可認定，應依法論科。二、論罪科刑：(一)查海洛因係毒品危害防制條例所列管之第一級毒品，此為該條例第2條第2項第1款所明定；又犯毒品危害防制條例第10條施用毒品之罪者，檢察官應聲請法院裁定，令被告入勒戒處所觀察、勒戒，經觀察、勒戒後，無繼續施用毒品之傾向者，應即釋放，並由檢察官為不起訴處分，有繼續施用毒品之傾向者，則由檢察官先聲請法院裁定令入戒治處所施以強制戒治，俟強制戒治期滿，再行釋放，並由檢察官為不起訴處分；而依前開規定觀察勒戒或強制戒治執行完畢釋放後，5年內再犯施用毒品之罪者，檢察官應依法追訴，毒品危害防制條例第20條第1項、第2項、第23條第2項分別定有明文。(二)核被告於觀察、勒戒執行完畢後，5年以內再犯施用第一級毒品海洛因之行為，係犯毒品危害防制條例第10條第1項之施用第一級毒品罪。被告持有第一級毒品海洛因之低度行為，應為施用毒品之高度行為所吸收，不另論罪。本院審酌被告犯罪之動機、吸食頻率僅一次、曾有施用毒品之前科仍不知戒除，惟犯罪後坦承犯行，且所犯之施用毒品犯行乃戕害自己身心健康，並未危及他人等一切情狀，量處如主文所示之刑，併諭知易科罰金之折算標準。(三)末查，扣案之注射針筒1支為市售一般藥用之物，雖非專供施用毒品之器具，此業據本院當庭勘驗無訛（94年12月14日審判筆錄參照），然屬被告所有供施打海洛因所用之物，業據被告供明無誤，爰依刑法第38條第1項第2款之規定宣告沒收。至扣案之玻璃球吸食器2組，核與本案施用海洛因之行為無關，且被告涉嫌施用第二級毒品安非他命案件，業經檢察官為不起訴處分，有偵查卷附不起訴處分書可稽，自無在本案宣告沒收之問題，附此說明。據上論斷，應依刑事訴訟法第273條之1第1項、第299條第1項前段，毒品危害防制條例第10條第1項，刑法第11條前段、第41條第1項前段、第38條第1項第2款，罰金罰鍰提高標準條例第2條，判決如主文。本案經檢察官甲○○到庭執行職務。中華民國94年12月28日刑事第五庭法官楊皓清以上正本證明與原本無異。對於本件判決如有不服，應於收受送達後10日內，向本院提出上訴書狀，上訴於臺灣高等法院，並按他造當事人之人數附具繕本。中華民國94年12月28日書記官王月娥附錄論罪法條：毒品危害防制條例第10條第1項：施用第一級毒品者，處6月以上5年以下有期徒刑。",
  "characters": {
    "judges": [
      "楊皓清"
    ],
    "prosecutors": [

    ],
    "lawyers": [

    ],
    "clerks": [
      "王月娥"
    ],
    "plaintiffs": [

    ],
    "defendants": [
      "乙○○"
    ],
    "prosecutor_office": [
      "臺灣基隆地方法院檢察署檢察官"
    ],
    "creditors": [

    ],
    "debtors": [

    ],
    "judicial_associate_officer": [

    ]
  },
  "adjudged_at": "2005-12-28",
  "created_at": "2016-02-07 03:29:14",
  "updated_at": "2016-02-07 03:29:14"
}