{
  "identify": "KSD-94-簡-7568-20051227-1",
  "court": {
    "name": "臺灣高雄地方法院",
    "code": "KSD"
  },
  "division": {
    "name": "刑事",
    "code": "M"
  },
  "year": 94,
  "word": "簡",
  "number": "7568",
  "jcheck": "1",
  "reason": "竊盜",
  "content": "臺灣高雄地方法院刑事簡易判決          94年度簡字第7568號\n聲  請  人  臺灣高雄地方法院檢察署檢察官\n被      告  甲○○\n上列被告因竊盜案件，經檢察官聲請以簡易判決處刑（94年度偵\n字第27205 號），本院判決如下：\n    主  文\n甲○○竊盜，處拘役拾日，如易科罰金，以參佰元折算壹日。\n    事實及理由\n一、本件犯罪事實及證據，均引用檢察官聲請簡易判決處刑書之\n    記載，如附件。\n二、核被告甲○○所為，係犯刑法第320 條第1 項之竊盜罪。爰\n    審酌被告為貪圖不法利益，竟率爾竊取他人財物，所為實不\n    足取，惟念及其犯後坦承犯行，態度良好，而所竊得之上開\n    物品業已全部歸還被害人，未對被害人造成進一步之損害，\n    且其犯罪手段與情節尚屬平和輕微等一切情狀，量處如主文\n    所示之刑，並諭知易科罰金之折算標準，以示儆懲。\n三、依刑事訴訟法第449 條第1 項前段、第454 條第2 項，刑法\n    第320 條第1 項、第41條第1 項前段，罰金罰鍰提高標準條\n    例第1 條前段、第2 條，判決如主文。\n中    華    民    國    94    年    12    月    27    日\n                  高雄簡易庭    法  官 陳君杰\n以上正本證明與原本無異。\n如不服本判決，應於判決送達後10日內，向本院提出上訴狀。\n中    華    民    國    94    年    12    月    27    日\n                                書記官 陳昱良\n附錄本判決論罪科刑法條全文：\n刑法第320 條第1 項\n意圖為自己或第三人不法之所有，而竊取他人之動產者，為竊盜\n罪，處5 年以下有期徒刑、拘役或500 元以下罰金。\n",
  "structure": {
    "main": "甲○○竊盜，處拘役拾日，如易科罰金，以參佰元折算壹日。",
    "fact": "一、本件犯罪事實及證據，均引用檢察官聲請簡易判決處刑書之\n    記載，如附件。\n二、核被告甲○○所為，係犯刑法第320 條第1 項之竊盜罪。爰\n    審酌被告為貪圖不法利益，竟率爾竊取他人財物，所為實不\n    足取，惟念及其犯後坦承犯行，態度良好，而所竊得之上開\n    物品業已全部歸還被害人，未對被害人造成進一步之損害，\n    且其犯罪手段與情節尚屬平和輕微等一切情狀，量處如主文\n    所示之刑，並諭知易科罰金之折算標準，以示儆懲。\n三、依刑事訴訟法第449 條第1 項前段、第454 條第2 項，刑法\n    第320 條第1 項、第41條第1 項前段，罰金罰鍰提高標準條\n    例第1 條前段、第2 條，判決如主文。",
    "reason": "一、本件犯罪事實及證據，均引用檢察官聲請簡易判決處刑書之\n    記載，如附件。\n二、核被告甲○○所為，係犯刑法第320 條第1 項之竊盜罪。爰\n    審酌被告為貪圖不法利益，竟率爾竊取他人財物，所為實不\n    足取，惟念及其犯後坦承犯行，態度良好，而所竊得之上開\n    物品業已全部歸還被害人，未對被害人造成進一步之損害，\n    且其犯罪手段與情節尚屬平和輕微等一切情狀，量處如主文\n    所示之刑，並諭知易科罰金之折算標準，以示儆懲。\n三、依刑事訴訟法第449 條第1 項前段、第454 條第2 項，刑法\n    第320 條第1 項、第41條第1 項前段，罰金罰鍰提高標準條\n    例第1 條前段、第2 條，判決如主文。"
  },
  "search": "臺灣高雄地方法院刑事簡易判決94年度簡字第7568號聲請人臺灣高雄地方法院檢察署檢察官被告甲○○上列被告因竊盜案件，經檢察官聲請以簡易判決處刑（94年度偵字第27205號），本院判決如下：主文甲○○竊盜，處拘役拾日，如易科罰金，以參佰元折算壹日。事實及理由一、本件犯罪事實及證據，均引用檢察官聲請簡易判決處刑書之記載，如附件。二、核被告甲○○所為，係犯刑法第320條第1項之竊盜罪。爰審酌被告為貪圖不法利益，竟率爾竊取他人財物，所為實不足取，惟念及其犯後坦承犯行，態度良好，而所竊得之上開物品業已全部歸還被害人，未對被害人造成進一步之損害，且其犯罪手段與情節尚屬平和輕微等一切情狀，量處如主文所示之刑，並諭知易科罰金之折算標準，以示儆懲。三、依刑事訴訟法第449條第1項前段、第454條第2項，刑法第320條第1項、第41條第1項前段，罰金罰鍰提高標準條例第1條前段、第2條，判決如主文。中華民國94年12月27日高雄簡易庭法官陳君杰以上正本證明與原本無異。如不服本判決，應於判決送達後10日內，向本院提出上訴狀。中華民國94年12月27日書記官陳昱良附錄本判決論罪科刑法條全文：刑法第320條第1項意圖為自己或第三人不法之所有，而竊取他人之動產者，為竊盜罪，處5年以下有期徒刑、拘役或500元以下罰金。",
  "characters": {
    "judges": [
      "陳君杰"
    ],
    "prosecutors": [

    ],
    "lawyers": [

    ],
    "clerks": [
      "陳昱良"
    ],
    "plaintiffs": [

    ],
    "defendants": [
      "甲○○"
    ],
    "prosecutor_office": [
      "臺灣高雄地方法院檢察署檢察官"
    ],
    "creditors": [

    ],
    "debtors": [

    ],
    "judicial_associate_officer": [

    ]
  },
  "adjudged_at": "2005-12-27",
  "created_at": "2016-02-07 03:19:30",
  "updated_at": "2016-02-07 03:19:30"
}