{
  "identify": "SCD-94-竹交簡-881-20051227-1",
  "court": {
    "name": "臺灣新竹地方法院",
    "code": "SCD"
  },
  "division": {
    "name": "刑事",
    "code": "M"
  },
  "year": 94,
  "word": "竹交簡",
  "number": "881",
  "jcheck": "1",
  "reason": "公共危險",
  "content": "臺灣新竹地方法院刑事簡易判決       94年度竹交簡字第881號\n聲  請  人  臺灣新竹地方法院檢察署檢察官\n被      告  乙○○\n上列被告因公共危險案件，經檢察官聲請簡易判決處刑（94年度\n速偵字第1582號），本院判決如下：\n    主      文\n乙○○服用酒類，不能安全駕駛動力交通工具而駕駛，處拘役肆\n拾日，如易科罰金，以佰元折算壹日。\n    事實及理由\n一、本件犯罪事實：乙○○前於民國90年間，因酒後駕車公共危\n    險案件，經本院以90年度竹北交簡字第60號判決判處罰金20\n    ,000 元確定，於90年10月7日易服勞役執行完畢（不構成累\n    犯），竟於94年10月14日19時至22時許，在新竹市○區○○\n    路某處小吃攤內飲用高粱酒約半瓶，酒後在不能安全駕駛動\n    力交通工具之狀況（未達精神耗弱之程度），仍騎乘車號F6\n    S─825號重型機車，欲返回新竹市住處，迨同日23時52分許\n    ，途經新竹市○區○○○路36號前，與甲○○所駕駛之車號\n    FJ─762號營業大客車發生擦撞，嗣經警到場處理事故，並\n    於翌日（15日）0時11分，測試其吐氣所含酒精濃度高達每\n    公升1.06毫克，始悉上情。案經新竹市警察局第二分局報請\n    臺灣新竹地方法院檢察署檢察官偵查後聲請簡易判決處刑。\n二、證據：\n  (一)被告乙○○於警詢及偵查中坦承上情不諱。\n  (二)證人甲○○證述被告騎乘車號F6S─825號重型機車與其所駕\n    駛之車號FJ─762號營業大客車發生擦撞之事實。\n  (三)刑法第185條之3案件測試觀察紀錄表、汽機車駕駛人酒後生\n    理協調平衡檢測紀錄表、酒精濃度測試值單及新竹市警察局\n    舉發違反道路交通管理事件通知單影本各1份在卷可稽。\n  (四)按對於酒精濃度呼氣已達每公升0點55毫克時，肇事率為一\n    般正常人之10倍，認已達不能安全駕駛之標準，有法務部88\n    年5月18日所發之88年度法檢字第001669號函1份在卷足憑，\n    而被告於員警測試時呼氣酒精濃度每公升高達1.06毫克，有\n    上開酒精濃度測試值單1紙足參。且經警當場對被告施作雙\n    腳併攏，兩手貼緊大腿將一腳向前抬高離地15公分，並停止\n    不動30秒；閉雙眼，30秒內朗誦阿拉伯數字，由1001到1030\n    及用筆在兩個同心圓之間的0點5公分環狀帶內畫另1個圓等\n    檢測結果均不合格，此有上開汽機車駕駛人酒後生理協調平\n    衡檢測紀錄表1份在卷可考，從而，被告顯已達酒醉而不能\n    安全駕駛之程度，堪予認定。\n三、核被告乙○○所為，係犯刑法第185條之3之服用酒類不能安\n    全駕駛動力交通工具而駕駛罪。\n四、量刑：爰審酌被告乙○○前於90年間，因酒後駕車公共危險\n    案件，經本院以90年度竹北交簡字第60號判決判處罰金20,\n    000元確定，於90年10月7日易服勞役執行完畢，有臺灣高等\n    法院被告前案紀錄表1份在卷可查，仍不知警惕，又再犯本\n    案，可見其輕忽法律及其他用路人行車安全之心態，惟其犯\n    罪後尚能坦承犯行等一切情狀，量處如主文所示之刑，並諭\n    知易科罰金之折算標準，以示懲儆。\n五、據上論斷，應依刑事訴訟法第449條第1項前段、第454條第\n    1項，刑法第185條之3、第41條第1項前段，罰金罰鍰提高標\n    準條例第2條，逕以簡易判決處如主文所示之刑。\n六、如不服本判決，得自收受送達之日起10日內，向本院提起上\n    訴。\n中    華    民    國    94    年    12  月     27     日\n                  新竹簡易庭    法  官  方鴻愷\n以上正本證明與原本無異。\n中    華    民    國    94    年    12  月     27     日\n                                書記官  吳美雲\n附錄本院論罪科刑法條：\n刑法第185條之3\n服用毒品、麻醉藥品、酒類或其他相類似之物，不能安全駕駛動\n力交通工具而駕駛者，處一年以下有期徒刑、拘役或三萬元以下\n罰金。\n",
  "structure": {
    "main": "乙○○服用酒類，不能安全駕駛動力交通工具而駕駛，處拘役肆\n拾日，如易科罰金，以佰元折算壹日。",
    "fact": "一、本件犯罪事實：乙○○前於民國90年間，因酒後駕車公共危\n    險案件，經本院以90年度竹北交簡字第60號判決判處罰金20\n    ,000 元確定，於90年10月7日易服勞役執行完畢（不構成累\n    犯），竟於94年10月14日19時至22時許，在新竹市○區○○\n    路某處小吃攤內飲用高粱酒約半瓶，酒後在不能安全駕駛動\n    力交通工具之狀況（未達精神耗弱之程度），仍騎乘車號F6\n    S─825號重型機車，欲返回新竹市住處，迨同日23時52分許\n    ，途經新竹市○區○○○路36號前，與甲○○所駕駛之車號\n    FJ─762號營業大客車發生擦撞，嗣經警到場處理事故，並\n    於翌日（15日）0時11分，測試其吐氣所含酒精濃度高達每\n    公升1.06毫克，始悉上情。案經新竹市警察局第二分局報請\n    臺灣新竹地方法院檢察署檢察官偵查後聲請簡易判決處刑。\n二、證據：\n  (一)被告乙○○於警詢及偵查中坦承上情不諱。\n  (二)證人甲○○證述被告騎乘車號F6S─825號重型機車與其所駕\n    駛之車號FJ─762號營業大客車發生擦撞之事實。\n  (三)刑法第185條之3案件測試觀察紀錄表、汽機車駕駛人酒後生\n    理協調平衡檢測紀錄表、酒精濃度測試值單及新竹市警察局\n    舉發違反道路交通管理事件通知單影本各1份在卷可稽。\n  (四)按對於酒精濃度呼氣已達每公升0點55毫克時，肇事率為一\n    般正常人之10倍，認已達不能安全駕駛之標準，有法務部88\n    年5月18日所發之88年度法檢字第001669號函1份在卷足憑，\n    而被告於員警測試時呼氣酒精濃度每公升高達1.06毫克，有\n    上開酒精濃度測試值單1紙足參。且經警當場對被告施作雙\n    腳併攏，兩手貼緊大腿將一腳向前抬高離地15公分，並停止\n    不動30秒；閉雙眼，30秒內朗誦阿拉伯數字，由1001到1030\n    及用筆在兩個同心圓之間的0點5公分環狀帶內畫另1個圓等\n    檢測結果均不合格，此有上開汽機車駕駛人酒後生理協調平\n    衡檢測紀錄表1份在卷可考，從而，被告顯已達酒醉而不能\n    安全駕駛之程度，堪予認定。\n三、核被告乙○○所為，係犯刑法第185條之3之服用酒類不能安\n    全駕駛動力交通工具而駕駛罪。\n四、量刑：爰審酌被告乙○○前於90年間，因酒後駕車公共危險\n    案件，經本院以90年度竹北交簡字第60號判決判處罰金20,\n    000元確定，於90年10月7日易服勞役執行完畢，有臺灣高等\n    法院被告前案紀錄表1份在卷可查，仍不知警惕，又再犯本\n    案，可見其輕忽法律及其他用路人行車安全之心態，惟其犯\n    罪後尚能坦承犯行等一切情狀，量處如主文所示之刑，並諭\n    知易科罰金之折算標準，以示懲儆。\n五、據上論斷，應依刑事訴訟法第449條第1項前段、第454條第\n    1項，刑法第185條之3、第41條第1項前段，罰金罰鍰提高標\n    準條例第2條，逕以簡易判決處如主文所示之刑。\n六、如不服本判決，得自收受送達之日起10日內，向本院提起上\n    訴。",
    "reason": "一、本件犯罪事實：乙○○前於民國90年間，因酒後駕車公共危\n    險案件，經本院以90年度竹北交簡字第60號判決判處罰金20\n    ,000 元確定，於90年10月7日易服勞役執行完畢（不構成累\n    犯），竟於94年10月14日19時至22時許，在新竹市○區○○\n    路某處小吃攤內飲用高粱酒約半瓶，酒後在不能安全駕駛動\n    力交通工具之狀況（未達精神耗弱之程度），仍騎乘車號F6\n    S─825號重型機車，欲返回新竹市住處，迨同日23時52分許\n    ，途經新竹市○區○○○路36號前，與甲○○所駕駛之車號\n    FJ─762號營業大客車發生擦撞，嗣經警到場處理事故，並\n    於翌日（15日）0時11分，測試其吐氣所含酒精濃度高達每\n    公升1.06毫克，始悉上情。案經新竹市警察局第二分局報請\n    臺灣新竹地方法院檢察署檢察官偵查後聲請簡易判決處刑。\n二、證據：\n  (一)被告乙○○於警詢及偵查中坦承上情不諱。\n  (二)證人甲○○證述被告騎乘車號F6S─825號重型機車與其所駕\n    駛之車號FJ─762號營業大客車發生擦撞之事實。\n  (三)刑法第185條之3案件測試觀察紀錄表、汽機車駕駛人酒後生\n    理協調平衡檢測紀錄表、酒精濃度測試值單及新竹市警察局\n    舉發違反道路交通管理事件通知單影本各1份在卷可稽。\n  (四)按對於酒精濃度呼氣已達每公升0點55毫克時，肇事率為一\n    般正常人之10倍，認已達不能安全駕駛之標準，有法務部88\n    年5月18日所發之88年度法檢字第001669號函1份在卷足憑，\n    而被告於員警測試時呼氣酒精濃度每公升高達1.06毫克，有\n    上開酒精濃度測試值單1紙足參。且經警當場對被告施作雙\n    腳併攏，兩手貼緊大腿將一腳向前抬高離地15公分，並停止\n    不動30秒；閉雙眼，30秒內朗誦阿拉伯數字，由1001到1030\n    及用筆在兩個同心圓之間的0點5公分環狀帶內畫另1個圓等\n    檢測結果均不合格，此有上開汽機車駕駛人酒後生理協調平\n    衡檢測紀錄表1份在卷可考，從而，被告顯已達酒醉而不能\n    安全駕駛之程度，堪予認定。\n三、核被告乙○○所為，係犯刑法第185條之3之服用酒類不能安\n    全駕駛動力交通工具而駕駛罪。\n四、量刑：爰審酌被告乙○○前於90年間，因酒後駕車公共危險\n    案件，經本院以90年度竹北交簡字第60號判決判處罰金20,\n    000元確定，於90年10月7日易服勞役執行完畢，有臺灣高等\n    法院被告前案紀錄表1份在卷可查，仍不知警惕，又再犯本\n    案，可見其輕忽法律及其他用路人行車安全之心態，惟其犯\n    罪後尚能坦承犯行等一切情狀，量處如主文所示之刑，並諭\n    知易科罰金之折算標準，以示懲儆。\n五、據上論斷，應依刑事訴訟法第449條第1項前段、第454條第\n    1項，刑法第185條之3、第41條第1項前段，罰金罰鍰提高標\n    準條例第2條，逕以簡易判決處如主文所示之刑。\n六、如不服本判決，得自收受送達之日起10日內，向本院提起上\n    訴。"
  },
  "search": "臺灣新竹地方法院刑事簡易判決94年度竹交簡字第881號聲請人臺灣新竹地方法院檢察署檢察官被告乙○○上列被告因公共危險案件，經檢察官聲請簡易判決處刑（94年度速偵字第1582號），本院判決如下：主文乙○○服用酒類，不能安全駕駛動力交通工具而駕駛，處拘役肆拾日，如易科罰金，以佰元折算壹日。事實及理由一、本件犯罪事實：乙○○前於民國90年間，因酒後駕車公共危險案件，經本院以90年度竹北交簡字第60號判決判處罰金20,000元確定，於90年10月7日易服勞役執行完畢（不構成累犯），竟於94年10月14日19時至22時許，在新竹市○區○○路某處小吃攤內飲用高粱酒約半瓶，酒後在不能安全駕駛動力交通工具之狀況（未達精神耗弱之程度），仍騎乘車號F6S─825號重型機車，欲返回新竹市住處，迨同日23時52分許，途經新竹市○區○○○路36號前，與甲○○所駕駛之車號FJ─762號營業大客車發生擦撞，嗣經警到場處理事故，並於翌日（15日）0時11分，測試其吐氣所含酒精濃度高達每公升1.06毫克，始悉上情。案經新竹市警察局第二分局報請臺灣新竹地方法院檢察署檢察官偵查後聲請簡易判決處刑。二、證據：(一)被告乙○○於警詢及偵查中坦承上情不諱。(二)證人甲○○證述被告騎乘車號F6S─825號重型機車與其所駕駛之車號FJ─762號營業大客車發生擦撞之事實。(三)刑法第185條之3案件測試觀察紀錄表、汽機車駕駛人酒後生理協調平衡檢測紀錄表、酒精濃度測試值單及新竹市警察局舉發違反道路交通管理事件通知單影本各1份在卷可稽。(四)按對於酒精濃度呼氣已達每公升0點55毫克時，肇事率為一般正常人之10倍，認已達不能安全駕駛之標準，有法務部88年5月18日所發之88年度法檢字第001669號函1份在卷足憑，而被告於員警測試時呼氣酒精濃度每公升高達1.06毫克，有上開酒精濃度測試值單1紙足參。且經警當場對被告施作雙腳併攏，兩手貼緊大腿將一腳向前抬高離地15公分，並停止不動30秒；閉雙眼，30秒內朗誦阿拉伯數字，由1001到1030及用筆在兩個同心圓之間的0點5公分環狀帶內畫另1個圓等檢測結果均不合格，此有上開汽機車駕駛人酒後生理協調平衡檢測紀錄表1份在卷可考，從而，被告顯已達酒醉而不能安全駕駛之程度，堪予認定。三、核被告乙○○所為，係犯刑法第185條之3之服用酒類不能安全駕駛動力交通工具而駕駛罪。四、量刑：爰審酌被告乙○○前於90年間，因酒後駕車公共危險案件，經本院以90年度竹北交簡字第60號判決判處罰金20,000元確定，於90年10月7日易服勞役執行完畢，有臺灣高等法院被告前案紀錄表1份在卷可查，仍不知警惕，又再犯本案，可見其輕忽法律及其他用路人行車安全之心態，惟其犯罪後尚能坦承犯行等一切情狀，量處如主文所示之刑，並諭知易科罰金之折算標準，以示懲儆。五、據上論斷，應依刑事訴訟法第449條第1項前段、第454條第1項，刑法第185條之3、第41條第1項前段，罰金罰鍰提高標準條例第2條，逕以簡易判決處如主文所示之刑。六、如不服本判決，得自收受送達之日起10日內，向本院提起上訴。中華民國94年12月27日新竹簡易庭法官方鴻愷以上正本證明與原本無異。中華民國94年12月27日書記官吳美雲附錄本院論罪科刑法條：刑法第185條之3服用毒品、麻醉藥品、酒類或其他相類似之物，不能安全駕駛動力交通工具而駕駛者，處一年以下有期徒刑、拘役或三萬元以下罰金。",
  "characters": {
    "judges": [
      "方鴻愷"
    ],
    "prosecutors": [

    ],
    "lawyers": [

    ],
    "clerks": [
      "吳美雲"
    ],
    "plaintiffs": [

    ],
    "defendants": [
      "乙○○"
    ],
    "prosecutor_office": [
      "臺灣新竹地方法院檢察署檢察官"
    ],
    "creditors": [

    ],
    "debtors": [

    ],
    "judicial_associate_officer": [

    ]
  },
  "adjudged_at": "2005-12-27",
  "created_at": "2016-02-07 03:18:41",
  "updated_at": "2016-02-07 03:18:41"
}