{
  "identify": "TCD-91-婚-64-20020524-1",
  "court": {
    "name": "臺灣臺中地方法院",
    "code": "TCD"
  },
  "division": {
    "name": "民事",
    "code": "V"
  },
  "year": 91,
  "word": "婚",
  "number": "64",
  "jcheck": "1",
  "reason": "離婚",
  "content": "臺灣臺中地方法院民事判決  九十一年度婚字第六四號\n    原      告  朱蓮池\n    被      告  甲○○\n右當事人間請求離婚事件，本院判決如左：\n    主    文\n准原告與被告離婚。\n訴訟費用由被告負擔。\n    事    實\n甲、原告方面：\n  一、聲明：如主文所示。\n  二、陳述：兩造係夫妻，現婚姻關係仍存續中，詎被告自民國八十一起間因行為不\n            檢，置家庭生活於不顧，無故離家出走，拒與原告履行同居生活，經原\n            告四處尋訪，仍無下落，顯然違背同居義務，為此提起本件訴訟，原告\n            乃提起履行同居之訴，業經鈞院於九十年十一月二十二日以九十年度婚\n            字第六七五號判決原告勝訴確定在案。惟被告仍未返家履行同居義務，\n            又無不能同居之正當理由，顯係惡意遺棄原告在繼續狀態中，原告依民\n            法第一千零五十二條第一項第五款規定，自得請求離婚。\n  三、證據：提出戶籍謄本一件、本院九十年度婚字第六七五號民事判決暨確定證明\n            影本各一件，並聲請訊問證人朱祈財、林遊府、許見、林章俊。\n乙、被告未於言詞辯論期日到場，亦未提出書狀作何聲明或陳述。\n丙、本院依職權調閱本院九十年度婚字第六七五號履行同居事件案卷。\n    理    由\n一、被告經合法通知，未於言詞辯論期日到場，核無民事訴訟法第三百八十六條各款\n    所列情形，爰依原告之聲請，由其一造辯論而為判決。\n二、原告主張兩造係夫妻，婚姻關係現仍存續中，及被告於八十一年間無故離家，經\n    本院於九十年十一月二十二日判決被告應與原告同居確定後，被告迄未履行同居\n    義務之事實，業據原告提出戶籍謄本一件、本院九十年度婚字第六七五號民事判\n    決暨確定證明影本各一件為證，並經證人朱祈財即原告之叔叔到庭證稱：「我的\n    住處離兩造的住址約一、二公里，我常到兩造的家，一星期約三、四次，我在幾\n    年前有見過被告，請她回去，但被告都置之不理，被告在八十年間離家出走至今\n    都沒也回來，原告的家裡現只有子女同住」、證人林遊府、許見即被告之養父、\n    母到庭證稱：「被告從她十七歲就離家未回，我不知到她人在何處，他們結婚時\n    我們也沒有參加，迄今他們也都沒有與我們聯絡，他們要離婚我沒有意見」、證\n    人林章俊即兩造住所地里長到庭具結證稱：「兩造都是我的里民，八十年我有看\n    過被告，之後就在也沒有看過了，我有問過原告，原告說被告已經離家了。」等\n    語在卷可稽，本院復調閱本院九十年度婚字第六七五號履行同居事件案卷審核無\n    誤，顯見被告迄未履行與原告同居之義務，且被告復未到庭爭執，自堪信原告之\n    主張為真實。\n三、按夫妻之一方，以惡意遺棄他方在繼續狀態中者，為判決離婚之原因，民法第一\n    千零五十二條第一項第五款定有明文。又夫妻之一方於同居之訴判決確定後，仍\n    不履行同居義務，在此狀態繼續存在中，而又無不能同居之正當理由者，即與民\n    法第一千零五十二條第一項第五款所定之離婚要件相當，此觀最高法院四十九年\n    台上字第九九○號、第一二三三號判例自明。本件兩造係夫妻，經本院以九十年\n    度婚字第六七五號判決被告應與原告同居確定，而被告迄未履行同居義務，已如\n    前述，被告又未到庭主張有何不能同居之正當理由，依上開判例意旨，被告行為\n    顯係惡意遺棄原告在繼續狀態中，從而，原告依民法第一千零五十二條第一項第\n    五款規定請求離婚，洵屬正當，應予准許。\n四、據上論結，本件原告之訴為有理由，並依民事訴訟法第三百八十五條第一項前段\n    、第七十八條，判決如主文。\n中      華      民      國    九十一    年      五     月    二十四    日\n                              臺灣臺中地方法院家事法庭\n~B法      官  楊國精\n右為正本係照原本作成\n如對本判決上訴，須於判決送達後二十日內，向本院提出上訴狀，同時表明上訴理由\n。\n中      華      民      國    九十一    年      五      月    二十四    日\n~B法院書記官\n",
  "structure": {
    "main": "准原告與被告離婚。\n訴訟費用由被告負擔。",
    "fact": "甲、原告方面：\n  一、聲明：如主文所示。\n  二、陳述：兩造係夫妻，現婚姻關係仍存續中，詎被告自民國八十一起間因行為不\n            檢，置家庭生活於不顧，無故離家出走，拒與原告履行同居生活，經原\n            告四處尋訪，仍無下落，顯然違背同居義務，為此提起本件訴訟，原告\n            乃提起履行同居之訴，業經鈞院於九十年十一月二十二日以九十年度婚\n            字第六七五號判決原告勝訴確定在案。惟被告仍未返家履行同居義務，\n            又無不能同居之正當理由，顯係惡意遺棄原告在繼續狀態中，原告依民\n            法第一千零五十二條第一項第五款規定，自得請求離婚。\n  三、證據：提出戶籍謄本一件、本院九十年度婚字第六七五號民事判決暨確定證明\n            影本各一件，並聲請訊問證人朱祈財、林遊府、許見、林章俊。\n乙、被告未於言詞辯論期日到場，亦未提出書狀作何聲明或陳述。\n丙、本院依職權調閱本院九十年度婚字第六七五號履行同居事件案卷。",
    "reason": "一、被告經合法通知，未於言詞辯論期日到場，核無民事訴訟法第三百八十六條各款\n    所列情形，爰依原告之聲請，由其一造辯論而為判決。\n二、原告主張兩造係夫妻，婚姻關係現仍存續中，及被告於八十一年間無故離家，經\n    本院於九十年十一月二十二日判決被告應與原告同居確定後，被告迄未履行同居\n    義務之事實，業據原告提出戶籍謄本一件、本院九十年度婚字第六七五號民事判\n    決暨確定證明影本各一件為證，並經證人朱祈財即原告之叔叔到庭證稱：「我的\n    住處離兩造的住址約一、二公里，我常到兩造的家，一星期約三、四次，我在幾\n    年前有見過被告，請她回去，但被告都置之不理，被告在八十年間離家出走至今\n    都沒也回來，原告的家裡現只有子女同住」、證人林遊府、許見即被告之養父、\n    母到庭證稱：「被告從她十七歲就離家未回，我不知到她人在何處，他們結婚時\n    我們也沒有參加，迄今他們也都沒有與我們聯絡，他們要離婚我沒有意見」、證\n    人林章俊即兩造住所地里長到庭具結證稱：「兩造都是我的里民，八十年我有看\n    過被告，之後就在也沒有看過了，我有問過原告，原告說被告已經離家了。」等\n    語在卷可稽，本院復調閱本院九十年度婚字第六七五號履行同居事件案卷審核無\n    誤，顯見被告迄未履行與原告同居之義務，且被告復未到庭爭執，自堪信原告之\n    主張為真實。\n三、按夫妻之一方，以惡意遺棄他方在繼續狀態中者，為判決離婚之原因，民法第一\n    千零五十二條第一項第五款定有明文。又夫妻之一方於同居之訴判決確定後，仍\n    不履行同居義務，在此狀態繼續存在中，而又無不能同居之正當理由者，即與民\n    法第一千零五十二條第一項第五款所定之離婚要件相當，此觀最高法院四十九年\n    台上字第九九○號、第一二三三號判例自明。本件兩造係夫妻，經本院以九十年\n    度婚字第六七五號判決被告應與原告同居確定，而被告迄未履行同居義務，已如\n    前述，被告又未到庭主張有何不能同居之正當理由，依上開判例意旨，被告行為\n    顯係惡意遺棄原告在繼續狀態中，從而，原告依民法第一千零五十二條第一項第\n    五款規定請求離婚，洵屬正當，應予准許。\n四、據上論結，本件原告之訴為有理由，並依民事訴訟法第三百八十五條第一項前段\n    、第七十八條，判決如主文。\n中      華      民      國    九十一    年      五     月    二十四    日\n                              臺灣臺中地方法院家事法庭\n~B法      官  楊國精\n右為正本係照原本作成\n如對本判決上訴，須於判決送達後二十日內，向本院提出上訴狀，同時表明上訴理由\n。"
  },
  "search": "臺灣臺中地方法院民事判決九十一年度婚字第六四號原告朱蓮池被告甲○○右當事人間請求離婚事件，本院判決如左：主文准原告與被告離婚。訴訟費用由被告負擔。事實甲、原告方面：一、聲明：如主文所示。二、陳述：兩造係夫妻，現婚姻關係仍存續中，詎被告自民國八十一起間因行為不檢，置家庭生活於不顧，無故離家出走，拒與原告履行同居生活，經原告四處尋訪，仍無下落，顯然違背同居義務，為此提起本件訴訟，原告乃提起履行同居之訴，業經鈞院於九十年十一月二十二日以九十年度婚字第六七五號判決原告勝訴確定在案。惟被告仍未返家履行同居義務，又無不能同居之正當理由，顯係惡意遺棄原告在繼續狀態中，原告依民法第一千零五十二條第一項第五款規定，自得請求離婚。三、證據：提出戶籍謄本一件、本院九十年度婚字第六七五號民事判決暨確定證明影本各一件，並聲請訊問證人朱祈財、林遊府、許見、林章俊。乙、被告未於言詞辯論期日到場，亦未提出書狀作何聲明或陳述。丙、本院依職權調閱本院九十年度婚字第六七五號履行同居事件案卷。理由一、被告經合法通知，未於言詞辯論期日到場，核無民事訴訟法第三百八十六條各款所列情形，爰依原告之聲請，由其一造辯論而為判決。二、原告主張兩造係夫妻，婚姻關係現仍存續中，及被告於八十一年間無故離家，經本院於九十年十一月二十二日判決被告應與原告同居確定後，被告迄未履行同居義務之事實，業據原告提出戶籍謄本一件、本院九十年度婚字第六七五號民事判決暨確定證明影本各一件為證，並經證人朱祈財即原告之叔叔到庭證稱：「我的住處離兩造的住址約一、二公里，我常到兩造的家，一星期約三、四次，我在幾年前有見過被告，請她回去，但被告都置之不理，被告在八十年間離家出走至今都沒也回來，原告的家裡現只有子女同住」、證人林遊府、許見即被告之養父、母到庭證稱：「被告從她十七歲就離家未回，我不知到她人在何處，他們結婚時我們也沒有參加，迄今他們也都沒有與我們聯絡，他們要離婚我沒有意見」、證人林章俊即兩造住所地里長到庭具結證稱：「兩造都是我的里民，八十年我有看過被告，之後就在也沒有看過了，我有問過原告，原告說被告已經離家了。」等語在卷可稽，本院復調閱本院九十年度婚字第六七五號履行同居事件案卷審核無誤，顯見被告迄未履行與原告同居之義務，且被告復未到庭爭執，自堪信原告之主張為真實。三、按夫妻之一方，以惡意遺棄他方在繼續狀態中者，為判決離婚之原因，民法第一千零五十二條第一項第五款定有明文。又夫妻之一方於同居之訴判決確定後，仍不履行同居義務，在此狀態繼續存在中，而又無不能同居之正當理由者，即與民法第一千零五十二條第一項第五款所定之離婚要件相當，此觀最高法院四十九年台上字第九九○號、第一二三三號判例自明。本件兩造係夫妻，經本院以九十年度婚字第六七五號判決被告應與原告同居確定，而被告迄未履行同居義務，已如前述，被告又未到庭主張有何不能同居之正當理由，依上開判例意旨，被告行為顯係惡意遺棄原告在繼續狀態中，從而，原告依民法第一千零五十二條第一項第五款規定請求離婚，洵屬正當，應予准許。四、據上論結，本件原告之訴為有理由，並依民事訴訟法第三百八十五條第一項前段、第七十八條，判決如主文。中華民國九十一年五月二十四日臺灣臺中地方法院家事法庭~B法官楊國精右為正本係照原本作成如對本判決上訴，須於判決送達後二十日內，向本院提出上訴狀，同時表明上訴理由。中華民國九十一年五月二十四日~B法院書記官",
  "characters": {
    "judges": [
      "楊國精"
    ],
    "prosecutors": [

    ],
    "lawyers": [

    ],
    "clerks": [

    ],
    "plaintiffs": [
      "朱蓮池"
    ],
    "defendants": [
      "甲○○",
      "右當事人間請求離婚事件，本院判決如左："
    ],
    "prosecutor_office": [

    ],
    "creditors": [

    ],
    "debtors": [

    ],
    "judicial_associate_officer": [

    ]
  },
  "adjudged_at": "2002-05-24",
  "created_at": "2016-02-04 14:20:35",
  "updated_at": "2016-02-04 14:20:35"
}