{
  "identify": "CHD-100-交簡-79-20110208-1",
  "court": {
    "name": "臺灣彰化地方法院",
    "code": "CHD"
  },
  "division": {
    "name": "刑事",
    "code": "M"
  },
  "year": 100,
  "word": "交簡",
  "number": "79",
  "jcheck": "1",
  "reason": "公共危險",
  "content": "臺灣彰化地方法院刑事簡易判決        100年度交簡字第79號\n聲  請  人  臺灣彰化地方法院檢察署檢察官\n被      告  陳文宗\n上列被告因公共危險案件，經檢察官聲請簡易判決處刑（99年度\n偵字第11244號），本院逕以簡易判決處刑如下：\n    主    文\n陳文宗犯不能安全駕駛動力交通工具罪，處有期徒刑月，如易\n科罰金，以新臺幣壹仟元折算壹日。\n    事實及理由\n一、本件犯罪事實、證據及所犯法條，除就證據部分，補充和解\n    書1份外，其餘引用檢察官聲請簡易判決處刑書所載（如附\n    件）。\n二、爰審酌被告罔顧個人及他人生命、財產之安全，漠視政府多\n    年來有關酒後禁止駕車之宣導，仍於飲酒後，已達不能安全\n    駕駛程度，貿然駕駛汽車，嗣因不勝酒力，不慎撞斷路旁之\n    電線桿，導致被害人鄭芳宜閃避不及而摔倒受傷，造成被害\n    人右手、左腳受有擦傷，且雙方車輛車體皆受損，經警測得\n    其呼氣所含酒精濃度高達每公升1.55毫克，顯示其醉態駕駛\n    情節嚴重，原難予輕縱，惟念及被告並無前科又係初犯本罪\n    ，有臺灣高等法院被告前案紀錄在卷可佐，素行尚佳，且已\n    與被害人達成和解（有上開和解書可證），及被告自身亦受\n    有傷害（頭部損傷、臉部及手指開放性傷口），有秀傳醫療\n    社團法人秀傳醫院診斷證明書附卷可憑，是被告此次肇事後\n    ，已付出健康、醫療費用及財物損失等代價，兼衡被告之智\n    識程度、坦承犯行之犯後態度等一切情狀，量處如主文所示\n    之刑，並諭知易科罰金之折算標準，以示懲戒。\n三、依刑事訴訟法第449條第1項前段、第454條第2項，刑法第18\n    5條之3、第41條第1項前段，刑法施行法第1條之1，逕以簡\n    易判決處如主文所示之刑。\n四、如不服本件判決，應於判決送達後10日內，以書狀敘述理由\n    ，向本院提出上訴（須附繕本）。\n中    華    民    國   100    年    2     月    8     日\n                  刑事第七庭          法  官  黃玉齡\n以上正本證明與原本無異。\n如不服本件判決，得自收受送達之翌日起10日，表明上訴理由，\n向本院提起上訴狀（須附繕本）。\n中    華    民    國   100    年    2     月    8     日\n                                      書記官  黃鏽金\n附錄本案論罪科刑法條全文：\n中華民國刑法第185條之3\n服用毒品、麻醉藥品、酒類或其他相類之物，不能安全駕駛動力\n交通工具而駕駛者，處1年以下有期徒刑、拘役或科或併科15萬\n元以下罰金。",
  "structure": {
    "main": "陳文宗犯不能安全駕駛動力交通工具罪，處有期徒刑月，如易\n科罰金，以新臺幣壹仟元折算壹日。",
    "fact": "一、本件犯罪事實、證據及所犯法條，除就證據部分，補充和解\n    書1份外，其餘引用檢察官聲請簡易判決處刑書所載（如附\n    件）。\n二、爰審酌被告罔顧個人及他人生命、財產之安全，漠視政府多\n    年來有關酒後禁止駕車之宣導，仍於飲酒後，已達不能安全\n    駕駛程度，貿然駕駛汽車，嗣因不勝酒力，不慎撞斷路旁之\n    電線桿，導致被害人鄭芳宜閃避不及而摔倒受傷，造成被害\n    人右手、左腳受有擦傷，且雙方車輛車體皆受損，經警測得\n    其呼氣所含酒精濃度高達每公升1.55毫克，顯示其醉態駕駛\n    情節嚴重，原難予輕縱，惟念及被告並無前科又係初犯本罪\n    ，有臺灣高等法院被告前案紀錄在卷可佐，素行尚佳，且已\n    與被害人達成和解（有上開和解書可證），及被告自身亦受\n    有傷害（頭部損傷、臉部及手指開放性傷口），有秀傳醫療\n    社團法人秀傳醫院診斷證明書附卷可憑，是被告此次肇事後\n    ，已付出健康、醫療費用及財物損失等代價，兼衡被告之智\n    識程度、坦承犯行之犯後態度等一切情狀，量處如主文所示\n    之刑，並諭知易科罰金之折算標準，以示懲戒。\n三、依刑事訴訟法第449條第1項前段、第454條第2項，刑法第18\n    5條之3、第41條第1項前段，刑法施行法第1條之1，逕以簡\n    易判決處如主文所示之刑。\n四、如不服本件判決，應於判決送達後10日內，以書狀敘述理由\n    ，向本院提出上訴（須附繕本）。",
    "reason": "一、本件犯罪事實、證據及所犯法條，除就證據部分，補充和解\n    書1份外，其餘引用檢察官聲請簡易判決處刑書所載（如附\n    件）。\n二、爰審酌被告罔顧個人及他人生命、財產之安全，漠視政府多\n    年來有關酒後禁止駕車之宣導，仍於飲酒後，已達不能安全\n    駕駛程度，貿然駕駛汽車，嗣因不勝酒力，不慎撞斷路旁之\n    電線桿，導致被害人鄭芳宜閃避不及而摔倒受傷，造成被害\n    人右手、左腳受有擦傷，且雙方車輛車體皆受損，經警測得\n    其呼氣所含酒精濃度高達每公升1.55毫克，顯示其醉態駕駛\n    情節嚴重，原難予輕縱，惟念及被告並無前科又係初犯本罪\n    ，有臺灣高等法院被告前案紀錄在卷可佐，素行尚佳，且已\n    與被害人達成和解（有上開和解書可證），及被告自身亦受\n    有傷害（頭部損傷、臉部及手指開放性傷口），有秀傳醫療\n    社團法人秀傳醫院診斷證明書附卷可憑，是被告此次肇事後\n    ，已付出健康、醫療費用及財物損失等代價，兼衡被告之智\n    識程度、坦承犯行之犯後態度等一切情狀，量處如主文所示\n    之刑，並諭知易科罰金之折算標準，以示懲戒。\n三、依刑事訴訟法第449條第1項前段、第454條第2項，刑法第18\n    5條之3、第41條第1項前段，刑法施行法第1條之1，逕以簡\n    易判決處如主文所示之刑。\n四、如不服本件判決，應於判決送達後10日內，以書狀敘述理由\n    ，向本院提出上訴（須附繕本）。"
  },
  "search": "臺灣彰化地方法院刑事簡易判決100年度交簡字第79號聲請人臺灣彰化地方法院檢察署檢察官被告陳文宗上列被告因公共危險案件，經檢察官聲請簡易判決處刑（99年度偵字第11244號），本院逕以簡易判決處刑如下：主文陳文宗犯不能安全駕駛動力交通工具罪，處有期徒刑月，如易科罰金，以新臺幣壹仟元折算壹日。事實及理由一、本件犯罪事實、證據及所犯法條，除就證據部分，補充和解書1份外，其餘引用檢察官聲請簡易判決處刑書所載（如附件）。二、爰審酌被告罔顧個人及他人生命、財產之安全，漠視政府多年來有關酒後禁止駕車之宣導，仍於飲酒後，已達不能安全駕駛程度，貿然駕駛汽車，嗣因不勝酒力，不慎撞斷路旁之電線桿，導致被害人鄭芳宜閃避不及而摔倒受傷，造成被害人右手、左腳受有擦傷，且雙方車輛車體皆受損，經警測得其呼氣所含酒精濃度高達每公升1.55毫克，顯示其醉態駕駛情節嚴重，原難予輕縱，惟念及被告並無前科又係初犯本罪，有臺灣高等法院被告前案紀錄在卷可佐，素行尚佳，且已與被害人達成和解（有上開和解書可證），及被告自身亦受有傷害（頭部損傷、臉部及手指開放性傷口），有秀傳醫療社團法人秀傳醫院診斷證明書附卷可憑，是被告此次肇事後，已付出健康、醫療費用及財物損失等代價，兼衡被告之智識程度、坦承犯行之犯後態度等一切情狀，量處如主文所示之刑，並諭知易科罰金之折算標準，以示懲戒。三、依刑事訴訟法第449條第1項前段、第454條第2項，刑法第185條之3、第41條第1項前段，刑法施行法第1條之1，逕以簡易判決處如主文所示之刑。四、如不服本件判決，應於判決送達後10日內，以書狀敘述理由，向本院提出上訴（須附繕本）。中華民國100年2月8日刑事第七庭法官黃玉齡以上正本證明與原本無異。如不服本件判決，得自收受送達之翌日起10日，表明上訴理由，向本院提起上訴狀（須附繕本）。中華民國100年2月8日書記官黃鏽金附錄本案論罪科刑法條全文：中華民國刑法第185條之3服用毒品、麻醉藥品、酒類或其他相類之物，不能安全駕駛動力交通工具而駕駛者，處1年以下有期徒刑、拘役或科或併科15萬元以下罰金。",
  "characters": {
    "judges": [
      "黃玉齡"
    ],
    "prosecutors": [

    ],
    "lawyers": [

    ],
    "clerks": [
      "黃鏽金"
    ],
    "plaintiffs": [

    ],
    "defendants": [
      "陳文宗"
    ],
    "prosecutor_office": [
      "臺灣彰化地方法院檢察署檢察官"
    ],
    "creditors": [

    ],
    "debtors": [

    ],
    "judicial_associate_officer": [

    ]
  },
  "adjudged_at": "2011-02-08",
  "created_at": "2016-02-12 06:25:44",
  "updated_at": "2016-02-12 06:25:44"
}