{
  "identify": "KSD-91-訴-1809-20020731-1",
  "court": {
    "name": "臺灣高雄地方法院",
    "code": "KSD"
  },
  "division": {
    "name": "刑事",
    "code": "M"
  },
  "year": 91,
  "word": "訴",
  "number": "1809",
  "jcheck": "1",
  "reason": "毒品危害防制條例",
  "content": "臺灣高雄地方法院刑事判決                        九十一年度訴字第一八九號\n    公  訴  人  臺灣高雄地方法院檢察署檢察官\n    被      告  甲○○\n右列被告因違反毒品危害防治條例案件，經檢察官提起公訴（九十一年度毒偵字第一\n九七五號），本院判決如左：\n    主  文\n甲○○連續施用第一級毒品，處有期徒刑捌月。扣案殘留海洛因之注射針筒及殘留海\n洛因之分裝杓各壹支，均沒收銷燬之。\n    事  實\n一、甲○○前因施用毒品案件，經依本院以八十七年度毒聲字第四五○九號裁定送觀\n    察、勒戒後，認無繼續施用毒品之傾向，由臺灣高雄地方法院檢察署檢察官於民\n    國八十八年一月十一日，以八十七年度偵字第二四四五號為不起訴處分確定在案\n    。詎仍不知悔悟，竟基於施用第一級毒品海洛因之概括犯意，自九十一年一月中\n    旬起至同年四月二十九日下午一時四十分許止，連續在高雄縣橋頭鄉○○村○○\n    路仁義巷二號住處等地，以將海洛因摻在香煙內點煙吸食或摻水以針筒注射血管\n    之方式，施用第一級毒品海洛因多次，嗣於九十一年四月二十九日下午二時許，\n    在高雄市○○區○○路與海功路口為警查獲，並扣得注射針筒及分裝杓各一支（\n    公訴人贅載扣得海洛因毛重○˙三公克及海洛因殘渣袋一個），復經依本院九十\n    一年度毒聲字第二三二二號裁定送觀察勒戒後，認有繼續施用毒品傾向。\n二、案經高雄市政府警察局三民第一分局移請臺灣高雄地方法院檢察署檢察官偵查起\n    訴。\n    理  由\n一、訊據被告甲○○於右揭時、地施用第一級毒品海洛因之事實，坦白不諱，且被告\n    經警查獲並採集其尿液送驗之結果，呈嗎啡陽性反應，此有高雄市立凱旋醫院於\n    九十一年五月二十八日出具之高市凱醫檢字第○○四六五號煙毒尿液檢驗成績書\n    暨高雄市政府警察局三民第一分局毒品案件尿液送驗編號與真實對照表在卷可憑\n    ，及載有扣押注射針筒及分裝杓各一支之扣押筆錄暨扣押物品目錄附卷可參，且\n    扣案注射針筒及分裝杓經送高雄醫學院附設中和紀念醫院檢驗結果，確含有嗎啡\n    陽性反應，有高雄醫學院附設中和紀念醫院九十一年七月九日編號九一○七─五\n    二號、九一○七─五三號檢驗報告單各一紙在卷足證。又被告前因施用毒品案件\n    ，經依本院以八十七年度毒聲字第四五○九號裁定送觀察、勒戒後，認無繼續施\n    用毒品之傾向，由臺灣高雄地方法院檢察署檢察官於民國八十八年一月十一日，\n    以八十七年度偵字第二四四號為不起訴處分確定，有臺灣高雄地方法院被告全國\n    前案紀錄表暨臺灣高雄地方法院檢察署刑案資料查註紀錄表各一份在卷足憑。其\n    於五年後再犯毒品危害防制條例第十條之罪，經裁定送觀察勒戒，認有繼續施用\n    毒品之傾向，有臺灣高雄地方法院九十一年度毒聲字第二三二二號裁定及臺灣高\n    雄看守所附設勒戒處所九十一年五月九日高所坤戒勒字第八二六號函送之證明書\n    一份附卷可參，是本案罪證明確，被告上揭犯行洵堪認定，應依法論科。\n二、核被告甲○○所為，係違反毒品危害防制條例第十條第一項之施用第一級毒品罪\n    。其持有第一級毒品後進而施用，持有之低度行為為施用毒品之高度行為所吸收\n    ，不另論罪。被告先後多次分別施用第一級毒品海洛因之行為，時間緊接、方法\n    相同，係觸犯構成要件相同之罪名，顯係基於概括犯意為之，為連續犯，應依刑\n    法第五十六條之規定，各以一罪論，並加重其刑。而被告自九十一年一月中旬起\n    至同年四月二十九日被查獲前止，即有施用海洛因等情，業據其於本院審理中自\n    承甚明（見本院審理筆錄），是公訴人起訴事實雖未述及上開犯行，然該部份事\n    實與已起訴之被告於九十一年四月二十九日下午一時四十分許施用海洛因之犯行\n    ，有連續犯之裁判上一罪關係，應為起訴效力所及，本院自應併與審究，附此敘\n    明。爰審酌被告於前案獲不起訴處分經釋放後，又再度施用第一級毒品海洛因，\n    顯見其不知警惕，意志不堅，惟姑念其犯罪後坦承犯行，及施用毒品亦為自我戕\n    害行為，並未危害他人等一切情狀，量處如主文所示之刑。至扣案之注射針筒及\n    分裝杓各一支（因海洛因殘渣附著於上剝離不易，應將之整體視為海洛因毒品）\n    ，均應依毒品危害防制條例第十八條第一項前段規定，不問屬於犯人與否，均沒\n    收銷燬之。\n三、被告經警查獲時所採集之尿液，經送高雄市立凱旋醫院檢驗之結果，除呈現嗎啡\n    之陽性反應外，亦呈現甲基安非他命之陽性反應，有上開煙毒尿液檢驗成績書乙\n    紙附卷可按，而按第二級毒品安非他命係屬晶體，第一級毒品海洛因係屬粉末狀\n    ，且毒品性質不同，衡情被告應非將安非他命與海洛因一起吸食，而應係分別施\n    用，惟其涉犯施用第二級毒品之犯行，惟與本案施用第一級毒品罪之間，犯意各\n    別，行為互殊，應屬數罪併罰，並非裁判上一罪之關係，本院自無由予以審酌，\n    此部分應由檢察官另為妥適之處理。\n據上論斷，應依刑事訴訟法第二百九十九條第一項前段，毒品危害防制條例第十條第\n條第一項、第十八條第一項前段，刑法第十一條、第五十六條，判決如主文。\n本案經檢察官王柏敦到庭執行職務。\n中      華      民      國    九十一    年      七      月    三十一    日\n                                    臺灣高雄地方法院刑事第四庭\n                                       法  官   廖純卿\n右正本證明與原本無異。\n如不服本判決，應於判決送達後十日內，向本院提出上訴狀。\n                                       書記官   劉企萍\n中      華      民      國    九十一    年      八      月      二      日\n附錄本案論罪科刑法條：\n毒品危害防制條例第十條\n施用第一級毒品者，處六月以上五年以下有期徒刑。\n施用第二級毒品者，處三年以下有期徒刑。\n",
  "structure": {
    "main": "甲○○連續施用第一級毒品，處有期徒刑捌月。扣案殘留海洛因之注射針筒及殘留海\n洛因之分裝杓各壹支，均沒收銷燬之。",
    "fact": "一、甲○○前因施用毒品案件，經依本院以八十七年度毒聲字第四五○九號裁定送觀\n    察、勒戒後，認無繼續施用毒品之傾向，由臺灣高雄地方法院檢察署檢察官於民\n    國八十八年一月十一日，以八十七年度偵字第二四四五號為不起訴處分確定在案\n    。詎仍不知悔悟，竟基於施用第一級毒品海洛因之概括犯意，自九十一年一月中\n    旬起至同年四月二十九日下午一時四十分許止，連續在高雄縣橋頭鄉○○村○○\n    路仁義巷二號住處等地，以將海洛因摻在香煙內點煙吸食或摻水以針筒注射血管\n    之方式，施用第一級毒品海洛因多次，嗣於九十一年四月二十九日下午二時許，\n    在高雄市○○區○○路與海功路口為警查獲，並扣得注射針筒及分裝杓各一支（\n    公訴人贅載扣得海洛因毛重○˙三公克及海洛因殘渣袋一個），復經依本院九十\n    一年度毒聲字第二三二二號裁定送觀察勒戒後，認有繼續施用毒品傾向。\n二、案經高雄市政府警察局三民第一分局移請臺灣高雄地方法院檢察署檢察官偵查起\n    訴。",
    "reason": "一、訊據被告甲○○於右揭時、地施用第一級毒品海洛因之事實，坦白不諱，且被告\n    經警查獲並採集其尿液送驗之結果，呈嗎啡陽性反應，此有高雄市立凱旋醫院於\n    九十一年五月二十八日出具之高市凱醫檢字第○○四六五號煙毒尿液檢驗成績書\n    暨高雄市政府警察局三民第一分局毒品案件尿液送驗編號與真實對照表在卷可憑\n    ，及載有扣押注射針筒及分裝杓各一支之扣押筆錄暨扣押物品目錄附卷可參，且\n    扣案注射針筒及分裝杓經送高雄醫學院附設中和紀念醫院檢驗結果，確含有嗎啡\n    陽性反應，有高雄醫學院附設中和紀念醫院九十一年七月九日編號九一○七─五\n    二號、九一○七─五三號檢驗報告單各一紙在卷足證。又被告前因施用毒品案件\n    ，經依本院以八十七年度毒聲字第四五○九號裁定送觀察、勒戒後，認無繼續施\n    用毒品之傾向，由臺灣高雄地方法院檢察署檢察官於民國八十八年一月十一日，\n    以八十七年度偵字第二四四號為不起訴處分確定，有臺灣高雄地方法院被告全國\n    前案紀錄表暨臺灣高雄地方法院檢察署刑案資料查註紀錄表各一份在卷足憑。其\n    於五年後再犯毒品危害防制條例第十條之罪，經裁定送觀察勒戒，認有繼續施用\n    毒品之傾向，有臺灣高雄地方法院九十一年度毒聲字第二三二二號裁定及臺灣高\n    雄看守所附設勒戒處所九十一年五月九日高所坤戒勒字第八二六號函送之證明書\n    一份附卷可參，是本案罪證明確，被告上揭犯行洵堪認定，應依法論科。\n二、核被告甲○○所為，係違反毒品危害防制條例第十條第一項之施用第一級毒品罪\n    。其持有第一級毒品後進而施用，持有之低度行為為施用毒品之高度行為所吸收\n    ，不另論罪。被告先後多次分別施用第一級毒品海洛因之行為，時間緊接、方法\n    相同，係觸犯構成要件相同之罪名，顯係基於概括犯意為之，為連續犯，應依刑\n    法第五十六條之規定，各以一罪論，並加重其刑。而被告自九十一年一月中旬起\n    至同年四月二十九日被查獲前止，即有施用海洛因等情，業據其於本院審理中自\n    承甚明（見本院審理筆錄），是公訴人起訴事實雖未述及上開犯行，然該部份事\n    實與已起訴之被告於九十一年四月二十九日下午一時四十分許施用海洛因之犯行\n    ，有連續犯之裁判上一罪關係，應為起訴效力所及，本院自應併與審究，附此敘\n    明。爰審酌被告於前案獲不起訴處分經釋放後，又再度施用第一級毒品海洛因，\n    顯見其不知警惕，意志不堅，惟姑念其犯罪後坦承犯行，及施用毒品亦為自我戕\n    害行為，並未危害他人等一切情狀，量處如主文所示之刑。至扣案之注射針筒及\n    分裝杓各一支（因海洛因殘渣附著於上剝離不易，應將之整體視為海洛因毒品）\n    ，均應依毒品危害防制條例第十八條第一項前段規定，不問屬於犯人與否，均沒\n    收銷燬之。\n三、被告經警查獲時所採集之尿液，經送高雄市立凱旋醫院檢驗之結果，除呈現嗎啡\n    之陽性反應外，亦呈現甲基安非他命之陽性反應，有上開煙毒尿液檢驗成績書乙\n    紙附卷可按，而按第二級毒品安非他命係屬晶體，第一級毒品海洛因係屬粉末狀\n    ，且毒品性質不同，衡情被告應非將安非他命與海洛因一起吸食，而應係分別施\n    用，惟其涉犯施用第二級毒品之犯行，惟與本案施用第一級毒品罪之間，犯意各\n    別，行為互殊，應屬數罪併罰，並非裁判上一罪之關係，本院自無由予以審酌，\n    此部分應由檢察官另為妥適之處理。\n據上論斷，應依刑事訴訟法第二百九十九條第一項前段，毒品危害防制條例第十條第\n條第一項、第十八條第一項前段，刑法第十一條、第五十六條，判決如主文。\n本案經檢察官王柏敦到庭執行職務。\n中      華      民      國    九十一    年      七      月    三十一    日\n                                    臺灣高雄地方法院刑事第四庭\n                                       法  官   廖純卿\n右正本證明與原本無異。\n如不服本判決，應於判決送達後十日內，向本院提出上訴狀。\n                                       書記官   劉企萍"
  },
  "search": "臺灣高雄地方法院刑事判決九十一年度訴字第一八九號公訴人臺灣高雄地方法院檢察署檢察官被告甲○○右列被告因違反毒品危害防治條例案件，經檢察官提起公訴（九十一年度毒偵字第一九七五號），本院判決如左：主文甲○○連續施用第一級毒品，處有期徒刑捌月。扣案殘留海洛因之注射針筒及殘留海洛因之分裝杓各壹支，均沒收銷燬之。事實一、甲○○前因施用毒品案件，經依本院以八十七年度毒聲字第四五○九號裁定送觀察、勒戒後，認無繼續施用毒品之傾向，由臺灣高雄地方法院檢察署檢察官於民國八十八年一月十一日，以八十七年度偵字第二四四五號為不起訴處分確定在案。詎仍不知悔悟，竟基於施用第一級毒品海洛因之概括犯意，自九十一年一月中旬起至同年四月二十九日下午一時四十分許止，連續在高雄縣橋頭鄉○○村○○路仁義巷二號住處等地，以將海洛因摻在香煙內點煙吸食或摻水以針筒注射血管之方式，施用第一級毒品海洛因多次，嗣於九十一年四月二十九日下午二時許，在高雄市○○區○○路與海功路口為警查獲，並扣得注射針筒及分裝杓各一支（公訴人贅載扣得海洛因毛重○˙三公克及海洛因殘渣袋一個），復經依本院九十一年度毒聲字第二三二二號裁定送觀察勒戒後，認有繼續施用毒品傾向。二、案經高雄市政府警察局三民第一分局移請臺灣高雄地方法院檢察署檢察官偵查起訴。理由一、訊據被告甲○○於右揭時、地施用第一級毒品海洛因之事實，坦白不諱，且被告經警查獲並採集其尿液送驗之結果，呈嗎啡陽性反應，此有高雄市立凱旋醫院於九十一年五月二十八日出具之高市凱醫檢字第○○四六五號煙毒尿液檢驗成績書暨高雄市政府警察局三民第一分局毒品案件尿液送驗編號與真實對照表在卷可憑，及載有扣押注射針筒及分裝杓各一支之扣押筆錄暨扣押物品目錄附卷可參，且扣案注射針筒及分裝杓經送高雄醫學院附設中和紀念醫院檢驗結果，確含有嗎啡陽性反應，有高雄醫學院附設中和紀念醫院九十一年七月九日編號九一○七─五二號、九一○七─五三號檢驗報告單各一紙在卷足證。又被告前因施用毒品案件，經依本院以八十七年度毒聲字第四五○九號裁定送觀察、勒戒後，認無繼續施用毒品之傾向，由臺灣高雄地方法院檢察署檢察官於民國八十八年一月十一日，以八十七年度偵字第二四四號為不起訴處分確定，有臺灣高雄地方法院被告全國前案紀錄表暨臺灣高雄地方法院檢察署刑案資料查註紀錄表各一份在卷足憑。其於五年後再犯毒品危害防制條例第十條之罪，經裁定送觀察勒戒，認有繼續施用毒品之傾向，有臺灣高雄地方法院九十一年度毒聲字第二三二二號裁定及臺灣高雄看守所附設勒戒處所九十一年五月九日高所坤戒勒字第八二六號函送之證明書一份附卷可參，是本案罪證明確，被告上揭犯行洵堪認定，應依法論科。二、核被告甲○○所為，係違反毒品危害防制條例第十條第一項之施用第一級毒品罪。其持有第一級毒品後進而施用，持有之低度行為為施用毒品之高度行為所吸收，不另論罪。被告先後多次分別施用第一級毒品海洛因之行為，時間緊接、方法相同，係觸犯構成要件相同之罪名，顯係基於概括犯意為之，為連續犯，應依刑法第五十六條之規定，各以一罪論，並加重其刑。而被告自九十一年一月中旬起至同年四月二十九日被查獲前止，即有施用海洛因等情，業據其於本院審理中自承甚明（見本院審理筆錄），是公訴人起訴事實雖未述及上開犯行，然該部份事實與已起訴之被告於九十一年四月二十九日下午一時四十分許施用海洛因之犯行，有連續犯之裁判上一罪關係，應為起訴效力所及，本院自應併與審究，附此敘明。爰審酌被告於前案獲不起訴處分經釋放後，又再度施用第一級毒品海洛因，顯見其不知警惕，意志不堅，惟姑念其犯罪後坦承犯行，及施用毒品亦為自我戕害行為，並未危害他人等一切情狀，量處如主文所示之刑。至扣案之注射針筒及分裝杓各一支（因海洛因殘渣附著於上剝離不易，應將之整體視為海洛因毒品），均應依毒品危害防制條例第十八條第一項前段規定，不問屬於犯人與否，均沒收銷燬之。三、被告經警查獲時所採集之尿液，經送高雄市立凱旋醫院檢驗之結果，除呈現嗎啡之陽性反應外，亦呈現甲基安非他命之陽性反應，有上開煙毒尿液檢驗成績書乙紙附卷可按，而按第二級毒品安非他命係屬晶體，第一級毒品海洛因係屬粉末狀，且毒品性質不同，衡情被告應非將安非他命與海洛因一起吸食，而應係分別施用，惟其涉犯施用第二級毒品之犯行，惟與本案施用第一級毒品罪之間，犯意各別，行為互殊，應屬數罪併罰，並非裁判上一罪之關係，本院自無由予以審酌，此部分應由檢察官另為妥適之處理。據上論斷，應依刑事訴訟法第二百九十九條第一項前段，毒品危害防制條例第十條第條第一項、第十八條第一項前段，刑法第十一條、第五十六條，判決如主文。本案經檢察官王柏敦到庭執行職務。中華民國九十一年七月三十一日臺灣高雄地方法院刑事第四庭法官廖純卿右正本證明與原本無異。如不服本判決，應於判決送達後十日內，向本院提出上訴狀。書記官劉企萍中華民國九十一年八月二日附錄本案論罪科刑法條：毒品危害防制條例第十條施用第一級毒品者，處六月以上五年以下有期徒刑。施用第二級毒品者，處三年以下有期徒刑。",
  "characters": {
    "judges": [
      "廖純卿"
    ],
    "prosecutors": [
      "王柏敦"
    ],
    "lawyers": [

    ],
    "clerks": [
      "劉企萍"
    ],
    "plaintiffs": [

    ],
    "defendants": [
      "甲○○",
      "右列被告因違反毒品危害防治條例案件，經檢察官提起公訴（九十一年度毒偵字第一",
      "九七五號），本院判決如左："
    ],
    "prosecutor_office": [
      "臺灣高雄地方法院檢察署檢察官"
    ],
    "creditors": [

    ],
    "debtors": [

    ],
    "judicial_associate_officer": [

    ]
  },
  "adjudged_at": "2002-07-31",
  "created_at": "2016-02-05 17:36:09",
  "updated_at": "2016-02-05 17:36:09"
}