{
  "identify": "TYD-90-易-138-20020731-1",
  "court": {
    "name": "臺灣桃園地方法院",
    "code": "TYD"
  },
  "division": {
    "name": "刑事",
    "code": "M"
  },
  "year": 90,
  "word": "易",
  "number": "138",
  "jcheck": "1",
  "reason": "侵占",
  "content": "臺灣桃園地方法院刑事判決                            九十年度易字第一三八號\n    公  訴  人  臺灣桃園地方法院檢察署檢察官\n    被      告  庚○○\n    選任辯護人  何啟熏律師\n                沈明達律師\n右列被告因侵占案件，經檢察官提起公訴（八十九年度偵字第三二六五號），本院判\n決如左：\n    主  文\n庚○○無罪。\n    理  由\n一、公訴意旨略以：被告庚○○係設在桃園縣蘆竹鄉○○路○段二三一巷四一號九五\n    實業有限公司（下稱九五公司）之負責人，於民國八十八年七月三十一日，向丙\n    ○○所經營設在臺北市○○區○○路三段三一０巷六弄一二號之全南企業有限公\n    司（下稱全南公司），訂購單相油壓箱二臺及鐵弗龍油壓缸一百支，價額共計新\n    臺幣十五萬八千零二十五元，俟全南公司交貨後，庚○○因發現貨有瑕疵，遂三\n    度寄發存證信函通知全南公司派員前來檢測，並主張拒絕受領，全南公司獲悉後\n    ，則寄發存證信函回絕九五公司，表示此舉如同刁難，未便所請。詎料，庚○○\n    依民法第三百五十八條第一項規定，於全南公司在桃園縣境無代理人有暫為保管\n    之責之情形下，竟意圖為自己不法之所有，以變易持有為所有之意思，將鐵弗龍\n    油壓缸一百支侵占入己。得手後，其為掩飾犯行，於同年十月四日，偽以退貨方\n    式，將四只空紙箱連同單相油壓箱二臺，委由大榮貨運汽車股份有限公司（下稱\n    大榮貨運公司）載至全南公司，惟因全南公司售予九五公司之鐵弗龍油壓缸，最\n    輕規格之重量一支有八‧六公斤，一百支起碼逾八百六十公斤，且依尺寸規格不\n    可能以四只紙箱裝畢，是丙○○見到退貨後，察覺有異，並發現紙箱重量差距過\n    大而未簽收，大榮貨運公司遇此情狀僅得載回上開貨物另作拒收處理，迄同年十\n    一月十八日十三時三十五分許，大榮貨運公司二度將上開貨物載至全南公司，丙\n    ○○即請大榮貨運公司轉載至警局，嗣經當場拆封，發現紙箱內除報紙外空無一\n    物，方查悉上情，並訴警究辦。因認被告庚○○涉犯刑法第三百三十五條第一項\n    之侵占罪嫌等語。\n二、按按犯罪事實，應依證據認定之，無證據不得推定其犯罪事實；又不能證明被告\n    犯罪者，應諭知無罪之判決，刑事訴訟法第一百五十四條、第三百零一條第一項\n    分別定有明文。再所謂認定犯罪事實之證據，係指足以認定被告確有犯罪行為之\n    積極證據而言，如未發現相當證據，或證據不足以證明，自不能以推測或擬制之\n    方法，以為裁判基礎。且刑事訴訟上證明之資料，無論其為直接證據或間接證據\n    ，均須達於通常一般人均不致於有所懷疑，而得確信其為真實之程度，始得據為\n    有罪之認定，若其關於被告是否犯罪之證明未能達此程度，而有合理性懷疑之存\n    在，致使無從形成有罪之確信，根據「罪證有疑，利於被告」之證據法則，即不\n    得遽為不利被告之認定，其以情況證據（即間接證據）斷罪時，尤須基於該證據\n    在直接關係上所可證明之他項情況事實，本乎推理作用足以確證被告有罪，方為\n    合法，不得徒憑主觀上之推想，將一般經驗上有利被告之其他合理情況逕予排除\n    ，此經最高法院三十二年度上字六七號、七十六年台上字第四九八六號著有判例\n    闡述甚明。又告訴人之告訴，本以使被告受刑事訴追為目的，故其陳述是否與事\n    實相符，自應調查其他證據，以資審認，苟其所為攻擊之詞，尚有瑕疵，則在此\n    瑕疵未予究明以前，即不能遽採為斷罪之基礎。\n三、訊據被告庚○○堅詞否認涉有上揭侵占犯行，辯稱：伊於八十八年七月三十一日\n    向全南公司負責人丙○○訂購一百支鐵弗龍油壓缸，惟於同年八月二十三日收到\n    該批貨物後，發現其品質不良，不堪使用，經通知告訴人處理，亦未獲理會，乃\n    囑咐員工甲○○、辛○○二人將該總重約一百公斤之鐵弗龍油壓缸，以四紙箱分\n    裝後託由大榮貨運公司送貨退還予全南公司，詎丙○○於同年十月四日收到該批\n    退貨後，竟私自將箱內之鐵弗龍油壓缸取出，再將紙箱復原，經一個多月後始於\n    同年十一月十八日濫行指控伊退回之貨物為空箱，實則並無侵占之事實，且告訴\n    人依買賣關係將上開貨物交付與伊，伊即取得該貨物之所有權，嗣因該批貨物有\n    瑕疵而將之退還，要屬是否應負物之瑕疵擔保責任之民事問題，核與侵占罪之構\n    成要件尚屬有間等語。經查公訴人認被告涉有上揭侵占犯行，無非以告訴人全南\n    公司代理人丙○○之指訴、證人即八十八年十月四日前往九五公司載運退貨之大\n    榮貨運公司南崁站員工丁○○、當日將退貨載至全南公司之大榮貨運公司新店站\n    職員己○○、全南公司拒收後處理退貨之大榮公司南崁站副主任乙○○、同年十\n    一月十八日二度將退貨載至全南公司之大榮貨運公司新店站副主任戊○○之證詞\n    ，又據告訴人指稱該鐵弗龍油壓缸最輕規格之重量一支有六‧八公斤，以此計算\n    ，一百支逾六百八十公斤，顯不可能以卷附相片所拍攝之四只紙箱裝畢，且縱以\n    被告所主張之規格最輕者○‧七三公斤計算，一百支亦有七十三公斤，與證人戊\n    ○○於全南公司拒收後將四只紙箱秤重僅七公斤，二者重量相差懸殊，被告所辯\n    顯不足採等情資為論據。惟查：\n    （一）據告訴人之代表人丙○○於偵查中指稱：該鐵弗龍油壓缸有九種規格，其\n          中最輕一支為八‧六公斤（台灣桃園地方法院檢察署八十九年度偵字第三\n          二六五號偵查卷第八十二頁反面）、於本院陳稱：最重的有二六‧五公斤\n          等語，另於本院桃園簡易庭八十九年十月十一日審理時陳稱：一百支油壓\n          缸之總重量是一千六百三十一公斤等語（參卷附八十八年桃簡字第一四八\n          九號民事卷宗第八十三頁），並於台灣台北地方法院檢察署檢察官於八十\n          九年一月七日偵訊時提出該二六‧五公斤重、長三十七公分之油壓缸相片\n          一張附卷（見同日訊問筆錄），另關於油壓缸之體積，據其於本院陳稱：\n          行程一百之長度如同被告所言，但如果內徑不一樣，長度也會不一樣，伊\n          之前於偵查中所提出的，是內徑七五、行程一百的等語。是由丙○○所陳\n          ，一百支鐵弗龍油壓缸之總重量有一千六百三十一公斤，然據證人即八十\n          八年十月四日前往九五公司載運退貨之大榮貨運公司司機丁○○於八十九\n          年一月十七日偵訊時證稱：「被告退貨計有六件，其中有兩件較重，老闆\n          幫我搬，四箱是小姐幫我搬，一才約十公斤，以體積哪個大或重量哪個重\n          ，就以較大或較重的為計算標準」等語，於同年八月十六日偵訊時證稱：\n          「四箱重量當時沒有秤重，但感覺特別輕，是我要搬下貨才知道」等語；\n          次據證人即將退貨載至全南公司之大榮貨運公司新店站職員己○○於八十\n          九年九月四日偵訊時證稱：「送去時因貨很輕，丙○○拒收，他有照相，\n          物件未離開我視線，也未拆封，因他沒簽收，我就將貨載回」等語；另全\n          南公司拒收後處理退貨之大榮貨運公司南崁站主任乙○○於八十九年八月\n          十六日偵訊時證稱：「十月四日丙○○拒收，新店站聯絡我說發生退貨情\n          事，我就聯絡九五公司如何處理，他們說將貨放在全南公司門口即可，因\n          雙方拒收，該貨放在南崁站有一陣子，後來我聯絡台中總公司，才決定暫\n          時送至台中總公司倉儲」等語；又證人即於同年十一月十八日二度將退貨\n          載至全南公司之大榮貨運公司新店站副主任戊○○於八十九年一月七日偵\n          訊時證稱：「十月四日己○○送貨至全南公司，經其回報說丙○○稱貨有\n          問題，四箱很輕，拒收，我說做拒收處理，同日貨送回來後，丙○○要求\n          我們秤重量，我立刻回報南崁站，並將貨退回南崁站，並通知總公司，十\n          一月十七日貨從台中寄出，十八日寄到新店站，我問丙○○貨送到哪，他\n          說送派出所，下貨前請丙○○簽收，運費交給我」等語，另經證人戊○○\n          秤重結果該四只紙箱之重量分別為三公斤、一公斤、二公斤、一公斤，有\n          卷附貨物收據一紙附卷可稽，是由上以查，該批貨物之總重如係達一千六\n          百三十一公斤，無論在體積及重量上，皆不可能以卷附四只紙箱裝載完成\n          ，亦不可能僅由一人搬動，被告如欲假退貨之名行侵占之實，豈會愚蠢至\n          以此輕易為人察覺之方式為之；而丙○○於八十八年十月四日收到上開退\n          貨後，當即知悉箱內絕非其所交付之貨品，既知預先拍照存證，何不立即\n          報警並儘速聯絡九五公司前來處理，其不此之為，反於一個多月後之同年\n          十一月十八日始聯絡大榮貨運公司將貨物直接運至派出所，實不免啟人疑\n          竇；再大榮貨運公司於全南公司認貨物有問題而拒收時，為釐清責任歸屬\n          ，避免瓜田李下，及收取應收運費，理應將貨物逕行退回託運人並由託運\n          人負擔因此所支出之一切費用，此觀卷附大榮汽車貨運股份有限公司運送\n          契約第三條明文定有拒收之處理情形甚明，乃竟不依規定而行，反將貨物\n          輾轉送至台中總公司存放達一個多月，其處置情形亦堪置疑；繼觀之卷附\n          由大榮貨運公司於八十八年十月四日所出具之貨物收據竟有二種不同之版\n          本，據證人即大榮貨運公司南崁站站長廖文章於本院民事庭承審法官於九\n          十年五月十七日前往大榮貨運南崁站履勘時證稱：「簡易庭卷宗第八十一\n          頁之單據 (即經戊○○將該四只紙箱秤重後分別標明其重量之貨物收據)\n          係原始單據，並沒有隨貨送到新店站，而係由南崁站另行製作單據 (即另\n          紙由丙○○簽收之貨物收據)，該原始單據是後來才補送到新店站」等語\n          ，由此可知，證人戊○○證稱貨物經丙○○拒收退回後，伊即將之秤重云\n          云，然戊○○並未將秤重結果標明在該紙隨貨送至全南公司之貨物收據上\n          ，而係將之標明在事後始送至新店站之原始貨物收據上，則被告質疑高錦\n          隆並非於拒收貨物當天秤重而係事後所為，非無可能；且觀該八十八年十\n          月四日之貨物收據上業經丙○○簽名收受，並蓋有付訖字樣，應即推定林\n          英麟於上揭時日已受領該批貨物，並付清運費，雖丙○○陳稱其係於大榮\n          貨運公司於八十八年十一月十八日二度送貨時經戊○○要求，始在八十八\n          年十月四日之貨物收據上補簽名，並因此不慎複寫至同年十一月十八日之\n          貨物收據上，此節雖經證人戊○○證述在卷，然丙○○既已於八十八年十\n          一月十八日之貨物收據上簽名具領，即已表示收受該批貨物，殊無必要重\n          複在曾經其拒收之八十八年十月四日貨物收據上簽名收受，而丙○○既拒\n          收八十八年十月四日送達之貨物，亦應註明拒收才是，焉有再重行補簽之\n          理，所為顯不合常情之至，而因該八十八年十一月十八日貨物收據上之「\n          丙○○」字樣之複寫字跡過於模糊，是否係丙○○於八十八年十月四日之\n          貨物收據上簽名時複寫所造成，亦無從比對，是尚乏據足認丙○○於八十\n          八年十月四日貨物收據上之簽名確係於同年十一月十八日補簽而非於八十\n          八年十月四日送貨時所簽收。\n    （二）其次觀諸卷附丙○○於本院九十年七月十一日開庭時提出之八十八年十月\n          四日收貨照片、台灣台北地方法院檢察署八八年偵字第二六九八八號偵查\n          卷附刑案現場照片所示於八十八年十一月十八日拍攝之貨物照片、被告提\n          出卷附大榮貨運公司前來收貨前所拍攝之貨物外觀相片以查，大榮貨運公\n          司前往九五公司收貨前，該四只紙箱以紅色繩索綑綁之方式係每面重複以\n          兩條繩索捆綁，包裝整齊牢靠，明顯與丙○○提出之八十八年十月四日收\n          貨相片及八十八年十一月十八日刑案現場相片所示紙箱之綁法均僅以一條\n          繩索綁成十字形，包裝較為鬆散不同，可見上開紙箱曾有遭開啟後再予回\n          復之情形，且收貨前紙箱之外觀包裝良好並無破損，然該紙箱於八十八年\n          十一月十八日再度送達時其外觀包裝卻破損凌亂不堪，是被告質疑上開紙\n          箱有遭人開啟後將內容物掉包之情形，要非無稽。\n    （三）九五公司於八十八年七月二十三日向全南公司訂購如卷附訂貨單所示九種\n          規格之鐵弗龍油壓缸，其重量究竟為何，經被告提出與上開訂貨單相同規\n          格分別由名超企業有限公司、宏庫貿易有限公司、華郁塑膠有限公司、中\n          壢電木企業有限公司所出具之鐵弗龍油壓缸報價單及發票一份（參卷附刑\n          證三）所示，最輕者為○‧七三公斤、最重者為一‧四公斤，一百支總重\n          約一○○‧二公斤；而該等油壓缸之體積據被告於本院供稱：訂貨單「內\n          徑六五」是指六‧五公分，「行程一百」是指十公分，行程是指缸體內徑\n          之長度，油壓缸全長是二十公分，九種規格長度都一樣，只有內徑不一樣\n          等語。而經被告將其向上開四家廠商訂購之一百支鐵弗龍油壓缸以卷附四\n          只紙箱實際裝箱結果，確可容納一節，亦有被告於本院九十年七月十一日\n          庭訊時提出相片一紙附卷可憑。另據證人丁○○於偵訊時證稱：被告退貨\n          其中有兩件較重，老闆幫我搬，四箱是小姐幫我搬，一才約十公斤，以體\n          積哪個大或重量哪個重，就以較大或較重的為計算標準，四箱重量當時沒\n          有秤重，但感覺特別輕，是我要搬下貨才知道等語，有如前述，另證人林\n          柏青於本院證稱：「丁○○去收貨，當天是四個箱子，二個機台，一才十\n          公斤，兩個機台各約三十幾公斤，算七才，四個箱子每個約兩才，一才體\n          積是七尺立方」等語，丁○○於收貨時既不清楚紙箱重量，則其如何得知\n          應以體積或重量為計算標準，是其稱於下貨時始知箱子這麼輕云云，顯有\n          可疑，且退貨之二座機台每座約重三十餘公斤，丁○○於收貨時亦以「才\n          」為計算標準，二座機台總共為七才，從而該四只紙箱非不可能以重量為\n          計算標準，而如以每箱二才十公斤計算，上開四只紙箱總重量為八十公斤\n          ，與上述被告所主張之一百公斤相去不遠，從而被告辯稱其所訂購之鐵弗\n          龍油壓缸重約一百公斤，而得以卷附之四只紙箱分裝完成一節，尚非無據\n          。\n    （四）末按買受人對於由他地送到之物，主張有瑕疵，不願受領者，如出賣人於\n          受領地無代理人，買受人有暫為保管之責，民法第三百五十八第一項固定\n          有明文，而依卷附銷貨單上由九五公司員工辛○○所註明之「暫收待驗」\n          字樣，究係主張送來之貨物已經發覺有瑕疵而應退貨，或有無瑕疵尚待檢\n          驗，如係前者，則被告既經發覺貨物有瑕疵，自得請託運人將貨物載回拒\n          絕受領，如係暫為保管，依同法第三百五十八條第二項規定應即依相當方\n          法證明瑕疵存在，否則推定為受領時為無瑕疵，被告於八十八年八月二十\n          三日受領後，延宕至同年九月十六日始以存證信函催告全南公司派員前來\n          檢測驗收，是被告顯未於相當時間以相當方法證明瑕疵存在，應視為已受\n          領無瑕疵之物，而本件民事部分，經全南公司向本院桃園簡易庭訴請九五\n          公司給付貨款事件，亦由本院桃園簡易庭以八十八年度桃簡字第一四八九\n          號民事判決認定全南公司已將本件貨物交付九五公司受領，有上開民事判\n          決一紙附卷可參，從而全南公司本於雙方買賣關係將本案貨物交付九五公\n          司而移轉所有權，九五公司即因交付而取得該貨物之所有權，嗣被告以全\n          南公司所交付之貨物有瑕疵而退貨，乃屬物之瑕疵擔保責任問題，要與侵\n          占罪須意圖為自己不法所有而侵占他人之物之構成要件有間。\n    （五）從而本件既有上述諸多合理之懷疑存在，致使本院無從形成有罪之確信，\n          此外復查無其他積極證據，足認被告有公訴意旨所指侵占犯行，參照前揭\n          判例意旨所揭示之「罪疑惟輕」原則，即應為被告無罪之諭知，以免冤抑\n          。\n據上論斷，應依刑事訴訟法第三百零一條第一項，判決如主文。\n本案經檢察官許炳文到庭執行職務。\n中      華      民      國      九十一      年   七     月    三十一  日\n                                臺灣桃園地方法院刑事第五庭\n                                    審判長法  官  江振義\n                                          法  官  江德民\n                                          法  官  鍾淑慧\n右正本證明與原本無異。\n如不服本判決，應於判決送達後十日內，向本院提出上訴狀。\n                                          書記官  蕭琪男\n中      華      民      國      九十一      年     八     月      五    日\n",
  "structure": {
    "main": "庚○○無罪。",
    "reason": "一、公訴意旨略以：被告庚○○係設在桃園縣蘆竹鄉○○路○段二三一巷四一號九五\n    實業有限公司（下稱九五公司）之負責人，於民國八十八年七月三十一日，向丙\n    ○○所經營設在臺北市○○區○○路三段三一０巷六弄一二號之全南企業有限公\n    司（下稱全南公司），訂購單相油壓箱二臺及鐵弗龍油壓缸一百支，價額共計新\n    臺幣十五萬八千零二十五元，俟全南公司交貨後，庚○○因發現貨有瑕疵，遂三\n    度寄發存證信函通知全南公司派員前來檢測，並主張拒絕受領，全南公司獲悉後\n    ，則寄發存證信函回絕九五公司，表示此舉如同刁難，未便所請。詎料，庚○○\n    依民法第三百五十八條第一項規定，於全南公司在桃園縣境無代理人有暫為保管\n    之責之情形下，竟意圖為自己不法之所有，以變易持有為所有之意思，將鐵弗龍\n    油壓缸一百支侵占入己。得手後，其為掩飾犯行，於同年十月四日，偽以退貨方\n    式，將四只空紙箱連同單相油壓箱二臺，委由大榮貨運汽車股份有限公司（下稱\n    大榮貨運公司）載至全南公司，惟因全南公司售予九五公司之鐵弗龍油壓缸，最\n    輕規格之重量一支有八‧六公斤，一百支起碼逾八百六十公斤，且依尺寸規格不\n    可能以四只紙箱裝畢，是丙○○見到退貨後，察覺有異，並發現紙箱重量差距過\n    大而未簽收，大榮貨運公司遇此情狀僅得載回上開貨物另作拒收處理，迄同年十\n    一月十八日十三時三十五分許，大榮貨運公司二度將上開貨物載至全南公司，丙\n    ○○即請大榮貨運公司轉載至警局，嗣經當場拆封，發現紙箱內除報紙外空無一\n    物，方查悉上情，並訴警究辦。因認被告庚○○涉犯刑法第三百三十五條第一項\n    之侵占罪嫌等語。\n二、按按犯罪事實，應依證據認定之，無證據不得推定其犯罪事實；又不能證明被告\n    犯罪者，應諭知無罪之判決，刑事訴訟法第一百五十四條、第三百零一條第一項\n    分別定有明文。再所謂認定犯罪事實之證據，係指足以認定被告確有犯罪行為之\n    積極證據而言，如未發現相當證據，或證據不足以證明，自不能以推測或擬制之\n    方法，以為裁判基礎。且刑事訴訟上證明之資料，無論其為直接證據或間接證據\n    ，均須達於通常一般人均不致於有所懷疑，而得確信其為真實之程度，始得據為\n    有罪之認定，若其關於被告是否犯罪之證明未能達此程度，而有合理性懷疑之存\n    在，致使無從形成有罪之確信，根據「罪證有疑，利於被告」之證據法則，即不\n    得遽為不利被告之認定，其以情況證據（即間接證據）斷罪時，尤須基於該證據\n    在直接關係上所可證明之他項情況事實，本乎推理作用足以確證被告有罪，方為\n    合法，不得徒憑主觀上之推想，將一般經驗上有利被告之其他合理情況逕予排除\n    ，此經最高法院三十二年度上字六七號、七十六年台上字第四九八六號著有判例\n    闡述甚明。又告訴人之告訴，本以使被告受刑事訴追為目的，故其陳述是否與事\n    實相符，自應調查其他證據，以資審認，苟其所為攻擊之詞，尚有瑕疵，則在此\n    瑕疵未予究明以前，即不能遽採為斷罪之基礎。\n三、訊據被告庚○○堅詞否認涉有上揭侵占犯行，辯稱：伊於八十八年七月三十一日\n    向全南公司負責人丙○○訂購一百支鐵弗龍油壓缸，惟於同年八月二十三日收到\n    該批貨物後，發現其品質不良，不堪使用，經通知告訴人處理，亦未獲理會，乃\n    囑咐員工甲○○、辛○○二人將該總重約一百公斤之鐵弗龍油壓缸，以四紙箱分\n    裝後託由大榮貨運公司送貨退還予全南公司，詎丙○○於同年十月四日收到該批\n    退貨後，竟私自將箱內之鐵弗龍油壓缸取出，再將紙箱復原，經一個多月後始於\n    同年十一月十八日濫行指控伊退回之貨物為空箱，實則並無侵占之事實，且告訴\n    人依買賣關係將上開貨物交付與伊，伊即取得該貨物之所有權，嗣因該批貨物有\n    瑕疵而將之退還，要屬是否應負物之瑕疵擔保責任之民事問題，核與侵占罪之構\n    成要件尚屬有間等語。經查公訴人認被告涉有上揭侵占犯行，無非以告訴人全南\n    公司代理人丙○○之指訴、證人即八十八年十月四日前往九五公司載運退貨之大\n    榮貨運公司南崁站員工丁○○、當日將退貨載至全南公司之大榮貨運公司新店站\n    職員己○○、全南公司拒收後處理退貨之大榮公司南崁站副主任乙○○、同年十\n    一月十八日二度將退貨載至全南公司之大榮貨運公司新店站副主任戊○○之證詞\n    ，又據告訴人指稱該鐵弗龍油壓缸最輕規格之重量一支有六‧八公斤，以此計算\n    ，一百支逾六百八十公斤，顯不可能以卷附相片所拍攝之四只紙箱裝畢，且縱以\n    被告所主張之規格最輕者○‧七三公斤計算，一百支亦有七十三公斤，與證人戊\n    ○○於全南公司拒收後將四只紙箱秤重僅七公斤，二者重量相差懸殊，被告所辯\n    顯不足採等情資為論據。惟查：\n    （一）據告訴人之代表人丙○○於偵查中指稱：該鐵弗龍油壓缸有九種規格，其\n          中最輕一支為八‧六公斤（台灣桃園地方法院檢察署八十九年度偵字第三\n          二六五號偵查卷第八十二頁反面）、於本院陳稱：最重的有二六‧五公斤\n          等語，另於本院桃園簡易庭八十九年十月十一日審理時陳稱：一百支油壓\n          缸之總重量是一千六百三十一公斤等語（參卷附八十八年桃簡字第一四八\n          九號民事卷宗第八十三頁），並於台灣台北地方法院檢察署檢察官於八十\n          九年一月七日偵訊時提出該二六‧五公斤重、長三十七公分之油壓缸相片\n          一張附卷（見同日訊問筆錄），另關於油壓缸之體積，據其於本院陳稱：\n          行程一百之長度如同被告所言，但如果內徑不一樣，長度也會不一樣，伊\n          之前於偵查中所提出的，是內徑七五、行程一百的等語。是由丙○○所陳\n          ，一百支鐵弗龍油壓缸之總重量有一千六百三十一公斤，然據證人即八十\n          八年十月四日前往九五公司載運退貨之大榮貨運公司司機丁○○於八十九\n          年一月十七日偵訊時證稱：「被告退貨計有六件，其中有兩件較重，老闆\n          幫我搬，四箱是小姐幫我搬，一才約十公斤，以體積哪個大或重量哪個重\n          ，就以較大或較重的為計算標準」等語，於同年八月十六日偵訊時證稱：\n          「四箱重量當時沒有秤重，但感覺特別輕，是我要搬下貨才知道」等語；\n          次據證人即將退貨載至全南公司之大榮貨運公司新店站職員己○○於八十\n          九年九月四日偵訊時證稱：「送去時因貨很輕，丙○○拒收，他有照相，\n          物件未離開我視線，也未拆封，因他沒簽收，我就將貨載回」等語；另全\n          南公司拒收後處理退貨之大榮貨運公司南崁站主任乙○○於八十九年八月\n          十六日偵訊時證稱：「十月四日丙○○拒收，新店站聯絡我說發生退貨情\n          事，我就聯絡九五公司如何處理，他們說將貨放在全南公司門口即可，因\n          雙方拒收，該貨放在南崁站有一陣子，後來我聯絡台中總公司，才決定暫\n          時送至台中總公司倉儲」等語；又證人即於同年十一月十八日二度將退貨\n          載至全南公司之大榮貨運公司新店站副主任戊○○於八十九年一月七日偵\n          訊時證稱：「十月四日己○○送貨至全南公司，經其回報說丙○○稱貨有\n          問題，四箱很輕，拒收，我說做拒收處理，同日貨送回來後，丙○○要求\n          我們秤重量，我立刻回報南崁站，並將貨退回南崁站，並通知總公司，十\n          一月十七日貨從台中寄出，十八日寄到新店站，我問丙○○貨送到哪，他\n          說送派出所，下貨前請丙○○簽收，運費交給我」等語，另經證人戊○○\n          秤重結果該四只紙箱之重量分別為三公斤、一公斤、二公斤、一公斤，有\n          卷附貨物收據一紙附卷可稽，是由上以查，該批貨物之總重如係達一千六\n          百三十一公斤，無論在體積及重量上，皆不可能以卷附四只紙箱裝載完成\n          ，亦不可能僅由一人搬動，被告如欲假退貨之名行侵占之實，豈會愚蠢至\n          以此輕易為人察覺之方式為之；而丙○○於八十八年十月四日收到上開退\n          貨後，當即知悉箱內絕非其所交付之貨品，既知預先拍照存證，何不立即\n          報警並儘速聯絡九五公司前來處理，其不此之為，反於一個多月後之同年\n          十一月十八日始聯絡大榮貨運公司將貨物直接運至派出所，實不免啟人疑\n          竇；再大榮貨運公司於全南公司認貨物有問題而拒收時，為釐清責任歸屬\n          ，避免瓜田李下，及收取應收運費，理應將貨物逕行退回託運人並由託運\n          人負擔因此所支出之一切費用，此觀卷附大榮汽車貨運股份有限公司運送\n          契約第三條明文定有拒收之處理情形甚明，乃竟不依規定而行，反將貨物\n          輾轉送至台中總公司存放達一個多月，其處置情形亦堪置疑；繼觀之卷附\n          由大榮貨運公司於八十八年十月四日所出具之貨物收據竟有二種不同之版\n          本，據證人即大榮貨運公司南崁站站長廖文章於本院民事庭承審法官於九\n          十年五月十七日前往大榮貨運南崁站履勘時證稱：「簡易庭卷宗第八十一\n          頁之單據 (即經戊○○將該四只紙箱秤重後分別標明其重量之貨物收據)\n          係原始單據，並沒有隨貨送到新店站，而係由南崁站另行製作單據 (即另\n          紙由丙○○簽收之貨物收據)，該原始單據是後來才補送到新店站」等語\n          ，由此可知，證人戊○○證稱貨物經丙○○拒收退回後，伊即將之秤重云\n          云，然戊○○並未將秤重結果標明在該紙隨貨送至全南公司之貨物收據上\n          ，而係將之標明在事後始送至新店站之原始貨物收據上，則被告質疑高錦\n          隆並非於拒收貨物當天秤重而係事後所為，非無可能；且觀該八十八年十\n          月四日之貨物收據上業經丙○○簽名收受，並蓋有付訖字樣，應即推定林\n          英麟於上揭時日已受領該批貨物，並付清運費，雖丙○○陳稱其係於大榮\n          貨運公司於八十八年十一月十八日二度送貨時經戊○○要求，始在八十八\n          年十月四日之貨物收據上補簽名，並因此不慎複寫至同年十一月十八日之\n          貨物收據上，此節雖經證人戊○○證述在卷，然丙○○既已於八十八年十\n          一月十八日之貨物收據上簽名具領，即已表示收受該批貨物，殊無必要重\n          複在曾經其拒收之八十八年十月四日貨物收據上簽名收受，而丙○○既拒\n          收八十八年十月四日送達之貨物，亦應註明拒收才是，焉有再重行補簽之\n          理，所為顯不合常情之至，而因該八十八年十一月十八日貨物收據上之「\n          丙○○」字樣之複寫字跡過於模糊，是否係丙○○於八十八年十月四日之\n          貨物收據上簽名時複寫所造成，亦無從比對，是尚乏據足認丙○○於八十\n          八年十月四日貨物收據上之簽名確係於同年十一月十八日補簽而非於八十\n          八年十月四日送貨時所簽收。\n    （二）其次觀諸卷附丙○○於本院九十年七月十一日開庭時提出之八十八年十月\n          四日收貨照片、台灣台北地方法院檢察署八八年偵字第二六九八八號偵查\n          卷附刑案現場照片所示於八十八年十一月十八日拍攝之貨物照片、被告提\n          出卷附大榮貨運公司前來收貨前所拍攝之貨物外觀相片以查，大榮貨運公\n          司前往九五公司收貨前，該四只紙箱以紅色繩索綑綁之方式係每面重複以\n          兩條繩索捆綁，包裝整齊牢靠，明顯與丙○○提出之八十八年十月四日收\n          貨相片及八十八年十一月十八日刑案現場相片所示紙箱之綁法均僅以一條\n          繩索綁成十字形，包裝較為鬆散不同，可見上開紙箱曾有遭開啟後再予回\n          復之情形，且收貨前紙箱之外觀包裝良好並無破損，然該紙箱於八十八年\n          十一月十八日再度送達時其外觀包裝卻破損凌亂不堪，是被告質疑上開紙\n          箱有遭人開啟後將內容物掉包之情形，要非無稽。\n    （三）九五公司於八十八年七月二十三日向全南公司訂購如卷附訂貨單所示九種\n          規格之鐵弗龍油壓缸，其重量究竟為何，經被告提出與上開訂貨單相同規\n          格分別由名超企業有限公司、宏庫貿易有限公司、華郁塑膠有限公司、中\n          壢電木企業有限公司所出具之鐵弗龍油壓缸報價單及發票一份（參卷附刑\n          證三）所示，最輕者為○‧七三公斤、最重者為一‧四公斤，一百支總重\n          約一○○‧二公斤；而該等油壓缸之體積據被告於本院供稱：訂貨單「內\n          徑六五」是指六‧五公分，「行程一百」是指十公分，行程是指缸體內徑\n          之長度，油壓缸全長是二十公分，九種規格長度都一樣，只有內徑不一樣\n          等語。而經被告將其向上開四家廠商訂購之一百支鐵弗龍油壓缸以卷附四\n          只紙箱實際裝箱結果，確可容納一節，亦有被告於本院九十年七月十一日\n          庭訊時提出相片一紙附卷可憑。另據證人丁○○於偵訊時證稱：被告退貨\n          其中有兩件較重，老闆幫我搬，四箱是小姐幫我搬，一才約十公斤，以體\n          積哪個大或重量哪個重，就以較大或較重的為計算標準，四箱重量當時沒\n          有秤重，但感覺特別輕，是我要搬下貨才知道等語，有如前述，另證人林\n          柏青於本院證稱：「丁○○去收貨，當天是四個箱子，二個機台，一才十\n          公斤，兩個機台各約三十幾公斤，算七才，四個箱子每個約兩才，一才體\n          積是七尺立方」等語，丁○○於收貨時既不清楚紙箱重量，則其如何得知\n          應以體積或重量為計算標準，是其稱於下貨時始知箱子這麼輕云云，顯有\n          可疑，且退貨之二座機台每座約重三十餘公斤，丁○○於收貨時亦以「才\n          」為計算標準，二座機台總共為七才，從而該四只紙箱非不可能以重量為\n          計算標準，而如以每箱二才十公斤計算，上開四只紙箱總重量為八十公斤\n          ，與上述被告所主張之一百公斤相去不遠，從而被告辯稱其所訂購之鐵弗\n          龍油壓缸重約一百公斤，而得以卷附之四只紙箱分裝完成一節，尚非無據\n          。\n    （四）末按買受人對於由他地送到之物，主張有瑕疵，不願受領者，如出賣人於\n          受領地無代理人，買受人有暫為保管之責，民法第三百五十八第一項固定\n          有明文，而依卷附銷貨單上由九五公司員工辛○○所註明之「暫收待驗」\n          字樣，究係主張送來之貨物已經發覺有瑕疵而應退貨，或有無瑕疵尚待檢\n          驗，如係前者，則被告既經發覺貨物有瑕疵，自得請託運人將貨物載回拒\n          絕受領，如係暫為保管，依同法第三百五十八條第二項規定應即依相當方\n          法證明瑕疵存在，否則推定為受領時為無瑕疵，被告於八十八年八月二十\n          三日受領後，延宕至同年九月十六日始以存證信函催告全南公司派員前來\n          檢測驗收，是被告顯未於相當時間以相當方法證明瑕疵存在，應視為已受\n          領無瑕疵之物，而本件民事部分，經全南公司向本院桃園簡易庭訴請九五\n          公司給付貨款事件，亦由本院桃園簡易庭以八十八年度桃簡字第一四八九\n          號民事判決認定全南公司已將本件貨物交付九五公司受領，有上開民事判\n          決一紙附卷可參，從而全南公司本於雙方買賣關係將本案貨物交付九五公\n          司而移轉所有權，九五公司即因交付而取得該貨物之所有權，嗣被告以全\n          南公司所交付之貨物有瑕疵而退貨，乃屬物之瑕疵擔保責任問題，要與侵\n          占罪須意圖為自己不法所有而侵占他人之物之構成要件有間。\n    （五）從而本件既有上述諸多合理之懷疑存在，致使本院無從形成有罪之確信，\n          此外復查無其他積極證據，足認被告有公訴意旨所指侵占犯行，參照前揭\n          判例意旨所揭示之「罪疑惟輕」原則，即應為被告無罪之諭知，以免冤抑\n          。\n據上論斷，應依刑事訴訟法第三百零一條第一項，判決如主文。\n本案經檢察官許炳文到庭執行職務。"
  },
  "search": "臺灣桃園地方法院刑事判決九十年度易字第一三八號公訴人臺灣桃園地方法院檢察署檢察官被告庚○○選任辯護人何啟熏律師沈明達律師右列被告因侵占案件，經檢察官提起公訴（八十九年度偵字第三二六五號），本院判決如左：主文庚○○無罪。理由一、公訴意旨略以：被告庚○○係設在桃園縣蘆竹鄉○○路○段二三一巷四一號九五實業有限公司（下稱九五公司）之負責人，於民國八十八年七月三十一日，向丙○○所經營設在臺北市○○區○○路三段三一０巷六弄一二號之全南企業有限公司（下稱全南公司），訂購單相油壓箱二臺及鐵弗龍油壓缸一百支，價額共計新臺幣十五萬八千零二十五元，俟全南公司交貨後，庚○○因發現貨有瑕疵，遂三度寄發存證信函通知全南公司派員前來檢測，並主張拒絕受領，全南公司獲悉後，則寄發存證信函回絕九五公司，表示此舉如同刁難，未便所請。詎料，庚○○依民法第三百五十八條第一項規定，於全南公司在桃園縣境無代理人有暫為保管之責之情形下，竟意圖為自己不法之所有，以變易持有為所有之意思，將鐵弗龍油壓缸一百支侵占入己。得手後，其為掩飾犯行，於同年十月四日，偽以退貨方式，將四只空紙箱連同單相油壓箱二臺，委由大榮貨運汽車股份有限公司（下稱大榮貨運公司）載至全南公司，惟因全南公司售予九五公司之鐵弗龍油壓缸，最輕規格之重量一支有八‧六公斤，一百支起碼逾八百六十公斤，且依尺寸規格不可能以四只紙箱裝畢，是丙○○見到退貨後，察覺有異，並發現紙箱重量差距過大而未簽收，大榮貨運公司遇此情狀僅得載回上開貨物另作拒收處理，迄同年十一月十八日十三時三十五分許，大榮貨運公司二度將上開貨物載至全南公司，丙○○即請大榮貨運公司轉載至警局，嗣經當場拆封，發現紙箱內除報紙外空無一物，方查悉上情，並訴警究辦。因認被告庚○○涉犯刑法第三百三十五條第一項之侵占罪嫌等語。二、按按犯罪事實，應依證據認定之，無證據不得推定其犯罪事實；又不能證明被告犯罪者，應諭知無罪之判決，刑事訴訟法第一百五十四條、第三百零一條第一項分別定有明文。再所謂認定犯罪事實之證據，係指足以認定被告確有犯罪行為之積極證據而言，如未發現相當證據，或證據不足以證明，自不能以推測或擬制之方法，以為裁判基礎。且刑事訴訟上證明之資料，無論其為直接證據或間接證據，均須達於通常一般人均不致於有所懷疑，而得確信其為真實之程度，始得據為有罪之認定，若其關於被告是否犯罪之證明未能達此程度，而有合理性懷疑之存在，致使無從形成有罪之確信，根據「罪證有疑，利於被告」之證據法則，即不得遽為不利被告之認定，其以情況證據（即間接證據）斷罪時，尤須基於該證據在直接關係上所可證明之他項情況事實，本乎推理作用足以確證被告有罪，方為合法，不得徒憑主觀上之推想，將一般經驗上有利被告之其他合理情況逕予排除，此經最高法院三十二年度上字六七號、七十六年台上字第四九八六號著有判例闡述甚明。又告訴人之告訴，本以使被告受刑事訴追為目的，故其陳述是否與事實相符，自應調查其他證據，以資審認，苟其所為攻擊之詞，尚有瑕疵，則在此瑕疵未予究明以前，即不能遽採為斷罪之基礎。三、訊據被告庚○○堅詞否認涉有上揭侵占犯行，辯稱：伊於八十八年七月三十一日向全南公司負責人丙○○訂購一百支鐵弗龍油壓缸，惟於同年八月二十三日收到該批貨物後，發現其品質不良，不堪使用，經通知告訴人處理，亦未獲理會，乃囑咐員工甲○○、辛○○二人將該總重約一百公斤之鐵弗龍油壓缸，以四紙箱分裝後託由大榮貨運公司送貨退還予全南公司，詎丙○○於同年十月四日收到該批退貨後，竟私自將箱內之鐵弗龍油壓缸取出，再將紙箱復原，經一個多月後始於同年十一月十八日濫行指控伊退回之貨物為空箱，實則並無侵占之事實，且告訴人依買賣關係將上開貨物交付與伊，伊即取得該貨物之所有權，嗣因該批貨物有瑕疵而將之退還，要屬是否應負物之瑕疵擔保責任之民事問題，核與侵占罪之構成要件尚屬有間等語。經查公訴人認被告涉有上揭侵占犯行，無非以告訴人全南公司代理人丙○○之指訴、證人即八十八年十月四日前往九五公司載運退貨之大榮貨運公司南崁站員工丁○○、當日將退貨載至全南公司之大榮貨運公司新店站職員己○○、全南公司拒收後處理退貨之大榮公司南崁站副主任乙○○、同年十一月十八日二度將退貨載至全南公司之大榮貨運公司新店站副主任戊○○之證詞，又據告訴人指稱該鐵弗龍油壓缸最輕規格之重量一支有六‧八公斤，以此計算，一百支逾六百八十公斤，顯不可能以卷附相片所拍攝之四只紙箱裝畢，且縱以被告所主張之規格最輕者○‧七三公斤計算，一百支亦有七十三公斤，與證人戊○○於全南公司拒收後將四只紙箱秤重僅七公斤，二者重量相差懸殊，被告所辯顯不足採等情資為論據。惟查：（一）據告訴人之代表人丙○○於偵查中指稱：該鐵弗龍油壓缸有九種規格，其中最輕一支為八‧六公斤（台灣桃園地方法院檢察署八十九年度偵字第三二六五號偵查卷第八十二頁反面）、於本院陳稱：最重的有二六‧五公斤等語，另於本院桃園簡易庭八十九年十月十一日審理時陳稱：一百支油壓缸之總重量是一千六百三十一公斤等語（參卷附八十八年桃簡字第一四八九號民事卷宗第八十三頁），並於台灣台北地方法院檢察署檢察官於八十九年一月七日偵訊時提出該二六‧五公斤重、長三十七公分之油壓缸相片一張附卷（見同日訊問筆錄），另關於油壓缸之體積，據其於本院陳稱：行程一百之長度如同被告所言，但如果內徑不一樣，長度也會不一樣，伊之前於偵查中所提出的，是內徑七五、行程一百的等語。是由丙○○所陳，一百支鐵弗龍油壓缸之總重量有一千六百三十一公斤，然據證人即八十八年十月四日前往九五公司載運退貨之大榮貨運公司司機丁○○於八十九年一月十七日偵訊時證稱：「被告退貨計有六件，其中有兩件較重，老闆幫我搬，四箱是小姐幫我搬，一才約十公斤，以體積哪個大或重量哪個重，就以較大或較重的為計算標準」等語，於同年八月十六日偵訊時證稱：「四箱重量當時沒有秤重，但感覺特別輕，是我要搬下貨才知道」等語；次據證人即將退貨載至全南公司之大榮貨運公司新店站職員己○○於八十九年九月四日偵訊時證稱：「送去時因貨很輕，丙○○拒收，他有照相，物件未離開我視線，也未拆封，因他沒簽收，我就將貨載回」等語；另全南公司拒收後處理退貨之大榮貨運公司南崁站主任乙○○於八十九年八月十六日偵訊時證稱：「十月四日丙○○拒收，新店站聯絡我說發生退貨情事，我就聯絡九五公司如何處理，他們說將貨放在全南公司門口即可，因雙方拒收，該貨放在南崁站有一陣子，後來我聯絡台中總公司，才決定暫時送至台中總公司倉儲」等語；又證人即於同年十一月十八日二度將退貨載至全南公司之大榮貨運公司新店站副主任戊○○於八十九年一月七日偵訊時證稱：「十月四日己○○送貨至全南公司，經其回報說丙○○稱貨有問題，四箱很輕，拒收，我說做拒收處理，同日貨送回來後，丙○○要求我們秤重量，我立刻回報南崁站，並將貨退回南崁站，並通知總公司，十一月十七日貨從台中寄出，十八日寄到新店站，我問丙○○貨送到哪，他說送派出所，下貨前請丙○○簽收，運費交給我」等語，另經證人戊○○秤重結果該四只紙箱之重量分別為三公斤、一公斤、二公斤、一公斤，有卷附貨物收據一紙附卷可稽，是由上以查，該批貨物之總重如係達一千六百三十一公斤，無論在體積及重量上，皆不可能以卷附四只紙箱裝載完成，亦不可能僅由一人搬動，被告如欲假退貨之名行侵占之實，豈會愚蠢至以此輕易為人察覺之方式為之；而丙○○於八十八年十月四日收到上開退貨後，當即知悉箱內絕非其所交付之貨品，既知預先拍照存證，何不立即報警並儘速聯絡九五公司前來處理，其不此之為，反於一個多月後之同年十一月十八日始聯絡大榮貨運公司將貨物直接運至派出所，實不免啟人疑竇；再大榮貨運公司於全南公司認貨物有問題而拒收時，為釐清責任歸屬，避免瓜田李下，及收取應收運費，理應將貨物逕行退回託運人並由託運人負擔因此所支出之一切費用，此觀卷附大榮汽車貨運股份有限公司運送契約第三條明文定有拒收之處理情形甚明，乃竟不依規定而行，反將貨物輾轉送至台中總公司存放達一個多月，其處置情形亦堪置疑；繼觀之卷附由大榮貨運公司於八十八年十月四日所出具之貨物收據竟有二種不同之版本，據證人即大榮貨運公司南崁站站長廖文章於本院民事庭承審法官於九十年五月十七日前往大榮貨運南崁站履勘時證稱：「簡易庭卷宗第八十一頁之單據(即經戊○○將該四只紙箱秤重後分別標明其重量之貨物收據)係原始單據，並沒有隨貨送到新店站，而係由南崁站另行製作單據(即另紙由丙○○簽收之貨物收據)，該原始單據是後來才補送到新店站」等語，由此可知，證人戊○○證稱貨物經丙○○拒收退回後，伊即將之秤重云云，然戊○○並未將秤重結果標明在該紙隨貨送至全南公司之貨物收據上，而係將之標明在事後始送至新店站之原始貨物收據上，則被告質疑高錦隆並非於拒收貨物當天秤重而係事後所為，非無可能；且觀該八十八年十月四日之貨物收據上業經丙○○簽名收受，並蓋有付訖字樣，應即推定林英麟於上揭時日已受領該批貨物，並付清運費，雖丙○○陳稱其係於大榮貨運公司於八十八年十一月十八日二度送貨時經戊○○要求，始在八十八年十月四日之貨物收據上補簽名，並因此不慎複寫至同年十一月十八日之貨物收據上，此節雖經證人戊○○證述在卷，然丙○○既已於八十八年十一月十八日之貨物收據上簽名具領，即已表示收受該批貨物，殊無必要重複在曾經其拒收之八十八年十月四日貨物收據上簽名收受，而丙○○既拒收八十八年十月四日送達之貨物，亦應註明拒收才是，焉有再重行補簽之理，所為顯不合常情之至，而因該八十八年十一月十八日貨物收據上之「丙○○」字樣之複寫字跡過於模糊，是否係丙○○於八十八年十月四日之貨物收據上簽名時複寫所造成，亦無從比對，是尚乏據足認丙○○於八十八年十月四日貨物收據上之簽名確係於同年十一月十八日補簽而非於八十八年十月四日送貨時所簽收。（二）其次觀諸卷附丙○○於本院九十年七月十一日開庭時提出之八十八年十月四日收貨照片、台灣台北地方法院檢察署八八年偵字第二六九八八號偵查卷附刑案現場照片所示於八十八年十一月十八日拍攝之貨物照片、被告提出卷附大榮貨運公司前來收貨前所拍攝之貨物外觀相片以查，大榮貨運公司前往九五公司收貨前，該四只紙箱以紅色繩索綑綁之方式係每面重複以兩條繩索捆綁，包裝整齊牢靠，明顯與丙○○提出之八十八年十月四日收貨相片及八十八年十一月十八日刑案現場相片所示紙箱之綁法均僅以一條繩索綁成十字形，包裝較為鬆散不同，可見上開紙箱曾有遭開啟後再予回復之情形，且收貨前紙箱之外觀包裝良好並無破損，然該紙箱於八十八年十一月十八日再度送達時其外觀包裝卻破損凌亂不堪，是被告質疑上開紙箱有遭人開啟後將內容物掉包之情形，要非無稽。（三）九五公司於八十八年七月二十三日向全南公司訂購如卷附訂貨單所示九種規格之鐵弗龍油壓缸，其重量究竟為何，經被告提出與上開訂貨單相同規格分別由名超企業有限公司、宏庫貿易有限公司、華郁塑膠有限公司、中壢電木企業有限公司所出具之鐵弗龍油壓缸報價單及發票一份（參卷附刑證三）所示，最輕者為○‧七三公斤、最重者為一‧四公斤，一百支總重約一○○‧二公斤；而該等油壓缸之體積據被告於本院供稱：訂貨單「內徑六五」是指六‧五公分，「行程一百」是指十公分，行程是指缸體內徑之長度，油壓缸全長是二十公分，九種規格長度都一樣，只有內徑不一樣等語。而經被告將其向上開四家廠商訂購之一百支鐵弗龍油壓缸以卷附四只紙箱實際裝箱結果，確可容納一節，亦有被告於本院九十年七月十一日庭訊時提出相片一紙附卷可憑。另據證人丁○○於偵訊時證稱：被告退貨其中有兩件較重，老闆幫我搬，四箱是小姐幫我搬，一才約十公斤，以體積哪個大或重量哪個重，就以較大或較重的為計算標準，四箱重量當時沒有秤重，但感覺特別輕，是我要搬下貨才知道等語，有如前述，另證人林柏青於本院證稱：「丁○○去收貨，當天是四個箱子，二個機台，一才十公斤，兩個機台各約三十幾公斤，算七才，四個箱子每個約兩才，一才體積是七尺立方」等語，丁○○於收貨時既不清楚紙箱重量，則其如何得知應以體積或重量為計算標準，是其稱於下貨時始知箱子這麼輕云云，顯有可疑，且退貨之二座機台每座約重三十餘公斤，丁○○於收貨時亦以「才」為計算標準，二座機台總共為七才，從而該四只紙箱非不可能以重量為計算標準，而如以每箱二才十公斤計算，上開四只紙箱總重量為八十公斤，與上述被告所主張之一百公斤相去不遠，從而被告辯稱其所訂購之鐵弗龍油壓缸重約一百公斤，而得以卷附之四只紙箱分裝完成一節，尚非無據。（四）末按買受人對於由他地送到之物，主張有瑕疵，不願受領者，如出賣人於受領地無代理人，買受人有暫為保管之責，民法第三百五十八第一項固定有明文，而依卷附銷貨單上由九五公司員工辛○○所註明之「暫收待驗」字樣，究係主張送來之貨物已經發覺有瑕疵而應退貨，或有無瑕疵尚待檢驗，如係前者，則被告既經發覺貨物有瑕疵，自得請託運人將貨物載回拒絕受領，如係暫為保管，依同法第三百五十八條第二項規定應即依相當方法證明瑕疵存在，否則推定為受領時為無瑕疵，被告於八十八年八月二十三日受領後，延宕至同年九月十六日始以存證信函催告全南公司派員前來檢測驗收，是被告顯未於相當時間以相當方法證明瑕疵存在，應視為已受領無瑕疵之物，而本件民事部分，經全南公司向本院桃園簡易庭訴請九五公司給付貨款事件，亦由本院桃園簡易庭以八十八年度桃簡字第一四八九號民事判決認定全南公司已將本件貨物交付九五公司受領，有上開民事判決一紙附卷可參，從而全南公司本於雙方買賣關係將本案貨物交付九五公司而移轉所有權，九五公司即因交付而取得該貨物之所有權，嗣被告以全南公司所交付之貨物有瑕疵而退貨，乃屬物之瑕疵擔保責任問題，要與侵占罪須意圖為自己不法所有而侵占他人之物之構成要件有間。（五）從而本件既有上述諸多合理之懷疑存在，致使本院無從形成有罪之確信，此外復查無其他積極證據，足認被告有公訴意旨所指侵占犯行，參照前揭判例意旨所揭示之「罪疑惟輕」原則，即應為被告無罪之諭知，以免冤抑。據上論斷，應依刑事訴訟法第三百零一條第一項，判決如主文。本案經檢察官許炳文到庭執行職務。中華民國九十一年七月三十一日臺灣桃園地方法院刑事第五庭審判長法官江振義法官江德民法官鍾淑慧右正本證明與原本無異。如不服本判決，應於判決送達後十日內，向本院提出上訴狀。書記官蕭琪男中華民國九十一年八月五日",
  "characters": {
    "judges": [
      "江振義",
      "江德民",
      "鍾淑慧"
    ],
    "prosecutors": [
      "許炳文"
    ],
    "lawyers": [
      "何啟熏",
      "沈明達"
    ],
    "clerks": [
      "蕭琪男"
    ],
    "plaintiffs": [

    ],
    "defendants": [
      "庚○○"
    ],
    "prosecutor_office": [
      "臺灣桃園地方法院檢察署檢察官"
    ],
    "creditors": [

    ],
    "debtors": [

    ],
    "judicial_associate_officer": [

    ]
  },
  "adjudged_at": "2002-07-31",
  "created_at": "2016-02-05 17:45:33",
  "updated_at": "2016-02-05 17:45:33"
}