{
  "identify": "ULD-99-除-150-20110106-1",
  "court": {
    "name": "臺灣雲林地方法院",
    "code": "ULD"
  },
  "division": {
    "name": "民事",
    "code": "V"
  },
  "year": 99,
  "word": "除",
  "number": "150",
  "jcheck": "1",
  "reason": "除權判決",
  "content": "臺灣雲林地方法院民事判決               99年度除字第150號\n聲  請  人  李世乾\n上列聲請人聲請除權判決事件，本院判決如下：\n    主  文\n附表所示之證券無效。\n程序費用由聲請人負擔。\n    理  由\n一、上開證券經本院以99年度司催字第76號公示催告在案。\n二、所定申報權利期間已於民國99年12月15日屆滿，迄今無人申\n    報權利。\n三、依民事訴訟法第564 條第1 項、第549 條之1 前段，判決如\n    主文。\n中    華    民    國   100    年    1     月    6     日\n                  民事第二庭    法  官  蔡碧蓉\n以上正本係照原本作成。\n本判決不得上訴。\n中    華    民    國   100    年    1     月    6     日\n                                書記官  蘇紋泙\n┌───────────────────────────────────────────────────────┐\n│附表：                                                                                      99年度除字第150 號│\n├─┬─────────┬─────────┬───────────┬─────────┬────────┬──┤\n│編│  發    票    人  │  付    款    人  │發        票        日│票面金額（新台幣）│ 支  票  號  碼 │備考│\n│號│                  │                  │                      │                  │                │    │\n├─┼─────────┼─────────┼───────────┼─────────┼────────┼──┤\n│01│堯溢企業有限公司黃│兆豐銀行斗六分行  │99年5月31日           │12,350元          │１０４３９５    │    │\n│  │榮華              │                  │                      │                  │                │    │\n└─┴─────────┴─────────┴───────────┴─────────┴────────┴──┘",
  "structure": {
    "main": "附表所示之證券無效。\n程序費用由聲請人負擔。",
    "reason": "一、上開證券經本院以99年度司催字第76號公示催告在案。\n二、所定申報權利期間已於民國99年12月15日屆滿，迄今無人申\n    報權利。\n三、依民事訴訟法第564 條第1 項、第549 條之1 前段，判決如\n    主文。"
  },
  "search": "臺灣雲林地方法院民事判決99年度除字第150號聲請人李世乾上列聲請人聲請除權判決事件，本院判決如下：主文附表所示之證券無效。程序費用由聲請人負擔。理由一、上開證券經本院以99年度司催字第76號公示催告在案。二、所定申報權利期間已於民國99年12月15日屆滿，迄今無人申報權利。三、依民事訴訟法第564條第1項、第549條之1前段，判決如主文。中華民國100年1月6日民事第二庭法官蔡碧蓉以上正本係照原本作成。本判決不得上訴。中華民國100年1月6日書記官蘇紋泙┌───────────────────────────────────────────────────────┐│附表：99年度除字第150號│├─┬─────────┬─────────┬───────────┬─────────┬────────┬──┤│編│發票人│付款人│發票日│票面金額（新台幣）│支票號碼│備考││號│││││││├─┼─────────┼─────────┼───────────┼─────────┼────────┼──┤│01│堯溢企業有限公司黃│兆豐銀行斗六分行│99年5月31日│12,350元│１０４３９５││││榮華││││││└─┴─────────┴─────────┴───────────┴─────────┴────────┴──┘",
  "characters": {
    "judges": [
      "蔡碧蓉"
    ],
    "prosecutors": [

    ],
    "lawyers": [

    ],
    "clerks": [
      "蘇紋泙"
    ],
    "plaintiffs": [

    ],
    "defendants": [

    ],
    "prosecutor_office": [
      "李世乾"
    ],
    "creditors": [

    ],
    "debtors": [

    ],
    "judicial_associate_officer": [

    ]
  },
  "adjudged_at": "2011-01-06",
  "created_at": "2016-02-13 04:18:21",
  "updated_at": "2016-02-13 04:18:21"
}