{
  "identify": "MLD-94-苗小-149-20050316-1",
  "court": {
    "name": "臺灣苗栗地方法院",
    "code": "MLD"
  },
  "division": {
    "name": "民事",
    "code": "V"
  },
  "year": 94,
  "word": "苗小",
  "number": "149",
  "jcheck": "1",
  "reason": "返還消費借貸款",
  "content": "臺灣苗栗地方法院民事小額判決         94年度苗小字第149號\n原      告  合作金庫銀行股份有限公司\n法定代理人  丁○○\n訴訟代理人  乙○○\n            甲○○\n被      告  丙○○\n上列當事人間請求返還消費借貸款事件，本院於民國94年3 月2\n日言詞辯論終結，判決如下：\n    主  文\n被告應給付原告新臺幣貳萬陸仟柒佰肆拾參元，及其中新臺幣壹\n萬伍仟玖佰肆拾貳元，自民國九十三年十二月二日起至清償日止\n，按年息百分之十四點六計算之利息，並自民國九十三年十二月\n十六日起至清償日止，按上開利息總額百分之十計算之違約金；\n其中新臺幣捌仟玖佰參拾貳元，自民國九十三年十二月二日起至\n清償日止，按年息百分之十四點六計算之利息，並自民國九十三\n年十二月十六日起至清償日止，按上開利息總額百分之十計算之\n違約金。\n訴訟費用新臺幣壹仟元由被告負擔。\n本判決得假執行。\n    事實及理由\n本件為小額訴訟事件，依民事訴訟法第436 條之18第1 項前段之\n規定，判決書得僅記載主文。\n中    華    民    國    94    年    3     月    16    日\n                  苗栗簡易庭法  官  黃佩韻\n以上正本係照原本作成。\n如不服本判決，應於判決送達後20日內，以判決違背法令為理由\n，向本院提出上訴\n狀並表明上訴理由，及須按他造當事人之人數附繕本。上訴理由\n應表明：\n  一、原判決所違背之法令及其具體內容，\n  二、依訴訟資料可認為原判決有違背法令之具體事實。\n如未表明上訴理由者，應於上訴後20日內向本院提出上訴理由。\n當事人如對本件訴訟內容有所疑義，得聲請閱卷。\n中    華    民    國    94    年    3     月    16    日\n                            書記官  陳玲誼\n",
  "structure": {
    "main": "被告應給付原告新臺幣貳萬陸仟柒佰肆拾參元，及其中新臺幣壹\n萬伍仟玖佰肆拾貳元，自民國九十三年十二月二日起至清償日止\n，按年息百分之十四點六計算之利息，並自民國九十三年十二月\n十六日起至清償日止，按上開利息總額百分之十計算之違約金；\n其中新臺幣捌仟玖佰參拾貳元，自民國九十三年十二月二日起至\n清償日止，按年息百分之十四點六計算之利息，並自民國九十三\n年十二月十六日起至清償日止，按上開利息總額百分之十計算之\n違約金。\n訴訟費用新臺幣壹仟元由被告負擔。\n本判決得假執行。",
    "fact": "本件為小額訴訟事件，依民事訴訟法第436 條之18第1 項前段之\n規定，判決書得僅記載主文。",
    "reason": "本件為小額訴訟事件，依民事訴訟法第436 條之18第1 項前段之\n規定，判決書得僅記載主文。"
  },
  "search": "臺灣苗栗地方法院民事小額判決94年度苗小字第149號原告合作金庫銀行股份有限公司法定代理人丁○○訴訟代理人乙○○甲○○被告丙○○上列當事人間請求返還消費借貸款事件，本院於民國94年3月2日言詞辯論終結，判決如下：主文被告應給付原告新臺幣貳萬陸仟柒佰肆拾參元，及其中新臺幣壹萬伍仟玖佰肆拾貳元，自民國九十三年十二月二日起至清償日止，按年息百分之十四點六計算之利息，並自民國九十三年十二月十六日起至清償日止，按上開利息總額百分之十計算之違約金；其中新臺幣捌仟玖佰參拾貳元，自民國九十三年十二月二日起至清償日止，按年息百分之十四點六計算之利息，並自民國九十三年十二月十六日起至清償日止，按上開利息總額百分之十計算之違約金。訴訟費用新臺幣壹仟元由被告負擔。本判決得假執行。事實及理由本件為小額訴訟事件，依民事訴訟法第436條之18第1項前段之規定，判決書得僅記載主文。中華民國94年3月16日苗栗簡易庭法官黃佩韻以上正本係照原本作成。如不服本判決，應於判決送達後20日內，以判決違背法令為理由，向本院提出上訴狀並表明上訴理由，及須按他造當事人之人數附繕本。上訴理由應表明：一、原判決所違背之法令及其具體內容，二、依訴訟資料可認為原判決有違背法令之具體事實。如未表明上訴理由者，應於上訴後20日內向本院提出上訴理由。當事人如對本件訴訟內容有所疑義，得聲請閱卷。中華民國94年3月16日書記官陳玲誼",
  "characters": {
    "judges": [
      "黃佩韻"
    ],
    "prosecutors": [

    ],
    "lawyers": [

    ],
    "clerks": [
      "陳玲誼"
    ],
    "plaintiffs": [
      "合作金庫銀行股份有限公司"
    ],
    "defendants": [
      "丙○○"
    ],
    "prosecutor_office": [

    ],
    "creditors": [

    ],
    "debtors": [

    ],
    "judicial_associate_officer": [

    ]
  },
  "adjudged_at": "2005-03-16",
  "created_at": "2016-02-07 08:16:11",
  "updated_at": "2016-02-07 08:16:11"
}