{
  "identify": "TND-93-易-1030-20050317-1",
  "court": {
    "name": "臺灣南投地方法院",
    "code": "TND"
  },
  "division": {
    "name": "刑事",
    "code": "M"
  },
  "year": 93,
  "word": "易",
  "number": "1030",
  "jcheck": "1",
  "reason": "傷害",
  "content": "臺灣臺南地方法院刑事判決              93年度易字第1030號\n公  訴  人  臺灣台南地方法院檢察署檢察官\n被      告  甲○○  男  44歲.\n上列被告因傷害案件，經檢察官提起公訴（93年度營偵字第1156\n號），本院判決如左：\n    主  文\n甲○○傷害人之身體，處有期徒刑參月，如易科罰金，以佰元\n折算壹日。\n    事  實\n一、甲○○係乙○○○○之胞弟，其於民國九十三年九月四日下\n    午三時三十分許，在台南縣後壁鄉頂安村二二五之十號，因\n    兄弟分財產一事與乙○○○○發生爭執，竟基於傷害人身體\n    之犯意，出手毆打乙○○○○，致其受有顏面多處瘀腫（３\n    Ｘ３cm）、前胸瘀腫（６Ｘ５cm）及後背挫傷等傷害。\n二、案經乙○○○○訴由臺南縣警察局白河分局報請臺灣臺南地\n    方法院檢察署檢察官偵查起訴。\n    理  由\n一、訊據被告甲○○固坦承於前揭時地與告訴人乙○○○○即其\n    胞姐發生爭執並有拉扯等情，惟矢口否認有何傷害犯行，辯\n    稱並沒有打告訴人，她的傷可能是拉扯所致云云。經查：右\n    揭事實業據告訴人於本院以證人身分具結供證甚詳。另被告\n    先後於七十九年、八十三年、九十年間均曾毆打其父親乙節\n    ，業據被告於本院九十四年一月七日準備程序供承在卷，並\n    有刑案資料作業個別查詢報表在卷可稽（見警卷第十一頁）\n    ，故告訴人指證被告前曾毆打親人多次等情，應屬可信，參\n    以被告自承前揭時地有與告訴人發生爭執及拉扯之事實，益\n    徵告訴人之供證非出於捏造，此外，復有行政院衛生署新營\n    醫院傷害診斷證明書一紙附卷可參。故被告所辯顯係卸責之\n    詞，不足採信，事證明確，其犯行應足認定。\n二、核被告所為，係犯刑法第二百七十七條第一項之傷害罪。爰\n    審酌被告犯罪動機、目的、手段、素行、與告訴人係姐弟關\n    係、犯後態度不佳毫無悔意及告訴人傷勢尚屬輕微等一切情\n    狀，量處如主文所示之刑，並諭知易科罰金之折算標準，以\n    示懲儆。\n據上論斷，應依刑事訴訟法第二百九十九條第一項前段，刑法第\n二百七十七條第一項、第四十一條第一項前段，罰金罰鍰提高標\n準條例第一條前段、第二條，判決如主文。\n本案經檢察官丙○○到庭執行職務\n中    華    民    國    94    年    3    月    17    日\n                  刑事第六庭  審判長   法  官  陳忠鎣\n                                       法  官  林勝利\n                                       法  官  鍾邦久\n以上正本證明與原本無異。\n如不服本判決，應於判決送達後10日內，向本院提出上訴狀。\n                                       書記官  張豐榮\n中    華    民    國    94    年    3    月    17    日\n附錄法條：\n中華民國刑法第277條\n (普通傷害罪)\n傷害人之身體或健康者，處三年以下有期徒刑、拘役或一千元以\n下罰金。\n犯前項之罪因而致人於死者，處無期徒刑或七年以上有期徒刑；\n致重傷者，處三年以上十年以下有期徒刑。\n",
  "structure": {
    "main": "甲○○傷害人之身體，處有期徒刑參月，如易科罰金，以佰元\n折算壹日。",
    "fact": "一、甲○○係乙○○○○之胞弟，其於民國九十三年九月四日下\n    午三時三十分許，在台南縣後壁鄉頂安村二二五之十號，因\n    兄弟分財產一事與乙○○○○發生爭執，竟基於傷害人身體\n    之犯意，出手毆打乙○○○○，致其受有顏面多處瘀腫（３\n    Ｘ３cm）、前胸瘀腫（６Ｘ５cm）及後背挫傷等傷害。\n二、案經乙○○○○訴由臺南縣警察局白河分局報請臺灣臺南地\n    方法院檢察署檢察官偵查起訴。",
    "reason": "一、訊據被告甲○○固坦承於前揭時地與告訴人乙○○○○即其\n    胞姐發生爭執並有拉扯等情，惟矢口否認有何傷害犯行，辯\n    稱並沒有打告訴人，她的傷可能是拉扯所致云云。經查：右\n    揭事實業據告訴人於本院以證人身分具結供證甚詳。另被告\n    先後於七十九年、八十三年、九十年間均曾毆打其父親乙節\n    ，業據被告於本院九十四年一月七日準備程序供承在卷，並\n    有刑案資料作業個別查詢報表在卷可稽（見警卷第十一頁）\n    ，故告訴人指證被告前曾毆打親人多次等情，應屬可信，參\n    以被告自承前揭時地有與告訴人發生爭執及拉扯之事實，益\n    徵告訴人之供證非出於捏造，此外，復有行政院衛生署新營\n    醫院傷害診斷證明書一紙附卷可參。故被告所辯顯係卸責之\n    詞，不足採信，事證明確，其犯行應足認定。\n二、核被告所為，係犯刑法第二百七十七條第一項之傷害罪。爰\n    審酌被告犯罪動機、目的、手段、素行、與告訴人係姐弟關\n    係、犯後態度不佳毫無悔意及告訴人傷勢尚屬輕微等一切情\n    狀，量處如主文所示之刑，並諭知易科罰金之折算標準，以\n    示懲儆。\n據上論斷，應依刑事訴訟法第二百九十九條第一項前段，刑法第\n二百七十七條第一項、第四十一條第一項前段，罰金罰鍰提高標\n準條例第一條前段、第二條，判決如主文。\n本案經檢察官丙○○到庭執行職務\n中    華    民    國    94    年    3    月    17    日\n                  刑事第六庭  審判長   法  官  陳忠鎣\n                                       法  官  林勝利\n                                       法  官  鍾邦久\n以上正本證明與原本無異。\n如不服本判決，應於判決送達後10日內，向本院提出上訴狀。\n                                       書記官  張豐榮"
  },
  "search": "臺灣臺南地方法院刑事判決93年度易字第1030號公訴人臺灣台南地方法院檢察署檢察官被告甲○○男44歲.上列被告因傷害案件，經檢察官提起公訴（93年度營偵字第1156號），本院判決如左：主文甲○○傷害人之身體，處有期徒刑參月，如易科罰金，以佰元折算壹日。事實一、甲○○係乙○○○○之胞弟，其於民國九十三年九月四日下午三時三十分許，在台南縣後壁鄉頂安村二二五之十號，因兄弟分財產一事與乙○○○○發生爭執，竟基於傷害人身體之犯意，出手毆打乙○○○○，致其受有顏面多處瘀腫（３Ｘ３cm）、前胸瘀腫（６Ｘ５cm）及後背挫傷等傷害。二、案經乙○○○○訴由臺南縣警察局白河分局報請臺灣臺南地方法院檢察署檢察官偵查起訴。理由一、訊據被告甲○○固坦承於前揭時地與告訴人乙○○○○即其胞姐發生爭執並有拉扯等情，惟矢口否認有何傷害犯行，辯稱並沒有打告訴人，她的傷可能是拉扯所致云云。經查：右揭事實業據告訴人於本院以證人身分具結供證甚詳。另被告先後於七十九年、八十三年、九十年間均曾毆打其父親乙節，業據被告於本院九十四年一月七日準備程序供承在卷，並有刑案資料作業個別查詢報表在卷可稽（見警卷第十一頁），故告訴人指證被告前曾毆打親人多次等情，應屬可信，參以被告自承前揭時地有與告訴人發生爭執及拉扯之事實，益徵告訴人之供證非出於捏造，此外，復有行政院衛生署新營醫院傷害診斷證明書一紙附卷可參。故被告所辯顯係卸責之詞，不足採信，事證明確，其犯行應足認定。二、核被告所為，係犯刑法第二百七十七條第一項之傷害罪。爰審酌被告犯罪動機、目的、手段、素行、與告訴人係姐弟關係、犯後態度不佳毫無悔意及告訴人傷勢尚屬輕微等一切情狀，量處如主文所示之刑，並諭知易科罰金之折算標準，以示懲儆。據上論斷，應依刑事訴訟法第二百九十九條第一項前段，刑法第二百七十七條第一項、第四十一條第一項前段，罰金罰鍰提高標準條例第一條前段、第二條，判決如主文。本案經檢察官丙○○到庭執行職務中華民國94年3月17日刑事第六庭審判長法官陳忠鎣法官林勝利法官鍾邦久以上正本證明與原本無異。如不服本判決，應於判決送達後10日內，向本院提出上訴狀。書記官張豐榮中華民國94年3月17日附錄法條：中華民國刑法第277條(普通傷害罪)傷害人之身體或健康者，處三年以下有期徒刑、拘役或一千元以下罰金。犯前項之罪因而致人於死者，處無期徒刑或七年以上有期徒刑；致重傷者，處三年以上十年以下有期徒刑。",
  "characters": {
    "judges": [
      "陳忠鎣",
      "林勝利",
      "鍾邦久"
    ],
    "prosecutors": [

    ],
    "lawyers": [

    ],
    "clerks": [
      "張豐榮"
    ],
    "plaintiffs": [

    ],
    "defendants": [
      "甲○○  男  44歲."
    ],
    "prosecutor_office": [
      "臺灣台南地方法院檢察署檢察官"
    ],
    "creditors": [

    ],
    "debtors": [

    ],
    "judicial_associate_officer": [

    ]
  },
  "adjudged_at": "2005-03-17",
  "created_at": "2016-02-07 08:15:03",
  "updated_at": "2016-02-07 08:15:03"
}