{
  "identify": "TCD-100-簡-419-20110624-1",
  "court": {
    "name": "臺灣臺中地方法院",
    "code": "TCD"
  },
  "division": {
    "name": "刑事",
    "code": "M"
  },
  "year": 100,
  "word": "簡",
  "number": "419",
  "jcheck": "1",
  "reason": "重利",
  "content": "臺灣臺中地方法院刑事簡易判決      100年度簡字第419號\n公  訴  人  臺灣臺中地方法院檢察署檢察官\n被      告  王家偉\n上列被告因重利案件，經檢察官提起公訴（九十九年度偵字第二\n六三一二號），被告對檢察官起訴書所載之犯罪事實為認罪之答\n辯，爰裁定以簡易判決處刑如下：\n    主      文\n王家偉共同乘他人急迫貸以金錢，而取得與原本顯不相當之重利\n，處拘役貳拾日，如易科罰金，以新臺幣壹仟元折算壹日。\n    事實及理由\n一、本案犯罪事實、證據及理由，除補充被告王家偉於本院審理\n    時自白犯行外，餘均引用附件檢察官起訴書之記載。\n二、核被告所為，係犯刑法第三百四十四條之重利罪。被告與綽\n    號「小吳」間，有犯意聯絡及行為分擔，為共同正犯。爰審\n    酌被告從事貸款收取重利之行為，所為對社會經濟秩序及借\n    款人之生計均有不良影響，其行為手段殊無可取，而高額利\n    率肇常致債務人陷於龐大債務之泥淖，難以翻身，對發生經\n    濟危機之個人及合乎經濟秩序之信賴均有損害，惟考量被告\n    貸放金額非鉅，所生危害尚非重大，且犯後坦承犯行等一切\n    情狀，量處如主文所示之刑，並諭知易科罰金之折算標準，\n    以示懲儆。\n三、依刑事訴訟法第四百四十九條第二項、第四百五十四條第二\n    項，刑法第二十八條、第三百四十四條、第四十一條第一項\n    前段，刑法施行法第一條之一，逕以簡易判決處刑如主文。\n四、如不服本判決，得自收受送達之日起十日內向本院提出上訴\n    狀，上訴於本院第二審合議庭（須附繕本）。\n本案經檢察官王亮欽到庭執行職務。\n中    華    民    國   100    年    6     月    24    日\n                  刑事第十二庭  法  官  周莉菁\n以上正本證明與原本無異。\n告訴人或被害人對於判決如有不服具備理由請求檢察官上訴者，\n其上訴期間之計算係以檢察官收受判決正本之日期為準。\n                                書記官  吳彩華\n中    華    民    國   100    年    6     月    24    日\n附錄本判決論罪科刑法條：\n刑法第344條：\n乘他人急迫、輕率或無經驗貸以金錢或其他物品，而取得與原本\n顯不相當之重利者，處一年以下有期徒刑、拘役或科或併科一千\n元以下罰金。",
  "structure": {
    "main": "王家偉共同乘他人急迫貸以金錢，而取得與原本顯不相當之重利\n，處拘役貳拾日，如易科罰金，以新臺幣壹仟元折算壹日。",
    "fact": "一、本案犯罪事實、證據及理由，除補充被告王家偉於本院審理\n    時自白犯行外，餘均引用附件檢察官起訴書之記載。\n二、核被告所為，係犯刑法第三百四十四條之重利罪。被告與綽\n    號「小吳」間，有犯意聯絡及行為分擔，為共同正犯。爰審\n    酌被告從事貸款收取重利之行為，所為對社會經濟秩序及借\n    款人之生計均有不良影響，其行為手段殊無可取，而高額利\n    率肇常致債務人陷於龐大債務之泥淖，難以翻身，對發生經\n    濟危機之個人及合乎經濟秩序之信賴均有損害，惟考量被告\n    貸放金額非鉅，所生危害尚非重大，且犯後坦承犯行等一切\n    情狀，量處如主文所示之刑，並諭知易科罰金之折算標準，\n    以示懲儆。\n三、依刑事訴訟法第四百四十九條第二項、第四百五十四條第二\n    項，刑法第二十八條、第三百四十四條、第四十一條第一項\n    前段，刑法施行法第一條之一，逕以簡易判決處刑如主文。\n四、如不服本判決，得自收受送達之日起十日內向本院提出上訴\n    狀，上訴於本院第二審合議庭（須附繕本）。\n本案經檢察官王亮欽到庭執行職務。",
    "reason": "一、本案犯罪事實、證據及理由，除補充被告王家偉於本院審理\n    時自白犯行外，餘均引用附件檢察官起訴書之記載。\n二、核被告所為，係犯刑法第三百四十四條之重利罪。被告與綽\n    號「小吳」間，有犯意聯絡及行為分擔，為共同正犯。爰審\n    酌被告從事貸款收取重利之行為，所為對社會經濟秩序及借\n    款人之生計均有不良影響，其行為手段殊無可取，而高額利\n    率肇常致債務人陷於龐大債務之泥淖，難以翻身，對發生經\n    濟危機之個人及合乎經濟秩序之信賴均有損害，惟考量被告\n    貸放金額非鉅，所生危害尚非重大，且犯後坦承犯行等一切\n    情狀，量處如主文所示之刑，並諭知易科罰金之折算標準，\n    以示懲儆。\n三、依刑事訴訟法第四百四十九條第二項、第四百五十四條第二\n    項，刑法第二十八條、第三百四十四條、第四十一條第一項\n    前段，刑法施行法第一條之一，逕以簡易判決處刑如主文。\n四、如不服本判決，得自收受送達之日起十日內向本院提出上訴\n    狀，上訴於本院第二審合議庭（須附繕本）。\n本案經檢察官王亮欽到庭執行職務。"
  },
  "search": "臺灣臺中地方法院刑事簡易判決100年度簡字第419號公訴人臺灣臺中地方法院檢察署檢察官被告王家偉上列被告因重利案件，經檢察官提起公訴（九十九年度偵字第二六三一二號），被告對檢察官起訴書所載之犯罪事實為認罪之答辯，爰裁定以簡易判決處刑如下：主文王家偉共同乘他人急迫貸以金錢，而取得與原本顯不相當之重利，處拘役貳拾日，如易科罰金，以新臺幣壹仟元折算壹日。事實及理由一、本案犯罪事實、證據及理由，除補充被告王家偉於本院審理時自白犯行外，餘均引用附件檢察官起訴書之記載。二、核被告所為，係犯刑法第三百四十四條之重利罪。被告與綽號「小吳」間，有犯意聯絡及行為分擔，為共同正犯。爰審酌被告從事貸款收取重利之行為，所為對社會經濟秩序及借款人之生計均有不良影響，其行為手段殊無可取，而高額利率肇常致債務人陷於龐大債務之泥淖，難以翻身，對發生經濟危機之個人及合乎經濟秩序之信賴均有損害，惟考量被告貸放金額非鉅，所生危害尚非重大，且犯後坦承犯行等一切情狀，量處如主文所示之刑，並諭知易科罰金之折算標準，以示懲儆。三、依刑事訴訟法第四百四十九條第二項、第四百五十四條第二項，刑法第二十八條、第三百四十四條、第四十一條第一項前段，刑法施行法第一條之一，逕以簡易判決處刑如主文。四、如不服本判決，得自收受送達之日起十日內向本院提出上訴狀，上訴於本院第二審合議庭（須附繕本）。本案經檢察官王亮欽到庭執行職務。中華民國100年6月24日刑事第十二庭法官周莉菁以上正本證明與原本無異。告訴人或被害人對於判決如有不服具備理由請求檢察官上訴者，其上訴期間之計算係以檢察官收受判決正本之日期為準。書記官吳彩華中華民國100年6月24日附錄本判決論罪科刑法條：刑法第344條：乘他人急迫、輕率或無經驗貸以金錢或其他物品，而取得與原本顯不相當之重利者，處一年以下有期徒刑、拘役或科或併科一千元以下罰金。",
  "characters": {
    "judges": [
      "周莉菁"
    ],
    "prosecutors": [
      "王亮欽"
    ],
    "lawyers": [

    ],
    "clerks": [
      "吳彩華"
    ],
    "plaintiffs": [

    ],
    "defendants": [
      "王家偉"
    ],
    "prosecutor_office": [
      "臺灣臺中地方法院檢察署檢察官"
    ],
    "creditors": [

    ],
    "debtors": [

    ],
    "judicial_associate_officer": [

    ]
  },
  "adjudged_at": "2011-06-24",
  "created_at": "2016-02-13 16:41:12",
  "updated_at": "2016-02-13 16:41:12"
}