{
  "identify": "TPH-99-上重訴-37-20110624-6",
  "court": {
    "name": "臺灣高等法院",
    "code": "TPH"
  },
  "division": {
    "name": "刑事",
    "code": "M"
  },
  "year": 99,
  "word": "上重訴",
  "number": "37",
  "jcheck": "6",
  "reason": "殺人等",
  "content": "臺灣高等法院刑事裁定                99年度上重訴字第37號\n上  訴  人\n即  被  告  宋志宏\n選任辯護人  鄧湘全律師\n            王唯鳳律師\n            賴玉梅律師\n上列被告因殺人等上訴案件，本院裁定如下：\n    主  文\n宋志宏羈押期間，自民國一○○年七月一日起，延長貳月。\n    理  由\n一、上訴人即被告宋志宏，前經本院以其經原審認定犯刑法第27\n    1 條第1 項殺人罪，判處無期徒刑，褫奪公權終身；又犯藥\n    事法第83條第1 項之轉讓禁藥罪，判處有期徒刑1 年，定應\n    執行無期徒刑，褫奪公權終身在案，犯罪嫌疑重大，亦有事\n    實足認被告有畏重罪執行而逃亡之虞，及有事實足認被告有\n    湮滅、偽造、變造證據或勾串共犯或證人之虞，同時符合刑\n    事訴訟法第101 條第1 項第1 、2 、3 款之羈押事由，非予\n    羈押，顯難進行審判，於民國99年6 月14日執行羈押（其間\n    ，被告因另違反臺灣地區與大陸地區人民關係條例案件，經\n    臺灣板橋地方法院98年度簡字第5783號判決拘役50日確定，\n    本院暫予停止羈押被告，由臺灣板橋地方法院檢察署檢察官\n    自99 年7月6 日起，迄同年8 月24日止，借提指揮執行上述\n    刑罰，再經本院自執行期滿翌日99年8 月25日起，續行羈押\n    被告），並先後延長被告羈押期間，迄今被告延長羈押期間\n    即將於100 年6 月30日屆滿。\n二、茲本院於100 年6 月22日撤銷原審判決關於被告殺人及定執\n    行刑部分，就被告被訴涉犯殺人罪部分，改依刑法第277 條\n    第2 項之傷害致死罪，判處有期徒刑15年，轉讓禁藥部分則\n    駁回上訴，維持原審判決，並諭知上述2 罪應執行有期徒刑\n    15年6 月在案。本院於同日訊問被告，並對被告及其辯護人\n    告以刑事訴訟法第101 條第1 項第1 款、第3 款所定羈押事\n    由及聽取其等意見陳述後，認被告既經本院判處上述罪刑，\n    非屬短期自由刑，被告仍有畏重罪執行而逃亡之高度誘因，\n    有相當理由認被告有逃亡之虞，且傷害致死罪係法定本刑為\n    無期徒刑、7 年以上有期徒刑之重罪。從而，本件得認被告\n    同時具有刑事訴訟法第101 條第1 項第1 、3 款所定情形。\n    又本院判決後，被告及檢察官均得提起第三審上訴，為確保\n    將來審判程序或判決確定後之執行程序得以順利進行，仍有\n    繼續羈押被告之必要，其羈押期間，應自100 年7 月1 日起\n    ，延長2 月。\n據上論斷，爰依刑事訴訟法第108條第 1項、第5項，裁定如主文\n。\n中    華    民    國  100    年    6     月    24     日\n                 刑事第二十四庭  審判長法  官  李錦樑\n                                       法  官  朱瑞娟\n                                       法  官  陳恆寬\n以上正本證明與原本無異。\n如不服本裁定，應於收受送達後五日內向本院提出抗告狀。\n                                       書記官  黃家麟\n中    華    民    國   100    年    6     月    24    日",
  "structure": {
    "main": "宋志宏羈押期間，自民國一○○年七月一日起，延長貳月。",
    "reason": "一、上訴人即被告宋志宏，前經本院以其經原審認定犯刑法第27\n    1 條第1 項殺人罪，判處無期徒刑，褫奪公權終身；又犯藥\n    事法第83條第1 項之轉讓禁藥罪，判處有期徒刑1 年，定應\n    執行無期徒刑，褫奪公權終身在案，犯罪嫌疑重大，亦有事\n    實足認被告有畏重罪執行而逃亡之虞，及有事實足認被告有\n    湮滅、偽造、變造證據或勾串共犯或證人之虞，同時符合刑\n    事訴訟法第101 條第1 項第1 、2 、3 款之羈押事由，非予\n    羈押，顯難進行審判，於民國99年6 月14日執行羈押（其間\n    ，被告因另違反臺灣地區與大陸地區人民關係條例案件，經\n    臺灣板橋地方法院98年度簡字第5783號判決拘役50日確定，\n    本院暫予停止羈押被告，由臺灣板橋地方法院檢察署檢察官\n    自99 年7月6 日起，迄同年8 月24日止，借提指揮執行上述\n    刑罰，再經本院自執行期滿翌日99年8 月25日起，續行羈押\n    被告），並先後延長被告羈押期間，迄今被告延長羈押期間\n    即將於100 年6 月30日屆滿。\n二、茲本院於100 年6 月22日撤銷原審判決關於被告殺人及定執\n    行刑部分，就被告被訴涉犯殺人罪部分，改依刑法第277 條\n    第2 項之傷害致死罪，判處有期徒刑15年，轉讓禁藥部分則\n    駁回上訴，維持原審判決，並諭知上述2 罪應執行有期徒刑\n    15年6 月在案。本院於同日訊問被告，並對被告及其辯護人\n    告以刑事訴訟法第101 條第1 項第1 款、第3 款所定羈押事\n    由及聽取其等意見陳述後，認被告既經本院判處上述罪刑，\n    非屬短期自由刑，被告仍有畏重罪執行而逃亡之高度誘因，\n    有相當理由認被告有逃亡之虞，且傷害致死罪係法定本刑為\n    無期徒刑、7 年以上有期徒刑之重罪。從而，本件得認被告\n    同時具有刑事訴訟法第101 條第1 項第1 、3 款所定情形。\n    又本院判決後，被告及檢察官均得提起第三審上訴，為確保\n    將來審判程序或判決確定後之執行程序得以順利進行，仍有\n    繼續羈押被告之必要，其羈押期間，應自100 年7 月1 日起\n    ，延長2 月。\n據上論斷，爰依刑事訴訟法第108條第 1項、第5項，裁定如主文\n。"
  },
  "search": "臺灣高等法院刑事裁定99年度上重訴字第37號上訴人即被告宋志宏選任辯護人鄧湘全律師王唯鳳律師賴玉梅律師上列被告因殺人等上訴案件，本院裁定如下：主文宋志宏羈押期間，自民國一○○年七月一日起，延長貳月。理由一、上訴人即被告宋志宏，前經本院以其經原審認定犯刑法第271條第1項殺人罪，判處無期徒刑，褫奪公權終身；又犯藥事法第83條第1項之轉讓禁藥罪，判處有期徒刑1年，定應執行無期徒刑，褫奪公權終身在案，犯罪嫌疑重大，亦有事實足認被告有畏重罪執行而逃亡之虞，及有事實足認被告有湮滅、偽造、變造證據或勾串共犯或證人之虞，同時符合刑事訴訟法第101條第1項第1、2、3款之羈押事由，非予羈押，顯難進行審判，於民國99年6月14日執行羈押（其間，被告因另違反臺灣地區與大陸地區人民關係條例案件，經臺灣板橋地方法院98年度簡字第5783號判決拘役50日確定，本院暫予停止羈押被告，由臺灣板橋地方法院檢察署檢察官自99年7月6日起，迄同年8月24日止，借提指揮執行上述刑罰，再經本院自執行期滿翌日99年8月25日起，續行羈押被告），並先後延長被告羈押期間，迄今被告延長羈押期間即將於100年6月30日屆滿。二、茲本院於100年6月22日撤銷原審判決關於被告殺人及定執行刑部分，就被告被訴涉犯殺人罪部分，改依刑法第277條第2項之傷害致死罪，判處有期徒刑15年，轉讓禁藥部分則駁回上訴，維持原審判決，並諭知上述2罪應執行有期徒刑15年6月在案。本院於同日訊問被告，並對被告及其辯護人告以刑事訴訟法第101條第1項第1款、第3款所定羈押事由及聽取其等意見陳述後，認被告既經本院判處上述罪刑，非屬短期自由刑，被告仍有畏重罪執行而逃亡之高度誘因，有相當理由認被告有逃亡之虞，且傷害致死罪係法定本刑為無期徒刑、7年以上有期徒刑之重罪。從而，本件得認被告同時具有刑事訴訟法第101條第1項第1、3款所定情形。又本院判決後，被告及檢察官均得提起第三審上訴，為確保將來審判程序或判決確定後之執行程序得以順利進行，仍有繼續羈押被告之必要，其羈押期間，應自100年7月1日起，延長2月。據上論斷，爰依刑事訴訟法第108條第1項、第5項，裁定如主文。中華民國100年6月24日刑事第二十四庭審判長法官李錦樑法官朱瑞娟法官陳恆寬以上正本證明與原本無異。如不服本裁定，應於收受送達後五日內向本院提出抗告狀。書記官黃家麟中華民國100年6月24日",
  "characters": {
    "judges": [
      "李錦樑",
      "朱瑞娟",
      "陳恆寬"
    ],
    "prosecutors": [

    ],
    "lawyers": [
      "鄧湘全",
      "王唯鳳",
      "賴玉梅"
    ],
    "clerks": [
      "黃家麟"
    ],
    "plaintiffs": [

    ],
    "defendants": [
      "宋志宏"
    ],
    "prosecutor_office": [

    ],
    "creditors": [

    ],
    "debtors": [

    ],
    "judicial_associate_officer": [

    ]
  },
  "adjudged_at": "2011-06-24",
  "created_at": "2016-02-13 16:29:24",
  "updated_at": "2016-02-13 16:29:24"
}