{
  "identify": "KLD-100-基簡-1914-20111220-1",
  "court": {
    "name": "臺灣基隆地方法院",
    "code": "KLD"
  },
  "division": {
    "name": "刑事",
    "code": "M"
  },
  "year": 100,
  "word": "基簡",
  "number": "1914",
  "jcheck": "1",
  "reason": "竊盜",
  "content": "臺灣基隆地方法院刑事簡易判決       100年度基簡字第1914號\n聲  請  人  臺灣基隆地方法院檢察署檢察官\n被      告  張志宏\n上列被告因竊盜案件，經檢察官聲請以簡易判決處刑（100 年度\n偵字第4339號），本院判決如下：\n    主      文\n張志宏竊盜，累犯，處拘役肆拾日，如易科罰金，以新臺幣壹仟\n元折算壹日。\n    事實及理由\n一、本件犯罪事實及證據均引用檢察官聲請簡易判決處刑書之記\n    載（如附件）。\n二、核被告所為，係犯刑法第320條第1項之竊盜罪。被告有事實\n    欄所載之科刑執行情形，有台灣高等法院被告前案紀錄表在\n    卷可稽，其於受有期徒刑之執行完畢後，5 年內再犯有期徒\n    刑以上之本罪，為累犯，應依刑法第47條第1 項規定加重其\n    刑。參酌被告犯罪之動機、目的、所受之剌激、手段、品行\n    、智識程度、所生之危害及犯罪後之態度等一切情狀，爰量\n    處如主文所示之刑，併諭知易科罰金之折算標準，以示懲儆\n    。\n三、依刑事訴訟法第449條第1 項前段、第454條第2 項，刑法第\n    320條第1項、第41條第1項前段、第47條第1項，刑法施行法\n    第1條之1，逕以簡易判決處刑如主文。\n四、自簡易判決送達之日起10日內，得向本院提起上訴（須附繕\n    本）。\n中    華    民    國   100    年    12    月    20    日\n                  基隆簡易庭法  官  王福康\n如不服本判決，應於判決送達後10日內，向本院提出上訴書狀，\n敘述上訴理由，上訴於本院合議庭，並按他造當事人之人數附具\n繕本。\n中    華    民    國   100    年    12    月    20    日\n                            書記官  彭淑芳\n【附錄論罪法條】\n刑法第320條第1項：\n    意圖為自己或第三人不法之所有，而竊取他人之動產者，為\n    竊盜罪，處5年以下有期徒刑、拘役或5百元以下罰金。\n【附件】\n臺灣基隆地方法院檢察署檢察官聲請簡易判決處刑書\n                                     100年度偵字第4339號\n    被      告  張志宏  男  43歲（民國○○年○○月○日生）\n                        住基隆市○○區○○路243巷48之2號\n                        國民身分證統一編號：Ｚ000000000號\n上列被告因竊盜案件，業經偵查終結，認為宜聲請以簡易判決處\n刑，茲將犯罪事實及證據並所犯法條分敘如下：\n        犯罪事實\n一、張志宏前於民國96年間，因竊盜案件，經臺灣基隆地方法院\n    以96年基簡字第1210號判決應執行有期徒刑6月確定；又因\n    竊盜案件，經同法院以96年易字第728號判決應執行有期徒\n    刑10月確定；復因施用毒品案件，經同法院以96年訴字第\n    985號判決應執行有期徒刑10月確定；再因竊盜案件，經臺\n    灣士林地方法院以96年易字第2271號判決應執行有期徒刑10\n    月確定；另因竊盜案件，經臺灣基隆地方法院以96年度易字\n    第833號判決應執行有期徒刑1年確定，上開各刑經接續執行\n    ，於100年1月14日縮短刑期假釋付保護管束出監，而於100\n    年4月14日因保護管束期滿，未經撤銷假釋而視為執行完畢\n    。猶不知悛悔，仍於100年9月1日19時10分許，行經基隆市\n    ○○區○○路47巷口時，見張明山所有之李鵠鳳梨酥1袋（\n    內有鳳梨酥2盒，價值新臺幣700元）掛置於車牌號碼LDV-79\n    2號重型機車把手上，無人看管，竟意圖為自己不法之所有\n    ，徒手竊取該鳳梨酥後離去，適不知情的陳正哲在設址基隆\n    市○○區○○路1號「萊爾富便利商店」內值班，張志宏旋\n    進入店內並將該袋鳳梨酥交予陳正哲暫為保管。俟因張明山\n    發覺遭竊，調閱監視器畫面報警處理，而循線查悉上情。\n二、案經張明山訴由基隆市警察局第一分局報告偵辦。\n        證據並所犯法條\n一、證據：（一）被告張志宏於偵查中之自白。\n          （二）證人即告訴人張明山於警詢時、偵查中之證言\n                。\n          （三）證人陳正哲於警詢時、偵查中之證言。\n          （四）基隆市警察局第一分局搜索扣押筆錄1份暨扣\n                案之鳳梨酥2盒、贓物認領保管單1紙。\n          （五）照片7張在卷可資佐證，被告犯嫌已堪認定。\n二、核被告所為，係犯刑法第320條第1項竊盜罪嫌。被告有如犯\n    罪事實欄所載之論罪科刑執行情形，有刑案資料查註紀錄表\n    在卷可稽，其於有期徒刑執行完畢後，5年以內故意再犯本\n    件有期徒刑以上之罪，為累犯，請依刑法第47條第1項之規\n    定加重其刑。\n三、依刑事訴訟法第451條第1項聲請逕以簡易判決處刑。\n    此    致\n臺灣基隆地方法院基隆簡易庭\n中    華    民    國   100    年    11    月    30    日\n                              檢  察  官  蔡妍蓁\n本件正本證明與原本無異\n中    華    民    國   100    年    12    月    8     日\n                              書  記  官  李曉旻\n附錄本案所犯法條全文\n中華民國刑法第320條（普通竊盜罪、竊佔罪）\n意圖為自己或第三人不法之所有，而竊取他人之動產者，為竊盜\n罪，處5  年以下有期徒刑、拘役或 5 百元以下罰金。\n意圖為自己或第三人不法之利益，而竊佔他人之不動產者，依前\n項之規定處斷。\n前二項之未遂犯罰之。",
  "structure": {
    "main": "張志宏竊盜，累犯，處拘役肆拾日，如易科罰金，以新臺幣壹仟\n元折算壹日。",
    "fact": "一、本件犯罪事實及證據均引用檢察官聲請簡易判決處刑書之記\n    載（如附件）。\n二、核被告所為，係犯刑法第320條第1項之竊盜罪。被告有事實\n    欄所載之科刑執行情形，有台灣高等法院被告前案紀錄表在\n    卷可稽，其於受有期徒刑之執行完畢後，5 年內再犯有期徒\n    刑以上之本罪，為累犯，應依刑法第47條第1 項規定加重其\n    刑。參酌被告犯罪之動機、目的、所受之剌激、手段、品行\n    、智識程度、所生之危害及犯罪後之態度等一切情狀，爰量\n    處如主文所示之刑，併諭知易科罰金之折算標準，以示懲儆\n    。\n三、依刑事訴訟法第449條第1 項前段、第454條第2 項，刑法第\n    320條第1項、第41條第1項前段、第47條第1項，刑法施行法\n    第1條之1，逕以簡易判決處刑如主文。\n四、自簡易判決送達之日起10日內，得向本院提起上訴（須附繕\n    本）。",
    "reason": "一、本件犯罪事實及證據均引用檢察官聲請簡易判決處刑書之記\n    載（如附件）。\n二、核被告所為，係犯刑法第320條第1項之竊盜罪。被告有事實\n    欄所載之科刑執行情形，有台灣高等法院被告前案紀錄表在\n    卷可稽，其於受有期徒刑之執行完畢後，5 年內再犯有期徒\n    刑以上之本罪，為累犯，應依刑法第47條第1 項規定加重其\n    刑。參酌被告犯罪之動機、目的、所受之剌激、手段、品行\n    、智識程度、所生之危害及犯罪後之態度等一切情狀，爰量\n    處如主文所示之刑，併諭知易科罰金之折算標準，以示懲儆\n    。\n三、依刑事訴訟法第449條第1 項前段、第454條第2 項，刑法第\n    320條第1項、第41條第1項前段、第47條第1項，刑法施行法\n    第1條之1，逕以簡易判決處刑如主文。\n四、自簡易判決送達之日起10日內，得向本院提起上訴（須附繕\n    本）。"
  },
  "search": "臺灣基隆地方法院刑事簡易判決100年度基簡字第1914號聲請人臺灣基隆地方法院檢察署檢察官被告張志宏上列被告因竊盜案件，經檢察官聲請以簡易判決處刑（100年度偵字第4339號），本院判決如下：主文張志宏竊盜，累犯，處拘役肆拾日，如易科罰金，以新臺幣壹仟元折算壹日。事實及理由一、本件犯罪事實及證據均引用檢察官聲請簡易判決處刑書之記載（如附件）。二、核被告所為，係犯刑法第320條第1項之竊盜罪。被告有事實欄所載之科刑執行情形，有台灣高等法院被告前案紀錄表在卷可稽，其於受有期徒刑之執行完畢後，5年內再犯有期徒刑以上之本罪，為累犯，應依刑法第47條第1項規定加重其刑。參酌被告犯罪之動機、目的、所受之剌激、手段、品行、智識程度、所生之危害及犯罪後之態度等一切情狀，爰量處如主文所示之刑，併諭知易科罰金之折算標準，以示懲儆。三、依刑事訴訟法第449條第1項前段、第454條第2項，刑法第320條第1項、第41條第1項前段、第47條第1項，刑法施行法第1條之1，逕以簡易判決處刑如主文。四、自簡易判決送達之日起10日內，得向本院提起上訴（須附繕本）。中華民國100年12月20日基隆簡易庭法官王福康如不服本判決，應於判決送達後10日內，向本院提出上訴書狀，敘述上訴理由，上訴於本院合議庭，並按他造當事人之人數附具繕本。中華民國100年12月20日書記官彭淑芳【附錄論罪法條】刑法第320條第1項：意圖為自己或第三人不法之所有，而竊取他人之動產者，為竊盜罪，處5年以下有期徒刑、拘役或5百元以下罰金。【附件】臺灣基隆地方法院檢察署檢察官聲請簡易判決處刑書100年度偵字第4339號被告張志宏男43歲（民國○○年○○月○日生）住基隆市○○區○○路243巷48之2號國民身分證統一編號：Ｚ000000000號上列被告因竊盜案件，業經偵查終結，認為宜聲請以簡易判決處刑，茲將犯罪事實及證據並所犯法條分敘如下：犯罪事實一、張志宏前於民國96年間，因竊盜案件，經臺灣基隆地方法院以96年基簡字第1210號判決應執行有期徒刑6月確定；又因竊盜案件，經同法院以96年易字第728號判決應執行有期徒刑10月確定；復因施用毒品案件，經同法院以96年訴字第985號判決應執行有期徒刑10月確定；再因竊盜案件，經臺灣士林地方法院以96年易字第2271號判決應執行有期徒刑10月確定；另因竊盜案件，經臺灣基隆地方法院以96年度易字第833號判決應執行有期徒刑1年確定，上開各刑經接續執行，於100年1月14日縮短刑期假釋付保護管束出監，而於100年4月14日因保護管束期滿，未經撤銷假釋而視為執行完畢。猶不知悛悔，仍於100年9月1日19時10分許，行經基隆市○○區○○路47巷口時，見張明山所有之李鵠鳳梨酥1袋（內有鳳梨酥2盒，價值新臺幣700元）掛置於車牌號碼LDV-792號重型機車把手上，無人看管，竟意圖為自己不法之所有，徒手竊取該鳳梨酥後離去，適不知情的陳正哲在設址基隆市○○區○○路1號「萊爾富便利商店」內值班，張志宏旋進入店內並將該袋鳳梨酥交予陳正哲暫為保管。俟因張明山發覺遭竊，調閱監視器畫面報警處理，而循線查悉上情。二、案經張明山訴由基隆市警察局第一分局報告偵辦。證據並所犯法條一、證據：（一）被告張志宏於偵查中之自白。（二）證人即告訴人張明山於警詢時、偵查中之證言。（三）證人陳正哲於警詢時、偵查中之證言。（四）基隆市警察局第一分局搜索扣押筆錄1份暨扣案之鳳梨酥2盒、贓物認領保管單1紙。（五）照片7張在卷可資佐證，被告犯嫌已堪認定。二、核被告所為，係犯刑法第320條第1項竊盜罪嫌。被告有如犯罪事實欄所載之論罪科刑執行情形，有刑案資料查註紀錄表在卷可稽，其於有期徒刑執行完畢後，5年以內故意再犯本件有期徒刑以上之罪，為累犯，請依刑法第47條第1項之規定加重其刑。三、依刑事訴訟法第451條第1項聲請逕以簡易判決處刑。此致臺灣基隆地方法院基隆簡易庭中華民國100年11月30日檢察官蔡妍蓁本件正本證明與原本無異中華民國100年12月8日書記官李曉旻附錄本案所犯法條全文中華民國刑法第320條（普通竊盜罪、竊佔罪）意圖為自己或第三人不法之所有，而竊取他人之動產者，為竊盜罪，處5年以下有期徒刑、拘役或5百元以下罰金。意圖為自己或第三人不法之利益，而竊佔他人之不動產者，依前項之規定處斷。前二項之未遂犯罰之。",
  "characters": {
    "judges": [
      "王福康"
    ],
    "prosecutors": [

    ],
    "lawyers": [

    ],
    "clerks": [
      "彭淑芳"
    ],
    "plaintiffs": [

    ],
    "defendants": [
      "張志宏",
      "張志宏  男  43歲（民國○○年○○月○日生）"
    ],
    "prosecutor_office": [
      "臺灣基隆地方法院檢察署檢察官"
    ],
    "creditors": [

    ],
    "debtors": [

    ],
    "judicial_associate_officer": [

    ]
  },
  "adjudged_at": "2011-12-20",
  "created_at": "2016-02-13 14:22:05",
  "updated_at": "2016-02-13 14:22:05"
}