{
  "identify": "TND-100-簡-2697-20111219-1",
  "court": {
    "name": "臺灣南投地方法院",
    "code": "TND"
  },
  "division": {
    "name": "刑事",
    "code": "M"
  },
  "year": 100,
  "word": "簡",
  "number": "2697",
  "jcheck": "1",
  "reason": "妨害名譽",
  "content": "臺灣臺南地方法院刑事簡易判決         100年度簡字第2697號\n聲  請  人  臺灣臺南地方法院檢察署檢察官\n被      告  楊成進\n上列被告因妨害名譽案件，經檢察官聲請以簡易判決處刑（100\n年度調偵字第1397號），本院判決如下：\n    主  文\n楊成進犯公然侮辱罪，處拘役拾日，如易科罰金，以新臺幣壹仟\n元折算壹日。\n    事實及理由\n一、本院認定被告楊成進之犯罪事實、證據及應適用之法條，與\n    檢察官聲請簡易判決處刑書之記載相同，茲引用之（如附件\n    ）。\n二、核被告所為，係犯刑法第309 條第1 項之公然侮辱罪。爰審\n    酌被告與告訴人乃姻親關係，不思和睦相處，因管教小孩理\n    念不同，率爾出言對告訴人加以辱罵，對告訴人之名譽、人\n    格評價造成傷害，且迄未與告訴人達成民事和解，賠償損害\n    ，並兼衡其犯後態度、前科素行、智識程度、生活狀況等一\n    切情狀，量處如主文所示之刑，並諭知易科罰金之折算標準\n    。\n三、應依刑事訴訟法第449 條第1 項前段、第454 條第2 項，刑\n    法第309 條第1 項、第41條第1 項前段，刑法施行法第1 條\n    之1，逕以簡易判決如主文。\n四、如不服本判決，應於判決送達之日起10日內，向本院提出上\n    訴狀。\n中    華    民    國   100    年    12    月    19    日\n                  刑事第八庭  法  官  蘇碧珠\n以上正本證明與原本無異。\n                              書記官  許哲萍\n中    華    民    國   100    年    12    月    19    日\n附錄本案論罪科刑法條全文\n中華民國刑法第309條第1項：\n公然侮辱人者，處拘役或 3 百元以下罰金。",
  "structure": {
    "main": "楊成進犯公然侮辱罪，處拘役拾日，如易科罰金，以新臺幣壹仟\n元折算壹日。",
    "fact": "一、本院認定被告楊成進之犯罪事實、證據及應適用之法條，與\n    檢察官聲請簡易判決處刑書之記載相同，茲引用之（如附件\n    ）。\n二、核被告所為，係犯刑法第309 條第1 項之公然侮辱罪。爰審\n    酌被告與告訴人乃姻親關係，不思和睦相處，因管教小孩理\n    念不同，率爾出言對告訴人加以辱罵，對告訴人之名譽、人\n    格評價造成傷害，且迄未與告訴人達成民事和解，賠償損害\n    ，並兼衡其犯後態度、前科素行、智識程度、生活狀況等一\n    切情狀，量處如主文所示之刑，並諭知易科罰金之折算標準\n    。\n三、應依刑事訴訟法第449 條第1 項前段、第454 條第2 項，刑\n    法第309 條第1 項、第41條第1 項前段，刑法施行法第1 條\n    之1，逕以簡易判決如主文。\n四、如不服本判決，應於判決送達之日起10日內，向本院提出上\n    訴狀。",
    "reason": "一、本院認定被告楊成進之犯罪事實、證據及應適用之法條，與\n    檢察官聲請簡易判決處刑書之記載相同，茲引用之（如附件\n    ）。\n二、核被告所為，係犯刑法第309 條第1 項之公然侮辱罪。爰審\n    酌被告與告訴人乃姻親關係，不思和睦相處，因管教小孩理\n    念不同，率爾出言對告訴人加以辱罵，對告訴人之名譽、人\n    格評價造成傷害，且迄未與告訴人達成民事和解，賠償損害\n    ，並兼衡其犯後態度、前科素行、智識程度、生活狀況等一\n    切情狀，量處如主文所示之刑，並諭知易科罰金之折算標準\n    。\n三、應依刑事訴訟法第449 條第1 項前段、第454 條第2 項，刑\n    法第309 條第1 項、第41條第1 項前段，刑法施行法第1 條\n    之1，逕以簡易判決如主文。\n四、如不服本判決，應於判決送達之日起10日內，向本院提出上\n    訴狀。"
  },
  "search": "臺灣臺南地方法院刑事簡易判決100年度簡字第2697號聲請人臺灣臺南地方法院檢察署檢察官被告楊成進上列被告因妨害名譽案件，經檢察官聲請以簡易判決處刑（100年度調偵字第1397號），本院判決如下：主文楊成進犯公然侮辱罪，處拘役拾日，如易科罰金，以新臺幣壹仟元折算壹日。事實及理由一、本院認定被告楊成進之犯罪事實、證據及應適用之法條，與檢察官聲請簡易判決處刑書之記載相同，茲引用之（如附件）。二、核被告所為，係犯刑法第309條第1項之公然侮辱罪。爰審酌被告與告訴人乃姻親關係，不思和睦相處，因管教小孩理念不同，率爾出言對告訴人加以辱罵，對告訴人之名譽、人格評價造成傷害，且迄未與告訴人達成民事和解，賠償損害，並兼衡其犯後態度、前科素行、智識程度、生活狀況等一切情狀，量處如主文所示之刑，並諭知易科罰金之折算標準。三、應依刑事訴訟法第449條第1項前段、第454條第2項，刑法第309條第1項、第41條第1項前段，刑法施行法第1條之1，逕以簡易判決如主文。四、如不服本判決，應於判決送達之日起10日內，向本院提出上訴狀。中華民國100年12月19日刑事第八庭法官蘇碧珠以上正本證明與原本無異。書記官許哲萍中華民國100年12月19日附錄本案論罪科刑法條全文中華民國刑法第309條第1項：公然侮辱人者，處拘役或3百元以下罰金。",
  "characters": {
    "judges": [
      "蘇碧珠"
    ],
    "prosecutors": [

    ],
    "lawyers": [

    ],
    "clerks": [
      "許哲萍"
    ],
    "plaintiffs": [

    ],
    "defendants": [
      "楊成進"
    ],
    "prosecutor_office": [
      "臺灣臺南地方法院檢察署檢察官"
    ],
    "creditors": [

    ],
    "debtors": [

    ],
    "judicial_associate_officer": [

    ]
  },
  "adjudged_at": "2011-12-19",
  "created_at": "2016-02-13 14:31:25",
  "updated_at": "2016-02-13 14:31:25"
}