{
  "identify": "TYD-100-訴-229-20111220-1",
  "court": {
    "name": "臺灣桃園地方法院",
    "code": "TYD"
  },
  "division": {
    "name": "刑事",
    "code": "M"
  },
  "year": 100,
  "word": "訴",
  "number": "229",
  "jcheck": "1",
  "reason": "違反槍砲彈藥刀械管制條例",
  "content": "臺灣桃園地方法院刑事判決              100年度訴字第229號\n公  訴  人  臺灣桃園地方法院檢察署檢察官\n被      告  簡瑞寬\n選任辯護人  何啟熏律師\n上列被告因槍砲彈藥刀械管制條例案件，經檢察官提起公訴（99\n年度偵字第12164 號），本院判決如下︰\n    主  文\n簡瑞寬無罪。\n    理  由\n壹、證據能力：\n一、扣案槍、彈鑑定報告之證據能力：\n    按「被告以外之人於審判外之言詞或書面陳述，除法律有規\n    定者外，不得作為證據」，刑事訴訟法第159條第1項固定有\n    明文，然「鑑定之經過及其結果，應命鑑定人以言詞或『書\n    面』報告」，同法第206條第1項亦規定甚明，是鑑定人以書\n    面為鑑定報告提出於法院，依刑事訴訟法第159條第1項立法\n    理由及同法第206條第1項規定，即具有證據能力。又法院或\n    檢察官得囑託醫院、學校或其他相當之機關、團體為鑑定，\n    或審查他人之鑑定，並準用第203條至第206條之1之規定，\n    刑事訴訟法第208條第1項亦定有明文。依此，檢察官對於偵\n    查中之案件，認須實施鑑定者，固應就具體個案，選任鑑定\n    人或囑託鑑定機關（團體）為之；但對於司法警察機關調查\n    中之案件，或有量大或急迫之情形，為因應實務之現實需求\n    ，如檢察官針對該類案件之性質（例如：查扣之毒品必須檢\n    驗其成份、對施用毒品之犯罪嫌疑人必須檢驗其體內有無毒\n    品代謝反應、對於查扣之槍砲彈藥必須檢驗有無殺傷力、對\n    違反野生動物保育法案件必須鑑定是否屬於保育類動物案件\n    等），認為當然有鑑定之必要者，經參看法務部92年5月20\n    日法檢字第092080203號函送之法務部「因應刑事訴訟法修\n    正工作小組」研討之刑事訴訟法修正相關議題第21則之共識\n    結論，以及臺灣高等法院於92年8月1日舉行之刑事訴訟法新\n    制法律問題研討會第三則法律問題研討結果之多數說（載於\n    司法院92年8月印行「刑事訴訟法新制法律問題彙編」第15\n    頁至第18頁），基於檢察一體原則，得由該管檢察長對於轄\n    區內之案件，以事前概括選任鑑定人或囑託鑑定機關（團體\n    ）之方式，俾便轄區內之司法警察官、司法警察對於調查中\n    之此類案件，得即時送請事前已選任之鑑定人或囑託之鑑定\n    機關（團體）實施鑑定，該鑑定人或鑑定機關（團體）亦應\n    視同受承辦檢察官所選任或囑託而執行鑑定業務，其等出具\n    之書面鑑定報告應屬刑事訴訟法第206條所定之傳聞例外，\n    當具有證據能力（參看法務部92年9月1日法檢字第09200350\n    83號函）。從而，本件扣案槍彈，經由查獲之桃園縣政府警\n    察局平鎮分局依先前轄區檢察署檢察長事前概括選任槍彈鑑\n    定機關即桃園縣政府警察局實施鑑定，而經該局出具99年4\n    月20日桃警鑑字第0990021734號鑑驗書，自應認具有證據能\n    力而得為本件之證據。再依上開說明，本院再命桃園縣政府\n    警察局鑑定扣案空氣槍在去除槍管前端之滅音器之狀態下之\n    動能，該局鑑定後以100 年10月4 日桃警鑑字第1000022257\n    號鑑定書回覆本院，該鑑定書亦具證據能力。\n二、按被告以外之人於審判外之言詞或書面陳述，除法律有規定\n    者外，不得作為證據。又被告以外之人於審判外之陳述，雖\n    不符前4 條之規定，而經當事人於審判程序同意作為證據，\n    法院審酌該言詞陳述或書面陳述作成時之情況，認為適當者\n    ，亦得為證據。當事人、代理人或辯護人於法院調查證據時\n    ，知有第159 條第1 項不得為證據之情形，而未於言詞辯論\n    終結前聲明異議者，視為有前項同意，刑事訴訟法159 條第\n    1 項、第159 條之5 分別定有明文。查證人湯喬偉之警詢陳\n    述，固係審判外之陳述而屬傳聞證據，惟被告及辯護人就上\n    開審判外之陳述，於本院審理中，知有該項證據，均未曾於\n    言詞辯論終結前聲明異議，而本院審酌該證人陳述作成時之\n    情況，並無違法取證及證明力過低之瑕疵，亦認以之作為證\n    據為適當，依前揭規定說明，自有證據能力。\n三、按被告以外之人於偵查中向檢察官所為之陳述，除顯有不可\n    信之情況者外，得為證據，刑事訴訟法第159 條之1 第2 項\n    定有明文。查證人湯僑偉偵查中於供前具結所為之陳述，係\n    檢察官依法訊問，復無其他事證足資認定其等於檢察官訊問\n    時有受違法取供情事，是自外部情況觀之，無顯不可信之情\n    況，是依上開規定有證據能力。\n四、被告簡瑞寬於99年4 月17日凌晨0 時40分許，搭乘友人潘博\n    文所駕駛之車號2216-PK 號自小客車，途經桃園縣平鎮市○\n    ○路153 巷7 弄8 號前經警盤查，潘博文乘隙逃逸，警方由\n    上開自小客車前擋風玻璃目擊在車內駕駛座、副駕駛座座椅\n    上各有1 支手槍，其中副駕駛座座椅上之手槍為被告所有之\n    空氣槍，有刑案現場照片附卷可稽，並經被告簡瑞寬於警詢\n    自承在卷，是可見被告與潘博文均涉現行犯，此時警方自得\n    依刑事訴訟法第130 條之規定為附帶搜索，是上開在副駕駛\n    座座椅上之空氣槍及警方嗣後在被告所攜帶之背包內所扣得\n    之瓦斯鋼瓶2 瓶、鋼珠1 包，均為合法搜索之所得，自具有\n    證據能力。\n五、另本件認定事實所引用之卷內其餘卷證資料，並無證據證明\n    係公務員違背法定程序所取得，被告及辯護人於審判程序中\n    復未於言詞辯論終結前表示異議，且卷內之文書證據，亦無\n    刑事訴訟法第159 條之4 之顯有不可信之情況與不得作為證\n    據之情形，則依刑事訴訟法第159 條之5 之規定，本件認定\n    事實所引用之所有文書證據，均有證據能力，合先敘明。\n貳、實體部分：\n一、公訴意旨以：被告簡瑞寬明知具有殺傷力之空氣槍1 枝（槍\n    枝管制編號桃警鑑0000000000）係為槍砲彈藥刀械管制條例\n    所管制之槍械，未經許可不得持有，竟於民國99年4 月15日\n    之某時，以新臺幣6000元之代價，在桃園縣大溪鎮○○路\n    135 號之「雷峰商行」購入後而持有之，嗣於99年4 月17日\n    凌晨0 時40分許，為警於桃園縣平鎮市○○路153 巷7 弄8\n    號前遭查獲，並扣得上開空氣長槍1 枝、瓦斯鋼瓶2 支、鋼\n    珠1 包，因認被告涉犯槍砲彈藥刀械管制條例第8 條第4 項\n    之罪嫌。\n二、按犯罪事實應依證據認定之，無證據不得認定犯罪事實；次\n    按不能證明被告犯罪或其行為不罰者，應諭知無罪之判決，\n    刑事訴訟法第154 條第2 項、第301 條第1 項，分別定有明\n    文。再按認定不利於被告之事實，須依積極證據，苟積極證\n    據不足為不利於被告事實之認定時，即應為有利於被告之認\n    定，更不必有何有利之證據，最高法院30年上字第816 號著\n    有判例；再按事實審法院對於證據之取捨，依法雖有自由判\n    斷之權，然積極證據不足證明犯罪事實時，被告之抗辯或反\n    證縱屬虛偽，仍不能以此資為積極證據應予採信之理由，又\n    認定犯罪事實應依證據，為刑事訴訟法所明定，故被告否認\n    犯罪事實所持之辯解，縱屬不能成立，仍非有積極證據足以\n    證明其犯罪行為，不能遽為有罪之認定，最高法院30年上字\n    第482 號、30年上字第1831號判例可資參照。\n三、經核公訴人認定被告簡瑞寬上開犯罪，無非係以如附件所之\n    證據清單，為其主要論據。訊據被告簡瑞寬固承認扣案之上\n    開空氣槍1 支、瓦斯鋼瓶2 瓶、鋼珠1 包，為其所有，然矢\n    口否犯行，辯稱：上開空氣槍1 支、瓦斯鋼瓶2 瓶、鋼珠1\n    包均係伊於99年4 月15日向桃園縣大溪鎮○○路135 號之「\n    阿偉槍館」之老闆湯喬偉買來的，伊於案發日要帶去魚池試\n    射，尚未試射即被查獲，伊未改造過上開空氣槍云云。辯護\n    人另辯稱：本案空氣槍經鑑定試射三顆彈丸，其中第1 、2\n    顆超過20焦耳／平方公分，但第2 顆若算入誤差值，則未超\n    過20焦耳／平方公分，本罪疑惟輕，應為無罪之判決。經查\n    ：(1)證人湯喬偉於99年6 月15日偵訊時證稱被告簡瑞寬於偵\n    查時所提出之售後服務卡是伊於99年4 月15日出售空氣槍給\n    被告簡瑞寬時所附的，該卡上面寫出售日期是90年4 月15日\n    是寫錯了，伊出售時有當場以測速器測試三發彈丸，測試的\n    初速就如該卡上所載之87米／秒、92米／秒、90米／秒等語\n    ；後於99年8 月4 日警詢時證稱伊販賣槍枝時，會在空氣槍\n    握把內做記號即刻上販售日期，但警方扣案之上開空氣槍經\n    伊會同警方檢視並未發現有記號，所以伊無法確定扣案之上\n    開空氣槍是否為伊販賣給被告簡瑞寬之空氣槍等語，其再於\n    99 年8月24日偵訊時證以該語，且於本院100 年8 月25日審\n    理時證稱警方於99年8 月3 日帶2 把槍請伊協助做測試，該\n    2 把槍都不是伊所販賣的，因為伊賣給簡瑞寬的槍都有槍枝\n    編號，刻在槍枝握把後面，而警方帶來的2 把槍枝都沒有這\n    樣的槍枝編號，伊之槍枝編號是刻當天販售的日期，伊用機\n    器雕刻筆刻在打開塑膠握把、刻在其內的金屬握把的後面，\n    伊所出售的空氣槍不可以單獨換握把，所以扣案之編號0000\n    000000號之空氣槍不是伊當初賣給被告簡瑞寬的槍枝等語。\n    是被告簡瑞寬辯稱扣案之上開空氣槍是其向湯喬偉買得云云\n    ，即無可信。(2)扣案之上開空氣槍雖經鑑定機關即桃園縣政\n    府警察局使用直徑約6MM 、重量0.88克金屬彈丸測速，經測\n    速結果第1 顆、第2 顆、第3 顆之速度分別為116 米／秒、\n    114 米／秒、113 米／秒，換算單位面積動能分別為20.94\n    焦耳／平方公分、20.22 焦耳／平方公分、19.87 焦耳／平\n    方公分。有桃園縣政府警察局出具之99年4 月20日桃警鑑字\n    第09900217 34 號鑑驗書附卷可稽。依日本科學警察之研究\n    結果，彈丸單位面積動能達20焦耳／平方公分，則足以穿入\n    人體皮肉層，我國司法實務亦普採彈丸單位面積動能達20焦\n    耳／平方公分為槍枝是否具殺傷力之認定準據。然依上開鑑\n    驗書同時記載，本件測速儀器之誤差率為±1 米／秒，依此\n    ，若誤差值為－1 米／秒，則第2 顆彈丸之單位面積動能與\n    第3 顆彈丸之單位面積動能相同，亦即均未達20焦耳／平方\n    公分。(3)證人即桃園縣政府警察局出具之99年4 月20 日 桃\n    警鑑字第0990021734號鑑驗書之實際鑑定人施信宏警官於本\n    院審理時證稱「（審判長問：你當時在測試的時候，有無裝\n    上滅音器？）證物到達我手上的時候就是有裝上滅音器的，\n    所以測試的時候我是以現狀測試，沒有將滅音器拆掉。」、\n    「（審判長問：有裝上滅音器或沒有裝上滅音器是否會影響\n    子彈速度？）會，槍管愈長，速度愈快，滅音器也算是槍管\n    的一部分。」、「（審判長問：為何你所作的陳述與證人湯\n    喬偉所作的陳述不同？）我沒有去測量滅音器與彈丸的密合\n    度，即我沒有測量滅音器的口徑。」、「（審判長問：假如\n    就滅音器的口徑比槍管要大，如證人湯喬偉所說本案的滅音\n    器口徑比槍管大，所以滅音器的口徑與彈丸比較沒有密合，\n    而會減緩子彈的速度，是否如此？）彈丸與槍管的密合度愈\n    高，子彈的速度愈快，反之就會慢。」等語。是以，本件自\n    有必要將扣案之上開空氣槍去除槍管前端所裝之滅音器測試\n    其之發射動能，本院依職權將扣案之上開空氣槍再送桃園縣\n    政府警察局鑑定其動能，經該局將扣案之上開空氣槍前端之\n    滅音器去除後，以直徑約5.99MM、重量0.88 克 金屬彈丸測\n    速，經測速結果第1 顆、第2 顆、第3 顆之速度分別為111\n    米／秒、113 米／秒、112 米／秒，換算單位面積動能分別\n    為19.23 焦耳／平方公分、19.90 焦耳／平方公分、19.55\n    焦耳／平方公分，有桃園縣政府警察局出具之100 年10月4\n    日桃警鑑字第1000022257號鑑定書附卷可稽。是該項鑑定結\n    果即將扣案之上開空氣槍前端之滅音器去除後，測試所得之\n    該空氣槍之動能較諸滅音器去除前為弱，是該鑑定結果與證\n    人施信宏於本院所證稱之槍管愈長、速度愈快相符。惟無論\n    如何，即使扣案之上開空氣槍加上滅音器所測得之單位面積\n    動能，若加上誤差值－1 米／秒，則測試之第2 顆彈丸之單\n    位面積動能與第3 顆彈丸之單位面積動能相同，即均在20焦\n    耳／平方公分以下，而僅有測試之第1 顆彈丸之單位面積動\n    能，即使算入誤差值－1 米／秒，仍在20焦耳／平方公分以\n    上。綜上所論，扣案之上開空氣槍經鑑定結果，其射擊適用\n    之彈丸不能穩定達到單位面積動能20焦耳／平方公分以上之\n    結論，依罪疑惟輕之原則，自不能認扣案之上開空氣槍具有\n    殺傷力。綜此，公訴人所舉證據尚不能證明被告之上開犯罪\n    ，自應依法諭知該被告無罪之判決。\n據上論斷，應依刑事訴訟法第301 條第1 項，判決如主文。\n本案經檢察官王齡梓到庭執行職務\n中    華    民    國  100     年    12    月    20    日\n                  刑事第三庭審判長法  官  曾家貽\n                                  法  官  吳芙蓉\n                                  法  官  曾雨明\n以上正本證明與原本無異。\n如不服本判決，應於判決送達後10日內向本院提出上訴狀（應附\n繕本），其未敘述上訴理由者，應於上訴期間屆滿後20日內補提\n理由書狀於本院。\n                                  書記官  李靜華\n中    華    民    國   100    年    12    月    27    日\n附件：\n ┌──┬───────────┬───────────────┐\n │編號│證據清單              │待證事實                      │\n ├──┼───────────┼───────────────┤\n │一  │被告簡瑞寬於警詢及本署│坦承持有具殺傷力空氣槍之事實，│\n │    │偵訊中之供述。        │惟辯稱該空氣槍購得時未曾改造過│\n │    │                      │，不知為何會有殺傷力。        │\n ├──┼───────────┼───────────────┤\n │二  │證人湯僑偉於本署偵訊中│被告持有之空氣槍是否為伊所售無│\n │    │之證述。              │法確定，然伊出售之空氣槍時均有│\n │    │                      │測試，初速並未超過113m/s，且扣│\n │    │                      │案之空氣槍握把並無註記編號。  │\n ├──┼───────────┼───────────────┤\n │三  │桃園縣政府警察局桃警鑑│扣案之空氣槍1把認係氣動式槍枝 │\n │    │字第0950008416號槍彈鑑│，以小型高壓氣體鋼瓶內氣體發射│\n │    │定書。                │動力，可發射直徑約6.0mm、量約 │\n │    │                      │0.88g之金屬彈丸，槍長約32cm、 │\n │    │                      │高約14cm，試射彈丸3顆，其單位 │\n │    │                      │面積動能（焦耳/平方公分）分別 │\n │    │                      │為20.94、20.22、19.87，具殺傷 │\n │    │                      │力之事實。                    │\n ├──┼───────────┼───────────────┤\n │四  │扣案之瓦斯空氣長槍1把 │被告持有具殺傷力空氣槍之事實。│\n │    │、瓦斯鋼瓶2支、鋼彈1包│                              │\n │    │、及查獲現場照片6張。 │                              │\n └──┴───────────┴───────────────┘",
  "structure": {
    "main": "簡瑞寬無罪。\n    理  由\n壹、證據能力：\n一、扣案槍、彈鑑定報告之證據能力：\n    按「被告以外之人於審判外之言詞或書面陳述，除法律有規\n    定者外，不得作為證據」，刑事訴訟法第159條第1項固定有\n    明文，然「鑑定之經過及其結果，應命鑑定人以言詞或『書\n    面』報告」，同法第206條第1項亦規定甚明，是鑑定人以書\n    面為鑑定報告提出於法院，依刑事訴訟法第159條第1項立法\n    理由及同法第206條第1項規定，即具有證據能力。又法院或\n    檢察官得囑託醫院、學校或其他相當之機關、團體為鑑定，\n    或審查他人之鑑定，並準用第203條至第206條之1之規定，\n    刑事訴訟法第208條第1項亦定有明文。依此，檢察官對於偵\n    查中之案件，認須實施鑑定者，固應就具體個案，選任鑑定\n    人或囑託鑑定機關（團體）為之；但對於司法警察機關調查\n    中之案件，或有量大或急迫之情形，為因應實務之現實需求\n    ，如檢察官針對該類案件之性質（例如：查扣之毒品必須檢\n    驗其成份、對施用毒品之犯罪嫌疑人必須檢驗其體內有無毒\n    品代謝反應、對於查扣之槍砲彈藥必須檢驗有無殺傷力、對\n    違反野生動物保育法案件必須鑑定是否屬於保育類動物案件\n    等），認為當然有鑑定之必要者，經參看法務部92年5月20\n    日法檢字第092080203號函送之法務部「因應刑事訴訟法修\n    正工作小組」研討之刑事訴訟法修正相關議題第21則之共識\n    結論，以及臺灣高等法院於92年8月1日舉行之刑事訴訟法新\n    制法律問題研討會第三則法律問題研討結果之多數說（載於\n    司法院92年8月印行「刑事訴訟法新制法律問題彙編」第15\n    頁至第18頁），基於檢察一體原則，得由該管檢察長對於轄\n    區內之案件，以事前概括選任鑑定人或囑託鑑定機關（團體\n    ）之方式，俾便轄區內之司法警察官、司法警察對於調查中\n    之此類案件，得即時送請事前已選任之鑑定人或囑託之鑑定\n    機關（團體）實施鑑定，該鑑定人或鑑定機關（團體）亦應\n    視同受承辦檢察官所選任或囑託而執行鑑定業務，其等出具\n    之書面鑑定報告應屬刑事訴訟法第206條所定之傳聞例外，\n    當具有證據能力（參看法務部92年9月1日法檢字第09200350\n    83號函）。從而，本件扣案槍彈，經由查獲之桃園縣政府警\n    察局平鎮分局依先前轄區檢察署檢察長事前概括選任槍彈鑑\n    定機關即桃園縣政府警察局實施鑑定，而經該局出具99年4\n    月20日桃警鑑字第0990021734號鑑驗書，自應認具有證據能\n    力而得為本件之證據。再依上開說明，本院再命桃園縣政府\n    警察局鑑定扣案空氣槍在去除槍管前端之滅音器之狀態下之\n    動能，該局鑑定後以100 年10月4 日桃警鑑字第1000022257\n    號鑑定書回覆本院，該鑑定書亦具證據能力。\n二、按被告以外之人於審判外之言詞或書面陳述，除法律有規定\n    者外，不得作為證據。又被告以外之人於審判外之陳述，雖\n    不符前4 條之規定，而經當事人於審判程序同意作為證據，\n    法院審酌該言詞陳述或書面陳述作成時之情況，認為適當者\n    ，亦得為證據。當事人、代理人或辯護人於法院調查證據時\n    ，知有第159 條第1 項不得為證據之情形，而未於言詞辯論\n    終結前聲明異議者，視為有前項同意，刑事訴訟法159 條第\n    1 項、第159 條之5 分別定有明文。查證人湯喬偉之警詢陳\n    述，固係審判外之陳述而屬傳聞證據，惟被告及辯護人就上\n    開審判外之陳述，於本院審理中，知有該項證據，均未曾於\n    言詞辯論終結前聲明異議，而本院審酌該證人陳述作成時之\n    情況，並無違法取證及證明力過低之瑕疵，亦認以之作為證\n    據為適當，依前揭規定說明，自有證據能力。\n三、按被告以外之人於偵查中向檢察官所為之陳述，除顯有不可\n    信之情況者外，得為證據，刑事訴訟法第159 條之1 第2 項\n    定有明文。查證人湯僑偉偵查中於供前具結所為之陳述，係\n    檢察官依法訊問，復無其他事證足資認定其等於檢察官訊問\n    時有受違法取供情事，是自外部情況觀之，無顯不可信之情\n    況，是依上開規定有證據能力。\n四、被告簡瑞寬於99年4 月17日凌晨0 時40分許，搭乘友人潘博\n    文所駕駛之車號2216-PK 號自小客車，途經桃園縣平鎮市○\n    ○路153 巷7 弄8 號前經警盤查，潘博文乘隙逃逸，警方由\n    上開自小客車前擋風玻璃目擊在車內駕駛座、副駕駛座座椅\n    上各有1 支手槍，其中副駕駛座座椅上之手槍為被告所有之\n    空氣槍，有刑案現場照片附卷可稽，並經被告簡瑞寬於警詢\n    自承在卷，是可見被告與潘博文均涉現行犯，此時警方自得\n    依刑事訴訟法第130 條之規定為附帶搜索，是上開在副駕駛\n    座座椅上之空氣槍及警方嗣後在被告所攜帶之背包內所扣得\n    之瓦斯鋼瓶2 瓶、鋼珠1 包，均為合法搜索之所得，自具有\n    證據能力。\n五、另本件認定事實所引用之卷內其餘卷證資料，並無證據證明\n    係公務員違背法定程序所取得，被告及辯護人於審判程序中\n    復未於言詞辯論終結前表示異議，且卷內之文書證據，亦無\n    刑事訴訟法第159 條之4 之顯有不可信之情況與不得作為證\n    據之情形，則依刑事訴訟法第159 條之5 之規定，本件認定\n    事實所引用之所有文書證據，均有證據能力，合先敘明。\n貳、實體部分：\n一、公訴意旨以：被告簡瑞寬明知具有殺傷力之空氣槍1 枝（槍\n    枝管制編號桃警鑑0000000000）係為槍砲彈藥刀械管制條例\n    所管制之槍械，未經許可不得持有，竟於民國99年4 月15日\n    之某時，以新臺幣6000元之代價，在桃園縣大溪鎮○○路\n    135 號之「雷峰商行」購入後而持有之，嗣於99年4 月17日\n    凌晨0 時40分許，為警於桃園縣平鎮市○○路153 巷7 弄8\n    號前遭查獲，並扣得上開空氣長槍1 枝、瓦斯鋼瓶2 支、鋼\n    珠1 包，因認被告涉犯槍砲彈藥刀械管制條例第8 條第4 項\n    之罪嫌。\n二、按犯罪事實應依證據認定之，無證據不得認定犯罪事實；次\n    按不能證明被告犯罪或其行為不罰者，應諭知無罪之判決，\n    刑事訴訟法第154 條第2 項、第301 條第1 項，分別定有明\n    文。再按認定不利於被告之事實，須依積極證據，苟積極證\n    據不足為不利於被告事實之認定時，即應為有利於被告之認\n    定，更不必有何有利之證據，最高法院30年上字第816 號著\n    有判例；再按事實審法院對於證據之取捨，依法雖有自由判\n    斷之權，然積極證據不足證明犯罪事實時，被告之抗辯或反\n    證縱屬虛偽，仍不能以此資為積極證據應予採信之理由，又\n    認定犯罪事實應依證據，為刑事訴訟法所明定，故被告否認",
    "fact": "證明其犯罪行為，不能遽為有罪之認定，最高法院30年上字\n    第482 號、30年上字第1831號判例可資參照。\n三、經核公訴人認定被告簡瑞寬上開犯罪，無非係以如附件所之\n    證據清單，為其主要論據。訊據被告簡瑞寬固承認扣案之上\n    開空氣槍1 支、瓦斯鋼瓶2 瓶、鋼珠1 包，為其所有，然矢\n    口否犯行，辯稱：上開空氣槍1 支、瓦斯鋼瓶2 瓶、鋼珠1\n    包均係伊於99年4 月15日向桃園縣大溪鎮○○路135 號之「\n    阿偉槍館」之老闆湯喬偉買來的，伊於案發日要帶去魚池試\n    射，尚未試射即被查獲，伊未改造過上開空氣槍云云。辯護\n    人另辯稱：本案空氣槍經鑑定試射三顆彈丸，其中第1 、2\n    顆超過20焦耳／平方公分，但第2 顆若算入誤差值，則未超\n    過20焦耳／平方公分，本罪疑惟輕，應為無罪之判決。經查\n    ：(1)證人湯喬偉於99年6 月15日偵訊時證稱被告簡瑞寬於偵\n    查時所提出之售後服務卡是伊於99年4 月15日出售空氣槍給\n    被告簡瑞寬時所附的，該卡上面寫出售日期是90年4 月15日\n    是寫錯了，伊出售時有當場以測速器測試三發彈丸，測試的\n    初速就如該卡上所載之87米／秒、92米／秒、90米／秒等語\n    ；後於99年8 月4 日警詢時證稱伊販賣槍枝時，會在空氣槍\n    握把內做記號即刻上販售日期，但警方扣案之上開空氣槍經\n    伊會同警方檢視並未發現有記號，所以伊無法確定扣案之上\n    開空氣槍是否為伊販賣給被告簡瑞寬之空氣槍等語，其再於\n    99 年8月24日偵訊時證以該語，且於本院100 年8 月25日審\n    理時證稱警方於99年8 月3 日帶2 把槍請伊協助做測試，該\n    2 把槍都不是伊所販賣的，因為伊賣給簡瑞寬的槍都有槍枝\n    編號，刻在槍枝握把後面，而警方帶來的2 把槍枝都沒有這\n    樣的槍枝編號，伊之槍枝編號是刻當天販售的日期，伊用機\n    器雕刻筆刻在打開塑膠握把、刻在其內的金屬握把的後面，\n    伊所出售的空氣槍不可以單獨換握把，所以扣案之編號0000\n    000000號之空氣槍不是伊當初賣給被告簡瑞寬的槍枝等語。\n    是被告簡瑞寬辯稱扣案之上開空氣槍是其向湯喬偉買得云云\n    ，即無可信。(2)扣案之上開空氣槍雖經鑑定機關即桃園縣政\n    府警察局使用直徑約6MM 、重量0.88克金屬彈丸測速，經測\n    速結果第1 顆、第2 顆、第3 顆之速度分別為116 米／秒、\n    114 米／秒、113 米／秒，換算單位面積動能分別為20.94\n    焦耳／平方公分、20.22 焦耳／平方公分、19.87 焦耳／平\n    方公分。有桃園縣政府警察局出具之99年4 月20日桃警鑑字\n    第09900217 34 號鑑驗書附卷可稽。依日本科學警察之研究\n    結果，彈丸單位面積動能達20焦耳／平方公分，則足以穿入\n    人體皮肉層，我國司法實務亦普採彈丸單位面積動能達20焦\n    耳／平方公分為槍枝是否具殺傷力之認定準據。然依上開鑑\n    驗書同時記載，本件測速儀器之誤差率為±1 米／秒，依此\n    ，若誤差值為－1 米／秒，則第2 顆彈丸之單位面積動能與\n    第3 顆彈丸之單位面積動能相同，亦即均未達20焦耳／平方\n    公分。(3)證人即桃園縣政府警察局出具之99年4 月20 日 桃\n    警鑑字第0990021734號鑑驗書之實際鑑定人施信宏警官於本\n    院審理時證稱「（審判長問：你當時在測試的時候，有無裝\n    上滅音器？）證物到達我手上的時候就是有裝上滅音器的，\n    所以測試的時候我是以現狀測試，沒有將滅音器拆掉。」、\n    「（審判長問：有裝上滅音器或沒有裝上滅音器是否會影響\n    子彈速度？）會，槍管愈長，速度愈快，滅音器也算是槍管\n    的一部分。」、「（審判長問：為何你所作的陳述與證人湯\n    喬偉所作的陳述不同？）我沒有去測量滅音器與彈丸的密合\n    度，即我沒有測量滅音器的口徑。」、「（審判長問：假如\n    就滅音器的口徑比槍管要大，如證人湯喬偉所說本案的滅音\n    器口徑比槍管大，所以滅音器的口徑與彈丸比較沒有密合，\n    而會減緩子彈的速度，是否如此？）彈丸與槍管的密合度愈\n    高，子彈的速度愈快，反之就會慢。」等語。是以，本件自\n    有必要將扣案之上開空氣槍去除槍管前端所裝之滅音器測試\n    其之發射動能，本院依職權將扣案之上開空氣槍再送桃園縣\n    政府警察局鑑定其動能，經該局將扣案之上開空氣槍前端之\n    滅音器去除後，以直徑約5.99MM、重量0.88 克 金屬彈丸測\n    速，經測速結果第1 顆、第2 顆、第3 顆之速度分別為111\n    米／秒、113 米／秒、112 米／秒，換算單位面積動能分別\n    為19.23 焦耳／平方公分、19.90 焦耳／平方公分、19.55\n    焦耳／平方公分，有桃園縣政府警察局出具之100 年10月4\n    日桃警鑑字第1000022257號鑑定書附卷可稽。是該項鑑定結\n    果即將扣案之上開空氣槍前端之滅音器去除後，測試所得之\n    該空氣槍之動能較諸滅音器去除前為弱，是該鑑定結果與證\n    人施信宏於本院所證稱之槍管愈長、速度愈快相符。惟無論\n    如何，即使扣案之上開空氣槍加上滅音器所測得之單位面積\n    動能，若加上誤差值－1 米／秒，則測試之第2 顆彈丸之單\n    位面積動能與第3 顆彈丸之單位面積動能相同，即均在20焦\n    耳／平方公分以下，而僅有測試之第1 顆彈丸之單位面積動\n    能，即使算入誤差值－1 米／秒，仍在20焦耳／平方公分以\n    上。綜上所論，扣案之上開空氣槍經鑑定結果，其射擊適用\n    之彈丸不能穩定達到單位面積動能20焦耳／平方公分以上之\n    結論，依罪疑惟輕之原則，自不能認扣案之上開空氣槍具有\n    殺傷力。綜此，公訴人所舉證據尚不能證明被告之上開犯罪\n    ，自應依法諭知該被告無罪之判決。\n據上論斷，應依刑事訴訟法第301 條第1 項，判決如主文。\n本案經檢察官王齡梓到庭執行職務"
  },
  "search": "臺灣桃園地方法院刑事判決100年度訴字第229號公訴人臺灣桃園地方法院檢察署檢察官被告簡瑞寬選任辯護人何啟熏律師上列被告因槍砲彈藥刀械管制條例案件，經檢察官提起公訴（99年度偵字第12164號），本院判決如下︰主文簡瑞寬無罪。理由壹、證據能力：一、扣案槍、彈鑑定報告之證據能力：按「被告以外之人於審判外之言詞或書面陳述，除法律有規定者外，不得作為證據」，刑事訴訟法第159條第1項固定有明文，然「鑑定之經過及其結果，應命鑑定人以言詞或『書面』報告」，同法第206條第1項亦規定甚明，是鑑定人以書面為鑑定報告提出於法院，依刑事訴訟法第159條第1項立法理由及同法第206條第1項規定，即具有證據能力。又法院或檢察官得囑託醫院、學校或其他相當之機關、團體為鑑定，或審查他人之鑑定，並準用第203條至第206條之1之規定，刑事訴訟法第208條第1項亦定有明文。依此，檢察官對於偵查中之案件，認須實施鑑定者，固應就具體個案，選任鑑定人或囑託鑑定機關（團體）為之；但對於司法警察機關調查中之案件，或有量大或急迫之情形，為因應實務之現實需求，如檢察官針對該類案件之性質（例如：查扣之毒品必須檢驗其成份、對施用毒品之犯罪嫌疑人必須檢驗其體內有無毒品代謝反應、對於查扣之槍砲彈藥必須檢驗有無殺傷力、對違反野生動物保育法案件必須鑑定是否屬於保育類動物案件等），認為當然有鑑定之必要者，經參看法務部92年5月20日法檢字第092080203號函送之法務部「因應刑事訴訟法修正工作小組」研討之刑事訴訟法修正相關議題第21則之共識結論，以及臺灣高等法院於92年8月1日舉行之刑事訴訟法新制法律問題研討會第三則法律問題研討結果之多數說（載於司法院92年8月印行「刑事訴訟法新制法律問題彙編」第15頁至第18頁），基於檢察一體原則，得由該管檢察長對於轄區內之案件，以事前概括選任鑑定人或囑託鑑定機關（團體）之方式，俾便轄區內之司法警察官、司法警察對於調查中之此類案件，得即時送請事前已選任之鑑定人或囑託之鑑定機關（團體）實施鑑定，該鑑定人或鑑定機關（團體）亦應視同受承辦檢察官所選任或囑託而執行鑑定業務，其等出具之書面鑑定報告應屬刑事訴訟法第206條所定之傳聞例外，當具有證據能力（參看法務部92年9月1日法檢字第0920035083號函）。從而，本件扣案槍彈，經由查獲之桃園縣政府警察局平鎮分局依先前轄區檢察署檢察長事前概括選任槍彈鑑定機關即桃園縣政府警察局實施鑑定，而經該局出具99年4月20日桃警鑑字第0990021734號鑑驗書，自應認具有證據能力而得為本件之證據。再依上開說明，本院再命桃園縣政府警察局鑑定扣案空氣槍在去除槍管前端之滅音器之狀態下之動能，該局鑑定後以100年10月4日桃警鑑字第1000022257號鑑定書回覆本院，該鑑定書亦具證據能力。二、按被告以外之人於審判外之言詞或書面陳述，除法律有規定者外，不得作為證據。又被告以外之人於審判外之陳述，雖不符前4條之規定，而經當事人於審判程序同意作為證據，法院審酌該言詞陳述或書面陳述作成時之情況，認為適當者，亦得為證據。當事人、代理人或辯護人於法院調查證據時，知有第159條第1項不得為證據之情形，而未於言詞辯論終結前聲明異議者，視為有前項同意，刑事訴訟法159條第1項、第159條之5分別定有明文。查證人湯喬偉之警詢陳述，固係審判外之陳述而屬傳聞證據，惟被告及辯護人就上開審判外之陳述，於本院審理中，知有該項證據，均未曾於言詞辯論終結前聲明異議，而本院審酌該證人陳述作成時之情況，並無違法取證及證明力過低之瑕疵，亦認以之作為證據為適當，依前揭規定說明，自有證據能力。三、按被告以外之人於偵查中向檢察官所為之陳述，除顯有不可信之情況者外，得為證據，刑事訴訟法第159條之1第2項定有明文。查證人湯僑偉偵查中於供前具結所為之陳述，係檢察官依法訊問，復無其他事證足資認定其等於檢察官訊問時有受違法取供情事，是自外部情況觀之，無顯不可信之情況，是依上開規定有證據能力。四、被告簡瑞寬於99年4月17日凌晨0時40分許，搭乘友人潘博文所駕駛之車號2216-PK號自小客車，途經桃園縣平鎮市○○路153巷7弄8號前經警盤查，潘博文乘隙逃逸，警方由上開自小客車前擋風玻璃目擊在車內駕駛座、副駕駛座座椅上各有1支手槍，其中副駕駛座座椅上之手槍為被告所有之空氣槍，有刑案現場照片附卷可稽，並經被告簡瑞寬於警詢自承在卷，是可見被告與潘博文均涉現行犯，此時警方自得依刑事訴訟法第130條之規定為附帶搜索，是上開在副駕駛座座椅上之空氣槍及警方嗣後在被告所攜帶之背包內所扣得之瓦斯鋼瓶2瓶、鋼珠1包，均為合法搜索之所得，自具有證據能力。五、另本件認定事實所引用之卷內其餘卷證資料，並無證據證明係公務員違背法定程序所取得，被告及辯護人於審判程序中復未於言詞辯論終結前表示異議，且卷內之文書證據，亦無刑事訴訟法第159條之4之顯有不可信之情況與不得作為證據之情形，則依刑事訴訟法第159條之5之規定，本件認定事實所引用之所有文書證據，均有證據能力，合先敘明。貳、實體部分：一、公訴意旨以：被告簡瑞寬明知具有殺傷力之空氣槍1枝（槍枝管制編號桃警鑑0000000000）係為槍砲彈藥刀械管制條例所管制之槍械，未經許可不得持有，竟於民國99年4月15日之某時，以新臺幣6000元之代價，在桃園縣大溪鎮○○路135號之「雷峰商行」購入後而持有之，嗣於99年4月17日凌晨0時40分許，為警於桃園縣平鎮市○○路153巷7弄8號前遭查獲，並扣得上開空氣長槍1枝、瓦斯鋼瓶2支、鋼珠1包，因認被告涉犯槍砲彈藥刀械管制條例第8條第4項之罪嫌。二、按犯罪事實應依證據認定之，無證據不得認定犯罪事實；次按不能證明被告犯罪或其行為不罰者，應諭知無罪之判決，刑事訴訟法第154條第2項、第301條第1項，分別定有明文。再按認定不利於被告之事實，須依積極證據，苟積極證據不足為不利於被告事實之認定時，即應為有利於被告之認定，更不必有何有利之證據，最高法院30年上字第816號著有判例；再按事實審法院對於證據之取捨，依法雖有自由判斷之權，然積極證據不足證明犯罪事實時，被告之抗辯或反證縱屬虛偽，仍不能以此資為積極證據應予採信之理由，又認定犯罪事實應依證據，為刑事訴訟法所明定，故被告否認犯罪事實所持之辯解，縱屬不能成立，仍非有積極證據足以證明其犯罪行為，不能遽為有罪之認定，最高法院30年上字第482號、30年上字第1831號判例可資參照。三、經核公訴人認定被告簡瑞寬上開犯罪，無非係以如附件所之證據清單，為其主要論據。訊據被告簡瑞寬固承認扣案之上開空氣槍1支、瓦斯鋼瓶2瓶、鋼珠1包，為其所有，然矢口否犯行，辯稱：上開空氣槍1支、瓦斯鋼瓶2瓶、鋼珠1包均係伊於99年4月15日向桃園縣大溪鎮○○路135號之「阿偉槍館」之老闆湯喬偉買來的，伊於案發日要帶去魚池試射，尚未試射即被查獲，伊未改造過上開空氣槍云云。辯護人另辯稱：本案空氣槍經鑑定試射三顆彈丸，其中第1、2顆超過20焦耳／平方公分，但第2顆若算入誤差值，則未超過20焦耳／平方公分，本罪疑惟輕，應為無罪之判決。經查：(1)證人湯喬偉於99年6月15日偵訊時證稱被告簡瑞寬於偵查時所提出之售後服務卡是伊於99年4月15日出售空氣槍給被告簡瑞寬時所附的，該卡上面寫出售日期是90年4月15日是寫錯了，伊出售時有當場以測速器測試三發彈丸，測試的初速就如該卡上所載之87米／秒、92米／秒、90米／秒等語；後於99年8月4日警詢時證稱伊販賣槍枝時，會在空氣槍握把內做記號即刻上販售日期，但警方扣案之上開空氣槍經伊會同警方檢視並未發現有記號，所以伊無法確定扣案之上開空氣槍是否為伊販賣給被告簡瑞寬之空氣槍等語，其再於99年8月24日偵訊時證以該語，且於本院100年8月25日審理時證稱警方於99年8月3日帶2把槍請伊協助做測試，該2把槍都不是伊所販賣的，因為伊賣給簡瑞寬的槍都有槍枝編號，刻在槍枝握把後面，而警方帶來的2把槍枝都沒有這樣的槍枝編號，伊之槍枝編號是刻當天販售的日期，伊用機器雕刻筆刻在打開塑膠握把、刻在其內的金屬握把的後面，伊所出售的空氣槍不可以單獨換握把，所以扣案之編號0000000000號之空氣槍不是伊當初賣給被告簡瑞寬的槍枝等語。是被告簡瑞寬辯稱扣案之上開空氣槍是其向湯喬偉買得云云，即無可信。(2)扣案之上開空氣槍雖經鑑定機關即桃園縣政府警察局使用直徑約6MM、重量0.88克金屬彈丸測速，經測速結果第1顆、第2顆、第3顆之速度分別為116米／秒、114米／秒、113米／秒，換算單位面積動能分別為20.94焦耳／平方公分、20.22焦耳／平方公分、19.87焦耳／平方公分。有桃園縣政府警察局出具之99年4月20日桃警鑑字第0990021734號鑑驗書附卷可稽。依日本科學警察之研究結果，彈丸單位面積動能達20焦耳／平方公分，則足以穿入人體皮肉層，我國司法實務亦普採彈丸單位面積動能達20焦耳／平方公分為槍枝是否具殺傷力之認定準據。然依上開鑑驗書同時記載，本件測速儀器之誤差率為±1米／秒，依此，若誤差值為－1米／秒，則第2顆彈丸之單位面積動能與第3顆彈丸之單位面積動能相同，亦即均未達20焦耳／平方公分。(3)證人即桃園縣政府警察局出具之99年4月20日桃警鑑字第0990021734號鑑驗書之實際鑑定人施信宏警官於本院審理時證稱「（審判長問：你當時在測試的時候，有無裝上滅音器？）證物到達我手上的時候就是有裝上滅音器的，所以測試的時候我是以現狀測試，沒有將滅音器拆掉。」、「（審判長問：有裝上滅音器或沒有裝上滅音器是否會影響子彈速度？）會，槍管愈長，速度愈快，滅音器也算是槍管的一部分。」、「（審判長問：為何你所作的陳述與證人湯喬偉所作的陳述不同？）我沒有去測量滅音器與彈丸的密合度，即我沒有測量滅音器的口徑。」、「（審判長問：假如就滅音器的口徑比槍管要大，如證人湯喬偉所說本案的滅音器口徑比槍管大，所以滅音器的口徑與彈丸比較沒有密合，而會減緩子彈的速度，是否如此？）彈丸與槍管的密合度愈高，子彈的速度愈快，反之就會慢。」等語。是以，本件自有必要將扣案之上開空氣槍去除槍管前端所裝之滅音器測試其之發射動能，本院依職權將扣案之上開空氣槍再送桃園縣政府警察局鑑定其動能，經該局將扣案之上開空氣槍前端之滅音器去除後，以直徑約5.99MM、重量0.88克金屬彈丸測速，經測速結果第1顆、第2顆、第3顆之速度分別為111米／秒、113米／秒、112米／秒，換算單位面積動能分別為19.23焦耳／平方公分、19.90焦耳／平方公分、19.55焦耳／平方公分，有桃園縣政府警察局出具之100年10月4日桃警鑑字第1000022257號鑑定書附卷可稽。是該項鑑定結果即將扣案之上開空氣槍前端之滅音器去除後，測試所得之該空氣槍之動能較諸滅音器去除前為弱，是該鑑定結果與證人施信宏於本院所證稱之槍管愈長、速度愈快相符。惟無論如何，即使扣案之上開空氣槍加上滅音器所測得之單位面積動能，若加上誤差值－1米／秒，則測試之第2顆彈丸之單位面積動能與第3顆彈丸之單位面積動能相同，即均在20焦耳／平方公分以下，而僅有測試之第1顆彈丸之單位面積動能，即使算入誤差值－1米／秒，仍在20焦耳／平方公分以上。綜上所論，扣案之上開空氣槍經鑑定結果，其射擊適用之彈丸不能穩定達到單位面積動能20焦耳／平方公分以上之結論，依罪疑惟輕之原則，自不能認扣案之上開空氣槍具有殺傷力。綜此，公訴人所舉證據尚不能證明被告之上開犯罪，自應依法諭知該被告無罪之判決。據上論斷，應依刑事訴訟法第301條第1項，判決如主文。本案經檢察官王齡梓到庭執行職務中華民國100年12月20日刑事第三庭審判長法官曾家貽法官吳芙蓉法官曾雨明以上正本證明與原本無異。如不服本判決，應於判決送達後10日內向本院提出上訴狀（應附繕本），其未敘述上訴理由者，應於上訴期間屆滿後20日內補提理由書狀於本院。書記官李靜華中華民國100年12月27日附件：┌──┬───────────┬───────────────┐│編號│證據清單│待證事實│├──┼───────────┼───────────────┤│一│被告簡瑞寬於警詢及本署│坦承持有具殺傷力空氣槍之事實，│││偵訊中之供述。│惟辯稱該空氣槍購得時未曾改造過││││，不知為何會有殺傷力。│├──┼───────────┼───────────────┤│二│證人湯僑偉於本署偵訊中│被告持有之空氣槍是否為伊所售無│││之證述。│法確定，然伊出售之空氣槍時均有││││測試，初速並未超過113m/s，且扣││││案之空氣槍握把並無註記編號。│├──┼───────────┼───────────────┤│三│桃園縣政府警察局桃警鑑│扣案之空氣槍1把認係氣動式槍枝│││字第0950008416號槍彈鑑│，以小型高壓氣體鋼瓶內氣體發射│││定書。│動力，可發射直徑約6.0mm、量約││││0.88g之金屬彈丸，槍長約32cm、││││高約14cm，試射彈丸3顆，其單位││││面積動能（焦耳/平方公分）分別││││為20.94、20.22、19.87，具殺傷││││力之事實。│├──┼───────────┼───────────────┤│四│扣案之瓦斯空氣長槍1把│被告持有具殺傷力空氣槍之事實。│││、瓦斯鋼瓶2支、鋼彈1包││││、及查獲現場照片6張。││└──┴───────────┴───────────────┘",
  "characters": {
    "judges": [
      "曾家貽",
      "吳芙蓉",
      "曾雨明"
    ],
    "prosecutors": [
      "王齡梓"
    ],
    "lawyers": [
      "何啟熏"
    ],
    "clerks": [
      "李靜華"
    ],
    "plaintiffs": [

    ],
    "defendants": [
      "簡瑞寬"
    ],
    "prosecutor_office": [
      "臺灣桃園地方法院檢察署檢察官"
    ],
    "creditors": [

    ],
    "debtors": [

    ],
    "judicial_associate_officer": [

    ]
  },
  "adjudged_at": "2011-12-20",
  "created_at": "2016-02-13 14:20:01",
  "updated_at": "2016-02-13 14:20:01"
}