{
  "identify": "TPH-93-上易-2059-20050524-1",
  "court": {
    "name": "臺灣高等法院",
    "code": "TPH"
  },
  "division": {
    "name": "刑事",
    "code": "M"
  },
  "year": 93,
  "word": "上易",
  "number": "2059",
  "jcheck": "1",
  "reason": "竊盜等",
  "content": "臺灣高等法院刑事判決                93年度上易字第2059號\n上  訴  人  臺灣板橋地方法院檢察署檢察官\n被      告  丁○○\n                      十五弄三十四號三樓之二\n            庚○○\n上  一  人\n選任辯護人  邱群傑律師\n            許卓敏律師\n上列上訴人因被告等竊盜等案件，不服臺灣板橋地方法院92年度\n易字第2277號，中華民國93年10月29日第一審判決（起訴案號：\n臺灣板橋地方法院檢察署92年度偵字第2627號），提起上訴，本\n院判決如下：\n    主  文\n上訴駁回。\n    理  由\n一、本案經本院審理結果，認第一審判決對被告丁○○、庚○○\n    均為無罪之諭知，核無不當，應予維持，並引用第一審判決\n    書記載之證據及理由（如附件）。\n二、檢察官上訴意旨略以：\n（一）被告丁○○於偵查及原審審理時，對於贓物之來源前後供\n      述不一，被告於偵查中或原審審理中之所辯，均屬卸責之\n      詞，難謂原判決翔實無誤。\n（二）被害人等前往台北縣警察局三重分局認領贓物時，均表示\n      如有冒領願法律責任，而於贓物認領保管單簽名署押，足\n      認被害人等所具領之物品，悉屬贓物無疑，原判決以該等\n      物品是否確係失竊，尚值懷疑，尚有未洽。\n（三）被告庚○○有多次因贓物罪嫌而獲不起訴處分之案件，則\n      被告庚○○對於所購入他人所販來源不明之物有更高之注\n      意查核之義務，竟數度以低於市價之價格購買來源不明之\n      物，被告庚○○有不確定故買贓物之故意彰彰甚明云云。\n三、惟查：\n（一）認定犯罪事實應依證據，為刑事訴訟法所明定，故被告否\n      認犯罪事實所持之辯解，縱屬不能成立，仍非有積極證據\n      足以證明其犯罪行為，不能遽為有罪之認定。最高法院30\n      年上字第1831號著有判例可資參照。檢察官上訴意旨以：\n      被告丁○○於偵查及原審審理時，對於贓物之來源前後供\n      述不一，所辯均屬卸責之詞云云，縱認屬實，亦非有積極\n      證據足資證明被告丁○○有檢察官所指之竊盜犯行，法院\n      不得僅憑被告丁○○於偵審中之供述不一，而遽為被告丁\n      ○○有罪之判決。檢察官此部分上訴理由，顯無可採。\n（二）被害人楊超為、戊○○、丙○○、王文良、李金煌、林明\n      德、林廷弘、陳明池、鄭國珍、李永成、曹進和等人於原\n      審審理時均證稱其等並未因失竊而向警報案，被害人等既\n      未報案而無紀錄可資查考，則究竟被害人等確有無失竊本\n      件檢察官所指之主機、面板等物，即乏證據證明而非無可\n      疑；且該等主機、面板上並無任何足茲辨明其間之差異之\n      記載或特徵，欲認定該等物品係贓物，僅能憑藉眾被害人\n      對於自己物品之記憶力爾。其中證人王文良、楊文強、李\n      金煌、李俊慶、陳明池等人明白證稱係以一模一樣、機型\n      相同、大同小異等，為其認領之依據；另證人己○○、陳\n      明宗、鄭國珍及李永成則以手擦痕跡、認得出來、有做記\n      號等為依據。惟衡諸常情，將極易失竊之物品在不妨害其\n      價值及功效之情形下標示記號，雖可理解，然前揭證人等\n      對於其等所認領之物與他人之物之區別，顯有模糊不明確\n      之情形，在此等情況下，渠等填載贓物領據所認領之無線\n      電主機、面板等物，是否確係失竊之物，殊值懷疑等情，\n      業據原判決於理由欄內論述甚明，亦核與日常生活經驗無\n      所違背。檢察官上訴意旨，徒以被害人等認領查扣物品時\n      業已書具認領保管單，表示願負擔法律上之責任，即認該\n      等物品確屬贓物，尚嫌率斷，顯無足取。\n（三）對於無線電主機及面板之價格，同案被告李逸龍證稱係以\n      面板新台幣（下同）1500至2000元、機身連面板2500至\n      3500元賣給被告庚○○，賣了3次，得款11000元左右。\n      而證人戊○○證稱：伊買舊的無線電主機含面板，大約價\n      值4、5000元；證人丙○○證稱：伊買新的主機含面板約\n      8000多元；證人楊文強證稱：我那時裝到好12000元，那是\n      舊的，編號是Ｖ七型。證人己○○證稱：面板大約價值\n      4、5000元，一部主機13500元，機型是Ｖ七（均見原審93\n      年9月16日審判筆錄）。證人陳明宗證稱：無線電主機含面\n      板新機買來10000多元；證人李永成證稱：無線電主機含面\n      板買中古的，值7000多元等（均見原審93年10月15日審判\n      筆錄。由上開多名證人證述情節觀之，無線電主機含面板\n      的中古機型價格略有4、5000元至7、8000元不等，甚有至\n      萬餘元，可見不同機型、年份以及使用狀況均影響到中古\n      機型之價格，然以李逸龍所證述上開販售予庚○○之價格\n      ，雖與證人等所證述之中古機型之買入價格稍低，惟能否\n      遽認與市場行情顯不相當，非無斟酌之餘地。且被告庚○\n      ○既係以收購中古無線電主機及面板，再予以販售之方式\n      以賺取差價，則在商言商，其壓低向李逸龍收購之價格，\n      再以較高價錢賣出，係屬當然之理，亦符合社會一般交易\n      常規，惟於法尚不得因此遽認庚○○係明知贓物而買受。\n      亦據原判決於理由欄內詳予論述。檢察官上訴意旨徒以被\n      告庚○○有多次因贓物罪嫌而獲不起訴處分之案件，而認\n      被告庚○○對於所購入他人所販來源不明之物有更高之注\n      意查核之義務，而無視於前引證人等關於中古機型之不同\n      價格之證述，率認被告庚○○數度以低於市價之價格購買\n      來源不明之物，必有不確定故買贓物之故意，於法尚非有\n      據，此等出於臆測之上訴理由，顯無可取。\n四、綜上所述，檢察官前述上訴意旨所陳各節，於法均非可採。\n    其執此上訴意旨，任意指摘原判決不當，求予撤銷改判，顯\n    無理由，應予駁回其上訴。\n據上論結，應依刑事訴訟法第373條、第368條，判決如主文。\n本案經檢察官李良忠到庭執行職務。\n中    華    民    國    94    年    5     月    24    日\n                  刑事第六庭審判長法  官  許國宏\n                                  法  官  洪光燦\n                                  法  官  林銓正\n以上正本證明與原本無異。\n不得上訴。\n                                  書記官  陳玲憶\n中    華    民    國    94    年    5     月    26    日\n附件：\n臺灣板橋地方法院刑事判決      九十二年度易字第二二七七號\n    公  訴  人  臺灣板橋地方法院檢察署檢察官\n    被      告  丁○○  男  31歲（民國○○年○月○○日生）\n                        住桃園縣楊梅鎮○○○路○段390巷\n                          巷45弄34號3樓之2\n                        身分證統一編號：Ｚ000000000號\n                庚○○  男  47歲（民國○○年○月○○日生）\n                        住臺北縣三重市○○路○段67號\n                        身分證統一編號：Ｚ000000000號\n    右一人\n    選任辯護人  邱群傑律師\n                許卓敏律師\n右列被告等因竊盜等案件，經檢察官提起公訴（九十二年度偵字\n第二六二七號、第四九三一號、第六六四一號、第一一二八號\n、第一四四號、第一一二七七號），本院判決如左：\n    主  文\n丁○○、庚○○均無罪。\n    理  由\n一、公訴意旨略以：\n（一）被告李逸龍、林炳志（均已結）共同基於意圖為自己不法\n      所有之概括犯意聯絡，連續在附表所示之時、地，竊取如\n      附表所示被害人財物（詳細行竊時間、地點、行為人、手\n      法、所得財物等，均如附表所示），並將上開竊得之無線\n      電主機與面板等物持向被告庚○○所開設位於臺北縣三重\n      市○○路○段六七號之「富貴無線電專賣店」（現改名「\n      中野通訊社」）變賣，所得由二人朋分花用。被告庚○○\n      明知上開無線電主機及面板等物均係李逸龍、林炳志二人\n      竊得之贓物，竟仍基於故買贓物之概括犯意，自九十一年\n      九月間某日起，迄九十二年一月間止，連續在其所開設位\n      於臺北縣三重市○○路○段六七號之「富貴無線電專賣店\n      」內，以低於市價四分之一之價格購入。嗣於九十二年一\n      月十七日二十一時許，經警在庚○○所開設之前揭通訊行\n      內，查獲ＫＥＮＷＯＯＤ牌車裝無線電ＴＭ─七三三型四\n      台、無線電面板六具、ＴＭ─Ｖ七型車裝無線電一台、無\n      線電面板三具、ＴＭ─七三二型無線電面板三具後，循線\n      查獲上情。\n（二）被告丁○○基於意圖為自己不法所有之概括犯意，以擊破\n      車窗之方式，連續(1)於九十一年十月十日零時許，在臺北\n      縣三重市○○○路五十四號前，竊取被害人林俊毅所有車\n      裝音響主機一台、螢幕一台；(2)於九十一年十一月十五日\n      ，在臺北縣新莊市○○街九號二樓，竊取被害人陳文炳所\n      有之手提電腦一台；(3)於九十一年十二月三十日，在臺北\n      縣板橋市○○路九十三巷三號，竊取被害人甲○○所有之\n      手提電腦一台；(4)於九十二年一月十六日二時許，在臺北\n      縣中和市○○路八八九號地下停車場，竊取被害人黃昭維\n      所有之中華民國護照一本、太陽眼鏡二副、明牌皮夾二個\n      ；(5)於九十二年一月十七日七時許，在臺北市○○區○○\n      街二八四巷三六弄二二號地下停車場，竊取被害人江佰卿\n      所有之車內音響主機一台、液晶螢幕一台、ＣＤ盒一個、\n      車用音響轉換器一台；(6)於九十二年一月十七日七時三十\n      分許，在臺北市○○區○○街二八四巷三十弄八三號地下\n      室，竊取被害人乙○○所有之中國信託信用卡一張、何嘉\n      仁書店貴賓卡一張、太陽眼鏡一副。嗣於九十二年一月十\n      七日二十三時五十分許，經警在丁○○位於臺北縣中和市\n      ○○街十四巷四十弄十二之二號三樓住處，查獲筆記型電\n      腦三台、車用音響ＣＤ盒三台、車用音響主機面板六台、\n      車用音響主機七台、電腦光碟機三台、電子翻譯機三台、\n      太陽眼鏡三付、名牌皮夾二個、黃昭維護照一本、何嘉仁\n      書店貴賓卡一張、起子與扳手等工具二十支等物，始循線\n      查獲上情。\n    因認被告庚○○涉有刑法第三百四十九條第二項之故買贓物\n    罪嫌，被告丁○○涉    有刑法第三百二十一條第一項第三\n    款之攜帶兇器竊盜罪嫌。\n二、按犯罪事實應依證據認定之，無證據不得認定犯罪事實，又\n    不能證明被告犯罪或其行為不罰者，應諭知無罪之判決，刑\n    事訴訟法第一百五十四條第二項、第三百零一條第一項分別\n    定有明文。而認定不利於被告之事實，須依積極證據，苟積\n    極證據不足為不利於被告事實之認定時，即應為有利於被告\n    之認定，更不必有何有利之證據。最高法院著有判例可循（\n    最高法院三十年上字第八一六號判例參照）。末按認定犯罪\n    事實所憑證據，雖不以直接證據為限，間接證據亦包括在內\n    ；然無論直接或間接證據，其為訴訟上之證明，須於通常一\n    般之人均不致有所懷疑，而得確信其為真實之程度者，始得\n    據為有罪之認定。如未能發現相當證據，或證據不足以證明\n    ，自不能以推測或擬制之方法，以為裁判基礎，最高法院亦\n    著有七十六年臺上字第四九八六號判例、四十年臺上字第八\n    六號判例足參\n三、公訴人認為被告庚○○、丁○○涉有上開犯行，無非係以被\n    告庚○○、丁○○皆無法供出前述查獲物品之來源以供本院\n    查證，亦為被告二人於警詢及本署偵訊時供認無訛，有警詢\n    及本署偵訊筆錄在卷可考。且被告二人遭查獲右開物品，多\n    係無線電、汽車音響及筆記型電腦，而被告庚○○本身即在\n    經營通訊行，對無線電之物之價錢等必是瞭解，被告丁○○\n    非係在一般出售汽車音響、筆記型電腦等固定商家購買前述\n    物品，反係在臺北縣三重市重新橋下之跳蚤市場入前開物品\n    ，並如前述，依經驗法則而論，汽車音響、筆記型電腦、無\n    線電等物為高科技、精密度極高之產品，一般有理性之人，\n    為求品質保證及日後維修之便利，皆會前往有固定店面之商\n    家購買，且該商家亦會交付保證書以保證其出售之電腦品質\n    無問題，乃被告庚○○、丁○○仍非向一般販售之商行購買\n    ，反係分別向被告李逸龍等及不詳之人所購買，顯不符合一\n    般之交易習慣，復未索取保證書證明前述物品品質無問題，\n    又購買之物品又皆係他人失竊之贓物，則被告庚○○顯有前\n    述物品皆係來源不明之贓物之認識，被告丁○○前揭所辯不\n    可採信，顯屬無疑等，為其主要論據。\n四、訊據被告庚○○、丁○○均堅詞否認上開犯行，被告庚○○\n    辯稱：只有四塊無線電主機板是李逸龍拿來賣我的，至於是\n    那四塊，我不能區分出來，因為機型、外型都一樣，我是用\n    二、三千元跟他買三個面板，另外買一個主機，主機是用三\n    、四千元買的，他分四次拿來賣我，第一次拿面板來賣我時\n    ，他說是他父親貨車上的，不用了，我問他為何只有面板而\n    沒有主機，所以當天下午他又拿了一個主機來賣給我。後來\n    另外二次他又分別拿了二塊面板來賣我等語。被告丁○○則\n    辯稱：除了我分租給阿明的房間搜出來的東西，其他在我家\n    搜到的東西是我的，東西是我買來的或是維修的，我有電動\n    螺絲起子、我的手提電腦警方也把他查扣了，東西是我從網\n    路、回收站買來的，是在不同時間買來的，有的是買來後要\n    維修才能用，為何被害人說是失竊的東西，我不知道等語。\n    經查：\n（一）被害人對於前往警局認領無線電主機及面板之過程，證人\n      楊超為證稱：我沒有報警，因為這種事情常常發生，因為\n      我有保險，事後是車行通知我們有抓到小偷，叫我們去領\n      失物，我去三重分局領失物，領回無線電面板。（如何認\n      定你領回的東西就是你失竊的無線電面板？）我有做記號\n      ，當時在分局有很多，我就慢慢找。（什麼記號？）用尖\n      銳的東西刮痕，做個符號。（刮哪裡，做什麼記號？）在\n      面板上做一個符號，隨便刮三痕做為符號。（買了多久失\n      竊？）好幾年，買的時候一萬多元，失竊的時候，我那台\n      已經不再產，失竊時的中古行情大約七千多。證人戊○○\n      證稱：沒有報警，因為是舊主機，所以大約價值四、五千\n      元，我買了大約八個月左右，我買的時候就是舊的。因為\n      我的主機接線部分有一個螺絲破掉，我都用塑膠繩綁，所\n      以我認得出來。證人丙○○證稱：（有失竊何物？）車機\n      面板，新的價值約五千元，我那時候買整台八千多，面板\n      不知道多少錢。因為我已經失竊二次，都沒有報警。車行\n      通知我們，說有抓到，叫我們去三重分局。因為我那個液\n      晶面板前面有斷字，而且旋轉鈕有一個沒有辦法轉大小聲\n      ，少一個塑膠袋。警方有一堆讓我們去認，我那個面板少\n      一個旋轉鈕。警方並無要求提出失竊身分或失竊證明，因\n      為我們沒有報警。是車行通知我們東西有找到，叫我們過\n      去，車行通知我們有失竊，因為要出險，車行有幫我們保\n      險。證人王文良證稱：沒有報警，這次有找回來，我事後\n      跟被告庚○○買一台，買回來之後，又找回來，在三重分\n      局找回來，是有無線電通知我們，所以我就去三重分局看\n      看。東西都一模一樣，去的時候只剩幾個，就隨便領一個\n      回去。去分局，警方沒有身分過濾，或是失竊證明。我是\n      跟別人買中古的，買的時候六、七千，失竊的時候價值多\n      少我不知道。證人楊文強證稱：我的無線電面板被偷走，\n      因為我的主機藏在隱密的地方，沒有被偷走，我那時裝到\n      好一萬二，那是舊的，單獨面板值多少錢，我不是很清楚\n      。（後來面板有無找回？）有，在三重分局，因為朋友跟\n      我說的。（面板有無特殊記號？）沒有，因為面板有的都\n      一樣，我是認我自己的型號，編號是Ｖ七型。證人李金煌\n      證稱：（後來有無找回失物？）有，後來經友台無線電廣\n      播，我找到一些贓物，去三重分局認領，有找到。（失竊\n      有無報警？）想說找不到，沒有去報警，但是有去報修玻\n      璃，我們是民間保險互助會。（警方有無要你提供報案證\n      明等？）我們有叫他去查，我們修理玻璃都有案底，他們\n      可以查得到。（如何辨認那就是你失竊的東西？）天天在\n      車上用，比較面熟，機台大同小異，因為天天在用，面板\n      磨損程度比較記得。（大約磨損程度？特徵？）面板有點\n      模糊不是很清楚，機台被拆下來也有被破壞一點，因為面\n      板天天在看，一天在車上十五個小時，就看十五個小時‧\n      ‧‧。（失竊時機台價值？）大約六、七千元的價值。證\n      人李俊慶證稱：無線電的主機含面板被偷，價值大約一萬\n      元左右，我買一萬多，買蠻久了，大約一年多。車行通知\n      我們去三重分局。我掉的就是那個東西，我掉的就是那個\n      機型跟面板，機型是我買的我認得，機型Ｖ七，Ｋ開頭的\n      牌子。東西都一樣，我是從機型辨別。當時整台主機跟面\n      板的機型好像只有一台，當時現場還有七三三的其他機型\n      ，但是我掉的就是這一型，所以我就領回。證人己○○證\n      稱：我放在手扶箱裡面，我藏在裡面被翻動，大約價值四\n      、五千元，一部主機一萬三千五，主機沒有被偷，只有面\n      板被偷。面板是塑膠的，我常常用手擦，有痕跡，我去看\n      的時候，只剩下這一台有手擦的痕跡，所以我想應該就是\n      這一部。證人林明德證稱：同行通知我，叫我去三重分局\n      看看有無我失竊的東西，最後有領回。因為面板我使用很\n      久，磨損的痕跡我認得。我是買整台，整台五千元，大約\n      買了一、二年被偷。（當初去分局認領，警方有無要求你\n      提供報案證明或是失竊證明？）他有問我，但是我跟他們\n      說我沒有報案，他問我這裡有無我失竊的東西。（如何辨\n      認領回的面板？）因為面板使用久了，每天看，之前我有\n      貼魔鬼貼，用刀片割的時候，有一點磨損。證人林廷弘證\n      稱：無線電的主機台及面板被偷。那時我買舊的是七千九\n      。沒有報警。朋友跟我講三重分局有個案件進來，有查獲\n      主機板叫我去看看有無失竊的東西。當時我看到我的面板\n      ，面板我曾經自己拆過，上面的刮痕我有印象。認領時警\n      方沒有要我提供報案證明（以上均詳見本院九十三年九月\n      十六日審判筆錄）。另證人陳明池證稱：沒有報警。機子\n      沒有記號，有領回面板，我的面板是七三三型，因為是同\n      一機型我就領回了。證人陳明宗證稱：有報警，有找回面\n      板，面板是用很久的，我認的出來。買一萬多元，面板值\n      二、三千元。所謂一萬多元，是指新機的價錢。證人鄭國\n      珍證稱：沒有報警，被偷很多次。七三三型的，我有故意\n      作記號。整台一萬多元。證人李永成證稱：沒有報警有找\n      回來，是無線電車隊通知去三重分局看看，主機和面板都\n      有找回來，七三三型的，我有做記號。買中古的，值七千\n      多元，現在又被偷了。證人曹進和證稱：七三二型面板被\n      偷，我沒有報警。在三重分局找到，機子有卡到水泥的特\n      徵，是我姐夫送我的，後來又被偷了（見本院九十三年十\n      月十五日審判筆錄）。由上開證人之證述可知，甚多被害\n      人因無線電主機及面板時常遭竊或其他因素而未報案，既\n      然未有報案紀錄，則究竟有無失竊，即無認定之標準。況\n      且，若真有失竊，警方或許礙於人力不足而便宜行事，由\n      眾人自行尋找，此時，該等主機、面板上並無任何「序號\n      」或「原廠編號」足茲辨明其間之差異，欲認定該等物品\n      係贓物，僅能憑藉眾人對於自己物品之記憶力而已。其中\n      證人王文良、楊文強、李金煌、李俊慶、陳明池等人明白\n      證稱係以一模一樣、機型相同、大同小異等，為其認領之\n      依據；另己○○、陳明宗、鄭國珍及李永成則以手擦痕跡\n      、認得出來、有做記號等為依據。惟衡諸常情，將極易失\n      竊之物品在不妨害其價值及功效之情形下標示記號，雖非\n      無法理解，然前揭證人等之形容畢竟過於模糊而不明確，\n      在此情況下，渠等填載贓物領據所領走之無線電主機、面\n      板等物，是否確係失竊之物，甚值懷疑。況縱認該等物品\n      確係贓物，以被告庚○○經營無線電通訊行此一行業，平\n      日店內即堆放數量頗多之舊無線電主機零件及面板，該等\n      無線電主機面板之來源，或為客戶購買新機時，將其舊無\n      線電作價收購，或為客戶送修舊機所拋棄之主機面板，由\n      被告庚○○取其零件充當維修使用，而依一般商業習慣，\n      折舊抵價收購應無向客戶索取收據之理，且舊物多為瑕疵\n      或不敷使用之廢棄物，自無取得品質保證書之可能。僅以\n      被告無法取得來源證明，又無品質保證書等情而認定被告\n      收受時明知係贓物，並將上開有利被告之合理情況予以排\n      除，自嫌速斷。\n（二）同案被告李逸龍於偵查中供稱：（賣給庚○○時有無向他\n      說是偷來的？）沒有，我跟他說是家裡的（臺灣板橋地方\n      法院檢察署，九十二年度偵字第二六二七號卷，第一一四\n      頁）。又於本院審理時證稱：（拿去賣他的時候，如何告\n      知？）說是我家裡的。（你有告訴他來源嗎？）沒有。（\n      事後有告訴林炳志你賣給庚○○的經過及價格？）我有告\n      訴林炳志我賣的價格。（賣給庚○○時，他有無問你主機\n      面板如何來，或是他有無要你提供出廠證明？）他只問我\n      東西哪裡來的，我說是家裡來的，他沒有要我提出證明，\n      他也沒有開收據給我。（庚○○有無懷疑你這個東西是偷\n      來的贓物？）有，他問我這是不是偷來的，我說不是（本\n      院九十三年九月十六日審判筆錄）。由李逸龍之證述，可\n      認被告庚○○於向其收購主機及面板時，李逸龍並未告知\n      該等物品係偷竊而來，甚且於庚○○質疑是否為贓物之際\n      ，猶一再陳稱並非贓物，係家中物品，則能否遽認庚○○\n      對所收購之物品係贓物一節有所認識，實堪存疑。\n（三）對於無線電主機及面板之價格，同案被告李逸龍證稱係以\n      面板一千五至二千元、機身連面板二千五百元至三千五百\n      元賣給庚○○，賣了三次，得款一萬一千元左右。而證人\n      戊○○證稱：伊買舊的無線電主機含面板，大約價值四、\n      五千元；證人丙○○證稱：伊買新的主機含面板約八千多\n      元；證人楊文強證稱：我那時裝到好一萬二，那是舊的，\n      編號是Ｖ七型。證人己○○證稱：面板大約價值四、五千\n      元，一部主機一萬三千五，機型是Ｖ七（均詳見本院九十\n      三年九月十六日審判筆錄）。證人陳明宗證稱：無線電主\n      機含面板新機買來一萬多元；證人李永成證稱：無線電主\n      機含面板買中古的，值七千多元等（均見本院九十三年十\n      月十五日審判筆錄。由上開多名證人證述情節觀之，無線\n      電主機含面板的中古機型價格略有四、五千元至七、八千\n      元不等，甚有至萬餘元，可見不同機型、年份以及使用狀\n      況均影響到中古機型之價格，然以李逸龍所證述上開販售\n      予庚○○之價格，雖與證人買入中古機型之價格稍低，惟\n      能否遽認與市場行情顯不相當，實有斟酌之餘。蓋庚○○\n      既收購中古無線電主機及面板，再予以販售以賺取差價之\n      利潤，其向李逸龍收購之價格自然會壓低再以較高價錢賣\n      出，此乃當然之理，亦符合社會一般交易習慣，非可因此\n      遽認庚○○係明知贓物而買受。\n（四）對於被告丁○○部分，其於偵訊時對於贓物何來，始終供\n      稱係於三重重新橋、永和福和橋下之跳蚤市場買得（臺灣\n      板橋地方法院檢察署，九十二年度偵字第二六二七號卷，\n      第一五二頁背面、九十二年度偵字第一一二八號卷，第\n      二二頁背面）。另稱：（黃昭維、乙○○二人的護照、信\n      用卡何來？）阿明留下來的，他租我的房間，從他房間搜\n      出來的（九十二年度偵字第一一二八號卷，第二二頁背\n      面），丁○○上揭贓物何來之供述與在本院審理時前揭辯\n      稱：從網路、回收站買來等語並不一致，雖有可疑，然與\n      竊盜犯嫌無涉。縱認為「阿明」其人係丁○○所杜撰，實\n      際上並無其人，仍無法以此即認黃昭維、乙○○之物品為\n      丁○○所竊取。此外，共同被告李逸龍對於是否將偷來之\n      物賣給丁○○，先供稱：丁○○我不認識他（九十二年度\n      偵字第一一二七七號卷，第三七、三七頁背面）。被告即\n      證人林炳志亦供稱：據我所知，沒有賣給丁○○（九十二\n      年度偵字第二六二七號卷，第一二九頁背面）。嗣於本院\n      訊問時，李逸龍及林炳志乃翻異前詞，供稱：賣給丁○○\n      ，賣了一個ＶＣＤ主機跟車上的液晶電視的螢幕，分兩次\n      賣等語（本院九十三年五月十八日準備程序筆錄）。渠前\n      後供述雖互核不一，然該二人之供述均與丁○○是否涉有\n      竊盜犯行無關，自無法於本案採為對被告丁○○涉嫌竊盜\n      之不利認定。另證人江佰卿及甲○○雖於偵訊時證述物品\n      失竊之情，惟均稱未看到係何人所竊，亦未曾見過被告（\n      臺灣板橋地方法院檢察署，九十二年度偵字第二六二七號\n      卷，第一五三頁、一五三頁背面），二證人既未親眼目擊\n      何人竊取贓物，警方又無在現場採得被告指紋等證據，自\n      亦不足證明被告丁○○涉有竊盜行為。綜上，被告持有贓\n      物之原因，不一而足，固可能係自行竊取而得，然尚不能\n      排除係向他人買受之可能性，僅由丁○○住處查獲贓物之\n      情，尚不因此即認被告涉有竊盜犯行。\n五、如上所述，公訴人指訴被告庚○○涉有贓物罪嫌、被告丁○\n    ○涉有竊盜罪嫌，依本件現存之證明資料，尚未達於通常一\n    般之人均不致有所懷疑，而得確信其為真實之證明程度，仍\n    有合理懷疑之存在，致使無從形成對被告二人為有罪之確信\n    ，此外復查無其他積極事證可認被告二人確有何公訴人所指\n    之犯行，依前開說明及「罪證有疑，利於被告」之證據法則\n    ，本件公訴人分別起訴被告庚○○贓物犯嫌及丁○○竊盜之\n    犯嫌尚屬未能證明，自應為二人無罪判決之諭知。至被告丁\n    ○○是否涉及贓物罪嫌，因非本件起訴範圍，本院無從變更\n    起訴法條逕予審理，應由檢察官另行偵查處理，附此敘明。\n據上論斷，應依刑事訴訟法第三百零一條第一項前段，判決如主\n文。\n本案經檢察官王秀慧、陳鴻濤到庭執行職務。\n中    華    民    國    93    年    10    月    29    日\n                  臺灣板橋地方法院刑事第九庭\n                          審判長法  官  胡  堅  勤\n                                法  官  王  瑜  玲\n                                法  官  李  君  豪\n右正本證明與原本無異。\n如不服本判決，應於判決送達後十日內，向本院提出上訴狀。\n                                書記官  蕭  汝  芳\n中    華    民    國    93    年    10    月    29    日\n",
  "structure": {
    "main": "上訴駁回。\n    理  由\n一、本案經本院審理結果，認第一審判決對被告丁○○、庚○○\n    均為無罪之諭知，核無不當，應予維持，並引用第一審判決\n    書記載之證據及理由（如附件）。\n二、檢察官上訴意旨略以：\n（一）被告丁○○於偵查及原審審理時，對於贓物之來源前後供\n      述不一，被告於偵查中或原審審理中之所辯，均屬卸責之\n      詞，難謂原判決翔實無誤。\n（二）被害人等前往台北縣警察局三重分局認領贓物時，均表示\n      如有冒領願法律責任，而於贓物認領保管單簽名署押，足\n      認被害人等所具領之物品，悉屬贓物無疑，原判決以該等\n      物品是否確係失竊，尚值懷疑，尚有未洽。\n（三）被告庚○○有多次因贓物罪嫌而獲不起訴處分之案件，則\n      被告庚○○對於所購入他人所販來源不明之物有更高之注\n      意查核之義務，竟數度以低於市價之價格購買來源不明之\n      物，被告庚○○有不確定故買贓物之故意彰彰甚明云云。\n三、惟查：\n（一）認定犯罪事實應依證據，為刑事訴訟法所明定，故被告否\n      認犯罪事實所持之辯解，縱屬不能成立，仍非有積極證據\n      足以證明其犯罪行為，不能遽為有罪之認定。最高法院30\n      年上字第1831號著有判例可資參照。檢察官上訴意旨以：\n      被告丁○○於偵查及原審審理時，對於贓物之來源前後供\n      述不一，所辯均屬卸責之詞云云，縱認屬實，亦非有積極\n      證據足資證明被告丁○○有檢察官所指之竊盜犯行，法院\n      不得僅憑被告丁○○於偵審中之供述不一，而遽為被告丁\n      ○○有罪之判決。檢察官此部分上訴理由，顯無可採。\n（二）被害人楊超為、戊○○、丙○○、王文良、李金煌、林明\n      德、林廷弘、陳明池、鄭國珍、李永成、曹進和等人於原\n      審審理時均證稱其等並未因失竊而向警報案，被害人等既\n      未報案而無紀錄可資查考，則究竟被害人等確有無失竊本\n      件檢察官所指之主機、面板等物，即乏證據證明而非無可\n      疑；且該等主機、面板上並無任何足茲辨明其間之差異之\n      記載或特徵，欲認定該等物品係贓物，僅能憑藉眾被害人\n      對於自己物品之記憶力爾。其中證人王文良、楊文強、李\n      金煌、李俊慶、陳明池等人明白證稱係以一模一樣、機型\n      相同、大同小異等，為其認領之依據；另證人己○○、陳\n      明宗、鄭國珍及李永成則以手擦痕跡、認得出來、有做記\n      號等為依據。惟衡諸常情，將極易失竊之物品在不妨害其\n      價值及功效之情形下標示記號，雖可理解，然前揭證人等\n      對於其等所認領之物與他人之物之區別，顯有模糊不明確\n      之情形，在此等情況下，渠等填載贓物領據所認領之無線\n      電主機、面板等物，是否確係失竊之物，殊值懷疑等情，\n      業據原判決於理由欄內論述甚明，亦核與日常生活經驗無\n      所違背。檢察官上訴意旨，徒以被害人等認領查扣物品時\n      業已書具認領保管單，表示願負擔法律上之責任，即認該\n      等物品確屬贓物，尚嫌率斷，顯無足取。\n（三）對於無線電主機及面板之價格，同案被告李逸龍證稱係以\n      面板新台幣（下同）1500至2000元、機身連面板2500至\n      3500元賣給被告庚○○，賣了3次，得款11000元左右。\n      而證人戊○○證稱：伊買舊的無線電主機含面板，大約價\n      值4、5000元；證人丙○○證稱：伊買新的主機含面板約\n      8000多元；證人楊文強證稱：我那時裝到好12000元，那是\n      舊的，編號是Ｖ七型。證人己○○證稱：面板大約價值\n      4、5000元，一部主機13500元，機型是Ｖ七（均見原審93\n      年9月16日審判筆錄）。證人陳明宗證稱：無線電主機含面\n      板新機買來10000多元；證人李永成證稱：無線電主機含面\n      板買中古的，值7000多元等（均見原審93年10月15日審判\n      筆錄。由上開多名證人證述情節觀之，無線電主機含面板\n      的中古機型價格略有4、5000元至7、8000元不等，甚有至\n      萬餘元，可見不同機型、年份以及使用狀況均影響到中古\n      機型之價格，然以李逸龍所證述上開販售予庚○○之價格\n      ，雖與證人等所證述之中古機型之買入價格稍低，惟能否\n      遽認與市場行情顯不相當，非無斟酌之餘地。且被告庚○\n      ○既係以收購中古無線電主機及面板，再予以販售之方式\n      以賺取差價，則在商言商，其壓低向李逸龍收購之價格，\n      再以較高價錢賣出，係屬當然之理，亦符合社會一般交易\n      常規，惟於法尚不得因此遽認庚○○係明知贓物而買受。\n      亦據原判決於理由欄內詳予論述。檢察官上訴意旨徒以被\n      告庚○○有多次因贓物罪嫌而獲不起訴處分之案件，而認\n      被告庚○○對於所購入他人所販來源不明之物有更高之注\n      意查核之義務，而無視於前引證人等關於中古機型之不同\n      價格之證述，率認被告庚○○數度以低於市價之價格購買\n      來源不明之物，必有不確定故買贓物之故意，於法尚非有\n      據，此等出於臆測之上訴理由，顯無可取。\n四、綜上所述，檢察官前述上訴意旨所陳各節，於法均非可採。\n    其執此上訴意旨，任意指摘原判決不當，求予撤銷改判，顯\n    無理由，應予駁回其上訴。\n據上論結，應依刑事訴訟法第373條、第368條，判決如主文。\n本案經檢察官李良忠到庭執行職務。\n中    華    民    國    94    年    5     月    24    日\n                  刑事第六庭審判長法  官  許國宏\n                                  法  官  洪光燦\n                                  法  官  林銓正\n以上正本證明與原本無異。\n不得上訴。\n                                  書記官  陳玲憶\n中    華    民    國    94    年    5     月    26    日\n附件：\n臺灣板橋地方法院刑事判決      九十二年度易字第二二七七號\n    公  訴  人  臺灣板橋地方法院檢察署檢察官\n    被      告  丁○○  男  31歲（民國○○年○月○○日生）\n                        住桃園縣楊梅鎮○○○路○段390巷\n                          巷45弄34號3樓之2\n                        身分證統一編號：Ｚ000000000號\n                庚○○  男  47歲（民國○○年○月○○日生）\n                        住臺北縣三重市○○路○段67號\n                        身分證統一編號：Ｚ000000000號\n    右一人\n    選任辯護人  邱群傑律師\n                許卓敏律師\n右列被告等因竊盜等案件，經檢察官提起公訴（九十二年度偵字\n第二六二七號、第四九三一號、第六六四一號、第一一二八號\n、第一四四號、第一一二七七號），本院判決如左：\n    主  文\n丁○○、庚○○均無罪。",
    "reason": "一、本案經本院審理結果，認第一審判決對被告丁○○、庚○○\n    均為無罪之諭知，核無不當，應予維持，並引用第一審判決\n    書記載之證據及理由（如附件）。\n二、檢察官上訴意旨略以：\n（一）被告丁○○於偵查及原審審理時，對於贓物之來源前後供\n      述不一，被告於偵查中或原審審理中之所辯，均屬卸責之\n      詞，難謂原判決翔實無誤。\n（二）被害人等前往台北縣警察局三重分局認領贓物時，均表示\n      如有冒領願法律責任，而於贓物認領保管單簽名署押，足\n      認被害人等所具領之物品，悉屬贓物無疑，原判決以該等\n      物品是否確係失竊，尚值懷疑，尚有未洽。\n（三）被告庚○○有多次因贓物罪嫌而獲不起訴處分之案件，則\n      被告庚○○對於所購入他人所販來源不明之物有更高之注\n      意查核之義務，竟數度以低於市價之價格購買來源不明之\n      物，被告庚○○有不確定故買贓物之故意彰彰甚明云云。\n三、惟查：\n（一）認定犯罪事實應依證據，為刑事訴訟法所明定，故被告否\n      認犯罪事實所持之辯解，縱屬不能成立，仍非有積極證據\n      足以證明其犯罪行為，不能遽為有罪之認定。最高法院30\n      年上字第1831號著有判例可資參照。檢察官上訴意旨以：\n      被告丁○○於偵查及原審審理時，對於贓物之來源前後供\n      述不一，所辯均屬卸責之詞云云，縱認屬實，亦非有積極\n      證據足資證明被告丁○○有檢察官所指之竊盜犯行，法院\n      不得僅憑被告丁○○於偵審中之供述不一，而遽為被告丁\n      ○○有罪之判決。檢察官此部分上訴理由，顯無可採。\n（二）被害人楊超為、戊○○、丙○○、王文良、李金煌、林明\n      德、林廷弘、陳明池、鄭國珍、李永成、曹進和等人於原\n      審審理時均證稱其等並未因失竊而向警報案，被害人等既\n      未報案而無紀錄可資查考，則究竟被害人等確有無失竊本\n      件檢察官所指之主機、面板等物，即乏證據證明而非無可\n      疑；且該等主機、面板上並無任何足茲辨明其間之差異之\n      記載或特徵，欲認定該等物品係贓物，僅能憑藉眾被害人\n      對於自己物品之記憶力爾。其中證人王文良、楊文強、李\n      金煌、李俊慶、陳明池等人明白證稱係以一模一樣、機型\n      相同、大同小異等，為其認領之依據；另證人己○○、陳\n      明宗、鄭國珍及李永成則以手擦痕跡、認得出來、有做記\n      號等為依據。惟衡諸常情，將極易失竊之物品在不妨害其\n      價值及功效之情形下標示記號，雖可理解，然前揭證人等\n      對於其等所認領之物與他人之物之區別，顯有模糊不明確\n      之情形，在此等情況下，渠等填載贓物領據所認領之無線\n      電主機、面板等物，是否確係失竊之物，殊值懷疑等情，\n      業據原判決於理由欄內論述甚明，亦核與日常生活經驗無\n      所違背。檢察官上訴意旨，徒以被害人等認領查扣物品時\n      業已書具認領保管單，表示願負擔法律上之責任，即認該\n      等物品確屬贓物，尚嫌率斷，顯無足取。\n（三）對於無線電主機及面板之價格，同案被告李逸龍證稱係以\n      面板新台幣（下同）1500至2000元、機身連面板2500至\n      3500元賣給被告庚○○，賣了3次，得款11000元左右。\n      而證人戊○○證稱：伊買舊的無線電主機含面板，大約價\n      值4、5000元；證人丙○○證稱：伊買新的主機含面板約\n      8000多元；證人楊文強證稱：我那時裝到好12000元，那是\n      舊的，編號是Ｖ七型。證人己○○證稱：面板大約價值\n      4、5000元，一部主機13500元，機型是Ｖ七（均見原審93\n      年9月16日審判筆錄）。證人陳明宗證稱：無線電主機含面\n      板新機買來10000多元；證人李永成證稱：無線電主機含面\n      板買中古的，值7000多元等（均見原審93年10月15日審判\n      筆錄。由上開多名證人證述情節觀之，無線電主機含面板\n      的中古機型價格略有4、5000元至7、8000元不等，甚有至\n      萬餘元，可見不同機型、年份以及使用狀況均影響到中古\n      機型之價格，然以李逸龍所證述上開販售予庚○○之價格\n      ，雖與證人等所證述之中古機型之買入價格稍低，惟能否\n      遽認與市場行情顯不相當，非無斟酌之餘地。且被告庚○\n      ○既係以收購中古無線電主機及面板，再予以販售之方式\n      以賺取差價，則在商言商，其壓低向李逸龍收購之價格，\n      再以較高價錢賣出，係屬當然之理，亦符合社會一般交易\n      常規，惟於法尚不得因此遽認庚○○係明知贓物而買受。\n      亦據原判決於理由欄內詳予論述。檢察官上訴意旨徒以被\n      告庚○○有多次因贓物罪嫌而獲不起訴處分之案件，而認\n      被告庚○○對於所購入他人所販來源不明之物有更高之注\n      意查核之義務，而無視於前引證人等關於中古機型之不同\n      價格之證述，率認被告庚○○數度以低於市價之價格購買\n      來源不明之物，必有不確定故買贓物之故意，於法尚非有\n      據，此等出於臆測之上訴理由，顯無可取。\n四、綜上所述，檢察官前述上訴意旨所陳各節，於法均非可採。\n    其執此上訴意旨，任意指摘原判決不當，求予撤銷改判，顯\n    無理由，應予駁回其上訴。\n據上論結，應依刑事訴訟法第373條、第368條，判決如主文。\n本案經檢察官李良忠到庭執行職務。"
  },
  "search": "臺灣高等法院刑事判決93年度上易字第2059號上訴人臺灣板橋地方法院檢察署檢察官被告丁○○十五弄三十四號三樓之二庚○○上一人選任辯護人邱群傑律師許卓敏律師上列上訴人因被告等竊盜等案件，不服臺灣板橋地方法院92年度易字第2277號，中華民國93年10月29日第一審判決（起訴案號：臺灣板橋地方法院檢察署92年度偵字第2627號），提起上訴，本院判決如下：主文上訴駁回。理由一、本案經本院審理結果，認第一審判決對被告丁○○、庚○○均為無罪之諭知，核無不當，應予維持，並引用第一審判決書記載之證據及理由（如附件）。二、檢察官上訴意旨略以：（一）被告丁○○於偵查及原審審理時，對於贓物之來源前後供述不一，被告於偵查中或原審審理中之所辯，均屬卸責之詞，難謂原判決翔實無誤。（二）被害人等前往台北縣警察局三重分局認領贓物時，均表示如有冒領願法律責任，而於贓物認領保管單簽名署押，足認被害人等所具領之物品，悉屬贓物無疑，原判決以該等物品是否確係失竊，尚值懷疑，尚有未洽。（三）被告庚○○有多次因贓物罪嫌而獲不起訴處分之案件，則被告庚○○對於所購入他人所販來源不明之物有更高之注意查核之義務，竟數度以低於市價之價格購買來源不明之物，被告庚○○有不確定故買贓物之故意彰彰甚明云云。三、惟查：（一）認定犯罪事實應依證據，為刑事訴訟法所明定，故被告否認犯罪事實所持之辯解，縱屬不能成立，仍非有積極證據足以證明其犯罪行為，不能遽為有罪之認定。最高法院30年上字第1831號著有判例可資參照。檢察官上訴意旨以：被告丁○○於偵查及原審審理時，對於贓物之來源前後供述不一，所辯均屬卸責之詞云云，縱認屬實，亦非有積極證據足資證明被告丁○○有檢察官所指之竊盜犯行，法院不得僅憑被告丁○○於偵審中之供述不一，而遽為被告丁○○有罪之判決。檢察官此部分上訴理由，顯無可採。（二）被害人楊超為、戊○○、丙○○、王文良、李金煌、林明德、林廷弘、陳明池、鄭國珍、李永成、曹進和等人於原審審理時均證稱其等並未因失竊而向警報案，被害人等既未報案而無紀錄可資查考，則究竟被害人等確有無失竊本件檢察官所指之主機、面板等物，即乏證據證明而非無可疑；且該等主機、面板上並無任何足茲辨明其間之差異之記載或特徵，欲認定該等物品係贓物，僅能憑藉眾被害人對於自己物品之記憶力爾。其中證人王文良、楊文強、李金煌、李俊慶、陳明池等人明白證稱係以一模一樣、機型相同、大同小異等，為其認領之依據；另證人己○○、陳明宗、鄭國珍及李永成則以手擦痕跡、認得出來、有做記號等為依據。惟衡諸常情，將極易失竊之物品在不妨害其價值及功效之情形下標示記號，雖可理解，然前揭證人等對於其等所認領之物與他人之物之區別，顯有模糊不明確之情形，在此等情況下，渠等填載贓物領據所認領之無線電主機、面板等物，是否確係失竊之物，殊值懷疑等情，業據原判決於理由欄內論述甚明，亦核與日常生活經驗無所違背。檢察官上訴意旨，徒以被害人等認領查扣物品時業已書具認領保管單，表示願負擔法律上之責任，即認該等物品確屬贓物，尚嫌率斷，顯無足取。（三）對於無線電主機及面板之價格，同案被告李逸龍證稱係以面板新台幣（下同）1500至2000元、機身連面板2500至3500元賣給被告庚○○，賣了3次，得款11000元左右。而證人戊○○證稱：伊買舊的無線電主機含面板，大約價值4、5000元；證人丙○○證稱：伊買新的主機含面板約8000多元；證人楊文強證稱：我那時裝到好12000元，那是舊的，編號是Ｖ七型。證人己○○證稱：面板大約價值4、5000元，一部主機13500元，機型是Ｖ七（均見原審93年9月16日審判筆錄）。證人陳明宗證稱：無線電主機含面板新機買來10000多元；證人李永成證稱：無線電主機含面板買中古的，值7000多元等（均見原審93年10月15日審判筆錄。由上開多名證人證述情節觀之，無線電主機含面板的中古機型價格略有4、5000元至7、8000元不等，甚有至萬餘元，可見不同機型、年份以及使用狀況均影響到中古機型之價格，然以李逸龍所證述上開販售予庚○○之價格，雖與證人等所證述之中古機型之買入價格稍低，惟能否遽認與市場行情顯不相當，非無斟酌之餘地。且被告庚○○既係以收購中古無線電主機及面板，再予以販售之方式以賺取差價，則在商言商，其壓低向李逸龍收購之價格，再以較高價錢賣出，係屬當然之理，亦符合社會一般交易常規，惟於法尚不得因此遽認庚○○係明知贓物而買受。亦據原判決於理由欄內詳予論述。檢察官上訴意旨徒以被告庚○○有多次因贓物罪嫌而獲不起訴處分之案件，而認被告庚○○對於所購入他人所販來源不明之物有更高之注意查核之義務，而無視於前引證人等關於中古機型之不同價格之證述，率認被告庚○○數度以低於市價之價格購買來源不明之物，必有不確定故買贓物之故意，於法尚非有據，此等出於臆測之上訴理由，顯無可取。四、綜上所述，檢察官前述上訴意旨所陳各節，於法均非可採。其執此上訴意旨，任意指摘原判決不當，求予撤銷改判，顯無理由，應予駁回其上訴。據上論結，應依刑事訴訟法第373條、第368條，判決如主文。本案經檢察官李良忠到庭執行職務。中華民國94年5月24日刑事第六庭審判長法官許國宏法官洪光燦法官林銓正以上正本證明與原本無異。不得上訴。書記官陳玲憶中華民國94年5月26日附件：臺灣板橋地方法院刑事判決九十二年度易字第二二七七號公訴人臺灣板橋地方法院檢察署檢察官被告丁○○男31歲（民國○○年○月○○日生）住桃園縣楊梅鎮○○○路○段390巷巷45弄34號3樓之2身分證統一編號：Ｚ000000000號庚○○男47歲（民國○○年○月○○日生）住臺北縣三重市○○路○段67號身分證統一編號：Ｚ000000000號右一人選任辯護人邱群傑律師許卓敏律師右列被告等因竊盜等案件，經檢察官提起公訴（九十二年度偵字第二六二七號、第四九三一號、第六六四一號、第一一二八號、第一四四號、第一一二七七號），本院判決如左：主文丁○○、庚○○均無罪。理由一、公訴意旨略以：（一）被告李逸龍、林炳志（均已結）共同基於意圖為自己不法所有之概括犯意聯絡，連續在附表所示之時、地，竊取如附表所示被害人財物（詳細行竊時間、地點、行為人、手法、所得財物等，均如附表所示），並將上開竊得之無線電主機與面板等物持向被告庚○○所開設位於臺北縣三重市○○路○段六七號之「富貴無線電專賣店」（現改名「中野通訊社」）變賣，所得由二人朋分花用。被告庚○○明知上開無線電主機及面板等物均係李逸龍、林炳志二人竊得之贓物，竟仍基於故買贓物之概括犯意，自九十一年九月間某日起，迄九十二年一月間止，連續在其所開設位於臺北縣三重市○○路○段六七號之「富貴無線電專賣店」內，以低於市價四分之一之價格購入。嗣於九十二年一月十七日二十一時許，經警在庚○○所開設之前揭通訊行內，查獲ＫＥＮＷＯＯＤ牌車裝無線電ＴＭ─七三三型四台、無線電面板六具、ＴＭ─Ｖ七型車裝無線電一台、無線電面板三具、ＴＭ─七三二型無線電面板三具後，循線查獲上情。（二）被告丁○○基於意圖為自己不法所有之概括犯意，以擊破車窗之方式，連續(1)於九十一年十月十日零時許，在臺北縣三重市○○○路五十四號前，竊取被害人林俊毅所有車裝音響主機一台、螢幕一台；(2)於九十一年十一月十五日，在臺北縣新莊市○○街九號二樓，竊取被害人陳文炳所有之手提電腦一台；(3)於九十一年十二月三十日，在臺北縣板橋市○○路九十三巷三號，竊取被害人甲○○所有之手提電腦一台；(4)於九十二年一月十六日二時許，在臺北縣中和市○○路八八九號地下停車場，竊取被害人黃昭維所有之中華民國護照一本、太陽眼鏡二副、明牌皮夾二個；(5)於九十二年一月十七日七時許，在臺北市○○區○○街二八四巷三六弄二二號地下停車場，竊取被害人江佰卿所有之車內音響主機一台、液晶螢幕一台、ＣＤ盒一個、車用音響轉換器一台；(6)於九十二年一月十七日七時三十分許，在臺北市○○區○○街二八四巷三十弄八三號地下室，竊取被害人乙○○所有之中國信託信用卡一張、何嘉仁書店貴賓卡一張、太陽眼鏡一副。嗣於九十二年一月十七日二十三時五十分許，經警在丁○○位於臺北縣中和市○○街十四巷四十弄十二之二號三樓住處，查獲筆記型電腦三台、車用音響ＣＤ盒三台、車用音響主機面板六台、車用音響主機七台、電腦光碟機三台、電子翻譯機三台、太陽眼鏡三付、名牌皮夾二個、黃昭維護照一本、何嘉仁書店貴賓卡一張、起子與扳手等工具二十支等物，始循線查獲上情。因認被告庚○○涉有刑法第三百四十九條第二項之故買贓物罪嫌，被告丁○○涉有刑法第三百二十一條第一項第三款之攜帶兇器竊盜罪嫌。二、按犯罪事實應依證據認定之，無證據不得認定犯罪事實，又不能證明被告犯罪或其行為不罰者，應諭知無罪之判決，刑事訴訟法第一百五十四條第二項、第三百零一條第一項分別定有明文。而認定不利於被告之事實，須依積極證據，苟積極證據不足為不利於被告事實之認定時，即應為有利於被告之認定，更不必有何有利之證據。最高法院著有判例可循（最高法院三十年上字第八一六號判例參照）。末按認定犯罪事實所憑證據，雖不以直接證據為限，間接證據亦包括在內；然無論直接或間接證據，其為訴訟上之證明，須於通常一般之人均不致有所懷疑，而得確信其為真實之程度者，始得據為有罪之認定。如未能發現相當證據，或證據不足以證明，自不能以推測或擬制之方法，以為裁判基礎，最高法院亦著有七十六年臺上字第四九八六號判例、四十年臺上字第八六號判例足參三、公訴人認為被告庚○○、丁○○涉有上開犯行，無非係以被告庚○○、丁○○皆無法供出前述查獲物品之來源以供本院查證，亦為被告二人於警詢及本署偵訊時供認無訛，有警詢及本署偵訊筆錄在卷可考。且被告二人遭查獲右開物品，多係無線電、汽車音響及筆記型電腦，而被告庚○○本身即在經營通訊行，對無線電之物之價錢等必是瞭解，被告丁○○非係在一般出售汽車音響、筆記型電腦等固定商家購買前述物品，反係在臺北縣三重市重新橋下之跳蚤市場入前開物品，並如前述，依經驗法則而論，汽車音響、筆記型電腦、無線電等物為高科技、精密度極高之產品，一般有理性之人，為求品質保證及日後維修之便利，皆會前往有固定店面之商家購買，且該商家亦會交付保證書以保證其出售之電腦品質無問題，乃被告庚○○、丁○○仍非向一般販售之商行購買，反係分別向被告李逸龍等及不詳之人所購買，顯不符合一般之交易習慣，復未索取保證書證明前述物品品質無問題，又購買之物品又皆係他人失竊之贓物，則被告庚○○顯有前述物品皆係來源不明之贓物之認識，被告丁○○前揭所辯不可採信，顯屬無疑等，為其主要論據。四、訊據被告庚○○、丁○○均堅詞否認上開犯行，被告庚○○辯稱：只有四塊無線電主機板是李逸龍拿來賣我的，至於是那四塊，我不能區分出來，因為機型、外型都一樣，我是用二、三千元跟他買三個面板，另外買一個主機，主機是用三、四千元買的，他分四次拿來賣我，第一次拿面板來賣我時，他說是他父親貨車上的，不用了，我問他為何只有面板而沒有主機，所以當天下午他又拿了一個主機來賣給我。後來另外二次他又分別拿了二塊面板來賣我等語。被告丁○○則辯稱：除了我分租給阿明的房間搜出來的東西，其他在我家搜到的東西是我的，東西是我買來的或是維修的，我有電動螺絲起子、我的手提電腦警方也把他查扣了，東西是我從網路、回收站買來的，是在不同時間買來的，有的是買來後要維修才能用，為何被害人說是失竊的東西，我不知道等語。經查：（一）被害人對於前往警局認領無線電主機及面板之過程，證人楊超為證稱：我沒有報警，因為這種事情常常發生，因為我有保險，事後是車行通知我們有抓到小偷，叫我們去領失物，我去三重分局領失物，領回無線電面板。（如何認定你領回的東西就是你失竊的無線電面板？）我有做記號，當時在分局有很多，我就慢慢找。（什麼記號？）用尖銳的東西刮痕，做個符號。（刮哪裡，做什麼記號？）在面板上做一個符號，隨便刮三痕做為符號。（買了多久失竊？）好幾年，買的時候一萬多元，失竊的時候，我那台已經不再產，失竊時的中古行情大約七千多。證人戊○○證稱：沒有報警，因為是舊主機，所以大約價值四、五千元，我買了大約八個月左右，我買的時候就是舊的。因為我的主機接線部分有一個螺絲破掉，我都用塑膠繩綁，所以我認得出來。證人丙○○證稱：（有失竊何物？）車機面板，新的價值約五千元，我那時候買整台八千多，面板不知道多少錢。因為我已經失竊二次，都沒有報警。車行通知我們，說有抓到，叫我們去三重分局。因為我那個液晶面板前面有斷字，而且旋轉鈕有一個沒有辦法轉大小聲，少一個塑膠袋。警方有一堆讓我們去認，我那個面板少一個旋轉鈕。警方並無要求提出失竊身分或失竊證明，因為我們沒有報警。是車行通知我們東西有找到，叫我們過去，車行通知我們有失竊，因為要出險，車行有幫我們保險。證人王文良證稱：沒有報警，這次有找回來，我事後跟被告庚○○買一台，買回來之後，又找回來，在三重分局找回來，是有無線電通知我們，所以我就去三重分局看看。東西都一模一樣，去的時候只剩幾個，就隨便領一個回去。去分局，警方沒有身分過濾，或是失竊證明。我是跟別人買中古的，買的時候六、七千，失竊的時候價值多少我不知道。證人楊文強證稱：我的無線電面板被偷走，因為我的主機藏在隱密的地方，沒有被偷走，我那時裝到好一萬二，那是舊的，單獨面板值多少錢，我不是很清楚。（後來面板有無找回？）有，在三重分局，因為朋友跟我說的。（面板有無特殊記號？）沒有，因為面板有的都一樣，我是認我自己的型號，編號是Ｖ七型。證人李金煌證稱：（後來有無找回失物？）有，後來經友台無線電廣播，我找到一些贓物，去三重分局認領，有找到。（失竊有無報警？）想說找不到，沒有去報警，但是有去報修玻璃，我們是民間保險互助會。（警方有無要你提供報案證明等？）我們有叫他去查，我們修理玻璃都有案底，他們可以查得到。（如何辨認那就是你失竊的東西？）天天在車上用，比較面熟，機台大同小異，因為天天在用，面板磨損程度比較記得。（大約磨損程度？特徵？）面板有點模糊不是很清楚，機台被拆下來也有被破壞一點，因為面板天天在看，一天在車上十五個小時，就看十五個小時‧‧‧。（失竊時機台價值？）大約六、七千元的價值。證人李俊慶證稱：無線電的主機含面板被偷，價值大約一萬元左右，我買一萬多，買蠻久了，大約一年多。車行通知我們去三重分局。我掉的就是那個東西，我掉的就是那個機型跟面板，機型是我買的我認得，機型Ｖ七，Ｋ開頭的牌子。東西都一樣，我是從機型辨別。當時整台主機跟面板的機型好像只有一台，當時現場還有七三三的其他機型，但是我掉的就是這一型，所以我就領回。證人己○○證稱：我放在手扶箱裡面，我藏在裡面被翻動，大約價值四、五千元，一部主機一萬三千五，主機沒有被偷，只有面板被偷。面板是塑膠的，我常常用手擦，有痕跡，我去看的時候，只剩下這一台有手擦的痕跡，所以我想應該就是這一部。證人林明德證稱：同行通知我，叫我去三重分局看看有無我失竊的東西，最後有領回。因為面板我使用很久，磨損的痕跡我認得。我是買整台，整台五千元，大約買了一、二年被偷。（當初去分局認領，警方有無要求你提供報案證明或是失竊證明？）他有問我，但是我跟他們說我沒有報案，他問我這裡有無我失竊的東西。（如何辨認領回的面板？）因為面板使用久了，每天看，之前我有貼魔鬼貼，用刀片割的時候，有一點磨損。證人林廷弘證稱：無線電的主機台及面板被偷。那時我買舊的是七千九。沒有報警。朋友跟我講三重分局有個案件進來，有查獲主機板叫我去看看有無失竊的東西。當時我看到我的面板，面板我曾經自己拆過，上面的刮痕我有印象。認領時警方沒有要我提供報案證明（以上均詳見本院九十三年九月十六日審判筆錄）。另證人陳明池證稱：沒有報警。機子沒有記號，有領回面板，我的面板是七三三型，因為是同一機型我就領回了。證人陳明宗證稱：有報警，有找回面板，面板是用很久的，我認的出來。買一萬多元，面板值二、三千元。所謂一萬多元，是指新機的價錢。證人鄭國珍證稱：沒有報警，被偷很多次。七三三型的，我有故意作記號。整台一萬多元。證人李永成證稱：沒有報警有找回來，是無線電車隊通知去三重分局看看，主機和面板都有找回來，七三三型的，我有做記號。買中古的，值七千多元，現在又被偷了。證人曹進和證稱：七三二型面板被偷，我沒有報警。在三重分局找到，機子有卡到水泥的特徵，是我姐夫送我的，後來又被偷了（見本院九十三年十月十五日審判筆錄）。由上開證人之證述可知，甚多被害人因無線電主機及面板時常遭竊或其他因素而未報案，既然未有報案紀錄，則究竟有無失竊，即無認定之標準。況且，若真有失竊，警方或許礙於人力不足而便宜行事，由眾人自行尋找，此時，該等主機、面板上並無任何「序號」或「原廠編號」足茲辨明其間之差異，欲認定該等物品係贓物，僅能憑藉眾人對於自己物品之記憶力而已。其中證人王文良、楊文強、李金煌、李俊慶、陳明池等人明白證稱係以一模一樣、機型相同、大同小異等，為其認領之依據；另己○○、陳明宗、鄭國珍及李永成則以手擦痕跡、認得出來、有做記號等為依據。惟衡諸常情，將極易失竊之物品在不妨害其價值及功效之情形下標示記號，雖非無法理解，然前揭證人等之形容畢竟過於模糊而不明確，在此情況下，渠等填載贓物領據所領走之無線電主機、面板等物，是否確係失竊之物，甚值懷疑。況縱認該等物品確係贓物，以被告庚○○經營無線電通訊行此一行業，平日店內即堆放數量頗多之舊無線電主機零件及面板，該等無線電主機面板之來源，或為客戶購買新機時，將其舊無線電作價收購，或為客戶送修舊機所拋棄之主機面板，由被告庚○○取其零件充當維修使用，而依一般商業習慣，折舊抵價收購應無向客戶索取收據之理，且舊物多為瑕疵或不敷使用之廢棄物，自無取得品質保證書之可能。僅以被告無法取得來源證明，又無品質保證書等情而認定被告收受時明知係贓物，並將上開有利被告之合理情況予以排除，自嫌速斷。（二）同案被告李逸龍於偵查中供稱：（賣給庚○○時有無向他說是偷來的？）沒有，我跟他說是家裡的（臺灣板橋地方法院檢察署，九十二年度偵字第二六二七號卷，第一一四頁）。又於本院審理時證稱：（拿去賣他的時候，如何告知？）說是我家裡的。（你有告訴他來源嗎？）沒有。（事後有告訴林炳志你賣給庚○○的經過及價格？）我有告訴林炳志我賣的價格。（賣給庚○○時，他有無問你主機面板如何來，或是他有無要你提供出廠證明？）他只問我東西哪裡來的，我說是家裡來的，他沒有要我提出證明，他也沒有開收據給我。（庚○○有無懷疑你這個東西是偷來的贓物？）有，他問我這是不是偷來的，我說不是（本院九十三年九月十六日審判筆錄）。由李逸龍之證述，可認被告庚○○於向其收購主機及面板時，李逸龍並未告知該等物品係偷竊而來，甚且於庚○○質疑是否為贓物之際，猶一再陳稱並非贓物，係家中物品，則能否遽認庚○○對所收購之物品係贓物一節有所認識，實堪存疑。（三）對於無線電主機及面板之價格，同案被告李逸龍證稱係以面板一千五至二千元、機身連面板二千五百元至三千五百元賣給庚○○，賣了三次，得款一萬一千元左右。而證人戊○○證稱：伊買舊的無線電主機含面板，大約價值四、五千元；證人丙○○證稱：伊買新的主機含面板約八千多元；證人楊文強證稱：我那時裝到好一萬二，那是舊的，編號是Ｖ七型。證人己○○證稱：面板大約價值四、五千元，一部主機一萬三千五，機型是Ｖ七（均詳見本院九十三年九月十六日審判筆錄）。證人陳明宗證稱：無線電主機含面板新機買來一萬多元；證人李永成證稱：無線電主機含面板買中古的，值七千多元等（均見本院九十三年十月十五日審判筆錄。由上開多名證人證述情節觀之，無線電主機含面板的中古機型價格略有四、五千元至七、八千元不等，甚有至萬餘元，可見不同機型、年份以及使用狀況均影響到中古機型之價格，然以李逸龍所證述上開販售予庚○○之價格，雖與證人買入中古機型之價格稍低，惟能否遽認與市場行情顯不相當，實有斟酌之餘。蓋庚○○既收購中古無線電主機及面板，再予以販售以賺取差價之利潤，其向李逸龍收購之價格自然會壓低再以較高價錢賣出，此乃當然之理，亦符合社會一般交易習慣，非可因此遽認庚○○係明知贓物而買受。（四）對於被告丁○○部分，其於偵訊時對於贓物何來，始終供稱係於三重重新橋、永和福和橋下之跳蚤市場買得（臺灣板橋地方法院檢察署，九十二年度偵字第二六二七號卷，第一五二頁背面、九十二年度偵字第一一二八號卷，第二二頁背面）。另稱：（黃昭維、乙○○二人的護照、信用卡何來？）阿明留下來的，他租我的房間，從他房間搜出來的（九十二年度偵字第一一二八號卷，第二二頁背面），丁○○上揭贓物何來之供述與在本院審理時前揭辯稱：從網路、回收站買來等語並不一致，雖有可疑，然與竊盜犯嫌無涉。縱認為「阿明」其人係丁○○所杜撰，實際上並無其人，仍無法以此即認黃昭維、乙○○之物品為丁○○所竊取。此外，共同被告李逸龍對於是否將偷來之物賣給丁○○，先供稱：丁○○我不認識他（九十二年度偵字第一一二七七號卷，第三七、三七頁背面）。被告即證人林炳志亦供稱：據我所知，沒有賣給丁○○（九十二年度偵字第二六二七號卷，第一二九頁背面）。嗣於本院訊問時，李逸龍及林炳志乃翻異前詞，供稱：賣給丁○○，賣了一個ＶＣＤ主機跟車上的液晶電視的螢幕，分兩次賣等語（本院九十三年五月十八日準備程序筆錄）。渠前後供述雖互核不一，然該二人之供述均與丁○○是否涉有竊盜犯行無關，自無法於本案採為對被告丁○○涉嫌竊盜之不利認定。另證人江佰卿及甲○○雖於偵訊時證述物品失竊之情，惟均稱未看到係何人所竊，亦未曾見過被告（臺灣板橋地方法院檢察署，九十二年度偵字第二六二七號卷，第一五三頁、一五三頁背面），二證人既未親眼目擊何人竊取贓物，警方又無在現場採得被告指紋等證據，自亦不足證明被告丁○○涉有竊盜行為。綜上，被告持有贓物之原因，不一而足，固可能係自行竊取而得，然尚不能排除係向他人買受之可能性，僅由丁○○住處查獲贓物之情，尚不因此即認被告涉有竊盜犯行。五、如上所述，公訴人指訴被告庚○○涉有贓物罪嫌、被告丁○○涉有竊盜罪嫌，依本件現存之證明資料，尚未達於通常一般之人均不致有所懷疑，而得確信其為真實之證明程度，仍有合理懷疑之存在，致使無從形成對被告二人為有罪之確信，此外復查無其他積極事證可認被告二人確有何公訴人所指之犯行，依前開說明及「罪證有疑，利於被告」之證據法則，本件公訴人分別起訴被告庚○○贓物犯嫌及丁○○竊盜之犯嫌尚屬未能證明，自應為二人無罪判決之諭知。至被告丁○○是否涉及贓物罪嫌，因非本件起訴範圍，本院無從變更起訴法條逕予審理，應由檢察官另行偵查處理，附此敘明。據上論斷，應依刑事訴訟法第三百零一條第一項前段，判決如主文。本案經檢察官王秀慧、陳鴻濤到庭執行職務。中華民國93年10月29日臺灣板橋地方法院刑事第九庭審判長法官胡堅勤法官王瑜玲法官李君豪右正本證明與原本無異。如不服本判決，應於判決送達後十日內，向本院提出上訴狀。書記官蕭汝芳中華民國93年10月29日",
  "characters": {
    "judges": [
      "許國宏",
      "洪光燦",
      "林銓正",
      "胡堅勤",
      "王瑜玲",
      "李君豪"
    ],
    "prosecutors": [
      "李良忠"
    ],
    "lawyers": [
      "邱群傑",
      "許卓敏",
      "邱群傑",
      "許卓敏"
    ],
    "clerks": [
      "陳玲憶",
      "蕭汝芳"
    ],
    "plaintiffs": [

    ],
    "defendants": [
      "丁○○",
      "丁○○  男  31歲（民國○○年○月○○日生）"
    ],
    "prosecutor_office": [
      "臺灣板橋地方法院檢察署檢察官"
    ],
    "creditors": [

    ],
    "debtors": [

    ],
    "judicial_associate_officer": [

    ]
  },
  "adjudged_at": "2005-05-24",
  "created_at": "2016-02-06 16:30:32",
  "updated_at": "2016-02-06 16:30:32"
}