{
  "identify": "CYD-94-嘉交簡-216-20050412-1",
  "court": {
    "name": "臺灣嘉義地方法院",
    "code": "CYD"
  },
  "division": {
    "name": "刑事",
    "code": "M"
  },
  "year": 94,
  "word": "嘉交簡",
  "number": "216",
  "jcheck": "1",
  "reason": "公共危險等",
  "content": "臺灣嘉義地方法院刑事簡易判決    94年度嘉交簡字第216號\n聲  請  人  臺灣嘉義地方法院檢察署檢察官\n被      告  甲○○  男  51歲.\n上列被告因公共危險案件，經檢察官聲請簡易判決處刑（93年度\n偵字第7311號），本院逕以簡易判決如下：\n    主  文\n甲○○駕駛動力交通工具肇事，致人傷而逃逸，處有期徒刑6月\n，如易科罰金，以300元折算1日，緩刑2年。\n    事實及理由\n一、本件犯罪事實及證據均引用檢察官聲請簡易判決處刑書有關\n    甲○○肇事逃逸部分之記載 (如附件)；被告甲○○涉有過\n    失傷害告訴人乙○○○之部分，業據告訴人撤回告訴，由本\n    院另行判決不受理。\n二、查被告甲○○前未曾受有期徒刑以上刑之宣告，有臺灣高等\n    法院被告全國前案紀錄表1份在卷可按，其因一時失慮，致\n    觸犯刑典，事後已與告訴人達成和解，有調解筆錄1紙在卷\n    可按，諒其經此刑之宣告後，應知警惕而無再犯之虞，本院\n    因認暫不執行其刑為當，予以宣告緩刑2年，用啟自新。\n三、依刑事訴訟法第449條第1項前段、第454條第2項，刑法第18\n    5條之4、第41條第1項前段、第74條第1款，罰金罰鍰提高標\n    準條例第2條，逕以簡易判決處如主文所示之刑。\n四、如對本判決不服，須於判決送達後10日內向本院提出上訴。\n中    華    民    國    94    年    4     月    12    日\n                  嘉義簡易庭法  官  蘇姵文\n以上正本證明與原本無異。\n中    華    民    國    94    年    4     月    12    日\n                            書記官  林金福\n附錄法條:\n中華民國刑法第185條之4\n駕駛動力交通工具肇事，致人死傷而逃逸者，處六月以上五年以\n下有期徒刑。\n",
  "structure": {
    "main": "甲○○駕駛動力交通工具肇事，致人傷而逃逸，處有期徒刑6月\n，如易科罰金，以300元折算1日，緩刑2年。",
    "fact": "一、本件犯罪事實及證據均引用檢察官聲請簡易判決處刑書有關\n    甲○○肇事逃逸部分之記載 (如附件)；被告甲○○涉有過\n    失傷害告訴人乙○○○之部分，業據告訴人撤回告訴，由本\n    院另行判決不受理。\n二、查被告甲○○前未曾受有期徒刑以上刑之宣告，有臺灣高等\n    法院被告全國前案紀錄表1份在卷可按，其因一時失慮，致\n    觸犯刑典，事後已與告訴人達成和解，有調解筆錄1紙在卷\n    可按，諒其經此刑之宣告後，應知警惕而無再犯之虞，本院\n    因認暫不執行其刑為當，予以宣告緩刑2年，用啟自新。\n三、依刑事訴訟法第449條第1項前段、第454條第2項，刑法第18\n    5條之4、第41條第1項前段、第74條第1款，罰金罰鍰提高標\n    準條例第2條，逕以簡易判決處如主文所示之刑。\n四、如對本判決不服，須於判決送達後10日內向本院提出上訴。",
    "reason": "一、本件犯罪事實及證據均引用檢察官聲請簡易判決處刑書有關\n    甲○○肇事逃逸部分之記載 (如附件)；被告甲○○涉有過\n    失傷害告訴人乙○○○之部分，業據告訴人撤回告訴，由本\n    院另行判決不受理。\n二、查被告甲○○前未曾受有期徒刑以上刑之宣告，有臺灣高等\n    法院被告全國前案紀錄表1份在卷可按，其因一時失慮，致\n    觸犯刑典，事後已與告訴人達成和解，有調解筆錄1紙在卷\n    可按，諒其經此刑之宣告後，應知警惕而無再犯之虞，本院\n    因認暫不執行其刑為當，予以宣告緩刑2年，用啟自新。\n三、依刑事訴訟法第449條第1項前段、第454條第2項，刑法第18\n    5條之4、第41條第1項前段、第74條第1款，罰金罰鍰提高標\n    準條例第2條，逕以簡易判決處如主文所示之刑。\n四、如對本判決不服，須於判決送達後10日內向本院提出上訴。"
  },
  "search": "臺灣嘉義地方法院刑事簡易判決94年度嘉交簡字第216號聲請人臺灣嘉義地方法院檢察署檢察官被告甲○○男51歲.上列被告因公共危險案件，經檢察官聲請簡易判決處刑（93年度偵字第7311號），本院逕以簡易判決如下：主文甲○○駕駛動力交通工具肇事，致人傷而逃逸，處有期徒刑6月，如易科罰金，以300元折算1日，緩刑2年。事實及理由一、本件犯罪事實及證據均引用檢察官聲請簡易判決處刑書有關甲○○肇事逃逸部分之記載(如附件)；被告甲○○涉有過失傷害告訴人乙○○○之部分，業據告訴人撤回告訴，由本院另行判決不受理。二、查被告甲○○前未曾受有期徒刑以上刑之宣告，有臺灣高等法院被告全國前案紀錄表1份在卷可按，其因一時失慮，致觸犯刑典，事後已與告訴人達成和解，有調解筆錄1紙在卷可按，諒其經此刑之宣告後，應知警惕而無再犯之虞，本院因認暫不執行其刑為當，予以宣告緩刑2年，用啟自新。三、依刑事訴訟法第449條第1項前段、第454條第2項，刑法第185條之4、第41條第1項前段、第74條第1款，罰金罰鍰提高標準條例第2條，逕以簡易判決處如主文所示之刑。四、如對本判決不服，須於判決送達後10日內向本院提出上訴。中華民國94年4月12日嘉義簡易庭法官蘇姵文以上正本證明與原本無異。中華民國94年4月12日書記官林金福附錄法條:中華民國刑法第185條之4駕駛動力交通工具肇事，致人死傷而逃逸者，處六月以上五年以下有期徒刑。",
  "characters": {
    "judges": [
      "蘇姵文"
    ],
    "prosecutors": [

    ],
    "lawyers": [

    ],
    "clerks": [
      "林金福"
    ],
    "plaintiffs": [

    ],
    "defendants": [
      "甲○○  男  51歲."
    ],
    "prosecutor_office": [
      "臺灣嘉義地方法院檢察署檢察官"
    ],
    "creditors": [

    ],
    "debtors": [

    ],
    "judicial_associate_officer": [

    ]
  },
  "adjudged_at": "2005-04-12",
  "created_at": "2016-02-06 18:39:06",
  "updated_at": "2016-02-06 18:39:06"
}