{
  "identify": "TNH-94-聲-65-20050412-1",
  "court": {
    "name": "臺灣高等法院",
    "code": "TNH"
  },
  "division": {
    "name": "刑事",
    "code": "M"
  },
  "year": 94,
  "word": "聲",
  "number": "65",
  "jcheck": "1",
  "reason": "聲請解除限制出境",
  "content": "臺灣高等法院臺南分院刑事裁定\n聲  請  人\n即  被  告  甲○○\n選任辯護人  朱俊雄  律師\n上列被告因民國九十三年度金上重更一字第二十七號違反證券交\n易法等案件，聲請人聲請解除限制出境，本院裁定如下：\n      主      文\n聲請駁回。\n      理      由\n一、本件聲請意旨略以：\n（一）聲請人即被告甲○○於民國（下同）九十一年七月十九日\n      上午原高等法院行調查庭時，因另有要事由陳文忠律師代\n      為請假未到庭，遭到場之高昇公司告訴代理人嚴加指責，\n      並當場要求法官對甲○○限制出境。並稱高昇公司遭甲○\n      ○詐騙之金額全未償還。承審法院當時即以未有正當理由\n      不到庭以及涉嚴重經濟犯罪為由將甲○○限制出境。\n（二）高昇公司對甲○○所提之詐欺告訴，已蒙前審法院認未成\n      立詐欺罪判決在案，在前事實審判決前甲○○亦已與高昇\n      公司和解而由高昇公司之告訴代理人陳水聰律師於九十二\n      年五月十五日遞狀陳報甲○○不僅已陸續與其他債權人解\n      決債務外，亦已與告訴人公司達成和解並已履行和解條件\n      （見原二審卷第二本第二百九十八頁以下），並陳述甲○\n      ○態度良好求處從輕量刑，故當時法院考量應限制出境之\n      情形已完全解除。\n（三）甲○○於前審歷經多次法院審判程序至今，從未有一庭未\n      到庭，在外更未有脫產逃避責任之行為，期間雖明知可能\n      面臨服刑之待遇，猶積極努力與受其侵占行為而受有損害\n      之所有金融機構及廠商進行分期償還債務之履行，雖所涉\n      之自首案件金額較大，但仍有全數和解清償之可能性，可\n      謂犯後態度良好，況其在地檢署及地方法院審理時因犯後\n      態度良好而受檢察官及法官之肯定而未受有限制出境之處\n      分，且桂豪公司當初在美國夏威夷所設廢鐵公司有鉅額應\n      收之帳款，非由當時之主導人甲○○親自美國接洽確認金\n      額並收取，否則難以保障桂豪公司債權人之權益，請准予\n      撤銷原限制出境處分云云。\n二、按「限制出境，係執行限制住居方法之一種，屬刑事訴訟法\n    第四百十六條第一項第一款具保處分之範圍，應由事實審法\n    院決定。」、「限制出境之處分，無非為輔助具保、責付之\n    效力，故有無限制出境之必要，當以此為考量。」，最高法\n    院七十九年度臺抗字第四七六號、八十八年度臺抗字第一六\n    六號裁定可資參照。\n三、經查：聲請人因違反證券交易法等案件，臺灣臺南地方法院\n    於九十一年三月十九日，以九十年度訴字第一五七號判處聲\n    請人有期徒刑六年，併科罰金新台幣一百萬元。聲請人上訴\n    ，於九十一年七月十九日時，法院以未有正當理由不到庭及\n    涉嚴重經濟犯罪等由將之限制出境，另經本院上訴審判處聲\n    請人有期徒刑六年，併科罰金新台幣二百萬元。聲請人再上\n    訴，經最高法院發回更審，現由本院審理中。聲請人經原審\n    及本院前審均判處有期徒刑五年以上之重刑，如任其自由出\n    境，日後審理或執行顯有困難，具保之功能亦徒具形式，足\n    見限制聲請人出境之理由仍然存在，聲請人聲請准予解除被\n    告出境，尚難准許，應予駁回。爰裁定如主文。\n中    華    民    國    94    年    4     月    12    日\n                  刑事第四庭     審判長法  官  鄭文肅\n                                       法  官  陳珍如\n                                       法  官  林勝木\n以上正本證明與原本無異。\n如不服本裁定，應於收受本裁定後五日內向本院提出抗告狀。\n                                       書記官  吳秋賢\n中    華    民    國    94    年    4     月    14    日\n",
  "structure": {
    "main": "聲請駁回。",
    "reason": "一、本件聲請意旨略以：\n（一）聲請人即被告甲○○於民國（下同）九十一年七月十九日\n      上午原高等法院行調查庭時，因另有要事由陳文忠律師代\n      為請假未到庭，遭到場之高昇公司告訴代理人嚴加指責，\n      並當場要求法官對甲○○限制出境。並稱高昇公司遭甲○\n      ○詐騙之金額全未償還。承審法院當時即以未有正當理由\n      不到庭以及涉嚴重經濟犯罪為由將甲○○限制出境。\n（二）高昇公司對甲○○所提之詐欺告訴，已蒙前審法院認未成\n      立詐欺罪判決在案，在前事實審判決前甲○○亦已與高昇\n      公司和解而由高昇公司之告訴代理人陳水聰律師於九十二\n      年五月十五日遞狀陳報甲○○不僅已陸續與其他債權人解\n      決債務外，亦已與告訴人公司達成和解並已履行和解條件\n      （見原二審卷第二本第二百九十八頁以下），並陳述甲○\n      ○態度良好求處從輕量刑，故當時法院考量應限制出境之\n      情形已完全解除。\n（三）甲○○於前審歷經多次法院審判程序至今，從未有一庭未\n      到庭，在外更未有脫產逃避責任之行為，期間雖明知可能\n      面臨服刑之待遇，猶積極努力與受其侵占行為而受有損害\n      之所有金融機構及廠商進行分期償還債務之履行，雖所涉\n      之自首案件金額較大，但仍有全數和解清償之可能性，可\n      謂犯後態度良好，況其在地檢署及地方法院審理時因犯後\n      態度良好而受檢察官及法官之肯定而未受有限制出境之處\n      分，且桂豪公司當初在美國夏威夷所設廢鐵公司有鉅額應\n      收之帳款，非由當時之主導人甲○○親自美國接洽確認金\n      額並收取，否則難以保障桂豪公司債權人之權益，請准予\n      撤銷原限制出境處分云云。\n二、按「限制出境，係執行限制住居方法之一種，屬刑事訴訟法\n    第四百十六條第一項第一款具保處分之範圍，應由事實審法\n    院決定。」、「限制出境之處分，無非為輔助具保、責付之\n    效力，故有無限制出境之必要，當以此為考量。」，最高法\n    院七十九年度臺抗字第四七六號、八十八年度臺抗字第一六\n    六號裁定可資參照。\n三、經查：聲請人因違反證券交易法等案件，臺灣臺南地方法院\n    於九十一年三月十九日，以九十年度訴字第一五七號判處聲\n    請人有期徒刑六年，併科罰金新台幣一百萬元。聲請人上訴\n    ，於九十一年七月十九日時，法院以未有正當理由不到庭及\n    涉嚴重經濟犯罪等由將之限制出境，另經本院上訴審判處聲\n    請人有期徒刑六年，併科罰金新台幣二百萬元。聲請人再上\n    訴，經最高法院發回更審，現由本院審理中。聲請人經原審\n    及本院前審均判處有期徒刑五年以上之重刑，如任其自由出\n    境，日後審理或執行顯有困難，具保之功能亦徒具形式，足\n    見限制聲請人出境之理由仍然存在，聲請人聲請准予解除被\n    告出境，尚難准許，應予駁回。爰裁定如主文。"
  },
  "search": "臺灣高等法院臺南分院刑事裁定聲請人即被告甲○○選任辯護人朱俊雄律師上列被告因民國九十三年度金上重更一字第二十七號違反證券交易法等案件，聲請人聲請解除限制出境，本院裁定如下：主文聲請駁回。理由一、本件聲請意旨略以：（一）聲請人即被告甲○○於民國（下同）九十一年七月十九日上午原高等法院行調查庭時，因另有要事由陳文忠律師代為請假未到庭，遭到場之高昇公司告訴代理人嚴加指責，並當場要求法官對甲○○限制出境。並稱高昇公司遭甲○○詐騙之金額全未償還。承審法院當時即以未有正當理由不到庭以及涉嚴重經濟犯罪為由將甲○○限制出境。（二）高昇公司對甲○○所提之詐欺告訴，已蒙前審法院認未成立詐欺罪判決在案，在前事實審判決前甲○○亦已與高昇公司和解而由高昇公司之告訴代理人陳水聰律師於九十二年五月十五日遞狀陳報甲○○不僅已陸續與其他債權人解決債務外，亦已與告訴人公司達成和解並已履行和解條件（見原二審卷第二本第二百九十八頁以下），並陳述甲○○態度良好求處從輕量刑，故當時法院考量應限制出境之情形已完全解除。（三）甲○○於前審歷經多次法院審判程序至今，從未有一庭未到庭，在外更未有脫產逃避責任之行為，期間雖明知可能面臨服刑之待遇，猶積極努力與受其侵占行為而受有損害之所有金融機構及廠商進行分期償還債務之履行，雖所涉之自首案件金額較大，但仍有全數和解清償之可能性，可謂犯後態度良好，況其在地檢署及地方法院審理時因犯後態度良好而受檢察官及法官之肯定而未受有限制出境之處分，且桂豪公司當初在美國夏威夷所設廢鐵公司有鉅額應收之帳款，非由當時之主導人甲○○親自美國接洽確認金額並收取，否則難以保障桂豪公司債權人之權益，請准予撤銷原限制出境處分云云。二、按「限制出境，係執行限制住居方法之一種，屬刑事訴訟法第四百十六條第一項第一款具保處分之範圍，應由事實審法院決定。」、「限制出境之處分，無非為輔助具保、責付之效力，故有無限制出境之必要，當以此為考量。」，最高法院七十九年度臺抗字第四七六號、八十八年度臺抗字第一六六號裁定可資參照。三、經查：聲請人因違反證券交易法等案件，臺灣臺南地方法院於九十一年三月十九日，以九十年度訴字第一五七號判處聲請人有期徒刑六年，併科罰金新台幣一百萬元。聲請人上訴，於九十一年七月十九日時，法院以未有正當理由不到庭及涉嚴重經濟犯罪等由將之限制出境，另經本院上訴審判處聲請人有期徒刑六年，併科罰金新台幣二百萬元。聲請人再上訴，經最高法院發回更審，現由本院審理中。聲請人經原審及本院前審均判處有期徒刑五年以上之重刑，如任其自由出境，日後審理或執行顯有困難，具保之功能亦徒具形式，足見限制聲請人出境之理由仍然存在，聲請人聲請准予解除被告出境，尚難准許，應予駁回。爰裁定如主文。中華民國94年4月12日刑事第四庭審判長法官鄭文肅法官陳珍如法官林勝木以上正本證明與原本無異。如不服本裁定，應於收受本裁定後五日內向本院提出抗告狀。書記官吳秋賢中華民國94年4月14日",
  "characters": {
    "judges": [
      "鄭文肅",
      "陳珍如",
      "林勝木"
    ],
    "prosecutors": [

    ],
    "lawyers": [
      "公司和解而由高昇公司之告訴代理人陳水聰"
    ],
    "clerks": [
      "吳秋賢"
    ],
    "plaintiffs": [

    ],
    "defendants": [
      "甲"
    ],
    "prosecutor_office": [

    ],
    "creditors": [

    ],
    "debtors": [

    ],
    "judicial_associate_officer": [

    ]
  },
  "adjudged_at": "2005-04-12",
  "created_at": "2016-02-06 18:36:29",
  "updated_at": "2016-02-06 18:36:29"
}