{
  "identify": "KSD-100-簡-4276-20110804-1",
  "court": {
    "name": "臺灣高雄地方法院",
    "code": "KSD"
  },
  "division": {
    "name": "刑事",
    "code": "M"
  },
  "year": 100,
  "word": "簡",
  "number": "4276",
  "jcheck": "1",
  "reason": "竊盜",
  "content": "臺灣高雄地方法院刑事簡易判決         100年度簡字第4276號\n聲  請  人  臺灣高雄地方法院檢察署檢察官\n被      告  吳亞凌\n上列被告因竊盜案件，經檢察官聲請以簡易判決處刑（100年度\n偵字第19940號），本院判決如下：\n    主      文\n吳亞凌犯竊盜罪，累犯，處有期徒刑伍月，如易科罰金，以新臺\n幣壹仟元折算壹日。\n    事實及理由\n一、本件犯罪事實及證據，除犯罪事實欄一補充並更正被告前科\n    紀錄為「吳亞凌前因施用毒品案件，經本院分別以95年度訴\n    字第1155號判處有期徒刑10月、6 月，並定應執行有期徒刑\n    1 年2 月確定；再因竊盜案件，經本院以95年度易字第409\n    號判處有期徒刑1 年8 月確定，上開案件經本院以96年度聲\n    減字第3875號裁定減刑並定應執行有期徒刑為2 年2 月確定\n    ，甫於民國97年3 月22日縮刑期滿執行完畢。」、第7 行有\n    關所竊財物補充「價值約新臺幣（下同）2 萬多元」外，其\n    餘均引用檢察官聲請簡易判決處刑書所載如附件。\n二、核被告吳亞凌所為，係犯刑法第354 條第1 項之毀損罪及同\n    法第320 條第1 項之普通竊盜罪。被告基於獲取車內財物之\n    同一目的，犯毀損罪及竊盜罪，乃一行為觸犯數罪名，為想\n    像競合犯，應從一重之竊盜罪論處，檢察官聲請意旨認為毀\n    棄損壞車窗之行為，為竊盜行為之一部分，應論以一罪，容\n    有誤會，併此指明。又被告有上述所載之犯罪科刑及執行情\n    形，有臺灣高等法院被告前案紀錄表1 份在卷可查，其於受\n    有期徒刑執行完畢後，5 年內故意再犯本件有期徒刑以上之\n    罪，為累犯，應依刑法第47條第1 項規定，加重其刑。爰審\n    酌被告正值壯年，不思以正當方法謀取生活上所需，竟為貪\n    圖不法利益，率爾毀損他人物品並竊取他人財物，其犯罪之\n    動機、手段、目的均非可取，惟念其坦承犯行，且其另於94\n    年、100 年間因竊盜案件，經本院94年度簡字第3800號及99\n    年度簡字第2095號分別判處有期徒刑3 月及4 月之紀錄，此\n    品行資料有上開前案紀錄表可佐，並所竊財物價值（共2 萬\n    多元），查獲時已無從歸還告訴人，兼衡其自稱高職畢業、\n    家境勉持之智識程度與生活狀況等上開被告個人具體之行為\n    人責任基礎之一切情狀，量處如主文所示之刑，並諭知易科\n    罰金之折算標準。\n三、依刑事訴訟法第449 條第1 項前段、第3 項、第454 條第2\n    項，刑法第320 條第1 項、第354 條、第55條、第47條第1\n    項、第41條第1 項前段，刑法施行法第1 條之1 第1 項、第\n    2 項前段，逕以簡易判決處刑如主文。\n四、如不服本判決，應於收受送達判決之日起10日內，向本院提\n    起上訴（須附繕本）。\n中    華    民    國   100    年    8     月    4     日\n                    高雄簡易庭  法  官  饒志民\n以上正本，係照原本作成，證明與原本無異。\n如不服本判決，得自收受送達之日起10日內，向本院提起上訴。\n中    華    民    國   100    年    8     月    5     日\n                                書記官  蕭永同\n附錄本判決論罪之法條：\n中華民國刑法第320條\n意圖為自己或第三人不法之所有，而竊取他人之動產者，為竊盜\n罪，處5年以下有期徒刑、拘役或5百元以下罰金。\n意圖為自己或第三人不法之利益，而竊佔他人之不動產者，依前\n項之規定處斷。\n前二項之未遂犯罰之。\n中華民國刑法第354條\n毀棄、損壞前二條以外之他人之物或致令不堪用，足以生損害於\n公眾或他人者，處2年以下有期徒刑、拘役或5百元以下罰金。\n附件\n臺灣高雄地方法院檢察署檢察官聲請簡易判決處刑書\n                                    100年度偵字第19940號\n    被      告  吳亞凌  男  36歲（民國○○年○月○日生）\n                        籍設高雄市○○區○○里○○路光明\n                            6巷30號\n                        （另案執行中）\n                        國民身分證統一編號：Ｚ000000000號\n上列被告因竊盜案件，業經偵查終結，認為宜聲請以簡易判決處\n刑，茲將犯罪事實及證據並所犯法條分敘如下：\n        犯罪事實\n一、吳亞凌前因竊盜及違反毒品危害防制條例案件，經臺灣高雄\n    地方法院分別判處有期徒刑1年8月、6月及10月，應執行有\n    期徒刑2年8月確定，上開3罪接續執行，於民國97年3月23日\n    執行完畢。詎吳亞凌仍不知悔改，於100年4月23日13時30分\n    許，騎乘車牌號碼712—BAP號之普通重型機車前往設於高雄\n    市苓雅區境內之新光碼頭內，見陳政陽所有之公事包（品牌\n    為COACH，內有員工、客戶之個人資料及LED燈泡樣品等財物\n    ）置於陳政陽所停放於上址，車牌號碼8265—UU號自用小客\n    車內，竟基於不法所有之意圖，先徒手毀損上開車輛之右前\n    車窗玻璃，致上開車輛之右前座位之車窗玻璃因而有破損之\n    損害，迨上開車窗玻璃毀壞後，吳亞凌遂徒手竊取該公事包\n    得手。詎吳亞凌竊得該公事包後，見手提包內僅有個人資料\n    及LED燈，而無其欲竊取之現金，乃於同日，在高雄市○○\n    路與海邊路口之橋上，將該公事包丟棄於愛河內。嗣經員警\n    調閱監視錄影畫面後循線查獲，始知上情。\n二、案經陳政陽訴由高雄市政府警察局苓雅分局移送偵辦。\n        證據並所犯法條\n一、上揭犯罪事實，業據被告吳亞凌坦承不諱，核與告訴人陳政\n    陽之指訴情節相符，並有車輛詳細資料報表2份、照片7紙附\n    卷足稽，是綜上查證，被告之罪嫌應均堪予認定。\n二、核被告所為，係犯刑法第320條第1項之竊盜罪嫌。又被告雖\n    以毀棄損壞車窗玻璃之方式竊取財物，但此係毀棄損壞車窗\n    之行為，為竊盜行為之一部分，請論以一罪。而被告事後丟\n    棄財物之犯行，亦屬竊盜後處分財物之行為，為不罰之後行\n    為。至被告曾受有期徒刑執行完畢（有本署刑案資料查註紀\n    錄表附卷足稽）後，5年內再犯本件有期徒刑以上之罪，為\n    累犯，請依刑法第47條第1項之規定，加重其刑。\n三、依刑事訴訟法第451條第1項聲請逕以簡易判決處刑。\n    此  致\n臺灣高雄地方法院\n中    華    民    國   100    年    7     月    13    日\n                        檢 察 官    殷 玉 龍",
  "structure": {
    "main": "吳亞凌犯竊盜罪，累犯，處有期徒刑伍月，如易科罰金，以新臺\n幣壹仟元折算壹日。",
    "fact": "一、本件犯罪事實及證據，除犯罪事實欄一補充並更正被告前科\n    紀錄為「吳亞凌前因施用毒品案件，經本院分別以95年度訴\n    字第1155號判處有期徒刑10月、6 月，並定應執行有期徒刑\n    1 年2 月確定；再因竊盜案件，經本院以95年度易字第409\n    號判處有期徒刑1 年8 月確定，上開案件經本院以96年度聲\n    減字第3875號裁定減刑並定應執行有期徒刑為2 年2 月確定\n    ，甫於民國97年3 月22日縮刑期滿執行完畢。」、第7 行有\n    關所竊財物補充「價值約新臺幣（下同）2 萬多元」外，其\n    餘均引用檢察官聲請簡易判決處刑書所載如附件。\n二、核被告吳亞凌所為，係犯刑法第354 條第1 項之毀損罪及同\n    法第320 條第1 項之普通竊盜罪。被告基於獲取車內財物之\n    同一目的，犯毀損罪及竊盜罪，乃一行為觸犯數罪名，為想\n    像競合犯，應從一重之竊盜罪論處，檢察官聲請意旨認為毀\n    棄損壞車窗之行為，為竊盜行為之一部分，應論以一罪，容\n    有誤會，併此指明。又被告有上述所載之犯罪科刑及執行情\n    形，有臺灣高等法院被告前案紀錄表1 份在卷可查，其於受\n    有期徒刑執行完畢後，5 年內故意再犯本件有期徒刑以上之\n    罪，為累犯，應依刑法第47條第1 項規定，加重其刑。爰審\n    酌被告正值壯年，不思以正當方法謀取生活上所需，竟為貪\n    圖不法利益，率爾毀損他人物品並竊取他人財物，其犯罪之\n    動機、手段、目的均非可取，惟念其坦承犯行，且其另於94\n    年、100 年間因竊盜案件，經本院94年度簡字第3800號及99\n    年度簡字第2095號分別判處有期徒刑3 月及4 月之紀錄，此\n    品行資料有上開前案紀錄表可佐，並所竊財物價值（共2 萬\n    多元），查獲時已無從歸還告訴人，兼衡其自稱高職畢業、\n    家境勉持之智識程度與生活狀況等上開被告個人具體之行為\n    人責任基礎之一切情狀，量處如主文所示之刑，並諭知易科\n    罰金之折算標準。\n三、依刑事訴訟法第449 條第1 項前段、第3 項、第454 條第2\n    項，刑法第320 條第1 項、第354 條、第55條、第47條第1\n    項、第41條第1 項前段，刑法施行法第1 條之1 第1 項、第\n    2 項前段，逕以簡易判決處刑如主文。\n四、如不服本判決，應於收受送達判決之日起10日內，向本院提\n    起上訴（須附繕本）。",
    "reason": "一、本件犯罪事實及證據，除犯罪事實欄一補充並更正被告前科\n    紀錄為「吳亞凌前因施用毒品案件，經本院分別以95年度訴\n    字第1155號判處有期徒刑10月、6 月，並定應執行有期徒刑\n    1 年2 月確定；再因竊盜案件，經本院以95年度易字第409\n    號判處有期徒刑1 年8 月確定，上開案件經本院以96年度聲\n    減字第3875號裁定減刑並定應執行有期徒刑為2 年2 月確定\n    ，甫於民國97年3 月22日縮刑期滿執行完畢。」、第7 行有\n    關所竊財物補充「價值約新臺幣（下同）2 萬多元」外，其\n    餘均引用檢察官聲請簡易判決處刑書所載如附件。\n二、核被告吳亞凌所為，係犯刑法第354 條第1 項之毀損罪及同\n    法第320 條第1 項之普通竊盜罪。被告基於獲取車內財物之\n    同一目的，犯毀損罪及竊盜罪，乃一行為觸犯數罪名，為想\n    像競合犯，應從一重之竊盜罪論處，檢察官聲請意旨認為毀\n    棄損壞車窗之行為，為竊盜行為之一部分，應論以一罪，容\n    有誤會，併此指明。又被告有上述所載之犯罪科刑及執行情\n    形，有臺灣高等法院被告前案紀錄表1 份在卷可查，其於受\n    有期徒刑執行完畢後，5 年內故意再犯本件有期徒刑以上之\n    罪，為累犯，應依刑法第47條第1 項規定，加重其刑。爰審\n    酌被告正值壯年，不思以正當方法謀取生活上所需，竟為貪\n    圖不法利益，率爾毀損他人物品並竊取他人財物，其犯罪之\n    動機、手段、目的均非可取，惟念其坦承犯行，且其另於94\n    年、100 年間因竊盜案件，經本院94年度簡字第3800號及99\n    年度簡字第2095號分別判處有期徒刑3 月及4 月之紀錄，此\n    品行資料有上開前案紀錄表可佐，並所竊財物價值（共2 萬\n    多元），查獲時已無從歸還告訴人，兼衡其自稱高職畢業、\n    家境勉持之智識程度與生活狀況等上開被告個人具體之行為\n    人責任基礎之一切情狀，量處如主文所示之刑，並諭知易科\n    罰金之折算標準。\n三、依刑事訴訟法第449 條第1 項前段、第3 項、第454 條第2\n    項，刑法第320 條第1 項、第354 條、第55條、第47條第1\n    項、第41條第1 項前段，刑法施行法第1 條之1 第1 項、第\n    2 項前段，逕以簡易判決處刑如主文。\n四、如不服本判決，應於收受送達判決之日起10日內，向本院提\n    起上訴（須附繕本）。"
  },
  "search": "臺灣高雄地方法院刑事簡易判決100年度簡字第4276號聲請人臺灣高雄地方法院檢察署檢察官被告吳亞凌上列被告因竊盜案件，經檢察官聲請以簡易判決處刑（100年度偵字第19940號），本院判決如下：主文吳亞凌犯竊盜罪，累犯，處有期徒刑伍月，如易科罰金，以新臺幣壹仟元折算壹日。事實及理由一、本件犯罪事實及證據，除犯罪事實欄一補充並更正被告前科紀錄為「吳亞凌前因施用毒品案件，經本院分別以95年度訴字第1155號判處有期徒刑10月、6月，並定應執行有期徒刑1年2月確定；再因竊盜案件，經本院以95年度易字第409號判處有期徒刑1年8月確定，上開案件經本院以96年度聲減字第3875號裁定減刑並定應執行有期徒刑為2年2月確定，甫於民國97年3月22日縮刑期滿執行完畢。」、第7行有關所竊財物補充「價值約新臺幣（下同）2萬多元」外，其餘均引用檢察官聲請簡易判決處刑書所載如附件。二、核被告吳亞凌所為，係犯刑法第354條第1項之毀損罪及同法第320條第1項之普通竊盜罪。被告基於獲取車內財物之同一目的，犯毀損罪及竊盜罪，乃一行為觸犯數罪名，為想像競合犯，應從一重之竊盜罪論處，檢察官聲請意旨認為毀棄損壞車窗之行為，為竊盜行為之一部分，應論以一罪，容有誤會，併此指明。又被告有上述所載之犯罪科刑及執行情形，有臺灣高等法院被告前案紀錄表1份在卷可查，其於受有期徒刑執行完畢後，5年內故意再犯本件有期徒刑以上之罪，為累犯，應依刑法第47條第1項規定，加重其刑。爰審酌被告正值壯年，不思以正當方法謀取生活上所需，竟為貪圖不法利益，率爾毀損他人物品並竊取他人財物，其犯罪之動機、手段、目的均非可取，惟念其坦承犯行，且其另於94年、100年間因竊盜案件，經本院94年度簡字第3800號及99年度簡字第2095號分別判處有期徒刑3月及4月之紀錄，此品行資料有上開前案紀錄表可佐，並所竊財物價值（共2萬多元），查獲時已無從歸還告訴人，兼衡其自稱高職畢業、家境勉持之智識程度與生活狀況等上開被告個人具體之行為人責任基礎之一切情狀，量處如主文所示之刑，並諭知易科罰金之折算標準。三、依刑事訴訟法第449條第1項前段、第3項、第454條第2項，刑法第320條第1項、第354條、第55條、第47條第1項、第41條第1項前段，刑法施行法第1條之1第1項、第2項前段，逕以簡易判決處刑如主文。四、如不服本判決，應於收受送達判決之日起10日內，向本院提起上訴（須附繕本）。中華民國100年8月4日高雄簡易庭法官饒志民以上正本，係照原本作成，證明與原本無異。如不服本判決，得自收受送達之日起10日內，向本院提起上訴。中華民國100年8月5日書記官蕭永同附錄本判決論罪之法條：中華民國刑法第320條意圖為自己或第三人不法之所有，而竊取他人之動產者，為竊盜罪，處5年以下有期徒刑、拘役或5百元以下罰金。意圖為自己或第三人不法之利益，而竊佔他人之不動產者，依前項之規定處斷。前二項之未遂犯罰之。中華民國刑法第354條毀棄、損壞前二條以外之他人之物或致令不堪用，足以生損害於公眾或他人者，處2年以下有期徒刑、拘役或5百元以下罰金。附件臺灣高雄地方法院檢察署檢察官聲請簡易判決處刑書100年度偵字第19940號被告吳亞凌男36歲（民國○○年○月○日生）籍設高雄市○○區○○里○○路光明6巷30號（另案執行中）國民身分證統一編號：Ｚ000000000號上列被告因竊盜案件，業經偵查終結，認為宜聲請以簡易判決處刑，茲將犯罪事實及證據並所犯法條分敘如下：犯罪事實一、吳亞凌前因竊盜及違反毒品危害防制條例案件，經臺灣高雄地方法院分別判處有期徒刑1年8月、6月及10月，應執行有期徒刑2年8月確定，上開3罪接續執行，於民國97年3月23日執行完畢。詎吳亞凌仍不知悔改，於100年4月23日13時30分許，騎乘車牌號碼712—BAP號之普通重型機車前往設於高雄市苓雅區境內之新光碼頭內，見陳政陽所有之公事包（品牌為COACH，內有員工、客戶之個人資料及LED燈泡樣品等財物）置於陳政陽所停放於上址，車牌號碼8265—UU號自用小客車內，竟基於不法所有之意圖，先徒手毀損上開車輛之右前車窗玻璃，致上開車輛之右前座位之車窗玻璃因而有破損之損害，迨上開車窗玻璃毀壞後，吳亞凌遂徒手竊取該公事包得手。詎吳亞凌竊得該公事包後，見手提包內僅有個人資料及LED燈，而無其欲竊取之現金，乃於同日，在高雄市○○路與海邊路口之橋上，將該公事包丟棄於愛河內。嗣經員警調閱監視錄影畫面後循線查獲，始知上情。二、案經陳政陽訴由高雄市政府警察局苓雅分局移送偵辦。證據並所犯法條一、上揭犯罪事實，業據被告吳亞凌坦承不諱，核與告訴人陳政陽之指訴情節相符，並有車輛詳細資料報表2份、照片7紙附卷足稽，是綜上查證，被告之罪嫌應均堪予認定。二、核被告所為，係犯刑法第320條第1項之竊盜罪嫌。又被告雖以毀棄損壞車窗玻璃之方式竊取財物，但此係毀棄損壞車窗之行為，為竊盜行為之一部分，請論以一罪。而被告事後丟棄財物之犯行，亦屬竊盜後處分財物之行為，為不罰之後行為。至被告曾受有期徒刑執行完畢（有本署刑案資料查註紀錄表附卷足稽）後，5年內再犯本件有期徒刑以上之罪，為累犯，請依刑法第47條第1項之規定，加重其刑。三、依刑事訴訟法第451條第1項聲請逕以簡易判決處刑。此致臺灣高雄地方法院中華民國100年7月13日檢察官殷玉龍",
  "characters": {
    "judges": [
      "饒志民"
    ],
    "prosecutors": [

    ],
    "lawyers": [

    ],
    "clerks": [
      "蕭永同"
    ],
    "plaintiffs": [

    ],
    "defendants": [
      "吳亞凌",
      "吳亞凌  男  36歲（民國○○年○月○日生）"
    ],
    "prosecutor_office": [
      "臺灣高雄地方法院檢察署檢察官"
    ],
    "creditors": [

    ],
    "debtors": [

    ],
    "judicial_associate_officer": [

    ]
  },
  "adjudged_at": "2011-08-04",
  "created_at": "2016-02-12 19:46:24",
  "updated_at": "2016-02-12 19:46:24"
}