{
  "identify": "TPH-100-聲-2374-20110804-1",
  "court": {
    "name": "臺灣高等法院",
    "code": "TPH"
  },
  "division": {
    "name": "刑事",
    "code": "M"
  },
  "year": 100,
  "word": "聲",
  "number": "2374",
  "jcheck": "1",
  "reason": "聲請定其應執行刑",
  "content": "臺灣高等法院刑事裁定                 100年度聲字第2374號\n聲  請  人  臺灣高等法院檢察署檢察官\n受  刑  人  林育宗\n上列聲請人因受刑人數罪併罰有二裁判以上，聲請定其應執行之\n刑（聲請案號：100年度執聲字第1132號），本院裁定如下：\n    主  文\n林育宗因犯如附表所示各罪所處之刑，應執行有期徒刑拾貳年\n月。\n    理  由\n一、受刑人林育宗因犯毒品危害防制條例等數罪，經本院判處如\n    附表所示之刑，受刑人上訴最高法院，經最高法院以100年\n    度台上字3691號判決，就附表所示之數罪，駁回上訴，業經\n    確定在案。茲檢察官聲請定其應執行之刑，本院審核認聲請\n    為正當，應定其應執行之刑如主文所示。\n二、據上論斷，應依刑事訴訟法第477條第1項、刑法第53條、第\n    51條第5款，裁定如主文。\n中    華    民    國   100    年    8     月    4     日\n                  刑事第二十庭      審判長法  官  周盈文\n                                          法  官  潘進柳\n                                          法  官  詹駿鴻\n以上正本證明與原本無異。\n如不服本裁定，應於收受送達後五日內向本院提出抗告狀。\n                                          書記官  梁淑時\n中    華    民    國   100    年    8     月    4     日",
  "structure": {
    "main": "林育宗因犯如附表所示各罪所處之刑，應執行有期徒刑拾貳年\n月。",
    "reason": "一、受刑人林育宗因犯毒品危害防制條例等數罪，經本院判處如\n    附表所示之刑，受刑人上訴最高法院，經最高法院以100年\n    度台上字3691號判決，就附表所示之數罪，駁回上訴，業經\n    確定在案。茲檢察官聲請定其應執行之刑，本院審核認聲請\n    為正當，應定其應執行之刑如主文所示。\n二、據上論斷，應依刑事訴訟法第477條第1項、刑法第53條、第\n    51條第5款，裁定如主文。"
  },
  "search": "臺灣高等法院刑事裁定100年度聲字第2374號聲請人臺灣高等法院檢察署檢察官受刑人林育宗上列聲請人因受刑人數罪併罰有二裁判以上，聲請定其應執行之刑（聲請案號：100年度執聲字第1132號），本院裁定如下：主文林育宗因犯如附表所示各罪所處之刑，應執行有期徒刑拾貳年月。理由一、受刑人林育宗因犯毒品危害防制條例等數罪，經本院判處如附表所示之刑，受刑人上訴最高法院，經最高法院以100年度台上字3691號判決，就附表所示之數罪，駁回上訴，業經確定在案。茲檢察官聲請定其應執行之刑，本院審核認聲請為正當，應定其應執行之刑如主文所示。二、據上論斷，應依刑事訴訟法第477條第1項、刑法第53條、第51條第5款，裁定如主文。中華民國100年8月4日刑事第二十庭審判長法官周盈文法官潘進柳法官詹駿鴻以上正本證明與原本無異。如不服本裁定，應於收受送達後五日內向本院提出抗告狀。書記官梁淑時中華民國100年8月4日",
  "characters": {
    "judges": [
      "周盈文",
      "潘進柳",
      "詹駿鴻"
    ],
    "prosecutors": [

    ],
    "lawyers": [

    ],
    "clerks": [
      "梁淑時"
    ],
    "plaintiffs": [

    ],
    "defendants": [

    ],
    "prosecutor_office": [
      "臺灣高等法院檢察署檢察官"
    ],
    "creditors": [

    ],
    "debtors": [

    ],
    "judicial_associate_officer": [

    ]
  },
  "adjudged_at": "2011-08-04",
  "created_at": "2016-02-12 19:41:23",
  "updated_at": "2016-02-12 19:41:23"
}