{
  "identify": "TPH-93-上訴-2986-20050107-1",
  "court": {
    "name": "臺灣高等法院",
    "code": "TPH"
  },
  "division": {
    "name": "刑事",
    "code": "M"
  },
  "year": 93,
  "word": "上訴",
  "number": "2986",
  "jcheck": "1",
  "reason": "殺人等",
  "content": "臺灣高等法院刑事裁定                93年度上訴字第2986號\n上  訴  人\n即  被  告  甲○○\n                    號（\n指定辯護人  本院公設辯護人  王永炫\n上列被告因殺人等案件，本院裁定如下：\n    主  文\n甲○○羈押期間，自民國九十四年一月二十日起，延長貳月。\n    理  由\n一、上訴人即被告甲○○前經本院認犯殺人等罪嫌疑重大，有刑\n    事訴訟法第101 條第1 項第3 款情形，非予羈押，顯難進行\n    審判，於民國（下同）93年10月20日執行羈押，至94 年1月\n    19日，3 個月羈押期間即將屆滿。\n二、茲本院以前項原因依然存在，認有繼續羈押之必要，應自民\n    國94年1 月20日起，延長羈押2 月，爰依刑事訴訟法第108\n    條第1 項、第5 項，裁定如主文。\n中    華    民    國    94    年    1     月    7     日\n                  刑事第十六庭審判長法  官  許增男\n                                    法  官  周煙平\n                                    法  官  謝靜恒\n以上正本證明與原本無異。\n如不服本裁定應於收送受達後5日內向本院提出抗告書狀。\n                                    書記官  魏淑娟\n中    華    民    國    94    年    1     月    7     日\n",
  "structure": {
    "main": "甲○○羈押期間，自民國九十四年一月二十日起，延長貳月。",
    "reason": "一、上訴人即被告甲○○前經本院認犯殺人等罪嫌疑重大，有刑\n    事訴訟法第101 條第1 項第3 款情形，非予羈押，顯難進行\n    審判，於民國（下同）93年10月20日執行羈押，至94 年1月\n    19日，3 個月羈押期間即將屆滿。\n二、茲本院以前項原因依然存在，認有繼續羈押之必要，應自民\n    國94年1 月20日起，延長羈押2 月，爰依刑事訴訟法第108\n    條第1 項、第5 項，裁定如主文。"
  },
  "search": "臺灣高等法院刑事裁定93年度上訴字第2986號上訴人即被告甲○○號（指定辯護人本院公設辯護人王永炫上列被告因殺人等案件，本院裁定如下：主文甲○○羈押期間，自民國九十四年一月二十日起，延長貳月。理由一、上訴人即被告甲○○前經本院認犯殺人等罪嫌疑重大，有刑事訴訟法第101條第1項第3款情形，非予羈押，顯難進行審判，於民國（下同）93年10月20日執行羈押，至94年1月19日，3個月羈押期間即將屆滿。二、茲本院以前項原因依然存在，認有繼續羈押之必要，應自民國94年1月20日起，延長羈押2月，爰依刑事訴訟法第108條第1項、第5項，裁定如主文。中華民國94年1月7日刑事第十六庭審判長法官許增男法官周煙平法官謝靜恒以上正本證明與原本無異。如不服本裁定應於收送受達後5日內向本院提出抗告書狀。書記官魏淑娟中華民國94年1月7日",
  "characters": {
    "judges": [
      "許增男",
      "周煙平",
      "謝靜恒"
    ],
    "prosecutors": [

    ],
    "lawyers": [

    ],
    "clerks": [
      "魏淑娟"
    ],
    "plaintiffs": [

    ],
    "defendants": [
      "甲"
    ],
    "prosecutor_office": [

    ],
    "creditors": [

    ],
    "debtors": [

    ],
    "judicial_associate_officer": [

    ]
  },
  "adjudged_at": "2005-01-07",
  "created_at": "2016-02-07 02:26:03",
  "updated_at": "2016-02-07 02:26:03"
}