{
  "identify": "PCD-100-交易-492-20110919-1",
  "court": {
    "name": "臺灣新北地方法院",
    "code": "PCD"
  },
  "division": {
    "name": "刑事",
    "code": "M"
  },
  "year": 100,
  "word": "交易",
  "number": "492",
  "jcheck": "1",
  "reason": "過失傷害",
  "content": "臺灣板橋地方法院刑事判決            100年度交易字第492號\n公  訴  人  臺灣板橋地方法院檢察署檢察官\n被      告  林昇永\n上列被告因過失傷害案件，經檢察官提起公訴（100 年度偵字第\n4176號），本院判決如下：\n    主  文\n本件公訴不受理。\n    理  由\n一、公訴意旨略以：被告林昇永係公車司機，為從事駕駛業務之\n    人，於民國99年11月26日16時30分許，駕駛車牌號碼AG-873\n    號營業大客車，沿臺北縣中和市（現改制為新北市中和區○\n    ○○路○ 段行駛，嗣行至臺北縣中和市○○路○ 段60號前之\n    南勢角站，開啟車門供乘客下車後，本應注意關閉車門時，\n    須注意乘客是否業已上下車完畢，以避免車門於開閉之際傷\n    及乘客，且依當時情況亦無不能注意情事，竟疏未注意尚有\n    乘客即告訴人公保在後車門處欲下車，貿然將車門關閉，致\n    夾傷告訴人腳部，嗣經告訴人之子才仁班覺呼叫被告停車，\n    被告於車輛未完全停妥之際，即開啟車門，致告訴人跌落車\n    外地面，因而受有右側足踝骨折之傷害。因認被告涉犯刑法\n    第284 條第2 項之業務過失傷害罪嫌云云。\n二、按告訴乃論之罪，告訴人於第一審辯論終結前得撤回其告訴\n    ；告訴經撤回者，應諭知不受理之判決；又前開不受理判決\n    得不經言詞辯論為之，刑事訴訟法第238 條第1 項、第303\n    條第3 款、第307 條分別定有明文。\n三、查本件告訴人公保告訴被告林昇永過失傷害案件，起訴書認\n    被告係觸犯刑法第284 條第2 項之業務過失傷害罪，依同法\n    第287 條前段規定，須告訴乃論。茲據告訴人具狀撤回告訴\n    ，有聲請撤回告訴狀1 份在卷可憑，依照首開說明，本件爰\n    不經言詞辯論，逕為不受理之諭知。\n據上論斷，應依刑事訴訟法第303 條第3 款、第307 條，判決如\n主文。\n中    華    民    國   100    年    9     月    19    日\n                  刑事第十四庭  法  官  俞秀美\n上列正本證明與原本無異。\n如不服本判決，應於判決送達後10日內敘明上訴理由，向本院提\n出上訴狀 (應附繕本) ，上訴於臺灣高等法院。其未敘述上訴理\n由者，應於上訴期間屆滿後20日內向本院補提理由書「切勿逕送\n上級法院」。\n                                書記官  謝怡貞\n中    華    民    國   100    年    9     月    19    日",
  "structure": {
    "main": "本件公訴不受理。",
    "reason": "一、公訴意旨略以：被告林昇永係公車司機，為從事駕駛業務之\n    人，於民國99年11月26日16時30分許，駕駛車牌號碼AG-873\n    號營業大客車，沿臺北縣中和市（現改制為新北市中和區○\n    ○○路○ 段行駛，嗣行至臺北縣中和市○○路○ 段60號前之\n    南勢角站，開啟車門供乘客下車後，本應注意關閉車門時，\n    須注意乘客是否業已上下車完畢，以避免車門於開閉之際傷\n    及乘客，且依當時情況亦無不能注意情事，竟疏未注意尚有\n    乘客即告訴人公保在後車門處欲下車，貿然將車門關閉，致\n    夾傷告訴人腳部，嗣經告訴人之子才仁班覺呼叫被告停車，\n    被告於車輛未完全停妥之際，即開啟車門，致告訴人跌落車\n    外地面，因而受有右側足踝骨折之傷害。因認被告涉犯刑法\n    第284 條第2 項之業務過失傷害罪嫌云云。\n二、按告訴乃論之罪，告訴人於第一審辯論終結前得撤回其告訴\n    ；告訴經撤回者，應諭知不受理之判決；又前開不受理判決\n    得不經言詞辯論為之，刑事訴訟法第238 條第1 項、第303\n    條第3 款、第307 條分別定有明文。\n三、查本件告訴人公保告訴被告林昇永過失傷害案件，起訴書認\n    被告係觸犯刑法第284 條第2 項之業務過失傷害罪，依同法\n    第287 條前段規定，須告訴乃論。茲據告訴人具狀撤回告訴\n    ，有聲請撤回告訴狀1 份在卷可憑，依照首開說明，本件爰\n    不經言詞辯論，逕為不受理之諭知。\n據上論斷，應依刑事訴訟法第303 條第3 款、第307 條，判決如\n主文。"
  },
  "search": "臺灣板橋地方法院刑事判決100年度交易字第492號公訴人臺灣板橋地方法院檢察署檢察官被告林昇永上列被告因過失傷害案件，經檢察官提起公訴（100年度偵字第4176號），本院判決如下：主文本件公訴不受理。理由一、公訴意旨略以：被告林昇永係公車司機，為從事駕駛業務之人，於民國99年11月26日16時30分許，駕駛車牌號碼AG-873號營業大客車，沿臺北縣中和市（現改制為新北市中和區○○○路○段行駛，嗣行至臺北縣中和市○○路○段60號前之南勢角站，開啟車門供乘客下車後，本應注意關閉車門時，須注意乘客是否業已上下車完畢，以避免車門於開閉之際傷及乘客，且依當時情況亦無不能注意情事，竟疏未注意尚有乘客即告訴人公保在後車門處欲下車，貿然將車門關閉，致夾傷告訴人腳部，嗣經告訴人之子才仁班覺呼叫被告停車，被告於車輛未完全停妥之際，即開啟車門，致告訴人跌落車外地面，因而受有右側足踝骨折之傷害。因認被告涉犯刑法第284條第2項之業務過失傷害罪嫌云云。二、按告訴乃論之罪，告訴人於第一審辯論終結前得撤回其告訴；告訴經撤回者，應諭知不受理之判決；又前開不受理判決得不經言詞辯論為之，刑事訴訟法第238條第1項、第303條第3款、第307條分別定有明文。三、查本件告訴人公保告訴被告林昇永過失傷害案件，起訴書認被告係觸犯刑法第284條第2項之業務過失傷害罪，依同法第287條前段規定，須告訴乃論。茲據告訴人具狀撤回告訴，有聲請撤回告訴狀1份在卷可憑，依照首開說明，本件爰不經言詞辯論，逕為不受理之諭知。據上論斷，應依刑事訴訟法第303條第3款、第307條，判決如主文。中華民國100年9月19日刑事第十四庭法官俞秀美上列正本證明與原本無異。如不服本判決，應於判決送達後10日內敘明上訴理由，向本院提出上訴狀(應附繕本)，上訴於臺灣高等法院。其未敘述上訴理由者，應於上訴期間屆滿後20日內向本院補提理由書「切勿逕送上級法院」。書記官謝怡貞中華民國100年9月19日",
  "characters": {
    "judges": [
      "俞秀美"
    ],
    "prosecutors": [

    ],
    "lawyers": [

    ],
    "clerks": [
      "謝怡貞"
    ],
    "plaintiffs": [

    ],
    "defendants": [
      "林昇永"
    ],
    "prosecutor_office": [
      "臺灣板橋地方法院檢察署檢察官"
    ],
    "creditors": [

    ],
    "debtors": [

    ],
    "judicial_associate_officer": [

    ]
  },
  "adjudged_at": "2011-09-19",
  "created_at": "2016-02-12 11:45:02",
  "updated_at": "2016-02-12 11:45:02"
}