{
  "identify": "KSD-93-訴-3239-20041227-1",
  "court": {
    "name": "臺灣高雄地方法院",
    "code": "KSD"
  },
  "division": {
    "name": "刑事",
    "code": "M"
  },
  "year": 93,
  "word": "訴",
  "number": "3239",
  "jcheck": "1",
  "reason": "毒品危害防制條例",
  "content": "臺灣高雄地方法院刑事判決                        九十三年度訴字第三二三九號\n    公  訴  人  臺灣高雄地方法院檢察署檢察官\n    被      告  乙○○  男  二.\n右列被告因違反毒品危害防制條例案件，經檢察官提起公訴（九十三年度毒偵字第五\n六一八號），嗣因被告就被訴事實為有罪之陳述，經本院合議庭裁定由受命法官獨任\n適用簡式審判程序審理，本院判決如左：\n    主  文\n乙○○施用第一級毒品，處有期徒刑柒月。\n    事  實\n一、乙○○前因施用毒品案件，經本院以九十年度毒聲字第三六四二號裁定送觀察、\n    勒戒後，認有繼續施用毒品之傾向，經本院以九十年度毒聲字第三九一四號裁定\n    令入戒治處所施以強制戒治，於戒治期間表現良好，經本院以九十年度毒聲字第\n    七六六○號裁定停止戒治，所餘戒治期間付保護管束，於民國九十一年六月二十\n    七日保護管束期滿視為執行完畢，由臺灣高雄地方法院檢察署檢察官於九十一年\n    八月五日，以九十一年度戒毒偵字第七二七號不起訴處分確定。詎不知悔改，於\n    上開強制戒治執行完畢釋放後五年內，基於施用第一級毒品之犯意，於九十三年\n    七月二十七日中午，在高雄縣林園鄉○○村○○路上王爺廟旁，以將海洛因摻入\n    香菸內點火吸食其霧化氣體之方式，施用第一級毒品海洛因一次。嗣因臺灣高雄\n    地方法院檢察署檢察官依法對乙○○核發強制採驗尿液許可書，警方持該許可書\n    ，於九十三年七月二十八日上午十一時五分許，至乙○○位於高雄縣林園鄉○○\n    村○○路一○一巷一八號之住處，通知乙○○配合至高雄縣政府警察局鳳山採尿\n    室採受強制採尿送驗後查獲。\n二、案經高雄縣政府警察局林園分局報請臺灣高雄地方法院檢察署檢察官偵查起訴後\n    ，由本院改依簡式審判程序審理。\n    理  由\n一、本件被告所犯為死刑、無期徒刑、最輕本刑為三年以上有期徒刑以外之罪，其於\n    準備程序進行中，就被訴事實為有罪之陳述，經受命法官告知簡式審判程序之旨\n    ，並聽取當事人之意見後，本院合議庭裁定由受命法官獨任進行簡式審判程序，\n    合先敘明。\n二、前揭事實，業據被告乙○○於本院審理中自白不諱，且被告於九十三年七月二十\n    八日為警採集尿液送驗結果，呈嗎啡陽性反應，有臺灣檢驗科技股份有限公司九\n    十三年八月二十四日編號ＫＺ000000000000號濫用藥物尿液檢驗報\n    告、列管毒品人口尿液檢體採集送驗紀錄表各一份附卷可憑，堪認被告上開自白\n    與事實相符，其確有施用海洛因無疑。再被告前因施用毒品案件，經本院以九十\n    年度毒聲字第三六四二號裁定送觀察、勒戒後，認有繼續施用毒品之傾向，經本\n    院以九十年度毒聲字第三九一四號裁定令入戒治處所施以強制戒治，於戒治期間\n    表現良好，經本院以九十年度毒聲字第七六六○號裁定停止戒治，所餘戒治期間\n    付保護管束，於九十一年六月二十七日保護管束期滿視為執行完畢，由臺灣高雄\n    地方法院檢察署檢察官於九十一年八月五日，以九十一年度戒毒偵字第七二七號\n    不起訴處分確定之事實，有臺灣高等法院被告全國前案紀錄表、本院被告院內索\n    引卡紀錄表、臺灣高雄地方法院檢察署刑案資料查註紀錄表各一紙在卷可稽，被\n    告於強制戒治執行完畢釋放後五年內，再度犯施用海洛因罪，事證明確，其犯行\n    應堪認定。\n三、按海洛因係毒品危害防制條例第二條第二項第一款所稱之第一級毒品，不得非法\n    持有、施用。次按犯毒品危害防制條例第十條施用第一級、第二級毒品之罪者，\n    檢察官應先將被告送勒戒處所觀察、勒戒，經觀察、勒戒後，認有繼續施用毒品\n    傾向者，應由檢察官聲請法院裁定令入戒治處所施以強制戒治，強制戒治期滿，\n    應由檢察官為不起訴之處分，依此強制戒治執行完畢釋放後，五年內再犯第十條\n    之罪，檢察官應依一般刑事訴訟程序予以起訴論罪科刑，此觀諸毒品危害防制條\n    例第二十條第一項、第二項、第二十三條第二項前段規定自明。本件被告前經強\n    制戒治執行完畢釋放後，五年內再犯本案施用毒品犯行，即屬應依法論罪科刑之\n    行為，是核被告所為，係犯毒品危害防制條例第十條第一項之施用第一級毒品罪\n    。被告施用第一級毒品前後持有海洛因之低度行為，為施用之高度行為所吸收，\n    不另論罪。爰審酌被告歷經觀察、勒戒及強制戒治等程序，猶無法戒絕毒癮，仍\n    再度施用海洛因，顯見其意志不堅，無悔改之決心，有違政府制定毒品危害防制\n    條例之立法美意，本不宜寬貸，惟念其所為尚未害及他人，且犯後坦承犯行，態\n    度尚佳等一切情狀，量處如主文所示之刑，以資懲儆。\n據上論斷，應依刑事訴訟法第二百九十九條第一項前段、第二百七十三條之一第一項\n，毒品危害防制條例第十條第一項，判決如主文。\n本案經檢察官甲○○到庭執行職務。\n中      華      民      國    九十三    年     十二     月    二十七    日\n                                  臺灣高雄地方法院刑事庭\n                                        法      官  莊珮君\n右正本證明與原本無異。\n如不服本判決，應於判決送達後十日內，向本院提出上訴狀。\n                                        法院書記官  呂怜勳\n中      華      民      國    九十三    年     十二     月    二十七    日\n附錄：\n毒品危害防制條例第十條第一項\n施用第一級毒品者，處六月以上五年以下有期徒刑。\n",
  "structure": {
    "main": "乙○○施用第一級毒品，處有期徒刑柒月。",
    "fact": "一、乙○○前因施用毒品案件，經本院以九十年度毒聲字第三六四二號裁定送觀察、\n    勒戒後，認有繼續施用毒品之傾向，經本院以九十年度毒聲字第三九一四號裁定\n    令入戒治處所施以強制戒治，於戒治期間表現良好，經本院以九十年度毒聲字第\n    七六六○號裁定停止戒治，所餘戒治期間付保護管束，於民國九十一年六月二十\n    七日保護管束期滿視為執行完畢，由臺灣高雄地方法院檢察署檢察官於九十一年\n    八月五日，以九十一年度戒毒偵字第七二七號不起訴處分確定。詎不知悔改，於\n    上開強制戒治執行完畢釋放後五年內，基於施用第一級毒品之犯意，於九十三年\n    七月二十七日中午，在高雄縣林園鄉○○村○○路上王爺廟旁，以將海洛因摻入\n    香菸內點火吸食其霧化氣體之方式，施用第一級毒品海洛因一次。嗣因臺灣高雄\n    地方法院檢察署檢察官依法對乙○○核發強制採驗尿液許可書，警方持該許可書\n    ，於九十三年七月二十八日上午十一時五分許，至乙○○位於高雄縣林園鄉○○\n    村○○路一○一巷一八號之住處，通知乙○○配合至高雄縣政府警察局鳳山採尿\n    室採受強制採尿送驗後查獲。\n二、案經高雄縣政府警察局林園分局報請臺灣高雄地方法院檢察署檢察官偵查起訴後\n    ，由本院改依簡式審判程序審理。",
    "reason": "一、本件被告所犯為死刑、無期徒刑、最輕本刑為三年以上有期徒刑以外之罪，其於\n    準備程序進行中，就被訴事實為有罪之陳述，經受命法官告知簡式審判程序之旨\n    ，並聽取當事人之意見後，本院合議庭裁定由受命法官獨任進行簡式審判程序，\n    合先敘明。\n二、前揭事實，業據被告乙○○於本院審理中自白不諱，且被告於九十三年七月二十\n    八日為警採集尿液送驗結果，呈嗎啡陽性反應，有臺灣檢驗科技股份有限公司九\n    十三年八月二十四日編號ＫＺ000000000000號濫用藥物尿液檢驗報\n    告、列管毒品人口尿液檢體採集送驗紀錄表各一份附卷可憑，堪認被告上開自白\n    與事實相符，其確有施用海洛因無疑。再被告前因施用毒品案件，經本院以九十\n    年度毒聲字第三六四二號裁定送觀察、勒戒後，認有繼續施用毒品之傾向，經本\n    院以九十年度毒聲字第三九一四號裁定令入戒治處所施以強制戒治，於戒治期間\n    表現良好，經本院以九十年度毒聲字第七六六○號裁定停止戒治，所餘戒治期間\n    付保護管束，於九十一年六月二十七日保護管束期滿視為執行完畢，由臺灣高雄\n    地方法院檢察署檢察官於九十一年八月五日，以九十一年度戒毒偵字第七二七號\n    不起訴處分確定之事實，有臺灣高等法院被告全國前案紀錄表、本院被告院內索\n    引卡紀錄表、臺灣高雄地方法院檢察署刑案資料查註紀錄表各一紙在卷可稽，被\n    告於強制戒治執行完畢釋放後五年內，再度犯施用海洛因罪，事證明確，其犯行\n    應堪認定。\n三、按海洛因係毒品危害防制條例第二條第二項第一款所稱之第一級毒品，不得非法\n    持有、施用。次按犯毒品危害防制條例第十條施用第一級、第二級毒品之罪者，\n    檢察官應先將被告送勒戒處所觀察、勒戒，經觀察、勒戒後，認有繼續施用毒品\n    傾向者，應由檢察官聲請法院裁定令入戒治處所施以強制戒治，強制戒治期滿，\n    應由檢察官為不起訴之處分，依此強制戒治執行完畢釋放後，五年內再犯第十條\n    之罪，檢察官應依一般刑事訴訟程序予以起訴論罪科刑，此觀諸毒品危害防制條\n    例第二十條第一項、第二項、第二十三條第二項前段規定自明。本件被告前經強\n    制戒治執行完畢釋放後，五年內再犯本案施用毒品犯行，即屬應依法論罪科刑之\n    行為，是核被告所為，係犯毒品危害防制條例第十條第一項之施用第一級毒品罪\n    。被告施用第一級毒品前後持有海洛因之低度行為，為施用之高度行為所吸收，\n    不另論罪。爰審酌被告歷經觀察、勒戒及強制戒治等程序，猶無法戒絕毒癮，仍\n    再度施用海洛因，顯見其意志不堅，無悔改之決心，有違政府制定毒品危害防制\n    條例之立法美意，本不宜寬貸，惟念其所為尚未害及他人，且犯後坦承犯行，態\n    度尚佳等一切情狀，量處如主文所示之刑，以資懲儆。\n據上論斷，應依刑事訴訟法第二百九十九條第一項前段、第二百七十三條之一第一項\n，毒品危害防制條例第十條第一項，判決如主文。\n本案經檢察官甲○○到庭執行職務。\n中      華      民      國    九十三    年     十二     月    二十七    日\n                                  臺灣高雄地方法院刑事庭\n                                        法      官  莊珮君\n右正本證明與原本無異。\n如不服本判決，應於判決送達後十日內，向本院提出上訴狀。\n                                        法院書記官  呂怜勳"
  },
  "search": "臺灣高雄地方法院刑事判決九十三年度訴字第三二三九號公訴人臺灣高雄地方法院檢察署檢察官被告乙○○男二.右列被告因違反毒品危害防制條例案件，經檢察官提起公訴（九十三年度毒偵字第五六一八號），嗣因被告就被訴事實為有罪之陳述，經本院合議庭裁定由受命法官獨任適用簡式審判程序審理，本院判決如左：主文乙○○施用第一級毒品，處有期徒刑柒月。事實一、乙○○前因施用毒品案件，經本院以九十年度毒聲字第三六四二號裁定送觀察、勒戒後，認有繼續施用毒品之傾向，經本院以九十年度毒聲字第三九一四號裁定令入戒治處所施以強制戒治，於戒治期間表現良好，經本院以九十年度毒聲字第七六六○號裁定停止戒治，所餘戒治期間付保護管束，於民國九十一年六月二十七日保護管束期滿視為執行完畢，由臺灣高雄地方法院檢察署檢察官於九十一年八月五日，以九十一年度戒毒偵字第七二七號不起訴處分確定。詎不知悔改，於上開強制戒治執行完畢釋放後五年內，基於施用第一級毒品之犯意，於九十三年七月二十七日中午，在高雄縣林園鄉○○村○○路上王爺廟旁，以將海洛因摻入香菸內點火吸食其霧化氣體之方式，施用第一級毒品海洛因一次。嗣因臺灣高雄地方法院檢察署檢察官依法對乙○○核發強制採驗尿液許可書，警方持該許可書，於九十三年七月二十八日上午十一時五分許，至乙○○位於高雄縣林園鄉○○村○○路一○一巷一八號之住處，通知乙○○配合至高雄縣政府警察局鳳山採尿室採受強制採尿送驗後查獲。二、案經高雄縣政府警察局林園分局報請臺灣高雄地方法院檢察署檢察官偵查起訴後，由本院改依簡式審判程序審理。理由一、本件被告所犯為死刑、無期徒刑、最輕本刑為三年以上有期徒刑以外之罪，其於準備程序進行中，就被訴事實為有罪之陳述，經受命法官告知簡式審判程序之旨，並聽取當事人之意見後，本院合議庭裁定由受命法官獨任進行簡式審判程序，合先敘明。二、前揭事實，業據被告乙○○於本院審理中自白不諱，且被告於九十三年七月二十八日為警採集尿液送驗結果，呈嗎啡陽性反應，有臺灣檢驗科技股份有限公司九十三年八月二十四日編號ＫＺ000000000000號濫用藥物尿液檢驗報告、列管毒品人口尿液檢體採集送驗紀錄表各一份附卷可憑，堪認被告上開自白與事實相符，其確有施用海洛因無疑。再被告前因施用毒品案件，經本院以九十年度毒聲字第三六四二號裁定送觀察、勒戒後，認有繼續施用毒品之傾向，經本院以九十年度毒聲字第三九一四號裁定令入戒治處所施以強制戒治，於戒治期間表現良好，經本院以九十年度毒聲字第七六六○號裁定停止戒治，所餘戒治期間付保護管束，於九十一年六月二十七日保護管束期滿視為執行完畢，由臺灣高雄地方法院檢察署檢察官於九十一年八月五日，以九十一年度戒毒偵字第七二七號不起訴處分確定之事實，有臺灣高等法院被告全國前案紀錄表、本院被告院內索引卡紀錄表、臺灣高雄地方法院檢察署刑案資料查註紀錄表各一紙在卷可稽，被告於強制戒治執行完畢釋放後五年內，再度犯施用海洛因罪，事證明確，其犯行應堪認定。三、按海洛因係毒品危害防制條例第二條第二項第一款所稱之第一級毒品，不得非法持有、施用。次按犯毒品危害防制條例第十條施用第一級、第二級毒品之罪者，檢察官應先將被告送勒戒處所觀察、勒戒，經觀察、勒戒後，認有繼續施用毒品傾向者，應由檢察官聲請法院裁定令入戒治處所施以強制戒治，強制戒治期滿，應由檢察官為不起訴之處分，依此強制戒治執行完畢釋放後，五年內再犯第十條之罪，檢察官應依一般刑事訴訟程序予以起訴論罪科刑，此觀諸毒品危害防制條例第二十條第一項、第二項、第二十三條第二項前段規定自明。本件被告前經強制戒治執行完畢釋放後，五年內再犯本案施用毒品犯行，即屬應依法論罪科刑之行為，是核被告所為，係犯毒品危害防制條例第十條第一項之施用第一級毒品罪。被告施用第一級毒品前後持有海洛因之低度行為，為施用之高度行為所吸收，不另論罪。爰審酌被告歷經觀察、勒戒及強制戒治等程序，猶無法戒絕毒癮，仍再度施用海洛因，顯見其意志不堅，無悔改之決心，有違政府制定毒品危害防制條例之立法美意，本不宜寬貸，惟念其所為尚未害及他人，且犯後坦承犯行，態度尚佳等一切情狀，量處如主文所示之刑，以資懲儆。據上論斷，應依刑事訴訟法第二百九十九條第一項前段、第二百七十三條之一第一項，毒品危害防制條例第十條第一項，判決如主文。本案經檢察官甲○○到庭執行職務。中華民國九十三年十二月二十七日臺灣高雄地方法院刑事庭法官莊珮君右正本證明與原本無異。如不服本判決，應於判決送達後十日內，向本院提出上訴狀。法院書記官呂怜勳中華民國九十三年十二月二十七日附錄：毒品危害防制條例第十條第一項施用第一級毒品者，處六月以上五年以下有期徒刑。",
  "characters": {
    "judges": [
      "莊珮君"
    ],
    "prosecutors": [

    ],
    "lawyers": [

    ],
    "clerks": [
      "法院"
    ],
    "plaintiffs": [

    ],
    "defendants": [
      "乙○○  男  二.",
      "右列被告因違反毒品危害防制條例案件，經檢察官提起公訴（九十三年度毒偵字第五",
      "六一八號），嗣因被告就被訴事實為有罪之陳述，經本院合議庭裁定由受命法官獨任",
      "適用簡式審判程序審理，本院判決如左："
    ],
    "prosecutor_office": [
      "臺灣高雄地方法院檢察署檢察官"
    ],
    "creditors": [

    ],
    "debtors": [

    ],
    "judicial_associate_officer": [

    ]
  },
  "adjudged_at": "2004-12-27",
  "created_at": "2016-02-06 06:26:48",
  "updated_at": "2016-02-06 06:26:48"
}