{
  "identify": "KSD-93-易-1762-20041227-1",
  "court": {
    "name": "臺灣高雄地方法院",
    "code": "KSD"
  },
  "division": {
    "name": "刑事",
    "code": "M"
  },
  "year": 93,
  "word": "易",
  "number": "1762",
  "jcheck": "1",
  "reason": "毒品危害防制條例",
  "content": "臺灣高雄地方法院刑事判決                        九十三年度易字第一七六二號\n    公  訴  人  臺灣高雄地方法院檢察署檢察官\n    被      告  乙○○  男  二.\n右列被告因違反毒品危害防制條例案件，經檢察官提起公訴（九十三年度毒偵字第四\n五五二號），嗣因被告就被訴事實為有罪之陳述，經本院合議庭裁定由受命法官獨任\n適用簡式審判程序審理，本院判決如左：\n    主  文\n乙○○連續施用第二級毒品，累犯，處有期徒刑陸月，如易科罰金，以參佰元折算壹\n日。扣案甲基安非他命壹包（驗後毛重零點貳公克）沒收銷燬之。\n    事  實\n一、乙○○前因施用毒品案件，經臺灣高等法院高雄分院以八十七年度上易字第一七\n    六五號裁定送觀察、勒戒後，認無繼續施用毒品之傾向，由該院於民國八十七年\n    九月十五日，以八十七年度上易字第一七六五號判決免刑確定，復因施用毒品案\n    件，經本院以八十九年度毒聲字第五九三四號裁定送觀察、勒戒後，認有繼續施\n    用毒品之傾向，經本院以八十九年度毒聲字第七一六七號裁定令入戒治處所施強\n    制戒治，於戒治期間表現良好，於九十年三月十六日停止戒治付保管束，嗣因違\n    反保護管束遵守之事項情節重大，經本院裁定撤銷停止戒治，令入戒治處所施以\n    強制戒治，於九十一年五月十一日戒治期滿執行完畢，且其施用毒品犯行，經本\n    院以九十年度鳳簡字第一六三號判處有期徒刑三月確定，於九十一年六月十七日\n    執行完畢。詎不知悔改，於上開強制戒治執行完畢釋放後五年內，基於施用第二\n    級毒品之概括犯意，於九十三年七月十五日晚間起至同年八月八日晚間十時許止\n    ，在其位於高雄縣林園鄉○○路一五巷六弄二號住處，以將甲基安非他命置於玻\n    璃吸食器上隔火加熱吸食其霧化氣體之方式，約一星期一次，連續施用第二級毒\n    品甲基安非他命多次。嗣乙○○之母顏蘇金鳳見其子吸食甲基安非他命，為助乙\n    ○○戒除毒癮，乃向警方檢舉，警方遂於九十三年八月十三日下午二時許，徵得\n    顏蘇金鳳之同意，至上址進行搜索，扣得乙○○所有供施用之甲基安非他命一包\n    （驗後毛重零點二公克），因而查獲。\n二、案經高雄市政府警察局小港分局報請臺灣高雄地方法院檢察署檢察官偵查起訴後\n    ，由本院改依簡式審判程序審理。\n    理  由\n一、本件被告所犯為死刑、無期徒刑、最輕本刑為三年以上有期徒刑以外之罪，其於\n    準備程序進行中，就被訴事實為有罪之陳述，經受命法官告知簡式審判程序之旨\n    ，並聽取當事人之意見後，本院合議庭裁定由受命法官獨任進行簡式審判程序，\n    合先敘明。\n二、右揭事實，業據被告乙○○於本院審理中自白不諱，核與證人即被告之母顏蘇金\n    鳳、證人即被告之兄顏國榮於警、偵訊之陳述相符，並有白色晶體一包扣案可證\n    ，而扣案之白色晶體一包經送驗結果，呈甲基安非他命陽性反應，驗前毛重零點\n    三公克、驗後毛重零點二公克，有高雄醫學大學附設中和紀念醫院九十三年十一\n    月三十日編號0000－000號檢驗報告一紙存卷足憑，堪認被告上開自白與\n    事實相符，其確有連續施用甲基安非他命無疑。至被告於九十三年八月十三日下\n    午三時十五分許經警採集尿液送驗結果，雖呈甲基安非他命陰性反應，有高雄市\n    凱旋醫院九十三年八月三十日濫用藥物尿液檢驗報告、尿液代碼與姓名對照表各\n    一份在卷可憑，惟按甲基安非他命經口服投與後約百分之七十於二十四小時內自\n    尿中排出，約百分之九十於九十六小時內自尿中排出，其檢出與投與方式、投與\n    量、個人體質、採尿時間與檢測儀器之精密度等諸多因素有關，因此僅憑尿液中\n    呈安非他命陽性反應，並無法確實推算吸食時間距採尿時間長短，唯依上開資料\n    推斷，最長可能不會超過四日，此有行政院衛生署藥物食品檢驗局八十一年二月\n    八日藥檢壹字第一一五六號函示足據。本案被告最後一次施用甲基安非他命之\n    時間為九十三年八月八日晚間十時許，距離被告前揭於九十三年八月十三日下午\n    三時十五分許經警方採尿送驗時間，已逾四日，是其尿液經檢驗雖呈甲基安非他\n    命陰性反應，尚難據為有利於被告之認定，附此敘明。再被告前因施用毒品案件\n    ，經臺灣高等法院高雄分院以八十七年度上易字第一七六五號裁定送觀察、勒戒\n    後，認無繼續施用毒品之傾向，由該院於八十七年九月十五日，以八十七年度上\n    易字第一七六五號判決免刑確定，復因施用毒品案件，經本院以八十九年度毒聲\n    字第五九三四號裁定送觀察、勒戒後，認有繼續施用毒品之傾向，經本院以八十\n    九年度毒聲字第七一六七號裁定令入戒治處所施強制戒治，於戒治期間表現良好\n    ，於九十年三月十六日停止戒治付保管束，嗣因違反保護管束遵守之事項情節重\n    大，經本院裁定撤銷停止戒治，令入戒治處所施以強制戒治，於九十一年五月十\n    一日戒治期滿執行完畢，且其施用毒品犯行，經本院以九十年度鳳簡字第一六三\n    號判處有期徒刑三月確定，於九十一年六月十七日執行完畢之事實，有上開刑事\n    判決書、裁定書、臺灣高等法院被告全國前案紀錄表、本院被告院內索引卡紀錄\n    表各一紙存卷供參，被告於強制戒治執行完畢釋放後五年內，再犯施用甲基安非\n    他命罪，事證明確，其犯行應堪認定。\n三、按甲基安非他命係毒品危害防制條例第二條第二項第二款所稱之第二級毒品，不\n    得非法持有、施用。次按犯毒品危害防制條例第十條施用第一級、第二級毒品之\n    罪者，檢察官應先聲請法院將被告送勒戒處所觀察、勒戒，經觀察、勒戒後，認\n    有繼續施用毒品傾向者，應由檢察官聲請法院裁定令入戒治處所施以強制戒治，\n    強制戒治期滿，應由檢察官為不起訴之處分，依此強制戒治執行完畢釋放後，五\n    年內再犯第十條之罪，檢察官應依一般刑事訴訟程序予以起訴論罪科刑，此觀諸\n    毒品危害防制條例第二十條第一項、第二項、第二十三條第二項前段規定自明。\n    本件被告前經強制戒治執行完畢放後，五年內再犯本案施用毒品犯行，即屬應依\n    法論罪科刑之行為，是核被告所為，係犯毒品危害防制條例第十條第二項之施用\n    第二級毒品罪。被告持有第二級毒品進而施用，持有之低度行為為施用之高度行\n    為所吸收，不另論罪。被告先後多次施用第二級毒品之犯行，時間緊接，手法相\n    同，觸犯構成要件相同之罪，顯係基於概括犯意為之，為連續犯，爰依刑法第五\n    十六條之規定以一罪論，並加重其刑。被告前因違反毒品危害防制條例，經本院\n    以九十年度鳳簡字第一六三號有期徒刑三月確定，於九十一年六月十七日執行完\n    畢，有卷附臺灣高等法院被告全國前案紀錄表在卷可按，其受有期徒刑之執行完\n    畢，五年以內再犯本案有期徒刑以上之罪，為累犯，應依法加重其刑，並遞加之\n    。茲審酌被告施用足以導致精神障礙、性格異常，甚至造成生命危險之毒品，戕\n    害一己之身體健康，惟念所為尚未害及他人，且犯後坦承犯行，態度良好等一切\n    情狀，量處如主文所示之刑，並諭知易科罰金之折算標準。扣案甲基安非他命一\n    包（驗後毛重零點二公克）屬毒品危害防制條例規定之第二級毒品，應依同條例\n    第十八條第一項前段規定宣告沒收銷燬之。\n據上論斷，應依刑事訴訟法第二百九十九條第一項前段、第二百七十三條之一第一項\n，毒品危害防制條例第十條第二項、第十八條第一項前段，刑法第十一條、第五十六\n條、第四十七條、第四十一條第一項前段，罰金罰鍰提高標準條例第二條，判決如主\n文。\n本案經檢察官甲○○到庭執行職務。\n中      華      民      國    九十三    年     十二     月    二十七    日\n                                  臺灣高雄地方法院刑事庭\n                                        法      官  莊珮君\n右正本證明與原本無異。\n如不服本判決，應於判決送達後十日內，向本院提出上訴狀。\n                                        法院書記官  呂怜勳\n中      華      民      國    九十三    年     十二     月    二十七    日\n附錄：\n毒品危害防制條例第十條第二項\n施用第二級毒品者，處三年以下有期徒刑。\n",
  "structure": {
    "main": "乙○○連續施用第二級毒品，累犯，處有期徒刑陸月，如易科罰金，以參佰元折算壹\n日。扣案甲基安非他命壹包（驗後毛重零點貳公克）沒收銷燬之。",
    "fact": "一、乙○○前因施用毒品案件，經臺灣高等法院高雄分院以八十七年度上易字第一七\n    六五號裁定送觀察、勒戒後，認無繼續施用毒品之傾向，由該院於民國八十七年\n    九月十五日，以八十七年度上易字第一七六五號判決免刑確定，復因施用毒品案\n    件，經本院以八十九年度毒聲字第五九三四號裁定送觀察、勒戒後，認有繼續施\n    用毒品之傾向，經本院以八十九年度毒聲字第七一六七號裁定令入戒治處所施強\n    制戒治，於戒治期間表現良好，於九十年三月十六日停止戒治付保管束，嗣因違\n    反保護管束遵守之事項情節重大，經本院裁定撤銷停止戒治，令入戒治處所施以\n    強制戒治，於九十一年五月十一日戒治期滿執行完畢，且其施用毒品犯行，經本\n    院以九十年度鳳簡字第一六三號判處有期徒刑三月確定，於九十一年六月十七日\n    執行完畢。詎不知悔改，於上開強制戒治執行完畢釋放後五年內，基於施用第二\n    級毒品之概括犯意，於九十三年七月十五日晚間起至同年八月八日晚間十時許止\n    ，在其位於高雄縣林園鄉○○路一五巷六弄二號住處，以將甲基安非他命置於玻\n    璃吸食器上隔火加熱吸食其霧化氣體之方式，約一星期一次，連續施用第二級毒\n    品甲基安非他命多次。嗣乙○○之母顏蘇金鳳見其子吸食甲基安非他命，為助乙\n    ○○戒除毒癮，乃向警方檢舉，警方遂於九十三年八月十三日下午二時許，徵得\n    顏蘇金鳳之同意，至上址進行搜索，扣得乙○○所有供施用之甲基安非他命一包\n    （驗後毛重零點二公克），因而查獲。\n二、案經高雄市政府警察局小港分局報請臺灣高雄地方法院檢察署檢察官偵查起訴後\n    ，由本院改依簡式審判程序審理。",
    "reason": "一、本件被告所犯為死刑、無期徒刑、最輕本刑為三年以上有期徒刑以外之罪，其於\n    準備程序進行中，就被訴事實為有罪之陳述，經受命法官告知簡式審判程序之旨\n    ，並聽取當事人之意見後，本院合議庭裁定由受命法官獨任進行簡式審判程序，\n    合先敘明。\n二、右揭事實，業據被告乙○○於本院審理中自白不諱，核與證人即被告之母顏蘇金\n    鳳、證人即被告之兄顏國榮於警、偵訊之陳述相符，並有白色晶體一包扣案可證\n    ，而扣案之白色晶體一包經送驗結果，呈甲基安非他命陽性反應，驗前毛重零點\n    三公克、驗後毛重零點二公克，有高雄醫學大學附設中和紀念醫院九十三年十一\n    月三十日編號0000－000號檢驗報告一紙存卷足憑，堪認被告上開自白與\n    事實相符，其確有連續施用甲基安非他命無疑。至被告於九十三年八月十三日下\n    午三時十五分許經警採集尿液送驗結果，雖呈甲基安非他命陰性反應，有高雄市\n    凱旋醫院九十三年八月三十日濫用藥物尿液檢驗報告、尿液代碼與姓名對照表各\n    一份在卷可憑，惟按甲基安非他命經口服投與後約百分之七十於二十四小時內自\n    尿中排出，約百分之九十於九十六小時內自尿中排出，其檢出與投與方式、投與\n    量、個人體質、採尿時間與檢測儀器之精密度等諸多因素有關，因此僅憑尿液中\n    呈安非他命陽性反應，並無法確實推算吸食時間距採尿時間長短，唯依上開資料\n    推斷，最長可能不會超過四日，此有行政院衛生署藥物食品檢驗局八十一年二月\n    八日藥檢壹字第一一五六號函示足據。本案被告最後一次施用甲基安非他命之\n    時間為九十三年八月八日晚間十時許，距離被告前揭於九十三年八月十三日下午\n    三時十五分許經警方採尿送驗時間，已逾四日，是其尿液經檢驗雖呈甲基安非他\n    命陰性反應，尚難據為有利於被告之認定，附此敘明。再被告前因施用毒品案件\n    ，經臺灣高等法院高雄分院以八十七年度上易字第一七六五號裁定送觀察、勒戒\n    後，認無繼續施用毒品之傾向，由該院於八十七年九月十五日，以八十七年度上\n    易字第一七六五號判決免刑確定，復因施用毒品案件，經本院以八十九年度毒聲\n    字第五九三四號裁定送觀察、勒戒後，認有繼續施用毒品之傾向，經本院以八十\n    九年度毒聲字第七一六七號裁定令入戒治處所施強制戒治，於戒治期間表現良好\n    ，於九十年三月十六日停止戒治付保管束，嗣因違反保護管束遵守之事項情節重\n    大，經本院裁定撤銷停止戒治，令入戒治處所施以強制戒治，於九十一年五月十\n    一日戒治期滿執行完畢，且其施用毒品犯行，經本院以九十年度鳳簡字第一六三\n    號判處有期徒刑三月確定，於九十一年六月十七日執行完畢之事實，有上開刑事\n    判決書、裁定書、臺灣高等法院被告全國前案紀錄表、本院被告院內索引卡紀錄\n    表各一紙存卷供參，被告於強制戒治執行完畢釋放後五年內，再犯施用甲基安非\n    他命罪，事證明確，其犯行應堪認定。\n三、按甲基安非他命係毒品危害防制條例第二條第二項第二款所稱之第二級毒品，不\n    得非法持有、施用。次按犯毒品危害防制條例第十條施用第一級、第二級毒品之\n    罪者，檢察官應先聲請法院將被告送勒戒處所觀察、勒戒，經觀察、勒戒後，認\n    有繼續施用毒品傾向者，應由檢察官聲請法院裁定令入戒治處所施以強制戒治，\n    強制戒治期滿，應由檢察官為不起訴之處分，依此強制戒治執行完畢釋放後，五\n    年內再犯第十條之罪，檢察官應依一般刑事訴訟程序予以起訴論罪科刑，此觀諸\n    毒品危害防制條例第二十條第一項、第二項、第二十三條第二項前段規定自明。\n    本件被告前經強制戒治執行完畢放後，五年內再犯本案施用毒品犯行，即屬應依\n    法論罪科刑之行為，是核被告所為，係犯毒品危害防制條例第十條第二項之施用\n    第二級毒品罪。被告持有第二級毒品進而施用，持有之低度行為為施用之高度行\n    為所吸收，不另論罪。被告先後多次施用第二級毒品之犯行，時間緊接，手法相\n    同，觸犯構成要件相同之罪，顯係基於概括犯意為之，為連續犯，爰依刑法第五\n    十六條之規定以一罪論，並加重其刑。被告前因違反毒品危害防制條例，經本院\n    以九十年度鳳簡字第一六三號有期徒刑三月確定，於九十一年六月十七日執行完\n    畢，有卷附臺灣高等法院被告全國前案紀錄表在卷可按，其受有期徒刑之執行完\n    畢，五年以內再犯本案有期徒刑以上之罪，為累犯，應依法加重其刑，並遞加之\n    。茲審酌被告施用足以導致精神障礙、性格異常，甚至造成生命危險之毒品，戕\n    害一己之身體健康，惟念所為尚未害及他人，且犯後坦承犯行，態度良好等一切\n    情狀，量處如主文所示之刑，並諭知易科罰金之折算標準。扣案甲基安非他命一\n    包（驗後毛重零點二公克）屬毒品危害防制條例規定之第二級毒品，應依同條例\n    第十八條第一項前段規定宣告沒收銷燬之。\n據上論斷，應依刑事訴訟法第二百九十九條第一項前段、第二百七十三條之一第一項\n，毒品危害防制條例第十條第二項、第十八條第一項前段，刑法第十一條、第五十六\n條、第四十七條、第四十一條第一項前段，罰金罰鍰提高標準條例第二條，判決如主\n文。\n本案經檢察官甲○○到庭執行職務。\n中      華      民      國    九十三    年     十二     月    二十七    日\n                                  臺灣高雄地方法院刑事庭\n                                        法      官  莊珮君\n右正本證明與原本無異。\n如不服本判決，應於判決送達後十日內，向本院提出上訴狀。\n                                        法院書記官  呂怜勳"
  },
  "search": "臺灣高雄地方法院刑事判決九十三年度易字第一七六二號公訴人臺灣高雄地方法院檢察署檢察官被告乙○○男二.右列被告因違反毒品危害防制條例案件，經檢察官提起公訴（九十三年度毒偵字第四五五二號），嗣因被告就被訴事實為有罪之陳述，經本院合議庭裁定由受命法官獨任適用簡式審判程序審理，本院判決如左：主文乙○○連續施用第二級毒品，累犯，處有期徒刑陸月，如易科罰金，以參佰元折算壹日。扣案甲基安非他命壹包（驗後毛重零點貳公克）沒收銷燬之。事實一、乙○○前因施用毒品案件，經臺灣高等法院高雄分院以八十七年度上易字第一七六五號裁定送觀察、勒戒後，認無繼續施用毒品之傾向，由該院於民國八十七年九月十五日，以八十七年度上易字第一七六五號判決免刑確定，復因施用毒品案件，經本院以八十九年度毒聲字第五九三四號裁定送觀察、勒戒後，認有繼續施用毒品之傾向，經本院以八十九年度毒聲字第七一六七號裁定令入戒治處所施強制戒治，於戒治期間表現良好，於九十年三月十六日停止戒治付保管束，嗣因違反保護管束遵守之事項情節重大，經本院裁定撤銷停止戒治，令入戒治處所施以強制戒治，於九十一年五月十一日戒治期滿執行完畢，且其施用毒品犯行，經本院以九十年度鳳簡字第一六三號判處有期徒刑三月確定，於九十一年六月十七日執行完畢。詎不知悔改，於上開強制戒治執行完畢釋放後五年內，基於施用第二級毒品之概括犯意，於九十三年七月十五日晚間起至同年八月八日晚間十時許止，在其位於高雄縣林園鄉○○路一五巷六弄二號住處，以將甲基安非他命置於玻璃吸食器上隔火加熱吸食其霧化氣體之方式，約一星期一次，連續施用第二級毒品甲基安非他命多次。嗣乙○○之母顏蘇金鳳見其子吸食甲基安非他命，為助乙○○戒除毒癮，乃向警方檢舉，警方遂於九十三年八月十三日下午二時許，徵得顏蘇金鳳之同意，至上址進行搜索，扣得乙○○所有供施用之甲基安非他命一包（驗後毛重零點二公克），因而查獲。二、案經高雄市政府警察局小港分局報請臺灣高雄地方法院檢察署檢察官偵查起訴後，由本院改依簡式審判程序審理。理由一、本件被告所犯為死刑、無期徒刑、最輕本刑為三年以上有期徒刑以外之罪，其於準備程序進行中，就被訴事實為有罪之陳述，經受命法官告知簡式審判程序之旨，並聽取當事人之意見後，本院合議庭裁定由受命法官獨任進行簡式審判程序，合先敘明。二、右揭事實，業據被告乙○○於本院審理中自白不諱，核與證人即被告之母顏蘇金鳳、證人即被告之兄顏國榮於警、偵訊之陳述相符，並有白色晶體一包扣案可證，而扣案之白色晶體一包經送驗結果，呈甲基安非他命陽性反應，驗前毛重零點三公克、驗後毛重零點二公克，有高雄醫學大學附設中和紀念醫院九十三年十一月三十日編號0000－000號檢驗報告一紙存卷足憑，堪認被告上開自白與事實相符，其確有連續施用甲基安非他命無疑。至被告於九十三年八月十三日下午三時十五分許經警採集尿液送驗結果，雖呈甲基安非他命陰性反應，有高雄市凱旋醫院九十三年八月三十日濫用藥物尿液檢驗報告、尿液代碼與姓名對照表各一份在卷可憑，惟按甲基安非他命經口服投與後約百分之七十於二十四小時內自尿中排出，約百分之九十於九十六小時內自尿中排出，其檢出與投與方式、投與量、個人體質、採尿時間與檢測儀器之精密度等諸多因素有關，因此僅憑尿液中呈安非他命陽性反應，並無法確實推算吸食時間距採尿時間長短，唯依上開資料推斷，最長可能不會超過四日，此有行政院衛生署藥物食品檢驗局八十一年二月八日藥檢壹字第一一五六號函示足據。本案被告最後一次施用甲基安非他命之時間為九十三年八月八日晚間十時許，距離被告前揭於九十三年八月十三日下午三時十五分許經警方採尿送驗時間，已逾四日，是其尿液經檢驗雖呈甲基安非他命陰性反應，尚難據為有利於被告之認定，附此敘明。再被告前因施用毒品案件，經臺灣高等法院高雄分院以八十七年度上易字第一七六五號裁定送觀察、勒戒後，認無繼續施用毒品之傾向，由該院於八十七年九月十五日，以八十七年度上易字第一七六五號判決免刑確定，復因施用毒品案件，經本院以八十九年度毒聲字第五九三四號裁定送觀察、勒戒後，認有繼續施用毒品之傾向，經本院以八十九年度毒聲字第七一六七號裁定令入戒治處所施強制戒治，於戒治期間表現良好，於九十年三月十六日停止戒治付保管束，嗣因違反保護管束遵守之事項情節重大，經本院裁定撤銷停止戒治，令入戒治處所施以強制戒治，於九十一年五月十一日戒治期滿執行完畢，且其施用毒品犯行，經本院以九十年度鳳簡字第一六三號判處有期徒刑三月確定，於九十一年六月十七日執行完畢之事實，有上開刑事判決書、裁定書、臺灣高等法院被告全國前案紀錄表、本院被告院內索引卡紀錄表各一紙存卷供參，被告於強制戒治執行完畢釋放後五年內，再犯施用甲基安非他命罪，事證明確，其犯行應堪認定。三、按甲基安非他命係毒品危害防制條例第二條第二項第二款所稱之第二級毒品，不得非法持有、施用。次按犯毒品危害防制條例第十條施用第一級、第二級毒品之罪者，檢察官應先聲請法院將被告送勒戒處所觀察、勒戒，經觀察、勒戒後，認有繼續施用毒品傾向者，應由檢察官聲請法院裁定令入戒治處所施以強制戒治，強制戒治期滿，應由檢察官為不起訴之處分，依此強制戒治執行完畢釋放後，五年內再犯第十條之罪，檢察官應依一般刑事訴訟程序予以起訴論罪科刑，此觀諸毒品危害防制條例第二十條第一項、第二項、第二十三條第二項前段規定自明。本件被告前經強制戒治執行完畢放後，五年內再犯本案施用毒品犯行，即屬應依法論罪科刑之行為，是核被告所為，係犯毒品危害防制條例第十條第二項之施用第二級毒品罪。被告持有第二級毒品進而施用，持有之低度行為為施用之高度行為所吸收，不另論罪。被告先後多次施用第二級毒品之犯行，時間緊接，手法相同，觸犯構成要件相同之罪，顯係基於概括犯意為之，為連續犯，爰依刑法第五十六條之規定以一罪論，並加重其刑。被告前因違反毒品危害防制條例，經本院以九十年度鳳簡字第一六三號有期徒刑三月確定，於九十一年六月十七日執行完畢，有卷附臺灣高等法院被告全國前案紀錄表在卷可按，其受有期徒刑之執行完畢，五年以內再犯本案有期徒刑以上之罪，為累犯，應依法加重其刑，並遞加之。茲審酌被告施用足以導致精神障礙、性格異常，甚至造成生命危險之毒品，戕害一己之身體健康，惟念所為尚未害及他人，且犯後坦承犯行，態度良好等一切情狀，量處如主文所示之刑，並諭知易科罰金之折算標準。扣案甲基安非他命一包（驗後毛重零點二公克）屬毒品危害防制條例規定之第二級毒品，應依同條例第十八條第一項前段規定宣告沒收銷燬之。據上論斷，應依刑事訴訟法第二百九十九條第一項前段、第二百七十三條之一第一項，毒品危害防制條例第十條第二項、第十八條第一項前段，刑法第十一條、第五十六條、第四十七條、第四十一條第一項前段，罰金罰鍰提高標準條例第二條，判決如主文。本案經檢察官甲○○到庭執行職務。中華民國九十三年十二月二十七日臺灣高雄地方法院刑事庭法官莊珮君右正本證明與原本無異。如不服本判決，應於判決送達後十日內，向本院提出上訴狀。法院書記官呂怜勳中華民國九十三年十二月二十七日附錄：毒品危害防制條例第十條第二項施用第二級毒品者，處三年以下有期徒刑。",
  "characters": {
    "judges": [
      "莊珮君"
    ],
    "prosecutors": [

    ],
    "lawyers": [

    ],
    "clerks": [
      "法院"
    ],
    "plaintiffs": [

    ],
    "defendants": [
      "乙○○  男  二.",
      "右列被告因違反毒品危害防制條例案件，經檢察官提起公訴（九十三年度毒偵字第四",
      "五五二號），嗣因被告就被訴事實為有罪之陳述，經本院合議庭裁定由受命法官獨任",
      "適用簡式審判程序審理，本院判決如左："
    ],
    "prosecutor_office": [
      "臺灣高雄地方法院檢察署檢察官"
    ],
    "creditors": [

    ],
    "debtors": [

    ],
    "judicial_associate_officer": [

    ]
  },
  "adjudged_at": "2004-12-27",
  "created_at": "2016-02-06 06:30:16",
  "updated_at": "2016-02-06 06:30:16"
}