{
  "identify": "TPD-93-簡-2217-20040915-1",
  "court": {
    "name": "臺灣臺北地方法院",
    "code": "TPD"
  },
  "division": {
    "name": "刑事",
    "code": "M"
  },
  "year": 93,
  "word": "簡",
  "number": "2217",
  "jcheck": "1",
  "reason": "竊盜",
  "content": "臺灣臺北地方法院刑事簡易判決                    九十三年度簡字第二二一七號\n    聲  請  人  臺灣臺北地方法院檢察署檢察官\n    被      告  甲○○\n右列被告因竊盜案件，經檢察官聲請以簡易判決處刑（九十三年度偵字第一三四九四\n號），本院判決如左：\n    主  文\n甲○○竊盜，處罰金伍仟元，如易服勞役，以參佰元折算壹日。緩刑貳年。\n    事實及理由\n一、本件犯罪事實、證據及應適用之法條，均引用檢察官聲請簡易判決處刑書之記載\n    （如附件）。\n二、被告甲○○未曾受有期徒刑以上刑之宣告，有台灣高等法院被告全國前案紀錄表\n    附卷可稽，其經此次起訴審判後，當能知所警惕，本院因認所宣告之刑，以暫不\n    執行為適當，爰併宣告緩刑二年，以啟自新。\n三、依刑事訴訟法第四百四十九條第一項前段、第三項、第四百五十四條第二項，刑\n    法第三百二十條第一項、第七十四條第一款、第四十二條第二項，罰金罰鍰提高\n    標準條例第一條前段、第二條，以簡易判決處刑如主文。\n如不服本判決，得於收受判決送達之日起十日內，向本院提出上訴狀，上訴於本院第\n二審合議庭。\n中      華      民      國    九十三    年      九      月    十五      日\n                                      臺灣臺北地方法院刑事第十一庭\n                                          法  官 陳容正\n右正本證明與原本無異。\n                                          書記官 陳豪達\n中      華      民      國    九十三    年      九      月    十五      日\n附錄論罪科刑法條全文：\n刑法第三百二十條第一項\n意圖為自己或第三人不法之所有，而竊取他人之動產者，為竊盜罪，處五年以下有期\n徒刑、拘役或五百元以下罰金。\n",
  "structure": {
    "main": "甲○○竊盜，處罰金伍仟元，如易服勞役，以參佰元折算壹日。緩刑貳年。",
    "fact": "一、本件犯罪事實、證據及應適用之法條，均引用檢察官聲請簡易判決處刑書之記載\n    （如附件）。\n二、被告甲○○未曾受有期徒刑以上刑之宣告，有台灣高等法院被告全國前案紀錄表\n    附卷可稽，其經此次起訴審判後，當能知所警惕，本院因認所宣告之刑，以暫不\n    執行為適當，爰併宣告緩刑二年，以啟自新。\n三、依刑事訴訟法第四百四十九條第一項前段、第三項、第四百五十四條第二項，刑\n    法第三百二十條第一項、第七十四條第一款、第四十二條第二項，罰金罰鍰提高\n    標準條例第一條前段、第二條，以簡易判決處刑如主文。\n如不服本判決，得於收受判決送達之日起十日內，向本院提出上訴狀，上訴於本院第\n二審合議庭。",
    "reason": "一、本件犯罪事實、證據及應適用之法條，均引用檢察官聲請簡易判決處刑書之記載\n    （如附件）。\n二、被告甲○○未曾受有期徒刑以上刑之宣告，有台灣高等法院被告全國前案紀錄表\n    附卷可稽，其經此次起訴審判後，當能知所警惕，本院因認所宣告之刑，以暫不\n    執行為適當，爰併宣告緩刑二年，以啟自新。\n三、依刑事訴訟法第四百四十九條第一項前段、第三項、第四百五十四條第二項，刑\n    法第三百二十條第一項、第七十四條第一款、第四十二條第二項，罰金罰鍰提高\n    標準條例第一條前段、第二條，以簡易判決處刑如主文。\n如不服本判決，得於收受判決送達之日起十日內，向本院提出上訴狀，上訴於本院第\n二審合議庭。"
  },
  "search": "臺灣臺北地方法院刑事簡易判決九十三年度簡字第二二一七號聲請人臺灣臺北地方法院檢察署檢察官被告甲○○右列被告因竊盜案件，經檢察官聲請以簡易判決處刑（九十三年度偵字第一三四九四號），本院判決如左：主文甲○○竊盜，處罰金伍仟元，如易服勞役，以參佰元折算壹日。緩刑貳年。事實及理由一、本件犯罪事實、證據及應適用之法條，均引用檢察官聲請簡易判決處刑書之記載（如附件）。二、被告甲○○未曾受有期徒刑以上刑之宣告，有台灣高等法院被告全國前案紀錄表附卷可稽，其經此次起訴審判後，當能知所警惕，本院因認所宣告之刑，以暫不執行為適當，爰併宣告緩刑二年，以啟自新。三、依刑事訴訟法第四百四十九條第一項前段、第三項、第四百五十四條第二項，刑法第三百二十條第一項、第七十四條第一款、第四十二條第二項，罰金罰鍰提高標準條例第一條前段、第二條，以簡易判決處刑如主文。如不服本判決，得於收受判決送達之日起十日內，向本院提出上訴狀，上訴於本院第二審合議庭。中華民國九十三年九月十五日臺灣臺北地方法院刑事第十一庭法官陳容正右正本證明與原本無異。書記官陳豪達中華民國九十三年九月十五日附錄論罪科刑法條全文：刑法第三百二十條第一項意圖為自己或第三人不法之所有，而竊取他人之動產者，為竊盜罪，處五年以下有期徒刑、拘役或五百元以下罰金。",
  "characters": {
    "judges": [
      "陳容正"
    ],
    "prosecutors": [

    ],
    "lawyers": [

    ],
    "clerks": [
      "陳豪達"
    ],
    "plaintiffs": [

    ],
    "defendants": [
      "甲○○",
      "右列被告因竊盜案件，經檢察官聲請以簡易判決處刑（九十三年度偵字第一三四九四",
      "號），本院判決如左："
    ],
    "prosecutor_office": [
      "臺灣臺北地方法院檢察署檢察官"
    ],
    "creditors": [

    ],
    "debtors": [

    ],
    "judicial_associate_officer": [

    ]
  },
  "adjudged_at": "2004-09-15",
  "created_at": "2016-02-06 00:18:19",
  "updated_at": "2016-02-06 00:18:19"
}