{
  "identify": "KSH-99-上訴-1687-20110420-1",
  "court": {
    "name": "臺灣高等法院",
    "code": "KSH"
  },
  "division": {
    "name": "刑事",
    "code": "M"
  },
  "year": 99,
  "word": "上訴",
  "number": "1687",
  "jcheck": "1",
  "reason": "偽造文書等",
  "content": "臺灣高等法院高雄分院刑事判決        99年度上訴字第1687號\n上  訴  人  臺灣高雄地方法院檢察署檢察官\n被      告  楊琇麟\n選任辯護人  黃錫耀律師\n            周中臣律師\n上列上訴人因被告偽造文書等案件，不服臺灣高雄地方法院99年\n度訴字第398 號中華民國99年8 月18日第一審判決（起訴案號：\n臺灣高雄地方法院檢察署96年度偵緝字第1574號），提起上訴，\n本院判決如下：\n     主  文\n原判決撤銷。\n楊琇麟犯行使偽造私文書罪，累犯，處有期徒刑陸月；減為有期\n徒刑參月，如易科罰金，以銀元參佰元即新台幣玖佰元折算壹日\n。未扣案之偽造「黃英哲」、「永奧股份有限公司」等印章（連\n同領收證上之印文）各壹枚，及領收證上之「黃英哲」署押壹枚\n，均沒收。\n     事  實\n一、楊琇麟曾於民國88年間因犯偽造文書罪，經臺灣高雄地方法\n    院以88年度易字第2881號判處有期徒刑2 月確定，於88年11\n    月10日易科罰金執行完畢；詎不知警惕，仍基於行使偽造私\n    文書之犯意，於民國90年12月28日前之不詳時、地，偽刻「\n    黃英哲」、「永奧股份有限公司」（下稱永奧公司）印章後\n    ，再偽簽「黃英哲」之署名，以偽造永奧公司（法定代理人\n    黃英哲）於90年12月28日領收日本人岩間丈男所交付之美金\n    72916 元之領收證一紙，並於91年1 月3 日（起訴書誤載為\n    92年1 月3 日）趁日本人岩間丈男前來台灣，投宿於高雄市\n    ○○路之麗尊酒店時，將上開偽造之領收證交與岩間丈男以\n    為行使，足生損害於岩間丈男及黃英哲、永奧公司。\n二、案經告訴人黃英哲訴請臺灣高雄地方法院檢察署檢察官偵查\n    起訴。\n     理  由\n壹、有罪部分：\n一、程序方面：\n  (一)按被告以外之人於審判外之言詞或書面陳述，除法律有規定\n    者外，不得作為證據，刑事訴訟法第159 條第1 項定有明文\n    。本件告訴人黃英哲、證人林文浚於警詢中之陳述，係被告\n    以外之人於審判外之言詞陳述；另卷附所謂證人岩間丈男之\n    陳述書（見偵卷(三)第103 至109 頁，實際上係由告訴人所提\n    出，未見證人岩間丈男簽名作為確認），亦係被告以外之人\n    於審判外之書面陳述，且經被告及其辯護人於原審法院審理\n    中主張其無證據能力。且告訴人、證人林文浚上開警詢中之\n    陳述，並無刑事訴訟法第159 條之2 規定「被告以外之人於\n    檢察事務官、司法警察官或司法警察調查中所為之陳述，與\n    審判中不符時，其先前之陳述具有較可信之特別情況，且為\n    證明犯罪事實存否所必要者，得為證據」之情形，復查無其\n    他依法得為證據之情事，自不得作為證據。\n  (二)按證人依法應具結而未具結者，其證言不得作為證據，刑事\n    訴訟法第158 條之3 定有明文。本件告訴人黃英哲於94年6\n    月23日、同年7 月6 日、同年10月17日、同年11月28日、同\n    年12月5 日；證人岩間丈男、林文浚於94年12月5 日在檢察\n    官偵訊中作證時，檢察官均未命渠等具結（見偵(二)卷第19、\n    20、25、26頁、偵(三)卷第31、32頁、第79至82頁、第85至89\n    頁）；而告訴人及證人林文浚於97年10月30日在檢察官偵訊\n    中作證時，檢察官雖有命渠2 人具結，然未見渠2 人簽署之\n    證人結文附卷，自無從認渠2 人該次作證已經合法具結，是\n    上開證據依刑事訴訟法第158 條之3 之規定，自不得採為證\n    詞而均無證據能力。\n二、訊據被告楊琇麟（下稱被告）固坦承上開領收證為伊製作（\n    書寫）等情，惟矢口否認有行使偽造私文書之犯行，辯稱：\n    90年12月28日伊人在日本，領收證是91年1 月2 日在麗尊酒\n    店岩間丈男來的時候，黃英哲提供印章及公司用的信紙給伊\n    ，領收證上面的字是我寫的，印章是黃英哲蓋的；岩間丈男\n    也承認是91年1 月2 日拿給他的，因為12月28日那天要匯款\n    、作帳，我們是寫商品代金，意思就是貨款；因為押匯之後\n    ，錢要支付貨款，錢匯到黃英哲永奧公司的帳戶，必須要用\n    永奧公司的收據才能報銷；伊開立系爭領收證並簽署告訴人\n    黃英哲之姓名，告訴人黃英哲均知悉、同意云云。\n三、經查，上開事實，業據告訴人黃英哲於原審審理中證述甚詳\n    （見原審訴字卷第66頁），並有領收證1 紙在卷可稽（見94\n    年度偵緝第2121號卷第90頁）；而上開領收證上之「永奧股\n    份有限公司」之印章，確非永奧公司之印鑑章等情，亦有華\n    南商業銀行苓雅分行函（內附永奧公司及黃英哲之印鑑卡，\n    附於原審訴字卷第95頁）可憑。況且不論領收證內所記載之\n    內容是否真實，但就形式真實而言，如告訴人黃英哲當時曾\n    知悉此事而同意出具該領收證，縱然不懂日文，但亦可自行\n    於上開領收證上簽名、蓋章，根本無庸連『黃英哲』之簽名\n    ，亦由被告代為書寫？顯然被告為上開領收證之製作時，告\n    訴人黃英哲根本不知此事，更遑論同意以永奧公司名義出具\n    領收證。又被告未獲告訴人黃英哲（永奧公司）之同意而擅\n    自出具領收證予日本人岩間丈男，致使日本人岩間丈男信以\n    為真，並使告訴人黃英哲（永奧公司）可能遭受債務之追索\n    ，自足生損害於告訴人黃英哲、永奧公司及日本人岩間丈男\n    。是被告上開所辯，顯有違常理，不足採信，其有前揭犯行\n    堪以認定。\n四、核被告所為，係犯刑法第216 條、第210 條之行使偽造私文\n    書罪。又被告偽刻「黃英哲」、「永奧股份有限公司」等印\n    章，及偽簽「黃英哲」之署押等行為，均屬偽造私文書（領\n    收證）之部分行為，故不另論偽造印章及署押罪；又偽造偽\n    造私文書（領收證）之低度行為，為事後行使偽造私文書（\n    領收證）之高度行為所吸收，故亦不另論偽造私文書罪。又\n    被告曾於88年間因犯偽造文書罪，經臺灣高雄地方法院以88\n    年度易字第2881號判處有期徒刑2 月確定，於88年11月10日\n    易科罰金執行完畢，有臺灣高等法院被告前案紀錄表可參，\n    其於執行完畢後5 年內故意再犯本件有期徒刑以上之罪，依\n    修正後刑法第47條第1 項，論以累犯並加重其刑。\n五、原審未予詳查，遽為被告無罪之判決，容有不當；公訴人上\n    訴意旨，指摘原判決不當，為有理由，自應由本院將原判決\n    撤銷改判。爰審酌被告冒用他人名義出具私文書，將可能造\n    成他人之損害，且至今未與被害人達成和解；及其犯罪之動\n    機、目的、手段等一切情狀，量處有期徒刑6 月（易科罰金\n    於減刑後另述）。至於未扣案之偽刻「黃英哲」、「永奧股\n    份有限公司」等印章（連同領收證上之印文）各1 枚，及偽\n    簽於上開領收證「黃英哲」之署押1 枚，均依刑法第219 條\n    規定，不問屬於犯人與否，宣告沒收之。\n六、又被告所犯上開行使偽造私文書罪，其犯罪時間在96年4 月\n    24日以前，是依中華民國九十六年罪犯減刑條例第2 條第1\n    項第2 款之規定，應就其宣告刑減其刑期二分之一即為有期\n    徒刑3 月，並諭知如易科罰金以新台幣900 元即銀元300 元\n    折算1 日（按被告行為後，刑法已於94年2 月2 日修正公布\n    ，於95年7 月1 日施行，新修正刑法第41條易科罰金之折算\n    標準修正為以新台幣1 千元、2 千元、3 千元折算1 日，較\n    修正前舊法之銀元300 元即新台幣900 元折算1 日為重，修\n    正後之法律易科罰金較重，依刑法第2 條第1 項前段從舊從\n    輕之規定，亦應適用有利於被告之修正前之刑法第41條易科\n    罰金之折算標準處罰。）\n貳、不另為無罪部分：\n一、公訴意旨略以：楊琇麟基於意圖為自己不法所有之犯意，於\n    民國90年11月間，在高雄市新興區○○○路206 號9 樓之3\n    之永奧股份有限公司（下稱永奧公司）內，向告訴人即永奧\n    公司負責人黃英哲謊稱可接洽外銷電腦墨水匣10萬個至香港\n    地區，議定價格條件為第1 張信用狀金額美金26萬元，給付\n    楊琇麟5 ％佣金即美金1 萬3000元；第2 張信用狀金額為美\n    金68萬元，給付楊琇麟5 ％佣金即美金3 萬4300元，告訴人\n    因而陷於錯誤，委由公司股東林文浚匯款第一筆佣金美金1\n    萬3000元至楊琇麟所指定之香港帳戶。嗣於90年12月28日，\n    又基於意圖為自己不法所有之犯意，在日本東京飯店內，向\n    日本廠商岩間丈男謊稱得以介紹與永奧公司從事生意，並表\n    示需支付美金20萬元匯入永奧公司帳戶，岩間丈男因而陷於\n    錯誤，遂於同日匯款美金20萬元至永奧公司之華南商業銀行\n    外幣帳戶，隨後楊琇麟即向告訴人黃英哲謊稱有幫告訴人黃\n    英哲處理買賣，且已有美金20萬元匯入其戶頭，告訴人遂陷\n    於錯誤，誤以為楊琇麟確有處理買賣事務。之後岩間丈男於\n    91年1 月3 日（起訴書誤載為92年1 月3 日）前來高雄市○\n    ○路之麗尊酒店與楊琇麟相約見面，楊琇麟乃趁告訴人黃英\n    哲尚未到場之際，將上開偽造之領收證交與岩間丈男，加以\n    行使，足生損害於岩間丈男及告訴人、永奧公司。嗣告訴人\n    黃英哲、林文浚到場後，即將上開岩間丈男所匯美金20萬元\n    以新臺幣方式交與被告，而誤以為確實可完成上開墨水匣之\n    生意。嗣於91年2 月初，楊琇麟謊稱第1 張信用狀尚在作業\n    中，並要求先給付第2 筆佣金，告訴人因收到岩間丈男所匯\n    入之美金20萬元，且已與岩間丈男在臺灣見面，因而陷於錯\n    誤，再於同年2 月9 日，由林文浚匯入第二筆佣金美金3 萬\n    4300元至香港同一帳戶，被告並開立本票2 紙，且在本票背\n    面註明信用狀開出經銀行確認即抵銷取回本票等字樣。詎楊\n    琇麟收受上開佣金後，竟未依約開具信用狀，並藉詞亦遭人\n    欺騙為由，而置之不理。嗣經日商岩間丈男持上開偽造之領\n    收證向告訴人催討貨款，告訴人始知受騙，因認被告楊琇麟\n    另涉犯刑法第339 條第1 項之詐欺取財罪嫌。\n二、按被告未經審判證明有罪確定前，推定其為無罪；犯罪事實\n    ，應依證據認定之，無證據不得認定犯罪事實。又不能證明\n    被告犯罪者，應諭知無罪之判決，刑事訴訟法第154 條、第\n    301 條第1 項分別定有明文。次按，認定犯罪事實所憑之證\n    據，雖不以直接證據為限，間接證據亦包括在內，然而無論\n    直接證據或間接證據，其為訴訟上之證明，須於通常一般人\n    均不致有所懷疑，而得確信其為真實之程度者，始得據為有\n    罪之認定，倘其證明尚未達到此一程度，而有合理之懷疑存\n    在時，即難遽採為不利被告之認定，最高法院著有76年臺上\n    字第4986號判例可資參照。又依刑事訴訟法第161 條第1 項\n    規定，檢察官就被告犯罪事實，應負舉證責任，並指出證明\n    之方法。因此，檢察官對於起訴之犯罪事實，應負提出證據\n    及說服之實質舉證責任。倘其所提出之證據，不足為被告有\n    罪之積極證明，或其指出證明之方法，無從說服法院以形成\n    被告有罪之心證，基於無罪推定之原則，自應為被告無罪判\n    決之諭知，最高法院亦著有92年臺上字第128 號判例可參。\n三、公訴人認被告涉犯上開詐欺取財罪嫌，無非係以被告之供述\n    、告訴人、證人林文浚、岩間丈男之陳述暨有系爭領收證、\n    永奧公司之華南商業銀行帳戶交易明細、被告書寫之日文文\n    件、證人岩間丈男為匯款之匯款單、被告之入出國日期證明\n    書、被告簽發之2 紙本票、告訴人提出之證人岩間丈男陳述\n    書附卷為依據。惟訊據被告固不否認有簽發前揭2 紙本票與\n    證人林文浚，並製作領收證交與證人岩間丈男收受等事實，\n    然堅決否認有何前開詐欺取財犯行，辯稱：伊未曾向告訴人\n    提及要幫忙其接洽外銷墨水匣之事，之所以會簽發金額分別\n    為美金1 萬3000元、美金3 萬4300元之本票給林文浚，是因\n    為伊與林文浚於90年9 月間，本來要共同從事1 件信用狀詐\n    騙案，而林文浚需負擔部分支出，所以陸續交付共美金1 萬\n    3000元之款項給伊，伊則簽發前開美金1 萬3000元之本票給\n    林文浚作為擔保；嗣該件信用狀詐騙案沒做成，伊與林文浚\n    、香港人譚大明又計畫從事另1 件信用狀詐騙案，依據伊等\n    人的計畫，係由林文浚出資美金5 萬5000元，伊出資美金4\n    萬5000元（另1 名為韓平之人出資美金5 萬元），而扣除上\n    開林文浚已交給伊的美金1 萬3000元及林文浚因洽商該詐騙\n    案所為之支出後，林文浚有分別以面交現金及匯款的方式，\n    將剩餘的款項交付給伊；又因為林文浚已經從另1 件信用狀\n    詐騙案（即下述岩間丈男匯款美金20萬元至永奧公司帳戶部\n    分）取回部分出資，所以伊就林文浚尚未有擔保之出資，簽\n    發另紙美金3 萬4300元之本票給林文浚作為擔保，但之後因\n    為譚大明表示伊等人出資之美金15萬元，遭他人騙走，所以\n    該件信用狀詐騙案也沒成功；又伊與告訴人、林文浚、岩間\n    丈男、王子琪等人，有合作1 件信用狀詐騙案成功，當時是\n    由香港的杜邦公司開信用狀、馬來西亞1 家電線電纜公司出\n    貨、岩間丈男在日本的公司押匯、永奧公司則負責接受貨款\n    ，而為了分配詐得款項，所以由岩間丈男於90年12月28日，\n    將美金20萬元匯到永奧公司帳戶，依據眾人當時之約定，伊\n    、岩間丈男、王子琪3 人，可分別獲得日幣300 萬元之利益\n    ，伊另外又得到2 次至日本洽商之日幣55萬2000元的旅費補\n    貼；前揭總共日幣955 萬2000元之金額，因岩間丈男要求開\n    立領收證以供其公司會計作帳使用，伊遂於91年1 月2 日，\n    利用岩間丈男前來臺灣，在高雄麗尊酒店與告訴人、林文浚\n    見面之機會，由伊書寫系爭領收證之內容，並代告訴人簽名\n    ；又依岩間丈男的要求，配合其匯出款項之時間，將該領收\n    證日期記載為90年12月28日，至於會由伊製作該領收證，是\n    因為告訴人不懂日文而伊懂日文所致；伊並未以介紹外銷墨\n    水匣生意為由，向告訴人詐騙佣金，也未向岩間丈男詐騙美\n    金20萬元等語。\n四、經查：\n  (一)被告於90、91年間，因自證人林文浚處收受款項，因而簽發\n    票面金額為美金1 萬3000元（發票日為90年12月10日，到期\n    日為91年1 月10日）、美金3 萬4300元（發票日為91年2 月\n    9 日，未記載到期日）之本票各1 紙供作擔保之事實，業據\n    被告自承不諱，並有前揭2 紙本票在卷可稽（見原審卷(三)第\n    87、88頁），自堪予以認定。但關於被告是否有詐欺取財之\n    犯行，告訴人於原審審理中固證稱：伊是永奧公司的負責人\n    ，係經由友人王子琪的介紹而認識被告，於本案發生之前，\n    已從事國際貿易約4 、5 年的時間；被告於90年11月間，有\n    到高雄介紹1 筆外銷墨水匣到香港的生意，當時主要是由林\n    文浚與被告在接洽，林文浚還因此去到香港。當時被告沒有\n    說買方是誰，但有談到會開出2 張信用狀，金額分別為美金\n    26萬元及美金68萬元，永奧公司則給付信用狀金額的5 ％給\n    被告作為佣金，並約定匯出佣金後的1 個月內，被告需分別\n    開出前揭2 張信用狀，而因為當時永奧公司帳戶內的錢不多\n    ，所以是由林文浚匯款美金1 萬3000元及美金3 萬4300元至\n    被告指定之帳戶，而被告也於收到佣金後，先後開立面額為\n    上開佣金金額的2 張本票給伊與林文浚作為收執；期間被告\n    提及其與日本人岩間丈男有生意往來，岩間丈男要匯款與其\n    ，但其在臺灣的戶頭不方便，所以有借用永奧公司的帳戶，\n    嗣也有美金20萬元匯到永奧公司華南商業銀行的帳戶；91年\n    1 月3 日，因為被告說要介紹岩間丈男給伊認識，所以伊及\n    林文浚有到麗尊酒店與被告、岩間丈男會面，伊與林文浚並\n    有去銀行把上開美金20萬元換成新臺幣，再將之全數交與被\n    告，沒有從中獲取任何利益；又因為岩間丈男來臺灣，並匯\n    入美金20萬元至永奧公司帳戶，伊認為被告所介紹的外銷墨\n    水匣生意是真的，伊與林文浚才會匯美金3 萬4300元的第2\n    筆佣金至被告指定之帳戶，但匯美金1 萬3000元的第1 筆佣\n    金之前，被告則沒有拿出任何有關外銷墨水匣生意的資料，\n    沒想到被告拿了佣金後，就經常找不到人，也未依約開出信\n    用狀，並說其在香港遭到他人詐騙，有提到一個叫譚大明的\n    人，但詳細情形伊不清楚；又因為被告沒有依約開出信用狀\n    ，所以永奧公司沒有去作訂貨、存貨的動作，除了佣金以外\n    ，本件並沒有額外的損失等語。而證人林文浚於原審審理中\n    亦證稱：伊是永奧公司的股東，並擔任總經理工作，於90、\n    91年間，告訴人因為被告幫永奧公司介紹外銷墨水匣的生意\n    ，而拜託伊匯款美金1 萬3000元、美金3 萬4300元至被告指\n    定之香港帳戶，目的是要支付佣金給被告，而當時伊是分2\n    次匯款，被告並依據佣金的金額，開立2 張本票給告訴人；\n    於91年1 月7 日，伊剛好有其他事要去香港，所以有經由被\n    告的介紹，在香港見一下前開外銷墨水匣生意的譚姓客戶，\n    但當時並沒有談到什麼，因為之前就有說好要交易了。而於\n    伊匯出上開第2 筆佣金前，被告有向永奧公司借用帳戶，不\n    久就有1 筆美金20萬元的款項匯進來，嗣伊與告訴人並有將\n    該筆款項還給被告；因為有上開美金20萬元的事情，伊與告\n    訴人認為被告經濟實力很好，不可能騙一點點的佣金，告訴\n    人遂因此要伊匯出第2 筆佣金云云（見原審卷(三)第102 至11\n    9 頁）。告訴人並提出被告所簽發之前揭2 紙本票及系爭領\n    收證（見偵卷(四)第13頁，內容以日文書寫，填載之開立日期\n    為90年12月28日，內容略為告訴人有收受商品價金美金7 萬\n    2916元，即日幣955 萬2000元）以為佐證。\n  (二)然查，就國際貿易而言，如依告訴人上揭證詞，其於被告居\n    間介紹所謂之外銷墨水匣生意之前，已從事國際貿易約4、5\n    年；然其卻在未知悉買主係何人，且被告亦未提供任何有關\n    該筆交易之資料（信用狀類）的狀況下（按告訴人及證人林\n    文浚於原審及本院審理中亦均稱：無法提出任何買賣交易之\n    資料），即僅憑被告之說詞及認為被告經濟狀況良好，即先\n    後給付多達美金1 萬3000元、美金3 萬4300元之佣金與被告\n    （依原審卷(一)第8-1 頁之永奧公司華南商業銀行帳戶交易明\n    細所示，當時美金與新臺幣之兌換比例，約為1 ：35，是交\n    付與被告之款項，換算後分別約為新臺幣45萬5000元、120\n    萬500 元），事屬荒繆，難予置信。況且，告訴人於原審審\n    理中證述：「被告介紹外銷墨水匣生意這件事，主要是由林\n    文浚與被告在接洽」云云（見原審卷(三)第62頁），要與證人\n    林文浚於原審及本院審理中分別證稱：「案發當時，伊另外\n    在證券公司有工作，所以永奧公司的經營，伊只是負責出資\n    、看一下帳，業務部分都是由告訴人負責。被告介紹外銷墨\n    水匣生意這件事，基本上是由告訴人與被告洽商，而伊只是\n    利用去香港的機會，順便見一下譚姓客戶，並沒有與之接洽\n    生意。」、「（你是不是永奧公司之總經理？）公司只有我\n    與黃英哲二人，且我還在證券公司工作，公司沒有其他員工\n    。」等語（見原審卷(三)第102 至104 頁、第110 、116 頁及\n    本院卷第119 頁），二人所述情節顯然有所矛盾，則本件是\n    否如告訴人及證人林文浚所言，被告有以介紹外銷墨水匣生\n    意為由，向永奧公司取得佣金？實有疑義。而觀之告訴人於\n    原審審理中陳稱：因被告未依約開出信用狀，故永奧公司尚\n    未就上開外銷墨水匣生意為訂貨、存貨之動作云云（見原審\n    卷(三)第74頁）；然其前於檢察官偵訊中卻表示：被告與永奧\n    公司接洽上開外銷墨水匣生意後，永奧公司有將墨水匣包裝\n    好放在倉庫內云云（見偵卷(二)第19頁），先後所述顯然有所\n    矛盾。而經原審法院就前揭矛盾之處訊問告訴人，告訴人雖\n    又改稱：永奧公司當時有訂一小部分的貨，但因為貨是由林\n    文浚去訂的，所以伊不記得是向那個公司訂的云云（見原審\n    卷(三)第74頁），惟此與證人林文浚於原審審理中證稱：本件\n    外銷墨水匣的生意，是由告訴人去訂貨，因為業務都是由告\n    訴人在負責，伊並沒有負責（後經原審提示告訴人上開證詞\n    ，其方改稱係由其或告訴人其中1 人去訂貨）云云（見原審\n    卷(三)第117 、118 頁），亦有所歧異。\n  (三)告訴人與證人林文浚雖又稱：係因日人岩間丈男有匯入前開\n    美金20萬元至永奧公司帳戶，渠2 人方相信被告所言為真，\n    因而匯款美金3 萬4300元之第2 筆佣金與被告云云；然依告\n    訴人告訴狀之記載（見偵卷(一)第3 頁）及告訴人初於偵訊中\n    之證詞（見偵卷(三)第31頁），其均謂不知道何以會有該筆美\n    金20萬元之匯款，與其日後陳稱係被告向其借用永奧公司帳\n    戶乙節（見原審卷(三)第60頁），先後所述亦有歧異。而告訴\n    人若果因日人岩間丈男匯入前揭美金20萬元之款項，以致於\n    其誤信被告經濟能力甚佳，進而匯出所謂之第2 筆佣金與被\n    告，則其對於造成其受騙之此一重要因素，理應記憶清楚，\n    何以會先後2 次均表示不知為何會有該筆美金20萬元款項匯\n    入永奧公司帳戶？實與常情未符。再者，告訴人與證人林文\n    浚雖證稱：於91年1 月3 日，有將日人岩間丈男匯入之前開\n    美金20萬元，全數提領兌換成新臺幣後，再以現金交付方式\n    交還與被告云云。然依永奧公司前揭帳戶之交易明細顯示，\n    證人岩間丈男匯入該筆美金20萬元（換算為新臺幣係698 萬\n    5800元）之款項後，該帳戶之持用人，係先於91年1 月2 日\n    ，以轉帳方式轉出新臺幣576 萬70元款項，嗣再於91年1 月\n    3 日，以轉帳方式，分別轉出新臺幣1 萬4192元、新臺幣11\n    0 萬元等2 筆款項，另以現金提領方式，提領出新臺幣2 萬\n    6000元之款項（見原審卷(一)第8-1 頁），是該筆美金20萬元\n    之款項，非但僅有極少部分係以現金方式提領而出，且其去\n    向顯係分作不同處理，否則無須分成3 筆款項而為轉帳。準\n    此，告訴人與證人林文浚此部分之證述情節，要與上開帳戶\n    交易明細所示情形有異，反係被告辯稱：上開美金20萬元之\n    款項，係從事他起信用狀詐騙案成功，為分配詐得款項，方\n    由證人岩間丈男匯至永奧公司上開帳戶乙情，較為符合前開\n    帳戶交易明細所示情形。\n  (四)另依據告訴人提出之被告所簽發前開面額美金3 萬4300元本\n    票背面所載之附註文字：「此本票係開信用狀給永奧公司的\n    『開證費押金』，當信用狀開出經銀行確認完畢後即抵銷。\n    信用狀金額：美金50萬美元以上」顯示，被告簽發該本票時\n    ，並非表明該本票係因收受介紹生意之佣金而簽發；反而敘\n    明該本票係作為「信用狀開證費押金」使用，而此與被告所\n    執前揭辯詞要無不符。再觀之該本票背面附註「信用狀金額\n    ：美金50萬美元以上」此等文字，足見被告簽發該本票時，\n    僅係承諾日後將開出金額美金50萬元以上之信用狀，並未將\n    信用狀之金額特定為美金68萬元，則告訴人於警詢、偵訊、\n    原審審理中陳述：被告說會開出2 張信用狀，其抽取信用狀\n    金額的5 ％作為佣金，而其中1 張信用狀金額為美金68萬元\n    ，永奧公司據此金額之5 ％給付佣金給被告，被告亦因而簽\n    發前開面額美金3 萬4300元之本票與永奧公司作為憑證。因\n    此，於被告簽發上開本票給永奧公司時，永奧公司已經大概\n    知道前開墨水匣生意之買賣價額云云（見偵卷(二)第4 頁、偵\n    卷(三)第31頁、原審卷(三)第59、77、78頁），要與上開本票背\n    面附註文字所示情節不符（況美金68萬元之5 ％，應係美金\n    3 萬4000元，而非該本票面額之美金3 萬4300元）。雖經原\n    審法院將上開本票背面附註文字與告訴人前揭證述內容不符\n    之處訊問告訴人，告訴人改稱：本件外銷墨水匣生意，因買\n    方的能力不確定，所以只有大概的買賣金額，詳細之買賣金\n    額並不確定，而給付給被告之佣金，日後會依據信用狀開出\n    金額，再予多退少補云云（見原審卷(三)第78頁）；惟若本件\n    被告居中介紹生意之成交價額無法確定，則永奧公司於預先\n    給付被告佣金時，亦應以最低交易金額計算需先行給付被告\n    之佣金（依上開本票背面附註文字所載，應係美金50萬元×\n    5 ％＝美金2 萬5000元），待日後被告談得超過最低交易金\n    額之價額，再依超出之金額計算應補給付之佣金，較符常理\n    。又永奧公司先行給付與被告之佣金，縱因被告要求而需給\n    付超出最低交易金額計算所得之佣金時，亦係以整數交易價\n    額計算佣金金額（如以美金60萬元、美金70萬元計算，分別\n    給付美金3 萬元、3 萬5000元）或係直接給付整數之佣金金\n    額（如直接給付美金3 萬元、3 萬5000元作為佣金），方符\n    常情，實無可能於交易價額無法確定之情形下，計算出美金\n    3 萬4300元此一金額，作為給付與被告之佣金數額。因此，\n    告訴人於原審審理中改口所為之前揭證詞，顯然悖於常情，\n    無從採信；反以被告所辯，上開本票上之美金3 萬4300元此\n    一數額，係與證人林文浚會算、找補後所得之金額，較為可\n    採。至被告所簽發前開面額美金1 萬3000元本票背面所載之\n    附註文字：「票面金額相當於港幣10萬1400元正。約定開出\n    26萬美金信用證給永奧公司後換回本票」，則與告訴人、證\n    人林文浚上開證詞或被告所執前揭辯詞均無衝突，自無從以\n    之作為有利或不利於被告之認定，附此敘明。\n  (五)綜上，依告訴人及證人林文浚於原審及本院審理中之證稱：\n    係分2 次匯款與被告云云；然告訴人及證人林文浚自始至今\n    ，均未能提出相關匯款單據或匯款資料以佐其說；且經本院\n    查詢告訴人及證人林文浚所稱永奧公司往來之二家銀行即華\n    南銀行苓雅分行、中國信託銀行（見本院卷第120 頁），亦\n    均無法確認或查有該二筆外匯之交易資料，有華南銀行苓雅\n    分行、中國信託銀行回函在卷可稽（見本院卷第125 頁、第\n    126 頁）；甚至證人林文浚於本院審理中到庭作證時，就本\n    院訊之永奧公司是否有記帳乙事，竟稱：事實上也沒有作什\n    麼生意等語（見本院卷第119 頁），足見告訴人及證人林文\n    浚所稱：因被告介紹外銷墨水匣生意，分2 次匯款與被告，\n    其目的是作為被告介紹生意之佣金云云，即無買賣交易資料\n    （訂單類），更查無所謂給付被告之二筆佣金之匯款（交付\n    ）資料，均屬空言，殊難採信。\n  (六)至於日人岩間丈男於90年12月28日，有匯款美金20萬元至永\n    奧公司華南商業銀行帳戶之事實，有日人岩間丈男之匯款資\n    料（見偵卷(三)第92、93頁）、永奧公司華南商業銀行帳號：\n    000000000000號帳戶之交易明細（見原審卷(一)第8-1 頁）在\n    卷可稽，復為被告所不否認，自堪予以認定。惟關於證人岩\n    間丈男匯款美金20萬元至永奧公司前揭帳戶之原因，依證人\n    岩間丈男於偵訊中之陳述，其全然未提及有何遭被告詐騙之\n    情（見偵卷(三)第85、86頁，其當時僅稱係與被告有生意往來\n    而匯入該筆款項），是公訴意旨認被告「基於意圖為自己不\n    法所有之犯意，在日本東京飯店內，向證人岩間丈男謊稱得\n    以介紹與永奧公司從事生意，而使證人岩間丈男陷於錯誤，\n    因而匯款美金20萬元至永奧公司帳戶」乙節，純屬個人臆測\n    。又告訴人提出之所謂證人岩間丈男之陳述書（見偵卷(三)第\n    103 至109 頁），依據該陳述書所載內容，其固謂證人岩間\n    丈男匯款美金20萬元至永奧公司上開帳戶，係因被告介紹證\n    人岩間丈男與永奧公司從事生意所致；姑且不論該日人岩間\n    丈男所稱是否屬實，但就形式而言，其間亦未敘及被告有公\n    訴意旨所稱詐騙證人岩間丈男美金20萬元之情。是公訴人就\n    此部分之起訴意旨，容有誤解。\n五、本件檢察官認被告涉嫌上揭詐欺取財犯行所憑之證據，尚未\n    達於通常一般之人均不致有所懷疑，而得確信其為真實之程\n    度，依刑事訴訟制度「倘有懷疑，即從被告之利益為解釋」\n    、「被告應被推定為無罪」之原則，即難據以為被告不利之\n    認定。此外，復查無其他積極之證據，足資認定被告確有前\n    揭被訴犯行，自屬不能證明被告此部分犯罪，依首開說明，\n    就詐欺取財部分原應為被告無罪之諭知；惟公訴人認此部分\n    與上開有罪部分有裁判上之一罪關係，爰不另為無罪之諭知\n    。\n據上論斷，應依刑事訴訟法第369 條第1 項前段、第364 條、第\n299 條第1 項前段，刑法第2 條第1 項前段、第216 條、第210\n條、第47條第1 項、第219 條，修正前刑法第41條第1 項、刑法\n施行法第1 條之1 ，修正前罰金罰鍰提高標準條例第2 條，中華\n民國九十六年罪犯減刑條例第2 條第1 項第3 款、第7 條、第9\n條，判決如主文。\n本案經檢察官高大方到庭執行職務。\n中    華    民    國  100     年    4     月    20    日\n                  刑事第四庭    審判長法  官  蕭權閔\n                                      法  官  莊松泉\n                                      法  官  吳進寶\n以上正本證明與原本無異。\n如不服本判決應於收受本判決後10日內向本院提出上訴書狀，其\n未敘述上訴理由者，並得於提起上訴後10日內向本院補提理由書\n狀（均須按他造當事人之人數附繕本）「切勿逕送上級法院」。\n中    華    民    國   100    年    4     月    20    日\n                                      書記官  唐奇燕\n附錄本判決論罪科刑法條：\n刑法第216 條\n行使第210 條至第215 條之文書者，依偽造、變造文書或登載不\n實事項或使登載不實事項之規定處斷。\n刑法第210 條\n偽造、變造私文書，足以生損害於公眾或他人者，處5 年以下有\n期徒刑。",
  "structure": {
    "main": "原判決撤銷。\n楊琇麟犯行使偽造私文書罪，累犯，處有期徒刑陸月；減為有期\n徒刑參月，如易科罰金，以銀元參佰元即新台幣玖佰元折算壹日\n。未扣案之偽造「黃英哲」、「永奧股份有限公司」等印章（連\n同領收證上之印文）各壹枚，及領收證上之「黃英哲」署押壹枚\n，均沒收。",
    "fact": "一、楊琇麟曾於民國88年間因犯偽造文書罪，經臺灣高雄地方法\n    院以88年度易字第2881號判處有期徒刑2 月確定，於88年11\n    月10日易科罰金執行完畢；詎不知警惕，仍基於行使偽造私\n    文書之犯意，於民國90年12月28日前之不詳時、地，偽刻「\n    黃英哲」、「永奧股份有限公司」（下稱永奧公司）印章後\n    ，再偽簽「黃英哲」之署名，以偽造永奧公司（法定代理人\n    黃英哲）於90年12月28日領收日本人岩間丈男所交付之美金\n    72916 元之領收證一紙，並於91年1 月3 日（起訴書誤載為\n    92年1 月3 日）趁日本人岩間丈男前來台灣，投宿於高雄市\n    ○○路之麗尊酒店時，將上開偽造之領收證交與岩間丈男以\n    為行使，足生損害於岩間丈男及黃英哲、永奧公司。\n二、案經告訴人黃英哲訴請臺灣高雄地方法院檢察署檢察官偵查\n    起訴。",
    "reason": "壹、有罪部分：\n一、程序方面：\n  (一)按被告以外之人於審判外之言詞或書面陳述，除法律有規定\n    者外，不得作為證據，刑事訴訟法第159 條第1 項定有明文\n    。本件告訴人黃英哲、證人林文浚於警詢中之陳述，係被告\n    以外之人於審判外之言詞陳述；另卷附所謂證人岩間丈男之\n    陳述書（見偵卷(三)第103 至109 頁，實際上係由告訴人所提\n    出，未見證人岩間丈男簽名作為確認），亦係被告以外之人\n    於審判外之書面陳述，且經被告及其辯護人於原審法院審理\n    中主張其無證據能力。且告訴人、證人林文浚上開警詢中之\n    陳述，並無刑事訴訟法第159 條之2 規定「被告以外之人於\n    檢察事務官、司法警察官或司法警察調查中所為之陳述，與\n    審判中不符時，其先前之陳述具有較可信之特別情況，且為\n    證明犯罪事實存否所必要者，得為證據」之情形，復查無其\n    他依法得為證據之情事，自不得作為證據。\n  (二)按證人依法應具結而未具結者，其證言不得作為證據，刑事\n    訴訟法第158 條之3 定有明文。本件告訴人黃英哲於94年6\n    月23日、同年7 月6 日、同年10月17日、同年11月28日、同\n    年12月5 日；證人岩間丈男、林文浚於94年12月5 日在檢察\n    官偵訊中作證時，檢察官均未命渠等具結（見偵(二)卷第19、\n    20、25、26頁、偵(三)卷第31、32頁、第79至82頁、第85至89\n    頁）；而告訴人及證人林文浚於97年10月30日在檢察官偵訊\n    中作證時，檢察官雖有命渠2 人具結，然未見渠2 人簽署之\n    證人結文附卷，自無從認渠2 人該次作證已經合法具結，是\n    上開證據依刑事訴訟法第158 條之3 之規定，自不得採為證\n    詞而均無證據能力。\n二、訊據被告楊琇麟（下稱被告）固坦承上開領收證為伊製作（\n    書寫）等情，惟矢口否認有行使偽造私文書之犯行，辯稱：\n    90年12月28日伊人在日本，領收證是91年1 月2 日在麗尊酒\n    店岩間丈男來的時候，黃英哲提供印章及公司用的信紙給伊\n    ，領收證上面的字是我寫的，印章是黃英哲蓋的；岩間丈男\n    也承認是91年1 月2 日拿給他的，因為12月28日那天要匯款\n    、作帳，我們是寫商品代金，意思就是貨款；因為押匯之後\n    ，錢要支付貨款，錢匯到黃英哲永奧公司的帳戶，必須要用\n    永奧公司的收據才能報銷；伊開立系爭領收證並簽署告訴人\n    黃英哲之姓名，告訴人黃英哲均知悉、同意云云。\n三、經查，上開事實，業據告訴人黃英哲於原審審理中證述甚詳\n    （見原審訴字卷第66頁），並有領收證1 紙在卷可稽（見94\n    年度偵緝第2121號卷第90頁）；而上開領收證上之「永奧股\n    份有限公司」之印章，確非永奧公司之印鑑章等情，亦有華\n    南商業銀行苓雅分行函（內附永奧公司及黃英哲之印鑑卡，\n    附於原審訴字卷第95頁）可憑。況且不論領收證內所記載之\n    內容是否真實，但就形式真實而言，如告訴人黃英哲當時曾\n    知悉此事而同意出具該領收證，縱然不懂日文，但亦可自行\n    於上開領收證上簽名、蓋章，根本無庸連『黃英哲』之簽名\n    ，亦由被告代為書寫？顯然被告為上開領收證之製作時，告\n    訴人黃英哲根本不知此事，更遑論同意以永奧公司名義出具\n    領收證。又被告未獲告訴人黃英哲（永奧公司）之同意而擅\n    自出具領收證予日本人岩間丈男，致使日本人岩間丈男信以\n    為真，並使告訴人黃英哲（永奧公司）可能遭受債務之追索\n    ，自足生損害於告訴人黃英哲、永奧公司及日本人岩間丈男\n    。是被告上開所辯，顯有違常理，不足採信，其有前揭犯行\n    堪以認定。\n四、核被告所為，係犯刑法第216 條、第210 條之行使偽造私文\n    書罪。又被告偽刻「黃英哲」、「永奧股份有限公司」等印\n    章，及偽簽「黃英哲」之署押等行為，均屬偽造私文書（領\n    收證）之部分行為，故不另論偽造印章及署押罪；又偽造偽\n    造私文書（領收證）之低度行為，為事後行使偽造私文書（\n    領收證）之高度行為所吸收，故亦不另論偽造私文書罪。又\n    被告曾於88年間因犯偽造文書罪，經臺灣高雄地方法院以88\n    年度易字第2881號判處有期徒刑2 月確定，於88年11月10日\n    易科罰金執行完畢，有臺灣高等法院被告前案紀錄表可參，\n    其於執行完畢後5 年內故意再犯本件有期徒刑以上之罪，依\n    修正後刑法第47條第1 項，論以累犯並加重其刑。\n五、原審未予詳查，遽為被告無罪之判決，容有不當；公訴人上\n    訴意旨，指摘原判決不當，為有理由，自應由本院將原判決\n    撤銷改判。爰審酌被告冒用他人名義出具私文書，將可能造\n    成他人之損害，且至今未與被害人達成和解；及其犯罪之動\n    機、目的、手段等一切情狀，量處有期徒刑6 月（易科罰金\n    於減刑後另述）。至於未扣案之偽刻「黃英哲」、「永奧股\n    份有限公司」等印章（連同領收證上之印文）各1 枚，及偽\n    簽於上開領收證「黃英哲」之署押1 枚，均依刑法第219 條\n    規定，不問屬於犯人與否，宣告沒收之。\n六、又被告所犯上開行使偽造私文書罪，其犯罪時間在96年4 月\n    24日以前，是依中華民國九十六年罪犯減刑條例第2 條第1\n    項第2 款之規定，應就其宣告刑減其刑期二分之一即為有期\n    徒刑3 月，並諭知如易科罰金以新台幣900 元即銀元300 元\n    折算1 日（按被告行為後，刑法已於94年2 月2 日修正公布\n    ，於95年7 月1 日施行，新修正刑法第41條易科罰金之折算\n    標準修正為以新台幣1 千元、2 千元、3 千元折算1 日，較\n    修正前舊法之銀元300 元即新台幣900 元折算1 日為重，修\n    正後之法律易科罰金較重，依刑法第2 條第1 項前段從舊從\n    輕之規定，亦應適用有利於被告之修正前之刑法第41條易科\n    罰金之折算標準處罰。）\n貳、不另為無罪部分：\n一、公訴意旨略以：楊琇麟基於意圖為自己不法所有之犯意，於\n    民國90年11月間，在高雄市新興區○○○路206 號9 樓之3\n    之永奧股份有限公司（下稱永奧公司）內，向告訴人即永奧\n    公司負責人黃英哲謊稱可接洽外銷電腦墨水匣10萬個至香港\n    地區，議定價格條件為第1 張信用狀金額美金26萬元，給付\n    楊琇麟5 ％佣金即美金1 萬3000元；第2 張信用狀金額為美\n    金68萬元，給付楊琇麟5 ％佣金即美金3 萬4300元，告訴人\n    因而陷於錯誤，委由公司股東林文浚匯款第一筆佣金美金1\n    萬3000元至楊琇麟所指定之香港帳戶。嗣於90年12月28日，\n    又基於意圖為自己不法所有之犯意，在日本東京飯店內，向\n    日本廠商岩間丈男謊稱得以介紹與永奧公司從事生意，並表\n    示需支付美金20萬元匯入永奧公司帳戶，岩間丈男因而陷於\n    錯誤，遂於同日匯款美金20萬元至永奧公司之華南商業銀行\n    外幣帳戶，隨後楊琇麟即向告訴人黃英哲謊稱有幫告訴人黃\n    英哲處理買賣，且已有美金20萬元匯入其戶頭，告訴人遂陷\n    於錯誤，誤以為楊琇麟確有處理買賣事務。之後岩間丈男於\n    91年1 月3 日（起訴書誤載為92年1 月3 日）前來高雄市○\n    ○路之麗尊酒店與楊琇麟相約見面，楊琇麟乃趁告訴人黃英\n    哲尚未到場之際，將上開偽造之領收證交與岩間丈男，加以\n    行使，足生損害於岩間丈男及告訴人、永奧公司。嗣告訴人\n    黃英哲、林文浚到場後，即將上開岩間丈男所匯美金20萬元\n    以新臺幣方式交與被告，而誤以為確實可完成上開墨水匣之\n    生意。嗣於91年2 月初，楊琇麟謊稱第1 張信用狀尚在作業\n    中，並要求先給付第2 筆佣金，告訴人因收到岩間丈男所匯\n    入之美金20萬元，且已與岩間丈男在臺灣見面，因而陷於錯\n    誤，再於同年2 月9 日，由林文浚匯入第二筆佣金美金3 萬\n    4300元至香港同一帳戶，被告並開立本票2 紙，且在本票背\n    面註明信用狀開出經銀行確認即抵銷取回本票等字樣。詎楊\n    琇麟收受上開佣金後，竟未依約開具信用狀，並藉詞亦遭人\n    欺騙為由，而置之不理。嗣經日商岩間丈男持上開偽造之領\n    收證向告訴人催討貨款，告訴人始知受騙，因認被告楊琇麟\n    另涉犯刑法第339 條第1 項之詐欺取財罪嫌。\n二、按被告未經審判證明有罪確定前，推定其為無罪；犯罪事實\n    ，應依證據認定之，無證據不得認定犯罪事實。又不能證明\n    被告犯罪者，應諭知無罪之判決，刑事訴訟法第154 條、第\n    301 條第1 項分別定有明文。次按，認定犯罪事實所憑之證\n    據，雖不以直接證據為限，間接證據亦包括在內，然而無論\n    直接證據或間接證據，其為訴訟上之證明，須於通常一般人\n    均不致有所懷疑，而得確信其為真實之程度者，始得據為有\n    罪之認定，倘其證明尚未達到此一程度，而有合理之懷疑存\n    在時，即難遽採為不利被告之認定，最高法院著有76年臺上\n    字第4986號判例可資參照。又依刑事訴訟法第161 條第1 項\n    規定，檢察官就被告犯罪事實，應負舉證責任，並指出證明\n    之方法。因此，檢察官對於起訴之犯罪事實，應負提出證據\n    及說服之實質舉證責任。倘其所提出之證據，不足為被告有\n    罪之積極證明，或其指出證明之方法，無從說服法院以形成\n    被告有罪之心證，基於無罪推定之原則，自應為被告無罪判\n    決之諭知，最高法院亦著有92年臺上字第128 號判例可參。\n三、公訴人認被告涉犯上開詐欺取財罪嫌，無非係以被告之供述\n    、告訴人、證人林文浚、岩間丈男之陳述暨有系爭領收證、\n    永奧公司之華南商業銀行帳戶交易明細、被告書寫之日文文\n    件、證人岩間丈男為匯款之匯款單、被告之入出國日期證明\n    書、被告簽發之2 紙本票、告訴人提出之證人岩間丈男陳述\n    書附卷為依據。惟訊據被告固不否認有簽發前揭2 紙本票與\n    證人林文浚，並製作領收證交與證人岩間丈男收受等事實，\n    然堅決否認有何前開詐欺取財犯行，辯稱：伊未曾向告訴人\n    提及要幫忙其接洽外銷墨水匣之事，之所以會簽發金額分別\n    為美金1 萬3000元、美金3 萬4300元之本票給林文浚，是因\n    為伊與林文浚於90年9 月間，本來要共同從事1 件信用狀詐\n    騙案，而林文浚需負擔部分支出，所以陸續交付共美金1 萬\n    3000元之款項給伊，伊則簽發前開美金1 萬3000元之本票給\n    林文浚作為擔保；嗣該件信用狀詐騙案沒做成，伊與林文浚\n    、香港人譚大明又計畫從事另1 件信用狀詐騙案，依據伊等\n    人的計畫，係由林文浚出資美金5 萬5000元，伊出資美金4\n    萬5000元（另1 名為韓平之人出資美金5 萬元），而扣除上\n    開林文浚已交給伊的美金1 萬3000元及林文浚因洽商該詐騙\n    案所為之支出後，林文浚有分別以面交現金及匯款的方式，\n    將剩餘的款項交付給伊；又因為林文浚已經從另1 件信用狀\n    詐騙案（即下述岩間丈男匯款美金20萬元至永奧公司帳戶部\n    分）取回部分出資，所以伊就林文浚尚未有擔保之出資，簽\n    發另紙美金3 萬4300元之本票給林文浚作為擔保，但之後因\n    為譚大明表示伊等人出資之美金15萬元，遭他人騙走，所以\n    該件信用狀詐騙案也沒成功；又伊與告訴人、林文浚、岩間\n    丈男、王子琪等人，有合作1 件信用狀詐騙案成功，當時是\n    由香港的杜邦公司開信用狀、馬來西亞1 家電線電纜公司出\n    貨、岩間丈男在日本的公司押匯、永奧公司則負責接受貨款\n    ，而為了分配詐得款項，所以由岩間丈男於90年12月28日，\n    將美金20萬元匯到永奧公司帳戶，依據眾人當時之約定，伊\n    、岩間丈男、王子琪3 人，可分別獲得日幣300 萬元之利益\n    ，伊另外又得到2 次至日本洽商之日幣55萬2000元的旅費補\n    貼；前揭總共日幣955 萬2000元之金額，因岩間丈男要求開\n    立領收證以供其公司會計作帳使用，伊遂於91年1 月2 日，\n    利用岩間丈男前來臺灣，在高雄麗尊酒店與告訴人、林文浚\n    見面之機會，由伊書寫系爭領收證之內容，並代告訴人簽名\n    ；又依岩間丈男的要求，配合其匯出款項之時間，將該領收\n    證日期記載為90年12月28日，至於會由伊製作該領收證，是\n    因為告訴人不懂日文而伊懂日文所致；伊並未以介紹外銷墨\n    水匣生意為由，向告訴人詐騙佣金，也未向岩間丈男詐騙美\n    金20萬元等語。\n四、經查：\n  (一)被告於90、91年間，因自證人林文浚處收受款項，因而簽發\n    票面金額為美金1 萬3000元（發票日為90年12月10日，到期\n    日為91年1 月10日）、美金3 萬4300元（發票日為91年2 月\n    9 日，未記載到期日）之本票各1 紙供作擔保之事實，業據\n    被告自承不諱，並有前揭2 紙本票在卷可稽（見原審卷(三)第\n    87、88頁），自堪予以認定。但關於被告是否有詐欺取財之\n    犯行，告訴人於原審審理中固證稱：伊是永奧公司的負責人\n    ，係經由友人王子琪的介紹而認識被告，於本案發生之前，\n    已從事國際貿易約4 、5 年的時間；被告於90年11月間，有\n    到高雄介紹1 筆外銷墨水匣到香港的生意，當時主要是由林\n    文浚與被告在接洽，林文浚還因此去到香港。當時被告沒有\n    說買方是誰，但有談到會開出2 張信用狀，金額分別為美金\n    26萬元及美金68萬元，永奧公司則給付信用狀金額的5 ％給\n    被告作為佣金，並約定匯出佣金後的1 個月內，被告需分別\n    開出前揭2 張信用狀，而因為當時永奧公司帳戶內的錢不多\n    ，所以是由林文浚匯款美金1 萬3000元及美金3 萬4300元至\n    被告指定之帳戶，而被告也於收到佣金後，先後開立面額為\n    上開佣金金額的2 張本票給伊與林文浚作為收執；期間被告\n    提及其與日本人岩間丈男有生意往來，岩間丈男要匯款與其\n    ，但其在臺灣的戶頭不方便，所以有借用永奧公司的帳戶，\n    嗣也有美金20萬元匯到永奧公司華南商業銀行的帳戶；91年\n    1 月3 日，因為被告說要介紹岩間丈男給伊認識，所以伊及\n    林文浚有到麗尊酒店與被告、岩間丈男會面，伊與林文浚並\n    有去銀行把上開美金20萬元換成新臺幣，再將之全數交與被\n    告，沒有從中獲取任何利益；又因為岩間丈男來臺灣，並匯\n    入美金20萬元至永奧公司帳戶，伊認為被告所介紹的外銷墨\n    水匣生意是真的，伊與林文浚才會匯美金3 萬4300元的第2\n    筆佣金至被告指定之帳戶，但匯美金1 萬3000元的第1 筆佣\n    金之前，被告則沒有拿出任何有關外銷墨水匣生意的資料，\n    沒想到被告拿了佣金後，就經常找不到人，也未依約開出信\n    用狀，並說其在香港遭到他人詐騙，有提到一個叫譚大明的\n    人，但詳細情形伊不清楚；又因為被告沒有依約開出信用狀\n    ，所以永奧公司沒有去作訂貨、存貨的動作，除了佣金以外\n    ，本件並沒有額外的損失等語。而證人林文浚於原審審理中\n    亦證稱：伊是永奧公司的股東，並擔任總經理工作，於90、\n    91年間，告訴人因為被告幫永奧公司介紹外銷墨水匣的生意\n    ，而拜託伊匯款美金1 萬3000元、美金3 萬4300元至被告指\n    定之香港帳戶，目的是要支付佣金給被告，而當時伊是分2\n    次匯款，被告並依據佣金的金額，開立2 張本票給告訴人；\n    於91年1 月7 日，伊剛好有其他事要去香港，所以有經由被\n    告的介紹，在香港見一下前開外銷墨水匣生意的譚姓客戶，\n    但當時並沒有談到什麼，因為之前就有說好要交易了。而於\n    伊匯出上開第2 筆佣金前，被告有向永奧公司借用帳戶，不\n    久就有1 筆美金20萬元的款項匯進來，嗣伊與告訴人並有將\n    該筆款項還給被告；因為有上開美金20萬元的事情，伊與告\n    訴人認為被告經濟實力很好，不可能騙一點點的佣金，告訴\n    人遂因此要伊匯出第2 筆佣金云云（見原審卷(三)第102 至11\n    9 頁）。告訴人並提出被告所簽發之前揭2 紙本票及系爭領\n    收證（見偵卷(四)第13頁，內容以日文書寫，填載之開立日期\n    為90年12月28日，內容略為告訴人有收受商品價金美金7 萬\n    2916元，即日幣955 萬2000元）以為佐證。\n  (二)然查，就國際貿易而言，如依告訴人上揭證詞，其於被告居\n    間介紹所謂之外銷墨水匣生意之前，已從事國際貿易約4、5\n    年；然其卻在未知悉買主係何人，且被告亦未提供任何有關\n    該筆交易之資料（信用狀類）的狀況下（按告訴人及證人林\n    文浚於原審及本院審理中亦均稱：無法提出任何買賣交易之\n    資料），即僅憑被告之說詞及認為被告經濟狀況良好，即先\n    後給付多達美金1 萬3000元、美金3 萬4300元之佣金與被告\n    （依原審卷(一)第8-1 頁之永奧公司華南商業銀行帳戶交易明\n    細所示，當時美金與新臺幣之兌換比例，約為1 ：35，是交\n    付與被告之款項，換算後分別約為新臺幣45萬5000元、120\n    萬500 元），事屬荒繆，難予置信。況且，告訴人於原審審\n    理中證述：「被告介紹外銷墨水匣生意這件事，主要是由林\n    文浚與被告在接洽」云云（見原審卷(三)第62頁），要與證人\n    林文浚於原審及本院審理中分別證稱：「案發當時，伊另外\n    在證券公司有工作，所以永奧公司的經營，伊只是負責出資\n    、看一下帳，業務部分都是由告訴人負責。被告介紹外銷墨\n    水匣生意這件事，基本上是由告訴人與被告洽商，而伊只是\n    利用去香港的機會，順便見一下譚姓客戶，並沒有與之接洽\n    生意。」、「（你是不是永奧公司之總經理？）公司只有我\n    與黃英哲二人，且我還在證券公司工作，公司沒有其他員工\n    。」等語（見原審卷(三)第102 至104 頁、第110 、116 頁及\n    本院卷第119 頁），二人所述情節顯然有所矛盾，則本件是\n    否如告訴人及證人林文浚所言，被告有以介紹外銷墨水匣生\n    意為由，向永奧公司取得佣金？實有疑義。而觀之告訴人於\n    原審審理中陳稱：因被告未依約開出信用狀，故永奧公司尚\n    未就上開外銷墨水匣生意為訂貨、存貨之動作云云（見原審\n    卷(三)第74頁）；然其前於檢察官偵訊中卻表示：被告與永奧\n    公司接洽上開外銷墨水匣生意後，永奧公司有將墨水匣包裝\n    好放在倉庫內云云（見偵卷(二)第19頁），先後所述顯然有所\n    矛盾。而經原審法院就前揭矛盾之處訊問告訴人，告訴人雖\n    又改稱：永奧公司當時有訂一小部分的貨，但因為貨是由林\n    文浚去訂的，所以伊不記得是向那個公司訂的云云（見原審\n    卷(三)第74頁），惟此與證人林文浚於原審審理中證稱：本件\n    外銷墨水匣的生意，是由告訴人去訂貨，因為業務都是由告\n    訴人在負責，伊並沒有負責（後經原審提示告訴人上開證詞\n    ，其方改稱係由其或告訴人其中1 人去訂貨）云云（見原審\n    卷(三)第117 、118 頁），亦有所歧異。\n  (三)告訴人與證人林文浚雖又稱：係因日人岩間丈男有匯入前開\n    美金20萬元至永奧公司帳戶，渠2 人方相信被告所言為真，\n    因而匯款美金3 萬4300元之第2 筆佣金與被告云云；然依告\n    訴人告訴狀之記載（見偵卷(一)第3 頁）及告訴人初於偵訊中\n    之證詞（見偵卷(三)第31頁），其均謂不知道何以會有該筆美\n    金20萬元之匯款，與其日後陳稱係被告向其借用永奧公司帳\n    戶乙節（見原審卷(三)第60頁），先後所述亦有歧異。而告訴\n    人若果因日人岩間丈男匯入前揭美金20萬元之款項，以致於\n    其誤信被告經濟能力甚佳，進而匯出所謂之第2 筆佣金與被\n    告，則其對於造成其受騙之此一重要因素，理應記憶清楚，\n    何以會先後2 次均表示不知為何會有該筆美金20萬元款項匯\n    入永奧公司帳戶？實與常情未符。再者，告訴人與證人林文\n    浚雖證稱：於91年1 月3 日，有將日人岩間丈男匯入之前開\n    美金20萬元，全數提領兌換成新臺幣後，再以現金交付方式\n    交還與被告云云。然依永奧公司前揭帳戶之交易明細顯示，\n    證人岩間丈男匯入該筆美金20萬元（換算為新臺幣係698 萬\n    5800元）之款項後，該帳戶之持用人，係先於91年1 月2 日\n    ，以轉帳方式轉出新臺幣576 萬70元款項，嗣再於91年1 月\n    3 日，以轉帳方式，分別轉出新臺幣1 萬4192元、新臺幣11\n    0 萬元等2 筆款項，另以現金提領方式，提領出新臺幣2 萬\n    6000元之款項（見原審卷(一)第8-1 頁），是該筆美金20萬元\n    之款項，非但僅有極少部分係以現金方式提領而出，且其去\n    向顯係分作不同處理，否則無須分成3 筆款項而為轉帳。準\n    此，告訴人與證人林文浚此部分之證述情節，要與上開帳戶\n    交易明細所示情形有異，反係被告辯稱：上開美金20萬元之\n    款項，係從事他起信用狀詐騙案成功，為分配詐得款項，方\n    由證人岩間丈男匯至永奧公司上開帳戶乙情，較為符合前開\n    帳戶交易明細所示情形。\n  (四)另依據告訴人提出之被告所簽發前開面額美金3 萬4300元本\n    票背面所載之附註文字：「此本票係開信用狀給永奧公司的\n    『開證費押金』，當信用狀開出經銀行確認完畢後即抵銷。\n    信用狀金額：美金50萬美元以上」顯示，被告簽發該本票時\n    ，並非表明該本票係因收受介紹生意之佣金而簽發；反而敘\n    明該本票係作為「信用狀開證費押金」使用，而此與被告所\n    執前揭辯詞要無不符。再觀之該本票背面附註「信用狀金額\n    ：美金50萬美元以上」此等文字，足見被告簽發該本票時，\n    僅係承諾日後將開出金額美金50萬元以上之信用狀，並未將\n    信用狀之金額特定為美金68萬元，則告訴人於警詢、偵訊、\n    原審審理中陳述：被告說會開出2 張信用狀，其抽取信用狀\n    金額的5 ％作為佣金，而其中1 張信用狀金額為美金68萬元\n    ，永奧公司據此金額之5 ％給付佣金給被告，被告亦因而簽\n    發前開面額美金3 萬4300元之本票與永奧公司作為憑證。因\n    此，於被告簽發上開本票給永奧公司時，永奧公司已經大概\n    知道前開墨水匣生意之買賣價額云云（見偵卷(二)第4 頁、偵\n    卷(三)第31頁、原審卷(三)第59、77、78頁），要與上開本票背\n    面附註文字所示情節不符（況美金68萬元之5 ％，應係美金\n    3 萬4000元，而非該本票面額之美金3 萬4300元）。雖經原\n    審法院將上開本票背面附註文字與告訴人前揭證述內容不符\n    之處訊問告訴人，告訴人改稱：本件外銷墨水匣生意，因買\n    方的能力不確定，所以只有大概的買賣金額，詳細之買賣金\n    額並不確定，而給付給被告之佣金，日後會依據信用狀開出\n    金額，再予多退少補云云（見原審卷(三)第78頁）；惟若本件\n    被告居中介紹生意之成交價額無法確定，則永奧公司於預先\n    給付被告佣金時，亦應以最低交易金額計算需先行給付被告\n    之佣金（依上開本票背面附註文字所載，應係美金50萬元×\n    5 ％＝美金2 萬5000元），待日後被告談得超過最低交易金\n    額之價額，再依超出之金額計算應補給付之佣金，較符常理\n    。又永奧公司先行給付與被告之佣金，縱因被告要求而需給\n    付超出最低交易金額計算所得之佣金時，亦係以整數交易價\n    額計算佣金金額（如以美金60萬元、美金70萬元計算，分別\n    給付美金3 萬元、3 萬5000元）或係直接給付整數之佣金金\n    額（如直接給付美金3 萬元、3 萬5000元作為佣金），方符\n    常情，實無可能於交易價額無法確定之情形下，計算出美金\n    3 萬4300元此一金額，作為給付與被告之佣金數額。因此，\n    告訴人於原審審理中改口所為之前揭證詞，顯然悖於常情，\n    無從採信；反以被告所辯，上開本票上之美金3 萬4300元此\n    一數額，係與證人林文浚會算、找補後所得之金額，較為可\n    採。至被告所簽發前開面額美金1 萬3000元本票背面所載之\n    附註文字：「票面金額相當於港幣10萬1400元正。約定開出\n    26萬美金信用證給永奧公司後換回本票」，則與告訴人、證\n    人林文浚上開證詞或被告所執前揭辯詞均無衝突，自無從以\n    之作為有利或不利於被告之認定，附此敘明。\n  (五)綜上，依告訴人及證人林文浚於原審及本院審理中之證稱：\n    係分2 次匯款與被告云云；然告訴人及證人林文浚自始至今\n    ，均未能提出相關匯款單據或匯款資料以佐其說；且經本院\n    查詢告訴人及證人林文浚所稱永奧公司往來之二家銀行即華\n    南銀行苓雅分行、中國信託銀行（見本院卷第120 頁），亦\n    均無法確認或查有該二筆外匯之交易資料，有華南銀行苓雅\n    分行、中國信託銀行回函在卷可稽（見本院卷第125 頁、第\n    126 頁）；甚至證人林文浚於本院審理中到庭作證時，就本\n    院訊之永奧公司是否有記帳乙事，竟稱：事實上也沒有作什\n    麼生意等語（見本院卷第119 頁），足見告訴人及證人林文\n    浚所稱：因被告介紹外銷墨水匣生意，分2 次匯款與被告，\n    其目的是作為被告介紹生意之佣金云云，即無買賣交易資料\n    （訂單類），更查無所謂給付被告之二筆佣金之匯款（交付\n    ）資料，均屬空言，殊難採信。\n  (六)至於日人岩間丈男於90年12月28日，有匯款美金20萬元至永\n    奧公司華南商業銀行帳戶之事實，有日人岩間丈男之匯款資\n    料（見偵卷(三)第92、93頁）、永奧公司華南商業銀行帳號：\n    000000000000號帳戶之交易明細（見原審卷(一)第8-1 頁）在\n    卷可稽，復為被告所不否認，自堪予以認定。惟關於證人岩\n    間丈男匯款美金20萬元至永奧公司前揭帳戶之原因，依證人\n    岩間丈男於偵訊中之陳述，其全然未提及有何遭被告詐騙之\n    情（見偵卷(三)第85、86頁，其當時僅稱係與被告有生意往來\n    而匯入該筆款項），是公訴意旨認被告「基於意圖為自己不\n    法所有之犯意，在日本東京飯店內，向證人岩間丈男謊稱得\n    以介紹與永奧公司從事生意，而使證人岩間丈男陷於錯誤，\n    因而匯款美金20萬元至永奧公司帳戶」乙節，純屬個人臆測\n    。又告訴人提出之所謂證人岩間丈男之陳述書（見偵卷(三)第\n    103 至109 頁），依據該陳述書所載內容，其固謂證人岩間\n    丈男匯款美金20萬元至永奧公司上開帳戶，係因被告介紹證\n    人岩間丈男與永奧公司從事生意所致；姑且不論該日人岩間\n    丈男所稱是否屬實，但就形式而言，其間亦未敘及被告有公\n    訴意旨所稱詐騙證人岩間丈男美金20萬元之情。是公訴人就\n    此部分之起訴意旨，容有誤解。\n五、本件檢察官認被告涉嫌上揭詐欺取財犯行所憑之證據，尚未\n    達於通常一般之人均不致有所懷疑，而得確信其為真實之程\n    度，依刑事訴訟制度「倘有懷疑，即從被告之利益為解釋」\n    、「被告應被推定為無罪」之原則，即難據以為被告不利之\n    認定。此外，復查無其他積極之證據，足資認定被告確有前\n    揭被訴犯行，自屬不能證明被告此部分犯罪，依首開說明，\n    就詐欺取財部分原應為被告無罪之諭知；惟公訴人認此部分\n    與上開有罪部分有裁判上之一罪關係，爰不另為無罪之諭知\n    。\n據上論斷，應依刑事訴訟法第369 條第1 項前段、第364 條、第\n299 條第1 項前段，刑法第2 條第1 項前段、第216 條、第210\n條、第47條第1 項、第219 條，修正前刑法第41條第1 項、刑法\n施行法第1 條之1 ，修正前罰金罰鍰提高標準條例第2 條，中華\n民國九十六年罪犯減刑條例第2 條第1 項第3 款、第7 條、第9\n條，判決如主文。\n本案經檢察官高大方到庭執行職務。\n中    華    民    國  100     年    4     月    20    日\n                  刑事第四庭    審判長法  官  蕭權閔\n                                      法  官  莊松泉\n                                      法  官  吳進寶\n以上正本證明與原本無異。\n如不服本判決應於收受本判決後10日內向本院提出上訴書狀，其\n未敘述上訴理由者，並得於提起上訴後10日內向本院補提理由書\n狀（均須按他造當事人之人數附繕本）「切勿逕送上級法院」。"
  },
  "search": "臺灣高等法院高雄分院刑事判決99年度上訴字第1687號上訴人臺灣高雄地方法院檢察署檢察官被告楊琇麟選任辯護人黃錫耀律師周中臣律師上列上訴人因被告偽造文書等案件，不服臺灣高雄地方法院99年度訴字第398號中華民國99年8月18日第一審判決（起訴案號：臺灣高雄地方法院檢察署96年度偵緝字第1574號），提起上訴，本院判決如下：主文原判決撤銷。楊琇麟犯行使偽造私文書罪，累犯，處有期徒刑陸月；減為有期徒刑參月，如易科罰金，以銀元參佰元即新台幣玖佰元折算壹日。未扣案之偽造「黃英哲」、「永奧股份有限公司」等印章（連同領收證上之印文）各壹枚，及領收證上之「黃英哲」署押壹枚，均沒收。事實一、楊琇麟曾於民國88年間因犯偽造文書罪，經臺灣高雄地方法院以88年度易字第2881號判處有期徒刑2月確定，於88年11月10日易科罰金執行完畢；詎不知警惕，仍基於行使偽造私文書之犯意，於民國90年12月28日前之不詳時、地，偽刻「黃英哲」、「永奧股份有限公司」（下稱永奧公司）印章後，再偽簽「黃英哲」之署名，以偽造永奧公司（法定代理人黃英哲）於90年12月28日領收日本人岩間丈男所交付之美金72916元之領收證一紙，並於91年1月3日（起訴書誤載為92年1月3日）趁日本人岩間丈男前來台灣，投宿於高雄市○○路之麗尊酒店時，將上開偽造之領收證交與岩間丈男以為行使，足生損害於岩間丈男及黃英哲、永奧公司。二、案經告訴人黃英哲訴請臺灣高雄地方法院檢察署檢察官偵查起訴。理由壹、有罪部分：一、程序方面：(一)按被告以外之人於審判外之言詞或書面陳述，除法律有規定者外，不得作為證據，刑事訴訟法第159條第1項定有明文。本件告訴人黃英哲、證人林文浚於警詢中之陳述，係被告以外之人於審判外之言詞陳述；另卷附所謂證人岩間丈男之陳述書（見偵卷(三)第103至109頁，實際上係由告訴人所提出，未見證人岩間丈男簽名作為確認），亦係被告以外之人於審判外之書面陳述，且經被告及其辯護人於原審法院審理中主張其無證據能力。且告訴人、證人林文浚上開警詢中之陳述，並無刑事訴訟法第159條之2規定「被告以外之人於檢察事務官、司法警察官或司法警察調查中所為之陳述，與審判中不符時，其先前之陳述具有較可信之特別情況，且為證明犯罪事實存否所必要者，得為證據」之情形，復查無其他依法得為證據之情事，自不得作為證據。(二)按證人依法應具結而未具結者，其證言不得作為證據，刑事訴訟法第158條之3定有明文。本件告訴人黃英哲於94年6月23日、同年7月6日、同年10月17日、同年11月28日、同年12月5日；證人岩間丈男、林文浚於94年12月5日在檢察官偵訊中作證時，檢察官均未命渠等具結（見偵(二)卷第19、20、25、26頁、偵(三)卷第31、32頁、第79至82頁、第85至89頁）；而告訴人及證人林文浚於97年10月30日在檢察官偵訊中作證時，檢察官雖有命渠2人具結，然未見渠2人簽署之證人結文附卷，自無從認渠2人該次作證已經合法具結，是上開證據依刑事訴訟法第158條之3之規定，自不得採為證詞而均無證據能力。二、訊據被告楊琇麟（下稱被告）固坦承上開領收證為伊製作（書寫）等情，惟矢口否認有行使偽造私文書之犯行，辯稱：90年12月28日伊人在日本，領收證是91年1月2日在麗尊酒店岩間丈男來的時候，黃英哲提供印章及公司用的信紙給伊，領收證上面的字是我寫的，印章是黃英哲蓋的；岩間丈男也承認是91年1月2日拿給他的，因為12月28日那天要匯款、作帳，我們是寫商品代金，意思就是貨款；因為押匯之後，錢要支付貨款，錢匯到黃英哲永奧公司的帳戶，必須要用永奧公司的收據才能報銷；伊開立系爭領收證並簽署告訴人黃英哲之姓名，告訴人黃英哲均知悉、同意云云。三、經查，上開事實，業據告訴人黃英哲於原審審理中證述甚詳（見原審訴字卷第66頁），並有領收證1紙在卷可稽（見94年度偵緝第2121號卷第90頁）；而上開領收證上之「永奧股份有限公司」之印章，確非永奧公司之印鑑章等情，亦有華南商業銀行苓雅分行函（內附永奧公司及黃英哲之印鑑卡，附於原審訴字卷第95頁）可憑。況且不論領收證內所記載之內容是否真實，但就形式真實而言，如告訴人黃英哲當時曾知悉此事而同意出具該領收證，縱然不懂日文，但亦可自行於上開領收證上簽名、蓋章，根本無庸連『黃英哲』之簽名，亦由被告代為書寫？顯然被告為上開領收證之製作時，告訴人黃英哲根本不知此事，更遑論同意以永奧公司名義出具領收證。又被告未獲告訴人黃英哲（永奧公司）之同意而擅自出具領收證予日本人岩間丈男，致使日本人岩間丈男信以為真，並使告訴人黃英哲（永奧公司）可能遭受債務之追索，自足生損害於告訴人黃英哲、永奧公司及日本人岩間丈男。是被告上開所辯，顯有違常理，不足採信，其有前揭犯行堪以認定。四、核被告所為，係犯刑法第216條、第210條之行使偽造私文書罪。又被告偽刻「黃英哲」、「永奧股份有限公司」等印章，及偽簽「黃英哲」之署押等行為，均屬偽造私文書（領收證）之部分行為，故不另論偽造印章及署押罪；又偽造偽造私文書（領收證）之低度行為，為事後行使偽造私文書（領收證）之高度行為所吸收，故亦不另論偽造私文書罪。又被告曾於88年間因犯偽造文書罪，經臺灣高雄地方法院以88年度易字第2881號判處有期徒刑2月確定，於88年11月10日易科罰金執行完畢，有臺灣高等法院被告前案紀錄表可參，其於執行完畢後5年內故意再犯本件有期徒刑以上之罪，依修正後刑法第47條第1項，論以累犯並加重其刑。五、原審未予詳查，遽為被告無罪之判決，容有不當；公訴人上訴意旨，指摘原判決不當，為有理由，自應由本院將原判決撤銷改判。爰審酌被告冒用他人名義出具私文書，將可能造成他人之損害，且至今未與被害人達成和解；及其犯罪之動機、目的、手段等一切情狀，量處有期徒刑6月（易科罰金於減刑後另述）。至於未扣案之偽刻「黃英哲」、「永奧股份有限公司」等印章（連同領收證上之印文）各1枚，及偽簽於上開領收證「黃英哲」之署押1枚，均依刑法第219條規定，不問屬於犯人與否，宣告沒收之。六、又被告所犯上開行使偽造私文書罪，其犯罪時間在96年4月24日以前，是依中華民國九十六年罪犯減刑條例第2條第1項第2款之規定，應就其宣告刑減其刑期二分之一即為有期徒刑3月，並諭知如易科罰金以新台幣900元即銀元300元折算1日（按被告行為後，刑法已於94年2月2日修正公布，於95年7月1日施行，新修正刑法第41條易科罰金之折算標準修正為以新台幣1千元、2千元、3千元折算1日，較修正前舊法之銀元300元即新台幣900元折算1日為重，修正後之法律易科罰金較重，依刑法第2條第1項前段從舊從輕之規定，亦應適用有利於被告之修正前之刑法第41條易科罰金之折算標準處罰。）貳、不另為無罪部分：一、公訴意旨略以：楊琇麟基於意圖為自己不法所有之犯意，於民國90年11月間，在高雄市新興區○○○路206號9樓之3之永奧股份有限公司（下稱永奧公司）內，向告訴人即永奧公司負責人黃英哲謊稱可接洽外銷電腦墨水匣10萬個至香港地區，議定價格條件為第1張信用狀金額美金26萬元，給付楊琇麟5％佣金即美金1萬3000元；第2張信用狀金額為美金68萬元，給付楊琇麟5％佣金即美金3萬4300元，告訴人因而陷於錯誤，委由公司股東林文浚匯款第一筆佣金美金1萬3000元至楊琇麟所指定之香港帳戶。嗣於90年12月28日，又基於意圖為自己不法所有之犯意，在日本東京飯店內，向日本廠商岩間丈男謊稱得以介紹與永奧公司從事生意，並表示需支付美金20萬元匯入永奧公司帳戶，岩間丈男因而陷於錯誤，遂於同日匯款美金20萬元至永奧公司之華南商業銀行外幣帳戶，隨後楊琇麟即向告訴人黃英哲謊稱有幫告訴人黃英哲處理買賣，且已有美金20萬元匯入其戶頭，告訴人遂陷於錯誤，誤以為楊琇麟確有處理買賣事務。之後岩間丈男於91年1月3日（起訴書誤載為92年1月3日）前來高雄市○○路之麗尊酒店與楊琇麟相約見面，楊琇麟乃趁告訴人黃英哲尚未到場之際，將上開偽造之領收證交與岩間丈男，加以行使，足生損害於岩間丈男及告訴人、永奧公司。嗣告訴人黃英哲、林文浚到場後，即將上開岩間丈男所匯美金20萬元以新臺幣方式交與被告，而誤以為確實可完成上開墨水匣之生意。嗣於91年2月初，楊琇麟謊稱第1張信用狀尚在作業中，並要求先給付第2筆佣金，告訴人因收到岩間丈男所匯入之美金20萬元，且已與岩間丈男在臺灣見面，因而陷於錯誤，再於同年2月9日，由林文浚匯入第二筆佣金美金3萬4300元至香港同一帳戶，被告並開立本票2紙，且在本票背面註明信用狀開出經銀行確認即抵銷取回本票等字樣。詎楊琇麟收受上開佣金後，竟未依約開具信用狀，並藉詞亦遭人欺騙為由，而置之不理。嗣經日商岩間丈男持上開偽造之領收證向告訴人催討貨款，告訴人始知受騙，因認被告楊琇麟另涉犯刑法第339條第1項之詐欺取財罪嫌。二、按被告未經審判證明有罪確定前，推定其為無罪；犯罪事實，應依證據認定之，無證據不得認定犯罪事實。又不能證明被告犯罪者，應諭知無罪之判決，刑事訴訟法第154條、第301條第1項分別定有明文。次按，認定犯罪事實所憑之證據，雖不以直接證據為限，間接證據亦包括在內，然而無論直接證據或間接證據，其為訴訟上之證明，須於通常一般人均不致有所懷疑，而得確信其為真實之程度者，始得據為有罪之認定，倘其證明尚未達到此一程度，而有合理之懷疑存在時，即難遽採為不利被告之認定，最高法院著有76年臺上字第4986號判例可資參照。又依刑事訴訟法第161條第1項規定，檢察官就被告犯罪事實，應負舉證責任，並指出證明之方法。因此，檢察官對於起訴之犯罪事實，應負提出證據及說服之實質舉證責任。倘其所提出之證據，不足為被告有罪之積極證明，或其指出證明之方法，無從說服法院以形成被告有罪之心證，基於無罪推定之原則，自應為被告無罪判決之諭知，最高法院亦著有92年臺上字第128號判例可參。三、公訴人認被告涉犯上開詐欺取財罪嫌，無非係以被告之供述、告訴人、證人林文浚、岩間丈男之陳述暨有系爭領收證、永奧公司之華南商業銀行帳戶交易明細、被告書寫之日文文件、證人岩間丈男為匯款之匯款單、被告之入出國日期證明書、被告簽發之2紙本票、告訴人提出之證人岩間丈男陳述書附卷為依據。惟訊據被告固不否認有簽發前揭2紙本票與證人林文浚，並製作領收證交與證人岩間丈男收受等事實，然堅決否認有何前開詐欺取財犯行，辯稱：伊未曾向告訴人提及要幫忙其接洽外銷墨水匣之事，之所以會簽發金額分別為美金1萬3000元、美金3萬4300元之本票給林文浚，是因為伊與林文浚於90年9月間，本來要共同從事1件信用狀詐騙案，而林文浚需負擔部分支出，所以陸續交付共美金1萬3000元之款項給伊，伊則簽發前開美金1萬3000元之本票給林文浚作為擔保；嗣該件信用狀詐騙案沒做成，伊與林文浚、香港人譚大明又計畫從事另1件信用狀詐騙案，依據伊等人的計畫，係由林文浚出資美金5萬5000元，伊出資美金4萬5000元（另1名為韓平之人出資美金5萬元），而扣除上開林文浚已交給伊的美金1萬3000元及林文浚因洽商該詐騙案所為之支出後，林文浚有分別以面交現金及匯款的方式，將剩餘的款項交付給伊；又因為林文浚已經從另1件信用狀詐騙案（即下述岩間丈男匯款美金20萬元至永奧公司帳戶部分）取回部分出資，所以伊就林文浚尚未有擔保之出資，簽發另紙美金3萬4300元之本票給林文浚作為擔保，但之後因為譚大明表示伊等人出資之美金15萬元，遭他人騙走，所以該件信用狀詐騙案也沒成功；又伊與告訴人、林文浚、岩間丈男、王子琪等人，有合作1件信用狀詐騙案成功，當時是由香港的杜邦公司開信用狀、馬來西亞1家電線電纜公司出貨、岩間丈男在日本的公司押匯、永奧公司則負責接受貨款，而為了分配詐得款項，所以由岩間丈男於90年12月28日，將美金20萬元匯到永奧公司帳戶，依據眾人當時之約定，伊、岩間丈男、王子琪3人，可分別獲得日幣300萬元之利益，伊另外又得到2次至日本洽商之日幣55萬2000元的旅費補貼；前揭總共日幣955萬2000元之金額，因岩間丈男要求開立領收證以供其公司會計作帳使用，伊遂於91年1月2日，利用岩間丈男前來臺灣，在高雄麗尊酒店與告訴人、林文浚見面之機會，由伊書寫系爭領收證之內容，並代告訴人簽名；又依岩間丈男的要求，配合其匯出款項之時間，將該領收證日期記載為90年12月28日，至於會由伊製作該領收證，是因為告訴人不懂日文而伊懂日文所致；伊並未以介紹外銷墨水匣生意為由，向告訴人詐騙佣金，也未向岩間丈男詐騙美金20萬元等語。四、經查：(一)被告於90、91年間，因自證人林文浚處收受款項，因而簽發票面金額為美金1萬3000元（發票日為90年12月10日，到期日為91年1月10日）、美金3萬4300元（發票日為91年2月9日，未記載到期日）之本票各1紙供作擔保之事實，業據被告自承不諱，並有前揭2紙本票在卷可稽（見原審卷(三)第87、88頁），自堪予以認定。但關於被告是否有詐欺取財之犯行，告訴人於原審審理中固證稱：伊是永奧公司的負責人，係經由友人王子琪的介紹而認識被告，於本案發生之前，已從事國際貿易約4、5年的時間；被告於90年11月間，有到高雄介紹1筆外銷墨水匣到香港的生意，當時主要是由林文浚與被告在接洽，林文浚還因此去到香港。當時被告沒有說買方是誰，但有談到會開出2張信用狀，金額分別為美金26萬元及美金68萬元，永奧公司則給付信用狀金額的5％給被告作為佣金，並約定匯出佣金後的1個月內，被告需分別開出前揭2張信用狀，而因為當時永奧公司帳戶內的錢不多，所以是由林文浚匯款美金1萬3000元及美金3萬4300元至被告指定之帳戶，而被告也於收到佣金後，先後開立面額為上開佣金金額的2張本票給伊與林文浚作為收執；期間被告提及其與日本人岩間丈男有生意往來，岩間丈男要匯款與其，但其在臺灣的戶頭不方便，所以有借用永奧公司的帳戶，嗣也有美金20萬元匯到永奧公司華南商業銀行的帳戶；91年1月3日，因為被告說要介紹岩間丈男給伊認識，所以伊及林文浚有到麗尊酒店與被告、岩間丈男會面，伊與林文浚並有去銀行把上開美金20萬元換成新臺幣，再將之全數交與被告，沒有從中獲取任何利益；又因為岩間丈男來臺灣，並匯入美金20萬元至永奧公司帳戶，伊認為被告所介紹的外銷墨水匣生意是真的，伊與林文浚才會匯美金3萬4300元的第2筆佣金至被告指定之帳戶，但匯美金1萬3000元的第1筆佣金之前，被告則沒有拿出任何有關外銷墨水匣生意的資料，沒想到被告拿了佣金後，就經常找不到人，也未依約開出信用狀，並說其在香港遭到他人詐騙，有提到一個叫譚大明的人，但詳細情形伊不清楚；又因為被告沒有依約開出信用狀，所以永奧公司沒有去作訂貨、存貨的動作，除了佣金以外，本件並沒有額外的損失等語。而證人林文浚於原審審理中亦證稱：伊是永奧公司的股東，並擔任總經理工作，於90、91年間，告訴人因為被告幫永奧公司介紹外銷墨水匣的生意，而拜託伊匯款美金1萬3000元、美金3萬4300元至被告指定之香港帳戶，目的是要支付佣金給被告，而當時伊是分2次匯款，被告並依據佣金的金額，開立2張本票給告訴人；於91年1月7日，伊剛好有其他事要去香港，所以有經由被告的介紹，在香港見一下前開外銷墨水匣生意的譚姓客戶，但當時並沒有談到什麼，因為之前就有說好要交易了。而於伊匯出上開第2筆佣金前，被告有向永奧公司借用帳戶，不久就有1筆美金20萬元的款項匯進來，嗣伊與告訴人並有將該筆款項還給被告；因為有上開美金20萬元的事情，伊與告訴人認為被告經濟實力很好，不可能騙一點點的佣金，告訴人遂因此要伊匯出第2筆佣金云云（見原審卷(三)第102至119頁）。告訴人並提出被告所簽發之前揭2紙本票及系爭領收證（見偵卷(四)第13頁，內容以日文書寫，填載之開立日期為90年12月28日，內容略為告訴人有收受商品價金美金7萬2916元，即日幣955萬2000元）以為佐證。(二)然查，就國際貿易而言，如依告訴人上揭證詞，其於被告居間介紹所謂之外銷墨水匣生意之前，已從事國際貿易約4、5年；然其卻在未知悉買主係何人，且被告亦未提供任何有關該筆交易之資料（信用狀類）的狀況下（按告訴人及證人林文浚於原審及本院審理中亦均稱：無法提出任何買賣交易之資料），即僅憑被告之說詞及認為被告經濟狀況良好，即先後給付多達美金1萬3000元、美金3萬4300元之佣金與被告（依原審卷(一)第8-1頁之永奧公司華南商業銀行帳戶交易明細所示，當時美金與新臺幣之兌換比例，約為1：35，是交付與被告之款項，換算後分別約為新臺幣45萬5000元、120萬500元），事屬荒繆，難予置信。況且，告訴人於原審審理中證述：「被告介紹外銷墨水匣生意這件事，主要是由林文浚與被告在接洽」云云（見原審卷(三)第62頁），要與證人林文浚於原審及本院審理中分別證稱：「案發當時，伊另外在證券公司有工作，所以永奧公司的經營，伊只是負責出資、看一下帳，業務部分都是由告訴人負責。被告介紹外銷墨水匣生意這件事，基本上是由告訴人與被告洽商，而伊只是利用去香港的機會，順便見一下譚姓客戶，並沒有與之接洽生意。」、「（你是不是永奧公司之總經理？）公司只有我與黃英哲二人，且我還在證券公司工作，公司沒有其他員工。」等語（見原審卷(三)第102至104頁、第110、116頁及本院卷第119頁），二人所述情節顯然有所矛盾，則本件是否如告訴人及證人林文浚所言，被告有以介紹外銷墨水匣生意為由，向永奧公司取得佣金？實有疑義。而觀之告訴人於原審審理中陳稱：因被告未依約開出信用狀，故永奧公司尚未就上開外銷墨水匣生意為訂貨、存貨之動作云云（見原審卷(三)第74頁）；然其前於檢察官偵訊中卻表示：被告與永奧公司接洽上開外銷墨水匣生意後，永奧公司有將墨水匣包裝好放在倉庫內云云（見偵卷(二)第19頁），先後所述顯然有所矛盾。而經原審法院就前揭矛盾之處訊問告訴人，告訴人雖又改稱：永奧公司當時有訂一小部分的貨，但因為貨是由林文浚去訂的，所以伊不記得是向那個公司訂的云云（見原審卷(三)第74頁），惟此與證人林文浚於原審審理中證稱：本件外銷墨水匣的生意，是由告訴人去訂貨，因為業務都是由告訴人在負責，伊並沒有負責（後經原審提示告訴人上開證詞，其方改稱係由其或告訴人其中1人去訂貨）云云（見原審卷(三)第117、118頁），亦有所歧異。(三)告訴人與證人林文浚雖又稱：係因日人岩間丈男有匯入前開美金20萬元至永奧公司帳戶，渠2人方相信被告所言為真，因而匯款美金3萬4300元之第2筆佣金與被告云云；然依告訴人告訴狀之記載（見偵卷(一)第3頁）及告訴人初於偵訊中之證詞（見偵卷(三)第31頁），其均謂不知道何以會有該筆美金20萬元之匯款，與其日後陳稱係被告向其借用永奧公司帳戶乙節（見原審卷(三)第60頁），先後所述亦有歧異。而告訴人若果因日人岩間丈男匯入前揭美金20萬元之款項，以致於其誤信被告經濟能力甚佳，進而匯出所謂之第2筆佣金與被告，則其對於造成其受騙之此一重要因素，理應記憶清楚，何以會先後2次均表示不知為何會有該筆美金20萬元款項匯入永奧公司帳戶？實與常情未符。再者，告訴人與證人林文浚雖證稱：於91年1月3日，有將日人岩間丈男匯入之前開美金20萬元，全數提領兌換成新臺幣後，再以現金交付方式交還與被告云云。然依永奧公司前揭帳戶之交易明細顯示，證人岩間丈男匯入該筆美金20萬元（換算為新臺幣係698萬5800元）之款項後，該帳戶之持用人，係先於91年1月2日，以轉帳方式轉出新臺幣576萬70元款項，嗣再於91年1月3日，以轉帳方式，分別轉出新臺幣1萬4192元、新臺幣110萬元等2筆款項，另以現金提領方式，提領出新臺幣2萬6000元之款項（見原審卷(一)第8-1頁），是該筆美金20萬元之款項，非但僅有極少部分係以現金方式提領而出，且其去向顯係分作不同處理，否則無須分成3筆款項而為轉帳。準此，告訴人與證人林文浚此部分之證述情節，要與上開帳戶交易明細所示情形有異，反係被告辯稱：上開美金20萬元之款項，係從事他起信用狀詐騙案成功，為分配詐得款項，方由證人岩間丈男匯至永奧公司上開帳戶乙情，較為符合前開帳戶交易明細所示情形。(四)另依據告訴人提出之被告所簽發前開面額美金3萬4300元本票背面所載之附註文字：「此本票係開信用狀給永奧公司的『開證費押金』，當信用狀開出經銀行確認完畢後即抵銷。信用狀金額：美金50萬美元以上」顯示，被告簽發該本票時，並非表明該本票係因收受介紹生意之佣金而簽發；反而敘明該本票係作為「信用狀開證費押金」使用，而此與被告所執前揭辯詞要無不符。再觀之該本票背面附註「信用狀金額：美金50萬美元以上」此等文字，足見被告簽發該本票時，僅係承諾日後將開出金額美金50萬元以上之信用狀，並未將信用狀之金額特定為美金68萬元，則告訴人於警詢、偵訊、原審審理中陳述：被告說會開出2張信用狀，其抽取信用狀金額的5％作為佣金，而其中1張信用狀金額為美金68萬元，永奧公司據此金額之5％給付佣金給被告，被告亦因而簽發前開面額美金3萬4300元之本票與永奧公司作為憑證。因此，於被告簽發上開本票給永奧公司時，永奧公司已經大概知道前開墨水匣生意之買賣價額云云（見偵卷(二)第4頁、偵卷(三)第31頁、原審卷(三)第59、77、78頁），要與上開本票背面附註文字所示情節不符（況美金68萬元之5％，應係美金3萬4000元，而非該本票面額之美金3萬4300元）。雖經原審法院將上開本票背面附註文字與告訴人前揭證述內容不符之處訊問告訴人，告訴人改稱：本件外銷墨水匣生意，因買方的能力不確定，所以只有大概的買賣金額，詳細之買賣金額並不確定，而給付給被告之佣金，日後會依據信用狀開出金額，再予多退少補云云（見原審卷(三)第78頁）；惟若本件被告居中介紹生意之成交價額無法確定，則永奧公司於預先給付被告佣金時，亦應以最低交易金額計算需先行給付被告之佣金（依上開本票背面附註文字所載，應係美金50萬元×5％＝美金2萬5000元），待日後被告談得超過最低交易金額之價額，再依超出之金額計算應補給付之佣金，較符常理。又永奧公司先行給付與被告之佣金，縱因被告要求而需給付超出最低交易金額計算所得之佣金時，亦係以整數交易價額計算佣金金額（如以美金60萬元、美金70萬元計算，分別給付美金3萬元、3萬5000元）或係直接給付整數之佣金金額（如直接給付美金3萬元、3萬5000元作為佣金），方符常情，實無可能於交易價額無法確定之情形下，計算出美金3萬4300元此一金額，作為給付與被告之佣金數額。因此，告訴人於原審審理中改口所為之前揭證詞，顯然悖於常情，無從採信；反以被告所辯，上開本票上之美金3萬4300元此一數額，係與證人林文浚會算、找補後所得之金額，較為可採。至被告所簽發前開面額美金1萬3000元本票背面所載之附註文字：「票面金額相當於港幣10萬1400元正。約定開出26萬美金信用證給永奧公司後換回本票」，則與告訴人、證人林文浚上開證詞或被告所執前揭辯詞均無衝突，自無從以之作為有利或不利於被告之認定，附此敘明。(五)綜上，依告訴人及證人林文浚於原審及本院審理中之證稱：係分2次匯款與被告云云；然告訴人及證人林文浚自始至今，均未能提出相關匯款單據或匯款資料以佐其說；且經本院查詢告訴人及證人林文浚所稱永奧公司往來之二家銀行即華南銀行苓雅分行、中國信託銀行（見本院卷第120頁），亦均無法確認或查有該二筆外匯之交易資料，有華南銀行苓雅分行、中國信託銀行回函在卷可稽（見本院卷第125頁、第126頁）；甚至證人林文浚於本院審理中到庭作證時，就本院訊之永奧公司是否有記帳乙事，竟稱：事實上也沒有作什麼生意等語（見本院卷第119頁），足見告訴人及證人林文浚所稱：因被告介紹外銷墨水匣生意，分2次匯款與被告，其目的是作為被告介紹生意之佣金云云，即無買賣交易資料（訂單類），更查無所謂給付被告之二筆佣金之匯款（交付）資料，均屬空言，殊難採信。(六)至於日人岩間丈男於90年12月28日，有匯款美金20萬元至永奧公司華南商業銀行帳戶之事實，有日人岩間丈男之匯款資料（見偵卷(三)第92、93頁）、永奧公司華南商業銀行帳號：000000000000號帳戶之交易明細（見原審卷(一)第8-1頁）在卷可稽，復為被告所不否認，自堪予以認定。惟關於證人岩間丈男匯款美金20萬元至永奧公司前揭帳戶之原因，依證人岩間丈男於偵訊中之陳述，其全然未提及有何遭被告詐騙之情（見偵卷(三)第85、86頁，其當時僅稱係與被告有生意往來而匯入該筆款項），是公訴意旨認被告「基於意圖為自己不法所有之犯意，在日本東京飯店內，向證人岩間丈男謊稱得以介紹與永奧公司從事生意，而使證人岩間丈男陷於錯誤，因而匯款美金20萬元至永奧公司帳戶」乙節，純屬個人臆測。又告訴人提出之所謂證人岩間丈男之陳述書（見偵卷(三)第103至109頁），依據該陳述書所載內容，其固謂證人岩間丈男匯款美金20萬元至永奧公司上開帳戶，係因被告介紹證人岩間丈男與永奧公司從事生意所致；姑且不論該日人岩間丈男所稱是否屬實，但就形式而言，其間亦未敘及被告有公訴意旨所稱詐騙證人岩間丈男美金20萬元之情。是公訴人就此部分之起訴意旨，容有誤解。五、本件檢察官認被告涉嫌上揭詐欺取財犯行所憑之證據，尚未達於通常一般之人均不致有所懷疑，而得確信其為真實之程度，依刑事訴訟制度「倘有懷疑，即從被告之利益為解釋」、「被告應被推定為無罪」之原則，即難據以為被告不利之認定。此外，復查無其他積極之證據，足資認定被告確有前揭被訴犯行，自屬不能證明被告此部分犯罪，依首開說明，就詐欺取財部分原應為被告無罪之諭知；惟公訴人認此部分與上開有罪部分有裁判上之一罪關係，爰不另為無罪之諭知。據上論斷，應依刑事訴訟法第369條第1項前段、第364條、第299條第1項前段，刑法第2條第1項前段、第216條、第210條、第47條第1項、第219條，修正前刑法第41條第1項、刑法施行法第1條之1，修正前罰金罰鍰提高標準條例第2條，中華民國九十六年罪犯減刑條例第2條第1項第3款、第7條、第9條，判決如主文。本案經檢察官高大方到庭執行職務。中華民國100年4月20日刑事第四庭審判長法官蕭權閔法官莊松泉法官吳進寶以上正本證明與原本無異。如不服本判決應於收受本判決後10日內向本院提出上訴書狀，其未敘述上訴理由者，並得於提起上訴後10日內向本院補提理由書狀（均須按他造當事人之人數附繕本）「切勿逕送上級法院」。中華民國100年4月20日書記官唐奇燕附錄本判決論罪科刑法條：刑法第216條行使第210條至第215條之文書者，依偽造、變造文書或登載不實事項或使登載不實事項之規定處斷。刑法第210條偽造、變造私文書，足以生損害於公眾或他人者，處5年以下有期徒刑。",
  "characters": {
    "judges": [
      "蕭權閔",
      "莊松泉",
      "吳進寶"
    ],
    "prosecutors": [
      "高大方"
    ],
    "lawyers": [
      "黃錫耀",
      "周中臣"
    ],
    "clerks": [
      "唐奇燕"
    ],
    "plaintiffs": [

    ],
    "defendants": [
      "楊琇麟"
    ],
    "prosecutor_office": [

    ],
    "creditors": [

    ],
    "debtors": [

    ],
    "judicial_associate_officer": [

    ]
  },
  "adjudged_at": "2011-04-20",
  "created_at": "2016-02-12 11:17:12",
  "updated_at": "2016-02-12 11:17:12"
}