{
  "identify": "PCD-100-簡-2733-20110419-1",
  "court": {
    "name": "臺灣新北地方法院",
    "code": "PCD"
  },
  "division": {
    "name": "刑事",
    "code": "M"
  },
  "year": 100,
  "word": "簡",
  "number": "2733",
  "jcheck": "1",
  "reason": "竊盜等",
  "content": "臺灣板橋地方法院刑事簡易判決         100年度簡字第2733號\n聲  請  人  臺灣板橋地方法院檢察署檢察官\n被      告  吳俊義\n上列被告因竊盜等案件，經檢察官聲請以簡易判決處刑（100 年\n度偵字第7793號），本院判決如下：\n    主  文\n吳俊義無故侵入他人建築物，處有期徒刑貳月，如易科罰金，以\n新臺幣壹仟元折算壹日；又踰越牆垣竊盜，未遂，處有期徒刑\n月，如易科罰金，以新臺幣壹仟元折算壹日。應執行有期徒刑肆\n月，如易科罰金，以新臺幣壹仟元折算壹日。\n    事實及理由\n一、本件犯罪事實及證據，除證據並所犯法條欄第2 行「目擊證\n    人蔡紹康」更正為「證人即中興保全公司人員蔡紹康」外，\n    其餘均引用如附件檢察官聲請簡易判決處刑書之記載。\n二、核被告吳俊義所為，係犯刑法第306 條第1 項之無故侵入他\n    人建築物罪、同法第320 條第2 項、第1 項第2 款之踰越牆\n    垣竊盜未遂罪。其所犯上開2 罪間，犯意各別，行為互殊，\n    應予分論併罰。又被告上揭竊盜犯行，雖已著手行竊，惟尚\n    未成功竊得財物前，即因觸動保全設備而為警查獲，顯係已\n    著手於竊盜犯行之實行而不遂，為未遂犯，爰依刑法第25條\n    第2 項規定減輕其刑。爰審酌被告正值青壯，卻不思循以正\n    途獲取所需，恣意侵入他人所有之建築物內竊取財物，行為\n    所生危害非淺，兼衡其犯罪之動機、目的、手段及犯罪後坦\n    承犯行之態度等一切情狀，分別量處如主文所示之刑，並定\n    其應執行之刑，及均諭知易科罰金之折算標準，以資懲儆。\n三、依刑事訴訟法第449 條第1 項前段、第3 項、第454 條第2\n    項，刑法第306 條第1 項、第321 條第2 項、第1 項第2 款\n    、第25條第2 項、第51條第5 款、第41條第1 項前段，刑法\n    施行法第1 條之1 第1 項、第2 項前段，逕以簡易判決處刑\n    如主文。\n四、如不服本判決，得自收受送達之日起10日內向本院提出上訴\n    狀，上訴於本院第二審合議庭（須附繕本）。\n中    華    民    國   100    年    4     月    19    日\n                  刑事第二十二庭  法  官  陳苑文\n上列正本證明與原本無異。\n                                  書記官  張玫玲\n中    華    民    國   100    年    4     月    20    日\n附錄本案論罪科刑法條全文：\n中華民國刑法第306條\n無故侵入他人住宅、建築物或附連圍繞之土地或船艦者，處 1\n年以下有期徒刑、拘役或 3 百元以下罰金。\n無故隱匿其內，或受退去之要求而仍留滯者，亦同。\n中華民國刑法第321條\n犯竊盜罪而有下列情形之一者，處 6 月以上、5 年以下有期徒\n刑，得併科新臺幣 10 萬元以下罰金：\n一、侵入住宅或有人居住之建築物、船艦或隱匿其內而犯之者。\n二、毀越門扇、牆垣或其他安全設備而犯之者。\n三、攜帶兇器而犯之者。\n四、結夥三人以上而犯之者。\n五、乘火災、水災或其他災害之際而犯之者。\n六、在車站、埠頭、航空站或其他供水、陸、空公眾運輸之舟、\n    車、航空機內而犯之者。\n前項之未遂犯罰之。",
  "structure": {
    "main": "吳俊義無故侵入他人建築物，處有期徒刑貳月，如易科罰金，以\n新臺幣壹仟元折算壹日；又踰越牆垣竊盜，未遂，處有期徒刑\n月，如易科罰金，以新臺幣壹仟元折算壹日。應執行有期徒刑肆\n月，如易科罰金，以新臺幣壹仟元折算壹日。",
    "fact": "一、本件犯罪事實及證據，除證據並所犯法條欄第2 行「目擊證\n    人蔡紹康」更正為「證人即中興保全公司人員蔡紹康」外，\n    其餘均引用如附件檢察官聲請簡易判決處刑書之記載。\n二、核被告吳俊義所為，係犯刑法第306 條第1 項之無故侵入他\n    人建築物罪、同法第320 條第2 項、第1 項第2 款之踰越牆\n    垣竊盜未遂罪。其所犯上開2 罪間，犯意各別，行為互殊，\n    應予分論併罰。又被告上揭竊盜犯行，雖已著手行竊，惟尚\n    未成功竊得財物前，即因觸動保全設備而為警查獲，顯係已\n    著手於竊盜犯行之實行而不遂，為未遂犯，爰依刑法第25條\n    第2 項規定減輕其刑。爰審酌被告正值青壯，卻不思循以正\n    途獲取所需，恣意侵入他人所有之建築物內竊取財物，行為\n    所生危害非淺，兼衡其犯罪之動機、目的、手段及犯罪後坦\n    承犯行之態度等一切情狀，分別量處如主文所示之刑，並定\n    其應執行之刑，及均諭知易科罰金之折算標準，以資懲儆。\n三、依刑事訴訟法第449 條第1 項前段、第3 項、第454 條第2\n    項，刑法第306 條第1 項、第321 條第2 項、第1 項第2 款\n    、第25條第2 項、第51條第5 款、第41條第1 項前段，刑法\n    施行法第1 條之1 第1 項、第2 項前段，逕以簡易判決處刑\n    如主文。\n四、如不服本判決，得自收受送達之日起10日內向本院提出上訴\n    狀，上訴於本院第二審合議庭（須附繕本）。",
    "reason": "一、本件犯罪事實及證據，除證據並所犯法條欄第2 行「目擊證\n    人蔡紹康」更正為「證人即中興保全公司人員蔡紹康」外，\n    其餘均引用如附件檢察官聲請簡易判決處刑書之記載。\n二、核被告吳俊義所為，係犯刑法第306 條第1 項之無故侵入他\n    人建築物罪、同法第320 條第2 項、第1 項第2 款之踰越牆\n    垣竊盜未遂罪。其所犯上開2 罪間，犯意各別，行為互殊，\n    應予分論併罰。又被告上揭竊盜犯行，雖已著手行竊，惟尚\n    未成功竊得財物前，即因觸動保全設備而為警查獲，顯係已\n    著手於竊盜犯行之實行而不遂，為未遂犯，爰依刑法第25條\n    第2 項規定減輕其刑。爰審酌被告正值青壯，卻不思循以正\n    途獲取所需，恣意侵入他人所有之建築物內竊取財物，行為\n    所生危害非淺，兼衡其犯罪之動機、目的、手段及犯罪後坦\n    承犯行之態度等一切情狀，分別量處如主文所示之刑，並定\n    其應執行之刑，及均諭知易科罰金之折算標準，以資懲儆。\n三、依刑事訴訟法第449 條第1 項前段、第3 項、第454 條第2\n    項，刑法第306 條第1 項、第321 條第2 項、第1 項第2 款\n    、第25條第2 項、第51條第5 款、第41條第1 項前段，刑法\n    施行法第1 條之1 第1 項、第2 項前段，逕以簡易判決處刑\n    如主文。\n四、如不服本判決，得自收受送達之日起10日內向本院提出上訴\n    狀，上訴於本院第二審合議庭（須附繕本）。"
  },
  "search": "臺灣板橋地方法院刑事簡易判決100年度簡字第2733號聲請人臺灣板橋地方法院檢察署檢察官被告吳俊義上列被告因竊盜等案件，經檢察官聲請以簡易判決處刑（100年度偵字第7793號），本院判決如下：主文吳俊義無故侵入他人建築物，處有期徒刑貳月，如易科罰金，以新臺幣壹仟元折算壹日；又踰越牆垣竊盜，未遂，處有期徒刑月，如易科罰金，以新臺幣壹仟元折算壹日。應執行有期徒刑肆月，如易科罰金，以新臺幣壹仟元折算壹日。事實及理由一、本件犯罪事實及證據，除證據並所犯法條欄第2行「目擊證人蔡紹康」更正為「證人即中興保全公司人員蔡紹康」外，其餘均引用如附件檢察官聲請簡易判決處刑書之記載。二、核被告吳俊義所為，係犯刑法第306條第1項之無故侵入他人建築物罪、同法第320條第2項、第1項第2款之踰越牆垣竊盜未遂罪。其所犯上開2罪間，犯意各別，行為互殊，應予分論併罰。又被告上揭竊盜犯行，雖已著手行竊，惟尚未成功竊得財物前，即因觸動保全設備而為警查獲，顯係已著手於竊盜犯行之實行而不遂，為未遂犯，爰依刑法第25條第2項規定減輕其刑。爰審酌被告正值青壯，卻不思循以正途獲取所需，恣意侵入他人所有之建築物內竊取財物，行為所生危害非淺，兼衡其犯罪之動機、目的、手段及犯罪後坦承犯行之態度等一切情狀，分別量處如主文所示之刑，並定其應執行之刑，及均諭知易科罰金之折算標準，以資懲儆。三、依刑事訴訟法第449條第1項前段、第3項、第454條第2項，刑法第306條第1項、第321條第2項、第1項第2款、第25條第2項、第51條第5款、第41條第1項前段，刑法施行法第1條之1第1項、第2項前段，逕以簡易判決處刑如主文。四、如不服本判決，得自收受送達之日起10日內向本院提出上訴狀，上訴於本院第二審合議庭（須附繕本）。中華民國100年4月19日刑事第二十二庭法官陳苑文上列正本證明與原本無異。書記官張玫玲中華民國100年4月20日附錄本案論罪科刑法條全文：中華民國刑法第306條無故侵入他人住宅、建築物或附連圍繞之土地或船艦者，處1年以下有期徒刑、拘役或3百元以下罰金。無故隱匿其內，或受退去之要求而仍留滯者，亦同。中華民國刑法第321條犯竊盜罪而有下列情形之一者，處6月以上、5年以下有期徒刑，得併科新臺幣10萬元以下罰金：一、侵入住宅或有人居住之建築物、船艦或隱匿其內而犯之者。二、毀越門扇、牆垣或其他安全設備而犯之者。三、攜帶兇器而犯之者。四、結夥三人以上而犯之者。五、乘火災、水災或其他災害之際而犯之者。六、在車站、埠頭、航空站或其他供水、陸、空公眾運輸之舟、車、航空機內而犯之者。前項之未遂犯罰之。",
  "characters": {
    "judges": [
      "陳苑文"
    ],
    "prosecutors": [

    ],
    "lawyers": [

    ],
    "clerks": [
      "張玫玲"
    ],
    "plaintiffs": [

    ],
    "defendants": [
      "吳俊義"
    ],
    "prosecutor_office": [
      "臺灣板橋地方法院檢察署檢察官"
    ],
    "creditors": [

    ],
    "debtors": [

    ],
    "judicial_associate_officer": [

    ]
  },
  "adjudged_at": "2011-04-19",
  "created_at": "2016-02-12 11:18:30",
  "updated_at": "2016-02-12 11:18:30"
}