{
  "identify": "TND-100-交簡-776-20110420-1",
  "court": {
    "name": "臺灣臺南地方法院",
    "code": "TND"
  },
  "division": {
    "name": "刑事",
    "code": "M"
  },
  "year": 100,
  "word": "交簡",
  "number": "776",
  "jcheck": "1",
  "reason": "公共危險",
  "content": "臺灣臺南地方法院刑事簡易判決        100年度交簡字第776號\n聲  請  人  臺灣臺南地方法院檢察署檢察官\n被      告  翁宗熙\n上列被告因公共危險案件，經檢察官聲請以簡易判決處刑（100\n年度偵字第3529號），本院判決如下：\n    主  文\n翁宗熙服用酒類，不能安全駕駛動力交通工具而駕駛，處有期徒\n刑月，如易科罰金，以新臺幣壹仟元折算壹日。\n    事實及理由\n一、本件犯罪事實及證據，均引用檢察官聲請簡易判決處刑書（\n    如附件）之記載。\n二、被告雖辯稱：飲酒後有自信能夠安全駕駛車輛，不會影響其\n    他來往車輛及行人安全云云；然按刑法第185條之3所稱服用\n    酒類或其他相類之物，不能安全駕駛動力交通工具之公共危\n    險罪，係屬抽象危險犯之規定，此種抽象危險係伴隨飲酒過\n    量之行為而當然成立。換言之，只需客觀上有此種行為出現\n    ，危險即視為存在，其是否果真肇事，均不影響公共危險罪\n    責之成立，且參考德國、美國之認定標準，對於酒精濃度呼\n    氣已達每公升0.55毫克或血液濃度達0.11％以上，肇事率為\n    一般正常人之10倍，認為已達「不能安全駕駛」之標準，此\n    有法務部民國88年5月18日法88檢字第001669號函可資參照\n    。況駕駛人飲酒後，會降低對光線之適應能力，削弱其對於\n    路況及車前狀況辨識之正確性，亦使神經反應遲鈍，致使駕\n    駛人駕車時無法適切操控車輛，且駕駛人對此常不自知，而\n    自認仍能安全駕駛車輛。經查被告經警查獲時其酒精濃度呼\n    氣已達每公升0.6毫克，再者係因駕車蛇行、車身搖擺不定\n    之駕駛操控力欠佳始為警攔檢，且對員警指揮反應遲鈍及問\n    訊過程中被告有呈現多語之情形，其心智確已受飲酒之影響\n    而無法正常反應，此有刑法第185條之3案件測試觀察紀錄表\n    乙紙附卷可參，益徵被告當時已達不能安全駕駛之程度，被\n    告上開所辯，並不足採。本件事證明確，被告犯行堪以認定\n    。\n三、核被告所為，係犯刑法第185條之3之服用酒類不能安全駕駛\n    動力交通工具而駕駛罪。又被告於97年間即有聲請簡易判決\n    處刑書所載之酒後駕車之公共危險前科，經法院判處罰金新\n    台幣6萬元，並以易服社會勞動執行完畢，有臺灣高等法院\n    被告前案紀錄表1份在卷可按。爰審酌被告有前述酒後駕車\n    之公共危險前科，雖非累犯，惟其應已明知酒後不能駕車及\n    酒醉駕車之危險性，竟毫不思警醒，猶漠視自己安危，更枉\n    顧法律禁止規範與公眾道路通行之安全，再度於酒後駕駛車\n    輛，對公眾交通往來顯已造成潛在之高度危險，殊為不該，\n    兼衡其智識程度、家庭經濟狀況及犯罪後之態度等一切情狀\n    ，量處如主文所示之刑，並諭知易科罰金之折算標準，以資\n    懲儆。\n四、依刑事訴訟法第449條第1項前段、第3項、第454條第2項，\n    刑法第185條之3、第41條第1項前段，刑法施行法第1條之1\n    第1項，逕以簡易判決處如主文所示之刑。\n五、如不服本件判決，得自收受送達後10日內，向本院提出上訴\n    狀（附繕本），上訴於本院管轄之第二審地方法院合議庭。\n中    華    民    國   100    年    4     月    20    日\n                  刑事第四庭    法  官  鄧希賢\n以上正本證明與原本無異。\n如不服本判決應於收受送達後10日內向本院提出上訴書狀（應附\n繕本）。\n                                書記官  黃秋萍\n中    華    民    國   100    年    4     月    20    日\n附錄本案論罪科刑法條全文：\n中華民國刑法第一百八十五條之三\n服用毒品、麻醉藥品、酒類或其他相類之物，不能安全駕駛動力\n交通工具而駕駛者，處一年以下有期徒刑、拘役或科或併科十五\n萬元以下罰金。",
  "structure": {
    "main": "翁宗熙服用酒類，不能安全駕駛動力交通工具而駕駛，處有期徒\n刑月，如易科罰金，以新臺幣壹仟元折算壹日。",
    "fact": "一、本件犯罪事實及證據，均引用檢察官聲請簡易判決處刑書（\n    如附件）之記載。\n二、被告雖辯稱：飲酒後有自信能夠安全駕駛車輛，不會影響其\n    他來往車輛及行人安全云云；然按刑法第185條之3所稱服用\n    酒類或其他相類之物，不能安全駕駛動力交通工具之公共危\n    險罪，係屬抽象危險犯之規定，此種抽象危險係伴隨飲酒過\n    量之行為而當然成立。換言之，只需客觀上有此種行為出現\n    ，危險即視為存在，其是否果真肇事，均不影響公共危險罪\n    責之成立，且參考德國、美國之認定標準，對於酒精濃度呼\n    氣已達每公升0.55毫克或血液濃度達0.11％以上，肇事率為\n    一般正常人之10倍，認為已達「不能安全駕駛」之標準，此\n    有法務部民國88年5月18日法88檢字第001669號函可資參照\n    。況駕駛人飲酒後，會降低對光線之適應能力，削弱其對於\n    路況及車前狀況辨識之正確性，亦使神經反應遲鈍，致使駕\n    駛人駕車時無法適切操控車輛，且駕駛人對此常不自知，而\n    自認仍能安全駕駛車輛。經查被告經警查獲時其酒精濃度呼\n    氣已達每公升0.6毫克，再者係因駕車蛇行、車身搖擺不定\n    之駕駛操控力欠佳始為警攔檢，且對員警指揮反應遲鈍及問\n    訊過程中被告有呈現多語之情形，其心智確已受飲酒之影響\n    而無法正常反應，此有刑法第185條之3案件測試觀察紀錄表\n    乙紙附卷可參，益徵被告當時已達不能安全駕駛之程度，被\n    告上開所辯，並不足採。本件事證明確，被告犯行堪以認定\n    。\n三、核被告所為，係犯刑法第185條之3之服用酒類不能安全駕駛\n    動力交通工具而駕駛罪。又被告於97年間即有聲請簡易判決\n    處刑書所載之酒後駕車之公共危險前科，經法院判處罰金新\n    台幣6萬元，並以易服社會勞動執行完畢，有臺灣高等法院\n    被告前案紀錄表1份在卷可按。爰審酌被告有前述酒後駕車\n    之公共危險前科，雖非累犯，惟其應已明知酒後不能駕車及\n    酒醉駕車之危險性，竟毫不思警醒，猶漠視自己安危，更枉\n    顧法律禁止規範與公眾道路通行之安全，再度於酒後駕駛車\n    輛，對公眾交通往來顯已造成潛在之高度危險，殊為不該，\n    兼衡其智識程度、家庭經濟狀況及犯罪後之態度等一切情狀\n    ，量處如主文所示之刑，並諭知易科罰金之折算標準，以資\n    懲儆。\n四、依刑事訴訟法第449條第1項前段、第3項、第454條第2項，\n    刑法第185條之3、第41條第1項前段，刑法施行法第1條之1\n    第1項，逕以簡易判決處如主文所示之刑。\n五、如不服本件判決，得自收受送達後10日內，向本院提出上訴\n    狀（附繕本），上訴於本院管轄之第二審地方法院合議庭。",
    "reason": "一、本件犯罪事實及證據，均引用檢察官聲請簡易判決處刑書（\n    如附件）之記載。\n二、被告雖辯稱：飲酒後有自信能夠安全駕駛車輛，不會影響其\n    他來往車輛及行人安全云云；然按刑法第185條之3所稱服用\n    酒類或其他相類之物，不能安全駕駛動力交通工具之公共危\n    險罪，係屬抽象危險犯之規定，此種抽象危險係伴隨飲酒過\n    量之行為而當然成立。換言之，只需客觀上有此種行為出現\n    ，危險即視為存在，其是否果真肇事，均不影響公共危險罪\n    責之成立，且參考德國、美國之認定標準，對於酒精濃度呼\n    氣已達每公升0.55毫克或血液濃度達0.11％以上，肇事率為\n    一般正常人之10倍，認為已達「不能安全駕駛」之標準，此\n    有法務部民國88年5月18日法88檢字第001669號函可資參照\n    。況駕駛人飲酒後，會降低對光線之適應能力，削弱其對於\n    路況及車前狀況辨識之正確性，亦使神經反應遲鈍，致使駕\n    駛人駕車時無法適切操控車輛，且駕駛人對此常不自知，而\n    自認仍能安全駕駛車輛。經查被告經警查獲時其酒精濃度呼\n    氣已達每公升0.6毫克，再者係因駕車蛇行、車身搖擺不定\n    之駕駛操控力欠佳始為警攔檢，且對員警指揮反應遲鈍及問\n    訊過程中被告有呈現多語之情形，其心智確已受飲酒之影響\n    而無法正常反應，此有刑法第185條之3案件測試觀察紀錄表\n    乙紙附卷可參，益徵被告當時已達不能安全駕駛之程度，被\n    告上開所辯，並不足採。本件事證明確，被告犯行堪以認定\n    。\n三、核被告所為，係犯刑法第185條之3之服用酒類不能安全駕駛\n    動力交通工具而駕駛罪。又被告於97年間即有聲請簡易判決\n    處刑書所載之酒後駕車之公共危險前科，經法院判處罰金新\n    台幣6萬元，並以易服社會勞動執行完畢，有臺灣高等法院\n    被告前案紀錄表1份在卷可按。爰審酌被告有前述酒後駕車\n    之公共危險前科，雖非累犯，惟其應已明知酒後不能駕車及\n    酒醉駕車之危險性，竟毫不思警醒，猶漠視自己安危，更枉\n    顧法律禁止規範與公眾道路通行之安全，再度於酒後駕駛車\n    輛，對公眾交通往來顯已造成潛在之高度危險，殊為不該，\n    兼衡其智識程度、家庭經濟狀況及犯罪後之態度等一切情狀\n    ，量處如主文所示之刑，並諭知易科罰金之折算標準，以資\n    懲儆。\n四、依刑事訴訟法第449條第1項前段、第3項、第454條第2項，\n    刑法第185條之3、第41條第1項前段，刑法施行法第1條之1\n    第1項，逕以簡易判決處如主文所示之刑。\n五、如不服本件判決，得自收受送達後10日內，向本院提出上訴\n    狀（附繕本），上訴於本院管轄之第二審地方法院合議庭。"
  },
  "search": "臺灣臺南地方法院刑事簡易判決100年度交簡字第776號聲請人臺灣臺南地方法院檢察署檢察官被告翁宗熙上列被告因公共危險案件，經檢察官聲請以簡易判決處刑（100年度偵字第3529號），本院判決如下：主文翁宗熙服用酒類，不能安全駕駛動力交通工具而駕駛，處有期徒刑月，如易科罰金，以新臺幣壹仟元折算壹日。事實及理由一、本件犯罪事實及證據，均引用檢察官聲請簡易判決處刑書（如附件）之記載。二、被告雖辯稱：飲酒後有自信能夠安全駕駛車輛，不會影響其他來往車輛及行人安全云云；然按刑法第185條之3所稱服用酒類或其他相類之物，不能安全駕駛動力交通工具之公共危險罪，係屬抽象危險犯之規定，此種抽象危險係伴隨飲酒過量之行為而當然成立。換言之，只需客觀上有此種行為出現，危險即視為存在，其是否果真肇事，均不影響公共危險罪責之成立，且參考德國、美國之認定標準，對於酒精濃度呼氣已達每公升0.55毫克或血液濃度達0.11％以上，肇事率為一般正常人之10倍，認為已達「不能安全駕駛」之標準，此有法務部民國88年5月18日法88檢字第001669號函可資參照。況駕駛人飲酒後，會降低對光線之適應能力，削弱其對於路況及車前狀況辨識之正確性，亦使神經反應遲鈍，致使駕駛人駕車時無法適切操控車輛，且駕駛人對此常不自知，而自認仍能安全駕駛車輛。經查被告經警查獲時其酒精濃度呼氣已達每公升0.6毫克，再者係因駕車蛇行、車身搖擺不定之駕駛操控力欠佳始為警攔檢，且對員警指揮反應遲鈍及問訊過程中被告有呈現多語之情形，其心智確已受飲酒之影響而無法正常反應，此有刑法第185條之3案件測試觀察紀錄表乙紙附卷可參，益徵被告當時已達不能安全駕駛之程度，被告上開所辯，並不足採。本件事證明確，被告犯行堪以認定。三、核被告所為，係犯刑法第185條之3之服用酒類不能安全駕駛動力交通工具而駕駛罪。又被告於97年間即有聲請簡易判決處刑書所載之酒後駕車之公共危險前科，經法院判處罰金新台幣6萬元，並以易服社會勞動執行完畢，有臺灣高等法院被告前案紀錄表1份在卷可按。爰審酌被告有前述酒後駕車之公共危險前科，雖非累犯，惟其應已明知酒後不能駕車及酒醉駕車之危險性，竟毫不思警醒，猶漠視自己安危，更枉顧法律禁止規範與公眾道路通行之安全，再度於酒後駕駛車輛，對公眾交通往來顯已造成潛在之高度危險，殊為不該，兼衡其智識程度、家庭經濟狀況及犯罪後之態度等一切情狀，量處如主文所示之刑，並諭知易科罰金之折算標準，以資懲儆。四、依刑事訴訟法第449條第1項前段、第3項、第454條第2項，刑法第185條之3、第41條第1項前段，刑法施行法第1條之1第1項，逕以簡易判決處如主文所示之刑。五、如不服本件判決，得自收受送達後10日內，向本院提出上訴狀（附繕本），上訴於本院管轄之第二審地方法院合議庭。中華民國100年4月20日刑事第四庭法官鄧希賢以上正本證明與原本無異。如不服本判決應於收受送達後10日內向本院提出上訴書狀（應附繕本）。書記官黃秋萍中華民國100年4月20日附錄本案論罪科刑法條全文：中華民國刑法第一百八十五條之三服用毒品、麻醉藥品、酒類或其他相類之物，不能安全駕駛動力交通工具而駕駛者，處一年以下有期徒刑、拘役或科或併科十五萬元以下罰金。",
  "characters": {
    "judges": [
      "鄧希賢"
    ],
    "prosecutors": [

    ],
    "lawyers": [

    ],
    "clerks": [
      "黃秋萍"
    ],
    "plaintiffs": [

    ],
    "defendants": [
      "翁宗熙"
    ],
    "prosecutor_office": [
      "臺灣臺南地方法院檢察署檢察官"
    ],
    "creditors": [

    ],
    "debtors": [

    ],
    "judicial_associate_officer": [

    ]
  },
  "adjudged_at": "2011-04-20",
  "created_at": "2016-02-12 11:27:16",
  "updated_at": "2016-02-12 11:27:16"
}