{
  "identify": "TCD-100-聲-4073-20111025-1",
  "court": {
    "name": "臺灣臺中地方法院",
    "code": "TCD"
  },
  "division": {
    "name": "刑事",
    "code": "M"
  },
  "year": 100,
  "word": "聲",
  "number": "4073",
  "jcheck": "1",
  "reason": "聲請定應執行之刑",
  "content": "臺灣臺中地方法院刑事裁定             100年度聲字第4073號\n聲  請  人  臺灣臺中地方法院檢察署檢察官\n受  刑  人  吳蒼燕\n上列聲請人因受刑人數罪併罰有二裁判以上，聲請定其應執行之\n刑（100 年度執聲字第2926號、100 年度執字第10353 號），本\n院裁定如下：\n    主    文\n吳蒼燕因犯如附表所示各罪所處之刑，應執行有期徒刑貳年捌月\n。\n    理    由\n一、被告吳蒼燕所犯如附表所示毒品危害防制條例等罪，先後經\n    臺灣南投地方法院與本院，以如附表所示判決判處如附表所\n    示之刑，均經分別確定在案，有上開案件判決書附卷可稽。\n    聲請人認應依刑法第53條、第51條第5 款定應執行之刑，本\n    院認為本件聲請於法尚無不合，應予准許。\n二、爰依刑事訴訟法第477 條第1 項、第220 條、刑法第53條、\n    第51條第5 款，裁定如主文。\n中    華    民    國   100    年    10    月    25    日\n                刑事第十二庭  法  官  簡婉倫\n上正本證明與原本無異。\n如不服本裁定，應於送達後5 日內，向本院提出抗告狀。\n                              書記官  許千士\n中    華    民    國   100    年    10    月    25    日\n附表\n臺灣臺中地方法院檢察署受刑人吳蒼燕定應執行刑案件一覽表\n┌────────┬─────────┬─────────┬─────────┐\n│編            號│        1         │        2         │        3         │\n├────────┼─────────┼─────────┼─────────┤\n│罪            名│ 毒品危害防制條例 │ 毒品危害防制條例 │ 毒品危害防制條例 │\n├────────┼─────────┼─────────┼─────────┤\n│宣     告     刑│   有期徒刑8月    │   有期徒刑8月    │    有期徒刑5 月  │\n├────────┼─────────┼─────────┼─────────┤\n│犯  罪   日   期│99.8.28 中午1 時許│99.10.26上午10時許│99.10.26上午12時許│\n├────────┼─────────┼─────────┼─────────┤\n│偵查（自訴）機關│南投地檢99年度毒偵│南投地檢99年度毒偵│南投地檢99年度毒偵│\n│年  度   案   號│字第1240、1294號  │字第1240、1294號  │字第1240、1294號  │\n├─┬──────┼─────────┼─────────┼─────────┤\n│最│法        院│     南投地院     │     南投地院     │     南投地院     │\n│後├──────┼─────────┼─────────┼─────────┤\n│事│案        號│100年度訴字第20號 │100年度訴字第20號 │100年度訴字第20號 │\n│  │            │                  │                  │                  │\n│實├──────┼─────────┼─────────┼─────────┤\n│審│判 決  日 期│     100.2.25     │     100.2.25     │     100.2.25     │\n├─┼──────┼─────────┼─────────┼─────────┤\n│確│法        院│     南投地院     │     南投地院     │     南投地院     │\n│定├──────┼─────────┼─────────┼─────────┤\n│  │案        號│100 年度訴字第20號│100 年度訴字第20號│100 年度訴字第20號│\n│  │            │                  │                  │                  │\n│  ├──────┼─────────┼─────────┼─────────┤\n│判│判        決│     100.3.22     │     100.3.22     │     100.3.22     │\n│決│確 定  日 期│                  │                  │                  │\n├─┴──────┼─────────┼─────────┼─────────┤\n│備           註 │臺中地檢100 年度執│臺中地檢100 年度執│臺中地檢100 年度執│\n│                │字第902號         │字第902號         │字第902號         │\n└────────┴─────────┴─────────┴─────────┘\n臺灣臺中地方法院檢察署受刑人吳蒼燕定應執行刑案件一覽表\n┌────────┬─────────┬─────────┬─────────┐\n│編            號│        4         │        5         │        6         │\n├────────┼─────────┼─────────┼─────────┤\n│罪            名│ 毒品危害防制條例 │ 毒品危害防制條例 │ 毒品危害防制條例 │\n├────────┼─────────┼─────────┼─────────┤\n│宣     告     刑│   有期徒刑8月    │   有期徒刑8月    │    有期徒刑8月   │\n├────────┼─────────┼─────────┼─────────┤\n│犯  罪   日   期│  99.10.31日某時  │ 100.1.9 日17時許 │100.1.14日某時許  │\n├────────┼─────────┼─────────┼─────────┤\n│偵查（自訴）機關│臺中地檢100 年度毒│臺中地檢100 年度毒│臺中地檢100 年度毒│\n│年  度   案   號│偵字第768號       │偵字第768號       │偵字第768號       │\n├─┬──────┼─────────┼─────────┼─────────┤\n│最│法        院│     臺中地院     │     臺中地院     │     臺中地院     │\n│後├──────┼─────────┼─────────┼─────────┤\n│事│案        號│100 年度訴字第1965│100 年度訴字第1965│100 年度訴字第1965│\n│  │            │號                │號                │號                │\n│實├──────┼─────────┼─────────┼─────────┤\n│審│判 決  日 期│     100.7.29     │     100.7.29     │     100.7.29     │\n├─┼──────┼─────────┼─────────┼─────────┤\n│確│法        院│     臺中地院     │     臺中地院     │     臺中地院     │\n│定├──────┼─────────┼─────────┼─────────┤\n│  │案        號│100 年度訴字第1965│100 年度訴字第1965│100 年度訴字第1965│\n│  │            │號                │號                │號                │\n│  ├──────┼─────────┼─────────┼─────────┤\n│判│判        決│     100.8.22     │     100.8.22     │     100.8.22     │\n│決│確 定  日 期│                  │                  │                  │\n├─┴──────┼─────────┼─────────┼─────────┤\n│備           註 │臺中地檢100 年度執│臺中地檢100 年度執│臺中地檢100 年度執│\n│                │字第10530號       │字第10530號       │字第10530號       │\n└────────┴─────────┴─────────┴─────────┘",
  "structure": {
    "main": "吳蒼燕因犯如附表所示各罪所處之刑，應執行有期徒刑貳年捌月\n。",
    "reason": "一、被告吳蒼燕所犯如附表所示毒品危害防制條例等罪，先後經\n    臺灣南投地方法院與本院，以如附表所示判決判處如附表所\n    示之刑，均經分別確定在案，有上開案件判決書附卷可稽。\n    聲請人認應依刑法第53條、第51條第5 款定應執行之刑，本\n    院認為本件聲請於法尚無不合，應予准許。\n二、爰依刑事訴訟法第477 條第1 項、第220 條、刑法第53條、\n    第51條第5 款，裁定如主文。"
  },
  "search": "臺灣臺中地方法院刑事裁定100年度聲字第4073號聲請人臺灣臺中地方法院檢察署檢察官受刑人吳蒼燕上列聲請人因受刑人數罪併罰有二裁判以上，聲請定其應執行之刑（100年度執聲字第2926號、100年度執字第10353號），本院裁定如下：主文吳蒼燕因犯如附表所示各罪所處之刑，應執行有期徒刑貳年捌月。理由一、被告吳蒼燕所犯如附表所示毒品危害防制條例等罪，先後經臺灣南投地方法院與本院，以如附表所示判決判處如附表所示之刑，均經分別確定在案，有上開案件判決書附卷可稽。聲請人認應依刑法第53條、第51條第5款定應執行之刑，本院認為本件聲請於法尚無不合，應予准許。二、爰依刑事訴訟法第477條第1項、第220條、刑法第53條、第51條第5款，裁定如主文。中華民國100年10月25日刑事第十二庭法官簡婉倫上正本證明與原本無異。如不服本裁定，應於送達後5日內，向本院提出抗告狀。書記官許千士中華民國100年10月25日附表臺灣臺中地方法院檢察署受刑人吳蒼燕定應執行刑案件一覽表┌────────┬─────────┬─────────┬─────────┐│編號│1│2│3│├────────┼─────────┼─────────┼─────────┤│罪名│毒品危害防制條例│毒品危害防制條例│毒品危害防制條例│├────────┼─────────┼─────────┼─────────┤│宣告刑│有期徒刑8月│有期徒刑8月│有期徒刑5月│├────────┼─────────┼─────────┼─────────┤│犯罪日期│99.8.28中午1時許│99.10.26上午10時許│99.10.26上午12時許│├────────┼─────────┼─────────┼─────────┤│偵查（自訴）機關│南投地檢99年度毒偵│南投地檢99年度毒偵│南投地檢99年度毒偵││年度案號│字第1240、1294號│字第1240、1294號│字第1240、1294號│├─┬──────┼─────────┼─────────┼─────────┤│最│法院│南投地院│南投地院│南投地院││後├──────┼─────────┼─────────┼─────────┤│事│案號│100年度訴字第20號│100年度訴字第20號│100年度訴字第20號││││││││實├──────┼─────────┼─────────┼─────────┤│審│判決日期│100.2.25│100.2.25│100.2.25│├─┼──────┼─────────┼─────────┼─────────┤│確│法院│南投地院│南投地院│南投地院││定├──────┼─────────┼─────────┼─────────┤││案號│100年度訴字第20號│100年度訴字第20號│100年度訴字第20號││││││││├──────┼─────────┼─────────┼─────────┤│判│判決│100.3.22│100.3.22│100.3.22││決│確定日期││││├─┴──────┼─────────┼─────────┼─────────┤│備註│臺中地檢100年度執│臺中地檢100年度執│臺中地檢100年度執│││字第902號│字第902號│字第902號│└────────┴─────────┴─────────┴─────────┘臺灣臺中地方法院檢察署受刑人吳蒼燕定應執行刑案件一覽表┌────────┬─────────┬─────────┬─────────┐│編號│4│5│6│├────────┼─────────┼─────────┼─────────┤│罪名│毒品危害防制條例│毒品危害防制條例│毒品危害防制條例│├────────┼─────────┼─────────┼─────────┤│宣告刑│有期徒刑8月│有期徒刑8月│有期徒刑8月│├────────┼─────────┼─────────┼─────────┤│犯罪日期│99.10.31日某時│100.1.9日17時許│100.1.14日某時許│├────────┼─────────┼─────────┼─────────┤│偵查（自訴）機關│臺中地檢100年度毒│臺中地檢100年度毒│臺中地檢100年度毒││年度案號│偵字第768號│偵字第768號│偵字第768號│├─┬──────┼─────────┼─────────┼─────────┤│最│法院│臺中地院│臺中地院│臺中地院││後├──────┼─────────┼─────────┼─────────┤│事│案號│100年度訴字第1965│100年度訴字第1965│100年度訴字第1965││││號│號│號││實├──────┼─────────┼─────────┼─────────┤│審│判決日期│100.7.29│100.7.29│100.7.29│├─┼──────┼─────────┼─────────┼─────────┤│確│法院│臺中地院│臺中地院│臺中地院││定├──────┼─────────┼─────────┼─────────┤││案號│100年度訴字第1965│100年度訴字第1965│100年度訴字第1965││││號│號│號││├──────┼─────────┼─────────┼─────────┤│判│判決│100.8.22│100.8.22│100.8.22││決│確定日期││││├─┴──────┼─────────┼─────────┼─────────┤│備註│臺中地檢100年度執│臺中地檢100年度執│臺中地檢100年度執│││字第10530號│字第10530號│字第10530號│└────────┴─────────┴─────────┴─────────┘",
  "characters": {
    "judges": [
      "簡婉倫"
    ],
    "prosecutors": [

    ],
    "lawyers": [

    ],
    "clerks": [
      "許千士"
    ],
    "plaintiffs": [

    ],
    "defendants": [

    ],
    "prosecutor_office": [
      "臺灣臺中地方法院檢察署檢察官"
    ],
    "creditors": [

    ],
    "debtors": [

    ],
    "judicial_associate_officer": [

    ]
  },
  "adjudged_at": "2011-10-25",
  "created_at": "2016-02-14 06:41:54",
  "updated_at": "2016-02-14 06:41:54"
}