{
  "identify": "TPD-100-聲-2760-20111025-1",
  "court": {
    "name": "臺灣臺北地方法院",
    "code": "TPD"
  },
  "division": {
    "name": "刑事",
    "code": "M"
  },
  "year": 100,
  "word": "聲",
  "number": "2760",
  "jcheck": "1",
  "reason": "聲請單獨宣告沒收扣押物",
  "content": "臺灣臺北地方法院刑事裁定             100年度聲字第2760號\n聲  請  人  臺灣臺北地方法院檢察署檢察官\n被      告  王德明\n上列聲請人因被告妨害秘密案件，聲請單獨宣告沒收扣押物（一\n００年度執聲字第一七０七號），本院裁定如下：\n    主  文\n扣案之筆記型電腦壹臺及側錄器壹臺均沒收。\n    理  由\n一、聲請意旨略以：被告王德明妨害秘密乙案，業經臺灣臺北地\n    方法院檢察署檢察官聲請簡易判決處刑，經本院以一００年\n    度簡字第二六一八號判處拘役五十九日確定在案，而扣案之\n    筆記型電腦一台及側錄器一台，係被告所有且用以竊錄之附\n    著物及物品，爰依刑法第三百十五條之三之規定，聲請單獨\n    宣告沒收等語。\n二、按供犯罪所用之物或因犯罪所得之物，以屬於犯罪行為人者\n    為限，得沒收之，但有特別規定者，依其規定；沒收，除有\n    特別規定者外，於裁判時併宣告之；違禁物或專科沒收之物\n    得單獨宣告沒收；刑法第三十八條第一項第二款、第三款、\n    第三項，以及同法第四十條分別定有明文。又竊錄內容之附\n    著物及物品，不問屬於犯人與否，沒收之，刑法第三百十五\n    條之三亦規定甚明。復按刑法第四十條第二項所定「專科沒\n    收之物」，係指性質不宜任令在外流通之物而言（刑法第四\n    十條第二項民國九十四年二月二日修正理由參照）。\n三、經查，本件被告因妨害秘密案件，經臺灣臺北地方法院檢察\n    署檢察官聲請簡易判決處刑，經本院以一００年度簡字第二\n    六一八號判處拘役五十九日確定在案等情，有上開判決書、\n    臺灣高等法院被告前案記錄表各一份附卷可參。而扣案之筆\n    記型電腦一台及側錄器一台均存有被告竊錄被害人如廁之私\n    密影片，且該竊錄內容縱經刪除，仍可能透過還原軟體使竊\n    錄內容回復，揆諸刑法第三百十五條之三立法意旨，即係為\n    免此種侵害持續存在，而設義務沒收之規定，若將上開扣案\n    之物發還被告，無異存有傷害被害人之可能，是扣案之筆記\n    型電腦一台及側錄器一台係屬竊錄內容之附著物及物品，依\n    刑法第三百十五條之三規定，不問屬於犯人與否，均應予以\n    沒收，為專科沒收之物，聲請人聲請單獨宣告沒收，核無不\n    合，應予准許。\n四、依刑事訴訟法第二百二十條，刑法第三百十五條之三、第四\n    十條第二項，裁定如主文。\n中    華    民    國   100    年    10    月    25    日\n                  刑事第九庭  法  官  鄭富城\n以上正本證明與原本無異。\n如不服本裁定，應於送達後5日內，向本院提出抗告狀。\n                              書記官  顏淑華\n中    華    民    國   100    年    10    月    25    日",
  "structure": {
    "main": "扣案之筆記型電腦壹臺及側錄器壹臺均沒收。",
    "reason": "一、聲請意旨略以：被告王德明妨害秘密乙案，業經臺灣臺北地\n    方法院檢察署檢察官聲請簡易判決處刑，經本院以一００年\n    度簡字第二六一八號判處拘役五十九日確定在案，而扣案之\n    筆記型電腦一台及側錄器一台，係被告所有且用以竊錄之附\n    著物及物品，爰依刑法第三百十五條之三之規定，聲請單獨\n    宣告沒收等語。\n二、按供犯罪所用之物或因犯罪所得之物，以屬於犯罪行為人者\n    為限，得沒收之，但有特別規定者，依其規定；沒收，除有\n    特別規定者外，於裁判時併宣告之；違禁物或專科沒收之物\n    得單獨宣告沒收；刑法第三十八條第一項第二款、第三款、\n    第三項，以及同法第四十條分別定有明文。又竊錄內容之附\n    著物及物品，不問屬於犯人與否，沒收之，刑法第三百十五\n    條之三亦規定甚明。復按刑法第四十條第二項所定「專科沒\n    收之物」，係指性質不宜任令在外流通之物而言（刑法第四\n    十條第二項民國九十四年二月二日修正理由參照）。\n三、經查，本件被告因妨害秘密案件，經臺灣臺北地方法院檢察\n    署檢察官聲請簡易判決處刑，經本院以一００年度簡字第二\n    六一八號判處拘役五十九日確定在案等情，有上開判決書、\n    臺灣高等法院被告前案記錄表各一份附卷可參。而扣案之筆\n    記型電腦一台及側錄器一台均存有被告竊錄被害人如廁之私\n    密影片，且該竊錄內容縱經刪除，仍可能透過還原軟體使竊\n    錄內容回復，揆諸刑法第三百十五條之三立法意旨，即係為\n    免此種侵害持續存在，而設義務沒收之規定，若將上開扣案\n    之物發還被告，無異存有傷害被害人之可能，是扣案之筆記\n    型電腦一台及側錄器一台係屬竊錄內容之附著物及物品，依\n    刑法第三百十五條之三規定，不問屬於犯人與否，均應予以\n    沒收，為專科沒收之物，聲請人聲請單獨宣告沒收，核無不\n    合，應予准許。\n四、依刑事訴訟法第二百二十條，刑法第三百十五條之三、第四\n    十條第二項，裁定如主文。"
  },
  "search": "臺灣臺北地方法院刑事裁定100年度聲字第2760號聲請人臺灣臺北地方法院檢察署檢察官被告王德明上列聲請人因被告妨害秘密案件，聲請單獨宣告沒收扣押物（一００年度執聲字第一七０七號），本院裁定如下：主文扣案之筆記型電腦壹臺及側錄器壹臺均沒收。理由一、聲請意旨略以：被告王德明妨害秘密乙案，業經臺灣臺北地方法院檢察署檢察官聲請簡易判決處刑，經本院以一００年度簡字第二六一八號判處拘役五十九日確定在案，而扣案之筆記型電腦一台及側錄器一台，係被告所有且用以竊錄之附著物及物品，爰依刑法第三百十五條之三之規定，聲請單獨宣告沒收等語。二、按供犯罪所用之物或因犯罪所得之物，以屬於犯罪行為人者為限，得沒收之，但有特別規定者，依其規定；沒收，除有特別規定者外，於裁判時併宣告之；違禁物或專科沒收之物得單獨宣告沒收；刑法第三十八條第一項第二款、第三款、第三項，以及同法第四十條分別定有明文。又竊錄內容之附著物及物品，不問屬於犯人與否，沒收之，刑法第三百十五條之三亦規定甚明。復按刑法第四十條第二項所定「專科沒收之物」，係指性質不宜任令在外流通之物而言（刑法第四十條第二項民國九十四年二月二日修正理由參照）。三、經查，本件被告因妨害秘密案件，經臺灣臺北地方法院檢察署檢察官聲請簡易判決處刑，經本院以一００年度簡字第二六一八號判處拘役五十九日確定在案等情，有上開判決書、臺灣高等法院被告前案記錄表各一份附卷可參。而扣案之筆記型電腦一台及側錄器一台均存有被告竊錄被害人如廁之私密影片，且該竊錄內容縱經刪除，仍可能透過還原軟體使竊錄內容回復，揆諸刑法第三百十五條之三立法意旨，即係為免此種侵害持續存在，而設義務沒收之規定，若將上開扣案之物發還被告，無異存有傷害被害人之可能，是扣案之筆記型電腦一台及側錄器一台係屬竊錄內容之附著物及物品，依刑法第三百十五條之三規定，不問屬於犯人與否，均應予以沒收，為專科沒收之物，聲請人聲請單獨宣告沒收，核無不合，應予准許。四、依刑事訴訟法第二百二十條，刑法第三百十五條之三、第四十條第二項，裁定如主文。中華民國100年10月25日刑事第九庭法官鄭富城以上正本證明與原本無異。如不服本裁定，應於送達後5日內，向本院提出抗告狀。書記官顏淑華中華民國100年10月25日",
  "characters": {
    "judges": [
      "鄭富城"
    ],
    "prosecutors": [

    ],
    "lawyers": [

    ],
    "clerks": [
      "顏淑華"
    ],
    "plaintiffs": [

    ],
    "defendants": [
      "王德明"
    ],
    "prosecutor_office": [
      "臺灣臺北地方法院檢察署檢察官"
    ],
    "creditors": [

    ],
    "debtors": [

    ],
    "judicial_associate_officer": [

    ]
  },
  "adjudged_at": "2011-10-25",
  "created_at": "2016-02-14 06:33:23",
  "updated_at": "2016-02-14 06:33:23"
}