{
  "identify": "PTD-93-訴-700-20050131-1",
  "court": {
    "name": "臺灣屏東地方法院",
    "code": "PTD"
  },
  "division": {
    "name": "刑事",
    "code": "M"
  },
  "year": 93,
  "word": "訴",
  "number": "700",
  "jcheck": "1",
  "reason": "違反毒品危害防制條例",
  "content": "臺灣屏東地方法院刑事判決                          九十三年度訴字第七００號\n    公  訴  人  臺灣屏東地方法院檢察署檢察官\n    被      告  甲○○  男  三.\n右列被告因違反毒品危害防制條例案件，經檢察官提起公訴（九十三年度毒偵字第一\n五三三號），被告就被訴事實為有罪之陳述，本院裁定行簡式審判程序，判決如左：\n    主  文\n甲○○連續施用第一級毒品，累犯，處有期徒刑拾月。\n    事  實\n一、甲○○前於民國八十七年間因違反毒品危害防制條例案件，經臺灣高等法院高雄\n    分院八十八年度上訴字第八二七號判處有期徒刑一年二月確定，自八十九年九月\n    一日起入監服刑，迄九十年六月七日，因縮短刑期假釋出監，而於九十年八月二\n    十七日縮刑期滿未經撤銷假釋以視為執行完畢論。另於八十七年間因施用毒品案\n    件，經本院八十七年度毒聲字第三七四號裁定送觀察、勒戒後，認有繼續施用毒\n    品之傾向，再依本院八十七年度毒聲字第五三二號裁定入戒治處所施以強制戒治\n    ，其後經本院八十八年度毒聲字第四七一號裁定停止戒治，所餘戒治期間付保護\n    管束，嗣再經本院八十九年度毒聲字第四四０號裁定撤銷停止戒治，於八十九年\n    八月二十二日經強制戒治期滿，由臺灣屏東地方法院檢察署檢察官於八十九年八\n    月二十八日，以八十九年度戒毒偵字第三六六號不起訴處分確定。詎其猶不知悔\n    改，竟基於施用第一級毒品海洛因之概括犯意，自九十三年二月二十日早上某時\n    起，至同年六月三日二十一時許止，在屏東縣長治鄉○○村○○路一八二號住處\n    內，以將第一級毒品海洛因加水再以注射針筒注入手臂內之方式，約一星期施用\n    一天，該天施用第一級毒品海洛因三次之頻率，連續施用第一級毒品海洛因多次\n    ，嗣於九十三年六月五日十四時二十分許，為警在屏東縣麟洛鄉○○村○○路第\n    三公墓內查獲。\n二、案經屏東縣警察局屏東分局報請臺灣屏東地方法院檢察署檢察官偵查起訴。甲○\n    ○於審理時逃匿，經本院發布通緝後，始於九十三年十二月十八日為警逮捕歸案\n    。\n    理  由\n一、右揭事實，業據被告甲○○於警詢時、偵查中及本院審理時坦承不諱，且被告為\n    警查獲時所採集之尿液檢體，經送請屏東縣衛生局檢驗，結果呈嗎啡陽性反應，\n    有該局煙毒及麻醉藥品類委託檢驗結果通知書影本一紙（見警卷第一一頁）附卷\n    可稽，堪信被告上開自白確與事實相符。次查被告先前如事實欄所載，其於八十\n    七年間因施用毒品案件，經本院八十七年度毒聲字第三七四號裁定送觀察、勒戒\n    後，認有繼續施用毒品之傾向，再依本院八十七年度毒聲字第五三二號裁定入戒\n    治處所施以強制戒治，其後經本院八十八年度毒聲字第四七一號裁定停止戒治，\n    所餘戒治期間付保護管束，嗣再經本院八十九年度毒聲字第四四０號裁定撤銷停\n    止戒治，經強制戒治期滿，由臺灣屏東地方法院檢察署檢察官於八十九年八月二\n    十八日，以八十九年度戒毒偵字第三六六號不起訴處分確定等節，有本院八十七\n    年度毒聲字第五三二號裁定、八十八年度毒聲字第四七一號裁定、八十九年度毒\n    聲字第四四０號裁定、臺灣屏東地方法院檢察署檢察官八十九年度戒毒偵字第三\n    六六號不起訴處分書（見本院卷第五一頁至第五四頁）、臺灣高等法院被告全國\n    前案紀錄表及全國施用毒品案件紀錄表各一份在卷足憑，本件事證已臻明確，被\n    告五年內再犯本件施用第一級毒品海洛因犯行洵堪認定。\n二、查海洛因為毒品危害防制條例第二條第二項第一款明定之第一級毒品，不得持有\n    及施用，核被告甲○○所為，係犯毒品危害防制條例第十條第一項之施用第一級\n    毒品罪。其施用前持有第一級毒品海洛因之低度行為，應為其施用第一級毒品之\n    高度行為所吸收，不另論罪；其先後多次施用第一級毒品海洛因犯行，時間緊接\n    、犯罪構成要件相同，顯然基於概括犯意反覆為之，應依連續犯之規定論以一罪\n    ，並依法加重其刑；且被告曾於八十七年間因違反毒品危害防制條例案件，經臺\n    灣高等法院高雄分院八十八年度上訴字第八二七號判處有期徒刑一年二月確定，\n    自八十九年九月一日起入監服刑，迄九十年六月七日，因縮短刑期假釋出監，而\n    於九十年八月二十七日縮刑期滿未經撤銷假釋以視為執行完畢論，有臺灣高等法\n    院被告全國前案紀錄表一份在卷可稽，其於有期徒刑執行完畢，五年以內再犯本\n    件有期徒刑以上之罪，為累犯，應依刑法第四十七條之規定遞加重其刑。爰審酌\n    被告前經觀察、勒戒及強制戒治後，仍未戒斷其施用毒品之惡習，並參酌其素行\n    狀況、犯罪之動機、目的、手段、所生戕害其身心情形及犯罪後坦承犯行，態度\n    尚非惡劣等一切情狀，量處如主文所示之刑，以資懲儆。\n據上論斷，應依刑事訴訟法第二百九十九條第一項前段、第二百七十三條之一第一項\n，毒品危害防制條例第十條第一項，刑法第十一條、第五十六條、第四十七條，判決\n如主文。\n本案經檢察官葉容芳到庭執行職務。\n中      華      民      國    九十四    年      一      月    三十一    日\n                                      臺灣屏東地方法院刑事第六庭\n                                          法  官  林家聖\n右正本證明與原本無異。\n如不服本判決應於收受本判決送達後十日內向本院提出上訴書狀，其未敘述上訴理由\n者，並得於提起上訴後十日內向本院補提理由書狀（均須按他造當事人之人數附繕本\n ）「切勿逕送上級法院」\n                                          書記官  唐淑嫻\n中      華      民      國    九十四    年      一      月    三十一    日\n附錄本判決論罪科刑法條全文：\n毒品危害防制條例第十條第一項\n施用第一級毒品者，處六月以上五年以下有期徒刑。\n",
  "structure": {
    "main": "甲○○連續施用第一級毒品，累犯，處有期徒刑拾月。",
    "fact": "一、甲○○前於民國八十七年間因違反毒品危害防制條例案件，經臺灣高等法院高雄\n    分院八十八年度上訴字第八二七號判處有期徒刑一年二月確定，自八十九年九月\n    一日起入監服刑，迄九十年六月七日，因縮短刑期假釋出監，而於九十年八月二\n    十七日縮刑期滿未經撤銷假釋以視為執行完畢論。另於八十七年間因施用毒品案\n    件，經本院八十七年度毒聲字第三七四號裁定送觀察、勒戒後，認有繼續施用毒\n    品之傾向，再依本院八十七年度毒聲字第五三二號裁定入戒治處所施以強制戒治\n    ，其後經本院八十八年度毒聲字第四七一號裁定停止戒治，所餘戒治期間付保護\n    管束，嗣再經本院八十九年度毒聲字第四四０號裁定撤銷停止戒治，於八十九年\n    八月二十二日經強制戒治期滿，由臺灣屏東地方法院檢察署檢察官於八十九年八\n    月二十八日，以八十九年度戒毒偵字第三六六號不起訴處分確定。詎其猶不知悔\n    改，竟基於施用第一級毒品海洛因之概括犯意，自九十三年二月二十日早上某時\n    起，至同年六月三日二十一時許止，在屏東縣長治鄉○○村○○路一八二號住處\n    內，以將第一級毒品海洛因加水再以注射針筒注入手臂內之方式，約一星期施用\n    一天，該天施用第一級毒品海洛因三次之頻率，連續施用第一級毒品海洛因多次\n    ，嗣於九十三年六月五日十四時二十分許，為警在屏東縣麟洛鄉○○村○○路第\n    三公墓內查獲。\n二、案經屏東縣警察局屏東分局報請臺灣屏東地方法院檢察署檢察官偵查起訴。甲○\n    ○於審理時逃匿，經本院發布通緝後，始於九十三年十二月十八日為警逮捕歸案\n    。",
    "reason": "一、右揭事實，業據被告甲○○於警詢時、偵查中及本院審理時坦承不諱，且被告為\n    警查獲時所採集之尿液檢體，經送請屏東縣衛生局檢驗，結果呈嗎啡陽性反應，\n    有該局煙毒及麻醉藥品類委託檢驗結果通知書影本一紙（見警卷第一一頁）附卷\n    可稽，堪信被告上開自白確與事實相符。次查被告先前如事實欄所載，其於八十\n    七年間因施用毒品案件，經本院八十七年度毒聲字第三七四號裁定送觀察、勒戒\n    後，認有繼續施用毒品之傾向，再依本院八十七年度毒聲字第五三二號裁定入戒\n    治處所施以強制戒治，其後經本院八十八年度毒聲字第四七一號裁定停止戒治，\n    所餘戒治期間付保護管束，嗣再經本院八十九年度毒聲字第四四０號裁定撤銷停\n    止戒治，經強制戒治期滿，由臺灣屏東地方法院檢察署檢察官於八十九年八月二\n    十八日，以八十九年度戒毒偵字第三六六號不起訴處分確定等節，有本院八十七\n    年度毒聲字第五三二號裁定、八十八年度毒聲字第四七一號裁定、八十九年度毒\n    聲字第四四０號裁定、臺灣屏東地方法院檢察署檢察官八十九年度戒毒偵字第三\n    六六號不起訴處分書（見本院卷第五一頁至第五四頁）、臺灣高等法院被告全國\n    前案紀錄表及全國施用毒品案件紀錄表各一份在卷足憑，本件事證已臻明確，被\n    告五年內再犯本件施用第一級毒品海洛因犯行洵堪認定。\n二、查海洛因為毒品危害防制條例第二條第二項第一款明定之第一級毒品，不得持有\n    及施用，核被告甲○○所為，係犯毒品危害防制條例第十條第一項之施用第一級\n    毒品罪。其施用前持有第一級毒品海洛因之低度行為，應為其施用第一級毒品之\n    高度行為所吸收，不另論罪；其先後多次施用第一級毒品海洛因犯行，時間緊接\n    、犯罪構成要件相同，顯然基於概括犯意反覆為之，應依連續犯之規定論以一罪\n    ，並依法加重其刑；且被告曾於八十七年間因違反毒品危害防制條例案件，經臺\n    灣高等法院高雄分院八十八年度上訴字第八二七號判處有期徒刑一年二月確定，\n    自八十九年九月一日起入監服刑，迄九十年六月七日，因縮短刑期假釋出監，而\n    於九十年八月二十七日縮刑期滿未經撤銷假釋以視為執行完畢論，有臺灣高等法\n    院被告全國前案紀錄表一份在卷可稽，其於有期徒刑執行完畢，五年以內再犯本\n    件有期徒刑以上之罪，為累犯，應依刑法第四十七條之規定遞加重其刑。爰審酌\n    被告前經觀察、勒戒及強制戒治後，仍未戒斷其施用毒品之惡習，並參酌其素行\n    狀況、犯罪之動機、目的、手段、所生戕害其身心情形及犯罪後坦承犯行，態度\n    尚非惡劣等一切情狀，量處如主文所示之刑，以資懲儆。\n據上論斷，應依刑事訴訟法第二百九十九條第一項前段、第二百七十三條之一第一項\n，毒品危害防制條例第十條第一項，刑法第十一條、第五十六條、第四十七條，判決\n如主文。\n本案經檢察官葉容芳到庭執行職務。\n中      華      民      國    九十四    年      一      月    三十一    日\n                                      臺灣屏東地方法院刑事第六庭\n                                          法  官  林家聖\n右正本證明與原本無異。\n如不服本判決應於收受本判決送達後十日內向本院提出上訴書狀，其未敘述上訴理由\n者，並得於提起上訴後十日內向本院補提理由書狀（均須按他造當事人之人數附繕本\n ）「切勿逕送上級法院」\n                                          書記官  唐淑嫻"
  },
  "search": "臺灣屏東地方法院刑事判決九十三年度訴字第七００號公訴人臺灣屏東地方法院檢察署檢察官被告甲○○男三.右列被告因違反毒品危害防制條例案件，經檢察官提起公訴（九十三年度毒偵字第一五三三號），被告就被訴事實為有罪之陳述，本院裁定行簡式審判程序，判決如左：主文甲○○連續施用第一級毒品，累犯，處有期徒刑拾月。事實一、甲○○前於民國八十七年間因違反毒品危害防制條例案件，經臺灣高等法院高雄分院八十八年度上訴字第八二七號判處有期徒刑一年二月確定，自八十九年九月一日起入監服刑，迄九十年六月七日，因縮短刑期假釋出監，而於九十年八月二十七日縮刑期滿未經撤銷假釋以視為執行完畢論。另於八十七年間因施用毒品案件，經本院八十七年度毒聲字第三七四號裁定送觀察、勒戒後，認有繼續施用毒品之傾向，再依本院八十七年度毒聲字第五三二號裁定入戒治處所施以強制戒治，其後經本院八十八年度毒聲字第四七一號裁定停止戒治，所餘戒治期間付保護管束，嗣再經本院八十九年度毒聲字第四四０號裁定撤銷停止戒治，於八十九年八月二十二日經強制戒治期滿，由臺灣屏東地方法院檢察署檢察官於八十九年八月二十八日，以八十九年度戒毒偵字第三六六號不起訴處分確定。詎其猶不知悔改，竟基於施用第一級毒品海洛因之概括犯意，自九十三年二月二十日早上某時起，至同年六月三日二十一時許止，在屏東縣長治鄉○○村○○路一八二號住處內，以將第一級毒品海洛因加水再以注射針筒注入手臂內之方式，約一星期施用一天，該天施用第一級毒品海洛因三次之頻率，連續施用第一級毒品海洛因多次，嗣於九十三年六月五日十四時二十分許，為警在屏東縣麟洛鄉○○村○○路第三公墓內查獲。二、案經屏東縣警察局屏東分局報請臺灣屏東地方法院檢察署檢察官偵查起訴。甲○○於審理時逃匿，經本院發布通緝後，始於九十三年十二月十八日為警逮捕歸案。理由一、右揭事實，業據被告甲○○於警詢時、偵查中及本院審理時坦承不諱，且被告為警查獲時所採集之尿液檢體，經送請屏東縣衛生局檢驗，結果呈嗎啡陽性反應，有該局煙毒及麻醉藥品類委託檢驗結果通知書影本一紙（見警卷第一一頁）附卷可稽，堪信被告上開自白確與事實相符。次查被告先前如事實欄所載，其於八十七年間因施用毒品案件，經本院八十七年度毒聲字第三七四號裁定送觀察、勒戒後，認有繼續施用毒品之傾向，再依本院八十七年度毒聲字第五三二號裁定入戒治處所施以強制戒治，其後經本院八十八年度毒聲字第四七一號裁定停止戒治，所餘戒治期間付保護管束，嗣再經本院八十九年度毒聲字第四四０號裁定撤銷停止戒治，經強制戒治期滿，由臺灣屏東地方法院檢察署檢察官於八十九年八月二十八日，以八十九年度戒毒偵字第三六六號不起訴處分確定等節，有本院八十七年度毒聲字第五三二號裁定、八十八年度毒聲字第四七一號裁定、八十九年度毒聲字第四四０號裁定、臺灣屏東地方法院檢察署檢察官八十九年度戒毒偵字第三六六號不起訴處分書（見本院卷第五一頁至第五四頁）、臺灣高等法院被告全國前案紀錄表及全國施用毒品案件紀錄表各一份在卷足憑，本件事證已臻明確，被告五年內再犯本件施用第一級毒品海洛因犯行洵堪認定。二、查海洛因為毒品危害防制條例第二條第二項第一款明定之第一級毒品，不得持有及施用，核被告甲○○所為，係犯毒品危害防制條例第十條第一項之施用第一級毒品罪。其施用前持有第一級毒品海洛因之低度行為，應為其施用第一級毒品之高度行為所吸收，不另論罪；其先後多次施用第一級毒品海洛因犯行，時間緊接、犯罪構成要件相同，顯然基於概括犯意反覆為之，應依連續犯之規定論以一罪，並依法加重其刑；且被告曾於八十七年間因違反毒品危害防制條例案件，經臺灣高等法院高雄分院八十八年度上訴字第八二七號判處有期徒刑一年二月確定，自八十九年九月一日起入監服刑，迄九十年六月七日，因縮短刑期假釋出監，而於九十年八月二十七日縮刑期滿未經撤銷假釋以視為執行完畢論，有臺灣高等法院被告全國前案紀錄表一份在卷可稽，其於有期徒刑執行完畢，五年以內再犯本件有期徒刑以上之罪，為累犯，應依刑法第四十七條之規定遞加重其刑。爰審酌被告前經觀察、勒戒及強制戒治後，仍未戒斷其施用毒品之惡習，並參酌其素行狀況、犯罪之動機、目的、手段、所生戕害其身心情形及犯罪後坦承犯行，態度尚非惡劣等一切情狀，量處如主文所示之刑，以資懲儆。據上論斷，應依刑事訴訟法第二百九十九條第一項前段、第二百七十三條之一第一項，毒品危害防制條例第十條第一項，刑法第十一條、第五十六條、第四十七條，判決如主文。本案經檢察官葉容芳到庭執行職務。中華民國九十四年一月三十一日臺灣屏東地方法院刑事第六庭法官林家聖右正本證明與原本無異。如不服本判決應於收受本判決送達後十日內向本院提出上訴書狀，其未敘述上訴理由者，並得於提起上訴後十日內向本院補提理由書狀（均須按他造當事人之人數附繕本）「切勿逕送上級法院」書記官唐淑嫻中華民國九十四年一月三十一日附錄本判決論罪科刑法條全文：毒品危害防制條例第十條第一項施用第一級毒品者，處六月以上五年以下有期徒刑。",
  "characters": {
    "judges": [
      "林家聖"
    ],
    "prosecutors": [
      "葉容芳"
    ],
    "lawyers": [

    ],
    "clerks": [
      "唐淑嫻"
    ],
    "plaintiffs": [

    ],
    "defendants": [
      "甲○○  男  三.",
      "右列被告因違反毒品危害防制條例案件，經檢察官提起公訴（九十三年度毒偵字第一",
      "五三三號），被告就被訴事實為有罪之陳述，本院裁定行簡式審判程序，判決如左："
    ],
    "prosecutor_office": [
      "臺灣屏東地方法院檢察署檢察官"
    ],
    "creditors": [

    ],
    "debtors": [

    ],
    "judicial_associate_officer": [

    ]
  },
  "adjudged_at": "2005-01-31",
  "created_at": "2016-02-07 02:10:08",
  "updated_at": "2016-02-07 02:10:08"
}