{
  "identify": "SCD-94-竹交簡-69-20050131-1",
  "court": {
    "name": "臺灣新竹地方法院",
    "code": "SCD"
  },
  "division": {
    "name": "刑事",
    "code": "M"
  },
  "year": 94,
  "word": "竹交簡",
  "number": "69",
  "jcheck": "1",
  "reason": "公共危險",
  "content": "臺灣新竹地方法院刑事簡易判決        94年度竹交簡字第69號\n聲  請  人  臺灣新竹地方法院檢察署檢察官\n被      告  甲○○  男  31歲.\n上列被告因公共危險案件，經檢察官聲請簡易判決處刑（93年度\n速偵字第1187號），本院判決如下：\n     主  文\n甲○○服用酒類，不能安全駕駛動力交通工具而駕駛，處拘役伍\n拾日，如易科罰金，以佰元折算壹日。緩刑貳年。\n     事  實  及  理  由\n一、本院認定被告甲○○之犯罪事實、證據及應適用之法條，除\n    犯罪事實欄第5行至第6行「當場為警攔檢查獲」應補充並更\n    正為「以140公里之時速超速行駛，為警方攔檢」外，餘檢\n    察官聲請簡易判決處刑書之記載相同，茲引用之（如附件）\n    。\n二、爰審酌被告無何前科之素行、酒醉駕駛自用小客車超速行駛\n    高速公路，嚴重危害高速公路用路人之安全、酒醉程度不高\n    、酒醉駕車，幸未肇事波及其他用路人及坦認犯行之犯罪後\n    態度等一切情狀，量處如主文所示之刑，並諭知易科罰金之\n    折算標準。\n三、被告未曾受有期徒刑以上刑之宣告，有臺灣新竹地方法院檢\n    察署刑案資料查註紀錄表及臺灣高等法院被告前案紀錄表各\n    一紙在卷可證，其經此次偵、審程序及刑之宣告，當知所警\n    惕，無再犯之虞，本院綜核各情認上開拘役刑之宣告，已足\n    策其自新，所宣告之刑，以暫不執行為適當，併依法諭知緩\n    刑二年，以啟向上。\n四、依刑事訴訟法第449條第1項前段、第452條第2項，刑法第18\n    5條之3、第41條第1項前段、第74條第1款，罰金罰鍰提高標\n    準條例第2條，逕以簡易判決量處如主文所示之刑。\n五、如不服本判決，應於判決送達後10日內，向本院提出上訴狀\n    。\n中    華    民    國    94    年    1     月    31    日\n                  刑事第六庭  法  官  林昌義\n以上正本證明與原本無異。\n                              書記官  黃旭淑\n中    華    民    國    94    年    1     月    31    日\n刑法第185條之3\n服用毒品、麻醉藥品、酒類或其他相類似之物，不能安全駕駛動\n力交通工具而駕駛者，處一年以下有期徒刑、拘役或30,000元以\n下罰金。\n",
  "structure": {
    "main": "甲○○服用酒類，不能安全駕駛動力交通工具而駕駛，處拘役伍\n拾日，如易科罰金，以佰元折算壹日。緩刑貳年。\n     事  實  及  理  由\n一、本院認定被告甲○○之犯罪事實、證據及應適用之法條，除",
    "fact": "一、本院認定被告甲○○之犯罪事實、證據及應適用之法條，除\n    犯罪事實欄第5行至第6行「當場為警攔檢查獲」應補充並更\n    正為「以140公里之時速超速行駛，為警方攔檢」外，餘檢\n    察官聲請簡易判決處刑書之記載相同，茲引用之（如附件）\n    。\n二、爰審酌被告無何前科之素行、酒醉駕駛自用小客車超速行駛\n    高速公路，嚴重危害高速公路用路人之安全、酒醉程度不高\n    、酒醉駕車，幸未肇事波及其他用路人及坦認犯行之犯罪後\n    態度等一切情狀，量處如主文所示之刑，並諭知易科罰金之\n    折算標準。\n三、被告未曾受有期徒刑以上刑之宣告，有臺灣新竹地方法院檢\n    察署刑案資料查註紀錄表及臺灣高等法院被告前案紀錄表各\n    一紙在卷可證，其經此次偵、審程序及刑之宣告，當知所警\n    惕，無再犯之虞，本院綜核各情認上開拘役刑之宣告，已足\n    策其自新，所宣告之刑，以暫不執行為適當，併依法諭知緩\n    刑二年，以啟向上。\n四、依刑事訴訟法第449條第1項前段、第452條第2項，刑法第18\n    5條之3、第41條第1項前段、第74條第1款，罰金罰鍰提高標\n    準條例第2條，逕以簡易判決量處如主文所示之刑。\n五、如不服本判決，應於判決送達後10日內，向本院提出上訴狀\n    。"
  },
  "search": "臺灣新竹地方法院刑事簡易判決94年度竹交簡字第69號聲請人臺灣新竹地方法院檢察署檢察官被告甲○○男31歲.上列被告因公共危險案件，經檢察官聲請簡易判決處刑（93年度速偵字第1187號），本院判決如下：主文甲○○服用酒類，不能安全駕駛動力交通工具而駕駛，處拘役伍拾日，如易科罰金，以佰元折算壹日。緩刑貳年。事實及理由一、本院認定被告甲○○之犯罪事實、證據及應適用之法條，除犯罪事實欄第5行至第6行「當場為警攔檢查獲」應補充並更正為「以140公里之時速超速行駛，為警方攔檢」外，餘檢察官聲請簡易判決處刑書之記載相同，茲引用之（如附件）。二、爰審酌被告無何前科之素行、酒醉駕駛自用小客車超速行駛高速公路，嚴重危害高速公路用路人之安全、酒醉程度不高、酒醉駕車，幸未肇事波及其他用路人及坦認犯行之犯罪後態度等一切情狀，量處如主文所示之刑，並諭知易科罰金之折算標準。三、被告未曾受有期徒刑以上刑之宣告，有臺灣新竹地方法院檢察署刑案資料查註紀錄表及臺灣高等法院被告前案紀錄表各一紙在卷可證，其經此次偵、審程序及刑之宣告，當知所警惕，無再犯之虞，本院綜核各情認上開拘役刑之宣告，已足策其自新，所宣告之刑，以暫不執行為適當，併依法諭知緩刑二年，以啟向上。四、依刑事訴訟法第449條第1項前段、第452條第2項，刑法第185條之3、第41條第1項前段、第74條第1款，罰金罰鍰提高標準條例第2條，逕以簡易判決量處如主文所示之刑。五、如不服本判決，應於判決送達後10日內，向本院提出上訴狀。中華民國94年1月31日刑事第六庭法官林昌義以上正本證明與原本無異。書記官黃旭淑中華民國94年1月31日刑法第185條之3服用毒品、麻醉藥品、酒類或其他相類似之物，不能安全駕駛動力交通工具而駕駛者，處一年以下有期徒刑、拘役或30,000元以下罰金。",
  "characters": {
    "judges": [
      "林昌義"
    ],
    "prosecutors": [

    ],
    "lawyers": [

    ],
    "clerks": [
      "黃旭淑"
    ],
    "plaintiffs": [

    ],
    "defendants": [
      "甲○○  男  31歲."
    ],
    "prosecutor_office": [
      "臺灣新竹地方法院檢察署檢察官"
    ],
    "creditors": [

    ],
    "debtors": [

    ],
    "judicial_associate_officer": [

    ]
  },
  "adjudged_at": "2005-01-31",
  "created_at": "2016-02-07 02:11:39",
  "updated_at": "2016-02-07 02:11:39"
}