{
  "identify": "SLD-93-訴-1247-20050131-1",
  "court": {
    "name": "臺灣士林地方法院",
    "code": "SLD"
  },
  "division": {
    "name": "民事",
    "code": "V"
  },
  "year": 93,
  "word": "訴",
  "number": "1247",
  "jcheck": "1",
  "reason": "清償信用卡消費款",
  "content": "臺灣士林地方法院民事判決              93年度訴字第1247號\n原      告  台北富邦商業銀行股份有限公司\n法定代理人  丁予康\n訴訟代理人  甲○○\n被      告  乙○○\n上列當事人間請求清償信用卡消費款事件，本院於民國94年1 月\n19 日 言詞辯論終結，判決如下：\n    主  文\n被告應給付原告新台幣伍拾萬壹仟柒佰貳拾貳元，及其中新台\n幣伍拾萬仟捌佰伍拾伍元部份，自民國九十三年十一月四日起\n至清償日止，按年息百分之十九點六九計算之利息，暨按上開利\n息百分之十計算之違約金。\n訴訟費用由被告負擔。\n    事實及理由\n甲、程序方面：\n一、本件原告名稱原為富邦商業銀行股份有限公司，因於94年1\n    月1 日與台北銀行股份有限公司（下稱台北銀行）合併，存\n    續銀行台北銀行並更名為台北富邦商業銀行股份有限公司，\n    有經濟部函暨該公司變更登記表影本在卷可稽，是由合併後\n    存續之台北富邦商業銀行股份有限公司（法定代理人丁予康\n    ）聲明承受訴訟，自屬合法，合先敘明。\n二、本件被告未於言詞辯論期日到場，核無民事訴訟法第386 條\n    各款所列情形，爰依原告之聲請，由其一造辯論而為判決。\n三、兩造於信用卡約定條款第27條約定「甲方（指持卡人）及其\n    連帶保證人不履行本約定條款致涉訟時同意以臺灣士林地方\n    法院或臺灣士林地方法院內湖簡易庭為第一審管轄法院。但\n    ：：」之內容，依民事訴訟法第24條規定，本院就本件訴訟\n    自有管轄權，應予敘明。\n乙、實體方面：\n一、原告起訴主張：被告於民國（下同）92年8 月21日與原告訂\n    立信用卡使用契約，申領原告發行之信用卡（卡號00000000\n    00000000），依約被告得持卡至特約商店記帳消費，而應於\n    當期繳款截止日前向原告清償全部之消費款，或以循環信用\n    方式繳付最低應繳金額，逾期逾期清償者，除喪失期限利益\n    外，應另給付原告按年息19.69%計算之利息，另按上開利息\n    加計10% 之違約金。而被告領用信用卡後，於特約商店簽帳\n    消費，至93年10月18日止，尚積欠消費帳款503, 855元、手\n    續費1,350 元及循環息、延滯息26,517元，共計531,722 元\n    ，即未給付，為此，依信用卡使用契約關係提起本訴，聲明\n    求為判決命被告給付531,722 元，及其中503,85 5元部份，\n    自93年11月4 日（即最後繳款期限翌日）起至清償日止，按\n    年息19.69%計算之利息，暨按上開利息10% 計算之違約金等\n    語。\n二、被告則經合法通知未到場，亦未提出書狀作何聲明或陳述。\n三、原告主張前揭事實，業據其提出信用卡申請書、約定條款、\n    對帳單資料查詢、信用卡客戶滯納消費款明細資料、滯納費\n    用款明細資料及滯納利息款明細資料各一份為證，核屬相符\n    ，被告經合法通知未到場，亦未提出書狀爭執，依上開證據\n    ，堪信原告之主張為真正。\n四、從而，原告依信用卡使用契約關係，請求被告給付531,722\n    元，及其中503,855 元部份，自93年11月4 日起至清償日止\n    ，按年息19.69%計算之利息，暨按上開利息10% 計算之違約\n    金，為有理由，應予准許。\n丙、據上論結，原告之訴為有理由，依民事訴訟法第385 條第1\n    項前段、第78條，判決如主文。\n中    華    民    國    94    年    1     月    31    日\n                  民事第二庭  法  官  施月燿\n以上正本證明與原本無異。\n如對本判決上訴須於判決送達後20日內向本院提出上訴狀。\n中    華    民    國    94    年    2     月     2    日\n                              書記官  韓金發\n",
  "structure": {
    "main": "被告應給付原告新台幣伍拾萬壹仟柒佰貳拾貳元，及其中新台\n幣伍拾萬仟捌佰伍拾伍元部份，自民國九十三年十一月四日起\n至清償日止，按年息百分之十九點六九計算之利息，暨按上開利\n息百分之十計算之違約金。\n訴訟費用由被告負擔。",
    "fact": "甲、程序方面：\n一、本件原告名稱原為富邦商業銀行股份有限公司，因於94年1\n    月1 日與台北銀行股份有限公司（下稱台北銀行）合併，存\n    續銀行台北銀行並更名為台北富邦商業銀行股份有限公司，\n    有經濟部函暨該公司變更登記表影本在卷可稽，是由合併後\n    存續之台北富邦商業銀行股份有限公司（法定代理人丁予康\n    ）聲明承受訴訟，自屬合法，合先敘明。\n二、本件被告未於言詞辯論期日到場，核無民事訴訟法第386 條\n    各款所列情形，爰依原告之聲請，由其一造辯論而為判決。\n三、兩造於信用卡約定條款第27條約定「甲方（指持卡人）及其\n    連帶保證人不履行本約定條款致涉訟時同意以臺灣士林地方\n    法院或臺灣士林地方法院內湖簡易庭為第一審管轄法院。但\n    ：：」之內容，依民事訴訟法第24條規定，本院就本件訴訟\n    自有管轄權，應予敘明。\n乙、實體方面：\n一、原告起訴主張：被告於民國（下同）92年8 月21日與原告訂\n    立信用卡使用契約，申領原告發行之信用卡（卡號00000000\n    00000000），依約被告得持卡至特約商店記帳消費，而應於\n    當期繳款截止日前向原告清償全部之消費款，或以循環信用\n    方式繳付最低應繳金額，逾期逾期清償者，除喪失期限利益\n    外，應另給付原告按年息19.69%計算之利息，另按上開利息\n    加計10% 之違約金。而被告領用信用卡後，於特約商店簽帳\n    消費，至93年10月18日止，尚積欠消費帳款503, 855元、手\n    續費1,350 元及循環息、延滯息26,517元，共計531,722 元\n    ，即未給付，為此，依信用卡使用契約關係提起本訴，聲明\n    求為判決命被告給付531,722 元，及其中503,85 5元部份，\n    自93年11月4 日（即最後繳款期限翌日）起至清償日止，按\n    年息19.69%計算之利息，暨按上開利息10% 計算之違約金等\n    語。\n二、被告則經合法通知未到場，亦未提出書狀作何聲明或陳述。\n三、原告主張前揭事實，業據其提出信用卡申請書、約定條款、\n    對帳單資料查詢、信用卡客戶滯納消費款明細資料、滯納費\n    用款明細資料及滯納利息款明細資料各一份為證，核屬相符\n    ，被告經合法通知未到場，亦未提出書狀爭執，依上開證據\n    ，堪信原告之主張為真正。\n四、從而，原告依信用卡使用契約關係，請求被告給付531,722\n    元，及其中503,855 元部份，自93年11月4 日起至清償日止\n    ，按年息19.69%計算之利息，暨按上開利息10% 計算之違約\n    金，為有理由，應予准許。\n丙、據上論結，原告之訴為有理由，依民事訴訟法第385 條第1\n    項前段、第78條，判決如主文。",
    "reason": "甲、程序方面：\n一、本件原告名稱原為富邦商業銀行股份有限公司，因於94年1\n    月1 日與台北銀行股份有限公司（下稱台北銀行）合併，存\n    續銀行台北銀行並更名為台北富邦商業銀行股份有限公司，\n    有經濟部函暨該公司變更登記表影本在卷可稽，是由合併後\n    存續之台北富邦商業銀行股份有限公司（法定代理人丁予康\n    ）聲明承受訴訟，自屬合法，合先敘明。\n二、本件被告未於言詞辯論期日到場，核無民事訴訟法第386 條\n    各款所列情形，爰依原告之聲請，由其一造辯論而為判決。\n三、兩造於信用卡約定條款第27條約定「甲方（指持卡人）及其\n    連帶保證人不履行本約定條款致涉訟時同意以臺灣士林地方\n    法院或臺灣士林地方法院內湖簡易庭為第一審管轄法院。但\n    ：：」之內容，依民事訴訟法第24條規定，本院就本件訴訟\n    自有管轄權，應予敘明。\n乙、實體方面：\n一、原告起訴主張：被告於民國（下同）92年8 月21日與原告訂\n    立信用卡使用契約，申領原告發行之信用卡（卡號00000000\n    00000000），依約被告得持卡至特約商店記帳消費，而應於\n    當期繳款截止日前向原告清償全部之消費款，或以循環信用\n    方式繳付最低應繳金額，逾期逾期清償者，除喪失期限利益\n    外，應另給付原告按年息19.69%計算之利息，另按上開利息\n    加計10% 之違約金。而被告領用信用卡後，於特約商店簽帳\n    消費，至93年10月18日止，尚積欠消費帳款503, 855元、手\n    續費1,350 元及循環息、延滯息26,517元，共計531,722 元\n    ，即未給付，為此，依信用卡使用契約關係提起本訴，聲明\n    求為判決命被告給付531,722 元，及其中503,85 5元部份，\n    自93年11月4 日（即最後繳款期限翌日）起至清償日止，按\n    年息19.69%計算之利息，暨按上開利息10% 計算之違約金等\n    語。\n二、被告則經合法通知未到場，亦未提出書狀作何聲明或陳述。\n三、原告主張前揭事實，業據其提出信用卡申請書、約定條款、\n    對帳單資料查詢、信用卡客戶滯納消費款明細資料、滯納費\n    用款明細資料及滯納利息款明細資料各一份為證，核屬相符\n    ，被告經合法通知未到場，亦未提出書狀爭執，依上開證據\n    ，堪信原告之主張為真正。\n四、從而，原告依信用卡使用契約關係，請求被告給付531,722\n    元，及其中503,855 元部份，自93年11月4 日起至清償日止\n    ，按年息19.69%計算之利息，暨按上開利息10% 計算之違約\n    金，為有理由，應予准許。\n丙、據上論結，原告之訴為有理由，依民事訴訟法第385 條第1\n    項前段、第78條，判決如主文。"
  },
  "search": "臺灣士林地方法院民事判決93年度訴字第1247號原告台北富邦商業銀行股份有限公司法定代理人丁予康訴訟代理人甲○○被告乙○○上列當事人間請求清償信用卡消費款事件，本院於民國94年1月19日言詞辯論終結，判決如下：主文被告應給付原告新台幣伍拾萬壹仟柒佰貳拾貳元，及其中新台幣伍拾萬仟捌佰伍拾伍元部份，自民國九十三年十一月四日起至清償日止，按年息百分之十九點六九計算之利息，暨按上開利息百分之十計算之違約金。訴訟費用由被告負擔。事實及理由甲、程序方面：一、本件原告名稱原為富邦商業銀行股份有限公司，因於94年1月1日與台北銀行股份有限公司（下稱台北銀行）合併，存續銀行台北銀行並更名為台北富邦商業銀行股份有限公司，有經濟部函暨該公司變更登記表影本在卷可稽，是由合併後存續之台北富邦商業銀行股份有限公司（法定代理人丁予康）聲明承受訴訟，自屬合法，合先敘明。二、本件被告未於言詞辯論期日到場，核無民事訴訟法第386條各款所列情形，爰依原告之聲請，由其一造辯論而為判決。三、兩造於信用卡約定條款第27條約定「甲方（指持卡人）及其連帶保證人不履行本約定條款致涉訟時同意以臺灣士林地方法院或臺灣士林地方法院內湖簡易庭為第一審管轄法院。但：：」之內容，依民事訴訟法第24條規定，本院就本件訴訟自有管轄權，應予敘明。乙、實體方面：一、原告起訴主張：被告於民國（下同）92年8月21日與原告訂立信用卡使用契約，申領原告發行之信用卡（卡號0000000000000000），依約被告得持卡至特約商店記帳消費，而應於當期繳款截止日前向原告清償全部之消費款，或以循環信用方式繳付最低應繳金額，逾期逾期清償者，除喪失期限利益外，應另給付原告按年息19.69%計算之利息，另按上開利息加計10%之違約金。而被告領用信用卡後，於特約商店簽帳消費，至93年10月18日止，尚積欠消費帳款503,855元、手續費1,350元及循環息、延滯息26,517元，共計531,722元，即未給付，為此，依信用卡使用契約關係提起本訴，聲明求為判決命被告給付531,722元，及其中503,855元部份，自93年11月4日（即最後繳款期限翌日）起至清償日止，按年息19.69%計算之利息，暨按上開利息10%計算之違約金等語。二、被告則經合法通知未到場，亦未提出書狀作何聲明或陳述。三、原告主張前揭事實，業據其提出信用卡申請書、約定條款、對帳單資料查詢、信用卡客戶滯納消費款明細資料、滯納費用款明細資料及滯納利息款明細資料各一份為證，核屬相符，被告經合法通知未到場，亦未提出書狀爭執，依上開證據，堪信原告之主張為真正。四、從而，原告依信用卡使用契約關係，請求被告給付531,722元，及其中503,855元部份，自93年11月4日起至清償日止，按年息19.69%計算之利息，暨按上開利息10%計算之違約金，為有理由，應予准許。丙、據上論結，原告之訴為有理由，依民事訴訟法第385條第1項前段、第78條，判決如主文。中華民國94年1月31日民事第二庭法官施月燿以上正本證明與原本無異。如對本判決上訴須於判決送達後20日內向本院提出上訴狀。中華民國94年2月2日書記官韓金發",
  "characters": {
    "judges": [
      "施月燿"
    ],
    "prosecutors": [

    ],
    "lawyers": [

    ],
    "clerks": [
      "韓金發"
    ],
    "plaintiffs": [
      "台北富邦商業銀行股份有限公司"
    ],
    "defendants": [
      "乙○○"
    ],
    "prosecutor_office": [

    ],
    "creditors": [

    ],
    "debtors": [

    ],
    "judicial_associate_officer": [

    ]
  },
  "adjudged_at": "2005-01-31",
  "created_at": "2016-02-07 02:11:18",
  "updated_at": "2016-02-07 02:11:18"
}