{
  "identify": "TPD-94-附民緝-3-20050131-1",
  "court": {
    "name": "臺灣臺北地方法院",
    "code": "TPD"
  },
  "division": {
    "name": "刑事",
    "code": "M"
  },
  "year": 94,
  "word": "附民緝",
  "number": "3",
  "jcheck": "1",
  "reason": "因竊盜案附帶民訴",
  "content": "臺灣臺北地方法院刑事附帶民事訴訟判決  94年度附民緝字第3號\n原      告  乙○○\n被      告  甲○○\n上列被告因本院94年度易緝字第4號竊盜案件，經原告提起附帶\n民事訴訟，本院判決如下：\n    主  文\n原告之訴及假執行之聲請均駁回。\n    事  實\n一、原告訴之聲明及陳述如附件刑事附帶民事起訴狀影本所示。\n二、被告未為任何聲明或陳述，亦未提出任何書狀。\n    理  由\n一、按刑事訴訟諭知免訴之判決者，對於附帶民事訴訟部分應以\n    判決駁回原告之訴，刑事訴訟法第503條第1項前段定有明文\n    。\n二、本件被告甲○○被訴竊盜一案，業經本院刑事判決諭知被告\n    免訴，揆諸上開說明，原告之訴，自應予以駁回，其假執行\n    之聲請，亦失所附麗，應併予駁回。\n三、據上論結，依刑事訴訟法第503 條第1 項前段，判決如主文\n    。\n中    華    民    國    94    年    1     月    31    日\n                  刑事第五庭  審判長法  官  黃程暉\n                                    法  官  高偉文\n                                    法  官  李宜娟\n以上正本證明與原本無異。\n對於本判決如不服，非對刑事判決上訴時不得上訴，並應於送達\n後10日內向本院提出上訴狀。\n                                    書記官  游秀珠\n中    華    民    國    94    年    2     月    17    日\n",
  "structure": {
    "main": "原告之訴及假執行之聲請均駁回。",
    "fact": "一、原告訴之聲明及陳述如附件刑事附帶民事起訴狀影本所示。\n二、被告未為任何聲明或陳述，亦未提出任何書狀。",
    "reason": "一、按刑事訴訟諭知免訴之判決者，對於附帶民事訴訟部分應以\n    判決駁回原告之訴，刑事訴訟法第503條第1項前段定有明文\n    。\n二、本件被告甲○○被訴竊盜一案，業經本院刑事判決諭知被告\n    免訴，揆諸上開說明，原告之訴，自應予以駁回，其假執行\n    之聲請，亦失所附麗，應併予駁回。\n三、據上論結，依刑事訴訟法第503 條第1 項前段，判決如主文\n    。\n中    華    民    國    94    年    1     月    31    日\n                  刑事第五庭  審判長法  官  黃程暉\n                                    法  官  高偉文\n                                    法  官  李宜娟\n以上正本證明與原本無異。\n對於本判決如不服，非對刑事判決上訴時不得上訴，並應於送達\n後10日內向本院提出上訴狀。\n                                    書記官  游秀珠"
  },
  "search": "臺灣臺北地方法院刑事附帶民事訴訟判決94年度附民緝字第3號原告乙○○被告甲○○上列被告因本院94年度易緝字第4號竊盜案件，經原告提起附帶民事訴訟，本院判決如下：主文原告之訴及假執行之聲請均駁回。事實一、原告訴之聲明及陳述如附件刑事附帶民事起訴狀影本所示。二、被告未為任何聲明或陳述，亦未提出任何書狀。理由一、按刑事訴訟諭知免訴之判決者，對於附帶民事訴訟部分應以判決駁回原告之訴，刑事訴訟法第503條第1項前段定有明文。二、本件被告甲○○被訴竊盜一案，業經本院刑事判決諭知被告免訴，揆諸上開說明，原告之訴，自應予以駁回，其假執行之聲請，亦失所附麗，應併予駁回。三、據上論結，依刑事訴訟法第503條第1項前段，判決如主文。中華民國94年1月31日刑事第五庭審判長法官黃程暉法官高偉文法官李宜娟以上正本證明與原本無異。對於本判決如不服，非對刑事判決上訴時不得上訴，並應於送達後10日內向本院提出上訴狀。書記官游秀珠中華民國94年2月17日",
  "characters": {
    "judges": [
      "黃程暉",
      "高偉文",
      "李宜娟"
    ],
    "prosecutors": [

    ],
    "lawyers": [

    ],
    "clerks": [
      "游秀珠"
    ],
    "plaintiffs": [
      "乙○○"
    ],
    "defendants": [
      "甲○○"
    ],
    "prosecutor_office": [

    ],
    "creditors": [

    ],
    "debtors": [

    ],
    "judicial_associate_officer": [

    ]
  },
  "adjudged_at": "2005-01-31",
  "created_at": "2016-02-07 02:04:06",
  "updated_at": "2016-02-07 02:04:06"
}