{
  "identify": "TPD-94-訴-118-20050131-1",
  "court": {
    "name": "臺灣臺北地方法院",
    "code": "TPD"
  },
  "division": {
    "name": "民事",
    "code": "V"
  },
  "year": 94,
  "word": "訴",
  "number": "118",
  "jcheck": "1",
  "reason": "給付信用卡消費款",
  "content": "臺灣臺北地方法院民事判決      九十四年度訴字第一一八號\n    原      告  國泰世華商業銀行股份有限公司\n    法定代理人  甲○○\n    訴訟代理人  乙○○\n    被      告  丙○○\n右當事人間給付信用卡消費款事件，本院於民國九十四年一月二\n十七日辯論終結，判決如左：\n    主  文\n被告應給付原告新台幣伍拾壹萬玖仟貳佰貳拾伍元，及其中本金\n肆拾捌萬玖仟佰伍拾壹元部分自民國九十三年十一月二十四日\n起至清償日止，按年息百分之十九點七計算之利息。\n訴訟費用由被告負擔。\n    事實及理由\n甲、程序方面：\n本件被告未於言詞辯論期日到場，核無民事訴訟法第 386條所列\n各款情形，應依原告之聲請，由其一造辯論而為判決。\n乙、實體方面：\n一、本件原告主張被告於民國90年11月2日、91年3月25日、92年\n    3月6日、 92年4月23日與原告成立信用卡使用契約，領用信\n    用卡，依約被告就使用系爭信用卡所生之債務，負全部給付\n    之責，被告領用系爭信用卡後，即得於各特約商店記帳消費\n    ，依信用卡約定條款第14、15條之約定，應於當期繳款截止\n    日前向原告全部清償，或以循環信用方式繳付最低應繳金額\n    ，逾期清償者，依信用卡約定條款第15、21、22條之約定，\n    除喪失期限利益外，應另行給付債權人按年息百分之19點7\n    計算之利息。\n二、另被告於 91年3月26日與原告約定以代償卡由原告代付其於\n    台新國際商業銀行信用卡中心之信用卡欠款，就該代償部分\n    之利息及費用，計收方式係以代償後前6個月以年息百分之6\n    點 4計收利息，後一年以年息百分之14點97計收利息（手續\n    費為前 12個月按月收取新台幣110元，提前清償者仍須一次\n    繳足代償手續費），上述期滿則以年息百分之 19點7計算收\n    利息。\n三、被告另於92年3月6日與原告成立簡易通信貸款契約，向原告\n    貸款16萬元，按年息百分之18點5計算之利息，約定分5年共\n    60期清償，依年金法按月計付本息，併入信用卡帳單中與信\n    用卡帳款一同繳納，依約定條款第 1條之約定，如未依約於\n    繳款期限前繳款或未繳足月付金時，原告得將未繳金額本金\n    部分，或視為到期之本金部分，按信用卡循環利率 19點7計\n    算之利息。依約定條款第4、5條之約定，倘遲延繳款，除喪\n    失期限利益外，視同全部到期。\n四、被告至93年11月23日止，帳款尚餘51萬9千2百25元未按期繳\n    付，迭經催討無效。爰依信用卡契約之法律關係，請求被告\n    給付如主文第一項所示等情，業據提出債權明細表、信用卡\n    申請書、信用卡約定條款、代償卡申請書、代償卡約定條款\n    、帳單影本（被告未於言詞辯論期日到場，亦未提出書狀供\n    本院審酌），堪信為真實。\n五、從而原告依信用卡契約之法律關係，請求被告給付如主文第\n    一項所示，為有理由，應予准許。\n丙、結論：\n    本件原告之訴為有理由，依民事訴訟法第385條第1項前段、\n    第78條，判決如主文。\n中   華   民    國    九十四  年    一    月  三十一  日\n                          民事第二庭  法  官  楊代華\n以上正本係照原本作成。\n如對本判決上訴，須於判決送達後廿日內向本院提出上訴狀。\n中   華   民    國    九十四  年    一    月  三十一  日\n                                  法院書記官  劉碧輝\n",
  "structure": {
    "main": "被告應給付原告新台幣伍拾壹萬玖仟貳佰貳拾伍元，及其中本金\n肆拾捌萬玖仟佰伍拾壹元部分自民國九十三年十一月二十四日\n起至清償日止，按年息百分之十九點七計算之利息。\n訴訟費用由被告負擔。",
    "fact": "甲、程序方面：\n本件被告未於言詞辯論期日到場，核無民事訴訟法第 386條所列\n各款情形，應依原告之聲請，由其一造辯論而為判決。\n乙、實體方面：\n一、本件原告主張被告於民國90年11月2日、91年3月25日、92年\n    3月6日、 92年4月23日與原告成立信用卡使用契約，領用信\n    用卡，依約被告就使用系爭信用卡所生之債務，負全部給付\n    之責，被告領用系爭信用卡後，即得於各特約商店記帳消費\n    ，依信用卡約定條款第14、15條之約定，應於當期繳款截止\n    日前向原告全部清償，或以循環信用方式繳付最低應繳金額\n    ，逾期清償者，依信用卡約定條款第15、21、22條之約定，\n    除喪失期限利益外，應另行給付債權人按年息百分之19點7\n    計算之利息。\n二、另被告於 91年3月26日與原告約定以代償卡由原告代付其於\n    台新國際商業銀行信用卡中心之信用卡欠款，就該代償部分\n    之利息及費用，計收方式係以代償後前6個月以年息百分之6\n    點 4計收利息，後一年以年息百分之14點97計收利息（手續\n    費為前 12個月按月收取新台幣110元，提前清償者仍須一次\n    繳足代償手續費），上述期滿則以年息百分之 19點7計算收\n    利息。\n三、被告另於92年3月6日與原告成立簡易通信貸款契約，向原告\n    貸款16萬元，按年息百分之18點5計算之利息，約定分5年共\n    60期清償，依年金法按月計付本息，併入信用卡帳單中與信\n    用卡帳款一同繳納，依約定條款第 1條之約定，如未依約於\n    繳款期限前繳款或未繳足月付金時，原告得將未繳金額本金\n    部分，或視為到期之本金部分，按信用卡循環利率 19點7計\n    算之利息。依約定條款第4、5條之約定，倘遲延繳款，除喪\n    失期限利益外，視同全部到期。\n四、被告至93年11月23日止，帳款尚餘51萬9千2百25元未按期繳\n    付，迭經催討無效。爰依信用卡契約之法律關係，請求被告\n    給付如主文第一項所示等情，業據提出債權明細表、信用卡\n    申請書、信用卡約定條款、代償卡申請書、代償卡約定條款\n    、帳單影本（被告未於言詞辯論期日到場，亦未提出書狀供\n    本院審酌），堪信為真實。\n五、從而原告依信用卡契約之法律關係，請求被告給付如主文第\n    一項所示，為有理由，應予准許。\n丙、結論：\n    本件原告之訴為有理由，依民事訴訟法第385條第1項前段、\n    第78條，判決如主文。",
    "reason": "甲、程序方面：\n本件被告未於言詞辯論期日到場，核無民事訴訟法第 386條所列\n各款情形，應依原告之聲請，由其一造辯論而為判決。\n乙、實體方面：\n一、本件原告主張被告於民國90年11月2日、91年3月25日、92年\n    3月6日、 92年4月23日與原告成立信用卡使用契約，領用信\n    用卡，依約被告就使用系爭信用卡所生之債務，負全部給付\n    之責，被告領用系爭信用卡後，即得於各特約商店記帳消費\n    ，依信用卡約定條款第14、15條之約定，應於當期繳款截止\n    日前向原告全部清償，或以循環信用方式繳付最低應繳金額\n    ，逾期清償者，依信用卡約定條款第15、21、22條之約定，\n    除喪失期限利益外，應另行給付債權人按年息百分之19點7\n    計算之利息。\n二、另被告於 91年3月26日與原告約定以代償卡由原告代付其於\n    台新國際商業銀行信用卡中心之信用卡欠款，就該代償部分\n    之利息及費用，計收方式係以代償後前6個月以年息百分之6\n    點 4計收利息，後一年以年息百分之14點97計收利息（手續\n    費為前 12個月按月收取新台幣110元，提前清償者仍須一次\n    繳足代償手續費），上述期滿則以年息百分之 19點7計算收\n    利息。\n三、被告另於92年3月6日與原告成立簡易通信貸款契約，向原告\n    貸款16萬元，按年息百分之18點5計算之利息，約定分5年共\n    60期清償，依年金法按月計付本息，併入信用卡帳單中與信\n    用卡帳款一同繳納，依約定條款第 1條之約定，如未依約於\n    繳款期限前繳款或未繳足月付金時，原告得將未繳金額本金\n    部分，或視為到期之本金部分，按信用卡循環利率 19點7計\n    算之利息。依約定條款第4、5條之約定，倘遲延繳款，除喪\n    失期限利益外，視同全部到期。\n四、被告至93年11月23日止，帳款尚餘51萬9千2百25元未按期繳\n    付，迭經催討無效。爰依信用卡契約之法律關係，請求被告\n    給付如主文第一項所示等情，業據提出債權明細表、信用卡\n    申請書、信用卡約定條款、代償卡申請書、代償卡約定條款\n    、帳單影本（被告未於言詞辯論期日到場，亦未提出書狀供\n    本院審酌），堪信為真實。\n五、從而原告依信用卡契約之法律關係，請求被告給付如主文第\n    一項所示，為有理由，應予准許。\n丙、結論：\n    本件原告之訴為有理由，依民事訴訟法第385條第1項前段、\n    第78條，判決如主文。"
  },
  "search": "臺灣臺北地方法院民事判決九十四年度訴字第一一八號原告國泰世華商業銀行股份有限公司法定代理人甲○○訴訟代理人乙○○被告丙○○右當事人間給付信用卡消費款事件，本院於民國九十四年一月二十七日辯論終結，判決如左：主文被告應給付原告新台幣伍拾壹萬玖仟貳佰貳拾伍元，及其中本金肆拾捌萬玖仟佰伍拾壹元部分自民國九十三年十一月二十四日起至清償日止，按年息百分之十九點七計算之利息。訴訟費用由被告負擔。事實及理由甲、程序方面：本件被告未於言詞辯論期日到場，核無民事訴訟法第386條所列各款情形，應依原告之聲請，由其一造辯論而為判決。乙、實體方面：一、本件原告主張被告於民國90年11月2日、91年3月25日、92年3月6日、92年4月23日與原告成立信用卡使用契約，領用信用卡，依約被告就使用系爭信用卡所生之債務，負全部給付之責，被告領用系爭信用卡後，即得於各特約商店記帳消費，依信用卡約定條款第14、15條之約定，應於當期繳款截止日前向原告全部清償，或以循環信用方式繳付最低應繳金額，逾期清償者，依信用卡約定條款第15、21、22條之約定，除喪失期限利益外，應另行給付債權人按年息百分之19點7計算之利息。二、另被告於91年3月26日與原告約定以代償卡由原告代付其於台新國際商業銀行信用卡中心之信用卡欠款，就該代償部分之利息及費用，計收方式係以代償後前6個月以年息百分之6點4計收利息，後一年以年息百分之14點97計收利息（手續費為前12個月按月收取新台幣110元，提前清償者仍須一次繳足代償手續費），上述期滿則以年息百分之19點7計算收利息。三、被告另於92年3月6日與原告成立簡易通信貸款契約，向原告貸款16萬元，按年息百分之18點5計算之利息，約定分5年共60期清償，依年金法按月計付本息，併入信用卡帳單中與信用卡帳款一同繳納，依約定條款第1條之約定，如未依約於繳款期限前繳款或未繳足月付金時，原告得將未繳金額本金部分，或視為到期之本金部分，按信用卡循環利率19點7計算之利息。依約定條款第4、5條之約定，倘遲延繳款，除喪失期限利益外，視同全部到期。四、被告至93年11月23日止，帳款尚餘51萬9千2百25元未按期繳付，迭經催討無效。爰依信用卡契約之法律關係，請求被告給付如主文第一項所示等情，業據提出債權明細表、信用卡申請書、信用卡約定條款、代償卡申請書、代償卡約定條款、帳單影本（被告未於言詞辯論期日到場，亦未提出書狀供本院審酌），堪信為真實。五、從而原告依信用卡契約之法律關係，請求被告給付如主文第一項所示，為有理由，應予准許。丙、結論：本件原告之訴為有理由，依民事訴訟法第385條第1項前段、第78條，判決如主文。中華民國九十四年一月三十一日民事第二庭法官楊代華以上正本係照原本作成。如對本判決上訴，須於判決送達後廿日內向本院提出上訴狀。中華民國九十四年一月三十一日法院書記官劉碧輝",
  "characters": {
    "judges": [
      "楊代華"
    ],
    "prosecutors": [

    ],
    "lawyers": [

    ],
    "clerks": [
      "法院"
    ],
    "plaintiffs": [
      "國泰世華商業銀行股份有限公司"
    ],
    "defendants": [
      "丙○○",
      "右當事人間給付信用卡消費款事件，本院於民國九十四年一月二",
      "十七日辯論終結，判決如左："
    ],
    "prosecutor_office": [

    ],
    "creditors": [

    ],
    "debtors": [

    ],
    "judicial_associate_officer": [

    ]
  },
  "adjudged_at": "2005-01-31",
  "created_at": "2016-02-07 02:03:27",
  "updated_at": "2016-02-07 02:03:27"
}