{
  "identify": "TCD-99-婚-562-20110125-1",
  "court": {
    "name": "臺灣臺中地方法院",
    "code": "TCD"
  },
  "division": {
    "name": "民事",
    "code": "V"
  },
  "year": 99,
  "word": "婚",
  "number": "562",
  "jcheck": "1",
  "reason": "履行同居",
  "content": "臺灣臺中地方法院民事判決               99年度婚字第562號\n原      告  蕭國棟\n被      告  廖翠夢即LIAU-.\n上列當事人間請求履行同居事件，本院於中華民國100年1月6日\n言詞辯論終結，判決如下：\n    主    文\n被告應與原告同居。\n訴訟費用由被告負擔。\n    事實及理由\n甲、程序方面：\n    被告受合法通知，無正當理由，未於言詞辯論期日到場，核\n    無民事訴訟法第386 條所列各款情形，爰依原告之聲請，由\n    其一造辯論而為判決。\n乙、實體方面：\n壹、原告起訴主張：被告為印尼國籍人民，兩造於民國96年8月6\n    日結婚，並約定被告應在臺灣與原告共同生活，且以原告之\n    住所為共同住所，嗣原告在臺灣戶政機關辦妥結婚登記手續\n    ，被告亦於98年7 月18日來臺與原告共同生活。嗣兩造於同\n    年12月8 日前往印尼度蜜月，被告竟於同年月10日不知所蹤\n    ，原告在當地報警後，先行返臺，原告經聯繫被告在臺之母\n    親、胞姐，其等亦不知被告行蹤，此後被告即未曾再入境臺\n    灣，被告拒與原告履行同居生活，顯然違背夫妻同居之義務\n    ，為此提起本件訴訟等語。並聲明：如主文所示。\n貳、被告未於言詞辯論期日到場，亦未提出書狀作何聲明或陳述\n    。\n、得心證之理由：\n一、原告主張被告為印尼國人民，兩造於96年8月6日結婚，約定\n    婚後被告應來臺與原告共同生活，且以原告之住所為共同住\n    所，嗣被告雖來臺與原告共同生活，惟兩造於98年12月8 日\n    前往印尼度蜜月後，被告於同年月10日不知所縱，迄今未曾\n    在入境臺灣等事實，業據其提出警政署證明書影本（含印尼\n    文、中文譯本）、結婚證書影本（含印尼文、中文譯本）、\n    戶籍謄本、被告入出國日期證明書各1 件為證；復經證人即\n    原告之舅舅葉耀堂於本院99年10月5 日行言詞辯論期日到庭\n    證述：伊住在原告家附近，幾乎每天去原告家，兩造結婚的\n    事情，是伊替兩造辦理的，兩造去度蜜月時，被告將一些金\n    飾跟錢都帶走，後來就未與原告一起回來，之後被告也沒有\n    與原告聯絡，伊曾陪同原告道臺中市新社區去找被告的媽媽\n    ，他們也找不到被告等語明確。而觀諸前揭被告入出國日期\n    證明書記載，被告確自98年12月8 日離境迄今，未再入境。\n    是依上開證據所示，堪認原告之主張為真實。\n二、涉外民事事件有關婚姻之效力，依夫之本國法；除有不能同\n    居之正當理由外，夫妻互負同居之義務，涉外民事法律適用\n    法第12條前段、民法第1001條分別定有明文。原告為我國人\n    民，被告則係印尼國人，故本件婚姻效力（履行同居）之準\n    據法應適用我國法律。又被告既與原告約定婚後來臺共同生\n    活，且兩造夫妻關係現仍存續中，除有不能同居之正當理由\n    外，被告應負有與原告同居之義務，被告卻自98年12月10日\n    不知所蹤，迄今未返家，本院復查無任何證據足資證明其有\n    不能履行同居義務之正當情事。從而，原告本於民法第1001\n    條之規定，訴請被告履行同居，為有理由，應予准許。\n丙、訴訟費用負擔之依據：民事訴訟法第78條。\n中    華    民    國   100    年    1     月    25    日\n                  家事法庭      法  官  郭妙俐\n以上正本係照原本作成。\n如對本判決上訴，須於判決送達後20日內向本院提出上訴書狀（\n須附繕本）。\n如委任律師提起上訴者，應一併繳納上訴審裁判費。\n中    華    民    國   100    年    1     月    25    日\n                                 書記官  魏宏銘",
  "structure": {
    "main": "被告應與原告同居。\n訴訟費用由被告負擔。",
    "fact": "甲、程序方面：\n    被告受合法通知，無正當理由，未於言詞辯論期日到場，核\n    無民事訴訟法第386 條所列各款情形，爰依原告之聲請，由\n    其一造辯論而為判決。\n乙、實體方面：\n壹、原告起訴主張：被告為印尼國籍人民，兩造於民國96年8月6\n    日結婚，並約定被告應在臺灣與原告共同生活，且以原告之\n    住所為共同住所，嗣原告在臺灣戶政機關辦妥結婚登記手續\n    ，被告亦於98年7 月18日來臺與原告共同生活。嗣兩造於同\n    年12月8 日前往印尼度蜜月，被告竟於同年月10日不知所蹤\n    ，原告在當地報警後，先行返臺，原告經聯繫被告在臺之母\n    親、胞姐，其等亦不知被告行蹤，此後被告即未曾再入境臺\n    灣，被告拒與原告履行同居生活，顯然違背夫妻同居之義務\n    ，為此提起本件訴訟等語。並聲明：如主文所示。\n貳、被告未於言詞辯論期日到場，亦未提出書狀作何聲明或陳述\n    。\n、得心證之理由：\n一、原告主張被告為印尼國人民，兩造於96年8月6日結婚，約定\n    婚後被告應來臺與原告共同生活，且以原告之住所為共同住\n    所，嗣被告雖來臺與原告共同生活，惟兩造於98年12月8 日\n    前往印尼度蜜月後，被告於同年月10日不知所縱，迄今未曾\n    在入境臺灣等事實，業據其提出警政署證明書影本（含印尼\n    文、中文譯本）、結婚證書影本（含印尼文、中文譯本）、\n    戶籍謄本、被告入出國日期證明書各1 件為證；復經證人即\n    原告之舅舅葉耀堂於本院99年10月5 日行言詞辯論期日到庭\n    證述：伊住在原告家附近，幾乎每天去原告家，兩造結婚的\n    事情，是伊替兩造辦理的，兩造去度蜜月時，被告將一些金\n    飾跟錢都帶走，後來就未與原告一起回來，之後被告也沒有\n    與原告聯絡，伊曾陪同原告道臺中市新社區去找被告的媽媽\n    ，他們也找不到被告等語明確。而觀諸前揭被告入出國日期\n    證明書記載，被告確自98年12月8 日離境迄今，未再入境。\n    是依上開證據所示，堪認原告之主張為真實。\n二、涉外民事事件有關婚姻之效力，依夫之本國法；除有不能同\n    居之正當理由外，夫妻互負同居之義務，涉外民事法律適用\n    法第12條前段、民法第1001條分別定有明文。原告為我國人\n    民，被告則係印尼國人，故本件婚姻效力（履行同居）之準\n    據法應適用我國法律。又被告既與原告約定婚後來臺共同生\n    活，且兩造夫妻關係現仍存續中，除有不能同居之正當理由\n    外，被告應負有與原告同居之義務，被告卻自98年12月10日\n    不知所蹤，迄今未返家，本院復查無任何證據足資證明其有\n    不能履行同居義務之正當情事。從而，原告本於民法第1001\n    條之規定，訴請被告履行同居，為有理由，應予准許。\n丙、訴訟費用負擔之依據：民事訴訟法第78條。",
    "reason": "甲、程序方面：\n    被告受合法通知，無正當理由，未於言詞辯論期日到場，核\n    無民事訴訟法第386 條所列各款情形，爰依原告之聲請，由\n    其一造辯論而為判決。\n乙、實體方面：\n壹、原告起訴主張：被告為印尼國籍人民，兩造於民國96年8月6\n    日結婚，並約定被告應在臺灣與原告共同生活，且以原告之\n    住所為共同住所，嗣原告在臺灣戶政機關辦妥結婚登記手續\n    ，被告亦於98年7 月18日來臺與原告共同生活。嗣兩造於同\n    年12月8 日前往印尼度蜜月，被告竟於同年月10日不知所蹤\n    ，原告在當地報警後，先行返臺，原告經聯繫被告在臺之母\n    親、胞姐，其等亦不知被告行蹤，此後被告即未曾再入境臺\n    灣，被告拒與原告履行同居生活，顯然違背夫妻同居之義務\n    ，為此提起本件訴訟等語。並聲明：如主文所示。\n貳、被告未於言詞辯論期日到場，亦未提出書狀作何聲明或陳述\n    。\n、得心證之理由：\n一、原告主張被告為印尼國人民，兩造於96年8月6日結婚，約定\n    婚後被告應來臺與原告共同生活，且以原告之住所為共同住\n    所，嗣被告雖來臺與原告共同生活，惟兩造於98年12月8 日\n    前往印尼度蜜月後，被告於同年月10日不知所縱，迄今未曾\n    在入境臺灣等事實，業據其提出警政署證明書影本（含印尼\n    文、中文譯本）、結婚證書影本（含印尼文、中文譯本）、\n    戶籍謄本、被告入出國日期證明書各1 件為證；復經證人即\n    原告之舅舅葉耀堂於本院99年10月5 日行言詞辯論期日到庭\n    證述：伊住在原告家附近，幾乎每天去原告家，兩造結婚的\n    事情，是伊替兩造辦理的，兩造去度蜜月時，被告將一些金\n    飾跟錢都帶走，後來就未與原告一起回來，之後被告也沒有\n    與原告聯絡，伊曾陪同原告道臺中市新社區去找被告的媽媽\n    ，他們也找不到被告等語明確。而觀諸前揭被告入出國日期\n    證明書記載，被告確自98年12月8 日離境迄今，未再入境。\n    是依上開證據所示，堪認原告之主張為真實。\n二、涉外民事事件有關婚姻之效力，依夫之本國法；除有不能同\n    居之正當理由外，夫妻互負同居之義務，涉外民事法律適用\n    法第12條前段、民法第1001條分別定有明文。原告為我國人\n    民，被告則係印尼國人，故本件婚姻效力（履行同居）之準\n    據法應適用我國法律。又被告既與原告約定婚後來臺共同生\n    活，且兩造夫妻關係現仍存續中，除有不能同居之正當理由\n    外，被告應負有與原告同居之義務，被告卻自98年12月10日\n    不知所蹤，迄今未返家，本院復查無任何證據足資證明其有\n    不能履行同居義務之正當情事。從而，原告本於民法第1001\n    條之規定，訴請被告履行同居，為有理由，應予准許。\n丙、訴訟費用負擔之依據：民事訴訟法第78條。"
  },
  "search": "臺灣臺中地方法院民事判決99年度婚字第562號原告蕭國棟被告廖翠夢即LIAU-.上列當事人間請求履行同居事件，本院於中華民國100年1月6日言詞辯論終結，判決如下：主文被告應與原告同居。訴訟費用由被告負擔。事實及理由甲、程序方面：被告受合法通知，無正當理由，未於言詞辯論期日到場，核無民事訴訟法第386條所列各款情形，爰依原告之聲請，由其一造辯論而為判決。乙、實體方面：壹、原告起訴主張：被告為印尼國籍人民，兩造於民國96年8月6日結婚，並約定被告應在臺灣與原告共同生活，且以原告之住所為共同住所，嗣原告在臺灣戶政機關辦妥結婚登記手續，被告亦於98年7月18日來臺與原告共同生活。嗣兩造於同年12月8日前往印尼度蜜月，被告竟於同年月10日不知所蹤，原告在當地報警後，先行返臺，原告經聯繫被告在臺之母親、胞姐，其等亦不知被告行蹤，此後被告即未曾再入境臺灣，被告拒與原告履行同居生活，顯然違背夫妻同居之義務，為此提起本件訴訟等語。並聲明：如主文所示。貳、被告未於言詞辯論期日到場，亦未提出書狀作何聲明或陳述。、得心證之理由：一、原告主張被告為印尼國人民，兩造於96年8月6日結婚，約定婚後被告應來臺與原告共同生活，且以原告之住所為共同住所，嗣被告雖來臺與原告共同生活，惟兩造於98年12月8日前往印尼度蜜月後，被告於同年月10日不知所縱，迄今未曾在入境臺灣等事實，業據其提出警政署證明書影本（含印尼文、中文譯本）、結婚證書影本（含印尼文、中文譯本）、戶籍謄本、被告入出國日期證明書各1件為證；復經證人即原告之舅舅葉耀堂於本院99年10月5日行言詞辯論期日到庭證述：伊住在原告家附近，幾乎每天去原告家，兩造結婚的事情，是伊替兩造辦理的，兩造去度蜜月時，被告將一些金飾跟錢都帶走，後來就未與原告一起回來，之後被告也沒有與原告聯絡，伊曾陪同原告道臺中市新社區去找被告的媽媽，他們也找不到被告等語明確。而觀諸前揭被告入出國日期證明書記載，被告確自98年12月8日離境迄今，未再入境。是依上開證據所示，堪認原告之主張為真實。二、涉外民事事件有關婚姻之效力，依夫之本國法；除有不能同居之正當理由外，夫妻互負同居之義務，涉外民事法律適用法第12條前段、民法第1001條分別定有明文。原告為我國人民，被告則係印尼國人，故本件婚姻效力（履行同居）之準據法應適用我國法律。又被告既與原告約定婚後來臺共同生活，且兩造夫妻關係現仍存續中，除有不能同居之正當理由外，被告應負有與原告同居之義務，被告卻自98年12月10日不知所蹤，迄今未返家，本院復查無任何證據足資證明其有不能履行同居義務之正當情事。從而，原告本於民法第1001條之規定，訴請被告履行同居，為有理由，應予准許。丙、訴訟費用負擔之依據：民事訴訟法第78條。中華民國100年1月25日家事法庭法官郭妙俐以上正本係照原本作成。如對本判決上訴，須於判決送達後20日內向本院提出上訴書狀（須附繕本）。如委任律師提起上訴者，應一併繳納上訴審裁判費。中華民國100年1月25日書記官魏宏銘",
  "characters": {
    "judges": [
      "郭妙俐"
    ],
    "prosecutors": [

    ],
    "lawyers": [
      "如委任"
    ],
    "clerks": [

    ],
    "plaintiffs": [
      "蕭國棟"
    ],
    "defendants": [
      "廖翠夢即LIAU-."
    ],
    "prosecutor_office": [

    ],
    "creditors": [

    ],
    "debtors": [

    ],
    "judicial_associate_officer": [

    ]
  },
  "adjudged_at": "2011-01-25",
  "created_at": "2016-02-13 06:28:19",
  "updated_at": "2016-02-13 06:28:19"
}