{
  "identify": "KSH-94-上更(一)-23-20050518-1",
  "court": {
    "name": "臺灣高等法院",
    "code": "KSH"
  },
  "division": {
    "name": "刑事",
    "code": "M"
  },
  "year": 94,
  "word": "上更(一)",
  "number": "23",
  "jcheck": "1",
  "reason": "強盜",
  "content": "臺灣高等法院高雄分院刑事判決      94年度上更(一)字第23號\n    上  訴  人\n    即自 訴 人  甲○○\n                          號\n    代  理  人  侯重信律師\n    被      告  戊○○\n                          號\n                丙○○\n                          號\n                丁○○\n                          4號.\n                乙○○\n                          4號.\n                己○○\n                          號\n    共      同\n    指定辯護人  義務辯護人吳保仁律師\n上列上訴人因被告強盜案件，不服臺灣屏東地方法院90年度自字\n第15號中華民國90年5 月24日第一審判決，提起上訴，經判決後\n，由最高法院發回更審，本院判決如下：\n      主  文\n上訴駁回。\n      理  由\n一、自訴意旨略以：坐落屏東縣枋寮鄉○○段北勢寮小段2331號\n    土地上海福海產攤係自訴人出資購買生財器具所經營，其後\n    出租蘇玉花營業，詎被告戊○○、丙○○、丁○○、乙○○\n    、己○○共同意圖為自己不法之所有，且基於犯意聯絡，推\n    由被告戊○○於民國88年6 月10日上午3 、4 時許，在海福\n    海產攤內，向承租人蘇玉花出言恐嚇稱如不搬走，要將蘇玉\n    花販售東西丟入海中等語，致蘇玉花心生畏懼不能抗拒，而\n    將海福海產攤及生財器具交付被告戊○○，被告戊○○即與\n    被告丙○○、丁○○、乙○○、己○○共同在海福海產攤營\n    業，因認被告5 人共同涉犯加重強盜罪嫌。\n二、自訴人認被告5 人共同涉犯加重強盜罪嫌，係以證人蘇玉花\n    、邱官封之證述及卷附購物收據、繳納土地租金收據、證人\n    委託書（見原審卷第17～31頁、本院卷），資為論據。惟訊\n    據被告5 人均堅詞否認有強盜犯行，被告戊○○辯稱海福海\n    產攤之生財器具均係其出資購買，並無強取他人財物等語，\n    被告丁○○、乙○○辯稱其等係向被告戊○○承租海福海產\n    攤營業，並無與被告戊○○共同強取他人財物等語，被告丙\n    ○○、己○○辯稱其等僅閒暇時偶至海福海產攤幫忙，並無\n    與被告戊○○共同強取他人財物等語。\n三、經查：\n    (一)自訴人主張出資購買海福海產店內之生財器具一節，固據\n      其提出之購物收據、繳納土地租金收據、證人委託書為證\n      （見原審卷第17～37頁、本院卷）。然上開購物收據、繳\n      納土地租金收據、證人委託書分別係個人、公司及商號等\n      第三人製作之私文書，既非屬刑事訴訟法第159 條之4 規\n      定之得為證據文書，且經被告否認證據能力，自訴人提出\n      之上開購物收據、繳納土地租金收據、證人委託書即無證\n      據能力，不得作為證據，先予敘明。\n    (二)自訴人主張出資購買海福海產攤之生財器具之情，已經證\n      人蘇玉花於本院前審結證稱：「‧‧‧我在那裡做的時候\n      ，我看到有人送貨來，都是甲○○付錢的‧‧‧」等語（\n      見本院上訴卷第72頁），證人邱官封於原審及本院亦結證\n      稱：「‧‧‧店裡的生財器具都是被告與自訴人一起去買\n      ，但錢都是自訴人付的‧‧‧」、「‧‧‧後來買餐具是\n      我們與自訴人一起去買，大家一起去看，人家送貨來，都\n      是自訴人付錢。」、「我也做得迷迷糊糊，我原來以為自\n      訴人沒付錢，但後來有人送貨來，我看到是甲○○付錢。\n      」、「（生財器具）都是我和甲○○一起去買的。」、「\n      都甲○○支出。」等語（見原審卷第165 ～166 頁、本院\n      上訴卷第70頁、本院94年5 月4 日言詞辯論筆錄）。另參\n      以被告戊○○於原審曾自白與自訴人合夥經營海福海產攤\n      ，約出資新台幣20 ,000 餘元，負責出買菜及部分器具款\n      項等語（見原審卷第86、106 、162 頁）。互核證人蘇玉\n      花、邱官封之證述及被告戊○○之自白大致相符，足佐自\n      訴人主張出資購買海福海產攤之生財器具，堪以採信。至\n      被告戊○○其後雖改稱海福海產攤之生財器具均係其出資\n      購買，並未與自訴人合夥，自訴人係受僱擔任會計等語。\n      然海福海產攤之生財器具苟係被告戊○○自行出資購買，\n      自訴人並無出資情事，而自訴人竟自訴被告戊○○強取財\n      物犯行，衡諸一般常情，被告戊○○當會義正嚴辭主張自\n      己權益。但觀諸被告戊○○於原審先係陳述自己約出資新\n      台幣（下同）2,000 餘元，其後始改稱自行出資購買海福\n      海產攤生財器具，被告戊○○其後所辯，顯不符常情，難\n      以採取。\n    (三)自訴人指訴被告5 人共同強盜犯行，固據證人蘇玉花迭於\n      原審及本院結證稱被告戊○○有向其恫稱如不搬走，要將\n      其販售之物品丟入海中等語，致其心生畏懼，乃遷離海福\n      海產攤及交還生財器具等語（見原審卷第65頁、本院94年\n      5 月4 日言詞辯論筆錄）。又被告丁○○、乙○○其後向\n      被告戊○○承租將海福海產攤營業，被告丙○○、己○○\n      則偶至海福海產攤幫忙一節，亦經被告5 人不爭執，應堪\n      認定。然依證人蘇玉花證述被告戊○○令其搬遷時，其隨\n      即打電話給自訴人，自訴人到場後表示繼續經營沒有關係\n      ，被告戊○○當時並沒有說話等語（見本院94年5 月4 日\n      言詞辯論筆錄），在客觀上，尚無從認證人蘇玉花係有因\n      被告戊○○之言語，喪失意思自由，致使不能抗拒，而遷\n      離海福海產攤及交還生財器具。再證人即保安宮副董事長\n      沈枝忠於本院已結證稱坐落屏東縣枋寮鄉○○段北勢寮小\n      段2331號土地係國有地而由保安宮管理，被告戊○○曾於\n      87年間與保安宮簽約承租該土地擺攤，且大部分均係被告\n      戊○○繳納租金等語（見本院94年5 月4 日言詞辯論筆錄\n      ），證人即保安宮總幹事吳炳源於本院亦結證稱有收取被\n      告戊○○繳納之租金等語（見本院94年5 月4 日言詞辯論\n      筆錄），是被告戊○○合夥經營海福海產店，即非無據。\n      另證人蘇玉花積欠海福海產攤租金情事，已經證人蘇玉花\n      結證在卷（見本院94年5 月4 日言詞辯論筆錄）。是被告\n      戊○○因證人蘇玉花積欠租金，因而令證人蘇玉花遷離，\n      當時應無為自己不法所有之意圖，被告戊○○之行為亦與\n      恐嚇取財罪之構成要件不符。至被告戊○○其後將海福海\n      產攤出租被告丁○○、乙○○營業，被告戊○○是否涉犯\n      侵占犯行，因非屬自訴人自訴範圍，本院自不得審理。此\n      外，復查無其他積極證據足認被告戊○○、丙○○、丁○\n      ○、乙○○、己○○有強盜或恐嚇取財等犯行，被告5 人\n      之犯罪即屬不能證明。\n    (四)又被告戊○○取回海福海產攤及生財器具，而後出租被告\n      丁○○、乙○○營業，已如前述，被告5 人行為核與竊盜\n      、竊佔之犯罪構成要件尚不相符，且被告戊○○之犯罪既\n      屬不能證明，被告戊○○取得海福海產攤及生財器具，即\n      非因犯罪所得，被告丁○○、乙○○、丙○○、己○○分\n      別承租、幫忙海福海產攤營業行為，自無成立贓物罪之可\n      能。另依證人蘇玉花證述被告戊○○係出言向其恫嚇之情\n      ，被告戊○○自非出言恐嚇自訴人。自訴人就此部分既非\n      犯罪被害人，依法本不得提起自訴，本院即無審酌餘地，\n      均併予敘明。\n四、原審以不能證明被告犯罪，而諭知無罪之判決，核無不合。\n    自訴人上訴意旨，仍執前詞，指摘原判決不當，為無理由，\n    應予駁回。\n據上論結，應依刑事訴訟法第368 條，判決如主文。\n中    華    民    國    94    年    5     月    18    日\n                  刑事第九庭  審判長法    官 張明松\n                                    法    官 任森銓\n                                    法    官 郭玫利\n以上正本證明與原本無異。\n如不服本判決應於收受本判決後10日內向本院提出上訴書狀，其\n未敘述上訴理由者，並得於提起上訴後10日內向本院補提理由書\n狀（均須按他造當事人之人數附繕本）「切勿逕送上級法院」\n中    華    民    國    94    年    5     月    18    日\n                                      書記官 翁心欣\n",
  "structure": {
    "main": "上訴駁回。",
    "reason": "一、自訴意旨略以：坐落屏東縣枋寮鄉○○段北勢寮小段2331號\n    土地上海福海產攤係自訴人出資購買生財器具所經營，其後\n    出租蘇玉花營業，詎被告戊○○、丙○○、丁○○、乙○○\n    、己○○共同意圖為自己不法之所有，且基於犯意聯絡，推\n    由被告戊○○於民國88年6 月10日上午3 、4 時許，在海福\n    海產攤內，向承租人蘇玉花出言恐嚇稱如不搬走，要將蘇玉\n    花販售東西丟入海中等語，致蘇玉花心生畏懼不能抗拒，而\n    將海福海產攤及生財器具交付被告戊○○，被告戊○○即與\n    被告丙○○、丁○○、乙○○、己○○共同在海福海產攤營\n    業，因認被告5 人共同涉犯加重強盜罪嫌。\n二、自訴人認被告5 人共同涉犯加重強盜罪嫌，係以證人蘇玉花\n    、邱官封之證述及卷附購物收據、繳納土地租金收據、證人\n    委託書（見原審卷第17～31頁、本院卷），資為論據。惟訊\n    據被告5 人均堅詞否認有強盜犯行，被告戊○○辯稱海福海\n    產攤之生財器具均係其出資購買，並無強取他人財物等語，\n    被告丁○○、乙○○辯稱其等係向被告戊○○承租海福海產\n    攤營業，並無與被告戊○○共同強取他人財物等語，被告丙\n    ○○、己○○辯稱其等僅閒暇時偶至海福海產攤幫忙，並無\n    與被告戊○○共同強取他人財物等語。\n三、經查：\n    (一)自訴人主張出資購買海福海產店內之生財器具一節，固據\n      其提出之購物收據、繳納土地租金收據、證人委託書為證\n      （見原審卷第17～37頁、本院卷）。然上開購物收據、繳\n      納土地租金收據、證人委託書分別係個人、公司及商號等\n      第三人製作之私文書，既非屬刑事訴訟法第159 條之4 規\n      定之得為證據文書，且經被告否認證據能力，自訴人提出\n      之上開購物收據、繳納土地租金收據、證人委託書即無證\n      據能力，不得作為證據，先予敘明。\n    (二)自訴人主張出資購買海福海產攤之生財器具之情，已經證\n      人蘇玉花於本院前審結證稱：「‧‧‧我在那裡做的時候\n      ，我看到有人送貨來，都是甲○○付錢的‧‧‧」等語（\n      見本院上訴卷第72頁），證人邱官封於原審及本院亦結證\n      稱：「‧‧‧店裡的生財器具都是被告與自訴人一起去買\n      ，但錢都是自訴人付的‧‧‧」、「‧‧‧後來買餐具是\n      我們與自訴人一起去買，大家一起去看，人家送貨來，都\n      是自訴人付錢。」、「我也做得迷迷糊糊，我原來以為自\n      訴人沒付錢，但後來有人送貨來，我看到是甲○○付錢。\n      」、「（生財器具）都是我和甲○○一起去買的。」、「\n      都甲○○支出。」等語（見原審卷第165 ～166 頁、本院\n      上訴卷第70頁、本院94年5 月4 日言詞辯論筆錄）。另參\n      以被告戊○○於原審曾自白與自訴人合夥經營海福海產攤\n      ，約出資新台幣20 ,000 餘元，負責出買菜及部分器具款\n      項等語（見原審卷第86、106 、162 頁）。互核證人蘇玉\n      花、邱官封之證述及被告戊○○之自白大致相符，足佐自\n      訴人主張出資購買海福海產攤之生財器具，堪以採信。至\n      被告戊○○其後雖改稱海福海產攤之生財器具均係其出資\n      購買，並未與自訴人合夥，自訴人係受僱擔任會計等語。\n      然海福海產攤之生財器具苟係被告戊○○自行出資購買，\n      自訴人並無出資情事，而自訴人竟自訴被告戊○○強取財\n      物犯行，衡諸一般常情，被告戊○○當會義正嚴辭主張自\n      己權益。但觀諸被告戊○○於原審先係陳述自己約出資新\n      台幣（下同）2,000 餘元，其後始改稱自行出資購買海福\n      海產攤生財器具，被告戊○○其後所辯，顯不符常情，難\n      以採取。\n    (三)自訴人指訴被告5 人共同強盜犯行，固據證人蘇玉花迭於\n      原審及本院結證稱被告戊○○有向其恫稱如不搬走，要將\n      其販售之物品丟入海中等語，致其心生畏懼，乃遷離海福\n      海產攤及交還生財器具等語（見原審卷第65頁、本院94年\n      5 月4 日言詞辯論筆錄）。又被告丁○○、乙○○其後向\n      被告戊○○承租將海福海產攤營業，被告丙○○、己○○\n      則偶至海福海產攤幫忙一節，亦經被告5 人不爭執，應堪\n      認定。然依證人蘇玉花證述被告戊○○令其搬遷時，其隨\n      即打電話給自訴人，自訴人到場後表示繼續經營沒有關係\n      ，被告戊○○當時並沒有說話等語（見本院94年5 月4 日\n      言詞辯論筆錄），在客觀上，尚無從認證人蘇玉花係有因\n      被告戊○○之言語，喪失意思自由，致使不能抗拒，而遷\n      離海福海產攤及交還生財器具。再證人即保安宮副董事長\n      沈枝忠於本院已結證稱坐落屏東縣枋寮鄉○○段北勢寮小\n      段2331號土地係國有地而由保安宮管理，被告戊○○曾於\n      87年間與保安宮簽約承租該土地擺攤，且大部分均係被告\n      戊○○繳納租金等語（見本院94年5 月4 日言詞辯論筆錄\n      ），證人即保安宮總幹事吳炳源於本院亦結證稱有收取被\n      告戊○○繳納之租金等語（見本院94年5 月4 日言詞辯論\n      筆錄），是被告戊○○合夥經營海福海產店，即非無據。\n      另證人蘇玉花積欠海福海產攤租金情事，已經證人蘇玉花\n      結證在卷（見本院94年5 月4 日言詞辯論筆錄）。是被告\n      戊○○因證人蘇玉花積欠租金，因而令證人蘇玉花遷離，\n      當時應無為自己不法所有之意圖，被告戊○○之行為亦與\n      恐嚇取財罪之構成要件不符。至被告戊○○其後將海福海\n      產攤出租被告丁○○、乙○○營業，被告戊○○是否涉犯\n      侵占犯行，因非屬自訴人自訴範圍，本院自不得審理。此\n      外，復查無其他積極證據足認被告戊○○、丙○○、丁○\n      ○、乙○○、己○○有強盜或恐嚇取財等犯行，被告5 人\n      之犯罪即屬不能證明。\n    (四)又被告戊○○取回海福海產攤及生財器具，而後出租被告\n      丁○○、乙○○營業，已如前述，被告5 人行為核與竊盜\n      、竊佔之犯罪構成要件尚不相符，且被告戊○○之犯罪既\n      屬不能證明，被告戊○○取得海福海產攤及生財器具，即\n      非因犯罪所得，被告丁○○、乙○○、丙○○、己○○分\n      別承租、幫忙海福海產攤營業行為，自無成立贓物罪之可\n      能。另依證人蘇玉花證述被告戊○○係出言向其恫嚇之情\n      ，被告戊○○自非出言恐嚇自訴人。自訴人就此部分既非\n      犯罪被害人，依法本不得提起自訴，本院即無審酌餘地，\n      均併予敘明。\n四、原審以不能證明被告犯罪，而諭知無罪之判決，核無不合。\n    自訴人上訴意旨，仍執前詞，指摘原判決不當，為無理由，\n    應予駁回。\n據上論結，應依刑事訴訟法第368 條，判決如主文。"
  },
  "search": "臺灣高等法院高雄分院刑事判決94年度上更(一)字第23號上訴人即自訴人甲○○號代理人侯重信律師被告戊○○號丙○○號丁○○4號.乙○○4號.己○○號共同指定辯護人義務辯護人吳保仁律師上列上訴人因被告強盜案件，不服臺灣屏東地方法院90年度自字第15號中華民國90年5月24日第一審判決，提起上訴，經判決後，由最高法院發回更審，本院判決如下：主文上訴駁回。理由一、自訴意旨略以：坐落屏東縣枋寮鄉○○段北勢寮小段2331號土地上海福海產攤係自訴人出資購買生財器具所經營，其後出租蘇玉花營業，詎被告戊○○、丙○○、丁○○、乙○○、己○○共同意圖為自己不法之所有，且基於犯意聯絡，推由被告戊○○於民國88年6月10日上午3、4時許，在海福海產攤內，向承租人蘇玉花出言恐嚇稱如不搬走，要將蘇玉花販售東西丟入海中等語，致蘇玉花心生畏懼不能抗拒，而將海福海產攤及生財器具交付被告戊○○，被告戊○○即與被告丙○○、丁○○、乙○○、己○○共同在海福海產攤營業，因認被告5人共同涉犯加重強盜罪嫌。二、自訴人認被告5人共同涉犯加重強盜罪嫌，係以證人蘇玉花、邱官封之證述及卷附購物收據、繳納土地租金收據、證人委託書（見原審卷第17～31頁、本院卷），資為論據。惟訊據被告5人均堅詞否認有強盜犯行，被告戊○○辯稱海福海產攤之生財器具均係其出資購買，並無強取他人財物等語，被告丁○○、乙○○辯稱其等係向被告戊○○承租海福海產攤營業，並無與被告戊○○共同強取他人財物等語，被告丙○○、己○○辯稱其等僅閒暇時偶至海福海產攤幫忙，並無與被告戊○○共同強取他人財物等語。三、經查：(一)自訴人主張出資購買海福海產店內之生財器具一節，固據其提出之購物收據、繳納土地租金收據、證人委託書為證（見原審卷第17～37頁、本院卷）。然上開購物收據、繳納土地租金收據、證人委託書分別係個人、公司及商號等第三人製作之私文書，既非屬刑事訴訟法第159條之4規定之得為證據文書，且經被告否認證據能力，自訴人提出之上開購物收據、繳納土地租金收據、證人委託書即無證據能力，不得作為證據，先予敘明。(二)自訴人主張出資購買海福海產攤之生財器具之情，已經證人蘇玉花於本院前審結證稱：「‧‧‧我在那裡做的時候，我看到有人送貨來，都是甲○○付錢的‧‧‧」等語（見本院上訴卷第72頁），證人邱官封於原審及本院亦結證稱：「‧‧‧店裡的生財器具都是被告與自訴人一起去買，但錢都是自訴人付的‧‧‧」、「‧‧‧後來買餐具是我們與自訴人一起去買，大家一起去看，人家送貨來，都是自訴人付錢。」、「我也做得迷迷糊糊，我原來以為自訴人沒付錢，但後來有人送貨來，我看到是甲○○付錢。」、「（生財器具）都是我和甲○○一起去買的。」、「都甲○○支出。」等語（見原審卷第165～166頁、本院上訴卷第70頁、本院94年5月4日言詞辯論筆錄）。另參以被告戊○○於原審曾自白與自訴人合夥經營海福海產攤，約出資新台幣20,000餘元，負責出買菜及部分器具款項等語（見原審卷第86、106、162頁）。互核證人蘇玉花、邱官封之證述及被告戊○○之自白大致相符，足佐自訴人主張出資購買海福海產攤之生財器具，堪以採信。至被告戊○○其後雖改稱海福海產攤之生財器具均係其出資購買，並未與自訴人合夥，自訴人係受僱擔任會計等語。然海福海產攤之生財器具苟係被告戊○○自行出資購買，自訴人並無出資情事，而自訴人竟自訴被告戊○○強取財物犯行，衡諸一般常情，被告戊○○當會義正嚴辭主張自己權益。但觀諸被告戊○○於原審先係陳述自己約出資新台幣（下同）2,000餘元，其後始改稱自行出資購買海福海產攤生財器具，被告戊○○其後所辯，顯不符常情，難以採取。(三)自訴人指訴被告5人共同強盜犯行，固據證人蘇玉花迭於原審及本院結證稱被告戊○○有向其恫稱如不搬走，要將其販售之物品丟入海中等語，致其心生畏懼，乃遷離海福海產攤及交還生財器具等語（見原審卷第65頁、本院94年5月4日言詞辯論筆錄）。又被告丁○○、乙○○其後向被告戊○○承租將海福海產攤營業，被告丙○○、己○○則偶至海福海產攤幫忙一節，亦經被告5人不爭執，應堪認定。然依證人蘇玉花證述被告戊○○令其搬遷時，其隨即打電話給自訴人，自訴人到場後表示繼續經營沒有關係，被告戊○○當時並沒有說話等語（見本院94年5月4日言詞辯論筆錄），在客觀上，尚無從認證人蘇玉花係有因被告戊○○之言語，喪失意思自由，致使不能抗拒，而遷離海福海產攤及交還生財器具。再證人即保安宮副董事長沈枝忠於本院已結證稱坐落屏東縣枋寮鄉○○段北勢寮小段2331號土地係國有地而由保安宮管理，被告戊○○曾於87年間與保安宮簽約承租該土地擺攤，且大部分均係被告戊○○繳納租金等語（見本院94年5月4日言詞辯論筆錄），證人即保安宮總幹事吳炳源於本院亦結證稱有收取被告戊○○繳納之租金等語（見本院94年5月4日言詞辯論筆錄），是被告戊○○合夥經營海福海產店，即非無據。另證人蘇玉花積欠海福海產攤租金情事，已經證人蘇玉花結證在卷（見本院94年5月4日言詞辯論筆錄）。是被告戊○○因證人蘇玉花積欠租金，因而令證人蘇玉花遷離，當時應無為自己不法所有之意圖，被告戊○○之行為亦與恐嚇取財罪之構成要件不符。至被告戊○○其後將海福海產攤出租被告丁○○、乙○○營業，被告戊○○是否涉犯侵占犯行，因非屬自訴人自訴範圍，本院自不得審理。此外，復查無其他積極證據足認被告戊○○、丙○○、丁○○、乙○○、己○○有強盜或恐嚇取財等犯行，被告5人之犯罪即屬不能證明。(四)又被告戊○○取回海福海產攤及生財器具，而後出租被告丁○○、乙○○營業，已如前述，被告5人行為核與竊盜、竊佔之犯罪構成要件尚不相符，且被告戊○○之犯罪既屬不能證明，被告戊○○取得海福海產攤及生財器具，即非因犯罪所得，被告丁○○、乙○○、丙○○、己○○分別承租、幫忙海福海產攤營業行為，自無成立贓物罪之可能。另依證人蘇玉花證述被告戊○○係出言向其恫嚇之情，被告戊○○自非出言恐嚇自訴人。自訴人就此部分既非犯罪被害人，依法本不得提起自訴，本院即無審酌餘地，均併予敘明。四、原審以不能證明被告犯罪，而諭知無罪之判決，核無不合。自訴人上訴意旨，仍執前詞，指摘原判決不當，為無理由，應予駁回。據上論結，應依刑事訴訟法第368條，判決如主文。中華民國94年5月18日刑事第九庭審判長法官張明松法官任森銓法官郭玫利以上正本證明與原本無異。如不服本判決應於收受本判決後10日內向本院提出上訴書狀，其未敘述上訴理由者，並得於提起上訴後10日內向本院補提理由書狀（均須按他造當事人之人數附繕本）「切勿逕送上級法院」中華民國94年5月18日書記官翁心欣",
  "characters": {
    "judges": [
      "張明松",
      "任森銓",
      "郭玫利"
    ],
    "prosecutors": [

    ],
    "lawyers": [
      "侯重信",
      "義務辯護人吳保仁"
    ],
    "clerks": [
      "翁心欣"
    ],
    "plaintiffs": [

    ],
    "defendants": [
      "戊○○"
    ],
    "prosecutor_office": [

    ],
    "creditors": [

    ],
    "debtors": [

    ],
    "judicial_associate_officer": [

    ]
  },
  "adjudged_at": "2005-05-18",
  "created_at": "2016-02-06 14:47:26",
  "updated_at": "2016-02-06 14:47:26"
}