{
  "identify": "KSD-100-除-68-20110217-1",
  "court": {
    "name": "臺灣高雄地方法院",
    "code": "KSD"
  },
  "division": {
    "name": "民事",
    "code": "V"
  },
  "year": 100,
  "word": "除",
  "number": "68",
  "jcheck": "1",
  "reason": "除權判決",
  "content": "臺灣高雄地方法院民事判決               100年度除字第68號\n聲  請  人  大滿生物科技股份有限公司\n法定代理人  周建豐\n訴訟代理人  白蕙穎\n上列聲請人聲請宣告支票無效事件，本院於民國100 年2 月16日\n言詞辯論終結，判決如下：\n  主  文\n附表所示支票壹張無效。\n訴訟費用由聲請人負擔。\n  事  實\n本件聲請意旨略以：聲請人原執有如附表所示支票1 張，前因遺\n失而經依法聲請本院以99年度司催字第615 號裁定公示催告，並\n刊登新聞紙在案。現因申報權利期間已滿，且無人申報權利及提\n出原支票，為此聲請宣告該支票無效。\n  理  由\n一、上開支票業經本院以99年度司催字第615 號裁定公示催告在\n    案。\n二、所定申報權利期間已於民國100 年1 月25日屆滿，迄今仍無\n    人申報權利，故聲請人前揭聲請應予准許。\n三、依民事訴訟法第564條第1項，判決如主文。\n中    華    民    國   100    年    2     月    17    日\n                  民事第六庭  法  官  陳明呈\n正本係照原本作成。\n本判決不得上訴。\n中    華    民    國   100    年    2     月    17    日\n                              書記官  黃靖媛\n附表：\n┌──┬─────┬───────┬──────┬────────┬──────┬─────┬──┐\n│編號│發  票  人│付  款  人    │帳     號   │票面金額(新台幣)│發  票  日  │支票號碼  │備考│\n├──┼─────┼───────┼──────┼────────┼──────┼─────┼──┤\n│  │楊光遠    │台灣中小企業銀│00000000000 │31000元         │99年7月10日 │AZ0000000 │    │\n│    │          │行大昌分行    │            │                │            │          │    │\n└──┴─────┴───────┴──────┴────────┴──────┴─────┴──┘",
  "structure": {
    "main": "附表所示支票壹張無效。\n訴訟費用由聲請人負擔。",
    "fact": "本件聲請意旨略以：聲請人原執有如附表所示支票1 張，前因遺\n失而經依法聲請本院以99年度司催字第615 號裁定公示催告，並\n刊登新聞紙在案。現因申報權利期間已滿，且無人申報權利及提\n出原支票，為此聲請宣告該支票無效。",
    "reason": "一、上開支票業經本院以99年度司催字第615 號裁定公示催告在\n    案。\n二、所定申報權利期間已於民國100 年1 月25日屆滿，迄今仍無\n    人申報權利，故聲請人前揭聲請應予准許。\n三、依民事訴訟法第564條第1項，判決如主文。\n中    華    民    國   100    年    2     月    17    日\n                  民事第六庭  法  官  陳明呈\n正本係照原本作成。\n本判決不得上訴。"
  },
  "search": "臺灣高雄地方法院民事判決100年度除字第68號聲請人大滿生物科技股份有限公司法定代理人周建豐訴訟代理人白蕙穎上列聲請人聲請宣告支票無效事件，本院於民國100年2月16日言詞辯論終結，判決如下：主文附表所示支票壹張無效。訴訟費用由聲請人負擔。事實本件聲請意旨略以：聲請人原執有如附表所示支票1張，前因遺失而經依法聲請本院以99年度司催字第615號裁定公示催告，並刊登新聞紙在案。現因申報權利期間已滿，且無人申報權利及提出原支票，為此聲請宣告該支票無效。理由一、上開支票業經本院以99年度司催字第615號裁定公示催告在案。二、所定申報權利期間已於民國100年1月25日屆滿，迄今仍無人申報權利，故聲請人前揭聲請應予准許。三、依民事訴訟法第564條第1項，判決如主文。中華民國100年2月17日民事第六庭法官陳明呈正本係照原本作成。本判決不得上訴。中華民國100年2月17日書記官黃靖媛附表：┌──┬─────┬───────┬──────┬────────┬──────┬─────┬──┐│編號│發票人│付款人│帳號│票面金額(新台幣)│發票日│支票號碼│備考│├──┼─────┼───────┼──────┼────────┼──────┼─────┼──┤││楊光遠│台灣中小企業銀│00000000000│31000元│99年7月10日│AZ0000000│││││行大昌分行││││││└──┴─────┴───────┴──────┴────────┴──────┴─────┴──┘",
  "characters": {
    "judges": [
      "陳明呈"
    ],
    "prosecutors": [

    ],
    "lawyers": [

    ],
    "clerks": [
      "黃靖媛"
    ],
    "plaintiffs": [

    ],
    "defendants": [

    ],
    "prosecutor_office": [
      "大滿生物科技股份有限公司"
    ],
    "creditors": [

    ],
    "debtors": [

    ],
    "judicial_associate_officer": [

    ]
  },
  "adjudged_at": "2011-02-17",
  "created_at": "2016-02-12 07:41:01",
  "updated_at": "2016-02-12 07:41:01"
}