{
  "identify": "TYD-91-易-431-20020628-1",
  "court": {
    "name": "臺灣桃園地方法院",
    "code": "TYD"
  },
  "division": {
    "name": "刑事",
    "code": "M"
  },
  "year": 91,
  "word": "易",
  "number": "431",
  "jcheck": "1",
  "reason": "毒品危害防制條例",
  "content": "臺灣桃園地方法院刑事判決                          九十一年度易字第四三一號\n    公  訴  人  臺灣桃園地方法院檢察署檢察官\n    被      告  甲○○\n右列被告因違反毒品危害防制條例案件，經檢察官聲請簡易判決處刑（八十九年度毒\n偵字第四三０六、六三０一號、九十年度毒偵字第八五三號），經本院桃園簡易庭審\n理後（九十一年度桃簡字第一二九八號），認為不宜以簡易判決處刑，改依通常審判\n程序審理，本院判決如左：\n    主    文\n甲○○連續施用第二級毒品，累犯，處有期徒刑伍月，如易科罰金，以參佰元折算壹\n日，扣案之第二級毒品安非他命壹小包（毛重零點伍公克）。又共同連續持有第一級\n毒品，累犯，處有期徒刑肆月，如易科罰金，以參佰元折算壹日，扣案第一級毒品海\n洛因壹小包（驗餘淨重壹點肆伍公克）、第一級毒品海洛因壹小包（淨重零點零伍公\n克），均沒收銷燬之。應執行有期徒刑捌月，如易科罰金，以參佰元折算壹日，扣案\n第二級毒品安非他命壹小包（毛重零點伍公克）、第一級毒品海洛因壹小包（驗餘淨\n重壹點肆伍公克）、第一級毒品海洛因壹小包（淨重零點零伍公克），均沒收銷燬之\n。\n    事    實\n一、甲○○前因違反麻醉藥品管理條例案件經本院於民國八十五年八月十三日以八十\n    五年易字第一七五八號判決判處有期徒刑四月，如易科罰金以三百元折算一日確\n    定，指揮書執行完畢日期為八十六年八月四日。\n二、甲○○於八十七年間曾因施用第二級毒品案件，依本院裁定送觀察勒戒、強制戒\n    治、停止強制戒治付保護管束及撤銷停止強制戒治，經強制戒治期間屆滿後，於\n    民國八十九年八月二日由本院以八十七年度易字第一六二四號判決免刑確定。詎\n    仍不知悔改，又基於施用第二級毒品安非他命之概括犯意，自該判決確定後翌日\n    起至民國九十年二月二十一日止，先後在桃園縣境內，連續施用第二級毒品安非\n    他命多次，分別於八十九年十一月二十七日上午九十許，在桃園縣桃園市○○路\n    土地工廟前查獲；復於九十年二月二十一日下午十七時許，在桃園縣三民路一段\n    二十八號前查獲，並扣得第二級毒品安非他命一小包（毛重０‧五公克）。並經\n    本院以九十年度毒聲字第一一八四號裁定強制戒治一年。\n三、甲○○，明知海洛因為第一級毒品，不得非法持有，基於持有第一級毒品海洛因\n    之概括犯意，先於八十九年八月二日下午十九時許，在桃園縣桃園市○○街二十\n    五號凱園賓館六樓處，與黃國書（由檢察官另案偵辦）共同持有第一級毒品海洛\n    因，為警盤查時索查獲，並扣得第一級毒品海洛因一小包（驗餘淨重一‧四五公\n    克），現由法務部調查局保管中【人工鑑別編號000000000號】）。復\n    於九十年二月二十一日下午十七時三十分許，在桃園縣桃園市○○路○段二十八\n    號前，持有第一級毒品海洛因，為警盤查時查獲，並扣得第一級毒品海洛因一小\n    包（驗餘淨重０‧０五公克），現由法務部調查局保管中【人工鑑別編號000\n    000000號】）。\n四、案經桃園縣警察局及桃園縣警察局桃園分局分別移送、報告臺灣桃園地方法院檢\n    察署檢察官偵查起訴。\n    理    由\n一、程序部分：\n    按檢察官聲請以簡易判決處刑之案件，經法院認有刑事訴訟法第四百五十一條之\n    一第四項但書之情形者，應適用通常程序審判之，此觀諸刑事訴訟法第四百五十\n    二條之規定甚明。本件係檢察官聲請以簡易判決處刑之案件，因被告所犯之罪不\n    合刑事訴訟法第四百四十九條所定得以簡易判決處刑之案件，本院改用通常程序\n    審判之。\n二、認定犯罪事實所憑的證據及理由：\n（一）施用第二級毒品安非他命部分：\n      被告甲○○對於右揭施用第二級毒品安非他命之事實，坦承不諱，並有如事實\n      欄所載第二級毒品安非他命一小包毛重０‧五公克，扣案可稽，且被告二次被\n      查獲時所採集之尿液，經送驗結果均呈甲基安非他命陽性反應，此有桃園縣衛\n      生局民國八十九年十二月十三日、九十年三月五日不法藥物尿液檢定書二紙附\n      卷可參，被告之自白與事實相符，其多次施用第一級毒品海洛因之事實，堪以\n      認定。查被告甲○○於八十七年間曾因施用第二級毒品案件，依本院裁定送觀\n      察勒戒、強制戒治、停止強制戒治付保護管束及撤銷停止強制戒治，經強制戒\n      治期間屆滿後，於民國八十九年八月二日由本院以八十七年度易字第一六二四\n      號判決免刑確定，有臺灣高等法院被告全國前案紀錄表及前開判決書一份附卷\n      可稽，被告於前開免刑判決後，五年內再犯毒品危害防制條例第十條之罪，依\n      毒品危害防制條例第二十三條第二項前段規定，應予依法論科。\n（二）持有第一級毒品海洛因部分：\n  １、被告對於右揭持有第一級毒品海洛因之事實於本院審理時坦承不諱。\n  ２、另案共犯黃國書於警訊中稱：「我於八十九年八月二日十九時在桃園市○○街\n      二五號凱園賓館六樓電梯，遇警盤查身分時，我自行交出內有海洛因一‧六公\n      克」、「（你交出物品海洛因一‧六公克為何人所有？）該物品我不知道何人\n      所有，甲○○於八十九年八月二日到我家並騎機車載我至桃園市○○街二五號\n      凱園賓館，要我將花盤旁之一團衛生紙拿起來，隨即我們一同搭電梯上六樓」\n      （見八十九年度毒偵字第四三０六號卷第十四頁背面、十五頁）等語。\n  ３、而經警先後查扣之白粉經送鑑結果，確含第一級毒品海洛因成分，此有法務部\n      調查局鑑驗通知書（電腦條碼編號：000000000號）、（電腦條碼編\n      號：000000000號）二紙附卷足憑，並有海洛因一小包（驗餘淨重一\n      ‧四五公克）、海洛因一小包（驗餘淨重０‧０五公克）扣案可稽。\n（三）綜上，本件被告事證明確，犯行堪以認定。\n三、論罪的理由：\n（一）被告甲○○所為係犯毒品危害防制條例第十條二項之施用第二級毒品罪、同法\n      第十一條第一項之持有第一級毒品罪。被告持有毒品持有安非他命係為供施用\n      ，其持有之低度行為，應為其施用之高度行為所吸收，不另論罪。\n（二）被告與黃國書間，就持有第一級毒品海洛因犯行，有犯意聯絡及行為分擔，為\n      共同正犯。\n（三）又被告先後多次施用第二級毒品及持有第一級毒品之行為，均時間緊接，犯罪\n      構成要件相同，各顯係基於概括犯意為之，均應依連續犯規定以一罪論，並各\n      依法加重其刑。其所犯上開二罪之間，犯意各別，行為互殊，應予分論併罰。\n（四）又被告甲○○前因違反麻醉藥品管理條例案件經本院於民國八十五年八月十三\n      日以八十五年易字第一七五八號判決判處有期徒刑四月，如易科罰金以三百元\n      折算一日確定，指揮書執行完畢日期為八十六年八月四日，其於刑之執行完畢\n      五年以內再犯本件有期徒刑以上之罪，為累犯，依刑法第四十七條規定加重其\n      刑，並各依法遞加之。\n（五）爰審酌被告施用毒品次數，犯行所生危害，已曾因相同犯行經觀察、勒戒、強\n      制戒治等處遇後猶未能使其知所省惕，根絕施用毒品惡習，足徵其沾染甚深，\n      及犯後態度，坦承犯行等一切情狀，各量處如主文所示之刑，並定其應執行之\n      刑及諭知易科罰金之折算標準。\n四、沒收之依據：\n    扣案之第二級毒品安非他命一小包毛重０‧五公克、第一級毒品海洛因一小包（\n    驗餘淨重一‧四五公克）及第一級毒品海洛因一小包（驗餘淨重０‧０五公克）\n    ，均係屬毒品，應依毒品危害防制條例第十八條第一項前段之規定沒收並銷燬之\n    。\n據上論斷，應依刑事訴訟法第四百五十二條、第二百九十九條第一項前段，毒品危害\n防制條例第十條第二項、第十一條第一項、第十八條第一項前段、第二十三條第二項\n前段，刑法第十一條、第二十八條、第五十六條、第四十七條、第四十一條第一項前\n段，罰金罰鍰提高標準條例第二條，判決如主文。\n本案經檢察官翁珮嫻到庭執行職務。\n中      華      民      國    九十一    年      六      月    二十八    日\n                                  臺灣桃園地方法院刑事第六庭\n                                      法  官   黃永定\n右正本證明與原本無異。\n如不服本判決，應於判決送達後十日內向本院提出上訴狀( 應附繕本 )，上訴於\n臺灣高等法院。\n                                      書記官   陳月桂\n中      華      民      國    九十一    年      六      月    二十八    日\n附論罪科刑依據之法條：\n毒品危害防制條例第十條\n施用第一級毒品者，處六月以上五年以下有期徒刑。\n施用第二級毒品者，處三年以下有期徒刑。\n毒品危害防制條例第十一條第一項\n持有第一級毒品者，處三年以下有期徒刑、拘役或新台幣五萬元以下罰金。\n",
  "structure": {
    "main": "甲○○連續施用第二級毒品，累犯，處有期徒刑伍月，如易科罰金，以參佰元折算壹\n日，扣案之第二級毒品安非他命壹小包（毛重零點伍公克）。又共同連續持有第一級\n毒品，累犯，處有期徒刑肆月，如易科罰金，以參佰元折算壹日，扣案第一級毒品海\n洛因壹小包（驗餘淨重壹點肆伍公克）、第一級毒品海洛因壹小包（淨重零點零伍公\n克），均沒收銷燬之。應執行有期徒刑捌月，如易科罰金，以參佰元折算壹日，扣案\n第二級毒品安非他命壹小包（毛重零點伍公克）、第一級毒品海洛因壹小包（驗餘淨\n重壹點肆伍公克）、第一級毒品海洛因壹小包（淨重零點零伍公克），均沒收銷燬之\n。",
    "fact": "一、甲○○前因違反麻醉藥品管理條例案件經本院於民國八十五年八月十三日以八十\n    五年易字第一七五八號判決判處有期徒刑四月，如易科罰金以三百元折算一日確\n    定，指揮書執行完畢日期為八十六年八月四日。\n二、甲○○於八十七年間曾因施用第二級毒品案件，依本院裁定送觀察勒戒、強制戒\n    治、停止強制戒治付保護管束及撤銷停止強制戒治，經強制戒治期間屆滿後，於\n    民國八十九年八月二日由本院以八十七年度易字第一六二四號判決免刑確定。詎\n    仍不知悔改，又基於施用第二級毒品安非他命之概括犯意，自該判決確定後翌日\n    起至民國九十年二月二十一日止，先後在桃園縣境內，連續施用第二級毒品安非\n    他命多次，分別於八十九年十一月二十七日上午九十許，在桃園縣桃園市○○路\n    土地工廟前查獲；復於九十年二月二十一日下午十七時許，在桃園縣三民路一段\n    二十八號前查獲，並扣得第二級毒品安非他命一小包（毛重０‧五公克）。並經\n    本院以九十年度毒聲字第一一八四號裁定強制戒治一年。\n三、甲○○，明知海洛因為第一級毒品，不得非法持有，基於持有第一級毒品海洛因\n    之概括犯意，先於八十九年八月二日下午十九時許，在桃園縣桃園市○○街二十\n    五號凱園賓館六樓處，與黃國書（由檢察官另案偵辦）共同持有第一級毒品海洛\n    因，為警盤查時索查獲，並扣得第一級毒品海洛因一小包（驗餘淨重一‧四五公\n    克），現由法務部調查局保管中【人工鑑別編號000000000號】）。復\n    於九十年二月二十一日下午十七時三十分許，在桃園縣桃園市○○路○段二十八\n    號前，持有第一級毒品海洛因，為警盤查時查獲，並扣得第一級毒品海洛因一小\n    包（驗餘淨重０‧０五公克），現由法務部調查局保管中【人工鑑別編號000\n    000000號】）。\n四、案經桃園縣警察局及桃園縣警察局桃園分局分別移送、報告臺灣桃園地方法院檢\n    察署檢察官偵查起訴。",
    "reason": "一、程序部分：\n    按檢察官聲請以簡易判決處刑之案件，經法院認有刑事訴訟法第四百五十一條之\n    一第四項但書之情形者，應適用通常程序審判之，此觀諸刑事訴訟法第四百五十\n    二條之規定甚明。本件係檢察官聲請以簡易判決處刑之案件，因被告所犯之罪不\n    合刑事訴訟法第四百四十九條所定得以簡易判決處刑之案件，本院改用通常程序\n    審判之。\n二、認定犯罪事實所憑的證據及理由：\n（一）施用第二級毒品安非他命部分：\n      被告甲○○對於右揭施用第二級毒品安非他命之事實，坦承不諱，並有如事實\n      欄所載第二級毒品安非他命一小包毛重０‧五公克，扣案可稽，且被告二次被\n      查獲時所採集之尿液，經送驗結果均呈甲基安非他命陽性反應，此有桃園縣衛\n      生局民國八十九年十二月十三日、九十年三月五日不法藥物尿液檢定書二紙附\n      卷可參，被告之自白與事實相符，其多次施用第一級毒品海洛因之事實，堪以\n      認定。查被告甲○○於八十七年間曾因施用第二級毒品案件，依本院裁定送觀\n      察勒戒、強制戒治、停止強制戒治付保護管束及撤銷停止強制戒治，經強制戒\n      治期間屆滿後，於民國八十九年八月二日由本院以八十七年度易字第一六二四\n      號判決免刑確定，有臺灣高等法院被告全國前案紀錄表及前開判決書一份附卷\n      可稽，被告於前開免刑判決後，五年內再犯毒品危害防制條例第十條之罪，依\n      毒品危害防制條例第二十三條第二項前段規定，應予依法論科。\n（二）持有第一級毒品海洛因部分：\n  １、被告對於右揭持有第一級毒品海洛因之事實於本院審理時坦承不諱。\n  ２、另案共犯黃國書於警訊中稱：「我於八十九年八月二日十九時在桃園市○○街\n      二五號凱園賓館六樓電梯，遇警盤查身分時，我自行交出內有海洛因一‧六公\n      克」、「（你交出物品海洛因一‧六公克為何人所有？）該物品我不知道何人\n      所有，甲○○於八十九年八月二日到我家並騎機車載我至桃園市○○街二五號\n      凱園賓館，要我將花盤旁之一團衛生紙拿起來，隨即我們一同搭電梯上六樓」\n      （見八十九年度毒偵字第四三０六號卷第十四頁背面、十五頁）等語。\n  ３、而經警先後查扣之白粉經送鑑結果，確含第一級毒品海洛因成分，此有法務部\n      調查局鑑驗通知書（電腦條碼編號：000000000號）、（電腦條碼編\n      號：000000000號）二紙附卷足憑，並有海洛因一小包（驗餘淨重一\n      ‧四五公克）、海洛因一小包（驗餘淨重０‧０五公克）扣案可稽。\n（三）綜上，本件被告事證明確，犯行堪以認定。\n三、論罪的理由：\n（一）被告甲○○所為係犯毒品危害防制條例第十條二項之施用第二級毒品罪、同法\n      第十一條第一項之持有第一級毒品罪。被告持有毒品持有安非他命係為供施用\n      ，其持有之低度行為，應為其施用之高度行為所吸收，不另論罪。\n（二）被告與黃國書間，就持有第一級毒品海洛因犯行，有犯意聯絡及行為分擔，為\n      共同正犯。\n（三）又被告先後多次施用第二級毒品及持有第一級毒品之行為，均時間緊接，犯罪\n      構成要件相同，各顯係基於概括犯意為之，均應依連續犯規定以一罪論，並各\n      依法加重其刑。其所犯上開二罪之間，犯意各別，行為互殊，應予分論併罰。\n（四）又被告甲○○前因違反麻醉藥品管理條例案件經本院於民國八十五年八月十三\n      日以八十五年易字第一七五八號判決判處有期徒刑四月，如易科罰金以三百元\n      折算一日確定，指揮書執行完畢日期為八十六年八月四日，其於刑之執行完畢\n      五年以內再犯本件有期徒刑以上之罪，為累犯，依刑法第四十七條規定加重其\n      刑，並各依法遞加之。\n（五）爰審酌被告施用毒品次數，犯行所生危害，已曾因相同犯行經觀察、勒戒、強\n      制戒治等處遇後猶未能使其知所省惕，根絕施用毒品惡習，足徵其沾染甚深，\n      及犯後態度，坦承犯行等一切情狀，各量處如主文所示之刑，並定其應執行之\n      刑及諭知易科罰金之折算標準。\n四、沒收之依據：\n    扣案之第二級毒品安非他命一小包毛重０‧五公克、第一級毒品海洛因一小包（\n    驗餘淨重一‧四五公克）及第一級毒品海洛因一小包（驗餘淨重０‧０五公克）\n    ，均係屬毒品，應依毒品危害防制條例第十八條第一項前段之規定沒收並銷燬之\n    。\n據上論斷，應依刑事訴訟法第四百五十二條、第二百九十九條第一項前段，毒品危害\n防制條例第十條第二項、第十一條第一項、第十八條第一項前段、第二十三條第二項\n前段，刑法第十一條、第二十八條、第五十六條、第四十七條、第四十一條第一項前\n段，罰金罰鍰提高標準條例第二條，判決如主文。\n本案經檢察官翁珮嫻到庭執行職務。\n中      華      民      國    九十一    年      六      月    二十八    日\n                                  臺灣桃園地方法院刑事第六庭\n                                      法  官   黃永定\n右正本證明與原本無異。\n如不服本判決，應於判決送達後十日內向本院提出上訴狀( 應附繕本 )，上訴於\n臺灣高等法院。\n                                      書記官   陳月桂"
  },
  "search": "臺灣桃園地方法院刑事判決九十一年度易字第四三一號公訴人臺灣桃園地方法院檢察署檢察官被告甲○○右列被告因違反毒品危害防制條例案件，經檢察官聲請簡易判決處刑（八十九年度毒偵字第四三０六、六三０一號、九十年度毒偵字第八五三號），經本院桃園簡易庭審理後（九十一年度桃簡字第一二九八號），認為不宜以簡易判決處刑，改依通常審判程序審理，本院判決如左：主文甲○○連續施用第二級毒品，累犯，處有期徒刑伍月，如易科罰金，以參佰元折算壹日，扣案之第二級毒品安非他命壹小包（毛重零點伍公克）。又共同連續持有第一級毒品，累犯，處有期徒刑肆月，如易科罰金，以參佰元折算壹日，扣案第一級毒品海洛因壹小包（驗餘淨重壹點肆伍公克）、第一級毒品海洛因壹小包（淨重零點零伍公克），均沒收銷燬之。應執行有期徒刑捌月，如易科罰金，以參佰元折算壹日，扣案第二級毒品安非他命壹小包（毛重零點伍公克）、第一級毒品海洛因壹小包（驗餘淨重壹點肆伍公克）、第一級毒品海洛因壹小包（淨重零點零伍公克），均沒收銷燬之。事實一、甲○○前因違反麻醉藥品管理條例案件經本院於民國八十五年八月十三日以八十五年易字第一七五八號判決判處有期徒刑四月，如易科罰金以三百元折算一日確定，指揮書執行完畢日期為八十六年八月四日。二、甲○○於八十七年間曾因施用第二級毒品案件，依本院裁定送觀察勒戒、強制戒治、停止強制戒治付保護管束及撤銷停止強制戒治，經強制戒治期間屆滿後，於民國八十九年八月二日由本院以八十七年度易字第一六二四號判決免刑確定。詎仍不知悔改，又基於施用第二級毒品安非他命之概括犯意，自該判決確定後翌日起至民國九十年二月二十一日止，先後在桃園縣境內，連續施用第二級毒品安非他命多次，分別於八十九年十一月二十七日上午九十許，在桃園縣桃園市○○路土地工廟前查獲；復於九十年二月二十一日下午十七時許，在桃園縣三民路一段二十八號前查獲，並扣得第二級毒品安非他命一小包（毛重０‧五公克）。並經本院以九十年度毒聲字第一一八四號裁定強制戒治一年。三、甲○○，明知海洛因為第一級毒品，不得非法持有，基於持有第一級毒品海洛因之概括犯意，先於八十九年八月二日下午十九時許，在桃園縣桃園市○○街二十五號凱園賓館六樓處，與黃國書（由檢察官另案偵辦）共同持有第一級毒品海洛因，為警盤查時索查獲，並扣得第一級毒品海洛因一小包（驗餘淨重一‧四五公克），現由法務部調查局保管中【人工鑑別編號000000000號】）。復於九十年二月二十一日下午十七時三十分許，在桃園縣桃園市○○路○段二十八號前，持有第一級毒品海洛因，為警盤查時查獲，並扣得第一級毒品海洛因一小包（驗餘淨重０‧０五公克），現由法務部調查局保管中【人工鑑別編號000000000號】）。四、案經桃園縣警察局及桃園縣警察局桃園分局分別移送、報告臺灣桃園地方法院檢察署檢察官偵查起訴。理由一、程序部分：按檢察官聲請以簡易判決處刑之案件，經法院認有刑事訴訟法第四百五十一條之一第四項但書之情形者，應適用通常程序審判之，此觀諸刑事訴訟法第四百五十二條之規定甚明。本件係檢察官聲請以簡易判決處刑之案件，因被告所犯之罪不合刑事訴訟法第四百四十九條所定得以簡易判決處刑之案件，本院改用通常程序審判之。二、認定犯罪事實所憑的證據及理由：（一）施用第二級毒品安非他命部分：被告甲○○對於右揭施用第二級毒品安非他命之事實，坦承不諱，並有如事實欄所載第二級毒品安非他命一小包毛重０‧五公克，扣案可稽，且被告二次被查獲時所採集之尿液，經送驗結果均呈甲基安非他命陽性反應，此有桃園縣衛生局民國八十九年十二月十三日、九十年三月五日不法藥物尿液檢定書二紙附卷可參，被告之自白與事實相符，其多次施用第一級毒品海洛因之事實，堪以認定。查被告甲○○於八十七年間曾因施用第二級毒品案件，依本院裁定送觀察勒戒、強制戒治、停止強制戒治付保護管束及撤銷停止強制戒治，經強制戒治期間屆滿後，於民國八十九年八月二日由本院以八十七年度易字第一六二四號判決免刑確定，有臺灣高等法院被告全國前案紀錄表及前開判決書一份附卷可稽，被告於前開免刑判決後，五年內再犯毒品危害防制條例第十條之罪，依毒品危害防制條例第二十三條第二項前段規定，應予依法論科。（二）持有第一級毒品海洛因部分：１、被告對於右揭持有第一級毒品海洛因之事實於本院審理時坦承不諱。２、另案共犯黃國書於警訊中稱：「我於八十九年八月二日十九時在桃園市○○街二五號凱園賓館六樓電梯，遇警盤查身分時，我自行交出內有海洛因一‧六公克」、「（你交出物品海洛因一‧六公克為何人所有？）該物品我不知道何人所有，甲○○於八十九年八月二日到我家並騎機車載我至桃園市○○街二五號凱園賓館，要我將花盤旁之一團衛生紙拿起來，隨即我們一同搭電梯上六樓」（見八十九年度毒偵字第四三０六號卷第十四頁背面、十五頁）等語。３、而經警先後查扣之白粉經送鑑結果，確含第一級毒品海洛因成分，此有法務部調查局鑑驗通知書（電腦條碼編號：000000000號）、（電腦條碼編號：000000000號）二紙附卷足憑，並有海洛因一小包（驗餘淨重一‧四五公克）、海洛因一小包（驗餘淨重０‧０五公克）扣案可稽。（三）綜上，本件被告事證明確，犯行堪以認定。三、論罪的理由：（一）被告甲○○所為係犯毒品危害防制條例第十條二項之施用第二級毒品罪、同法第十一條第一項之持有第一級毒品罪。被告持有毒品持有安非他命係為供施用，其持有之低度行為，應為其施用之高度行為所吸收，不另論罪。（二）被告與黃國書間，就持有第一級毒品海洛因犯行，有犯意聯絡及行為分擔，為共同正犯。（三）又被告先後多次施用第二級毒品及持有第一級毒品之行為，均時間緊接，犯罪構成要件相同，各顯係基於概括犯意為之，均應依連續犯規定以一罪論，並各依法加重其刑。其所犯上開二罪之間，犯意各別，行為互殊，應予分論併罰。（四）又被告甲○○前因違反麻醉藥品管理條例案件經本院於民國八十五年八月十三日以八十五年易字第一七五八號判決判處有期徒刑四月，如易科罰金以三百元折算一日確定，指揮書執行完畢日期為八十六年八月四日，其於刑之執行完畢五年以內再犯本件有期徒刑以上之罪，為累犯，依刑法第四十七條規定加重其刑，並各依法遞加之。（五）爰審酌被告施用毒品次數，犯行所生危害，已曾因相同犯行經觀察、勒戒、強制戒治等處遇後猶未能使其知所省惕，根絕施用毒品惡習，足徵其沾染甚深，及犯後態度，坦承犯行等一切情狀，各量處如主文所示之刑，並定其應執行之刑及諭知易科罰金之折算標準。四、沒收之依據：扣案之第二級毒品安非他命一小包毛重０‧五公克、第一級毒品海洛因一小包（驗餘淨重一‧四五公克）及第一級毒品海洛因一小包（驗餘淨重０‧０五公克），均係屬毒品，應依毒品危害防制條例第十八條第一項前段之規定沒收並銷燬之。據上論斷，應依刑事訴訟法第四百五十二條、第二百九十九條第一項前段，毒品危害防制條例第十條第二項、第十一條第一項、第十八條第一項前段、第二十三條第二項前段，刑法第十一條、第二十八條、第五十六條、第四十七條、第四十一條第一項前段，罰金罰鍰提高標準條例第二條，判決如主文。本案經檢察官翁珮嫻到庭執行職務。中華民國九十一年六月二十八日臺灣桃園地方法院刑事第六庭法官黃永定右正本證明與原本無異。如不服本判決，應於判決送達後十日內向本院提出上訴狀(應附繕本)，上訴於臺灣高等法院。書記官陳月桂中華民國九十一年六月二十八日附論罪科刑依據之法條：毒品危害防制條例第十條施用第一級毒品者，處六月以上五年以下有期徒刑。施用第二級毒品者，處三年以下有期徒刑。毒品危害防制條例第十一條第一項持有第一級毒品者，處三年以下有期徒刑、拘役或新台幣五萬元以下罰金。",
  "characters": {
    "judges": [
      "黃永定"
    ],
    "prosecutors": [
      "翁珮嫻"
    ],
    "lawyers": [

    ],
    "clerks": [
      "陳月桂"
    ],
    "plaintiffs": [

    ],
    "defendants": [
      "甲○○",
      "右列被告因違反毒品危害防制條例案件，經檢察官聲請簡易判決處刑（八十九年度毒",
      "偵字第四三０六、六三０一號、九十年度毒偵字第八五三號），經本院桃園簡易庭審",
      "理後（九十一年度桃簡字第一二九八號），認為不宜以簡易判決處刑，改依通常審判",
      "程序審理，本院判決如左："
    ],
    "prosecutor_office": [
      "臺灣桃園地方法院檢察署檢察官"
    ],
    "creditors": [

    ],
    "debtors": [

    ],
    "judicial_associate_officer": [

    ]
  },
  "adjudged_at": "2002-06-28",
  "created_at": "2016-02-05 15:26:56",
  "updated_at": "2016-02-05 15:26:56"
}