{
  "identify": "KSD-91-訴-1691-20020828-1",
  "court": {
    "name": "臺灣高雄地方法院",
    "code": "KSD"
  },
  "division": {
    "name": "刑事",
    "code": "M"
  },
  "year": 91,
  "word": "訴",
  "number": "1691",
  "jcheck": "1",
  "reason": "違反電信法等",
  "content": "臺灣高雄地方法院刑事判決                        九十一年度訴字第一六九一號\n    公  訴  人  臺灣高雄地方法院檢察署檢察官\n    被      告  戊○○\n右列被告因違反電信法等案件，經檢察官提起公訴（九十一年度偵字第九五一七號）\n，本院判決如左：\n    主  文\n本件免訴。\n    理  由\n一、公訴意旨係以：被告戊○○曾有違反懲治盜匪條例與搶奪等前科，為法院判決應\n    執行刑有期徒刑五年十月，現於台灣高雄監獄執行中。被告戊○○於民國九十年\n    一月中旬某日，竟意圖為自己不法所有，在高雄縣鳳山市鎮○里○○路十三巷五\n    號，趁甲○○不在之際，竊取放置於客廳抽屜內之物品（計有(一)方燕翼身分證影\n    本、印章與郵局存款簿，(二)丙○○○所有身分證影本、印章、郵局存款簿與世華\n    銀行存款簿，(三)乙○○所有之印章，(四)己○○所有土地銀行存款簿等物）。另洪\n    瓊華與陳繹傑兩人（該兩人業經臺灣高雄地方法院檢察署九十年度偵字第二一一\n    四九號提起公訴）為朋友關係，均以辦理行動電話門號為業，陳繹傑先以辦理門\n    號送行動電話方式在報紙上刊登廣告，招徠民眾申請行動電話門號，洪瓊華則擺\n    設攤位受理民眾辦理門號，並兼出售行動電話。被告戊○○竊取上揭物品得手後\n    ，復於九十年一月下旬某日，與洪瓊華及陳繹傑兩人基於偽造文書之共同犯意，\n    由被告戊○○將上述所竊得方許壁愛與丁○○兩人身份證影本及印章，持往高雄\n    市旗津區大港超市騎樓下洪瓊華所擺設辦理行動電話門號之攤位，向洪瓊華申請\n    台灣大哥大股份有限公司行動電話八個門號（以方許壁愛名義申請000000\n    0000、0000000000、0000000000等三個電話門號，復\n    以方燕翼名義申請0000000000、0000000000、00000\n    00000、0000000000、0000000000等五個電話門號）\n    ，被告戊○○每申請一個門號，可向陳繹傑取得新台幣一千元代價，洪瓊華所贈\n    送行動電話則由陳繹傑取得。被告戊○○於上揭時地申辦行動電話門號時，洪瓊\n    華在方燕翼上開三個門號申請書及同意書上偽簽「方燕翼」署押並盜蓋印章，被\n    告戊○○則在以方許璧愛名義申請五個門號之申請書及同意書上，偽簽「方許璧\n    愛」署押並盜蓋印章，復由陳繹傑出具偽造之方燕翼與方許璧愛在職證明書，持\n    向台灣大哥大股份有限公司申請上述八個門號而行使之，並取得所贈送之八具行\n    動電話。被告戊○○從陳繹傑處取得上揭門號後，連續持以撥打電話使用，通話\n    費用與月租費共計四萬八千零七元，事後均未繳納，足生損害於台灣大哥大股份\n    有限公司、方燕翼與方許璧愛，因認被告戊○○涉有刑法第三百二十條第一項竊\n    盜罪及同法第二百十條、第二百十六條行使偽造私文書，及電信法第五十六條第\n    一項盜用他人電信設備罪嫌云云。\n二、按案件曾經判決確定者，應為免訴之判決，此項原則關於實質上一罪或裁判上一\n    罪，均有其適用。連續犯係裁判上一罪，其一部分犯罪事實曾經判決確定者，其\n    效力當然及於全部，故檢察官復將其他部分重行起訴，亦應諭知免訴之判決（最\n    高法院四十九年台非字第二Ｏ號判例參照）。又犯一罪而其方法或結果之行為犯\n    他罪名者，刑法第五十五條既規定從一重處斷，則牽連犯之一部經判決確定，其\n    效力即及於全部，倘檢察官復就所犯之他罪名重行起訴，法院應依刑事訴訟法第\n    二百九十四條第一款諭知免訴，無再就所犯罪名論科之餘地（最高法院五十年台\n    非字第一０八號判例參照）。\n三、查本件被告戊○○前被訴基於偽造文書之概括犯意，連續於：(一)九十年二月二十\n    一日，利用謝逸琳委其代為申請一支行動電話搭配門號之便，將謝女所交付之身\n    分證影本私下多影印一份，持向高雄市新興區○○○路一五二號「亞東電話企業\n    行」，擅自在「遠傳行動電話服務申請書」（一式三份）之申請人簽章欄內偽造\n    「謝逸琳」之簽名，並持向不知情之店員詹陳碧珠主張欲辦理行動電話而行使，\n    利用該不知情店員代向遠傳電信股份有限公司申請，並因此取得0000000\n    000號之行動電話門號及ＳＩＭ卡一枚，嗣因無法通話而將ＳＩＭ卡丟棄。(二)\n    同年月二十六日，戊○○復以相同手法，利用其兄林煜書委其代為申請一個行動\n    電話門號之便，將林煜書所交付之身分證影本私下多影印一份，持向上開「亞東\n    電話企業行」，擅自在「遠傳行動電話服務申請書」（一式三份）之申請人簽章\n    欄內偽造「林煜書」之簽名，並持向不知情之店員詹陳碧珠主張欲辦理行動電話\n    而行使，利用該不知情店員代向遠傳電信股份有限公司申請，並因此取得000\n    0000000號之行動電話門號及ＳＩＭ卡一枚，嗣因無法通話而將ＳＩＭ卡\n    丟棄。(三)同年三月九日，戊○○持姓名年籍不詳、綽號「康仔」之成年男子轉交\n    之林宜靜身分證一張，至上開「亞東電話企業行」，在「和信ＯＮＬＩＮＥ服務\n    申請表」（一式三份）之申請人簽章欄內偽造「林宜靜」之簽名，並持向不知情\n    之店員詹陳碧珠主張欲申請行動電話門號而行使，利用該不知情店員代向和信電\n    信股份有限公司申請，並因此取得0000000000號之行動電話門號及Ｓ\n    ＩＭ卡一枚，旋即將該卡交付「康仔」使用，戊○○上開行為均足以生損害於謝\n    逸琳、林煜書、林宜靜及遠傳、和信電信股份有限公司對行動電話客戶管理之正\n    確性。其所涉刑法第二百十六條、第二百十條行使偽造私文書罪嫌，業經檢察官\n    提起公訴，並由臺灣屏東地方法院於九十一年三月二十五日，以九十年訴字第九\n    五八號刑事判決判處有期徒刑六月，於九十一年四月二十二日確定在案（見偵卷\n    附臺灣屏東地方法院九十年訴字第九五八號刑事判決及臺灣高等法院被告全國前\n    案記錄表）。該案與本件檢察官所起訴被告持方燕翼、丙○○○所有身分證影本\n    、印章、存款簿等物，與洪瓊華與陳繹傑二人基於偽造文書之共同犯意，由洪瓊\n    華及戊○○分別在申請書及同意書上偽簽方燕翼及丙○○○之署押並盜蓋印章，\n    復由陳繹傑出具偽造之在職證明書，持向臺灣大哥大股份有限公司申請行動電話\n    八個門號之犯罪事實，時間緊接，持他人證件冒名申請行動電話使用之犯罪手法\n    相同，顯係基於概括犯意，而犯構成要件相同之罪名，自屬連續犯，為裁判上一\n    罪；又本件檢察官起訴之竊取(一)方燕翼身分證影本、印章與郵局存款簿，(二)丙○\n    ○○所有身分證影本、印章、郵局存款簿與世華銀行存款簿，(三)乙○○所有之印\n    章，(四)己○○所有土地銀行存款簿等物，以及取得行動電話門號後持以撥打使用\n    之犯罪事實，與前揭檢察官起訴之行使偽造私文書亦有方法結果之牽連犯關係，\n    故依審判不可分原則，前揭臺灣屏東地方法院九十年訴字第九五八號判決之效力\n    ，應及於本案有連續犯及牽連犯關係之全部犯罪事實。揆諸前揭說明，爰不經言\n    詞辯論，依法為免訴判決之諭知。\n據上論結，應依刑事訴訟法第三百零二條第一款、第三百零七條，判決如主文。\n中     華     民     國     九十一     年     八      月      二十八    日\n                                臺灣高雄地方法院刑事第六庭\n    審判長  法  官      李政庭\n                                            法  官      周玉群\n                                            法  官      邱泰錄\n右正本證明與原本無異。\n如不服本判決，應於判決送達後十日內，向本院提出上訴狀。\n                                            書記官      林慧君\n中    華    民    國      九十一      年      八   月     二十八      日\n",
  "structure": {
    "main": "本件免訴。",
    "reason": "一、公訴意旨係以：被告戊○○曾有違反懲治盜匪條例與搶奪等前科，為法院判決應\n    執行刑有期徒刑五年十月，現於台灣高雄監獄執行中。被告戊○○於民國九十年\n    一月中旬某日，竟意圖為自己不法所有，在高雄縣鳳山市鎮○里○○路十三巷五\n    號，趁甲○○不在之際，竊取放置於客廳抽屜內之物品（計有(一)方燕翼身分證影\n    本、印章與郵局存款簿，(二)丙○○○所有身分證影本、印章、郵局存款簿與世華\n    銀行存款簿，(三)乙○○所有之印章，(四)己○○所有土地銀行存款簿等物）。另洪\n    瓊華與陳繹傑兩人（該兩人業經臺灣高雄地方法院檢察署九十年度偵字第二一一\n    四九號提起公訴）為朋友關係，均以辦理行動電話門號為業，陳繹傑先以辦理門\n    號送行動電話方式在報紙上刊登廣告，招徠民眾申請行動電話門號，洪瓊華則擺\n    設攤位受理民眾辦理門號，並兼出售行動電話。被告戊○○竊取上揭物品得手後\n    ，復於九十年一月下旬某日，與洪瓊華及陳繹傑兩人基於偽造文書之共同犯意，\n    由被告戊○○將上述所竊得方許壁愛與丁○○兩人身份證影本及印章，持往高雄\n    市旗津區大港超市騎樓下洪瓊華所擺設辦理行動電話門號之攤位，向洪瓊華申請\n    台灣大哥大股份有限公司行動電話八個門號（以方許壁愛名義申請000000\n    0000、0000000000、0000000000等三個電話門號，復\n    以方燕翼名義申請0000000000、0000000000、00000\n    00000、0000000000、0000000000等五個電話門號）\n    ，被告戊○○每申請一個門號，可向陳繹傑取得新台幣一千元代價，洪瓊華所贈\n    送行動電話則由陳繹傑取得。被告戊○○於上揭時地申辦行動電話門號時，洪瓊\n    華在方燕翼上開三個門號申請書及同意書上偽簽「方燕翼」署押並盜蓋印章，被\n    告戊○○則在以方許璧愛名義申請五個門號之申請書及同意書上，偽簽「方許璧\n    愛」署押並盜蓋印章，復由陳繹傑出具偽造之方燕翼與方許璧愛在職證明書，持\n    向台灣大哥大股份有限公司申請上述八個門號而行使之，並取得所贈送之八具行\n    動電話。被告戊○○從陳繹傑處取得上揭門號後，連續持以撥打電話使用，通話\n    費用與月租費共計四萬八千零七元，事後均未繳納，足生損害於台灣大哥大股份\n    有限公司、方燕翼與方許璧愛，因認被告戊○○涉有刑法第三百二十條第一項竊\n    盜罪及同法第二百十條、第二百十六條行使偽造私文書，及電信法第五十六條第\n    一項盜用他人電信設備罪嫌云云。\n二、按案件曾經判決確定者，應為免訴之判決，此項原則關於實質上一罪或裁判上一\n    罪，均有其適用。連續犯係裁判上一罪，其一部分犯罪事實曾經判決確定者，其\n    效力當然及於全部，故檢察官復將其他部分重行起訴，亦應諭知免訴之判決（最\n    高法院四十九年台非字第二Ｏ號判例參照）。又犯一罪而其方法或結果之行為犯\n    他罪名者，刑法第五十五條既規定從一重處斷，則牽連犯之一部經判決確定，其\n    效力即及於全部，倘檢察官復就所犯之他罪名重行起訴，法院應依刑事訴訟法第\n    二百九十四條第一款諭知免訴，無再就所犯罪名論科之餘地（最高法院五十年台\n    非字第一０八號判例參照）。\n三、查本件被告戊○○前被訴基於偽造文書之概括犯意，連續於：(一)九十年二月二十\n    一日，利用謝逸琳委其代為申請一支行動電話搭配門號之便，將謝女所交付之身\n    分證影本私下多影印一份，持向高雄市新興區○○○路一五二號「亞東電話企業\n    行」，擅自在「遠傳行動電話服務申請書」（一式三份）之申請人簽章欄內偽造\n    「謝逸琳」之簽名，並持向不知情之店員詹陳碧珠主張欲辦理行動電話而行使，\n    利用該不知情店員代向遠傳電信股份有限公司申請，並因此取得0000000\n    000號之行動電話門號及ＳＩＭ卡一枚，嗣因無法通話而將ＳＩＭ卡丟棄。(二)\n    同年月二十六日，戊○○復以相同手法，利用其兄林煜書委其代為申請一個行動\n    電話門號之便，將林煜書所交付之身分證影本私下多影印一份，持向上開「亞東\n    電話企業行」，擅自在「遠傳行動電話服務申請書」（一式三份）之申請人簽章\n    欄內偽造「林煜書」之簽名，並持向不知情之店員詹陳碧珠主張欲辦理行動電話\n    而行使，利用該不知情店員代向遠傳電信股份有限公司申請，並因此取得000\n    0000000號之行動電話門號及ＳＩＭ卡一枚，嗣因無法通話而將ＳＩＭ卡\n    丟棄。(三)同年三月九日，戊○○持姓名年籍不詳、綽號「康仔」之成年男子轉交\n    之林宜靜身分證一張，至上開「亞東電話企業行」，在「和信ＯＮＬＩＮＥ服務\n    申請表」（一式三份）之申請人簽章欄內偽造「林宜靜」之簽名，並持向不知情\n    之店員詹陳碧珠主張欲申請行動電話門號而行使，利用該不知情店員代向和信電\n    信股份有限公司申請，並因此取得0000000000號之行動電話門號及Ｓ\n    ＩＭ卡一枚，旋即將該卡交付「康仔」使用，戊○○上開行為均足以生損害於謝\n    逸琳、林煜書、林宜靜及遠傳、和信電信股份有限公司對行動電話客戶管理之正\n    確性。其所涉刑法第二百十六條、第二百十條行使偽造私文書罪嫌，業經檢察官\n    提起公訴，並由臺灣屏東地方法院於九十一年三月二十五日，以九十年訴字第九\n    五八號刑事判決判處有期徒刑六月，於九十一年四月二十二日確定在案（見偵卷\n    附臺灣屏東地方法院九十年訴字第九五八號刑事判決及臺灣高等法院被告全國前\n    案記錄表）。該案與本件檢察官所起訴被告持方燕翼、丙○○○所有身分證影本\n    、印章、存款簿等物，與洪瓊華與陳繹傑二人基於偽造文書之共同犯意，由洪瓊\n    華及戊○○分別在申請書及同意書上偽簽方燕翼及丙○○○之署押並盜蓋印章，\n    復由陳繹傑出具偽造之在職證明書，持向臺灣大哥大股份有限公司申請行動電話\n    八個門號之犯罪事實，時間緊接，持他人證件冒名申請行動電話使用之犯罪手法\n    相同，顯係基於概括犯意，而犯構成要件相同之罪名，自屬連續犯，為裁判上一\n    罪；又本件檢察官起訴之竊取(一)方燕翼身分證影本、印章與郵局存款簿，(二)丙○\n    ○○所有身分證影本、印章、郵局存款簿與世華銀行存款簿，(三)乙○○所有之印\n    章，(四)己○○所有土地銀行存款簿等物，以及取得行動電話門號後持以撥打使用\n    之犯罪事實，與前揭檢察官起訴之行使偽造私文書亦有方法結果之牽連犯關係，\n    故依審判不可分原則，前揭臺灣屏東地方法院九十年訴字第九五八號判決之效力\n    ，應及於本案有連續犯及牽連犯關係之全部犯罪事實。揆諸前揭說明，爰不經言\n    詞辯論，依法為免訴判決之諭知。\n據上論結，應依刑事訴訟法第三百零二條第一款、第三百零七條，判決如主文。"
  },
  "search": "臺灣高雄地方法院刑事判決九十一年度訴字第一六九一號公訴人臺灣高雄地方法院檢察署檢察官被告戊○○右列被告因違反電信法等案件，經檢察官提起公訴（九十一年度偵字第九五一七號），本院判決如左：主文本件免訴。理由一、公訴意旨係以：被告戊○○曾有違反懲治盜匪條例與搶奪等前科，為法院判決應執行刑有期徒刑五年十月，現於台灣高雄監獄執行中。被告戊○○於民國九十年一月中旬某日，竟意圖為自己不法所有，在高雄縣鳳山市鎮○里○○路十三巷五號，趁甲○○不在之際，竊取放置於客廳抽屜內之物品（計有(一)方燕翼身分證影本、印章與郵局存款簿，(二)丙○○○所有身分證影本、印章、郵局存款簿與世華銀行存款簿，(三)乙○○所有之印章，(四)己○○所有土地銀行存款簿等物）。另洪瓊華與陳繹傑兩人（該兩人業經臺灣高雄地方法院檢察署九十年度偵字第二一一四九號提起公訴）為朋友關係，均以辦理行動電話門號為業，陳繹傑先以辦理門號送行動電話方式在報紙上刊登廣告，招徠民眾申請行動電話門號，洪瓊華則擺設攤位受理民眾辦理門號，並兼出售行動電話。被告戊○○竊取上揭物品得手後，復於九十年一月下旬某日，與洪瓊華及陳繹傑兩人基於偽造文書之共同犯意，由被告戊○○將上述所竊得方許壁愛與丁○○兩人身份證影本及印章，持往高雄市旗津區大港超市騎樓下洪瓊華所擺設辦理行動電話門號之攤位，向洪瓊華申請台灣大哥大股份有限公司行動電話八個門號（以方許壁愛名義申請0000000000、0000000000、0000000000等三個電話門號，復以方燕翼名義申請0000000000、0000000000、0000000000、0000000000、0000000000等五個電話門號），被告戊○○每申請一個門號，可向陳繹傑取得新台幣一千元代價，洪瓊華所贈送行動電話則由陳繹傑取得。被告戊○○於上揭時地申辦行動電話門號時，洪瓊華在方燕翼上開三個門號申請書及同意書上偽簽「方燕翼」署押並盜蓋印章，被告戊○○則在以方許璧愛名義申請五個門號之申請書及同意書上，偽簽「方許璧愛」署押並盜蓋印章，復由陳繹傑出具偽造之方燕翼與方許璧愛在職證明書，持向台灣大哥大股份有限公司申請上述八個門號而行使之，並取得所贈送之八具行動電話。被告戊○○從陳繹傑處取得上揭門號後，連續持以撥打電話使用，通話費用與月租費共計四萬八千零七元，事後均未繳納，足生損害於台灣大哥大股份有限公司、方燕翼與方許璧愛，因認被告戊○○涉有刑法第三百二十條第一項竊盜罪及同法第二百十條、第二百十六條行使偽造私文書，及電信法第五十六條第一項盜用他人電信設備罪嫌云云。二、按案件曾經判決確定者，應為免訴之判決，此項原則關於實質上一罪或裁判上一罪，均有其適用。連續犯係裁判上一罪，其一部分犯罪事實曾經判決確定者，其效力當然及於全部，故檢察官復將其他部分重行起訴，亦應諭知免訴之判決（最高法院四十九年台非字第二Ｏ號判例參照）。又犯一罪而其方法或結果之行為犯他罪名者，刑法第五十五條既規定從一重處斷，則牽連犯之一部經判決確定，其效力即及於全部，倘檢察官復就所犯之他罪名重行起訴，法院應依刑事訴訟法第二百九十四條第一款諭知免訴，無再就所犯罪名論科之餘地（最高法院五十年台非字第一０八號判例參照）。三、查本件被告戊○○前被訴基於偽造文書之概括犯意，連續於：(一)九十年二月二十一日，利用謝逸琳委其代為申請一支行動電話搭配門號之便，將謝女所交付之身分證影本私下多影印一份，持向高雄市新興區○○○路一五二號「亞東電話企業行」，擅自在「遠傳行動電話服務申請書」（一式三份）之申請人簽章欄內偽造「謝逸琳」之簽名，並持向不知情之店員詹陳碧珠主張欲辦理行動電話而行使，利用該不知情店員代向遠傳電信股份有限公司申請，並因此取得0000000000號之行動電話門號及ＳＩＭ卡一枚，嗣因無法通話而將ＳＩＭ卡丟棄。(二)同年月二十六日，戊○○復以相同手法，利用其兄林煜書委其代為申請一個行動電話門號之便，將林煜書所交付之身分證影本私下多影印一份，持向上開「亞東電話企業行」，擅自在「遠傳行動電話服務申請書」（一式三份）之申請人簽章欄內偽造「林煜書」之簽名，並持向不知情之店員詹陳碧珠主張欲辦理行動電話而行使，利用該不知情店員代向遠傳電信股份有限公司申請，並因此取得0000000000號之行動電話門號及ＳＩＭ卡一枚，嗣因無法通話而將ＳＩＭ卡丟棄。(三)同年三月九日，戊○○持姓名年籍不詳、綽號「康仔」之成年男子轉交之林宜靜身分證一張，至上開「亞東電話企業行」，在「和信ＯＮＬＩＮＥ服務申請表」（一式三份）之申請人簽章欄內偽造「林宜靜」之簽名，並持向不知情之店員詹陳碧珠主張欲申請行動電話門號而行使，利用該不知情店員代向和信電信股份有限公司申請，並因此取得0000000000號之行動電話門號及ＳＩＭ卡一枚，旋即將該卡交付「康仔」使用，戊○○上開行為均足以生損害於謝逸琳、林煜書、林宜靜及遠傳、和信電信股份有限公司對行動電話客戶管理之正確性。其所涉刑法第二百十六條、第二百十條行使偽造私文書罪嫌，業經檢察官提起公訴，並由臺灣屏東地方法院於九十一年三月二十五日，以九十年訴字第九五八號刑事判決判處有期徒刑六月，於九十一年四月二十二日確定在案（見偵卷附臺灣屏東地方法院九十年訴字第九五八號刑事判決及臺灣高等法院被告全國前案記錄表）。該案與本件檢察官所起訴被告持方燕翼、丙○○○所有身分證影本、印章、存款簿等物，與洪瓊華與陳繹傑二人基於偽造文書之共同犯意，由洪瓊華及戊○○分別在申請書及同意書上偽簽方燕翼及丙○○○之署押並盜蓋印章，復由陳繹傑出具偽造之在職證明書，持向臺灣大哥大股份有限公司申請行動電話八個門號之犯罪事實，時間緊接，持他人證件冒名申請行動電話使用之犯罪手法相同，顯係基於概括犯意，而犯構成要件相同之罪名，自屬連續犯，為裁判上一罪；又本件檢察官起訴之竊取(一)方燕翼身分證影本、印章與郵局存款簿，(二)丙○○○所有身分證影本、印章、郵局存款簿與世華銀行存款簿，(三)乙○○所有之印章，(四)己○○所有土地銀行存款簿等物，以及取得行動電話門號後持以撥打使用之犯罪事實，與前揭檢察官起訴之行使偽造私文書亦有方法結果之牽連犯關係，故依審判不可分原則，前揭臺灣屏東地方法院九十年訴字第九五八號判決之效力，應及於本案有連續犯及牽連犯關係之全部犯罪事實。揆諸前揭說明，爰不經言詞辯論，依法為免訴判決之諭知。據上論結，應依刑事訴訟法第三百零二條第一款、第三百零七條，判決如主文。中華民國九十一年八月二十八日臺灣高雄地方法院刑事第六庭審判長法官李政庭法官周玉群法官邱泰錄右正本證明與原本無異。如不服本判決，應於判決送達後十日內，向本院提出上訴狀。書記官林慧君中華民國九十一年八月二十八日",
  "characters": {
    "judges": [
      "李政庭",
      "周玉群",
      "邱泰錄"
    ],
    "prosecutors": [

    ],
    "lawyers": [

    ],
    "clerks": [
      "林慧君"
    ],
    "plaintiffs": [

    ],
    "defendants": [
      "戊○○",
      "右列被告因違反電信法等案件，經檢察官提起公訴（九十一年度偵字第九五一七號）",
      "，本院判決如左："
    ],
    "prosecutor_office": [
      "臺灣高雄地方法院檢察署檢察官"
    ],
    "creditors": [

    ],
    "debtors": [

    ],
    "judicial_associate_officer": [

    ]
  },
  "adjudged_at": "2002-08-28",
  "created_at": "2016-02-04 19:04:24",
  "updated_at": "2016-02-04 19:04:24"
}