{
  "identify": "KSD-100-簡-2793-20110523-1",
  "court": {
    "name": "臺灣高雄地方法院",
    "code": "KSD"
  },
  "division": {
    "name": "刑事",
    "code": "M"
  },
  "year": 100,
  "word": "簡",
  "number": "2793",
  "jcheck": "1",
  "reason": "竊盜",
  "content": "臺灣高雄地方法院刑事簡易判決         100年度簡字第2793號\n聲  請  人  臺灣高雄地方法院檢察署檢察官\n被      告  林世聰\n上列被告因竊盜案件，經檢察官聲請以簡易判決處刑（100 年度\n偵字第12952 號），本院判決如下：\n    主  文\n林世聰犯竊盜罪，處有期徒刑貳月，如易科罰金，以新臺幣壹仟\n元折算壹日。\n    事實及理由\n一、本件犯罪事實及證據，除犯罪事實一、第2 行「羅光雄」更\n    正為「羅清淵」外，餘均引用檢察官聲請簡易判決處刑書之\n    記載（如附件）。\n二、核被告林世聰所為，係犯刑法第320條第1項之竊盜罪。爰審\n    酌被告正值青壯年，不思以正當方法謀取生活上所需，竟為\n    貪圖不法利益，率爾以自備鑰匙竊取他人所有之機車，其犯\n    罪之動機、手段、目的均非可取，惟被告犯後坦承犯行，態\n    度尚可，又所竊之機車，業已返還被害人，損害已有減輕，\n    有贓物認領保管單1 紙在卷可稽，然被告前有毒品前科，素\n    行不佳，兼衡其自稱國中肄業、家境勉持之智識程度與生活\n    狀況等上開被告個人具體之行為人責任基礎之一切情狀，量\n    處如主文所示之刑，並諭知易科罰金之折算標準，以資警惕\n    。至扣案之鑰匙1 支，為被告拾獲之物，並非被告所有，業\n    據被告於警詢中供承在卷，爰不予沒收，附此敘明。\n三、依刑事訴訟法第449 條第1 項前段、第3 項、第454 條第2\n    項，刑法第320 條第1 項、第41條第1 項前段，刑法施行法\n    第1 條之1 第1 項、第2 項前段，逕以簡易判決處刑如主文\n    。\n四、如不服本件判決，得自收受送達之日起10日內，向本院提起\n    上訴狀，上訴於本院管轄之第二審地方法院合議庭。\n中    華    民    國  100     年    5     月    23    日\n                   高雄簡易庭   法  官  陳采葳\n以上正本證明與原本無異。\n如不服本判決應於判決送達之日起10日內向本院提出上訴書狀。\n中    華    民    國   100    年    5     月    23    日\n                                書記官  馮欽鳳\n附錄本判決論罪之法條：\n刑法第320條第1項\n意圖為自己或第三人不法之所有，而竊取他人之動產者，為竊盜\n罪，處 5 年以下有期徒刑、拘役或 5 百元（新臺幣 1 萬 5 千\n元）以下罰金。",
  "structure": {
    "main": "林世聰犯竊盜罪，處有期徒刑貳月，如易科罰金，以新臺幣壹仟\n元折算壹日。",
    "fact": "一、本件犯罪事實及證據，除犯罪事實一、第2 行「羅光雄」更\n    正為「羅清淵」外，餘均引用檢察官聲請簡易判決處刑書之\n    記載（如附件）。\n二、核被告林世聰所為，係犯刑法第320條第1項之竊盜罪。爰審\n    酌被告正值青壯年，不思以正當方法謀取生活上所需，竟為\n    貪圖不法利益，率爾以自備鑰匙竊取他人所有之機車，其犯\n    罪之動機、手段、目的均非可取，惟被告犯後坦承犯行，態\n    度尚可，又所竊之機車，業已返還被害人，損害已有減輕，\n    有贓物認領保管單1 紙在卷可稽，然被告前有毒品前科，素\n    行不佳，兼衡其自稱國中肄業、家境勉持之智識程度與生活\n    狀況等上開被告個人具體之行為人責任基礎之一切情狀，量\n    處如主文所示之刑，並諭知易科罰金之折算標準，以資警惕\n    。至扣案之鑰匙1 支，為被告拾獲之物，並非被告所有，業\n    據被告於警詢中供承在卷，爰不予沒收，附此敘明。\n三、依刑事訴訟法第449 條第1 項前段、第3 項、第454 條第2\n    項，刑法第320 條第1 項、第41條第1 項前段，刑法施行法\n    第1 條之1 第1 項、第2 項前段，逕以簡易判決處刑如主文\n    。\n四、如不服本件判決，得自收受送達之日起10日內，向本院提起\n    上訴狀，上訴於本院管轄之第二審地方法院合議庭。",
    "reason": "一、本件犯罪事實及證據，除犯罪事實一、第2 行「羅光雄」更\n    正為「羅清淵」外，餘均引用檢察官聲請簡易判決處刑書之\n    記載（如附件）。\n二、核被告林世聰所為，係犯刑法第320條第1項之竊盜罪。爰審\n    酌被告正值青壯年，不思以正當方法謀取生活上所需，竟為\n    貪圖不法利益，率爾以自備鑰匙竊取他人所有之機車，其犯\n    罪之動機、手段、目的均非可取，惟被告犯後坦承犯行，態\n    度尚可，又所竊之機車，業已返還被害人，損害已有減輕，\n    有贓物認領保管單1 紙在卷可稽，然被告前有毒品前科，素\n    行不佳，兼衡其自稱國中肄業、家境勉持之智識程度與生活\n    狀況等上開被告個人具體之行為人責任基礎之一切情狀，量\n    處如主文所示之刑，並諭知易科罰金之折算標準，以資警惕\n    。至扣案之鑰匙1 支，為被告拾獲之物，並非被告所有，業\n    據被告於警詢中供承在卷，爰不予沒收，附此敘明。\n三、依刑事訴訟法第449 條第1 項前段、第3 項、第454 條第2\n    項，刑法第320 條第1 項、第41條第1 項前段，刑法施行法\n    第1 條之1 第1 項、第2 項前段，逕以簡易判決處刑如主文\n    。\n四、如不服本件判決，得自收受送達之日起10日內，向本院提起\n    上訴狀，上訴於本院管轄之第二審地方法院合議庭。"
  },
  "search": "臺灣高雄地方法院刑事簡易判決100年度簡字第2793號聲請人臺灣高雄地方法院檢察署檢察官被告林世聰上列被告因竊盜案件，經檢察官聲請以簡易判決處刑（100年度偵字第12952號），本院判決如下：主文林世聰犯竊盜罪，處有期徒刑貳月，如易科罰金，以新臺幣壹仟元折算壹日。事實及理由一、本件犯罪事實及證據，除犯罪事實一、第2行「羅光雄」更正為「羅清淵」外，餘均引用檢察官聲請簡易判決處刑書之記載（如附件）。二、核被告林世聰所為，係犯刑法第320條第1項之竊盜罪。爰審酌被告正值青壯年，不思以正當方法謀取生活上所需，竟為貪圖不法利益，率爾以自備鑰匙竊取他人所有之機車，其犯罪之動機、手段、目的均非可取，惟被告犯後坦承犯行，態度尚可，又所竊之機車，業已返還被害人，損害已有減輕，有贓物認領保管單1紙在卷可稽，然被告前有毒品前科，素行不佳，兼衡其自稱國中肄業、家境勉持之智識程度與生活狀況等上開被告個人具體之行為人責任基礎之一切情狀，量處如主文所示之刑，並諭知易科罰金之折算標準，以資警惕。至扣案之鑰匙1支，為被告拾獲之物，並非被告所有，業據被告於警詢中供承在卷，爰不予沒收，附此敘明。三、依刑事訴訟法第449條第1項前段、第3項、第454條第2項，刑法第320條第1項、第41條第1項前段，刑法施行法第1條之1第1項、第2項前段，逕以簡易判決處刑如主文。四、如不服本件判決，得自收受送達之日起10日內，向本院提起上訴狀，上訴於本院管轄之第二審地方法院合議庭。中華民國100年5月23日高雄簡易庭法官陳采葳以上正本證明與原本無異。如不服本判決應於判決送達之日起10日內向本院提出上訴書狀。中華民國100年5月23日書記官馮欽鳳附錄本判決論罪之法條：刑法第320條第1項意圖為自己或第三人不法之所有，而竊取他人之動產者，為竊盜罪，處5年以下有期徒刑、拘役或5百元（新臺幣1萬5千元）以下罰金。",
  "characters": {
    "judges": [
      "陳采葳"
    ],
    "prosecutors": [

    ],
    "lawyers": [

    ],
    "clerks": [
      "馮欽鳳"
    ],
    "plaintiffs": [

    ],
    "defendants": [
      "林世聰"
    ],
    "prosecutor_office": [
      "臺灣高雄地方法院檢察署檢察官"
    ],
    "creditors": [

    ],
    "debtors": [

    ],
    "judicial_associate_officer": [

    ]
  },
  "adjudged_at": "2011-05-23",
  "created_at": "2016-02-12 03:44:17",
  "updated_at": "2016-02-12 03:44:17"
}