{
  "identify": "KSD-100-簡-2304-20110523-1",
  "court": {
    "name": "臺灣高雄地方法院",
    "code": "KSD"
  },
  "division": {
    "name": "刑事",
    "code": "M"
  },
  "year": 100,
  "word": "簡",
  "number": "2304",
  "jcheck": "1",
  "reason": "竊盜",
  "content": "臺灣高雄地方法院刑事簡易判決         100年度簡字第2304號\n聲  請  人  臺灣高雄地方法院檢察署檢察官\n被      告  宋佳蓉\n上列被告因竊盜案件，經檢察官聲請以簡易判決處刑（100年度速\n偵字第107 號），本院判決如下：\n    主      文\n宋佳蓉犯竊盜罪，共貳罪，各處拘役拾日，如易科罰金，均以\n新臺幣壹仟元折算壹日。應執行拘役伍拾日，如易科罰金，以新\n臺幣壹仟元折算壹日。緩刑貳年，並向公庫支付新臺幣捌仟元。\n    事實及理由\n一、本件犯罪事實及證據，除犯罪事實欄一4 ～5 行「測速器1\n    支（價值約2990元）得手」應補充為「測速器1 支（價值約\n    2,990 元）及現金至少120 元得手」、第7 ～8 行「福特汽\n    車1 本」應更正為「福特汽車說明書1 本」外，餘均引用檢\n    察官聲請簡易判決處刑書所載（如附件）。\n二、核被告宋佳蓉所為，均係犯刑法第320 條第1 項之竊盜罪。\n    其先後2 次竊盜犯行，犯意各別、行為互殊，應予分論併罰\n    。爰審酌被告為貪圖不法利益，竟率爾竊取他人財物，其犯\n    罪之動機、手段、目的均非可取，且其前於99年間甫因竊盜\n    犯行，經臺灣高雄地方法院檢察署檢察官以99年度偵字第36\n    970 號為職權不起訴處分確定，此品行資料有臺灣高等法院\n    被告前案紀錄表1 份在卷可查，竟再為本件犯行，惟念其尚\n    知坦承犯行，復衡酌其所竊財物之價值（2 次犯行共計至少\n    新臺幣〈下同〉7,100 元），並業據告訴人陳寬鴻及被害人\n    潘紀燦分別領回，有贓物認領保管單2 紙在卷可查，犯罪所\n    生損害已稍有減輕，兼衡其自稱不識字、家境貧寒並領有輕\n    度智障身心障礙手冊之智識程度與生活狀況等上開被告個人\n    具體之行為人責任基礎之一切情狀，分別量處如主文所示之\n    刑，併均諭知易科罰金之折算標準，並定其應執行之刑及易\n    科罰金之折算標準。又本件被告未曾因故意犯罪受有期徒刑\n    以上刑之宣告，有前揭前案紀錄表在卷可佐，其於犯後已坦\n    承犯行並知悉所為實屬不該，念其經此教訓後，應知所警惕\n    ，本院因認所宣告之刑以暫不執行為適當，併諭知緩刑2 年\n    ，以啟自新，並命被告應給付8,000 元予公庫，以維法治。\n三、依刑事訴訟法第449 條第1 項前段、第3 項、第454 條第2\n    項，刑法第320 條第1 項、第41條第1 項前段、第51條第6\n    款、第74條第1 項第1 款、第2 項第4 款，刑法施行法第1\n    條之1 第1 項、第2 項前段，逕以簡易判決處刑如主文。\n四、如不服本判決，應於判決送達之日起10日內，向本院提出上\n    訴狀。\n中    華    民    國  100     年    5     月    23   日\n                  高雄簡易庭  法  官  陳薏\n以上正本證明與原本無異。\n如不服本判決，應於送達之日起10日內向本院提出上訴書狀。\n中    華    民    國  100     年    5     月    23    日\n                              書記官  戴金龍\n附錄本案論罪科刑法條：\n刑法第320條第1項\n意圖為自己或第三人不法之所有，而竊取他人之動產者，為竊盜\n罪，處5 年以下有期徒刑、拘役或5 百元以下罰金。\n附件：\n臺灣高雄地方法院檢察署檢察官聲請簡易判決處刑書\n                                    100年度速偵字第107號\n    被      告  宋佳蓉  女  20歲（民國○○年○ 月○○日生）\n                        住高雄市鳳山區○○○街62號2 樓\n                        國民身分證統一編號：Ｚ000000000號\n上被告因竊盜案件，已經偵查終結，認為宜以簡易判決處刑，茲\n敘述犯罪事實及證據並所犯法條如下：\n        犯罪事實\n一、宋佳蓉意圖為自己不法之所有，先於民國100 年3 月16日2\n    時34分許，在高雄市○○區○○街26號前，徒手竊取陳寬鴻\n    所有、放置在車牌號碼6060-GP 號自用小客車內之衛星導航\n    1支（價值約新台幣【下同】3990 元）、測速器1 支（價值\n    約2990元）得手；再於同年月30日2 時15分許，在高雄市○\n    ○區○○街34號對面，徒手竊取潘紀燦所有、放置在車牌號\n    碼ON-4466 號自用小客車內之測速器1 支、眼鏡1 付、福特\n    汽車1 本、筷子1 雙、錄音帶1 卷等物得手，並適為巡邏員\n    警當場查獲，再循線查悉上情。\n二、案經高雄市政府警察局鳳山分局移送偵辦。\n            證據並所犯法條\n一、訊據被告宋佳蓉對於上開事實坦白承認，核與被害人陳寬鴻\n    與潘紀燦於警詢時指述之情節相符，復有高雄市政府警察局\n    鳳山分局文山派出所搜索扣押筆錄1 份、扣押物品目錄表2\n    紙、贓物認領保管單2 紙、查獲現場照片4 張及監視器畫面\n    4 紙在卷可佐。本件事證明確，是被告竊盜犯行堪以認定。\n二、核被告所為，係犯刑法第320 條第1 項之竊盜罪嫌。又被告\n    所犯上開2 次竊盜犯行，犯意各別，行為互殊，請分論併罰\n    。\n三、依刑事訴訟法第451 條第1 項聲請逕以簡易判決處刑。\n    此  致\n臺灣高雄地方法院\n中    華    民    國   100    年    4     月    1     日\n                              檢  察  官  吳正中\n上正本證明與原本無異\n中    華    民    國   100    年    4     月    8     日\n                              書  記  官  林穎慧\n所犯法條：\n中華民國刑法第320條\n（普通竊盜罪、竊佔罪）\n意圖為自己或第三人不法之所有，而竊取他人之動產者，為竊盜\n罪，處 5 年以下有期徒刑、拘役或 5 百元以下罰金。\n意圖為自己或第三人不法之利益，而竊佔他人之不動產者，依前\n項之規定處斷。\n前二項之未遂犯罰之。\n附記事項：本件係依刑事訴訟法簡易程序辦理，法院簡易庭得不\n傳喚被告、輔佐人、告訴人、告發人等出庭即以簡易判決處刑；\n被告、被害人、告訴人等對告訴乃論案件如已達成民事和解而要\n撤回告訴或對非告訴乃論案件認有受傳喚到庭陳述意見之必要時\n，請即另以書狀向簡易法庭陳述或請求傳訊。",
  "structure": {
    "main": "宋佳蓉犯竊盜罪，共貳罪，各處拘役拾日，如易科罰金，均以\n新臺幣壹仟元折算壹日。應執行拘役伍拾日，如易科罰金，以新\n臺幣壹仟元折算壹日。緩刑貳年，並向公庫支付新臺幣捌仟元。",
    "fact": "一、本件犯罪事實及證據，除犯罪事實欄一4 ～5 行「測速器1\n    支（價值約2990元）得手」應補充為「測速器1 支（價值約\n    2,990 元）及現金至少120 元得手」、第7 ～8 行「福特汽\n    車1 本」應更正為「福特汽車說明書1 本」外，餘均引用檢\n    察官聲請簡易判決處刑書所載（如附件）。\n二、核被告宋佳蓉所為，均係犯刑法第320 條第1 項之竊盜罪。\n    其先後2 次竊盜犯行，犯意各別、行為互殊，應予分論併罰\n    。爰審酌被告為貪圖不法利益，竟率爾竊取他人財物，其犯\n    罪之動機、手段、目的均非可取，且其前於99年間甫因竊盜\n    犯行，經臺灣高雄地方法院檢察署檢察官以99年度偵字第36\n    970 號為職權不起訴處分確定，此品行資料有臺灣高等法院\n    被告前案紀錄表1 份在卷可查，竟再為本件犯行，惟念其尚\n    知坦承犯行，復衡酌其所竊財物之價值（2 次犯行共計至少\n    新臺幣〈下同〉7,100 元），並業據告訴人陳寬鴻及被害人\n    潘紀燦分別領回，有贓物認領保管單2 紙在卷可查，犯罪所\n    生損害已稍有減輕，兼衡其自稱不識字、家境貧寒並領有輕\n    度智障身心障礙手冊之智識程度與生活狀況等上開被告個人\n    具體之行為人責任基礎之一切情狀，分別量處如主文所示之\n    刑，併均諭知易科罰金之折算標準，並定其應執行之刑及易\n    科罰金之折算標準。又本件被告未曾因故意犯罪受有期徒刑\n    以上刑之宣告，有前揭前案紀錄表在卷可佐，其於犯後已坦\n    承犯行並知悉所為實屬不該，念其經此教訓後，應知所警惕\n    ，本院因認所宣告之刑以暫不執行為適當，併諭知緩刑2 年\n    ，以啟自新，並命被告應給付8,000 元予公庫，以維法治。\n三、依刑事訴訟法第449 條第1 項前段、第3 項、第454 條第2\n    項，刑法第320 條第1 項、第41條第1 項前段、第51條第6\n    款、第74條第1 項第1 款、第2 項第4 款，刑法施行法第1\n    條之1 第1 項、第2 項前段，逕以簡易判決處刑如主文。\n四、如不服本判決，應於判決送達之日起10日內，向本院提出上\n    訴狀。",
    "reason": "一、本件犯罪事實及證據，除犯罪事實欄一4 ～5 行「測速器1\n    支（價值約2990元）得手」應補充為「測速器1 支（價值約\n    2,990 元）及現金至少120 元得手」、第7 ～8 行「福特汽\n    車1 本」應更正為「福特汽車說明書1 本」外，餘均引用檢\n    察官聲請簡易判決處刑書所載（如附件）。\n二、核被告宋佳蓉所為，均係犯刑法第320 條第1 項之竊盜罪。\n    其先後2 次竊盜犯行，犯意各別、行為互殊，應予分論併罰\n    。爰審酌被告為貪圖不法利益，竟率爾竊取他人財物，其犯\n    罪之動機、手段、目的均非可取，且其前於99年間甫因竊盜\n    犯行，經臺灣高雄地方法院檢察署檢察官以99年度偵字第36\n    970 號為職權不起訴處分確定，此品行資料有臺灣高等法院\n    被告前案紀錄表1 份在卷可查，竟再為本件犯行，惟念其尚\n    知坦承犯行，復衡酌其所竊財物之價值（2 次犯行共計至少\n    新臺幣〈下同〉7,100 元），並業據告訴人陳寬鴻及被害人\n    潘紀燦分別領回，有贓物認領保管單2 紙在卷可查，犯罪所\n    生損害已稍有減輕，兼衡其自稱不識字、家境貧寒並領有輕\n    度智障身心障礙手冊之智識程度與生活狀況等上開被告個人\n    具體之行為人責任基礎之一切情狀，分別量處如主文所示之\n    刑，併均諭知易科罰金之折算標準，並定其應執行之刑及易\n    科罰金之折算標準。又本件被告未曾因故意犯罪受有期徒刑\n    以上刑之宣告，有前揭前案紀錄表在卷可佐，其於犯後已坦\n    承犯行並知悉所為實屬不該，念其經此教訓後，應知所警惕\n    ，本院因認所宣告之刑以暫不執行為適當，併諭知緩刑2 年\n    ，以啟自新，並命被告應給付8,000 元予公庫，以維法治。\n三、依刑事訴訟法第449 條第1 項前段、第3 項、第454 條第2\n    項，刑法第320 條第1 項、第41條第1 項前段、第51條第6\n    款、第74條第1 項第1 款、第2 項第4 款，刑法施行法第1\n    條之1 第1 項、第2 項前段，逕以簡易判決處刑如主文。\n四、如不服本判決，應於判決送達之日起10日內，向本院提出上\n    訴狀。"
  },
  "search": "臺灣高雄地方法院刑事簡易判決100年度簡字第2304號聲請人臺灣高雄地方法院檢察署檢察官被告宋佳蓉上列被告因竊盜案件，經檢察官聲請以簡易判決處刑（100年度速偵字第107號），本院判決如下：主文宋佳蓉犯竊盜罪，共貳罪，各處拘役拾日，如易科罰金，均以新臺幣壹仟元折算壹日。應執行拘役伍拾日，如易科罰金，以新臺幣壹仟元折算壹日。緩刑貳年，並向公庫支付新臺幣捌仟元。事實及理由一、本件犯罪事實及證據，除犯罪事實欄一4～5行「測速器1支（價值約2990元）得手」應補充為「測速器1支（價值約2,990元）及現金至少120元得手」、第7～8行「福特汽車1本」應更正為「福特汽車說明書1本」外，餘均引用檢察官聲請簡易判決處刑書所載（如附件）。二、核被告宋佳蓉所為，均係犯刑法第320條第1項之竊盜罪。其先後2次竊盜犯行，犯意各別、行為互殊，應予分論併罰。爰審酌被告為貪圖不法利益，竟率爾竊取他人財物，其犯罪之動機、手段、目的均非可取，且其前於99年間甫因竊盜犯行，經臺灣高雄地方法院檢察署檢察官以99年度偵字第36970號為職權不起訴處分確定，此品行資料有臺灣高等法院被告前案紀錄表1份在卷可查，竟再為本件犯行，惟念其尚知坦承犯行，復衡酌其所竊財物之價值（2次犯行共計至少新臺幣〈下同〉7,100元），並業據告訴人陳寬鴻及被害人潘紀燦分別領回，有贓物認領保管單2紙在卷可查，犯罪所生損害已稍有減輕，兼衡其自稱不識字、家境貧寒並領有輕度智障身心障礙手冊之智識程度與生活狀況等上開被告個人具體之行為人責任基礎之一切情狀，分別量處如主文所示之刑，併均諭知易科罰金之折算標準，並定其應執行之刑及易科罰金之折算標準。又本件被告未曾因故意犯罪受有期徒刑以上刑之宣告，有前揭前案紀錄表在卷可佐，其於犯後已坦承犯行並知悉所為實屬不該，念其經此教訓後，應知所警惕，本院因認所宣告之刑以暫不執行為適當，併諭知緩刑2年，以啟自新，並命被告應給付8,000元予公庫，以維法治。三、依刑事訴訟法第449條第1項前段、第3項、第454條第2項，刑法第320條第1項、第41條第1項前段、第51條第6款、第74條第1項第1款、第2項第4款，刑法施行法第1條之1第1項、第2項前段，逕以簡易判決處刑如主文。四、如不服本判決，應於判決送達之日起10日內，向本院提出上訴狀。中華民國100年5月23日高雄簡易庭法官陳薏以上正本證明與原本無異。如不服本判決，應於送達之日起10日內向本院提出上訴書狀。中華民國100年5月23日書記官戴金龍附錄本案論罪科刑法條：刑法第320條第1項意圖為自己或第三人不法之所有，而竊取他人之動產者，為竊盜罪，處5年以下有期徒刑、拘役或5百元以下罰金。附件：臺灣高雄地方法院檢察署檢察官聲請簡易判決處刑書100年度速偵字第107號被告宋佳蓉女20歲（民國○○年○月○○日生）住高雄市鳳山區○○○街62號2樓國民身分證統一編號：Ｚ000000000號上被告因竊盜案件，已經偵查終結，認為宜以簡易判決處刑，茲敘述犯罪事實及證據並所犯法條如下：犯罪事實一、宋佳蓉意圖為自己不法之所有，先於民國100年3月16日2時34分許，在高雄市○○區○○街26號前，徒手竊取陳寬鴻所有、放置在車牌號碼6060-GP號自用小客車內之衛星導航1支（價值約新台幣【下同】3990元）、測速器1支（價值約2990元）得手；再於同年月30日2時15分許，在高雄市○○區○○街34號對面，徒手竊取潘紀燦所有、放置在車牌號碼ON-4466號自用小客車內之測速器1支、眼鏡1付、福特汽車1本、筷子1雙、錄音帶1卷等物得手，並適為巡邏員警當場查獲，再循線查悉上情。二、案經高雄市政府警察局鳳山分局移送偵辦。證據並所犯法條一、訊據被告宋佳蓉對於上開事實坦白承認，核與被害人陳寬鴻與潘紀燦於警詢時指述之情節相符，復有高雄市政府警察局鳳山分局文山派出所搜索扣押筆錄1份、扣押物品目錄表2紙、贓物認領保管單2紙、查獲現場照片4張及監視器畫面4紙在卷可佐。本件事證明確，是被告竊盜犯行堪以認定。二、核被告所為，係犯刑法第320條第1項之竊盜罪嫌。又被告所犯上開2次竊盜犯行，犯意各別，行為互殊，請分論併罰。三、依刑事訴訟法第451條第1項聲請逕以簡易判決處刑。此致臺灣高雄地方法院中華民國100年4月1日檢察官吳正中上正本證明與原本無異中華民國100年4月8日書記官林穎慧所犯法條：中華民國刑法第320條（普通竊盜罪、竊佔罪）意圖為自己或第三人不法之所有，而竊取他人之動產者，為竊盜罪，處5年以下有期徒刑、拘役或5百元以下罰金。意圖為自己或第三人不法之利益，而竊佔他人之不動產者，依前項之規定處斷。前二項之未遂犯罰之。附記事項：本件係依刑事訴訟法簡易程序辦理，法院簡易庭得不傳喚被告、輔佐人、告訴人、告發人等出庭即以簡易判決處刑；被告、被害人、告訴人等對告訴乃論案件如已達成民事和解而要撤回告訴或對非告訴乃論案件認有受傳喚到庭陳述意見之必要時，請即另以書狀向簡易法庭陳述或請求傳訊。",
  "characters": {
    "judges": [
      "陳薏"
    ],
    "prosecutors": [

    ],
    "lawyers": [

    ],
    "clerks": [
      "戴金龍"
    ],
    "plaintiffs": [

    ],
    "defendants": [
      "宋佳蓉",
      "宋佳蓉  女  20歲（民國○○年○ 月○○日生）"
    ],
    "prosecutor_office": [
      "臺灣高雄地方法院檢察署檢察官"
    ],
    "creditors": [

    ],
    "debtors": [

    ],
    "judicial_associate_officer": [

    ]
  },
  "adjudged_at": "2011-05-23",
  "created_at": "2016-02-12 03:26:31",
  "updated_at": "2016-02-12 03:26:31"
}