{
  "identify": "PCD-100-簡上-493-20110722-2",
  "court": {
    "name": "臺灣新北地方法院",
    "code": "PCD"
  },
  "division": {
    "name": "刑事",
    "code": "M"
  },
  "year": 100,
  "word": "簡上",
  "number": "493",
  "jcheck": "2",
  "reason": "妨害公務",
  "content": "臺灣板橋地方法院刑事裁定            100年度簡上字第493號\n上  訴  人\n即  被  告  蘇美文\n上列上訴人即被告因妨害公務案件，不服本院100 年度簡上字第\n493 號，中華民國100 年6 月30日所為之第二審判決（聲請簡易\n判決處刑案號：100 年度偵字第1305號），提起上訴，本院裁定\n如下：\n    主  文\n上訴駁回。\n    理  由\n一、按原審（即第二審）法院認為上訴不合法律上之程式或法律\n    上不應准許或其上訴權已經喪失者，應以裁定駁回之。刑事\n    訴訟法第384 條前段定有明文。次按，不服地方法院之第一\n    審判決而上訴者，應向管轄第二審之高等法院為之。不服高\n    等法院之第二審或第一審判決而上訴者，應向最高法院為之\n    。同法第361 條第1 項、第375 條第1 項亦分別定有明文。\n    從而，不服地方法院之第二審判決者，即不得上訴，此觀刑\n    事訴訟法第7 編「簡易程序」，並無關於不服地方法院之第\n    二審判決而提起上訴之規定亦明。是此種不得上訴第三審之\n    案件，於第二審法院宣示或送達判決時，即告確定。倘對於\n    此種法律規定不得上訴於第三審之案件，而提起上訴者，即\n    屬違背法律上之程式（最高法院21年抗字第33號判例意旨參\n    照）。\n二、經查，本件上訴人即被告蘇美文被訴妨害公務案件，經本院\n    第一審依簡易程序，以100 年度簡字第2749號刑事簡易判決\n    判處拘役40日、20日，應執行拘役50日，並均諭知如易科罰\n    金，以新臺幣1000元折算1 日，上訴人不服提起上訴，經本\n    院管轄第二審之合議庭認上訴人上訴逾期，不經言詞辯論，\n    以100 年度簡上字第493 號刑事判決駁回上訴，並於100 年\n    7 月7 日將該駁回上訴之第二審判決合法送達與被告之事實\n    ，有本院100 年度簡字第2749號刑事簡易判決書、100 年度\n    簡上字第493 號刑事判決書各1 件及本院送達證書2 紙在卷\n    可稽。從而，本案屬不得上訴於第三審之案件，業於本院合\n    法送達第二審判決與上訴人時，即告確定。上訴人猶對本院\n    所為之第二審確定判決聲明不服而提起上訴，揆諸前揭說明\n    ，其上訴即屬不合法律上之程式，應以裁定駁回之。\n據上論斷，應依刑事訴訟法第384 條前段，裁定如主文。\n中    華    民    國    100   年    7     月    22    日\n                  刑事第八庭審判長法  官  陳鴻清\n                                  法  官  劉安榕\n                                  法  官  賴彥魁\n以上正本證明與原本無異。\n本件不得抗告。\n                                  書記官  楊文祥\n中    華    民    國    100   年    7     月    22    日",
  "structure": {
    "main": "上訴駁回。",
    "reason": "一、按原審（即第二審）法院認為上訴不合法律上之程式或法律\n    上不應准許或其上訴權已經喪失者，應以裁定駁回之。刑事\n    訴訟法第384 條前段定有明文。次按，不服地方法院之第一\n    審判決而上訴者，應向管轄第二審之高等法院為之。不服高\n    等法院之第二審或第一審判決而上訴者，應向最高法院為之\n    。同法第361 條第1 項、第375 條第1 項亦分別定有明文。\n    從而，不服地方法院之第二審判決者，即不得上訴，此觀刑\n    事訴訟法第7 編「簡易程序」，並無關於不服地方法院之第\n    二審判決而提起上訴之規定亦明。是此種不得上訴第三審之\n    案件，於第二審法院宣示或送達判決時，即告確定。倘對於\n    此種法律規定不得上訴於第三審之案件，而提起上訴者，即\n    屬違背法律上之程式（最高法院21年抗字第33號判例意旨參\n    照）。\n二、經查，本件上訴人即被告蘇美文被訴妨害公務案件，經本院\n    第一審依簡易程序，以100 年度簡字第2749號刑事簡易判決\n    判處拘役40日、20日，應執行拘役50日，並均諭知如易科罰\n    金，以新臺幣1000元折算1 日，上訴人不服提起上訴，經本\n    院管轄第二審之合議庭認上訴人上訴逾期，不經言詞辯論，\n    以100 年度簡上字第493 號刑事判決駁回上訴，並於100 年\n    7 月7 日將該駁回上訴之第二審判決合法送達與被告之事實\n    ，有本院100 年度簡字第2749號刑事簡易判決書、100 年度\n    簡上字第493 號刑事判決書各1 件及本院送達證書2 紙在卷\n    可稽。從而，本案屬不得上訴於第三審之案件，業於本院合\n    法送達第二審判決與上訴人時，即告確定。上訴人猶對本院\n    所為之第二審確定判決聲明不服而提起上訴，揆諸前揭說明\n    ，其上訴即屬不合法律上之程式，應以裁定駁回之。\n據上論斷，應依刑事訴訟法第384 條前段，裁定如主文。"
  },
  "search": "臺灣板橋地方法院刑事裁定100年度簡上字第493號上訴人即被告蘇美文上列上訴人即被告因妨害公務案件，不服本院100年度簡上字第493號，中華民國100年6月30日所為之第二審判決（聲請簡易判決處刑案號：100年度偵字第1305號），提起上訴，本院裁定如下：主文上訴駁回。理由一、按原審（即第二審）法院認為上訴不合法律上之程式或法律上不應准許或其上訴權已經喪失者，應以裁定駁回之。刑事訴訟法第384條前段定有明文。次按，不服地方法院之第一審判決而上訴者，應向管轄第二審之高等法院為之。不服高等法院之第二審或第一審判決而上訴者，應向最高法院為之。同法第361條第1項、第375條第1項亦分別定有明文。從而，不服地方法院之第二審判決者，即不得上訴，此觀刑事訴訟法第7編「簡易程序」，並無關於不服地方法院之第二審判決而提起上訴之規定亦明。是此種不得上訴第三審之案件，於第二審法院宣示或送達判決時，即告確定。倘對於此種法律規定不得上訴於第三審之案件，而提起上訴者，即屬違背法律上之程式（最高法院21年抗字第33號判例意旨參照）。二、經查，本件上訴人即被告蘇美文被訴妨害公務案件，經本院第一審依簡易程序，以100年度簡字第2749號刑事簡易判決判處拘役40日、20日，應執行拘役50日，並均諭知如易科罰金，以新臺幣1000元折算1日，上訴人不服提起上訴，經本院管轄第二審之合議庭認上訴人上訴逾期，不經言詞辯論，以100年度簡上字第493號刑事判決駁回上訴，並於100年7月7日將該駁回上訴之第二審判決合法送達與被告之事實，有本院100年度簡字第2749號刑事簡易判決書、100年度簡上字第493號刑事判決書各1件及本院送達證書2紙在卷可稽。從而，本案屬不得上訴於第三審之案件，業於本院合法送達第二審判決與上訴人時，即告確定。上訴人猶對本院所為之第二審確定判決聲明不服而提起上訴，揆諸前揭說明，其上訴即屬不合法律上之程式，應以裁定駁回之。據上論斷，應依刑事訴訟法第384條前段，裁定如主文。中華民國100年7月22日刑事第八庭審判長法官陳鴻清法官劉安榕法官賴彥魁以上正本證明與原本無異。本件不得抗告。書記官楊文祥中華民國100年7月22日",
  "characters": {
    "judges": [
      "陳鴻清",
      "劉安榕",
      "賴彥魁"
    ],
    "prosecutors": [

    ],
    "lawyers": [

    ],
    "clerks": [
      "楊文祥"
    ],
    "plaintiffs": [

    ],
    "defendants": [
      "蘇美文"
    ],
    "prosecutor_office": [

    ],
    "creditors": [

    ],
    "debtors": [

    ],
    "judicial_associate_officer": [

    ]
  },
  "adjudged_at": "2011-07-22",
  "created_at": "2016-02-14 04:05:19",
  "updated_at": "2016-02-14 04:05:19"
}