{
  "identify": "TCD-100-訴-1158-20110722-1",
  "court": {
    "name": "臺灣臺中地方法院",
    "code": "TCD"
  },
  "division": {
    "name": "刑事",
    "code": "M"
  },
  "year": 100,
  "word": "訴",
  "number": "1158",
  "jcheck": "1",
  "reason": "毒品危害防制條例等",
  "content": "臺灣臺中地方法院刑事裁定             100年度訴字第1158號\n公  訴  人  臺灣臺中地方法院檢察署檢察官\n被      告  張樹忠\n指定辯護人  本院公設辯護人  蔡育萍\n上列被告因違反毒品危害防制條例案件，經檢察官提起公訴（\n99年度偵字第28670號、100年度偵字第1094、1326號、100年度\n毒偵字第143號），本院裁定如下：\n    主    文\n張樹忠自民國一百年七月二十七日起延長羈押貳月，並禁止接見\n、通信。\n    理    由\n一、按羈押被告，審判中不得逾3月。但有繼續羈押之必要者，\n    得於期間未滿前，經法院依第101條或第101條之1之規定訊\n    問被告後，以裁定延長之，刑事訴訟法第108條第1項前段定\n    有明文。\n二、經查，被告張樹忠前因違反毒品危害防制條例等案件，經本\n    院訊問及核閱相關卷證後，以被告涉犯毒品危害防制條例第\n    4條第1項、第2項、第8條第1項、第2項、第10條第1項、第2\n    項、藥事法第83條第1項、槍砲彈藥刀械管制條例第8條第4\n    項、第12條第4項、刑法第216條、第212條、第349條第1項\n    、第2項等罪，認犯罪嫌疑重大，尚有證人仍待訊問，有串\n    證之虞，且其中涉犯毒品危害防制條例第4條第1項、第2項\n    之販賣第一、二級毒品罪，為最輕本刑5年以上有期徒刑之\n    罪，有事實足認為有逃亡之虞，非予羈押，顯難進行審判、\n    執行，且有羈押必要，經本院於民國100年4月27日依刑事訴\n    訟法第101條第1項第1、2、3款之規定裁定執行羈押，並禁\n    止接見通信在案。茲因被告羈押期間即將屆滿，經本院訊問\n    後，認本件被告所犯，有證人黃啟水、楊錫鍊、張嘉惠、黃\n    彥、王茗富、呂家榮、盧幸宜、黃靖尊、林焜煌、蔡佩珊等\n    人分別於警詢、偵查及本院審理中之證述，及中山醫學大學\n    附設醫院檢驗科藥物檢測中心尿液檢驗報告、臺中市政府警\n    察局刑事警察大隊委託檢驗尿液代號與真實姓名對照表、法\n    務部調查局100年3月4日調科壹字第10023005740號鑑定書、\n    通訊監察譯文、雙向通聯紀錄、內政部警政署刑事警察局出\n    具之100年1月18日刑鑑字第1000001831號鑑定書，贓物認領\n    保管單、現場照片等證據附卷可稽。此外，並有電子磅秤1\n    臺、甲基安非他命7包、海洛因5包、白色馬自達（引擎號碼\n    ：00000000D）、黑色馬自達（車身號碼72F00197D、引擎號\n    碼00000000D）自小客車各1部、車牌號碼6359-WJ車牌2面、\n    偽造塑膠車牌7061-TF號2面、行動電話（序號：0000000\n    00000000、000000000000000）、行動電話（含SIM卡000\n    0000000號、序號00000000000000002號）、行動電話（含\n    SIM卡0000000000號、序號00000000000000號）各1支、土造\n    轉輪霰彈槍1支、霰彈3顆等物可資佐證，足見其犯罪嫌疑重\n    大，而其所涉犯販賣第一、二級毒品罪，為死刑、無期徒刑\n    及最輕本刑5年以上有期徒刑之罪，良以重罪常伴有逃亡、\n    滅證之高度可能，係趨吉避凶、脫免刑責、不甘受罰之基本\n    人性，倘一般正常之人，依其合理判斷，可認為該犯重罪嫌\n    疑重大之人具有逃亡或滅證之相當或然率存在（最高法院98\n    年度臺抗字第798號裁定意旨可資參照），認被告逃匿以規\n    避審判程序進行及刑罰執行之可能性甚高，有相當理由足認\n    為其有逃亡之虞，復有證人陳漢鴻、陳文豪仍待訊問，是羈\n    押之原因尚未消滅，而有刑事訴訟法第101條第1項第1、2、\n    3款之羈押原因，為確保日後本案之審理、執行，本院認仍\n    有繼續羈押被告及禁止接見通信之必要，應自100年7月27日\n    起延長羈押2月，並禁止接見、通信。\n三、爰依刑事訴訟法第108條第1項、第2項、第105條第3項裁定\n    如主文。\n中    華    民    國   100    年    7     月    22    日\n                  刑事第三庭  審判長法  官  張靜琪\n                                    法  官  李婉玉\n                                    法  官  黃麗玲\n上正本證明與原本無異。\n如不服本裁定，應於送達後五日內，向本院提出抗告狀。\n中    華    民    國   100    年    7     月    22    日\n                                    書記官  黃毅皓",
  "structure": {
    "main": "張樹忠自民國一百年七月二十七日起延長羈押貳月，並禁止接見\n、通信。",
    "reason": "一、按羈押被告，審判中不得逾3月。但有繼續羈押之必要者，\n    得於期間未滿前，經法院依第101條或第101條之1之規定訊\n    問被告後，以裁定延長之，刑事訴訟法第108條第1項前段定\n    有明文。\n二、經查，被告張樹忠前因違反毒品危害防制條例等案件，經本\n    院訊問及核閱相關卷證後，以被告涉犯毒品危害防制條例第\n    4條第1項、第2項、第8條第1項、第2項、第10條第1項、第2\n    項、藥事法第83條第1項、槍砲彈藥刀械管制條例第8條第4\n    項、第12條第4項、刑法第216條、第212條、第349條第1項\n    、第2項等罪，認犯罪嫌疑重大，尚有證人仍待訊問，有串\n    證之虞，且其中涉犯毒品危害防制條例第4條第1項、第2項\n    之販賣第一、二級毒品罪，為最輕本刑5年以上有期徒刑之\n    罪，有事實足認為有逃亡之虞，非予羈押，顯難進行審判、\n    執行，且有羈押必要，經本院於民國100年4月27日依刑事訴\n    訟法第101條第1項第1、2、3款之規定裁定執行羈押，並禁\n    止接見通信在案。茲因被告羈押期間即將屆滿，經本院訊問\n    後，認本件被告所犯，有證人黃啟水、楊錫鍊、張嘉惠、黃\n    彥、王茗富、呂家榮、盧幸宜、黃靖尊、林焜煌、蔡佩珊等\n    人分別於警詢、偵查及本院審理中之證述，及中山醫學大學\n    附設醫院檢驗科藥物檢測中心尿液檢驗報告、臺中市政府警\n    察局刑事警察大隊委託檢驗尿液代號與真實姓名對照表、法\n    務部調查局100年3月4日調科壹字第10023005740號鑑定書、\n    通訊監察譯文、雙向通聯紀錄、內政部警政署刑事警察局出\n    具之100年1月18日刑鑑字第1000001831號鑑定書，贓物認領\n    保管單、現場照片等證據附卷可稽。此外，並有電子磅秤1\n    臺、甲基安非他命7包、海洛因5包、白色馬自達（引擎號碼\n    ：00000000D）、黑色馬自達（車身號碼72F00197D、引擎號\n    碼00000000D）自小客車各1部、車牌號碼6359-WJ車牌2面、\n    偽造塑膠車牌7061-TF號2面、行動電話（序號：0000000\n    00000000、000000000000000）、行動電話（含SIM卡000\n    0000000號、序號00000000000000002號）、行動電話（含\n    SIM卡0000000000號、序號00000000000000號）各1支、土造\n    轉輪霰彈槍1支、霰彈3顆等物可資佐證，足見其犯罪嫌疑重\n    大，而其所涉犯販賣第一、二級毒品罪，為死刑、無期徒刑\n    及最輕本刑5年以上有期徒刑之罪，良以重罪常伴有逃亡、\n    滅證之高度可能，係趨吉避凶、脫免刑責、不甘受罰之基本\n    人性，倘一般正常之人，依其合理判斷，可認為該犯重罪嫌\n    疑重大之人具有逃亡或滅證之相當或然率存在（最高法院98\n    年度臺抗字第798號裁定意旨可資參照），認被告逃匿以規\n    避審判程序進行及刑罰執行之可能性甚高，有相當理由足認\n    為其有逃亡之虞，復有證人陳漢鴻、陳文豪仍待訊問，是羈\n    押之原因尚未消滅，而有刑事訴訟法第101條第1項第1、2、\n    3款之羈押原因，為確保日後本案之審理、執行，本院認仍\n    有繼續羈押被告及禁止接見通信之必要，應自100年7月27日\n    起延長羈押2月，並禁止接見、通信。\n三、爰依刑事訴訟法第108條第1項、第2項、第105條第3項裁定\n    如主文。"
  },
  "search": "臺灣臺中地方法院刑事裁定100年度訴字第1158號公訴人臺灣臺中地方法院檢察署檢察官被告張樹忠指定辯護人本院公設辯護人蔡育萍上列被告因違反毒品危害防制條例案件，經檢察官提起公訴（99年度偵字第28670號、100年度偵字第1094、1326號、100年度毒偵字第143號），本院裁定如下：主文張樹忠自民國一百年七月二十七日起延長羈押貳月，並禁止接見、通信。理由一、按羈押被告，審判中不得逾3月。但有繼續羈押之必要者，得於期間未滿前，經法院依第101條或第101條之1之規定訊問被告後，以裁定延長之，刑事訴訟法第108條第1項前段定有明文。二、經查，被告張樹忠前因違反毒品危害防制條例等案件，經本院訊問及核閱相關卷證後，以被告涉犯毒品危害防制條例第4條第1項、第2項、第8條第1項、第2項、第10條第1項、第2項、藥事法第83條第1項、槍砲彈藥刀械管制條例第8條第4項、第12條第4項、刑法第216條、第212條、第349條第1項、第2項等罪，認犯罪嫌疑重大，尚有證人仍待訊問，有串證之虞，且其中涉犯毒品危害防制條例第4條第1項、第2項之販賣第一、二級毒品罪，為最輕本刑5年以上有期徒刑之罪，有事實足認為有逃亡之虞，非予羈押，顯難進行審判、執行，且有羈押必要，經本院於民國100年4月27日依刑事訴訟法第101條第1項第1、2、3款之規定裁定執行羈押，並禁止接見通信在案。茲因被告羈押期間即將屆滿，經本院訊問後，認本件被告所犯，有證人黃啟水、楊錫鍊、張嘉惠、黃彥、王茗富、呂家榮、盧幸宜、黃靖尊、林焜煌、蔡佩珊等人分別於警詢、偵查及本院審理中之證述，及中山醫學大學附設醫院檢驗科藥物檢測中心尿液檢驗報告、臺中市政府警察局刑事警察大隊委託檢驗尿液代號與真實姓名對照表、法務部調查局100年3月4日調科壹字第10023005740號鑑定書、通訊監察譯文、雙向通聯紀錄、內政部警政署刑事警察局出具之100年1月18日刑鑑字第1000001831號鑑定書，贓物認領保管單、現場照片等證據附卷可稽。此外，並有電子磅秤1臺、甲基安非他命7包、海洛因5包、白色馬自達（引擎號碼：00000000D）、黑色馬自達（車身號碼72F00197D、引擎號碼00000000D）自小客車各1部、車牌號碼6359-WJ車牌2面、偽造塑膠車牌7061-TF號2面、行動電話（序號：000000000000000、000000000000000）、行動電話（含SIM卡0000000000號、序號00000000000000002號）、行動電話（含SIM卡0000000000號、序號00000000000000號）各1支、土造轉輪霰彈槍1支、霰彈3顆等物可資佐證，足見其犯罪嫌疑重大，而其所涉犯販賣第一、二級毒品罪，為死刑、無期徒刑及最輕本刑5年以上有期徒刑之罪，良以重罪常伴有逃亡、滅證之高度可能，係趨吉避凶、脫免刑責、不甘受罰之基本人性，倘一般正常之人，依其合理判斷，可認為該犯重罪嫌疑重大之人具有逃亡或滅證之相當或然率存在（最高法院98年度臺抗字第798號裁定意旨可資參照），認被告逃匿以規避審判程序進行及刑罰執行之可能性甚高，有相當理由足認為其有逃亡之虞，復有證人陳漢鴻、陳文豪仍待訊問，是羈押之原因尚未消滅，而有刑事訴訟法第101條第1項第1、2、3款之羈押原因，為確保日後本案之審理、執行，本院認仍有繼續羈押被告及禁止接見通信之必要，應自100年7月27日起延長羈押2月，並禁止接見、通信。三、爰依刑事訴訟法第108條第1項、第2項、第105條第3項裁定如主文。中華民國100年7月22日刑事第三庭審判長法官張靜琪法官李婉玉法官黃麗玲上正本證明與原本無異。如不服本裁定，應於送達後五日內，向本院提出抗告狀。中華民國100年7月22日書記官黃毅皓",
  "characters": {
    "judges": [
      "張靜琪",
      "李婉玉",
      "黃麗玲"
    ],
    "prosecutors": [

    ],
    "lawyers": [

    ],
    "clerks": [

    ],
    "plaintiffs": [

    ],
    "defendants": [
      "張樹忠"
    ],
    "prosecutor_office": [
      "臺灣臺中地方法院檢察署檢察官"
    ],
    "creditors": [

    ],
    "debtors": [

    ],
    "judicial_associate_officer": [

    ]
  },
  "adjudged_at": "2011-07-22",
  "created_at": "2016-02-14 04:04:58",
  "updated_at": "2016-02-14 04:04:58"
}