{
  "identify": "TPD-91-簡-3917-20021210-1",
  "court": {
    "name": "臺灣臺北地方法院",
    "code": "TPD"
  },
  "division": {
    "name": "刑事",
    "code": "M"
  },
  "year": 91,
  "word": "簡",
  "number": "3917",
  "jcheck": "1",
  "reason": "違反商標法",
  "content": "臺灣臺北地方法院刑事簡易判決                    九十一年度簡字第三九一七號\n    聲  請  人  臺灣臺北地方法院檢察署檢察官\n    被      告  甲○○\n右列被告因違反商標法案件，經檢察官聲請以簡易判決處刑（九十一年度偵字第一九\n九八八號），本院判決如左：\n    主      文\n甲○○連續明知為意圖欺騙他人，於同一商品，使用相同於他人註冊商標之圖樣之商\n品而販賣，處有期徒刑伍月，如易科罰金，以佰元折算壹日。\n扣案仿冒「NOKIA」商標之手機外殼捌佰陸拾玖件均沒收。\n    事實及理由\n一、本件犯罪事實引用附件所示檢察官聲請簡易判決處刑書，並補充更正如下：甲○\n    ○明知「NOKIA」商標為國際著名商標，由諾基亞公司向經濟部中央標準局（現\n    改制為經濟部智慧財產局）申請核准註冊，取得商標專用權，指定使用於收音機\n    、錄音機、通訊器材等專用商品，現仍在專用期間；且明知姓名年籍不詳之業務\n    員、後火車站商店所販賣之手機外殼，為意圖欺騙他人，於同一商品，使用相同\n    於「NOKIA」註冊商標之圖樣之商品；竟基於販賣營利之概括犯意，自民國九十\n    年三月間某日起，以真品一半之價格，向姓名不詳之業務員及後火車站附近商店\n    ，販入仿冒「NOKIA」商標之手機外殼後，陳列在臺北市萬華區○○○路三六號\n    一樓六六室「全方立通訊廣場」商店內加價求售，連續販賣予不特定顧客，賺取\n    差價牟利，迄九十年十二月二十七日下午五時許，為警在上址當場查獲，並扣得\n    仿冒「NOKIA」商標之手機外殼八百六十九件。\n二、證據：（一）被告甲○○警偵訊時之自白。（二）告訴人諾基亞公司之指訴。（\n    三）證人周士傑、鄭彥伯警偵訊之證詞。（四）商標註冊證一份。（五）鑑定報\n    告一份。（六）現場照片九幀、仿冒手機外殼照片二幀。（七）估價單一紙。（\n    八）世界最有價值品牌排名表一張。（九）扣案仿冒商標商品八百六十九件。\n三、依刑事訴訟法第四百四十九條第一項前段、第三項、第四百五十條第一項、第四\n    百五十四條第二項，商標法第六十三條、第六十四條，刑法第十一條前段、第五\n    十六條、第四十一條第一項前段，罰金罰鍰提高標準條例第二條，逕以簡易判決\n    處刑如主文。\n如不服本件判決，得自收受送達之日起十日內，表明上訴理由，向本院提起上訴狀。\n中    華    民    國      九十一      年      十二      月      十      日\n                                  臺灣臺北地方法院刑事第四庭\n                                      法  官  吳靜怡\n右正本證明與原本無異。\n                                      書記官  游秀珠\n中    華    民    國      九十一      年      十二      月      十一    日\n附錄本案論罪科刑法條全文：\n商標法第六十三條\n明知為前條商品而販賣、意圖販賣而陳列、輸出或輸入者，處一年以下有期徒刑、拘\n役或科或併科新臺幣五萬元以下罰金。\n",
  "structure": {
    "main": "甲○○連續明知為意圖欺騙他人，於同一商品，使用相同於他人註冊商標之圖樣之商\n品而販賣，處有期徒刑伍月，如易科罰金，以佰元折算壹日。\n扣案仿冒「NOKIA」商標之手機外殼捌佰陸拾玖件均沒收。",
    "fact": "一、本件犯罪事實引用附件所示檢察官聲請簡易判決處刑書，並補充更正如下：甲○\n    ○明知「NOKIA」商標為國際著名商標，由諾基亞公司向經濟部中央標準局（現\n    改制為經濟部智慧財產局）申請核准註冊，取得商標專用權，指定使用於收音機\n    、錄音機、通訊器材等專用商品，現仍在專用期間；且明知姓名年籍不詳之業務\n    員、後火車站商店所販賣之手機外殼，為意圖欺騙他人，於同一商品，使用相同\n    於「NOKIA」註冊商標之圖樣之商品；竟基於販賣營利之概括犯意，自民國九十\n    年三月間某日起，以真品一半之價格，向姓名不詳之業務員及後火車站附近商店\n    ，販入仿冒「NOKIA」商標之手機外殼後，陳列在臺北市萬華區○○○路三六號\n    一樓六六室「全方立通訊廣場」商店內加價求售，連續販賣予不特定顧客，賺取\n    差價牟利，迄九十年十二月二十七日下午五時許，為警在上址當場查獲，並扣得\n    仿冒「NOKIA」商標之手機外殼八百六十九件。\n二、證據：（一）被告甲○○警偵訊時之自白。（二）告訴人諾基亞公司之指訴。（\n    三）證人周士傑、鄭彥伯警偵訊之證詞。（四）商標註冊證一份。（五）鑑定報\n    告一份。（六）現場照片九幀、仿冒手機外殼照片二幀。（七）估價單一紙。（\n    八）世界最有價值品牌排名表一張。（九）扣案仿冒商標商品八百六十九件。\n三、依刑事訴訟法第四百四十九條第一項前段、第三項、第四百五十條第一項、第四\n    百五十四條第二項，商標法第六十三條、第六十四條，刑法第十一條前段、第五\n    十六條、第四十一條第一項前段，罰金罰鍰提高標準條例第二條，逕以簡易判決\n    處刑如主文。\n如不服本件判決，得自收受送達之日起十日內，表明上訴理由，向本院提起上訴狀。",
    "reason": "一、本件犯罪事實引用附件所示檢察官聲請簡易判決處刑書，並補充更正如下：甲○\n    ○明知「NOKIA」商標為國際著名商標，由諾基亞公司向經濟部中央標準局（現\n    改制為經濟部智慧財產局）申請核准註冊，取得商標專用權，指定使用於收音機\n    、錄音機、通訊器材等專用商品，現仍在專用期間；且明知姓名年籍不詳之業務\n    員、後火車站商店所販賣之手機外殼，為意圖欺騙他人，於同一商品，使用相同\n    於「NOKIA」註冊商標之圖樣之商品；竟基於販賣營利之概括犯意，自民國九十\n    年三月間某日起，以真品一半之價格，向姓名不詳之業務員及後火車站附近商店\n    ，販入仿冒「NOKIA」商標之手機外殼後，陳列在臺北市萬華區○○○路三六號\n    一樓六六室「全方立通訊廣場」商店內加價求售，連續販賣予不特定顧客，賺取\n    差價牟利，迄九十年十二月二十七日下午五時許，為警在上址當場查獲，並扣得\n    仿冒「NOKIA」商標之手機外殼八百六十九件。\n二、證據：（一）被告甲○○警偵訊時之自白。（二）告訴人諾基亞公司之指訴。（\n    三）證人周士傑、鄭彥伯警偵訊之證詞。（四）商標註冊證一份。（五）鑑定報\n    告一份。（六）現場照片九幀、仿冒手機外殼照片二幀。（七）估價單一紙。（\n    八）世界最有價值品牌排名表一張。（九）扣案仿冒商標商品八百六十九件。\n三、依刑事訴訟法第四百四十九條第一項前段、第三項、第四百五十條第一項、第四\n    百五十四條第二項，商標法第六十三條、第六十四條，刑法第十一條前段、第五\n    十六條、第四十一條第一項前段，罰金罰鍰提高標準條例第二條，逕以簡易判決\n    處刑如主文。\n如不服本件判決，得自收受送達之日起十日內，表明上訴理由，向本院提起上訴狀。"
  },
  "search": "臺灣臺北地方法院刑事簡易判決九十一年度簡字第三九一七號聲請人臺灣臺北地方法院檢察署檢察官被告甲○○右列被告因違反商標法案件，經檢察官聲請以簡易判決處刑（九十一年度偵字第一九九八八號），本院判決如左：主文甲○○連續明知為意圖欺騙他人，於同一商品，使用相同於他人註冊商標之圖樣之商品而販賣，處有期徒刑伍月，如易科罰金，以佰元折算壹日。扣案仿冒「NOKIA」商標之手機外殼捌佰陸拾玖件均沒收。事實及理由一、本件犯罪事實引用附件所示檢察官聲請簡易判決處刑書，並補充更正如下：甲○○明知「NOKIA」商標為國際著名商標，由諾基亞公司向經濟部中央標準局（現改制為經濟部智慧財產局）申請核准註冊，取得商標專用權，指定使用於收音機、錄音機、通訊器材等專用商品，現仍在專用期間；且明知姓名年籍不詳之業務員、後火車站商店所販賣之手機外殼，為意圖欺騙他人，於同一商品，使用相同於「NOKIA」註冊商標之圖樣之商品；竟基於販賣營利之概括犯意，自民國九十年三月間某日起，以真品一半之價格，向姓名不詳之業務員及後火車站附近商店，販入仿冒「NOKIA」商標之手機外殼後，陳列在臺北市萬華區○○○路三六號一樓六六室「全方立通訊廣場」商店內加價求售，連續販賣予不特定顧客，賺取差價牟利，迄九十年十二月二十七日下午五時許，為警在上址當場查獲，並扣得仿冒「NOKIA」商標之手機外殼八百六十九件。二、證據：（一）被告甲○○警偵訊時之自白。（二）告訴人諾基亞公司之指訴。（三）證人周士傑、鄭彥伯警偵訊之證詞。（四）商標註冊證一份。（五）鑑定報告一份。（六）現場照片九幀、仿冒手機外殼照片二幀。（七）估價單一紙。（八）世界最有價值品牌排名表一張。（九）扣案仿冒商標商品八百六十九件。三、依刑事訴訟法第四百四十九條第一項前段、第三項、第四百五十條第一項、第四百五十四條第二項，商標法第六十三條、第六十四條，刑法第十一條前段、第五十六條、第四十一條第一項前段，罰金罰鍰提高標準條例第二條，逕以簡易判決處刑如主文。如不服本件判決，得自收受送達之日起十日內，表明上訴理由，向本院提起上訴狀。中華民國九十一年十二月十日臺灣臺北地方法院刑事第四庭法官吳靜怡右正本證明與原本無異。書記官游秀珠中華民國九十一年十二月十一日附錄本案論罪科刑法條全文：商標法第六十三條明知為前條商品而販賣、意圖販賣而陳列、輸出或輸入者，處一年以下有期徒刑、拘役或科或併科新臺幣五萬元以下罰金。",
  "characters": {
    "judges": [
      "吳靜怡"
    ],
    "prosecutors": [

    ],
    "lawyers": [

    ],
    "clerks": [
      "游秀珠"
    ],
    "plaintiffs": [

    ],
    "defendants": [
      "甲○○",
      "右列被告因違反商標法案件，經檢察官聲請以簡易判決處刑（九十一年度偵字第一九",
      "九八八號），本院判決如左："
    ],
    "prosecutor_office": [
      "臺灣臺北地方法院檢察署檢察官"
    ],
    "creditors": [

    ],
    "debtors": [

    ],
    "judicial_associate_officer": [

    ]
  },
  "adjudged_at": "2002-12-10",
  "created_at": "2016-02-05 05:12:05",
  "updated_at": "2016-02-05 05:12:05"
}