{
  "identify": "ILD-100-易-619-20111026-1",
  "court": {
    "name": "臺灣宜蘭地方法院",
    "code": "ILD"
  },
  "division": {
    "name": "刑事",
    "code": "M"
  },
  "year": 100,
  "word": "易",
  "number": "619",
  "jcheck": "1",
  "reason": "傷害",
  "content": "臺灣宜蘭地方法院刑事判決              100年度易字第619號\n公  訴  人  臺灣宜蘭地方法院檢察署檢察官\n被      告  張惠芳\n上列被告因傷害案件，經檢察官提起公訴（100年度偵字第1757\n號），本院判決如下：\n    主  文\n本件公訴不受理。\n    理  由\n一、公訴意旨略以：被告張惠芳與告訴人劉慧琴為鄰居關係，緣\n    被告在宜蘭縣蘇澳鎮○○路148號鐵皮屋經營小吃店，於民\n    國100年3月30日下午3時40分許，告訴人至其小吃店喝酒，\n    席間因告訴人在其店內摔杯子影響小吃店生意，雙方發生口\n    角爭執，詎被告一時氣憤竟基於傷害之犯意，以手拉告訴人\n    之衣服並推其身體，使其倒地受傷，迨告訴人起身後，繼而\n    以拳頭毆打告訴人之嘴巴，致告訴人受有上下唇裂傷、右肩\n    鈍挫傷等傷害。\n二、按告訴乃論之罪，告訴人於第一審辯論終結前得撤回其告訴\n    ，又告訴經撤回者，應諭知不受理之判決，刑事訴訟法第\n    238條第1項、第303條第3款分別定有明文。查本件告訴人告\n    訴被告傷害案件，起訴書認被告係觸犯刑法第277條第1項傷\n    害罪名，依同法第287條前段規定，須告訴乃論；茲據告訴\n    人撤回告訴，有撤回狀在卷可按，依照首開說明，本件爰不\n    經言詞辯論，逕為不受理判決之諭知。\n據上論斷，應依刑事訴訟法第303條第3款、第307條，判決如主\n文。\n中    華    民    國   100    年    10    月    26    日\n                  刑事第五庭  法  官  辜漢忠\n以上正本證明與原本無異。\n如不服本判決應於收受本判決後10日內向本院提出上訴書狀，並\n應敘述具體理由。若未敘述理由者，應於上訴期間屆滿後20日內\n向本院補提理由書狀(均須按他造當事人之人數附繕本)。\n                              書記官  林詩綺\n中    華    民    國   100    年    10    月    26    日",
  "structure": {
    "main": "本件公訴不受理。",
    "reason": "一、公訴意旨略以：被告張惠芳與告訴人劉慧琴為鄰居關係，緣\n    被告在宜蘭縣蘇澳鎮○○路148號鐵皮屋經營小吃店，於民\n    國100年3月30日下午3時40分許，告訴人至其小吃店喝酒，\n    席間因告訴人在其店內摔杯子影響小吃店生意，雙方發生口\n    角爭執，詎被告一時氣憤竟基於傷害之犯意，以手拉告訴人\n    之衣服並推其身體，使其倒地受傷，迨告訴人起身後，繼而\n    以拳頭毆打告訴人之嘴巴，致告訴人受有上下唇裂傷、右肩\n    鈍挫傷等傷害。\n二、按告訴乃論之罪，告訴人於第一審辯論終結前得撤回其告訴\n    ，又告訴經撤回者，應諭知不受理之判決，刑事訴訟法第\n    238條第1項、第303條第3款分別定有明文。查本件告訴人告\n    訴被告傷害案件，起訴書認被告係觸犯刑法第277條第1項傷\n    害罪名，依同法第287條前段規定，須告訴乃論；茲據告訴\n    人撤回告訴，有撤回狀在卷可按，依照首開說明，本件爰不\n    經言詞辯論，逕為不受理判決之諭知。\n據上論斷，應依刑事訴訟法第303條第3款、第307條，判決如主\n文。"
  },
  "search": "臺灣宜蘭地方法院刑事判決100年度易字第619號公訴人臺灣宜蘭地方法院檢察署檢察官被告張惠芳上列被告因傷害案件，經檢察官提起公訴（100年度偵字第1757號），本院判決如下：主文本件公訴不受理。理由一、公訴意旨略以：被告張惠芳與告訴人劉慧琴為鄰居關係，緣被告在宜蘭縣蘇澳鎮○○路148號鐵皮屋經營小吃店，於民國100年3月30日下午3時40分許，告訴人至其小吃店喝酒，席間因告訴人在其店內摔杯子影響小吃店生意，雙方發生口角爭執，詎被告一時氣憤竟基於傷害之犯意，以手拉告訴人之衣服並推其身體，使其倒地受傷，迨告訴人起身後，繼而以拳頭毆打告訴人之嘴巴，致告訴人受有上下唇裂傷、右肩鈍挫傷等傷害。二、按告訴乃論之罪，告訴人於第一審辯論終結前得撤回其告訴，又告訴經撤回者，應諭知不受理之判決，刑事訴訟法第238條第1項、第303條第3款分別定有明文。查本件告訴人告訴被告傷害案件，起訴書認被告係觸犯刑法第277條第1項傷害罪名，依同法第287條前段規定，須告訴乃論；茲據告訴人撤回告訴，有撤回狀在卷可按，依照首開說明，本件爰不經言詞辯論，逕為不受理判決之諭知。據上論斷，應依刑事訴訟法第303條第3款、第307條，判決如主文。中華民國100年10月26日刑事第五庭法官辜漢忠以上正本證明與原本無異。如不服本判決應於收受本判決後10日內向本院提出上訴書狀，並應敘述具體理由。若未敘述理由者，應於上訴期間屆滿後20日內向本院補提理由書狀(均須按他造當事人之人數附繕本)。書記官林詩綺中華民國100年10月26日",
  "characters": {
    "judges": [
      "辜漢忠"
    ],
    "prosecutors": [

    ],
    "lawyers": [

    ],
    "clerks": [
      "林詩綺"
    ],
    "plaintiffs": [

    ],
    "defendants": [
      "張惠芳"
    ],
    "prosecutor_office": [
      "臺灣宜蘭地方法院檢察署檢察官"
    ],
    "creditors": [

    ],
    "debtors": [

    ],
    "judicial_associate_officer": [

    ]
  },
  "adjudged_at": "2011-10-26",
  "created_at": "2016-02-14 05:16:54",
  "updated_at": "2016-02-14 05:16:54"
}