{
  "identify": "PCD-100-訴-2231-20111026-1",
  "court": {
    "name": "臺灣新北地方法院",
    "code": "PCD"
  },
  "division": {
    "name": "民事",
    "code": "V"
  },
  "year": 100,
  "word": "訴",
  "number": "2231",
  "jcheck": "1",
  "reason": "確認本票債權不存在等",
  "content": "臺灣板橋地方法院民事裁定             100年度訴字第2231號\n原      告  唐永正\n訴訟代理人  唐永洪律師\n            呂理胡律師\n被      告  陳永錦\n上列當事人間請求確認本票債權不存在等事件，本院裁定如下：\n    主  文\n本件移送臺灣桃園地方法院。\n    理  由\n一、按訴訟之全部或一部，法院認為無管轄權者，依原告聲請或\n    依職權以裁定移送其管轄法院，民事訴訟法第28條第1項定\n    有明文。\n二、本件被告住、居所地係在桃園縣，依民事訴訟法第1條第1項\n    之規定，自應由臺灣桃園地方法院管轄（兩造於不動產買賣\n    契約書第12條第10項亦合意臺灣桃園地方法院為第一審管轄\n    法院）。玆原告向無管轄權之本院起訴，顯係違誤，爰依職\n    權將本件移送於該管轄法院。\n三、原告係主張解除不動產買賣契約，請求確認原告為給付第1\n    期簽約款而簽發交付被告持有之系爭本票債權不存在，並請\n    求被告返還系爭本票，並非主張系爭本票係偽造、變造，是\n    本院雖為系爭本票准許強制執行裁定之法院，原告仍不得依\n    非訴事件法第195條第1項規定向本院提起確認之訴，附此敘\n    明。\n四、依首開法條裁定如主文。\n中    華    民    國   100    年    10    月    26    日\n                  民事第二庭    法  官  連士綱\n以上正本係照原本作成\n如對本裁定抗告須於裁定送達後10日內向本院提出抗告狀，並應\n繳納抗告費新台幣1,000元整。\n中    華    民    國   100    年    10    月    26    日\n                                書記官  吳俞玲",
  "structure": {
    "main": "本件移送臺灣桃園地方法院。",
    "reason": "一、按訴訟之全部或一部，法院認為無管轄權者，依原告聲請或\n    依職權以裁定移送其管轄法院，民事訴訟法第28條第1項定\n    有明文。\n二、本件被告住、居所地係在桃園縣，依民事訴訟法第1條第1項\n    之規定，自應由臺灣桃園地方法院管轄（兩造於不動產買賣\n    契約書第12條第10項亦合意臺灣桃園地方法院為第一審管轄\n    法院）。玆原告向無管轄權之本院起訴，顯係違誤，爰依職\n    權將本件移送於該管轄法院。\n三、原告係主張解除不動產買賣契約，請求確認原告為給付第1\n    期簽約款而簽發交付被告持有之系爭本票債權不存在，並請\n    求被告返還系爭本票，並非主張系爭本票係偽造、變造，是\n    本院雖為系爭本票准許強制執行裁定之法院，原告仍不得依\n    非訴事件法第195條第1項規定向本院提起確認之訴，附此敘\n    明。\n四、依首開法條裁定如主文。"
  },
  "search": "臺灣板橋地方法院民事裁定100年度訴字第2231號原告唐永正訴訟代理人唐永洪律師呂理胡律師被告陳永錦上列當事人間請求確認本票債權不存在等事件，本院裁定如下：主文本件移送臺灣桃園地方法院。理由一、按訴訟之全部或一部，法院認為無管轄權者，依原告聲請或依職權以裁定移送其管轄法院，民事訴訟法第28條第1項定有明文。二、本件被告住、居所地係在桃園縣，依民事訴訟法第1條第1項之規定，自應由臺灣桃園地方法院管轄（兩造於不動產買賣契約書第12條第10項亦合意臺灣桃園地方法院為第一審管轄法院）。玆原告向無管轄權之本院起訴，顯係違誤，爰依職權將本件移送於該管轄法院。三、原告係主張解除不動產買賣契約，請求確認原告為給付第1期簽約款而簽發交付被告持有之系爭本票債權不存在，並請求被告返還系爭本票，並非主張系爭本票係偽造、變造，是本院雖為系爭本票准許強制執行裁定之法院，原告仍不得依非訴事件法第195條第1項規定向本院提起確認之訴，附此敘明。四、依首開法條裁定如主文。中華民國100年10月26日民事第二庭法官連士綱以上正本係照原本作成如對本裁定抗告須於裁定送達後10日內向本院提出抗告狀，並應繳納抗告費新台幣1,000元整。中華民國100年10月26日書記官吳俞玲",
  "characters": {
    "judges": [
      "連士綱"
    ],
    "prosecutors": [

    ],
    "lawyers": [
      "唐永洪",
      "呂理胡"
    ],
    "clerks": [

    ],
    "plaintiffs": [
      "唐永正"
    ],
    "defendants": [
      "陳永錦"
    ],
    "prosecutor_office": [

    ],
    "creditors": [

    ],
    "debtors": [

    ],
    "judicial_associate_officer": [

    ]
  },
  "adjudged_at": "2011-10-26",
  "created_at": "2016-02-14 04:55:22",
  "updated_at": "2016-02-14 04:55:22"
}