{
  "identify": "TPD-100-簡-3823-20111026-1",
  "court": {
    "name": "臺灣臺北地方法院",
    "code": "TPD"
  },
  "division": {
    "name": "刑事",
    "code": "M"
  },
  "year": 100,
  "word": "簡",
  "number": "3823",
  "jcheck": "1",
  "reason": "毒品危害防制條例",
  "content": "臺灣臺北地方法院刑事簡易判決         100年度簡字第3823號\n聲  請  人  臺灣臺北地方法院檢察署檢察官\n被      告  王心怡\n上列被告因違反毒品危害防制條例案件，經檢察官聲請以簡易判\n決處刑（100年度偵字第15185號），本院判決如下：\n    主  文\n王心怡持有第三級毒品純質淨重二十公克以上，處有期徒刑月\n，如易科罰金，以新臺幣壹仟元折算壹日，扣案如附表一編號二\n至編號七所示之物均沒收銷燬之，包裝如附表一編號二至編號七\n所示毒品之包裝袋拾捌個、扣案如附表一編號一所示之毒品及包\n裝該毒品之包裝袋貳拾貳個、扣案如附表一編號八所示之物均沒\n收。\n    事實及理由\n一、本案犯罪事實及證明犯罪事實之證據方法並其證據，除犯罪\n    事實欄第1行至第8行更正為：「王心怡明知3,4-亞甲基雙氧\n    甲基安非他命（MDMA，俗稱搖頭丸，下稱MDMA）、甲基安非\n    他命均係毒品危害防制條例第2條第2項第2款所規範之第二\n    級毒品；愷他命（Ketamine，俗稱K他命，下稱愷他命）係\n    毒品危害防制條例第2條第2項第3款所規範之第三級毒品，\n    非經許可，均不得擅自持有，竟意圖供己施用，而於民國\n    100年7月初某日時許，在臺北市○○區○○路某不詳夜店內\n    ，向真實姓名、年籍均不詳之成年人，以新臺幣（下同）\n    25,000元之總價，一次購入如附表一編號2至編號7所示含有\n    第二級毒品MDMA、甲基安非他命成分之錠劑共18顆（聲請簡\n    易判決處刑書誤載為30顆），及如附表一編號1所示含有第\n    三級毒品愷他命成分之白色結晶共22包，而自斯時起非法持\n    有之。...」外，其餘均引用檢察官聲請簡易判決處刑書之\n    記載（如附件）。\n二、按MDMA、甲基安非他命均為毒品危害防制條例第2條第2項第\n    2款所稱之第二級毒品；愷他命為同條例第2條第2項第3款所\n    稱之第三級毒品，均不得非法持有。是核被告就持有扣案如\n    附表一編號2至編號7所示含有第二級毒品MDMA、甲基安非他\n    命成分之錠劑，及持有扣案如附表一編號1所示法定數量以\n    上之純質總淨重30.5002公克之第三級毒品愷他命之行為，\n    分別係犯毒品危害防制條例第11條第2項之持有第二級毒品\n    罪，與同條第5項之持有法定數量以上第三級毒品罪。被告\n    以一持有行為同時持有上開扣案之第二級毒品MDMA、甲基安\n    非他命，及法定數量以上之第三級毒品愷他命，為一行為觸\n    犯數罪名之想像競合犯，應依刑法第55條規定，從一重之持\n    有法定數量以上第三級毒品罪處斷。爰審酌被告明知MDMA、\n    甲基安非他命均為足以導致精神障礙並造成生命危險之成癮\n    性毒品，非但戕害個人之身心健康，且對社會治安亦造成潛\n    在之危險，仍為供己施用而購買持有之，復不思戒除愷他命\n    毒癮，反再次為滿足一己毒癮而同時購入扣案之超過法定數\n    量之愷他命，顯未能自我克制，所為實非可取，惟念其犯後\n    坦承犯行之尚可態度，暨其持有毒品之目的、持有之數量、\n    生活狀況、過往素行等一切情狀，量處如主文所示之刑，並\n    諭知易科罰金之折算標準，以示儆懲。\n三、沒收：\n  (一)扣案如附表一編號2至編號7所示之錠劑共18顆，各含有如附\n    表一編號2至編號7「鑑驗結果成分欄」所示之第二級毒品成\n    分之情，有如附表一編號2「鑑定書」欄所示之毒品鑑定書1\n    紙附卷可稽（各別之數量、重量詳見附表一編號2至編號7）\n    ，均屬查獲之第二級毒品，不問是否屬於犯人所有，均應依\n    毒品危害防制條例第18條第1項前段規定，均諭知沒收銷燬\n    之。至於鑑驗耗損部分，既已滅失不存在，自無庸併予宣告\n    沒收。包裝上開毒品之包裝袋共18個，均具有防止毒品裸露\n    、逸出及潮濕之功用，並便於攜帶，而均屬供被告犯本案犯\n    罪所用之物，且該等包裝袋連同袋內盛裝之上開毒品均屬被\n    告所有之情，業據被告供承明確（見偵查卷第10頁），爰依\n    刑法第38條第1項第2款規定，就該包裝袋18個均諭知沒收。\n  (二)按毒品危害防制條例第11條之1雖明定無正當理由，不得擅\n    自持有第三級毒品；同條例第18條第1項後段復規定查獲之\n    第三級毒品，無正當理由而擅自持有者，沒入銷燬之，然依\n    同條例第18條第1項後段應沒入銷燬之毒品，專指查獲施用\n    或持有之第三級毒品，尚不構成犯罪行為，而應依行政程序\n    沒入銷燬而言。從而，持有第三級毒品純質淨重20公克以上\n    者，既屬同條例第11條第5項明文規定處罰之犯罪行為，即\n    非該條項應依行政程序沒入銷燬之範圍，則被告所持有扣案\n    如附表一編號1所示數量之第三級毒品愷他命，其總純質淨\n    重既已逾20公克，自屬不受法律保護之違禁物，應依刑法第\n    38條第1項第1款之規定沒收之，始為適法（最高法院96年度\n    台上字第727號、96年台上字第884號判決意旨參照、最高法\n    院100年度第3次刑事庭會議決議意旨參照）。從而，扣案如\n    附表一編號1所示數量之愷他命（驗餘總淨重35.9575公克，\n    總純質淨重30.5002公克），均屬違禁物，不問屬於被告與\n    否，均應依刑法第38條第1項第1款規定諭知沒收。至於鑑驗\n    耗損部分，既已滅失不存在，自無庸併予宣告沒收。包裝上\n    開愷他命之包裝袋共22個，均具有防止毒品裸露、逸出及潮\n    濕之功用，並便於攜帶，自均屬供被告犯本案犯罪所用之物\n    ，且該等包裝袋連同袋內盛裝之上開毒品均屬被告所有之情\n    ，業據被告供承明確，爰依刑法第38條第1項第2款規定，就\n    該包裝袋22個均併予諭知沒收。另扣案如附表一編號8所示\n    之經剪裁牛皮薪資袋14個，為被告所有，供其分散裝載前揭\n    扣案愷他命22包，以掩人耳目並便於攜帶之情，業據被告供\n    明，自均屬供被告犯本案犯罪所用之物，爰依刑法第38條第\n    1項第2款之規定，均諭知沒收。\n  (三)扣案如附表二所示之錠劑12顆、現金2,000元，雖均係被告\n    所有，惟如附表二所示之錠劑均未檢出任何毒品成分之情，\n    有交通部民用航空局航空醫務中心100年8月12日航藥鑑字第\n    0000000號毒品鑑定書1張存卷可佐（見偵查卷第66頁正反面\n    ），又扣案現金2,000元乃被告平日花用所憑之零用錢，與\n    被告為本案犯行並無關聯之情，亦據被告供明，且依卷內證\n    據復無法證明該等扣案物與被告本案持有毒品之犯行間有何\n    關聯，而沒收既屬從刑之一種，依主從不可分原則，自應附\n    隨於主刑而同時宣告之，上開物品既均與本案無關，爰均不\n    為沒收之宣告，均併此敘明。\n四、依刑事訴訟法第449條第1項前段、第3項、第450條第1項、\n    第454條第2項，毒品危害防制條例第11條第2項、第5項、第\n    18條第1項前段，刑法第11條前段、第55條、第41條第1項前\n    段、第38條第1項第1款、第2款，逕以簡易判決處刑如主文\n    。\n五、如不服本案判決，得自收受送達之日起10日內，向本院提起\n    上訴狀。\n中    華    民    國   100    年    10    月    26    日\n                  刑事第二庭  法  官  謝昀璉\n上正本證明與原本無異。\n如不服本判決應於收受送達後10日內向本院提出上訴書狀，並應\n敘述具體理由；其未敘述上訴理由者，應於上訴期間屆滿後20日\n內向本院補提理由書（均須按他造當事人之人數附繕本）「切勿\n逕送上級法院」。\n                              書記官  鄭雅文\n中    華    民    國   100    年    10    月    31    日\n附錄論罪科刑法條：\n毒品危害防制條例第11條第2項、第5項。\n毒品危害防制條例第11條\n持有第一級毒品者，處3 年以下有期徒刑、拘役或新臺幣5 萬元\n以下罰金。\n持有第二級毒品者，處2 年以下有期徒刑、拘役或新臺幣3 萬元\n以下罰金。\n持有第一級毒品純質淨重十公克以上者，處1 年以上7 年以下有\n期徒刑，得併科新臺幣1 百萬元以下罰金。\n持有第二級毒品純質淨重二十公克以上者，處6 月以上5 年以下\n有期徒刑，得併科新臺幣70萬元以下罰金。\n持有第三級毒品純質淨重二十公克以上者，處3 年以下有期徒刑\n，得併科新臺幣30萬元以下罰金。\n持有第四級毒品純質淨重二十公克以上者，處1 年以下有期徒刑\n，得併科新臺幣10萬元以下罰金。\n持有專供製造或施用第一級、第二級毒品之器具者，處1 年以下\n有期徒刑、拘役或新臺幣1 萬元以下罰金。\n附表一：（沒收物）\n┌───┬──────┬───┬─────────────┬──────┬──────┐\n│      │            │      │鑑     驗     結     果   │            │            │\n│編  號│扣押物品名稱│數  量│                          │毒品沒收之依│   鑑定書   │\n│      │            │      ├───────┬─────┤據          │            │\n│      │            │      │重          量│成      分│            │            │\n├───┼──────┼───┼───────┼─────┼──────┼──────┤\n│  1   │白色結晶    │22包  │總毛重42.193公│均檢出第三│刑法第38條第│交通部民用航│\n│      │            │      │克，驗餘總淨重│級毒品愷他│1項第1款。  │空局航空醫務│\n│      │            │      │35.9575公克， │命成分。  │            │中心100年8月│\n│      │            │      │總純質淨重    │          │            │31日航藥鑑字│\n│      │            │      │30.5002公克。 │          │            │第0000000Q號│\n│      │            │      │              │          │            │毒品鑑定書（│\n│      │            │      │              │          │            │見偵查卷第69│\n│      │            │      │              │          │            │頁至第70頁）│\n├───┼──────┼───┼───────┼─────┼──────┼──────┤\n│  2   │桃紅色圓形鑽│4顆   │總淨重1.085公 │均檢出第二│毒品危害防制│交通部民用航│\n│      │石形狀錠劑  │      │克，驗餘總淨重│級毒品MDMA│條例第18條第│空局航空醫務│\n│      │            │      │1.0815公克。  │成分。    │1項前段。   │中心100年8月│\n│      │            │      │              │          │            │12日航藥鑑字│\n│      │            │      │              │          │            │第0000000號 │\n│      │            │      │              │          │            │毒品鑑定書（│\n│      │            │      │              │          │            │見偵查卷第66│\n│      │            │      │              │          │            │頁正反面）  │\n├───┼──────┼───┼───────┼─────┼──────┼──────┤\n│  3   │藍色圓形錠劑│3顆   │總淨重0.8520公│均檢出第二│同上。      │同上。      │\n│      │            │      │克，驗餘總淨重│級毒品MDMA│            │            │\n│      │            │      │0.8502公克。  │成分。    │            │            │\n│      │            │      │              │          │            │            │\n├───┼──────┼───┼───────┼─────┼──────┼──────┤\n│  4   │粉紅色圓形錠│2顆   │總淨重0.5810公│均檢出第二│同上。      │同上。      │\n│      │劑          │      │克，驗餘總淨重│級毒品MDMA│            │            │\n│      │            │      │0.5787公克。  │成分。    │            │            │\n├───┼──────┼───┼───────┼─────┼──────┼──────┤\n│  5   │淡橘色圓形錠│2顆   │總淨重0.6080公│均檢出第二│同上。      │同上。      │\n│      │劑          │      │克，驗餘總淨重│級毒品甲基│            │            │\n│      │            │      │0.6051公克。  │安非他命、│            │            │\n│      │            │      │              │MDMA成分。│            │            │\n├───┼──────┼───┼───────┼─────┼──────┼──────┤\n│  6   │褐色圓形錠劑│4顆   │總淨重1.2920公│均檢出第二│同上。      │同上。      │\n│      │            │      │克，驗餘總淨重│級毒品甲基│            │            │\n│      │            │      │1.2892公克。  │安非他命成│            │            │\n│      │            │      │              │分。      │            │            │\n├───┼──────┼───┼───────┼─────┼──────┼──────┤\n│  7   │米白色圓形錠│3顆   │總淨重0.8740公│均檢出第二│同上。      │同上。      │\n│      │劑          │      │克，驗餘總淨重│級毒品MDMA│            │            │\n│      │            │      │0.8711公克。  │成分。    │            │            │\n│      │            │      │              │          │            │            │\n├───┼──────┼───┼───────┼─────┼──────┼──────┤\n│  8   │剪裁後之牛皮│14個  │無。          │無。      │刑法第38條第│無。        │\n│      │薪資袋      │      │              │          │1項第2款。  │            │\n│      │            │      │              │          │            │            │\n└───┴──────┴───┴───────┴─────┴──────┴──────┘\n附表二：（不予沒收）\n┌───┬──────┬───┬─────────────┬──────┐\n│      │            │      │鑑     驗     結     果   │            │\n│編  號│扣押物品名稱│數  量│                          │   鑑定書   │\n│      │            │      ├───────┬─────┤            │\n│      │            │      │重          量│成      分│            │\n├───┼──────┼───┼───────┼─────┼──────┤\n│  1   │綠色圓形錠劑│3顆   │總淨重0.9660公│均僅檢出未│交通部民用航│\n│      │            │      │克，驗餘總淨重│經列管之咖│空局航空醫務│\n│      │            │      │0.9639公克。  │啡因、氯安│中心100年8月│\n│      │            │      │              │非他命（Ch│12日航藥鑑字│\n│      │            │      │              │loroamphet│第0000000號 │\n│      │            │      │              │amine）成 │毒品鑑定書（│\n│      │            │      │              │分，而均未│見偵查卷第66│\n│      │            │      │              │檢出毒品成│頁正反面）  │\n│      │            │      │              │分。      │            │\n├───┼──────┼───┼───────┼─────┼──────┤\n│  2   │藍色圓形錠劑│3顆   │總淨重1.1110公│均僅檢出咖│同上。      │\n│      │            │      │克，驗餘總淨重│啡因、Meth│            │\n│      │            │      │1.1083公克。  │ylone(3,4-│            │\n│      │            │      │              │亞甲基雙氧│            │\n│      │            │      │              │甲基卡西酮│            │\n│      │            │      │              │，亦稱3,4-│            │\n│      │            │      │              │methylened│            │\n│      │            │      │              │ioxyme、bk│            │\n│      │            │      │              │-MDMA，於1│            │\n│      │            │      │              │00年9月8日│            │\n│      │            │      │              │始經行政院│            │\n│      │            │      │              │以院臺法字│            │\n│      │            │      │              │第00000000│            │\n│      │            │      │              │44號函公告│            │\n│      │            │      │              │列為第三級│            │\n│      │            │      │              │毒品，被告│            │\n│      │            │      │              │持有時尚非│            │\n│      │            │      │              │經公告列管│            │\n│      │            │      │              │之毒品）成│            │\n│      │            │      │              │分。      │            │\n├───┼──────┼───┼───────┼─────┼──────┤\n│  3   │黃綠色圓形錠│3顆   │總淨重0.9740公│均僅檢出咖│同上。      │\n│      │劑          │      │克，驗餘總淨重│啡因、氯安│            │\n│      │            │      │0.9719公克。  │非他命成分│            │\n│      │            │      │              │，而均未檢│            │\n│      │            │      │              │出毒品成分│            │\n│      │            │      │              │。        │            │\n├───┼──────┼───┼───────┼─────┼──────┤\n│  4   │珊瑚紅色圓形│3顆   │總淨重0.9560公│均僅檢出咖│同上。      │\n│      │錠劑        │      │克，驗餘總淨重│啡因、氯安│            │\n│      │            │      │0.9507公克。  │非他命成分│            │\n│      │            │      │              │，而均未檢│            │\n│      │            │      │              │出毒品成分│            │\n│      │            │      │              │。        │            │\n└───┴──────┴───┴───────┴─────┴──────┘",
  "structure": {
    "main": "王心怡持有第三級毒品純質淨重二十公克以上，處有期徒刑月\n，如易科罰金，以新臺幣壹仟元折算壹日，扣案如附表一編號二\n至編號七所示之物均沒收銷燬之，包裝如附表一編號二至編號七\n所示毒品之包裝袋拾捌個、扣案如附表一編號一所示之毒品及包\n裝該毒品之包裝袋貳拾貳個、扣案如附表一編號八所示之物均沒\n收。",
    "fact": "一、本案犯罪事實及證明犯罪事實之證據方法並其證據，除犯罪\n    事實欄第1行至第8行更正為：「王心怡明知3,4-亞甲基雙氧\n    甲基安非他命（MDMA，俗稱搖頭丸，下稱MDMA）、甲基安非\n    他命均係毒品危害防制條例第2條第2項第2款所規範之第二\n    級毒品；愷他命（Ketamine，俗稱K他命，下稱愷他命）係\n    毒品危害防制條例第2條第2項第3款所規範之第三級毒品，\n    非經許可，均不得擅自持有，竟意圖供己施用，而於民國\n    100年7月初某日時許，在臺北市○○區○○路某不詳夜店內\n    ，向真實姓名、年籍均不詳之成年人，以新臺幣（下同）\n    25,000元之總價，一次購入如附表一編號2至編號7所示含有\n    第二級毒品MDMA、甲基安非他命成分之錠劑共18顆（聲請簡\n    易判決處刑書誤載為30顆），及如附表一編號1所示含有第\n    三級毒品愷他命成分之白色結晶共22包，而自斯時起非法持\n    有之。...」外，其餘均引用檢察官聲請簡易判決處刑書之\n    記載（如附件）。\n二、按MDMA、甲基安非他命均為毒品危害防制條例第2條第2項第\n    2款所稱之第二級毒品；愷他命為同條例第2條第2項第3款所\n    稱之第三級毒品，均不得非法持有。是核被告就持有扣案如\n    附表一編號2至編號7所示含有第二級毒品MDMA、甲基安非他\n    命成分之錠劑，及持有扣案如附表一編號1所示法定數量以\n    上之純質總淨重30.5002公克之第三級毒品愷他命之行為，\n    分別係犯毒品危害防制條例第11條第2項之持有第二級毒品\n    罪，與同條第5項之持有法定數量以上第三級毒品罪。被告\n    以一持有行為同時持有上開扣案之第二級毒品MDMA、甲基安\n    非他命，及法定數量以上之第三級毒品愷他命，為一行為觸\n    犯數罪名之想像競合犯，應依刑法第55條規定，從一重之持\n    有法定數量以上第三級毒品罪處斷。爰審酌被告明知MDMA、\n    甲基安非他命均為足以導致精神障礙並造成生命危險之成癮\n    性毒品，非但戕害個人之身心健康，且對社會治安亦造成潛\n    在之危險，仍為供己施用而購買持有之，復不思戒除愷他命\n    毒癮，反再次為滿足一己毒癮而同時購入扣案之超過法定數\n    量之愷他命，顯未能自我克制，所為實非可取，惟念其犯後\n    坦承犯行之尚可態度，暨其持有毒品之目的、持有之數量、\n    生活狀況、過往素行等一切情狀，量處如主文所示之刑，並\n    諭知易科罰金之折算標準，以示儆懲。\n三、沒收：\n  (一)扣案如附表一編號2至編號7所示之錠劑共18顆，各含有如附\n    表一編號2至編號7「鑑驗結果成分欄」所示之第二級毒品成\n    分之情，有如附表一編號2「鑑定書」欄所示之毒品鑑定書1\n    紙附卷可稽（各別之數量、重量詳見附表一編號2至編號7）\n    ，均屬查獲之第二級毒品，不問是否屬於犯人所有，均應依\n    毒品危害防制條例第18條第1項前段規定，均諭知沒收銷燬\n    之。至於鑑驗耗損部分，既已滅失不存在，自無庸併予宣告\n    沒收。包裝上開毒品之包裝袋共18個，均具有防止毒品裸露\n    、逸出及潮濕之功用，並便於攜帶，而均屬供被告犯本案犯\n    罪所用之物，且該等包裝袋連同袋內盛裝之上開毒品均屬被\n    告所有之情，業據被告供承明確（見偵查卷第10頁），爰依\n    刑法第38條第1項第2款規定，就該包裝袋18個均諭知沒收。\n  (二)按毒品危害防制條例第11條之1雖明定無正當理由，不得擅\n    自持有第三級毒品；同條例第18條第1項後段復規定查獲之\n    第三級毒品，無正當理由而擅自持有者，沒入銷燬之，然依\n    同條例第18條第1項後段應沒入銷燬之毒品，專指查獲施用\n    或持有之第三級毒品，尚不構成犯罪行為，而應依行政程序\n    沒入銷燬而言。從而，持有第三級毒品純質淨重20公克以上\n    者，既屬同條例第11條第5項明文規定處罰之犯罪行為，即\n    非該條項應依行政程序沒入銷燬之範圍，則被告所持有扣案\n    如附表一編號1所示數量之第三級毒品愷他命，其總純質淨\n    重既已逾20公克，自屬不受法律保護之違禁物，應依刑法第\n    38條第1項第1款之規定沒收之，始為適法（最高法院96年度\n    台上字第727號、96年台上字第884號判決意旨參照、最高法\n    院100年度第3次刑事庭會議決議意旨參照）。從而，扣案如\n    附表一編號1所示數量之愷他命（驗餘總淨重35.9575公克，\n    總純質淨重30.5002公克），均屬違禁物，不問屬於被告與\n    否，均應依刑法第38條第1項第1款規定諭知沒收。至於鑑驗\n    耗損部分，既已滅失不存在，自無庸併予宣告沒收。包裝上\n    開愷他命之包裝袋共22個，均具有防止毒品裸露、逸出及潮\n    濕之功用，並便於攜帶，自均屬供被告犯本案犯罪所用之物\n    ，且該等包裝袋連同袋內盛裝之上開毒品均屬被告所有之情\n    ，業據被告供承明確，爰依刑法第38條第1項第2款規定，就\n    該包裝袋22個均併予諭知沒收。另扣案如附表一編號8所示\n    之經剪裁牛皮薪資袋14個，為被告所有，供其分散裝載前揭\n    扣案愷他命22包，以掩人耳目並便於攜帶之情，業據被告供\n    明，自均屬供被告犯本案犯罪所用之物，爰依刑法第38條第\n    1項第2款之規定，均諭知沒收。\n  (三)扣案如附表二所示之錠劑12顆、現金2,000元，雖均係被告\n    所有，惟如附表二所示之錠劑均未檢出任何毒品成分之情，\n    有交通部民用航空局航空醫務中心100年8月12日航藥鑑字第\n    0000000號毒品鑑定書1張存卷可佐（見偵查卷第66頁正反面\n    ），又扣案現金2,000元乃被告平日花用所憑之零用錢，與\n    被告為本案犯行並無關聯之情，亦據被告供明，且依卷內證\n    據復無法證明該等扣案物與被告本案持有毒品之犯行間有何\n    關聯，而沒收既屬從刑之一種，依主從不可分原則，自應附\n    隨於主刑而同時宣告之，上開物品既均與本案無關，爰均不\n    為沒收之宣告，均併此敘明。\n四、依刑事訴訟法第449條第1項前段、第3項、第450條第1項、\n    第454條第2項，毒品危害防制條例第11條第2項、第5項、第\n    18條第1項前段，刑法第11條前段、第55條、第41條第1項前\n    段、第38條第1項第1款、第2款，逕以簡易判決處刑如主文\n    。\n五、如不服本案判決，得自收受送達之日起10日內，向本院提起\n    上訴狀。",
    "reason": "一、本案犯罪事實及證明犯罪事實之證據方法並其證據，除犯罪\n    事實欄第1行至第8行更正為：「王心怡明知3,4-亞甲基雙氧\n    甲基安非他命（MDMA，俗稱搖頭丸，下稱MDMA）、甲基安非\n    他命均係毒品危害防制條例第2條第2項第2款所規範之第二\n    級毒品；愷他命（Ketamine，俗稱K他命，下稱愷他命）係\n    毒品危害防制條例第2條第2項第3款所規範之第三級毒品，\n    非經許可，均不得擅自持有，竟意圖供己施用，而於民國\n    100年7月初某日時許，在臺北市○○區○○路某不詳夜店內\n    ，向真實姓名、年籍均不詳之成年人，以新臺幣（下同）\n    25,000元之總價，一次購入如附表一編號2至編號7所示含有\n    第二級毒品MDMA、甲基安非他命成分之錠劑共18顆（聲請簡\n    易判決處刑書誤載為30顆），及如附表一編號1所示含有第\n    三級毒品愷他命成分之白色結晶共22包，而自斯時起非法持\n    有之。...」外，其餘均引用檢察官聲請簡易判決處刑書之\n    記載（如附件）。\n二、按MDMA、甲基安非他命均為毒品危害防制條例第2條第2項第\n    2款所稱之第二級毒品；愷他命為同條例第2條第2項第3款所\n    稱之第三級毒品，均不得非法持有。是核被告就持有扣案如\n    附表一編號2至編號7所示含有第二級毒品MDMA、甲基安非他\n    命成分之錠劑，及持有扣案如附表一編號1所示法定數量以\n    上之純質總淨重30.5002公克之第三級毒品愷他命之行為，\n    分別係犯毒品危害防制條例第11條第2項之持有第二級毒品\n    罪，與同條第5項之持有法定數量以上第三級毒品罪。被告\n    以一持有行為同時持有上開扣案之第二級毒品MDMA、甲基安\n    非他命，及法定數量以上之第三級毒品愷他命，為一行為觸\n    犯數罪名之想像競合犯，應依刑法第55條規定，從一重之持\n    有法定數量以上第三級毒品罪處斷。爰審酌被告明知MDMA、\n    甲基安非他命均為足以導致精神障礙並造成生命危險之成癮\n    性毒品，非但戕害個人之身心健康，且對社會治安亦造成潛\n    在之危險，仍為供己施用而購買持有之，復不思戒除愷他命\n    毒癮，反再次為滿足一己毒癮而同時購入扣案之超過法定數\n    量之愷他命，顯未能自我克制，所為實非可取，惟念其犯後\n    坦承犯行之尚可態度，暨其持有毒品之目的、持有之數量、\n    生活狀況、過往素行等一切情狀，量處如主文所示之刑，並\n    諭知易科罰金之折算標準，以示儆懲。\n三、沒收：\n  (一)扣案如附表一編號2至編號7所示之錠劑共18顆，各含有如附\n    表一編號2至編號7「鑑驗結果成分欄」所示之第二級毒品成\n    分之情，有如附表一編號2「鑑定書」欄所示之毒品鑑定書1\n    紙附卷可稽（各別之數量、重量詳見附表一編號2至編號7）\n    ，均屬查獲之第二級毒品，不問是否屬於犯人所有，均應依\n    毒品危害防制條例第18條第1項前段規定，均諭知沒收銷燬\n    之。至於鑑驗耗損部分，既已滅失不存在，自無庸併予宣告\n    沒收。包裝上開毒品之包裝袋共18個，均具有防止毒品裸露\n    、逸出及潮濕之功用，並便於攜帶，而均屬供被告犯本案犯\n    罪所用之物，且該等包裝袋連同袋內盛裝之上開毒品均屬被\n    告所有之情，業據被告供承明確（見偵查卷第10頁），爰依\n    刑法第38條第1項第2款規定，就該包裝袋18個均諭知沒收。\n  (二)按毒品危害防制條例第11條之1雖明定無正當理由，不得擅\n    自持有第三級毒品；同條例第18條第1項後段復規定查獲之\n    第三級毒品，無正當理由而擅自持有者，沒入銷燬之，然依\n    同條例第18條第1項後段應沒入銷燬之毒品，專指查獲施用\n    或持有之第三級毒品，尚不構成犯罪行為，而應依行政程序\n    沒入銷燬而言。從而，持有第三級毒品純質淨重20公克以上\n    者，既屬同條例第11條第5項明文規定處罰之犯罪行為，即\n    非該條項應依行政程序沒入銷燬之範圍，則被告所持有扣案\n    如附表一編號1所示數量之第三級毒品愷他命，其總純質淨\n    重既已逾20公克，自屬不受法律保護之違禁物，應依刑法第\n    38條第1項第1款之規定沒收之，始為適法（最高法院96年度\n    台上字第727號、96年台上字第884號判決意旨參照、最高法\n    院100年度第3次刑事庭會議決議意旨參照）。從而，扣案如\n    附表一編號1所示數量之愷他命（驗餘總淨重35.9575公克，\n    總純質淨重30.5002公克），均屬違禁物，不問屬於被告與\n    否，均應依刑法第38條第1項第1款規定諭知沒收。至於鑑驗\n    耗損部分，既已滅失不存在，自無庸併予宣告沒收。包裝上\n    開愷他命之包裝袋共22個，均具有防止毒品裸露、逸出及潮\n    濕之功用，並便於攜帶，自均屬供被告犯本案犯罪所用之物\n    ，且該等包裝袋連同袋內盛裝之上開毒品均屬被告所有之情\n    ，業據被告供承明確，爰依刑法第38條第1項第2款規定，就\n    該包裝袋22個均併予諭知沒收。另扣案如附表一編號8所示\n    之經剪裁牛皮薪資袋14個，為被告所有，供其分散裝載前揭\n    扣案愷他命22包，以掩人耳目並便於攜帶之情，業據被告供\n    明，自均屬供被告犯本案犯罪所用之物，爰依刑法第38條第\n    1項第2款之規定，均諭知沒收。\n  (三)扣案如附表二所示之錠劑12顆、現金2,000元，雖均係被告\n    所有，惟如附表二所示之錠劑均未檢出任何毒品成分之情，\n    有交通部民用航空局航空醫務中心100年8月12日航藥鑑字第\n    0000000號毒品鑑定書1張存卷可佐（見偵查卷第66頁正反面\n    ），又扣案現金2,000元乃被告平日花用所憑之零用錢，與\n    被告為本案犯行並無關聯之情，亦據被告供明，且依卷內證\n    據復無法證明該等扣案物與被告本案持有毒品之犯行間有何\n    關聯，而沒收既屬從刑之一種，依主從不可分原則，自應附\n    隨於主刑而同時宣告之，上開物品既均與本案無關，爰均不\n    為沒收之宣告，均併此敘明。\n四、依刑事訴訟法第449條第1項前段、第3項、第450條第1項、\n    第454條第2項，毒品危害防制條例第11條第2項、第5項、第\n    18條第1項前段，刑法第11條前段、第55條、第41條第1項前\n    段、第38條第1項第1款、第2款，逕以簡易判決處刑如主文\n    。\n五、如不服本案判決，得自收受送達之日起10日內，向本院提起\n    上訴狀。"
  },
  "search": "臺灣臺北地方法院刑事簡易判決100年度簡字第3823號聲請人臺灣臺北地方法院檢察署檢察官被告王心怡上列被告因違反毒品危害防制條例案件，經檢察官聲請以簡易判決處刑（100年度偵字第15185號），本院判決如下：主文王心怡持有第三級毒品純質淨重二十公克以上，處有期徒刑月，如易科罰金，以新臺幣壹仟元折算壹日，扣案如附表一編號二至編號七所示之物均沒收銷燬之，包裝如附表一編號二至編號七所示毒品之包裝袋拾捌個、扣案如附表一編號一所示之毒品及包裝該毒品之包裝袋貳拾貳個、扣案如附表一編號八所示之物均沒收。事實及理由一、本案犯罪事實及證明犯罪事實之證據方法並其證據，除犯罪事實欄第1行至第8行更正為：「王心怡明知3,4-亞甲基雙氧甲基安非他命（MDMA，俗稱搖頭丸，下稱MDMA）、甲基安非他命均係毒品危害防制條例第2條第2項第2款所規範之第二級毒品；愷他命（Ketamine，俗稱K他命，下稱愷他命）係毒品危害防制條例第2條第2項第3款所規範之第三級毒品，非經許可，均不得擅自持有，竟意圖供己施用，而於民國100年7月初某日時許，在臺北市○○區○○路某不詳夜店內，向真實姓名、年籍均不詳之成年人，以新臺幣（下同）25,000元之總價，一次購入如附表一編號2至編號7所示含有第二級毒品MDMA、甲基安非他命成分之錠劑共18顆（聲請簡易判決處刑書誤載為30顆），及如附表一編號1所示含有第三級毒品愷他命成分之白色結晶共22包，而自斯時起非法持有之。...」外，其餘均引用檢察官聲請簡易判決處刑書之記載（如附件）。二、按MDMA、甲基安非他命均為毒品危害防制條例第2條第2項第2款所稱之第二級毒品；愷他命為同條例第2條第2項第3款所稱之第三級毒品，均不得非法持有。是核被告就持有扣案如附表一編號2至編號7所示含有第二級毒品MDMA、甲基安非他命成分之錠劑，及持有扣案如附表一編號1所示法定數量以上之純質總淨重30.5002公克之第三級毒品愷他命之行為，分別係犯毒品危害防制條例第11條第2項之持有第二級毒品罪，與同條第5項之持有法定數量以上第三級毒品罪。被告以一持有行為同時持有上開扣案之第二級毒品MDMA、甲基安非他命，及法定數量以上之第三級毒品愷他命，為一行為觸犯數罪名之想像競合犯，應依刑法第55條規定，從一重之持有法定數量以上第三級毒品罪處斷。爰審酌被告明知MDMA、甲基安非他命均為足以導致精神障礙並造成生命危險之成癮性毒品，非但戕害個人之身心健康，且對社會治安亦造成潛在之危險，仍為供己施用而購買持有之，復不思戒除愷他命毒癮，反再次為滿足一己毒癮而同時購入扣案之超過法定數量之愷他命，顯未能自我克制，所為實非可取，惟念其犯後坦承犯行之尚可態度，暨其持有毒品之目的、持有之數量、生活狀況、過往素行等一切情狀，量處如主文所示之刑，並諭知易科罰金之折算標準，以示儆懲。三、沒收：(一)扣案如附表一編號2至編號7所示之錠劑共18顆，各含有如附表一編號2至編號7「鑑驗結果成分欄」所示之第二級毒品成分之情，有如附表一編號2「鑑定書」欄所示之毒品鑑定書1紙附卷可稽（各別之數量、重量詳見附表一編號2至編號7），均屬查獲之第二級毒品，不問是否屬於犯人所有，均應依毒品危害防制條例第18條第1項前段規定，均諭知沒收銷燬之。至於鑑驗耗損部分，既已滅失不存在，自無庸併予宣告沒收。包裝上開毒品之包裝袋共18個，均具有防止毒品裸露、逸出及潮濕之功用，並便於攜帶，而均屬供被告犯本案犯罪所用之物，且該等包裝袋連同袋內盛裝之上開毒品均屬被告所有之情，業據被告供承明確（見偵查卷第10頁），爰依刑法第38條第1項第2款規定，就該包裝袋18個均諭知沒收。(二)按毒品危害防制條例第11條之1雖明定無正當理由，不得擅自持有第三級毒品；同條例第18條第1項後段復規定查獲之第三級毒品，無正當理由而擅自持有者，沒入銷燬之，然依同條例第18條第1項後段應沒入銷燬之毒品，專指查獲施用或持有之第三級毒品，尚不構成犯罪行為，而應依行政程序沒入銷燬而言。從而，持有第三級毒品純質淨重20公克以上者，既屬同條例第11條第5項明文規定處罰之犯罪行為，即非該條項應依行政程序沒入銷燬之範圍，則被告所持有扣案如附表一編號1所示數量之第三級毒品愷他命，其總純質淨重既已逾20公克，自屬不受法律保護之違禁物，應依刑法第38條第1項第1款之規定沒收之，始為適法（最高法院96年度台上字第727號、96年台上字第884號判決意旨參照、最高法院100年度第3次刑事庭會議決議意旨參照）。從而，扣案如附表一編號1所示數量之愷他命（驗餘總淨重35.9575公克，總純質淨重30.5002公克），均屬違禁物，不問屬於被告與否，均應依刑法第38條第1項第1款規定諭知沒收。至於鑑驗耗損部分，既已滅失不存在，自無庸併予宣告沒收。包裝上開愷他命之包裝袋共22個，均具有防止毒品裸露、逸出及潮濕之功用，並便於攜帶，自均屬供被告犯本案犯罪所用之物，且該等包裝袋連同袋內盛裝之上開毒品均屬被告所有之情，業據被告供承明確，爰依刑法第38條第1項第2款規定，就該包裝袋22個均併予諭知沒收。另扣案如附表一編號8所示之經剪裁牛皮薪資袋14個，為被告所有，供其分散裝載前揭扣案愷他命22包，以掩人耳目並便於攜帶之情，業據被告供明，自均屬供被告犯本案犯罪所用之物，爰依刑法第38條第1項第2款之規定，均諭知沒收。(三)扣案如附表二所示之錠劑12顆、現金2,000元，雖均係被告所有，惟如附表二所示之錠劑均未檢出任何毒品成分之情，有交通部民用航空局航空醫務中心100年8月12日航藥鑑字第0000000號毒品鑑定書1張存卷可佐（見偵查卷第66頁正反面），又扣案現金2,000元乃被告平日花用所憑之零用錢，與被告為本案犯行並無關聯之情，亦據被告供明，且依卷內證據復無法證明該等扣案物與被告本案持有毒品之犯行間有何關聯，而沒收既屬從刑之一種，依主從不可分原則，自應附隨於主刑而同時宣告之，上開物品既均與本案無關，爰均不為沒收之宣告，均併此敘明。四、依刑事訴訟法第449條第1項前段、第3項、第450條第1項、第454條第2項，毒品危害防制條例第11條第2項、第5項、第18條第1項前段，刑法第11條前段、第55條、第41條第1項前段、第38條第1項第1款、第2款，逕以簡易判決處刑如主文。五、如不服本案判決，得自收受送達之日起10日內，向本院提起上訴狀。中華民國100年10月26日刑事第二庭法官謝昀璉上正本證明與原本無異。如不服本判決應於收受送達後10日內向本院提出上訴書狀，並應敘述具體理由；其未敘述上訴理由者，應於上訴期間屆滿後20日內向本院補提理由書（均須按他造當事人之人數附繕本）「切勿逕送上級法院」。書記官鄭雅文中華民國100年10月31日附錄論罪科刑法條：毒品危害防制條例第11條第2項、第5項。毒品危害防制條例第11條持有第一級毒品者，處3年以下有期徒刑、拘役或新臺幣5萬元以下罰金。持有第二級毒品者，處2年以下有期徒刑、拘役或新臺幣3萬元以下罰金。持有第一級毒品純質淨重十公克以上者，處1年以上7年以下有期徒刑，得併科新臺幣1百萬元以下罰金。持有第二級毒品純質淨重二十公克以上者，處6月以上5年以下有期徒刑，得併科新臺幣70萬元以下罰金。持有第三級毒品純質淨重二十公克以上者，處3年以下有期徒刑，得併科新臺幣30萬元以下罰金。持有第四級毒品純質淨重二十公克以上者，處1年以下有期徒刑，得併科新臺幣10萬元以下罰金。持有專供製造或施用第一級、第二級毒品之器具者，處1年以下有期徒刑、拘役或新臺幣1萬元以下罰金。附表一：（沒收物）┌───┬──────┬───┬─────────────┬──────┬──────┐││││鑑驗結果││││編號│扣押物品名稱│數量││毒品沒收之依│鑑定書││││├───────┬─────┤據││││││重量│成分│││├───┼──────┼───┼───────┼─────┼──────┼──────┤│1│白色結晶│22包│總毛重42.193公│均檢出第三│刑法第38條第│交通部民用航│││││克，驗餘總淨重│級毒品愷他│1項第1款。│空局航空醫務│││││35.9575公克，│命成分。││中心100年8月│││││總純質淨重│││31日航藥鑑字│││││30.5002公克。│││第0000000Q號││││││││毒品鑑定書（││││││││見偵查卷第69││││││││頁至第70頁）│├───┼──────┼───┼───────┼─────┼──────┼──────┤│2│桃紅色圓形鑽│4顆│總淨重1.085公│均檢出第二│毒品危害防制│交通部民用航│││石形狀錠劑││克，驗餘總淨重│級毒品MDMA│條例第18條第│空局航空醫務│││││1.0815公克。│成分。│1項前段。│中心100年8月││││││││12日航藥鑑字││││││││第0000000號││││││││毒品鑑定書（││││││││見偵查卷第66││││││││頁正反面）│├───┼──────┼───┼───────┼─────┼──────┼──────┤│3│藍色圓形錠劑│3顆│總淨重0.8520公│均檢出第二│同上。│同上。│││││克，驗餘總淨重│級毒品MDMA│││││││0.8502公克。│成分。│││││││││││├───┼──────┼───┼───────┼─────┼──────┼──────┤│4│粉紅色圓形錠│2顆│總淨重0.5810公│均檢出第二│同上。│同上。│││劑││克，驗餘總淨重│級毒品MDMA│││││││0.5787公克。│成分。│││├───┼──────┼───┼───────┼─────┼──────┼──────┤│5│淡橘色圓形錠│2顆│總淨重0.6080公│均檢出第二│同上。│同上。│││劑││克，驗餘總淨重│級毒品甲基│││││││0.6051公克。│安非他命、││││││││MDMA成分。│││├───┼──────┼───┼───────┼─────┼──────┼──────┤│6│褐色圓形錠劑│4顆│總淨重1.2920公│均檢出第二│同上。│同上。│││││克，驗餘總淨重│級毒品甲基│││││││1.2892公克。│安非他命成││││││││分。│││├───┼──────┼───┼───────┼─────┼──────┼──────┤│7│米白色圓形錠│3顆│總淨重0.8740公│均檢出第二│同上。│同上。│││劑││克，驗餘總淨重│級毒品MDMA│││││││0.8711公克。│成分。│││││││││││├───┼──────┼───┼───────┼─────┼──────┼──────┤│8│剪裁後之牛皮│14個│無。│無。│刑法第38條第│無。│││薪資袋││││1項第2款。││││││││││└───┴──────┴───┴───────┴─────┴──────┴──────┘附表二：（不予沒收）┌───┬──────┬───┬─────────────┬──────┐││││鑑驗結果│││編號│扣押物品名稱│數量││鑑定書││││├───────┬─────┤│││││重量│成分││├───┼──────┼───┼───────┼─────┼──────┤│1│綠色圓形錠劑│3顆│總淨重0.9660公│均僅檢出未│交通部民用航│││││克，驗餘總淨重│經列管之咖│空局航空醫務│││││0.9639公克。│啡因、氯安│中心100年8月││││││非他命（Ch│12日航藥鑑字││││││loroamphet│第0000000號││││││amine）成│毒品鑑定書（││││││分，而均未│見偵查卷第66││││││檢出毒品成│頁正反面）││││││分。││├───┼──────┼───┼───────┼─────┼──────┤│2│藍色圓形錠劑│3顆│總淨重1.1110公│均僅檢出咖│同上。│││││克，驗餘總淨重│啡因、Meth││││││1.1083公克。│ylone(3,4-│││││││亞甲基雙氧│││││││甲基卡西酮│││││││，亦稱3,4-│││││││methylened│││││││ioxyme、bk│││││││-MDMA，於1│││││││00年9月8日│││││││始經行政院│││││││以院臺法字│││││││第00000000│││││││44號函公告│││││││列為第三級│││││││毒品，被告│││││││持有時尚非│││││││經公告列管│││││││之毒品）成│││││││分。││├───┼──────┼───┼───────┼─────┼──────┤│3│黃綠色圓形錠│3顆│總淨重0.9740公│均僅檢出咖│同上。│││劑││克，驗餘總淨重│啡因、氯安││││││0.9719公克。│非他命成分│││││││，而均未檢│││││││出毒品成分│││││││。││├───┼──────┼───┼───────┼─────┼──────┤│4│珊瑚紅色圓形│3顆│總淨重0.9560公│均僅檢出咖│同上。│││錠劑││克，驗餘總淨重│啡因、氯安││││││0.9507公克。│非他命成分│││││││，而均未檢│││││││出毒品成分│││││││。││└───┴──────┴───┴───────┴─────┴──────┘",
  "characters": {
    "judges": [
      "謝昀璉"
    ],
    "prosecutors": [

    ],
    "lawyers": [

    ],
    "clerks": [
      "鄭雅文"
    ],
    "plaintiffs": [

    ],
    "defendants": [
      "王心怡"
    ],
    "prosecutor_office": [
      "臺灣臺北地方法院檢察署檢察官"
    ],
    "creditors": [

    ],
    "debtors": [

    ],
    "judicial_associate_officer": [

    ]
  },
  "adjudged_at": "2011-10-26",
  "created_at": "2016-02-14 04:58:56",
  "updated_at": "2016-02-14 04:58:56"
}