{
  "identify": "TPH-100-聲再-454-20111026-1",
  "court": {
    "name": "臺灣高等法院",
    "code": "TPH"
  },
  "division": {
    "name": "刑事",
    "code": "M"
  },
  "year": 100,
  "word": "聲再",
  "number": "454",
  "jcheck": "1",
  "reason": "偽造文書等",
  "content": "臺灣高等法院刑事裁定                100年度聲再字第454號\n再審聲請人\n即受判決人  張淑美\n選任辯護人  陳韋霖律師\n上列聲請人因偽造文書等案件，對於本院100 年度上訴字第1295\n號，中華民國100 年6月8日所為之第二審確定判決（原審案號：\n灣基隆地方法院99年度訴字第590 號），聲請再審，本院裁定如\n下：\n    主  文\n再審之聲請駁回。\n    理  由\n一、按「聲請再審應以再審書狀敘述理由，附具原判決之繕本及\n    證據，提出於管轄法院為之」；「法院認為聲請再審之程序\n    違背規定者，應以裁定駁回之」，刑事訴訟法第429 條、第\n    433 條分別定有明文。而同法對於不合法定程式之再審聲請\n    ，並無應定期間先命補正之規定，亦無準用同法第三編有關\n    上訴之規定，故此種訴訟程式之欠缺，法院無須先命補正。\n    （最高法院71年台抗字第337號判例、88年度台抗字第416號\n    裁定意旨可參）。\n二、經查：再審聲請人即受判決人張淑美對本院100年度上訴字\n    第1295號之確定案件聲請再審，然未據提出原判決之繕本，\n    其聲請再審之程式顯有欠缺，此項聲請再審程式之欠缺，法\n    律並無應定期先命補正之規定。因之，本件受判決人聲請再\n    審，揆諸前揭說明，於法即有未合，其聲請再審之程序顯屬\n    違背規定，應予駁回。\n三、據上論斷，應依同法第433條，裁定如主文。\n中    華    民    國   100    年    10    月    26    日\n                  刑事第二十一庭審判長法  官  周政達\n                                      法  官  江翠萍\n                                      法  官  許永煌\n以上正本證明與原本無異。\n如不服本裁定，應於收受送達後五日內向本院提出抗告狀。\n                                      書記官  賴資旻\n中    華    民    國   100    年    10    月    27    日",
  "structure": {
    "main": "再審之聲請駁回。",
    "reason": "一、按「聲請再審應以再審書狀敘述理由，附具原判決之繕本及\n    證據，提出於管轄法院為之」；「法院認為聲請再審之程序\n    違背規定者，應以裁定駁回之」，刑事訴訟法第429 條、第\n    433 條分別定有明文。而同法對於不合法定程式之再審聲請\n    ，並無應定期間先命補正之規定，亦無準用同法第三編有關\n    上訴之規定，故此種訴訟程式之欠缺，法院無須先命補正。\n    （最高法院71年台抗字第337號判例、88年度台抗字第416號\n    裁定意旨可參）。\n二、經查：再審聲請人即受判決人張淑美對本院100年度上訴字\n    第1295號之確定案件聲請再審，然未據提出原判決之繕本，\n    其聲請再審之程式顯有欠缺，此項聲請再審程式之欠缺，法\n    律並無應定期先命補正之規定。因之，本件受判決人聲請再\n    審，揆諸前揭說明，於法即有未合，其聲請再審之程序顯屬\n    違背規定，應予駁回。\n三、據上論斷，應依同法第433條，裁定如主文。"
  },
  "search": "臺灣高等法院刑事裁定100年度聲再字第454號再審聲請人即受判決人張淑美選任辯護人陳韋霖律師上列聲請人因偽造文書等案件，對於本院100年度上訴字第1295號，中華民國100年6月8日所為之第二審確定判決（原審案號：灣基隆地方法院99年度訴字第590號），聲請再審，本院裁定如下：主文再審之聲請駁回。理由一、按「聲請再審應以再審書狀敘述理由，附具原判決之繕本及證據，提出於管轄法院為之」；「法院認為聲請再審之程序違背規定者，應以裁定駁回之」，刑事訴訟法第429條、第433條分別定有明文。而同法對於不合法定程式之再審聲請，並無應定期間先命補正之規定，亦無準用同法第三編有關上訴之規定，故此種訴訟程式之欠缺，法院無須先命補正。（最高法院71年台抗字第337號判例、88年度台抗字第416號裁定意旨可參）。二、經查：再審聲請人即受判決人張淑美對本院100年度上訴字第1295號之確定案件聲請再審，然未據提出原判決之繕本，其聲請再審之程式顯有欠缺，此項聲請再審程式之欠缺，法律並無應定期先命補正之規定。因之，本件受判決人聲請再審，揆諸前揭說明，於法即有未合，其聲請再審之程序顯屬違背規定，應予駁回。三、據上論斷，應依同法第433條，裁定如主文。中華民國100年10月26日刑事第二十一庭審判長法官周政達法官江翠萍法官許永煌以上正本證明與原本無異。如不服本裁定，應於收受送達後五日內向本院提出抗告狀。書記官賴資旻中華民國100年10月27日",
  "characters": {
    "judges": [
      "周政達",
      "江翠萍",
      "許永煌"
    ],
    "prosecutors": [

    ],
    "lawyers": [
      "陳韋霖"
    ],
    "clerks": [
      "賴資旻"
    ],
    "plaintiffs": [

    ],
    "defendants": [

    ],
    "prosecutor_office": [

    ],
    "creditors": [

    ],
    "debtors": [

    ],
    "judicial_associate_officer": [

    ]
  },
  "adjudged_at": "2011-10-26",
  "created_at": "2016-02-14 05:03:42",
  "updated_at": "2016-02-14 05:03:42"
}