{
  "identify": "TYD-100-審易-2299-20111026-1",
  "court": {
    "name": "臺灣桃園地方法院",
    "code": "TYD"
  },
  "division": {
    "name": "刑事",
    "code": "M"
  },
  "year": 100,
  "word": "審易",
  "number": "2299",
  "jcheck": "1",
  "reason": "詐欺",
  "content": "臺灣桃園地方法院刑事判決           100年度審易字第2299號\n公  訴  人  臺灣桃園地方法院檢察署檢察官\n被      告  徐再生\n上列被告因詐欺案件，經檢察官提起公訴（99年度偵字第 22680\n號），本院判決如下：\n    主  文\n本件公訴不受理。\n    理  由\n一、本件公訴意旨略以：被告徐再生不思悔改，明知自己經濟困\n    頓，無力付款，竟意圖為自己不法所有，於民國99年2 月14\n    日，至桃園縣平鎮市○○路○○段1 巷42弄11號陶雄所經營\n    之雜貨店，選購共計價值新臺幣540 元之貨物後，向陶雄表\n    示要賒帳，經陶雄拒絕後，遂佯稱要將國民身分證、戶口名\n    簿交予陶雄作為抵押，其要回去拿錢等語，致使陶雄信以為\n    真而陷於錯誤，而於收受徐再生所交付之國民身分證及戶口\n    名簿後將上開貨物交予徐再生，惟徐再生離去後並未依約回\n    來付款。陶雄始知受騙並報警處理，而獲上情。因認被告涉\n    犯刑法第339 條第1 項詐欺取財罪嫌。\n二、按被告死亡者，應諭知不受理之判決，並得不經言詞辯論逕\n    行判決，刑事訴訟法第303 條第5 款、第307 條分別定有明\n    文。\n三、經查，被告徐再生業於100 年6 月28日，因肺結核合併兩側\n    肋膜積水，引發呼吸衰竭而死亡之情，有個人戶籍謄本、死\n    亡登記申請書、個人基本資料查詢結果、壢新醫院死亡證明\n    書各1 份附卷可稽，揆諸首開說明，爰不經言詞辯論，逕行\n    諭知不受理之判決。\n據上論斷，應依刑事訴訟法第303 條第5 款、第307 條，判決如\n主文。\n中    華    民    國   100    年    10    月    26    日\n                        刑事庭  審判長法  官  游紅桃\n                                      法  官  黃翊哲\n                                      法  官  蘇昌澤\n以上正本證明與原本無異。\n如不服本判決應於收受判決後10日內向本院提出上訴書狀，並應\n敘述具體理由。其未敘述上訴理由者，應於上訴期間屆滿後20日\n內向本院補提理由書( 均須按他造當事人之人數附繕本) 「切勿\n逕送上級法院」。\n                                      書記官  李佳穎\n中    華    民    國   100    年    10    月    26    日",
  "structure": {
    "main": "本件公訴不受理。",
    "reason": "一、本件公訴意旨略以：被告徐再生不思悔改，明知自己經濟困\n    頓，無力付款，竟意圖為自己不法所有，於民國99年2 月14\n    日，至桃園縣平鎮市○○路○○段1 巷42弄11號陶雄所經營\n    之雜貨店，選購共計價值新臺幣540 元之貨物後，向陶雄表\n    示要賒帳，經陶雄拒絕後，遂佯稱要將國民身分證、戶口名\n    簿交予陶雄作為抵押，其要回去拿錢等語，致使陶雄信以為\n    真而陷於錯誤，而於收受徐再生所交付之國民身分證及戶口\n    名簿後將上開貨物交予徐再生，惟徐再生離去後並未依約回\n    來付款。陶雄始知受騙並報警處理，而獲上情。因認被告涉\n    犯刑法第339 條第1 項詐欺取財罪嫌。\n二、按被告死亡者，應諭知不受理之判決，並得不經言詞辯論逕\n    行判決，刑事訴訟法第303 條第5 款、第307 條分別定有明\n    文。\n三、經查，被告徐再生業於100 年6 月28日，因肺結核合併兩側\n    肋膜積水，引發呼吸衰竭而死亡之情，有個人戶籍謄本、死\n    亡登記申請書、個人基本資料查詢結果、壢新醫院死亡證明\n    書各1 份附卷可稽，揆諸首開說明，爰不經言詞辯論，逕行\n    諭知不受理之判決。\n據上論斷，應依刑事訴訟法第303 條第5 款、第307 條，判決如\n主文。"
  },
  "search": "臺灣桃園地方法院刑事判決100年度審易字第2299號公訴人臺灣桃園地方法院檢察署檢察官被告徐再生上列被告因詐欺案件，經檢察官提起公訴（99年度偵字第22680號），本院判決如下：主文本件公訴不受理。理由一、本件公訴意旨略以：被告徐再生不思悔改，明知自己經濟困頓，無力付款，竟意圖為自己不法所有，於民國99年2月14日，至桃園縣平鎮市○○路○○段1巷42弄11號陶雄所經營之雜貨店，選購共計價值新臺幣540元之貨物後，向陶雄表示要賒帳，經陶雄拒絕後，遂佯稱要將國民身分證、戶口名簿交予陶雄作為抵押，其要回去拿錢等語，致使陶雄信以為真而陷於錯誤，而於收受徐再生所交付之國民身分證及戶口名簿後將上開貨物交予徐再生，惟徐再生離去後並未依約回來付款。陶雄始知受騙並報警處理，而獲上情。因認被告涉犯刑法第339條第1項詐欺取財罪嫌。二、按被告死亡者，應諭知不受理之判決，並得不經言詞辯論逕行判決，刑事訴訟法第303條第5款、第307條分別定有明文。三、經查，被告徐再生業於100年6月28日，因肺結核合併兩側肋膜積水，引發呼吸衰竭而死亡之情，有個人戶籍謄本、死亡登記申請書、個人基本資料查詢結果、壢新醫院死亡證明書各1份附卷可稽，揆諸首開說明，爰不經言詞辯論，逕行諭知不受理之判決。據上論斷，應依刑事訴訟法第303條第5款、第307條，判決如主文。中華民國100年10月26日刑事庭審判長法官游紅桃法官黃翊哲法官蘇昌澤以上正本證明與原本無異。如不服本判決應於收受判決後10日內向本院提出上訴書狀，並應敘述具體理由。其未敘述上訴理由者，應於上訴期間屆滿後20日內向本院補提理由書(均須按他造當事人之人數附繕本)「切勿逕送上級法院」。書記官李佳穎中華民國100年10月26日",
  "characters": {
    "judges": [
      "游紅桃",
      "黃翊哲",
      "蘇昌澤"
    ],
    "prosecutors": [

    ],
    "lawyers": [

    ],
    "clerks": [
      "李佳穎"
    ],
    "plaintiffs": [

    ],
    "defendants": [
      "徐再生"
    ],
    "prosecutor_office": [
      "臺灣桃園地方法院檢察署檢察官"
    ],
    "creditors": [

    ],
    "debtors": [

    ],
    "judicial_associate_officer": [

    ]
  },
  "adjudged_at": "2011-10-26",
  "created_at": "2016-02-14 05:03:55",
  "updated_at": "2016-02-14 05:03:55"
}