{
  "identify": "KSD-94-聲-564-20050429-1",
  "court": {
    "name": "臺灣高雄地方法院",
    "code": "KSD"
  },
  "division": {
    "name": "民事",
    "code": "V"
  },
  "year": 94,
  "word": "聲",
  "number": "564",
  "jcheck": "1",
  "reason": "確定訴訟費用",
  "content": "臺灣高雄地方法院民事裁定               94年度聲字第564號\n聲  請  人  陽信商業銀行股份有限公司\n法定代理人  陳勝宏\n                      送達代收.\n相  對  人  張源駿\n當事人間請求清償借款事件，聲請人聲請確定訴訟費用額，本院\n裁定如下：\n    主      文\n相對人應負擔之訴訟費用額確定為新台幣壹萬捌仟零參拾陸元，\n及自本裁定送達翌日起至清償日止，按週年利率百分之5 計算之\n利息。\n    理      由\n一、聲請人與相對人間請求清償借款事件，經本院民國93年度訴\n    字第2575號判決確定，其訴訟費用應由相對人負擔。\n二、經本院調卷審查後，相對人應給付聲請人之訴訟費用額，依\n    後附計算書確定為如主文所示金額。\n三、依民事訴訟法第91條，裁定如主文。\n中    華    民    國    94    年    4     月    29    日\n                  民事第二庭法  官  黃呈熹\n正本係照原本作成。\n如不服本裁定，應於送達後10日內，向本院提出抗告狀，並繳納\n裁判費新台幣1,000元。\n中    華    民    國    94    年    4     月    29    日\n                                書記官  曾瓊玉\n┌───────────────────────────────┐\n│計算書                                                        │\n├───────┬──────────┬────────────┤\n│  項      目  │  金  額（新台幣）  │      備        註      │\n├───────┼──────────┼────────────┤\n│裁判費        │17236元             │                        │\n├───────┼──────────┼────────────┤\n│送達費        │800元               │                        │\n├───────┴──────────┴────────────┤\n│共計18036元                                                   │\n└───────────────────────────────┘\n",
  "structure": {
    "main": "相對人應負擔之訴訟費用額確定為新台幣壹萬捌仟零參拾陸元，\n及自本裁定送達翌日起至清償日止，按週年利率百分之5 計算之\n利息。",
    "reason": "一、聲請人與相對人間請求清償借款事件，經本院民國93年度訴\n    字第2575號判決確定，其訴訟費用應由相對人負擔。\n二、經本院調卷審查後，相對人應給付聲請人之訴訟費用額，依\n    後附計算書確定為如主文所示金額。\n三、依民事訴訟法第91條，裁定如主文。"
  },
  "search": "臺灣高雄地方法院民事裁定94年度聲字第564號聲請人陽信商業銀行股份有限公司法定代理人陳勝宏送達代收.相對人張源駿當事人間請求清償借款事件，聲請人聲請確定訴訟費用額，本院裁定如下：主文相對人應負擔之訴訟費用額確定為新台幣壹萬捌仟零參拾陸元，及自本裁定送達翌日起至清償日止，按週年利率百分之5計算之利息。理由一、聲請人與相對人間請求清償借款事件，經本院民國93年度訴字第2575號判決確定，其訴訟費用應由相對人負擔。二、經本院調卷審查後，相對人應給付聲請人之訴訟費用額，依後附計算書確定為如主文所示金額。三、依民事訴訟法第91條，裁定如主文。中華民國94年4月29日民事第二庭法官黃呈熹正本係照原本作成。如不服本裁定，應於送達後10日內，向本院提出抗告狀，並繳納裁判費新台幣1,000元。中華民國94年4月29日書記官曾瓊玉┌───────────────────────────────┐│計算書│├───────┬──────────┬────────────┤│項目│金額（新台幣）│備註│├───────┼──────────┼────────────┤│裁判費│17236元││├───────┼──────────┼────────────┤│送達費│800元││├───────┴──────────┴────────────┤│共計18036元│└───────────────────────────────┘",
  "characters": {
    "judges": [
      "黃呈熹"
    ],
    "prosecutors": [

    ],
    "lawyers": [

    ],
    "clerks": [
      "曾瓊玉"
    ],
    "plaintiffs": [

    ],
    "defendants": [

    ],
    "prosecutor_office": [
      "陽信商業銀行股份有限公司"
    ],
    "creditors": [

    ],
    "debtors": [

    ],
    "judicial_associate_officer": [

    ]
  },
  "adjudged_at": "2005-04-29",
  "created_at": "2016-02-06 19:03:09",
  "updated_at": "2016-02-06 19:03:09"
}