{
  "identify": "SLD-94-重訴-105-20050429-2",
  "court": {
    "name": "臺灣士林地方法院",
    "code": "SLD"
  },
  "division": {
    "name": "民事",
    "code": "V"
  },
  "year": 94,
  "word": "重訴",
  "number": "105",
  "jcheck": "2",
  "reason": "給付貨款",
  "content": "臺灣士林地方法院民事裁定  94年度重訴字第105號\n原      告  甲○○○○○○○ .\n法定代理人  Steven J..\n訴訟代理人  陳長文律師\n            宋耀明律師\n            賴文萍律師\n被      告  宇詮科技股份有限公司\n法定代理人  游良福\n上列當事人間請求給付貨款事件，本院裁定如下：\n    主  文\n原告之訴駁回。\n訴訟費用由原告負擔。\n    理  由\n一、按因財產權而起訴，應依民事訴訟法第77條之13規定繳納裁\n    判費，此為必須具備之程式。\n二、本件原告起訴，僅繳納部分裁判費，經本院於民國94年4 月\n    11日裁定命原告於5 日內補正。該項裁定已於民國94年4 月\n    15日送達原告，有送達證書附卷可憑。\n三、原告逾期迄未補正，其訴顯難認為合法，應予駁回。\n四、依民事訴訟法第249 條第1 項第6 款、第95條、第78條裁定\n    如主文。\n中    華    民    國    94    年    4     月    29    日\n                  民事第一庭法  官  陳麗芬\n以上正本證明與原本無異。\n如對本裁定抗告應於送達後10日內向本院提出抗告狀。\n中    華    民    國    94    年    4     月    29    日\n                            書記官  黃惠苹\n",
  "structure": {
    "main": "原告之訴駁回。\n訴訟費用由原告負擔。",
    "reason": "一、按因財產權而起訴，應依民事訴訟法第77條之13規定繳納裁\n    判費，此為必須具備之程式。\n二、本件原告起訴，僅繳納部分裁判費，經本院於民國94年4 月\n    11日裁定命原告於5 日內補正。該項裁定已於民國94年4 月\n    15日送達原告，有送達證書附卷可憑。\n三、原告逾期迄未補正，其訴顯難認為合法，應予駁回。\n四、依民事訴訟法第249 條第1 項第6 款、第95條、第78條裁定\n    如主文。"
  },
  "search": "臺灣士林地方法院民事裁定94年度重訴字第105號原告甲○○○○○○○.法定代理人StevenJ..訴訟代理人陳長文律師宋耀明律師賴文萍律師被告宇詮科技股份有限公司法定代理人游良福上列當事人間請求給付貨款事件，本院裁定如下：主文原告之訴駁回。訴訟費用由原告負擔。理由一、按因財產權而起訴，應依民事訴訟法第77條之13規定繳納裁判費，此為必須具備之程式。二、本件原告起訴，僅繳納部分裁判費，經本院於民國94年4月11日裁定命原告於5日內補正。該項裁定已於民國94年4月15日送達原告，有送達證書附卷可憑。三、原告逾期迄未補正，其訴顯難認為合法，應予駁回。四、依民事訴訟法第249條第1項第6款、第95條、第78條裁定如主文。中華民國94年4月29日民事第一庭法官陳麗芬以上正本證明與原本無異。如對本裁定抗告應於送達後10日內向本院提出抗告狀。中華民國94年4月29日書記官黃惠苹",
  "characters": {
    "judges": [
      "陳麗芬"
    ],
    "prosecutors": [

    ],
    "lawyers": [
      "陳長文",
      "宋耀明",
      "賴文萍"
    ],
    "clerks": [
      "黃惠苹"
    ],
    "plaintiffs": [
      "甲"
    ],
    "defendants": [
      "宇詮科技股份有限公司"
    ],
    "prosecutor_office": [

    ],
    "creditors": [

    ],
    "debtors": [

    ],
    "judicial_associate_officer": [

    ]
  },
  "adjudged_at": "2005-04-29",
  "created_at": "2016-02-06 19:14:42",
  "updated_at": "2016-02-06 19:14:42"
}