{
  "identify": "CYD-94-自-10-20051025-1",
  "court": {
    "name": "臺灣嘉義地方法院",
    "code": "CYD"
  },
  "division": {
    "name": "刑事",
    "code": "M"
  },
  "year": 94,
  "word": "自",
  "number": "10",
  "jcheck": "1",
  "reason": "偽造文書",
  "content": "臺灣嘉義地方法院刑事裁定                 94年度自字第10號\n    自  訴  人  丙○○○\n    被      告  甲○○\n                乙○○\n    共      同\n    選任辯護人  林春發律師\n上列被告因偽造文書案件，經自訴人提起自訴，本院裁定如下：\n    主  文\n自訴人丙○○○應於本裁定送達後拾日內委任代理人。\n    理  由\n一、按「自訴之提起，應委任律師行之。」；「自訴人未委任代\n    理人，法院應定期間以裁定命其委任代理人；逾期仍不委任\n    者，應諭知不受理之判決。」刑事訴訟法第三百十九條第二\n    項、第三百二十九條第二項均有明文。\n二、查本件自訴人原委任之代理人陳培芬律師已於民國九十四年\n    十月二十五日遞狀解除本件自訴代理人之委任，自訴人自斯\n    時起已無代理人可言。爰依刑事訴訟法第三百二十九條第二\n    項規定裁定命自訴人於裁定送達後十日內委任代理人，逾期\n    仍未委任，本院將諭知不受理之判決。\n中    華    民    國    94    年    10    月    25    日\n                            臺灣嘉義地方法院刑事第一庭\n                                審判長法  官  許進國\n                                      法  官  蔡廷宜\n                                      法  官  張道周\n上列正本證明與原本無異。\n本件不得抗告。\n中    華    民    國    94    年    10    月    26    日\n                                      書記官  黃意雯\n",
  "structure": {
    "main": "自訴人丙○○○應於本裁定送達後拾日內委任代理人。",
    "reason": "一、按「自訴之提起，應委任律師行之。」；「自訴人未委任代\n    理人，法院應定期間以裁定命其委任代理人；逾期仍不委任\n    者，應諭知不受理之判決。」刑事訴訟法第三百十九條第二\n    項、第三百二十九條第二項均有明文。\n二、查本件自訴人原委任之代理人陳培芬律師已於民國九十四年\n    十月二十五日遞狀解除本件自訴代理人之委任，自訴人自斯\n    時起已無代理人可言。爰依刑事訴訟法第三百二十九條第二\n    項規定裁定命自訴人於裁定送達後十日內委任代理人，逾期\n    仍未委任，本院將諭知不受理之判決。"
  },
  "search": "臺灣嘉義地方法院刑事裁定94年度自字第10號自訴人丙○○○被告甲○○乙○○共同選任辯護人林春發律師上列被告因偽造文書案件，經自訴人提起自訴，本院裁定如下：主文自訴人丙○○○應於本裁定送達後拾日內委任代理人。理由一、按「自訴之提起，應委任律師行之。」；「自訴人未委任代理人，法院應定期間以裁定命其委任代理人；逾期仍不委任者，應諭知不受理之判決。」刑事訴訟法第三百十九條第二項、第三百二十九條第二項均有明文。二、查本件自訴人原委任之代理人陳培芬律師已於民國九十四年十月二十五日遞狀解除本件自訴代理人之委任，自訴人自斯時起已無代理人可言。爰依刑事訴訟法第三百二十九條第二項規定裁定命自訴人於裁定送達後十日內委任代理人，逾期仍未委任，本院將諭知不受理之判決。中華民國94年10月25日臺灣嘉義地方法院刑事第一庭審判長法官許進國法官蔡廷宜法官張道周上列正本證明與原本無異。本件不得抗告。中華民國94年10月26日書記官黃意雯",
  "characters": {
    "judges": [
      "許進國",
      "蔡廷宜",
      "張道周"
    ],
    "prosecutors": [

    ],
    "lawyers": [
      "林春發"
    ],
    "clerks": [
      "黃意雯"
    ],
    "plaintiffs": [

    ],
    "defendants": [
      "甲○○"
    ],
    "prosecutor_office": [

    ],
    "creditors": [

    ],
    "debtors": [

    ],
    "judicial_associate_officer": [

    ]
  },
  "adjudged_at": "2005-10-25",
  "created_at": "2016-02-07 10:38:04",
  "updated_at": "2016-02-07 10:38:04"
}