{
  "identify": "PTD-94-交簡-661-20051024-1",
  "court": {
    "name": "臺灣屏東地方法院",
    "code": "PTD"
  },
  "division": {
    "name": "刑事",
    "code": "M"
  },
  "year": 94,
  "word": "交簡",
  "number": "661",
  "jcheck": "1",
  "reason": "公共危險",
  "content": "臺灣屏東地方法院刑事判決             94年度交簡字第661號\n聲  請  人  臺灣屏東地方法院檢察署檢察官\n被      告  甲○○\n上列被告因公共危險案件，經檢察官聲請簡易判決處刑（94年度\n偵字第4669 號），本院判決如下：\n    主  文\n甲○○服用酒類，不能安全駕駛動力交通工具而駕駛，處有期徒\n刑伍月，如易科罰金，以佰元折算壹日。\n    事實及理由\n一、本院認定被告之犯罪事實、證據及應適用之法條，除犯罪事\n    實第一行「甲○○明知酒後駕駛動力交通工具」補充更正為\n    「甲○○前於民國76年間因業務過失致死案件，經臺灣高雄\n    地方法院76年度交訴字第282 號判處有期徒刑1 年，緩刑 5\n    年確定；復於92年間因業務過失致死案件，經臺灣高等法院\n    高雄分院92年度交上訴字第80號判處有期徒刑8 月，緩刑 3\n    年確定。詎其猶不知悔改，明知酒後駕駛動力交通工具」等\n    語外，餘均與檢察官聲請簡易判決處刑書之記載相同，茲引\n    用之（如附件）。理由部分並補充：按刑法第185 條之3 所\n    稱不能安全駕駛動力交通工具，依法務部召集內政部警政署\n    等相關單位研議，並參考德國、美國之認定標準，對於酒精\n    濃度呼氣已達每公升0.55毫克或血液濃度達百分之0.11點以\n    上，肇事率為一般正常人之十倍，認為已達「不能安全駕駛\n    」之標準，有法務部88年5 月18日法88檢字第001669號函可\n    參。查被告為警查獲時，經抽血檢測其血液中酒精濃度，測\n    得其血液中酒精濃度高達為252 ｍｇ／ｄｌ（換算呼氣酒精\n    濃度約為每公升1.26毫克)， 復佐以被告駕車自行倒地及依\n    卷附刑法第185 條之3 案件測試觀察紀錄表所載：被告查獲\n    過程有昏睡叫喚不醒、泥醉等情事，堪認被告駕車當時，確\n    已達於不能安全駕駛動力交通工具之程度。本件事證明確，\n    被告犯行堪予認定。\n二、核被告所為，係犯刑法第185 條之3 酒醉駕車公共危險罪。\n    爰審酌被告飲酒之程度、駕駛之動力交通工具為重型機車、\n    對使用道路之人、車所生之危害、犯後供承酒後駕車，及其\n    曾有2 次過失致死前科，現仍在緩刑期內，竟不思謹慎，再\n    犯本件酒醉駕車案件，顯見其莫視用路人、車之安全，並無\n    悔改之意等一切情狀，量處如主文所示之刑，並諭知易科罰\n    金之折算標準。\n三、據上論斷，應依刑事訴訟法第449 條第1 項前段、第454 條\n    第2 項，刑法第185 條之3 、第41條第1 項前段，罰金罰鍰\n    提高標準條例第2條，逕以簡易判決如主文。\n中    華    民    國    94    年    10    月    24    日\n                  交通法庭   法  官  蘇碧珠\n右正本證明與原本無異。\n如不服本判決，得於判決書送達之翌日起十日內，以書狀敘述理\n由，向本庭提出上訴。\n                             書記官  賀燕花\n中    華    民    國    94    年    10    月    24    日\n附錄本判決論罪科刑法條全文\n刑法第185條之3：\n服用毒品、麻醉藥品、酒類或其他相類之物，不能安全駕駛動力\n交通工具而駕駛者，處一年以下有期徒刑、拘役或三萬元以下罰\n金。\n",
  "structure": {
    "main": "甲○○服用酒類，不能安全駕駛動力交通工具而駕駛，處有期徒\n刑伍月，如易科罰金，以佰元折算壹日。",
    "fact": "一、本院認定被告之犯罪事實、證據及應適用之法條，除犯罪事\n    實第一行「甲○○明知酒後駕駛動力交通工具」補充更正為\n    「甲○○前於民國76年間因業務過失致死案件，經臺灣高雄\n    地方法院76年度交訴字第282 號判處有期徒刑1 年，緩刑 5\n    年確定；復於92年間因業務過失致死案件，經臺灣高等法院\n    高雄分院92年度交上訴字第80號判處有期徒刑8 月，緩刑 3\n    年確定。詎其猶不知悔改，明知酒後駕駛動力交通工具」等\n    語外，餘均與檢察官聲請簡易判決處刑書之記載相同，茲引\n    用之（如附件）。理由部分並補充：按刑法第185 條之3 所\n    稱不能安全駕駛動力交通工具，依法務部召集內政部警政署\n    等相關單位研議，並參考德國、美國之認定標準，對於酒精\n    濃度呼氣已達每公升0.55毫克或血液濃度達百分之0.11點以\n    上，肇事率為一般正常人之十倍，認為已達「不能安全駕駛\n    」之標準，有法務部88年5 月18日法88檢字第001669號函可\n    參。查被告為警查獲時，經抽血檢測其血液中酒精濃度，測\n    得其血液中酒精濃度高達為252 ｍｇ／ｄｌ（換算呼氣酒精\n    濃度約為每公升1.26毫克)， 復佐以被告駕車自行倒地及依\n    卷附刑法第185 條之3 案件測試觀察紀錄表所載：被告查獲\n    過程有昏睡叫喚不醒、泥醉等情事，堪認被告駕車當時，確\n    已達於不能安全駕駛動力交通工具之程度。本件事證明確，\n    被告犯行堪予認定。\n二、核被告所為，係犯刑法第185 條之3 酒醉駕車公共危險罪。\n    爰審酌被告飲酒之程度、駕駛之動力交通工具為重型機車、\n    對使用道路之人、車所生之危害、犯後供承酒後駕車，及其\n    曾有2 次過失致死前科，現仍在緩刑期內，竟不思謹慎，再\n    犯本件酒醉駕車案件，顯見其莫視用路人、車之安全，並無\n    悔改之意等一切情狀，量處如主文所示之刑，並諭知易科罰\n    金之折算標準。\n三、據上論斷，應依刑事訴訟法第449 條第1 項前段、第454 條\n    第2 項，刑法第185 條之3 、第41條第1 項前段，罰金罰鍰\n    提高標準條例第2條，逕以簡易判決如主文。",
    "reason": "一、本院認定被告之犯罪事實、證據及應適用之法條，除犯罪事\n    實第一行「甲○○明知酒後駕駛動力交通工具」補充更正為\n    「甲○○前於民國76年間因業務過失致死案件，經臺灣高雄\n    地方法院76年度交訴字第282 號判處有期徒刑1 年，緩刑 5\n    年確定；復於92年間因業務過失致死案件，經臺灣高等法院\n    高雄分院92年度交上訴字第80號判處有期徒刑8 月，緩刑 3\n    年確定。詎其猶不知悔改，明知酒後駕駛動力交通工具」等\n    語外，餘均與檢察官聲請簡易判決處刑書之記載相同，茲引\n    用之（如附件）。理由部分並補充：按刑法第185 條之3 所\n    稱不能安全駕駛動力交通工具，依法務部召集內政部警政署\n    等相關單位研議，並參考德國、美國之認定標準，對於酒精\n    濃度呼氣已達每公升0.55毫克或血液濃度達百分之0.11點以\n    上，肇事率為一般正常人之十倍，認為已達「不能安全駕駛\n    」之標準，有法務部88年5 月18日法88檢字第001669號函可\n    參。查被告為警查獲時，經抽血檢測其血液中酒精濃度，測\n    得其血液中酒精濃度高達為252 ｍｇ／ｄｌ（換算呼氣酒精\n    濃度約為每公升1.26毫克)， 復佐以被告駕車自行倒地及依\n    卷附刑法第185 條之3 案件測試觀察紀錄表所載：被告查獲\n    過程有昏睡叫喚不醒、泥醉等情事，堪認被告駕車當時，確\n    已達於不能安全駕駛動力交通工具之程度。本件事證明確，\n    被告犯行堪予認定。\n二、核被告所為，係犯刑法第185 條之3 酒醉駕車公共危險罪。\n    爰審酌被告飲酒之程度、駕駛之動力交通工具為重型機車、\n    對使用道路之人、車所生之危害、犯後供承酒後駕車，及其\n    曾有2 次過失致死前科，現仍在緩刑期內，竟不思謹慎，再\n    犯本件酒醉駕車案件，顯見其莫視用路人、車之安全，並無\n    悔改之意等一切情狀，量處如主文所示之刑，並諭知易科罰\n    金之折算標準。\n三、據上論斷，應依刑事訴訟法第449 條第1 項前段、第454 條\n    第2 項，刑法第185 條之3 、第41條第1 項前段，罰金罰鍰\n    提高標準條例第2條，逕以簡易判決如主文。"
  },
  "search": "臺灣屏東地方法院刑事判決94年度交簡字第661號聲請人臺灣屏東地方法院檢察署檢察官被告甲○○上列被告因公共危險案件，經檢察官聲請簡易判決處刑（94年度偵字第4669號），本院判決如下：主文甲○○服用酒類，不能安全駕駛動力交通工具而駕駛，處有期徒刑伍月，如易科罰金，以佰元折算壹日。事實及理由一、本院認定被告之犯罪事實、證據及應適用之法條，除犯罪事實第一行「甲○○明知酒後駕駛動力交通工具」補充更正為「甲○○前於民國76年間因業務過失致死案件，經臺灣高雄地方法院76年度交訴字第282號判處有期徒刑1年，緩刑5年確定；復於92年間因業務過失致死案件，經臺灣高等法院高雄分院92年度交上訴字第80號判處有期徒刑8月，緩刑3年確定。詎其猶不知悔改，明知酒後駕駛動力交通工具」等語外，餘均與檢察官聲請簡易判決處刑書之記載相同，茲引用之（如附件）。理由部分並補充：按刑法第185條之3所稱不能安全駕駛動力交通工具，依法務部召集內政部警政署等相關單位研議，並參考德國、美國之認定標準，對於酒精濃度呼氣已達每公升0.55毫克或血液濃度達百分之0.11點以上，肇事率為一般正常人之十倍，認為已達「不能安全駕駛」之標準，有法務部88年5月18日法88檢字第001669號函可參。查被告為警查獲時，經抽血檢測其血液中酒精濃度，測得其血液中酒精濃度高達為252ｍｇ／ｄｌ（換算呼氣酒精濃度約為每公升1.26毫克)，復佐以被告駕車自行倒地及依卷附刑法第185條之3案件測試觀察紀錄表所載：被告查獲過程有昏睡叫喚不醒、泥醉等情事，堪認被告駕車當時，確已達於不能安全駕駛動力交通工具之程度。本件事證明確，被告犯行堪予認定。二、核被告所為，係犯刑法第185條之3酒醉駕車公共危險罪。爰審酌被告飲酒之程度、駕駛之動力交通工具為重型機車、對使用道路之人、車所生之危害、犯後供承酒後駕車，及其曾有2次過失致死前科，現仍在緩刑期內，竟不思謹慎，再犯本件酒醉駕車案件，顯見其莫視用路人、車之安全，並無悔改之意等一切情狀，量處如主文所示之刑，並諭知易科罰金之折算標準。三、據上論斷，應依刑事訴訟法第449條第1項前段、第454條第2項，刑法第185條之3、第41條第1項前段，罰金罰鍰提高標準條例第2條，逕以簡易判決如主文。中華民國94年10月24日交通法庭法官蘇碧珠右正本證明與原本無異。如不服本判決，得於判決書送達之翌日起十日內，以書狀敘述理由，向本庭提出上訴。書記官賀燕花中華民國94年10月24日附錄本判決論罪科刑法條全文刑法第185條之3：服用毒品、麻醉藥品、酒類或其他相類之物，不能安全駕駛動力交通工具而駕駛者，處一年以下有期徒刑、拘役或三萬元以下罰金。",
  "characters": {
    "judges": [
      "蘇碧珠"
    ],
    "prosecutors": [

    ],
    "lawyers": [

    ],
    "clerks": [
      "賀燕花"
    ],
    "plaintiffs": [

    ],
    "defendants": [
      "甲○○"
    ],
    "prosecutor_office": [
      "臺灣屏東地方法院檢察署檢察官"
    ],
    "creditors": [

    ],
    "debtors": [

    ],
    "judicial_associate_officer": [

    ]
  },
  "adjudged_at": "2005-10-24",
  "created_at": "2016-02-07 10:39:35",
  "updated_at": "2016-02-07 10:39:35"
}