{
  "identify": "TND-94-交簡-1935-20051024-1",
  "court": {
    "name": "臺灣臺南地方法院",
    "code": "TND"
  },
  "division": {
    "name": "刑事",
    "code": "M"
  },
  "year": 94,
  "word": "交簡",
  "number": "1935",
  "jcheck": "1",
  "reason": "公共危險",
  "content": "臺灣臺南地方法院刑事簡易判決        94年度交簡字第1935號\n聲  請  人  臺灣臺南地方法院檢察署檢察官\n被      告  甲○○\n上列被告因公共危險案件，經檢察官聲請以簡易判決處刑（94年\n度偵字第11784號），本院判決如下：\n    主  文\n甲○○服用酒類，不能安全駕駛動力交通工具而駕駛，處罰金伍\n仟元，如易服勞役，以佰元折算壹日。\n    事實及理由\n一、本件犯罪事實、證據均引用檢察官聲請簡易判決處刑書之記\n    載（如附件）。\n二、依刑事訴訟法第四百四十九條第一項前段、第四百五十四條\n    第二項，刑法第一百八十五條之三、第四十二條第二項，罰\n    金罰鍰提高標準條例第二條，逕以簡易判決處刑如主文。\n三、如不服本判決，得自收受送達之日起十日內，向本院提起上\n    訴。\n中    華    民    國    94    年    10    月    24    日\n                  刑事第六庭    法  官  張瑛宗\n以上正本證明與原本無異。\n                                書記官  吳姁穗\n中    華    民    國    94    年    10    月    24    日\n附錄本案論罪科刑法條：\n中華民國刑法第185條之3\n  服用毒品、麻醉藥品、酒類或其他相類之物，不能安全駕駛動\n  力交通工具而駕駛者，處1年以下有期徒刑、拘役或3萬元以下\n  罰金。\n",
  "structure": {
    "main": "甲○○服用酒類，不能安全駕駛動力交通工具而駕駛，處罰金伍\n仟元，如易服勞役，以佰元折算壹日。",
    "fact": "一、本件犯罪事實、證據均引用檢察官聲請簡易判決處刑書之記\n    載（如附件）。\n二、依刑事訴訟法第四百四十九條第一項前段、第四百五十四條\n    第二項，刑法第一百八十五條之三、第四十二條第二項，罰\n    金罰鍰提高標準條例第二條，逕以簡易判決處刑如主文。\n三、如不服本判決，得自收受送達之日起十日內，向本院提起上\n    訴。",
    "reason": "一、本件犯罪事實、證據均引用檢察官聲請簡易判決處刑書之記\n    載（如附件）。\n二、依刑事訴訟法第四百四十九條第一項前段、第四百五十四條\n    第二項，刑法第一百八十五條之三、第四十二條第二項，罰\n    金罰鍰提高標準條例第二條，逕以簡易判決處刑如主文。\n三、如不服本判決，得自收受送達之日起十日內，向本院提起上\n    訴。"
  },
  "search": "臺灣臺南地方法院刑事簡易判決94年度交簡字第1935號聲請人臺灣臺南地方法院檢察署檢察官被告甲○○上列被告因公共危險案件，經檢察官聲請以簡易判決處刑（94年度偵字第11784號），本院判決如下：主文甲○○服用酒類，不能安全駕駛動力交通工具而駕駛，處罰金伍仟元，如易服勞役，以佰元折算壹日。事實及理由一、本件犯罪事實、證據均引用檢察官聲請簡易判決處刑書之記載（如附件）。二、依刑事訴訟法第四百四十九條第一項前段、第四百五十四條第二項，刑法第一百八十五條之三、第四十二條第二項，罰金罰鍰提高標準條例第二條，逕以簡易判決處刑如主文。三、如不服本判決，得自收受送達之日起十日內，向本院提起上訴。中華民國94年10月24日刑事第六庭法官張瑛宗以上正本證明與原本無異。書記官吳姁穗中華民國94年10月24日附錄本案論罪科刑法條：中華民國刑法第185條之3服用毒品、麻醉藥品、酒類或其他相類之物，不能安全駕駛動力交通工具而駕駛者，處1年以下有期徒刑、拘役或3萬元以下罰金。",
  "characters": {
    "judges": [
      "張瑛宗"
    ],
    "prosecutors": [

    ],
    "lawyers": [

    ],
    "clerks": [
      "吳姁穗"
    ],
    "plaintiffs": [

    ],
    "defendants": [
      "甲○○"
    ],
    "prosecutor_office": [
      "臺灣臺南地方法院檢察署檢察官"
    ],
    "creditors": [

    ],
    "debtors": [

    ],
    "judicial_associate_officer": [

    ]
  },
  "adjudged_at": "2005-10-24",
  "created_at": "2016-02-07 10:38:00",
  "updated_at": "2016-02-07 10:38:00"
}