{
  "identify": "TPD-94-訴-4221-20051024-1",
  "court": {
    "name": "臺灣臺北地方法院",
    "code": "TPD"
  },
  "division": {
    "name": "民事",
    "code": "V"
  },
  "year": 94,
  "word": "訴",
  "number": "4221",
  "jcheck": "1",
  "reason": "返還消費借貸款",
  "content": "臺灣臺北地方法院民事判決              94年度訴字第4221號\n原      告  第一商業銀行股份有限公司\n法定代理人  乙○○\n訴訟代理人  丁○○\n被      告  建逸國際有限公司\n兼法定代理人  甲○○\n被      告    丙○○\n上開當事人間請求清償借款事件，本院於民國94年10月17日言詞\n辯論終結，判決如下：\n    主    文\n被告應連帶給付原告新臺幣貳佰拾壹萬玖仟伍佰肆拾陸元及如\n附表所示之利息及違約金。\n訴訟費用由被告連帶負擔。\n    事    實\n甲、原告方面：\n  一、聲明：如主文第1項所示。\n  二、陳述：\n    (一)被告建逸國際有限公司以被告甲○○、丙○○為連帶保證\n      人，於民國93年5月6日起向原告借款兩筆，金額分別為新\n      臺幣（下同）90萬元、210萬元，均約定自93年5月6日起\n      至98年5月6日止按月依年金法於每月6日平均攤還本息，\n      利息依原告公告之基準利率加年利率3.2％計付，並於原\n      告調整基準利率時，自調整日後第一個應繳款日起，改按\n      調整後之基準利率加原約定加碼利率調整計付，如未依約\n      清償，借款視為全部到期，除按上開利率計息外，其逾期\n      在6個月以內者，按上開利率10％，逾期超過6個月者，按\n      上開利率20％加付違約金。\n    (二)詎被告繳息至94年6月10日後即未繳納本息，依約借款視\n      為全部到期，至今尚欠本金2,319,546元及利息、違約金\n      ，爰依法請求被告連帶清償。\n  三、證據：提出借據、約定書、保證書、放款戶授信明細查詢\n      單、基準利率表、放款貸放傳票、轉帳收入傳票等件為證\n      。\n乙、被告方面：\n    被告均未於言詞辯論期日到場，亦均未提出書狀作何聲明或\n    陳述。\n    理    由\n甲、程序方面：\n  一、按當事人得以合意定第1審管轄法院， 民事訴訟法第24條\n      第1項前段定有明文。經查，兩造簽訂之約定書第13條及\n      保證書第7條約定，合意以本院為第1審管轄法院，是本院\n      就本件訴訟應有管轄權，合先敘明。\n  二、被告均未於言詞辯論期日到場，均核無民事訴訟法第386\n      條所列各款情形，應依原告之聲請，由其一造辯論而為判\n      決。\n乙、實體方面：\n  一、原告主張之事實，業據提出借據、約定書、保證書、放款\n      戶授信明細查詢單、基準利率表、放款貸放傳票、轉帳收\n      入傳票為證，被告對於上開事實，已於相當時期受合法之\n      通知，而不於言詞辯論期日到場爭執，亦不提出書狀答辯\n      ，經本院參酌原告提出之上開證據、資料，堪信原告之主\n      張為真實。\n  二、從而，原告依消費借貸及連帶保證之法律關係請求被告連\n      帶給付如主文第1項所示之本金、 利息及違約金為有理由\n      ，應予准許。\n  三、原告之訴為有理由，依民事訴訟法第385條第1項前段、第\n      85條第2項，判決如主文。\n中    華    民    國    94    年    10    月    24    日\n                        臺灣台北地方法院民事第四庭\n                                  法  官  林玲玉\n以上正本係照原本作成。\n如對本判決上訴，須於判決送達後20日內向本院提出上訴狀。\n中    華    民    國    94    年    10    月    24    日\n                                  書記官  江虹儀\n附表\n┌─┬─────┬───────┬──────┬─────────┐\n│編│貸款金額  │利息          │借款起迄日  │違約金計算期間及利│\n│號├─────┼──┬────┤            │率                │\n│  │現欠本金  │期間│約定利率│            │                  │\n├─┼─────┼──┼────┼──────┼─────────┤\n│1 │90萬元    │94年│年利率  │93年5月6日至│自94年7月11日起至 │\n│  ├─────┤6月 │6.81％  │98年5月6日  │清償日止，其逾期在│\n│  │69萬      │11日│        │            │6個月以內者，按前 │\n│  │5864元    │起至│        │            │開約定利率10％，逾│\n├─┼─────┤清償│        ├──────┤期超過6個月者，按 │\n│2 │210萬元   │日止│        │93年5月6日至│前開約定利率20％計│\n│  ├─────┤    │        │98年5月6日  │算。              │\n│  │162萬     │    │        │            │                  │\n│  │3682元    │    │        │            │                  │\n├─┴─────┴──┴────┴──────┴─────────┤\n│合計尚欠本金：2,319,546元                                       │\n└────────────────────────────────┘\n",
  "structure": {
    "main": "被告應連帶給付原告新臺幣貳佰拾壹萬玖仟伍佰肆拾陸元及如\n附表所示之利息及違約金。\n訴訟費用由被告連帶負擔。",
    "fact": "甲、原告方面：\n  一、聲明：如主文第1項所示。\n  二、陳述：\n    (一)被告建逸國際有限公司以被告甲○○、丙○○為連帶保證\n      人，於民國93年5月6日起向原告借款兩筆，金額分別為新\n      臺幣（下同）90萬元、210萬元，均約定自93年5月6日起\n      至98年5月6日止按月依年金法於每月6日平均攤還本息，\n      利息依原告公告之基準利率加年利率3.2％計付，並於原\n      告調整基準利率時，自調整日後第一個應繳款日起，改按\n      調整後之基準利率加原約定加碼利率調整計付，如未依約\n      清償，借款視為全部到期，除按上開利率計息外，其逾期\n      在6個月以內者，按上開利率10％，逾期超過6個月者，按\n      上開利率20％加付違約金。\n    (二)詎被告繳息至94年6月10日後即未繳納本息，依約借款視\n      為全部到期，至今尚欠本金2,319,546元及利息、違約金\n      ，爰依法請求被告連帶清償。\n  三、證據：提出借據、約定書、保證書、放款戶授信明細查詢\n      單、基準利率表、放款貸放傳票、轉帳收入傳票等件為證\n      。\n乙、被告方面：\n    被告均未於言詞辯論期日到場，亦均未提出書狀作何聲明或\n    陳述。",
    "reason": "甲、程序方面：\n  一、按當事人得以合意定第1審管轄法院， 民事訴訟法第24條\n      第1項前段定有明文。經查，兩造簽訂之約定書第13條及\n      保證書第7條約定，合意以本院為第1審管轄法院，是本院\n      就本件訴訟應有管轄權，合先敘明。\n  二、被告均未於言詞辯論期日到場，均核無民事訴訟法第386\n      條所列各款情形，應依原告之聲請，由其一造辯論而為判\n      決。\n乙、實體方面：\n  一、原告主張之事實，業據提出借據、約定書、保證書、放款\n      戶授信明細查詢單、基準利率表、放款貸放傳票、轉帳收\n      入傳票為證，被告對於上開事實，已於相當時期受合法之\n      通知，而不於言詞辯論期日到場爭執，亦不提出書狀答辯\n      ，經本院參酌原告提出之上開證據、資料，堪信原告之主\n      張為真實。\n  二、從而，原告依消費借貸及連帶保證之法律關係請求被告連\n      帶給付如主文第1項所示之本金、 利息及違約金為有理由\n      ，應予准許。\n  三、原告之訴為有理由，依民事訴訟法第385條第1項前段、第\n      85條第2項，判決如主文。\n中    華    民    國    94    年    10    月    24    日\n                        臺灣台北地方法院民事第四庭\n                                  法  官  林玲玉\n以上正本係照原本作成。\n如對本判決上訴，須於判決送達後20日內向本院提出上訴狀。"
  },
  "search": "臺灣臺北地方法院民事判決94年度訴字第4221號原告第一商業銀行股份有限公司法定代理人乙○○訴訟代理人丁○○被告建逸國際有限公司兼法定代理人甲○○被告丙○○上開當事人間請求清償借款事件，本院於民國94年10月17日言詞辯論終結，判決如下：主文被告應連帶給付原告新臺幣貳佰拾壹萬玖仟伍佰肆拾陸元及如附表所示之利息及違約金。訴訟費用由被告連帶負擔。事實甲、原告方面：一、聲明：如主文第1項所示。二、陳述：(一)被告建逸國際有限公司以被告甲○○、丙○○為連帶保證人，於民國93年5月6日起向原告借款兩筆，金額分別為新臺幣（下同）90萬元、210萬元，均約定自93年5月6日起至98年5月6日止按月依年金法於每月6日平均攤還本息，利息依原告公告之基準利率加年利率3.2％計付，並於原告調整基準利率時，自調整日後第一個應繳款日起，改按調整後之基準利率加原約定加碼利率調整計付，如未依約清償，借款視為全部到期，除按上開利率計息外，其逾期在6個月以內者，按上開利率10％，逾期超過6個月者，按上開利率20％加付違約金。(二)詎被告繳息至94年6月10日後即未繳納本息，依約借款視為全部到期，至今尚欠本金2,319,546元及利息、違約金，爰依法請求被告連帶清償。三、證據：提出借據、約定書、保證書、放款戶授信明細查詢單、基準利率表、放款貸放傳票、轉帳收入傳票等件為證。乙、被告方面：被告均未於言詞辯論期日到場，亦均未提出書狀作何聲明或陳述。理由甲、程序方面：一、按當事人得以合意定第1審管轄法院，民事訴訟法第24條第1項前段定有明文。經查，兩造簽訂之約定書第13條及保證書第7條約定，合意以本院為第1審管轄法院，是本院就本件訴訟應有管轄權，合先敘明。二、被告均未於言詞辯論期日到場，均核無民事訴訟法第386條所列各款情形，應依原告之聲請，由其一造辯論而為判決。乙、實體方面：一、原告主張之事實，業據提出借據、約定書、保證書、放款戶授信明細查詢單、基準利率表、放款貸放傳票、轉帳收入傳票為證，被告對於上開事實，已於相當時期受合法之通知，而不於言詞辯論期日到場爭執，亦不提出書狀答辯，經本院參酌原告提出之上開證據、資料，堪信原告之主張為真實。二、從而，原告依消費借貸及連帶保證之法律關係請求被告連帶給付如主文第1項所示之本金、利息及違約金為有理由，應予准許。三、原告之訴為有理由，依民事訴訟法第385條第1項前段、第85條第2項，判決如主文。中華民國94年10月24日臺灣台北地方法院民事第四庭法官林玲玉以上正本係照原本作成。如對本判決上訴，須於判決送達後20日內向本院提出上訴狀。中華民國94年10月24日書記官江虹儀附表┌─┬─────┬───────┬──────┬─────────┐│編│貸款金額│利息│借款起迄日│違約金計算期間及利││號├─────┼──┬────┤│率│││現欠本金│期間│約定利率│││├─┼─────┼──┼────┼──────┼─────────┤│1│90萬元│94年│年利率│93年5月6日至│自94年7月11日起至││├─────┤6月│6.81％│98年5月6日│清償日止，其逾期在│││69萬│11日│││6個月以內者，按前│││5864元│起至│││開約定利率10％，逾│├─┼─────┤清償│├──────┤期超過6個月者，按││2│210萬元│日止││93年5月6日至│前開約定利率20％計││├─────┤││98年5月6日│算。│││162萬│││││││3682元│││││├─┴─────┴──┴────┴──────┴─────────┤│合計尚欠本金：2,319,546元│└────────────────────────────────┘",
  "characters": {
    "judges": [
      "林玲玉"
    ],
    "prosecutors": [

    ],
    "lawyers": [

    ],
    "clerks": [
      "江虹儀"
    ],
    "plaintiffs": [
      "第一商業銀行股份有限公司"
    ],
    "defendants": [
      "建逸國際有限公司",
      "兼法定代理人  甲○○",
      "被      告    丙○○"
    ],
    "prosecutor_office": [

    ],
    "creditors": [

    ],
    "debtors": [

    ],
    "judicial_associate_officer": [

    ]
  },
  "adjudged_at": "2005-10-24",
  "created_at": "2016-02-07 10:43:15",
  "updated_at": "2016-02-07 10:43:15"
}