{
  "identify": "SLD-100-聲-1443-20110819-1",
  "court": {
    "name": "臺灣士林地方法院",
    "code": "SLD"
  },
  "division": {
    "name": "刑事",
    "code": "M"
  },
  "year": 100,
  "word": "聲",
  "number": "1443",
  "jcheck": "1",
  "reason": "宣告沒收",
  "content": "臺灣士林地方法院刑事裁定             100年度聲字第1443號\n聲  請  人  臺灣士林地方法院檢察署檢察官\n被      告  李玉茹\n上列聲請人因被告違反毒品危害防制條例案件（99年度毒偵字第\n2050號），聲請宣告沒收（100 年度聲沒字第113 號），本院裁\n定如下：\n    主  文\n扣案之第二級毒品甲基安非他命壹包（驗餘淨重零點貳陸捌捌公\n克）沒收銷燬。\n    理  由\n一、按違禁物得單獨宣告沒收，刑法第40條但書定有明文；又查\n    獲之第一、二級毒品，不問屬於犯人與否，均沒收銷燬之，\n    毒品危害防制條例第18條第1 項前段亦有明文。次按甲基安\n    非他命為毒品危害防制條例第2 條第2 項第2 款所定之第二\n    級毒品，依同條例第11條第2 項規定，不得持有，故屬違禁\n    物甚明。\n二、本件聲請意旨略以：被告李玉茹因施用第二級毒品甲基安非\n    他命，經鈞院裁定送觀察、勒戒後，認無繼續施用毒品之傾\n    向，並經本署檢察官以99年度毒偵字第2050號不起訴處分確\n    定。扣案被告所持有之第二級毒品甲基安非他命1 包（驗餘\n    淨重0.2688公克），經送交通部民用航空局航空醫務中心鑑\n    定後，檢出第二級毒品甲基安非他命成分，此有該中心99年\n    10月11日航藥鑑字第0996336 號鑑定書1 紙附卷為憑，因屬\n    違禁物，爰依前開法條規定聲請宣告沒收並銷燬之。\n三、經查：本件被告李玉茹涉嫌毒品危害防制條例第10條第2 項\n    之施用第二級毒品犯行，經本院以100 年度毒聲字第115 號\n    裁定送觀察、勒戒後，認無繼續施用毒品之傾向，而經臺灣\n    士林地方法院檢察署檢察官以99年度毒偵字第2050號不起訴\n    處分確定在案，此有上開案號不起訴處分書在卷可參，並經\n    本院核閱上開偵查卷宗審認無訛，且有臺灣高等法院被告前\n    案紀錄表存卷供參。又本件扣案之白色透明晶體1 包，經送\n    交通部民用航空局航空醫務中心鑑定後，檢出第二級毒品甲\n    基安非命他成分（淨重0.2690公克，取樣0.0002公克，餘重\n    0.2688公克），此有該中心99年10月11日航藥鑑字第099633\n    6 號毒品鑑定書1 紙在卷為憑，扣案之物確為第二級毒品無\n    訛，揆諸前開說明，屬違禁物，自應依前開法條規定宣告沒\n    收銷燬之，爰裁定如主文。\n中    華    民    國   100    年    8     月    19    日\n                  刑事第五庭法  官  雷雯華\n以上正本證明與原本無異。\n如不服本裁定應於送達後5日內向本院提出抗告狀\n                            書記官  蔡東晏\n中    華    民    國  100     年    8     月    22    日",
  "structure": {
    "main": "扣案之第二級毒品甲基安非他命壹包（驗餘淨重零點貳陸捌捌公\n克）沒收銷燬。",
    "reason": "一、按違禁物得單獨宣告沒收，刑法第40條但書定有明文；又查\n    獲之第一、二級毒品，不問屬於犯人與否，均沒收銷燬之，\n    毒品危害防制條例第18條第1 項前段亦有明文。次按甲基安\n    非他命為毒品危害防制條例第2 條第2 項第2 款所定之第二\n    級毒品，依同條例第11條第2 項規定，不得持有，故屬違禁\n    物甚明。\n二、本件聲請意旨略以：被告李玉茹因施用第二級毒品甲基安非\n    他命，經鈞院裁定送觀察、勒戒後，認無繼續施用毒品之傾\n    向，並經本署檢察官以99年度毒偵字第2050號不起訴處分確\n    定。扣案被告所持有之第二級毒品甲基安非他命1 包（驗餘\n    淨重0.2688公克），經送交通部民用航空局航空醫務中心鑑\n    定後，檢出第二級毒品甲基安非他命成分，此有該中心99年\n    10月11日航藥鑑字第0996336 號鑑定書1 紙附卷為憑，因屬\n    違禁物，爰依前開法條規定聲請宣告沒收並銷燬之。\n三、經查：本件被告李玉茹涉嫌毒品危害防制條例第10條第2 項\n    之施用第二級毒品犯行，經本院以100 年度毒聲字第115 號\n    裁定送觀察、勒戒後，認無繼續施用毒品之傾向，而經臺灣\n    士林地方法院檢察署檢察官以99年度毒偵字第2050號不起訴\n    處分確定在案，此有上開案號不起訴處分書在卷可參，並經\n    本院核閱上開偵查卷宗審認無訛，且有臺灣高等法院被告前\n    案紀錄表存卷供參。又本件扣案之白色透明晶體1 包，經送\n    交通部民用航空局航空醫務中心鑑定後，檢出第二級毒品甲\n    基安非命他成分（淨重0.2690公克，取樣0.0002公克，餘重\n    0.2688公克），此有該中心99年10月11日航藥鑑字第099633\n    6 號毒品鑑定書1 紙在卷為憑，扣案之物確為第二級毒品無\n    訛，揆諸前開說明，屬違禁物，自應依前開法條規定宣告沒\n    收銷燬之，爰裁定如主文。"
  },
  "search": "臺灣士林地方法院刑事裁定100年度聲字第1443號聲請人臺灣士林地方法院檢察署檢察官被告李玉茹上列聲請人因被告違反毒品危害防制條例案件（99年度毒偵字第2050號），聲請宣告沒收（100年度聲沒字第113號），本院裁定如下：主文扣案之第二級毒品甲基安非他命壹包（驗餘淨重零點貳陸捌捌公克）沒收銷燬。理由一、按違禁物得單獨宣告沒收，刑法第40條但書定有明文；又查獲之第一、二級毒品，不問屬於犯人與否，均沒收銷燬之，毒品危害防制條例第18條第1項前段亦有明文。次按甲基安非他命為毒品危害防制條例第2條第2項第2款所定之第二級毒品，依同條例第11條第2項規定，不得持有，故屬違禁物甚明。二、本件聲請意旨略以：被告李玉茹因施用第二級毒品甲基安非他命，經鈞院裁定送觀察、勒戒後，認無繼續施用毒品之傾向，並經本署檢察官以99年度毒偵字第2050號不起訴處分確定。扣案被告所持有之第二級毒品甲基安非他命1包（驗餘淨重0.2688公克），經送交通部民用航空局航空醫務中心鑑定後，檢出第二級毒品甲基安非他命成分，此有該中心99年10月11日航藥鑑字第0996336號鑑定書1紙附卷為憑，因屬違禁物，爰依前開法條規定聲請宣告沒收並銷燬之。三、經查：本件被告李玉茹涉嫌毒品危害防制條例第10條第2項之施用第二級毒品犯行，經本院以100年度毒聲字第115號裁定送觀察、勒戒後，認無繼續施用毒品之傾向，而經臺灣士林地方法院檢察署檢察官以99年度毒偵字第2050號不起訴處分確定在案，此有上開案號不起訴處分書在卷可參，並經本院核閱上開偵查卷宗審認無訛，且有臺灣高等法院被告前案紀錄表存卷供參。又本件扣案之白色透明晶體1包，經送交通部民用航空局航空醫務中心鑑定後，檢出第二級毒品甲基安非命他成分（淨重0.2690公克，取樣0.0002公克，餘重0.2688公克），此有該中心99年10月11日航藥鑑字第0996336號毒品鑑定書1紙在卷為憑，扣案之物確為第二級毒品無訛，揆諸前開說明，屬違禁物，自應依前開法條規定宣告沒收銷燬之，爰裁定如主文。中華民國100年8月19日刑事第五庭法官雷雯華以上正本證明與原本無異。如不服本裁定應於送達後5日內向本院提出抗告狀書記官蔡東晏中華民國100年8月22日",
  "characters": {
    "judges": [
      "雷雯華"
    ],
    "prosecutors": [

    ],
    "lawyers": [

    ],
    "clerks": [
      "蔡東晏"
    ],
    "plaintiffs": [

    ],
    "defendants": [
      "李玉茹"
    ],
    "prosecutor_office": [
      "臺灣士林地方法院檢察署檢察官"
    ],
    "creditors": [

    ],
    "debtors": [

    ],
    "judicial_associate_officer": [

    ]
  },
  "adjudged_at": "2011-08-19",
  "created_at": "2016-02-12 20:43:43",
  "updated_at": "2016-02-12 20:43:43"
}