{
  "identify": "CYD-93-嘉交簡-57-20040331-1",
  "court": {
    "name": "臺灣嘉義地方法院",
    "code": "CYD"
  },
  "division": {
    "name": "刑事",
    "code": "M"
  },
  "year": 93,
  "word": "嘉交簡",
  "number": "57",
  "jcheck": "1",
  "reason": "公共危險",
  "content": "臺灣嘉義地方法院刑事簡易判決                    九十三年度嘉交簡字第五七號\n    聲  請  人  臺灣嘉義地方法院檢察署檢察官\n    被      告  甲○○\n右列被告因公共危險案件，經檢察官聲請以簡易判決處刑（九十三年度偵字第一五一\n○號），本院判決如左：\n    主  文\n甲○○服用酒類，不能安全駕駛動力交通工具而駕駛，處拘役參拾日，如易科罰金，\n以佰元折算壹日。\n    事實及理由\n一、本件犯罪事實及證據均引用檢察官聲請簡易判決處刑書之記載（如附件）。\n二、依刑事訴訟法第四百四十九條第一項前段、第四百五十四條第二項，刑法第一百\n    八十五條之三、第四十一條第一項前段，罰金罰鍰提高標準條例第二條，逕以簡\n    易判決處刑如主文。\n中      華      民      國    九十三    年      三      月    三十一    日\n                                    臺灣嘉義地方法院簡易庭\n                                        法  官  夏  金  郎\n右正本證明與原本無異。\n如對本判決上訴，須於判決送達後十日內向本院提出上訴狀（應附繕本）\n中      華      民      國    九十三    年      三      月    三十一    日\n                                        書記官  洪  秋  華\n附錄法條:\n刑法第一百八十五條之三：\n服用毒品、麻醉藥品、酒類或其他相類之物，不能安全駕駛動力交通工具而駕駛者，\n處一年以下有期徒刑、拘役或三萬元以下罰金。\n",
  "structure": {
    "main": "甲○○服用酒類，不能安全駕駛動力交通工具而駕駛，處拘役參拾日，如易科罰金，\n以佰元折算壹日。",
    "fact": "一、本件犯罪事實及證據均引用檢察官聲請簡易判決處刑書之記載（如附件）。\n二、依刑事訴訟法第四百四十九條第一項前段、第四百五十四條第二項，刑法第一百\n    八十五條之三、第四十一條第一項前段，罰金罰鍰提高標準條例第二條，逕以簡\n    易判決處刑如主文。",
    "reason": "一、本件犯罪事實及證據均引用檢察官聲請簡易判決處刑書之記載（如附件）。\n二、依刑事訴訟法第四百四十九條第一項前段、第四百五十四條第二項，刑法第一百\n    八十五條之三、第四十一條第一項前段，罰金罰鍰提高標準條例第二條，逕以簡\n    易判決處刑如主文。"
  },
  "search": "臺灣嘉義地方法院刑事簡易判決九十三年度嘉交簡字第五七號聲請人臺灣嘉義地方法院檢察署檢察官被告甲○○右列被告因公共危險案件，經檢察官聲請以簡易判決處刑（九十三年度偵字第一五一○號），本院判決如左：主文甲○○服用酒類，不能安全駕駛動力交通工具而駕駛，處拘役參拾日，如易科罰金，以佰元折算壹日。事實及理由一、本件犯罪事實及證據均引用檢察官聲請簡易判決處刑書之記載（如附件）。二、依刑事訴訟法第四百四十九條第一項前段、第四百五十四條第二項，刑法第一百八十五條之三、第四十一條第一項前段，罰金罰鍰提高標準條例第二條，逕以簡易判決處刑如主文。中華民國九十三年三月三十一日臺灣嘉義地方法院簡易庭法官夏金郎右正本證明與原本無異。如對本判決上訴，須於判決送達後十日內向本院提出上訴狀（應附繕本）中華民國九十三年三月三十一日書記官洪秋華附錄法條:刑法第一百八十五條之三：服用毒品、麻醉藥品、酒類或其他相類之物，不能安全駕駛動力交通工具而駕駛者，處一年以下有期徒刑、拘役或三萬元以下罰金。",
  "characters": {
    "judges": [
      "夏金郎"
    ],
    "prosecutors": [

    ],
    "lawyers": [

    ],
    "clerks": [
      "洪秋華"
    ],
    "plaintiffs": [

    ],
    "defendants": [
      "甲○○",
      "右列被告因公共危險案件，經檢察官聲請以簡易判決處刑（九十三年度偵字第一五一",
      "○號），本院判決如左："
    ],
    "prosecutor_office": [
      "臺灣嘉義地方法院檢察署檢察官"
    ],
    "creditors": [

    ],
    "debtors": [

    ],
    "judicial_associate_officer": [

    ]
  },
  "adjudged_at": "2004-03-31",
  "created_at": "2016-02-06 10:28:08",
  "updated_at": "2016-02-06 10:28:08"
}