{
  "identify": "TYD-93-桃簡-356-20040331-1",
  "court": {
    "name": "臺灣桃園地方法院",
    "code": "TYD"
  },
  "division": {
    "name": "刑事",
    "code": "M"
  },
  "year": 93,
  "word": "桃簡",
  "number": "356",
  "jcheck": "1",
  "reason": "竊盜",
  "content": "臺灣桃園地方法院刑事簡易判決                    九十三年度桃簡字第三五六號\n    聲  請  人  臺灣桃園地方法院檢察署檢察官\n    被      告  甲○○\n右列被告因竊盜案件經檢察官聲請以簡易判決處刑，（九十三年度偵字第三五八一號\n）本院判決如左：\n    主  文\n甲○○竊盜，處拘役貳拾日，如易科罰金以參佰元折算壹日。\n    事實及理由\n一、犯罪事實與檢察官聲請書之記載同，茲引用之。\n二、證據：１、被告自白。２、證人胡明文、被害人乙○○之指述。３、贓物認領保\n    管收據乙紙。\n三、依刑事訴訟法第四百四十九條第一項前段，刑法第三百二十條第一項、第四十一\n    條第一項，罰金罰鍰提高標準條例第一條前段，第二條逕以判決處如主文所示之\n    刑。\n如不服本判決，得於判決書送達之翌日起十日內，以書狀敘述理由，向本庭提出上訴\n。\n中      華        民        國    九十三  年    三        月  三十一    日\n                                  臺灣桃園地方法院刑事第五庭\n                                      法  官  潘政宏\n右正本證明與原本無異。\n                                      書記官   李佩玲\n中        華        民        國   九十三   年   三   月    三十一    日\n附論罪科刑之法條：\n中華民國刑法第三百二十條\n(普通竊盜罪、竊佔罪)\n意圖為自己或第三人不法之所有，而竊取他人之動產者，為竊盜罪，處五\n年以下有期徒刑、拘役或五百元以下罰金。\n意圖為自己或第三人不法之利益，而竊佔他人之不動產者，依前項之規定\n處斷。\n前二項之未遂犯罰之。\n",
  "structure": {
    "main": "甲○○竊盜，處拘役貳拾日，如易科罰金以參佰元折算壹日。",
    "fact": "一、犯罪事實與檢察官聲請書之記載同，茲引用之。\n二、證據：１、被告自白。２、證人胡明文、被害人乙○○之指述。３、贓物認領保\n    管收據乙紙。\n三、依刑事訴訟法第四百四十九條第一項前段，刑法第三百二十條第一項、第四十一\n    條第一項，罰金罰鍰提高標準條例第一條前段，第二條逕以判決處如主文所示之\n    刑。\n如不服本判決，得於判決書送達之翌日起十日內，以書狀敘述理由，向本庭提出上訴\n。",
    "reason": "一、犯罪事實與檢察官聲請書之記載同，茲引用之。\n二、證據：１、被告自白。２、證人胡明文、被害人乙○○之指述。３、贓物認領保\n    管收據乙紙。\n三、依刑事訴訟法第四百四十九條第一項前段，刑法第三百二十條第一項、第四十一\n    條第一項，罰金罰鍰提高標準條例第一條前段，第二條逕以判決處如主文所示之\n    刑。\n如不服本判決，得於判決書送達之翌日起十日內，以書狀敘述理由，向本庭提出上訴\n。"
  },
  "search": "臺灣桃園地方法院刑事簡易判決九十三年度桃簡字第三五六號聲請人臺灣桃園地方法院檢察署檢察官被告甲○○右列被告因竊盜案件經檢察官聲請以簡易判決處刑，（九十三年度偵字第三五八一號）本院判決如左：主文甲○○竊盜，處拘役貳拾日，如易科罰金以參佰元折算壹日。事實及理由一、犯罪事實與檢察官聲請書之記載同，茲引用之。二、證據：１、被告自白。２、證人胡明文、被害人乙○○之指述。３、贓物認領保管收據乙紙。三、依刑事訴訟法第四百四十九條第一項前段，刑法第三百二十條第一項、第四十一條第一項，罰金罰鍰提高標準條例第一條前段，第二條逕以判決處如主文所示之刑。如不服本判決，得於判決書送達之翌日起十日內，以書狀敘述理由，向本庭提出上訴。中華民國九十三年三月三十一日臺灣桃園地方法院刑事第五庭法官潘政宏右正本證明與原本無異。書記官李佩玲中華民國九十三年三月三十一日附論罪科刑之法條：中華民國刑法第三百二十條(普通竊盜罪、竊佔罪)意圖為自己或第三人不法之所有，而竊取他人之動產者，為竊盜罪，處五年以下有期徒刑、拘役或五百元以下罰金。意圖為自己或第三人不法之利益，而竊佔他人之不動產者，依前項之規定處斷。前二項之未遂犯罰之。",
  "characters": {
    "judges": [
      "潘政宏"
    ],
    "prosecutors": [

    ],
    "lawyers": [

    ],
    "clerks": [
      "李佩玲"
    ],
    "plaintiffs": [

    ],
    "defendants": [
      "甲○○",
      "右列被告因竊盜案件經檢察官聲請以簡易判決處刑，（九十三年度偵字第三五八一號",
      "）本院判決如左："
    ],
    "prosecutor_office": [
      "臺灣桃園地方法院檢察署檢察官"
    ],
    "creditors": [

    ],
    "debtors": [

    ],
    "judicial_associate_officer": [

    ]
  },
  "adjudged_at": "2004-03-31",
  "created_at": "2016-02-06 10:32:50",
  "updated_at": "2016-02-06 10:32:50"
}