{
  "identify": "TYD-93-壢簡-214-20040401-1",
  "court": {
    "name": "臺灣桃園地方法院",
    "code": "TYD"
  },
  "division": {
    "name": "刑事",
    "code": "M"
  },
  "year": 93,
  "word": "壢簡",
  "number": "214",
  "jcheck": "1",
  "reason": "竊盜",
  "content": "臺灣桃園地方法院刑事簡易判決                    九十三年度壢簡字第二一四號\n    聲  請  人  臺灣桃園地方法院檢察署檢察官\n    被      告  甲○○\n右列被告因竊盜案件，經檢察官聲請以簡易判決處刑（九十三年度偵字第三六八七號\n），本院判決如左：\n    主  文\n甲○○竊盜，處罰金壹仟捌佰元，如易服勞役，以參佰元折算壹日。\n    事實及理由\n一、本件犯罪事實如下：被告甲○○於民國九十三年二月二十九日晚間十一時許，在\n    桃園縣中壢市○○路八十九號二樓乙○○所經營之「墊腳石書店」內，意圖為自\n    己不法之所有，徒手竊取乙○○所有之漫畫書籍五本，欲供己閱讀，為乙○○發\n    現而報警當場查獲，案經乙○○訴由桃園縣政府警察局中壢分局報請台灣桃園地\n    方法院檢察署檢察官偵辦後，聲請以簡易判決處刑。\n二、本件證據均引用檢察官聲請簡易判決處刑書所載（如附件）。\n三、核被告所犯，係刑法第三百二十條第一項竊盜罪。爰審酌被告不思以正常管道取\n    得財物，竟下手行竊，及其犯罪手段、竊得漫畫書籍之價值非高，及被告犯後坦\n    承犯行，態度尚佳等一切情狀，量處如主文所示之刑，並諭知易服勞役之折算標\n    準，以示懲儆。\n四、聲請意旨雖以：被告甲○○坦承曾於九十三年二月二十二日起在前開商店竊取漫\n    畫書籍四至五次，認被告涉有連續竊盜犯行。惟按：被告之自白，不得作為有罪\n    判決之唯一證據，仍應調查其他必要證據，以察其是否與事實相符，刑事訴訟法\n    第一百五十六條第二項定有明文。查本件被告是否確有前開連續竊盜行為，除被\n    告自白外，查無該等竊取之漫畫書籍可資佐證，告訴人乙○○亦指稱並無發現行\n    竊行為，是乏其他證據足認被告自白合於事實，依上開法條規定，尚非可遽為被\n    告有連續竊盜犯行之認定，附此敘明。\n五、依刑事訴訟法第四百四十九條第一項前段、第四百五十四條第二項，刑法第三百\n    二十條第一項、第四十二條第二項，罰金罰鍰提高標準條例第一條前段、第二條\n    ，逕以簡易判決如主文。\n六、如不服本判決，得於判決書送達之翌日起十日內，以書狀敘述理由，向本院提出\n    上訴。\n中      華      民      國    九十三    年      四      月      一      日\n                                  臺灣桃園地方法院刑事第三庭\n                                      法  官  楊晴翔\n右正本證明與原本無異。\n                                    書記官   姜國駒\n中        華        民        國   九十三   年   四   月    十二   日\n附錄本案論罪科刑法條：\n中華民國刑法第三百二十條\n意圖為自己或第三人不法之所有，而竊取他人之動產者，為竊盜罪，處五年以下有期\n徒刑、拘役或五百元以下罰金（已提高為十倍，單位為銀元）。\n意圖為自己或第三人不法之利益，而竊佔他人之不動產者，依前項之規定處斷。\n前二項之未遂犯罰之。\n",
  "structure": {
    "main": "甲○○竊盜，處罰金壹仟捌佰元，如易服勞役，以參佰元折算壹日。",
    "fact": "一、本件犯罪事實如下：被告甲○○於民國九十三年二月二十九日晚間十一時許，在\n    桃園縣中壢市○○路八十九號二樓乙○○所經營之「墊腳石書店」內，意圖為自\n    己不法之所有，徒手竊取乙○○所有之漫畫書籍五本，欲供己閱讀，為乙○○發\n    現而報警當場查獲，案經乙○○訴由桃園縣政府警察局中壢分局報請台灣桃園地\n    方法院檢察署檢察官偵辦後，聲請以簡易判決處刑。\n二、本件證據均引用檢察官聲請簡易判決處刑書所載（如附件）。\n三、核被告所犯，係刑法第三百二十條第一項竊盜罪。爰審酌被告不思以正常管道取\n    得財物，竟下手行竊，及其犯罪手段、竊得漫畫書籍之價值非高，及被告犯後坦\n    承犯行，態度尚佳等一切情狀，量處如主文所示之刑，並諭知易服勞役之折算標\n    準，以示懲儆。\n四、聲請意旨雖以：被告甲○○坦承曾於九十三年二月二十二日起在前開商店竊取漫\n    畫書籍四至五次，認被告涉有連續竊盜犯行。惟按：被告之自白，不得作為有罪\n    判決之唯一證據，仍應調查其他必要證據，以察其是否與事實相符，刑事訴訟法\n    第一百五十六條第二項定有明文。查本件被告是否確有前開連續竊盜行為，除被\n    告自白外，查無該等竊取之漫畫書籍可資佐證，告訴人乙○○亦指稱並無發現行\n    竊行為，是乏其他證據足認被告自白合於事實，依上開法條規定，尚非可遽為被\n    告有連續竊盜犯行之認定，附此敘明。\n五、依刑事訴訟法第四百四十九條第一項前段、第四百五十四條第二項，刑法第三百\n    二十條第一項、第四十二條第二項，罰金罰鍰提高標準條例第一條前段、第二條\n    ，逕以簡易判決如主文。\n六、如不服本判決，得於判決書送達之翌日起十日內，以書狀敘述理由，向本院提出\n    上訴。",
    "reason": "一、本件犯罪事實如下：被告甲○○於民國九十三年二月二十九日晚間十一時許，在\n    桃園縣中壢市○○路八十九號二樓乙○○所經營之「墊腳石書店」內，意圖為自\n    己不法之所有，徒手竊取乙○○所有之漫畫書籍五本，欲供己閱讀，為乙○○發\n    現而報警當場查獲，案經乙○○訴由桃園縣政府警察局中壢分局報請台灣桃園地\n    方法院檢察署檢察官偵辦後，聲請以簡易判決處刑。\n二、本件證據均引用檢察官聲請簡易判決處刑書所載（如附件）。\n三、核被告所犯，係刑法第三百二十條第一項竊盜罪。爰審酌被告不思以正常管道取\n    得財物，竟下手行竊，及其犯罪手段、竊得漫畫書籍之價值非高，及被告犯後坦\n    承犯行，態度尚佳等一切情狀，量處如主文所示之刑，並諭知易服勞役之折算標\n    準，以示懲儆。\n四、聲請意旨雖以：被告甲○○坦承曾於九十三年二月二十二日起在前開商店竊取漫\n    畫書籍四至五次，認被告涉有連續竊盜犯行。惟按：被告之自白，不得作為有罪\n    判決之唯一證據，仍應調查其他必要證據，以察其是否與事實相符，刑事訴訟法\n    第一百五十六條第二項定有明文。查本件被告是否確有前開連續竊盜行為，除被\n    告自白外，查無該等竊取之漫畫書籍可資佐證，告訴人乙○○亦指稱並無發現行\n    竊行為，是乏其他證據足認被告自白合於事實，依上開法條規定，尚非可遽為被\n    告有連續竊盜犯行之認定，附此敘明。\n五、依刑事訴訟法第四百四十九條第一項前段、第四百五十四條第二項，刑法第三百\n    二十條第一項、第四十二條第二項，罰金罰鍰提高標準條例第一條前段、第二條\n    ，逕以簡易判決如主文。\n六、如不服本判決，得於判決書送達之翌日起十日內，以書狀敘述理由，向本院提出\n    上訴。"
  },
  "search": "臺灣桃園地方法院刑事簡易判決九十三年度壢簡字第二一四號聲請人臺灣桃園地方法院檢察署檢察官被告甲○○右列被告因竊盜案件，經檢察官聲請以簡易判決處刑（九十三年度偵字第三六八七號），本院判決如左：主文甲○○竊盜，處罰金壹仟捌佰元，如易服勞役，以參佰元折算壹日。事實及理由一、本件犯罪事實如下：被告甲○○於民國九十三年二月二十九日晚間十一時許，在桃園縣中壢市○○路八十九號二樓乙○○所經營之「墊腳石書店」內，意圖為自己不法之所有，徒手竊取乙○○所有之漫畫書籍五本，欲供己閱讀，為乙○○發現而報警當場查獲，案經乙○○訴由桃園縣政府警察局中壢分局報請台灣桃園地方法院檢察署檢察官偵辦後，聲請以簡易判決處刑。二、本件證據均引用檢察官聲請簡易判決處刑書所載（如附件）。三、核被告所犯，係刑法第三百二十條第一項竊盜罪。爰審酌被告不思以正常管道取得財物，竟下手行竊，及其犯罪手段、竊得漫畫書籍之價值非高，及被告犯後坦承犯行，態度尚佳等一切情狀，量處如主文所示之刑，並諭知易服勞役之折算標準，以示懲儆。四、聲請意旨雖以：被告甲○○坦承曾於九十三年二月二十二日起在前開商店竊取漫畫書籍四至五次，認被告涉有連續竊盜犯行。惟按：被告之自白，不得作為有罪判決之唯一證據，仍應調查其他必要證據，以察其是否與事實相符，刑事訴訟法第一百五十六條第二項定有明文。查本件被告是否確有前開連續竊盜行為，除被告自白外，查無該等竊取之漫畫書籍可資佐證，告訴人乙○○亦指稱並無發現行竊行為，是乏其他證據足認被告自白合於事實，依上開法條規定，尚非可遽為被告有連續竊盜犯行之認定，附此敘明。五、依刑事訴訟法第四百四十九條第一項前段、第四百五十四條第二項，刑法第三百二十條第一項、第四十二條第二項，罰金罰鍰提高標準條例第一條前段、第二條，逕以簡易判決如主文。六、如不服本判決，得於判決書送達之翌日起十日內，以書狀敘述理由，向本院提出上訴。中華民國九十三年四月一日臺灣桃園地方法院刑事第三庭法官楊晴翔右正本證明與原本無異。書記官姜國駒中華民國九十三年四月十二日附錄本案論罪科刑法條：中華民國刑法第三百二十條意圖為自己或第三人不法之所有，而竊取他人之動產者，為竊盜罪，處五年以下有期徒刑、拘役或五百元以下罰金（已提高為十倍，單位為銀元）。意圖為自己或第三人不法之利益，而竊佔他人之不動產者，依前項之規定處斷。前二項之未遂犯罰之。",
  "characters": {
    "judges": [
      "楊晴翔"
    ],
    "prosecutors": [

    ],
    "lawyers": [

    ],
    "clerks": [
      "姜國駒"
    ],
    "plaintiffs": [

    ],
    "defendants": [
      "甲○○",
      "右列被告因竊盜案件，經檢察官聲請以簡易判決處刑（九十三年度偵字第三六八七號",
      "），本院判決如左："
    ],
    "prosecutor_office": [
      "臺灣桃園地方法院檢察署檢察官"
    ],
    "creditors": [

    ],
    "debtors": [

    ],
    "judicial_associate_officer": [

    ]
  },
  "adjudged_at": "2004-04-01",
  "created_at": "2016-02-06 10:38:14",
  "updated_at": "2016-02-06 10:38:14"
}