{
  "identify": "PCD-100-聲-466-20110210-1",
  "court": {
    "name": "臺灣新北地方法院",
    "code": "PCD"
  },
  "division": {
    "name": "刑事",
    "code": "M"
  },
  "year": 100,
  "word": "聲",
  "number": "466",
  "jcheck": "1",
  "reason": "聲請宣告沒收違禁物",
  "content": "臺灣板橋地方法院刑事裁定              100年度聲字第466號\n聲  請  人  臺灣板橋地方法院檢察署檢察官\n被      告  鄭孝武\n上列聲請人聲請宣告沒收違禁物案件（100 年度聲沒字第75號）\n，本院裁定如下：\n    主  文\n扣案如附表所示之物沒收銷燬。\n    理  由\n一、按違禁物得單獨宣告沒收，刑法第40條第2 項定有明文。而\n    甲基安非他命業經毒品危害防制條例第2 條第2 項第2 款列\n    為第二級毒品，為違禁物，不問屬於犯人與否，應沒收銷燬\n    之，亦為同條例第18條第1 項前段所明定。經查，聲請人以\n    被告鄭孝武違反毒品危害防制條例案件，業經臺灣板橋地方\n    法院檢察署檢察官以99年度毒偵字第4403號為不起訴處分在\n    案，扣案如附表所示之第二級毒品甲基安非他命2 包，為違\n    禁物，不問屬於犯人與否，應予沒收銷燬為由，向本院為本\n    件聲請，並提出前揭不起訴處分書及毒品鑑定資料各1 份為\n    憑。經核尚無不合，應予准許。\n二、依刑事訴訟法第220 條，毒品危害防制條例第18條第1 項前\n    段，刑法第11條、第40條第2 項，裁定如主文。\n中    華    民    國   100    年    2     月    10    日\n                  刑事第十九庭  法  官  許炎灶\n以上正本證明與原本無異。\n如不服本裁定，應於裁定送達後5 日內向本院提出抗告狀。\n                                書記官  周百川\n中    華    民    國   100    年    2     月    10    日\n附表：\n┌──┬────────┬────────┬────────┐\n│編號│沒     收     物│重            量│ 鑑  定  資  料 │\n├──┼────────┼────────┼────────┤\n│ 1  │第二級毒品甲基安│淨重1.5240公克  │交通部民用航空局│\n│    │非他命2 包      │取樣0.0002公克  │航空醫務中心99年│\n│    │                │餘重1.5238公克  │6 月1 日航藥鑑字│\n│    │                │                │第0000000 號毒品│\n│    │                │                │鑑定書          │\n└──┴────────┴────────┴────────┘",
  "structure": {
    "main": "扣案如附表所示之物沒收銷燬。",
    "reason": "一、按違禁物得單獨宣告沒收，刑法第40條第2 項定有明文。而\n    甲基安非他命業經毒品危害防制條例第2 條第2 項第2 款列\n    為第二級毒品，為違禁物，不問屬於犯人與否，應沒收銷燬\n    之，亦為同條例第18條第1 項前段所明定。經查，聲請人以\n    被告鄭孝武違反毒品危害防制條例案件，業經臺灣板橋地方\n    法院檢察署檢察官以99年度毒偵字第4403號為不起訴處分在\n    案，扣案如附表所示之第二級毒品甲基安非他命2 包，為違\n    禁物，不問屬於犯人與否，應予沒收銷燬為由，向本院為本\n    件聲請，並提出前揭不起訴處分書及毒品鑑定資料各1 份為\n    憑。經核尚無不合，應予准許。\n二、依刑事訴訟法第220 條，毒品危害防制條例第18條第1 項前\n    段，刑法第11條、第40條第2 項，裁定如主文。"
  },
  "search": "臺灣板橋地方法院刑事裁定100年度聲字第466號聲請人臺灣板橋地方法院檢察署檢察官被告鄭孝武上列聲請人聲請宣告沒收違禁物案件（100年度聲沒字第75號），本院裁定如下：主文扣案如附表所示之物沒收銷燬。理由一、按違禁物得單獨宣告沒收，刑法第40條第2項定有明文。而甲基安非他命業經毒品危害防制條例第2條第2項第2款列為第二級毒品，為違禁物，不問屬於犯人與否，應沒收銷燬之，亦為同條例第18條第1項前段所明定。經查，聲請人以被告鄭孝武違反毒品危害防制條例案件，業經臺灣板橋地方法院檢察署檢察官以99年度毒偵字第4403號為不起訴處分在案，扣案如附表所示之第二級毒品甲基安非他命2包，為違禁物，不問屬於犯人與否，應予沒收銷燬為由，向本院為本件聲請，並提出前揭不起訴處分書及毒品鑑定資料各1份為憑。經核尚無不合，應予准許。二、依刑事訴訟法第220條，毒品危害防制條例第18條第1項前段，刑法第11條、第40條第2項，裁定如主文。中華民國100年2月10日刑事第十九庭法官許炎灶以上正本證明與原本無異。如不服本裁定，應於裁定送達後5日內向本院提出抗告狀。書記官周百川中華民國100年2月10日附表：┌──┬────────┬────────┬────────┐│編號│沒收物│重量│鑑定資料│├──┼────────┼────────┼────────┤│1│第二級毒品甲基安│淨重1.5240公克│交通部民用航空局│││非他命2包│取樣0.0002公克│航空醫務中心99年││││餘重1.5238公克│6月1日航藥鑑字│││││第0000000號毒品│││││鑑定書│└──┴────────┴────────┴────────┘",
  "characters": {
    "judges": [
      "許炎灶"
    ],
    "prosecutors": [

    ],
    "lawyers": [

    ],
    "clerks": [
      "周百川"
    ],
    "plaintiffs": [

    ],
    "defendants": [
      "鄭孝武"
    ],
    "prosecutor_office": [
      "臺灣板橋地方法院檢察署檢察官"
    ],
    "creditors": [

    ],
    "debtors": [

    ],
    "judicial_associate_officer": [

    ]
  },
  "adjudged_at": "2011-02-10",
  "created_at": "2016-02-12 06:55:58",
  "updated_at": "2016-02-12 06:55:58"
}