{
  "identify": "TCD-100-交易-55-20110210-1",
  "court": {
    "name": "臺灣臺中地方法院",
    "code": "TCD"
  },
  "division": {
    "name": "刑事",
    "code": "M"
  },
  "year": 100,
  "word": "交易",
  "number": "55",
  "jcheck": "1",
  "reason": "公共危險",
  "content": "臺灣臺中地方法院刑事判決             100年度交易字第55號\n公  訴  人  臺灣臺中地方法院檢察署檢察官\n被      告  邱文生\n上列被告因公共危險案件，經檢察官提起公訴（99年度偵字第\n27241號），本院判決如下：\n    主    文\n邱文生犯不能安全駕駛動力交通工具罪，累犯，處有期徒刑柒月\n。\n    犯罪事實\n一、犯罪事實：邱文生前因公共危險案件，經本院於民國99 年3\n    月22日以99年度豐交簡字第97號判決判處有期徒刑6月確定\n    ，並於99年4月22日易科罰金執行完畢。詎猶不知悔改，自\n    99 年11月24日下午4時許起，至同日下午6時許止，在臺中\n    市工業區某處，飲用啤酒約5、6瓶後，已達不能安全駕駛動\n    力交通工具之程度，竟駕駛牌照號碼CQ-3366號自用小客車\n    ，欲返回其位於民權二街之住處，嗣於99年11月24日晚上18\n    時40 分許，行經臺中縣神岡鄉○○路與八德路口時，因不\n    勝酒力，注意力及控制力降低，不慎追撞王義貴駕駛之牌照\n    號碼6V-135號自用大貨車，幸無人受傷。經警據報前往處理\n    ，於同日20時27分許測得邱文生呼氣酒精濃度達0.77mg/l\n    。\n二、案經臺中縣（現臺中市）警察局豐原分局報告臺灣臺中地方\n    法院檢察署檢察官偵查起訴。\n    理     由\n一、按傳聞法則之重要理論依據，在於傳聞證據未經當事人之反\n    對詰問予以核實，乃予排斥，惟若當事人已放棄對原供述人\n    之反對詰問權，於法院審判時表明同意該等傳聞證據可作為\n    證據，基於證據資料愈豐富，愈有助於真實發現之理念，並\n    貫徹刑事訴訟法修法加重當事人進行主義之精神，確認當事\n    人對於證據能力有處分權之制度，傳聞證據經當事人同意作\n    為證據，法院認為適當者，亦得為證據。另當事人於調查證\n    據時，對於傳聞證據表示「沒有意見」、「對於證據調查無\n    意見」，而未於言詞辯論終結前聲明異議，應視為已有將該\n    等傳聞證據採為證據之同意，此刑事訴訟法第159條之5定有\n    明文。查本案所引之下列證據，本案當事人於本院審理時，\n    對於證據能力均表示無意見，亦未於本案言詞辯論終結前聲\n    明異議，則本院審酌該等證據並無違法取證或證明力顯然過\n    低之情事，均得採為證據。\n二、認定犯罪事實所憑之證據及理由：上揭犯罪事實，業據被告\n    於警詢及檢察官偵訊中坦承不諱，核與證人王義貴於警詢中\n    證述之情節相符，並有酒精濃度檢測單、汽車駕駛人酒後生\n    理協調平衡檢測紀錄卡、道路交通事故現場圖、道路交通事\n    故調查報告表（一）、（二）、臺中縣警察局舉發違反道路\n    交通管理事件通知單影本、現場照片11張及職務報告等附卷\n    可稽。足認被告之自白與事實相符，犯行堪以認定。\n三、論罪科刑之理由：核被告所為，係犯刑法第185條之3服用酒\n    類致無法安全駕駛動力交通工具罪。查被告前因公共危險案\n    件，經本院於99年3月22日以99年度豐交簡字第97號判決判\n    處有期徒刑6月確定，並於99年4月22日易科罰金執行完畢，\n    其於前案有期徒刑執行完畢後，5年內故意再犯本件有期徒\n    刑以上之罪，依刑法第47條第1項之規定，論以累犯並加重\n    其刑。爰審酌被告前因犯不能安全駕駛動力交通工具罪，於\n    98年經臺灣臺中地方法院檢察署檢察官以98年度偵字第1713\n    4號聲請簡易判決處刑，為本院以99年度豐交簡字第539 號\n    判決判處有期徒刑3月確定；復因相同案件，經檢察官聲請\n    簡易判決處刑，分別經本院以98年度豐交簡字第763號判決\n    判處有期徒刑5月確定；以99年度豐交簡字第97號判決判處\n    有期徒刑6月確定，並均經易科罰金執行完畢，此有上開紀\n    錄表存卷足憑，被告於本案之前犯有多次酒後不能安全駕駛\n    動力交通工具罪，且於前案判決有期徒刑6月，於99年4 月\n    22日易科罰金執行完畢後，於同年間又再犯酒後駕車，足認\n    被告對酒後駕車，全無悔意，且被告酒後呼氣酒精濃度高達\n    每公升0. 77毫克，實對其他用路人產生相當大之危險，於\n    本件亦發生車禍，幸未有人受傷及於偵、審中坦承犯行等一\n    切情狀，量處如主文所示之刑。\n據上論斷，依刑事訴訟法第299條第1項前段，刑法第185條之3、\n第47條第1項，判決如主文。\n本案經檢察官鐘祖聲到庭執行職務。\n中    華    民    國  100    年   2    月    10    日\n                        刑事第四庭    法  官  黃益茂\n以上正本證明與原本無異。\n如不服本判決應於收受送達後10日內向本院提出上訴書狀，並應\n敘述具體理由；其未敘述上訴理由者，應於上訴期間屆滿後20日\n內向本院補提理由書（均須按他造當事人之人數附繕本）「切勿\n逕送上級法院」。\n                                      書記官  蔡秋明\n中    華    民    國    100  年    2  月    10     日\n附錄論罪科刑法條\n刑法第185條之3\n服用毒品、麻醉藥品、酒類或其他相類之物，不能安全駕駛動力\n交通工具而駕駛者，處一年以下有期徒刑、拘役或科或併科十五\n萬元以下罰金。",
  "structure": {
    "main": "邱文生犯不能安全駕駛動力交通工具罪，累犯，處有期徒刑柒月\n。",
    "fact": "一、犯罪事實：邱文生前因公共危險案件，經本院於民國99 年3\n    月22日以99年度豐交簡字第97號判決判處有期徒刑6月確定\n    ，並於99年4月22日易科罰金執行完畢。詎猶不知悔改，自\n    99 年11月24日下午4時許起，至同日下午6時許止，在臺中\n    市工業區某處，飲用啤酒約5、6瓶後，已達不能安全駕駛動\n    力交通工具之程度，竟駕駛牌照號碼CQ-3366號自用小客車\n    ，欲返回其位於民權二街之住處，嗣於99年11月24日晚上18\n    時40 分許，行經臺中縣神岡鄉○○路與八德路口時，因不\n    勝酒力，注意力及控制力降低，不慎追撞王義貴駕駛之牌照\n    號碼6V-135號自用大貨車，幸無人受傷。經警據報前往處理\n    ，於同日20時27分許測得邱文生呼氣酒精濃度達0.77mg/l\n    。\n二、案經臺中縣（現臺中市）警察局豐原分局報告臺灣臺中地方\n    法院檢察署檢察官偵查起訴。\n    理     由\n一、按傳聞法則之重要理論依據，在於傳聞證據未經當事人之反\n    對詰問予以核實，乃予排斥，惟若當事人已放棄對原供述人\n    之反對詰問權，於法院審判時表明同意該等傳聞證據可作為\n    證據，基於證據資料愈豐富，愈有助於真實發現之理念，並\n    貫徹刑事訴訟法修法加重當事人進行主義之精神，確認當事\n    人對於證據能力有處分權之制度，傳聞證據經當事人同意作\n    為證據，法院認為適當者，亦得為證據。另當事人於調查證\n    據時，對於傳聞證據表示「沒有意見」、「對於證據調查無\n    意見」，而未於言詞辯論終結前聲明異議，應視為已有將該\n    等傳聞證據採為證據之同意，此刑事訴訟法第159條之5定有\n    明文。查本案所引之下列證據，本案當事人於本院審理時，\n    對於證據能力均表示無意見，亦未於本案言詞辯論終結前聲\n    明異議，則本院審酌該等證據並無違法取證或證明力顯然過\n    低之情事，均得採為證據。\n二、認定犯罪事實所憑之證據及理由：上揭犯罪事實，業據被告\n    於警詢及檢察官偵訊中坦承不諱，核與證人王義貴於警詢中\n    證述之情節相符，並有酒精濃度檢測單、汽車駕駛人酒後生\n    理協調平衡檢測紀錄卡、道路交通事故現場圖、道路交通事\n    故調查報告表（一）、（二）、臺中縣警察局舉發違反道路\n    交通管理事件通知單影本、現場照片11張及職務報告等附卷\n    可稽。足認被告之自白與事實相符，犯行堪以認定。\n三、論罪科刑之理由：核被告所為，係犯刑法第185條之3服用酒\n    類致無法安全駕駛動力交通工具罪。查被告前因公共危險案\n    件，經本院於99年3月22日以99年度豐交簡字第97號判決判\n    處有期徒刑6月確定，並於99年4月22日易科罰金執行完畢，\n    其於前案有期徒刑執行完畢後，5年內故意再犯本件有期徒\n    刑以上之罪，依刑法第47條第1項之規定，論以累犯並加重\n    其刑。爰審酌被告前因犯不能安全駕駛動力交通工具罪，於\n    98年經臺灣臺中地方法院檢察署檢察官以98年度偵字第1713\n    4號聲請簡易判決處刑，為本院以99年度豐交簡字第539 號\n    判決判處有期徒刑3月確定；復因相同案件，經檢察官聲請\n    簡易判決處刑，分別經本院以98年度豐交簡字第763號判決\n    判處有期徒刑5月確定；以99年度豐交簡字第97號判決判處\n    有期徒刑6月確定，並均經易科罰金執行完畢，此有上開紀\n    錄表存卷足憑，被告於本案之前犯有多次酒後不能安全駕駛\n    動力交通工具罪，且於前案判決有期徒刑6月，於99年4 月\n    22日易科罰金執行完畢後，於同年間又再犯酒後駕車，足認\n    被告對酒後駕車，全無悔意，且被告酒後呼氣酒精濃度高達\n    每公升0. 77毫克，實對其他用路人產生相當大之危險，於\n    本件亦發生車禍，幸未有人受傷及於偵、審中坦承犯行等一\n    切情狀，量處如主文所示之刑。\n據上論斷，依刑事訴訟法第299條第1項前段，刑法第185條之3、\n第47條第1項，判決如主文。\n本案經檢察官鐘祖聲到庭執行職務。"
  },
  "search": "臺灣臺中地方法院刑事判決100年度交易字第55號公訴人臺灣臺中地方法院檢察署檢察官被告邱文生上列被告因公共危險案件，經檢察官提起公訴（99年度偵字第27241號），本院判決如下：主文邱文生犯不能安全駕駛動力交通工具罪，累犯，處有期徒刑柒月。犯罪事實一、犯罪事實：邱文生前因公共危險案件，經本院於民國99年3月22日以99年度豐交簡字第97號判決判處有期徒刑6月確定，並於99年4月22日易科罰金執行完畢。詎猶不知悔改，自99年11月24日下午4時許起，至同日下午6時許止，在臺中市工業區某處，飲用啤酒約5、6瓶後，已達不能安全駕駛動力交通工具之程度，竟駕駛牌照號碼CQ-3366號自用小客車，欲返回其位於民權二街之住處，嗣於99年11月24日晚上18時40分許，行經臺中縣神岡鄉○○路與八德路口時，因不勝酒力，注意力及控制力降低，不慎追撞王義貴駕駛之牌照號碼6V-135號自用大貨車，幸無人受傷。經警據報前往處理，於同日20時27分許測得邱文生呼氣酒精濃度達0.77mg/l。二、案經臺中縣（現臺中市）警察局豐原分局報告臺灣臺中地方法院檢察署檢察官偵查起訴。理由一、按傳聞法則之重要理論依據，在於傳聞證據未經當事人之反對詰問予以核實，乃予排斥，惟若當事人已放棄對原供述人之反對詰問權，於法院審判時表明同意該等傳聞證據可作為證據，基於證據資料愈豐富，愈有助於真實發現之理念，並貫徹刑事訴訟法修法加重當事人進行主義之精神，確認當事人對於證據能力有處分權之制度，傳聞證據經當事人同意作為證據，法院認為適當者，亦得為證據。另當事人於調查證據時，對於傳聞證據表示「沒有意見」、「對於證據調查無意見」，而未於言詞辯論終結前聲明異議，應視為已有將該等傳聞證據採為證據之同意，此刑事訴訟法第159條之5定有明文。查本案所引之下列證據，本案當事人於本院審理時，對於證據能力均表示無意見，亦未於本案言詞辯論終結前聲明異議，則本院審酌該等證據並無違法取證或證明力顯然過低之情事，均得採為證據。二、認定犯罪事實所憑之證據及理由：上揭犯罪事實，業據被告於警詢及檢察官偵訊中坦承不諱，核與證人王義貴於警詢中證述之情節相符，並有酒精濃度檢測單、汽車駕駛人酒後生理協調平衡檢測紀錄卡、道路交通事故現場圖、道路交通事故調查報告表（一）、（二）、臺中縣警察局舉發違反道路交通管理事件通知單影本、現場照片11張及職務報告等附卷可稽。足認被告之自白與事實相符，犯行堪以認定。三、論罪科刑之理由：核被告所為，係犯刑法第185條之3服用酒類致無法安全駕駛動力交通工具罪。查被告前因公共危險案件，經本院於99年3月22日以99年度豐交簡字第97號判決判處有期徒刑6月確定，並於99年4月22日易科罰金執行完畢，其於前案有期徒刑執行完畢後，5年內故意再犯本件有期徒刑以上之罪，依刑法第47條第1項之規定，論以累犯並加重其刑。爰審酌被告前因犯不能安全駕駛動力交通工具罪，於98年經臺灣臺中地方法院檢察署檢察官以98年度偵字第17134號聲請簡易判決處刑，為本院以99年度豐交簡字第539號判決判處有期徒刑3月確定；復因相同案件，經檢察官聲請簡易判決處刑，分別經本院以98年度豐交簡字第763號判決判處有期徒刑5月確定；以99年度豐交簡字第97號判決判處有期徒刑6月確定，並均經易科罰金執行完畢，此有上開紀錄表存卷足憑，被告於本案之前犯有多次酒後不能安全駕駛動力交通工具罪，且於前案判決有期徒刑6月，於99年4月22日易科罰金執行完畢後，於同年間又再犯酒後駕車，足認被告對酒後駕車，全無悔意，且被告酒後呼氣酒精濃度高達每公升0.77毫克，實對其他用路人產生相當大之危險，於本件亦發生車禍，幸未有人受傷及於偵、審中坦承犯行等一切情狀，量處如主文所示之刑。據上論斷，依刑事訴訟法第299條第1項前段，刑法第185條之3、第47條第1項，判決如主文。本案經檢察官鐘祖聲到庭執行職務。中華民國100年2月10日刑事第四庭法官黃益茂以上正本證明與原本無異。如不服本判決應於收受送達後10日內向本院提出上訴書狀，並應敘述具體理由；其未敘述上訴理由者，應於上訴期間屆滿後20日內向本院補提理由書（均須按他造當事人之人數附繕本）「切勿逕送上級法院」。書記官蔡秋明中華民國100年2月10日附錄論罪科刑法條刑法第185條之3服用毒品、麻醉藥品、酒類或其他相類之物，不能安全駕駛動力交通工具而駕駛者，處一年以下有期徒刑、拘役或科或併科十五萬元以下罰金。",
  "characters": {
    "judges": [
      "黃益茂"
    ],
    "prosecutors": [
      "鐘祖聲"
    ],
    "lawyers": [

    ],
    "clerks": [
      "蔡秋明"
    ],
    "plaintiffs": [

    ],
    "defendants": [
      "邱文生"
    ],
    "prosecutor_office": [
      "臺灣臺中地方法院檢察署檢察官"
    ],
    "creditors": [

    ],
    "debtors": [

    ],
    "judicial_associate_officer": [

    ]
  },
  "adjudged_at": "2011-02-10",
  "created_at": "2016-02-12 06:42:43",
  "updated_at": "2016-02-12 06:42:43"
}