{
  "identify": "MLD-100-苗簡-624-20110713-1",
  "court": {
    "name": "臺灣苗栗地方法院",
    "code": "MLD"
  },
  "division": {
    "name": "刑事",
    "code": "M"
  },
  "year": 100,
  "word": "苗簡",
  "number": "624",
  "jcheck": "1",
  "reason": "侵占",
  "content": "臺灣苗栗地方法院刑事簡易判決       100年度苗簡字第624號\n聲  請  人  臺灣苗栗地方法院檢察署檢察官\n被      告  賴喜珍\n上列被告因侵占案件，經檢察官聲請以簡易判決處刑（100年度\n偵字第1036號），本院判決如下：\n    主  文\n賴喜珍犯侵占遺失物罪，處罰金新臺幣伍仟元，如易服勞役，以\n新臺幣壹仟元折算壹日。\n    事實及理由\n一、本件犯罪事實及證據均引用檢察官聲請簡易判決處刑書內容\n    之記載（如附件）。\n二、爰審酌被告犯罪之動機、目的、手段及其品行、智識程度、\n    被害財物僅為獎券1 張等一切情狀，量處如主文所示之刑，\n    併諭知易服勞役之折算標準。\n三、應適用法條：\n  （一）刑事訴訟法第449 條第1 項前段、第454 條第2 項。\n  （二）刑法第337 條、第42條第3 項前段。\n  （三）刑法施行法第1 條之1 第1 項、第2 項前段。\n四、如不服本判決，得自收受送達之日起10日內，向本院提起上\n    訴（須附繕本），上訴於本院合議庭。\n中    華    民    國  100     年    7     月    13    日\n                  苗栗簡易庭  法  官  周靜妮\n以上正本證明與原本無異。\n如不服本判決應於收受判決後10日內向本院提出上訴書狀，並應\n應敘述具體理由。其未敘述上訴理由者，應於上訴期間屆滿後20\n日內向本院補提理由書( 均須按他造當事人之人數附繕本) 「切\n勿逕送上級法院」。告訴人或被害人如對本判決不服者，應具備\n理由請求檢察官上訴，其上訴期間之計算係以檢察官收受判決正\n本之日期為準。\n                              書記官  巫穎\n中    華    民    國  100     年    7     月    13    日\n附錄本判決論罪科刑法條：\n刑法第337 條\n意圖為自己或第三人不法之所有，而侵占遺失物、漂流物或其他\n離本人所持有之物者，處5 百元以下罰金。\n附件：\n臺灣苗栗地方法院檢察署檢察官聲請簡易判決處刑書\n                                     100年度偵字第1036號\n    被  告  賴喜珍  女  45歲（民國○○年○○月○○日生）\n                    國民身分證統一編號：Ｚ000000000號\n                    住新北市○○區○○里○○鄰○○路○段92\n                    巷8號3樓\n                    居苗栗縣苗栗市○○路423號\n上列被告因侵占案件，業經偵查終結，認為宜以簡易判決處刑，\n茲將犯罪事實及證據並所犯法條分敘如下：\n        犯罪事實\n一、賴喜珍係經營彩券行業務，於民國99年12月10日0時5分許，\n    步行前往址設苗栗縣苗栗市○○路 399號「全家便利商店苗\n    栗富樂店」購物後正欲離去之際，行經影印機旁拾獲陳敏忠\n    所遺失中國信託商業銀行委託台灣彩券股份有限公司發行序\n    號026605─034號之刮刮樂彩券1紙，詎其明知該紙刮刮樂彩\n    券係非出於所有人或持有人本意而遺失之物，竟仍意圖為自\n    己不法之所有，未將之送警處理，而加以侵占入己，並隨即\n    在返回苗栗市○○路 423號之居所後，將前揭拾獲之該紙刮\n    刮樂彩券放置在抽屜內。後於99年12月13日12時許，賴喜珍\n    瞥然想起該紙刮刮樂彩券，經將其上之編號輸入電腦後，發\n    覺該紙刮刮樂彩券尚未兌領獎金，乃於同日13時許，持該紙\n    刮刮樂彩券前往址設苗栗市○○路 686號「華南商業銀行苗\n    栗分行」（以下簡稱華南銀行苗栗分行），並在該紙刮刮樂\n    彩券背面「姓名」、「身分證字號」、「電話」、「中獎人\n    簽名處」及「戶籍地址」等欄位內填載資料後，兌領獎金新\n    臺幣（下同） 3,980元（按此係扣除百分之20之競技競賽及\n    機會中獎獎金1,000元及千分之4之印花稅20元後所得之金額\n    ）。嗣因陳敏忠發覺其所有之上開刮刮樂彩券不見，經向華\n    南銀行苗栗分行承辦人員查詢後，獲悉該紙刮刮樂彩券業經\n    他人兌領獎金，乃報警處理，並經警調閱「全家便利商店苗\n    栗富樂店」現場監視錄影系統畫面而循線追索後，始查悉上\n    情。\n二、案經陳敏忠訴由苗栗縣警察局苗栗分局報告偵辦。\n        證據並所犯法條\n一、本案之證據清單臚列如下：\n  (一)被告賴喜珍於警詢及本署偵訊時之供述─證明被告坦承確有\n    於前揭時、地拾獲告訴人陳敏忠所遺失之刮刮樂彩券之情，\n    惟矢口否認有何侵占之犯行，辯稱略以：伊因為是彩券經銷\n    商，要保管彩券，經常是客戶將中獎的彩券先行交給伊，先\n    由伊墊款給客戶，再由伊持彩券向華南銀行苗栗分行兌領獎\n    金，而本件亦是如此，是由伊先行墊付款項給客戶云云。\n  (二)告訴人陳敏忠於警詢及本署偵訊中之指訴─證明被告所拾獲\n    之該紙刮刮樂彩券，係其妻子所經營之彩券行購入並賣出的\n    ，經由客人拿來兌獎，由其先墊付獎金，再拿去華南銀行苗\n    栗分行兌領獎金，則被告對於該紙刮刮樂彩券之來源出處，\n    既無以提出相關實據以為佐憑，而難以信其為真實。且以，\n    對照被告供稱曾向台灣彩券股份有限公司客服人員詢問兌領\n    獎金之方式，益徵被告對於所拾獲該紙刮刮樂彩券之來源出\n    處已有所質疑，顯有可疑為非出於所有人或持有人本意而遺\n    失之物，猶且本於所有權人之地位，而持向華南銀行苗栗分\n    行承辦人員兌領獎金，其主觀上已存有侵占之意圖。\n  (三)證人即全家便利商店苗栗富樂店店長徐意苓於警詢時之證述\n    ─證明被告拾獲告訴人所遺失之刮刮樂彩券，並以之侵占入\n    己之事實經過情節。\n  (四)收據及華南銀行苗栗分行100年3月 8日華苗存字第100073號\n    函暨所附兌獎資料影本各 1份─證明被告持以所拾獲之該紙\n    刮刮樂彩券兌領獎金之事實。\n二、核被告所為，係犯刑法第337條之侵占遺失物罪嫌。\n三、依刑事訴訟法第451條第1項聲請逕以簡易判決處刑。\n    此  致\n臺灣苗栗地方法院\n中    華    民    國   100    年    5     月    30    日\n                              檢 察 官  黃棋安\n本件證明與原本無異\n中    華    民    國   100    年    6     月    3     日\n                              書 記 官  張穎文",
  "structure": {
    "main": "賴喜珍犯侵占遺失物罪，處罰金新臺幣伍仟元，如易服勞役，以\n新臺幣壹仟元折算壹日。",
    "fact": "一、本件犯罪事實及證據均引用檢察官聲請簡易判決處刑書內容\n    之記載（如附件）。\n二、爰審酌被告犯罪之動機、目的、手段及其品行、智識程度、\n    被害財物僅為獎券1 張等一切情狀，量處如主文所示之刑，\n    併諭知易服勞役之折算標準。\n三、應適用法條：\n  （一）刑事訴訟法第449 條第1 項前段、第454 條第2 項。\n  （二）刑法第337 條、第42條第3 項前段。\n  （三）刑法施行法第1 條之1 第1 項、第2 項前段。\n四、如不服本判決，得自收受送達之日起10日內，向本院提起上\n    訴（須附繕本），上訴於本院合議庭。",
    "reason": "一、本件犯罪事實及證據均引用檢察官聲請簡易判決處刑書內容\n    之記載（如附件）。\n二、爰審酌被告犯罪之動機、目的、手段及其品行、智識程度、\n    被害財物僅為獎券1 張等一切情狀，量處如主文所示之刑，\n    併諭知易服勞役之折算標準。\n三、應適用法條：\n  （一）刑事訴訟法第449 條第1 項前段、第454 條第2 項。\n  （二）刑法第337 條、第42條第3 項前段。\n  （三）刑法施行法第1 條之1 第1 項、第2 項前段。\n四、如不服本判決，得自收受送達之日起10日內，向本院提起上\n    訴（須附繕本），上訴於本院合議庭。"
  },
  "search": "臺灣苗栗地方法院刑事簡易判決100年度苗簡字第624號聲請人臺灣苗栗地方法院檢察署檢察官被告賴喜珍上列被告因侵占案件，經檢察官聲請以簡易判決處刑（100年度偵字第1036號），本院判決如下：主文賴喜珍犯侵占遺失物罪，處罰金新臺幣伍仟元，如易服勞役，以新臺幣壹仟元折算壹日。事實及理由一、本件犯罪事實及證據均引用檢察官聲請簡易判決處刑書內容之記載（如附件）。二、爰審酌被告犯罪之動機、目的、手段及其品行、智識程度、被害財物僅為獎券1張等一切情狀，量處如主文所示之刑，併諭知易服勞役之折算標準。三、應適用法條：（一）刑事訴訟法第449條第1項前段、第454條第2項。（二）刑法第337條、第42條第3項前段。（三）刑法施行法第1條之1第1項、第2項前段。四、如不服本判決，得自收受送達之日起10日內，向本院提起上訴（須附繕本），上訴於本院合議庭。中華民國100年7月13日苗栗簡易庭法官周靜妮以上正本證明與原本無異。如不服本判決應於收受判決後10日內向本院提出上訴書狀，並應應敘述具體理由。其未敘述上訴理由者，應於上訴期間屆滿後20日內向本院補提理由書(均須按他造當事人之人數附繕本)「切勿逕送上級法院」。告訴人或被害人如對本判決不服者，應具備理由請求檢察官上訴，其上訴期間之計算係以檢察官收受判決正本之日期為準。書記官巫穎中華民國100年7月13日附錄本判決論罪科刑法條：刑法第337條意圖為自己或第三人不法之所有，而侵占遺失物、漂流物或其他離本人所持有之物者，處5百元以下罰金。附件：臺灣苗栗地方法院檢察署檢察官聲請簡易判決處刑書100年度偵字第1036號被告賴喜珍女45歲（民國○○年○○月○○日生）國民身分證統一編號：Ｚ000000000號住新北市○○區○○里○○鄰○○路○段92巷8號3樓居苗栗縣苗栗市○○路423號上列被告因侵占案件，業經偵查終結，認為宜以簡易判決處刑，茲將犯罪事實及證據並所犯法條分敘如下：犯罪事實一、賴喜珍係經營彩券行業務，於民國99年12月10日0時5分許，步行前往址設苗栗縣苗栗市○○路399號「全家便利商店苗栗富樂店」購物後正欲離去之際，行經影印機旁拾獲陳敏忠所遺失中國信託商業銀行委託台灣彩券股份有限公司發行序號026605─034號之刮刮樂彩券1紙，詎其明知該紙刮刮樂彩券係非出於所有人或持有人本意而遺失之物，竟仍意圖為自己不法之所有，未將之送警處理，而加以侵占入己，並隨即在返回苗栗市○○路423號之居所後，將前揭拾獲之該紙刮刮樂彩券放置在抽屜內。後於99年12月13日12時許，賴喜珍瞥然想起該紙刮刮樂彩券，經將其上之編號輸入電腦後，發覺該紙刮刮樂彩券尚未兌領獎金，乃於同日13時許，持該紙刮刮樂彩券前往址設苗栗市○○路686號「華南商業銀行苗栗分行」（以下簡稱華南銀行苗栗分行），並在該紙刮刮樂彩券背面「姓名」、「身分證字號」、「電話」、「中獎人簽名處」及「戶籍地址」等欄位內填載資料後，兌領獎金新臺幣（下同）3,980元（按此係扣除百分之20之競技競賽及機會中獎獎金1,000元及千分之4之印花稅20元後所得之金額）。嗣因陳敏忠發覺其所有之上開刮刮樂彩券不見，經向華南銀行苗栗分行承辦人員查詢後，獲悉該紙刮刮樂彩券業經他人兌領獎金，乃報警處理，並經警調閱「全家便利商店苗栗富樂店」現場監視錄影系統畫面而循線追索後，始查悉上情。二、案經陳敏忠訴由苗栗縣警察局苗栗分局報告偵辦。證據並所犯法條一、本案之證據清單臚列如下：(一)被告賴喜珍於警詢及本署偵訊時之供述─證明被告坦承確有於前揭時、地拾獲告訴人陳敏忠所遺失之刮刮樂彩券之情，惟矢口否認有何侵占之犯行，辯稱略以：伊因為是彩券經銷商，要保管彩券，經常是客戶將中獎的彩券先行交給伊，先由伊墊款給客戶，再由伊持彩券向華南銀行苗栗分行兌領獎金，而本件亦是如此，是由伊先行墊付款項給客戶云云。(二)告訴人陳敏忠於警詢及本署偵訊中之指訴─證明被告所拾獲之該紙刮刮樂彩券，係其妻子所經營之彩券行購入並賣出的，經由客人拿來兌獎，由其先墊付獎金，再拿去華南銀行苗栗分行兌領獎金，則被告對於該紙刮刮樂彩券之來源出處，既無以提出相關實據以為佐憑，而難以信其為真實。且以，對照被告供稱曾向台灣彩券股份有限公司客服人員詢問兌領獎金之方式，益徵被告對於所拾獲該紙刮刮樂彩券之來源出處已有所質疑，顯有可疑為非出於所有人或持有人本意而遺失之物，猶且本於所有權人之地位，而持向華南銀行苗栗分行承辦人員兌領獎金，其主觀上已存有侵占之意圖。(三)證人即全家便利商店苗栗富樂店店長徐意苓於警詢時之證述─證明被告拾獲告訴人所遺失之刮刮樂彩券，並以之侵占入己之事實經過情節。(四)收據及華南銀行苗栗分行100年3月8日華苗存字第100073號函暨所附兌獎資料影本各1份─證明被告持以所拾獲之該紙刮刮樂彩券兌領獎金之事實。二、核被告所為，係犯刑法第337條之侵占遺失物罪嫌。三、依刑事訴訟法第451條第1項聲請逕以簡易判決處刑。此致臺灣苗栗地方法院中華民國100年5月30日檢察官黃棋安本件證明與原本無異中華民國100年6月3日書記官張穎文",
  "characters": {
    "judges": [
      "周靜妮"
    ],
    "prosecutors": [

    ],
    "lawyers": [

    ],
    "clerks": [
      "巫穎"
    ],
    "plaintiffs": [

    ],
    "defendants": [
      "賴喜珍",
      "賴喜珍  女  45歲（民國○○年○○月○○日生）"
    ],
    "prosecutor_office": [
      "臺灣苗栗地方法院檢察署檢察官"
    ],
    "creditors": [

    ],
    "debtors": [

    ],
    "judicial_associate_officer": [

    ]
  },
  "adjudged_at": "2011-07-13",
  "created_at": "2016-02-14 02:39:19",
  "updated_at": "2016-02-14 02:39:19"
}