{
  "identify": "PTD-100-易-596-20110712-1",
  "court": {
    "name": "臺灣屏東地方法院",
    "code": "PTD"
  },
  "division": {
    "name": "刑事",
    "code": "M"
  },
  "year": 100,
  "word": "易",
  "number": "596",
  "jcheck": "1",
  "reason": "竊盜",
  "content": "臺灣屏東地方法院刑事判決              100年度易字第596號\n公  訴  人  臺灣屏東地方法院檢察署檢察官\n被      告  趙能賢\n上列被告因竊盜案件，經檢察官提起公訴（99年度偵字第6968、\n9793號、99年度偵緝字第433 號），被告於準備程序中，就被訴\n事實為有罪之陳述，本院告知其簡式審判程序之旨，聽取當事人\n意見後，裁定由受命法官獨任依簡式審判程序審理，茲判決如下\n：\n    主  文\n趙能賢犯如附表一主文欄所示之罪，均累犯，各處如附表一主文\n欄所示之刑。應執行有期徒刑貳年拾月。\n    事  實\n一、趙能賢前因竊盜案件，經本院以93年度易字第507 號判決判\n    處有期徒刑1 年確定，於民國96年1 月5 日執行完畢。詎猶\n    不知悔改，竟與真實姓名、年籍不詳綽號「阿文」之成年男\n    子（下稱「阿文」）共同意圖為自己不法之所有，基於竊盜\n    之犯意聯絡，於如附表一編號1 所示之時間、地點，以如附\n    表一編號1 所示之方式，竊取如附表一編號1 所示之被害人\n    財物；又與劉昌碾（通緝中，到案後另行審結）共同意圖為\n    自己不法之所有，基於竊盜之犯意聯絡，於如附表一編號2\n    至4 所示之時間、地點，以如附表一編號2 至4 所示之方式\n    ，竊取如附表一編號2 至4 所示之被害人財物。嗣因如附表\n    一編號1 至4 所示之查獲方式，為警查獲，而悉上情。\n二、案經屏東縣政府警察局屏東分局、里港分局報告臺灣屏東地\n    方法院檢察署檢察官偵查起訴。\n    理  由\n一、上開犯罪事實，業經被告趙能賢於本院審理時坦承不諱（見\n    本院卷第65頁背面、第66頁），並有如附表一證據欄所示之\n    證據可資佐證，足認被告自白與事實相符。本案事證明確，\n    被告犯行洵堪認定，應依法論科。\n二、按被告行為後，如附表二所示之刑法第321 條第1 項第1 款\n    、第2 款、第3 款已於100 年1 月26日修正公布，於100 年\n    1 月28日施行，茲依規範行為後法律變更所生新舊法律比較\n    適用之準據法即刑法第2 條第1 項之規定，為「從舊從輕」\n    之比較（詳如附表二所示），因行為後之法律之法定刑較重\n    ，並未對其較有利，故應適用行為時即修正前之規定論處。\n三、按刑法第321 條第1 項第2 款規定將「門扇」、「牆垣」、\n    「其他安全設備」並列，而所謂「門扇」應專指門戶，即分\n    隔住宅或建築物內外之間之出入口大門而言。另所謂「其他\n    安全設備」，則指門扇、牆垣以外，依社會通常觀念足認為\n    防盜之一切設備而言，如門鎖、窗戶、房間門或通往陽臺之\n    門即屬之（最高法院45年臺上字第1443號判例、55年臺上字\n    第547 號判例意旨參照）；復按刑法第321 條第1 項第3 款\n    所稱兇器，其種類並無限制，凡客觀上足對人之生命、身體\n    、安全構成威脅，具有危險性之兇器均屬之，且祇須行竊時\n    攜帶此種具有危險性之兇器為已足，並不以攜帶之初有行兇\n    之意圖為必要（最高法院79年臺上字第5253號判例意旨參照\n    ），被告於為如附表一編號2 所示之竊盜犯行時所持有之T\n    字扳手固未扣案，然既得破壞車鎖，應屬金屬材質且質地堅\n    硬，而劉昌碾於為如附表一編號4 所示之竊盜犯行所持有之\n    噴槍、螺絲起子雖亦未扣案，然劉昌碾既得持該噴槍毀壞該\n    住處陽臺玻璃門，且一般而言，螺絲起子質地堅硬，則持上\n    開T 字扳手、噴槍、螺絲起子使用、揮擊當足以對人之生命\n    、身體、安全造成威脅，故上開T 字扳手、噴槍、螺絲起子\n    顯為具有危險性之兇器無訛。是核被告如附表一編號1 所為\n    ，係犯行為時刑法第321 條第1 項第2 款之踰越安全設備竊\n    盜罪；如附表一編號2 所為，係犯行為時刑法第321 條第1\n    項第3 款之攜帶兇器竊盜罪；如附表一編號3 所為，係犯行\n    為時刑法第321 條第1 項第1 款之夜間侵入住宅竊盜罪；如\n    附表一編號4 所為，則係犯行為時刑法第321 條第1 項第1\n    款、第2 款、第3 款之攜帶兇器、踰越牆垣、毀壞安全設備\n    、夜間侵入住宅竊盜罪。又被告如附表一編號1 所示之犯行\n    ，檢察官認被告有夜間侵入住宅之行為，然被告於警詢、偵\n    訊及本院審理時均陳稱其行竊之時間為99年6 月6 日上午5\n    時許，斯時已天亮等語（見警卷(三)第4 頁；偵查卷(一)第112\n    頁；本院卷第65頁背面），而99年6 月6 日之日出時刻為上\n    午5 時12分，有日出日沒時刻表1 份在卷可憑（見本院卷第\n    61頁），則被告上開所稱非無可能，基於罪疑唯輕原則，應\n    認被告之行竊時間非屬夜間；被告如附表一編號4 所示之犯\n    行，檢察官雖指訴劉昌碾有破壞門鎖之情，然並無提出證據\n    以實其說，本院亦查無有積極證據證明劉昌碾有毀壞門鎖一\n    節，且檢察官亦漏未斟酌劉昌碾於偵訊時所證其與被告有翻\n    越該住處圍牆及其有毀壞該住處3 樓陽台玻璃門等語（見偵\n    查卷(一)第73頁），然此等係屬竊盜加重條件之減少、增加，\n    尚不生變更起訴法條問題，附此敘明。被告與「阿文」間就\n    如附表一編號1 所示之犯行、被告與劉昌碾間就如附表一編\n    號2 至4 所示之犯行，均具犯意聯絡及行為分擔，均為共同\n    正犯。被告所犯如附表一編號1 至4 所示之犯行間，犯意各\n    別，行為互殊，應予分論併罰。另被告有如事實欄所示之前\n    案紀錄，於96年1 月5 日執行完畢乙節，有臺灣高等法院被\n    告前案紀錄表1 份在卷可參（見本院卷第17、18頁），其於\n    有期徒刑執行完畢後5 年內，故意再犯如附表一編號1 至4\n    所示有期徒刑以上之罪，均為累犯，所犯之罪皆應依刑法第\n    47條第1 項之規定加重其刑。爰審酌被告正值壯年，不思正\n    途賺取財物，竟與「阿文」、劉昌碾共同竊取他人財物，所\n    為非是，惟事後坦承犯行，態度尚無不良，暨其犯罪之動機\n    、目的、手段、素行、竊得財物之價值、部分遭竊財物已經\n    被害人領回等一切情狀，分別量處如主文所示之刑，並定其\n    應執行刑。\n據上論斷，應依刑事訴訟法第273 條之1 第1 項、第284 條之1\n、第299 條第1 項前段，行為時刑法第321 條第1 項第1 款、第\n2 款、第3 款，刑法第2 條第1 項前段、第28條、第51條第5 款\n、第47條第1 項，判決如主文。\n本案經檢察官潘國威到庭執行職務。\n中    華    民    國   100    年    7     月    12    日\n                  刑事第三庭    法  官  許嘉仁\n附表一：\n┌──┬────┬────┬───┬──────────┬──────────┬───────┐\n│編號│犯罪時間│犯罪地點│被害人│犯    罪    方    法│竊    取    物    品│查  獲  方  式│\n├──┼────┼────┼───┼──────────┼──────────┼───────┤\n│ 1  │99年6 月│屏東縣屏│李靜枝│被告、「阿文」踰越左│土地所有權狀、地籍謄│經警訪查得知被│\n│    │6 日上午│東市大連│      │揭被害人住處3 樓之窗│本、臺灣銀行套幣50套│告駕駛所租賃之│\n│    │5 時許  │路11巷3 │      │戶後，入內徒手竊取得│、黃金嬰兒送禮1 盒  │車牌號碼ZZ-837│\n│    │        │弄214 號│      │手                  │                    │1 號黑色汽車行│\n│    │        │住處    │      │                    │                    │竊後，向小馬小│\n│    │        │        │      │                    │                    │客車租賃股份有│\n│    │        │        │      │                    │                    │限公司調閱租用│\n│    │        │        │      │                    │                    │上開汽車之承租│\n│    │        │        │      │                    │                    │人資料，循線查│\n│    │        │        │      │                    │                    │悉左情        │\n│    ├────┴────┴───┴──────────┴──────────┴───────┤\n│    │主文：趙能賢共同犯踰越安全設備竊盜罪，累犯，處有期徒刑拾月。                          │\n│    ├───────────────────────────────────────────┤\n│    │證據：                                                                                │\n│    │被告於警詢、偵訊時之自白（見警卷(二)第11頁；警卷(三)第3 至5 頁；偵查卷(一)第112 至114 頁）│\n│    │  。                                                                                  │\n│    │證人即被害人李靜枝於警詢時之證述（見警卷(二)第31頁、第31頁背面；警卷(三)第1-1 、2 頁）。│\n│    │贓物認領保管單1 份（見警卷(二)第54頁）。                                              │\n│    │汽車出租單1 份（見警卷(三)第15頁）。                                                  │\n│    │車籍查詢基本資料詳細畫面1 份（見警卷(三)第14頁）。                                    │\n│    │偵查報告1 份（見警卷(三)第1 頁）。                                                    │\n│    │日出日末時刻表1 份（見本院卷第61頁）。                                              │\n├──┼────┬────┬───┬──────────┬──────────┬───────┤\n│編號│犯罪時間│犯罪地點│被害人│犯    罪    方    法│竊    取    物    品│查  獲  方  式│\n├──┼────┼────┼───┼──────────┼──────────┼───────┤\n│ 2  │99年7 月│屏東縣屏│鄭志嬿│被告以其所攜帶客觀上│車牌號碼P4-8570 號自│嗣於99年7 月20│\n│    │10日下午│東市和平│      │足供兇器使用之T 字扳│小客車1 部（內含駕照│日下午4 時30分│\n│    │2 時許  │路之中正│      │手1 支（未扣案）破壞│及保險卡各1 份）    │許，在屏東縣屏│\n│    │        │藝術館停│      │車牌號碼P4-8570 號自│                    │東市○○路42巷│\n│    │        │車場    │      │小客車之車鎖後竊取得│                    │25號之進成賓館│\n│    │        │        │      │手，劉昌碾則負責把風│                    │，為警查獲    │\n│    ├────┴────┴───┴──────────┴──────────┴───────┤\n│    │主文：趙能賢共同犯攜帶兇器竊盜罪，累犯，處有期徒刑捌月。                              │\n│    ├───────────────────────────────────────────┤\n│    │證據：                                                                                │\n│    │證人即被害人鄭志嬿於警詢時之證述（見警卷(二)第32頁、第32頁背面）。                    │\n│    │證人即共犯劉昌碾於警詢、偵訊時之證述（見偵查卷(一)第78、79、126 、127 頁、第89頁背面）│\n│    │  。                                                                                  │\n│    │贓物認領保管單1 份（見警卷(二)第53頁）。                                              │\n│    │車輛詳細資料報表1 份（見警卷(二)第57頁）。                                            │\n│    │照片26張（見警卷(二)第59至61頁；偵查卷(一)第95頁）。                                    │\n├──┼────┬────┬───┬──────────┬──────────┬───────┤\n│編號│犯罪時間│犯罪地點│被害人│犯    罪    方    法│竊    取    物    品│查  獲  方  式│\n├──┼────┼────┼───┼──────────┼──────────┼───────┤\n│ 3  │99年7 月│屏東縣屏│曾美惠│被告、劉昌碾夜間侵入│MP4 隨身聽1 臺、長江│嗣於99年7 月20│\n│    │18日凌晨│東市公園│      │左揭被害人住處後，徒│七號行動電話1 支、co│日下午4 時30分│\n│    │2 時許  │東路22號│      │手竊取得手          │ntax牌相機1 臺、零錢│許，在屏東縣屏│\n│    │        │住處    │      │                    │（新臺幣〈下同〉1 元│東市○○路42巷│\n│    │        │        │      │                    │硬幣333 枚、5 元硬幣│25號之進成賓館│\n│    │        │        │      │                    │49枚、50元硬幣4 枚）│，為警查獲    │\n│    ├────┴────┴───┴──────────┴──────────┴───────┤\n│    │主文：趙能賢共同犯夜間侵入住宅竊盜罪，累犯，處有期徒刑捌月。                          │\n│    ├───────────────────────────────────────────┤\n│    │證據：                                                                                │\n│    │證人即被害人曾美惠於警詢時之證述（見警卷(二)第26至30頁）。                            │\n│    │證人即共犯劉昌碾於警詢、偵訊時之證述（見偵查卷(一)第73、78、91頁、第90頁背面）。      │\n│    │贓物認領保管單1 份（見警卷(二)第56頁）。                                              │\n│    │照片27張（見警卷(二)第59至61頁；偵查卷(一)第97頁）。                                    │\n│    │公務電話紀錄1 份（見本院卷第72頁）。                                                │\n├──┼────┬────┬───┬──────────┬──────────┬───────┤\n│編號│犯罪時間│犯罪地點│被害人│犯    罪    方    法│竊    取    物    品│查  獲  方  式│\n├──┼────┼────┼───┼──────────┼──────────┼───────┤\n│ 4  │99年7 月│屏東縣屏│林明和│被告、劉昌碾夜間踰越│coach 皮包1 個、鑽石│嗣於99年7 月20│\n│    │18日凌晨│東市莊敬│      │左揭被害人住處圍牆，│戒指2 只、電腦1 臺、│日下午4 時30分│\n│    │3 時許  │街2 段89│      │由劉昌碾攜帶客觀上足│米奇造型黃金1 只、珍│許，在屏東縣屏│\n│    │        │巷45號住│      │供兇器使用之噴槍及螺│珠項鍊3 條、首飾1 包│東市○○路42巷│\n│    │        │處      │      │絲起子各1 支（均未扣│、LV皮夾1 個、耳環1 │25號之進成賓館│\n│    │        │        │      │案），並以上開噴槍破│對、行李箱1 個、車牌│，為警查獲    │\n│    │        │        │      │壞左揭被害人住處3 樓│號碼UP-9535 號自小客│              │\n│    │        │        │      │陽臺玻璃門，入內竊取│車1 部              │              │\n│    │        │        │      │得手，被告則負責把風│                    │              │\n│    ├────┴────┴───┴──────────┴──────────┴───────┤\n│    │主文：趙能賢共同犯攜帶兇器、踰越牆垣、毀壞安全設備、夜間侵入住宅竊盜罪，累犯，處有期徒│\n│    │      刑拾壹月。                                                                      │\n│    ├───────────────────────────────────────────┤\n│    │證據：                                                                                │\n│    │證人即被害人林明和於警詢時之證述（見警卷(二)第24至25頁；偵查卷(一)第85至86頁）。        │\n│    │證人即共犯劉昌碾於警詢、偵訊時之證述（見偵查卷(一)第73至74、90頁、第90頁背面） 。     │\n│    │贓物認領保管單1 份（見警卷(二)第55頁）。                                              │\n│    │車輛詳細資料1 份（見警卷(二)第58頁）。                                                │\n│    │照片27張（見警卷(二)第59至61頁；偵查卷(一)第96頁）。                                    │\n└──┴───────────────────────────────────────────┘\n附表二：\n┌──────┬───────────┬───────────┬────────────┐\n│相關法律規定│行為時（修正前）之規定│裁判時（修正後）之規定│本案具體適用後之比較結果│\n├──────┼───────────┼───────────┼────────────┤\n│刑法第321 條│犯竊盜罪而有左列情形之│犯竊盜罪而有下列情形之│修正後之規定刪除「夜間」│\n│第1 項第1 款│一者，處6 月以上、5 年│一者，處6 月以上、5 年│之構成要件，並於法定刑增│\n│第2 款、第3 │以下有期徒刑：        │以下有期徒刑，得併科新│訂「得併科新臺幣10萬元以│\n│款          │一、於夜間侵入住宅或有│臺幣10萬元以下罰金：  │下罰金」，以行為時之規定│\n│            │    人居住之建築物、船│一、侵入住宅或有人居住│較有利於被告。          │\n│            │    艦或隱匿其內而犯之│    之建築物、船艦或隱│                        │\n│            │    者。              │    匿其內而犯之者。  │                        │\n│            │二、毀越門扇、牆垣或其│二、毀越門扇、牆垣或其│                        │\n│            │    他安全設備而犯之者│    他安全設備而犯之者│                        │\n│            │    。                │    。                │                        │\n│            │三、攜帶兇器而犯之者。│三、攜帶兇器而犯之者。│                        │\n└──────┴───────────┴───────────┴────────────┘\n以上正本證明與原本無異。\n如不服本判決應於收受判決後10日內向本院提出上訴書狀，並\n應敘述具體理由；其未敘述上訴理由者，應於上訴期間屆滿後\n20日內向本院補提理由書（均須按他造當事人之人數附繕本）\n「切勿逕送上級法院」。\n中    華    民    國   100    年    7     月    12    日\n                                書記官  劉淑蓉\n附錄本案論罪科刑之法條：\n行為時中華民國刑法第321條第1項第1款、第2款、第3款\n行為時中華民國刑法第321條\n（加重竊盜罪）\n犯竊盜罪而有左列情形之一者，處 6 月以上、 5 年以下有期徒\n刑：\n一  於夜間侵入住宅或有人居住之建築物、船艦或隱匿其內而犯\n    之者。\n二  毀越門扇、牆垣或其他安全設備而犯之者。\n三  攜帶兇器而犯之者。\n四  結夥三人以上而犯之者。\n五  乘火災、水災或其他災害之際而犯之者。\n六  在車站或埠頭而犯之者。\n前項之未遂犯罰之。",
  "structure": {
    "main": "趙能賢犯如附表一主文欄所示之罪，均累犯，各處如附表一主文\n欄所示之刑。應執行有期徒刑貳年拾月。",
    "fact": "一、趙能賢前因竊盜案件，經本院以93年度易字第507 號判決判\n    處有期徒刑1 年確定，於民國96年1 月5 日執行完畢。詎猶\n    不知悔改，竟與真實姓名、年籍不詳綽號「阿文」之成年男\n    子（下稱「阿文」）共同意圖為自己不法之所有，基於竊盜\n    之犯意聯絡，於如附表一編號1 所示之時間、地點，以如附\n    表一編號1 所示之方式，竊取如附表一編號1 所示之被害人\n    財物；又與劉昌碾（通緝中，到案後另行審結）共同意圖為\n    自己不法之所有，基於竊盜之犯意聯絡，於如附表一編號2\n    至4 所示之時間、地點，以如附表一編號2 至4 所示之方式\n    ，竊取如附表一編號2 至4 所示之被害人財物。嗣因如附表\n    一編號1 至4 所示之查獲方式，為警查獲，而悉上情。\n二、案經屏東縣政府警察局屏東分局、里港分局報告臺灣屏東地\n    方法院檢察署檢察官偵查起訴。",
    "reason": "一、上開犯罪事實，業經被告趙能賢於本院審理時坦承不諱（見\n    本院卷第65頁背面、第66頁），並有如附表一證據欄所示之\n    證據可資佐證，足認被告自白與事實相符。本案事證明確，\n    被告犯行洵堪認定，應依法論科。\n二、按被告行為後，如附表二所示之刑法第321 條第1 項第1 款\n    、第2 款、第3 款已於100 年1 月26日修正公布，於100 年\n    1 月28日施行，茲依規範行為後法律變更所生新舊法律比較\n    適用之準據法即刑法第2 條第1 項之規定，為「從舊從輕」\n    之比較（詳如附表二所示），因行為後之法律之法定刑較重\n    ，並未對其較有利，故應適用行為時即修正前之規定論處。\n三、按刑法第321 條第1 項第2 款規定將「門扇」、「牆垣」、\n    「其他安全設備」並列，而所謂「門扇」應專指門戶，即分\n    隔住宅或建築物內外之間之出入口大門而言。另所謂「其他\n    安全設備」，則指門扇、牆垣以外，依社會通常觀念足認為\n    防盜之一切設備而言，如門鎖、窗戶、房間門或通往陽臺之\n    門即屬之（最高法院45年臺上字第1443號判例、55年臺上字\n    第547 號判例意旨參照）；復按刑法第321 條第1 項第3 款\n    所稱兇器，其種類並無限制，凡客觀上足對人之生命、身體\n    、安全構成威脅，具有危險性之兇器均屬之，且祇須行竊時\n    攜帶此種具有危險性之兇器為已足，並不以攜帶之初有行兇\n    之意圖為必要（最高法院79年臺上字第5253號判例意旨參照\n    ），被告於為如附表一編號2 所示之竊盜犯行時所持有之T\n    字扳手固未扣案，然既得破壞車鎖，應屬金屬材質且質地堅\n    硬，而劉昌碾於為如附表一編號4 所示之竊盜犯行所持有之\n    噴槍、螺絲起子雖亦未扣案，然劉昌碾既得持該噴槍毀壞該\n    住處陽臺玻璃門，且一般而言，螺絲起子質地堅硬，則持上\n    開T 字扳手、噴槍、螺絲起子使用、揮擊當足以對人之生命\n    、身體、安全造成威脅，故上開T 字扳手、噴槍、螺絲起子\n    顯為具有危險性之兇器無訛。是核被告如附表一編號1 所為\n    ，係犯行為時刑法第321 條第1 項第2 款之踰越安全設備竊\n    盜罪；如附表一編號2 所為，係犯行為時刑法第321 條第1\n    項第3 款之攜帶兇器竊盜罪；如附表一編號3 所為，係犯行\n    為時刑法第321 條第1 項第1 款之夜間侵入住宅竊盜罪；如\n    附表一編號4 所為，則係犯行為時刑法第321 條第1 項第1\n    款、第2 款、第3 款之攜帶兇器、踰越牆垣、毀壞安全設備\n    、夜間侵入住宅竊盜罪。又被告如附表一編號1 所示之犯行\n    ，檢察官認被告有夜間侵入住宅之行為，然被告於警詢、偵\n    訊及本院審理時均陳稱其行竊之時間為99年6 月6 日上午5\n    時許，斯時已天亮等語（見警卷(三)第4 頁；偵查卷(一)第112\n    頁；本院卷第65頁背面），而99年6 月6 日之日出時刻為上\n    午5 時12分，有日出日沒時刻表1 份在卷可憑（見本院卷第\n    61頁），則被告上開所稱非無可能，基於罪疑唯輕原則，應\n    認被告之行竊時間非屬夜間；被告如附表一編號4 所示之犯\n    行，檢察官雖指訴劉昌碾有破壞門鎖之情，然並無提出證據\n    以實其說，本院亦查無有積極證據證明劉昌碾有毀壞門鎖一\n    節，且檢察官亦漏未斟酌劉昌碾於偵訊時所證其與被告有翻\n    越該住處圍牆及其有毀壞該住處3 樓陽台玻璃門等語（見偵\n    查卷(一)第73頁），然此等係屬竊盜加重條件之減少、增加，\n    尚不生變更起訴法條問題，附此敘明。被告與「阿文」間就\n    如附表一編號1 所示之犯行、被告與劉昌碾間就如附表一編\n    號2 至4 所示之犯行，均具犯意聯絡及行為分擔，均為共同\n    正犯。被告所犯如附表一編號1 至4 所示之犯行間，犯意各\n    別，行為互殊，應予分論併罰。另被告有如事實欄所示之前\n    案紀錄，於96年1 月5 日執行完畢乙節，有臺灣高等法院被\n    告前案紀錄表1 份在卷可參（見本院卷第17、18頁），其於\n    有期徒刑執行完畢後5 年內，故意再犯如附表一編號1 至4\n    所示有期徒刑以上之罪，均為累犯，所犯之罪皆應依刑法第\n    47條第1 項之規定加重其刑。爰審酌被告正值壯年，不思正\n    途賺取財物，竟與「阿文」、劉昌碾共同竊取他人財物，所\n    為非是，惟事後坦承犯行，態度尚無不良，暨其犯罪之動機\n    、目的、手段、素行、竊得財物之價值、部分遭竊財物已經\n    被害人領回等一切情狀，分別量處如主文所示之刑，並定其\n    應執行刑。\n據上論斷，應依刑事訴訟法第273 條之1 第1 項、第284 條之1\n、第299 條第1 項前段，行為時刑法第321 條第1 項第1 款、第\n2 款、第3 款，刑法第2 條第1 項前段、第28條、第51條第5 款\n、第47條第1 項，判決如主文。\n本案經檢察官潘國威到庭執行職務。\n中    華    民    國   100    年    7     月    12    日\n                  刑事第三庭    法  官  許嘉仁\n附表一：\n┌──┬────┬────┬───┬──────────┬──────────┬───────┐\n│編號│犯罪時間│犯罪地點│被害人│犯    罪    方    法│竊    取    物    品│查  獲  方  式│\n├──┼────┼────┼───┼──────────┼──────────┼───────┤\n│ 1  │99年6 月│屏東縣屏│李靜枝│被告、「阿文」踰越左│土地所有權狀、地籍謄│經警訪查得知被│\n│    │6 日上午│東市大連│      │揭被害人住處3 樓之窗│本、臺灣銀行套幣50套│告駕駛所租賃之│\n│    │5 時許  │路11巷3 │      │戶後，入內徒手竊取得│、黃金嬰兒送禮1 盒  │車牌號碼ZZ-837│\n│    │        │弄214 號│      │手                  │                    │1 號黑色汽車行│\n│    │        │住處    │      │                    │                    │竊後，向小馬小│\n│    │        │        │      │                    │                    │客車租賃股份有│\n│    │        │        │      │                    │                    │限公司調閱租用│\n│    │        │        │      │                    │                    │上開汽車之承租│\n│    │        │        │      │                    │                    │人資料，循線查│\n│    │        │        │      │                    │                    │悉左情        │\n│    ├────┴────┴───┴──────────┴──────────┴───────┤\n│    │主文：趙能賢共同犯踰越安全設備竊盜罪，累犯，處有期徒刑拾月。                          │\n│    ├───────────────────────────────────────────┤\n│    │證據：                                                                                │\n│    │被告於警詢、偵訊時之自白（見警卷(二)第11頁；警卷(三)第3 至5 頁；偵查卷(一)第112 至114 頁）│\n│    │  。                                                                                  │\n│    │證人即被害人李靜枝於警詢時之證述（見警卷(二)第31頁、第31頁背面；警卷(三)第1-1 、2 頁）。│\n│    │贓物認領保管單1 份（見警卷(二)第54頁）。                                              │\n│    │汽車出租單1 份（見警卷(三)第15頁）。                                                  │\n│    │車籍查詢基本資料詳細畫面1 份（見警卷(三)第14頁）。                                    │\n│    │偵查報告1 份（見警卷(三)第1 頁）。                                                    │\n│    │日出日末時刻表1 份（見本院卷第61頁）。                                              │\n├──┼────┬────┬───┬──────────┬──────────┬───────┤\n│編號│犯罪時間│犯罪地點│被害人│犯    罪    方    法│竊    取    物    品│查  獲  方  式│\n├──┼────┼────┼───┼──────────┼──────────┼───────┤\n│ 2  │99年7 月│屏東縣屏│鄭志嬿│被告以其所攜帶客觀上│車牌號碼P4-8570 號自│嗣於99年7 月20│\n│    │10日下午│東市和平│      │足供兇器使用之T 字扳│小客車1 部（內含駕照│日下午4 時30分│\n│    │2 時許  │路之中正│      │手1 支（未扣案）破壞│及保險卡各1 份）    │許，在屏東縣屏│\n│    │        │藝術館停│      │車牌號碼P4-8570 號自│                    │東市○○路42巷│\n│    │        │車場    │      │小客車之車鎖後竊取得│                    │25號之進成賓館│\n│    │        │        │      │手，劉昌碾則負責把風│                    │，為警查獲    │\n│    ├────┴────┴───┴──────────┴──────────┴───────┤\n│    │主文：趙能賢共同犯攜帶兇器竊盜罪，累犯，處有期徒刑捌月。                              │\n│    ├───────────────────────────────────────────┤\n│    │證據：                                                                                │\n│    │證人即被害人鄭志嬿於警詢時之證述（見警卷(二)第32頁、第32頁背面）。                    │\n│    │證人即共犯劉昌碾於警詢、偵訊時之證述（見偵查卷(一)第78、79、126 、127 頁、第89頁背面）│\n│    │  。                                                                                  │\n│    │贓物認領保管單1 份（見警卷(二)第53頁）。                                              │\n│    │車輛詳細資料報表1 份（見警卷(二)第57頁）。                                            │\n│    │照片26張（見警卷(二)第59至61頁；偵查卷(一)第95頁）。                                    │\n├──┼────┬────┬───┬──────────┬──────────┬───────┤\n│編號│犯罪時間│犯罪地點│被害人│犯    罪    方    法│竊    取    物    品│查  獲  方  式│\n├──┼────┼────┼───┼──────────┼──────────┼───────┤\n│ 3  │99年7 月│屏東縣屏│曾美惠│被告、劉昌碾夜間侵入│MP4 隨身聽1 臺、長江│嗣於99年7 月20│\n│    │18日凌晨│東市公園│      │左揭被害人住處後，徒│七號行動電話1 支、co│日下午4 時30分│\n│    │2 時許  │東路22號│      │手竊取得手          │ntax牌相機1 臺、零錢│許，在屏東縣屏│\n│    │        │住處    │      │                    │（新臺幣〈下同〉1 元│東市○○路42巷│\n│    │        │        │      │                    │硬幣333 枚、5 元硬幣│25號之進成賓館│\n│    │        │        │      │                    │49枚、50元硬幣4 枚）│，為警查獲    │\n│    ├────┴────┴───┴──────────┴──────────┴───────┤\n│    │主文：趙能賢共同犯夜間侵入住宅竊盜罪，累犯，處有期徒刑捌月。                          │\n│    ├───────────────────────────────────────────┤\n│    │證據：                                                                                │\n│    │證人即被害人曾美惠於警詢時之證述（見警卷(二)第26至30頁）。                            │\n│    │證人即共犯劉昌碾於警詢、偵訊時之證述（見偵查卷(一)第73、78、91頁、第90頁背面）。      │\n│    │贓物認領保管單1 份（見警卷(二)第56頁）。                                              │\n│    │照片27張（見警卷(二)第59至61頁；偵查卷(一)第97頁）。                                    │\n│    │公務電話紀錄1 份（見本院卷第72頁）。                                                │\n├──┼────┬────┬───┬──────────┬──────────┬───────┤\n│編號│犯罪時間│犯罪地點│被害人│犯    罪    方    法│竊    取    物    品│查  獲  方  式│\n├──┼────┼────┼───┼──────────┼──────────┼───────┤\n│ 4  │99年7 月│屏東縣屏│林明和│被告、劉昌碾夜間踰越│coach 皮包1 個、鑽石│嗣於99年7 月20│\n│    │18日凌晨│東市莊敬│      │左揭被害人住處圍牆，│戒指2 只、電腦1 臺、│日下午4 時30分│\n│    │3 時許  │街2 段89│      │由劉昌碾攜帶客觀上足│米奇造型黃金1 只、珍│許，在屏東縣屏│\n│    │        │巷45號住│      │供兇器使用之噴槍及螺│珠項鍊3 條、首飾1 包│東市○○路42巷│\n│    │        │處      │      │絲起子各1 支（均未扣│、LV皮夾1 個、耳環1 │25號之進成賓館│\n│    │        │        │      │案），並以上開噴槍破│對、行李箱1 個、車牌│，為警查獲    │\n│    │        │        │      │壞左揭被害人住處3 樓│號碼UP-9535 號自小客│              │\n│    │        │        │      │陽臺玻璃門，入內竊取│車1 部              │              │\n│    │        │        │      │得手，被告則負責把風│                    │              │\n│    ├────┴────┴───┴──────────┴──────────┴───────┤\n│    │主文：趙能賢共同犯攜帶兇器、踰越牆垣、毀壞安全設備、夜間侵入住宅竊盜罪，累犯，處有期徒│\n│    │      刑拾壹月。                                                                      │\n│    ├───────────────────────────────────────────┤\n│    │證據：                                                                                │\n│    │證人即被害人林明和於警詢時之證述（見警卷(二)第24至25頁；偵查卷(一)第85至86頁）。        │\n│    │證人即共犯劉昌碾於警詢、偵訊時之證述（見偵查卷(一)第73至74、90頁、第90頁背面） 。     │\n│    │贓物認領保管單1 份（見警卷(二)第55頁）。                                              │\n│    │車輛詳細資料1 份（見警卷(二)第58頁）。                                                │\n│    │照片27張（見警卷(二)第59至61頁；偵查卷(一)第96頁）。                                    │\n└──┴───────────────────────────────────────────┘\n附表二：\n┌──────┬───────────┬───────────┬────────────┐\n│相關法律規定│行為時（修正前）之規定│裁判時（修正後）之規定│本案具體適用後之比較結果│\n├──────┼───────────┼───────────┼────────────┤\n│刑法第321 條│犯竊盜罪而有左列情形之│犯竊盜罪而有下列情形之│修正後之規定刪除「夜間」│\n│第1 項第1 款│一者，處6 月以上、5 年│一者，處6 月以上、5 年│之構成要件，並於法定刑增│\n│第2 款、第3 │以下有期徒刑：        │以下有期徒刑，得併科新│訂「得併科新臺幣10萬元以│\n│款          │一、於夜間侵入住宅或有│臺幣10萬元以下罰金：  │下罰金」，以行為時之規定│\n│            │    人居住之建築物、船│一、侵入住宅或有人居住│較有利於被告。          │\n│            │    艦或隱匿其內而犯之│    之建築物、船艦或隱│                        │\n│            │    者。              │    匿其內而犯之者。  │                        │\n│            │二、毀越門扇、牆垣或其│二、毀越門扇、牆垣或其│                        │\n│            │    他安全設備而犯之者│    他安全設備而犯之者│                        │\n│            │    。                │    。                │                        │\n│            │三、攜帶兇器而犯之者。│三、攜帶兇器而犯之者。│                        │\n└──────┴───────────┴───────────┴────────────┘\n以上正本證明與原本無異。\n如不服本判決應於收受判決後10日內向本院提出上訴書狀，並\n應敘述具體理由；其未敘述上訴理由者，應於上訴期間屆滿後\n20日內向本院補提理由書（均須按他造當事人之人數附繕本）\n「切勿逕送上級法院」。"
  },
  "search": "臺灣屏東地方法院刑事判決100年度易字第596號公訴人臺灣屏東地方法院檢察署檢察官被告趙能賢上列被告因竊盜案件，經檢察官提起公訴（99年度偵字第6968、9793號、99年度偵緝字第433號），被告於準備程序中，就被訴事實為有罪之陳述，本院告知其簡式審判程序之旨，聽取當事人意見後，裁定由受命法官獨任依簡式審判程序審理，茲判決如下：主文趙能賢犯如附表一主文欄所示之罪，均累犯，各處如附表一主文欄所示之刑。應執行有期徒刑貳年拾月。事實一、趙能賢前因竊盜案件，經本院以93年度易字第507號判決判處有期徒刑1年確定，於民國96年1月5日執行完畢。詎猶不知悔改，竟與真實姓名、年籍不詳綽號「阿文」之成年男子（下稱「阿文」）共同意圖為自己不法之所有，基於竊盜之犯意聯絡，於如附表一編號1所示之時間、地點，以如附表一編號1所示之方式，竊取如附表一編號1所示之被害人財物；又與劉昌碾（通緝中，到案後另行審結）共同意圖為自己不法之所有，基於竊盜之犯意聯絡，於如附表一編號2至4所示之時間、地點，以如附表一編號2至4所示之方式，竊取如附表一編號2至4所示之被害人財物。嗣因如附表一編號1至4所示之查獲方式，為警查獲，而悉上情。二、案經屏東縣政府警察局屏東分局、里港分局報告臺灣屏東地方法院檢察署檢察官偵查起訴。理由一、上開犯罪事實，業經被告趙能賢於本院審理時坦承不諱（見本院卷第65頁背面、第66頁），並有如附表一證據欄所示之證據可資佐證，足認被告自白與事實相符。本案事證明確，被告犯行洵堪認定，應依法論科。二、按被告行為後，如附表二所示之刑法第321條第1項第1款、第2款、第3款已於100年1月26日修正公布，於100年1月28日施行，茲依規範行為後法律變更所生新舊法律比較適用之準據法即刑法第2條第1項之規定，為「從舊從輕」之比較（詳如附表二所示），因行為後之法律之法定刑較重，並未對其較有利，故應適用行為時即修正前之規定論處。三、按刑法第321條第1項第2款規定將「門扇」、「牆垣」、「其他安全設備」並列，而所謂「門扇」應專指門戶，即分隔住宅或建築物內外之間之出入口大門而言。另所謂「其他安全設備」，則指門扇、牆垣以外，依社會通常觀念足認為防盜之一切設備而言，如門鎖、窗戶、房間門或通往陽臺之門即屬之（最高法院45年臺上字第1443號判例、55年臺上字第547號判例意旨參照）；復按刑法第321條第1項第3款所稱兇器，其種類並無限制，凡客觀上足對人之生命、身體、安全構成威脅，具有危險性之兇器均屬之，且祇須行竊時攜帶此種具有危險性之兇器為已足，並不以攜帶之初有行兇之意圖為必要（最高法院79年臺上字第5253號判例意旨參照），被告於為如附表一編號2所示之竊盜犯行時所持有之T字扳手固未扣案，然既得破壞車鎖，應屬金屬材質且質地堅硬，而劉昌碾於為如附表一編號4所示之竊盜犯行所持有之噴槍、螺絲起子雖亦未扣案，然劉昌碾既得持該噴槍毀壞該住處陽臺玻璃門，且一般而言，螺絲起子質地堅硬，則持上開T字扳手、噴槍、螺絲起子使用、揮擊當足以對人之生命、身體、安全造成威脅，故上開T字扳手、噴槍、螺絲起子顯為具有危險性之兇器無訛。是核被告如附表一編號1所為，係犯行為時刑法第321條第1項第2款之踰越安全設備竊盜罪；如附表一編號2所為，係犯行為時刑法第321條第1項第3款之攜帶兇器竊盜罪；如附表一編號3所為，係犯行為時刑法第321條第1項第1款之夜間侵入住宅竊盜罪；如附表一編號4所為，則係犯行為時刑法第321條第1項第1款、第2款、第3款之攜帶兇器、踰越牆垣、毀壞安全設備、夜間侵入住宅竊盜罪。又被告如附表一編號1所示之犯行，檢察官認被告有夜間侵入住宅之行為，然被告於警詢、偵訊及本院審理時均陳稱其行竊之時間為99年6月6日上午5時許，斯時已天亮等語（見警卷(三)第4頁；偵查卷(一)第112頁；本院卷第65頁背面），而99年6月6日之日出時刻為上午5時12分，有日出日沒時刻表1份在卷可憑（見本院卷第61頁），則被告上開所稱非無可能，基於罪疑唯輕原則，應認被告之行竊時間非屬夜間；被告如附表一編號4所示之犯行，檢察官雖指訴劉昌碾有破壞門鎖之情，然並無提出證據以實其說，本院亦查無有積極證據證明劉昌碾有毀壞門鎖一節，且檢察官亦漏未斟酌劉昌碾於偵訊時所證其與被告有翻越該住處圍牆及其有毀壞該住處3樓陽台玻璃門等語（見偵查卷(一)第73頁），然此等係屬竊盜加重條件之減少、增加，尚不生變更起訴法條問題，附此敘明。被告與「阿文」間就如附表一編號1所示之犯行、被告與劉昌碾間就如附表一編號2至4所示之犯行，均具犯意聯絡及行為分擔，均為共同正犯。被告所犯如附表一編號1至4所示之犯行間，犯意各別，行為互殊，應予分論併罰。另被告有如事實欄所示之前案紀錄，於96年1月5日執行完畢乙節，有臺灣高等法院被告前案紀錄表1份在卷可參（見本院卷第17、18頁），其於有期徒刑執行完畢後5年內，故意再犯如附表一編號1至4所示有期徒刑以上之罪，均為累犯，所犯之罪皆應依刑法第47條第1項之規定加重其刑。爰審酌被告正值壯年，不思正途賺取財物，竟與「阿文」、劉昌碾共同竊取他人財物，所為非是，惟事後坦承犯行，態度尚無不良，暨其犯罪之動機、目的、手段、素行、竊得財物之價值、部分遭竊財物已經被害人領回等一切情狀，分別量處如主文所示之刑，並定其應執行刑。據上論斷，應依刑事訴訟法第273條之1第1項、第284條之1、第299條第1項前段，行為時刑法第321條第1項第1款、第2款、第3款，刑法第2條第1項前段、第28條、第51條第5款、第47條第1項，判決如主文。本案經檢察官潘國威到庭執行職務。中華民國100年7月12日刑事第三庭法官許嘉仁附表一：┌──┬────┬────┬───┬──────────┬──────────┬───────┐│編號│犯罪時間│犯罪地點│被害人│犯罪方法│竊取物品│查獲方式│├──┼────┼────┼───┼──────────┼──────────┼───────┤│1│99年6月│屏東縣屏│李靜枝│被告、「阿文」踰越左│土地所有權狀、地籍謄│經警訪查得知被│││6日上午│東市大連││揭被害人住處3樓之窗│本、臺灣銀行套幣50套│告駕駛所租賃之│││5時許│路11巷3││戶後，入內徒手竊取得│、黃金嬰兒送禮1盒│車牌號碼ZZ-837││││弄214號││手││1號黑色汽車行││││住處││││竊後，向小馬小││││││││客車租賃股份有││││││││限公司調閱租用││││││││上開汽車之承租││││││││人資料，循線查││││││││悉左情││├────┴────┴───┴──────────┴──────────┴───────┤││主文：趙能賢共同犯踰越安全設備竊盜罪，累犯，處有期徒刑拾月。││├───────────────────────────────────────────┤││證據：│││被告於警詢、偵訊時之自白（見警卷(二)第11頁；警卷(三)第3至5頁；偵查卷(一)第112至114頁）│││。│││證人即被害人李靜枝於警詢時之證述（見警卷(二)第31頁、第31頁背面；警卷(三)第1-1、2頁）。│││贓物認領保管單1份（見警卷(二)第54頁）。│││汽車出租單1份（見警卷(三)第15頁）。│││車籍查詢基本資料詳細畫面1份（見警卷(三)第14頁）。│││偵查報告1份（見警卷(三)第1頁）。│││日出日末時刻表1份（見本院卷第61頁）。│├──┼────┬────┬───┬──────────┬──────────┬───────┤│編號│犯罪時間│犯罪地點│被害人│犯罪方法│竊取物品│查獲方式│├──┼────┼────┼───┼──────────┼──────────┼───────┤│2│99年7月│屏東縣屏│鄭志嬿│被告以其所攜帶客觀上│車牌號碼P4-8570號自│嗣於99年7月20│││10日下午│東市和平││足供兇器使用之T字扳│小客車1部（內含駕照│日下午4時30分│││2時許│路之中正││手1支（未扣案）破壞│及保險卡各1份）│許，在屏東縣屏││││藝術館停││車牌號碼P4-8570號自││東市○○路42巷││││車場││小客車之車鎖後竊取得││25號之進成賓館││││││手，劉昌碾則負責把風││，為警查獲││├────┴────┴───┴──────────┴──────────┴───────┤││主文：趙能賢共同犯攜帶兇器竊盜罪，累犯，處有期徒刑捌月。││├───────────────────────────────────────────┤││證據：│││證人即被害人鄭志嬿於警詢時之證述（見警卷(二)第32頁、第32頁背面）。│││證人即共犯劉昌碾於警詢、偵訊時之證述（見偵查卷(一)第78、79、126、127頁、第89頁背面）│││。│││贓物認領保管單1份（見警卷(二)第53頁）。│││車輛詳細資料報表1份（見警卷(二)第57頁）。│││照片26張（見警卷(二)第59至61頁；偵查卷(一)第95頁）。│├──┼────┬────┬───┬──────────┬──────────┬───────┤│編號│犯罪時間│犯罪地點│被害人│犯罪方法│竊取物品│查獲方式│├──┼────┼────┼───┼──────────┼──────────┼───────┤│3│99年7月│屏東縣屏│曾美惠│被告、劉昌碾夜間侵入│MP4隨身聽1臺、長江│嗣於99年7月20│││18日凌晨│東市公園││左揭被害人住處後，徒│七號行動電話1支、co│日下午4時30分│││2時許│東路22號││手竊取得手│ntax牌相機1臺、零錢│許，在屏東縣屏││││住處│││（新臺幣〈下同〉1元│東市○○路42巷│││││││硬幣333枚、5元硬幣│25號之進成賓館│││││││49枚、50元硬幣4枚）│，為警查獲││├────┴────┴───┴──────────┴──────────┴───────┤││主文：趙能賢共同犯夜間侵入住宅竊盜罪，累犯，處有期徒刑捌月。││├───────────────────────────────────────────┤││證據：│││證人即被害人曾美惠於警詢時之證述（見警卷(二)第26至30頁）。│││證人即共犯劉昌碾於警詢、偵訊時之證述（見偵查卷(一)第73、78、91頁、第90頁背面）。│││贓物認領保管單1份（見警卷(二)第56頁）。│││照片27張（見警卷(二)第59至61頁；偵查卷(一)第97頁）。│││公務電話紀錄1份（見本院卷第72頁）。│├──┼────┬────┬───┬──────────┬──────────┬───────┤│編號│犯罪時間│犯罪地點│被害人│犯罪方法│竊取物品│查獲方式│├──┼────┼────┼───┼──────────┼──────────┼───────┤│4│99年7月│屏東縣屏│林明和│被告、劉昌碾夜間踰越│coach皮包1個、鑽石│嗣於99年7月20│││18日凌晨│東市莊敬││左揭被害人住處圍牆，│戒指2只、電腦1臺、│日下午4時30分│││3時許│街2段89││由劉昌碾攜帶客觀上足│米奇造型黃金1只、珍│許，在屏東縣屏││││巷45號住││供兇器使用之噴槍及螺│珠項鍊3條、首飾1包│東市○○路42巷││││處││絲起子各1支（均未扣│、LV皮夾1個、耳環1│25號之進成賓館││││││案），並以上開噴槍破│對、行李箱1個、車牌│，為警查獲││││││壞左揭被害人住處3樓│號碼UP-9535號自小客│││││││陽臺玻璃門，入內竊取│車1部│││││││得手，被告則負責把風││││├────┴────┴───┴──────────┴──────────┴───────┤││主文：趙能賢共同犯攜帶兇器、踰越牆垣、毀壞安全設備、夜間侵入住宅竊盜罪，累犯，處有期徒│││刑拾壹月。││├───────────────────────────────────────────┤││證據：│││證人即被害人林明和於警詢時之證述（見警卷(二)第24至25頁；偵查卷(一)第85至86頁）。│││證人即共犯劉昌碾於警詢、偵訊時之證述（見偵查卷(一)第73至74、90頁、第90頁背面）。│││贓物認領保管單1份（見警卷(二)第55頁）。│││車輛詳細資料1份（見警卷(二)第58頁）。│││照片27張（見警卷(二)第59至61頁；偵查卷(一)第96頁）。│└──┴───────────────────────────────────────────┘附表二：┌──────┬───────────┬───────────┬────────────┐│相關法律規定│行為時（修正前）之規定│裁判時（修正後）之規定│本案具體適用後之比較結果│├──────┼───────────┼───────────┼────────────┤│刑法第321條│犯竊盜罪而有左列情形之│犯竊盜罪而有下列情形之│修正後之規定刪除「夜間」││第1項第1款│一者，處6月以上、5年│一者，處6月以上、5年│之構成要件，並於法定刑增││第2款、第3│以下有期徒刑：│以下有期徒刑，得併科新│訂「得併科新臺幣10萬元以││款│一、於夜間侵入住宅或有│臺幣10萬元以下罰金：│下罰金」，以行為時之規定│││人居住之建築物、船│一、侵入住宅或有人居住│較有利於被告。│││艦或隱匿其內而犯之│之建築物、船艦或隱││││者。│匿其內而犯之者。││││二、毀越門扇、牆垣或其│二、毀越門扇、牆垣或其││││他安全設備而犯之者│他安全設備而犯之者││││。│。││││三、攜帶兇器而犯之者。│三、攜帶兇器而犯之者。││└──────┴───────────┴───────────┴────────────┘以上正本證明與原本無異。如不服本判決應於收受判決後10日內向本院提出上訴書狀，並應敘述具體理由；其未敘述上訴理由者，應於上訴期間屆滿後20日內向本院補提理由書（均須按他造當事人之人數附繕本）「切勿逕送上級法院」。中華民國100年7月12日書記官劉淑蓉附錄本案論罪科刑之法條：行為時中華民國刑法第321條第1項第1款、第2款、第3款行為時中華民國刑法第321條（加重竊盜罪）犯竊盜罪而有左列情形之一者，處6月以上、5年以下有期徒刑：一於夜間侵入住宅或有人居住之建築物、船艦或隱匿其內而犯之者。二毀越門扇、牆垣或其他安全設備而犯之者。三攜帶兇器而犯之者。四結夥三人以上而犯之者。五乘火災、水災或其他災害之際而犯之者。六在車站或埠頭而犯之者。前項之未遂犯罰之。",
  "characters": {
    "judges": [
      "許嘉仁"
    ],
    "prosecutors": [
      "潘國威"
    ],
    "lawyers": [

    ],
    "clerks": [
      "劉淑蓉"
    ],
    "plaintiffs": [

    ],
    "defendants": [
      "趙能賢"
    ],
    "prosecutor_office": [
      "臺灣屏東地方法院檢察署檢察官"
    ],
    "creditors": [

    ],
    "debtors": [

    ],
    "judicial_associate_officer": [

    ]
  },
  "adjudged_at": "2011-07-12",
  "created_at": "2016-02-14 02:43:05",
  "updated_at": "2016-02-14 02:43:05"
}