{
  "identify": "PTD-100-簡上-104-20110713-1",
  "court": {
    "name": "臺灣屏東地方法院",
    "code": "PTD"
  },
  "division": {
    "name": "刑事",
    "code": "M"
  },
  "year": 100,
  "word": "簡上",
  "number": "104",
  "jcheck": "1",
  "reason": "違反毒品危害防制條例",
  "content": "臺灣屏東地方法院刑事判決      100年度簡上字第104號\n上  訴  人  石定萍\n即  被  告\n上列上訴人因違反毒品危害防制條例案件，不服本院100 年度簡\n字第547 號中華民國100 年4 月28日刑事簡易判決（100 年度毒\n偵字第239號），提起上訴，本院判決如下：\n    主  文\n上訴駁回。\n    事實及理由\n一、上訴人即被告之犯罪事實，如本院刑事簡易判決書所載（如\n    附件）。\n二、被告雖經合法通知，未到庭陳述，惟據其前於警詢中所述及\n    上訴狀所載，被告否認有施用甲基安非他命，並辯稱係因服\n    用藥物，以致尿液檢測呈甲基安非他命之陽性反應等語。然\n    被告經警採尿檢測結果，確呈安非他命及甲基安非他命之陽\n    性反應，有如刑事簡易判決書所載之證據可稽。被告雖稱其\n    有服用藥物，致尿液呈甲基安非他命及安非他命之反應，但\n    對於係因服用何種藥物所致，被告先於警詢中辯稱，最近感\n    冒服用感冒藥（國安感冒藥水及三支雨傘標感冒藥），但於\n    上訴狀中則稱，係因「長期鼻病」服用感冒及「退燒」藥，\n    且因患有糖尿病、高血壓、慢性胰臟炎，每日需服用及注射\n    大量藥物等語，但未曾提出相關之診斷證明及藥品名稱，且\n    究其所稱服用之藥物，及服用之原因，亦顯有前後矛盾情形\n    ，已難遽採；再就被告於警詢中所稱，因服用國安感冒藥水\n    及三支雨傘標感冒藥，以致尿液呈甲基安非他命及安非他命\n    反應一節，經行政院衛生署食品藥物管理局函釋：「行政衛\n    生署許可上市之藥品，均不含安非他命、甲基安非他命，服\n    用旨揭之藥品（國安感冒糖漿及三支雨傘標友露安感冒糖漿\n    ）後，不會代謝出安非他命及甲基安非他命。惟旨揭藥品成\n    分均含有甲基麻黃鹼，口服甲基麻黃鹼後24小時內，約有施\n    用劑量之32% 以原態由尿液排出，服用含該成分製劑後，其\n    尿液以免疫學方法進行初步篩檢，或可能造成甲基安非他命\n    偽陽性反應，但行政院衛生署認可之濫用藥物尿液檢驗機構\n    ，依規定須以氣相層析質譜儀進行確認檢驗，故結果不致呈\n    現甲基安非他命陽性反應」（該局99年10月14日FDA 管字第\n    0990061551號函），有該函可憑，而該被告之尿液係經由行\n    政院衛生署認可之濫用藥物尿液檢驗機構即臺灣檢驗科技股\n    份有限公司，以氣相層析質譜儀法檢驗，確認呈安非他命及\n    甲基安非他命之反應，有該檢驗報告可憑，故被告所辯顯無\n    可採。且查原審科刑所依之毒品危害防制條例第10條第2 項\n    ，其法定刑為3 年以下有期徒刑，且被告為累犯，依法應加\n    重其刑，故其法定刑度為4 年6 月以下有期徒刑，而原審斟\n    酌被告犯罪情節，量處其有期徒刑4 月，並諭知如易科罰金\n    之折算標準，認事用法均無不當，量刑亦顯屬低度刑，本件\n    上訴自無理由，應予駁回。\n三、被告經合法通知，無正當理由不到庭，爰不待其陳述，逕為\n    一造辯論判決。\n據上論斷，應依刑事訴訟法第455 條之1 第3 項、第368 條、第\n371 條、第373 條，判決如主文。\n本案經檢察官許英輝到庭執行職務。\n中    華    民    國   100    年    7     月    13    日\n            刑事第四庭    審判長法  官  莊鎮遠\n                                法  官  江振源\n                                法  官  李謀榮\n以上正本證明與原本無異。\n不得上訴。\n中    華    民    國   100    年    7     月    13    日\n                                書記官  鍾思賢",
  "structure": {
    "main": "上訴駁回。",
    "fact": "一、上訴人即被告之犯罪事實，如本院刑事簡易判決書所載（如\n    附件）。\n二、被告雖經合法通知，未到庭陳述，惟據其前於警詢中所述及\n    上訴狀所載，被告否認有施用甲基安非他命，並辯稱係因服\n    用藥物，以致尿液檢測呈甲基安非他命之陽性反應等語。然\n    被告經警採尿檢測結果，確呈安非他命及甲基安非他命之陽\n    性反應，有如刑事簡易判決書所載之證據可稽。被告雖稱其\n    有服用藥物，致尿液呈甲基安非他命及安非他命之反應，但\n    對於係因服用何種藥物所致，被告先於警詢中辯稱，最近感\n    冒服用感冒藥（國安感冒藥水及三支雨傘標感冒藥），但於\n    上訴狀中則稱，係因「長期鼻病」服用感冒及「退燒」藥，\n    且因患有糖尿病、高血壓、慢性胰臟炎，每日需服用及注射\n    大量藥物等語，但未曾提出相關之診斷證明及藥品名稱，且\n    究其所稱服用之藥物，及服用之原因，亦顯有前後矛盾情形\n    ，已難遽採；再就被告於警詢中所稱，因服用國安感冒藥水\n    及三支雨傘標感冒藥，以致尿液呈甲基安非他命及安非他命\n    反應一節，經行政院衛生署食品藥物管理局函釋：「行政衛\n    生署許可上市之藥品，均不含安非他命、甲基安非他命，服\n    用旨揭之藥品（國安感冒糖漿及三支雨傘標友露安感冒糖漿\n    ）後，不會代謝出安非他命及甲基安非他命。惟旨揭藥品成\n    分均含有甲基麻黃鹼，口服甲基麻黃鹼後24小時內，約有施\n    用劑量之32% 以原態由尿液排出，服用含該成分製劑後，其\n    尿液以免疫學方法進行初步篩檢，或可能造成甲基安非他命\n    偽陽性反應，但行政院衛生署認可之濫用藥物尿液檢驗機構\n    ，依規定須以氣相層析質譜儀進行確認檢驗，故結果不致呈\n    現甲基安非他命陽性反應」（該局99年10月14日FDA 管字第\n    0990061551號函），有該函可憑，而該被告之尿液係經由行\n    政院衛生署認可之濫用藥物尿液檢驗機構即臺灣檢驗科技股\n    份有限公司，以氣相層析質譜儀法檢驗，確認呈安非他命及\n    甲基安非他命之反應，有該檢驗報告可憑，故被告所辯顯無\n    可採。且查原審科刑所依之毒品危害防制條例第10條第2 項\n    ，其法定刑為3 年以下有期徒刑，且被告為累犯，依法應加\n    重其刑，故其法定刑度為4 年6 月以下有期徒刑，而原審斟\n    酌被告犯罪情節，量處其有期徒刑4 月，並諭知如易科罰金\n    之折算標準，認事用法均無不當，量刑亦顯屬低度刑，本件\n    上訴自無理由，應予駁回。\n三、被告經合法通知，無正當理由不到庭，爰不待其陳述，逕為\n    一造辯論判決。\n據上論斷，應依刑事訴訟法第455 條之1 第3 項、第368 條、第\n371 條、第373 條，判決如主文。\n本案經檢察官許英輝到庭執行職務。",
    "reason": "一、上訴人即被告之犯罪事實，如本院刑事簡易判決書所載（如\n    附件）。\n二、被告雖經合法通知，未到庭陳述，惟據其前於警詢中所述及\n    上訴狀所載，被告否認有施用甲基安非他命，並辯稱係因服\n    用藥物，以致尿液檢測呈甲基安非他命之陽性反應等語。然\n    被告經警採尿檢測結果，確呈安非他命及甲基安非他命之陽\n    性反應，有如刑事簡易判決書所載之證據可稽。被告雖稱其\n    有服用藥物，致尿液呈甲基安非他命及安非他命之反應，但\n    對於係因服用何種藥物所致，被告先於警詢中辯稱，最近感\n    冒服用感冒藥（國安感冒藥水及三支雨傘標感冒藥），但於\n    上訴狀中則稱，係因「長期鼻病」服用感冒及「退燒」藥，\n    且因患有糖尿病、高血壓、慢性胰臟炎，每日需服用及注射\n    大量藥物等語，但未曾提出相關之診斷證明及藥品名稱，且\n    究其所稱服用之藥物，及服用之原因，亦顯有前後矛盾情形\n    ，已難遽採；再就被告於警詢中所稱，因服用國安感冒藥水\n    及三支雨傘標感冒藥，以致尿液呈甲基安非他命及安非他命\n    反應一節，經行政院衛生署食品藥物管理局函釋：「行政衛\n    生署許可上市之藥品，均不含安非他命、甲基安非他命，服\n    用旨揭之藥品（國安感冒糖漿及三支雨傘標友露安感冒糖漿\n    ）後，不會代謝出安非他命及甲基安非他命。惟旨揭藥品成\n    分均含有甲基麻黃鹼，口服甲基麻黃鹼後24小時內，約有施\n    用劑量之32% 以原態由尿液排出，服用含該成分製劑後，其\n    尿液以免疫學方法進行初步篩檢，或可能造成甲基安非他命\n    偽陽性反應，但行政院衛生署認可之濫用藥物尿液檢驗機構\n    ，依規定須以氣相層析質譜儀進行確認檢驗，故結果不致呈\n    現甲基安非他命陽性反應」（該局99年10月14日FDA 管字第\n    0990061551號函），有該函可憑，而該被告之尿液係經由行\n    政院衛生署認可之濫用藥物尿液檢驗機構即臺灣檢驗科技股\n    份有限公司，以氣相層析質譜儀法檢驗，確認呈安非他命及\n    甲基安非他命之反應，有該檢驗報告可憑，故被告所辯顯無\n    可採。且查原審科刑所依之毒品危害防制條例第10條第2 項\n    ，其法定刑為3 年以下有期徒刑，且被告為累犯，依法應加\n    重其刑，故其法定刑度為4 年6 月以下有期徒刑，而原審斟\n    酌被告犯罪情節，量處其有期徒刑4 月，並諭知如易科罰金\n    之折算標準，認事用法均無不當，量刑亦顯屬低度刑，本件\n    上訴自無理由，應予駁回。\n三、被告經合法通知，無正當理由不到庭，爰不待其陳述，逕為\n    一造辯論判決。\n據上論斷，應依刑事訴訟法第455 條之1 第3 項、第368 條、第\n371 條、第373 條，判決如主文。\n本案經檢察官許英輝到庭執行職務。"
  },
  "search": "臺灣屏東地方法院刑事判決100年度簡上字第104號上訴人石定萍即被告上列上訴人因違反毒品危害防制條例案件，不服本院100年度簡字第547號中華民國100年4月28日刑事簡易判決（100年度毒偵字第239號），提起上訴，本院判決如下：主文上訴駁回。事實及理由一、上訴人即被告之犯罪事實，如本院刑事簡易判決書所載（如附件）。二、被告雖經合法通知，未到庭陳述，惟據其前於警詢中所述及上訴狀所載，被告否認有施用甲基安非他命，並辯稱係因服用藥物，以致尿液檢測呈甲基安非他命之陽性反應等語。然被告經警採尿檢測結果，確呈安非他命及甲基安非他命之陽性反應，有如刑事簡易判決書所載之證據可稽。被告雖稱其有服用藥物，致尿液呈甲基安非他命及安非他命之反應，但對於係因服用何種藥物所致，被告先於警詢中辯稱，最近感冒服用感冒藥（國安感冒藥水及三支雨傘標感冒藥），但於上訴狀中則稱，係因「長期鼻病」服用感冒及「退燒」藥，且因患有糖尿病、高血壓、慢性胰臟炎，每日需服用及注射大量藥物等語，但未曾提出相關之診斷證明及藥品名稱，且究其所稱服用之藥物，及服用之原因，亦顯有前後矛盾情形，已難遽採；再就被告於警詢中所稱，因服用國安感冒藥水及三支雨傘標感冒藥，以致尿液呈甲基安非他命及安非他命反應一節，經行政院衛生署食品藥物管理局函釋：「行政衛生署許可上市之藥品，均不含安非他命、甲基安非他命，服用旨揭之藥品（國安感冒糖漿及三支雨傘標友露安感冒糖漿）後，不會代謝出安非他命及甲基安非他命。惟旨揭藥品成分均含有甲基麻黃鹼，口服甲基麻黃鹼後24小時內，約有施用劑量之32%以原態由尿液排出，服用含該成分製劑後，其尿液以免疫學方法進行初步篩檢，或可能造成甲基安非他命偽陽性反應，但行政院衛生署認可之濫用藥物尿液檢驗機構，依規定須以氣相層析質譜儀進行確認檢驗，故結果不致呈現甲基安非他命陽性反應」（該局99年10月14日FDA管字第0990061551號函），有該函可憑，而該被告之尿液係經由行政院衛生署認可之濫用藥物尿液檢驗機構即臺灣檢驗科技股份有限公司，以氣相層析質譜儀法檢驗，確認呈安非他命及甲基安非他命之反應，有該檢驗報告可憑，故被告所辯顯無可採。且查原審科刑所依之毒品危害防制條例第10條第2項，其法定刑為3年以下有期徒刑，且被告為累犯，依法應加重其刑，故其法定刑度為4年6月以下有期徒刑，而原審斟酌被告犯罪情節，量處其有期徒刑4月，並諭知如易科罰金之折算標準，認事用法均無不當，量刑亦顯屬低度刑，本件上訴自無理由，應予駁回。三、被告經合法通知，無正當理由不到庭，爰不待其陳述，逕為一造辯論判決。據上論斷，應依刑事訴訟法第455條之1第3項、第368條、第371條、第373條，判決如主文。本案經檢察官許英輝到庭執行職務。中華民國100年7月13日刑事第四庭審判長法官莊鎮遠法官江振源法官李謀榮以上正本證明與原本無異。不得上訴。中華民國100年7月13日書記官鍾思賢",
  "characters": {
    "judges": [
      "莊鎮遠",
      "江振源",
      "李謀榮"
    ],
    "prosecutors": [
      "許英輝"
    ],
    "lawyers": [

    ],
    "clerks": [

    ],
    "plaintiffs": [

    ],
    "defendants": [
      "上列上訴人因違反毒品危害防制條例案件"
    ],
    "prosecutor_office": [

    ],
    "creditors": [

    ],
    "debtors": [

    ],
    "judicial_associate_officer": [

    ]
  },
  "adjudged_at": "2011-07-13",
  "created_at": "2016-02-14 02:55:48",
  "updated_at": "2016-02-14 02:55:48"
}