{
  "identify": "SLD-100-聲-1191-20110713-1",
  "court": {
    "name": "臺灣士林地方法院",
    "code": "SLD"
  },
  "division": {
    "name": "刑事",
    "code": "M"
  },
  "year": 100,
  "word": "聲",
  "number": "1191",
  "jcheck": "1",
  "reason": "宣告沒收",
  "content": "臺灣士林地方法院刑事裁定             100年度聲字第1191號\n聲  請  人  臺灣士林地方法院檢察署檢察官\n被      告  高青雲\n上列被告因妨害自由案件，經檢察官聲請宣告沒收（100 年度執\n聲字第770 號、97年度緩字第305 號），本院裁定如下：\n    主  文\n扣案之門號0000000000號ＮＯＫＩＡ廠牌手機壹支（含SIM 卡壹\n張）沒收。\n    理  由\n一、按檢察官依刑事訴訟法第二百五十三條或第二百五十三條之\n    一為不起訴或緩起訴之處分者，對供犯罪所用、供犯罪預備\n    或因犯罪所得之物，以屬於被告者為限，得單獨聲請法院宣\n    告沒收，刑事訴訟法第二百五十九條之一定有明文。\n二、本件聲請意旨略以：被告高青雲涉犯妨害自由案件，業經臺\n    灣士林地方法院檢察署檢察官以96年度偵字第10735 號為緩\n    起訴處分確定。而扣案之門號0000000000號ＮＯＫＩＡ廠牌\n    手機壹支（含SIM 卡壹張），為被告所有供犯罪所用之物，\n    爰依上開規定聲請宣告沒收等語。\n三、經查，被告涉犯妨害自由案件，業經臺灣士林地方法院檢察\n    署檢察官以96年度偵字第10735 號為緩起訴處分確定，有緩\n    起訴書一份在卷可稽。而扣案之門號000000000 號ＮＯＫＩ\n    Ａ廠牌手機壹支（含SIM 卡壹張），為被告所有供犯罪所用\n    之物，此亦據被告供承在卷，從而，聲請人聲請宣告沒收如\n    主文所示之物，核無不合，爰依首揭條文規定，裁定如主文\n    。\n中    華    民    國   100    年    7     月    13    日\n                  刑事第五庭法  官  徐文瑞\n以上正本證明與原本無異。\n如不服本裁定應於送達後5日內向本院提出抗告狀。\n                            書記官  桂大永\n中    華    民    國   100    年    7     月    15    日",
  "structure": {
    "main": "扣案之門號0000000000號ＮＯＫＩＡ廠牌手機壹支（含SIM 卡壹\n張）沒收。",
    "reason": "一、按檢察官依刑事訴訟法第二百五十三條或第二百五十三條之\n    一為不起訴或緩起訴之處分者，對供犯罪所用、供犯罪預備\n    或因犯罪所得之物，以屬於被告者為限，得單獨聲請法院宣\n    告沒收，刑事訴訟法第二百五十九條之一定有明文。\n二、本件聲請意旨略以：被告高青雲涉犯妨害自由案件，業經臺\n    灣士林地方法院檢察署檢察官以96年度偵字第10735 號為緩\n    起訴處分確定。而扣案之門號0000000000號ＮＯＫＩＡ廠牌\n    手機壹支（含SIM 卡壹張），為被告所有供犯罪所用之物，\n    爰依上開規定聲請宣告沒收等語。\n三、經查，被告涉犯妨害自由案件，業經臺灣士林地方法院檢察\n    署檢察官以96年度偵字第10735 號為緩起訴處分確定，有緩\n    起訴書一份在卷可稽。而扣案之門號000000000 號ＮＯＫＩ\n    Ａ廠牌手機壹支（含SIM 卡壹張），為被告所有供犯罪所用\n    之物，此亦據被告供承在卷，從而，聲請人聲請宣告沒收如\n    主文所示之物，核無不合，爰依首揭條文規定，裁定如主文\n    。"
  },
  "search": "臺灣士林地方法院刑事裁定100年度聲字第1191號聲請人臺灣士林地方法院檢察署檢察官被告高青雲上列被告因妨害自由案件，經檢察官聲請宣告沒收（100年度執聲字第770號、97年度緩字第305號），本院裁定如下：主文扣案之門號0000000000號ＮＯＫＩＡ廠牌手機壹支（含SIM卡壹張）沒收。理由一、按檢察官依刑事訴訟法第二百五十三條或第二百五十三條之一為不起訴或緩起訴之處分者，對供犯罪所用、供犯罪預備或因犯罪所得之物，以屬於被告者為限，得單獨聲請法院宣告沒收，刑事訴訟法第二百五十九條之一定有明文。二、本件聲請意旨略以：被告高青雲涉犯妨害自由案件，業經臺灣士林地方法院檢察署檢察官以96年度偵字第10735號為緩起訴處分確定。而扣案之門號0000000000號ＮＯＫＩＡ廠牌手機壹支（含SIM卡壹張），為被告所有供犯罪所用之物，爰依上開規定聲請宣告沒收等語。三、經查，被告涉犯妨害自由案件，業經臺灣士林地方法院檢察署檢察官以96年度偵字第10735號為緩起訴處分確定，有緩起訴書一份在卷可稽。而扣案之門號000000000號ＮＯＫＩＡ廠牌手機壹支（含SIM卡壹張），為被告所有供犯罪所用之物，此亦據被告供承在卷，從而，聲請人聲請宣告沒收如主文所示之物，核無不合，爰依首揭條文規定，裁定如主文。中華民國100年7月13日刑事第五庭法官徐文瑞以上正本證明與原本無異。如不服本裁定應於送達後5日內向本院提出抗告狀。書記官桂大永中華民國100年7月15日",
  "characters": {
    "judges": [
      "徐文瑞"
    ],
    "prosecutors": [

    ],
    "lawyers": [

    ],
    "clerks": [
      "桂大永"
    ],
    "plaintiffs": [

    ],
    "defendants": [
      "高青雲"
    ],
    "prosecutor_office": [
      "臺灣士林地方法院檢察署檢察官"
    ],
    "creditors": [

    ],
    "debtors": [

    ],
    "judicial_associate_officer": [

    ]
  },
  "adjudged_at": "2011-07-13",
  "created_at": "2016-02-14 02:49:21",
  "updated_at": "2016-02-14 02:49:21"
}