{
  "identify": "TPH-100-聲-2079-20110713-1",
  "court": {
    "name": "臺灣高等法院",
    "code": "TPH"
  },
  "division": {
    "name": "刑事",
    "code": "M"
  },
  "year": 100,
  "word": "聲",
  "number": "2079",
  "jcheck": "1",
  "reason": "保護管束",
  "content": "臺灣高等法院刑事裁定                 100年度聲字第2079號\n聲  請  人  臺灣高等法院檢察署檢察官\n受  刑  人  許世瑋\n上列聲請人因被告重傷害罪案件，聲請付保護管束（100年度執\n聲付字第693號），本院裁定如下：\n    主  文\n許世瑋假釋中付保護管束。\n    理  由\n一、聲請意旨略以：受刑人許世瑋因重傷害罪案件，經本院96年\n    度上訴字第1365號判處有期徒刑4年減為有期徒刑2年，並經\n    最高法院96年度台上字第6269號上訴駁回確定。於99年4月7\n    日送監執行，嗣經法務部於100年7月8日核准假釋在案，依\n    刑法第93條第2項規定假釋出獄者，在假釋中付保護管束，\n    爰依刑事訴訟法第481條第1項規定聲請裁定等語。\n二、本院審核法務部矯正司100年7月8日法授矯字第10001147931\n    號函及所附交付保護管束名冊，認聲請人之聲請為正當，爰\n    裁定如主文所示。\n據上論斷，應依刑事訴訟法第481條第1項，刑法第96條但書、第\n93條第2項，裁定如主文。\n中    華    民    國    100    年    7    月    13    日\n                  刑事第十一庭審判長法  官  許宗和\n                                    法  官  沈君玲\n                                    法  官  趙功恆\n以上正本證明與原本無異。\n如不服本裁定，應於收受送達後五日內向本院提出抗告狀。\n                                    書記官  周恩寧\n中    華    民    國   100    年    7     月    14    日",
  "structure": {
    "main": "許世瑋假釋中付保護管束。",
    "reason": "一、聲請意旨略以：受刑人許世瑋因重傷害罪案件，經本院96年\n    度上訴字第1365號判處有期徒刑4年減為有期徒刑2年，並經\n    最高法院96年度台上字第6269號上訴駁回確定。於99年4月7\n    日送監執行，嗣經法務部於100年7月8日核准假釋在案，依\n    刑法第93條第2項規定假釋出獄者，在假釋中付保護管束，\n    爰依刑事訴訟法第481條第1項規定聲請裁定等語。\n二、本院審核法務部矯正司100年7月8日法授矯字第10001147931\n    號函及所附交付保護管束名冊，認聲請人之聲請為正當，爰\n    裁定如主文所示。\n據上論斷，應依刑事訴訟法第481條第1項，刑法第96條但書、第\n93條第2項，裁定如主文。"
  },
  "search": "臺灣高等法院刑事裁定100年度聲字第2079號聲請人臺灣高等法院檢察署檢察官受刑人許世瑋上列聲請人因被告重傷害罪案件，聲請付保護管束（100年度執聲付字第693號），本院裁定如下：主文許世瑋假釋中付保護管束。理由一、聲請意旨略以：受刑人許世瑋因重傷害罪案件，經本院96年度上訴字第1365號判處有期徒刑4年減為有期徒刑2年，並經最高法院96年度台上字第6269號上訴駁回確定。於99年4月7日送監執行，嗣經法務部於100年7月8日核准假釋在案，依刑法第93條第2項規定假釋出獄者，在假釋中付保護管束，爰依刑事訴訟法第481條第1項規定聲請裁定等語。二、本院審核法務部矯正司100年7月8日法授矯字第10001147931號函及所附交付保護管束名冊，認聲請人之聲請為正當，爰裁定如主文所示。據上論斷，應依刑事訴訟法第481條第1項，刑法第96條但書、第93條第2項，裁定如主文。中華民國100年7月13日刑事第十一庭審判長法官許宗和法官沈君玲法官趙功恆以上正本證明與原本無異。如不服本裁定，應於收受送達後五日內向本院提出抗告狀。書記官周恩寧中華民國100年7月14日",
  "characters": {
    "judges": [
      "許宗和",
      "沈君玲",
      "趙功恆"
    ],
    "prosecutors": [

    ],
    "lawyers": [

    ],
    "clerks": [
      "周恩寧"
    ],
    "plaintiffs": [

    ],
    "defendants": [

    ],
    "prosecutor_office": [
      "臺灣高等法院檢察署檢察官"
    ],
    "creditors": [

    ],
    "debtors": [

    ],
    "judicial_associate_officer": [

    ]
  },
  "adjudged_at": "2011-07-13",
  "created_at": "2016-02-14 02:55:02",
  "updated_at": "2016-02-14 02:55:02"
}