{
  "identify": "TYD-100-桃簡-1896-20110726-1",
  "court": {
    "name": "臺灣桃園地方法院",
    "code": "TYD"
  },
  "division": {
    "name": "刑事",
    "code": "M"
  },
  "year": 100,
  "word": "桃簡",
  "number": "1896",
  "jcheck": "1",
  "reason": "妨害公務",
  "content": "臺灣桃園地方法院刑事簡易判決       100年度桃簡字第1896號\n聲  請  人  臺灣桃園地方法院檢察署檢察官\n被      告  傅子財\n上列被告因妨害公務案件，經檢察官聲請以簡易判決處刑(100年\n度偵字第15395號) ，本院判決如下:\n    主      文\n傅子財於公務員依法執行職務時，當場侮辱，累犯，處拘役伍拾\n日，如易科罰金，以新台幣壹仟元折算壹日。\n    事實及理由\n一、本件犯罪事實及證據，均引用檢察官聲請簡易判決處刑書\n    之記載( 如附件) 。\n二、核被告所為，係犯刑法第140 條第1 項之於公務員依法執行\n    職務時當場侮辱罪。又被告上開當場侮辱行為，雖係對於警\n    員3 人為之，惟因當場侮辱之妨害公務罪，所保護者為公務\n    員公務執行之國家法益，故僅成立1 罪。被告前受有如上開\n    附件犯罪事實欄所示之有期徒刑執行情形，此有臺灣高等法\n    院前案紀錄表1 份附卷可稽，其於有期徒刑執行完畢後，5\n    年以內故意再犯本件有期徒刑以上之罪，為累犯，應依刑法\n    第47條第1 項之規定加重其刑。爰審酌被告僅因不滿警員欲\n    依法對其實施盤查，即以言語辱罵警員，公然對公權力加以\n    挑釁之犯罪情節，及其所生危害非輕，惟犯後終能坦承犯行\n    ，態度尚可與其素行情形等一切情狀，量處如主文所示之刑\n    ，並諭知易科罰金之折算標準，以示懲儆。\n三、依刑事訴訟法第449 條第1 項前段、第454 條第2 項，刑法\n    第140 條第1 項、第47條第1 項、第41條第1 項前段，刑法\n    施行法第1 條之1 第1 項、第2 項前段，逕以簡易判決處刑\n    。\n四、如不服本判決，應於判決送達後10日內，向本院提出上訴狀\n    （應附繕本），上訴於本院合議庭。\n中    華    民    國   100    年    7     月    26    日\n                              刑事第二庭   法  官 李麗珍\n以上正本證明與原本無異。\n如不服本判決，得於判決書送達之翌日起10日內，以書狀敘述理\n由，向本庭提出上訴（應附繕本）。\n                                          書記官  李靜華\n中    華    民    國   100    年    8     月    4     日\n附錄法條:\n刑法第140條第1項\n於公務員依法執行職務時，當場侮辱，或對於其依法執行之職務\n公然侮辱者，處 6 月以下有期徒刑、拘役或 1 百元以下罰金。",
  "structure": {
    "main": "傅子財於公務員依法執行職務時，當場侮辱，累犯，處拘役伍拾\n日，如易科罰金，以新台幣壹仟元折算壹日。",
    "fact": "一、本件犯罪事實及證據，均引用檢察官聲請簡易判決處刑書\n    之記載( 如附件) 。\n二、核被告所為，係犯刑法第140 條第1 項之於公務員依法執行\n    職務時當場侮辱罪。又被告上開當場侮辱行為，雖係對於警\n    員3 人為之，惟因當場侮辱之妨害公務罪，所保護者為公務\n    員公務執行之國家法益，故僅成立1 罪。被告前受有如上開\n    附件犯罪事實欄所示之有期徒刑執行情形，此有臺灣高等法\n    院前案紀錄表1 份附卷可稽，其於有期徒刑執行完畢後，5\n    年以內故意再犯本件有期徒刑以上之罪，為累犯，應依刑法\n    第47條第1 項之規定加重其刑。爰審酌被告僅因不滿警員欲\n    依法對其實施盤查，即以言語辱罵警員，公然對公權力加以\n    挑釁之犯罪情節，及其所生危害非輕，惟犯後終能坦承犯行\n    ，態度尚可與其素行情形等一切情狀，量處如主文所示之刑\n    ，並諭知易科罰金之折算標準，以示懲儆。\n三、依刑事訴訟法第449 條第1 項前段、第454 條第2 項，刑法\n    第140 條第1 項、第47條第1 項、第41條第1 項前段，刑法\n    施行法第1 條之1 第1 項、第2 項前段，逕以簡易判決處刑\n    。\n四、如不服本判決，應於判決送達後10日內，向本院提出上訴狀\n    （應附繕本），上訴於本院合議庭。",
    "reason": "一、本件犯罪事實及證據，均引用檢察官聲請簡易判決處刑書\n    之記載( 如附件) 。\n二、核被告所為，係犯刑法第140 條第1 項之於公務員依法執行\n    職務時當場侮辱罪。又被告上開當場侮辱行為，雖係對於警\n    員3 人為之，惟因當場侮辱之妨害公務罪，所保護者為公務\n    員公務執行之國家法益，故僅成立1 罪。被告前受有如上開\n    附件犯罪事實欄所示之有期徒刑執行情形，此有臺灣高等法\n    院前案紀錄表1 份附卷可稽，其於有期徒刑執行完畢後，5\n    年以內故意再犯本件有期徒刑以上之罪，為累犯，應依刑法\n    第47條第1 項之規定加重其刑。爰審酌被告僅因不滿警員欲\n    依法對其實施盤查，即以言語辱罵警員，公然對公權力加以\n    挑釁之犯罪情節，及其所生危害非輕，惟犯後終能坦承犯行\n    ，態度尚可與其素行情形等一切情狀，量處如主文所示之刑\n    ，並諭知易科罰金之折算標準，以示懲儆。\n三、依刑事訴訟法第449 條第1 項前段、第454 條第2 項，刑法\n    第140 條第1 項、第47條第1 項、第41條第1 項前段，刑法\n    施行法第1 條之1 第1 項、第2 項前段，逕以簡易判決處刑\n    。\n四、如不服本判決，應於判決送達後10日內，向本院提出上訴狀\n    （應附繕本），上訴於本院合議庭。"
  },
  "search": "臺灣桃園地方法院刑事簡易判決100年度桃簡字第1896號聲請人臺灣桃園地方法院檢察署檢察官被告傅子財上列被告因妨害公務案件，經檢察官聲請以簡易判決處刑(100年度偵字第15395號)，本院判決如下:主文傅子財於公務員依法執行職務時，當場侮辱，累犯，處拘役伍拾日，如易科罰金，以新台幣壹仟元折算壹日。事實及理由一、本件犯罪事實及證據，均引用檢察官聲請簡易判決處刑書之記載(如附件)。二、核被告所為，係犯刑法第140條第1項之於公務員依法執行職務時當場侮辱罪。又被告上開當場侮辱行為，雖係對於警員3人為之，惟因當場侮辱之妨害公務罪，所保護者為公務員公務執行之國家法益，故僅成立1罪。被告前受有如上開附件犯罪事實欄所示之有期徒刑執行情形，此有臺灣高等法院前案紀錄表1份附卷可稽，其於有期徒刑執行完畢後，5年以內故意再犯本件有期徒刑以上之罪，為累犯，應依刑法第47條第1項之規定加重其刑。爰審酌被告僅因不滿警員欲依法對其實施盤查，即以言語辱罵警員，公然對公權力加以挑釁之犯罪情節，及其所生危害非輕，惟犯後終能坦承犯行，態度尚可與其素行情形等一切情狀，量處如主文所示之刑，並諭知易科罰金之折算標準，以示懲儆。三、依刑事訴訟法第449條第1項前段、第454條第2項，刑法第140條第1項、第47條第1項、第41條第1項前段，刑法施行法第1條之1第1項、第2項前段，逕以簡易判決處刑。四、如不服本判決，應於判決送達後10日內，向本院提出上訴狀（應附繕本），上訴於本院合議庭。中華民國100年7月26日刑事第二庭法官李麗珍以上正本證明與原本無異。如不服本判決，得於判決書送達之翌日起10日內，以書狀敘述理由，向本庭提出上訴（應附繕本）。書記官李靜華中華民國100年8月4日附錄法條:刑法第140條第1項於公務員依法執行職務時，當場侮辱，或對於其依法執行之職務公然侮辱者，處6月以下有期徒刑、拘役或1百元以下罰金。",
  "characters": {
    "judges": [
      "李麗珍"
    ],
    "prosecutors": [

    ],
    "lawyers": [

    ],
    "clerks": [
      "李靜華"
    ],
    "plaintiffs": [

    ],
    "defendants": [
      "傅子財"
    ],
    "prosecutor_office": [
      "臺灣桃園地方法院檢察署檢察官"
    ],
    "creditors": [

    ],
    "debtors": [

    ],
    "judicial_associate_officer": [

    ]
  },
  "adjudged_at": "2011-07-26",
  "created_at": "2016-02-14 00:44:51",
  "updated_at": "2016-02-14 00:44:51"
}