{
  "identify": "KSD-93-簡-1671-20040531-1",
  "court": {
    "name": "臺灣高雄地方法院",
    "code": "KSD"
  },
  "division": {
    "name": "刑事",
    "code": "M"
  },
  "year": 93,
  "word": "簡",
  "number": "1671",
  "jcheck": "1",
  "reason": "違反臺灣地區與大陸地區人民關係條例",
  "content": "臺灣高雄地方法院刑事簡易判決                    九十三年度簡字第一六七一號\n    聲  請  人  臺灣高雄地方法院檢察署檢察官\n    被      告  甲○○\n右列被告因違反臺灣地區與大陸地區人民關係條例案件，經檢察官聲請簡易判決處刑\n（九十三年度偵字第一一八一號），本院判決如左：\n    主  文\n甲○○違反不得僱用大陸地區人民在臺灣地區從事未經許可之工作之規定，處拘役伍\n拾日，如易科罰金，以佰元折算壹日。\n    事實及理由\n一、甲○○係位於高雄縣大社鄉○○路六十九號「唱呼爽小吃部」之負責人，明知不\n    得僱用大陸地區人民在臺灣地區從事未經許可之工作，而陳華珍係依法來臺探親\n    之大陸地區人民，未獲得行政院勞工委員會或主管機關之工作許可，依法不得僱\n    用陳華珍在臺灣地區從事未經許可之工作，竟自民國九十二年十一月十八日起至\n    同年十二月十八日止，僱用大陸地區人民陳華珍，在上址從事陪客人飲酒、唱歌\n    等工作。嗣於九十三年十二月十八日下午三時三十五分，陳華珍在上址陪男客鍾\n    新富、李賀順飲酒唱歌時，為警當場查獲，始知悉上情。\n二、訊據被告甲○○固坦承其為「唱呼爽小吃部」之負責人，惟矢口否認有何違反臺\n    灣地區與大陸地區人民關係條例之犯行，辯稱：伊並未僱用案外人陳華珍，亦不\n    知其為大陸地區人民，案外人係陳華珍與證人鍾新富、李賀順於九十三年十二月\n    十八日一同前來店內飲酒唱歌云云。惟查：\n  (一)右揭事實，業據證人鍾新富、李賀順分別於警詢、偵訊及本院審理時均證述明確\n    ，並有大陸地區人民陳華珍國人入出境端末查詢報表一紙、現場照片四紙附卷可\n    稽，而證人鍾新富、李賀順與被告素無怨隙，衡情應無設詞誣陷之可能，且於警\n    詢、偵訊及本院審理中均為相同一致之證述內容，從而上開證人之證詞，堪予採\n    信。\n  (二)被告雖以前詞置辯，且證人陳華珍於警詢時雖證稱：因為等朋友無聊，所以進入\n    該包廂內唱歌，其並未受雇於被告，亦未曾陪證人鍾新富唱歌過云云（參見警卷\n    九十二年十二月十八日警詢筆錄）。衡情證人陳華珍既為大陸地區人民至臺灣地\n    區探親，且明知未經許可不得受雇工作等情，亦為證人陳華珍於警詢中所自承，\n    故其為避免自己應負之法律責任，而於案發後，附和被告辯解而為之證詞，其可\n    性信較低，不足採信。從而被告上開所辯，應為事後卸責之詞，不足採信，本案\n    事證明確，被告犯行堪以認定，應予依法論科。\n三、核被告所為，係違反臺灣地區與大陸地區人民關係條例第十五條第四款之規定，\n    應依同條例第八十三條第一項之規定論處。又臺灣地區與大陸地區人民關係條例\n    於九十二年十月二十九日修正公布，其中第十五條、第八十三條，均係自九十三\n    年三月一日起施行、生效，惟新舊法關於第八十三條第一項之刑度並未修正，自\n    不生新舊法比較問題。爰審酌被告未經許可僱用大陸地區人民工作，影響主管機\n    關對於大陸地區人民聘僱管理之正確性，並損及我國勞工就業機會，惟念被告僱\n    用之人數僅一人，期間甚短等一切情狀，量處如主文所示之刑，並諭知易科罰金\n    之折算標準。\n四、依刑事訴訟法第四百四十九條第一項、第三項、第四百五十四條第一項，臺灣地\n    區與大陸地區人民關係條例第十五條第四款、第八十三條第一項，刑法第十一條\n    前段、第四十一條第一項前段，罰金罰鍰提高標準條例第二條，逕以簡易判決處\n    如主文所示之刑。\n五、如不服本判決，得自收受送達之日起十日內，向本院提起上訴。\n中      華      民  國    九十三    年      五      月    三十一    日\n                                  臺灣高雄地方法院鳳山簡易庭\n                                      法  官    唐中興\n右正本證明與原本無異。\n                                      書記官    陳掌珠\n中      華      民      國    九十三    年      五      月    三十一    日\n附錄本判決論罪科刑法條全文：\n臺灣地區與大陸地區人民關係條例第十五條\n下列行為不得為之：\n一  使大陸地區人民非法進入臺灣地區。\n二  明知臺灣地區人民未經許可，而招攬使之進入大陸地區。\n三  使大陸地區人民在臺灣地區從事未經許可或與許可目的不符之活動。\n四  僱用或留用大陸地區人民在臺灣地區從事未經許可或與許可範圍不符之工作。\n五  居間介紹他人為前款之行為。\n臺灣地區與大陸地區人民關係條例第八十三條第一項：\n違反第十五條第四款或第五款規定者，處二年以下有期徒刑、拘役或科或併科新臺幣\n三十萬元以下罰金。\n",
  "structure": {
    "main": "甲○○違反不得僱用大陸地區人民在臺灣地區從事未經許可之工作之規定，處拘役伍\n拾日，如易科罰金，以佰元折算壹日。",
    "fact": "一、甲○○係位於高雄縣大社鄉○○路六十九號「唱呼爽小吃部」之負責人，明知不\n    得僱用大陸地區人民在臺灣地區從事未經許可之工作，而陳華珍係依法來臺探親\n    之大陸地區人民，未獲得行政院勞工委員會或主管機關之工作許可，依法不得僱\n    用陳華珍在臺灣地區從事未經許可之工作，竟自民國九十二年十一月十八日起至\n    同年十二月十八日止，僱用大陸地區人民陳華珍，在上址從事陪客人飲酒、唱歌\n    等工作。嗣於九十三年十二月十八日下午三時三十五分，陳華珍在上址陪男客鍾\n    新富、李賀順飲酒唱歌時，為警當場查獲，始知悉上情。\n二、訊據被告甲○○固坦承其為「唱呼爽小吃部」之負責人，惟矢口否認有何違反臺\n    灣地區與大陸地區人民關係條例之犯行，辯稱：伊並未僱用案外人陳華珍，亦不\n    知其為大陸地區人民，案外人係陳華珍與證人鍾新富、李賀順於九十三年十二月\n    十八日一同前來店內飲酒唱歌云云。惟查：\n  (一)右揭事實，業據證人鍾新富、李賀順分別於警詢、偵訊及本院審理時均證述明確\n    ，並有大陸地區人民陳華珍國人入出境端末查詢報表一紙、現場照片四紙附卷可\n    稽，而證人鍾新富、李賀順與被告素無怨隙，衡情應無設詞誣陷之可能，且於警\n    詢、偵訊及本院審理中均為相同一致之證述內容，從而上開證人之證詞，堪予採\n    信。\n  (二)被告雖以前詞置辯，且證人陳華珍於警詢時雖證稱：因為等朋友無聊，所以進入\n    該包廂內唱歌，其並未受雇於被告，亦未曾陪證人鍾新富唱歌過云云（參見警卷\n    九十二年十二月十八日警詢筆錄）。衡情證人陳華珍既為大陸地區人民至臺灣地\n    區探親，且明知未經許可不得受雇工作等情，亦為證人陳華珍於警詢中所自承，\n    故其為避免自己應負之法律責任，而於案發後，附和被告辯解而為之證詞，其可\n    性信較低，不足採信。從而被告上開所辯，應為事後卸責之詞，不足採信，本案\n    事證明確，被告犯行堪以認定，應予依法論科。\n三、核被告所為，係違反臺灣地區與大陸地區人民關係條例第十五條第四款之規定，\n    應依同條例第八十三條第一項之規定論處。又臺灣地區與大陸地區人民關係條例\n    於九十二年十月二十九日修正公布，其中第十五條、第八十三條，均係自九十三\n    年三月一日起施行、生效，惟新舊法關於第八十三條第一項之刑度並未修正，自\n    不生新舊法比較問題。爰審酌被告未經許可僱用大陸地區人民工作，影響主管機\n    關對於大陸地區人民聘僱管理之正確性，並損及我國勞工就業機會，惟念被告僱\n    用之人數僅一人，期間甚短等一切情狀，量處如主文所示之刑，並諭知易科罰金\n    之折算標準。\n四、依刑事訴訟法第四百四十九條第一項、第三項、第四百五十四條第一項，臺灣地\n    區與大陸地區人民關係條例第十五條第四款、第八十三條第一項，刑法第十一條\n    前段、第四十一條第一項前段，罰金罰鍰提高標準條例第二條，逕以簡易判決處\n    如主文所示之刑。\n五、如不服本判決，得自收受送達之日起十日內，向本院提起上訴。",
    "reason": "一、甲○○係位於高雄縣大社鄉○○路六十九號「唱呼爽小吃部」之負責人，明知不\n    得僱用大陸地區人民在臺灣地區從事未經許可之工作，而陳華珍係依法來臺探親\n    之大陸地區人民，未獲得行政院勞工委員會或主管機關之工作許可，依法不得僱\n    用陳華珍在臺灣地區從事未經許可之工作，竟自民國九十二年十一月十八日起至\n    同年十二月十八日止，僱用大陸地區人民陳華珍，在上址從事陪客人飲酒、唱歌\n    等工作。嗣於九十三年十二月十八日下午三時三十五分，陳華珍在上址陪男客鍾\n    新富、李賀順飲酒唱歌時，為警當場查獲，始知悉上情。\n二、訊據被告甲○○固坦承其為「唱呼爽小吃部」之負責人，惟矢口否認有何違反臺\n    灣地區與大陸地區人民關係條例之犯行，辯稱：伊並未僱用案外人陳華珍，亦不\n    知其為大陸地區人民，案外人係陳華珍與證人鍾新富、李賀順於九十三年十二月\n    十八日一同前來店內飲酒唱歌云云。惟查：\n  (一)右揭事實，業據證人鍾新富、李賀順分別於警詢、偵訊及本院審理時均證述明確\n    ，並有大陸地區人民陳華珍國人入出境端末查詢報表一紙、現場照片四紙附卷可\n    稽，而證人鍾新富、李賀順與被告素無怨隙，衡情應無設詞誣陷之可能，且於警\n    詢、偵訊及本院審理中均為相同一致之證述內容，從而上開證人之證詞，堪予採\n    信。\n  (二)被告雖以前詞置辯，且證人陳華珍於警詢時雖證稱：因為等朋友無聊，所以進入\n    該包廂內唱歌，其並未受雇於被告，亦未曾陪證人鍾新富唱歌過云云（參見警卷\n    九十二年十二月十八日警詢筆錄）。衡情證人陳華珍既為大陸地區人民至臺灣地\n    區探親，且明知未經許可不得受雇工作等情，亦為證人陳華珍於警詢中所自承，\n    故其為避免自己應負之法律責任，而於案發後，附和被告辯解而為之證詞，其可\n    性信較低，不足採信。從而被告上開所辯，應為事後卸責之詞，不足採信，本案\n    事證明確，被告犯行堪以認定，應予依法論科。\n三、核被告所為，係違反臺灣地區與大陸地區人民關係條例第十五條第四款之規定，\n    應依同條例第八十三條第一項之規定論處。又臺灣地區與大陸地區人民關係條例\n    於九十二年十月二十九日修正公布，其中第十五條、第八十三條，均係自九十三\n    年三月一日起施行、生效，惟新舊法關於第八十三條第一項之刑度並未修正，自\n    不生新舊法比較問題。爰審酌被告未經許可僱用大陸地區人民工作，影響主管機\n    關對於大陸地區人民聘僱管理之正確性，並損及我國勞工就業機會，惟念被告僱\n    用之人數僅一人，期間甚短等一切情狀，量處如主文所示之刑，並諭知易科罰金\n    之折算標準。\n四、依刑事訴訟法第四百四十九條第一項、第三項、第四百五十四條第一項，臺灣地\n    區與大陸地區人民關係條例第十五條第四款、第八十三條第一項，刑法第十一條\n    前段、第四十一條第一項前段，罰金罰鍰提高標準條例第二條，逕以簡易判決處\n    如主文所示之刑。\n五、如不服本判決，得自收受送達之日起十日內，向本院提起上訴。"
  },
  "search": "臺灣高雄地方法院刑事簡易判決九十三年度簡字第一六七一號聲請人臺灣高雄地方法院檢察署檢察官被告甲○○右列被告因違反臺灣地區與大陸地區人民關係條例案件，經檢察官聲請簡易判決處刑（九十三年度偵字第一一八一號），本院判決如左：主文甲○○違反不得僱用大陸地區人民在臺灣地區從事未經許可之工作之規定，處拘役伍拾日，如易科罰金，以佰元折算壹日。事實及理由一、甲○○係位於高雄縣大社鄉○○路六十九號「唱呼爽小吃部」之負責人，明知不得僱用大陸地區人民在臺灣地區從事未經許可之工作，而陳華珍係依法來臺探親之大陸地區人民，未獲得行政院勞工委員會或主管機關之工作許可，依法不得僱用陳華珍在臺灣地區從事未經許可之工作，竟自民國九十二年十一月十八日起至同年十二月十八日止，僱用大陸地區人民陳華珍，在上址從事陪客人飲酒、唱歌等工作。嗣於九十三年十二月十八日下午三時三十五分，陳華珍在上址陪男客鍾新富、李賀順飲酒唱歌時，為警當場查獲，始知悉上情。二、訊據被告甲○○固坦承其為「唱呼爽小吃部」之負責人，惟矢口否認有何違反臺灣地區與大陸地區人民關係條例之犯行，辯稱：伊並未僱用案外人陳華珍，亦不知其為大陸地區人民，案外人係陳華珍與證人鍾新富、李賀順於九十三年十二月十八日一同前來店內飲酒唱歌云云。惟查：(一)右揭事實，業據證人鍾新富、李賀順分別於警詢、偵訊及本院審理時均證述明確，並有大陸地區人民陳華珍國人入出境端末查詢報表一紙、現場照片四紙附卷可稽，而證人鍾新富、李賀順與被告素無怨隙，衡情應無設詞誣陷之可能，且於警詢、偵訊及本院審理中均為相同一致之證述內容，從而上開證人之證詞，堪予採信。(二)被告雖以前詞置辯，且證人陳華珍於警詢時雖證稱：因為等朋友無聊，所以進入該包廂內唱歌，其並未受雇於被告，亦未曾陪證人鍾新富唱歌過云云（參見警卷九十二年十二月十八日警詢筆錄）。衡情證人陳華珍既為大陸地區人民至臺灣地區探親，且明知未經許可不得受雇工作等情，亦為證人陳華珍於警詢中所自承，故其為避免自己應負之法律責任，而於案發後，附和被告辯解而為之證詞，其可性信較低，不足採信。從而被告上開所辯，應為事後卸責之詞，不足採信，本案事證明確，被告犯行堪以認定，應予依法論科。三、核被告所為，係違反臺灣地區與大陸地區人民關係條例第十五條第四款之規定，應依同條例第八十三條第一項之規定論處。又臺灣地區與大陸地區人民關係條例於九十二年十月二十九日修正公布，其中第十五條、第八十三條，均係自九十三年三月一日起施行、生效，惟新舊法關於第八十三條第一項之刑度並未修正，自不生新舊法比較問題。爰審酌被告未經許可僱用大陸地區人民工作，影響主管機關對於大陸地區人民聘僱管理之正確性，並損及我國勞工就業機會，惟念被告僱用之人數僅一人，期間甚短等一切情狀，量處如主文所示之刑，並諭知易科罰金之折算標準。四、依刑事訴訟法第四百四十九條第一項、第三項、第四百五十四條第一項，臺灣地區與大陸地區人民關係條例第十五條第四款、第八十三條第一項，刑法第十一條前段、第四十一條第一項前段，罰金罰鍰提高標準條例第二條，逕以簡易判決處如主文所示之刑。五、如不服本判決，得自收受送達之日起十日內，向本院提起上訴。中華民國九十三年五月三十一日臺灣高雄地方法院鳳山簡易庭法官唐中興右正本證明與原本無異。書記官陳掌珠中華民國九十三年五月三十一日附錄本判決論罪科刑法條全文：臺灣地區與大陸地區人民關係條例第十五條下列行為不得為之：一使大陸地區人民非法進入臺灣地區。二明知臺灣地區人民未經許可，而招攬使之進入大陸地區。三使大陸地區人民在臺灣地區從事未經許可或與許可目的不符之活動。四僱用或留用大陸地區人民在臺灣地區從事未經許可或與許可範圍不符之工作。五居間介紹他人為前款之行為。臺灣地區與大陸地區人民關係條例第八十三條第一項：違反第十五條第四款或第五款規定者，處二年以下有期徒刑、拘役或科或併科新臺幣三十萬元以下罰金。",
  "characters": {
    "judges": [
      "唐中興"
    ],
    "prosecutors": [

    ],
    "lawyers": [

    ],
    "clerks": [
      "陳掌珠"
    ],
    "plaintiffs": [

    ],
    "defendants": [
      "甲○○",
      "右列被告因違反臺灣地區與大陸地區人民關係條例案件，經檢察官聲請簡易判決處刑",
      "（九十三年度偵字第一一八一號），本院判決如左："
    ],
    "prosecutor_office": [
      "臺灣高雄地方法院檢察署檢察官"
    ],
    "creditors": [

    ],
    "debtors": [

    ],
    "judicial_associate_officer": [

    ]
  },
  "adjudged_at": "2004-05-31",
  "created_at": "2016-02-05 20:57:28",
  "updated_at": "2016-02-05 20:57:28"
}