{
  "identify": "TCD-100-易-2560-20111121-3",
  "court": {
    "name": "臺灣臺中地方法院",
    "code": "TCD"
  },
  "division": {
    "name": "刑事",
    "code": "M"
  },
  "year": 100,
  "word": "易",
  "number": "2560",
  "jcheck": "3",
  "reason": "詐欺",
  "content": "臺灣臺中地方法院刑事裁定             100年度易字第2560號\n公  訴  人  臺灣臺中地方法院檢察署檢察官\n具  保  人  王慧嵐\n被      告  李洵斌\n上被告因詐欺案件，本院裁定如下：\n    主    文\n王慧嵐繳納之保證金新臺幣貳萬元，沒入之。\n    理    由\n一、被告李洵斌因詐欺案件，前經臺灣臺中地方法院檢察署檢察\n    官指定保證金新臺幣（下同）2萬元，由具保人王慧嵐繳納\n    現金後，已將被告李洵斌釋放。\n二、茲以該被告李洵斌逃匿，自應將原繳納上開保證金沒入。\n三、依刑事訴訟法第118條、第121條第1項，裁定如主文。\n中    華    民    國   100    年    11    月    21    日\n                        臺灣臺中地方法院刑事第十四庭\n                            審判長法  官  吳幸芬\n                                  法  官  戴嘉慧\n                                  法  官  劉麗瑛\n以上正本證明與原本無異。\n如不服本裁定，應於送達後5日，內向本院提出抗告狀。\n                                  書記官  王玟\n中    華    民    國   100    年    11    月    21    日",
  "structure": {
    "main": "王慧嵐繳納之保證金新臺幣貳萬元，沒入之。",
    "reason": "一、被告李洵斌因詐欺案件，前經臺灣臺中地方法院檢察署檢察\n    官指定保證金新臺幣（下同）2萬元，由具保人王慧嵐繳納\n    現金後，已將被告李洵斌釋放。\n二、茲以該被告李洵斌逃匿，自應將原繳納上開保證金沒入。\n三、依刑事訴訟法第118條、第121條第1項，裁定如主文。"
  },
  "search": "臺灣臺中地方法院刑事裁定100年度易字第2560號公訴人臺灣臺中地方法院檢察署檢察官具保人王慧嵐被告李洵斌上被告因詐欺案件，本院裁定如下：主文王慧嵐繳納之保證金新臺幣貳萬元，沒入之。理由一、被告李洵斌因詐欺案件，前經臺灣臺中地方法院檢察署檢察官指定保證金新臺幣（下同）2萬元，由具保人王慧嵐繳納現金後，已將被告李洵斌釋放。二、茲以該被告李洵斌逃匿，自應將原繳納上開保證金沒入。三、依刑事訴訟法第118條、第121條第1項，裁定如主文。中華民國100年11月21日臺灣臺中地方法院刑事第十四庭審判長法官吳幸芬法官戴嘉慧法官劉麗瑛以上正本證明與原本無異。如不服本裁定，應於送達後5日，內向本院提出抗告狀。書記官王玟中華民國100年11月21日",
  "characters": {
    "judges": [
      "吳幸芬",
      "戴嘉慧",
      "劉麗瑛"
    ],
    "prosecutors": [

    ],
    "lawyers": [

    ],
    "clerks": [
      "王玟"
    ],
    "plaintiffs": [

    ],
    "defendants": [
      "李洵斌"
    ],
    "prosecutor_office": [
      "臺灣臺中地方法院檢察署檢察官"
    ],
    "creditors": [

    ],
    "debtors": [

    ],
    "judicial_associate_officer": [

    ]
  },
  "adjudged_at": "2011-11-21",
  "created_at": "2016-02-12 21:48:50",
  "updated_at": "2016-02-12 21:48:50"
}