{
  "identify": "TPD-100-簡-4097-20111121-1",
  "court": {
    "name": "臺灣臺北地方法院",
    "code": "TPD"
  },
  "division": {
    "name": "刑事",
    "code": "M"
  },
  "year": 100,
  "word": "簡",
  "number": "4097",
  "jcheck": "1",
  "reason": "違反公司法等",
  "content": "臺灣臺北地方法院刑事簡易判決         100年度簡字第4097號\n聲  請  人  臺灣臺北地方法院檢察署檢察官\n被      告  李文選\n上列被告因違反公司法等案件，經檢察官聲請以簡易判決處刑（\n100 年度偵緝字第1086號），本院判決如下：\n    主  文\n李文選共同公司負責人，公司應收之股款，股東並未實際繳納，\n而以申請文件表明收足，處有期徒刑貳月，如易科罰金，以新臺\n幣壹仟元折算壹日。\n    事實及理由\n一、本件犯罪事實部分，引用檢察官聲請簡易判決處刑書之記載\n    （如附件）。\n二、證據名稱：\n(一)、被告李文選之自白（見100 年度偵緝字第1086號卷第17、28\n    頁）。\n(二)、第一商業銀行100 年10月20日100 一八德字第141 號函及函\n    附之「天之部落原住民實業有限公司籌備處」開戶資料（見\n    100年度偵緝字第1086號卷第52至56頁）。\n(三)、公司登記資料查詢、第一商業銀行存摺類存款憑條、取款憑\n    條影本各1 紙、臺北市商業管理處「天之部落原住民實業有\n    限公司」登記卷宗影本1 份（見99年度他字第4485號卷第4\n    頁及背面、6 、7 至19頁）。\n三、論罪科刑部分：\n(一)、被告為「天之部落原住民實業有限公司」之負責人，係公司\n    法及商業會計法所規定之公司負責人及商業負責人，其明知\n    公司應收股款，股東並未實際繳納，而以申請文件表明收足\n    ，使主管機關公務員登載於職務上所掌之公文書，自足以生\n    損害於臺北市政府商業管理處對公司管理之正確性。是核被\n    告所為，係犯公司法第9 條第1 項之公司負責人，公司應收\n    之股款，股東並未實際繳納而以申請文件表明收足罪、商業\n    會計法第71條第5 款之商業負責人利用不正當方法致使財務\n    報表發生不實結果罪及刑法第214 條之使公務員登載不實罪\n    。\n(二)、又商業會計法第71條之規定為刑法第215 條業務上登載不實\n    罪之特別規定，應優先適用，不再論以刑法第215 條之罪。\n(三)、被告利用不知情之會計師張崑銘犯上開各罪，為間接正犯。\n(四)、被告與不詳記帳業者（無證據證明未滿18歲）、金主洪蔡月\n    娥間，就本件犯行，有犯意聯絡及行為分擔，依刑法第31條\n    第1 項、第28條規定，為共同正犯。\n(五)、再被告所犯公司法第9 條第1 項、商業會計法第71條第5 款\n    及刑法第214 條等罪，就被告而言，僅有自然行為概念之一\n    行為，且係基於一個意思決定為之（即辦理公司設立登記）\n    ，自應評價為一個犯罪行為，而上開3 罪犯罪構成要件不同\n    ，其以一行為觸犯數罪名，應依刑法第55條前段之規定，從\n    較重之公司法第9 條第1 項規定處斷（最高法院96年臺上字\n    第6356號判決、96年度第7 次刑事庭會議決議意旨參照）。\n(六)、爰審酌被告為「天之部落原住民實業有限公司」之負責人，\n    其明知己身應繳納公司額定資本額之股款，竟未實際繳納股\n    款，而與不詳記帳業者及金主洪蔡月娥等人共同以申請文件\n    表明收足，向主管機關申請設立登記，對於與該公司交易之\n    第三人及主管機關對公司管理正確性之危害非輕，惟念其僅\n    因不諳法律規定而觸犯刑章，兼衡其犯罪動機、目的、手段\n    、智識程度、犯後坦承犯行，態度尚佳等一切情狀，量處如\n    主文所示之刑，併諭知易科罰金之折算標準。\n四、適用之法律：\n(一)、刑事訴訟法第449 條第1 項前段、第454 條第1 項、第2 項\n    。\n(二)、公司法第9 條第1 項前段，商業會計法第71條第5 款。\n(三)、刑法第11條前段、第28條、第31條第1 項、第214 條、第55\n    條前段、第41條第1 項前段。\n(四)、刑法施行法第1 條之1 第1 項、第2 項前段。\n五、如不服本判決，得自收受送達之翌日起10日內向本院提出上\n    訴狀，上訴於本院第二審合議庭（須附繕本）。\n中    華    民    國   100    年    11    月    21    日\n                  刑事第十一庭  法  官  陳諾樺\n以上正本證明與原本無異。\n如不服本判決應於收受送達後10日內向本院提出上訴書狀，並應\n敘述具體理由；其未敘述上訴理由者，應於上訴期間屆滿後20日\n內向本院補提理由書（均須按他造當事人之人數附繕本）「切勿\n逕送上級法院」。\n                                書記官  呂欣穎\n中    華    民    國   100    年    11    月    21    日\n附錄本案論罪科刑法條\n公司法第9 條第1項\n公司應收之股款，股東並未實際繳納，而以申請文件表明收足，\n或股東雖已繳納而於登記後將股款發還股東，或任由股東收回者\n，公司負責人各處5 年以下有期徒刑、拘役或科或併科新臺幣50\n萬元以上250 萬元以下罰金。\n商業會計法第71條第1項第5款\n商業負責人、主辦及經辦會計人員或依法受託代他人處理會計事\n務之人員有下列情事之一者，處5 年以下有期徒刑、拘役或科或\n併科新臺幣60萬元以下罰金：\n五、其他利用不正當方法，致使會計事項或財務報表發生不實之\n結果。\n中華民國刑法第214條\n明知為不實之事項，而使公務員登載於職務上所掌之公文書，足\n以生損害於公眾或他人者，處3年以下有期徒刑、拘役或5百元以\n下罰金。",
  "structure": {
    "main": "李文選共同公司負責人，公司應收之股款，股東並未實際繳納，\n而以申請文件表明收足，處有期徒刑貳月，如易科罰金，以新臺\n幣壹仟元折算壹日。",
    "fact": "一、本件犯罪事實部分，引用檢察官聲請簡易判決處刑書之記載\n    （如附件）。\n二、證據名稱：\n(一)、被告李文選之自白（見100 年度偵緝字第1086號卷第17、28\n    頁）。\n(二)、第一商業銀行100 年10月20日100 一八德字第141 號函及函\n    附之「天之部落原住民實業有限公司籌備處」開戶資料（見\n    100年度偵緝字第1086號卷第52至56頁）。\n(三)、公司登記資料查詢、第一商業銀行存摺類存款憑條、取款憑\n    條影本各1 紙、臺北市商業管理處「天之部落原住民實業有\n    限公司」登記卷宗影本1 份（見99年度他字第4485號卷第4\n    頁及背面、6 、7 至19頁）。\n三、論罪科刑部分：\n(一)、被告為「天之部落原住民實業有限公司」之負責人，係公司\n    法及商業會計法所規定之公司負責人及商業負責人，其明知\n    公司應收股款，股東並未實際繳納，而以申請文件表明收足\n    ，使主管機關公務員登載於職務上所掌之公文書，自足以生\n    損害於臺北市政府商業管理處對公司管理之正確性。是核被\n    告所為，係犯公司法第9 條第1 項之公司負責人，公司應收\n    之股款，股東並未實際繳納而以申請文件表明收足罪、商業\n    會計法第71條第5 款之商業負責人利用不正當方法致使財務\n    報表發生不實結果罪及刑法第214 條之使公務員登載不實罪\n    。\n(二)、又商業會計法第71條之規定為刑法第215 條業務上登載不實\n    罪之特別規定，應優先適用，不再論以刑法第215 條之罪。\n(三)、被告利用不知情之會計師張崑銘犯上開各罪，為間接正犯。\n(四)、被告與不詳記帳業者（無證據證明未滿18歲）、金主洪蔡月\n    娥間，就本件犯行，有犯意聯絡及行為分擔，依刑法第31條\n    第1 項、第28條規定，為共同正犯。\n(五)、再被告所犯公司法第9 條第1 項、商業會計法第71條第5 款\n    及刑法第214 條等罪，就被告而言，僅有自然行為概念之一\n    行為，且係基於一個意思決定為之（即辦理公司設立登記）\n    ，自應評價為一個犯罪行為，而上開3 罪犯罪構成要件不同\n    ，其以一行為觸犯數罪名，應依刑法第55條前段之規定，從\n    較重之公司法第9 條第1 項規定處斷（最高法院96年臺上字\n    第6356號判決、96年度第7 次刑事庭會議決議意旨參照）。\n(六)、爰審酌被告為「天之部落原住民實業有限公司」之負責人，\n    其明知己身應繳納公司額定資本額之股款，竟未實際繳納股\n    款，而與不詳記帳業者及金主洪蔡月娥等人共同以申請文件\n    表明收足，向主管機關申請設立登記，對於與該公司交易之\n    第三人及主管機關對公司管理正確性之危害非輕，惟念其僅\n    因不諳法律規定而觸犯刑章，兼衡其犯罪動機、目的、手段\n    、智識程度、犯後坦承犯行，態度尚佳等一切情狀，量處如\n    主文所示之刑，併諭知易科罰金之折算標準。\n四、適用之法律：\n(一)、刑事訴訟法第449 條第1 項前段、第454 條第1 項、第2 項\n    。\n(二)、公司法第9 條第1 項前段，商業會計法第71條第5 款。\n(三)、刑法第11條前段、第28條、第31條第1 項、第214 條、第55\n    條前段、第41條第1 項前段。\n(四)、刑法施行法第1 條之1 第1 項、第2 項前段。\n五、如不服本判決，得自收受送達之翌日起10日內向本院提出上\n    訴狀，上訴於本院第二審合議庭（須附繕本）。",
    "reason": "一、本件犯罪事實部分，引用檢察官聲請簡易判決處刑書之記載\n    （如附件）。\n二、證據名稱：\n(一)、被告李文選之自白（見100 年度偵緝字第1086號卷第17、28\n    頁）。\n(二)、第一商業銀行100 年10月20日100 一八德字第141 號函及函\n    附之「天之部落原住民實業有限公司籌備處」開戶資料（見\n    100年度偵緝字第1086號卷第52至56頁）。\n(三)、公司登記資料查詢、第一商業銀行存摺類存款憑條、取款憑\n    條影本各1 紙、臺北市商業管理處「天之部落原住民實業有\n    限公司」登記卷宗影本1 份（見99年度他字第4485號卷第4\n    頁及背面、6 、7 至19頁）。\n三、論罪科刑部分：\n(一)、被告為「天之部落原住民實業有限公司」之負責人，係公司\n    法及商業會計法所規定之公司負責人及商業負責人，其明知\n    公司應收股款，股東並未實際繳納，而以申請文件表明收足\n    ，使主管機關公務員登載於職務上所掌之公文書，自足以生\n    損害於臺北市政府商業管理處對公司管理之正確性。是核被\n    告所為，係犯公司法第9 條第1 項之公司負責人，公司應收\n    之股款，股東並未實際繳納而以申請文件表明收足罪、商業\n    會計法第71條第5 款之商業負責人利用不正當方法致使財務\n    報表發生不實結果罪及刑法第214 條之使公務員登載不實罪\n    。\n(二)、又商業會計法第71條之規定為刑法第215 條業務上登載不實\n    罪之特別規定，應優先適用，不再論以刑法第215 條之罪。\n(三)、被告利用不知情之會計師張崑銘犯上開各罪，為間接正犯。\n(四)、被告與不詳記帳業者（無證據證明未滿18歲）、金主洪蔡月\n    娥間，就本件犯行，有犯意聯絡及行為分擔，依刑法第31條\n    第1 項、第28條規定，為共同正犯。\n(五)、再被告所犯公司法第9 條第1 項、商業會計法第71條第5 款\n    及刑法第214 條等罪，就被告而言，僅有自然行為概念之一\n    行為，且係基於一個意思決定為之（即辦理公司設立登記）\n    ，自應評價為一個犯罪行為，而上開3 罪犯罪構成要件不同\n    ，其以一行為觸犯數罪名，應依刑法第55條前段之規定，從\n    較重之公司法第9 條第1 項規定處斷（最高法院96年臺上字\n    第6356號判決、96年度第7 次刑事庭會議決議意旨參照）。\n(六)、爰審酌被告為「天之部落原住民實業有限公司」之負責人，\n    其明知己身應繳納公司額定資本額之股款，竟未實際繳納股\n    款，而與不詳記帳業者及金主洪蔡月娥等人共同以申請文件\n    表明收足，向主管機關申請設立登記，對於與該公司交易之\n    第三人及主管機關對公司管理正確性之危害非輕，惟念其僅\n    因不諳法律規定而觸犯刑章，兼衡其犯罪動機、目的、手段\n    、智識程度、犯後坦承犯行，態度尚佳等一切情狀，量處如\n    主文所示之刑，併諭知易科罰金之折算標準。\n四、適用之法律：\n(一)、刑事訴訟法第449 條第1 項前段、第454 條第1 項、第2 項\n    。\n(二)、公司法第9 條第1 項前段，商業會計法第71條第5 款。\n(三)、刑法第11條前段、第28條、第31條第1 項、第214 條、第55\n    條前段、第41條第1 項前段。\n(四)、刑法施行法第1 條之1 第1 項、第2 項前段。\n五、如不服本判決，得自收受送達之翌日起10日內向本院提出上\n    訴狀，上訴於本院第二審合議庭（須附繕本）。"
  },
  "search": "臺灣臺北地方法院刑事簡易判決100年度簡字第4097號聲請人臺灣臺北地方法院檢察署檢察官被告李文選上列被告因違反公司法等案件，經檢察官聲請以簡易判決處刑（100年度偵緝字第1086號），本院判決如下：主文李文選共同公司負責人，公司應收之股款，股東並未實際繳納，而以申請文件表明收足，處有期徒刑貳月，如易科罰金，以新臺幣壹仟元折算壹日。事實及理由一、本件犯罪事實部分，引用檢察官聲請簡易判決處刑書之記載（如附件）。二、證據名稱：(一)、被告李文選之自白（見100年度偵緝字第1086號卷第17、28頁）。(二)、第一商業銀行100年10月20日100一八德字第141號函及函附之「天之部落原住民實業有限公司籌備處」開戶資料（見100年度偵緝字第1086號卷第52至56頁）。(三)、公司登記資料查詢、第一商業銀行存摺類存款憑條、取款憑條影本各1紙、臺北市商業管理處「天之部落原住民實業有限公司」登記卷宗影本1份（見99年度他字第4485號卷第4頁及背面、6、7至19頁）。三、論罪科刑部分：(一)、被告為「天之部落原住民實業有限公司」之負責人，係公司法及商業會計法所規定之公司負責人及商業負責人，其明知公司應收股款，股東並未實際繳納，而以申請文件表明收足，使主管機關公務員登載於職務上所掌之公文書，自足以生損害於臺北市政府商業管理處對公司管理之正確性。是核被告所為，係犯公司法第9條第1項之公司負責人，公司應收之股款，股東並未實際繳納而以申請文件表明收足罪、商業會計法第71條第5款之商業負責人利用不正當方法致使財務報表發生不實結果罪及刑法第214條之使公務員登載不實罪。(二)、又商業會計法第71條之規定為刑法第215條業務上登載不實罪之特別規定，應優先適用，不再論以刑法第215條之罪。(三)、被告利用不知情之會計師張崑銘犯上開各罪，為間接正犯。(四)、被告與不詳記帳業者（無證據證明未滿18歲）、金主洪蔡月娥間，就本件犯行，有犯意聯絡及行為分擔，依刑法第31條第1項、第28條規定，為共同正犯。(五)、再被告所犯公司法第9條第1項、商業會計法第71條第5款及刑法第214條等罪，就被告而言，僅有自然行為概念之一行為，且係基於一個意思決定為之（即辦理公司設立登記），自應評價為一個犯罪行為，而上開3罪犯罪構成要件不同，其以一行為觸犯數罪名，應依刑法第55條前段之規定，從較重之公司法第9條第1項規定處斷（最高法院96年臺上字第6356號判決、96年度第7次刑事庭會議決議意旨參照）。(六)、爰審酌被告為「天之部落原住民實業有限公司」之負責人，其明知己身應繳納公司額定資本額之股款，竟未實際繳納股款，而與不詳記帳業者及金主洪蔡月娥等人共同以申請文件表明收足，向主管機關申請設立登記，對於與該公司交易之第三人及主管機關對公司管理正確性之危害非輕，惟念其僅因不諳法律規定而觸犯刑章，兼衡其犯罪動機、目的、手段、智識程度、犯後坦承犯行，態度尚佳等一切情狀，量處如主文所示之刑，併諭知易科罰金之折算標準。四、適用之法律：(一)、刑事訴訟法第449條第1項前段、第454條第1項、第2項。(二)、公司法第9條第1項前段，商業會計法第71條第5款。(三)、刑法第11條前段、第28條、第31條第1項、第214條、第55條前段、第41條第1項前段。(四)、刑法施行法第1條之1第1項、第2項前段。五、如不服本判決，得自收受送達之翌日起10日內向本院提出上訴狀，上訴於本院第二審合議庭（須附繕本）。中華民國100年11月21日刑事第十一庭法官陳諾樺以上正本證明與原本無異。如不服本判決應於收受送達後10日內向本院提出上訴書狀，並應敘述具體理由；其未敘述上訴理由者，應於上訴期間屆滿後20日內向本院補提理由書（均須按他造當事人之人數附繕本）「切勿逕送上級法院」。書記官呂欣穎中華民國100年11月21日附錄本案論罪科刑法條公司法第9條第1項公司應收之股款，股東並未實際繳納，而以申請文件表明收足，或股東雖已繳納而於登記後將股款發還股東，或任由股東收回者，公司負責人各處5年以下有期徒刑、拘役或科或併科新臺幣50萬元以上250萬元以下罰金。商業會計法第71條第1項第5款商業負責人、主辦及經辦會計人員或依法受託代他人處理會計事務之人員有下列情事之一者，處5年以下有期徒刑、拘役或科或併科新臺幣60萬元以下罰金：五、其他利用不正當方法，致使會計事項或財務報表發生不實之結果。中華民國刑法第214條明知為不實之事項，而使公務員登載於職務上所掌之公文書，足以生損害於公眾或他人者，處3年以下有期徒刑、拘役或5百元以下罰金。",
  "characters": {
    "judges": [
      "陳諾樺"
    ],
    "prosecutors": [

    ],
    "lawyers": [

    ],
    "clerks": [
      "呂欣穎"
    ],
    "plaintiffs": [

    ],
    "defendants": [
      "李文選"
    ],
    "prosecutor_office": [
      "臺灣臺北地方法院檢察署檢察官"
    ],
    "creditors": [

    ],
    "debtors": [

    ],
    "judicial_associate_officer": [

    ]
  },
  "adjudged_at": "2011-11-21",
  "created_at": "2016-02-12 21:48:41",
  "updated_at": "2016-02-12 21:48:41"
}