{
  "identify": "TPD-93-交簡上-23-20040527-1",
  "court": {
    "name": "臺灣臺北地方法院",
    "code": "TPD"
  },
  "division": {
    "name": "刑事",
    "code": "M"
  },
  "year": 93,
  "word": "交簡上",
  "number": "23",
  "jcheck": "1",
  "reason": "公共危險",
  "content": "臺灣臺北地方法院刑事判決                        九十三年度交簡上字第二三號\n    上  訴  人\n    即  被  告  甲○○\n右列上訴人即被告因公共危險案件，不服本院臺北簡易庭於民國九十三年二月二十四\n日所為九十三年度北交簡字第二四八號第一審刑事簡易判決（聲請簡易判決處刑案號\n：九十二年度偵字第二四八八一號），提起上訴，本院管轄第二審之合議庭判決如左\n：\n    主  文\n上訴駁回。\n    事  實\n一、甲○○前於民國九十一年間因酒醉駕車觸犯公共危險罪，經臺灣桃園地方法院以\n    九十一年度桃交簡字第二一五三號判決判處拘役五十八日確定，詎其猶不知戒慎\n    ，於九十二年九月十七日某時在不詳地點服用酒類後，已達思考、個性行為改變\n    而無法安全駕駛動力交通工具之程度，仍於酒後騎乘動力交通工具即車號ＡＷＫ\n    －八二九號重型機車上路，嗣於同日下午四時五十八分許在臺北市○○區○○街\n    七十一巷口前因未戴安全帽而為警攔檢，並測得其呼氣所含酒精濃度達每公升零\n    點八六毫克。\n二、案經臺北市政府警察局信義分局報請臺灣臺北地方法院檢察署檢察官偵查後聲請\n    簡易判決處刑。\n    理  由\n一、訊據上訴人即被告甲○○對於在右揭時、地為警攔檢，測試其吐氣所含酒精成份\n    達每公升零點八六毫克之事實坦承不諱，並有吐氣所含酒精成份測試成果表壹紙\n    在卷可資佐證。按刑法第一百八十五條之三所規定服用酒類，不能安全駕駛動力\n    交通工具而駕駛者，應負刑事責任，揆其立法目的本在藉抽象危險犯之犯罪構成\n    要件，以嚇阻酒後駕車者對道路交通安全之危害，本不以發生實害為必要。而所\n    謂不能安全駕駛之認定，並無一定之數值可供界定，而係由法院以一般社會通念\n    之客觀標準，足生公共危險時即足。目前行政機關所取締酒後駕車之參考標準，\n    係依法務部於八十八年五月十日邀集司法院刑事廳、交通部、行政院衛生署、內\n    政部警政署及中央警察大學等機關開會，所為凡呼氣酒精濃度逾每公升含零點五\n    五毫克時，即屬不能安全駕駛之決議。上開會議決議本身固僅屬檢警取締酒後駕\n    車之參考，尚無拘束法院之效力，惟以上開會議決議所採之標準，係參考美國、\n    德國及日本等國家所進行之酒精濃度與精神狀態之測試實驗，亦即，各項實驗均\n    發現凡呼氣中酒精濃度達每公升零點五五毫克時，就人之生理方面，已產生視覺\n    反應遲鈍、影像不能集中、同時不能看清前方路況及車旁照後鏡等狀況，及駕駛\n    能力已受有影響、肇事率已為一般人正常人之十倍之事實。被告於遭警攔測時，\n    呼氣中酒精濃度每公升達零點八六毫克，有酒測單一份附卷可參，依一般社會通\n    念，已達不能安全駕駛之程度。且被告遭查獲前有腳步不穩之情狀，於查獲、測\n    試或訊問過程亦有語無倫次、含糊不清、多話等情事，有警製刑法第一百八十五\n    條之三案件測試觀察紀錄表在卷可參，益證被告於酒後已達不能安全駕駛動力交\n    通工具之程度。而被告於酒後確有駕車之事實，業如前述，準此，本件事證明確\n    ，被告確有於飲用酒類後，已達不能安全駕駛動力交通工具而仍然駕駛之犯行，\n    應予依法論科。\n二、核被告所為，係犯刑法第一百八十五條之三服用酒類不能安全駕駛動力交通工具\n    而駕駛罪。原審以被告犯行明確而適用上開法條、同法第四十一條第一項前段（\n    原判決誤載為第四十二條第二項）、罰金罰鍰提高標準條例第二條之規定，判處\n    有期徒刑三月並諭知易科罰金之折算標準，經核認事用法及量刑均無不當，應予\n    維持。被告上訴陳稱因伊經濟壓力沈重，請求本院給予緩刑自新機會，惟伊前已\n    有如事實欄所載因酒後駕車遭科處刑罰之紀錄，有卷附臺灣高等法院被告全國前\n    案紀錄表可按，其猶不知警惕，仍再次酒醉駕車，顯無反省、悔悟之心，伊空言\n    表示伊已痛改前非、無再犯之虞云云，誠難遽信。本件上訴難認有理，應予駁回\n    。\n據上論斷，依刑事訴訟法第四百五十五條之一第一項、第三項，第三百六十八條，判\n決如主文。\n本案經檢察官蔡秋明到庭執行職務\n中      華      民      國      九十三      年    五    月    二十七    日\n                                      臺灣臺北地方法院交通法庭\n                                          審判長法  官  洪文慧\n                                                法  官  鄧德倩\n                                                法  官  陳婷玉\n右正本證明與原本無異。\n不得上訴\n                                                書記官  陳弘文\n中      華      民      國      九十三      年    五    月    二十七    日\n",
  "structure": {
    "main": "上訴駁回。",
    "fact": "一、甲○○前於民國九十一年間因酒醉駕車觸犯公共危險罪，經臺灣桃園地方法院以\n    九十一年度桃交簡字第二一五三號判決判處拘役五十八日確定，詎其猶不知戒慎\n    ，於九十二年九月十七日某時在不詳地點服用酒類後，已達思考、個性行為改變\n    而無法安全駕駛動力交通工具之程度，仍於酒後騎乘動力交通工具即車號ＡＷＫ\n    －八二九號重型機車上路，嗣於同日下午四時五十八分許在臺北市○○區○○街\n    七十一巷口前因未戴安全帽而為警攔檢，並測得其呼氣所含酒精濃度達每公升零\n    點八六毫克。\n二、案經臺北市政府警察局信義分局報請臺灣臺北地方法院檢察署檢察官偵查後聲請\n    簡易判決處刑。",
    "reason": "一、訊據上訴人即被告甲○○對於在右揭時、地為警攔檢，測試其吐氣所含酒精成份\n    達每公升零點八六毫克之事實坦承不諱，並有吐氣所含酒精成份測試成果表壹紙\n    在卷可資佐證。按刑法第一百八十五條之三所規定服用酒類，不能安全駕駛動力\n    交通工具而駕駛者，應負刑事責任，揆其立法目的本在藉抽象危險犯之犯罪構成\n    要件，以嚇阻酒後駕車者對道路交通安全之危害，本不以發生實害為必要。而所\n    謂不能安全駕駛之認定，並無一定之數值可供界定，而係由法院以一般社會通念\n    之客觀標準，足生公共危險時即足。目前行政機關所取締酒後駕車之參考標準，\n    係依法務部於八十八年五月十日邀集司法院刑事廳、交通部、行政院衛生署、內\n    政部警政署及中央警察大學等機關開會，所為凡呼氣酒精濃度逾每公升含零點五\n    五毫克時，即屬不能安全駕駛之決議。上開會議決議本身固僅屬檢警取締酒後駕\n    車之參考，尚無拘束法院之效力，惟以上開會議決議所採之標準，係參考美國、\n    德國及日本等國家所進行之酒精濃度與精神狀態之測試實驗，亦即，各項實驗均\n    發現凡呼氣中酒精濃度達每公升零點五五毫克時，就人之生理方面，已產生視覺\n    反應遲鈍、影像不能集中、同時不能看清前方路況及車旁照後鏡等狀況，及駕駛\n    能力已受有影響、肇事率已為一般人正常人之十倍之事實。被告於遭警攔測時，\n    呼氣中酒精濃度每公升達零點八六毫克，有酒測單一份附卷可參，依一般社會通\n    念，已達不能安全駕駛之程度。且被告遭查獲前有腳步不穩之情狀，於查獲、測\n    試或訊問過程亦有語無倫次、含糊不清、多話等情事，有警製刑法第一百八十五\n    條之三案件測試觀察紀錄表在卷可參，益證被告於酒後已達不能安全駕駛動力交\n    通工具之程度。而被告於酒後確有駕車之事實，業如前述，準此，本件事證明確\n    ，被告確有於飲用酒類後，已達不能安全駕駛動力交通工具而仍然駕駛之犯行，\n    應予依法論科。\n二、核被告所為，係犯刑法第一百八十五條之三服用酒類不能安全駕駛動力交通工具\n    而駕駛罪。原審以被告犯行明確而適用上開法條、同法第四十一條第一項前段（\n    原判決誤載為第四十二條第二項）、罰金罰鍰提高標準條例第二條之規定，判處\n    有期徒刑三月並諭知易科罰金之折算標準，經核認事用法及量刑均無不當，應予\n    維持。被告上訴陳稱因伊經濟壓力沈重，請求本院給予緩刑自新機會，惟伊前已\n    有如事實欄所載因酒後駕車遭科處刑罰之紀錄，有卷附臺灣高等法院被告全國前\n    案紀錄表可按，其猶不知警惕，仍再次酒醉駕車，顯無反省、悔悟之心，伊空言\n    表示伊已痛改前非、無再犯之虞云云，誠難遽信。本件上訴難認有理，應予駁回\n    。\n據上論斷，依刑事訴訟法第四百五十五條之一第一項、第三項，第三百六十八條，判\n決如主文。\n本案經檢察官蔡秋明到庭執行職務\n中      華      民      國      九十三      年    五    月    二十七    日\n                                      臺灣臺北地方法院交通法庭\n                                          審判長法  官  洪文慧\n                                                法  官  鄧德倩\n                                                法  官  陳婷玉\n右正本證明與原本無異。\n不得上訴\n                                                書記官  陳弘文"
  },
  "search": "臺灣臺北地方法院刑事判決九十三年度交簡上字第二三號上訴人即被告甲○○右列上訴人即被告因公共危險案件，不服本院臺北簡易庭於民國九十三年二月二十四日所為九十三年度北交簡字第二四八號第一審刑事簡易判決（聲請簡易判決處刑案號：九十二年度偵字第二四八八一號），提起上訴，本院管轄第二審之合議庭判決如左：主文上訴駁回。事實一、甲○○前於民國九十一年間因酒醉駕車觸犯公共危險罪，經臺灣桃園地方法院以九十一年度桃交簡字第二一五三號判決判處拘役五十八日確定，詎其猶不知戒慎，於九十二年九月十七日某時在不詳地點服用酒類後，已達思考、個性行為改變而無法安全駕駛動力交通工具之程度，仍於酒後騎乘動力交通工具即車號ＡＷＫ－八二九號重型機車上路，嗣於同日下午四時五十八分許在臺北市○○區○○街七十一巷口前因未戴安全帽而為警攔檢，並測得其呼氣所含酒精濃度達每公升零點八六毫克。二、案經臺北市政府警察局信義分局報請臺灣臺北地方法院檢察署檢察官偵查後聲請簡易判決處刑。理由一、訊據上訴人即被告甲○○對於在右揭時、地為警攔檢，測試其吐氣所含酒精成份達每公升零點八六毫克之事實坦承不諱，並有吐氣所含酒精成份測試成果表壹紙在卷可資佐證。按刑法第一百八十五條之三所規定服用酒類，不能安全駕駛動力交通工具而駕駛者，應負刑事責任，揆其立法目的本在藉抽象危險犯之犯罪構成要件，以嚇阻酒後駕車者對道路交通安全之危害，本不以發生實害為必要。而所謂不能安全駕駛之認定，並無一定之數值可供界定，而係由法院以一般社會通念之客觀標準，足生公共危險時即足。目前行政機關所取締酒後駕車之參考標準，係依法務部於八十八年五月十日邀集司法院刑事廳、交通部、行政院衛生署、內政部警政署及中央警察大學等機關開會，所為凡呼氣酒精濃度逾每公升含零點五五毫克時，即屬不能安全駕駛之決議。上開會議決議本身固僅屬檢警取締酒後駕車之參考，尚無拘束法院之效力，惟以上開會議決議所採之標準，係參考美國、德國及日本等國家所進行之酒精濃度與精神狀態之測試實驗，亦即，各項實驗均發現凡呼氣中酒精濃度達每公升零點五五毫克時，就人之生理方面，已產生視覺反應遲鈍、影像不能集中、同時不能看清前方路況及車旁照後鏡等狀況，及駕駛能力已受有影響、肇事率已為一般人正常人之十倍之事實。被告於遭警攔測時，呼氣中酒精濃度每公升達零點八六毫克，有酒測單一份附卷可參，依一般社會通念，已達不能安全駕駛之程度。且被告遭查獲前有腳步不穩之情狀，於查獲、測試或訊問過程亦有語無倫次、含糊不清、多話等情事，有警製刑法第一百八十五條之三案件測試觀察紀錄表在卷可參，益證被告於酒後已達不能安全駕駛動力交通工具之程度。而被告於酒後確有駕車之事實，業如前述，準此，本件事證明確，被告確有於飲用酒類後，已達不能安全駕駛動力交通工具而仍然駕駛之犯行，應予依法論科。二、核被告所為，係犯刑法第一百八十五條之三服用酒類不能安全駕駛動力交通工具而駕駛罪。原審以被告犯行明確而適用上開法條、同法第四十一條第一項前段（原判決誤載為第四十二條第二項）、罰金罰鍰提高標準條例第二條之規定，判處有期徒刑三月並諭知易科罰金之折算標準，經核認事用法及量刑均無不當，應予維持。被告上訴陳稱因伊經濟壓力沈重，請求本院給予緩刑自新機會，惟伊前已有如事實欄所載因酒後駕車遭科處刑罰之紀錄，有卷附臺灣高等法院被告全國前案紀錄表可按，其猶不知警惕，仍再次酒醉駕車，顯無反省、悔悟之心，伊空言表示伊已痛改前非、無再犯之虞云云，誠難遽信。本件上訴難認有理，應予駁回。據上論斷，依刑事訴訟法第四百五十五條之一第一項、第三項，第三百六十八條，判決如主文。本案經檢察官蔡秋明到庭執行職務中華民國九十三年五月二十七日臺灣臺北地方法院交通法庭審判長法官洪文慧法官鄧德倩法官陳婷玉右正本證明與原本無異。不得上訴書記官陳弘文中華民國九十三年五月二十七日",
  "characters": {
    "judges": [
      "洪文慧",
      "鄧德倩",
      "陳婷玉"
    ],
    "prosecutors": [
      "蔡秋明"
    ],
    "lawyers": [

    ],
    "clerks": [
      "陳弘文"
    ],
    "plaintiffs": [

    ],
    "defendants": [
      "甲"
    ],
    "prosecutor_office": [

    ],
    "creditors": [

    ],
    "debtors": [

    ],
    "judicial_associate_officer": [

    ]
  },
  "adjudged_at": "2004-05-27",
  "created_at": "2016-02-05 19:50:28",
  "updated_at": "2016-02-05 19:50:28"
}