{
  "identify": "KSD-93-簡-5563-20041129-1",
  "court": {
    "name": "臺灣高雄地方法院",
    "code": "KSD"
  },
  "division": {
    "name": "刑事",
    "code": "M"
  },
  "year": 93,
  "word": "簡",
  "number": "5563",
  "jcheck": "1",
  "reason": "竊盜",
  "content": "臺灣高雄地方法院刑事簡易判決                    九十三年度簡字第五五六三號\n    聲  請  人  臺灣高雄地方法院檢察署檢察官\n    被      告  甲○○\n右列被告因竊盜案件，經檢察官聲請以簡易判決處刑（九十三年度偵字第二二四七九\n號），本院判決如左：\n    主  文\n甲○○共同竊盜，累犯，處拘役伍拾日，如易科罰金，以參佰元折算壹日。\n    事實及理由\n一、本件犯罪事實及證據均引用檢察官聲請簡易判決處刑書之記載（如附件）。\n二、核被告所為，係犯刑法第三百二十條第一項竊盜罪。被告與另案共同被告余鎮明\n    就上開犯行，有犯意聯絡及行為分擔，為共同正犯。又被告前於民國（下同）九\n    十年間因脫逃案件，經臺灣台南地方法院判處有期徒刑三月確定，於九十年十二\n    月二十七日執行完畢，有臺灣高等法院全國前案紀錄表在卷可稽，其於執行完畢\n    後五年內，再犯有期徒刑以上之本罪，為累犯，依法應加重其刑。爰審酌被告正\n    值青壯年，不思以己力謀生賺錢，竟擅自竊取他人財物，本不宜寬恕，惟念其所\n    竊之物價值尚非鉅大，及其犯本罪之動機、目的、手段，及其生活狀況、品行、\n    智識程度等一切情狀，量處如主文所示之刑，並諭知易科罰金之折算標準，以示\n    儆懲。\n三、依刑事訴訟法第四百四十九條第一項前段、第三項、第四百五十四條第二項，刑\n    法第二十八條、第三百二十條第一項、第四十七條、第四十一條第一項前段，罰\n    金罰鍰提高標準條例第一條前段、第二條，逕以簡易判決處刑如主文。\n五、如不服本判決，得自判決送達之日起十日內，向本院提出上訴狀\n中      華      民      國    九十三    年     十一     月    二十九    日\n                                    臺灣高雄地方法院高雄簡易庭\n                                        法  官  蔡川富\n右正本證明與原本無異。\n                                        書記官  邱秋珍\n中      華      民      國    九十三    年     十一     月    二十九    日\n附錄本判決論罪之法條：\n刑法第三百二十條第一項\n意圖為自己或第三人不法之所有，而竊取他人之動產者，為竊盜罪，處五年以下有期\n徒刑、拘役或五百元以下罰金。\n",
  "structure": {
    "main": "甲○○共同竊盜，累犯，處拘役伍拾日，如易科罰金，以參佰元折算壹日。",
    "fact": "一、本件犯罪事實及證據均引用檢察官聲請簡易判決處刑書之記載（如附件）。\n二、核被告所為，係犯刑法第三百二十條第一項竊盜罪。被告與另案共同被告余鎮明\n    就上開犯行，有犯意聯絡及行為分擔，為共同正犯。又被告前於民國（下同）九\n    十年間因脫逃案件，經臺灣台南地方法院判處有期徒刑三月確定，於九十年十二\n    月二十七日執行完畢，有臺灣高等法院全國前案紀錄表在卷可稽，其於執行完畢\n    後五年內，再犯有期徒刑以上之本罪，為累犯，依法應加重其刑。爰審酌被告正\n    值青壯年，不思以己力謀生賺錢，竟擅自竊取他人財物，本不宜寬恕，惟念其所\n    竊之物價值尚非鉅大，及其犯本罪之動機、目的、手段，及其生活狀況、品行、\n    智識程度等一切情狀，量處如主文所示之刑，並諭知易科罰金之折算標準，以示\n    儆懲。\n三、依刑事訴訟法第四百四十九條第一項前段、第三項、第四百五十四條第二項，刑\n    法第二十八條、第三百二十條第一項、第四十七條、第四十一條第一項前段，罰\n    金罰鍰提高標準條例第一條前段、第二條，逕以簡易判決處刑如主文。\n五、如不服本判決，得自判決送達之日起十日內，向本院提出上訴狀",
    "reason": "一、本件犯罪事實及證據均引用檢察官聲請簡易判決處刑書之記載（如附件）。\n二、核被告所為，係犯刑法第三百二十條第一項竊盜罪。被告與另案共同被告余鎮明\n    就上開犯行，有犯意聯絡及行為分擔，為共同正犯。又被告前於民國（下同）九\n    十年間因脫逃案件，經臺灣台南地方法院判處有期徒刑三月確定，於九十年十二\n    月二十七日執行完畢，有臺灣高等法院全國前案紀錄表在卷可稽，其於執行完畢\n    後五年內，再犯有期徒刑以上之本罪，為累犯，依法應加重其刑。爰審酌被告正\n    值青壯年，不思以己力謀生賺錢，竟擅自竊取他人財物，本不宜寬恕，惟念其所\n    竊之物價值尚非鉅大，及其犯本罪之動機、目的、手段，及其生活狀況、品行、\n    智識程度等一切情狀，量處如主文所示之刑，並諭知易科罰金之折算標準，以示\n    儆懲。\n三、依刑事訴訟法第四百四十九條第一項前段、第三項、第四百五十四條第二項，刑\n    法第二十八條、第三百二十條第一項、第四十七條、第四十一條第一項前段，罰\n    金罰鍰提高標準條例第一條前段、第二條，逕以簡易判決處刑如主文。\n五、如不服本判決，得自判決送達之日起十日內，向本院提出上訴狀"
  },
  "search": "臺灣高雄地方法院刑事簡易判決九十三年度簡字第五五六三號聲請人臺灣高雄地方法院檢察署檢察官被告甲○○右列被告因竊盜案件，經檢察官聲請以簡易判決處刑（九十三年度偵字第二二四七九號），本院判決如左：主文甲○○共同竊盜，累犯，處拘役伍拾日，如易科罰金，以參佰元折算壹日。事實及理由一、本件犯罪事實及證據均引用檢察官聲請簡易判決處刑書之記載（如附件）。二、核被告所為，係犯刑法第三百二十條第一項竊盜罪。被告與另案共同被告余鎮明就上開犯行，有犯意聯絡及行為分擔，為共同正犯。又被告前於民國（下同）九十年間因脫逃案件，經臺灣台南地方法院判處有期徒刑三月確定，於九十年十二月二十七日執行完畢，有臺灣高等法院全國前案紀錄表在卷可稽，其於執行完畢後五年內，再犯有期徒刑以上之本罪，為累犯，依法應加重其刑。爰審酌被告正值青壯年，不思以己力謀生賺錢，竟擅自竊取他人財物，本不宜寬恕，惟念其所竊之物價值尚非鉅大，及其犯本罪之動機、目的、手段，及其生活狀況、品行、智識程度等一切情狀，量處如主文所示之刑，並諭知易科罰金之折算標準，以示儆懲。三、依刑事訴訟法第四百四十九條第一項前段、第三項、第四百五十四條第二項，刑法第二十八條、第三百二十條第一項、第四十七條、第四十一條第一項前段，罰金罰鍰提高標準條例第一條前段、第二條，逕以簡易判決處刑如主文。五、如不服本判決，得自判決送達之日起十日內，向本院提出上訴狀中華民國九十三年十一月二十九日臺灣高雄地方法院高雄簡易庭法官蔡川富右正本證明與原本無異。書記官邱秋珍中華民國九十三年十一月二十九日附錄本判決論罪之法條：刑法第三百二十條第一項意圖為自己或第三人不法之所有，而竊取他人之動產者，為竊盜罪，處五年以下有期徒刑、拘役或五百元以下罰金。",
  "characters": {
    "judges": [
      "蔡川富"
    ],
    "prosecutors": [

    ],
    "lawyers": [

    ],
    "clerks": [
      "邱秋珍"
    ],
    "plaintiffs": [

    ],
    "defendants": [
      "甲○○",
      "右列被告因竊盜案件，經檢察官聲請以簡易判決處刑（九十三年度偵字第二二四七九",
      "號），本院判決如左："
    ],
    "prosecutor_office": [
      "臺灣高雄地方法院檢察署檢察官"
    ],
    "creditors": [

    ],
    "debtors": [

    ],
    "judicial_associate_officer": [

    ]
  },
  "adjudged_at": "2004-11-29",
  "created_at": "2016-02-06 03:52:43",
  "updated_at": "2016-02-06 03:52:43"
}