{
  "identify": "KSD-94-交簡-1108-20050421-1",
  "court": {
    "name": "臺灣高雄地方法院",
    "code": "KSD"
  },
  "division": {
    "name": "刑事",
    "code": "M"
  },
  "year": 94,
  "word": "交簡",
  "number": "1108",
  "jcheck": "1",
  "reason": "公共危險",
  "content": "臺灣高雄地方法院刑事簡易判決        94年度交簡字第1108號\n聲  請  人  臺灣高雄地方法院檢察署檢察官\n被      告  甲○○  男  27歲.\n上列被告因公共危險案件，經檢察官聲請以簡易判決處刑（\n93年度偵字第25417號），本院判決如下：\n    主  文\n甲○○服用酒類，不能安全駕駛動力交通工具而駕駛，處拘役\n拾日，如易科罰金，以參佰元折算壹日。\n    事實及理由\n一、本件犯罪事實及證據，除補充「飲用啤酒二至三瓶」及更正\n    為「甲○○直至93年12月20日凌晨零時45分許接受酒測」外\n    ，餘均引用檢察官聲請簡易判決處刑書之記載（如附件）。\n二、核被告所為，係犯刑法第一百八十五條之三服用酒類不能\n    安全駕駛動力交通工具而駕駛罪。爰審酌被告前因酒後駕車\n    案，業經臺灣高雄地方法院檢察署檢察官以93年度偵字第\n    14510 號緩起訴處分，應執行罰金新臺幣2 萬元在案，詎仍\n    不知悔改，又另行起意再犯本件酒後駕車案，於案發當日（\n    93 年12 月19日）晚間7 時許，因不勝酒力致肇事，遲至翌\n    日凌晨零時45分許始願意配合酒測，態度不佳，顯無悔改之\n    意，惟念其酒後騎乘機車，對公眾行之安全所生危害較小等\n    一切情狀，量處如主文所示之刑，並諭知易科罰金之折算標\n    準。\n三、結論：依刑事訴訟法第449條第1項前段、第3項、第454條\n    第2項，刑法第185條之3、第41條第1項前段，罰金罰鍰提\n    高標準條例第2條規定，逕以簡易判決處如主文所示之刑。\n中    華    民    國    94    年    4     月    21    日\n                       臺灣高雄地方法院交通法庭\n                                  法  官  郭瓊徽\n中    華    民    國    94    年    4     月    21    日\n以上正本證明與原本無異。\n如不服本判決，應於收受送達後10日內向本院提出上訴書狀。\n                                  書記官  陳瓊芳\n附錄本判決論罪之法條：\n中華民國刑法第一百八十五條之三\n    服用毒品、麻醉藥品、酒類或其他相類之物，不能安全駕駛\n    動力交通工具而駕駛    者，處一年以下有期徒刑、拘役或\n    三萬元以下罰金。\n",
  "structure": {
    "main": "甲○○服用酒類，不能安全駕駛動力交通工具而駕駛，處拘役\n拾日，如易科罰金，以參佰元折算壹日。",
    "fact": "一、本件犯罪事實及證據，除補充「飲用啤酒二至三瓶」及更正\n    為「甲○○直至93年12月20日凌晨零時45分許接受酒測」外\n    ，餘均引用檢察官聲請簡易判決處刑書之記載（如附件）。\n二、核被告所為，係犯刑法第一百八十五條之三服用酒類不能\n    安全駕駛動力交通工具而駕駛罪。爰審酌被告前因酒後駕車\n    案，業經臺灣高雄地方法院檢察署檢察官以93年度偵字第\n    14510 號緩起訴處分，應執行罰金新臺幣2 萬元在案，詎仍\n    不知悔改，又另行起意再犯本件酒後駕車案，於案發當日（\n    93 年12 月19日）晚間7 時許，因不勝酒力致肇事，遲至翌\n    日凌晨零時45分許始願意配合酒測，態度不佳，顯無悔改之\n    意，惟念其酒後騎乘機車，對公眾行之安全所生危害較小等\n    一切情狀，量處如主文所示之刑，並諭知易科罰金之折算標\n    準。\n三、結論：依刑事訴訟法第449條第1項前段、第3項、第454條\n    第2項，刑法第185條之3、第41條第1項前段，罰金罰鍰提\n    高標準條例第2條規定，逕以簡易判決處如主文所示之刑。",
    "reason": "一、本件犯罪事實及證據，除補充「飲用啤酒二至三瓶」及更正\n    為「甲○○直至93年12月20日凌晨零時45分許接受酒測」外\n    ，餘均引用檢察官聲請簡易判決處刑書之記載（如附件）。\n二、核被告所為，係犯刑法第一百八十五條之三服用酒類不能\n    安全駕駛動力交通工具而駕駛罪。爰審酌被告前因酒後駕車\n    案，業經臺灣高雄地方法院檢察署檢察官以93年度偵字第\n    14510 號緩起訴處分，應執行罰金新臺幣2 萬元在案，詎仍\n    不知悔改，又另行起意再犯本件酒後駕車案，於案發當日（\n    93 年12 月19日）晚間7 時許，因不勝酒力致肇事，遲至翌\n    日凌晨零時45分許始願意配合酒測，態度不佳，顯無悔改之\n    意，惟念其酒後騎乘機車，對公眾行之安全所生危害較小等\n    一切情狀，量處如主文所示之刑，並諭知易科罰金之折算標\n    準。\n三、結論：依刑事訴訟法第449條第1項前段、第3項、第454條\n    第2項，刑法第185條之3、第41條第1項前段，罰金罰鍰提\n    高標準條例第2條規定，逕以簡易判決處如主文所示之刑。"
  },
  "search": "臺灣高雄地方法院刑事簡易判決94年度交簡字第1108號聲請人臺灣高雄地方法院檢察署檢察官被告甲○○男27歲.上列被告因公共危險案件，經檢察官聲請以簡易判決處刑（93年度偵字第25417號），本院判決如下：主文甲○○服用酒類，不能安全駕駛動力交通工具而駕駛，處拘役拾日，如易科罰金，以參佰元折算壹日。事實及理由一、本件犯罪事實及證據，除補充「飲用啤酒二至三瓶」及更正為「甲○○直至93年12月20日凌晨零時45分許接受酒測」外，餘均引用檢察官聲請簡易判決處刑書之記載（如附件）。二、核被告所為，係犯刑法第一百八十五條之三服用酒類不能安全駕駛動力交通工具而駕駛罪。爰審酌被告前因酒後駕車案，業經臺灣高雄地方法院檢察署檢察官以93年度偵字第14510號緩起訴處分，應執行罰金新臺幣2萬元在案，詎仍不知悔改，又另行起意再犯本件酒後駕車案，於案發當日（93年12月19日）晚間7時許，因不勝酒力致肇事，遲至翌日凌晨零時45分許始願意配合酒測，態度不佳，顯無悔改之意，惟念其酒後騎乘機車，對公眾行之安全所生危害較小等一切情狀，量處如主文所示之刑，並諭知易科罰金之折算標準。三、結論：依刑事訴訟法第449條第1項前段、第3項、第454條第2項，刑法第185條之3、第41條第1項前段，罰金罰鍰提高標準條例第2條規定，逕以簡易判決處如主文所示之刑。中華民國94年4月21日臺灣高雄地方法院交通法庭法官郭瓊徽中華民國94年4月21日以上正本證明與原本無異。如不服本判決，應於收受送達後10日內向本院提出上訴書狀。書記官陳瓊芳附錄本判決論罪之法條：中華民國刑法第一百八十五條之三服用毒品、麻醉藥品、酒類或其他相類之物，不能安全駕駛動力交通工具而駕駛者，處一年以下有期徒刑、拘役或三萬元以下罰金。",
  "characters": {
    "judges": [
      "郭瓊徽"
    ],
    "prosecutors": [

    ],
    "lawyers": [

    ],
    "clerks": [
      "陳瓊芳"
    ],
    "plaintiffs": [

    ],
    "defendants": [
      "甲○○  男  27歲."
    ],
    "prosecutor_office": [
      "臺灣高雄地方法院檢察署檢察官"
    ],
    "creditors": [

    ],
    "debtors": [

    ],
    "judicial_associate_officer": [

    ]
  },
  "adjudged_at": "2005-04-21",
  "created_at": "2016-02-06 18:04:59",
  "updated_at": "2016-02-06 18:04:59"
}