{
  "identify": "ILD-100-交簡-724-20111115-1",
  "court": {
    "name": "臺灣宜蘭地方法院",
    "code": "ILD"
  },
  "division": {
    "name": "刑事",
    "code": "M"
  },
  "year": 100,
  "word": "交簡",
  "number": "724",
  "jcheck": "1",
  "reason": "公共危險",
  "content": "臺灣宜蘭地方法院刑事簡易判決        100年度交簡字第724號\n聲  請  人  臺灣宜蘭地方法院檢察署檢察官\n被      告  吳明育\n上列被告因公共危險案件，經檢察官聲請以簡易判決處刑（100\n年度偵字第4116號），本院判決如下：\n    主      文\n吳明育服用酒類，不能安全駕駛動力交通工具而駕駛，處有期徒\n刑貳月，如易科罰金，以新臺幣壹仟元折算壹日。\n    事實及理由\n一、本件犯罪事實及證據均引用檢察官聲請簡易判決處刑書之記\n    載（如附件聲請書）。\n二、核被告吳明育所為，係犯刑法第185 條之3 之服用酒類不能\n    安全駕駛動力交通工具而駕駛罪。爰審酌被告前因公共危險\n    案件，經臺灣宜蘭地方法院檢察署檢察官以100 年度偵字第\n    3027號為緩起訴處分確定，目前仍在緩起訴期間，有臺灣宜\n    蘭地方法院檢察署刑案資料查註紀錄表、臺灣高等法院被告\n    前案紀錄表各1 份附卷可按，再為本件公共危險犯行，顯見\n    其惡性非輕，又被告服用酒類後，於不能安全駕駛之情形下\n    ，竟仍貿然騎乘重型機車上路，危及道路交通安全，且乏尊\n    重其他用路人生命、財產安全之觀念，所為非是，及被告因\n    肇事送醫後，經採集其血液送驗，測得血液中之酒精濃度為\n    329MG/DL（換算呼氣所含酒精成分達每公升1.645 毫克）之\n    犯罪情節，被告之智識程度、犯罪所生危害、素行、犯後態\n    度等一切情狀，量處如主文所示之刑，並諭知易科罰金之折\n    算標準，以示懲儆。\n三、據上論斷，應依刑事訴訟法第449 條第1 項前段、第3 項、\n    第454 條第2 項，刑法第185 條之3 、第41條第1 項前段，\n    刑法施行法第1 條之1 第1 項，逕以簡易判決處刑如主文。\n四、如不服本判決，應於判決送達後10日內，向本院提出上訴狀\n    ，上訴於本院合議庭。\n中    華    民    國  100     年    11    月    15    日\n                  簡易庭  法  官  張淑華\n以上正本證明與原本無異。\n                          書記官  葉書毓\n中    華    民    國  100     年    11    月    15    日\n附錄論罪科刑條文：\n刑法第185條之3\n服用毒品、麻醉藥品、酒類或其他相類之物，不能安全駕駛動力\n交通工具而駕駛者，處一年以下有期徒刑、拘役或科或併科十五\n萬元以下罰金。",
  "structure": {
    "main": "吳明育服用酒類，不能安全駕駛動力交通工具而駕駛，處有期徒\n刑貳月，如易科罰金，以新臺幣壹仟元折算壹日。",
    "fact": "一、本件犯罪事實及證據均引用檢察官聲請簡易判決處刑書之記\n    載（如附件聲請書）。\n二、核被告吳明育所為，係犯刑法第185 條之3 之服用酒類不能\n    安全駕駛動力交通工具而駕駛罪。爰審酌被告前因公共危險\n    案件，經臺灣宜蘭地方法院檢察署檢察官以100 年度偵字第\n    3027號為緩起訴處分確定，目前仍在緩起訴期間，有臺灣宜\n    蘭地方法院檢察署刑案資料查註紀錄表、臺灣高等法院被告\n    前案紀錄表各1 份附卷可按，再為本件公共危險犯行，顯見\n    其惡性非輕，又被告服用酒類後，於不能安全駕駛之情形下\n    ，竟仍貿然騎乘重型機車上路，危及道路交通安全，且乏尊\n    重其他用路人生命、財產安全之觀念，所為非是，及被告因\n    肇事送醫後，經採集其血液送驗，測得血液中之酒精濃度為\n    329MG/DL（換算呼氣所含酒精成分達每公升1.645 毫克）之\n    犯罪情節，被告之智識程度、犯罪所生危害、素行、犯後態\n    度等一切情狀，量處如主文所示之刑，並諭知易科罰金之折\n    算標準，以示懲儆。\n三、據上論斷，應依刑事訴訟法第449 條第1 項前段、第3 項、\n    第454 條第2 項，刑法第185 條之3 、第41條第1 項前段，\n    刑法施行法第1 條之1 第1 項，逕以簡易判決處刑如主文。\n四、如不服本判決，應於判決送達後10日內，向本院提出上訴狀\n    ，上訴於本院合議庭。",
    "reason": "一、本件犯罪事實及證據均引用檢察官聲請簡易判決處刑書之記\n    載（如附件聲請書）。\n二、核被告吳明育所為，係犯刑法第185 條之3 之服用酒類不能\n    安全駕駛動力交通工具而駕駛罪。爰審酌被告前因公共危險\n    案件，經臺灣宜蘭地方法院檢察署檢察官以100 年度偵字第\n    3027號為緩起訴處分確定，目前仍在緩起訴期間，有臺灣宜\n    蘭地方法院檢察署刑案資料查註紀錄表、臺灣高等法院被告\n    前案紀錄表各1 份附卷可按，再為本件公共危險犯行，顯見\n    其惡性非輕，又被告服用酒類後，於不能安全駕駛之情形下\n    ，竟仍貿然騎乘重型機車上路，危及道路交通安全，且乏尊\n    重其他用路人生命、財產安全之觀念，所為非是，及被告因\n    肇事送醫後，經採集其血液送驗，測得血液中之酒精濃度為\n    329MG/DL（換算呼氣所含酒精成分達每公升1.645 毫克）之\n    犯罪情節，被告之智識程度、犯罪所生危害、素行、犯後態\n    度等一切情狀，量處如主文所示之刑，並諭知易科罰金之折\n    算標準，以示懲儆。\n三、據上論斷，應依刑事訴訟法第449 條第1 項前段、第3 項、\n    第454 條第2 項，刑法第185 條之3 、第41條第1 項前段，\n    刑法施行法第1 條之1 第1 項，逕以簡易判決處刑如主文。\n四、如不服本判決，應於判決送達後10日內，向本院提出上訴狀\n    ，上訴於本院合議庭。"
  },
  "search": "臺灣宜蘭地方法院刑事簡易判決100年度交簡字第724號聲請人臺灣宜蘭地方法院檢察署檢察官被告吳明育上列被告因公共危險案件，經檢察官聲請以簡易判決處刑（100年度偵字第4116號），本院判決如下：主文吳明育服用酒類，不能安全駕駛動力交通工具而駕駛，處有期徒刑貳月，如易科罰金，以新臺幣壹仟元折算壹日。事實及理由一、本件犯罪事實及證據均引用檢察官聲請簡易判決處刑書之記載（如附件聲請書）。二、核被告吳明育所為，係犯刑法第185條之3之服用酒類不能安全駕駛動力交通工具而駕駛罪。爰審酌被告前因公共危險案件，經臺灣宜蘭地方法院檢察署檢察官以100年度偵字第3027號為緩起訴處分確定，目前仍在緩起訴期間，有臺灣宜蘭地方法院檢察署刑案資料查註紀錄表、臺灣高等法院被告前案紀錄表各1份附卷可按，再為本件公共危險犯行，顯見其惡性非輕，又被告服用酒類後，於不能安全駕駛之情形下，竟仍貿然騎乘重型機車上路，危及道路交通安全，且乏尊重其他用路人生命、財產安全之觀念，所為非是，及被告因肇事送醫後，經採集其血液送驗，測得血液中之酒精濃度為329MG/DL（換算呼氣所含酒精成分達每公升1.645毫克）之犯罪情節，被告之智識程度、犯罪所生危害、素行、犯後態度等一切情狀，量處如主文所示之刑，並諭知易科罰金之折算標準，以示懲儆。三、據上論斷，應依刑事訴訟法第449條第1項前段、第3項、第454條第2項，刑法第185條之3、第41條第1項前段，刑法施行法第1條之1第1項，逕以簡易判決處刑如主文。四、如不服本判決，應於判決送達後10日內，向本院提出上訴狀，上訴於本院合議庭。中華民國100年11月15日簡易庭法官張淑華以上正本證明與原本無異。書記官葉書毓中華民國100年11月15日附錄論罪科刑條文：刑法第185條之3服用毒品、麻醉藥品、酒類或其他相類之物，不能安全駕駛動力交通工具而駕駛者，處一年以下有期徒刑、拘役或科或併科十五萬元以下罰金。",
  "characters": {
    "judges": [
      "張淑華"
    ],
    "prosecutors": [

    ],
    "lawyers": [

    ],
    "clerks": [
      "葉書毓"
    ],
    "plaintiffs": [

    ],
    "defendants": [
      "吳明育"
    ],
    "prosecutor_office": [
      "臺灣宜蘭地方法院檢察署檢察官"
    ],
    "creditors": [

    ],
    "debtors": [

    ],
    "judicial_associate_officer": [

    ]
  },
  "adjudged_at": "2011-11-15",
  "created_at": "2016-02-12 21:31:59",
  "updated_at": "2016-02-12 21:31:59"
}