{
  "identify": "PCD-100-簡-7451-20111116-1",
  "court": {
    "name": "臺灣新北地方法院",
    "code": "PCD"
  },
  "division": {
    "name": "刑事",
    "code": "M"
  },
  "year": 100,
  "word": "簡",
  "number": "7451",
  "jcheck": "1",
  "reason": "竊盜",
  "content": "臺灣板橋地方法院刑事簡易判決         100年度簡字第7451號\n聲  請  人  臺灣板橋地方法院檢察署檢察官\n被      告  胡淑惠\n上列被告因竊盜案件，經檢察官聲請以簡易判決處刑（100 年度\n偵字第19698 號），本院判決如下：\n    主  文\n胡淑惠竊盜，處罰金新臺幣肆仟元，如易服勞役，以新臺幣壹仟\n元折算壹日。\n    事實及理由\n一、本件犯罪事實及證據，除於一、證據欄(二)所載「監視錄影器\n    翻拍照片共4 張」更正為「監視錄影器翻拍照片共12張」外\n    ；其餘均引用如附件檢察官聲請簡易判決處刑書之記載。\n二、核被告胡淑惠所為，係犯刑法第320條第1 項之普通竊盜罪。\n    爰審酌被告胡淑惠為成年人，竟不思以正當方式獲取所需，\n    反任意竊取他人之財物，所為並非可取，又其前亦曾因竊盜\n    案件，甫經臺灣臺北地方法院以99年度易字第2461號判處罰\n    金新臺幣（下同）3,000 元在案，有臺灣高等法院被告前案\n    紀錄表可佐，已難認素行良善，惟念其犯罪後坦承犯行、態\n    度良好，且本件其所竊得之財物價值非鉅，僅3,960 元，亦\n    業經其與店家達成和解，有本院辦理刑事案件電話紀錄查詢\n    表1 紙在卷可參，則其犯罪所生之危害已獲得填補且並未繼\n    續擴大，兼衡其本身患有雙極性情感異常之病症，有陳信任\n    精神科診所出具之診斷證明書可佐，暨其犯罪之動機、目的\n    、手段、高中畢業之智識程度、無業而家庭經濟勉持之生活\n    狀況（見偵查卷第3 頁）等一切情狀，量處如主文所示之刑\n    ，併諭知易服勞役之折算標準，以資懲儆。\n三、依刑事訴訟法第449 條第1 項前段、第3 項、第454 條第2\n    項，刑法第320 條第1 項、第42條第3 項，刑法施行法第1\n    條之1 ，逕以簡易判決處刑如主文。\n四、如不服本判決，得自收受送達之翌日起十日內向本院提出上\n    訴狀，上訴於本院第二審合議庭（須附繕本）。\n中    華    民    國   100    年    11    月    16    日\n                  刑事第二十三庭  法  官  詹蕙嘉\n上列正本證明與原本無異。\n                                  書記官  陳語嫣\n中    華    民    國   100    年    11    月    18    日\n附錄本案論罪科刑法條全文：\n刑法第320 條\n意圖為自己或第三人不法之所有，而竊取他人之動產者，為竊盜\n罪，處5 年以下有期徒刑、拘役或500 元以下罰金。\n意圖為自己或第三人不法之利益，而竊佔他人之不動產者，依前\n項之規定處斷。\n前二項之未遂犯罰之。\n附件：\n臺灣板橋地方法院檢察署檢察官聲請簡易判決處刑書\n                                    100年度偵字第19698號\n    被      告  胡淑惠  女  39歲(民國○○年○月○日生)\n                        住新北市三重區○○○街205巷1號4\n                        樓\n                        身分證統一編號：Ｚ000000000號\n上列被告因竊盜案件，業經偵查終結，認為宜聲請以簡易判決處\n刑，茲將犯罪事實及證據並所犯法條分敘如下：\n        犯罪事實\n一、胡淑惠意圖為自己不法所有之犯意，於民國100年7月1日12\n    時22分許，在新北市○○區○○路三段4號1樓之「康是美藥\n    妝店」店內，趁店員楊淑欽疏未注意之際，徒手竊取店內由\n    楊淑欽所管領之「伊斯蘭纖姿魔術14 2入組」1盒（價值新台\n    幣3960元），得手旋即離去，嗣經楊淑欽調閱該店內之監視\n    器畫面，始悉上情並報警處理，因而查獲。\n二、案經楊淑欽訴由新北市政府警察局三重分局移送偵辦。\n        證據並所犯法條\n一、證據\n(一)上揭犯罪事實，業據被告胡淑惠坦承不諱，核與證人即告訴\n    人楊淑欽於警詢中之證述相符。\n(二)並有查獲照片2張、監視錄影器翻拍照片共4張、贓物認領保\n    管單、新北市政府警察局三重分局搜索扣押筆錄、扣押物品\n    目錄表各1份在卷可稽，是被告犯嫌堪以認定。\n二、核被告所為，係犯刑法第320條第1項之竊盜罪嫌。\n三、依刑事訴訟法第451條第1項聲請逕以簡易判決處刑。\n    此  致\n臺灣板橋地方法院\n中    華    民    國   100    年    9     月    23    日\n                              檢察官  楊植鈞\n上正本證明與原本無異\n本件係依刑事訴訟法簡易程序辦理，法院簡易庭得不傳喚被告、\n輔佐人、告訴人、告發人等出庭，即以簡易判決處刑；被告、被\n害人、告訴人等對告訴乃論案件，如已達成民事和解而要撤回告\n訴或對非告訴乃論案件，認有受傳喚到庭陳述意見之必要時，請\n即另以書狀向臺灣板橋地方法院簡易法庭陳述或請求傳訊。\n中    華    民    國   100    年    10    月    3     日\n                              書記官\n附錄本案所犯法條全文：\n中華民國刑法第320條第1項\n意圖為自己或第三人不法之所有，而竊取他人之動產者，為竊盜\n罪，處5  年以下有期徒刑、拘役或 5 百元以下罰金。",
  "structure": {
    "main": "胡淑惠竊盜，處罰金新臺幣肆仟元，如易服勞役，以新臺幣壹仟\n元折算壹日。",
    "fact": "一、本件犯罪事實及證據，除於一、證據欄(二)所載「監視錄影器\n    翻拍照片共4 張」更正為「監視錄影器翻拍照片共12張」外\n    ；其餘均引用如附件檢察官聲請簡易判決處刑書之記載。\n二、核被告胡淑惠所為，係犯刑法第320條第1 項之普通竊盜罪。\n    爰審酌被告胡淑惠為成年人，竟不思以正當方式獲取所需，\n    反任意竊取他人之財物，所為並非可取，又其前亦曾因竊盜\n    案件，甫經臺灣臺北地方法院以99年度易字第2461號判處罰\n    金新臺幣（下同）3,000 元在案，有臺灣高等法院被告前案\n    紀錄表可佐，已難認素行良善，惟念其犯罪後坦承犯行、態\n    度良好，且本件其所竊得之財物價值非鉅，僅3,960 元，亦\n    業經其與店家達成和解，有本院辦理刑事案件電話紀錄查詢\n    表1 紙在卷可參，則其犯罪所生之危害已獲得填補且並未繼\n    續擴大，兼衡其本身患有雙極性情感異常之病症，有陳信任\n    精神科診所出具之診斷證明書可佐，暨其犯罪之動機、目的\n    、手段、高中畢業之智識程度、無業而家庭經濟勉持之生活\n    狀況（見偵查卷第3 頁）等一切情狀，量處如主文所示之刑\n    ，併諭知易服勞役之折算標準，以資懲儆。\n三、依刑事訴訟法第449 條第1 項前段、第3 項、第454 條第2\n    項，刑法第320 條第1 項、第42條第3 項，刑法施行法第1\n    條之1 ，逕以簡易判決處刑如主文。\n四、如不服本判決，得自收受送達之翌日起十日內向本院提出上\n    訴狀，上訴於本院第二審合議庭（須附繕本）。",
    "reason": "一、本件犯罪事實及證據，除於一、證據欄(二)所載「監視錄影器\n    翻拍照片共4 張」更正為「監視錄影器翻拍照片共12張」外\n    ；其餘均引用如附件檢察官聲請簡易判決處刑書之記載。\n二、核被告胡淑惠所為，係犯刑法第320條第1 項之普通竊盜罪。\n    爰審酌被告胡淑惠為成年人，竟不思以正當方式獲取所需，\n    反任意竊取他人之財物，所為並非可取，又其前亦曾因竊盜\n    案件，甫經臺灣臺北地方法院以99年度易字第2461號判處罰\n    金新臺幣（下同）3,000 元在案，有臺灣高等法院被告前案\n    紀錄表可佐，已難認素行良善，惟念其犯罪後坦承犯行、態\n    度良好，且本件其所竊得之財物價值非鉅，僅3,960 元，亦\n    業經其與店家達成和解，有本院辦理刑事案件電話紀錄查詢\n    表1 紙在卷可參，則其犯罪所生之危害已獲得填補且並未繼\n    續擴大，兼衡其本身患有雙極性情感異常之病症，有陳信任\n    精神科診所出具之診斷證明書可佐，暨其犯罪之動機、目的\n    、手段、高中畢業之智識程度、無業而家庭經濟勉持之生活\n    狀況（見偵查卷第3 頁）等一切情狀，量處如主文所示之刑\n    ，併諭知易服勞役之折算標準，以資懲儆。\n三、依刑事訴訟法第449 條第1 項前段、第3 項、第454 條第2\n    項，刑法第320 條第1 項、第42條第3 項，刑法施行法第1\n    條之1 ，逕以簡易判決處刑如主文。\n四、如不服本判決，得自收受送達之翌日起十日內向本院提出上\n    訴狀，上訴於本院第二審合議庭（須附繕本）。"
  },
  "search": "臺灣板橋地方法院刑事簡易判決100年度簡字第7451號聲請人臺灣板橋地方法院檢察署檢察官被告胡淑惠上列被告因竊盜案件，經檢察官聲請以簡易判決處刑（100年度偵字第19698號），本院判決如下：主文胡淑惠竊盜，處罰金新臺幣肆仟元，如易服勞役，以新臺幣壹仟元折算壹日。事實及理由一、本件犯罪事實及證據，除於一、證據欄(二)所載「監視錄影器翻拍照片共4張」更正為「監視錄影器翻拍照片共12張」外；其餘均引用如附件檢察官聲請簡易判決處刑書之記載。二、核被告胡淑惠所為，係犯刑法第320條第1項之普通竊盜罪。爰審酌被告胡淑惠為成年人，竟不思以正當方式獲取所需，反任意竊取他人之財物，所為並非可取，又其前亦曾因竊盜案件，甫經臺灣臺北地方法院以99年度易字第2461號判處罰金新臺幣（下同）3,000元在案，有臺灣高等法院被告前案紀錄表可佐，已難認素行良善，惟念其犯罪後坦承犯行、態度良好，且本件其所竊得之財物價值非鉅，僅3,960元，亦業經其與店家達成和解，有本院辦理刑事案件電話紀錄查詢表1紙在卷可參，則其犯罪所生之危害已獲得填補且並未繼續擴大，兼衡其本身患有雙極性情感異常之病症，有陳信任精神科診所出具之診斷證明書可佐，暨其犯罪之動機、目的、手段、高中畢業之智識程度、無業而家庭經濟勉持之生活狀況（見偵查卷第3頁）等一切情狀，量處如主文所示之刑，併諭知易服勞役之折算標準，以資懲儆。三、依刑事訴訟法第449條第1項前段、第3項、第454條第2項，刑法第320條第1項、第42條第3項，刑法施行法第1條之1，逕以簡易判決處刑如主文。四、如不服本判決，得自收受送達之翌日起十日內向本院提出上訴狀，上訴於本院第二審合議庭（須附繕本）。中華民國100年11月16日刑事第二十三庭法官詹蕙嘉上列正本證明與原本無異。書記官陳語嫣中華民國100年11月18日附錄本案論罪科刑法條全文：刑法第320條意圖為自己或第三人不法之所有，而竊取他人之動產者，為竊盜罪，處5年以下有期徒刑、拘役或500元以下罰金。意圖為自己或第三人不法之利益，而竊佔他人之不動產者，依前項之規定處斷。前二項之未遂犯罰之。附件：臺灣板橋地方法院檢察署檢察官聲請簡易判決處刑書100年度偵字第19698號被告胡淑惠女39歲(民國○○年○月○日生)住新北市三重區○○○街205巷1號4樓身分證統一編號：Ｚ000000000號上列被告因竊盜案件，業經偵查終結，認為宜聲請以簡易判決處刑，茲將犯罪事實及證據並所犯法條分敘如下：犯罪事實一、胡淑惠意圖為自己不法所有之犯意，於民國100年7月1日12時22分許，在新北市○○區○○路三段4號1樓之「康是美藥妝店」店內，趁店員楊淑欽疏未注意之際，徒手竊取店內由楊淑欽所管領之「伊斯蘭纖姿魔術142入組」1盒（價值新台幣3960元），得手旋即離去，嗣經楊淑欽調閱該店內之監視器畫面，始悉上情並報警處理，因而查獲。二、案經楊淑欽訴由新北市政府警察局三重分局移送偵辦。證據並所犯法條一、證據(一)上揭犯罪事實，業據被告胡淑惠坦承不諱，核與證人即告訴人楊淑欽於警詢中之證述相符。(二)並有查獲照片2張、監視錄影器翻拍照片共4張、贓物認領保管單、新北市政府警察局三重分局搜索扣押筆錄、扣押物品目錄表各1份在卷可稽，是被告犯嫌堪以認定。二、核被告所為，係犯刑法第320條第1項之竊盜罪嫌。三、依刑事訴訟法第451條第1項聲請逕以簡易判決處刑。此致臺灣板橋地方法院中華民國100年9月23日檢察官楊植鈞上正本證明與原本無異本件係依刑事訴訟法簡易程序辦理，法院簡易庭得不傳喚被告、輔佐人、告訴人、告發人等出庭，即以簡易判決處刑；被告、被害人、告訴人等對告訴乃論案件，如已達成民事和解而要撤回告訴或對非告訴乃論案件，認有受傳喚到庭陳述意見之必要時，請即另以書狀向臺灣板橋地方法院簡易法庭陳述或請求傳訊。中華民國100年10月3日書記官附錄本案所犯法條全文：中華民國刑法第320條第1項意圖為自己或第三人不法之所有，而竊取他人之動產者，為竊盜罪，處5年以下有期徒刑、拘役或5百元以下罰金。",
  "characters": {
    "judges": [
      "詹蕙嘉"
    ],
    "prosecutors": [

    ],
    "lawyers": [

    ],
    "clerks": [
      "陳語嫣",
      "附錄本案所犯法條全文："
    ],
    "plaintiffs": [

    ],
    "defendants": [
      "胡淑惠",
      "胡淑惠  女  39歲(民國○○年○月○日生)"
    ],
    "prosecutor_office": [
      "臺灣板橋地方法院檢察署檢察官"
    ],
    "creditors": [

    ],
    "debtors": [

    ],
    "judicial_associate_officer": [

    ]
  },
  "adjudged_at": "2011-11-16",
  "created_at": "2016-02-12 21:37:50",
  "updated_at": "2016-02-12 21:37:50"
}