{
  "identify": "TCD-100-訴-2712-20111116-1",
  "court": {
    "name": "臺灣臺中地方法院",
    "code": "TCD"
  },
  "division": {
    "name": "刑事",
    "code": "M"
  },
  "year": 100,
  "word": "訴",
  "number": "2712",
  "jcheck": "1",
  "reason": "毒品危害防制條例",
  "content": "臺灣臺中地方法院刑事判決             100年度訴字第1678號\n                                     100年度訴字第2712號\n公  訴  人  臺灣臺中地方法院檢察署檢察官\n被      告  吳茂毅\n指定辯護人  本院公設辯護人戴遐齡\n上列被告因毒品危害防制條例案件，經檢察官提起公訴（99年度\n偵字第13990 號、第14634號 ）暨追加起訴（100 年度偵續字第\n214 號），本院判決如下：\n    主      文\n吳茂毅犯如附表一所示之罪，各處如附表一所示之刑（含主刑、\n從刑）。應執行有期徒刑柒年拾月，沒收部分併執行之。\n    事實及理由\n壹、犯罪事實：\n    吳茂毅（綽號「貓啊」、「喵仔」、「貓咪」）明知海洛因\n    、甲基安非他命及愷他命分別係毒品危害防制條例第2 條第\n    2 項第1 款、第2 款及第3 款所管制之第一級、第二級及第\n    三級毒品，不得販賣、轉讓、持有（持有第三級毒品部分純\n    質淨重20公克以上者亦不得持有），竟分別基於意圖營利販\n    賣第一級、第二級及第三級毒品以牟利，及轉讓第一級毒品\n    之犯意，為下列犯行：\n    一曾書賢於民國98年5 、6 月間某日，以門號0000000000號\n      行動電話撥打電話予吳茂毅所有如附表三編號3 所示之行\n      動電話，表示欲購買新臺幣（下同）400 元之愷他命，吳\n      茂毅應允後，至臺中市○○區○○路上之文雅國小（下稱\n      文雅國小）附近，將數量不詳之愷他命1 包（無證據證明\n      超過純質淨重20公克）販賣予曾書賢1 次，惟因曾書賢未\n      攜帶金錢，而暫時賒欠款項。\n    二曾書賢於98年6 月底某日，以門號0000000000號行動電話\n      撥打電話予吳茂毅之上開行動電話，表示欲購買400 元之\n      愷他命，雙方約定交易之時間、地點後，吳茂毅即前往文\n      雅國小附近，將數量不詳之愷他命1 包（無證據證明超過\n      純質淨重20公克）交與曾書賢，惟曾書賢仍未攜帶金錢，\n      故暫時賒欠款項。\n    三曾書賢於98年7 月中旬某日，再以門號0000000000號行動\n      電話撥打電話予吳茂毅之上開行動電話，表示購買愷他命\n      之意願，雙方議妥交易金額後，吳茂毅前往約定地點即文\n      雅國小附近，將數量不詳之愷他命1 包（無證據證明超過\n      純質淨重20公克）販賣予曾書賢1 次，然因曾書賢未攜帶\n      金錢，而暫時賒欠買賣價金400 元。嗣於99年1 月30日，\n      吳茂毅持用其所有如附表三編號4 所示之行動電話撥打曾\n      書賢持用之門號0000000000號行動電話，向曾書賢催討積\n      欠之款項，曾書賢始於不詳時間，在臺中市大雅區某國小\n      附近，將3 次購毒款項交與吳茂毅。\n    四曹家榮於99年1 月29日19時37分27秒、19時52分55秒、19\n      時56分17秒許，持用之行動電話門號0000000000號撥打吳\n      茂毅所有附表三編號4 所示之行動電話與之聯繫，雙方於\n      電話中，以「酒」代表海洛因，「停車場」代表交易地點\n      即吳茂毅位於臺中市○○區○○里○○街192 巷21號之住\n      處附近停車場，約定購買海洛因之事宜。待雙方於電話中\n      完成約定交易毒品之事宜後，吳茂毅即於當日通話完畢後\n      之某時，在其住處附近之停車場，以500 元之代價，販賣\n      海洛因1 小包與曹家榮，一手交錢、一手交貨，而完成交\n      易。\n    五鄒聖緯於99年1 月29日22時56分12秒、23時0 分21秒許所\n      持用之行動電話門號0000000000號行動電話撥打附表三編\n      號4 所示之行動電話與吳茂毅聯繫後，雙方於電話中，以\n      「3 罐」代表甲基安非他命，「臺新銀行」代表交易地點\n      即臺中市○○區○○路上之臺新銀行，雙方議妥交易甲基\n      安非他命事宜，吳茂毅即於當日通話完畢後之某時，至臺\n      中市○○區○○路上之臺新銀行前面，將甲基安非他命3\n      小包交予鄒聖緯，並向鄒聖緯收取現金1,500 元。\n    六徐嘉偉持用之行動電話門號0000000000號，於99年1 月30\n      日15時40分57秒、18時0 分1 秒、18時24分47秒許，以行\n      動電話門號0000000000號撥打附表三編號4 所示之行動電\n      話與吳茂毅聯繫，雙方於電話中，以「同款」代表海洛因\n      ，「3500」及「3000」各代表價值3,500 元及3,000 元之\n      海洛因，雙方於電話中完成約定交易毒品之事宜，吳茂毅\n      即於當日通話完畢後之某時，在臺中市○○區○○路上之\n      某停車場，以3,000 元之代價，販賣海洛因1 小包與徐嘉\n      偉，並當場向徐嘉偉收取現金3,000 元，完成交易。\n    七吳茂毅於99年1 月31日16時23分34秒許，以附表三編號4\n      所示之行動電話與曹家榮所持用之行動電話門號00000000\n      00號聯繫，曹家榮表示毒癮發作，請求吳茂毅無償轉讓些\n      許海洛因與其止癮，吳茂毅同意後，於同日晚間19時24分\n      前之某時，至曹家榮位在臺中市○○區○○路4號 之住處\n      前，無償轉讓海洛因1 小包（無證據證明超過淨重5 公克\n      ）予曹家榮。曹家榮施用完畢後，於當日19時24分17秒，\n      以上開行動電話傳遞簡訊：「品質不錯、保持下去、期待\n      明天、保持聯絡、新年快樂。」等語予吳茂毅。\n    八李明修持用之行動電話門號0000000000號於99年2 月4 日\n      凌晨0 時42分46秒許，撥打附表三編號4 所示之行動電話\n      與吳茂毅聯繫，雙方於電話中，以「啤酒」代表愷他命，\n      以「1 箱啤酒」、「半箱」及「4 分之1 」各代表30公克\n      、15公克及5 公克之愷他命，約定交易愷他命事宜。吳茂\n      毅於當日通話完畢後之某時，至臺中市○○區○道1 號高\n      速公路豐原交流道下，以2,000 元之代價，販賣約5 公克\n      之愷他命1 小包予李明修，一手交錢、一手交貨，而完成\n      交易。\n    九吳茂毅於99年2 月4 日23時2 分前之某時，在不詳之地點\n      ，以500 元之代價，販賣甲基安非他命予曹家榮，銀貨兩\n      訖。嗣因吳茂毅所販賣之甲基安非他命品質不佳，包裝袋\n      又有破洞，曹家榮遂於當日晚間2 月4 日23時2 分23秒，\n      以行動電話門號0000000000號傳遞簡訊：「怎麼酒又不夠\n      ，這樣下去很難交陪，杯子還破洞，注意點，別再出問題\n      了。」等語，至吳茂毅所持用附表三編號4 所示之行動電\n      話，抱怨此事。\n    十鄒聖緯所持用行動電話門號0000000000號，於99年2 月5\n      日18時55分6 秒、18時56分38秒許，撥打附表三編號4 所\n      示之行動電話與吳茂毅聯繫後，雙方於電話中，以「葡萄\n      酒」代表甲基安非他命，「上夢全家（臺語）」、「大楓\n      全家（臺語）」代表交易地點即吳茂毅位在臺中市大雅區\n      上楓里住處巷口之全家便利商店，雙方議妥交易甲基安非\n      他命事宜，吳茂毅即於當日通話完畢後之某時，在其住處\n      巷口之全家便利商店前，將甲基安非他命1 小包交予鄒聖\n      緯，並向鄒聖緯收取現金500 元。\n    嗣經警對吳茂毅持用之門號0000000000號行動電話實施通訊\n    監察，並於99年2 月5 日22時30分許，另案為警在臺中市○\n    ○路○ 段與崇德十路口拘提到案，並扣得吳茂毅所有之海洛\n    因7 小包（合計淨重2.44公克，驗餘合計淨重2.35公克，包\n    裝袋總重2.32公克，外包裝因與海洛因相結合無從析離而應\n    視為第一級毒品）、甲基安非他命20包（驗前總毛重17.32\n    公克，包裝袋總重4.80公克，驗前總純質淨重10.89 公克，\n    鑑驗用罄0.11公克，外包裝因與甲基安非他命相結合無從析\n    離而應視為第二級毒品）、吳茂毅所有供上揭販賣第一級、\n    第二級、第三級毒品及轉讓第一級毒品所用之GPLUS 廠牌行\n    動電話1 支（含門號0000000000號晶片卡1 張）、Sony Eri\n    sson廠牌行動電話1 支（含門號0000000000號晶片卡1 張）\n    、電子秤1 臺、吳茂毅所有預備供上揭各次販賣第一級、第\n    二級、第三級毒品及轉讓第一級毒品所用之分裝夾鍊袋2 包\n    ，而查獲上情。\n貳、認定犯罪事實所憑證據及理由：\n  一程序部分：\n    (一)按於第一審辯論終結前，得就與本案相牽連之犯罪或本罪\n      之誣告罪，追加起訴；追加起訴，得於審判期日以言詞為\n      之，刑事訴訟法第265 條定有明文。又一人犯數罪者，為\n      相牽連之案件，刑事訴訟法第7 條第1 款亦有明文。本件\n      檢察官原起訴被告吳茂毅販賣海洛因與曹家榮、徐嘉偉，\n      販賣甲基安非他命與鄒聖緯、曹家榮，販賣愷他命與李明\n      修，及轉讓海洛因與曹家榮，嗣於100 年9 月29日以追加\n      起訴書，追加起訴被告於98年5 、6 月間某日、同年6 月\n      底某日及同年7 月間某日分別販賣愷他命與曾書賢之犯罪\n      事實，上開追加之販賣第三級毒品罪與本案原起訴被告之\n      各罪間，有一人犯數罪之相牽連關係，依上開法條規定，\n      檢察官於言詞辯論終結前追加起訴，當屬合法，法院自應\n      就追加起訴部分予以審判。\n    (二)證據能力部分：\n      1.按被告以外之人於偵查中向檢察官所為之陳述，除顯有\n        不可信之情況者外，得為證據，刑事訴訟法第159 條之\n        1 第2 項定有明文。偵查中對被告以外之人（包括證人\n        、鑑定人、告訴人、被害人及共同被告等）所為之偵查\n        筆錄，或被告以外之人向檢察官所提之書面陳述，性質\n        上均屬傳聞證據。惟現階段刑事訴訟法規定檢察官代表\n        國家偵查犯罪、實施公訴，依法其有訊問被告、證人及\n        鑑定人之權，證人、鑑定人且須具結，而實務運作時，\n        檢察官偵查中向被告以外之人所取得之陳述，原則上均\n        能遵守法律規定，不致違法取供，其可信度極高，職是\n        ，被告以外之人前於偵查中已具結而為證述，除反對該\n        項供述得具有證據能力之一方，已釋明「顯有不可信之\n        情況」之理由外，不宜以該證人未能於審判中接受他造\n        之反對詰問，即遽指該證人於偵查中之陳述不具證據能\n        力。查本件證人曹家榮、曾書賢、徐嘉偉、李明修及鄒\n        聖緯於偵查中所為之陳述，雖屬傳聞證據，然其等於偵\n        查中所為證言，均經具結，而被告吳茂毅及其辯護人均\n        未釋明上開證人之陳述有何「顯不可信之情況」，且於\n        客觀之外部情狀上，難認有何顯不可信之情狀，依上揭\n        規定，應認證人曹家榮、曾書賢、徐嘉偉、李明修及鄒\n        聖緯於偵查中所為之證述，得為證據。\n      2.又偵查犯罪機關依法定程序監聽之錄音，係以監聽之錄\n        音帶為其調查犯罪所得之證據，司法警察依據監聽錄音\n        結果予以翻譯而製作之通訊監察譯文，乃該監聽錄音帶\n        內容之顯示，此為學理上所稱之「派生證據」，屬於文\n        書證據之一種。於被告或訴訟關係人對該譯文之真實性\n        發生爭執或有所懷疑時，法院固應依刑事訴訟法第165\n        條之1 第2 項之規定，勘驗該監聽錄音帶以踐行調查證\n        據之程序，俾確認該錄音之聲音是否為通訊者本人及其\n        內容與通訊監察譯文之記載是否相符，或傳喚該通訊者\n        為證據調查。倘被告或訴訟關係人對該通訊監察譯文之\n        真實性並不爭執，即無勘驗辨認其錄音之聲音予以調查\n        之必要，法院於審判期日如已踐行提示通訊監察譯文供\n        當事人辨認或告以要旨，使其表示意見等程序並為辯論\n        者，其所為之訴訟程序即無不合（最高法院97年度臺上\n        字第561 號判決意旨可資參照）。再按有事實足認被告\n        或犯罪嫌疑人有最輕本刑為3 年以上有期徒刑之罪嫌，\n        並危害國家安全或社會秩序情節重大，而有相當理由可\n        信其通訊內容與本案有關，且不能或難以其他方法蒐集\n        或調查證據者，得發通訊監察書。前項通訊監察書，偵\n        查中由檢察官依司法警察機關聲請或依職權以書面記載\n        第11條之事項，並敘明理由、檢附相關文件，聲請該管\n        法院核發。通訊保障及監察法第5 條第1 項第1款 、第\n        2 項定有明文。本案所引用有關行動電話號碼00000000\n        00號之監聽錄音，係經本院法官核准在案，有詳載案由\n        、監察電話、對象及時間等之99年度聲監字第163 號通\n        訊監察書、電話附表等附卷可參〔見臺灣臺中地方法院\n        檢察署99年度偵字第13990 號卷（下稱偵卷一）第36、\n        37頁〕，係依法所為之監聽；況審酌電話監聽侵害被告\n        權益之種類及輕重、對於被告訴訟上防禦不利益之程度\n        、犯罪所生之危害或實害等情形，兼顧人權保障及公共\n        利益之均衡維護，亦認此部分電話監聽合於比例原則，\n        是認應具有證據能力。且下列經本院所引用認定之通訊\n        監察譯文，被告及辯護人對該通訊監察譯文之真實性並\n        不爭執，復經本院於審判期日踐行提示通訊監聽譯文供\n        當事人、指定辯護人辨認並告以要旨，使其等表示意見\n        ，是該通訊監察譯文自亦有證據能力。\n      3.現行刑事訴訟法關於「鑑定」之規定，除選任自然人充\n        當鑑定人外，另設有囑託機關鑑定制度。依同法第198\n        條、第208 條之規定，不論鑑定人或鑑定機關、團體，\n        固均應由法院、審判長、受命法官或檢察官視具體個案\n        之需要而為選任、囑託，並依第206 條之規定，提出言\n        詞或書面報告，始符合同法第159 條第1 項所定得作為\n        證據之「法律有規定」之情形。否則所為之鑑定，仍屬\n        傳聞證據。然於司法警察機關調查中之案件，為因應實\n        務上，或因量大，或有急迫之現實需求，例行性當然有\n        鑑定之必要者，例如毒品之種類與成分、尿液之毒品反\n        應，或者槍彈有無殺傷力等鑑定，基於檢察一體原則，\n        得由該管檢察長對於轄區內之案件，以事前概括選任鑑\n        定人或囑託鑑定機關、團體之方式，俾便轄區內之司法\n        警察官、司法警察對於調查中之此類案件，得即時送請\n        先前已選任之鑑定人或囑託之鑑定機關、團體實施鑑定\n        ，以求時效（法務部92年9 月1 日法檢字第0920035083\n        號函參照）。此種由檢察機關概括選任鑑定人或概括囑\n        託鑑定機關、團體，再轉知司法警察官、司法警察於調\n        查犯罪時參考辦理之作為，法無明文禁止，係為因應現\n        行刑事訴訟法增訂傳聞法則及其例外規定之實務運作而\n        為。其所為之鑑定結果，與檢察官選任或囑託為鑑定者\n        ，性質上並無差異，同具有證據能力（最高法院96年度\n        臺上字第2860號判決要旨參照）。卷附之詮昕科技股份\n        有限公司濫用藥物尿液檢驗報告各3 份〔見臺灣雲林地\n        方法院檢察署99年度偵字第14634 偵查卷（下稱偵卷二\n        ）第130 至132 頁〕，均為臺中縣警察局清水分局（現\n        改制為臺中市政府警察局清水分局）送請鑑定，揆諸前\n        揭說明，屬「法律規定」得為證據者，應有證據能力。\n      4.再按被告以外之人於審判外之陳述，雖不符刑事訴訟法\n        第159 條之1 至第159 條之4 之規定，而經當事人於審\n        判程序同意作為證據，法院審酌該言詞陳述或書面陳述\n        作成時之情況，認為適當者，亦得為證據。當事人、代\n        理人或辯護人於法院調查證據時，知有第159 條第1 項\n        不得為證據之情形，而未於言詞辯論終結前聲明異議者\n        ，視為有前項之同意，刑事訴訟法第159 條之5 定有明\n        文。核其立法意旨在於傳聞證據未經當事人之反對詰問\n        予以核實，原則上先予排除。惟若當事人已放棄反對詰\n        問權，於審判程序中表明同意該等傳聞證據可作為證據\n        ；或於言詞辯論終結前未聲明異議，基於尊重當事人對\n        傳聞證據之處分權，及證據資料愈豐富，愈有助於真實\n        發見之理念，且強化言詞辯論主義，使訴訟程序得以順\n        暢進行，上開傳聞證據亦均具有證據能力。查：本判決\n        除上揭所述外，下列所引之被告以外之人於審判外所為\n        之陳述及卷內其他書證（供述證據部分），查無符合同\n        法第159 條之1 至之4 等前4 條之情形，檢察官、被告\n        及其辯護人於本院準備程序中均表示對該等傳聞證據之\n        證據能力均同意有證據能力〔見本院100 年度訴字第16\n        78號卷（下稱審卷一）第42頁〕，於本院審理時並未就\n        卷內其他證據資料之證據能力有所爭執，且迄本院言詞\n        辯論終結前，均未主張有刑事訴訟法第159 條第1 項不\n        得為證據之情形，是應認已同意卷內證據均得作為證據\n        ，且經本院審酌上開傳聞證據作成時，較無人情施壓或\n        干擾，亦無不當取證之情形，認為以之作為本案之證據\n        亦屬適當，是上揭傳聞證據自具有證據能力。\n  二得心證之理由：\n    (一)訊據被告就上開犯罪事實，於警詢、偵訊及本院審理時均\n      坦承不諱〔見偵卷一第12至20頁、第79、80頁、偵卷二第\n      14至18頁、第166 頁、第115 頁、臺灣臺中地方法院檢察\n      署100 年度偵續字第214 號卷（下稱偵卷三）第52頁〕，\n      復經證人曾書賢、曹家榮、鄒聖緯、徐嘉偉及李明修於警\n      詢（見偵卷一第38至43頁、偵卷二第25至31頁、第41至47\n      頁）、檢察官偵訊時（見偵卷一第70至72頁、偵卷二第64\n      、65、146 、168 、158 、159 頁、偵卷三第52頁）證述\n      明確。證人曹家榮於警詢時雖陳稱99年2 月4 日購買甲基\n      安非他命之金額為1,000 元，證人鄒聖緯於警詢時則陳稱\n      ：99年1 月29日此次「貓啊」有拿3 包甲基安非他命與伊\n      ，以1 包1,000 元賣伊等語，證人李明修另證稱交易時間\n      為99年2 月5 日或6 日之晚上11、12時許，惟查：1.證人\n      曹家榮於99年12月2 日偵訊時具結證稱：99年2 月4 日該\n      次交易是在發簡訊之前，地點伊記不清楚，不是在被告住\n      處附近，就是在其工作之工廠前，只能確定向被告買了50\n      0 元的甲基安非他命等語（見偵卷一第71頁）。被告於本\n      院審理時亦供稱：99年2 月4 日曹家榮傳簡訊抱怨這次，\n      伊販賣甲基安非他命之金額為500 元，伊本來要賣1,000\n      元，但曹家榮說錢不夠，伊就便宜賣其500 元，賺取較少\n      利潤等語（見審卷一第112 頁）。故證人曹家榮就該次交\n      易之金額於偵訊中之證述與被告於本院審理時之陳述相符\n      ，併基於罪疑惟輕之原則，應認定被告該次販賣甲基安非\n      他命與曹家榮之金額應為500 元。2.被告於100 年4 月28\n      日偵訊時供陳：李明修應該記錯日期了，因伊於99年2 月\n      5 日晚上9 點多就被抓了，所以當天應該是講完電話沒多\n      久就交易等語（見偵卷一第80頁）。而被告確於99年2 月\n      5 日22時30分為警在臺中市○○路○ 段與崇德十路口拘提\n      到案，並於同月6 日遭羈押於法務部矯正署臺中看守所，\n      有臺灣高等法院臺中分院99年度上訴字第1604號判決及臺\n      灣高等法院被告前案紀錄表各1 份在卷可按，核與被告前\n      開供述相符，被告之前開供述堪以採信。被告與李明修之\n      交易時間為99年2 月4 日當日通話後之某時，堪以認定。\n      3.被告於99年6 月9 日警詢時供稱：伊以門號0000000000\n      號行動電話於99年1 月29日17時3 分4 秒與鄒聖緯持用之\n      門號0000000000號行動電話聯繫，係鄒聖緯要向伊購買甲\n      基安非他命，通訊監察譯文中「2 罐」是代表1,000 元之\n      意思，伊於當日23時許在大雅區臺新銀行後面，拿甲基安\n      非他命3 小包給鄒聖緯，並向其收取1,500 元等語（見偵\n      卷二第17頁）。被告於100 年4 月28日偵訊時雖一度陳稱\n      該次交易之金額為3,000 元，然嗣後確認交易金額為1,50\n      0 元。再觀諸附表二編號２被告與曹家榮之通訊監察譯文\n      ，曹家榮於電話中表示欲購買「一」，而該次交易金額為\n      500 元，業經證人曹家榮證述明確，堪認被告於警詢中供\n      稱「2 罐」是代表1,000 元等語，應屬真實無訛。是鄒聖\n      緯於99年1 月29日22時56分12秒通話中表示要「3 罐」，\n      應係欲購買1,500 元之甲基安非他命之意，被告與鄒聖緯\n      該次之交易金額應為1,500 元，亦堪認定。\n    (二)另觀諸被告與曹家榮、曾書賢、徐嘉偉、李明修、鄒聖緯\n      所示通話對象之通話內容（詳如附表二所示），多使用暗\n      語如「酒」、「一」、「3 罐」、「3500」、「3000」、\n      「水」、「1 箱」等作為代號，且通話內容簡短，多半係\n      在談妥價格、數量或交易地點後，即結束通話，確屬實務\n      上常見之毒品交易對話，有本院99年度聲監字第163 號通\n      訊監察書1 份及如附表二所示之通訊監察譯文附卷足佐（\n      內容與證據出處均詳附表二所示），益徵上開人等通話之\n      目的確係要交易或轉讓毒品無疑。\n    (三)證人李明修及曾書賢於99年3 月18日經警採尿送驗，證人\n      李明修呈現愷他命陽性反應，證人曾書賢呈現甲基安非他\n      命及愷他命陽性反應，亦有詮昕科技股份有限公司濫用藥\n      物尿液檢驗報告2 份在卷可按，而證人曹家榮則於99年2\n      月4 日及同年月7 日分別因施用海洛因、甲基安非他命案\n      件，經本院分別判處有期徒刑8 月、3 月，定應執行有期\n      徒刑10月，亦有本院99年度訴字第1401號判決1 份附卷可\n      參。足認證人李明修、曾書賢均有施用愷他命之慣習，證\n      人曹家榮亦有施用海洛因、甲基安非他命之慣習，對外有\n      購毒之需求。\n    (四)又被告於99年2 月5 日22時30分許，另案為警在臺中市○\n      ○路○ 段與崇德十路口拘提到案，並扣得其所有之海洛因\n      7 小包（合計淨重2.44公克，驗餘合計淨重2.35公克，包\n      裝袋總重2.32公克，外包裝因與海洛因相結合無從析離而\n      應視為第一級毒品）、甲基安非他命20包（驗前總毛重17\n      .32 公克，包裝袋總重4.80公克，驗前總純質淨重10.89\n      公克，鑑驗用罄0.11公克，外包裝因與甲基安非他命相結\n      合無從析離而應視為第二級毒品）、其所有供上揭販賣第\n      一級、第二級、第三級毒品及轉讓第一級毒品所用如附表\n      三編號3 、4 所示之行動電話、電子秤1 臺、其所有預備\n      供上揭各次販賣第一級、第二級及第三級毒品及轉讓第一\n      級毒品所用之分裝夾鍊袋2 包，亦經臺中高分院99上訴字\n      第1604號判決認定屬實，有該判決附卷可參。可認被告確\n      有管道取得海洛因、甲基安非他命以供販賣、轉讓，並有\n      販賣及轉讓之工具。\n    (五)又被告供稱：伊販賣海洛因、甲基安非他命及愷他命，可\n      以從中賺到自己施用的部分，400 元之愷他命約可賺取0.\n      7 至0.8 公克之愷他命供己施用等語（見審卷一第112 、\n      138 頁），足認被告販賣海洛因、甲基安非他命及愷他命\n      ，主觀上有營利之意圖無訛。\n    (六)從而，被告之自白與相關證據均相符合，堪以採信，被告\n      各次販賣海洛因、甲基安非他命、愷他命及轉讓海洛因之\n      犯行，均堪認定，應依法論科。\n、論罪科刑之理由：\n  一核被告所為，犯罪事實一二三八部分，均係犯毒品危害防制\n    條例第4 條第3 項之販賣第三級毒品罪；犯罪事實四六部分\n    ，均係犯毒品危害防制條例第4 條第1 項之販賣第一級毒品\n    罪；犯罪事實五九十部分，係犯毒品危害防制條例第4 條第\n    2 項之販賣第二級毒品罪；犯罪事實七部分，則係犯同條例\n    第8條第1項轉讓第一級毒品罪。\n  二被告各該持有海洛因、甲基安非他命之低度行為，分別為販\n    賣、轉讓之高度行為所吸收，均不另論罪。又持有第三級毒\n    品愷他命之行為，毒品危害防制條例第11條第5 項規定：「\n    持有第三級毒品純質淨重20公克以上者，處3 年以下有期徒\n    刑，得併科新臺幣30萬元以下罰金。」然被告各次販賣愷他\n    命實際持有愷他命之重量不明，且未扣案無從鑑定愷他命之\n    純質淨重是否為20公克以上。準此，依無罪推定原則，被告\n    上開販賣前持有第三級毒品愷他命之行為不成立犯罪，而無\n    「吸收」之問題。至被告轉讓海洛因部分，亦無證據證明轉\n    讓之重量超過淨重5 公克，自不得依同條例第8 條第6 項予\n    以加重，附此敘明。\n  三被告所犯上開10罪，均犯意各別，行為各自獨立，應分論併\n    罰之。\n  四按98年5 月20日修正公布之毒品危害防制條例第17條第2 項\n    關於「犯第4 條至第8 條之罪於偵查及審判中均自白者，減\n    輕其刑。」之規定，旨在獎勵犯罪人之悛悔，同時使偵查或\n    審判機關易於發現真實，以利毒品查緝，俾收防制毒品危害\n    之效；故不論該被告之自白，係出於自動或被動、簡單或詳\n    細、一次或多次，並其自白後有無翻異，苟其於偵查及審判\n    中均有自白，即應依法減輕其刑。又刑法上所稱之自白，係\n    指行為人對其被訴之犯罪事實為任意性之供認而言（最高法\n    院98年度臺上字第6928號判決）。本件被告於檢察官偵訊時\n    及本院審理時均已自白其上揭販賣第一級、第二級、第三級\n    毒品及轉讓第一級毒品等犯行，業如上述，爰依毒品危害防\n    制條例第17條第2 項規定就上揭各罪均減輕其刑。\n  五又98年5 月20日修正公布之毒品危害防制條例第17條第1 項\n    規定：「犯第4 條至第8 條、第10條或第11條之罪，供出毒\n    品來源，因而查獲其他正犯或共犯者，減輕或免除其刑」。\n    被告吳茂毅於另案販賣毒品案件經檢察官偵訊時，供稱：伊\n    向一位綽號「小陳」（嗣經查為陳文仕）之人買毒品的，其\n    電話為0000000000；伊約今年（即99年）1 月中或1 月底，\n    交易地點好像在苗栗交流道，該次伊向綽號「小陳」拿了約\n    半兩多（約16、17公克）的安非他命，4 點多公克的海洛因\n    ，小陳跟伊說把毒品賣掉後，再將錢交給小陳，小陳說安非\n    他命要21,000元，海洛因要22,000元，但尚未給小陳錢；小\n    陳除0923的電話外，還有一支0000000000的電話等語（見審\n    卷一第65、66頁）。檢察官隨即依被告之供述而簽分偵辦小\n    陳販賣毒品案件，嗣確有查獲綽號「小陳」之陳文仕販賣海\n    洛因、甲基安非他命與被告之犯行，而予偵查起訴在案，亦\n    有臺灣臺中地方法院檢察署99年10月7 日中檢輝姜99偵4796\n    字第133021號函及該署99年度偵字第12459 、15267 號起訴\n    書可稽（見審卷一第67頁、第54至56頁）。是可認被告自99\n    年1 月起始向陳文仕購買海洛因、甲基安非他命，被告就犯\n    罪事實四至七九十之犯行供出毒品來源，因而查獲其他正犯\n    ，而就此部分販賣第一級毒品、第二級毒品及轉讓第一級毒\n    品犯行，各依毒品危害防制條例第17條第1 項遞減輕其刑。\n    至被告於警詢、偵訊時雖另供稱其係向葉文仁購買愷他命，\n    惟另案被告葉文仁並非因被告之供述而查獲其販賣愷他命之\n    犯行，亦有臺灣臺中地方法院檢察署中檢輝敦100 他3168字\n    第101475號函文、內政部警政署保安警察隊第三總隊第一大\n    隊100 年7 月6 日保三壹警刑字第1000003994號函文暨函附\n    之職務報告及葉文仁之臺灣高等法院被告前案紀錄表各1 份\n    在卷可按，是被告販賣第三級毒品之犯行，自無從適用毒品\n    危害防制條例第17條第1 項減刑規定之寬典，附此敘明。\n  六刑法第59條規定之適用：\n    (一)再按刑法第59條之減輕其刑，係裁判上之減輕，必以犯罪\n      之情狀可憫恕，認為宣告法定最低度之刑猶嫌過重者，始\n      有其適用；如別有法定減輕之事由，應先依法定減輕事由\n      減輕其刑後，猶嫌過重時，始得為之；若有2 種以上法定\n      減輕事由，仍應先依法定減輕事由遞減其刑後，猶嫌過重\n      時，始得再依刑法第59條規定酌減其刑，最高法院88年度\n      臺上字第1862號判決意旨可資參照。復按刑之量定，為求\n      個案裁判之妥當性，法律固賦予法院裁量權，但此項裁量\n      權之行使，除應依刑法第57條規定，審酌行為人及其行為\n      等一切情狀，為整體之評價，並應顧及比例原則與平等原\n      則，使罪刑均衡，輕重得宜，以契合社會之法律感情。販\n      賣第一級毒品罪之法定刑為「死刑或無期徒刑；處無期徒\n      刑者，得併科新臺幣20,000,000元以下罰金」。其法定刑\n      既為死刑、無期徒刑，別無其他自由刑之規定，刑度可謂\n      重大。然同為販賣第一級毒品之人，其原因動機不一，犯\n      罪情節未必盡同，或有大盤毒梟者，亦有中、小盤之分，\n      甚或僅止於吸毒者友儕間為求互通有無而為販賣者亦有之\n      ，其販賣行為所造成危害社會之程度自屬有異，法律科處\n      此類犯罪，所設之法定最低本刑卻同為死刑或無期徒刑，\n      且處無期徒刑者，得併科新臺幣20,000,000元以下之罰金\n      ，不可謂不重。於此情形，倘依其情狀處以有期徒刑，即\n      足以懲儆，並可達防衛社會之目的者，自非不可依客觀之\n      犯行與主觀之惡性二者加以考量其情狀是否有可憫恕之處\n      ，適用刑法第59條之規定酌量減輕其刑，期使個案裁判之\n      量刑，能斟酌至當，符合比例原則。又適用刑法第59條酌\n      量減輕其刑時，並不排除同法第57條所列舉10款事由之審\n      酌（最高法院70年5 月16日70年度第6 次刑事庭長會議決\n      議足供參考）。\n    (二)依上開說明意旨，本院認為被告所為犯罪事實四六所示之\n      販賣海洛因犯行，固戕害國民健康，助長施用毒品惡習，\n      其行為實屬不該，惟被告各次販賣海洛因之所得僅500 元\n      、3,000 元，均係小額交易，屬毒品交易之下游，販賣毒\n      品之對象曹家榮原即有施用毒品之慣習，有其臺灣高等法\n      院被告前案紀錄表1 份在卷可按，被告之惡性情節較諸大\n      量走私進口或長期販賣毒品之「大盤」、「中盤」毒販有\n      差異，其對社會整體侵害之程度尚非鉅大，被告亦染有施\n      用之惡習，業據被告供承在卷，被告係為圖自己得以施用\n      毒品，始鋌而走險販賣海洛因，惟被告就所犯之販賣第一\n      級毒品罪，其最輕法定本刑為無期徒刑，縱使被告所犯販\n      賣第一級毒品罪經依毒品危害防制條例第17條第2 項規定\n      減輕其刑，及依同條第1 項規定遞減輕其刑後，均量處法\n      定最低刑度之刑，仍嫌過重，而依被告客觀之犯行與主觀\n      之惡性二者加以考量其犯罪情狀，爰依刑法第59條之規定\n      ，就被告所犯上開販賣第一級毒品罪部分各酌量減輕其刑\n      ，並均遞減輕其刑。\n  七又「數罪併罰，分別宣告其罪之刑，依下列各款定其應執行\n    者：五宣告多數有期徒刑者，於各刑中之最長期以上，各刑\n    合併之刑期以下，定其刑期。但不得逾30年。」刑法第51條\n    第5 款定有明文。又法律上屬於自由裁量事項，尚非概無法\n    律性之拘束，在法律上有其外部界限及內部界限。前者法律\n    之具體規定，使法院得以具體選擇為適當裁判，此為自由裁\n    量之外部界限。後者法院為自由裁量時，應考量法律之目的\n    ，法律秩序之理念所在，此為自由裁量之內部界限。法院為\n    裁判時，二者均不得有所踰越。在數罪併罰應定其應執行刑\n    之案件，法院所為刑之酌定，固屬自由裁量事項，然對於法\n    律之內、外部界限，仍均應受其拘束。最高法院94年度臺非\n    字第21號判決要旨足供本案定刑之參考。從而，數罪併罰在\n    定其應執行之刑之際，自應再為應執行之刑的決定，亦屬一\n    種特別的量刑過程，其考量結果，並非單純表示一種數罪刑\n    度的總和而已，而是再次對於同一行為人責任的檢視。相較\n    刑法第57條定有科刑時應審酌的事項，此項規定係對一般犯\n    罪行為之裁量而言。而合併刑之宣告，則屬一種對犯罪人本\n    身及所犯之各種犯罪的綜合判斷。申言之，定執行之刑的宣\n    告，並非在法定範圍之內自由裁定，應注意行為人從其犯數\n    罪所反映的人格特性，及考量刑法目的相關刑事政策，妥為\n    宣告。而刑法的功能中，除一般預防及特別預防之外，更重\n    要的是，行為人再社會化及具體的社會保護作用，否則加諸\n    過度之刑罰於被告，徒僅造成責任報應，去實現一個未知、\n    抽象的正義。因此，是否為被告長期性監禁宣告的同時，應\n    一併考量被告犯案情節對社會之衝擊，並注意此舉是否造成\n    被告更生絕望的心理影響，使得被告的人格遭受完全性地抹\n    滅。換言之，必須考量刑罰手段的相當性，儘量選擇能使受\n    刑人復歸社會生活之刑罰方法。法官無法以所謂「治亂世用\n    重典」之理由，加重刑罰以圖遏止歪風，不能過度強調所謂\n    一般預防的刑罰目的。實則，就人性尊嚴及人權的思想而言\n    ，任何一個人均非他人的工具，以加重被告的刑罰作為達到\n    阻嚇其他人犯罪的手段，被告已淪為教化社會大眾的工具，\n    喪失了作為一個人主體性，這均與我國刑事政策之立法有違\n    。凡此即構成最高法院所揭示「內部界限」之意義。\n  八本院審酌前揭情狀（包括前述酌減之事由），並參酌被告有\n    違反毒品危害防制條例前科，有前開臺灣高等法院被告前案\n    紀錄表可參，被告之素行難認良善。被告明知海洛因、甲基\n    安非他命、愷他命係屬戕害人身心之毒品，竟為貪圖不法利\n    益，鋌而走險販賣供他人施用，另基於朋友情誼，無償提供\n    海洛因與曹家榮施用，擴大毒害，無視上開毒品足以使施用\n    者導致精神障礙、性格異常，甚至造成生命危險之生理成癮\n    性及心理依賴性，嚴重影響社會治安、戕害國民身心健康，\n    並考量被告各自販賣毒品之次數、販賣之所得非鉅、轉讓海\n    洛因之數量、次數，犯罪之動機、方法、手段，販賣毒品之\n    數量及對象，及犯後之態度等一切情狀，分別量處如主文所\n    示之刑。又被告現年27歲，若本院定以過重之應執行刑，其\n    效用可能隨著長期刑之執行，等比例地大幅下跌，效用甚低\n    ，對被告教化效果亦不佳，尚且加重國家財政無益負擔，亦\n    有害被告回歸社會，爰定其應執行之刑如主文所示，以期兼\n    顧對於被告之警示及更生。公訴檢察官雖請求量處被告有期\n    徒刑15年，然公訴檢察官未慮及被告販賣第一級毒品部分，\n    情輕法重，有毒品危害防制條例第17條第1 項、第2 項規定\n    之適用，並應依刑法第59條予以酌減，販賣第二級毒品部分\n    ，亦有毒品危害防制條例第17條第1 項、第2 項規定之適用\n    ，是公訴檢察官前開求刑實屬過重，尚有未洽。\n  九沒收部分：\n    (一)按以營利為目的販入毒品，經多次販賣後，持有剩餘毒品\n      被查獲，其各次販賣毒品行為，固應併合處罰。惟該持有\n      剩餘毒品之低度行為，應僅為最後一次販賣毒品之高度行\n      為所吸收，不另論罪。故就該查獲之剩餘毒品，祇能於最\n      後一次之販賣毒品罪宣告沒收銷燬，不得於各次販賣毒品\n      罪均宣告沒收銷燬；又應沒收銷燬之物執行完畢與不存在\n      ，係屬二事，本案中因犯罪依法必須沒收銷燬之物，縱已\n      於其他相關案件確定判決中諭知沒收銷燬並執行完畢，亦\n      不得認已滅失而不存在，且因該他案判決之認定僅具個案\n      拘束之效力，是於本案依法仍屬應宣告沒收銷燬之物，自\n      不得以該物因其他相關之判決已諭知沒收銷燬確定，並經\n      執行完畢為由，而不為沒收之諭知，最高法院98年度臺上\n      字第738 號、98年度臺上字第4258號判決要旨參照。是以\n      ：\n      1.本案被告吳茂毅所犯多次販賣第一級毒品及轉讓第一級\n        毒品罪，其最後一次轉讓第一級毒品之時間為99年1 月\n        31日，而被告另案於99年2 月5 日22時30分許，為警在\n        臺中市○○路○ 段與崇德十路口，扣得被告所有供販賣\n        所用之第一級毒品海洛因7 小包（合計淨重2.44公克，\n        驗餘合計淨重2.35公克，包裝袋總重2.32公克，外包裝\n        因與第一級毒品海洛因相結合無從析離而應視為第1級\n        毒品，行政院衛生署草屯療養院98年4 月21日草療鑑字\n        第0980002432號函、法務部調查局93年3 月19日調科壹\n        字第09300113060 號函、最高法院95年度臺上字第3934\n        號判決參照），係被告吳茂毅經多次販賣第一級毒品及\n        轉讓第一級毒品後，持有剩餘第一級毒品被查獲，縱經\n        臺中高分院以99年度上訴字第1604號判決宣告沒收銷燬\n        ，經最高法院駁回上訴後確定，惟該他案判決之認定僅\n        具個案拘束之效力，於本案依法仍屬應宣告沒收銷燬之\n        物，仍應依法宣告沒收銷燬之。故就前揭所查獲之剩餘\n        毒品，應於被告最後1 次之轉讓海洛因罪宣告沒收銷燬\n        ，不得於各次販賣毒品罪均宣告沒收銷燬，亦即前揭扣\n        案之海洛因自應於附表一編號７所示之主刑之後，依毒\n        品危害防制條例第18條第1 項前段宣告沒收銷燬之（最\n        高法院98年度臺上字第3060號判決意旨參照）。至因鑑\n        驗所耗損之第一級毒品海洛因部分，既已滅失，即不另\n        為沒收之諭知。\n      2.本案被告亦有犯多次販賣第二級毒品罪，其最後1 次販\n        賣第二級毒品之時間為99年2 月5 日，而被告另案於99\n        年2 月5 日22時30分許，為警在臺中市○○路○ 段與崇\n        德十路口，扣得之第二級毒品甲基安非他命20包（驗前\n        總毛重17.32 公克，包裝袋總重4.80公克，驗前總純質\n        淨重10.89 公克，鑑驗用罄0.11公克，外包裝因與第2\n        級毒品甲基安非他命相結合無從析離而應視為第二級毒\n        品，理由同上揭行政院衛生署草屯療養院函釋），係被\n        告經多次販賣第二級毒品後，持有剩餘第二級毒品被查\n        獲，縱經臺中高分院以99年度上訴字第1604號判決宣告\n        沒收銷燬，依前揭說明，仍應於本案諭知沒收銷燬之。\n        故就前揭所查獲之剩餘毒品，應於被告最後1 次之販賣\n        第二級毒品罪中宣告沒收銷燬，不得於各次販賣毒品罪\n        均宣告沒收銷燬，亦即前揭扣案之甲基安非他命自應於\n        附表一編號１０所示之主刑之後，依毒品危害防制條例第\n        18條第1 項前段宣告沒收銷燬之（最高法院98年度臺上\n        字第3060號判決意旨參照）。至因鑑驗所耗損之第二級\n        毒品甲基安非他命部分，既已滅失，即不另為沒收之諭\n        知。\n    (二)毒品危害防制條例第19條第1項規定，犯販賣毒品罪者，\n      其犯罪所得之財物均沒收之，係採義務沒收主義。故販賣\n      毒品所得之對價，不問其中成本若干，利潤多少，均應全\n      部諭知沒收，貫徹政府查禁煙毒之決心，以符立法本旨（\n      最高法院91年度臺上字第2419號判決意旨參照）。再按毒\n      品危害防制條例第19條第1 項，係刑法第38條第1 項第2\n      款之特別規定，採義務沒收主義，苟能證明係供犯罪所用\n      或因犯罪所得之財物，均應沒收之，如全部或一部不能沒\n      收時，追徵其價額或以其財產抵償之，並不以當場搜獲扣\n      押者為限（最高法院88年度臺上字2039號判決要旨參照）\n      。又毒品危害防制條例第19條第1項 規定性質上係沒收之\n      補充規定。其屬於本條所定沒收之標的，如得以直接沒收\n      者，判決主文僅宣告沒收即可，不生「追徵其價額」或「\n      以其財產抵償之」問題，須沒收之標的全部或一部不能沒\n      收時，始生「追徵其價額」或「以其財產抵償之」選項問\n      題。而「追徵其價額」或「以其財產抵償之」係屬兩種選\n      項，分別係針對現行貨幣以外之其他財產與現行貨幣而言\n      ，最高法院99年度第5 次刑事庭會議亦可供參酌。則販賣\n      毒品所得之金錢或所用之物，無論已否扣案，均應依法沒\n      收。從而：\n      1.被告各次販賣海洛因所得（詳如犯罪事實四六所載）、\n        各次販賣甲基安非他命所得（詳如犯罪事實五九十所載\n        ），及各次販賣愷他命所得（詳如犯罪事實一至三八所\n        載）均未扣案，應分別依毒品危害防制條例第19條第1\n        項宣告沒收之，並各在附表一編號１至６、８至１０所示\n        其所犯販賣第一級、第二級及第三級毒品罪項下，就各\n        次販賣毒品所得宣告沒收，如全部或一部不能沒收時，\n        以其財產抵償之。\n      2.另案扣案之Sony Ericsson 廠牌行動電話1 支（含門號\n        0000000000號晶片卡1 張）、GPLUS 廠牌行動電話1 支\n        （含門號0000000000號晶片卡1 張）分別為被告所有，\n        供其犯犯罪事實一至三之販賣第三級毒品罪（被告持用\n        Sony Ericsson 廠牌行動電話），及犯罪事實四至八十\n        所示販賣第一級、第二級與第三級毒品及轉讓第一級毒\n        品罪所用之物（被告持用GPLUS 廠牌行動電話），扣案\n        之電子秤1 臺，亦係被告所有供其犯犯罪事實一至十所\n        示之販賣第一級、第二級、第三級毒品罪及轉讓第一級\n        毒品所用之物，業據被告於本院審理時供承在卷（見審\n        卷一第110 、134 、135 、138 頁），上開扣案物除GP\n        LUS 廠牌行動電話（含門號0000000000號晶片卡1 張）\n        外，雖均經臺中高分院另案宣告沒收確定，然於本案依\n        法屬應宣告沒收之物，仍應毒品危害防制條例第19條第\n        1 項之規定，在各該附表一所示之各次犯行之主刑項下\n        分別予以諭知沒收之。\n      3.另案扣案之分裝夾鍊袋2 包，亦係被告所有，且供其犯\n        上揭各次販賣第一級、第二級、第三級毒品及轉讓第一\n        級毒品罪預備之物，業據被告於本院審理供承在卷（見\n        同上頁），雖亦經臺中高分院另案宣告沒收確定，依前\n        開說明，仍應依刑法第38條第1 項第2 款規定，在上揭\n        各罪主刑項下宣告沒收。\n肆、適用之法律：\n    依刑事訴訟法第299 條第1 項前段，毒品危害防制條例第4\n    條第1 項、第2 項、第3 項、第8 條第1 項、第17條第1 項\n    、第2 項、第18條第1 項前段、第19條第1 項，刑法第11條\n    、第59條、第51條第5 款、第9 款、第38條第1 項第2 款，\n    判決如主文。\n本案經檢察官黃勝裕到庭執行職務。\n中    華    民    國  100     年    11    月    16    日\n                  刑事第十三庭  審判長法  官  賴妙雲\n                                      法  官  黃麗玲\n                                      法  官  楊欣怡\n以上正本證明與原本無異。\n如不服本判決應於收受判決後10日內向本院提出上訴書狀，並應\n敘述具體理由；其未敘述上訴理由者，應於上訴期間屆滿後20日\n內向本院補提理由書（均須按他造當事人之人數附繕本）「切勿\n逕送上級法院」。\n                                      書記官  黃泰能\n中    華    民    國   100    年    11    月    16    日\n附錄論罪科刑法條：\n毒品危害防制條例第4條\n製造、運輸、販賣第一級毒品者，處死刑或無期徒刑；處無期徒\n刑者，得併科新臺幣2 千萬元以下罰金。\n製造、運輸、販賣第二級毒品者，處無期徒刑或7 年以上有期徒\n刑，得併科新臺幣1 千萬元以下罰金。\n製造、運輸、販賣第三級毒品者，處5 年以上有期徒刑，得併科\n新臺幣7 百萬元以下罰金。\n製造、運輸、販賣第四級毒品者，處3 年以上10年以下有期徒刑\n，得併科新臺幣3 百萬元以下罰金。\n製造、運輸、販賣專供製造或施用毒品之器具者，處1 年以上7\n年以下有期徒刑，得併科新臺幣1 百萬元以下罰金。\n前五項之未遂犯罰之。\n毒品危害防制條例第8條\n轉讓第一級毒品者，處1 年以上7 年以下有期徒刑，得併科新臺\n幣1 百萬元以下罰金。\n轉讓第二級毒品者，處6 月以上5 年以下有期徒刑，得併科新臺\n幣70萬元以下罰金。\n轉讓第三級毒品者，處3 年以下有期徒刑，得併科新臺幣30萬元\n以下罰金。\n轉讓第四級毒品者，處1 年以下有期徒刑，得併科新臺幣10萬元\n以下罰金。\n前四項之未遂犯罰之。\n轉讓毒品達一定數量者，加重其刑至二分之一，其標準由行政院\n定之。\n附表一\n┌──┬─────┬─────────────────┐\n│編號│ 犯罪事實 │所犯罪名及應處之刑（含主刑、從刑）│\n├──┼─────┼─────────────────┤\n│ １ │犯罪事實欄│吳茂毅販賣第三級毒品，處有期徒刑貳│\n│    │一所載之犯│年陸月。未扣案販賣第三級毒品所得新│\n│    │行        │臺幣肆佰元沒收之，如全部或一部不能│\n│    │          │沒收時，以其財產抵償之。扣案如附表│\n│    │          │三編號3、5、6所示之物均沒收。     │\n├──┼─────┼─────────────────┤\n│ ２ │犯罪事實欄│吳茂毅販賣第三級毒品，處有期徒刑貳│\n│    │二所載之犯│年陸月。未扣案販賣第三級毒品所得新│\n│    │行        │臺幣肆佰元沒收之，如全部或一部不能│\n│    │          │沒收時，以其財產抵償之。扣案如附表│\n│    │          │三編號3、5、6所示之物均沒收。     │\n├──┼─────┼─────────────────┤\n│ ３ │犯罪事實欄│吳茂毅販賣第三級毒品，處有期徒刑貳│\n│    │三所載之犯│年陸月。未扣案販賣第三級毒品所得新│\n│    │行        │臺幣肆佰元沒收之，如全部或一部不能│\n│    │          │沒收時，以其財產抵償之；扣案如附表│\n│    │          │三編號3、5、6所示之物均沒收。     │\n├──┼─────┼─────────────────┤\n│ ４ │犯罪事實欄│吳茂毅販賣第一級毒品，處有期徒刑│\n│    │四所載之犯│年拾月。未扣案販賣第一級毒品所得新│\n│    │行        │臺幣伍佰元沒收之，如全部或一部不能│\n│    │          │沒收時，以其財產抵償之。扣案如附表│\n│    │          │三編號3、5、6所示之物均沒收。     │\n├──┼─────┼─────────────────┤\n│ ５ │犯罪事實欄│吳茂毅販賣第二級毒品，處有期徒刑貳│\n│    │五所載之犯│年。未扣案販賣第二級毒品所得新臺幣│\n│    │行        │壹仟伍佰元沒收之，如全部或一部不能│\n│    │          │沒收時，以其財產抵償之。扣案如附表│\n│    │          │三編號4、5、6所示之物均沒收。     │\n├──┼─────┼─────────────────┤\n│ ６ │犯罪事實欄│吳茂毅販賣第一級毒品，處有期徒刑肆│\n│    │六所載之犯│年貳月。未扣案販賣第一級毒品所得新│\n│    │行        │臺幣仟元沒收之，如全部或一部不能│\n│    │          │沒收時，以其財產抵償之。扣案如附表│\n│    │          │三編號4、5、6所示之物均沒收。     │\n├──┼─────┼─────────────────┤\n│ ７ │犯罪事實欄│吳茂毅轉讓第一級毒品，處有期徒刑捌│\n│    │七所載之犯│月。扣案如附表三編號一所示之物沒收│\n│    │行        │銷燬之。扣案如附表三編號4 、5 、6 │\n│    │          │所示之物均沒收。                  │\n├──┼─────┼─────────────────┤\n│ ８ │犯罪事實欄│吳茂毅販賣第三級毒品，處有期徒刑貳│\n│    │八所載之犯│年捌月。未扣案販賣第三級毒品所得新│\n│    │行        │臺幣貳仟元沒收之，如全部或一部不能│\n│    │          │沒收時，以其財產抵償之。扣案如附表│\n│    │          │三編號4、5、6所示之物均沒收。     │\n├──┼─────┼─────────────────┤\n│ ９ │犯罪事實欄│吳茂毅販賣第二級毒品，處有期徒刑壹│\n│    │九所載之犯│年拾壹月。未扣案販賣第二級毒品所得│\n│    │行        │新臺幣伍佰元沒收之，如全部或一部不│\n│    │          │能沒收時，以其財產抵償之。扣案如附│\n│    │          │表三編號5、6所示之物均沒收。      │\n├──┼─────┼─────────────────┤\n│ １０ │犯罪事實欄│吳茂毅販賣第二級毒品，處有期徒刑壹│\n│    │十所載之犯│年拾壹月。扣案如附表三編號二所示之│\n│    │行        │物沒收銷燬之；未扣案販賣第二級毒品│\n│    │          │所得新臺幣伍佰元沒收之，如全部或一│\n│    │          │部不能沒收時，以其財產抵償之。扣案│\n│    │          │如附表三編號4 、5 、6 所示之物均沒│\n│    │          │收。                              │\n└──┴─────┴─────────────────┘\n附表二：\n┌──┬──────┬────────────────────┬──────┐\n│編號│時      間  │通  訊  監  察  譯  文  內  容          │備註        │\n├──┼──────┼────────────────────┼──────┤\n│１  │99年01月30日│A：0000000000（吳茂毅）                 │佐證犯罪事實│\n│    │00時07分55秒│B：0000000000（曾書賢）                 │一二三      │\n│    │            ├────────────────────┤通訊監察譯文│\n│    │            │A：那個「酒」（術語）你是要拿錢給我嗎？ │出處：99偵  │\n│    │            │B：沒有，我要順便跟你拿那個「酒」啦。對 │14634號卷第 │\n│    │            │阿。然後禮拜天「酒錢」在一次全部給你。  │59頁        │\n│    │            │A：上次欠三瓶嗎                         │            │\n│    │            │B：對阿對阿。                           │            │\n│    │            │A：二、三瓶嗎？                         │            │\n│    │            │B：二瓶啦。上次先跟你拿二瓶而已。還有欠 │            │\n│    │            │   三瓶吧！嘿呀。                       │            │\n│    │            │A：你往上楓的方向走會看到酒國英雄。還沒 │            │\n│    │            │   有到酒國英雄。哎～那條是什麼路？     │            │\n│    │            │B：酒國英雄對面那條路嘛。               │            │\n│    │            │A：嘿。酒國英雄那裡。                   │            │\n│    │            │（A男叫B男到酒國英雄在打給A男）         │            │\n├──┼──────┼────────────────────┼──────┤\n│２  │99年01月29日│A：0000000000（吳茂毅）                 │佐證犯罪事實│\n│    │19時37分27秒│B：0000000000（曹家榮）                 │四          │\n│    │            ├────────────────────┤通訊監察譯文│\n│    │            │A：喂。                                 │出處：99偵  │\n│    │            │B：喂。                                 │13990號卷第 │\n│    │            │A：怎麼了？                             │21頁        │\n│    │            │B：啊？                                 │            │\n│    │            │A：你不是在找我？                       │            │\n│    │            │B：哇操，都昏了。你那邊現在還有「酒」（ │            │\n│    │            │   術語）嗎？                           │            │\n│    │            │A：八點半就有了。                       │            │\n│    │            │B：喔～還好。那不用了、不用了。我剛才殺 │            │\n│    │            │   到那邊知道嗎？我殺到太平去買酒（術語 │            │\n│    │            │   ）吶。                               │            │\n│    │            │A：我這裡就有「酒」了。                 │            │\n│    │            │B：啊？                                 │            │\n│    │            │A：我這裡就有「酒」了。                 │            │\n│    │            │B：你在哪裡？                           │            │\n│    │            │A：我在家裡阿。                         │            │\n│    │            │B：啊？                                 │            │\n│    │            │A：我在我家阿。                         │            │\n│    │            │B：哭爸喔。你那邊現在就有了嗎？         │            │\n│    │            │A：嘿押。                               │            │\n│    │            │B ：「一」耶。我昏倒了。我又回去，你就馬│            │\n│    │            │   上要拿出來喔。                       │            │\n│    │            │A：好阿，你多久會到？                   │            │\n│    │            │B：……。喂。                           │            │\n│    │            │A：你打給我，我就出來了。               │            │\n│    │            │B：我差不多二十分就到了啦。             │            │\n│    │            │A：好。                                 │            │\n│    │            │B：不要給我弄太少啦。                   │            │\n│    │            │A：好，掰掰。                           │            │\n│    │            │B：好。                                 │            │\n│    ├──────┼────────────────────┼──────┤\n│    │99年01月29日│A：0000000000（吳茂毅）                 │佐證犯罪事實│\n│    │19時52分55秒│B：0000000000（曹家榮）                 │四          │\n│    │            ├────────────────────┤通訊監察譯文│\n│    │            │B：喂，到了啦。                         │出處：99偵  │\n│    │            │A：停車場。                             │13990號卷第 │\n│    │            │B：好啦。                               │22頁        │\n│    │            │                                        │            │\n│    ├──────┼────────────────────┼──────┤\n│    │99年01月29日│A：0000000000（吳茂毅）                 │佐證犯罪事實│\n│    │19時56分17秒│B：0000000000（曹家榮）                 │四          │\n│    │            ├────────────────────┤通訊監察譯文│\n│    │            │A：要出去了啦。                         │出處：99偵  │\n│    │            │B：吼～喔。                             │13990號卷第 │\n│    │            │                                        │22頁        │\n│    │            │                                        │            │\n│    ├──────┼────────────────────┼──────┤\n│    │99年01月29日│A：0000000000（吳茂毅）                 │佐證犯罪事實│\n│    │20時12分56秒│B：0000000000（曹家榮）                 │四          │\n│    │            ├────────────────────┤通訊監察譯文│\n│    │            │B：這樣子弄得話，我明天怎麼跟你弄？     │出處：99偵  │\n│    │            │A：喔我等一下跟他們講一下明天來換新的球 │13990號卷第 │\n│    │            │   給你。                               │22頁        │\n│    │            │B：喔，真的明天不要這樣子搞了喔。       │            │\n│    │            │A：你要什麼？                           │            │\n├──┼──────┼────────────────────┼──────┤\n│３  │99年01月29日│A：0000000000（吳茂毅）                 │佐證犯罪事實│\n│    │22時56分12秒│B：0000000000（鄒聖緯）                 │五          │\n│    │            ├────────────────────┤通訊監察譯文│\n│    │            │B：我要三罐。                           │出處：99偵  │\n│    │            │A：三罐喔。                             │14634號卷第 │\n│    │            │B：嘿。                                 │74頁        │\n│    │            │A：你在哪裡？                           │            │\n│    │            │B：我在大雅阿。                         │            │\n│    │            │A：我在大雅台新銀行等你。               │            │\n│    │            │B：哪裡？                               │            │\n│    │            │A：台新銀行。                           │            │\n│    │            │（B男在問台新銀行在哪裡）               │            │\n│    │            │A：我一分鐘就到了。                     │            │\n│    │            │B：好～。                               │            │\n│    │            │A：好～。                               │            │\n│    │            │B：我馬上過去。                         │            │\n│    │            │A：好。                                 │            │\n│    ├──────┼────────────────────┼──────┤\n│    │99年01月29日│A：0000000000（吳茂毅）                 │佐證犯罪事實│\n│    │23時00分21秒│B：0000000000（鄒聖偉）                 │五          │\n│    │            ├────────────────────┤通訊監察譯文│\n│    │            │A：喂你在哪裡？                         │出處：99偵  │\n│    │            │B：你在哪裡？我沒有看到你。             │14634號卷第 │\n│    │            │A：我到台新銀行後面，我繞出去了。       │74頁        │\n│    │            │B：台新銀行喔～。                       │            │\n│    │            │A：你到門口等。                         │            │\n├──┼──────┼────────────────────┼──────┤\n│４  │99年01月30日│A：0000000000（吳茂毅）                 │佐證犯罪事實│\n│    │15時40分57秒│B：0000000000（徐嘉偉）                 │六          │\n│    │            ├────────────────────┤通訊監察譯文│\n│    │            │A：你要借幾仟？                         │出處：99偵  │\n│    │            │B：同款阿。                             │14634號卷第 │\n│    │            │A：同款，三仟五嗎？                     │49頁        │\n│    │            │B：…。                                 │            │\n│    │            │A：三仟？好阿。三仟。你到相同的停車場打 │            │\n│    │            │   給我。我差不多十分鐘到那裡。         │            │\n│    │            │B：好阿。                               │            │\n│    │            │A：好。                                 │            │\n│    │            │B：我可能會晚點啦。我到了再打給你啦。   │            │\n│    │            │A：好啦。有確定嗎？                     │            │\n│    │            │B：嗯。                                 │            │\n│    │            │A：OK。                                 │            │\n│    ├──────┼────────────────────┼──────┤\n│    │99年01月30日│A：0000000000（吳茂毅）                 │佐證犯罪事實│\n│    │18時00分01秒│B：0000000000（徐嘉偉）                 │六          │\n│    │            ├────────────────────┤通訊監察譯文│\n│    │            │A：喂。                                 │出處：99偵  │\n│    │            │B：喂。我現在過去找你喔。               │14634號卷第 │\n│    │            │A：掰掰。                               │49頁        │\n│    │            │B：掰掰。                               │            │\n│    │            │                                        │            │\n│    │            │                                        │            │\n│    │            │                                        │            │\n│    │            │                                        │            │\n│    ├──────┼────────────────────┼──────┤\n│    │99年01月30日│A：0000000000（吳茂毅）                 │佐證犯罪事實│\n│    │18時24分47秒│B：0000000000（徐嘉偉）                 │六          │\n│    │            ├────────────────────┤通訊監察譯文│\n│    │            │A：你到了嗎？                           │出處：99偵  │\n│    │            │B：嘿。                                 │14634號卷第 │\n│    │            │A：我差不多三分到。                     │49頁        │\n│    │            │B：掰掰。                               │            │\n│    │            │A：掰。                                 │            │\n├──┼──────┼────────────────────┼──────┤\n│５  │99年01月31日│A：0000000000（吳茂毅）                 │佐證犯罪事實│\n│    │16時23分34秒│B：0000000000（曹家榮）                 │七          │\n│    │            ├────────────────────┤通訊監察譯文│\n│    │            │B：你什麼時候會回來？                   │出處：99偵  │\n│    │            │A：大概一個小時以內吧。                 │13990號卷第 │\n│    │            │B：一個小時以內嗎？                     │22頁        │\n│    │            │A：嘿。你要一瓶「水」（術語）嗎？       │            │\n│    │            │B：用半瓶好不好？                       │            │\n│    │            │A：半瓶嗎？                             │            │\n│    │            │B：好不好？                             │            │\n│    │            │A：好啦。                               │            │\n│    │            │B：喂貓咪。                             │            │\n│    │            │A：嘿。                                 │            │\n│    │            │B：給你救一次好不好？                   │            │\n│    │            │A：喔～。                               │            │\n│    │            │B：今天…都沒有用耶。                   │            │\n│    │            │A：早上吶。早上都沒有用？               │            │\n│    │            │B：對阿，今天都沒有用阿。早上那個是朋友 │            │\n│    │            │   的阿。                               │            │\n│    │            │A：…那個早上有用吶。我早上拿給那個誰， │            │\n│    │            │   比較好吶。                           │            │\n│    │            │B：不是啦，我是說：早上那個…那個沒有用 │            │\n│    │            │   啦。                                 │            │\n│    │            │A：喔～。                               │            │\n│    │            │B：好不好？                             │            │\n│    │            │A：那我再打給你。                       │            │\n│    │            │B：不要不接吶。老大。                   │            │\n│    │            │A：不會。                               │            │\n│    │            │B：我會死掉吶。                         │            │\n│    │            │A：好～。                               │            │\n│    ├──────┼────────────────────┼──────┤\n│    │99年01月31日│A：0000000000（吳茂毅）                 │佐證犯罪事實│\n│    │17時51分11秒│B：0000000000（曹家榮）                 │七          │\n│    │            ├────────────────────┤通訊監察譯文│\n│    │            │B：喂，你到了嗎？                       │出處：99偵  │\n│    │            │A：我差不多6點到。                      │13990號卷第 │\n│    │            │B：啊？                                 │23頁        │\n│    │            │A：我6點到台中打給你。                  │            │\n│    │            │B：好阿。                               │            │\n│    ├──────┼────────────────────┼──────┤\n│    │99年01月31日│A：0000000000（吳茂毅）                 │佐證犯罪事實│\n│    │18時01分53秒│B：0000000000（曹家榮）                 │七          │\n│    │            ├────────────────────┤通訊監察譯文│\n│    │            │簡訊：貓咪你說等你到6點電話卻不接我人在 │出處：99偵  │\n│    │            │不舒服你別這樣搞好嗎                    │13990號卷第 │\n│    │            │                                        │23頁        │\n│    │            │                                        │            │\n│    ├──────┼────────────────────┼──────┤\n│    │99年01月31日│A：0000000000（吳茂毅）                 │佐證犯罪事實│\n│    │19時24分17秒│B：0000000000（曹家榮）                 │七          │\n│    │            ├────────────────────┤通訊監察譯文│\n│    │            │簡訊：品質不錯，保持下去，期待明天，保持│出處：99偵  │\n│    │            │聯絡，新年快樂                          │13990號卷第 │\n│    │            │                                        │23頁        │\n│    │            │                                        │            │\n├──┼──────┼────────────────────┼──────┤\n│６  │99年02月04日│A：0000000000（吳茂毅）                 │佐證犯罪事實│\n│    │00時42分46秒│B：0000000000（李明修）                 │八          │\n│    │            ├────────────────────┤通訊監察譯文│\n│    │            │B：喂。                                 │出處：99偵  │\n│    │            │A：喂。你不要這樣子講啦。電話中你不要這 │14634號卷第 │\n│    │            │   樣子講啦。你若是被人監聽到，咱們倆都 │33頁        │\n│    │            │   會有事情吶。                         │            │\n│    │            │B：喲。                                 │            │\n│    │            │A：你可以用「一箱」（術語）。這我跟你說 │            │\n│    │            │   ，你跟他講：一萬啦。                 │            │\n│    │            │B：什麼？                               │            │\n│    │            │A：差不多一萬啦。嘿呀，他有在放嗎？     │            │\n│    │            │B：我不知道。                           │            │\n│    │            │A：你若說沒有。一就一萬啦。好不好？若他 │            │\n│    │            │   有拿我再請你喝的「啤酒」（術語）好不 │            │\n│    │            │   好？                                 │            │\n│    │            │B：抱歉了，我不曉得要怎麼講。           │            │\n│    │            │A：沒關係，你跟他說：一萬啦。半箱五仟五 │            │\n│    │            │   啦。若四分之一箱就跟他說：三仟啦。   │            │\n│    │            │B：好啦。                               │            │\n│    │            │A：吼好。                               │            │\n├──┼──────┼────────────────────┼──────┤\n│７  │99年02月04日│A：0000000000（吳茂毅）                 │佐證犯罪事實│\n│    │23時02分23秒│B：0000000000（曹家榮）                 │九          │\n│    │            ├────────────────────┤通訊監察譯文│\n│    │            │簡訊：怎麼酒又不夠，這樣下去很難交陪，杯│出處：99偵  │\n│    │            │子還破洞，注意點，別再出問題了。        │13990號卷第 │\n│    │            │                                        │23頁        │\n│    │            │                                        │            │\n├──┼──────┼────────────────────┼──────┤\n│８  │99年02月05日│A：0000000000（吳茂毅）                 │佐證犯罪事實│\n│    │18時55分06秒│B：0000000000（鄒聖緯）                 │十          │\n│    │            ├────────────────────┤通訊監察譯文│\n│    │            │B：喂。                                 │出處：99偵  │\n│    │            │A：你來上夢全家找我好媽？               │14634號卷第 │\n│    │            │B：大楓全家喔？                         │78頁        │\n│    │            │A：嘿～。吼，我在全家等你。             │            │\n│    │            │B：好～。                               │            │\n│    │            │A：好～。                               │            │\n│    ├──────┼────────────────────┼──────┤\n│    │99年02月05日│A：0000000000（吳茂毅）                 │佐證犯罪事實│\n│    │18時56分38秒│B：0000000000（鄒聖緯）                 │十          │\n│    │            ├────────────────────┤通訊監察譯文│\n│    │            │A：喂。                                 │出處：99偵  │\n│    │            │B：喂。順便帶一點「葡萄酒」（術語）出來 │14634號卷第 │\n│    │            │   喔。                                 │78頁        │\n│    │            │A：好～我知道。                         │            │\n│    │            │B：吼。我兩分鐘到啦。                   │            │\n│    │            │A：好。                                 │            │\n│    │            │B：好。                                 │            │\n└──┴──────┴────────────────────┴──────┘\n附表三\n┌──┬────────────────────────────┬───┐\n│編號│      扣     案     物     品     及     數     量      │所有人│\n├──┼────────────────────────────┼───┤\n│ 1  │海洛因7 小包（合計淨重2.44公克，驗餘淨重2.35公克，空包裝│吳茂毅│\n│    │總重2.32公克）                                          │      │\n├──┼────────────────────────────┼───┤\n│ 2  │甲基安非他命20包（驗前總毛重17.32 公克，包裝塑膠袋總重約│吳茂毅│\n│    │4.80公克）                                              │      │\n├──┼────────────────────────────┼───┤\n│ 3  │Sony Ericsson 廠牌行動電話1 支（含0000000000號晶片卡1 張│吳茂毅│\n│    │）                                                      │      │\n├──┼────────────────────────────┼───┤\n│ 4  │GPLUS 廠牌行動電話（雙卡手機）1 支（含門號0000000000號  │吳茂毅│\n│    │晶片卡1張）                                             │      │\n├──┼────────────────────────────┼───┤\n│ 5  │電子秤1臺                                               │吳茂毅│\n├──┼────────────────────────────┼───┤\n│ 6  │分裝夾鍊袋2包                                           │吳茂毅│\n└──┴────────────────────────────┴───┘",
  "structure": {
    "main": "吳茂毅犯如附表一所示之罪，各處如附表一所示之刑（含主刑、\n從刑）。應執行有期徒刑柒年拾月，沒收部分併執行之。",
    "fact": "壹、犯罪事實：\n    吳茂毅（綽號「貓啊」、「喵仔」、「貓咪」）明知海洛因\n    、甲基安非他命及愷他命分別係毒品危害防制條例第2 條第\n    2 項第1 款、第2 款及第3 款所管制之第一級、第二級及第\n    三級毒品，不得販賣、轉讓、持有（持有第三級毒品部分純\n    質淨重20公克以上者亦不得持有），竟分別基於意圖營利販\n    賣第一級、第二級及第三級毒品以牟利，及轉讓第一級毒品\n    之犯意，為下列犯行：\n    一曾書賢於民國98年5 、6 月間某日，以門號0000000000號\n      行動電話撥打電話予吳茂毅所有如附表三編號3 所示之行\n      動電話，表示欲購買新臺幣（下同）400 元之愷他命，吳\n      茂毅應允後，至臺中市○○區○○路上之文雅國小（下稱\n      文雅國小）附近，將數量不詳之愷他命1 包（無證據證明\n      超過純質淨重20公克）販賣予曾書賢1 次，惟因曾書賢未\n      攜帶金錢，而暫時賒欠款項。\n    二曾書賢於98年6 月底某日，以門號0000000000號行動電話\n      撥打電話予吳茂毅之上開行動電話，表示欲購買400 元之\n      愷他命，雙方約定交易之時間、地點後，吳茂毅即前往文\n      雅國小附近，將數量不詳之愷他命1 包（無證據證明超過\n      純質淨重20公克）交與曾書賢，惟曾書賢仍未攜帶金錢，\n      故暫時賒欠款項。\n    三曾書賢於98年7 月中旬某日，再以門號0000000000號行動\n      電話撥打電話予吳茂毅之上開行動電話，表示購買愷他命\n      之意願，雙方議妥交易金額後，吳茂毅前往約定地點即文\n      雅國小附近，將數量不詳之愷他命1 包（無證據證明超過\n      純質淨重20公克）販賣予曾書賢1 次，然因曾書賢未攜帶\n      金錢，而暫時賒欠買賣價金400 元。嗣於99年1 月30日，\n      吳茂毅持用其所有如附表三編號4 所示之行動電話撥打曾\n      書賢持用之門號0000000000號行動電話，向曾書賢催討積\n      欠之款項，曾書賢始於不詳時間，在臺中市大雅區某國小\n      附近，將3 次購毒款項交與吳茂毅。\n    四曹家榮於99年1 月29日19時37分27秒、19時52分55秒、19\n      時56分17秒許，持用之行動電話門號0000000000號撥打吳\n      茂毅所有附表三編號4 所示之行動電話與之聯繫，雙方於\n      電話中，以「酒」代表海洛因，「停車場」代表交易地點\n      即吳茂毅位於臺中市○○區○○里○○街192 巷21號之住\n      處附近停車場，約定購買海洛因之事宜。待雙方於電話中\n      完成約定交易毒品之事宜後，吳茂毅即於當日通話完畢後\n      之某時，在其住處附近之停車場，以500 元之代價，販賣\n      海洛因1 小包與曹家榮，一手交錢、一手交貨，而完成交\n      易。\n    五鄒聖緯於99年1 月29日22時56分12秒、23時0 分21秒許所\n      持用之行動電話門號0000000000號行動電話撥打附表三編\n      號4 所示之行動電話與吳茂毅聯繫後，雙方於電話中，以\n      「3 罐」代表甲基安非他命，「臺新銀行」代表交易地點\n      即臺中市○○區○○路上之臺新銀行，雙方議妥交易甲基\n      安非他命事宜，吳茂毅即於當日通話完畢後之某時，至臺\n      中市○○區○○路上之臺新銀行前面，將甲基安非他命3\n      小包交予鄒聖緯，並向鄒聖緯收取現金1,500 元。\n    六徐嘉偉持用之行動電話門號0000000000號，於99年1 月30\n      日15時40分57秒、18時0 分1 秒、18時24分47秒許，以行\n      動電話門號0000000000號撥打附表三編號4 所示之行動電\n      話與吳茂毅聯繫，雙方於電話中，以「同款」代表海洛因\n      ，「3500」及「3000」各代表價值3,500 元及3,000 元之\n      海洛因，雙方於電話中完成約定交易毒品之事宜，吳茂毅\n      即於當日通話完畢後之某時，在臺中市○○區○○路上之\n      某停車場，以3,000 元之代價，販賣海洛因1 小包與徐嘉\n      偉，並當場向徐嘉偉收取現金3,000 元，完成交易。\n    七吳茂毅於99年1 月31日16時23分34秒許，以附表三編號4\n      所示之行動電話與曹家榮所持用之行動電話門號00000000\n      00號聯繫，曹家榮表示毒癮發作，請求吳茂毅無償轉讓些\n      許海洛因與其止癮，吳茂毅同意後，於同日晚間19時24分\n      前之某時，至曹家榮位在臺中市○○區○○路4號 之住處\n      前，無償轉讓海洛因1 小包（無證據證明超過淨重5 公克\n      ）予曹家榮。曹家榮施用完畢後，於當日19時24分17秒，\n      以上開行動電話傳遞簡訊：「品質不錯、保持下去、期待\n      明天、保持聯絡、新年快樂。」等語予吳茂毅。\n    八李明修持用之行動電話門號0000000000號於99年2 月4 日\n      凌晨0 時42分46秒許，撥打附表三編號4 所示之行動電話\n      與吳茂毅聯繫，雙方於電話中，以「啤酒」代表愷他命，\n      以「1 箱啤酒」、「半箱」及「4 分之1 」各代表30公克\n      、15公克及5 公克之愷他命，約定交易愷他命事宜。吳茂\n      毅於當日通話完畢後之某時，至臺中市○○區○道1 號高\n      速公路豐原交流道下，以2,000 元之代價，販賣約5 公克\n      之愷他命1 小包予李明修，一手交錢、一手交貨，而完成\n      交易。\n    九吳茂毅於99年2 月4 日23時2 分前之某時，在不詳之地點\n      ，以500 元之代價，販賣甲基安非他命予曹家榮，銀貨兩\n      訖。嗣因吳茂毅所販賣之甲基安非他命品質不佳，包裝袋\n      又有破洞，曹家榮遂於當日晚間2 月4 日23時2 分23秒，\n      以行動電話門號0000000000號傳遞簡訊：「怎麼酒又不夠\n      ，這樣下去很難交陪，杯子還破洞，注意點，別再出問題\n      了。」等語，至吳茂毅所持用附表三編號4 所示之行動電\n      話，抱怨此事。\n    十鄒聖緯所持用行動電話門號0000000000號，於99年2 月5\n      日18時55分6 秒、18時56分38秒許，撥打附表三編號4 所\n      示之行動電話與吳茂毅聯繫後，雙方於電話中，以「葡萄\n      酒」代表甲基安非他命，「上夢全家（臺語）」、「大楓\n      全家（臺語）」代表交易地點即吳茂毅位在臺中市大雅區\n      上楓里住處巷口之全家便利商店，雙方議妥交易甲基安非\n      他命事宜，吳茂毅即於當日通話完畢後之某時，在其住處\n      巷口之全家便利商店前，將甲基安非他命1 小包交予鄒聖\n      緯，並向鄒聖緯收取現金500 元。\n    嗣經警對吳茂毅持用之門號0000000000號行動電話實施通訊\n    監察，並於99年2 月5 日22時30分許，另案為警在臺中市○\n    ○路○ 段與崇德十路口拘提到案，並扣得吳茂毅所有之海洛\n    因7 小包（合計淨重2.44公克，驗餘合計淨重2.35公克，包\n    裝袋總重2.32公克，外包裝因與海洛因相結合無從析離而應\n    視為第一級毒品）、甲基安非他命20包（驗前總毛重17.32\n    公克，包裝袋總重4.80公克，驗前總純質淨重10.89 公克，\n    鑑驗用罄0.11公克，外包裝因與甲基安非他命相結合無從析\n    離而應視為第二級毒品）、吳茂毅所有供上揭販賣第一級、\n    第二級、第三級毒品及轉讓第一級毒品所用之GPLUS 廠牌行\n    動電話1 支（含門號0000000000號晶片卡1 張）、Sony Eri\n    sson廠牌行動電話1 支（含門號0000000000號晶片卡1 張）\n    、電子秤1 臺、吳茂毅所有預備供上揭各次販賣第一級、第\n    二級、第三級毒品及轉讓第一級毒品所用之分裝夾鍊袋2 包\n    ，而查獲上情。\n貳、認定犯罪事實所憑證據及理由：\n  一程序部分：\n    (一)按於第一審辯論終結前，得就與本案相牽連之犯罪或本罪\n      之誣告罪，追加起訴；追加起訴，得於審判期日以言詞為\n      之，刑事訴訟法第265 條定有明文。又一人犯數罪者，為\n      相牽連之案件，刑事訴訟法第7 條第1 款亦有明文。本件\n      檢察官原起訴被告吳茂毅販賣海洛因與曹家榮、徐嘉偉，\n      販賣甲基安非他命與鄒聖緯、曹家榮，販賣愷他命與李明\n      修，及轉讓海洛因與曹家榮，嗣於100 年9 月29日以追加\n      起訴書，追加起訴被告於98年5 、6 月間某日、同年6 月\n      底某日及同年7 月間某日分別販賣愷他命與曾書賢之犯罪\n      事實，上開追加之販賣第三級毒品罪與本案原起訴被告之\n      各罪間，有一人犯數罪之相牽連關係，依上開法條規定，\n      檢察官於言詞辯論終結前追加起訴，當屬合法，法院自應\n      就追加起訴部分予以審判。\n    (二)證據能力部分：\n      1.按被告以外之人於偵查中向檢察官所為之陳述，除顯有\n        不可信之情況者外，得為證據，刑事訴訟法第159 條之\n        1 第2 項定有明文。偵查中對被告以外之人（包括證人\n        、鑑定人、告訴人、被害人及共同被告等）所為之偵查\n        筆錄，或被告以外之人向檢察官所提之書面陳述，性質\n        上均屬傳聞證據。惟現階段刑事訴訟法規定檢察官代表\n        國家偵查犯罪、實施公訴，依法其有訊問被告、證人及\n        鑑定人之權，證人、鑑定人且須具結，而實務運作時，\n        檢察官偵查中向被告以外之人所取得之陳述，原則上均\n        能遵守法律規定，不致違法取供，其可信度極高，職是\n        ，被告以外之人前於偵查中已具結而為證述，除反對該\n        項供述得具有證據能力之一方，已釋明「顯有不可信之\n        情況」之理由外，不宜以該證人未能於審判中接受他造\n        之反對詰問，即遽指該證人於偵查中之陳述不具證據能\n        力。查本件證人曹家榮、曾書賢、徐嘉偉、李明修及鄒\n        聖緯於偵查中所為之陳述，雖屬傳聞證據，然其等於偵\n        查中所為證言，均經具結，而被告吳茂毅及其辯護人均\n        未釋明上開證人之陳述有何「顯不可信之情況」，且於\n        客觀之外部情狀上，難認有何顯不可信之情狀，依上揭\n        規定，應認證人曹家榮、曾書賢、徐嘉偉、李明修及鄒\n        聖緯於偵查中所為之證述，得為證據。\n      2.又偵查犯罪機關依法定程序監聽之錄音，係以監聽之錄\n        音帶為其調查犯罪所得之證據，司法警察依據監聽錄音\n        結果予以翻譯而製作之通訊監察譯文，乃該監聽錄音帶\n        內容之顯示，此為學理上所稱之「派生證據」，屬於文\n        書證據之一種。於被告或訴訟關係人對該譯文之真實性\n        發生爭執或有所懷疑時，法院固應依刑事訴訟法第165\n        條之1 第2 項之規定，勘驗該監聽錄音帶以踐行調查證\n        據之程序，俾確認該錄音之聲音是否為通訊者本人及其\n        內容與通訊監察譯文之記載是否相符，或傳喚該通訊者\n        為證據調查。倘被告或訴訟關係人對該通訊監察譯文之\n        真實性並不爭執，即無勘驗辨認其錄音之聲音予以調查\n        之必要，法院於審判期日如已踐行提示通訊監察譯文供\n        當事人辨認或告以要旨，使其表示意見等程序並為辯論\n        者，其所為之訴訟程序即無不合（最高法院97年度臺上\n        字第561 號判決意旨可資參照）。再按有事實足認被告\n        或犯罪嫌疑人有最輕本刑為3 年以上有期徒刑之罪嫌，\n        並危害國家安全或社會秩序情節重大，而有相當理由可\n        信其通訊內容與本案有關，且不能或難以其他方法蒐集\n        或調查證據者，得發通訊監察書。前項通訊監察書，偵\n        查中由檢察官依司法警察機關聲請或依職權以書面記載\n        第11條之事項，並敘明理由、檢附相關文件，聲請該管\n        法院核發。通訊保障及監察法第5 條第1 項第1款 、第\n        2 項定有明文。本案所引用有關行動電話號碼00000000\n        00號之監聽錄音，係經本院法官核准在案，有詳載案由\n        、監察電話、對象及時間等之99年度聲監字第163 號通\n        訊監察書、電話附表等附卷可參〔見臺灣臺中地方法院\n        檢察署99年度偵字第13990 號卷（下稱偵卷一）第36、\n        37頁〕，係依法所為之監聽；況審酌電話監聽侵害被告\n        權益之種類及輕重、對於被告訴訟上防禦不利益之程度\n        、犯罪所生之危害或實害等情形，兼顧人權保障及公共\n        利益之均衡維護，亦認此部分電話監聽合於比例原則，\n        是認應具有證據能力。且下列經本院所引用認定之通訊\n        監察譯文，被告及辯護人對該通訊監察譯文之真實性並\n        不爭執，復經本院於審判期日踐行提示通訊監聽譯文供\n        當事人、指定辯護人辨認並告以要旨，使其等表示意見\n        ，是該通訊監察譯文自亦有證據能力。\n      3.現行刑事訴訟法關於「鑑定」之規定，除選任自然人充\n        當鑑定人外，另設有囑託機關鑑定制度。依同法第198\n        條、第208 條之規定，不論鑑定人或鑑定機關、團體，\n        固均應由法院、審判長、受命法官或檢察官視具體個案\n        之需要而為選任、囑託，並依第206 條之規定，提出言\n        詞或書面報告，始符合同法第159 條第1 項所定得作為\n        證據之「法律有規定」之情形。否則所為之鑑定，仍屬\n        傳聞證據。然於司法警察機關調查中之案件，為因應實\n        務上，或因量大，或有急迫之現實需求，例行性當然有\n        鑑定之必要者，例如毒品之種類與成分、尿液之毒品反\n        應，或者槍彈有無殺傷力等鑑定，基於檢察一體原則，\n        得由該管檢察長對於轄區內之案件，以事前概括選任鑑\n        定人或囑託鑑定機關、團體之方式，俾便轄區內之司法\n        警察官、司法警察對於調查中之此類案件，得即時送請\n        先前已選任之鑑定人或囑託之鑑定機關、團體實施鑑定\n        ，以求時效（法務部92年9 月1 日法檢字第0920035083\n        號函參照）。此種由檢察機關概括選任鑑定人或概括囑\n        託鑑定機關、團體，再轉知司法警察官、司法警察於調\n        查犯罪時參考辦理之作為，法無明文禁止，係為因應現\n        行刑事訴訟法增訂傳聞法則及其例外規定之實務運作而\n        為。其所為之鑑定結果，與檢察官選任或囑託為鑑定者\n        ，性質上並無差異，同具有證據能力（最高法院96年度\n        臺上字第2860號判決要旨參照）。卷附之詮昕科技股份\n        有限公司濫用藥物尿液檢驗報告各3 份〔見臺灣雲林地\n        方法院檢察署99年度偵字第14634 偵查卷（下稱偵卷二\n        ）第130 至132 頁〕，均為臺中縣警察局清水分局（現\n        改制為臺中市政府警察局清水分局）送請鑑定，揆諸前\n        揭說明，屬「法律規定」得為證據者，應有證據能力。\n      4.再按被告以外之人於審判外之陳述，雖不符刑事訴訟法\n        第159 條之1 至第159 條之4 之規定，而經當事人於審\n        判程序同意作為證據，法院審酌該言詞陳述或書面陳述\n        作成時之情況，認為適當者，亦得為證據。當事人、代\n        理人或辯護人於法院調查證據時，知有第159 條第1 項\n        不得為證據之情形，而未於言詞辯論終結前聲明異議者\n        ，視為有前項之同意，刑事訴訟法第159 條之5 定有明\n        文。核其立法意旨在於傳聞證據未經當事人之反對詰問\n        予以核實，原則上先予排除。惟若當事人已放棄反對詰\n        問權，於審判程序中表明同意該等傳聞證據可作為證據\n        ；或於言詞辯論終結前未聲明異議，基於尊重當事人對\n        傳聞證據之處分權，及證據資料愈豐富，愈有助於真實\n        發見之理念，且強化言詞辯論主義，使訴訟程序得以順\n        暢進行，上開傳聞證據亦均具有證據能力。查：本判決\n        除上揭所述外，下列所引之被告以外之人於審判外所為\n        之陳述及卷內其他書證（供述證據部分），查無符合同\n        法第159 條之1 至之4 等前4 條之情形，檢察官、被告\n        及其辯護人於本院準備程序中均表示對該等傳聞證據之\n        證據能力均同意有證據能力〔見本院100 年度訴字第16\n        78號卷（下稱審卷一）第42頁〕，於本院審理時並未就\n        卷內其他證據資料之證據能力有所爭執，且迄本院言詞\n        辯論終結前，均未主張有刑事訴訟法第159 條第1 項不\n        得為證據之情形，是應認已同意卷內證據均得作為證據\n        ，且經本院審酌上開傳聞證據作成時，較無人情施壓或\n        干擾，亦無不當取證之情形，認為以之作為本案之證據\n        亦屬適當，是上揭傳聞證據自具有證據能力。\n  二得心證之理由：\n    (一)訊據被告就上開犯罪事實，於警詢、偵訊及本院審理時均\n      坦承不諱〔見偵卷一第12至20頁、第79、80頁、偵卷二第\n      14至18頁、第166 頁、第115 頁、臺灣臺中地方法院檢察\n      署100 年度偵續字第214 號卷（下稱偵卷三）第52頁〕，\n      復經證人曾書賢、曹家榮、鄒聖緯、徐嘉偉及李明修於警\n      詢（見偵卷一第38至43頁、偵卷二第25至31頁、第41至47\n      頁）、檢察官偵訊時（見偵卷一第70至72頁、偵卷二第64\n      、65、146 、168 、158 、159 頁、偵卷三第52頁）證述\n      明確。證人曹家榮於警詢時雖陳稱99年2 月4 日購買甲基\n      安非他命之金額為1,000 元，證人鄒聖緯於警詢時則陳稱\n      ：99年1 月29日此次「貓啊」有拿3 包甲基安非他命與伊\n      ，以1 包1,000 元賣伊等語，證人李明修另證稱交易時間\n      為99年2 月5 日或6 日之晚上11、12時許，惟查：1.證人\n      曹家榮於99年12月2 日偵訊時具結證稱：99年2 月4 日該\n      次交易是在發簡訊之前，地點伊記不清楚，不是在被告住\n      處附近，就是在其工作之工廠前，只能確定向被告買了50\n      0 元的甲基安非他命等語（見偵卷一第71頁）。被告於本\n      院審理時亦供稱：99年2 月4 日曹家榮傳簡訊抱怨這次，\n      伊販賣甲基安非他命之金額為500 元，伊本來要賣1,000\n      元，但曹家榮說錢不夠，伊就便宜賣其500 元，賺取較少\n      利潤等語（見審卷一第112 頁）。故證人曹家榮就該次交\n      易之金額於偵訊中之證述與被告於本院審理時之陳述相符\n      ，併基於罪疑惟輕之原則，應認定被告該次販賣甲基安非\n      他命與曹家榮之金額應為500 元。2.被告於100 年4 月28\n      日偵訊時供陳：李明修應該記錯日期了，因伊於99年2 月\n      5 日晚上9 點多就被抓了，所以當天應該是講完電話沒多\n      久就交易等語（見偵卷一第80頁）。而被告確於99年2 月\n      5 日22時30分為警在臺中市○○路○ 段與崇德十路口拘提\n      到案，並於同月6 日遭羈押於法務部矯正署臺中看守所，\n      有臺灣高等法院臺中分院99年度上訴字第1604號判決及臺\n      灣高等法院被告前案紀錄表各1 份在卷可按，核與被告前\n      開供述相符，被告之前開供述堪以採信。被告與李明修之\n      交易時間為99年2 月4 日當日通話後之某時，堪以認定。\n      3.被告於99年6 月9 日警詢時供稱：伊以門號0000000000\n      號行動電話於99年1 月29日17時3 分4 秒與鄒聖緯持用之\n      門號0000000000號行動電話聯繫，係鄒聖緯要向伊購買甲\n      基安非他命，通訊監察譯文中「2 罐」是代表1,000 元之\n      意思，伊於當日23時許在大雅區臺新銀行後面，拿甲基安\n      非他命3 小包給鄒聖緯，並向其收取1,500 元等語（見偵\n      卷二第17頁）。被告於100 年4 月28日偵訊時雖一度陳稱\n      該次交易之金額為3,000 元，然嗣後確認交易金額為1,50\n      0 元。再觀諸附表二編號２被告與曹家榮之通訊監察譯文\n      ，曹家榮於電話中表示欲購買「一」，而該次交易金額為\n      500 元，業經證人曹家榮證述明確，堪認被告於警詢中供\n      稱「2 罐」是代表1,000 元等語，應屬真實無訛。是鄒聖\n      緯於99年1 月29日22時56分12秒通話中表示要「3 罐」，\n      應係欲購買1,500 元之甲基安非他命之意，被告與鄒聖緯\n      該次之交易金額應為1,500 元，亦堪認定。\n    (二)另觀諸被告與曹家榮、曾書賢、徐嘉偉、李明修、鄒聖緯\n      所示通話對象之通話內容（詳如附表二所示），多使用暗\n      語如「酒」、「一」、「3 罐」、「3500」、「3000」、\n      「水」、「1 箱」等作為代號，且通話內容簡短，多半係\n      在談妥價格、數量或交易地點後，即結束通話，確屬實務\n      上常見之毒品交易對話，有本院99年度聲監字第163 號通\n      訊監察書1 份及如附表二所示之通訊監察譯文附卷足佐（\n      內容與證據出處均詳附表二所示），益徵上開人等通話之\n      目的確係要交易或轉讓毒品無疑。\n    (三)證人李明修及曾書賢於99年3 月18日經警採尿送驗，證人\n      李明修呈現愷他命陽性反應，證人曾書賢呈現甲基安非他\n      命及愷他命陽性反應，亦有詮昕科技股份有限公司濫用藥\n      物尿液檢驗報告2 份在卷可按，而證人曹家榮則於99年2\n      月4 日及同年月7 日分別因施用海洛因、甲基安非他命案\n      件，經本院分別判處有期徒刑8 月、3 月，定應執行有期\n      徒刑10月，亦有本院99年度訴字第1401號判決1 份附卷可\n      參。足認證人李明修、曾書賢均有施用愷他命之慣習，證\n      人曹家榮亦有施用海洛因、甲基安非他命之慣習，對外有\n      購毒之需求。\n    (四)又被告於99年2 月5 日22時30分許，另案為警在臺中市○\n      ○路○ 段與崇德十路口拘提到案，並扣得其所有之海洛因\n      7 小包（合計淨重2.44公克，驗餘合計淨重2.35公克，包\n      裝袋總重2.32公克，外包裝因與海洛因相結合無從析離而\n      應視為第一級毒品）、甲基安非他命20包（驗前總毛重17\n      .32 公克，包裝袋總重4.80公克，驗前總純質淨重10.89\n      公克，鑑驗用罄0.11公克，外包裝因與甲基安非他命相結\n      合無從析離而應視為第二級毒品）、其所有供上揭販賣第\n      一級、第二級、第三級毒品及轉讓第一級毒品所用如附表\n      三編號3 、4 所示之行動電話、電子秤1 臺、其所有預備\n      供上揭各次販賣第一級、第二級及第三級毒品及轉讓第一\n      級毒品所用之分裝夾鍊袋2 包，亦經臺中高分院99上訴字\n      第1604號判決認定屬實，有該判決附卷可參。可認被告確\n      有管道取得海洛因、甲基安非他命以供販賣、轉讓，並有\n      販賣及轉讓之工具。\n    (五)又被告供稱：伊販賣海洛因、甲基安非他命及愷他命，可\n      以從中賺到自己施用的部分，400 元之愷他命約可賺取0.\n      7 至0.8 公克之愷他命供己施用等語（見審卷一第112 、\n      138 頁），足認被告販賣海洛因、甲基安非他命及愷他命\n      ，主觀上有營利之意圖無訛。\n    (六)從而，被告之自白與相關證據均相符合，堪以採信，被告\n      各次販賣海洛因、甲基安非他命、愷他命及轉讓海洛因之\n      犯行，均堪認定，應依法論科。\n、論罪科刑之理由：\n  一核被告所為，犯罪事實一二三八部分，均係犯毒品危害防制\n    條例第4 條第3 項之販賣第三級毒品罪；犯罪事實四六部分\n    ，均係犯毒品危害防制條例第4 條第1 項之販賣第一級毒品\n    罪；犯罪事實五九十部分，係犯毒品危害防制條例第4 條第\n    2 項之販賣第二級毒品罪；犯罪事實七部分，則係犯同條例\n    第8條第1項轉讓第一級毒品罪。\n  二被告各該持有海洛因、甲基安非他命之低度行為，分別為販\n    賣、轉讓之高度行為所吸收，均不另論罪。又持有第三級毒\n    品愷他命之行為，毒品危害防制條例第11條第5 項規定：「\n    持有第三級毒品純質淨重20公克以上者，處3 年以下有期徒\n    刑，得併科新臺幣30萬元以下罰金。」然被告各次販賣愷他\n    命實際持有愷他命之重量不明，且未扣案無從鑑定愷他命之\n    純質淨重是否為20公克以上。準此，依無罪推定原則，被告\n    上開販賣前持有第三級毒品愷他命之行為不成立犯罪，而無\n    「吸收」之問題。至被告轉讓海洛因部分，亦無證據證明轉\n    讓之重量超過淨重5 公克，自不得依同條例第8 條第6 項予\n    以加重，附此敘明。\n  三被告所犯上開10罪，均犯意各別，行為各自獨立，應分論併\n    罰之。\n  四按98年5 月20日修正公布之毒品危害防制條例第17條第2 項\n    關於「犯第4 條至第8 條之罪於偵查及審判中均自白者，減\n    輕其刑。」之規定，旨在獎勵犯罪人之悛悔，同時使偵查或\n    審判機關易於發現真實，以利毒品查緝，俾收防制毒品危害\n    之效；故不論該被告之自白，係出於自動或被動、簡單或詳\n    細、一次或多次，並其自白後有無翻異，苟其於偵查及審判\n    中均有自白，即應依法減輕其刑。又刑法上所稱之自白，係\n    指行為人對其被訴之犯罪事實為任意性之供認而言（最高法\n    院98年度臺上字第6928號判決）。本件被告於檢察官偵訊時\n    及本院審理時均已自白其上揭販賣第一級、第二級、第三級\n    毒品及轉讓第一級毒品等犯行，業如上述，爰依毒品危害防\n    制條例第17條第2 項規定就上揭各罪均減輕其刑。\n  五又98年5 月20日修正公布之毒品危害防制條例第17條第1 項\n    規定：「犯第4 條至第8 條、第10條或第11條之罪，供出毒\n    品來源，因而查獲其他正犯或共犯者，減輕或免除其刑」。\n    被告吳茂毅於另案販賣毒品案件經檢察官偵訊時，供稱：伊\n    向一位綽號「小陳」（嗣經查為陳文仕）之人買毒品的，其\n    電話為0000000000；伊約今年（即99年）1 月中或1 月底，\n    交易地點好像在苗栗交流道，該次伊向綽號「小陳」拿了約\n    半兩多（約16、17公克）的安非他命，4 點多公克的海洛因\n    ，小陳跟伊說把毒品賣掉後，再將錢交給小陳，小陳說安非\n    他命要21,000元，海洛因要22,000元，但尚未給小陳錢；小\n    陳除0923的電話外，還有一支0000000000的電話等語（見審\n    卷一第65、66頁）。檢察官隨即依被告之供述而簽分偵辦小\n    陳販賣毒品案件，嗣確有查獲綽號「小陳」之陳文仕販賣海\n    洛因、甲基安非他命與被告之犯行，而予偵查起訴在案，亦\n    有臺灣臺中地方法院檢察署99年10月7 日中檢輝姜99偵4796\n    字第133021號函及該署99年度偵字第12459 、15267 號起訴\n    書可稽（見審卷一第67頁、第54至56頁）。是可認被告自99\n    年1 月起始向陳文仕購買海洛因、甲基安非他命，被告就犯\n    罪事實四至七九十之犯行供出毒品來源，因而查獲其他正犯\n    ，而就此部分販賣第一級毒品、第二級毒品及轉讓第一級毒\n    品犯行，各依毒品危害防制條例第17條第1 項遞減輕其刑。\n    至被告於警詢、偵訊時雖另供稱其係向葉文仁購買愷他命，\n    惟另案被告葉文仁並非因被告之供述而查獲其販賣愷他命之\n    犯行，亦有臺灣臺中地方法院檢察署中檢輝敦100 他3168字\n    第101475號函文、內政部警政署保安警察隊第三總隊第一大\n    隊100 年7 月6 日保三壹警刑字第1000003994號函文暨函附\n    之職務報告及葉文仁之臺灣高等法院被告前案紀錄表各1 份\n    在卷可按，是被告販賣第三級毒品之犯行，自無從適用毒品\n    危害防制條例第17條第1 項減刑規定之寬典，附此敘明。\n  六刑法第59條規定之適用：\n    (一)再按刑法第59條之減輕其刑，係裁判上之減輕，必以犯罪\n      之情狀可憫恕，認為宣告法定最低度之刑猶嫌過重者，始\n      有其適用；如別有法定減輕之事由，應先依法定減輕事由\n      減輕其刑後，猶嫌過重時，始得為之；若有2 種以上法定\n      減輕事由，仍應先依法定減輕事由遞減其刑後，猶嫌過重\n      時，始得再依刑法第59條規定酌減其刑，最高法院88年度\n      臺上字第1862號判決意旨可資參照。復按刑之量定，為求\n      個案裁判之妥當性，法律固賦予法院裁量權，但此項裁量\n      權之行使，除應依刑法第57條規定，審酌行為人及其行為\n      等一切情狀，為整體之評價，並應顧及比例原則與平等原\n      則，使罪刑均衡，輕重得宜，以契合社會之法律感情。販\n      賣第一級毒品罪之法定刑為「死刑或無期徒刑；處無期徒\n      刑者，得併科新臺幣20,000,000元以下罰金」。其法定刑\n      既為死刑、無期徒刑，別無其他自由刑之規定，刑度可謂\n      重大。然同為販賣第一級毒品之人，其原因動機不一，犯\n      罪情節未必盡同，或有大盤毒梟者，亦有中、小盤之分，\n      甚或僅止於吸毒者友儕間為求互通有無而為販賣者亦有之\n      ，其販賣行為所造成危害社會之程度自屬有異，法律科處\n      此類犯罪，所設之法定最低本刑卻同為死刑或無期徒刑，\n      且處無期徒刑者，得併科新臺幣20,000,000元以下之罰金\n      ，不可謂不重。於此情形，倘依其情狀處以有期徒刑，即\n      足以懲儆，並可達防衛社會之目的者，自非不可依客觀之\n      犯行與主觀之惡性二者加以考量其情狀是否有可憫恕之處\n      ，適用刑法第59條之規定酌量減輕其刑，期使個案裁判之\n      量刑，能斟酌至當，符合比例原則。又適用刑法第59條酌\n      量減輕其刑時，並不排除同法第57條所列舉10款事由之審\n      酌（最高法院70年5 月16日70年度第6 次刑事庭長會議決\n      議足供參考）。\n    (二)依上開說明意旨，本院認為被告所為犯罪事實四六所示之\n      販賣海洛因犯行，固戕害國民健康，助長施用毒品惡習，\n      其行為實屬不該，惟被告各次販賣海洛因之所得僅500 元\n      、3,000 元，均係小額交易，屬毒品交易之下游，販賣毒\n      品之對象曹家榮原即有施用毒品之慣習，有其臺灣高等法\n      院被告前案紀錄表1 份在卷可按，被告之惡性情節較諸大\n      量走私進口或長期販賣毒品之「大盤」、「中盤」毒販有\n      差異，其對社會整體侵害之程度尚非鉅大，被告亦染有施\n      用之惡習，業據被告供承在卷，被告係為圖自己得以施用\n      毒品，始鋌而走險販賣海洛因，惟被告就所犯之販賣第一\n      級毒品罪，其最輕法定本刑為無期徒刑，縱使被告所犯販\n      賣第一級毒品罪經依毒品危害防制條例第17條第2 項規定\n      減輕其刑，及依同條第1 項規定遞減輕其刑後，均量處法\n      定最低刑度之刑，仍嫌過重，而依被告客觀之犯行與主觀\n      之惡性二者加以考量其犯罪情狀，爰依刑法第59條之規定\n      ，就被告所犯上開販賣第一級毒品罪部分各酌量減輕其刑\n      ，並均遞減輕其刑。\n  七又「數罪併罰，分別宣告其罪之刑，依下列各款定其應執行\n    者：五宣告多數有期徒刑者，於各刑中之最長期以上，各刑\n    合併之刑期以下，定其刑期。但不得逾30年。」刑法第51條\n    第5 款定有明文。又法律上屬於自由裁量事項，尚非概無法\n    律性之拘束，在法律上有其外部界限及內部界限。前者法律\n    之具體規定，使法院得以具體選擇為適當裁判，此為自由裁\n    量之外部界限。後者法院為自由裁量時，應考量法律之目的\n    ，法律秩序之理念所在，此為自由裁量之內部界限。法院為\n    裁判時，二者均不得有所踰越。在數罪併罰應定其應執行刑\n    之案件，法院所為刑之酌定，固屬自由裁量事項，然對於法\n    律之內、外部界限，仍均應受其拘束。最高法院94年度臺非\n    字第21號判決要旨足供本案定刑之參考。從而，數罪併罰在\n    定其應執行之刑之際，自應再為應執行之刑的決定，亦屬一\n    種特別的量刑過程，其考量結果，並非單純表示一種數罪刑\n    度的總和而已，而是再次對於同一行為人責任的檢視。相較\n    刑法第57條定有科刑時應審酌的事項，此項規定係對一般犯\n    罪行為之裁量而言。而合併刑之宣告，則屬一種對犯罪人本\n    身及所犯之各種犯罪的綜合判斷。申言之，定執行之刑的宣\n    告，並非在法定範圍之內自由裁定，應注意行為人從其犯數\n    罪所反映的人格特性，及考量刑法目的相關刑事政策，妥為\n    宣告。而刑法的功能中，除一般預防及特別預防之外，更重\n    要的是，行為人再社會化及具體的社會保護作用，否則加諸\n    過度之刑罰於被告，徒僅造成責任報應，去實現一個未知、\n    抽象的正義。因此，是否為被告長期性監禁宣告的同時，應\n    一併考量被告犯案情節對社會之衝擊，並注意此舉是否造成\n    被告更生絕望的心理影響，使得被告的人格遭受完全性地抹\n    滅。換言之，必須考量刑罰手段的相當性，儘量選擇能使受\n    刑人復歸社會生活之刑罰方法。法官無法以所謂「治亂世用\n    重典」之理由，加重刑罰以圖遏止歪風，不能過度強調所謂\n    一般預防的刑罰目的。實則，就人性尊嚴及人權的思想而言\n    ，任何一個人均非他人的工具，以加重被告的刑罰作為達到\n    阻嚇其他人犯罪的手段，被告已淪為教化社會大眾的工具，\n    喪失了作為一個人主體性，這均與我國刑事政策之立法有違\n    。凡此即構成最高法院所揭示「內部界限」之意義。\n  八本院審酌前揭情狀（包括前述酌減之事由），並參酌被告有\n    違反毒品危害防制條例前科，有前開臺灣高等法院被告前案\n    紀錄表可參，被告之素行難認良善。被告明知海洛因、甲基\n    安非他命、愷他命係屬戕害人身心之毒品，竟為貪圖不法利\n    益，鋌而走險販賣供他人施用，另基於朋友情誼，無償提供\n    海洛因與曹家榮施用，擴大毒害，無視上開毒品足以使施用\n    者導致精神障礙、性格異常，甚至造成生命危險之生理成癮\n    性及心理依賴性，嚴重影響社會治安、戕害國民身心健康，\n    並考量被告各自販賣毒品之次數、販賣之所得非鉅、轉讓海\n    洛因之數量、次數，犯罪之動機、方法、手段，販賣毒品之\n    數量及對象，及犯後之態度等一切情狀，分別量處如主文所\n    示之刑。又被告現年27歲，若本院定以過重之應執行刑，其\n    效用可能隨著長期刑之執行，等比例地大幅下跌，效用甚低\n    ，對被告教化效果亦不佳，尚且加重國家財政無益負擔，亦\n    有害被告回歸社會，爰定其應執行之刑如主文所示，以期兼\n    顧對於被告之警示及更生。公訴檢察官雖請求量處被告有期\n    徒刑15年，然公訴檢察官未慮及被告販賣第一級毒品部分，\n    情輕法重，有毒品危害防制條例第17條第1 項、第2 項規定\n    之適用，並應依刑法第59條予以酌減，販賣第二級毒品部分\n    ，亦有毒品危害防制條例第17條第1 項、第2 項規定之適用\n    ，是公訴檢察官前開求刑實屬過重，尚有未洽。\n  九沒收部分：\n    (一)按以營利為目的販入毒品，經多次販賣後，持有剩餘毒品\n      被查獲，其各次販賣毒品行為，固應併合處罰。惟該持有\n      剩餘毒品之低度行為，應僅為最後一次販賣毒品之高度行\n      為所吸收，不另論罪。故就該查獲之剩餘毒品，祇能於最\n      後一次之販賣毒品罪宣告沒收銷燬，不得於各次販賣毒品\n      罪均宣告沒收銷燬；又應沒收銷燬之物執行完畢與不存在\n      ，係屬二事，本案中因犯罪依法必須沒收銷燬之物，縱已\n      於其他相關案件確定判決中諭知沒收銷燬並執行完畢，亦\n      不得認已滅失而不存在，且因該他案判決之認定僅具個案\n      拘束之效力，是於本案依法仍屬應宣告沒收銷燬之物，自\n      不得以該物因其他相關之判決已諭知沒收銷燬確定，並經\n      執行完畢為由，而不為沒收之諭知，最高法院98年度臺上\n      字第738 號、98年度臺上字第4258號判決要旨參照。是以\n      ：\n      1.本案被告吳茂毅所犯多次販賣第一級毒品及轉讓第一級\n        毒品罪，其最後一次轉讓第一級毒品之時間為99年1 月\n        31日，而被告另案於99年2 月5 日22時30分許，為警在\n        臺中市○○路○ 段與崇德十路口，扣得被告所有供販賣\n        所用之第一級毒品海洛因7 小包（合計淨重2.44公克，\n        驗餘合計淨重2.35公克，包裝袋總重2.32公克，外包裝\n        因與第一級毒品海洛因相結合無從析離而應視為第1級\n        毒品，行政院衛生署草屯療養院98年4 月21日草療鑑字\n        第0980002432號函、法務部調查局93年3 月19日調科壹\n        字第09300113060 號函、最高法院95年度臺上字第3934\n        號判決參照），係被告吳茂毅經多次販賣第一級毒品及\n        轉讓第一級毒品後，持有剩餘第一級毒品被查獲，縱經\n        臺中高分院以99年度上訴字第1604號判決宣告沒收銷燬\n        ，經最高法院駁回上訴後確定，惟該他案判決之認定僅\n        具個案拘束之效力，於本案依法仍屬應宣告沒收銷燬之\n        物，仍應依法宣告沒收銷燬之。故就前揭所查獲之剩餘\n        毒品，應於被告最後1 次之轉讓海洛因罪宣告沒收銷燬\n        ，不得於各次販賣毒品罪均宣告沒收銷燬，亦即前揭扣\n        案之海洛因自應於附表一編號７所示之主刑之後，依毒\n        品危害防制條例第18條第1 項前段宣告沒收銷燬之（最\n        高法院98年度臺上字第3060號判決意旨參照）。至因鑑\n        驗所耗損之第一級毒品海洛因部分，既已滅失，即不另\n        為沒收之諭知。\n      2.本案被告亦有犯多次販賣第二級毒品罪，其最後1 次販\n        賣第二級毒品之時間為99年2 月5 日，而被告另案於99\n        年2 月5 日22時30分許，為警在臺中市○○路○ 段與崇\n        德十路口，扣得之第二級毒品甲基安非他命20包（驗前\n        總毛重17.32 公克，包裝袋總重4.80公克，驗前總純質\n        淨重10.89 公克，鑑驗用罄0.11公克，外包裝因與第2\n        級毒品甲基安非他命相結合無從析離而應視為第二級毒\n        品，理由同上揭行政院衛生署草屯療養院函釋），係被\n        告經多次販賣第二級毒品後，持有剩餘第二級毒品被查\n        獲，縱經臺中高分院以99年度上訴字第1604號判決宣告\n        沒收銷燬，依前揭說明，仍應於本案諭知沒收銷燬之。\n        故就前揭所查獲之剩餘毒品，應於被告最後1 次之販賣\n        第二級毒品罪中宣告沒收銷燬，不得於各次販賣毒品罪\n        均宣告沒收銷燬，亦即前揭扣案之甲基安非他命自應於\n        附表一編號１０所示之主刑之後，依毒品危害防制條例第\n        18條第1 項前段宣告沒收銷燬之（最高法院98年度臺上\n        字第3060號判決意旨參照）。至因鑑驗所耗損之第二級\n        毒品甲基安非他命部分，既已滅失，即不另為沒收之諭\n        知。\n    (二)毒品危害防制條例第19條第1項規定，犯販賣毒品罪者，\n      其犯罪所得之財物均沒收之，係採義務沒收主義。故販賣\n      毒品所得之對價，不問其中成本若干，利潤多少，均應全\n      部諭知沒收，貫徹政府查禁煙毒之決心，以符立法本旨（\n      最高法院91年度臺上字第2419號判決意旨參照）。再按毒\n      品危害防制條例第19條第1 項，係刑法第38條第1 項第2\n      款之特別規定，採義務沒收主義，苟能證明係供犯罪所用\n      或因犯罪所得之財物，均應沒收之，如全部或一部不能沒\n      收時，追徵其價額或以其財產抵償之，並不以當場搜獲扣\n      押者為限（最高法院88年度臺上字2039號判決要旨參照）\n      。又毒品危害防制條例第19條第1項 規定性質上係沒收之\n      補充規定。其屬於本條所定沒收之標的，如得以直接沒收\n      者，判決主文僅宣告沒收即可，不生「追徵其價額」或「\n      以其財產抵償之」問題，須沒收之標的全部或一部不能沒\n      收時，始生「追徵其價額」或「以其財產抵償之」選項問\n      題。而「追徵其價額」或「以其財產抵償之」係屬兩種選\n      項，分別係針對現行貨幣以外之其他財產與現行貨幣而言\n      ，最高法院99年度第5 次刑事庭會議亦可供參酌。則販賣\n      毒品所得之金錢或所用之物，無論已否扣案，均應依法沒\n      收。從而：\n      1.被告各次販賣海洛因所得（詳如犯罪事實四六所載）、\n        各次販賣甲基安非他命所得（詳如犯罪事實五九十所載\n        ），及各次販賣愷他命所得（詳如犯罪事實一至三八所\n        載）均未扣案，應分別依毒品危害防制條例第19條第1\n        項宣告沒收之，並各在附表一編號１至６、８至１０所示\n        其所犯販賣第一級、第二級及第三級毒品罪項下，就各\n        次販賣毒品所得宣告沒收，如全部或一部不能沒收時，\n        以其財產抵償之。\n      2.另案扣案之Sony Ericsson 廠牌行動電話1 支（含門號\n        0000000000號晶片卡1 張）、GPLUS 廠牌行動電話1 支\n        （含門號0000000000號晶片卡1 張）分別為被告所有，\n        供其犯犯罪事實一至三之販賣第三級毒品罪（被告持用\n        Sony Ericsson 廠牌行動電話），及犯罪事實四至八十\n        所示販賣第一級、第二級與第三級毒品及轉讓第一級毒\n        品罪所用之物（被告持用GPLUS 廠牌行動電話），扣案\n        之電子秤1 臺，亦係被告所有供其犯犯罪事實一至十所\n        示之販賣第一級、第二級、第三級毒品罪及轉讓第一級\n        毒品所用之物，業據被告於本院審理時供承在卷（見審\n        卷一第110 、134 、135 、138 頁），上開扣案物除GP\n        LUS 廠牌行動電話（含門號0000000000號晶片卡1 張）\n        外，雖均經臺中高分院另案宣告沒收確定，然於本案依\n        法屬應宣告沒收之物，仍應毒品危害防制條例第19條第\n        1 項之規定，在各該附表一所示之各次犯行之主刑項下\n        分別予以諭知沒收之。\n      3.另案扣案之分裝夾鍊袋2 包，亦係被告所有，且供其犯\n        上揭各次販賣第一級、第二級、第三級毒品及轉讓第一\n        級毒品罪預備之物，業據被告於本院審理供承在卷（見\n        同上頁），雖亦經臺中高分院另案宣告沒收確定，依前\n        開說明，仍應依刑法第38條第1 項第2 款規定，在上揭\n        各罪主刑項下宣告沒收。\n肆、適用之法律：\n    依刑事訴訟法第299 條第1 項前段，毒品危害防制條例第4\n    條第1 項、第2 項、第3 項、第8 條第1 項、第17條第1 項\n    、第2 項、第18條第1 項前段、第19條第1 項，刑法第11條\n    、第59條、第51條第5 款、第9 款、第38條第1 項第2 款，\n    判決如主文。\n本案經檢察官黃勝裕到庭執行職務。",
    "reason": "壹、犯罪事實：\n    吳茂毅（綽號「貓啊」、「喵仔」、「貓咪」）明知海洛因\n    、甲基安非他命及愷他命分別係毒品危害防制條例第2 條第\n    2 項第1 款、第2 款及第3 款所管制之第一級、第二級及第\n    三級毒品，不得販賣、轉讓、持有（持有第三級毒品部分純\n    質淨重20公克以上者亦不得持有），竟分別基於意圖營利販\n    賣第一級、第二級及第三級毒品以牟利，及轉讓第一級毒品\n    之犯意，為下列犯行：\n    一曾書賢於民國98年5 、6 月間某日，以門號0000000000號\n      行動電話撥打電話予吳茂毅所有如附表三編號3 所示之行\n      動電話，表示欲購買新臺幣（下同）400 元之愷他命，吳\n      茂毅應允後，至臺中市○○區○○路上之文雅國小（下稱\n      文雅國小）附近，將數量不詳之愷他命1 包（無證據證明\n      超過純質淨重20公克）販賣予曾書賢1 次，惟因曾書賢未\n      攜帶金錢，而暫時賒欠款項。\n    二曾書賢於98年6 月底某日，以門號0000000000號行動電話\n      撥打電話予吳茂毅之上開行動電話，表示欲購買400 元之\n      愷他命，雙方約定交易之時間、地點後，吳茂毅即前往文\n      雅國小附近，將數量不詳之愷他命1 包（無證據證明超過\n      純質淨重20公克）交與曾書賢，惟曾書賢仍未攜帶金錢，\n      故暫時賒欠款項。\n    三曾書賢於98年7 月中旬某日，再以門號0000000000號行動\n      電話撥打電話予吳茂毅之上開行動電話，表示購買愷他命\n      之意願，雙方議妥交易金額後，吳茂毅前往約定地點即文\n      雅國小附近，將數量不詳之愷他命1 包（無證據證明超過\n      純質淨重20公克）販賣予曾書賢1 次，然因曾書賢未攜帶\n      金錢，而暫時賒欠買賣價金400 元。嗣於99年1 月30日，\n      吳茂毅持用其所有如附表三編號4 所示之行動電話撥打曾\n      書賢持用之門號0000000000號行動電話，向曾書賢催討積\n      欠之款項，曾書賢始於不詳時間，在臺中市大雅區某國小\n      附近，將3 次購毒款項交與吳茂毅。\n    四曹家榮於99年1 月29日19時37分27秒、19時52分55秒、19\n      時56分17秒許，持用之行動電話門號0000000000號撥打吳\n      茂毅所有附表三編號4 所示之行動電話與之聯繫，雙方於\n      電話中，以「酒」代表海洛因，「停車場」代表交易地點\n      即吳茂毅位於臺中市○○區○○里○○街192 巷21號之住\n      處附近停車場，約定購買海洛因之事宜。待雙方於電話中\n      完成約定交易毒品之事宜後，吳茂毅即於當日通話完畢後\n      之某時，在其住處附近之停車場，以500 元之代價，販賣\n      海洛因1 小包與曹家榮，一手交錢、一手交貨，而完成交\n      易。\n    五鄒聖緯於99年1 月29日22時56分12秒、23時0 分21秒許所\n      持用之行動電話門號0000000000號行動電話撥打附表三編\n      號4 所示之行動電話與吳茂毅聯繫後，雙方於電話中，以\n      「3 罐」代表甲基安非他命，「臺新銀行」代表交易地點\n      即臺中市○○區○○路上之臺新銀行，雙方議妥交易甲基\n      安非他命事宜，吳茂毅即於當日通話完畢後之某時，至臺\n      中市○○區○○路上之臺新銀行前面，將甲基安非他命3\n      小包交予鄒聖緯，並向鄒聖緯收取現金1,500 元。\n    六徐嘉偉持用之行動電話門號0000000000號，於99年1 月30\n      日15時40分57秒、18時0 分1 秒、18時24分47秒許，以行\n      動電話門號0000000000號撥打附表三編號4 所示之行動電\n      話與吳茂毅聯繫，雙方於電話中，以「同款」代表海洛因\n      ，「3500」及「3000」各代表價值3,500 元及3,000 元之\n      海洛因，雙方於電話中完成約定交易毒品之事宜，吳茂毅\n      即於當日通話完畢後之某時，在臺中市○○區○○路上之\n      某停車場，以3,000 元之代價，販賣海洛因1 小包與徐嘉\n      偉，並當場向徐嘉偉收取現金3,000 元，完成交易。\n    七吳茂毅於99年1 月31日16時23分34秒許，以附表三編號4\n      所示之行動電話與曹家榮所持用之行動電話門號00000000\n      00號聯繫，曹家榮表示毒癮發作，請求吳茂毅無償轉讓些\n      許海洛因與其止癮，吳茂毅同意後，於同日晚間19時24分\n      前之某時，至曹家榮位在臺中市○○區○○路4號 之住處\n      前，無償轉讓海洛因1 小包（無證據證明超過淨重5 公克\n      ）予曹家榮。曹家榮施用完畢後，於當日19時24分17秒，\n      以上開行動電話傳遞簡訊：「品質不錯、保持下去、期待\n      明天、保持聯絡、新年快樂。」等語予吳茂毅。\n    八李明修持用之行動電話門號0000000000號於99年2 月4 日\n      凌晨0 時42分46秒許，撥打附表三編號4 所示之行動電話\n      與吳茂毅聯繫，雙方於電話中，以「啤酒」代表愷他命，\n      以「1 箱啤酒」、「半箱」及「4 分之1 」各代表30公克\n      、15公克及5 公克之愷他命，約定交易愷他命事宜。吳茂\n      毅於當日通話完畢後之某時，至臺中市○○區○道1 號高\n      速公路豐原交流道下，以2,000 元之代價，販賣約5 公克\n      之愷他命1 小包予李明修，一手交錢、一手交貨，而完成\n      交易。\n    九吳茂毅於99年2 月4 日23時2 分前之某時，在不詳之地點\n      ，以500 元之代價，販賣甲基安非他命予曹家榮，銀貨兩\n      訖。嗣因吳茂毅所販賣之甲基安非他命品質不佳，包裝袋\n      又有破洞，曹家榮遂於當日晚間2 月4 日23時2 分23秒，\n      以行動電話門號0000000000號傳遞簡訊：「怎麼酒又不夠\n      ，這樣下去很難交陪，杯子還破洞，注意點，別再出問題\n      了。」等語，至吳茂毅所持用附表三編號4 所示之行動電\n      話，抱怨此事。\n    十鄒聖緯所持用行動電話門號0000000000號，於99年2 月5\n      日18時55分6 秒、18時56分38秒許，撥打附表三編號4 所\n      示之行動電話與吳茂毅聯繫後，雙方於電話中，以「葡萄\n      酒」代表甲基安非他命，「上夢全家（臺語）」、「大楓\n      全家（臺語）」代表交易地點即吳茂毅位在臺中市大雅區\n      上楓里住處巷口之全家便利商店，雙方議妥交易甲基安非\n      他命事宜，吳茂毅即於當日通話完畢後之某時，在其住處\n      巷口之全家便利商店前，將甲基安非他命1 小包交予鄒聖\n      緯，並向鄒聖緯收取現金500 元。\n    嗣經警對吳茂毅持用之門號0000000000號行動電話實施通訊\n    監察，並於99年2 月5 日22時30分許，另案為警在臺中市○\n    ○路○ 段與崇德十路口拘提到案，並扣得吳茂毅所有之海洛\n    因7 小包（合計淨重2.44公克，驗餘合計淨重2.35公克，包\n    裝袋總重2.32公克，外包裝因與海洛因相結合無從析離而應\n    視為第一級毒品）、甲基安非他命20包（驗前總毛重17.32\n    公克，包裝袋總重4.80公克，驗前總純質淨重10.89 公克，\n    鑑驗用罄0.11公克，外包裝因與甲基安非他命相結合無從析\n    離而應視為第二級毒品）、吳茂毅所有供上揭販賣第一級、\n    第二級、第三級毒品及轉讓第一級毒品所用之GPLUS 廠牌行\n    動電話1 支（含門號0000000000號晶片卡1 張）、Sony Eri\n    sson廠牌行動電話1 支（含門號0000000000號晶片卡1 張）\n    、電子秤1 臺、吳茂毅所有預備供上揭各次販賣第一級、第\n    二級、第三級毒品及轉讓第一級毒品所用之分裝夾鍊袋2 包\n    ，而查獲上情。\n貳、認定犯罪事實所憑證據及理由：\n  一程序部分：\n    (一)按於第一審辯論終結前，得就與本案相牽連之犯罪或本罪\n      之誣告罪，追加起訴；追加起訴，得於審判期日以言詞為\n      之，刑事訴訟法第265 條定有明文。又一人犯數罪者，為\n      相牽連之案件，刑事訴訟法第7 條第1 款亦有明文。本件\n      檢察官原起訴被告吳茂毅販賣海洛因與曹家榮、徐嘉偉，\n      販賣甲基安非他命與鄒聖緯、曹家榮，販賣愷他命與李明\n      修，及轉讓海洛因與曹家榮，嗣於100 年9 月29日以追加\n      起訴書，追加起訴被告於98年5 、6 月間某日、同年6 月\n      底某日及同年7 月間某日分別販賣愷他命與曾書賢之犯罪\n      事實，上開追加之販賣第三級毒品罪與本案原起訴被告之\n      各罪間，有一人犯數罪之相牽連關係，依上開法條規定，\n      檢察官於言詞辯論終結前追加起訴，當屬合法，法院自應\n      就追加起訴部分予以審判。\n    (二)證據能力部分：\n      1.按被告以外之人於偵查中向檢察官所為之陳述，除顯有\n        不可信之情況者外，得為證據，刑事訴訟法第159 條之\n        1 第2 項定有明文。偵查中對被告以外之人（包括證人\n        、鑑定人、告訴人、被害人及共同被告等）所為之偵查\n        筆錄，或被告以外之人向檢察官所提之書面陳述，性質\n        上均屬傳聞證據。惟現階段刑事訴訟法規定檢察官代表\n        國家偵查犯罪、實施公訴，依法其有訊問被告、證人及\n        鑑定人之權，證人、鑑定人且須具結，而實務運作時，\n        檢察官偵查中向被告以外之人所取得之陳述，原則上均\n        能遵守法律規定，不致違法取供，其可信度極高，職是\n        ，被告以外之人前於偵查中已具結而為證述，除反對該\n        項供述得具有證據能力之一方，已釋明「顯有不可信之\n        情況」之理由外，不宜以該證人未能於審判中接受他造\n        之反對詰問，即遽指該證人於偵查中之陳述不具證據能\n        力。查本件證人曹家榮、曾書賢、徐嘉偉、李明修及鄒\n        聖緯於偵查中所為之陳述，雖屬傳聞證據，然其等於偵\n        查中所為證言，均經具結，而被告吳茂毅及其辯護人均\n        未釋明上開證人之陳述有何「顯不可信之情況」，且於\n        客觀之外部情狀上，難認有何顯不可信之情狀，依上揭\n        規定，應認證人曹家榮、曾書賢、徐嘉偉、李明修及鄒\n        聖緯於偵查中所為之證述，得為證據。\n      2.又偵查犯罪機關依法定程序監聽之錄音，係以監聽之錄\n        音帶為其調查犯罪所得之證據，司法警察依據監聽錄音\n        結果予以翻譯而製作之通訊監察譯文，乃該監聽錄音帶\n        內容之顯示，此為學理上所稱之「派生證據」，屬於文\n        書證據之一種。於被告或訴訟關係人對該譯文之真實性\n        發生爭執或有所懷疑時，法院固應依刑事訴訟法第165\n        條之1 第2 項之規定，勘驗該監聽錄音帶以踐行調查證\n        據之程序，俾確認該錄音之聲音是否為通訊者本人及其\n        內容與通訊監察譯文之記載是否相符，或傳喚該通訊者\n        為證據調查。倘被告或訴訟關係人對該通訊監察譯文之\n        真實性並不爭執，即無勘驗辨認其錄音之聲音予以調查\n        之必要，法院於審判期日如已踐行提示通訊監察譯文供\n        當事人辨認或告以要旨，使其表示意見等程序並為辯論\n        者，其所為之訴訟程序即無不合（最高法院97年度臺上\n        字第561 號判決意旨可資參照）。再按有事實足認被告\n        或犯罪嫌疑人有最輕本刑為3 年以上有期徒刑之罪嫌，\n        並危害國家安全或社會秩序情節重大，而有相當理由可\n        信其通訊內容與本案有關，且不能或難以其他方法蒐集\n        或調查證據者，得發通訊監察書。前項通訊監察書，偵\n        查中由檢察官依司法警察機關聲請或依職權以書面記載\n        第11條之事項，並敘明理由、檢附相關文件，聲請該管\n        法院核發。通訊保障及監察法第5 條第1 項第1款 、第\n        2 項定有明文。本案所引用有關行動電話號碼00000000\n        00號之監聽錄音，係經本院法官核准在案，有詳載案由\n        、監察電話、對象及時間等之99年度聲監字第163 號通\n        訊監察書、電話附表等附卷可參〔見臺灣臺中地方法院\n        檢察署99年度偵字第13990 號卷（下稱偵卷一）第36、\n        37頁〕，係依法所為之監聽；況審酌電話監聽侵害被告\n        權益之種類及輕重、對於被告訴訟上防禦不利益之程度\n        、犯罪所生之危害或實害等情形，兼顧人權保障及公共\n        利益之均衡維護，亦認此部分電話監聽合於比例原則，\n        是認應具有證據能力。且下列經本院所引用認定之通訊\n        監察譯文，被告及辯護人對該通訊監察譯文之真實性並\n        不爭執，復經本院於審判期日踐行提示通訊監聽譯文供\n        當事人、指定辯護人辨認並告以要旨，使其等表示意見\n        ，是該通訊監察譯文自亦有證據能力。\n      3.現行刑事訴訟法關於「鑑定」之規定，除選任自然人充\n        當鑑定人外，另設有囑託機關鑑定制度。依同法第198\n        條、第208 條之規定，不論鑑定人或鑑定機關、團體，\n        固均應由法院、審判長、受命法官或檢察官視具體個案\n        之需要而為選任、囑託，並依第206 條之規定，提出言\n        詞或書面報告，始符合同法第159 條第1 項所定得作為\n        證據之「法律有規定」之情形。否則所為之鑑定，仍屬\n        傳聞證據。然於司法警察機關調查中之案件，為因應實\n        務上，或因量大，或有急迫之現實需求，例行性當然有\n        鑑定之必要者，例如毒品之種類與成分、尿液之毒品反\n        應，或者槍彈有無殺傷力等鑑定，基於檢察一體原則，\n        得由該管檢察長對於轄區內之案件，以事前概括選任鑑\n        定人或囑託鑑定機關、團體之方式，俾便轄區內之司法\n        警察官、司法警察對於調查中之此類案件，得即時送請\n        先前已選任之鑑定人或囑託之鑑定機關、團體實施鑑定\n        ，以求時效（法務部92年9 月1 日法檢字第0920035083\n        號函參照）。此種由檢察機關概括選任鑑定人或概括囑\n        託鑑定機關、團體，再轉知司法警察官、司法警察於調\n        查犯罪時參考辦理之作為，法無明文禁止，係為因應現\n        行刑事訴訟法增訂傳聞法則及其例外規定之實務運作而\n        為。其所為之鑑定結果，與檢察官選任或囑託為鑑定者\n        ，性質上並無差異，同具有證據能力（最高法院96年度\n        臺上字第2860號判決要旨參照）。卷附之詮昕科技股份\n        有限公司濫用藥物尿液檢驗報告各3 份〔見臺灣雲林地\n        方法院檢察署99年度偵字第14634 偵查卷（下稱偵卷二\n        ）第130 至132 頁〕，均為臺中縣警察局清水分局（現\n        改制為臺中市政府警察局清水分局）送請鑑定，揆諸前\n        揭說明，屬「法律規定」得為證據者，應有證據能力。\n      4.再按被告以外之人於審判外之陳述，雖不符刑事訴訟法\n        第159 條之1 至第159 條之4 之規定，而經當事人於審\n        判程序同意作為證據，法院審酌該言詞陳述或書面陳述\n        作成時之情況，認為適當者，亦得為證據。當事人、代\n        理人或辯護人於法院調查證據時，知有第159 條第1 項\n        不得為證據之情形，而未於言詞辯論終結前聲明異議者\n        ，視為有前項之同意，刑事訴訟法第159 條之5 定有明\n        文。核其立法意旨在於傳聞證據未經當事人之反對詰問\n        予以核實，原則上先予排除。惟若當事人已放棄反對詰\n        問權，於審判程序中表明同意該等傳聞證據可作為證據\n        ；或於言詞辯論終結前未聲明異議，基於尊重當事人對\n        傳聞證據之處分權，及證據資料愈豐富，愈有助於真實\n        發見之理念，且強化言詞辯論主義，使訴訟程序得以順\n        暢進行，上開傳聞證據亦均具有證據能力。查：本判決\n        除上揭所述外，下列所引之被告以外之人於審判外所為\n        之陳述及卷內其他書證（供述證據部分），查無符合同\n        法第159 條之1 至之4 等前4 條之情形，檢察官、被告\n        及其辯護人於本院準備程序中均表示對該等傳聞證據之\n        證據能力均同意有證據能力〔見本院100 年度訴字第16\n        78號卷（下稱審卷一）第42頁〕，於本院審理時並未就\n        卷內其他證據資料之證據能力有所爭執，且迄本院言詞\n        辯論終結前，均未主張有刑事訴訟法第159 條第1 項不\n        得為證據之情形，是應認已同意卷內證據均得作為證據\n        ，且經本院審酌上開傳聞證據作成時，較無人情施壓或\n        干擾，亦無不當取證之情形，認為以之作為本案之證據\n        亦屬適當，是上揭傳聞證據自具有證據能力。\n  二得心證之理由：\n    (一)訊據被告就上開犯罪事實，於警詢、偵訊及本院審理時均\n      坦承不諱〔見偵卷一第12至20頁、第79、80頁、偵卷二第\n      14至18頁、第166 頁、第115 頁、臺灣臺中地方法院檢察\n      署100 年度偵續字第214 號卷（下稱偵卷三）第52頁〕，\n      復經證人曾書賢、曹家榮、鄒聖緯、徐嘉偉及李明修於警\n      詢（見偵卷一第38至43頁、偵卷二第25至31頁、第41至47\n      頁）、檢察官偵訊時（見偵卷一第70至72頁、偵卷二第64\n      、65、146 、168 、158 、159 頁、偵卷三第52頁）證述\n      明確。證人曹家榮於警詢時雖陳稱99年2 月4 日購買甲基\n      安非他命之金額為1,000 元，證人鄒聖緯於警詢時則陳稱\n      ：99年1 月29日此次「貓啊」有拿3 包甲基安非他命與伊\n      ，以1 包1,000 元賣伊等語，證人李明修另證稱交易時間\n      為99年2 月5 日或6 日之晚上11、12時許，惟查：1.證人\n      曹家榮於99年12月2 日偵訊時具結證稱：99年2 月4 日該\n      次交易是在發簡訊之前，地點伊記不清楚，不是在被告住\n      處附近，就是在其工作之工廠前，只能確定向被告買了50\n      0 元的甲基安非他命等語（見偵卷一第71頁）。被告於本\n      院審理時亦供稱：99年2 月4 日曹家榮傳簡訊抱怨這次，\n      伊販賣甲基安非他命之金額為500 元，伊本來要賣1,000\n      元，但曹家榮說錢不夠，伊就便宜賣其500 元，賺取較少\n      利潤等語（見審卷一第112 頁）。故證人曹家榮就該次交\n      易之金額於偵訊中之證述與被告於本院審理時之陳述相符\n      ，併基於罪疑惟輕之原則，應認定被告該次販賣甲基安非\n      他命與曹家榮之金額應為500 元。2.被告於100 年4 月28\n      日偵訊時供陳：李明修應該記錯日期了，因伊於99年2 月\n      5 日晚上9 點多就被抓了，所以當天應該是講完電話沒多\n      久就交易等語（見偵卷一第80頁）。而被告確於99年2 月\n      5 日22時30分為警在臺中市○○路○ 段與崇德十路口拘提\n      到案，並於同月6 日遭羈押於法務部矯正署臺中看守所，\n      有臺灣高等法院臺中分院99年度上訴字第1604號判決及臺\n      灣高等法院被告前案紀錄表各1 份在卷可按，核與被告前\n      開供述相符，被告之前開供述堪以採信。被告與李明修之\n      交易時間為99年2 月4 日當日通話後之某時，堪以認定。\n      3.被告於99年6 月9 日警詢時供稱：伊以門號0000000000\n      號行動電話於99年1 月29日17時3 分4 秒與鄒聖緯持用之\n      門號0000000000號行動電話聯繫，係鄒聖緯要向伊購買甲\n      基安非他命，通訊監察譯文中「2 罐」是代表1,000 元之\n      意思，伊於當日23時許在大雅區臺新銀行後面，拿甲基安\n      非他命3 小包給鄒聖緯，並向其收取1,500 元等語（見偵\n      卷二第17頁）。被告於100 年4 月28日偵訊時雖一度陳稱\n      該次交易之金額為3,000 元，然嗣後確認交易金額為1,50\n      0 元。再觀諸附表二編號２被告與曹家榮之通訊監察譯文\n      ，曹家榮於電話中表示欲購買「一」，而該次交易金額為\n      500 元，業經證人曹家榮證述明確，堪認被告於警詢中供\n      稱「2 罐」是代表1,000 元等語，應屬真實無訛。是鄒聖\n      緯於99年1 月29日22時56分12秒通話中表示要「3 罐」，\n      應係欲購買1,500 元之甲基安非他命之意，被告與鄒聖緯\n      該次之交易金額應為1,500 元，亦堪認定。\n    (二)另觀諸被告與曹家榮、曾書賢、徐嘉偉、李明修、鄒聖緯\n      所示通話對象之通話內容（詳如附表二所示），多使用暗\n      語如「酒」、「一」、「3 罐」、「3500」、「3000」、\n      「水」、「1 箱」等作為代號，且通話內容簡短，多半係\n      在談妥價格、數量或交易地點後，即結束通話，確屬實務\n      上常見之毒品交易對話，有本院99年度聲監字第163 號通\n      訊監察書1 份及如附表二所示之通訊監察譯文附卷足佐（\n      內容與證據出處均詳附表二所示），益徵上開人等通話之\n      目的確係要交易或轉讓毒品無疑。\n    (三)證人李明修及曾書賢於99年3 月18日經警採尿送驗，證人\n      李明修呈現愷他命陽性反應，證人曾書賢呈現甲基安非他\n      命及愷他命陽性反應，亦有詮昕科技股份有限公司濫用藥\n      物尿液檢驗報告2 份在卷可按，而證人曹家榮則於99年2\n      月4 日及同年月7 日分別因施用海洛因、甲基安非他命案\n      件，經本院分別判處有期徒刑8 月、3 月，定應執行有期\n      徒刑10月，亦有本院99年度訴字第1401號判決1 份附卷可\n      參。足認證人李明修、曾書賢均有施用愷他命之慣習，證\n      人曹家榮亦有施用海洛因、甲基安非他命之慣習，對外有\n      購毒之需求。\n    (四)又被告於99年2 月5 日22時30分許，另案為警在臺中市○\n      ○路○ 段與崇德十路口拘提到案，並扣得其所有之海洛因\n      7 小包（合計淨重2.44公克，驗餘合計淨重2.35公克，包\n      裝袋總重2.32公克，外包裝因與海洛因相結合無從析離而\n      應視為第一級毒品）、甲基安非他命20包（驗前總毛重17\n      .32 公克，包裝袋總重4.80公克，驗前總純質淨重10.89\n      公克，鑑驗用罄0.11公克，外包裝因與甲基安非他命相結\n      合無從析離而應視為第二級毒品）、其所有供上揭販賣第\n      一級、第二級、第三級毒品及轉讓第一級毒品所用如附表\n      三編號3 、4 所示之行動電話、電子秤1 臺、其所有預備\n      供上揭各次販賣第一級、第二級及第三級毒品及轉讓第一\n      級毒品所用之分裝夾鍊袋2 包，亦經臺中高分院99上訴字\n      第1604號判決認定屬實，有該判決附卷可參。可認被告確\n      有管道取得海洛因、甲基安非他命以供販賣、轉讓，並有\n      販賣及轉讓之工具。\n    (五)又被告供稱：伊販賣海洛因、甲基安非他命及愷他命，可\n      以從中賺到自己施用的部分，400 元之愷他命約可賺取0.\n      7 至0.8 公克之愷他命供己施用等語（見審卷一第112 、\n      138 頁），足認被告販賣海洛因、甲基安非他命及愷他命\n      ，主觀上有營利之意圖無訛。\n    (六)從而，被告之自白與相關證據均相符合，堪以採信，被告\n      各次販賣海洛因、甲基安非他命、愷他命及轉讓海洛因之\n      犯行，均堪認定，應依法論科。\n、論罪科刑之理由：\n  一核被告所為，犯罪事實一二三八部分，均係犯毒品危害防制\n    條例第4 條第3 項之販賣第三級毒品罪；犯罪事實四六部分\n    ，均係犯毒品危害防制條例第4 條第1 項之販賣第一級毒品\n    罪；犯罪事實五九十部分，係犯毒品危害防制條例第4 條第\n    2 項之販賣第二級毒品罪；犯罪事實七部分，則係犯同條例\n    第8條第1項轉讓第一級毒品罪。\n  二被告各該持有海洛因、甲基安非他命之低度行為，分別為販\n    賣、轉讓之高度行為所吸收，均不另論罪。又持有第三級毒\n    品愷他命之行為，毒品危害防制條例第11條第5 項規定：「\n    持有第三級毒品純質淨重20公克以上者，處3 年以下有期徒\n    刑，得併科新臺幣30萬元以下罰金。」然被告各次販賣愷他\n    命實際持有愷他命之重量不明，且未扣案無從鑑定愷他命之\n    純質淨重是否為20公克以上。準此，依無罪推定原則，被告\n    上開販賣前持有第三級毒品愷他命之行為不成立犯罪，而無\n    「吸收」之問題。至被告轉讓海洛因部分，亦無證據證明轉\n    讓之重量超過淨重5 公克，自不得依同條例第8 條第6 項予\n    以加重，附此敘明。\n  三被告所犯上開10罪，均犯意各別，行為各自獨立，應分論併\n    罰之。\n  四按98年5 月20日修正公布之毒品危害防制條例第17條第2 項\n    關於「犯第4 條至第8 條之罪於偵查及審判中均自白者，減\n    輕其刑。」之規定，旨在獎勵犯罪人之悛悔，同時使偵查或\n    審判機關易於發現真實，以利毒品查緝，俾收防制毒品危害\n    之效；故不論該被告之自白，係出於自動或被動、簡單或詳\n    細、一次或多次，並其自白後有無翻異，苟其於偵查及審判\n    中均有自白，即應依法減輕其刑。又刑法上所稱之自白，係\n    指行為人對其被訴之犯罪事實為任意性之供認而言（最高法\n    院98年度臺上字第6928號判決）。本件被告於檢察官偵訊時\n    及本院審理時均已自白其上揭販賣第一級、第二級、第三級\n    毒品及轉讓第一級毒品等犯行，業如上述，爰依毒品危害防\n    制條例第17條第2 項規定就上揭各罪均減輕其刑。\n  五又98年5 月20日修正公布之毒品危害防制條例第17條第1 項\n    規定：「犯第4 條至第8 條、第10條或第11條之罪，供出毒\n    品來源，因而查獲其他正犯或共犯者，減輕或免除其刑」。\n    被告吳茂毅於另案販賣毒品案件經檢察官偵訊時，供稱：伊\n    向一位綽號「小陳」（嗣經查為陳文仕）之人買毒品的，其\n    電話為0000000000；伊約今年（即99年）1 月中或1 月底，\n    交易地點好像在苗栗交流道，該次伊向綽號「小陳」拿了約\n    半兩多（約16、17公克）的安非他命，4 點多公克的海洛因\n    ，小陳跟伊說把毒品賣掉後，再將錢交給小陳，小陳說安非\n    他命要21,000元，海洛因要22,000元，但尚未給小陳錢；小\n    陳除0923的電話外，還有一支0000000000的電話等語（見審\n    卷一第65、66頁）。檢察官隨即依被告之供述而簽分偵辦小\n    陳販賣毒品案件，嗣確有查獲綽號「小陳」之陳文仕販賣海\n    洛因、甲基安非他命與被告之犯行，而予偵查起訴在案，亦\n    有臺灣臺中地方法院檢察署99年10月7 日中檢輝姜99偵4796\n    字第133021號函及該署99年度偵字第12459 、15267 號起訴\n    書可稽（見審卷一第67頁、第54至56頁）。是可認被告自99\n    年1 月起始向陳文仕購買海洛因、甲基安非他命，被告就犯\n    罪事實四至七九十之犯行供出毒品來源，因而查獲其他正犯\n    ，而就此部分販賣第一級毒品、第二級毒品及轉讓第一級毒\n    品犯行，各依毒品危害防制條例第17條第1 項遞減輕其刑。\n    至被告於警詢、偵訊時雖另供稱其係向葉文仁購買愷他命，\n    惟另案被告葉文仁並非因被告之供述而查獲其販賣愷他命之\n    犯行，亦有臺灣臺中地方法院檢察署中檢輝敦100 他3168字\n    第101475號函文、內政部警政署保安警察隊第三總隊第一大\n    隊100 年7 月6 日保三壹警刑字第1000003994號函文暨函附\n    之職務報告及葉文仁之臺灣高等法院被告前案紀錄表各1 份\n    在卷可按，是被告販賣第三級毒品之犯行，自無從適用毒品\n    危害防制條例第17條第1 項減刑規定之寬典，附此敘明。\n  六刑法第59條規定之適用：\n    (一)再按刑法第59條之減輕其刑，係裁判上之減輕，必以犯罪\n      之情狀可憫恕，認為宣告法定最低度之刑猶嫌過重者，始\n      有其適用；如別有法定減輕之事由，應先依法定減輕事由\n      減輕其刑後，猶嫌過重時，始得為之；若有2 種以上法定\n      減輕事由，仍應先依法定減輕事由遞減其刑後，猶嫌過重\n      時，始得再依刑法第59條規定酌減其刑，最高法院88年度\n      臺上字第1862號判決意旨可資參照。復按刑之量定，為求\n      個案裁判之妥當性，法律固賦予法院裁量權，但此項裁量\n      權之行使，除應依刑法第57條規定，審酌行為人及其行為\n      等一切情狀，為整體之評價，並應顧及比例原則與平等原\n      則，使罪刑均衡，輕重得宜，以契合社會之法律感情。販\n      賣第一級毒品罪之法定刑為「死刑或無期徒刑；處無期徒\n      刑者，得併科新臺幣20,000,000元以下罰金」。其法定刑\n      既為死刑、無期徒刑，別無其他自由刑之規定，刑度可謂\n      重大。然同為販賣第一級毒品之人，其原因動機不一，犯\n      罪情節未必盡同，或有大盤毒梟者，亦有中、小盤之分，\n      甚或僅止於吸毒者友儕間為求互通有無而為販賣者亦有之\n      ，其販賣行為所造成危害社會之程度自屬有異，法律科處\n      此類犯罪，所設之法定最低本刑卻同為死刑或無期徒刑，\n      且處無期徒刑者，得併科新臺幣20,000,000元以下之罰金\n      ，不可謂不重。於此情形，倘依其情狀處以有期徒刑，即\n      足以懲儆，並可達防衛社會之目的者，自非不可依客觀之\n      犯行與主觀之惡性二者加以考量其情狀是否有可憫恕之處\n      ，適用刑法第59條之規定酌量減輕其刑，期使個案裁判之\n      量刑，能斟酌至當，符合比例原則。又適用刑法第59條酌\n      量減輕其刑時，並不排除同法第57條所列舉10款事由之審\n      酌（最高法院70年5 月16日70年度第6 次刑事庭長會議決\n      議足供參考）。\n    (二)依上開說明意旨，本院認為被告所為犯罪事實四六所示之\n      販賣海洛因犯行，固戕害國民健康，助長施用毒品惡習，\n      其行為實屬不該，惟被告各次販賣海洛因之所得僅500 元\n      、3,000 元，均係小額交易，屬毒品交易之下游，販賣毒\n      品之對象曹家榮原即有施用毒品之慣習，有其臺灣高等法\n      院被告前案紀錄表1 份在卷可按，被告之惡性情節較諸大\n      量走私進口或長期販賣毒品之「大盤」、「中盤」毒販有\n      差異，其對社會整體侵害之程度尚非鉅大，被告亦染有施\n      用之惡習，業據被告供承在卷，被告係為圖自己得以施用\n      毒品，始鋌而走險販賣海洛因，惟被告就所犯之販賣第一\n      級毒品罪，其最輕法定本刑為無期徒刑，縱使被告所犯販\n      賣第一級毒品罪經依毒品危害防制條例第17條第2 項規定\n      減輕其刑，及依同條第1 項規定遞減輕其刑後，均量處法\n      定最低刑度之刑，仍嫌過重，而依被告客觀之犯行與主觀\n      之惡性二者加以考量其犯罪情狀，爰依刑法第59條之規定\n      ，就被告所犯上開販賣第一級毒品罪部分各酌量減輕其刑\n      ，並均遞減輕其刑。\n  七又「數罪併罰，分別宣告其罪之刑，依下列各款定其應執行\n    者：五宣告多數有期徒刑者，於各刑中之最長期以上，各刑\n    合併之刑期以下，定其刑期。但不得逾30年。」刑法第51條\n    第5 款定有明文。又法律上屬於自由裁量事項，尚非概無法\n    律性之拘束，在法律上有其外部界限及內部界限。前者法律\n    之具體規定，使法院得以具體選擇為適當裁判，此為自由裁\n    量之外部界限。後者法院為自由裁量時，應考量法律之目的\n    ，法律秩序之理念所在，此為自由裁量之內部界限。法院為\n    裁判時，二者均不得有所踰越。在數罪併罰應定其應執行刑\n    之案件，法院所為刑之酌定，固屬自由裁量事項，然對於法\n    律之內、外部界限，仍均應受其拘束。最高法院94年度臺非\n    字第21號判決要旨足供本案定刑之參考。從而，數罪併罰在\n    定其應執行之刑之際，自應再為應執行之刑的決定，亦屬一\n    種特別的量刑過程，其考量結果，並非單純表示一種數罪刑\n    度的總和而已，而是再次對於同一行為人責任的檢視。相較\n    刑法第57條定有科刑時應審酌的事項，此項規定係對一般犯\n    罪行為之裁量而言。而合併刑之宣告，則屬一種對犯罪人本\n    身及所犯之各種犯罪的綜合判斷。申言之，定執行之刑的宣\n    告，並非在法定範圍之內自由裁定，應注意行為人從其犯數\n    罪所反映的人格特性，及考量刑法目的相關刑事政策，妥為\n    宣告。而刑法的功能中，除一般預防及特別預防之外，更重\n    要的是，行為人再社會化及具體的社會保護作用，否則加諸\n    過度之刑罰於被告，徒僅造成責任報應，去實現一個未知、\n    抽象的正義。因此，是否為被告長期性監禁宣告的同時，應\n    一併考量被告犯案情節對社會之衝擊，並注意此舉是否造成\n    被告更生絕望的心理影響，使得被告的人格遭受完全性地抹\n    滅。換言之，必須考量刑罰手段的相當性，儘量選擇能使受\n    刑人復歸社會生活之刑罰方法。法官無法以所謂「治亂世用\n    重典」之理由，加重刑罰以圖遏止歪風，不能過度強調所謂\n    一般預防的刑罰目的。實則，就人性尊嚴及人權的思想而言\n    ，任何一個人均非他人的工具，以加重被告的刑罰作為達到\n    阻嚇其他人犯罪的手段，被告已淪為教化社會大眾的工具，\n    喪失了作為一個人主體性，這均與我國刑事政策之立法有違\n    。凡此即構成最高法院所揭示「內部界限」之意義。\n  八本院審酌前揭情狀（包括前述酌減之事由），並參酌被告有\n    違反毒品危害防制條例前科，有前開臺灣高等法院被告前案\n    紀錄表可參，被告之素行難認良善。被告明知海洛因、甲基\n    安非他命、愷他命係屬戕害人身心之毒品，竟為貪圖不法利\n    益，鋌而走險販賣供他人施用，另基於朋友情誼，無償提供\n    海洛因與曹家榮施用，擴大毒害，無視上開毒品足以使施用\n    者導致精神障礙、性格異常，甚至造成生命危險之生理成癮\n    性及心理依賴性，嚴重影響社會治安、戕害國民身心健康，\n    並考量被告各自販賣毒品之次數、販賣之所得非鉅、轉讓海\n    洛因之數量、次數，犯罪之動機、方法、手段，販賣毒品之\n    數量及對象，及犯後之態度等一切情狀，分別量處如主文所\n    示之刑。又被告現年27歲，若本院定以過重之應執行刑，其\n    效用可能隨著長期刑之執行，等比例地大幅下跌，效用甚低\n    ，對被告教化效果亦不佳，尚且加重國家財政無益負擔，亦\n    有害被告回歸社會，爰定其應執行之刑如主文所示，以期兼\n    顧對於被告之警示及更生。公訴檢察官雖請求量處被告有期\n    徒刑15年，然公訴檢察官未慮及被告販賣第一級毒品部分，\n    情輕法重，有毒品危害防制條例第17條第1 項、第2 項規定\n    之適用，並應依刑法第59條予以酌減，販賣第二級毒品部分\n    ，亦有毒品危害防制條例第17條第1 項、第2 項規定之適用\n    ，是公訴檢察官前開求刑實屬過重，尚有未洽。\n  九沒收部分：\n    (一)按以營利為目的販入毒品，經多次販賣後，持有剩餘毒品\n      被查獲，其各次販賣毒品行為，固應併合處罰。惟該持有\n      剩餘毒品之低度行為，應僅為最後一次販賣毒品之高度行\n      為所吸收，不另論罪。故就該查獲之剩餘毒品，祇能於最\n      後一次之販賣毒品罪宣告沒收銷燬，不得於各次販賣毒品\n      罪均宣告沒收銷燬；又應沒收銷燬之物執行完畢與不存在\n      ，係屬二事，本案中因犯罪依法必須沒收銷燬之物，縱已\n      於其他相關案件確定判決中諭知沒收銷燬並執行完畢，亦\n      不得認已滅失而不存在，且因該他案判決之認定僅具個案\n      拘束之效力，是於本案依法仍屬應宣告沒收銷燬之物，自\n      不得以該物因其他相關之判決已諭知沒收銷燬確定，並經\n      執行完畢為由，而不為沒收之諭知，最高法院98年度臺上\n      字第738 號、98年度臺上字第4258號判決要旨參照。是以\n      ：\n      1.本案被告吳茂毅所犯多次販賣第一級毒品及轉讓第一級\n        毒品罪，其最後一次轉讓第一級毒品之時間為99年1 月\n        31日，而被告另案於99年2 月5 日22時30分許，為警在\n        臺中市○○路○ 段與崇德十路口，扣得被告所有供販賣\n        所用之第一級毒品海洛因7 小包（合計淨重2.44公克，\n        驗餘合計淨重2.35公克，包裝袋總重2.32公克，外包裝\n        因與第一級毒品海洛因相結合無從析離而應視為第1級\n        毒品，行政院衛生署草屯療養院98年4 月21日草療鑑字\n        第0980002432號函、法務部調查局93年3 月19日調科壹\n        字第09300113060 號函、最高法院95年度臺上字第3934\n        號判決參照），係被告吳茂毅經多次販賣第一級毒品及\n        轉讓第一級毒品後，持有剩餘第一級毒品被查獲，縱經\n        臺中高分院以99年度上訴字第1604號判決宣告沒收銷燬\n        ，經最高法院駁回上訴後確定，惟該他案判決之認定僅\n        具個案拘束之效力，於本案依法仍屬應宣告沒收銷燬之\n        物，仍應依法宣告沒收銷燬之。故就前揭所查獲之剩餘\n        毒品，應於被告最後1 次之轉讓海洛因罪宣告沒收銷燬\n        ，不得於各次販賣毒品罪均宣告沒收銷燬，亦即前揭扣\n        案之海洛因自應於附表一編號７所示之主刑之後，依毒\n        品危害防制條例第18條第1 項前段宣告沒收銷燬之（最\n        高法院98年度臺上字第3060號判決意旨參照）。至因鑑\n        驗所耗損之第一級毒品海洛因部分，既已滅失，即不另\n        為沒收之諭知。\n      2.本案被告亦有犯多次販賣第二級毒品罪，其最後1 次販\n        賣第二級毒品之時間為99年2 月5 日，而被告另案於99\n        年2 月5 日22時30分許，為警在臺中市○○路○ 段與崇\n        德十路口，扣得之第二級毒品甲基安非他命20包（驗前\n        總毛重17.32 公克，包裝袋總重4.80公克，驗前總純質\n        淨重10.89 公克，鑑驗用罄0.11公克，外包裝因與第2\n        級毒品甲基安非他命相結合無從析離而應視為第二級毒\n        品，理由同上揭行政院衛生署草屯療養院函釋），係被\n        告經多次販賣第二級毒品後，持有剩餘第二級毒品被查\n        獲，縱經臺中高分院以99年度上訴字第1604號判決宣告\n        沒收銷燬，依前揭說明，仍應於本案諭知沒收銷燬之。\n        故就前揭所查獲之剩餘毒品，應於被告最後1 次之販賣\n        第二級毒品罪中宣告沒收銷燬，不得於各次販賣毒品罪\n        均宣告沒收銷燬，亦即前揭扣案之甲基安非他命自應於\n        附表一編號１０所示之主刑之後，依毒品危害防制條例第\n        18條第1 項前段宣告沒收銷燬之（最高法院98年度臺上\n        字第3060號判決意旨參照）。至因鑑驗所耗損之第二級\n        毒品甲基安非他命部分，既已滅失，即不另為沒收之諭\n        知。\n    (二)毒品危害防制條例第19條第1項規定，犯販賣毒品罪者，\n      其犯罪所得之財物均沒收之，係採義務沒收主義。故販賣\n      毒品所得之對價，不問其中成本若干，利潤多少，均應全\n      部諭知沒收，貫徹政府查禁煙毒之決心，以符立法本旨（\n      最高法院91年度臺上字第2419號判決意旨參照）。再按毒\n      品危害防制條例第19條第1 項，係刑法第38條第1 項第2\n      款之特別規定，採義務沒收主義，苟能證明係供犯罪所用\n      或因犯罪所得之財物，均應沒收之，如全部或一部不能沒\n      收時，追徵其價額或以其財產抵償之，並不以當場搜獲扣\n      押者為限（最高法院88年度臺上字2039號判決要旨參照）\n      。又毒品危害防制條例第19條第1項 規定性質上係沒收之\n      補充規定。其屬於本條所定沒收之標的，如得以直接沒收\n      者，判決主文僅宣告沒收即可，不生「追徵其價額」或「\n      以其財產抵償之」問題，須沒收之標的全部或一部不能沒\n      收時，始生「追徵其價額」或「以其財產抵償之」選項問\n      題。而「追徵其價額」或「以其財產抵償之」係屬兩種選\n      項，分別係針對現行貨幣以外之其他財產與現行貨幣而言\n      ，最高法院99年度第5 次刑事庭會議亦可供參酌。則販賣\n      毒品所得之金錢或所用之物，無論已否扣案，均應依法沒\n      收。從而：\n      1.被告各次販賣海洛因所得（詳如犯罪事實四六所載）、\n        各次販賣甲基安非他命所得（詳如犯罪事實五九十所載\n        ），及各次販賣愷他命所得（詳如犯罪事實一至三八所\n        載）均未扣案，應分別依毒品危害防制條例第19條第1\n        項宣告沒收之，並各在附表一編號１至６、８至１０所示\n        其所犯販賣第一級、第二級及第三級毒品罪項下，就各\n        次販賣毒品所得宣告沒收，如全部或一部不能沒收時，\n        以其財產抵償之。\n      2.另案扣案之Sony Ericsson 廠牌行動電話1 支（含門號\n        0000000000號晶片卡1 張）、GPLUS 廠牌行動電話1 支\n        （含門號0000000000號晶片卡1 張）分別為被告所有，\n        供其犯犯罪事實一至三之販賣第三級毒品罪（被告持用\n        Sony Ericsson 廠牌行動電話），及犯罪事實四至八十\n        所示販賣第一級、第二級與第三級毒品及轉讓第一級毒\n        品罪所用之物（被告持用GPLUS 廠牌行動電話），扣案\n        之電子秤1 臺，亦係被告所有供其犯犯罪事實一至十所\n        示之販賣第一級、第二級、第三級毒品罪及轉讓第一級\n        毒品所用之物，業據被告於本院審理時供承在卷（見審\n        卷一第110 、134 、135 、138 頁），上開扣案物除GP\n        LUS 廠牌行動電話（含門號0000000000號晶片卡1 張）\n        外，雖均經臺中高分院另案宣告沒收確定，然於本案依\n        法屬應宣告沒收之物，仍應毒品危害防制條例第19條第\n        1 項之規定，在各該附表一所示之各次犯行之主刑項下\n        分別予以諭知沒收之。\n      3.另案扣案之分裝夾鍊袋2 包，亦係被告所有，且供其犯\n        上揭各次販賣第一級、第二級、第三級毒品及轉讓第一\n        級毒品罪預備之物，業據被告於本院審理供承在卷（見\n        同上頁），雖亦經臺中高分院另案宣告沒收確定，依前\n        開說明，仍應依刑法第38條第1 項第2 款規定，在上揭\n        各罪主刑項下宣告沒收。\n肆、適用之法律：\n    依刑事訴訟法第299 條第1 項前段，毒品危害防制條例第4\n    條第1 項、第2 項、第3 項、第8 條第1 項、第17條第1 項\n    、第2 項、第18條第1 項前段、第19條第1 項，刑法第11條\n    、第59條、第51條第5 款、第9 款、第38條第1 項第2 款，\n    判決如主文。\n本案經檢察官黃勝裕到庭執行職務。"
  },
  "search": "臺灣臺中地方法院刑事判決100年度訴字第1678號100年度訴字第2712號公訴人臺灣臺中地方法院檢察署檢察官被告吳茂毅指定辯護人本院公設辯護人戴遐齡上列被告因毒品危害防制條例案件，經檢察官提起公訴（99年度偵字第13990號、第14634號）暨追加起訴（100年度偵續字第214號），本院判決如下：主文吳茂毅犯如附表一所示之罪，各處如附表一所示之刑（含主刑、從刑）。應執行有期徒刑柒年拾月，沒收部分併執行之。事實及理由壹、犯罪事實：吳茂毅（綽號「貓啊」、「喵仔」、「貓咪」）明知海洛因、甲基安非他命及愷他命分別係毒品危害防制條例第2條第2項第1款、第2款及第3款所管制之第一級、第二級及第三級毒品，不得販賣、轉讓、持有（持有第三級毒品部分純質淨重20公克以上者亦不得持有），竟分別基於意圖營利販賣第一級、第二級及第三級毒品以牟利，及轉讓第一級毒品之犯意，為下列犯行：一曾書賢於民國98年5、6月間某日，以門號0000000000號行動電話撥打電話予吳茂毅所有如附表三編號3所示之行動電話，表示欲購買新臺幣（下同）400元之愷他命，吳茂毅應允後，至臺中市○○區○○路上之文雅國小（下稱文雅國小）附近，將數量不詳之愷他命1包（無證據證明超過純質淨重20公克）販賣予曾書賢1次，惟因曾書賢未攜帶金錢，而暫時賒欠款項。二曾書賢於98年6月底某日，以門號0000000000號行動電話撥打電話予吳茂毅之上開行動電話，表示欲購買400元之愷他命，雙方約定交易之時間、地點後，吳茂毅即前往文雅國小附近，將數量不詳之愷他命1包（無證據證明超過純質淨重20公克）交與曾書賢，惟曾書賢仍未攜帶金錢，故暫時賒欠款項。三曾書賢於98年7月中旬某日，再以門號0000000000號行動電話撥打電話予吳茂毅之上開行動電話，表示購買愷他命之意願，雙方議妥交易金額後，吳茂毅前往約定地點即文雅國小附近，將數量不詳之愷他命1包（無證據證明超過純質淨重20公克）販賣予曾書賢1次，然因曾書賢未攜帶金錢，而暫時賒欠買賣價金400元。嗣於99年1月30日，吳茂毅持用其所有如附表三編號4所示之行動電話撥打曾書賢持用之門號0000000000號行動電話，向曾書賢催討積欠之款項，曾書賢始於不詳時間，在臺中市大雅區某國小附近，將3次購毒款項交與吳茂毅。四曹家榮於99年1月29日19時37分27秒、19時52分55秒、19時56分17秒許，持用之行動電話門號0000000000號撥打吳茂毅所有附表三編號4所示之行動電話與之聯繫，雙方於電話中，以「酒」代表海洛因，「停車場」代表交易地點即吳茂毅位於臺中市○○區○○里○○街192巷21號之住處附近停車場，約定購買海洛因之事宜。待雙方於電話中完成約定交易毒品之事宜後，吳茂毅即於當日通話完畢後之某時，在其住處附近之停車場，以500元之代價，販賣海洛因1小包與曹家榮，一手交錢、一手交貨，而完成交易。五鄒聖緯於99年1月29日22時56分12秒、23時0分21秒許所持用之行動電話門號0000000000號行動電話撥打附表三編號4所示之行動電話與吳茂毅聯繫後，雙方於電話中，以「3罐」代表甲基安非他命，「臺新銀行」代表交易地點即臺中市○○區○○路上之臺新銀行，雙方議妥交易甲基安非他命事宜，吳茂毅即於當日通話完畢後之某時，至臺中市○○區○○路上之臺新銀行前面，將甲基安非他命3小包交予鄒聖緯，並向鄒聖緯收取現金1,500元。六徐嘉偉持用之行動電話門號0000000000號，於99年1月30日15時40分57秒、18時0分1秒、18時24分47秒許，以行動電話門號0000000000號撥打附表三編號4所示之行動電話與吳茂毅聯繫，雙方於電話中，以「同款」代表海洛因，「3500」及「3000」各代表價值3,500元及3,000元之海洛因，雙方於電話中完成約定交易毒品之事宜，吳茂毅即於當日通話完畢後之某時，在臺中市○○區○○路上之某停車場，以3,000元之代價，販賣海洛因1小包與徐嘉偉，並當場向徐嘉偉收取現金3,000元，完成交易。七吳茂毅於99年1月31日16時23分34秒許，以附表三編號4所示之行動電話與曹家榮所持用之行動電話門號0000000000號聯繫，曹家榮表示毒癮發作，請求吳茂毅無償轉讓些許海洛因與其止癮，吳茂毅同意後，於同日晚間19時24分前之某時，至曹家榮位在臺中市○○區○○路4號之住處前，無償轉讓海洛因1小包（無證據證明超過淨重5公克）予曹家榮。曹家榮施用完畢後，於當日19時24分17秒，以上開行動電話傳遞簡訊：「品質不錯、保持下去、期待明天、保持聯絡、新年快樂。」等語予吳茂毅。八李明修持用之行動電話門號0000000000號於99年2月4日凌晨0時42分46秒許，撥打附表三編號4所示之行動電話與吳茂毅聯繫，雙方於電話中，以「啤酒」代表愷他命，以「1箱啤酒」、「半箱」及「4分之1」各代表30公克、15公克及5公克之愷他命，約定交易愷他命事宜。吳茂毅於當日通話完畢後之某時，至臺中市○○區○道1號高速公路豐原交流道下，以2,000元之代價，販賣約5公克之愷他命1小包予李明修，一手交錢、一手交貨，而完成交易。九吳茂毅於99年2月4日23時2分前之某時，在不詳之地點，以500元之代價，販賣甲基安非他命予曹家榮，銀貨兩訖。嗣因吳茂毅所販賣之甲基安非他命品質不佳，包裝袋又有破洞，曹家榮遂於當日晚間2月4日23時2分23秒，以行動電話門號0000000000號傳遞簡訊：「怎麼酒又不夠，這樣下去很難交陪，杯子還破洞，注意點，別再出問題了。」等語，至吳茂毅所持用附表三編號4所示之行動電話，抱怨此事。十鄒聖緯所持用行動電話門號0000000000號，於99年2月5日18時55分6秒、18時56分38秒許，撥打附表三編號4所示之行動電話與吳茂毅聯繫後，雙方於電話中，以「葡萄酒」代表甲基安非他命，「上夢全家（臺語）」、「大楓全家（臺語）」代表交易地點即吳茂毅位在臺中市大雅區上楓里住處巷口之全家便利商店，雙方議妥交易甲基安非他命事宜，吳茂毅即於當日通話完畢後之某時，在其住處巷口之全家便利商店前，將甲基安非他命1小包交予鄒聖緯，並向鄒聖緯收取現金500元。嗣經警對吳茂毅持用之門號0000000000號行動電話實施通訊監察，並於99年2月5日22時30分許，另案為警在臺中市○○路○段與崇德十路口拘提到案，並扣得吳茂毅所有之海洛因7小包（合計淨重2.44公克，驗餘合計淨重2.35公克，包裝袋總重2.32公克，外包裝因與海洛因相結合無從析離而應視為第一級毒品）、甲基安非他命20包（驗前總毛重17.32公克，包裝袋總重4.80公克，驗前總純質淨重10.89公克，鑑驗用罄0.11公克，外包裝因與甲基安非他命相結合無從析離而應視為第二級毒品）、吳茂毅所有供上揭販賣第一級、第二級、第三級毒品及轉讓第一級毒品所用之GPLUS廠牌行動電話1支（含門號0000000000號晶片卡1張）、SonyErisson廠牌行動電話1支（含門號0000000000號晶片卡1張）、電子秤1臺、吳茂毅所有預備供上揭各次販賣第一級、第二級、第三級毒品及轉讓第一級毒品所用之分裝夾鍊袋2包，而查獲上情。貳、認定犯罪事實所憑證據及理由：一程序部分：(一)按於第一審辯論終結前，得就與本案相牽連之犯罪或本罪之誣告罪，追加起訴；追加起訴，得於審判期日以言詞為之，刑事訴訟法第265條定有明文。又一人犯數罪者，為相牽連之案件，刑事訴訟法第7條第1款亦有明文。本件檢察官原起訴被告吳茂毅販賣海洛因與曹家榮、徐嘉偉，販賣甲基安非他命與鄒聖緯、曹家榮，販賣愷他命與李明修，及轉讓海洛因與曹家榮，嗣於100年9月29日以追加起訴書，追加起訴被告於98年5、6月間某日、同年6月底某日及同年7月間某日分別販賣愷他命與曾書賢之犯罪事實，上開追加之販賣第三級毒品罪與本案原起訴被告之各罪間，有一人犯數罪之相牽連關係，依上開法條規定，檢察官於言詞辯論終結前追加起訴，當屬合法，法院自應就追加起訴部分予以審判。(二)證據能力部分：1.按被告以外之人於偵查中向檢察官所為之陳述，除顯有不可信之情況者外，得為證據，刑事訴訟法第159條之1第2項定有明文。偵查中對被告以外之人（包括證人、鑑定人、告訴人、被害人及共同被告等）所為之偵查筆錄，或被告以外之人向檢察官所提之書面陳述，性質上均屬傳聞證據。惟現階段刑事訴訟法規定檢察官代表國家偵查犯罪、實施公訴，依法其有訊問被告、證人及鑑定人之權，證人、鑑定人且須具結，而實務運作時，檢察官偵查中向被告以外之人所取得之陳述，原則上均能遵守法律規定，不致違法取供，其可信度極高，職是，被告以外之人前於偵查中已具結而為證述，除反對該項供述得具有證據能力之一方，已釋明「顯有不可信之情況」之理由外，不宜以該證人未能於審判中接受他造之反對詰問，即遽指該證人於偵查中之陳述不具證據能力。查本件證人曹家榮、曾書賢、徐嘉偉、李明修及鄒聖緯於偵查中所為之陳述，雖屬傳聞證據，然其等於偵查中所為證言，均經具結，而被告吳茂毅及其辯護人均未釋明上開證人之陳述有何「顯不可信之情況」，且於客觀之外部情狀上，難認有何顯不可信之情狀，依上揭規定，應認證人曹家榮、曾書賢、徐嘉偉、李明修及鄒聖緯於偵查中所為之證述，得為證據。2.又偵查犯罪機關依法定程序監聽之錄音，係以監聽之錄音帶為其調查犯罪所得之證據，司法警察依據監聽錄音結果予以翻譯而製作之通訊監察譯文，乃該監聽錄音帶內容之顯示，此為學理上所稱之「派生證據」，屬於文書證據之一種。於被告或訴訟關係人對該譯文之真實性發生爭執或有所懷疑時，法院固應依刑事訴訟法第165條之1第2項之規定，勘驗該監聽錄音帶以踐行調查證據之程序，俾確認該錄音之聲音是否為通訊者本人及其內容與通訊監察譯文之記載是否相符，或傳喚該通訊者為證據調查。倘被告或訴訟關係人對該通訊監察譯文之真實性並不爭執，即無勘驗辨認其錄音之聲音予以調查之必要，法院於審判期日如已踐行提示通訊監察譯文供當事人辨認或告以要旨，使其表示意見等程序並為辯論者，其所為之訴訟程序即無不合（最高法院97年度臺上字第561號判決意旨可資參照）。再按有事實足認被告或犯罪嫌疑人有最輕本刑為3年以上有期徒刑之罪嫌，並危害國家安全或社會秩序情節重大，而有相當理由可信其通訊內容與本案有關，且不能或難以其他方法蒐集或調查證據者，得發通訊監察書。前項通訊監察書，偵查中由檢察官依司法警察機關聲請或依職權以書面記載第11條之事項，並敘明理由、檢附相關文件，聲請該管法院核發。通訊保障及監察法第5條第1項第1款、第2項定有明文。本案所引用有關行動電話號碼0000000000號之監聽錄音，係經本院法官核准在案，有詳載案由、監察電話、對象及時間等之99年度聲監字第163號通訊監察書、電話附表等附卷可參〔見臺灣臺中地方法院檢察署99年度偵字第13990號卷（下稱偵卷一）第36、37頁〕，係依法所為之監聽；況審酌電話監聽侵害被告權益之種類及輕重、對於被告訴訟上防禦不利益之程度、犯罪所生之危害或實害等情形，兼顧人權保障及公共利益之均衡維護，亦認此部分電話監聽合於比例原則，是認應具有證據能力。且下列經本院所引用認定之通訊監察譯文，被告及辯護人對該通訊監察譯文之真實性並不爭執，復經本院於審判期日踐行提示通訊監聽譯文供當事人、指定辯護人辨認並告以要旨，使其等表示意見，是該通訊監察譯文自亦有證據能力。3.現行刑事訴訟法關於「鑑定」之規定，除選任自然人充當鑑定人外，另設有囑託機關鑑定制度。依同法第198條、第208條之規定，不論鑑定人或鑑定機關、團體，固均應由法院、審判長、受命法官或檢察官視具體個案之需要而為選任、囑託，並依第206條之規定，提出言詞或書面報告，始符合同法第159條第1項所定得作為證據之「法律有規定」之情形。否則所為之鑑定，仍屬傳聞證據。然於司法警察機關調查中之案件，為因應實務上，或因量大，或有急迫之現實需求，例行性當然有鑑定之必要者，例如毒品之種類與成分、尿液之毒品反應，或者槍彈有無殺傷力等鑑定，基於檢察一體原則，得由該管檢察長對於轄區內之案件，以事前概括選任鑑定人或囑託鑑定機關、團體之方式，俾便轄區內之司法警察官、司法警察對於調查中之此類案件，得即時送請先前已選任之鑑定人或囑託之鑑定機關、團體實施鑑定，以求時效（法務部92年9月1日法檢字第0920035083號函參照）。此種由檢察機關概括選任鑑定人或概括囑託鑑定機關、團體，再轉知司法警察官、司法警察於調查犯罪時參考辦理之作為，法無明文禁止，係為因應現行刑事訴訟法增訂傳聞法則及其例外規定之實務運作而為。其所為之鑑定結果，與檢察官選任或囑託為鑑定者，性質上並無差異，同具有證據能力（最高法院96年度臺上字第2860號判決要旨參照）。卷附之詮昕科技股份有限公司濫用藥物尿液檢驗報告各3份〔見臺灣雲林地方法院檢察署99年度偵字第14634偵查卷（下稱偵卷二）第130至132頁〕，均為臺中縣警察局清水分局（現改制為臺中市政府警察局清水分局）送請鑑定，揆諸前揭說明，屬「法律規定」得為證據者，應有證據能力。4.再按被告以外之人於審判外之陳述，雖不符刑事訴訟法第159條之1至第159條之4之規定，而經當事人於審判程序同意作為證據，法院審酌該言詞陳述或書面陳述作成時之情況，認為適當者，亦得為證據。當事人、代理人或辯護人於法院調查證據時，知有第159條第1項不得為證據之情形，而未於言詞辯論終結前聲明異議者，視為有前項之同意，刑事訴訟法第159條之5定有明文。核其立法意旨在於傳聞證據未經當事人之反對詰問予以核實，原則上先予排除。惟若當事人已放棄反對詰問權，於審判程序中表明同意該等傳聞證據可作為證據；或於言詞辯論終結前未聲明異議，基於尊重當事人對傳聞證據之處分權，及證據資料愈豐富，愈有助於真實發見之理念，且強化言詞辯論主義，使訴訟程序得以順暢進行，上開傳聞證據亦均具有證據能力。查：本判決除上揭所述外，下列所引之被告以外之人於審判外所為之陳述及卷內其他書證（供述證據部分），查無符合同法第159條之1至之4等前4條之情形，檢察官、被告及其辯護人於本院準備程序中均表示對該等傳聞證據之證據能力均同意有證據能力〔見本院100年度訴字第1678號卷（下稱審卷一）第42頁〕，於本院審理時並未就卷內其他證據資料之證據能力有所爭執，且迄本院言詞辯論終結前，均未主張有刑事訴訟法第159條第1項不得為證據之情形，是應認已同意卷內證據均得作為證據，且經本院審酌上開傳聞證據作成時，較無人情施壓或干擾，亦無不當取證之情形，認為以之作為本案之證據亦屬適當，是上揭傳聞證據自具有證據能力。二得心證之理由：(一)訊據被告就上開犯罪事實，於警詢、偵訊及本院審理時均坦承不諱〔見偵卷一第12至20頁、第79、80頁、偵卷二第14至18頁、第166頁、第115頁、臺灣臺中地方法院檢察署100年度偵續字第214號卷（下稱偵卷三）第52頁〕，復經證人曾書賢、曹家榮、鄒聖緯、徐嘉偉及李明修於警詢（見偵卷一第38至43頁、偵卷二第25至31頁、第41至47頁）、檢察官偵訊時（見偵卷一第70至72頁、偵卷二第64、65、146、168、158、159頁、偵卷三第52頁）證述明確。證人曹家榮於警詢時雖陳稱99年2月4日購買甲基安非他命之金額為1,000元，證人鄒聖緯於警詢時則陳稱：99年1月29日此次「貓啊」有拿3包甲基安非他命與伊，以1包1,000元賣伊等語，證人李明修另證稱交易時間為99年2月5日或6日之晚上11、12時許，惟查：1.證人曹家榮於99年12月2日偵訊時具結證稱：99年2月4日該次交易是在發簡訊之前，地點伊記不清楚，不是在被告住處附近，就是在其工作之工廠前，只能確定向被告買了500元的甲基安非他命等語（見偵卷一第71頁）。被告於本院審理時亦供稱：99年2月4日曹家榮傳簡訊抱怨這次，伊販賣甲基安非他命之金額為500元，伊本來要賣1,000元，但曹家榮說錢不夠，伊就便宜賣其500元，賺取較少利潤等語（見審卷一第112頁）。故證人曹家榮就該次交易之金額於偵訊中之證述與被告於本院審理時之陳述相符，併基於罪疑惟輕之原則，應認定被告該次販賣甲基安非他命與曹家榮之金額應為500元。2.被告於100年4月28日偵訊時供陳：李明修應該記錯日期了，因伊於99年2月5日晚上9點多就被抓了，所以當天應該是講完電話沒多久就交易等語（見偵卷一第80頁）。而被告確於99年2月5日22時30分為警在臺中市○○路○段與崇德十路口拘提到案，並於同月6日遭羈押於法務部矯正署臺中看守所，有臺灣高等法院臺中分院99年度上訴字第1604號判決及臺灣高等法院被告前案紀錄表各1份在卷可按，核與被告前開供述相符，被告之前開供述堪以採信。被告與李明修之交易時間為99年2月4日當日通話後之某時，堪以認定。3.被告於99年6月9日警詢時供稱：伊以門號0000000000號行動電話於99年1月29日17時3分4秒與鄒聖緯持用之門號0000000000號行動電話聯繫，係鄒聖緯要向伊購買甲基安非他命，通訊監察譯文中「2罐」是代表1,000元之意思，伊於當日23時許在大雅區臺新銀行後面，拿甲基安非他命3小包給鄒聖緯，並向其收取1,500元等語（見偵卷二第17頁）。被告於100年4月28日偵訊時雖一度陳稱該次交易之金額為3,000元，然嗣後確認交易金額為1,500元。再觀諸附表二編號２被告與曹家榮之通訊監察譯文，曹家榮於電話中表示欲購買「一」，而該次交易金額為500元，業經證人曹家榮證述明確，堪認被告於警詢中供稱「2罐」是代表1,000元等語，應屬真實無訛。是鄒聖緯於99年1月29日22時56分12秒通話中表示要「3罐」，應係欲購買1,500元之甲基安非他命之意，被告與鄒聖緯該次之交易金額應為1,500元，亦堪認定。(二)另觀諸被告與曹家榮、曾書賢、徐嘉偉、李明修、鄒聖緯所示通話對象之通話內容（詳如附表二所示），多使用暗語如「酒」、「一」、「3罐」、「3500」、「3000」、「水」、「1箱」等作為代號，且通話內容簡短，多半係在談妥價格、數量或交易地點後，即結束通話，確屬實務上常見之毒品交易對話，有本院99年度聲監字第163號通訊監察書1份及如附表二所示之通訊監察譯文附卷足佐（內容與證據出處均詳附表二所示），益徵上開人等通話之目的確係要交易或轉讓毒品無疑。(三)證人李明修及曾書賢於99年3月18日經警採尿送驗，證人李明修呈現愷他命陽性反應，證人曾書賢呈現甲基安非他命及愷他命陽性反應，亦有詮昕科技股份有限公司濫用藥物尿液檢驗報告2份在卷可按，而證人曹家榮則於99年2月4日及同年月7日分別因施用海洛因、甲基安非他命案件，經本院分別判處有期徒刑8月、3月，定應執行有期徒刑10月，亦有本院99年度訴字第1401號判決1份附卷可參。足認證人李明修、曾書賢均有施用愷他命之慣習，證人曹家榮亦有施用海洛因、甲基安非他命之慣習，對外有購毒之需求。(四)又被告於99年2月5日22時30分許，另案為警在臺中市○○路○段與崇德十路口拘提到案，並扣得其所有之海洛因7小包（合計淨重2.44公克，驗餘合計淨重2.35公克，包裝袋總重2.32公克，外包裝因與海洛因相結合無從析離而應視為第一級毒品）、甲基安非他命20包（驗前總毛重17.32公克，包裝袋總重4.80公克，驗前總純質淨重10.89公克，鑑驗用罄0.11公克，外包裝因與甲基安非他命相結合無從析離而應視為第二級毒品）、其所有供上揭販賣第一級、第二級、第三級毒品及轉讓第一級毒品所用如附表三編號3、4所示之行動電話、電子秤1臺、其所有預備供上揭各次販賣第一級、第二級及第三級毒品及轉讓第一級毒品所用之分裝夾鍊袋2包，亦經臺中高分院99上訴字第1604號判決認定屬實，有該判決附卷可參。可認被告確有管道取得海洛因、甲基安非他命以供販賣、轉讓，並有販賣及轉讓之工具。(五)又被告供稱：伊販賣海洛因、甲基安非他命及愷他命，可以從中賺到自己施用的部分，400元之愷他命約可賺取0.7至0.8公克之愷他命供己施用等語（見審卷一第112、138頁），足認被告販賣海洛因、甲基安非他命及愷他命，主觀上有營利之意圖無訛。(六)從而，被告之自白與相關證據均相符合，堪以採信，被告各次販賣海洛因、甲基安非他命、愷他命及轉讓海洛因之犯行，均堪認定，應依法論科。、論罪科刑之理由：一核被告所為，犯罪事實一二三八部分，均係犯毒品危害防制條例第4條第3項之販賣第三級毒品罪；犯罪事實四六部分，均係犯毒品危害防制條例第4條第1項之販賣第一級毒品罪；犯罪事實五九十部分，係犯毒品危害防制條例第4條第2項之販賣第二級毒品罪；犯罪事實七部分，則係犯同條例第8條第1項轉讓第一級毒品罪。二被告各該持有海洛因、甲基安非他命之低度行為，分別為販賣、轉讓之高度行為所吸收，均不另論罪。又持有第三級毒品愷他命之行為，毒品危害防制條例第11條第5項規定：「持有第三級毒品純質淨重20公克以上者，處3年以下有期徒刑，得併科新臺幣30萬元以下罰金。」然被告各次販賣愷他命實際持有愷他命之重量不明，且未扣案無從鑑定愷他命之純質淨重是否為20公克以上。準此，依無罪推定原則，被告上開販賣前持有第三級毒品愷他命之行為不成立犯罪，而無「吸收」之問題。至被告轉讓海洛因部分，亦無證據證明轉讓之重量超過淨重5公克，自不得依同條例第8條第6項予以加重，附此敘明。三被告所犯上開10罪，均犯意各別，行為各自獨立，應分論併罰之。四按98年5月20日修正公布之毒品危害防制條例第17條第2項關於「犯第4條至第8條之罪於偵查及審判中均自白者，減輕其刑。」之規定，旨在獎勵犯罪人之悛悔，同時使偵查或審判機關易於發現真實，以利毒品查緝，俾收防制毒品危害之效；故不論該被告之自白，係出於自動或被動、簡單或詳細、一次或多次，並其自白後有無翻異，苟其於偵查及審判中均有自白，即應依法減輕其刑。又刑法上所稱之自白，係指行為人對其被訴之犯罪事實為任意性之供認而言（最高法院98年度臺上字第6928號判決）。本件被告於檢察官偵訊時及本院審理時均已自白其上揭販賣第一級、第二級、第三級毒品及轉讓第一級毒品等犯行，業如上述，爰依毒品危害防制條例第17條第2項規定就上揭各罪均減輕其刑。五又98年5月20日修正公布之毒品危害防制條例第17條第1項規定：「犯第4條至第8條、第10條或第11條之罪，供出毒品來源，因而查獲其他正犯或共犯者，減輕或免除其刑」。被告吳茂毅於另案販賣毒品案件經檢察官偵訊時，供稱：伊向一位綽號「小陳」（嗣經查為陳文仕）之人買毒品的，其電話為0000000000；伊約今年（即99年）1月中或1月底，交易地點好像在苗栗交流道，該次伊向綽號「小陳」拿了約半兩多（約16、17公克）的安非他命，4點多公克的海洛因，小陳跟伊說把毒品賣掉後，再將錢交給小陳，小陳說安非他命要21,000元，海洛因要22,000元，但尚未給小陳錢；小陳除0923的電話外，還有一支0000000000的電話等語（見審卷一第65、66頁）。檢察官隨即依被告之供述而簽分偵辦小陳販賣毒品案件，嗣確有查獲綽號「小陳」之陳文仕販賣海洛因、甲基安非他命與被告之犯行，而予偵查起訴在案，亦有臺灣臺中地方法院檢察署99年10月7日中檢輝姜99偵4796字第133021號函及該署99年度偵字第12459、15267號起訴書可稽（見審卷一第67頁、第54至56頁）。是可認被告自99年1月起始向陳文仕購買海洛因、甲基安非他命，被告就犯罪事實四至七九十之犯行供出毒品來源，因而查獲其他正犯，而就此部分販賣第一級毒品、第二級毒品及轉讓第一級毒品犯行，各依毒品危害防制條例第17條第1項遞減輕其刑。至被告於警詢、偵訊時雖另供稱其係向葉文仁購買愷他命，惟另案被告葉文仁並非因被告之供述而查獲其販賣愷他命之犯行，亦有臺灣臺中地方法院檢察署中檢輝敦100他3168字第101475號函文、內政部警政署保安警察隊第三總隊第一大隊100年7月6日保三壹警刑字第1000003994號函文暨函附之職務報告及葉文仁之臺灣高等法院被告前案紀錄表各1份在卷可按，是被告販賣第三級毒品之犯行，自無從適用毒品危害防制條例第17條第1項減刑規定之寬典，附此敘明。六刑法第59條規定之適用：(一)再按刑法第59條之減輕其刑，係裁判上之減輕，必以犯罪之情狀可憫恕，認為宣告法定最低度之刑猶嫌過重者，始有其適用；如別有法定減輕之事由，應先依法定減輕事由減輕其刑後，猶嫌過重時，始得為之；若有2種以上法定減輕事由，仍應先依法定減輕事由遞減其刑後，猶嫌過重時，始得再依刑法第59條規定酌減其刑，最高法院88年度臺上字第1862號判決意旨可資參照。復按刑之量定，為求個案裁判之妥當性，法律固賦予法院裁量權，但此項裁量權之行使，除應依刑法第57條規定，審酌行為人及其行為等一切情狀，為整體之評價，並應顧及比例原則與平等原則，使罪刑均衡，輕重得宜，以契合社會之法律感情。販賣第一級毒品罪之法定刑為「死刑或無期徒刑；處無期徒刑者，得併科新臺幣20,000,000元以下罰金」。其法定刑既為死刑、無期徒刑，別無其他自由刑之規定，刑度可謂重大。然同為販賣第一級毒品之人，其原因動機不一，犯罪情節未必盡同，或有大盤毒梟者，亦有中、小盤之分，甚或僅止於吸毒者友儕間為求互通有無而為販賣者亦有之，其販賣行為所造成危害社會之程度自屬有異，法律科處此類犯罪，所設之法定最低本刑卻同為死刑或無期徒刑，且處無期徒刑者，得併科新臺幣20,000,000元以下之罰金，不可謂不重。於此情形，倘依其情狀處以有期徒刑，即足以懲儆，並可達防衛社會之目的者，自非不可依客觀之犯行與主觀之惡性二者加以考量其情狀是否有可憫恕之處，適用刑法第59條之規定酌量減輕其刑，期使個案裁判之量刑，能斟酌至當，符合比例原則。又適用刑法第59條酌量減輕其刑時，並不排除同法第57條所列舉10款事由之審酌（最高法院70年5月16日70年度第6次刑事庭長會議決議足供參考）。(二)依上開說明意旨，本院認為被告所為犯罪事實四六所示之販賣海洛因犯行，固戕害國民健康，助長施用毒品惡習，其行為實屬不該，惟被告各次販賣海洛因之所得僅500元、3,000元，均係小額交易，屬毒品交易之下游，販賣毒品之對象曹家榮原即有施用毒品之慣習，有其臺灣高等法院被告前案紀錄表1份在卷可按，被告之惡性情節較諸大量走私進口或長期販賣毒品之「大盤」、「中盤」毒販有差異，其對社會整體侵害之程度尚非鉅大，被告亦染有施用之惡習，業據被告供承在卷，被告係為圖自己得以施用毒品，始鋌而走險販賣海洛因，惟被告就所犯之販賣第一級毒品罪，其最輕法定本刑為無期徒刑，縱使被告所犯販賣第一級毒品罪經依毒品危害防制條例第17條第2項規定減輕其刑，及依同條第1項規定遞減輕其刑後，均量處法定最低刑度之刑，仍嫌過重，而依被告客觀之犯行與主觀之惡性二者加以考量其犯罪情狀，爰依刑法第59條之規定，就被告所犯上開販賣第一級毒品罪部分各酌量減輕其刑，並均遞減輕其刑。七又「數罪併罰，分別宣告其罪之刑，依下列各款定其應執行者：五宣告多數有期徒刑者，於各刑中之最長期以上，各刑合併之刑期以下，定其刑期。但不得逾30年。」刑法第51條第5款定有明文。又法律上屬於自由裁量事項，尚非概無法律性之拘束，在法律上有其外部界限及內部界限。前者法律之具體規定，使法院得以具體選擇為適當裁判，此為自由裁量之外部界限。後者法院為自由裁量時，應考量法律之目的，法律秩序之理念所在，此為自由裁量之內部界限。法院為裁判時，二者均不得有所踰越。在數罪併罰應定其應執行刑之案件，法院所為刑之酌定，固屬自由裁量事項，然對於法律之內、外部界限，仍均應受其拘束。最高法院94年度臺非字第21號判決要旨足供本案定刑之參考。從而，數罪併罰在定其應執行之刑之際，自應再為應執行之刑的決定，亦屬一種特別的量刑過程，其考量結果，並非單純表示一種數罪刑度的總和而已，而是再次對於同一行為人責任的檢視。相較刑法第57條定有科刑時應審酌的事項，此項規定係對一般犯罪行為之裁量而言。而合併刑之宣告，則屬一種對犯罪人本身及所犯之各種犯罪的綜合判斷。申言之，定執行之刑的宣告，並非在法定範圍之內自由裁定，應注意行為人從其犯數罪所反映的人格特性，及考量刑法目的相關刑事政策，妥為宣告。而刑法的功能中，除一般預防及特別預防之外，更重要的是，行為人再社會化及具體的社會保護作用，否則加諸過度之刑罰於被告，徒僅造成責任報應，去實現一個未知、抽象的正義。因此，是否為被告長期性監禁宣告的同時，應一併考量被告犯案情節對社會之衝擊，並注意此舉是否造成被告更生絕望的心理影響，使得被告的人格遭受完全性地抹滅。換言之，必須考量刑罰手段的相當性，儘量選擇能使受刑人復歸社會生活之刑罰方法。法官無法以所謂「治亂世用重典」之理由，加重刑罰以圖遏止歪風，不能過度強調所謂一般預防的刑罰目的。實則，就人性尊嚴及人權的思想而言，任何一個人均非他人的工具，以加重被告的刑罰作為達到阻嚇其他人犯罪的手段，被告已淪為教化社會大眾的工具，喪失了作為一個人主體性，這均與我國刑事政策之立法有違。凡此即構成最高法院所揭示「內部界限」之意義。八本院審酌前揭情狀（包括前述酌減之事由），並參酌被告有違反毒品危害防制條例前科，有前開臺灣高等法院被告前案紀錄表可參，被告之素行難認良善。被告明知海洛因、甲基安非他命、愷他命係屬戕害人身心之毒品，竟為貪圖不法利益，鋌而走險販賣供他人施用，另基於朋友情誼，無償提供海洛因與曹家榮施用，擴大毒害，無視上開毒品足以使施用者導致精神障礙、性格異常，甚至造成生命危險之生理成癮性及心理依賴性，嚴重影響社會治安、戕害國民身心健康，並考量被告各自販賣毒品之次數、販賣之所得非鉅、轉讓海洛因之數量、次數，犯罪之動機、方法、手段，販賣毒品之數量及對象，及犯後之態度等一切情狀，分別量處如主文所示之刑。又被告現年27歲，若本院定以過重之應執行刑，其效用可能隨著長期刑之執行，等比例地大幅下跌，效用甚低，對被告教化效果亦不佳，尚且加重國家財政無益負擔，亦有害被告回歸社會，爰定其應執行之刑如主文所示，以期兼顧對於被告之警示及更生。公訴檢察官雖請求量處被告有期徒刑15年，然公訴檢察官未慮及被告販賣第一級毒品部分，情輕法重，有毒品危害防制條例第17條第1項、第2項規定之適用，並應依刑法第59條予以酌減，販賣第二級毒品部分，亦有毒品危害防制條例第17條第1項、第2項規定之適用，是公訴檢察官前開求刑實屬過重，尚有未洽。九沒收部分：(一)按以營利為目的販入毒品，經多次販賣後，持有剩餘毒品被查獲，其各次販賣毒品行為，固應併合處罰。惟該持有剩餘毒品之低度行為，應僅為最後一次販賣毒品之高度行為所吸收，不另論罪。故就該查獲之剩餘毒品，祇能於最後一次之販賣毒品罪宣告沒收銷燬，不得於各次販賣毒品罪均宣告沒收銷燬；又應沒收銷燬之物執行完畢與不存在，係屬二事，本案中因犯罪依法必須沒收銷燬之物，縱已於其他相關案件確定判決中諭知沒收銷燬並執行完畢，亦不得認已滅失而不存在，且因該他案判決之認定僅具個案拘束之效力，是於本案依法仍屬應宣告沒收銷燬之物，自不得以該物因其他相關之判決已諭知沒收銷燬確定，並經執行完畢為由，而不為沒收之諭知，最高法院98年度臺上字第738號、98年度臺上字第4258號判決要旨參照。是以：1.本案被告吳茂毅所犯多次販賣第一級毒品及轉讓第一級毒品罪，其最後一次轉讓第一級毒品之時間為99年1月31日，而被告另案於99年2月5日22時30分許，為警在臺中市○○路○段與崇德十路口，扣得被告所有供販賣所用之第一級毒品海洛因7小包（合計淨重2.44公克，驗餘合計淨重2.35公克，包裝袋總重2.32公克，外包裝因與第一級毒品海洛因相結合無從析離而應視為第1級毒品，行政院衛生署草屯療養院98年4月21日草療鑑字第0980002432號函、法務部調查局93年3月19日調科壹字第09300113060號函、最高法院95年度臺上字第3934號判決參照），係被告吳茂毅經多次販賣第一級毒品及轉讓第一級毒品後，持有剩餘第一級毒品被查獲，縱經臺中高分院以99年度上訴字第1604號判決宣告沒收銷燬，經最高法院駁回上訴後確定，惟該他案判決之認定僅具個案拘束之效力，於本案依法仍屬應宣告沒收銷燬之物，仍應依法宣告沒收銷燬之。故就前揭所查獲之剩餘毒品，應於被告最後1次之轉讓海洛因罪宣告沒收銷燬，不得於各次販賣毒品罪均宣告沒收銷燬，亦即前揭扣案之海洛因自應於附表一編號７所示之主刑之後，依毒品危害防制條例第18條第1項前段宣告沒收銷燬之（最高法院98年度臺上字第3060號判決意旨參照）。至因鑑驗所耗損之第一級毒品海洛因部分，既已滅失，即不另為沒收之諭知。2.本案被告亦有犯多次販賣第二級毒品罪，其最後1次販賣第二級毒品之時間為99年2月5日，而被告另案於99年2月5日22時30分許，為警在臺中市○○路○段與崇德十路口，扣得之第二級毒品甲基安非他命20包（驗前總毛重17.32公克，包裝袋總重4.80公克，驗前總純質淨重10.89公克，鑑驗用罄0.11公克，外包裝因與第2級毒品甲基安非他命相結合無從析離而應視為第二級毒品，理由同上揭行政院衛生署草屯療養院函釋），係被告經多次販賣第二級毒品後，持有剩餘第二級毒品被查獲，縱經臺中高分院以99年度上訴字第1604號判決宣告沒收銷燬，依前揭說明，仍應於本案諭知沒收銷燬之。故就前揭所查獲之剩餘毒品，應於被告最後1次之販賣第二級毒品罪中宣告沒收銷燬，不得於各次販賣毒品罪均宣告沒收銷燬，亦即前揭扣案之甲基安非他命自應於附表一編號１０所示之主刑之後，依毒品危害防制條例第18條第1項前段宣告沒收銷燬之（最高法院98年度臺上字第3060號判決意旨參照）。至因鑑驗所耗損之第二級毒品甲基安非他命部分，既已滅失，即不另為沒收之諭知。(二)毒品危害防制條例第19條第1項規定，犯販賣毒品罪者，其犯罪所得之財物均沒收之，係採義務沒收主義。故販賣毒品所得之對價，不問其中成本若干，利潤多少，均應全部諭知沒收，貫徹政府查禁煙毒之決心，以符立法本旨（最高法院91年度臺上字第2419號判決意旨參照）。再按毒品危害防制條例第19條第1項，係刑法第38條第1項第2款之特別規定，採義務沒收主義，苟能證明係供犯罪所用或因犯罪所得之財物，均應沒收之，如全部或一部不能沒收時，追徵其價額或以其財產抵償之，並不以當場搜獲扣押者為限（最高法院88年度臺上字2039號判決要旨參照）。又毒品危害防制條例第19條第1項規定性質上係沒收之補充規定。其屬於本條所定沒收之標的，如得以直接沒收者，判決主文僅宣告沒收即可，不生「追徵其價額」或「以其財產抵償之」問題，須沒收之標的全部或一部不能沒收時，始生「追徵其價額」或「以其財產抵償之」選項問題。而「追徵其價額」或「以其財產抵償之」係屬兩種選項，分別係針對現行貨幣以外之其他財產與現行貨幣而言，最高法院99年度第5次刑事庭會議亦可供參酌。則販賣毒品所得之金錢或所用之物，無論已否扣案，均應依法沒收。從而：1.被告各次販賣海洛因所得（詳如犯罪事實四六所載）、各次販賣甲基安非他命所得（詳如犯罪事實五九十所載），及各次販賣愷他命所得（詳如犯罪事實一至三八所載）均未扣案，應分別依毒品危害防制條例第19條第1項宣告沒收之，並各在附表一編號１至６、８至１０所示其所犯販賣第一級、第二級及第三級毒品罪項下，就各次販賣毒品所得宣告沒收，如全部或一部不能沒收時，以其財產抵償之。2.另案扣案之SonyEricsson廠牌行動電話1支（含門號0000000000號晶片卡1張）、GPLUS廠牌行動電話1支（含門號0000000000號晶片卡1張）分別為被告所有，供其犯犯罪事實一至三之販賣第三級毒品罪（被告持用SonyEricsson廠牌行動電話），及犯罪事實四至八十所示販賣第一級、第二級與第三級毒品及轉讓第一級毒品罪所用之物（被告持用GPLUS廠牌行動電話），扣案之電子秤1臺，亦係被告所有供其犯犯罪事實一至十所示之販賣第一級、第二級、第三級毒品罪及轉讓第一級毒品所用之物，業據被告於本院審理時供承在卷（見審卷一第110、134、135、138頁），上開扣案物除GPLUS廠牌行動電話（含門號0000000000號晶片卡1張）外，雖均經臺中高分院另案宣告沒收確定，然於本案依法屬應宣告沒收之物，仍應毒品危害防制條例第19條第1項之規定，在各該附表一所示之各次犯行之主刑項下分別予以諭知沒收之。3.另案扣案之分裝夾鍊袋2包，亦係被告所有，且供其犯上揭各次販賣第一級、第二級、第三級毒品及轉讓第一級毒品罪預備之物，業據被告於本院審理供承在卷（見同上頁），雖亦經臺中高分院另案宣告沒收確定，依前開說明，仍應依刑法第38條第1項第2款規定，在上揭各罪主刑項下宣告沒收。肆、適用之法律：依刑事訴訟法第299條第1項前段，毒品危害防制條例第4條第1項、第2項、第3項、第8條第1項、第17條第1項、第2項、第18條第1項前段、第19條第1項，刑法第11條、第59條、第51條第5款、第9款、第38條第1項第2款，判決如主文。本案經檢察官黃勝裕到庭執行職務。中華民國100年11月16日刑事第十三庭審判長法官賴妙雲法官黃麗玲法官楊欣怡以上正本證明與原本無異。如不服本判決應於收受判決後10日內向本院提出上訴書狀，並應敘述具體理由；其未敘述上訴理由者，應於上訴期間屆滿後20日內向本院補提理由書（均須按他造當事人之人數附繕本）「切勿逕送上級法院」。書記官黃泰能中華民國100年11月16日附錄論罪科刑法條：毒品危害防制條例第4條製造、運輸、販賣第一級毒品者，處死刑或無期徒刑；處無期徒刑者，得併科新臺幣2千萬元以下罰金。製造、運輸、販賣第二級毒品者，處無期徒刑或7年以上有期徒刑，得併科新臺幣1千萬元以下罰金。製造、運輸、販賣第三級毒品者，處5年以上有期徒刑，得併科新臺幣7百萬元以下罰金。製造、運輸、販賣第四級毒品者，處3年以上10年以下有期徒刑，得併科新臺幣3百萬元以下罰金。製造、運輸、販賣專供製造或施用毒品之器具者，處1年以上7年以下有期徒刑，得併科新臺幣1百萬元以下罰金。前五項之未遂犯罰之。毒品危害防制條例第8條轉讓第一級毒品者，處1年以上7年以下有期徒刑，得併科新臺幣1百萬元以下罰金。轉讓第二級毒品者，處6月以上5年以下有期徒刑，得併科新臺幣70萬元以下罰金。轉讓第三級毒品者，處3年以下有期徒刑，得併科新臺幣30萬元以下罰金。轉讓第四級毒品者，處1年以下有期徒刑，得併科新臺幣10萬元以下罰金。前四項之未遂犯罰之。轉讓毒品達一定數量者，加重其刑至二分之一，其標準由行政院定之。附表一┌──┬─────┬─────────────────┐│編號│犯罪事實│所犯罪名及應處之刑（含主刑、從刑）│├──┼─────┼─────────────────┤│１│犯罪事實欄│吳茂毅販賣第三級毒品，處有期徒刑貳│││一所載之犯│年陸月。未扣案販賣第三級毒品所得新│││行│臺幣肆佰元沒收之，如全部或一部不能││││沒收時，以其財產抵償之。扣案如附表││││三編號3、5、6所示之物均沒收。│├──┼─────┼─────────────────┤│２│犯罪事實欄│吳茂毅販賣第三級毒品，處有期徒刑貳│││二所載之犯│年陸月。未扣案販賣第三級毒品所得新│││行│臺幣肆佰元沒收之，如全部或一部不能││││沒收時，以其財產抵償之。扣案如附表││││三編號3、5、6所示之物均沒收。│├──┼─────┼─────────────────┤│３│犯罪事實欄│吳茂毅販賣第三級毒品，處有期徒刑貳│││三所載之犯│年陸月。未扣案販賣第三級毒品所得新│││行│臺幣肆佰元沒收之，如全部或一部不能││││沒收時，以其財產抵償之；扣案如附表││││三編號3、5、6所示之物均沒收。│├──┼─────┼─────────────────┤│４│犯罪事實欄│吳茂毅販賣第一級毒品，處有期徒刑│││四所載之犯│年拾月。未扣案販賣第一級毒品所得新│││行│臺幣伍佰元沒收之，如全部或一部不能││││沒收時，以其財產抵償之。扣案如附表││││三編號3、5、6所示之物均沒收。│├──┼─────┼─────────────────┤│５│犯罪事實欄│吳茂毅販賣第二級毒品，處有期徒刑貳│││五所載之犯│年。未扣案販賣第二級毒品所得新臺幣│││行│壹仟伍佰元沒收之，如全部或一部不能││││沒收時，以其財產抵償之。扣案如附表││││三編號4、5、6所示之物均沒收。│├──┼─────┼─────────────────┤│６│犯罪事實欄│吳茂毅販賣第一級毒品，處有期徒刑肆│││六所載之犯│年貳月。未扣案販賣第一級毒品所得新│││行│臺幣仟元沒收之，如全部或一部不能││││沒收時，以其財產抵償之。扣案如附表││││三編號4、5、6所示之物均沒收。│├──┼─────┼─────────────────┤│７│犯罪事實欄│吳茂毅轉讓第一級毒品，處有期徒刑捌│││七所載之犯│月。扣案如附表三編號一所示之物沒收│││行│銷燬之。扣案如附表三編號4、5、6││││所示之物均沒收。│├──┼─────┼─────────────────┤│８│犯罪事實欄│吳茂毅販賣第三級毒品，處有期徒刑貳│││八所載之犯│年捌月。未扣案販賣第三級毒品所得新│││行│臺幣貳仟元沒收之，如全部或一部不能││││沒收時，以其財產抵償之。扣案如附表││││三編號4、5、6所示之物均沒收。│├──┼─────┼─────────────────┤│９│犯罪事實欄│吳茂毅販賣第二級毒品，處有期徒刑壹│││九所載之犯│年拾壹月。未扣案販賣第二級毒品所得│││行│新臺幣伍佰元沒收之，如全部或一部不││││能沒收時，以其財產抵償之。扣案如附││││表三編號5、6所示之物均沒收。│├──┼─────┼─────────────────┤│１０│犯罪事實欄│吳茂毅販賣第二級毒品，處有期徒刑壹│││十所載之犯│年拾壹月。扣案如附表三編號二所示之│││行│物沒收銷燬之；未扣案販賣第二級毒品││││所得新臺幣伍佰元沒收之，如全部或一││││部不能沒收時，以其財產抵償之。扣案││││如附表三編號4、5、6所示之物均沒││││收。│└──┴─────┴─────────────────┘附表二：┌──┬──────┬────────────────────┬──────┐│編號│時間│通訊監察譯文內容│備註│├──┼──────┼────────────────────┼──────┤│１│99年01月30日│A：0000000000（吳茂毅）│佐證犯罪事實│││00時07分55秒│B：0000000000（曾書賢）│一二三│││├────────────────────┤通訊監察譯文││││A：那個「酒」（術語）你是要拿錢給我嗎？│出處：99偵││││B：沒有，我要順便跟你拿那個「酒」啦。對│14634號卷第││││阿。然後禮拜天「酒錢」在一次全部給你。│59頁││││A：上次欠三瓶嗎│││││B：對阿對阿。│││││A：二、三瓶嗎？│││││B：二瓶啦。上次先跟你拿二瓶而已。還有欠│││││三瓶吧！嘿呀。│││││A：你往上楓的方向走會看到酒國英雄。還沒│││││有到酒國英雄。哎～那條是什麼路？│││││B：酒國英雄對面那條路嘛。│││││A：嘿。酒國英雄那裡。│││││（A男叫B男到酒國英雄在打給A男）││├──┼──────┼────────────────────┼──────┤│２│99年01月29日│A：0000000000（吳茂毅）│佐證犯罪事實│││19時37分27秒│B：0000000000（曹家榮）│四│││├────────────────────┤通訊監察譯文││││A：喂。│出處：99偵││││B：喂。│13990號卷第││││A：怎麼了？│21頁││││B：啊？│││││A：你不是在找我？│││││B：哇操，都昏了。你那邊現在還有「酒」（│││││術語）嗎？│││││A：八點半就有了。│││││B：喔～還好。那不用了、不用了。我剛才殺│││││到那邊知道嗎？我殺到太平去買酒（術語│││││）吶。│││││A：我這裡就有「酒」了。│││││B：啊？│││││A：我這裡就有「酒」了。│││││B：你在哪裡？│││││A：我在家裡阿。│││││B：啊？│││││A：我在我家阿。│││││B：哭爸喔。你那邊現在就有了嗎？│││││A：嘿押。│││││B：「一」耶。我昏倒了。我又回去，你就馬│││││上要拿出來喔。│││││A：好阿，你多久會到？│││││B：……。喂。│││││A：你打給我，我就出來了。│││││B：我差不多二十分就到了啦。│││││A：好。│││││B：不要給我弄太少啦。│││││A：好，掰掰。│││││B：好。│││├──────┼────────────────────┼──────┤││99年01月29日│A：0000000000（吳茂毅）│佐證犯罪事實│││19時52分55秒│B：0000000000（曹家榮）│四│││├────────────────────┤通訊監察譯文││││B：喂，到了啦。│出處：99偵││││A：停車場。│13990號卷第││││B：好啦。│22頁│││││││├──────┼────────────────────┼──────┤││99年01月29日│A：0000000000（吳茂毅）│佐證犯罪事實│││19時56分17秒│B：0000000000（曹家榮）│四│││├────────────────────┤通訊監察譯文││││A：要出去了啦。│出處：99偵││││B：吼～喔。│13990號卷第│││││22頁│││││││├──────┼────────────────────┼──────┤││99年01月29日│A：0000000000（吳茂毅）│佐證犯罪事實│││20時12分56秒│B：0000000000（曹家榮）│四│││├────────────────────┤通訊監察譯文││││B：這樣子弄得話，我明天怎麼跟你弄？│出處：99偵││││A：喔我等一下跟他們講一下明天來換新的球│13990號卷第││││給你。│22頁││││B：喔，真的明天不要這樣子搞了喔。│││││A：你要什麼？││├──┼──────┼────────────────────┼──────┤│３│99年01月29日│A：0000000000（吳茂毅）│佐證犯罪事實│││22時56分12秒│B：0000000000（鄒聖緯）│五│││├────────────────────┤通訊監察譯文││││B：我要三罐。│出處：99偵││││A：三罐喔。│14634號卷第││││B：嘿。│74頁││││A：你在哪裡？│││││B：我在大雅阿。│││││A：我在大雅台新銀行等你。│││││B：哪裡？│││││A：台新銀行。│││││（B男在問台新銀行在哪裡）│││││A：我一分鐘就到了。│││││B：好～。│││││A：好～。│││││B：我馬上過去。│││││A：好。│││├──────┼────────────────────┼──────┤││99年01月29日│A：0000000000（吳茂毅）│佐證犯罪事實│││23時00分21秒│B：0000000000（鄒聖偉）│五│││├────────────────────┤通訊監察譯文││││A：喂你在哪裡？│出處：99偵││││B：你在哪裡？我沒有看到你。│14634號卷第││││A：我到台新銀行後面，我繞出去了。│74頁││││B：台新銀行喔～。│││││A：你到門口等。││├──┼──────┼────────────────────┼──────┤│４│99年01月30日│A：0000000000（吳茂毅）│佐證犯罪事實│││15時40分57秒│B：0000000000（徐嘉偉）│六│││├────────────────────┤通訊監察譯文││││A：你要借幾仟？│出處：99偵││││B：同款阿。│14634號卷第││││A：同款，三仟五嗎？│49頁││││B：…。│││││A：三仟？好阿。三仟。你到相同的停車場打│││││給我。我差不多十分鐘到那裡。│││││B：好阿。│││││A：好。│││││B：我可能會晚點啦。我到了再打給你啦。│││││A：好啦。有確定嗎？│││││B：嗯。│││││A：OK。│││├──────┼────────────────────┼──────┤││99年01月30日│A：0000000000（吳茂毅）│佐證犯罪事實│││18時00分01秒│B：0000000000（徐嘉偉）│六│││├────────────────────┤通訊監察譯文││││A：喂。│出處：99偵││││B：喂。我現在過去找你喔。│14634號卷第││││A：掰掰。│49頁││││B：掰掰。│││││││││││││││││││││││├──────┼────────────────────┼──────┤││99年01月30日│A：0000000000（吳茂毅）│佐證犯罪事實│││18時24分47秒│B：0000000000（徐嘉偉）│六│││├────────────────────┤通訊監察譯文││││A：你到了嗎？│出處：99偵││││B：嘿。│14634號卷第││││A：我差不多三分到。│49頁││││B：掰掰。│││││A：掰。││├──┼──────┼────────────────────┼──────┤│５│99年01月31日│A：0000000000（吳茂毅）│佐證犯罪事實│││16時23分34秒│B：0000000000（曹家榮）│七│││├────────────────────┤通訊監察譯文││││B：你什麼時候會回來？│出處：99偵││││A：大概一個小時以內吧。│13990號卷第││││B：一個小時以內嗎？│22頁││││A：嘿。你要一瓶「水」（術語）嗎？│││││B：用半瓶好不好？│││││A：半瓶嗎？│││││B：好不好？│││││A：好啦。│││││B：喂貓咪。│││││A：嘿。│││││B：給你救一次好不好？│││││A：喔～。│││││B：今天…都沒有用耶。│││││A：早上吶。早上都沒有用？│││││B：對阿，今天都沒有用阿。早上那個是朋友│││││的阿。│││││A：…那個早上有用吶。我早上拿給那個誰，│││││比較好吶。│││││B：不是啦，我是說：早上那個…那個沒有用│││││啦。│││││A：喔～。│││││B：好不好？│││││A：那我再打給你。│││││B：不要不接吶。老大。│││││A：不會。│││││B：我會死掉吶。│││││A：好～。│││├──────┼────────────────────┼──────┤││99年01月31日│A：0000000000（吳茂毅）│佐證犯罪事實│││17時51分11秒│B：0000000000（曹家榮）│七│││├────────────────────┤通訊監察譯文││││B：喂，你到了嗎？│出處：99偵││││A：我差不多6點到。│13990號卷第││││B：啊？│23頁││││A：我6點到台中打給你。│││││B：好阿。│││├──────┼────────────────────┼──────┤││99年01月31日│A：0000000000（吳茂毅）│佐證犯罪事實│││18時01分53秒│B：0000000000（曹家榮）│七│││├────────────────────┤通訊監察譯文││││簡訊：貓咪你說等你到6點電話卻不接我人在│出處：99偵││││不舒服你別這樣搞好嗎│13990號卷第│││││23頁│││││││├──────┼────────────────────┼──────┤││99年01月31日│A：0000000000（吳茂毅）│佐證犯罪事實│││19時24分17秒│B：0000000000（曹家榮）│七│││├────────────────────┤通訊監察譯文││││簡訊：品質不錯，保持下去，期待明天，保持│出處：99偵││││聯絡，新年快樂│13990號卷第│││││23頁││││││├──┼──────┼────────────────────┼──────┤│６│99年02月04日│A：0000000000（吳茂毅）│佐證犯罪事實│││00時42分46秒│B：0000000000（李明修）│八│││├────────────────────┤通訊監察譯文││││B：喂。│出處：99偵││││A：喂。你不要這樣子講啦。電話中你不要這│14634號卷第││││樣子講啦。你若是被人監聽到，咱們倆都│33頁││││會有事情吶。│││││B：喲。│││││A：你可以用「一箱」（術語）。這我跟你說│││││，你跟他講：一萬啦。│││││B：什麼？│││││A：差不多一萬啦。嘿呀，他有在放嗎？│││││B：我不知道。│││││A：你若說沒有。一就一萬啦。好不好？若他│││││有拿我再請你喝的「啤酒」（術語）好不│││││好？│││││B：抱歉了，我不曉得要怎麼講。│││││A：沒關係，你跟他說：一萬啦。半箱五仟五│││││啦。若四分之一箱就跟他說：三仟啦。│││││B：好啦。│││││A：吼好。││├──┼──────┼────────────────────┼──────┤│７│99年02月04日│A：0000000000（吳茂毅）│佐證犯罪事實│││23時02分23秒│B：0000000000（曹家榮）│九│││├────────────────────┤通訊監察譯文││││簡訊：怎麼酒又不夠，這樣下去很難交陪，杯│出處：99偵││││子還破洞，注意點，別再出問題了。│13990號卷第│││││23頁││││││├──┼──────┼────────────────────┼──────┤│８│99年02月05日│A：0000000000（吳茂毅）│佐證犯罪事實│││18時55分06秒│B：0000000000（鄒聖緯）│十│││├────────────────────┤通訊監察譯文││││B：喂。│出處：99偵││││A：你來上夢全家找我好媽？│14634號卷第││││B：大楓全家喔？│78頁││││A：嘿～。吼，我在全家等你。│││││B：好～。│││││A：好～。│││├──────┼────────────────────┼──────┤││99年02月05日│A：0000000000（吳茂毅）│佐證犯罪事實│││18時56分38秒│B：0000000000（鄒聖緯）│十│││├────────────────────┤通訊監察譯文││││A：喂。│出處：99偵││││B：喂。順便帶一點「葡萄酒」（術語）出來│14634號卷第││││喔。│78頁││││A：好～我知道。│││││B：吼。我兩分鐘到啦。│││││A：好。│││││B：好。││└──┴──────┴────────────────────┴──────┘附表三┌──┬────────────────────────────┬───┐│編號│扣案物品及數量│所有人│├──┼────────────────────────────┼───┤│1│海洛因7小包（合計淨重2.44公克，驗餘淨重2.35公克，空包裝│吳茂毅│││總重2.32公克）││├──┼────────────────────────────┼───┤│2│甲基安非他命20包（驗前總毛重17.32公克，包裝塑膠袋總重約│吳茂毅│││4.80公克）││├──┼────────────────────────────┼───┤│3│SonyEricsson廠牌行動電話1支（含0000000000號晶片卡1張│吳茂毅│││）││├──┼────────────────────────────┼───┤│4│GPLUS廠牌行動電話（雙卡手機）1支（含門號0000000000號│吳茂毅│││晶片卡1張）││├──┼────────────────────────────┼───┤│5│電子秤1臺│吳茂毅│├──┼────────────────────────────┼───┤│6│分裝夾鍊袋2包│吳茂毅│└──┴────────────────────────────┴───┘",
  "characters": {
    "judges": [
      "賴妙雲",
      "黃麗玲",
      "楊欣怡"
    ],
    "prosecutors": [
      "黃勝裕"
    ],
    "lawyers": [

    ],
    "clerks": [
      "黃泰能"
    ],
    "plaintiffs": [

    ],
    "defendants": [
      "吳茂毅"
    ],
    "prosecutor_office": [
      "臺灣臺中地方法院檢察署檢察官"
    ],
    "creditors": [

    ],
    "debtors": [

    ],
    "judicial_associate_officer": [

    ]
  },
  "adjudged_at": "2011-11-16",
  "created_at": "2016-02-12 21:22:20",
  "updated_at": "2016-02-12 21:22:20"
}