{
  "identify": "TCD-100-中簡-2558-20111116-1",
  "court": {
    "name": "臺灣臺中地方法院",
    "code": "TCD"
  },
  "division": {
    "name": "刑事",
    "code": "M"
  },
  "year": 100,
  "word": "中簡",
  "number": "2558",
  "jcheck": "1",
  "reason": "違反性騷擾防治法",
  "content": "臺灣臺中地方法院刑事簡易判決       100年度中簡字第2558號\n聲  請  人  臺灣臺中地方法院檢察署檢察官\n被      告  李家維\n上列被告因違反性騷擾防治法案件，經檢察官聲請以簡易判決處\n刑（100年度偵字第16150號），本院判決如下：\n    主    文\n李家維意圖性騷擾，乘人不及抗拒而為觸摸其胸部之行為，處拘\n役伍拾日，如易科罰金，以新臺幣壹仟元折算壹日。\n    犯罪事實及理由\n一、本件犯罪事實及證據，均引用檢察官聲請簡易判決處刑書之\n    記載（如附件）。\n二、核被告李家維所為，係犯性騷擾防治法第25條第1項之意圖\n    性騷擾，乘人不及抗拒而為觸摸其胸部之行為罪。爰審酌被\n    告為逞一己私欲，竟對於女性身體自主權毫不尊重，乘A女\n    不及抗拒之際，而觸摸A女之胸部，所為實值非難；兼衡酌\n    被告前無犯罪前科，及其犯後坦承犯行等一切情狀，量處如\n    主文所示之刑，並諭知易科罰金之折算標準。\n三、依刑事訴訟法第449條第1項、第454條，性騷擾防治法第25\n    條第1項，刑法第11條前段、第41條第1項前段，逕以簡易判\n    決處刑如主文。\n如不服本判決，應於判決送達後10日內向本院提出上訴狀（須附\n繕本）。\n中    華    民    國    100   年    11    月    16    日\n                  臺中簡易庭  法  官  戴嘉慧\n上正本證明與原本無異。\n告訴人或被害人對於判決如有不服具備理由請求檢察官上訴者，\n其上訴期間之計算係以檢察官收受判決正本之日期為準。\n                              書記官  劉晴芬\n中    華    民    國    100   年    11    月    16    日\n【附錄本案論罪科刑法條】\n《性騷擾防治法第25條第1項》\n意圖性騷擾，乘人不及抗拒而為親吻、擁抱或觸摸其臀部、胸部\n或其他身體隱私處之行為者，處二年以下有期徒刑、拘役或科或\n併科新臺幣十萬元以下罰金。\n【附件】\n臺灣臺中地方法院檢察署檢察官聲請簡易判決處刑書\n                                    100年度偵字第16150號\n    被      告  李家維  男  19歲（民國○○年○○月○日生）\n                        籍設臺中市○○區○○路2段31號\n                        現居臺中市○區○○路2段135巷7之1\n                        號2樓\n                        國民身分證統一編號：Ｚ000000000號\n上列被告因違反性騷擾防治法案件，業經偵查終結，認為宜聲請\n以簡易判決處刑，茲將犯罪事實及證據並所犯法條分敘如下：\n        犯罪事實\n一、李家維於民國100年6月20日晚間8時許，騎乘車牌號碼528\n    -GFY號重機車，途經臺中市西屯區○○○路與河南路交岔路\n    口附近，見A女（警卷代號3484-H10009，真實姓名及年籍資\n    料詳卷）單獨騎乘機車，即一路尾隨A女。迨至同日晚間8時\n    45分許，李家維尾隨A女行駛至臺中市南屯區昌明巷3之10號\n    前，見該處人煙較少，竟萌生性騷擾之犯意，乘A女不注意\n    之際，突然加速超越A女，並伸手撫摸A女之左胸部隱私部位\n    。得逞後，李家維即加速逃逸離去。\n二、案經A女訴由臺中市政府警察局第四分局報告偵辦。\n        證據並所犯法條\n一、證據：(一)被告李家維之自白；(二)告訴人A女之指訴；(三)路口\n    監視器之影像翻拍照片及被告之機車照片；(四)承辦警員程銀\n    燦之職務報告可資佐證。被告犯嫌已堪認定。\n二、核被告所為，係違反性騷擾防治法第25條第1項之罪嫌。\n三、依刑事訴訟法第451條第1項聲請逕以簡易判決處刑。\n    此致\n臺灣臺中地方法院\n中    華    民    國   100    年    10    月    11    日\n                              檢察官  林裕斌\n本件正本證明與原本無異\n中    華    民    國   100    年    10    月    19    日\n                              書記官  沈秀美",
  "structure": {
    "main": "李家維意圖性騷擾，乘人不及抗拒而為觸摸其胸部之行為，處拘\n役伍拾日，如易科罰金，以新臺幣壹仟元折算壹日。",
    "fact": "一、本件犯罪事實及證據，均引用檢察官聲請簡易判決處刑書之\n    記載（如附件）。\n二、核被告李家維所為，係犯性騷擾防治法第25條第1項之意圖\n    性騷擾，乘人不及抗拒而為觸摸其胸部之行為罪。爰審酌被\n    告為逞一己私欲，竟對於女性身體自主權毫不尊重，乘A女\n    不及抗拒之際，而觸摸A女之胸部，所為實值非難；兼衡酌\n    被告前無犯罪前科，及其犯後坦承犯行等一切情狀，量處如\n    主文所示之刑，並諭知易科罰金之折算標準。\n三、依刑事訴訟法第449條第1項、第454條，性騷擾防治法第25\n    條第1項，刑法第11條前段、第41條第1項前段，逕以簡易判\n    決處刑如主文。\n如不服本判決，應於判決送達後10日內向本院提出上訴狀（須附\n繕本）。",
    "reason": "一、本件犯罪事實及證據，均引用檢察官聲請簡易判決處刑書之\n    記載（如附件）。\n二、核被告李家維所為，係犯性騷擾防治法第25條第1項之意圖\n    性騷擾，乘人不及抗拒而為觸摸其胸部之行為罪。爰審酌被\n    告為逞一己私欲，竟對於女性身體自主權毫不尊重，乘A女\n    不及抗拒之際，而觸摸A女之胸部，所為實值非難；兼衡酌\n    被告前無犯罪前科，及其犯後坦承犯行等一切情狀，量處如\n    主文所示之刑，並諭知易科罰金之折算標準。\n三、依刑事訴訟法第449條第1項、第454條，性騷擾防治法第25\n    條第1項，刑法第11條前段、第41條第1項前段，逕以簡易判\n    決處刑如主文。\n如不服本判決，應於判決送達後10日內向本院提出上訴狀（須附\n繕本）。"
  },
  "search": "臺灣臺中地方法院刑事簡易判決100年度中簡字第2558號聲請人臺灣臺中地方法院檢察署檢察官被告李家維上列被告因違反性騷擾防治法案件，經檢察官聲請以簡易判決處刑（100年度偵字第16150號），本院判決如下：主文李家維意圖性騷擾，乘人不及抗拒而為觸摸其胸部之行為，處拘役伍拾日，如易科罰金，以新臺幣壹仟元折算壹日。犯罪事實及理由一、本件犯罪事實及證據，均引用檢察官聲請簡易判決處刑書之記載（如附件）。二、核被告李家維所為，係犯性騷擾防治法第25條第1項之意圖性騷擾，乘人不及抗拒而為觸摸其胸部之行為罪。爰審酌被告為逞一己私欲，竟對於女性身體自主權毫不尊重，乘A女不及抗拒之際，而觸摸A女之胸部，所為實值非難；兼衡酌被告前無犯罪前科，及其犯後坦承犯行等一切情狀，量處如主文所示之刑，並諭知易科罰金之折算標準。三、依刑事訴訟法第449條第1項、第454條，性騷擾防治法第25條第1項，刑法第11條前段、第41條第1項前段，逕以簡易判決處刑如主文。如不服本判決，應於判決送達後10日內向本院提出上訴狀（須附繕本）。中華民國100年11月16日臺中簡易庭法官戴嘉慧上正本證明與原本無異。告訴人或被害人對於判決如有不服具備理由請求檢察官上訴者，其上訴期間之計算係以檢察官收受判決正本之日期為準。書記官劉晴芬中華民國100年11月16日【附錄本案論罪科刑法條】《性騷擾防治法第25條第1項》意圖性騷擾，乘人不及抗拒而為親吻、擁抱或觸摸其臀部、胸部或其他身體隱私處之行為者，處二年以下有期徒刑、拘役或科或併科新臺幣十萬元以下罰金。【附件】臺灣臺中地方法院檢察署檢察官聲請簡易判決處刑書100年度偵字第16150號被告李家維男19歲（民國○○年○○月○日生）籍設臺中市○○區○○路2段31號現居臺中市○區○○路2段135巷7之1號2樓國民身分證統一編號：Ｚ000000000號上列被告因違反性騷擾防治法案件，業經偵查終結，認為宜聲請以簡易判決處刑，茲將犯罪事實及證據並所犯法條分敘如下：犯罪事實一、李家維於民國100年6月20日晚間8時許，騎乘車牌號碼528-GFY號重機車，途經臺中市西屯區○○○路與河南路交岔路口附近，見A女（警卷代號3484-H10009，真實姓名及年籍資料詳卷）單獨騎乘機車，即一路尾隨A女。迨至同日晚間8時45分許，李家維尾隨A女行駛至臺中市南屯區昌明巷3之10號前，見該處人煙較少，竟萌生性騷擾之犯意，乘A女不注意之際，突然加速超越A女，並伸手撫摸A女之左胸部隱私部位。得逞後，李家維即加速逃逸離去。二、案經A女訴由臺中市政府警察局第四分局報告偵辦。證據並所犯法條一、證據：(一)被告李家維之自白；(二)告訴人A女之指訴；(三)路口監視器之影像翻拍照片及被告之機車照片；(四)承辦警員程銀燦之職務報告可資佐證。被告犯嫌已堪認定。二、核被告所為，係違反性騷擾防治法第25條第1項之罪嫌。三、依刑事訴訟法第451條第1項聲請逕以簡易判決處刑。此致臺灣臺中地方法院中華民國100年10月11日檢察官林裕斌本件正本證明與原本無異中華民國100年10月19日書記官沈秀美",
  "characters": {
    "judges": [
      "戴嘉慧"
    ],
    "prosecutors": [

    ],
    "lawyers": [

    ],
    "clerks": [
      "劉晴芬"
    ],
    "plaintiffs": [

    ],
    "defendants": [
      "李家維",
      "李家維  男  19歲（民國○○年○○月○日生）"
    ],
    "prosecutor_office": [
      "臺灣臺中地方法院檢察署檢察官"
    ],
    "creditors": [

    ],
    "debtors": [

    ],
    "judicial_associate_officer": [

    ]
  },
  "adjudged_at": "2011-11-16",
  "created_at": "2016-02-12 21:26:44",
  "updated_at": "2016-02-12 21:26:44"
}