{
  "identify": "TCD-93-易緝-574-20041208-1",
  "court": {
    "name": "臺灣臺中地方法院",
    "code": "TCD"
  },
  "division": {
    "name": "刑事",
    "code": "M"
  },
  "year": 93,
  "word": "易緝",
  "number": "574",
  "jcheck": "1",
  "reason": "傷害",
  "content": "臺灣臺中地方法院刑事判決                        九十三年度易緝字第五七四號\n    公  訴  人  臺灣臺中地方法院檢察署檢察官\n    被      告  丙○○\n右列被告因傷害案件，經檢察官提起公訴（八十九年度偵字第九三六三號），本院判\n決如左：\n    主  文\n本件公訴不受理。\n    理  由\n一、公訴意旨略以：被告丙○○夥同謝宗麟（業經本院判決無罪確定）、吳健丞（業\n    經本院判處有期徒刑五月，得易科罰金確定）及另兩名不詳男子，於民國八十八\n    年五月七日上午二時許，在臺中市○○路一四六號大功園ＫＴＶ飲酒消費，因見\n    甲○○、乙○○不順眼，竟基於共同傷害之犯意聯絡及行為分擔，分持鋁棒、酒\n    瓶等物，敲擊、毆打甲○○、乙○○，使甲○○右尺骨骨折、頭枕頂部表皮裂傷\n    ，乙○○前額部表皮裂傷，直至甲○○、乙○○倒地不起始搭乘ＰＡ─三一三六\n    號自用小客車揚長而去，因認被告與吳健丞等人共同涉犯刑法傷害罪嫌。\n二、按告訴乃論之罪，其告訴經撤回者，應諭知不受理之判決，並得不經言詞辯論為\n    之，此為刑事訴訟法第三百零三條第三款、第三百零七條所明定。本件被告丙○\n    ○經檢察官以刑法第二百七十七條第一項之傷害罪提起公訴，依照同法第二百八\n    十七條前段規定係屬告訴乃論之罪，茲經告訴人甲○○、乙○○於第一審辯論終\n    結前具狀撤回告訴，爰不經言詞辯論，諭知不受理之判決。\n據上論斷，應依刑事訴訟法第三百零三條第三款，第三百零七條，判決如主文。\n中      華      民      國      九十三      年      十二  月    八      日\n                                        審判長法  官  張靜琪\n                                              法  官  王鏗普\n                                              法  官  賴妙雲\n右正本證明與原本無異。\n如不服本判決，應於送達後十日內向本院提出上訴狀（須附繕本），上訴於台灣高等\n法院台中分院。\n                                              書記官\n中      華      民      國      九十三      年      十二  月    八      日\n",
  "structure": {
    "main": "本件公訴不受理。",
    "reason": "一、公訴意旨略以：被告丙○○夥同謝宗麟（業經本院判決無罪確定）、吳健丞（業\n    經本院判處有期徒刑五月，得易科罰金確定）及另兩名不詳男子，於民國八十八\n    年五月七日上午二時許，在臺中市○○路一四六號大功園ＫＴＶ飲酒消費，因見\n    甲○○、乙○○不順眼，竟基於共同傷害之犯意聯絡及行為分擔，分持鋁棒、酒\n    瓶等物，敲擊、毆打甲○○、乙○○，使甲○○右尺骨骨折、頭枕頂部表皮裂傷\n    ，乙○○前額部表皮裂傷，直至甲○○、乙○○倒地不起始搭乘ＰＡ─三一三六\n    號自用小客車揚長而去，因認被告與吳健丞等人共同涉犯刑法傷害罪嫌。\n二、按告訴乃論之罪，其告訴經撤回者，應諭知不受理之判決，並得不經言詞辯論為\n    之，此為刑事訴訟法第三百零三條第三款、第三百零七條所明定。本件被告丙○\n    ○經檢察官以刑法第二百七十七條第一項之傷害罪提起公訴，依照同法第二百八\n    十七條前段規定係屬告訴乃論之罪，茲經告訴人甲○○、乙○○於第一審辯論終\n    結前具狀撤回告訴，爰不經言詞辯論，諭知不受理之判決。\n據上論斷，應依刑事訴訟法第三百零三條第三款，第三百零七條，判決如主文。"
  },
  "search": "臺灣臺中地方法院刑事判決九十三年度易緝字第五七四號公訴人臺灣臺中地方法院檢察署檢察官被告丙○○右列被告因傷害案件，經檢察官提起公訴（八十九年度偵字第九三六三號），本院判決如左：主文本件公訴不受理。理由一、公訴意旨略以：被告丙○○夥同謝宗麟（業經本院判決無罪確定）、吳健丞（業經本院判處有期徒刑五月，得易科罰金確定）及另兩名不詳男子，於民國八十八年五月七日上午二時許，在臺中市○○路一四六號大功園ＫＴＶ飲酒消費，因見甲○○、乙○○不順眼，竟基於共同傷害之犯意聯絡及行為分擔，分持鋁棒、酒瓶等物，敲擊、毆打甲○○、乙○○，使甲○○右尺骨骨折、頭枕頂部表皮裂傷，乙○○前額部表皮裂傷，直至甲○○、乙○○倒地不起始搭乘ＰＡ─三一三六號自用小客車揚長而去，因認被告與吳健丞等人共同涉犯刑法傷害罪嫌。二、按告訴乃論之罪，其告訴經撤回者，應諭知不受理之判決，並得不經言詞辯論為之，此為刑事訴訟法第三百零三條第三款、第三百零七條所明定。本件被告丙○○經檢察官以刑法第二百七十七條第一項之傷害罪提起公訴，依照同法第二百八十七條前段規定係屬告訴乃論之罪，茲經告訴人甲○○、乙○○於第一審辯論終結前具狀撤回告訴，爰不經言詞辯論，諭知不受理之判決。據上論斷，應依刑事訴訟法第三百零三條第三款，第三百零七條，判決如主文。中華民國九十三年十二月八日審判長法官張靜琪法官王鏗普法官賴妙雲右正本證明與原本無異。如不服本判決，應於送達後十日內向本院提出上訴狀（須附繕本），上訴於台灣高等法院台中分院。書記官中華民國九十三年十二月八日",
  "characters": {
    "judges": [
      "張靜琪",
      "王鏗普",
      "賴妙雲"
    ],
    "prosecutors": [

    ],
    "lawyers": [

    ],
    "clerks": [
      "中華民國九十三年十二月八日"
    ],
    "plaintiffs": [

    ],
    "defendants": [
      "丙○○",
      "右列被告因傷害案件，經檢察官提起公訴（八十九年度偵字第九三六三號），本院判",
      "決如左："
    ],
    "prosecutor_office": [
      "臺灣臺中地方法院檢察署檢察官"
    ],
    "creditors": [

    ],
    "debtors": [

    ],
    "judicial_associate_officer": [

    ]
  },
  "adjudged_at": "2004-12-08",
  "created_at": "2016-02-06 06:42:56",
  "updated_at": "2016-02-06 06:42:56"
}