{
  "identify": "CYD-100-嘉簡-1530-20111107-1",
  "court": {
    "name": "臺灣嘉義地方法院",
    "code": "CYD"
  },
  "division": {
    "name": "刑事",
    "code": "M"
  },
  "year": 100,
  "word": "嘉簡",
  "number": "1530",
  "jcheck": "1",
  "reason": "違反政府採購法",
  "content": "臺灣嘉義地方法院刑事簡易判決       100年度嘉簡字第1530號\n聲  請  人  臺灣嘉義地方法院檢察署檢察官\n被      告  蕭三奇\n            黃啟榮\n            陽明營造股份有限公司\n上  一  人\n代  表  人  黃龍泉\n上列被告因違反政府採購法案件，經檢察官聲請簡易判決處刑（\n100 年度偵字第4115號），本院逕以簡易判決如下：\n    主      文\n蕭三奇犯政府採購法第八十七條第五項前段之妨害投標罪，處有\n期徒刑肆月，如易科罰金，以新臺幣壹仟元折算壹日。緩刑貳年\n。\n黃啟榮犯政府採購法第八十七條第五項後段之妨害投標罪，處有\n期徒刑月，如易科罰金，以新臺幣壹仟元折算壹日。\n陽明營造股份有限公司因公司之代表人執行業務犯政府採購法第\n八十七條第五項後段之妨害投標罪，科罰金新臺幣伍萬元。\n    事實及理由\n一、本件犯罪事實及證據，除證據部分應補充「公司及分公司基\n    本資料查詢（明細）1 紙」外，其餘均引用檢察官聲請簡易\n    判決處刑書之記載（如附件）。\n二、核被告蕭三奇所為，係犯政府採購法第87條第5 項前段之妨\n    害投標罪；被告黃啟榮所為，係犯同法第87條第5 項後段之\n    妨害投標罪；被告陽明營造股份有限公司係犯同法第92條之\n    罪。爰審酌被告蕭三奇係專校畢業、被告黃啟榮係大學畢業\n    之智識程度，被告黃啟榮並為被告陽明營造股份有限公司之\n    實際負責人，被告蕭三奇則為三奇營造有限公司之負責人，\n    其明知三奇營造有限公司不符合嘉義縣政府所辦理之栗子倫\n    西崙村排水工程之投標資格，為達承作該工程之目的，乃借\n    用陽明營造股份有限公司之名義及證件予以投標且得標，而\n    被告黃啟榮則容許他人借用陽明營造股份有限公司之名義及\n    證件投標，均意圖影響投標結果、獲取不當利益，而被告蕭\n    三奇係起意之人，且立於指揮地位，行為惡性較重，復參以\n    被告蕭三奇、黃啟榮2 人犯後均坦承犯行之態度，以及本件\n    犯罪所生之危害等一切情狀，分別量處被告蕭三奇有期徒刑\n    4 月、被告黃啟榮有期徒刑3 月，並均諭知如易科罰金，均\n    以新臺幣1,000 元折算1 日之標準，被告陽明營造股份有限\n    公司則科以罰金新臺幣5 萬元，以資儆懲。另被告蕭三奇前\n    未曾受有期徒刑以上刑之宣告，有臺灣高等法院被告前案紀\n    錄表1 紙可憑，其因一時失慮，偶罹刑章，經此起訴審判之\n    教訓，當知所警惕，信無再犯之虞，本院認所宣告之刑，以\n    暫不執行為適當，依刑法第74條第1 款宣告緩刑2 年，以啟\n    自新。\n三、依刑事訴訟法第449 條第1 項前段、第454 條第2 項，政府\n    採購法第87條第5 項前段、後段、第92條，刑法第11條前段\n    、第41條第1 項前段、第74條第1 項第1 款，逕以簡易判決\n    處刑如主文。\n四、如不服本判決，得自收受送達之日起10日內，向本院提起上\n    訴（應附繕本）。\n中    華    民    國   100    年    11    月    7    日\n                  嘉義簡易庭    法  官  周欣怡\n上列正本證明與原本無異。\n如不服本判決，應於判決送達後10日內向本院提出上訴狀（應附\n繕本）。告訴人或被害人如對於本判決不服者，應具備理由請求\n檢察官上訴，其上訴期間之計算係以檢察官收受判決正本之日期\n為準。\n中    華    民    國   100    年    11    月    7     日\n                                書記官  柯于婷\n附錄本案論罪科刑法條全文：\n政府採購法第87條第5項\n意圖影響採購結果或獲取不當利益，而借用他人名義或證件投標\n者，處3 年以下有期徒刑，得併科新臺幣1 百萬元以下罰金。容\n許他人借用本人名義或證件參加投標者，亦同。\n政府採購法第92條\n廠商之代表人、代理人、受雇人或其他從業人員，因執行業務犯\n本法之罪者，除依該條規定處罰其行為人外，對該廠商亦科以該\n條之罰金。",
  "structure": {
    "main": "蕭三奇犯政府採購法第八十七條第五項前段之妨害投標罪，處有\n期徒刑肆月，如易科罰金，以新臺幣壹仟元折算壹日。緩刑貳年\n。\n黃啟榮犯政府採購法第八十七條第五項後段之妨害投標罪，處有\n期徒刑月，如易科罰金，以新臺幣壹仟元折算壹日。\n陽明營造股份有限公司因公司之代表人執行業務犯政府採購法第\n八十七條第五項後段之妨害投標罪，科罰金新臺幣伍萬元。",
    "fact": "一、本件犯罪事實及證據，除證據部分應補充「公司及分公司基\n    本資料查詢（明細）1 紙」外，其餘均引用檢察官聲請簡易\n    判決處刑書之記載（如附件）。\n二、核被告蕭三奇所為，係犯政府採購法第87條第5 項前段之妨\n    害投標罪；被告黃啟榮所為，係犯同法第87條第5 項後段之\n    妨害投標罪；被告陽明營造股份有限公司係犯同法第92條之\n    罪。爰審酌被告蕭三奇係專校畢業、被告黃啟榮係大學畢業\n    之智識程度，被告黃啟榮並為被告陽明營造股份有限公司之\n    實際負責人，被告蕭三奇則為三奇營造有限公司之負責人，\n    其明知三奇營造有限公司不符合嘉義縣政府所辦理之栗子倫\n    西崙村排水工程之投標資格，為達承作該工程之目的，乃借\n    用陽明營造股份有限公司之名義及證件予以投標且得標，而\n    被告黃啟榮則容許他人借用陽明營造股份有限公司之名義及\n    證件投標，均意圖影響投標結果、獲取不當利益，而被告蕭\n    三奇係起意之人，且立於指揮地位，行為惡性較重，復參以\n    被告蕭三奇、黃啟榮2 人犯後均坦承犯行之態度，以及本件\n    犯罪所生之危害等一切情狀，分別量處被告蕭三奇有期徒刑\n    4 月、被告黃啟榮有期徒刑3 月，並均諭知如易科罰金，均\n    以新臺幣1,000 元折算1 日之標準，被告陽明營造股份有限\n    公司則科以罰金新臺幣5 萬元，以資儆懲。另被告蕭三奇前\n    未曾受有期徒刑以上刑之宣告，有臺灣高等法院被告前案紀\n    錄表1 紙可憑，其因一時失慮，偶罹刑章，經此起訴審判之\n    教訓，當知所警惕，信無再犯之虞，本院認所宣告之刑，以\n    暫不執行為適當，依刑法第74條第1 款宣告緩刑2 年，以啟\n    自新。\n三、依刑事訴訟法第449 條第1 項前段、第454 條第2 項，政府\n    採購法第87條第5 項前段、後段、第92條，刑法第11條前段\n    、第41條第1 項前段、第74條第1 項第1 款，逕以簡易判決\n    處刑如主文。\n四、如不服本判決，得自收受送達之日起10日內，向本院提起上\n    訴（應附繕本）。",
    "reason": "一、本件犯罪事實及證據，除證據部分應補充「公司及分公司基\n    本資料查詢（明細）1 紙」外，其餘均引用檢察官聲請簡易\n    判決處刑書之記載（如附件）。\n二、核被告蕭三奇所為，係犯政府採購法第87條第5 項前段之妨\n    害投標罪；被告黃啟榮所為，係犯同法第87條第5 項後段之\n    妨害投標罪；被告陽明營造股份有限公司係犯同法第92條之\n    罪。爰審酌被告蕭三奇係專校畢業、被告黃啟榮係大學畢業\n    之智識程度，被告黃啟榮並為被告陽明營造股份有限公司之\n    實際負責人，被告蕭三奇則為三奇營造有限公司之負責人，\n    其明知三奇營造有限公司不符合嘉義縣政府所辦理之栗子倫\n    西崙村排水工程之投標資格，為達承作該工程之目的，乃借\n    用陽明營造股份有限公司之名義及證件予以投標且得標，而\n    被告黃啟榮則容許他人借用陽明營造股份有限公司之名義及\n    證件投標，均意圖影響投標結果、獲取不當利益，而被告蕭\n    三奇係起意之人，且立於指揮地位，行為惡性較重，復參以\n    被告蕭三奇、黃啟榮2 人犯後均坦承犯行之態度，以及本件\n    犯罪所生之危害等一切情狀，分別量處被告蕭三奇有期徒刑\n    4 月、被告黃啟榮有期徒刑3 月，並均諭知如易科罰金，均\n    以新臺幣1,000 元折算1 日之標準，被告陽明營造股份有限\n    公司則科以罰金新臺幣5 萬元，以資儆懲。另被告蕭三奇前\n    未曾受有期徒刑以上刑之宣告，有臺灣高等法院被告前案紀\n    錄表1 紙可憑，其因一時失慮，偶罹刑章，經此起訴審判之\n    教訓，當知所警惕，信無再犯之虞，本院認所宣告之刑，以\n    暫不執行為適當，依刑法第74條第1 款宣告緩刑2 年，以啟\n    自新。\n三、依刑事訴訟法第449 條第1 項前段、第454 條第2 項，政府\n    採購法第87條第5 項前段、後段、第92條，刑法第11條前段\n    、第41條第1 項前段、第74條第1 項第1 款，逕以簡易判決\n    處刑如主文。\n四、如不服本判決，得自收受送達之日起10日內，向本院提起上\n    訴（應附繕本）。"
  },
  "search": "臺灣嘉義地方法院刑事簡易判決100年度嘉簡字第1530號聲請人臺灣嘉義地方法院檢察署檢察官被告蕭三奇黃啟榮陽明營造股份有限公司上一人代表人黃龍泉上列被告因違反政府採購法案件，經檢察官聲請簡易判決處刑（100年度偵字第4115號），本院逕以簡易判決如下：主文蕭三奇犯政府採購法第八十七條第五項前段之妨害投標罪，處有期徒刑肆月，如易科罰金，以新臺幣壹仟元折算壹日。緩刑貳年。黃啟榮犯政府採購法第八十七條第五項後段之妨害投標罪，處有期徒刑月，如易科罰金，以新臺幣壹仟元折算壹日。陽明營造股份有限公司因公司之代表人執行業務犯政府採購法第八十七條第五項後段之妨害投標罪，科罰金新臺幣伍萬元。事實及理由一、本件犯罪事實及證據，除證據部分應補充「公司及分公司基本資料查詢（明細）1紙」外，其餘均引用檢察官聲請簡易判決處刑書之記載（如附件）。二、核被告蕭三奇所為，係犯政府採購法第87條第5項前段之妨害投標罪；被告黃啟榮所為，係犯同法第87條第5項後段之妨害投標罪；被告陽明營造股份有限公司係犯同法第92條之罪。爰審酌被告蕭三奇係專校畢業、被告黃啟榮係大學畢業之智識程度，被告黃啟榮並為被告陽明營造股份有限公司之實際負責人，被告蕭三奇則為三奇營造有限公司之負責人，其明知三奇營造有限公司不符合嘉義縣政府所辦理之栗子倫西崙村排水工程之投標資格，為達承作該工程之目的，乃借用陽明營造股份有限公司之名義及證件予以投標且得標，而被告黃啟榮則容許他人借用陽明營造股份有限公司之名義及證件投標，均意圖影響投標結果、獲取不當利益，而被告蕭三奇係起意之人，且立於指揮地位，行為惡性較重，復參以被告蕭三奇、黃啟榮2人犯後均坦承犯行之態度，以及本件犯罪所生之危害等一切情狀，分別量處被告蕭三奇有期徒刑4月、被告黃啟榮有期徒刑3月，並均諭知如易科罰金，均以新臺幣1,000元折算1日之標準，被告陽明營造股份有限公司則科以罰金新臺幣5萬元，以資儆懲。另被告蕭三奇前未曾受有期徒刑以上刑之宣告，有臺灣高等法院被告前案紀錄表1紙可憑，其因一時失慮，偶罹刑章，經此起訴審判之教訓，當知所警惕，信無再犯之虞，本院認所宣告之刑，以暫不執行為適當，依刑法第74條第1款宣告緩刑2年，以啟自新。三、依刑事訴訟法第449條第1項前段、第454條第2項，政府採購法第87條第5項前段、後段、第92條，刑法第11條前段、第41條第1項前段、第74條第1項第1款，逕以簡易判決處刑如主文。四、如不服本判決，得自收受送達之日起10日內，向本院提起上訴（應附繕本）。中華民國100年11月7日嘉義簡易庭法官周欣怡上列正本證明與原本無異。如不服本判決，應於判決送達後10日內向本院提出上訴狀（應附繕本）。告訴人或被害人如對於本判決不服者，應具備理由請求檢察官上訴，其上訴期間之計算係以檢察官收受判決正本之日期為準。中華民國100年11月7日書記官柯于婷附錄本案論罪科刑法條全文：政府採購法第87條第5項意圖影響採購結果或獲取不當利益，而借用他人名義或證件投標者，處3年以下有期徒刑，得併科新臺幣1百萬元以下罰金。容許他人借用本人名義或證件參加投標者，亦同。政府採購法第92條廠商之代表人、代理人、受雇人或其他從業人員，因執行業務犯本法之罪者，除依該條規定處罰其行為人外，對該廠商亦科以該條之罰金。",
  "characters": {
    "judges": [
      "周欣怡"
    ],
    "prosecutors": [

    ],
    "lawyers": [

    ],
    "clerks": [
      "柯于婷"
    ],
    "plaintiffs": [

    ],
    "defendants": [
      "蕭三奇"
    ],
    "prosecutor_office": [
      "臺灣嘉義地方法院檢察署檢察官"
    ],
    "creditors": [

    ],
    "debtors": [

    ],
    "judicial_associate_officer": [

    ]
  },
  "adjudged_at": "2011-11-07",
  "created_at": "2016-02-13 00:49:31",
  "updated_at": "2016-02-13 00:49:31"
}