{
  "identify": "KSD-100-簡-5908-20111108-1",
  "court": {
    "name": "臺灣高雄地方法院",
    "code": "KSD"
  },
  "division": {
    "name": "刑事",
    "code": "M"
  },
  "year": 100,
  "word": "簡",
  "number": "5908",
  "jcheck": "1",
  "reason": "竊盜",
  "content": "臺灣高雄地方法院刑事簡易判決         100年度簡字第5908號\n聲  請  人  臺灣高雄地方法院檢察署檢察官\n被      告  林聖富\n上列被告因竊盜案件，經檢察官聲請以簡易判決處刑（100 年度\n偵字第27337 號），本院判決如下：\n    主  文\n林聖富犯踰越安全設備竊盜罪，處有期徒刑陸月，如易科罰金，\n以新臺幣壹仟元折算壹日。\n    事實及理由\n一、本件犯罪事實及證據，除犯罪事實一、第3行「翻越工地建\n    築圍籬後，徒手竊取…」補充為「翻越工地建築圍籬，以此\n    方式踰越安全設備進入工地後，徒手竊取…」外，餘均引用\n    檢察官聲請簡易判決處刑書之記載（如附件）。\n二、按刑法第321 條第1 項第2 款規定將「門扇」、「牆垣」、\n    「其他安全設備」並列，則所謂「門扇」專指門戶而言，應\n    屬狹義，僅指分隔住宅或建築物內外之間之出入口大門而言\n    ；而所謂「其他安全設備」，指門扇牆垣以外，依通常觀念\n    足認防盜之一切設備而言。查被告於聲請簡易判決處刑書所\n    載之時、地翻越工地圍籬進入工地內，竊取聲請簡易判決處\n    刑書所載之物品，而該工地圍籬前有大門上鎖以管制出入，\n    此經告訴人即本件案發地點之工地負責人曾耀輝證述明確，\n    揆諸上開說明，該工地圍籬應屬「其他安全設備」無訛，是\n    核其所為，係犯刑法第321 條第1 項第2 款之踰越安全設備\n    竊盜罪。聲請簡易判決處刑意旨認被告上開行為係犯刑法第\n    320 條第1 項之普通竊盜罪，容有誤會，惟基於訴追之基本\n    社會事實同一，且已於審理中踐履告知被告變更罪名暨加重\n    竊盜罪之法定本刑之義務，本院自得就本件予以審理，並依\n    刑事訴訟法第300 條規定變更起訴法條，附此敘明。爰審酌\n    被告正值壯年，不思以正當方法謀取生活上所需，竟為貪圖\n    不法利益，率爾侵入他人工地竊取物品，其犯罪之動機、手\n    段、目的均非可取，惟念其坦承犯行，深具悔意，又無刑事\n    前科紀錄，且所竊得之財物價值非鉅（據被害人陳稱價值約\n    新臺幣6,000 元），並業經告訴人領回，此有贓物認領保管\n    單1 紙在卷可憑，犯罪所生損害已稍有減輕，兼衡其學歷為\n    國中畢業、經濟狀況為勉持等一切情狀，量處如主文所示之\n    刑，並諭知易科罰金之折算標準，以資懲儆。\n三、依刑事訴訟法第449 條第1 項後段、第3 項、第454 條第2\n    項、第300 條，刑法第321 條第1 項第2 款、第41條第1 項\n    前段，刑法施行法第1 條之1 第1 項、第2 項前段，逕以簡\n    易判決處刑如主文。\n四、如不服本件判決，得自收受送達之日起10日內，向本院提起\n    上訴狀，上訴於本院管轄之第二審地方法院合議庭。\n中    華    民    國  100     年    11    月    8     日\n                   高雄簡易庭   法  官  黃右萱\n以上正本證明與原本無異。\n如不服本判決應於判決送達之日起10日內向本院提出上訴書狀。\n\n中    華    民    國  100    年     11    月    8     日\n                                書記官  馮欽鳳\n附錄本判決論罪之法條：\n中華民國刑法第321條第1項第2款\n犯竊盜罪而有左列情形之一者，處6月以上、5年以下有期徒刑：\n二  毀越門扇、牆垣或其他安全設備而犯之者。\n附件：\n臺灣高雄地方法院檢察署檢察官聲請簡易判決處刑書\n                                    100年度偵字第27337號\n    被      告  林聖富  男  27歲（民國○○年○○月○日生）\n                        住高雄市仁武區○○○路216號\n                        國民身分證統一編號：Ｚ000000000號\n上列被告因竊盜案件，業經偵查終結，認為宜聲請以簡易判決處\n刑，茲敘述犯罪事實及證據並所犯法條如下：\n        犯罪事實\n一、林聖富於民國100年9月17日凌晨0時20分許，行經高雄市○\n    ○區○○街與大春三街口旁工地，竟臨時起意，意圖為自己\n    不法之所有，翻越工地建築圍籬後，徒手竊取曾耀輝所有之\n    噴燈1支、鐵鎚2支、活動板手3支、水管剪1支、鋼筋40支及\n    配線盒9個（約值新臺幣6000元）得逞。嗣經曾耀輝當場發\n    覺後以現行犯逮捕，並通知員警到場處理。\n二、案經曾耀輝訴由高雄市政府警察局仁武分局報告偵辦。\n        證據並所犯法條\n一、上開犯罪事實，業據被告林聖富於警詢及偵查中供承不諱，\n    核與告訴人曾耀輝在警詢時指述之情節相符，且有贓物認領\n    保管收據及現場照片在卷可資佐證，被告犯嫌堪以認定。\n二、核被告所為，係犯刑法第320條第1項之普通竊盜罪嫌。\n三、依刑事訴訟法第451條第1項聲請逕以簡易判決處刑。\n    此  致\n臺灣高雄地方法院\n中    華    民    國   100    年    9     月    29    日\n                          檢  察  官   黃  俊  嘉\n                          檢  察  官   張  家  芳",
  "structure": {
    "main": "林聖富犯踰越安全設備竊盜罪，處有期徒刑陸月，如易科罰金，\n以新臺幣壹仟元折算壹日。",
    "fact": "一、本件犯罪事實及證據，除犯罪事實一、第3行「翻越工地建\n    築圍籬後，徒手竊取…」補充為「翻越工地建築圍籬，以此\n    方式踰越安全設備進入工地後，徒手竊取…」外，餘均引用\n    檢察官聲請簡易判決處刑書之記載（如附件）。\n二、按刑法第321 條第1 項第2 款規定將「門扇」、「牆垣」、\n    「其他安全設備」並列，則所謂「門扇」專指門戶而言，應\n    屬狹義，僅指分隔住宅或建築物內外之間之出入口大門而言\n    ；而所謂「其他安全設備」，指門扇牆垣以外，依通常觀念\n    足認防盜之一切設備而言。查被告於聲請簡易判決處刑書所\n    載之時、地翻越工地圍籬進入工地內，竊取聲請簡易判決處\n    刑書所載之物品，而該工地圍籬前有大門上鎖以管制出入，\n    此經告訴人即本件案發地點之工地負責人曾耀輝證述明確，\n    揆諸上開說明，該工地圍籬應屬「其他安全設備」無訛，是\n    核其所為，係犯刑法第321 條第1 項第2 款之踰越安全設備\n    竊盜罪。聲請簡易判決處刑意旨認被告上開行為係犯刑法第\n    320 條第1 項之普通竊盜罪，容有誤會，惟基於訴追之基本\n    社會事實同一，且已於審理中踐履告知被告變更罪名暨加重\n    竊盜罪之法定本刑之義務，本院自得就本件予以審理，並依\n    刑事訴訟法第300 條規定變更起訴法條，附此敘明。爰審酌\n    被告正值壯年，不思以正當方法謀取生活上所需，竟為貪圖\n    不法利益，率爾侵入他人工地竊取物品，其犯罪之動機、手\n    段、目的均非可取，惟念其坦承犯行，深具悔意，又無刑事\n    前科紀錄，且所竊得之財物價值非鉅（據被害人陳稱價值約\n    新臺幣6,000 元），並業經告訴人領回，此有贓物認領保管\n    單1 紙在卷可憑，犯罪所生損害已稍有減輕，兼衡其學歷為\n    國中畢業、經濟狀況為勉持等一切情狀，量處如主文所示之\n    刑，並諭知易科罰金之折算標準，以資懲儆。\n三、依刑事訴訟法第449 條第1 項後段、第3 項、第454 條第2\n    項、第300 條，刑法第321 條第1 項第2 款、第41條第1 項\n    前段，刑法施行法第1 條之1 第1 項、第2 項前段，逕以簡\n    易判決處刑如主文。\n四、如不服本件判決，得自收受送達之日起10日內，向本院提起\n    上訴狀，上訴於本院管轄之第二審地方法院合議庭。",
    "reason": "一、本件犯罪事實及證據，除犯罪事實一、第3行「翻越工地建\n    築圍籬後，徒手竊取…」補充為「翻越工地建築圍籬，以此\n    方式踰越安全設備進入工地後，徒手竊取…」外，餘均引用\n    檢察官聲請簡易判決處刑書之記載（如附件）。\n二、按刑法第321 條第1 項第2 款規定將「門扇」、「牆垣」、\n    「其他安全設備」並列，則所謂「門扇」專指門戶而言，應\n    屬狹義，僅指分隔住宅或建築物內外之間之出入口大門而言\n    ；而所謂「其他安全設備」，指門扇牆垣以外，依通常觀念\n    足認防盜之一切設備而言。查被告於聲請簡易判決處刑書所\n    載之時、地翻越工地圍籬進入工地內，竊取聲請簡易判決處\n    刑書所載之物品，而該工地圍籬前有大門上鎖以管制出入，\n    此經告訴人即本件案發地點之工地負責人曾耀輝證述明確，\n    揆諸上開說明，該工地圍籬應屬「其他安全設備」無訛，是\n    核其所為，係犯刑法第321 條第1 項第2 款之踰越安全設備\n    竊盜罪。聲請簡易判決處刑意旨認被告上開行為係犯刑法第\n    320 條第1 項之普通竊盜罪，容有誤會，惟基於訴追之基本\n    社會事實同一，且已於審理中踐履告知被告變更罪名暨加重\n    竊盜罪之法定本刑之義務，本院自得就本件予以審理，並依\n    刑事訴訟法第300 條規定變更起訴法條，附此敘明。爰審酌\n    被告正值壯年，不思以正當方法謀取生活上所需，竟為貪圖\n    不法利益，率爾侵入他人工地竊取物品，其犯罪之動機、手\n    段、目的均非可取，惟念其坦承犯行，深具悔意，又無刑事\n    前科紀錄，且所竊得之財物價值非鉅（據被害人陳稱價值約\n    新臺幣6,000 元），並業經告訴人領回，此有贓物認領保管\n    單1 紙在卷可憑，犯罪所生損害已稍有減輕，兼衡其學歷為\n    國中畢業、經濟狀況為勉持等一切情狀，量處如主文所示之\n    刑，並諭知易科罰金之折算標準，以資懲儆。\n三、依刑事訴訟法第449 條第1 項後段、第3 項、第454 條第2\n    項、第300 條，刑法第321 條第1 項第2 款、第41條第1 項\n    前段，刑法施行法第1 條之1 第1 項、第2 項前段，逕以簡\n    易判決處刑如主文。\n四、如不服本件判決，得自收受送達之日起10日內，向本院提起\n    上訴狀，上訴於本院管轄之第二審地方法院合議庭。"
  },
  "search": "臺灣高雄地方法院刑事簡易判決100年度簡字第5908號聲請人臺灣高雄地方法院檢察署檢察官被告林聖富上列被告因竊盜案件，經檢察官聲請以簡易判決處刑（100年度偵字第27337號），本院判決如下：主文林聖富犯踰越安全設備竊盜罪，處有期徒刑陸月，如易科罰金，以新臺幣壹仟元折算壹日。事實及理由一、本件犯罪事實及證據，除犯罪事實一、第3行「翻越工地建築圍籬後，徒手竊取…」補充為「翻越工地建築圍籬，以此方式踰越安全設備進入工地後，徒手竊取…」外，餘均引用檢察官聲請簡易判決處刑書之記載（如附件）。二、按刑法第321條第1項第2款規定將「門扇」、「牆垣」、「其他安全設備」並列，則所謂「門扇」專指門戶而言，應屬狹義，僅指分隔住宅或建築物內外之間之出入口大門而言；而所謂「其他安全設備」，指門扇牆垣以外，依通常觀念足認防盜之一切設備而言。查被告於聲請簡易判決處刑書所載之時、地翻越工地圍籬進入工地內，竊取聲請簡易判決處刑書所載之物品，而該工地圍籬前有大門上鎖以管制出入，此經告訴人即本件案發地點之工地負責人曾耀輝證述明確，揆諸上開說明，該工地圍籬應屬「其他安全設備」無訛，是核其所為，係犯刑法第321條第1項第2款之踰越安全設備竊盜罪。聲請簡易判決處刑意旨認被告上開行為係犯刑法第320條第1項之普通竊盜罪，容有誤會，惟基於訴追之基本社會事實同一，且已於審理中踐履告知被告變更罪名暨加重竊盜罪之法定本刑之義務，本院自得就本件予以審理，並依刑事訴訟法第300條規定變更起訴法條，附此敘明。爰審酌被告正值壯年，不思以正當方法謀取生活上所需，竟為貪圖不法利益，率爾侵入他人工地竊取物品，其犯罪之動機、手段、目的均非可取，惟念其坦承犯行，深具悔意，又無刑事前科紀錄，且所竊得之財物價值非鉅（據被害人陳稱價值約新臺幣6,000元），並業經告訴人領回，此有贓物認領保管單1紙在卷可憑，犯罪所生損害已稍有減輕，兼衡其學歷為國中畢業、經濟狀況為勉持等一切情狀，量處如主文所示之刑，並諭知易科罰金之折算標準，以資懲儆。三、依刑事訴訟法第449條第1項後段、第3項、第454條第2項、第300條，刑法第321條第1項第2款、第41條第1項前段，刑法施行法第1條之1第1項、第2項前段，逕以簡易判決處刑如主文。四、如不服本件判決，得自收受送達之日起10日內，向本院提起上訴狀，上訴於本院管轄之第二審地方法院合議庭。中華民國100年11月8日高雄簡易庭法官黃右萱以上正本證明與原本無異。如不服本判決應於判決送達之日起10日內向本院提出上訴書狀。中華民國100年11月8日書記官馮欽鳳附錄本判決論罪之法條：中華民國刑法第321條第1項第2款犯竊盜罪而有左列情形之一者，處6月以上、5年以下有期徒刑：二毀越門扇、牆垣或其他安全設備而犯之者。附件：臺灣高雄地方法院檢察署檢察官聲請簡易判決處刑書100年度偵字第27337號被告林聖富男27歲（民國○○年○○月○日生）住高雄市仁武區○○○路216號國民身分證統一編號：Ｚ000000000號上列被告因竊盜案件，業經偵查終結，認為宜聲請以簡易判決處刑，茲敘述犯罪事實及證據並所犯法條如下：犯罪事實一、林聖富於民國100年9月17日凌晨0時20分許，行經高雄市○○區○○街與大春三街口旁工地，竟臨時起意，意圖為自己不法之所有，翻越工地建築圍籬後，徒手竊取曾耀輝所有之噴燈1支、鐵鎚2支、活動板手3支、水管剪1支、鋼筋40支及配線盒9個（約值新臺幣6000元）得逞。嗣經曾耀輝當場發覺後以現行犯逮捕，並通知員警到場處理。二、案經曾耀輝訴由高雄市政府警察局仁武分局報告偵辦。證據並所犯法條一、上開犯罪事實，業據被告林聖富於警詢及偵查中供承不諱，核與告訴人曾耀輝在警詢時指述之情節相符，且有贓物認領保管收據及現場照片在卷可資佐證，被告犯嫌堪以認定。二、核被告所為，係犯刑法第320條第1項之普通竊盜罪嫌。三、依刑事訴訟法第451條第1項聲請逕以簡易判決處刑。此致臺灣高雄地方法院中華民國100年9月29日檢察官黃俊嘉檢察官張家芳",
  "characters": {
    "judges": [
      "黃右萱"
    ],
    "prosecutors": [

    ],
    "lawyers": [

    ],
    "clerks": [
      "馮欽鳳"
    ],
    "plaintiffs": [

    ],
    "defendants": [
      "林聖富",
      "林聖富  男  27歲（民國○○年○○月○日生）"
    ],
    "prosecutor_office": [
      "臺灣高雄地方法院檢察署檢察官"
    ],
    "creditors": [

    ],
    "debtors": [

    ],
    "judicial_associate_officer": [

    ]
  },
  "adjudged_at": "2011-11-08",
  "created_at": "2016-02-13 00:39:21",
  "updated_at": "2016-02-13 00:39:21"
}