{
  "identify": "TPH-100-毒抗-328-20111107-1",
  "court": {
    "name": "臺灣高等法院",
    "code": "TPH"
  },
  "division": {
    "name": "刑事",
    "code": "M"
  },
  "year": 100,
  "word": "毒抗",
  "number": "328",
  "jcheck": "1",
  "reason": "毒品危害防制條例",
  "content": "臺灣高等法院刑事裁定                100年度毒抗字第328號\n抗  告  人\n即  被  告    張文生\n上列抗告人因違反毒品危害防制條例案件，不服臺灣板橋地方法\n院，中華民國100年10月11日觀察勒戒裁定（100年度毒聲字第90\n1號），提起抗告，本院裁定如下：\n    主  文\n抗告駁回。\n    理  由\n一、本件聲請意旨略以：被告張文生基於施用第二級毒品甲基安\n    非他命之犯意，於民國（下同）100年8月22日上午6時許，\n    在新北市○○區○○路560號新北市立殯儀館旁之工地，施\n    用第二級毒品甲基安非他命1次；嗣張文生於同日下午3時許\n    ，在新北市○○區○○路1段大同橋前為警查獲，其尿液送\n    檢驗呈安非他命類陽性反應，有濫用藥物檢驗報告附卷可稽\n    ，爰依毒品危害防制條例第20條第1項及觀察勒戒處分執行\n    條例第3條第1項規定，聲請裁定將被告送勒戒處所觀察、勒\n    戒等語。\n二、原裁定意旨略以：查被告張文生於上揭時地經警查獲後採得\n    之尿液檢體，經送臺灣檢驗科技股份有限公司以酵素免疫分\n    析法（EIA）初驗及以氣相層析質譜儀法（GC/MS）複驗檢驗\n    結果，呈安非他命類甲基安非他命陽性反應，有該公司100\n    年9月6日濫用藥物檢驗報告1紙在卷可稽。按甲基安非他命\n    經口服投與後約70%於24小時內自尿中排出，約90%於96小時\n    內自尿中排出，由於安非他命成分之檢出與其投與方式、投\n    與量、個人體質、採尿時間與檢測儀器之精密度等諸多因素\n    有關，因此僅憑尿液中呈安非他命陽性反應，並無法確實推\n    算吸食時間距採集時間之長短，惟依上述資料推斷，最長可\n    能不會超過4日，亦經行政院衛生署藥物食品檢驗局81年2月\n    8日（81）藥檢壹字第001156號函示明確。被告上開所採尿\n    液送驗結果既有安非他命類之陽性反應，且該結果係採用氣\n    相層析質譜儀法進行確認，已足排除被告因服用藥物導致呈\n    毒品偽陽性反應之可能，顯見被告在經警採尿前96小時內某\n    時點，確曾有施用第二級毒品甲基安非他命之事實。從而，\n    聲請人聲請將被告送勒戒處所觀察、勒戒，其聲請應予准許\n    。爰依毒品危害防制條例第20條第1項及觀察勒戒處分執行\n    條例第3條第1項，裁定被告張文生施用第二級毒品，應送勒\n    戒處所觀察、勒戒。\n三、本件抗告意旨略以：抗告人即被告患有食道癌腫瘤，需每天\n    至醫院接受放射合併化學治療。抗告人前因罹癌終日疼痛，\n    遂施用毒品以求降低身體痛楚，實非得己。若抗告人如進勒\n    戒處所執行觀察勒戒，恐因無法持續治療腫瘤，有害生命安\n    全，爰請求裁定免為執行云云。\n四、經查：\n（一）按犯毒品危害防制條例第10條之罪者，檢察官應聲請法院\n      裁定，或少年法院（地方法院少年法庭）應先裁定，令被\n      告或少年入勒戒處所觀察、勒戒，其期間不得逾2月，同\n      條例第20條第1項定有明文。\n（二）被告張文生基於施用第二級毒品甲基安非他命之犯意，於\n      100年8月22日上午6時許，在新北市○○區○○路560號新\n      北市立殯儀館旁之工地，施用第二級毒品甲基安非他命1\n      次；嗣張文生於同日下午3時許，在新北市○○區○○路1\n      段大同橋前為警查獲，其尿液送檢驗呈安非他命類陽性反\n      應，有前開濫用藥物檢驗報告附卷可稽，稽上各情，足認\n      被告施用第二級毒品犯行，事證明確。又毒品危害防制條\n      例第20條第1項規定係法定之強制處分程序，並無裁量餘\n      地，是被告抗告意旨以身體健康因素等詞為辯，尚無理由\n      ，應予駁回。\n五、綜上，原審以被告有施用第二級毒品之犯行，事證明確，依\n    毒品危害防制條例第20條第1項、觀察勒戒處分執行條例第3\n    條第1項之規定，裁定將被告送勒戒處所觀察、勒戒，經核\n    並無違誤，抗告意旨請求免予執行，並無理由，應予駁回。\n據上論斷，應依刑事訴訟法第412條，裁定如主文。\n中    華    民    國   100    年    11    月    7     日\n                  刑事第二十五庭審判長法  官  黃瑞華\n                                      法  官  許文章\n                                      法  官  高玉舜\n以上正本證明與原本無異。\n不得再抗告。\n                                      書記官  許雅淩\n中    華    民    國   100    年    11    月    7     日",
  "structure": {
    "main": "抗告駁回。",
    "reason": "一、本件聲請意旨略以：被告張文生基於施用第二級毒品甲基安\n    非他命之犯意，於民國（下同）100年8月22日上午6時許，\n    在新北市○○區○○路560號新北市立殯儀館旁之工地，施\n    用第二級毒品甲基安非他命1次；嗣張文生於同日下午3時許\n    ，在新北市○○區○○路1段大同橋前為警查獲，其尿液送\n    檢驗呈安非他命類陽性反應，有濫用藥物檢驗報告附卷可稽\n    ，爰依毒品危害防制條例第20條第1項及觀察勒戒處分執行\n    條例第3條第1項規定，聲請裁定將被告送勒戒處所觀察、勒\n    戒等語。\n二、原裁定意旨略以：查被告張文生於上揭時地經警查獲後採得\n    之尿液檢體，經送臺灣檢驗科技股份有限公司以酵素免疫分\n    析法（EIA）初驗及以氣相層析質譜儀法（GC/MS）複驗檢驗\n    結果，呈安非他命類甲基安非他命陽性反應，有該公司100\n    年9月6日濫用藥物檢驗報告1紙在卷可稽。按甲基安非他命\n    經口服投與後約70%於24小時內自尿中排出，約90%於96小時\n    內自尿中排出，由於安非他命成分之檢出與其投與方式、投\n    與量、個人體質、採尿時間與檢測儀器之精密度等諸多因素\n    有關，因此僅憑尿液中呈安非他命陽性反應，並無法確實推\n    算吸食時間距採集時間之長短，惟依上述資料推斷，最長可\n    能不會超過4日，亦經行政院衛生署藥物食品檢驗局81年2月\n    8日（81）藥檢壹字第001156號函示明確。被告上開所採尿\n    液送驗結果既有安非他命類之陽性反應，且該結果係採用氣\n    相層析質譜儀法進行確認，已足排除被告因服用藥物導致呈\n    毒品偽陽性反應之可能，顯見被告在經警採尿前96小時內某\n    時點，確曾有施用第二級毒品甲基安非他命之事實。從而，\n    聲請人聲請將被告送勒戒處所觀察、勒戒，其聲請應予准許\n    。爰依毒品危害防制條例第20條第1項及觀察勒戒處分執行\n    條例第3條第1項，裁定被告張文生施用第二級毒品，應送勒\n    戒處所觀察、勒戒。\n三、本件抗告意旨略以：抗告人即被告患有食道癌腫瘤，需每天\n    至醫院接受放射合併化學治療。抗告人前因罹癌終日疼痛，\n    遂施用毒品以求降低身體痛楚，實非得己。若抗告人如進勒\n    戒處所執行觀察勒戒，恐因無法持續治療腫瘤，有害生命安\n    全，爰請求裁定免為執行云云。\n四、經查：\n（一）按犯毒品危害防制條例第10條之罪者，檢察官應聲請法院\n      裁定，或少年法院（地方法院少年法庭）應先裁定，令被\n      告或少年入勒戒處所觀察、勒戒，其期間不得逾2月，同\n      條例第20條第1項定有明文。\n（二）被告張文生基於施用第二級毒品甲基安非他命之犯意，於\n      100年8月22日上午6時許，在新北市○○區○○路560號新\n      北市立殯儀館旁之工地，施用第二級毒品甲基安非他命1\n      次；嗣張文生於同日下午3時許，在新北市○○區○○路1\n      段大同橋前為警查獲，其尿液送檢驗呈安非他命類陽性反\n      應，有前開濫用藥物檢驗報告附卷可稽，稽上各情，足認\n      被告施用第二級毒品犯行，事證明確。又毒品危害防制條\n      例第20條第1項規定係法定之強制處分程序，並無裁量餘\n      地，是被告抗告意旨以身體健康因素等詞為辯，尚無理由\n      ，應予駁回。\n五、綜上，原審以被告有施用第二級毒品之犯行，事證明確，依\n    毒品危害防制條例第20條第1項、觀察勒戒處分執行條例第3\n    條第1項之規定，裁定將被告送勒戒處所觀察、勒戒，經核\n    並無違誤，抗告意旨請求免予執行，並無理由，應予駁回。\n據上論斷，應依刑事訴訟法第412條，裁定如主文。"
  },
  "search": "臺灣高等法院刑事裁定100年度毒抗字第328號抗告人即被告張文生上列抗告人因違反毒品危害防制條例案件，不服臺灣板橋地方法院，中華民國100年10月11日觀察勒戒裁定（100年度毒聲字第901號），提起抗告，本院裁定如下：主文抗告駁回。理由一、本件聲請意旨略以：被告張文生基於施用第二級毒品甲基安非他命之犯意，於民國（下同）100年8月22日上午6時許，在新北市○○區○○路560號新北市立殯儀館旁之工地，施用第二級毒品甲基安非他命1次；嗣張文生於同日下午3時許，在新北市○○區○○路1段大同橋前為警查獲，其尿液送檢驗呈安非他命類陽性反應，有濫用藥物檢驗報告附卷可稽，爰依毒品危害防制條例第20條第1項及觀察勒戒處分執行條例第3條第1項規定，聲請裁定將被告送勒戒處所觀察、勒戒等語。二、原裁定意旨略以：查被告張文生於上揭時地經警查獲後採得之尿液檢體，經送臺灣檢驗科技股份有限公司以酵素免疫分析法（EIA）初驗及以氣相層析質譜儀法（GC/MS）複驗檢驗結果，呈安非他命類甲基安非他命陽性反應，有該公司100年9月6日濫用藥物檢驗報告1紙在卷可稽。按甲基安非他命經口服投與後約70%於24小時內自尿中排出，約90%於96小時內自尿中排出，由於安非他命成分之檢出與其投與方式、投與量、個人體質、採尿時間與檢測儀器之精密度等諸多因素有關，因此僅憑尿液中呈安非他命陽性反應，並無法確實推算吸食時間距採集時間之長短，惟依上述資料推斷，最長可能不會超過4日，亦經行政院衛生署藥物食品檢驗局81年2月8日（81）藥檢壹字第001156號函示明確。被告上開所採尿液送驗結果既有安非他命類之陽性反應，且該結果係採用氣相層析質譜儀法進行確認，已足排除被告因服用藥物導致呈毒品偽陽性反應之可能，顯見被告在經警採尿前96小時內某時點，確曾有施用第二級毒品甲基安非他命之事實。從而，聲請人聲請將被告送勒戒處所觀察、勒戒，其聲請應予准許。爰依毒品危害防制條例第20條第1項及觀察勒戒處分執行條例第3條第1項，裁定被告張文生施用第二級毒品，應送勒戒處所觀察、勒戒。三、本件抗告意旨略以：抗告人即被告患有食道癌腫瘤，需每天至醫院接受放射合併化學治療。抗告人前因罹癌終日疼痛，遂施用毒品以求降低身體痛楚，實非得己。若抗告人如進勒戒處所執行觀察勒戒，恐因無法持續治療腫瘤，有害生命安全，爰請求裁定免為執行云云。四、經查：（一）按犯毒品危害防制條例第10條之罪者，檢察官應聲請法院裁定，或少年法院（地方法院少年法庭）應先裁定，令被告或少年入勒戒處所觀察、勒戒，其期間不得逾2月，同條例第20條第1項定有明文。（二）被告張文生基於施用第二級毒品甲基安非他命之犯意，於100年8月22日上午6時許，在新北市○○區○○路560號新北市立殯儀館旁之工地，施用第二級毒品甲基安非他命1次；嗣張文生於同日下午3時許，在新北市○○區○○路1段大同橋前為警查獲，其尿液送檢驗呈安非他命類陽性反應，有前開濫用藥物檢驗報告附卷可稽，稽上各情，足認被告施用第二級毒品犯行，事證明確。又毒品危害防制條例第20條第1項規定係法定之強制處分程序，並無裁量餘地，是被告抗告意旨以身體健康因素等詞為辯，尚無理由，應予駁回。五、綜上，原審以被告有施用第二級毒品之犯行，事證明確，依毒品危害防制條例第20條第1項、觀察勒戒處分執行條例第3條第1項之規定，裁定將被告送勒戒處所觀察、勒戒，經核並無違誤，抗告意旨請求免予執行，並無理由，應予駁回。據上論斷，應依刑事訴訟法第412條，裁定如主文。中華民國100年11月7日刑事第二十五庭審判長法官黃瑞華法官許文章法官高玉舜以上正本證明與原本無異。不得再抗告。書記官許雅淩中華民國100年11月7日",
  "characters": {
    "judges": [
      "黃瑞華",
      "許文章",
      "高玉舜"
    ],
    "prosecutors": [

    ],
    "lawyers": [

    ],
    "clerks": [
      "許雅淩"
    ],
    "plaintiffs": [

    ],
    "defendants": [
      "張文生"
    ],
    "prosecutor_office": [

    ],
    "creditors": [

    ],
    "debtors": [

    ],
    "judicial_associate_officer": [

    ]
  },
  "adjudged_at": "2011-11-07",
  "created_at": "2016-02-13 00:53:14",
  "updated_at": "2016-02-13 00:53:14"
}