{
  "identify": "TYD-100-桃簡-1906-20111107-1",
  "court": {
    "name": "臺灣桃園地方法院",
    "code": "TYD"
  },
  "division": {
    "name": "刑事",
    "code": "M"
  },
  "year": 100,
  "word": "桃簡",
  "number": "1906",
  "jcheck": "1",
  "reason": "頂替",
  "content": "臺灣桃園地方法院刑事簡易判決       100年度桃簡字第1906號\n聲  請  人  臺灣桃園地方法院檢察署檢察官\n被      告  王進寬\n上列被告因頂替案件，經檢察官聲請以簡易判決處刑（100 年度\n速偵字第164 號），本院判決如下：\n    主  文\n王進寬犯頂替罪，處拘役參拾日，如易科罰金，以新臺幣壹仟元\n折算壹日。\n    事實及理由\n一、本件犯罪事實、證據及所犯法條除引用檢察官聲請簡易判決\n    處刑書之記載（如附件）外，並補充：按刑法第164條第1項\n    之藏匿犯人或使之隱避罪，所謂「藏匿犯人」係指藏匿已經\n    犯罪之人而言（本院33年上字第1679號判例）；又此之所謂\n    「犯人」不以起訴後之人為限，為本院所持之見解；故凡觸\n    犯刑罰法規所規定之罪名者，不問其觸犯者係普通法或特別\n    法、實質刑法或形式刑法，只須其為實施犯罪行為之人，且\n    所犯之罪不問已否發覺或起訴或判處罪刑，均屬此之所謂「\n    犯人」（最高法院87年度台上字第757 號判決意旨參照）。\n    查本件王金蟬駕駛車號LF -9542號自用小客車行經桃園縣桃\n    園市○○路與山鶯路交岔路口時，疏未注意與被害人劉致雯\n    騎乘之車號BLB-699 號機車保持安全間隔，逕於左轉之際突\n    往右側駕駛，與騎乘機車行駛在其右側之劉致雯發生擦撞，\n    致劉致雯人車倒地，受有左手肘、左膝擦傷等情，業據被害\n    人劉致雯於警詢時證述詳實，並有道路交通事故現場圖、道\n    路交通事故調查報告表及現場照片在卷可佐，而被害人所受\n    之傷害，亦經本院查明屬實，有行政院國軍退除役官兵輔導\n    委員會桃園榮民醫院100 年9 月27日桃醫醫字第1000006729\n    號函附被害人之病歷摘要可憑，是王金蟬前揭過失傷害犯行\n    ，縱使未經起訴，仍無礙其為刑法第164 條之「犯人」。而\n    被告王進寬意圖使王金蟬隱避而頂替，自係犯刑法第164 條\n    第2 項、第1 項之頂替罪。爰審酌被告犯罪動機、目的、手\n    段、所生之危害及犯後之態度等一切情狀，量處如主文所示\n    之刑，並諭知易科罰金之折算標準，以示懲儆。\n二、依刑事訴訟法第449 條第1 項前段、第454 條第2 項，刑法\n    第164 條第2 項、第1 項、第41條第1 項前段，刑法施行法\n    第1 條之1 第1 項、第2 項前段，逕以簡易判決處如主文所\n    示之刑。\n如不服本判決，得於判決書送達之翌日起10日內，以書狀敘述理\n由，向本庭提出上訴。\n中    華    民    國  100     年    11    月     7    日\n                  刑事第九庭  法  官  吳為平\n以上正本證明與原本無異。\n如不服本判決，應於判決送達後10日內向本院提出上訴狀（應附\n繕本）。\n                              書記官  蕭烈華\n中    華    民    國   100    年    11    月    8     日\n附錄論罪科刑法條：\n刑法第164條規定：\n藏匿犯人或依法逮捕拘禁之脫逃人或使之隱避者，處 2 年以下\n有期徒刑、拘役或 5 百元以下罰金。\n意圖犯前項之罪而頂替者，亦同。",
  "structure": {
    "main": "王進寬犯頂替罪，處拘役參拾日，如易科罰金，以新臺幣壹仟元\n折算壹日。",
    "fact": "一、本件犯罪事實、證據及所犯法條除引用檢察官聲請簡易判決\n    處刑書之記載（如附件）外，並補充：按刑法第164條第1項\n    之藏匿犯人或使之隱避罪，所謂「藏匿犯人」係指藏匿已經\n    犯罪之人而言（本院33年上字第1679號判例）；又此之所謂\n    「犯人」不以起訴後之人為限，為本院所持之見解；故凡觸\n    犯刑罰法規所規定之罪名者，不問其觸犯者係普通法或特別\n    法、實質刑法或形式刑法，只須其為實施犯罪行為之人，且\n    所犯之罪不問已否發覺或起訴或判處罪刑，均屬此之所謂「\n    犯人」（最高法院87年度台上字第757 號判決意旨參照）。\n    查本件王金蟬駕駛車號LF -9542號自用小客車行經桃園縣桃\n    園市○○路與山鶯路交岔路口時，疏未注意與被害人劉致雯\n    騎乘之車號BLB-699 號機車保持安全間隔，逕於左轉之際突\n    往右側駕駛，與騎乘機車行駛在其右側之劉致雯發生擦撞，\n    致劉致雯人車倒地，受有左手肘、左膝擦傷等情，業據被害\n    人劉致雯於警詢時證述詳實，並有道路交通事故現場圖、道\n    路交通事故調查報告表及現場照片在卷可佐，而被害人所受\n    之傷害，亦經本院查明屬實，有行政院國軍退除役官兵輔導\n    委員會桃園榮民醫院100 年9 月27日桃醫醫字第1000006729\n    號函附被害人之病歷摘要可憑，是王金蟬前揭過失傷害犯行\n    ，縱使未經起訴，仍無礙其為刑法第164 條之「犯人」。而\n    被告王進寬意圖使王金蟬隱避而頂替，自係犯刑法第164 條\n    第2 項、第1 項之頂替罪。爰審酌被告犯罪動機、目的、手\n    段、所生之危害及犯後之態度等一切情狀，量處如主文所示\n    之刑，並諭知易科罰金之折算標準，以示懲儆。\n二、依刑事訴訟法第449 條第1 項前段、第454 條第2 項，刑法\n    第164 條第2 項、第1 項、第41條第1 項前段，刑法施行法\n    第1 條之1 第1 項、第2 項前段，逕以簡易判決處如主文所\n    示之刑。\n如不服本判決，得於判決書送達之翌日起10日內，以書狀敘述理\n由，向本庭提出上訴。",
    "reason": "一、本件犯罪事實、證據及所犯法條除引用檢察官聲請簡易判決\n    處刑書之記載（如附件）外，並補充：按刑法第164條第1項\n    之藏匿犯人或使之隱避罪，所謂「藏匿犯人」係指藏匿已經\n    犯罪之人而言（本院33年上字第1679號判例）；又此之所謂\n    「犯人」不以起訴後之人為限，為本院所持之見解；故凡觸\n    犯刑罰法規所規定之罪名者，不問其觸犯者係普通法或特別\n    法、實質刑法或形式刑法，只須其為實施犯罪行為之人，且\n    所犯之罪不問已否發覺或起訴或判處罪刑，均屬此之所謂「\n    犯人」（最高法院87年度台上字第757 號判決意旨參照）。\n    查本件王金蟬駕駛車號LF -9542號自用小客車行經桃園縣桃\n    園市○○路與山鶯路交岔路口時，疏未注意與被害人劉致雯\n    騎乘之車號BLB-699 號機車保持安全間隔，逕於左轉之際突\n    往右側駕駛，與騎乘機車行駛在其右側之劉致雯發生擦撞，\n    致劉致雯人車倒地，受有左手肘、左膝擦傷等情，業據被害\n    人劉致雯於警詢時證述詳實，並有道路交通事故現場圖、道\n    路交通事故調查報告表及現場照片在卷可佐，而被害人所受\n    之傷害，亦經本院查明屬實，有行政院國軍退除役官兵輔導\n    委員會桃園榮民醫院100 年9 月27日桃醫醫字第1000006729\n    號函附被害人之病歷摘要可憑，是王金蟬前揭過失傷害犯行\n    ，縱使未經起訴，仍無礙其為刑法第164 條之「犯人」。而\n    被告王進寬意圖使王金蟬隱避而頂替，自係犯刑法第164 條\n    第2 項、第1 項之頂替罪。爰審酌被告犯罪動機、目的、手\n    段、所生之危害及犯後之態度等一切情狀，量處如主文所示\n    之刑，並諭知易科罰金之折算標準，以示懲儆。\n二、依刑事訴訟法第449 條第1 項前段、第454 條第2 項，刑法\n    第164 條第2 項、第1 項、第41條第1 項前段，刑法施行法\n    第1 條之1 第1 項、第2 項前段，逕以簡易判決處如主文所\n    示之刑。\n如不服本判決，得於判決書送達之翌日起10日內，以書狀敘述理\n由，向本庭提出上訴。"
  },
  "search": "臺灣桃園地方法院刑事簡易判決100年度桃簡字第1906號聲請人臺灣桃園地方法院檢察署檢察官被告王進寬上列被告因頂替案件，經檢察官聲請以簡易判決處刑（100年度速偵字第164號），本院判決如下：主文王進寬犯頂替罪，處拘役參拾日，如易科罰金，以新臺幣壹仟元折算壹日。事實及理由一、本件犯罪事實、證據及所犯法條除引用檢察官聲請簡易判決處刑書之記載（如附件）外，並補充：按刑法第164條第1項之藏匿犯人或使之隱避罪，所謂「藏匿犯人」係指藏匿已經犯罪之人而言（本院33年上字第1679號判例）；又此之所謂「犯人」不以起訴後之人為限，為本院所持之見解；故凡觸犯刑罰法規所規定之罪名者，不問其觸犯者係普通法或特別法、實質刑法或形式刑法，只須其為實施犯罪行為之人，且所犯之罪不問已否發覺或起訴或判處罪刑，均屬此之所謂「犯人」（最高法院87年度台上字第757號判決意旨參照）。查本件王金蟬駕駛車號LF-9542號自用小客車行經桃園縣桃園市○○路與山鶯路交岔路口時，疏未注意與被害人劉致雯騎乘之車號BLB-699號機車保持安全間隔，逕於左轉之際突往右側駕駛，與騎乘機車行駛在其右側之劉致雯發生擦撞，致劉致雯人車倒地，受有左手肘、左膝擦傷等情，業據被害人劉致雯於警詢時證述詳實，並有道路交通事故現場圖、道路交通事故調查報告表及現場照片在卷可佐，而被害人所受之傷害，亦經本院查明屬實，有行政院國軍退除役官兵輔導委員會桃園榮民醫院100年9月27日桃醫醫字第1000006729號函附被害人之病歷摘要可憑，是王金蟬前揭過失傷害犯行，縱使未經起訴，仍無礙其為刑法第164條之「犯人」。而被告王進寬意圖使王金蟬隱避而頂替，自係犯刑法第164條第2項、第1項之頂替罪。爰審酌被告犯罪動機、目的、手段、所生之危害及犯後之態度等一切情狀，量處如主文所示之刑，並諭知易科罰金之折算標準，以示懲儆。二、依刑事訴訟法第449條第1項前段、第454條第2項，刑法第164條第2項、第1項、第41條第1項前段，刑法施行法第1條之1第1項、第2項前段，逕以簡易判決處如主文所示之刑。如不服本判決，得於判決書送達之翌日起10日內，以書狀敘述理由，向本庭提出上訴。中華民國100年11月7日刑事第九庭法官吳為平以上正本證明與原本無異。如不服本判決，應於判決送達後10日內向本院提出上訴狀（應附繕本）。書記官蕭烈華中華民國100年11月8日附錄論罪科刑法條：刑法第164條規定：藏匿犯人或依法逮捕拘禁之脫逃人或使之隱避者，處2年以下有期徒刑、拘役或5百元以下罰金。意圖犯前項之罪而頂替者，亦同。",
  "characters": {
    "judges": [
      "吳為平"
    ],
    "prosecutors": [

    ],
    "lawyers": [

    ],
    "clerks": [
      "蕭烈華"
    ],
    "plaintiffs": [

    ],
    "defendants": [
      "王進寬"
    ],
    "prosecutor_office": [
      "臺灣桃園地方法院檢察署檢察官"
    ],
    "creditors": [

    ],
    "debtors": [

    ],
    "judicial_associate_officer": [

    ]
  },
  "adjudged_at": "2011-11-07",
  "created_at": "2016-02-13 00:54:39",
  "updated_at": "2016-02-13 00:54:39"
}