{
  "identify": "TYD-100-壢簡-2126-20111108-1",
  "court": {
    "name": "臺灣桃園地方法院",
    "code": "TYD"
  },
  "division": {
    "name": "刑事",
    "code": "M"
  },
  "year": 100,
  "word": "壢簡",
  "number": "2126",
  "jcheck": "1",
  "reason": "詐欺",
  "content": "臺灣桃園地方法院刑事簡易判決       100年度壢簡字第2126號\n聲  請  人  臺灣桃園地方法院檢察署檢察官\n被      告  黃稟翔\n上列被告因詐欺案件，經檢察官聲請以簡易判決處刑（99年度偵\n字第15049、15050號），本院判決如下：\n    主      文\n黃稟翔幫助意圖為自己不法之所有，以詐術使人將本人之物交付\n，處拘役肆拾日，如易科罰金，以新臺幣壹仟元折算壹日。\n    事實及理由\n一、本件犯罪事實及證據，除檢察官聲請簡易判決處刑書於犯罪\n    事實欄一關於「黃永欽」之記載，均更正為「黃欽昌」外，\n    餘均引用檢察官聲請簡易判決處刑書之記載（如附件）。\n二、核被告所為，係犯刑法第30條第1 項前段、第339 條第1 項\n    之幫助詐欺取財罪。又上開詐欺集團正犯成員間，就上開犯\n    行，為有犯意聯絡與行為分擔之共同正犯，惟被告僅係基於\n    幫助詐欺取財意思，提供該帳戶之提款卡，以利贓款匯入及\n    提領，係提供詐欺取財構成要件以外之助力，為詐欺取財罪\n    之幫助犯，應依刑法第30條第2 項規定，依法減輕其刑。被\n    告交付上開銀行帳戶之犯行，係基於一幫助詐欺犯意，幫助\n    正犯詐取上開附件所示2 位被害人之財物，而侵害2 人之財\n    產法益，為想像競合犯，應從一重之幫助詐欺取財罪既遂處\n    斷。爰審酌被告輕易提供金融帳戶資料供他人掩飾犯罪所得\n    使用，非但增加被害人尋求救濟之困難，造成社會人心不安\n    ，亦助長詐騙犯罪者之氣焰，使詐欺犯罪者得以順利取得詐\n    欺所得之財物，危害財產交易安全，犯罪情節非輕，犯後猶\n    否認犯行暨其犯罪手段，本件被害人所受之損失甚鉅尚未填\n    補，及犯罪所造成之危害程度等一切情狀，量處如主文所示\n    之刑，並諭知易科罰金之折算標準，以示懲儆。至上開被告\n    所交付予詐欺集團之提款卡等物，雖係供犯罪所用之物，惟\n    業已交付且未經扣案，尚無證據證明現仍存在未滅失，爰不\n    為沒收之諭知，附此敘明。\n三、據上論斷，應依刑事訴訟法第449 條第1 項前段、第3 項、\n    第454 條第2 項，刑法第30條第1 項前段、第2 項、第339\n    條第1 項、第55條、第41條第1 項前段，刑法施行法第1 條\n    之1 第1 項、第2 項前段，逕以簡易判決處刑如主文。\n四、如不服本判決，應於判決送達後10日內，向本院提出上訴狀\n    （應附繕本），上訴於本院合議庭。\n中    華    民    國    100   年     11    月    8    日\n                              刑事第二庭  法  官  翁毓潔\n以上正本證明與原本無異。\n如不服本判決，應於判決送達後10日內向本院提出上訴狀（應附\n繕本）。\n                                          書記官  鍾雯芳\n中    華    民    國   100    年    11    月    14    日\n 附錄論罪科刑法條:\n中華民國刑法第339條",
  "structure": {
    "main": "黃稟翔幫助意圖為自己不法之所有，以詐術使人將本人之物交付\n，處拘役肆拾日，如易科罰金，以新臺幣壹仟元折算壹日。",
    "fact": "一、本件犯罪事實及證據，除檢察官聲請簡易判決處刑書於犯罪\n    事實欄一關於「黃永欽」之記載，均更正為「黃欽昌」外，\n    餘均引用檢察官聲請簡易判決處刑書之記載（如附件）。\n二、核被告所為，係犯刑法第30條第1 項前段、第339 條第1 項\n    之幫助詐欺取財罪。又上開詐欺集團正犯成員間，就上開犯\n    行，為有犯意聯絡與行為分擔之共同正犯，惟被告僅係基於\n    幫助詐欺取財意思，提供該帳戶之提款卡，以利贓款匯入及\n    提領，係提供詐欺取財構成要件以外之助力，為詐欺取財罪\n    之幫助犯，應依刑法第30條第2 項規定，依法減輕其刑。被\n    告交付上開銀行帳戶之犯行，係基於一幫助詐欺犯意，幫助\n    正犯詐取上開附件所示2 位被害人之財物，而侵害2 人之財\n    產法益，為想像競合犯，應從一重之幫助詐欺取財罪既遂處\n    斷。爰審酌被告輕易提供金融帳戶資料供他人掩飾犯罪所得\n    使用，非但增加被害人尋求救濟之困難，造成社會人心不安\n    ，亦助長詐騙犯罪者之氣焰，使詐欺犯罪者得以順利取得詐\n    欺所得之財物，危害財產交易安全，犯罪情節非輕，犯後猶\n    否認犯行暨其犯罪手段，本件被害人所受之損失甚鉅尚未填\n    補，及犯罪所造成之危害程度等一切情狀，量處如主文所示\n    之刑，並諭知易科罰金之折算標準，以示懲儆。至上開被告\n    所交付予詐欺集團之提款卡等物，雖係供犯罪所用之物，惟\n    業已交付且未經扣案，尚無證據證明現仍存在未滅失，爰不\n    為沒收之諭知，附此敘明。\n三、據上論斷，應依刑事訴訟法第449 條第1 項前段、第3 項、\n    第454 條第2 項，刑法第30條第1 項前段、第2 項、第339\n    條第1 項、第55條、第41條第1 項前段，刑法施行法第1 條\n    之1 第1 項、第2 項前段，逕以簡易判決處刑如主文。\n四、如不服本判決，應於判決送達後10日內，向本院提出上訴狀\n    （應附繕本），上訴於本院合議庭。",
    "reason": "一、本件犯罪事實及證據，除檢察官聲請簡易判決處刑書於犯罪\n    事實欄一關於「黃永欽」之記載，均更正為「黃欽昌」外，\n    餘均引用檢察官聲請簡易判決處刑書之記載（如附件）。\n二、核被告所為，係犯刑法第30條第1 項前段、第339 條第1 項\n    之幫助詐欺取財罪。又上開詐欺集團正犯成員間，就上開犯\n    行，為有犯意聯絡與行為分擔之共同正犯，惟被告僅係基於\n    幫助詐欺取財意思，提供該帳戶之提款卡，以利贓款匯入及\n    提領，係提供詐欺取財構成要件以外之助力，為詐欺取財罪\n    之幫助犯，應依刑法第30條第2 項規定，依法減輕其刑。被\n    告交付上開銀行帳戶之犯行，係基於一幫助詐欺犯意，幫助\n    正犯詐取上開附件所示2 位被害人之財物，而侵害2 人之財\n    產法益，為想像競合犯，應從一重之幫助詐欺取財罪既遂處\n    斷。爰審酌被告輕易提供金融帳戶資料供他人掩飾犯罪所得\n    使用，非但增加被害人尋求救濟之困難，造成社會人心不安\n    ，亦助長詐騙犯罪者之氣焰，使詐欺犯罪者得以順利取得詐\n    欺所得之財物，危害財產交易安全，犯罪情節非輕，犯後猶\n    否認犯行暨其犯罪手段，本件被害人所受之損失甚鉅尚未填\n    補，及犯罪所造成之危害程度等一切情狀，量處如主文所示\n    之刑，並諭知易科罰金之折算標準，以示懲儆。至上開被告\n    所交付予詐欺集團之提款卡等物，雖係供犯罪所用之物，惟\n    業已交付且未經扣案，尚無證據證明現仍存在未滅失，爰不\n    為沒收之諭知，附此敘明。\n三、據上論斷，應依刑事訴訟法第449 條第1 項前段、第3 項、\n    第454 條第2 項，刑法第30條第1 項前段、第2 項、第339\n    條第1 項、第55條、第41條第1 項前段，刑法施行法第1 條\n    之1 第1 項、第2 項前段，逕以簡易判決處刑如主文。\n四、如不服本判決，應於判決送達後10日內，向本院提出上訴狀\n    （應附繕本），上訴於本院合議庭。"
  },
  "search": "臺灣桃園地方法院刑事簡易判決100年度壢簡字第2126號聲請人臺灣桃園地方法院檢察署檢察官被告黃稟翔上列被告因詐欺案件，經檢察官聲請以簡易判決處刑（99年度偵字第15049、15050號），本院判決如下：主文黃稟翔幫助意圖為自己不法之所有，以詐術使人將本人之物交付，處拘役肆拾日，如易科罰金，以新臺幣壹仟元折算壹日。事實及理由一、本件犯罪事實及證據，除檢察官聲請簡易判決處刑書於犯罪事實欄一關於「黃永欽」之記載，均更正為「黃欽昌」外，餘均引用檢察官聲請簡易判決處刑書之記載（如附件）。二、核被告所為，係犯刑法第30條第1項前段、第339條第1項之幫助詐欺取財罪。又上開詐欺集團正犯成員間，就上開犯行，為有犯意聯絡與行為分擔之共同正犯，惟被告僅係基於幫助詐欺取財意思，提供該帳戶之提款卡，以利贓款匯入及提領，係提供詐欺取財構成要件以外之助力，為詐欺取財罪之幫助犯，應依刑法第30條第2項規定，依法減輕其刑。被告交付上開銀行帳戶之犯行，係基於一幫助詐欺犯意，幫助正犯詐取上開附件所示2位被害人之財物，而侵害2人之財產法益，為想像競合犯，應從一重之幫助詐欺取財罪既遂處斷。爰審酌被告輕易提供金融帳戶資料供他人掩飾犯罪所得使用，非但增加被害人尋求救濟之困難，造成社會人心不安，亦助長詐騙犯罪者之氣焰，使詐欺犯罪者得以順利取得詐欺所得之財物，危害財產交易安全，犯罪情節非輕，犯後猶否認犯行暨其犯罪手段，本件被害人所受之損失甚鉅尚未填補，及犯罪所造成之危害程度等一切情狀，量處如主文所示之刑，並諭知易科罰金之折算標準，以示懲儆。至上開被告所交付予詐欺集團之提款卡等物，雖係供犯罪所用之物，惟業已交付且未經扣案，尚無證據證明現仍存在未滅失，爰不為沒收之諭知，附此敘明。三、據上論斷，應依刑事訴訟法第449條第1項前段、第3項、第454條第2項，刑法第30條第1項前段、第2項、第339條第1項、第55條、第41條第1項前段，刑法施行法第1條之1第1項、第2項前段，逕以簡易判決處刑如主文。四、如不服本判決，應於判決送達後10日內，向本院提出上訴狀（應附繕本），上訴於本院合議庭。中華民國100年11月8日刑事第二庭法官翁毓潔以上正本證明與原本無異。如不服本判決，應於判決送達後10日內向本院提出上訴狀（應附繕本）。書記官鍾雯芳中華民國100年11月14日附錄論罪科刑法條:中華民國刑法第339條",
  "characters": {
    "judges": [
      "翁毓潔"
    ],
    "prosecutors": [

    ],
    "lawyers": [

    ],
    "clerks": [
      "鍾雯芳"
    ],
    "plaintiffs": [

    ],
    "defendants": [
      "黃稟翔"
    ],
    "prosecutor_office": [
      "臺灣桃園地方法院檢察署檢察官"
    ],
    "creditors": [

    ],
    "debtors": [

    ],
    "judicial_associate_officer": [

    ]
  },
  "adjudged_at": "2011-11-08",
  "created_at": "2016-02-13 00:42:40",
  "updated_at": "2016-02-13 00:42:40"
}