{
  "identify": "SCD-90-竹簡-619-20020225-1",
  "court": {
    "name": "臺灣新竹地方法院",
    "code": "SCD"
  },
  "division": {
    "name": "刑事",
    "code": "M"
  },
  "year": 90,
  "word": "竹簡",
  "number": "619",
  "jcheck": "1",
  "reason": "妨害兵役",
  "content": "臺灣新竹地方法院刑事簡易判決                      九十年度竹簡字第六一九號\n    公  訴  人  臺灣新竹地方法院檢察署檢察官\n    被      告  甲○○\n右列被告因妨害兵役案件，經檢察官聲請以簡易判決處刑（九十年度偵字第五九四０\n號），本院判決如左：\n      主  文\n甲○○後備軍人，居住處所遷移，無故不依規定申報，致使教育召集令無法送達，處\n有期徒刑貳月，如易科罰金，以參佰元折算壹日。\n    事實及理由\n一、犯罪事實：甲○○係新竹團管區司令部列管之後備軍人，原設籍並居住於新竹市\n    香山區○○里○○路○段四五九巷六弄二十四號，其於民國八十九年五月份起，\n    即將居住處所遷移，無故不依規定申報，致使新竹團管區司令部所發指定應於九\n    十年八月六日上午八時前往新竹縣關西鎮老庚寮二十二號關西營區報到、召集符\n    號為精誠十五之八號、編號０四一二號之教育召集令無法送達。案經台北師管區\n    司令部新竹團管區司令部移送臺灣新竹地方法院檢察署檢察官聲請簡易判決處刑\n    。\n二、證據：\n  （一）教育召集令。\n  （二）新竹市警察局第三分局朝山派出所戶口查察通報單。\n  （三）新竹市警察局第三分局後備軍人行方不明遷出未報年籍表。\n  （四）新竹市警察局第三分局朝山派出所警員孫宜斌証稱被告設籍該處，但該處目\n        前無人居住係空屋之証詞。\n  （五）法務部戶役政連結作業系統查詢資料。\n三、核被告所為，係犯妨害兵役治罪條例第十一條第三項、第一項第三款之罪，應依\n    同條例第七條第一項科刑。\n四、據上論斷，應依刑事訴訟法第四百四十九條第一項前段，妨害兵役治罪條例第十\n    一條第一項第三款、第三項、第七條第一項，刑法第十一條前段、第四十一條第\n    一項前段，罰金罰鍰提高標準條例第二條，判決如主文。\n五、如不服本判決，得自收受送達之日起十日內，向本院提起上訴。\n中      華      民      國    九十一      年    二    月    二十五      日\n                              臺灣新竹地方法院新竹簡易庭\n                                    法  官  王紋瑩\n右正本證明與原本無異。\n                                    書記官  馮玉玲\n中      華      民      國    九十一      年    二    月二十五      日\n附錄本案論罪科刑所適用法條全文：\n妨害兵役治罪條例第十一條：\n後備軍人有左列行為之一者，處一年以下有期徒刑、拘役或三百元以下罰金：\n一  離營歸鄉無故不依規定報到，或重複申報戶籍者。\n二  無故拒絕調查，或體格檢查不到者。\n三  居住處所遷移，無故不依規定申報者。\n國民兵犯前項第二款、第三款之罪者，處六月以下有期徒刑、拘役或一百元以下罰金\n。\n後備軍人犯第一項之罪或國民兵犯第二項之罪，致使召集令無法送達者，以意圖避免\n召集論；分別依第六條、第七條科刑。\n妨害兵役治罪條例第七條：\n意圖避免教育召集或勤務召集，而有左列行為之一者，處三年以下有期徒刑：\n一  捏造免役、除役、轉役或免除召集原因者。\n二  故意毀傷身體者。\n三  無故拒絕接受召集令者。\n四  無故逾應召期限二日者。\n五  使人頂替本人應召者。\n無故不參加點閱召集，或意圖避免點閱召集，而有前項第一款至第三款及第五款行為\n之一者，處一年以下有期徒刑、拘役或三百元以下罰金。\n",
  "structure": {
    "main": "甲○○後備軍人，居住處所遷移，無故不依規定申報，致使教育召集令無法送達，處\n有期徒刑貳月，如易科罰金，以參佰元折算壹日。",
    "fact": "一、犯罪事實：甲○○係新竹團管區司令部列管之後備軍人，原設籍並居住於新竹市\n    香山區○○里○○路○段四五九巷六弄二十四號，其於民國八十九年五月份起，\n    即將居住處所遷移，無故不依規定申報，致使新竹團管區司令部所發指定應於九\n    十年八月六日上午八時前往新竹縣關西鎮老庚寮二十二號關西營區報到、召集符\n    號為精誠十五之八號、編號０四一二號之教育召集令無法送達。案經台北師管區\n    司令部新竹團管區司令部移送臺灣新竹地方法院檢察署檢察官聲請簡易判決處刑\n    。\n二、證據：\n  （一）教育召集令。\n  （二）新竹市警察局第三分局朝山派出所戶口查察通報單。\n  （三）新竹市警察局第三分局後備軍人行方不明遷出未報年籍表。\n  （四）新竹市警察局第三分局朝山派出所警員孫宜斌証稱被告設籍該處，但該處目\n        前無人居住係空屋之証詞。\n  （五）法務部戶役政連結作業系統查詢資料。\n三、核被告所為，係犯妨害兵役治罪條例第十一條第三項、第一項第三款之罪，應依\n    同條例第七條第一項科刑。\n四、據上論斷，應依刑事訴訟法第四百四十九條第一項前段，妨害兵役治罪條例第十\n    一條第一項第三款、第三項、第七條第一項，刑法第十一條前段、第四十一條第\n    一項前段，罰金罰鍰提高標準條例第二條，判決如主文。\n五、如不服本判決，得自收受送達之日起十日內，向本院提起上訴。",
    "reason": "一、犯罪事實：甲○○係新竹團管區司令部列管之後備軍人，原設籍並居住於新竹市\n    香山區○○里○○路○段四五九巷六弄二十四號，其於民國八十九年五月份起，\n    即將居住處所遷移，無故不依規定申報，致使新竹團管區司令部所發指定應於九\n    十年八月六日上午八時前往新竹縣關西鎮老庚寮二十二號關西營區報到、召集符\n    號為精誠十五之八號、編號０四一二號之教育召集令無法送達。案經台北師管區\n    司令部新竹團管區司令部移送臺灣新竹地方法院檢察署檢察官聲請簡易判決處刑\n    。\n二、證據：\n  （一）教育召集令。\n  （二）新竹市警察局第三分局朝山派出所戶口查察通報單。\n  （三）新竹市警察局第三分局後備軍人行方不明遷出未報年籍表。\n  （四）新竹市警察局第三分局朝山派出所警員孫宜斌証稱被告設籍該處，但該處目\n        前無人居住係空屋之証詞。\n  （五）法務部戶役政連結作業系統查詢資料。\n三、核被告所為，係犯妨害兵役治罪條例第十一條第三項、第一項第三款之罪，應依\n    同條例第七條第一項科刑。\n四、據上論斷，應依刑事訴訟法第四百四十九條第一項前段，妨害兵役治罪條例第十\n    一條第一項第三款、第三項、第七條第一項，刑法第十一條前段、第四十一條第\n    一項前段，罰金罰鍰提高標準條例第二條，判決如主文。\n五、如不服本判決，得自收受送達之日起十日內，向本院提起上訴。"
  },
  "search": "臺灣新竹地方法院刑事簡易判決九十年度竹簡字第六一九號公訴人臺灣新竹地方法院檢察署檢察官被告甲○○右列被告因妨害兵役案件，經檢察官聲請以簡易判決處刑（九十年度偵字第五九四０號），本院判決如左：主文甲○○後備軍人，居住處所遷移，無故不依規定申報，致使教育召集令無法送達，處有期徒刑貳月，如易科罰金，以參佰元折算壹日。事實及理由一、犯罪事實：甲○○係新竹團管區司令部列管之後備軍人，原設籍並居住於新竹市香山區○○里○○路○段四五九巷六弄二十四號，其於民國八十九年五月份起，即將居住處所遷移，無故不依規定申報，致使新竹團管區司令部所發指定應於九十年八月六日上午八時前往新竹縣關西鎮老庚寮二十二號關西營區報到、召集符號為精誠十五之八號、編號０四一二號之教育召集令無法送達。案經台北師管區司令部新竹團管區司令部移送臺灣新竹地方法院檢察署檢察官聲請簡易判決處刑。二、證據：（一）教育召集令。（二）新竹市警察局第三分局朝山派出所戶口查察通報單。（三）新竹市警察局第三分局後備軍人行方不明遷出未報年籍表。（四）新竹市警察局第三分局朝山派出所警員孫宜斌証稱被告設籍該處，但該處目前無人居住係空屋之証詞。（五）法務部戶役政連結作業系統查詢資料。三、核被告所為，係犯妨害兵役治罪條例第十一條第三項、第一項第三款之罪，應依同條例第七條第一項科刑。四、據上論斷，應依刑事訴訟法第四百四十九條第一項前段，妨害兵役治罪條例第十一條第一項第三款、第三項、第七條第一項，刑法第十一條前段、第四十一條第一項前段，罰金罰鍰提高標準條例第二條，判決如主文。五、如不服本判決，得自收受送達之日起十日內，向本院提起上訴。中華民國九十一年二月二十五日臺灣新竹地方法院新竹簡易庭法官王紋瑩右正本證明與原本無異。書記官馮玉玲中華民國九十一年二月二十五日附錄本案論罪科刑所適用法條全文：妨害兵役治罪條例第十一條：後備軍人有左列行為之一者，處一年以下有期徒刑、拘役或三百元以下罰金：一離營歸鄉無故不依規定報到，或重複申報戶籍者。二無故拒絕調查，或體格檢查不到者。三居住處所遷移，無故不依規定申報者。國民兵犯前項第二款、第三款之罪者，處六月以下有期徒刑、拘役或一百元以下罰金。後備軍人犯第一項之罪或國民兵犯第二項之罪，致使召集令無法送達者，以意圖避免召集論；分別依第六條、第七條科刑。妨害兵役治罪條例第七條：意圖避免教育召集或勤務召集，而有左列行為之一者，處三年以下有期徒刑：一捏造免役、除役、轉役或免除召集原因者。二故意毀傷身體者。三無故拒絕接受召集令者。四無故逾應召期限二日者。五使人頂替本人應召者。無故不參加點閱召集，或意圖避免點閱召集，而有前項第一款至第三款及第五款行為之一者，處一年以下有期徒刑、拘役或三百元以下罰金。",
  "characters": {
    "judges": [
      "王紋瑩"
    ],
    "prosecutors": [

    ],
    "lawyers": [

    ],
    "clerks": [
      "馮玉玲"
    ],
    "plaintiffs": [

    ],
    "defendants": [
      "甲○○",
      "右列被告因妨害兵役案件，經檢察官聲請以簡易判決處刑（九十年度偵字第五九四０",
      "號），本院判決如左："
    ],
    "prosecutor_office": [
      "臺灣新竹地方法院檢察署檢察官"
    ],
    "creditors": [

    ],
    "debtors": [

    ],
    "judicial_associate_officer": [

    ]
  },
  "adjudged_at": "2002-02-25",
  "created_at": "2016-02-04 15:03:54",
  "updated_at": "2016-02-04 15:03:54"
}