{
  "identify": "TPH-94-聲-586-20050629-1",
  "court": {
    "name": "臺灣高等法院",
    "code": "TPH"
  },
  "division": {
    "name": "刑事",
    "code": "M"
  },
  "year": 94,
  "word": "聲",
  "number": "586",
  "jcheck": "1",
  "reason": "聲請定其應執行刑",
  "content": "臺灣高等法院刑事裁定                   94年度聲字第586號\n聲  請  人  臺灣高等法院檢察署檢察官\n受  刑  人  甲○○\n上列聲請人因受刑人數罪併罰有2裁判以上，聲請定其應執行之\n刑，本院裁定如下：\n    主  文\n甲○○因犯如附表所示各罪所處之刑，應執行有期徒刑玖年陸月\n，併科罰金新臺幣伍萬元，罰金如易服勞役以新臺幣玖佰元即銀\n元參佰元折算壹日。\n  理  由\n受刑人甲○○因違反毒品危害防制條例等數罪，經台灣士林地方\n法院及本院先後判處如附表所示之刑，均經分別確定在案。茲檢\n察官聲請定其應執行之刑，本院審核認聲請為正當，應定其應執\n行之刑。爰依刑事訴訟法第477條第1項、刑法第53條、第51條第\n5款、第42條第2項，罰金罰鍰提高標準條例第2條，裁定如主文\n。\n中    華    民    國    94    年    6     月    29    日\n                  刑事第六庭審判長法  官  許國宏\n                                  法  官  林銓正\n                                  法  官  洪光燦\n以上正本證明與原本無異。\n如不服本裁定，應於收受送達後5日內向本院提出抗告狀。\n                                  書記官  陳玉嬋\n中    華    民    國    94    年    6     月    30    日\n",
  "structure": {
    "main": "甲○○因犯如附表所示各罪所處之刑，應執行有期徒刑玖年陸月\n，併科罰金新臺幣伍萬元，罰金如易服勞役以新臺幣玖佰元即銀\n元參佰元折算壹日。",
    "reason": "受刑人甲○○因違反毒品危害防制條例等數罪，經台灣士林地方\n法院及本院先後判處如附表所示之刑，均經分別確定在案。茲檢\n察官聲請定其應執行之刑，本院審核認聲請為正當，應定其應執\n行之刑。爰依刑事訴訟法第477條第1項、刑法第53條、第51條第\n5款、第42條第2項，罰金罰鍰提高標準條例第2條，裁定如主文\n。"
  },
  "search": "臺灣高等法院刑事裁定94年度聲字第586號聲請人臺灣高等法院檢察署檢察官受刑人甲○○上列聲請人因受刑人數罪併罰有2裁判以上，聲請定其應執行之刑，本院裁定如下：主文甲○○因犯如附表所示各罪所處之刑，應執行有期徒刑玖年陸月，併科罰金新臺幣伍萬元，罰金如易服勞役以新臺幣玖佰元即銀元參佰元折算壹日。理由受刑人甲○○因違反毒品危害防制條例等數罪，經台灣士林地方法院及本院先後判處如附表所示之刑，均經分別確定在案。茲檢察官聲請定其應執行之刑，本院審核認聲請為正當，應定其應執行之刑。爰依刑事訴訟法第477條第1項、刑法第53條、第51條第5款、第42條第2項，罰金罰鍰提高標準條例第2條，裁定如主文。中華民國94年6月29日刑事第六庭審判長法官許國宏法官林銓正法官洪光燦以上正本證明與原本無異。如不服本裁定，應於收受送達後5日內向本院提出抗告狀。書記官陳玉嬋中華民國94年6月30日",
  "characters": {
    "judges": [
      "許國宏",
      "林銓正",
      "洪光燦"
    ],
    "prosecutors": [

    ],
    "lawyers": [

    ],
    "clerks": [
      "陳玉嬋"
    ],
    "plaintiffs": [

    ],
    "defendants": [

    ],
    "prosecutor_office": [
      "臺灣高等法院檢察署檢察官"
    ],
    "creditors": [

    ],
    "debtors": [

    ],
    "judicial_associate_officer": [

    ]
  },
  "adjudged_at": "2005-06-29",
  "created_at": "2016-02-07 05:17:46",
  "updated_at": "2016-02-07 05:17:46"
}