{
  "identify": "KSH-94-上訴-715-20051027-3",
  "court": {
    "name": "臺灣高等法院",
    "code": "KSH"
  },
  "division": {
    "name": "刑事",
    "code": "M"
  },
  "year": 94,
  "word": "上訴",
  "number": "715",
  "jcheck": "3",
  "reason": "違反毒品危害防制條例",
  "content": "臺灣高等法院高雄分院刑事裁定        94年度上訴字第715 號\n上  訴  人\n即  被  告  甲○○\n選任辯護人  柳聰賢律師\n上  訴  人\n即  被  告  乙○○\n  選任辯護人  陳聰敏律師\n上列上訴人等因違反毒品危害防制條例上訴案件，本院裁定如下\n：\n    主  文\n甲○○、乙○○羈押期間，均自九十四年十一月三日起，延長貳\n月。\n    理  由\n一、上訴人即被告甲○○、乙○○前經本院認為販賣第三級毒品\n    罪，嫌疑重大，有刑事訴訟法第101 條第1 項3 款情形，並\n    有羈押必要，於民國94年6 月3 日執行羈押，至民國94年9\n    月2 日第一次羈押期間已屆滿。嗣經第1 次延長羈押，至民\n    國94年11月2 日延長羈押期間即將屆滿。\n二、茲本院以前項原因依然存在，認有繼續羈押之必要，應自民\n    國94年11月3 日起，延長羈押2 月，爰依刑事訴訟法第108\n    條第1 項、第5 項，裁定如主文。\n中    華    民    國    94    年    10    月    27    日\n                  刑事第三庭    審判長法  官  周賢銳\n                                      法  官  黃仁松\n                                      法  官  謝宏宗\n以上正本證明與原本無異。\n如不服本裁定應於送達後5日內向本院提出抗告狀。\n中    華    民    國    94    年    10    月    27    日\n                                      書記官  熊惠津\n",
  "structure": {
    "main": "甲○○、乙○○羈押期間，均自九十四年十一月三日起，延長貳\n月。",
    "reason": "一、上訴人即被告甲○○、乙○○前經本院認為販賣第三級毒品\n    罪，嫌疑重大，有刑事訴訟法第101 條第1 項3 款情形，並\n    有羈押必要，於民國94年6 月3 日執行羈押，至民國94年9\n    月2 日第一次羈押期間已屆滿。嗣經第1 次延長羈押，至民\n    國94年11月2 日延長羈押期間即將屆滿。\n二、茲本院以前項原因依然存在，認有繼續羈押之必要，應自民\n    國94年11月3 日起，延長羈押2 月，爰依刑事訴訟法第108\n    條第1 項、第5 項，裁定如主文。"
  },
  "search": "臺灣高等法院高雄分院刑事裁定94年度上訴字第715號上訴人即被告甲○○選任辯護人柳聰賢律師上訴人即被告乙○○選任辯護人陳聰敏律師上列上訴人等因違反毒品危害防制條例上訴案件，本院裁定如下：主文甲○○、乙○○羈押期間，均自九十四年十一月三日起，延長貳月。理由一、上訴人即被告甲○○、乙○○前經本院認為販賣第三級毒品罪，嫌疑重大，有刑事訴訟法第101條第1項3款情形，並有羈押必要，於民國94年6月3日執行羈押，至民國94年9月2日第一次羈押期間已屆滿。嗣經第1次延長羈押，至民國94年11月2日延長羈押期間即將屆滿。二、茲本院以前項原因依然存在，認有繼續羈押之必要，應自民國94年11月3日起，延長羈押2月，爰依刑事訴訟法第108條第1項、第5項，裁定如主文。中華民國94年10月27日刑事第三庭審判長法官周賢銳法官黃仁松法官謝宏宗以上正本證明與原本無異。如不服本裁定應於送達後5日內向本院提出抗告狀。中華民國94年10月27日書記官熊惠津",
  "characters": {
    "judges": [
      "周賢銳",
      "黃仁松",
      "謝宏宗"
    ],
    "prosecutors": [

    ],
    "lawyers": [
      "柳聰賢",
      "陳聰敏"
    ],
    "clerks": [
      "熊惠津"
    ],
    "plaintiffs": [

    ],
    "defendants": [
      "甲",
      "乙"
    ],
    "prosecutor_office": [

    ],
    "creditors": [

    ],
    "debtors": [

    ],
    "judicial_associate_officer": [

    ]
  },
  "adjudged_at": "2005-10-27",
  "created_at": "2016-02-07 10:13:41",
  "updated_at": "2016-02-07 10:13:41"
}