{
  "identify": "KSD-90-易-4348-20020108-1",
  "court": {
    "name": "臺灣高雄地方法院",
    "code": "KSD"
  },
  "division": {
    "name": "刑事",
    "code": "M"
  },
  "year": 90,
  "word": "易",
  "number": "4348",
  "jcheck": "1",
  "reason": "傷害",
  "content": "臺灣高雄地方法院刑事判決                          九十年度易字第四三四八號\n    公  訴  人  臺灣高雄地方法院檢察署檢察官\n    被      告  甲○○\n    選任辯護人  陳三兒\n    被      告  乙○○\n右列被告因傷害案件，經檢察官提起公訴（九十年度偵字第一六六三八號），本院判\n決如左：\n    主  文\n本件公訴不受理。\n    理  由\n一、公訴意旨略以：緣被告甲○○積欠被告乙○○債務未償，乙○○乃於民國九十年\n    四月十九日上午至甲○○位於高雄縣大寮鄉○○村○○路七二號住處討債，二人\n    旋前往高雄縣警察局林園分局忠義派出所協調，惟協調未果，甲○○欲離去之際\n    ，乙○○竟基於傷害之犯意，在派出所門前以嘴咬傷甲○○之右前臂，造成擦傷\n    一處。嗣二人續往甲○○之住宅內協商債務，甲○○竟亦基於傷害之犯意，於同\n    日下午一時三十分許，出手抓打乙○○，造成乙○○兩側上肢多處挫擦傷，因認\n    被告二人均涉犯刑法第二百七十七條第一項之傷害罪嫌等語。\n二、按告訴乃論之罪，告訴人於第一審辯論終結前，得撤回其告訴；又告訴經撤回者\n    ，法院應諭知不受理之判決，刑事訴訟法第二百三十八條第一項及第三百零三條\n    第三款分別定有明文。\n三、本件被告甲○○、乙○○因傷害案件，經檢察官提起公訴，認被告二人均係犯刑\n    法第二百七十七條第一項之傷害罪，依同法第二百八十七條前段之規定，須告訴\n    乃論。然查，本案已均據被告即告訴人甲○○、乙○○於本院調查程序時以言詞\n    撤回其告訴，有本院九十一年一月七日訊問筆錄在卷可按，並有渠等切結書一份\n    在卷可憑。揆諸前開說明，爰不經言詞辯論，逕為諭知不受理之判決。\n據上論斷，應依刑事訴訟法第三百零三條第三款、第三百零七條，判決如主文。\n中      華      民      國      九十一      年      一      月    八    日\n                                  臺灣高雄地方法院刑事第六庭\n                                      審判長  法  官  趙家光\n        法  官  張世賢\n                                              法  官  林韋岑\n右正本證明與原本無異。\n如不服本判決，應於判決送達後十日內，向本院提出上訴狀。\n                                              書記官    董明惠\n中      華      民      國      九十一      年      一      月    八    日\n",
  "structure": {
    "main": "本件公訴不受理。",
    "reason": "一、公訴意旨略以：緣被告甲○○積欠被告乙○○債務未償，乙○○乃於民國九十年\n    四月十九日上午至甲○○位於高雄縣大寮鄉○○村○○路七二號住處討債，二人\n    旋前往高雄縣警察局林園分局忠義派出所協調，惟協調未果，甲○○欲離去之際\n    ，乙○○竟基於傷害之犯意，在派出所門前以嘴咬傷甲○○之右前臂，造成擦傷\n    一處。嗣二人續往甲○○之住宅內協商債務，甲○○竟亦基於傷害之犯意，於同\n    日下午一時三十分許，出手抓打乙○○，造成乙○○兩側上肢多處挫擦傷，因認\n    被告二人均涉犯刑法第二百七十七條第一項之傷害罪嫌等語。\n二、按告訴乃論之罪，告訴人於第一審辯論終結前，得撤回其告訴；又告訴經撤回者\n    ，法院應諭知不受理之判決，刑事訴訟法第二百三十八條第一項及第三百零三條\n    第三款分別定有明文。\n三、本件被告甲○○、乙○○因傷害案件，經檢察官提起公訴，認被告二人均係犯刑\n    法第二百七十七條第一項之傷害罪，依同法第二百八十七條前段之規定，須告訴\n    乃論。然查，本案已均據被告即告訴人甲○○、乙○○於本院調查程序時以言詞\n    撤回其告訴，有本院九十一年一月七日訊問筆錄在卷可按，並有渠等切結書一份\n    在卷可憑。揆諸前開說明，爰不經言詞辯論，逕為諭知不受理之判決。\n據上論斷，應依刑事訴訟法第三百零三條第三款、第三百零七條，判決如主文。"
  },
  "search": "臺灣高雄地方法院刑事判決九十年度易字第四三四八號公訴人臺灣高雄地方法院檢察署檢察官被告甲○○選任辯護人陳三兒被告乙○○右列被告因傷害案件，經檢察官提起公訴（九十年度偵字第一六六三八號），本院判決如左：主文本件公訴不受理。理由一、公訴意旨略以：緣被告甲○○積欠被告乙○○債務未償，乙○○乃於民國九十年四月十九日上午至甲○○位於高雄縣大寮鄉○○村○○路七二號住處討債，二人旋前往高雄縣警察局林園分局忠義派出所協調，惟協調未果，甲○○欲離去之際，乙○○竟基於傷害之犯意，在派出所門前以嘴咬傷甲○○之右前臂，造成擦傷一處。嗣二人續往甲○○之住宅內協商債務，甲○○竟亦基於傷害之犯意，於同日下午一時三十分許，出手抓打乙○○，造成乙○○兩側上肢多處挫擦傷，因認被告二人均涉犯刑法第二百七十七條第一項之傷害罪嫌等語。二、按告訴乃論之罪，告訴人於第一審辯論終結前，得撤回其告訴；又告訴經撤回者，法院應諭知不受理之判決，刑事訴訟法第二百三十八條第一項及第三百零三條第三款分別定有明文。三、本件被告甲○○、乙○○因傷害案件，經檢察官提起公訴，認被告二人均係犯刑法第二百七十七條第一項之傷害罪，依同法第二百八十七條前段之規定，須告訴乃論。然查，本案已均據被告即告訴人甲○○、乙○○於本院調查程序時以言詞撤回其告訴，有本院九十一年一月七日訊問筆錄在卷可按，並有渠等切結書一份在卷可憑。揆諸前開說明，爰不經言詞辯論，逕為諭知不受理之判決。據上論斷，應依刑事訴訟法第三百零三條第三款、第三百零七條，判決如主文。中華民國九十一年一月八日臺灣高雄地方法院刑事第六庭審判長法官趙家光法官張世賢法官林韋岑右正本證明與原本無異。如不服本判決，應於判決送達後十日內，向本院提出上訴狀。書記官董明惠中華民國九十一年一月八日",
  "characters": {
    "judges": [
      "趙家光",
      "張世賢",
      "林韋岑"
    ],
    "prosecutors": [

    ],
    "lawyers": [

    ],
    "clerks": [
      "董明惠"
    ],
    "plaintiffs": [

    ],
    "defendants": [
      "甲○○",
      "乙○○",
      "右列被告因傷害案件，經檢察官提起公訴（九十年度偵字第一六六三八號），本院判",
      "決如左："
    ],
    "prosecutor_office": [
      "臺灣高雄地方法院檢察署檢察官"
    ],
    "creditors": [

    ],
    "debtors": [

    ],
    "judicial_associate_officer": [

    ]
  },
  "adjudged_at": "2002-01-08",
  "created_at": "2016-02-05 04:15:03",
  "updated_at": "2016-02-05 04:15:03"
}