{
  "identify": "TCD-93-訴-477-20040224-1",
  "court": {
    "name": "臺灣臺中地方法院",
    "code": "TCD"
  },
  "division": {
    "name": "民事",
    "code": "V"
  },
  "year": 93,
  "word": "訴",
  "number": "477",
  "jcheck": "1",
  "reason": "清償借款",
  "content": "臺灣臺中地方法院民事裁定  九十三年度訴字第四七七號\n    原      告  合作金庫銀行股份有限公司\n    法定代理人  梁成金\n    送達代收人  劉淑芳\n    被      告  甲○○\n右當事人間清償借款事件，本院裁定如左：\n    主      文\n原告之訴駁回。\n訴訟費用由原告負擔。\n    理      由\n一、按提起民事訴訟，應依民事訴訟費用法第二條規定繳納裁判費，此為必須具備之\n    程式。\n二、本件原告起訴僅繳納部分裁判費，經本院於民國九十三年一月十四日裁定限期命\n    其於送達原告時起五日內補正，此項裁定已於民國九十三年一月二十九日送達原\n    告，有送達證書在卷可稽。\n三、原告逾期迄今仍未補正，其訴不能認為合法，應予駁回。\n四、依民事訴訟法第二百四十九條第一項第六款、第九十五條、第七十八條裁定如主\n    文。\n中      華      民      國    九十三    年      二      月    二十四    日\n                        臺灣臺中地方法院民事第二庭\n~B法      官  陳宗賢\n右為正本係照原本作成\n如對本裁定抗告應於送達後十日內向本院提出抗告狀\n中      華      民      國    九十三    年      二      月    二十四    日\n~B法院書記官  王嘉仁\n",
  "structure": {
    "main": "原告之訴駁回。\n訴訟費用由原告負擔。",
    "reason": "一、按提起民事訴訟，應依民事訴訟費用法第二條規定繳納裁判費，此為必須具備之\n    程式。\n二、本件原告起訴僅繳納部分裁判費，經本院於民國九十三年一月十四日裁定限期命\n    其於送達原告時起五日內補正，此項裁定已於民國九十三年一月二十九日送達原\n    告，有送達證書在卷可稽。\n三、原告逾期迄今仍未補正，其訴不能認為合法，應予駁回。\n四、依民事訴訟法第二百四十九條第一項第六款、第九十五條、第七十八條裁定如主\n    文。"
  },
  "search": "臺灣臺中地方法院民事裁定九十三年度訴字第四七七號原告合作金庫銀行股份有限公司法定代理人梁成金送達代收人劉淑芳被告甲○○右當事人間清償借款事件，本院裁定如左：主文原告之訴駁回。訴訟費用由原告負擔。理由一、按提起民事訴訟，應依民事訴訟費用法第二條規定繳納裁判費，此為必須具備之程式。二、本件原告起訴僅繳納部分裁判費，經本院於民國九十三年一月十四日裁定限期命其於送達原告時起五日內補正，此項裁定已於民國九十三年一月二十九日送達原告，有送達證書在卷可稽。三、原告逾期迄今仍未補正，其訴不能認為合法，應予駁回。四、依民事訴訟法第二百四十九條第一項第六款、第九十五條、第七十八條裁定如主文。中華民國九十三年二月二十四日臺灣臺中地方法院民事第二庭~B法官陳宗賢右為正本係照原本作成如對本裁定抗告應於送達後十日內向本院提出抗告狀中華民國九十三年二月二十四日~B法院書記官王嘉仁",
  "characters": {
    "judges": [
      "陳宗賢"
    ],
    "prosecutors": [

    ],
    "lawyers": [

    ],
    "clerks": [

    ],
    "plaintiffs": [
      "合作金庫銀行股份有限公司"
    ],
    "defendants": [
      "甲○○",
      "右當事人間清償借款事件，本院裁定如左："
    ],
    "prosecutor_office": [

    ],
    "creditors": [

    ],
    "debtors": [

    ],
    "judicial_associate_officer": [

    ]
  },
  "adjudged_at": "2004-02-24",
  "created_at": "2016-02-05 21:48:23",
  "updated_at": "2016-02-05 21:48:23"
}