{
  "identify": "KSD-93-訴-419-20040319-1",
  "court": {
    "name": "臺灣高雄地方法院",
    "code": "KSD"
  },
  "division": {
    "name": "刑事",
    "code": "M"
  },
  "year": 93,
  "word": "訴",
  "number": "419",
  "jcheck": "1",
  "reason": "贓物等",
  "content": "臺灣高雄地方法院刑事裁定                          九十三年度訴字第四一九號\n    公  訴  人  臺灣高雄地方法院檢察署檢察官\n    被      告  甲○○\n    選任辯護人  劉新安律師\n    被      告  石真印\n    選任辯護人  賴玉山律師\n                莊美玉律師\n右列被告等因贓物案件，本院裁定如左：\n    主  文\n甲○○提出新台幣伍萬元之保證書或保證金後，准予停止羈押。\n石真印提出新台幣伍萬元之保證書或保證金後，准予停止羈押。\n    理  由\n本件被告甲○○、石真印前經本院執行羈押。茲被告甲○○、石真印聲請停止羈押，\n經核符合規定，准予各提出新台幣伍萬元之保證書或證金後，停止羈押，爰依刑事訴\n訟法第一百十一條、第一百二十一條第一項，裁定如主文。\n中      華      民      國      九十三      年      三    月    十九    日\n                            臺灣高雄地方法院刑事庭\n                                審判長法  官    黃三友\n                                      法  官    王雅苑\n                                      法  官    涂裕洪\n右正本證明與原本無異。\n如不服本裁定，應於裁定送達後五日內，向本院提出抗告狀。\n                                      書記官    賴佳慧\n中    華    民    國      九十三     年      三     月      十九      日\n",
  "structure": {
    "main": "甲○○提出新台幣伍萬元之保證書或保證金後，准予停止羈押。\n石真印提出新台幣伍萬元之保證書或保證金後，准予停止羈押。",
    "reason": "本件被告甲○○、石真印前經本院執行羈押。茲被告甲○○、石真印聲請停止羈押，\n經核符合規定，准予各提出新台幣伍萬元之保證書或證金後，停止羈押，爰依刑事訴\n訟法第一百十一條、第一百二十一條第一項，裁定如主文。"
  },
  "search": "臺灣高雄地方法院刑事裁定九十三年度訴字第四一九號公訴人臺灣高雄地方法院檢察署檢察官被告甲○○選任辯護人劉新安律師被告石真印選任辯護人賴玉山律師莊美玉律師右列被告等因贓物案件，本院裁定如左：主文甲○○提出新台幣伍萬元之保證書或保證金後，准予停止羈押。石真印提出新台幣伍萬元之保證書或保證金後，准予停止羈押。理由本件被告甲○○、石真印前經本院執行羈押。茲被告甲○○、石真印聲請停止羈押，經核符合規定，准予各提出新台幣伍萬元之保證書或證金後，停止羈押，爰依刑事訴訟法第一百十一條、第一百二十一條第一項，裁定如主文。中華民國九十三年三月十九日臺灣高雄地方法院刑事庭審判長法官黃三友法官王雅苑法官涂裕洪右正本證明與原本無異。如不服本裁定，應於裁定送達後五日內，向本院提出抗告狀。書記官賴佳慧中華民國九十三年三月十九日",
  "characters": {
    "judges": [
      "黃三友",
      "王雅苑",
      "涂裕洪"
    ],
    "prosecutors": [

    ],
    "lawyers": [
      "劉新安",
      "賴玉山",
      "莊美玉"
    ],
    "clerks": [
      "賴佳慧"
    ],
    "plaintiffs": [

    ],
    "defendants": [
      "甲○○",
      "石真印"
    ],
    "prosecutor_office": [
      "臺灣高雄地方法院檢察署檢察官"
    ],
    "creditors": [

    ],
    "debtors": [

    ],
    "judicial_associate_officer": [

    ]
  },
  "adjudged_at": "2004-03-19",
  "created_at": "2016-02-06 11:18:55",
  "updated_at": "2016-02-06 11:18:55"
}