{
  "identify": "TYD-94-壢簡-55-20050509-1",
  "court": {
    "name": "臺灣桃園地方法院",
    "code": "TYD"
  },
  "division": {
    "name": "刑事",
    "code": "M"
  },
  "year": 94,
  "word": "壢簡",
  "number": "55",
  "jcheck": "1",
  "reason": "傷害",
  "content": "臺灣桃園地方法院刑事簡易判決          94年度壢簡字第55號\n聲  請  人  臺灣桃園地方法院檢察署檢察官\n被      告  甲○○  男  45歲.\n被      告  乙○○  男  46歲.\n上列被告等因傷害案件，經檢察官聲請以簡易判決處刑（93年度\n偵字第9350號），本院判決如左：\n    主  文\n甲○○、乙○○共同傷害人之身體，甲○○處拘役拾日，乙○\n○，累犯，處拘役拾日，如易科罰金，均以參佰元折算壹日。\n    事實及理由\n一、本件犯罪事實、證據，除補充被告乙○○前因違反肅清煙毒\n    條例、麻醉藥品管理條例、偽造文書等案件，於89年10 月\n    23日縮短刑期假釋出監，縮短刑期後刑期期滿日期為92年10\n    月23日，假釋未經撤銷，未執行之刑以已執行論。餘均引用\n    檢察官聲請簡易處刑書所載（如聲請書）。\n二、核被告甲○○、乙○○之所為，均係犯刑法第277 條第1 項\n    之傷害罪。被告2 人就上開傷害之犯行，有犯意聯絡與行為\n    分擔，均為共同正犯。又被告乙○○前因違反肅清煙毒條例\n    、麻醉藥品管理條例、偽造文書等案件，於89年10月23日縮\n    短刑期假釋出監，縮短刑期後刑期期滿日期為92年10 月23\n    日，假釋未經撤銷，未執行之刑以已執行論，有臺灣高等法\n    院被告全國前案記錄表一份附卷可稽，其於刑之執行完畢後\n    ，5 年以內再犯本件有期徒刑以上之罪，為累犯，依刑法第\n    47條規定加重其刑。爰分別審酌被告2 人與告訴人係同一公\n    司之同事，僅因告訴人皮夾失竊懷疑被告甲○○所為，被告\n    甲○○因此心生怨懟，與被告乙○○對告訴人施以暴力，顯\n    乏對自我行為之自制能力，兼衡告訴人所受傷害之程度、被\n    告2 人之素行、智識程度，犯後經合法傳喚均未到庭，亦未\n    與告訴人達成和解之態度等一切情狀，分別量處如主文所示\n    之刑，並均諭知易科罰金之折算標準，以示懲儆。\n三、依刑事訴訟法第449 條第1 項前段、第454 條第2 項，刑法\n    第28條、第277 條第1 項、第47條、第41條第1 項前段，罰\n    金罰鍰提高標準條例第1 條前段、第2 條，逕以簡易判決處\n    如主文所示之刑。\n四、如不服本判決，得自收受送達之日起10日內，向本院提起上\n    訴。\n中    華    民    國    94    年    5     月    9     日\n                  刑事第十二庭    法  官  黃永定\n以上正本證明與原本無異\n                                  書記官  施春祝\n中    華    民    國    94    年    5     月    9     日\n附本案論罪科刑之法條：\n中華民國刑法第277 條\n傷害人之身體或健康者，處三年以下有期徒刑、拘役或一千元以\n下罰金。\n犯前項之罪因而致人於死者，處無期徒刑或七年以上有期徒刑；\n致重傷者，處三年以上十年以下有期徒刑。\n",
  "structure": {
    "main": "甲○○、乙○○共同傷害人之身體，甲○○處拘役拾日，乙○\n○，累犯，處拘役拾日，如易科罰金，均以參佰元折算壹日。",
    "fact": "一、本件犯罪事實、證據，除補充被告乙○○前因違反肅清煙毒\n    條例、麻醉藥品管理條例、偽造文書等案件，於89年10 月\n    23日縮短刑期假釋出監，縮短刑期後刑期期滿日期為92年10\n    月23日，假釋未經撤銷，未執行之刑以已執行論。餘均引用\n    檢察官聲請簡易處刑書所載（如聲請書）。\n二、核被告甲○○、乙○○之所為，均係犯刑法第277 條第1 項\n    之傷害罪。被告2 人就上開傷害之犯行，有犯意聯絡與行為\n    分擔，均為共同正犯。又被告乙○○前因違反肅清煙毒條例\n    、麻醉藥品管理條例、偽造文書等案件，於89年10月23日縮\n    短刑期假釋出監，縮短刑期後刑期期滿日期為92年10 月23\n    日，假釋未經撤銷，未執行之刑以已執行論，有臺灣高等法\n    院被告全國前案記錄表一份附卷可稽，其於刑之執行完畢後\n    ，5 年以內再犯本件有期徒刑以上之罪，為累犯，依刑法第\n    47條規定加重其刑。爰分別審酌被告2 人與告訴人係同一公\n    司之同事，僅因告訴人皮夾失竊懷疑被告甲○○所為，被告\n    甲○○因此心生怨懟，與被告乙○○對告訴人施以暴力，顯\n    乏對自我行為之自制能力，兼衡告訴人所受傷害之程度、被\n    告2 人之素行、智識程度，犯後經合法傳喚均未到庭，亦未\n    與告訴人達成和解之態度等一切情狀，分別量處如主文所示\n    之刑，並均諭知易科罰金之折算標準，以示懲儆。\n三、依刑事訴訟法第449 條第1 項前段、第454 條第2 項，刑法\n    第28條、第277 條第1 項、第47條、第41條第1 項前段，罰\n    金罰鍰提高標準條例第1 條前段、第2 條，逕以簡易判決處\n    如主文所示之刑。\n四、如不服本判決，得自收受送達之日起10日內，向本院提起上\n    訴。",
    "reason": "一、本件犯罪事實、證據，除補充被告乙○○前因違反肅清煙毒\n    條例、麻醉藥品管理條例、偽造文書等案件，於89年10 月\n    23日縮短刑期假釋出監，縮短刑期後刑期期滿日期為92年10\n    月23日，假釋未經撤銷，未執行之刑以已執行論。餘均引用\n    檢察官聲請簡易處刑書所載（如聲請書）。\n二、核被告甲○○、乙○○之所為，均係犯刑法第277 條第1 項\n    之傷害罪。被告2 人就上開傷害之犯行，有犯意聯絡與行為\n    分擔，均為共同正犯。又被告乙○○前因違反肅清煙毒條例\n    、麻醉藥品管理條例、偽造文書等案件，於89年10月23日縮\n    短刑期假釋出監，縮短刑期後刑期期滿日期為92年10 月23\n    日，假釋未經撤銷，未執行之刑以已執行論，有臺灣高等法\n    院被告全國前案記錄表一份附卷可稽，其於刑之執行完畢後\n    ，5 年以內再犯本件有期徒刑以上之罪，為累犯，依刑法第\n    47條規定加重其刑。爰分別審酌被告2 人與告訴人係同一公\n    司之同事，僅因告訴人皮夾失竊懷疑被告甲○○所為，被告\n    甲○○因此心生怨懟，與被告乙○○對告訴人施以暴力，顯\n    乏對自我行為之自制能力，兼衡告訴人所受傷害之程度、被\n    告2 人之素行、智識程度，犯後經合法傳喚均未到庭，亦未\n    與告訴人達成和解之態度等一切情狀，分別量處如主文所示\n    之刑，並均諭知易科罰金之折算標準，以示懲儆。\n三、依刑事訴訟法第449 條第1 項前段、第454 條第2 項，刑法\n    第28條、第277 條第1 項、第47條、第41條第1 項前段，罰\n    金罰鍰提高標準條例第1 條前段、第2 條，逕以簡易判決處\n    如主文所示之刑。\n四、如不服本判決，得自收受送達之日起10日內，向本院提起上\n    訴。"
  },
  "search": "臺灣桃園地方法院刑事簡易判決94年度壢簡字第55號聲請人臺灣桃園地方法院檢察署檢察官被告甲○○男45歲.被告乙○○男46歲.上列被告等因傷害案件，經檢察官聲請以簡易判決處刑（93年度偵字第9350號），本院判決如左：主文甲○○、乙○○共同傷害人之身體，甲○○處拘役拾日，乙○○，累犯，處拘役拾日，如易科罰金，均以參佰元折算壹日。事實及理由一、本件犯罪事實、證據，除補充被告乙○○前因違反肅清煙毒條例、麻醉藥品管理條例、偽造文書等案件，於89年10月23日縮短刑期假釋出監，縮短刑期後刑期期滿日期為92年10月23日，假釋未經撤銷，未執行之刑以已執行論。餘均引用檢察官聲請簡易處刑書所載（如聲請書）。二、核被告甲○○、乙○○之所為，均係犯刑法第277條第1項之傷害罪。被告2人就上開傷害之犯行，有犯意聯絡與行為分擔，均為共同正犯。又被告乙○○前因違反肅清煙毒條例、麻醉藥品管理條例、偽造文書等案件，於89年10月23日縮短刑期假釋出監，縮短刑期後刑期期滿日期為92年10月23日，假釋未經撤銷，未執行之刑以已執行論，有臺灣高等法院被告全國前案記錄表一份附卷可稽，其於刑之執行完畢後，5年以內再犯本件有期徒刑以上之罪，為累犯，依刑法第47條規定加重其刑。爰分別審酌被告2人與告訴人係同一公司之同事，僅因告訴人皮夾失竊懷疑被告甲○○所為，被告甲○○因此心生怨懟，與被告乙○○對告訴人施以暴力，顯乏對自我行為之自制能力，兼衡告訴人所受傷害之程度、被告2人之素行、智識程度，犯後經合法傳喚均未到庭，亦未與告訴人達成和解之態度等一切情狀，分別量處如主文所示之刑，並均諭知易科罰金之折算標準，以示懲儆。三、依刑事訴訟法第449條第1項前段、第454條第2項，刑法第28條、第277條第1項、第47條、第41條第1項前段，罰金罰鍰提高標準條例第1條前段、第2條，逕以簡易判決處如主文所示之刑。四、如不服本判決，得自收受送達之日起10日內，向本院提起上訴。中華民國94年5月9日刑事第十二庭法官黃永定以上正本證明與原本無異書記官施春祝中華民國94年5月9日附本案論罪科刑之法條：中華民國刑法第277條傷害人之身體或健康者，處三年以下有期徒刑、拘役或一千元以下罰金。犯前項之罪因而致人於死者，處無期徒刑或七年以上有期徒刑；致重傷者，處三年以上十年以下有期徒刑。",
  "characters": {
    "judges": [
      "黃永定"
    ],
    "prosecutors": [

    ],
    "lawyers": [

    ],
    "clerks": [
      "施春祝"
    ],
    "plaintiffs": [

    ],
    "defendants": [
      "甲○○  男  45歲.",
      "被      告  乙○○  男  46歲."
    ],
    "prosecutor_office": [
      "臺灣桃園地方法院檢察署檢察官"
    ],
    "creditors": [

    ],
    "debtors": [

    ],
    "judicial_associate_officer": [

    ]
  },
  "adjudged_at": "2005-05-09",
  "created_at": "2016-02-06 15:08:59",
  "updated_at": "2016-02-06 15:08:59"
}