{
  "identify": "PCD-93-交簡附民-69-20040709-1",
  "court": {
    "name": "臺灣新北地方法院",
    "code": "PCD"
  },
  "division": {
    "name": "刑事",
    "code": "M"
  },
  "year": 93,
  "word": "交簡附民",
  "number": "69",
  "jcheck": "1",
  "reason": "過失傷害",
  "content": "臺灣板橋地方法院刑事附帶民事訴訟判決          九十三年度交簡附民字第六九號\n    原      告  乙○○\n    被      告  甲○○\n右列被告因傷害案件，經原告提起附帶民事訴訟，本院判決如左：\n    主  文\n原告之訴駁回。\n    事  實\n甲、原告方面：\n    壹、聲明：求為判決被告應給付原告新臺幣〔下同〕伍拾萬元，並自民國〔下同\n              〕九十二年九月二十二日起，至清償日止，按年息百分月伍計算之利\n              息。\n    貳、陳述：如刑事附帶民事起訴狀所載〔如附件〕          。\n乙、被告未為任何聲明或陳述，亦未提出任何書狀。\n    理  由\n甲、按提起附帶民事訴訟，應於刑事訴訟起訴後第二審辯論終結前為之，但在第一審\n    辯論終結後提起上訴前，不得提起，刑事訴訟法第四百八十八條定有明文。\n乙、查本件刑事附帶民事訴訟，係於『九十三年六月二十四日』繫屬本院，此有本院\n    收狀戳記足參。查被告甲○○被訴過失傷害案件，業經本院以九十三年度交簡字\n    第一九五號刑事簡易判決判處「甲○○過失傷害人，處拘役肆拾日，如易科罰金\n    ，以參佰元折算壹日。」，於九十三年五月十八日確定，嗣已移送執行。原告於\n    上開刑事案件終結並確定『後』，始提起本件附帶民事訴訟，顯有未合，原告之\n    訴自應予以駁回。\n結論：依民事訴訟法第五百零二條第一項，判決如主文。\n中      華      民      國    九十三    年      七      月      九      日\n                            臺灣板橋地方法院交通法庭\n                                審判長法  官  鄭水銓\n                                      法  官  侯志融\n                                      法  官  陳福來\n右正本證明與原本無異。\n對於本判決如有不服，應於送達後十日內，向本院提出上訴狀，但非對刑事訴訟之判\n                                      書記官  林兆嘉\n中      華      民      國    九十三    年      七      月      九      日\n",
  "structure": {
    "main": "原告之訴駁回。",
    "fact": "甲、原告方面：\n    壹、聲明：求為判決被告應給付原告新臺幣〔下同〕伍拾萬元，並自民國〔下同\n              〕九十二年九月二十二日起，至清償日止，按年息百分月伍計算之利\n              息。\n    貳、陳述：如刑事附帶民事起訴狀所載〔如附件〕          。\n乙、被告未為任何聲明或陳述，亦未提出任何書狀。",
    "reason": "甲、按提起附帶民事訴訟，應於刑事訴訟起訴後第二審辯論終結前為之，但在第一審\n    辯論終結後提起上訴前，不得提起，刑事訴訟法第四百八十八條定有明文。\n乙、查本件刑事附帶民事訴訟，係於『九十三年六月二十四日』繫屬本院，此有本院\n    收狀戳記足參。查被告甲○○被訴過失傷害案件，業經本院以九十三年度交簡字\n    第一九五號刑事簡易判決判處「甲○○過失傷害人，處拘役肆拾日，如易科罰金\n    ，以參佰元折算壹日。」，於九十三年五月十八日確定，嗣已移送執行。原告於\n    上開刑事案件終結並確定『後』，始提起本件附帶民事訴訟，顯有未合，原告之\n    訴自應予以駁回。\n結論：依民事訴訟法第五百零二條第一項，判決如主文。\n中      華      民      國    九十三    年      七      月      九      日\n                            臺灣板橋地方法院交通法庭\n                                審判長法  官  鄭水銓\n                                      法  官  侯志融\n                                      法  官  陳福來\n右正本證明與原本無異。\n對於本判決如有不服，應於送達後十日內，向本院提出上訴狀，但非對刑事訴訟之判\n                                      書記官  林兆嘉"
  },
  "search": "臺灣板橋地方法院刑事附帶民事訴訟判決九十三年度交簡附民字第六九號原告乙○○被告甲○○右列被告因傷害案件，經原告提起附帶民事訴訟，本院判決如左：主文原告之訴駁回。事實甲、原告方面：壹、聲明：求為判決被告應給付原告新臺幣〔下同〕伍拾萬元，並自民國〔下同〕九十二年九月二十二日起，至清償日止，按年息百分月伍計算之利息。貳、陳述：如刑事附帶民事起訴狀所載〔如附件〕。乙、被告未為任何聲明或陳述，亦未提出任何書狀。理由甲、按提起附帶民事訴訟，應於刑事訴訟起訴後第二審辯論終結前為之，但在第一審辯論終結後提起上訴前，不得提起，刑事訴訟法第四百八十八條定有明文。乙、查本件刑事附帶民事訴訟，係於『九十三年六月二十四日』繫屬本院，此有本院收狀戳記足參。查被告甲○○被訴過失傷害案件，業經本院以九十三年度交簡字第一九五號刑事簡易判決判處「甲○○過失傷害人，處拘役肆拾日，如易科罰金，以參佰元折算壹日。」，於九十三年五月十八日確定，嗣已移送執行。原告於上開刑事案件終結並確定『後』，始提起本件附帶民事訴訟，顯有未合，原告之訴自應予以駁回。結論：依民事訴訟法第五百零二條第一項，判決如主文。中華民國九十三年七月九日臺灣板橋地方法院交通法庭審判長法官鄭水銓法官侯志融法官陳福來右正本證明與原本無異。對於本判決如有不服，應於送達後十日內，向本院提出上訴狀，但非對刑事訴訟之判書記官林兆嘉中華民國九十三年七月九日",
  "characters": {
    "judges": [
      "鄭水銓",
      "侯志融",
      "陳福來"
    ],
    "prosecutors": [

    ],
    "lawyers": [

    ],
    "clerks": [
      "林兆嘉"
    ],
    "plaintiffs": [
      "乙"
    ],
    "defendants": [
      "甲○○",
      "右列被告因傷害案件，經原告提起附帶民事訴訟，本院判決如左："
    ],
    "prosecutor_office": [

    ],
    "creditors": [

    ],
    "debtors": [

    ],
    "judicial_associate_officer": [

    ]
  },
  "adjudged_at": "2004-07-09",
  "created_at": "2016-02-06 12:10:19",
  "updated_at": "2016-02-06 12:10:19"
}