{
  "identify": "KSD-93-簡-6411-20041230-1",
  "court": {
    "name": "臺灣高雄地方法院",
    "code": "KSD"
  },
  "division": {
    "name": "刑事",
    "code": "M"
  },
  "year": 93,
  "word": "簡",
  "number": "6411",
  "jcheck": "1",
  "reason": "妨害兵役",
  "content": "臺灣高雄地方法院刑事簡易判決                    九十三年度簡字第六四一一號\n    聲  請  人  臺灣高雄地方法院檢察署檢察官\n    被      告  甲○○  男  二.\n右列被告因妨害兵役案件，經檢察官聲請以簡易判決處刑（九十三年度偵字第二二九\n０五號），本院判決如左：\n    主  文\n甲○○後備軍人，意圖避免教育召集，居住處所遷移，無故不依規定申報，致使教育\n召集令無法送達，處有期徒刑月，如易科罰金，以參佰元折算壹日。\n    事實及理由\n一、本件犯罪事實及證據，事實部分補充：「由高雄縣政府警察局仁武分局大社分駐\n    所警員林基狄於民國九十三年九月二十三日負責送達甲○○之教育召集令，因甲\n    ○○未居住在\n    後備軍人身分，此為被告所明知，其應知悉未辦理\n    受召集令之結果，乃又未依規定辦理\n    」外，其餘均引用檢察官聲請簡易判決處刑書之記載（如附件）。\n二、查被告係依法退伍之人員，屬兵役法第二十七條之後備軍人，依軍事需要，於舉\n    行訓練或演習時，有受教育召集之義務，被告竟未向戶政事務所或警察機關申報\n    治罪條例第十條第一項第三款、第三項之規定，應依同條例第六條第一項規定科\n    刑。爰審酌被告無故未依規定申報住所遷移致犯本罪之行為，損害役政管理之正\n    確性，並衡其犯罪動機單純、所生危害尚微等一切情狀，量處如主文所示之刑，\n    並諭知易科罰金之折算標準，以資懲儆。\n三、依刑事訴訟法第四百四十九條第一項前段、第三項、第四百五十四條第二項，妨\n    害兵役治罪條例第十條第一項第三款、第三項、第六條第一項，刑法第十一條前\n    段、第四十一條第一項前段、第七十四條第一款，罰金罰鍰提高標準條例第二條\n    ，逕以簡易判決處如主文所示之刑。\n四、如不服本判決，應於送達後十日內，向本院提出上訴狀。\n中      華      民      國    九十三    年      十二    月    三十      日\n                                臺灣高雄地方法院高雄簡易庭\n                                    法  官  郭瓊徽\n右正本證明與原本無異。\n如不服本判決，應於判決送達後十日內，向本院提出上訴狀。\n                                    書記官  陳瓊芳\n中      華      民      國    九十四    年      一      月      三      日\n【附錄本判決論罪科刑法條】\n妨害兵役治罪條例第十條\n後備軍人意圖避免召集處理有下列行為之一者，處一年以下有期徒刑、拘役或科新臺\n幣九萬元以下罰金：一離營歸鄉無故不依規定報到，或重複申報戶籍者。\n二  拒絕依規定調查，或體格檢查不到者。\n三  居住處所遷移，無故不依規定申報者。\n國民兵犯前項第三款之罪者，處六月以下有期徒刑、拘役或科新臺幣三萬元以下罰金\n。\n後備軍人犯第一項之罪或國民兵犯前項之罪，致使召集令無法送達者，以意圖避免召\n集論；分別依第五條或第六條科刑。\n妨害兵役治罪條例第六條\n意圖避免教育召集或勤務召集，而有下列行為之一者，處三年以下有期徒刑：\n一  捏造免役、除役、轉役或免除召集原因者。\n二  毀傷身體者。\n三  拒絕接受召集令者。\n四  應受召集，無故逾應召期限二日者。\n五  使人頂替本人應召者。\n無故不參加點閱召集，或意圖避免點閱召集，而有前項第一款至第三款及第五款行為\n之一者，處一年以下有期徒刑、拘役或科新臺幣九萬元以下罰金。\n國民兵為避免應召集輔助軍事勤務犯第一項之罪者，處三年以下有期徒刑。\n",
  "structure": {
    "main": "甲○○後備軍人，意圖避免教育召集，居住處所遷移，無故不依規定申報，致使教育\n召集令無法送達，處有期徒刑月，如易科罰金，以參佰元折算壹日。",
    "fact": "一、本件犯罪事實及證據，事實部分補充：「由高雄縣政府警察局仁武分局大社分駐\n    所警員林基狄於民國九十三年九月二十三日負責送達甲○○之教育召集令，因甲\n    ○○未居住在\n    後備軍人身分，此為被告所明知，其應知悉未辦理\n    受召集令之結果，乃又未依規定辦理\n    」外，其餘均引用檢察官聲請簡易判決處刑書之記載（如附件）。\n二、查被告係依法退伍之人員，屬兵役法第二十七條之後備軍人，依軍事需要，於舉\n    行訓練或演習時，有受教育召集之義務，被告竟未向戶政事務所或警察機關申報\n    治罪條例第十條第一項第三款、第三項之規定，應依同條例第六條第一項規定科\n    刑。爰審酌被告無故未依規定申報住所遷移致犯本罪之行為，損害役政管理之正\n    確性，並衡其犯罪動機單純、所生危害尚微等一切情狀，量處如主文所示之刑，\n    並諭知易科罰金之折算標準，以資懲儆。\n三、依刑事訴訟法第四百四十九條第一項前段、第三項、第四百五十四條第二項，妨\n    害兵役治罪條例第十條第一項第三款、第三項、第六條第一項，刑法第十一條前\n    段、第四十一條第一項前段、第七十四條第一款，罰金罰鍰提高標準條例第二條\n    ，逕以簡易判決處如主文所示之刑。\n四、如不服本判決，應於送達後十日內，向本院提出上訴狀。",
    "reason": "一、本件犯罪事實及證據，事實部分補充：「由高雄縣政府警察局仁武分局大社分駐\n    所警員林基狄於民國九十三年九月二十三日負責送達甲○○之教育召集令，因甲\n    ○○未居住在\n    後備軍人身分，此為被告所明知，其應知悉未辦理\n    受召集令之結果，乃又未依規定辦理\n    」外，其餘均引用檢察官聲請簡易判決處刑書之記載（如附件）。\n二、查被告係依法退伍之人員，屬兵役法第二十七條之後備軍人，依軍事需要，於舉\n    行訓練或演習時，有受教育召集之義務，被告竟未向戶政事務所或警察機關申報\n    治罪條例第十條第一項第三款、第三項之規定，應依同條例第六條第一項規定科\n    刑。爰審酌被告無故未依規定申報住所遷移致犯本罪之行為，損害役政管理之正\n    確性，並衡其犯罪動機單純、所生危害尚微等一切情狀，量處如主文所示之刑，\n    並諭知易科罰金之折算標準，以資懲儆。\n三、依刑事訴訟法第四百四十九條第一項前段、第三項、第四百五十四條第二項，妨\n    害兵役治罪條例第十條第一項第三款、第三項、第六條第一項，刑法第十一條前\n    段、第四十一條第一項前段、第七十四條第一款，罰金罰鍰提高標準條例第二條\n    ，逕以簡易判決處如主文所示之刑。\n四、如不服本判決，應於送達後十日內，向本院提出上訴狀。"
  },
  "search": "臺灣高雄地方法院刑事簡易判決九十三年度簡字第六四一一號聲請人臺灣高雄地方法院檢察署檢察官被告甲○○男二.右列被告因妨害兵役案件，經檢察官聲請以簡易判決處刑（九十三年度偵字第二二九０五號），本院判決如左：主文甲○○後備軍人，意圖避免教育召集，居住處所遷移，無故不依規定申報，致使教育召集令無法送達，處有期徒刑月，如易科罰金，以參佰元折算壹日。事實及理由一、本件犯罪事實及證據，事實部分補充：「由高雄縣政府警察局仁武分局大社分駐所警員林基狄於民國九十三年九月二十三日負責送達甲○○之教育召集令，因甲○○未居住在後備軍人身分，此為被告所明知，其應知悉未辦理受召集令之結果，乃又未依規定辦理」外，其餘均引用檢察官聲請簡易判決處刑書之記載（如附件）。二、查被告係依法退伍之人員，屬兵役法第二十七條之後備軍人，依軍事需要，於舉行訓練或演習時，有受教育召集之義務，被告竟未向戶政事務所或警察機關申報治罪條例第十條第一項第三款、第三項之規定，應依同條例第六條第一項規定科刑。爰審酌被告無故未依規定申報住所遷移致犯本罪之行為，損害役政管理之正確性，並衡其犯罪動機單純、所生危害尚微等一切情狀，量處如主文所示之刑，並諭知易科罰金之折算標準，以資懲儆。三、依刑事訴訟法第四百四十九條第一項前段、第三項、第四百五十四條第二項，妨害兵役治罪條例第十條第一項第三款、第三項、第六條第一項，刑法第十一條前段、第四十一條第一項前段、第七十四條第一款，罰金罰鍰提高標準條例第二條，逕以簡易判決處如主文所示之刑。四、如不服本判決，應於送達後十日內，向本院提出上訴狀。中華民國九十三年十二月三十日臺灣高雄地方法院高雄簡易庭法官郭瓊徽右正本證明與原本無異。如不服本判決，應於判決送達後十日內，向本院提出上訴狀。書記官陳瓊芳中華民國九十四年一月三日【附錄本判決論罪科刑法條】妨害兵役治罪條例第十條後備軍人意圖避免召集處理有下列行為之一者，處一年以下有期徒刑、拘役或科新臺幣九萬元以下罰金：一離營歸鄉無故不依規定報到，或重複申報戶籍者。二拒絕依規定調查，或體格檢查不到者。三居住處所遷移，無故不依規定申報者。國民兵犯前項第三款之罪者，處六月以下有期徒刑、拘役或科新臺幣三萬元以下罰金。後備軍人犯第一項之罪或國民兵犯前項之罪，致使召集令無法送達者，以意圖避免召集論；分別依第五條或第六條科刑。妨害兵役治罪條例第六條意圖避免教育召集或勤務召集，而有下列行為之一者，處三年以下有期徒刑：一捏造免役、除役、轉役或免除召集原因者。二毀傷身體者。三拒絕接受召集令者。四應受召集，無故逾應召期限二日者。五使人頂替本人應召者。無故不參加點閱召集，或意圖避免點閱召集，而有前項第一款至第三款及第五款行為之一者，處一年以下有期徒刑、拘役或科新臺幣九萬元以下罰金。國民兵為避免應召集輔助軍事勤務犯第一項之罪者，處三年以下有期徒刑。",
  "characters": {
    "judges": [
      "郭瓊徽"
    ],
    "prosecutors": [

    ],
    "lawyers": [

    ],
    "clerks": [
      "陳瓊芳"
    ],
    "plaintiffs": [

    ],
    "defendants": [
      "甲○○  男  二.",
      "右列被告因妨害兵役案件，經檢察官聲請以簡易判決處刑（九十三年度偵字第二二九",
      "０五號），本院判決如左："
    ],
    "prosecutor_office": [
      "臺灣高雄地方法院檢察署檢察官"
    ],
    "creditors": [

    ],
    "debtors": [

    ],
    "judicial_associate_officer": [

    ]
  },
  "adjudged_at": "2004-12-30",
  "created_at": "2016-02-06 07:50:56",
  "updated_at": "2016-02-06 07:50:56"
}