{
  "identify": "KSD-93-交易-305-20041231-1",
  "court": {
    "name": "臺灣高雄地方法院",
    "code": "KSD"
  },
  "division": {
    "name": "刑事",
    "code": "M"
  },
  "year": 93,
  "word": "交易",
  "number": "305",
  "jcheck": "1",
  "reason": "過失傷害",
  "content": "臺灣高雄地方法院刑事簡易判決                    九十三年度交易字第三Ｏ五號\n    公  訴  人  臺灣高雄地方法院檢察署檢察官\n    被      告  丙○○\n右列被告因過失傷害案件，經檢察官聲請簡易判決處刑（九十三年度偵字第一三二一\n五號），本院認為不宜簡易判決處刑，改依通常程序審判，木院判決如左：\n    主  文\n本件公訴不受理。\n    事實及理由\n一、公訴意旨係以：被告丙○○於民國九十三年六月十二日二十三時五十分許，駕駛\n    向曾忠正租用車牌號碼四四一一—ＪＭ號自用小各車，沿高雄縣鳥松鄉○○路南\n    向北方向行駛，途經該路一ＯＯ號前時，理應注意汽車行駛時，駕駛人應注意直\n    前狀況，並隨時採取必要之安全措施，而依當時晴形，又無不能注意之情事，竟\n    疏於注意，貿然行駛，未注意車前路況，不慎從後擦撞行駛該路同向．由甲○○\n    所駕駛搭載乙○○車牌號碼Ｓ四—四七一六號自小貨車，致甲○○所駕車失控往\n    前偏離撞及路旁之電線桿，致乙○○受有頭部外傷之傷害，因認被告丙○○所為\n    ，涉犯刑法第二百八十四條第一項前段過失傷害罪嫌等語。\n二、按告訴乃論之罪，告訴人於第一審辯論終結前，得撤回其告訴；又告訴經撤回者\n    法院應諭知不受理之判決，刑事訴訟法第二百三十八條第一項、第三百零三條第\n    三款分別定有明文。另刑事事件於偵查中或第一審法院辯論終結前，調解成立，\n    經法院核定，並經當事人同意撤回者，視為於調解成立時撤回告訴，鄉鎮市調解\n    條例第二十五條第二項定有明文\n三、查本件被告丙○○涉犯過失傷害案件，經檢察官聲請簡易判決處刑，認被告係犯\n    刑法第二百八十四條第一項前段過失傷害罪，依同法第二百八十七條前段之規定\n    須告訴乃論。茲據告訴人乙○○與被告間已經於九十三年十月二十六日由高雄縣\n    鳥松鄉調解委員會調解成立，告訴人乙○○表示不再追究被告之刑事責任，並經\n    法院於九十三年十一月十八日核定，有高雄縣鳥松鄉調解委員會調解書一份在卷\n    可憑（附於本院九十三年交簡字第二五一六號卷），依前述規定，本件視為撤回\n    告訴，依照前開說明，爰不經言詞辯論，逕為諭知不受理之判決。\n四、被告丙○○被訴刑法第一百七十一條第一項、刑法第一百八十五條之四罪嫌部分\n    ，經本院高雄簡易庭另以九十三年度交簡字第二五一六號審結，附此敘明。\n據上論斷，應依刑事訴訟法第四百五十二條、第三百零三條第三款、第三百零七條，\n判決如主文。\n中      華      民      國    九十三    年    十二      月    三十一    日\n                                  臺灣高雄地方法院交通法庭\n                                      法  官  陳億芳\n右正本，係照原本作成，證明與原本無異。\n如不服本判決，應於收受送達後十日內向本院提出上訴書狀。\n                                      書記官  林國龍\n中      華      民      國    九十四    年      一      月      四      日\n",
  "structure": {
    "main": "本件公訴不受理。",
    "fact": "一、公訴意旨係以：被告丙○○於民國九十三年六月十二日二十三時五十分許，駕駛\n    向曾忠正租用車牌號碼四四一一—ＪＭ號自用小各車，沿高雄縣鳥松鄉○○路南\n    向北方向行駛，途經該路一ＯＯ號前時，理應注意汽車行駛時，駕駛人應注意直\n    前狀況，並隨時採取必要之安全措施，而依當時晴形，又無不能注意之情事，竟\n    疏於注意，貿然行駛，未注意車前路況，不慎從後擦撞行駛該路同向．由甲○○\n    所駕駛搭載乙○○車牌號碼Ｓ四—四七一六號自小貨車，致甲○○所駕車失控往\n    前偏離撞及路旁之電線桿，致乙○○受有頭部外傷之傷害，因認被告丙○○所為\n    ，涉犯刑法第二百八十四條第一項前段過失傷害罪嫌等語。\n二、按告訴乃論之罪，告訴人於第一審辯論終結前，得撤回其告訴；又告訴經撤回者\n    法院應諭知不受理之判決，刑事訴訟法第二百三十八條第一項、第三百零三條第\n    三款分別定有明文。另刑事事件於偵查中或第一審法院辯論終結前，調解成立，\n    經法院核定，並經當事人同意撤回者，視為於調解成立時撤回告訴，鄉鎮市調解\n    條例第二十五條第二項定有明文\n三、查本件被告丙○○涉犯過失傷害案件，經檢察官聲請簡易判決處刑，認被告係犯\n    刑法第二百八十四條第一項前段過失傷害罪，依同法第二百八十七條前段之規定\n    須告訴乃論。茲據告訴人乙○○與被告間已經於九十三年十月二十六日由高雄縣\n    鳥松鄉調解委員會調解成立，告訴人乙○○表示不再追究被告之刑事責任，並經\n    法院於九十三年十一月十八日核定，有高雄縣鳥松鄉調解委員會調解書一份在卷\n    可憑（附於本院九十三年交簡字第二五一六號卷），依前述規定，本件視為撤回\n    告訴，依照前開說明，爰不經言詞辯論，逕為諭知不受理之判決。\n四、被告丙○○被訴刑法第一百七十一條第一項、刑法第一百八十五條之四罪嫌部分\n    ，經本院高雄簡易庭另以九十三年度交簡字第二五一六號審結，附此敘明。\n據上論斷，應依刑事訴訟法第四百五十二條、第三百零三條第三款、第三百零七條，\n判決如主文。",
    "reason": "一、公訴意旨係以：被告丙○○於民國九十三年六月十二日二十三時五十分許，駕駛\n    向曾忠正租用車牌號碼四四一一—ＪＭ號自用小各車，沿高雄縣鳥松鄉○○路南\n    向北方向行駛，途經該路一ＯＯ號前時，理應注意汽車行駛時，駕駛人應注意直\n    前狀況，並隨時採取必要之安全措施，而依當時晴形，又無不能注意之情事，竟\n    疏於注意，貿然行駛，未注意車前路況，不慎從後擦撞行駛該路同向．由甲○○\n    所駕駛搭載乙○○車牌號碼Ｓ四—四七一六號自小貨車，致甲○○所駕車失控往\n    前偏離撞及路旁之電線桿，致乙○○受有頭部外傷之傷害，因認被告丙○○所為\n    ，涉犯刑法第二百八十四條第一項前段過失傷害罪嫌等語。\n二、按告訴乃論之罪，告訴人於第一審辯論終結前，得撤回其告訴；又告訴經撤回者\n    法院應諭知不受理之判決，刑事訴訟法第二百三十八條第一項、第三百零三條第\n    三款分別定有明文。另刑事事件於偵查中或第一審法院辯論終結前，調解成立，\n    經法院核定，並經當事人同意撤回者，視為於調解成立時撤回告訴，鄉鎮市調解\n    條例第二十五條第二項定有明文\n三、查本件被告丙○○涉犯過失傷害案件，經檢察官聲請簡易判決處刑，認被告係犯\n    刑法第二百八十四條第一項前段過失傷害罪，依同法第二百八十七條前段之規定\n    須告訴乃論。茲據告訴人乙○○與被告間已經於九十三年十月二十六日由高雄縣\n    鳥松鄉調解委員會調解成立，告訴人乙○○表示不再追究被告之刑事責任，並經\n    法院於九十三年十一月十八日核定，有高雄縣鳥松鄉調解委員會調解書一份在卷\n    可憑（附於本院九十三年交簡字第二五一六號卷），依前述規定，本件視為撤回\n    告訴，依照前開說明，爰不經言詞辯論，逕為諭知不受理之判決。\n四、被告丙○○被訴刑法第一百七十一條第一項、刑法第一百八十五條之四罪嫌部分\n    ，經本院高雄簡易庭另以九十三年度交簡字第二五一六號審結，附此敘明。\n據上論斷，應依刑事訴訟法第四百五十二條、第三百零三條第三款、第三百零七條，\n判決如主文。"
  },
  "search": "臺灣高雄地方法院刑事簡易判決九十三年度交易字第三Ｏ五號公訴人臺灣高雄地方法院檢察署檢察官被告丙○○右列被告因過失傷害案件，經檢察官聲請簡易判決處刑（九十三年度偵字第一三二一五號），本院認為不宜簡易判決處刑，改依通常程序審判，木院判決如左：主文本件公訴不受理。事實及理由一、公訴意旨係以：被告丙○○於民國九十三年六月十二日二十三時五十分許，駕駛向曾忠正租用車牌號碼四四一一—ＪＭ號自用小各車，沿高雄縣鳥松鄉○○路南向北方向行駛，途經該路一ＯＯ號前時，理應注意汽車行駛時，駕駛人應注意直前狀況，並隨時採取必要之安全措施，而依當時晴形，又無不能注意之情事，竟疏於注意，貿然行駛，未注意車前路況，不慎從後擦撞行駛該路同向．由甲○○所駕駛搭載乙○○車牌號碼Ｓ四—四七一六號自小貨車，致甲○○所駕車失控往前偏離撞及路旁之電線桿，致乙○○受有頭部外傷之傷害，因認被告丙○○所為，涉犯刑法第二百八十四條第一項前段過失傷害罪嫌等語。二、按告訴乃論之罪，告訴人於第一審辯論終結前，得撤回其告訴；又告訴經撤回者法院應諭知不受理之判決，刑事訴訟法第二百三十八條第一項、第三百零三條第三款分別定有明文。另刑事事件於偵查中或第一審法院辯論終結前，調解成立，經法院核定，並經當事人同意撤回者，視為於調解成立時撤回告訴，鄉鎮市調解條例第二十五條第二項定有明文三、查本件被告丙○○涉犯過失傷害案件，經檢察官聲請簡易判決處刑，認被告係犯刑法第二百八十四條第一項前段過失傷害罪，依同法第二百八十七條前段之規定須告訴乃論。茲據告訴人乙○○與被告間已經於九十三年十月二十六日由高雄縣鳥松鄉調解委員會調解成立，告訴人乙○○表示不再追究被告之刑事責任，並經法院於九十三年十一月十八日核定，有高雄縣鳥松鄉調解委員會調解書一份在卷可憑（附於本院九十三年交簡字第二五一六號卷），依前述規定，本件視為撤回告訴，依照前開說明，爰不經言詞辯論，逕為諭知不受理之判決。四、被告丙○○被訴刑法第一百七十一條第一項、刑法第一百八十五條之四罪嫌部分，經本院高雄簡易庭另以九十三年度交簡字第二五一六號審結，附此敘明。據上論斷，應依刑事訴訟法第四百五十二條、第三百零三條第三款、第三百零七條，判決如主文。中華民國九十三年十二月三十一日臺灣高雄地方法院交通法庭法官陳億芳右正本，係照原本作成，證明與原本無異。如不服本判決，應於收受送達後十日內向本院提出上訴書狀。書記官林國龍中華民國九十四年一月四日",
  "characters": {
    "judges": [
      "陳億芳"
    ],
    "prosecutors": [

    ],
    "lawyers": [

    ],
    "clerks": [
      "林國龍"
    ],
    "plaintiffs": [

    ],
    "defendants": [
      "丙○○",
      "右列被告因過失傷害案件，經檢察官聲請簡易判決處刑（九十三年度偵字第一三二一",
      "五號），本院認為不宜簡易判決處刑，改依通常程序審判，木院判決如左："
    ],
    "prosecutor_office": [
      "臺灣高雄地方法院檢察署檢察官"
    ],
    "creditors": [

    ],
    "debtors": [

    ],
    "judicial_associate_officer": [

    ]
  },
  "adjudged_at": "2004-12-31",
  "created_at": "2016-02-06 07:46:58",
  "updated_at": "2016-02-06 07:46:58"
}