{
  "identify": "SCD-93-竹簡-882-20041231-1",
  "court": {
    "name": "臺灣新竹地方法院",
    "code": "SCD"
  },
  "division": {
    "name": "刑事",
    "code": "M"
  },
  "year": 93,
  "word": "竹簡",
  "number": "882",
  "jcheck": "1",
  "reason": "竊盜",
  "content": "臺灣新竹地方法院刑事簡易判決                    九十三年度竹簡字第八八二號\n    聲  請  人  臺灣新竹地方法院檢察署檢察官\n    被      告  乙○○○\n右列被告因竊盜案件，經檢察官聲請以簡易判決處刑（九十三年度速偵字第一０六八\n號），本院判決如左：\n    主      文\n乙○○○竊盜，處拘役拾日，如易科罰金以佰元折算壹日。緩刑貳年。\n    事實及理由\n一、本件犯罪事實、證據，除犯罪事實欄：「第二行，美華泰流行生活館內，徒手竊\n    取甲○○所持有：：」應予更正外，餘均引用檢察官聲請簡易判決處刑書之記載\n    （如附件）。\n二、爰審酌被告不循正途謀取財物、本案犯罪之方法、被害人所受之損失及犯後態度\n    等一切情狀，量處如主文所示之刑，並諭知易科罰金之折算標準。末查，被告前\n    未曾受有期徒刑以上刑之宣告，有臺灣高等法院被告全國前案紀錄表一份附卷可\n    稽，其因一時失慮，偶罹刑典，諒經此偵審科刑宣告之教訓，當已足資促使其有\n    所警惕而無再犯之虞，本院因認前所宣告之刑，以暫不執行為適當，爰依刑法第\n    七十四條第一款之規定，併予宣告緩刑，以啟自新。\n三、依刑事訴訟法第四百四十九條第一項、第四百五十條第一項、第四百五十四條第\n    二項，刑法第三百二十條第一項、第四十一條第一項、第七十四條第一款，罰金\n    罰鍰提高標準條例第一條前段、第二條，逕以簡易判決處如主文所示之刑。\n四、如不服本判決，得自收受送達之日起十日內，向本院提起上訴。\n中      華      民      國    九十三    年     十二    月   三十一      日\n                                    臺灣新竹地方法院簡易庭\n                                        法  官  彭淑苑\n右正本證明與原本無異\n                                        書記官  蕭利峰\n中      華      民      國    九十三    年     十二    月   三十一      日\n附錄實體處罰條文：\n中華民國刑法第三百二十條第一項 (普通竊盜罪)\n意圖為自己或第三人不法之所有，而竊取他人之動產者，為竊盜罪，處五年以下有期\n徒刑、拘役或五百元以下罰金。\n",
  "structure": {
    "main": "乙○○○竊盜，處拘役拾日，如易科罰金以佰元折算壹日。緩刑貳年。",
    "fact": "一、本件犯罪事實、證據，除犯罪事實欄：「第二行，美華泰流行生活館內，徒手竊\n    取甲○○所持有：：」應予更正外，餘均引用檢察官聲請簡易判決處刑書之記載\n    （如附件）。\n二、爰審酌被告不循正途謀取財物、本案犯罪之方法、被害人所受之損失及犯後態度\n    等一切情狀，量處如主文所示之刑，並諭知易科罰金之折算標準。末查，被告前\n    未曾受有期徒刑以上刑之宣告，有臺灣高等法院被告全國前案紀錄表一份附卷可\n    稽，其因一時失慮，偶罹刑典，諒經此偵審科刑宣告之教訓，當已足資促使其有\n    所警惕而無再犯之虞，本院因認前所宣告之刑，以暫不執行為適當，爰依刑法第\n    七十四條第一款之規定，併予宣告緩刑，以啟自新。\n三、依刑事訴訟法第四百四十九條第一項、第四百五十條第一項、第四百五十四條第\n    二項，刑法第三百二十條第一項、第四十一條第一項、第七十四條第一款，罰金\n    罰鍰提高標準條例第一條前段、第二條，逕以簡易判決處如主文所示之刑。\n四、如不服本判決，得自收受送達之日起十日內，向本院提起上訴。",
    "reason": "一、本件犯罪事實、證據，除犯罪事實欄：「第二行，美華泰流行生活館內，徒手竊\n    取甲○○所持有：：」應予更正外，餘均引用檢察官聲請簡易判決處刑書之記載\n    （如附件）。\n二、爰審酌被告不循正途謀取財物、本案犯罪之方法、被害人所受之損失及犯後態度\n    等一切情狀，量處如主文所示之刑，並諭知易科罰金之折算標準。末查，被告前\n    未曾受有期徒刑以上刑之宣告，有臺灣高等法院被告全國前案紀錄表一份附卷可\n    稽，其因一時失慮，偶罹刑典，諒經此偵審科刑宣告之教訓，當已足資促使其有\n    所警惕而無再犯之虞，本院因認前所宣告之刑，以暫不執行為適當，爰依刑法第\n    七十四條第一款之規定，併予宣告緩刑，以啟自新。\n三、依刑事訴訟法第四百四十九條第一項、第四百五十條第一項、第四百五十四條第\n    二項，刑法第三百二十條第一項、第四十一條第一項、第七十四條第一款，罰金\n    罰鍰提高標準條例第一條前段、第二條，逕以簡易判決處如主文所示之刑。\n四、如不服本判決，得自收受送達之日起十日內，向本院提起上訴。"
  },
  "search": "臺灣新竹地方法院刑事簡易判決九十三年度竹簡字第八八二號聲請人臺灣新竹地方法院檢察署檢察官被告乙○○○右列被告因竊盜案件，經檢察官聲請以簡易判決處刑（九十三年度速偵字第一０六八號），本院判決如左：主文乙○○○竊盜，處拘役拾日，如易科罰金以佰元折算壹日。緩刑貳年。事實及理由一、本件犯罪事實、證據，除犯罪事實欄：「第二行，美華泰流行生活館內，徒手竊取甲○○所持有：：」應予更正外，餘均引用檢察官聲請簡易判決處刑書之記載（如附件）。二、爰審酌被告不循正途謀取財物、本案犯罪之方法、被害人所受之損失及犯後態度等一切情狀，量處如主文所示之刑，並諭知易科罰金之折算標準。末查，被告前未曾受有期徒刑以上刑之宣告，有臺灣高等法院被告全國前案紀錄表一份附卷可稽，其因一時失慮，偶罹刑典，諒經此偵審科刑宣告之教訓，當已足資促使其有所警惕而無再犯之虞，本院因認前所宣告之刑，以暫不執行為適當，爰依刑法第七十四條第一款之規定，併予宣告緩刑，以啟自新。三、依刑事訴訟法第四百四十九條第一項、第四百五十條第一項、第四百五十四條第二項，刑法第三百二十條第一項、第四十一條第一項、第七十四條第一款，罰金罰鍰提高標準條例第一條前段、第二條，逕以簡易判決處如主文所示之刑。四、如不服本判決，得自收受送達之日起十日內，向本院提起上訴。中華民國九十三年十二月三十一日臺灣新竹地方法院簡易庭法官彭淑苑右正本證明與原本無異書記官蕭利峰中華民國九十三年十二月三十一日附錄實體處罰條文：中華民國刑法第三百二十條第一項(普通竊盜罪)意圖為自己或第三人不法之所有，而竊取他人之動產者，為竊盜罪，處五年以下有期徒刑、拘役或五百元以下罰金。",
  "characters": {
    "judges": [
      "彭淑苑"
    ],
    "prosecutors": [

    ],
    "lawyers": [

    ],
    "clerks": [
      "蕭利峰"
    ],
    "plaintiffs": [

    ],
    "defendants": [
      "乙○○○",
      "右列被告因竊盜案件，經檢察官聲請以簡易判決處刑（九十三年度速偵字第一０六八",
      "號），本院判決如左："
    ],
    "prosecutor_office": [
      "臺灣新竹地方法院檢察署檢察官"
    ],
    "creditors": [

    ],
    "debtors": [

    ],
    "judicial_associate_officer": [

    ]
  },
  "adjudged_at": "2004-12-31",
  "created_at": "2016-02-06 07:37:11",
  "updated_at": "2016-02-06 07:37:11"
}