{
  "identify": "TYD-93-簡上-319-20041231-1",
  "court": {
    "name": "臺灣桃園地方法院",
    "code": "TYD"
  },
  "division": {
    "name": "刑事",
    "code": "M"
  },
  "year": 93,
  "word": "簡上",
  "number": "319",
  "jcheck": "1",
  "reason": "傷害",
  "content": "臺灣桃園地方法院刑事判決             93年度簡上字第319號\n公  訴  人  臺灣桃園地方法院檢察署檢察官\n上  訴  人  甲○○  男  34歲（民國59年3月20日生）\n                      號三樓\n上上訴人因傷害案件，不服本院桃園簡易庭九十三年度桃簡字第\n六七九號中華民國九十三年七月二十九日第一審簡易判決（聲請\n簡易判決處刑案號：九十三年度偵字第一００九號），提起上訴\n，本院管轄第二審之合議庭判決如下：\n    主      文\n上訴駁回。\n    事實及理由\n一、本件經本院管轄第二審之合議庭審理結果，認第一審以上訴\n    人即被告甲○○犯刑法第二百七十七條第一項傷害罪，判處\n    拘役三十日，並准以三百元折算一日易科罰金，經核其認事\n    用法及量刑均無不當，應予維持，並引用第一審判決書記載\n    之事實、證據及理由（如附件）。\n二、本件上訴人即被告對於其於民國九十二年八月二十九日二十\n    時許，在其桃園縣蘆竹鄉大華村建國二十村三八號住處，與\n    告訴人丙○○因車禍賠償款事宜發生爭執，雙方發生拉扯等\n    情，於本院審理時坦承不諱，惟其辯稱：伊不是故意要傷害\n    告訴人，是雙方在拉扯中告訴人自己摔倒而受傷云云。經查\n    ，被告於上開時間、地點，有拉住告訴人之右前臂，將告訴\n    人摔向牆壁，致使告訴人頭部撞牆後摔倒，腰部並撞擊牆邊\n    放置之椅子的扶手，因而受有右前臂、右腰瘀傷之傷害一節\n    ，業據證人即告訴人丙○○證稱：... 被告跟我起爭執，他\n    很生氣地把我往牆壁那邊撞，剛好牆壁那邊有一張椅子，我\n    的頭撞到牆壁，腰就撞到椅子扶手的位置等語（見本院九十\n    三年十二月二十一日審判筆錄第七頁），而證人即在現場目\n    擊之證人乙○○亦證稱：（問：被告有無將告訴人推倒在地\n    ？）有，告訴人剛進來的時候，被告有將她推倒，告訴人的\n    腰部有去撞到椅子扶手的下面等語（見本院九十三年十二月\n    二十一日審判筆錄第六頁），並有診斷證明書影本一紙附卷\n    可稽，故被告有拉住告訴人右前臂，並將其摔向牆壁，致使\n    告訴人腰部撞擊牆邊放置之椅子的扶手而受傷一事，堪可認\n    定，足見被告前開所為確有傷害告訴人之故意，其所辯稱：\n    伊無傷害告訴人之故意，是雙方拉扯中告訴人自己摔倒受傷\n    云云，顯係卸責之詞，不可採信。原審認事用法，核無不當\n    ，上訴人仍不服本院第一審判決，提起上訴，顯無理由，應\n    予駁回。\n據上論斷，應依刑事訴訟法第四百五十五條之一第三項、第三百\n六十八條、第三百七十三條，判決如主文。\n本案經檢察官張啟聰到庭執行職務。\n中    華    民    國    93    年    12    月    31    日\n                  臺灣桃園地方法院刑事第五庭\n                      審判長法  官  潘政宏\n                            法  官  周炳全\n                            法  官  張明儀\n正本證明與原本無異。\n如不服本判決，應於送達後10日內，向本院提出上訴狀。\n                            書記官  王嘉麒\n中    華    民    國    93    年    12    月    31    日\n",
  "structure": {
    "main": "上訴駁回。",
    "fact": "一、本件經本院管轄第二審之合議庭審理結果，認第一審以上訴\n    人即被告甲○○犯刑法第二百七十七條第一項傷害罪，判處\n    拘役三十日，並准以三百元折算一日易科罰金，經核其認事\n    用法及量刑均無不當，應予維持，並引用第一審判決書記載\n    之事實、證據及理由（如附件）。\n二、本件上訴人即被告對於其於民國九十二年八月二十九日二十\n    時許，在其桃園縣蘆竹鄉大華村建國二十村三八號住處，與\n    告訴人丙○○因車禍賠償款事宜發生爭執，雙方發生拉扯等\n    情，於本院審理時坦承不諱，惟其辯稱：伊不是故意要傷害\n    告訴人，是雙方在拉扯中告訴人自己摔倒而受傷云云。經查\n    ，被告於上開時間、地點，有拉住告訴人之右前臂，將告訴\n    人摔向牆壁，致使告訴人頭部撞牆後摔倒，腰部並撞擊牆邊\n    放置之椅子的扶手，因而受有右前臂、右腰瘀傷之傷害一節\n    ，業據證人即告訴人丙○○證稱：... 被告跟我起爭執，他\n    很生氣地把我往牆壁那邊撞，剛好牆壁那邊有一張椅子，我\n    的頭撞到牆壁，腰就撞到椅子扶手的位置等語（見本院九十\n    三年十二月二十一日審判筆錄第七頁），而證人即在現場目\n    擊之證人乙○○亦證稱：（問：被告有無將告訴人推倒在地\n    ？）有，告訴人剛進來的時候，被告有將她推倒，告訴人的\n    腰部有去撞到椅子扶手的下面等語（見本院九十三年十二月\n    二十一日審判筆錄第六頁），並有診斷證明書影本一紙附卷\n    可稽，故被告有拉住告訴人右前臂，並將其摔向牆壁，致使\n    告訴人腰部撞擊牆邊放置之椅子的扶手而受傷一事，堪可認\n    定，足見被告前開所為確有傷害告訴人之故意，其所辯稱：\n    伊無傷害告訴人之故意，是雙方拉扯中告訴人自己摔倒受傷\n    云云，顯係卸責之詞，不可採信。原審認事用法，核無不當\n    ，上訴人仍不服本院第一審判決，提起上訴，顯無理由，應\n    予駁回。\n據上論斷，應依刑事訴訟法第四百五十五條之一第三項、第三百\n六十八條、第三百七十三條，判決如主文。\n本案經檢察官張啟聰到庭執行職務。",
    "reason": "一、本件經本院管轄第二審之合議庭審理結果，認第一審以上訴\n    人即被告甲○○犯刑法第二百七十七條第一項傷害罪，判處\n    拘役三十日，並准以三百元折算一日易科罰金，經核其認事\n    用法及量刑均無不當，應予維持，並引用第一審判決書記載\n    之事實、證據及理由（如附件）。\n二、本件上訴人即被告對於其於民國九十二年八月二十九日二十\n    時許，在其桃園縣蘆竹鄉大華村建國二十村三八號住處，與\n    告訴人丙○○因車禍賠償款事宜發生爭執，雙方發生拉扯等\n    情，於本院審理時坦承不諱，惟其辯稱：伊不是故意要傷害\n    告訴人，是雙方在拉扯中告訴人自己摔倒而受傷云云。經查\n    ，被告於上開時間、地點，有拉住告訴人之右前臂，將告訴\n    人摔向牆壁，致使告訴人頭部撞牆後摔倒，腰部並撞擊牆邊\n    放置之椅子的扶手，因而受有右前臂、右腰瘀傷之傷害一節\n    ，業據證人即告訴人丙○○證稱：... 被告跟我起爭執，他\n    很生氣地把我往牆壁那邊撞，剛好牆壁那邊有一張椅子，我\n    的頭撞到牆壁，腰就撞到椅子扶手的位置等語（見本院九十\n    三年十二月二十一日審判筆錄第七頁），而證人即在現場目\n    擊之證人乙○○亦證稱：（問：被告有無將告訴人推倒在地\n    ？）有，告訴人剛進來的時候，被告有將她推倒，告訴人的\n    腰部有去撞到椅子扶手的下面等語（見本院九十三年十二月\n    二十一日審判筆錄第六頁），並有診斷證明書影本一紙附卷\n    可稽，故被告有拉住告訴人右前臂，並將其摔向牆壁，致使\n    告訴人腰部撞擊牆邊放置之椅子的扶手而受傷一事，堪可認\n    定，足見被告前開所為確有傷害告訴人之故意，其所辯稱：\n    伊無傷害告訴人之故意，是雙方拉扯中告訴人自己摔倒受傷\n    云云，顯係卸責之詞，不可採信。原審認事用法，核無不當\n    ，上訴人仍不服本院第一審判決，提起上訴，顯無理由，應\n    予駁回。\n據上論斷，應依刑事訴訟法第四百五十五條之一第三項、第三百\n六十八條、第三百七十三條，判決如主文。\n本案經檢察官張啟聰到庭執行職務。"
  },
  "search": "臺灣桃園地方法院刑事判決93年度簡上字第319號公訴人臺灣桃園地方法院檢察署檢察官上訴人甲○○男34歲（民國59年3月20日生）號三樓上上訴人因傷害案件，不服本院桃園簡易庭九十三年度桃簡字第六七九號中華民國九十三年七月二十九日第一審簡易判決（聲請簡易判決處刑案號：九十三年度偵字第一００九號），提起上訴，本院管轄第二審之合議庭判決如下：主文上訴駁回。事實及理由一、本件經本院管轄第二審之合議庭審理結果，認第一審以上訴人即被告甲○○犯刑法第二百七十七條第一項傷害罪，判處拘役三十日，並准以三百元折算一日易科罰金，經核其認事用法及量刑均無不當，應予維持，並引用第一審判決書記載之事實、證據及理由（如附件）。二、本件上訴人即被告對於其於民國九十二年八月二十九日二十時許，在其桃園縣蘆竹鄉大華村建國二十村三八號住處，與告訴人丙○○因車禍賠償款事宜發生爭執，雙方發生拉扯等情，於本院審理時坦承不諱，惟其辯稱：伊不是故意要傷害告訴人，是雙方在拉扯中告訴人自己摔倒而受傷云云。經查，被告於上開時間、地點，有拉住告訴人之右前臂，將告訴人摔向牆壁，致使告訴人頭部撞牆後摔倒，腰部並撞擊牆邊放置之椅子的扶手，因而受有右前臂、右腰瘀傷之傷害一節，業據證人即告訴人丙○○證稱：...被告跟我起爭執，他很生氣地把我往牆壁那邊撞，剛好牆壁那邊有一張椅子，我的頭撞到牆壁，腰就撞到椅子扶手的位置等語（見本院九十三年十二月二十一日審判筆錄第七頁），而證人即在現場目擊之證人乙○○亦證稱：（問：被告有無將告訴人推倒在地？）有，告訴人剛進來的時候，被告有將她推倒，告訴人的腰部有去撞到椅子扶手的下面等語（見本院九十三年十二月二十一日審判筆錄第六頁），並有診斷證明書影本一紙附卷可稽，故被告有拉住告訴人右前臂，並將其摔向牆壁，致使告訴人腰部撞擊牆邊放置之椅子的扶手而受傷一事，堪可認定，足見被告前開所為確有傷害告訴人之故意，其所辯稱：伊無傷害告訴人之故意，是雙方拉扯中告訴人自己摔倒受傷云云，顯係卸責之詞，不可採信。原審認事用法，核無不當，上訴人仍不服本院第一審判決，提起上訴，顯無理由，應予駁回。據上論斷，應依刑事訴訟法第四百五十五條之一第三項、第三百六十八條、第三百七十三條，判決如主文。本案經檢察官張啟聰到庭執行職務。中華民國93年12月31日臺灣桃園地方法院刑事第五庭審判長法官潘政宏法官周炳全法官張明儀正本證明與原本無異。如不服本判決，應於送達後10日內，向本院提出上訴狀。書記官王嘉麒中華民國93年12月31日",
  "characters": {
    "judges": [
      "潘政宏",
      "周炳全",
      "張明儀"
    ],
    "prosecutors": [
      "張啟聰"
    ],
    "lawyers": [

    ],
    "clerks": [
      "王嘉麒"
    ],
    "plaintiffs": [

    ],
    "defendants": [

    ],
    "prosecutor_office": [
      "臺灣桃園地方法院檢察署檢察官"
    ],
    "creditors": [

    ],
    "debtors": [

    ],
    "judicial_associate_officer": [

    ]
  },
  "adjudged_at": "2004-12-31",
  "created_at": "2016-02-06 07:49:23",
  "updated_at": "2016-02-06 07:49:23"
}