{
  "identify": "PCD-100-智訴-17-20110720-1",
  "court": {
    "name": "臺灣新北地方法院",
    "code": "PCD"
  },
  "division": {
    "name": "刑事",
    "code": "M"
  },
  "year": 100,
  "word": "智訴",
  "number": "17",
  "jcheck": "1",
  "reason": "著作權法",
  "content": "臺灣板橋地方法院刑事判決             100年度智訴字第17號\n公  訴  人  臺灣板橋地方法院檢察署檢察官\n被      告  林文貴\n上列被告因違反著作權法案件，經檢察官提起公訴（100 年度偵\n字第10721 號），本院判決如下：\n    主  文\n本件公訴不受理。\n    理  由\n一、公訴意旨略以：被告林文貴明知「流淚手心」等60首歌曲之\n    歌詞部分，均為大無限國際娛樂有限公司（下稱大無限公司\n    ）取得原著作財產權人之專屬授權，享有該歌詞著作之重製\n    權、散布權等著作財產權，非經大無限著作財產權人之同意\n    或授權，不得擅自重製、販售，竟仍基於意圖銷售、散布而\n    擅自以重製之方法侵害他人之著作財產權之犯意，自民國（\n    下同）98年2 月23日15時許起，在其臺北縣樹林市（現改制\n    為新北市樹林區，下同）忠孝街101 巷21號2 樓住處，以電\n    腦網路設備連結至露天拍賣網站，利用「akueil in 」帳號\n    ，刊登販售KTV 點歌軟體及安裝之廣告，並以附贈灌錄歌曲\n    之方式吸引買家下標點閱訂購，迨與買家達成交易協議後，\n    即在其所任職址設臺北縣樹林市○○街168 號公司內，將預\n    先備妥之存有前開曲、詞之影音著作檔案，擅自重製於儲存\n    媒體中，以待交貨。嗣經大無限公司人員發現，於100 年2\n    月14日，並以安裝點歌軟體附加3,000 首新歌、灌錄8,000\n    首舊歌，以及另購之2.5 吋500G外接硬碟等費用，共計新臺\n    幣3,500 元之價格與被告林文貴達成交易後，旋即報警處理\n    ，並於同年月22日19時10分許，為警通知到案，並扣得2.5\n    吋500G外接硬碟1 顆及傳輸線1 條，始查悉上情。因認被告\n    林文貴涉犯著作權法第91條第2 項之意圖銷售而擅自以重製\n    方法侵害他人著作財產權罪嫌。\n二、按告訴乃論之罪，告訴人於第一審辯論終結前得撤回其告訴\n    ；又告訴經撤回者，應諭知不受理之判決，且該判決得不經\n    言詞辯論，刑事訴訟法第238 條第1 項、第303 條第3 款及\n    第307 條分別定有明文。\n三、經查：本件告訴人大無限公司告訴被告林文貴違反著作權法\n    案件，公訴人認被告係觸犯著作權法第91條第2 項之意圖銷\n    售而擅自以重製方法侵害他人著作財產權罪嫌，則依著作權\n    法第100 條前段之規定，須告訴乃論。茲據告訴人於第一審\n    辯論終結前具狀撤回告訴，此有「刑事撤回告訴狀」1 紙在\n    卷可稽，揆諸上開法條及說明，爰不經言詞辯論，逕為不受\n    理判決之諭知。\n據上論斷，應依刑事訴訟法第303 條第3 款、第307 條，判決如\n主文。\n中    華    民    國  100     年    7     月    20    日\n            刑事第八庭  審判長法  官  陳鴻清\n                              法  官  劉安榕\n                              法  官  賴彥魁\n以上正本證明與原本無異。\n如不服本判決，應於判決送達後10日內敘明上訴理由，向本院提\n出上訴狀（應附繕本），上訴於臺灣高等法院。其未敘述上訴理\n由者，應於上訴期間屆滿後20日內向本院補提理由書「切勿逕送\n上級法院」。\n                              書記官  黃頌棻\n中    華    民    國  100     年    7     月    20    日",
  "structure": {
    "main": "本件公訴不受理。",
    "reason": "一、公訴意旨略以：被告林文貴明知「流淚手心」等60首歌曲之\n    歌詞部分，均為大無限國際娛樂有限公司（下稱大無限公司\n    ）取得原著作財產權人之專屬授權，享有該歌詞著作之重製\n    權、散布權等著作財產權，非經大無限著作財產權人之同意\n    或授權，不得擅自重製、販售，竟仍基於意圖銷售、散布而\n    擅自以重製之方法侵害他人之著作財產權之犯意，自民國（\n    下同）98年2 月23日15時許起，在其臺北縣樹林市（現改制\n    為新北市樹林區，下同）忠孝街101 巷21號2 樓住處，以電\n    腦網路設備連結至露天拍賣網站，利用「akueil in 」帳號\n    ，刊登販售KTV 點歌軟體及安裝之廣告，並以附贈灌錄歌曲\n    之方式吸引買家下標點閱訂購，迨與買家達成交易協議後，\n    即在其所任職址設臺北縣樹林市○○街168 號公司內，將預\n    先備妥之存有前開曲、詞之影音著作檔案，擅自重製於儲存\n    媒體中，以待交貨。嗣經大無限公司人員發現，於100 年2\n    月14日，並以安裝點歌軟體附加3,000 首新歌、灌錄8,000\n    首舊歌，以及另購之2.5 吋500G外接硬碟等費用，共計新臺\n    幣3,500 元之價格與被告林文貴達成交易後，旋即報警處理\n    ，並於同年月22日19時10分許，為警通知到案，並扣得2.5\n    吋500G外接硬碟1 顆及傳輸線1 條，始查悉上情。因認被告\n    林文貴涉犯著作權法第91條第2 項之意圖銷售而擅自以重製\n    方法侵害他人著作財產權罪嫌。\n二、按告訴乃論之罪，告訴人於第一審辯論終結前得撤回其告訴\n    ；又告訴經撤回者，應諭知不受理之判決，且該判決得不經\n    言詞辯論，刑事訴訟法第238 條第1 項、第303 條第3 款及\n    第307 條分別定有明文。\n三、經查：本件告訴人大無限公司告訴被告林文貴違反著作權法\n    案件，公訴人認被告係觸犯著作權法第91條第2 項之意圖銷\n    售而擅自以重製方法侵害他人著作財產權罪嫌，則依著作權\n    法第100 條前段之規定，須告訴乃論。茲據告訴人於第一審\n    辯論終結前具狀撤回告訴，此有「刑事撤回告訴狀」1 紙在\n    卷可稽，揆諸上開法條及說明，爰不經言詞辯論，逕為不受\n    理判決之諭知。\n據上論斷，應依刑事訴訟法第303 條第3 款、第307 條，判決如\n主文。"
  },
  "search": "臺灣板橋地方法院刑事判決100年度智訴字第17號公訴人臺灣板橋地方法院檢察署檢察官被告林文貴上列被告因違反著作權法案件，經檢察官提起公訴（100年度偵字第10721號），本院判決如下：主文本件公訴不受理。理由一、公訴意旨略以：被告林文貴明知「流淚手心」等60首歌曲之歌詞部分，均為大無限國際娛樂有限公司（下稱大無限公司）取得原著作財產權人之專屬授權，享有該歌詞著作之重製權、散布權等著作財產權，非經大無限著作財產權人之同意或授權，不得擅自重製、販售，竟仍基於意圖銷售、散布而擅自以重製之方法侵害他人之著作財產權之犯意，自民國（下同）98年2月23日15時許起，在其臺北縣樹林市（現改制為新北市樹林區，下同）忠孝街101巷21號2樓住處，以電腦網路設備連結至露天拍賣網站，利用「akueilin」帳號，刊登販售KTV點歌軟體及安裝之廣告，並以附贈灌錄歌曲之方式吸引買家下標點閱訂購，迨與買家達成交易協議後，即在其所任職址設臺北縣樹林市○○街168號公司內，將預先備妥之存有前開曲、詞之影音著作檔案，擅自重製於儲存媒體中，以待交貨。嗣經大無限公司人員發現，於100年2月14日，並以安裝點歌軟體附加3,000首新歌、灌錄8,000首舊歌，以及另購之2.5吋500G外接硬碟等費用，共計新臺幣3,500元之價格與被告林文貴達成交易後，旋即報警處理，並於同年月22日19時10分許，為警通知到案，並扣得2.5吋500G外接硬碟1顆及傳輸線1條，始查悉上情。因認被告林文貴涉犯著作權法第91條第2項之意圖銷售而擅自以重製方法侵害他人著作財產權罪嫌。二、按告訴乃論之罪，告訴人於第一審辯論終結前得撤回其告訴；又告訴經撤回者，應諭知不受理之判決，且該判決得不經言詞辯論，刑事訴訟法第238條第1項、第303條第3款及第307條分別定有明文。三、經查：本件告訴人大無限公司告訴被告林文貴違反著作權法案件，公訴人認被告係觸犯著作權法第91條第2項之意圖銷售而擅自以重製方法侵害他人著作財產權罪嫌，則依著作權法第100條前段之規定，須告訴乃論。茲據告訴人於第一審辯論終結前具狀撤回告訴，此有「刑事撤回告訴狀」1紙在卷可稽，揆諸上開法條及說明，爰不經言詞辯論，逕為不受理判決之諭知。據上論斷，應依刑事訴訟法第303條第3款、第307條，判決如主文。中華民國100年7月20日刑事第八庭審判長法官陳鴻清法官劉安榕法官賴彥魁以上正本證明與原本無異。如不服本判決，應於判決送達後10日內敘明上訴理由，向本院提出上訴狀（應附繕本），上訴於臺灣高等法院。其未敘述上訴理由者，應於上訴期間屆滿後20日內向本院補提理由書「切勿逕送上級法院」。書記官黃頌棻中華民國100年7月20日",
  "characters": {
    "judges": [
      "陳鴻清",
      "劉安榕",
      "賴彥魁"
    ],
    "prosecutors": [

    ],
    "lawyers": [

    ],
    "clerks": [
      "黃頌棻"
    ],
    "plaintiffs": [

    ],
    "defendants": [
      "林文貴"
    ],
    "prosecutor_office": [
      "臺灣板橋地方法院檢察署檢察官"
    ],
    "creditors": [

    ],
    "debtors": [

    ],
    "judicial_associate_officer": [

    ]
  },
  "adjudged_at": "2011-07-20",
  "created_at": "2016-02-14 03:22:01",
  "updated_at": "2016-02-14 03:22:01"
}