{
  "identify": "TCD-100-中簡-1662-20110721-1",
  "court": {
    "name": "臺灣臺中地方法院",
    "code": "TCD"
  },
  "division": {
    "name": "刑事",
    "code": "M"
  },
  "year": 100,
  "word": "中簡",
  "number": "1662",
  "jcheck": "1",
  "reason": "毒品危害防制條例",
  "content": "臺灣臺中地方法院刑事簡易判決       100年度中簡字第1662號\n聲  請  人  臺灣臺中地方法院檢察署檢察官\n被      告  林宏澤\n上列被告因違反毒品危害防制條例案件，經檢察官聲請以簡易判\n決處刑（100年度毒偵字第1723號），本院判決如下：\n    主      文\n林宏澤施用第二級毒品，累犯，處有期徒刑伍月，如易科罰金，\n以新臺幣壹仟元折算壹日。\n    事實及理由\n一、本案犯罪事實、證據及所犯法條，除證據部分補充臺中市警\n    察局（現改制為臺中市政府警察局）第五分局委託檢驗尿液\n    代號與真實姓名對照表1 份外，餘均引用檢察官聲請簡易判\n    決處刑書之記載（如附件）。\n二、依刑事訴訟法第449 條第1 項前段、第454 條第2 項，毒品\n    危害防制條例第10條第2 項，刑法第11條前段、第47條第1\n    項、第41條第1 項前段，逕以簡易判決處刑如主文。\n三、如不服本判決，應於收受送達後10日內，向本院提出上訴書\n    狀（應按他造當事人之人數附繕本）。\n中    華    民    國  100     年    7     月    21    日\n                  臺中簡易庭  法  官  楊欣怡\n以上正本證明與原本無異。\n如不服本判決，應於收受送達後10日內向本院提出上訴書狀（應\n附繕本）。\n                              書記官  黃泰能\n中    華    民    國   100    年    7     月    21    日\n附錄論罪科刑法條：\n毒品危害防制條例第10條\n施用第一級毒品者，處 6 月以上 5 年以下有期徒刑。\n施用第二級毒品者，處 3 年以下有期徒刑。",
  "structure": {
    "main": "林宏澤施用第二級毒品，累犯，處有期徒刑伍月，如易科罰金，\n以新臺幣壹仟元折算壹日。",
    "fact": "一、本案犯罪事實、證據及所犯法條，除證據部分補充臺中市警\n    察局（現改制為臺中市政府警察局）第五分局委託檢驗尿液\n    代號與真實姓名對照表1 份外，餘均引用檢察官聲請簡易判\n    決處刑書之記載（如附件）。\n二、依刑事訴訟法第449 條第1 項前段、第454 條第2 項，毒品\n    危害防制條例第10條第2 項，刑法第11條前段、第47條第1\n    項、第41條第1 項前段，逕以簡易判決處刑如主文。\n三、如不服本判決，應於收受送達後10日內，向本院提出上訴書\n    狀（應按他造當事人之人數附繕本）。",
    "reason": "一、本案犯罪事實、證據及所犯法條，除證據部分補充臺中市警\n    察局（現改制為臺中市政府警察局）第五分局委託檢驗尿液\n    代號與真實姓名對照表1 份外，餘均引用檢察官聲請簡易判\n    決處刑書之記載（如附件）。\n二、依刑事訴訟法第449 條第1 項前段、第454 條第2 項，毒品\n    危害防制條例第10條第2 項，刑法第11條前段、第47條第1\n    項、第41條第1 項前段，逕以簡易判決處刑如主文。\n三、如不服本判決，應於收受送達後10日內，向本院提出上訴書\n    狀（應按他造當事人之人數附繕本）。"
  },
  "search": "臺灣臺中地方法院刑事簡易判決100年度中簡字第1662號聲請人臺灣臺中地方法院檢察署檢察官被告林宏澤上列被告因違反毒品危害防制條例案件，經檢察官聲請以簡易判決處刑（100年度毒偵字第1723號），本院判決如下：主文林宏澤施用第二級毒品，累犯，處有期徒刑伍月，如易科罰金，以新臺幣壹仟元折算壹日。事實及理由一、本案犯罪事實、證據及所犯法條，除證據部分補充臺中市警察局（現改制為臺中市政府警察局）第五分局委託檢驗尿液代號與真實姓名對照表1份外，餘均引用檢察官聲請簡易判決處刑書之記載（如附件）。二、依刑事訴訟法第449條第1項前段、第454條第2項，毒品危害防制條例第10條第2項，刑法第11條前段、第47條第1項、第41條第1項前段，逕以簡易判決處刑如主文。三、如不服本判決，應於收受送達後10日內，向本院提出上訴書狀（應按他造當事人之人數附繕本）。中華民國100年7月21日臺中簡易庭法官楊欣怡以上正本證明與原本無異。如不服本判決，應於收受送達後10日內向本院提出上訴書狀（應附繕本）。書記官黃泰能中華民國100年7月21日附錄論罪科刑法條：毒品危害防制條例第10條施用第一級毒品者，處6月以上5年以下有期徒刑。施用第二級毒品者，處3年以下有期徒刑。",
  "characters": {
    "judges": [
      "楊欣怡"
    ],
    "prosecutors": [

    ],
    "lawyers": [

    ],
    "clerks": [
      "黃泰能"
    ],
    "plaintiffs": [

    ],
    "defendants": [
      "林宏澤"
    ],
    "prosecutor_office": [
      "臺灣臺中地方法院檢察署檢察官"
    ],
    "creditors": [

    ],
    "debtors": [

    ],
    "judicial_associate_officer": [

    ]
  },
  "adjudged_at": "2011-07-21",
  "created_at": "2016-02-14 03:28:32",
  "updated_at": "2016-02-14 03:28:32"
}