{
  "identify": "TYD-100-桃簡-1507-20110721-1",
  "court": {
    "name": "臺灣桃園地方法院",
    "code": "TYD"
  },
  "division": {
    "name": "刑事",
    "code": "M"
  },
  "year": 100,
  "word": "桃簡",
  "number": "1507",
  "jcheck": "1",
  "reason": "妨害風化",
  "content": "臺灣桃園地方法院刑事簡易判決       100年度桃簡字第1507號\n聲  請  人  臺灣桃園地方法院檢察署檢察官\n被      告  劉泰\n            王誌忠\n上列被告因妨害風化案件，經檢察官聲請簡易判決處刑（100年\n度偵字第12222號），本院逕以簡易判決處刑如下：\n    主      文\n劉泰共同意圖使女子與他人為猥褻之行為，而容留以營利，處\n有期徒刑肆月，如易科罰金，以新臺幣壹仟元折算壹日。\n王誌忠共同意圖使女子與他人為猥褻之行為，而容留以營利，處\n有期徒刑肆月，如易科罰金，以新臺幣壹仟元折算壹日。\n    事實及理由\n一、本件犯罪事實及證據，除檢察官聲請簡易判決處刑書犯罪事\n    實欄一第5 行「新越緣紓壓館」，應更正為「新越緣健康舒\n    壓館」、第7 行「不詳時間」應更正為「100 年3 月28日」\n    外，餘均引用檢察官聲請簡易判決處刑書之記載( 如附件)\n    。\n二、核被告2 人所為，均係犯刑法第231 條第1 項前段之意圖使\n    女子與他人為猥褻之行為而容留以營利罪。又其媒介之低度\n    行為為容留之高度行為所吸收，不另論罪。被告王誌忠與被\n    告劉泰間，就上開犯行間，有犯意聯絡及行為之分擔，為\n    共同正犯。爰審酌被告2 人以媒介、容留女子與他人從事猥\n    褻行為，將女性身體當作交易籌碼，並藉此牟利，不唯破壞\n    社會善良風俗，且將人身體物化，嚴重扭曲社會之價值觀，\n    並審酌被告2 人之素行，犯罪之動機、目的、手段，犯罪態\n    度等一切情狀，各量處如主文所示之刑，並均諭知易科罰金\n    之折算標準，以示懲儆。\n三、據上論斷，應依刑事訴訟法第449 條第1 項前段、第3 項、\n    第454條第2項，刑法第28條、第231 條第1 項前段、第41條\n    第1 項前段，刑法施行法第1 條之1 第1 項、第2 項但書，\n    逕以簡易判決處刑如主文。\n四、如不服本判決，應於判決送達後10日內，向本院提出上訴狀\n    （應附繕本），上訴於本院合議庭。\n中    華    民    國   100    年    7     月    21    日\n                            刑事第二庭    法  官  李麗珍\n以上正本證明與原本無異。\n如不服本判決，得於判決書送達之翌日起10日內，以書狀敘述理\n由，向本庭提出上訴（應附繕本）。\n                                          書記官  李靜華\n中    華    民    國   100    年    8     月    2     日\n附錄法條:\n中華民國刑法第231條\n（圖利使人為性交或猥褻罪）\n意圖使男女與他人為性交或猥褻之行為，而引誘、容留或媒介以\n營利者，處 5 年以下有期徒刑，得併科 10 萬元以下罰金。以\n詐術犯之者，亦同。\n公務員包庇他人犯前項之罪者，依前項之規定加重其刑至二分之\n一。",
  "structure": {
    "main": "劉泰共同意圖使女子與他人為猥褻之行為，而容留以營利，處\n有期徒刑肆月，如易科罰金，以新臺幣壹仟元折算壹日。\n王誌忠共同意圖使女子與他人為猥褻之行為，而容留以營利，處\n有期徒刑肆月，如易科罰金，以新臺幣壹仟元折算壹日。",
    "fact": "一、本件犯罪事實及證據，除檢察官聲請簡易判決處刑書犯罪事\n    實欄一第5 行「新越緣紓壓館」，應更正為「新越緣健康舒\n    壓館」、第7 行「不詳時間」應更正為「100 年3 月28日」\n    外，餘均引用檢察官聲請簡易判決處刑書之記載( 如附件)\n    。\n二、核被告2 人所為，均係犯刑法第231 條第1 項前段之意圖使\n    女子與他人為猥褻之行為而容留以營利罪。又其媒介之低度\n    行為為容留之高度行為所吸收，不另論罪。被告王誌忠與被\n    告劉泰間，就上開犯行間，有犯意聯絡及行為之分擔，為\n    共同正犯。爰審酌被告2 人以媒介、容留女子與他人從事猥\n    褻行為，將女性身體當作交易籌碼，並藉此牟利，不唯破壞\n    社會善良風俗，且將人身體物化，嚴重扭曲社會之價值觀，\n    並審酌被告2 人之素行，犯罪之動機、目的、手段，犯罪態\n    度等一切情狀，各量處如主文所示之刑，並均諭知易科罰金\n    之折算標準，以示懲儆。\n三、據上論斷，應依刑事訴訟法第449 條第1 項前段、第3 項、\n    第454條第2項，刑法第28條、第231 條第1 項前段、第41條\n    第1 項前段，刑法施行法第1 條之1 第1 項、第2 項但書，\n    逕以簡易判決處刑如主文。\n四、如不服本判決，應於判決送達後10日內，向本院提出上訴狀\n    （應附繕本），上訴於本院合議庭。",
    "reason": "一、本件犯罪事實及證據，除檢察官聲請簡易判決處刑書犯罪事\n    實欄一第5 行「新越緣紓壓館」，應更正為「新越緣健康舒\n    壓館」、第7 行「不詳時間」應更正為「100 年3 月28日」\n    外，餘均引用檢察官聲請簡易判決處刑書之記載( 如附件)\n    。\n二、核被告2 人所為，均係犯刑法第231 條第1 項前段之意圖使\n    女子與他人為猥褻之行為而容留以營利罪。又其媒介之低度\n    行為為容留之高度行為所吸收，不另論罪。被告王誌忠與被\n    告劉泰間，就上開犯行間，有犯意聯絡及行為之分擔，為\n    共同正犯。爰審酌被告2 人以媒介、容留女子與他人從事猥\n    褻行為，將女性身體當作交易籌碼，並藉此牟利，不唯破壞\n    社會善良風俗，且將人身體物化，嚴重扭曲社會之價值觀，\n    並審酌被告2 人之素行，犯罪之動機、目的、手段，犯罪態\n    度等一切情狀，各量處如主文所示之刑，並均諭知易科罰金\n    之折算標準，以示懲儆。\n三、據上論斷，應依刑事訴訟法第449 條第1 項前段、第3 項、\n    第454條第2項，刑法第28條、第231 條第1 項前段、第41條\n    第1 項前段，刑法施行法第1 條之1 第1 項、第2 項但書，\n    逕以簡易判決處刑如主文。\n四、如不服本判決，應於判決送達後10日內，向本院提出上訴狀\n    （應附繕本），上訴於本院合議庭。"
  },
  "search": "臺灣桃園地方法院刑事簡易判決100年度桃簡字第1507號聲請人臺灣桃園地方法院檢察署檢察官被告劉泰王誌忠上列被告因妨害風化案件，經檢察官聲請簡易判決處刑（100年度偵字第12222號），本院逕以簡易判決處刑如下：主文劉泰共同意圖使女子與他人為猥褻之行為，而容留以營利，處有期徒刑肆月，如易科罰金，以新臺幣壹仟元折算壹日。王誌忠共同意圖使女子與他人為猥褻之行為，而容留以營利，處有期徒刑肆月，如易科罰金，以新臺幣壹仟元折算壹日。事實及理由一、本件犯罪事實及證據，除檢察官聲請簡易判決處刑書犯罪事實欄一第5行「新越緣紓壓館」，應更正為「新越緣健康舒壓館」、第7行「不詳時間」應更正為「100年3月28日」外，餘均引用檢察官聲請簡易判決處刑書之記載(如附件)。二、核被告2人所為，均係犯刑法第231條第1項前段之意圖使女子與他人為猥褻之行為而容留以營利罪。又其媒介之低度行為為容留之高度行為所吸收，不另論罪。被告王誌忠與被告劉泰間，就上開犯行間，有犯意聯絡及行為之分擔，為共同正犯。爰審酌被告2人以媒介、容留女子與他人從事猥褻行為，將女性身體當作交易籌碼，並藉此牟利，不唯破壞社會善良風俗，且將人身體物化，嚴重扭曲社會之價值觀，並審酌被告2人之素行，犯罪之動機、目的、手段，犯罪態度等一切情狀，各量處如主文所示之刑，並均諭知易科罰金之折算標準，以示懲儆。三、據上論斷，應依刑事訴訟法第449條第1項前段、第3項、第454條第2項，刑法第28條、第231條第1項前段、第41條第1項前段，刑法施行法第1條之1第1項、第2項但書，逕以簡易判決處刑如主文。四、如不服本判決，應於判決送達後10日內，向本院提出上訴狀（應附繕本），上訴於本院合議庭。中華民國100年7月21日刑事第二庭法官李麗珍以上正本證明與原本無異。如不服本判決，得於判決書送達之翌日起10日內，以書狀敘述理由，向本庭提出上訴（應附繕本）。書記官李靜華中華民國100年8月2日附錄法條:中華民國刑法第231條（圖利使人為性交或猥褻罪）意圖使男女與他人為性交或猥褻之行為，而引誘、容留或媒介以營利者，處5年以下有期徒刑，得併科10萬元以下罰金。以詐術犯之者，亦同。公務員包庇他人犯前項之罪者，依前項之規定加重其刑至二分之一。",
  "characters": {
    "judges": [
      "李麗珍"
    ],
    "prosecutors": [

    ],
    "lawyers": [

    ],
    "clerks": [
      "李靜華"
    ],
    "plaintiffs": [

    ],
    "defendants": [
      "劉泰"
    ],
    "prosecutor_office": [
      "臺灣桃園地方法院檢察署檢察官"
    ],
    "creditors": [

    ],
    "debtors": [

    ],
    "judicial_associate_officer": [

    ]
  },
  "adjudged_at": "2011-07-21",
  "created_at": "2016-02-14 03:43:11",
  "updated_at": "2016-02-14 03:43:11"
}