{
  "identify": "KSD-91-易-1182-20020806-1",
  "court": {
    "name": "臺灣高雄地方法院",
    "code": "KSD"
  },
  "division": {
    "name": "刑事",
    "code": "M"
  },
  "year": 91,
  "word": "易",
  "number": "1182",
  "jcheck": "1",
  "reason": "贓物",
  "content": "臺灣高雄地方法院刑事判決                        九十一年度易字第一一八二號\n    公  訴  人  臺灣高雄地方法院檢察署檢察官\n    被      告  乙○○\n右列被告因贓物案件，經檢察官提起公訴（九十年度偵字第一九四四三號），本院判\n決如左：\n    主  文\n乙○○故買贓物，處拘役參拾日，如易科罰金，以參佰元折算壹日。\n    事  實\n一、乙○○明知友人甲○於民國九十年六月間某日，在高雄縣燕巢鄉甘蔗園內所拾得\n    引擎號碼ＣＧ00000000號之重型機車一輛（該車原車牌號碼為ＸＴＦ─\n    二一六號、係丁○○所有，於九十年四月十日二十三時四十五分許，在高雄縣大\n    社鄉○○路一巷六十六號前失竊），並無車籍證件亦未懸掛車牌，且係遭人置放\n    該處多時始經甲○拾回，有可能係來源不明之贓物，竟仍基於不惜違法之未必故\n    意，於其拾得後未幾，執意以新台幣（下同）一千五百元之賤價向甲○買受該贓\n    車，並花費三千元費用將之送修後供己騎用。嗣於九十年十月十一日十七時許，\n    騎乘該機車行經高雄縣燕巢鄉○○路旁時，為警攔檢查獲。\n二、案經高雄縣警察局岡山分局移送臺灣高雄地方法院檢察署檢察官偵查起訴。\n    理  由\n一、訊之被告乙○○固坦承有於右揭時地自甲○處收受上開未懸掛車牌之機車牌一輛\n    並將之送修，花費三千元等事實，惟矢口否認有故買贓物之犯行，辯稱：當時認\n    為機車應該是有人要的，只是想先牽回去等車主來認領，後來看車主久久沒來牽\n    ，因車子還可以騎所以就花了三千元牽去修理，想說修好後也是可以等車主來認\n    領，修好後一直沒有騎，都是放在住處路邊水溝旁，不知是贓車云云。經查，被\n    告乙○○於右揭時地自甲○處所買受上開未懸掛車牌之重型機車一輛係丁○○所\n    有，於九十年四月十日二十三時四十五分許，在高雄縣大社鄉○○路一巷六十六\n    號前失竊之事實，已據被害人丁○○於警訊及本院審理時指訴甚詳，並有贓物認\n    領保管單一紙附卷可稽，是該機車確屬贓車無訛；而該機車係被告在得知友人甲\n    ○拾得後，以一千五百元代價向甲○購得，並花費三千元將之送修後騎用，及該\n    機車之車齡為一年多，於送修時之外觀僅有些許破損，看起仍是有人使用等事實\n    ，亦據被告於警訊及檢察官初訊時坦認不諱，且經證人甲○證述該機車確係伊拾\n    得後交付被告等情明確，並經被害人丁○○證述：「我的車子是二手車，用二萬\n    八買的，賣我的人說他使用了一年多，我買來不到一個月就被偷，之後領回時沒\n    有車牌，車子外殼、後面的燈有損壞、內部零件及鑰匙孔都被破壞了，髒髒的，\n    鑰匙被換過了，車子的外觀顏色與我原來的顏色一樣沒有什麼改變，只是有些損\n    壞，看起來仍是有人在使用的，看起來不會像是人家不要丟棄的東西。車子牽回\n    來之後可以騎但很難騎，我將車子送去整修，花了八仟多元」等語，及證人即機\n    車店老闆丙○○證陳：「我與被告住同村莊，我經營修理機車行，在去年間，詳\n    細日期我忘記了，被告曾牽一部沒有掛車牌的機車來讓我修理，機車是他用牽的\n    牽過來的，修理的那些部分及修理費用我都不記得了，印象中那部機車外觀看起\n    來都很好，沒有什麼破損，看起來像是有人在使用的樣子，其價值應該還有二萬\n    多元。」等語屬實。雖被告仍以前開情詞置辯，惟被告既自陳該機車看起來仍是\n    有人要的，且該機車原係甲○所拾得而持有中，是苟若被告僅意在暫為保管，以\n    待車主前來認領為真，衡情只消建議甲○將之交由警方處理即可，又何需多此一\n    舉，以一千五百元之代價自甲○處取得該機車，並又花費三千元將之送修後，再\n    停放於住所路旁以待車主前來認領，而與常理有悖；再者機車乃現今社會大眾極\n    為通遍之交通工具，且每輛機車均懸掛有車牌並領有行車執照以車籍之管理，凡\n    此均屬眾所周知之事，被告為成年人，自應有此認識，而上開機車於甲○拾得時\n    ，既非他人丟棄不要之物，又未懸掛車牌，亦無車籍資料等證明文件，且遭人置\n    放多時，則值此情形下，若謂被告對該機車有可能係來源不明之贓物無所知悉，\n    孰人能信，然被告卻仍加以買受，並再花錢送修後騎用，其自始應即有縱使所購\n    得之上開機車係屬贓物，亦與其本意不相違背之未必故意至明，是綜上所述，被\n    告上開所辯，顯屬飾卸之詞，不足採信，事證明確，其犯行堪以認定。\n二、按行為人對於構成犯罪之事實，預見其發生而其發生並不違背其本意者，以故意\n    論，刑法第十三條第二項定有明文，此即學說上所稱之間接故意或未必故意，意\n    指行為人對於構成犯罪事實之可能發生有所預見，在主觀之構成要件上雖乏積極\n    付諸實現之意欲，惟仍聽任令其自然發展，終至犯罪結果發生，且與其本意不相\n    違背之心態之謂；本件被告乙○○向友人甲○購買上開機車時，該機車之外觀僅\n    有些許破損，未致不能使用之程度，而顯可認為有人使用之車輛，且知係甲○拾\n    得，並無車籍資料亦未懸掛車牌無從辦理過手續，以擔保來源之正當性，依此當\n    可預料該輛機車係屬來路不明之贓物可能性甚大，卻仍決意加以買受，顯見其自\n    始即有縱使所購得之機車係贓物亦與其本意不相違背之未必故意至明，是核其所\n    為，係犯刑法第三百四十九條第二項之故買贓物罪。爰審酌被告因一時貪念，致\n    罹刑章，所犯情節尚非重大，且犯後態度尚稱良好，及所得財物已為被害人領回\n    等一切情狀，量處如主文所示之刑，並諭知易科罰金之折算標準，以資懲儆。至\n    扣案之機車鑰匙一支雖係被告所有，惟非供其犯罪所用之物，爰不併為沒收之諭\n    知，附此敘明。\n據上論斷，應依刑事訴訟法第二百九十九條第一項前段，刑法第三百四十九條第二項\n、第四十一條第一項前段、罰金罰鍰提高標準條例第一條前段、第二條，判決如主文\n。\n中      華      民      國      九十一    年      八      月     六     日\n                                    臺灣高雄地方法院刑事第三庭\n                                        法    官  柯彩燕\n右正本證明與原本無異。\n如不服本判決，應於判決送達後十日內，向本院提出上訴狀。\n                                書記官    楊真芬\n中    華    民    國      九十一      年      八      月      八      日\n",
  "structure": {
    "main": "乙○○故買贓物，處拘役參拾日，如易科罰金，以參佰元折算壹日。",
    "fact": "一、乙○○明知友人甲○於民國九十年六月間某日，在高雄縣燕巢鄉甘蔗園內所拾得\n    引擎號碼ＣＧ00000000號之重型機車一輛（該車原車牌號碼為ＸＴＦ─\n    二一六號、係丁○○所有，於九十年四月十日二十三時四十五分許，在高雄縣大\n    社鄉○○路一巷六十六號前失竊），並無車籍證件亦未懸掛車牌，且係遭人置放\n    該處多時始經甲○拾回，有可能係來源不明之贓物，竟仍基於不惜違法之未必故\n    意，於其拾得後未幾，執意以新台幣（下同）一千五百元之賤價向甲○買受該贓\n    車，並花費三千元費用將之送修後供己騎用。嗣於九十年十月十一日十七時許，\n    騎乘該機車行經高雄縣燕巢鄉○○路旁時，為警攔檢查獲。\n二、案經高雄縣警察局岡山分局移送臺灣高雄地方法院檢察署檢察官偵查起訴。",
    "reason": "一、訊之被告乙○○固坦承有於右揭時地自甲○處收受上開未懸掛車牌之機車牌一輛\n    並將之送修，花費三千元等事實，惟矢口否認有故買贓物之犯行，辯稱：當時認\n    為機車應該是有人要的，只是想先牽回去等車主來認領，後來看車主久久沒來牽\n    ，因車子還可以騎所以就花了三千元牽去修理，想說修好後也是可以等車主來認\n    領，修好後一直沒有騎，都是放在住處路邊水溝旁，不知是贓車云云。經查，被\n    告乙○○於右揭時地自甲○處所買受上開未懸掛車牌之重型機車一輛係丁○○所\n    有，於九十年四月十日二十三時四十五分許，在高雄縣大社鄉○○路一巷六十六\n    號前失竊之事實，已據被害人丁○○於警訊及本院審理時指訴甚詳，並有贓物認\n    領保管單一紙附卷可稽，是該機車確屬贓車無訛；而該機車係被告在得知友人甲\n    ○拾得後，以一千五百元代價向甲○購得，並花費三千元將之送修後騎用，及該\n    機車之車齡為一年多，於送修時之外觀僅有些許破損，看起仍是有人使用等事實\n    ，亦據被告於警訊及檢察官初訊時坦認不諱，且經證人甲○證述該機車確係伊拾\n    得後交付被告等情明確，並經被害人丁○○證述：「我的車子是二手車，用二萬\n    八買的，賣我的人說他使用了一年多，我買來不到一個月就被偷，之後領回時沒\n    有車牌，車子外殼、後面的燈有損壞、內部零件及鑰匙孔都被破壞了，髒髒的，\n    鑰匙被換過了，車子的外觀顏色與我原來的顏色一樣沒有什麼改變，只是有些損\n    壞，看起來仍是有人在使用的，看起來不會像是人家不要丟棄的東西。車子牽回\n    來之後可以騎但很難騎，我將車子送去整修，花了八仟多元」等語，及證人即機\n    車店老闆丙○○證陳：「我與被告住同村莊，我經營修理機車行，在去年間，詳\n    細日期我忘記了，被告曾牽一部沒有掛車牌的機車來讓我修理，機車是他用牽的\n    牽過來的，修理的那些部分及修理費用我都不記得了，印象中那部機車外觀看起\n    來都很好，沒有什麼破損，看起來像是有人在使用的樣子，其價值應該還有二萬\n    多元。」等語屬實。雖被告仍以前開情詞置辯，惟被告既自陳該機車看起來仍是\n    有人要的，且該機車原係甲○所拾得而持有中，是苟若被告僅意在暫為保管，以\n    待車主前來認領為真，衡情只消建議甲○將之交由警方處理即可，又何需多此一\n    舉，以一千五百元之代價自甲○處取得該機車，並又花費三千元將之送修後，再\n    停放於住所路旁以待車主前來認領，而與常理有悖；再者機車乃現今社會大眾極\n    為通遍之交通工具，且每輛機車均懸掛有車牌並領有行車執照以車籍之管理，凡\n    此均屬眾所周知之事，被告為成年人，自應有此認識，而上開機車於甲○拾得時\n    ，既非他人丟棄不要之物，又未懸掛車牌，亦無車籍資料等證明文件，且遭人置\n    放多時，則值此情形下，若謂被告對該機車有可能係來源不明之贓物無所知悉，\n    孰人能信，然被告卻仍加以買受，並再花錢送修後騎用，其自始應即有縱使所購\n    得之上開機車係屬贓物，亦與其本意不相違背之未必故意至明，是綜上所述，被\n    告上開所辯，顯屬飾卸之詞，不足採信，事證明確，其犯行堪以認定。\n二、按行為人對於構成犯罪之事實，預見其發生而其發生並不違背其本意者，以故意\n    論，刑法第十三條第二項定有明文，此即學說上所稱之間接故意或未必故意，意\n    指行為人對於構成犯罪事實之可能發生有所預見，在主觀之構成要件上雖乏積極\n    付諸實現之意欲，惟仍聽任令其自然發展，終至犯罪結果發生，且與其本意不相\n    違背之心態之謂；本件被告乙○○向友人甲○購買上開機車時，該機車之外觀僅\n    有些許破損，未致不能使用之程度，而顯可認為有人使用之車輛，且知係甲○拾\n    得，並無車籍資料亦未懸掛車牌無從辦理過手續，以擔保來源之正當性，依此當\n    可預料該輛機車係屬來路不明之贓物可能性甚大，卻仍決意加以買受，顯見其自\n    始即有縱使所購得之機車係贓物亦與其本意不相違背之未必故意至明，是核其所\n    為，係犯刑法第三百四十九條第二項之故買贓物罪。爰審酌被告因一時貪念，致\n    罹刑章，所犯情節尚非重大，且犯後態度尚稱良好，及所得財物已為被害人領回\n    等一切情狀，量處如主文所示之刑，並諭知易科罰金之折算標準，以資懲儆。至\n    扣案之機車鑰匙一支雖係被告所有，惟非供其犯罪所用之物，爰不併為沒收之諭\n    知，附此敘明。\n據上論斷，應依刑事訴訟法第二百九十九條第一項前段，刑法第三百四十九條第二項\n、第四十一條第一項前段、罰金罰鍰提高標準條例第一條前段、第二條，判決如主文\n。\n中      華      民      國      九十一    年      八      月     六     日\n                                    臺灣高雄地方法院刑事第三庭\n                                        法    官  柯彩燕\n右正本證明與原本無異。\n如不服本判決，應於判決送達後十日內，向本院提出上訴狀。\n                                書記官    楊真芬"
  },
  "search": "臺灣高雄地方法院刑事判決九十一年度易字第一一八二號公訴人臺灣高雄地方法院檢察署檢察官被告乙○○右列被告因贓物案件，經檢察官提起公訴（九十年度偵字第一九四四三號），本院判決如左：主文乙○○故買贓物，處拘役參拾日，如易科罰金，以參佰元折算壹日。事實一、乙○○明知友人甲○於民國九十年六月間某日，在高雄縣燕巢鄉甘蔗園內所拾得引擎號碼ＣＧ00000000號之重型機車一輛（該車原車牌號碼為ＸＴＦ─二一六號、係丁○○所有，於九十年四月十日二十三時四十五分許，在高雄縣大社鄉○○路一巷六十六號前失竊），並無車籍證件亦未懸掛車牌，且係遭人置放該處多時始經甲○拾回，有可能係來源不明之贓物，竟仍基於不惜違法之未必故意，於其拾得後未幾，執意以新台幣（下同）一千五百元之賤價向甲○買受該贓車，並花費三千元費用將之送修後供己騎用。嗣於九十年十月十一日十七時許，騎乘該機車行經高雄縣燕巢鄉○○路旁時，為警攔檢查獲。二、案經高雄縣警察局岡山分局移送臺灣高雄地方法院檢察署檢察官偵查起訴。理由一、訊之被告乙○○固坦承有於右揭時地自甲○處收受上開未懸掛車牌之機車牌一輛並將之送修，花費三千元等事實，惟矢口否認有故買贓物之犯行，辯稱：當時認為機車應該是有人要的，只是想先牽回去等車主來認領，後來看車主久久沒來牽，因車子還可以騎所以就花了三千元牽去修理，想說修好後也是可以等車主來認領，修好後一直沒有騎，都是放在住處路邊水溝旁，不知是贓車云云。經查，被告乙○○於右揭時地自甲○處所買受上開未懸掛車牌之重型機車一輛係丁○○所有，於九十年四月十日二十三時四十五分許，在高雄縣大社鄉○○路一巷六十六號前失竊之事實，已據被害人丁○○於警訊及本院審理時指訴甚詳，並有贓物認領保管單一紙附卷可稽，是該機車確屬贓車無訛；而該機車係被告在得知友人甲○拾得後，以一千五百元代價向甲○購得，並花費三千元將之送修後騎用，及該機車之車齡為一年多，於送修時之外觀僅有些許破損，看起仍是有人使用等事實，亦據被告於警訊及檢察官初訊時坦認不諱，且經證人甲○證述該機車確係伊拾得後交付被告等情明確，並經被害人丁○○證述：「我的車子是二手車，用二萬八買的，賣我的人說他使用了一年多，我買來不到一個月就被偷，之後領回時沒有車牌，車子外殼、後面的燈有損壞、內部零件及鑰匙孔都被破壞了，髒髒的，鑰匙被換過了，車子的外觀顏色與我原來的顏色一樣沒有什麼改變，只是有些損壞，看起來仍是有人在使用的，看起來不會像是人家不要丟棄的東西。車子牽回來之後可以騎但很難騎，我將車子送去整修，花了八仟多元」等語，及證人即機車店老闆丙○○證陳：「我與被告住同村莊，我經營修理機車行，在去年間，詳細日期我忘記了，被告曾牽一部沒有掛車牌的機車來讓我修理，機車是他用牽的牽過來的，修理的那些部分及修理費用我都不記得了，印象中那部機車外觀看起來都很好，沒有什麼破損，看起來像是有人在使用的樣子，其價值應該還有二萬多元。」等語屬實。雖被告仍以前開情詞置辯，惟被告既自陳該機車看起來仍是有人要的，且該機車原係甲○所拾得而持有中，是苟若被告僅意在暫為保管，以待車主前來認領為真，衡情只消建議甲○將之交由警方處理即可，又何需多此一舉，以一千五百元之代價自甲○處取得該機車，並又花費三千元將之送修後，再停放於住所路旁以待車主前來認領，而與常理有悖；再者機車乃現今社會大眾極為通遍之交通工具，且每輛機車均懸掛有車牌並領有行車執照以車籍之管理，凡此均屬眾所周知之事，被告為成年人，自應有此認識，而上開機車於甲○拾得時，既非他人丟棄不要之物，又未懸掛車牌，亦無車籍資料等證明文件，且遭人置放多時，則值此情形下，若謂被告對該機車有可能係來源不明之贓物無所知悉，孰人能信，然被告卻仍加以買受，並再花錢送修後騎用，其自始應即有縱使所購得之上開機車係屬贓物，亦與其本意不相違背之未必故意至明，是綜上所述，被告上開所辯，顯屬飾卸之詞，不足採信，事證明確，其犯行堪以認定。二、按行為人對於構成犯罪之事實，預見其發生而其發生並不違背其本意者，以故意論，刑法第十三條第二項定有明文，此即學說上所稱之間接故意或未必故意，意指行為人對於構成犯罪事實之可能發生有所預見，在主觀之構成要件上雖乏積極付諸實現之意欲，惟仍聽任令其自然發展，終至犯罪結果發生，且與其本意不相違背之心態之謂；本件被告乙○○向友人甲○購買上開機車時，該機車之外觀僅有些許破損，未致不能使用之程度，而顯可認為有人使用之車輛，且知係甲○拾得，並無車籍資料亦未懸掛車牌無從辦理過手續，以擔保來源之正當性，依此當可預料該輛機車係屬來路不明之贓物可能性甚大，卻仍決意加以買受，顯見其自始即有縱使所購得之機車係贓物亦與其本意不相違背之未必故意至明，是核其所為，係犯刑法第三百四十九條第二項之故買贓物罪。爰審酌被告因一時貪念，致罹刑章，所犯情節尚非重大，且犯後態度尚稱良好，及所得財物已為被害人領回等一切情狀，量處如主文所示之刑，並諭知易科罰金之折算標準，以資懲儆。至扣案之機車鑰匙一支雖係被告所有，惟非供其犯罪所用之物，爰不併為沒收之諭知，附此敘明。據上論斷，應依刑事訴訟法第二百九十九條第一項前段，刑法第三百四十九條第二項、第四十一條第一項前段、罰金罰鍰提高標準條例第一條前段、第二條，判決如主文。中華民國九十一年八月六日臺灣高雄地方法院刑事第三庭法官柯彩燕右正本證明與原本無異。如不服本判決，應於判決送達後十日內，向本院提出上訴狀。書記官楊真芬中華民國九十一年八月八日",
  "characters": {
    "judges": [
      "柯彩燕"
    ],
    "prosecutors": [

    ],
    "lawyers": [

    ],
    "clerks": [
      "楊真芬"
    ],
    "plaintiffs": [

    ],
    "defendants": [
      "乙○○",
      "右列被告因贓物案件，經檢察官提起公訴（九十年度偵字第一九四四三號），本院判",
      "決如左："
    ],
    "prosecutor_office": [
      "臺灣高雄地方法院檢察署檢察官"
    ],
    "creditors": [

    ],
    "debtors": [

    ],
    "judicial_associate_officer": [

    ]
  },
  "adjudged_at": "2002-08-06",
  "created_at": "2016-02-04 18:59:22",
  "updated_at": "2016-02-04 18:59:22"
}