{
  "identify": "KSD-99-審訴-2973-20110318-1",
  "court": {
    "name": "臺灣高雄地方法院",
    "code": "KSD"
  },
  "division": {
    "name": "刑事",
    "code": "M"
  },
  "year": 99,
  "word": "審訴",
  "number": "2973",
  "jcheck": "1",
  "reason": "毒品危害防制條例",
  "content": "臺灣高雄地方法院刑事判決            99年度審訴字第2973號\n公  訴  人  臺灣高雄地方法院檢察署檢察官\n被      告  蘇文志\n上列被告因違反毒品危害防制條例案件，經檢察官提起公訴（99\n年度毒偵字第4192號），本院合議庭裁定由受命法官獨任行簡式\n審判程序，判決如下：\n    主  文\n蘇文志施用第一級毒品，累犯，處有期徒刑玖月。\n    事實及理由\n一、犯罪事實：\n    蘇文志前因施用毒品案件，經臺灣屏東地方法院以民國88年\n    度毒聲字第2243號裁定送觀察勒戒後，認有繼續施用毒品之\n    傾向，再以88年度毒聲字第2444號裁定令入戒治處所施以強\n    制戒治，嗣以88年度毒聲字第871 號裁定停止戒治付保護管\n    束，於89年11月17日期滿，視為執行完畢，並經臺灣屏東地\n    方法院檢察署檢察官以89年度戒毒偵字第467 號不起訴處分\n    確定。又於前揭強制戒治執行完畢後5 年內即92年間，又因\n    施用毒品案件，經本院以92年度訴字第995 號判處有期徒刑\n    10月確定，於94年8 月31日縮刑期滿執行完畢。詎仍未戒除\n    毒癮，基於施用第一級毒品海洛因之犯意，於99年3 月16或\n    17日某時許，在高雄市○○區○○路506 巷3 號住處，以將\n    海洛因摻水置於針筒內注射血管之方式，施用第一級毒品海\n    洛因1 次。嗣於99年3 月18日下午2 時30分許，在高雄市○\n    ○區○○路506 巷口，因形跡可疑，為警趨前盤查，並徵得\n    其同意採尿送驗，結果呈可待因及嗎啡陽性反應，始查獲上\n    情。\n二、程序部分：\n  (一)本件被告蘇文志所犯係死刑、無期徒刑、最輕本刑為3 年以\n    上有期徒刑以外之罪，其於準備程序中就被訴事實為有罪之\n    陳述，經法官告知簡式審判程序之旨，並聽取公訴人、被告\n    之意見後，本院合議庭認為適宜而裁定由受命法官獨任進行\n    簡式審判程序，先予敘明。\n  (二)被告前經送觀察、勒戒、強制戒治執行完畢後5 年內，已再\n    犯施用毒品案件，經法院判刑確定，是被告於「初犯」經觀\n    察、勒戒、強制戒治後，曾於5 年內再犯，經依法追訴處罰\n    ，本件施用毒品行為已屬3 犯以上，檢察官逕行起訴，即無\n    不合。\n三、證據名稱：\n  (一)高雄市立凱旋醫院99年4月8日濫用藥物尿液檢驗報告、高雄\n    市政府警察局三民二分局偵辦毒品案件嫌疑人尿液採證代碼\n    對照表各1份。\n  (二)被告之自白。\n四、論罪：\n    海洛因為毒品危害防制條例第2 條第2 項第1 款規定之第一\n    級毒品，依法不得施用、持有，是核被告蘇文志所為，係犯\n    毒品危害防制條例第10條第1 項施用第一級毒品罪。被告施\n    用第一級毒品海洛因前持有海洛因之低度行為，應為施用之\n    高度行為所吸收，不另論罪。被告有犯罪事實欄所述經判處\n    有期徒刑並執行完畢之情形，此有臺灣高等法院被告前案紀\n    錄表在卷可佐，其於徒刑執行完畢5 年之內故意再犯本件有\n    期徒刑以上之 罪，為累犯，應依法加重其刑。\n五、科刑：\n    爰審酌施用毒品之行為不僅戕害自身身心健康，亦間接影響\n    社會治安，被告前經觀察、勒戒、強制戒治執行完畢，又因\n    施用毒品等案件入監執行，方於97年12月23日假釋出監，且\n    於98年6 月因施用毒品遭警查獲，並經最高法院以99年台上\n    字第376 號判處有期徒刑8 月確定，被告於該案判決確定後\n    ，竟再犯本件犯行，顯見先前之偵審程序已不足以使被告心\n    生警惕或阻止被告施用毒品，其對毒品之依賴情形應已非輕\n    ，為達預防被告再犯之目的，應使被告受一定之監督及隔離\n    ，較有利於被告戒除毒癮，並考量被告犯後坦承犯行等一切\n    情狀，量處如主文所示之刑。\n據上論斷，應依刑事訴訟法第273 條之1 第1 項、第299 條第1\n項前段、第310 條之2 、第454 條，毒品危害防制條例第10條第\n1 項，刑法第11條前段、第47條第1項，判決如主文。\n本案經檢察官李英霆到庭執行職務。\n中    華    民    國   100    年    3     月    18    日\n                  刑事第十庭    法  官  王靖茹\n以上正本證明與原本無異。\n如不服本判決應於收受判決後10日內向本院提出上訴書狀，並應\n敘述具體理由。其未敘述上訴理由者，應於上訴期間屆滿後20日\n內向本院補提理由書(均須按他造當事人之人數附繕本)「切勿逕\n送上級法院」。\n中    華    民    國   100    年    3     月    18    日\n                                書記官  楊明月\n附錄本案論罪科刑法條：\n毒品危害防制條例第10條第1項\n施用第一級毒品者，處 6 月以上 5 年以下有期徒刑。",
  "structure": {
    "main": "蘇文志施用第一級毒品，累犯，處有期徒刑玖月。",
    "fact": "一、犯罪事實：\n    蘇文志前因施用毒品案件，經臺灣屏東地方法院以民國88年\n    度毒聲字第2243號裁定送觀察勒戒後，認有繼續施用毒品之\n    傾向，再以88年度毒聲字第2444號裁定令入戒治處所施以強\n    制戒治，嗣以88年度毒聲字第871 號裁定停止戒治付保護管\n    束，於89年11月17日期滿，視為執行完畢，並經臺灣屏東地\n    方法院檢察署檢察官以89年度戒毒偵字第467 號不起訴處分\n    確定。又於前揭強制戒治執行完畢後5 年內即92年間，又因\n    施用毒品案件，經本院以92年度訴字第995 號判處有期徒刑\n    10月確定，於94年8 月31日縮刑期滿執行完畢。詎仍未戒除\n    毒癮，基於施用第一級毒品海洛因之犯意，於99年3 月16或\n    17日某時許，在高雄市○○區○○路506 巷3 號住處，以將\n    海洛因摻水置於針筒內注射血管之方式，施用第一級毒品海\n    洛因1 次。嗣於99年3 月18日下午2 時30分許，在高雄市○\n    ○區○○路506 巷口，因形跡可疑，為警趨前盤查，並徵得\n    其同意採尿送驗，結果呈可待因及嗎啡陽性反應，始查獲上\n    情。\n二、程序部分：\n  (一)本件被告蘇文志所犯係死刑、無期徒刑、最輕本刑為3 年以\n    上有期徒刑以外之罪，其於準備程序中就被訴事實為有罪之\n    陳述，經法官告知簡式審判程序之旨，並聽取公訴人、被告\n    之意見後，本院合議庭認為適宜而裁定由受命法官獨任進行\n    簡式審判程序，先予敘明。\n  (二)被告前經送觀察、勒戒、強制戒治執行完畢後5 年內，已再\n    犯施用毒品案件，經法院判刑確定，是被告於「初犯」經觀\n    察、勒戒、強制戒治後，曾於5 年內再犯，經依法追訴處罰\n    ，本件施用毒品行為已屬3 犯以上，檢察官逕行起訴，即無\n    不合。\n三、證據名稱：\n  (一)高雄市立凱旋醫院99年4月8日濫用藥物尿液檢驗報告、高雄\n    市政府警察局三民二分局偵辦毒品案件嫌疑人尿液採證代碼\n    對照表各1份。\n  (二)被告之自白。\n四、論罪：\n    海洛因為毒品危害防制條例第2 條第2 項第1 款規定之第一\n    級毒品，依法不得施用、持有，是核被告蘇文志所為，係犯\n    毒品危害防制條例第10條第1 項施用第一級毒品罪。被告施\n    用第一級毒品海洛因前持有海洛因之低度行為，應為施用之\n    高度行為所吸收，不另論罪。被告有犯罪事實欄所述經判處\n    有期徒刑並執行完畢之情形，此有臺灣高等法院被告前案紀\n    錄表在卷可佐，其於徒刑執行完畢5 年之內故意再犯本件有\n    期徒刑以上之 罪，為累犯，應依法加重其刑。\n五、科刑：\n    爰審酌施用毒品之行為不僅戕害自身身心健康，亦間接影響\n    社會治安，被告前經觀察、勒戒、強制戒治執行完畢，又因\n    施用毒品等案件入監執行，方於97年12月23日假釋出監，且\n    於98年6 月因施用毒品遭警查獲，並經最高法院以99年台上\n    字第376 號判處有期徒刑8 月確定，被告於該案判決確定後\n    ，竟再犯本件犯行，顯見先前之偵審程序已不足以使被告心\n    生警惕或阻止被告施用毒品，其對毒品之依賴情形應已非輕\n    ，為達預防被告再犯之目的，應使被告受一定之監督及隔離\n    ，較有利於被告戒除毒癮，並考量被告犯後坦承犯行等一切\n    情狀，量處如主文所示之刑。\n據上論斷，應依刑事訴訟法第273 條之1 第1 項、第299 條第1\n項前段、第310 條之2 、第454 條，毒品危害防制條例第10條第\n1 項，刑法第11條前段、第47條第1項，判決如主文。\n本案經檢察官李英霆到庭執行職務。",
    "reason": "一、犯罪事實：\n    蘇文志前因施用毒品案件，經臺灣屏東地方法院以民國88年\n    度毒聲字第2243號裁定送觀察勒戒後，認有繼續施用毒品之\n    傾向，再以88年度毒聲字第2444號裁定令入戒治處所施以強\n    制戒治，嗣以88年度毒聲字第871 號裁定停止戒治付保護管\n    束，於89年11月17日期滿，視為執行完畢，並經臺灣屏東地\n    方法院檢察署檢察官以89年度戒毒偵字第467 號不起訴處分\n    確定。又於前揭強制戒治執行完畢後5 年內即92年間，又因\n    施用毒品案件，經本院以92年度訴字第995 號判處有期徒刑\n    10月確定，於94年8 月31日縮刑期滿執行完畢。詎仍未戒除\n    毒癮，基於施用第一級毒品海洛因之犯意，於99年3 月16或\n    17日某時許，在高雄市○○區○○路506 巷3 號住處，以將\n    海洛因摻水置於針筒內注射血管之方式，施用第一級毒品海\n    洛因1 次。嗣於99年3 月18日下午2 時30分許，在高雄市○\n    ○區○○路506 巷口，因形跡可疑，為警趨前盤查，並徵得\n    其同意採尿送驗，結果呈可待因及嗎啡陽性反應，始查獲上\n    情。\n二、程序部分：\n  (一)本件被告蘇文志所犯係死刑、無期徒刑、最輕本刑為3 年以\n    上有期徒刑以外之罪，其於準備程序中就被訴事實為有罪之\n    陳述，經法官告知簡式審判程序之旨，並聽取公訴人、被告\n    之意見後，本院合議庭認為適宜而裁定由受命法官獨任進行\n    簡式審判程序，先予敘明。\n  (二)被告前經送觀察、勒戒、強制戒治執行完畢後5 年內，已再\n    犯施用毒品案件，經法院判刑確定，是被告於「初犯」經觀\n    察、勒戒、強制戒治後，曾於5 年內再犯，經依法追訴處罰\n    ，本件施用毒品行為已屬3 犯以上，檢察官逕行起訴，即無\n    不合。\n三、證據名稱：\n  (一)高雄市立凱旋醫院99年4月8日濫用藥物尿液檢驗報告、高雄\n    市政府警察局三民二分局偵辦毒品案件嫌疑人尿液採證代碼\n    對照表各1份。\n  (二)被告之自白。\n四、論罪：\n    海洛因為毒品危害防制條例第2 條第2 項第1 款規定之第一\n    級毒品，依法不得施用、持有，是核被告蘇文志所為，係犯\n    毒品危害防制條例第10條第1 項施用第一級毒品罪。被告施\n    用第一級毒品海洛因前持有海洛因之低度行為，應為施用之\n    高度行為所吸收，不另論罪。被告有犯罪事實欄所述經判處\n    有期徒刑並執行完畢之情形，此有臺灣高等法院被告前案紀\n    錄表在卷可佐，其於徒刑執行完畢5 年之內故意再犯本件有\n    期徒刑以上之 罪，為累犯，應依法加重其刑。\n五、科刑：\n    爰審酌施用毒品之行為不僅戕害自身身心健康，亦間接影響\n    社會治安，被告前經觀察、勒戒、強制戒治執行完畢，又因\n    施用毒品等案件入監執行，方於97年12月23日假釋出監，且\n    於98年6 月因施用毒品遭警查獲，並經最高法院以99年台上\n    字第376 號判處有期徒刑8 月確定，被告於該案判決確定後\n    ，竟再犯本件犯行，顯見先前之偵審程序已不足以使被告心\n    生警惕或阻止被告施用毒品，其對毒品之依賴情形應已非輕\n    ，為達預防被告再犯之目的，應使被告受一定之監督及隔離\n    ，較有利於被告戒除毒癮，並考量被告犯後坦承犯行等一切\n    情狀，量處如主文所示之刑。\n據上論斷，應依刑事訴訟法第273 條之1 第1 項、第299 條第1\n項前段、第310 條之2 、第454 條，毒品危害防制條例第10條第\n1 項，刑法第11條前段、第47條第1項，判決如主文。\n本案經檢察官李英霆到庭執行職務。"
  },
  "search": "臺灣高雄地方法院刑事判決99年度審訴字第2973號公訴人臺灣高雄地方法院檢察署檢察官被告蘇文志上列被告因違反毒品危害防制條例案件，經檢察官提起公訴（99年度毒偵字第4192號），本院合議庭裁定由受命法官獨任行簡式審判程序，判決如下：主文蘇文志施用第一級毒品，累犯，處有期徒刑玖月。事實及理由一、犯罪事實：蘇文志前因施用毒品案件，經臺灣屏東地方法院以民國88年度毒聲字第2243號裁定送觀察勒戒後，認有繼續施用毒品之傾向，再以88年度毒聲字第2444號裁定令入戒治處所施以強制戒治，嗣以88年度毒聲字第871號裁定停止戒治付保護管束，於89年11月17日期滿，視為執行完畢，並經臺灣屏東地方法院檢察署檢察官以89年度戒毒偵字第467號不起訴處分確定。又於前揭強制戒治執行完畢後5年內即92年間，又因施用毒品案件，經本院以92年度訴字第995號判處有期徒刑10月確定，於94年8月31日縮刑期滿執行完畢。詎仍未戒除毒癮，基於施用第一級毒品海洛因之犯意，於99年3月16或17日某時許，在高雄市○○區○○路506巷3號住處，以將海洛因摻水置於針筒內注射血管之方式，施用第一級毒品海洛因1次。嗣於99年3月18日下午2時30分許，在高雄市○○區○○路506巷口，因形跡可疑，為警趨前盤查，並徵得其同意採尿送驗，結果呈可待因及嗎啡陽性反應，始查獲上情。二、程序部分：(一)本件被告蘇文志所犯係死刑、無期徒刑、最輕本刑為3年以上有期徒刑以外之罪，其於準備程序中就被訴事實為有罪之陳述，經法官告知簡式審判程序之旨，並聽取公訴人、被告之意見後，本院合議庭認為適宜而裁定由受命法官獨任進行簡式審判程序，先予敘明。(二)被告前經送觀察、勒戒、強制戒治執行完畢後5年內，已再犯施用毒品案件，經法院判刑確定，是被告於「初犯」經觀察、勒戒、強制戒治後，曾於5年內再犯，經依法追訴處罰，本件施用毒品行為已屬3犯以上，檢察官逕行起訴，即無不合。三、證據名稱：(一)高雄市立凱旋醫院99年4月8日濫用藥物尿液檢驗報告、高雄市政府警察局三民二分局偵辦毒品案件嫌疑人尿液採證代碼對照表各1份。(二)被告之自白。四、論罪：海洛因為毒品危害防制條例第2條第2項第1款規定之第一級毒品，依法不得施用、持有，是核被告蘇文志所為，係犯毒品危害防制條例第10條第1項施用第一級毒品罪。被告施用第一級毒品海洛因前持有海洛因之低度行為，應為施用之高度行為所吸收，不另論罪。被告有犯罪事實欄所述經判處有期徒刑並執行完畢之情形，此有臺灣高等法院被告前案紀錄表在卷可佐，其於徒刑執行完畢5年之內故意再犯本件有期徒刑以上之罪，為累犯，應依法加重其刑。五、科刑：爰審酌施用毒品之行為不僅戕害自身身心健康，亦間接影響社會治安，被告前經觀察、勒戒、強制戒治執行完畢，又因施用毒品等案件入監執行，方於97年12月23日假釋出監，且於98年6月因施用毒品遭警查獲，並經最高法院以99年台上字第376號判處有期徒刑8月確定，被告於該案判決確定後，竟再犯本件犯行，顯見先前之偵審程序已不足以使被告心生警惕或阻止被告施用毒品，其對毒品之依賴情形應已非輕，為達預防被告再犯之目的，應使被告受一定之監督及隔離，較有利於被告戒除毒癮，並考量被告犯後坦承犯行等一切情狀，量處如主文所示之刑。據上論斷，應依刑事訴訟法第273條之1第1項、第299條第1項前段、第310條之2、第454條，毒品危害防制條例第10條第1項，刑法第11條前段、第47條第1項，判決如主文。本案經檢察官李英霆到庭執行職務。中華民國100年3月18日刑事第十庭法官王靖茹以上正本證明與原本無異。如不服本判決應於收受判決後10日內向本院提出上訴書狀，並應敘述具體理由。其未敘述上訴理由者，應於上訴期間屆滿後20日內向本院補提理由書(均須按他造當事人之人數附繕本)「切勿逕送上級法院」。中華民國100年3月18日書記官楊明月附錄本案論罪科刑法條：毒品危害防制條例第10條第1項施用第一級毒品者，處6月以上5年以下有期徒刑。",
  "characters": {
    "judges": [
      "王靖茹"
    ],
    "prosecutors": [
      "李英霆"
    ],
    "lawyers": [

    ],
    "clerks": [
      "楊明月"
    ],
    "plaintiffs": [

    ],
    "defendants": [
      "蘇文志"
    ],
    "prosecutor_office": [
      "臺灣高雄地方法院檢察署檢察官"
    ],
    "creditors": [

    ],
    "debtors": [

    ],
    "judicial_associate_officer": [

    ]
  },
  "adjudged_at": "2011-03-18",
  "created_at": "2016-02-13 19:18:17",
  "updated_at": "2016-02-13 19:18:17"
}