{
  "identify": "TND-100-簡-547-20110318-1",
  "court": {
    "name": "臺灣南投地方法院",
    "code": "TND"
  },
  "division": {
    "name": "刑事",
    "code": "M"
  },
  "year": 100,
  "word": "簡",
  "number": "547",
  "jcheck": "1",
  "reason": "違反毒品危害防制條例",
  "content": "臺灣臺南地方法院刑事簡易判決          100年度簡字第547號\n聲  請  人  臺灣臺南地方法院檢察署檢察官\n被      告  林正修\n上列被告因違反毒品危害防制條例案件，經檢察官聲請以簡易判\n決處刑（100年度毒偵字第425號），本院判決如下：\n    主  文\n林正修施用第二級毒品，處有期徒刑參月，如易科罰金，以新臺\n幣壹仟元折算壹日。\n    事實及理由\n一、本件犯罪事實及證據名稱，均引用檢察官聲請簡易判決處刑\n    書之記載（如附件）。\n二、被告有犯罪事實欄所載前因施用毒品執行觀察、勒戒處分，\n    甫於民國99年12月29日執行完畢釋放之執行紀錄，此有臺灣\n    高等法院被告前案紀錄表1 份在卷可按，本件係其於觀察、\n    勒戒執行完畢釋放後，5 年內再犯施用第二級毒品罪，應由\n    本院依法論罪科刑，合先敘明。甲基安非他命屬毒品危害防\n    制條例第2 條第2 項第2 款所稱之第二級毒品，不得持有、\n    施用，被告竟持以施用，核其所為，係犯同條例第10條第2\n    項之施用第二級毒品罪。其施用前持有甲基安非他命之低度\n    行為，應為施用之高度行為所吸收，不另論罪。爰審酌被告\n    甫經觀察、勒戒，仍未能戒除毒癮，顯見其無戒毒悔改之意\n    ，惟念其施用毒品乃自戕行為，並兼衡其智識程度、生活狀\n    況及犯後態度等一切情狀，量處如主文所示之刑，並諭知易\n    科罰金之折算標準。\n三、應依刑事訴訟法第449 條第1 項前段、第3 項、第454 條第\n    2 項，毒品危害防制條例第10條第2 項，刑法第11條前段、\n    第41條第1 項前段，逕以簡易判決如主文。\n四、如不服本判決，得自收受送達後10日內，向本院提出上訴狀\n    （附繕本），上訴於本院管轄之第二審地方法院合議庭。\n中    華    民    國  100    年    3    月    18    日\n                  刑事第十庭    法  官  羅郁棣\n以上正本證明與原本無異。\n                                書記官  黃玉秀\n中    華    民    國  100    年    3    月    18    日\n附錄所犯法條：\n毒品危害防制條例第10條第2項\n施用第一級毒品者，處 6 月以上 5 年以下有期徒刑。\n施用第二級毒品者，處 3 年以下有期徒刑。",
  "structure": {
    "main": "林正修施用第二級毒品，處有期徒刑參月，如易科罰金，以新臺\n幣壹仟元折算壹日。",
    "fact": "一、本件犯罪事實及證據名稱，均引用檢察官聲請簡易判決處刑\n    書之記載（如附件）。\n二、被告有犯罪事實欄所載前因施用毒品執行觀察、勒戒處分，\n    甫於民國99年12月29日執行完畢釋放之執行紀錄，此有臺灣\n    高等法院被告前案紀錄表1 份在卷可按，本件係其於觀察、\n    勒戒執行完畢釋放後，5 年內再犯施用第二級毒品罪，應由\n    本院依法論罪科刑，合先敘明。甲基安非他命屬毒品危害防\n    制條例第2 條第2 項第2 款所稱之第二級毒品，不得持有、\n    施用，被告竟持以施用，核其所為，係犯同條例第10條第2\n    項之施用第二級毒品罪。其施用前持有甲基安非他命之低度\n    行為，應為施用之高度行為所吸收，不另論罪。爰審酌被告\n    甫經觀察、勒戒，仍未能戒除毒癮，顯見其無戒毒悔改之意\n    ，惟念其施用毒品乃自戕行為，並兼衡其智識程度、生活狀\n    況及犯後態度等一切情狀，量處如主文所示之刑，並諭知易\n    科罰金之折算標準。\n三、應依刑事訴訟法第449 條第1 項前段、第3 項、第454 條第\n    2 項，毒品危害防制條例第10條第2 項，刑法第11條前段、\n    第41條第1 項前段，逕以簡易判決如主文。\n四、如不服本判決，得自收受送達後10日內，向本院提出上訴狀\n    （附繕本），上訴於本院管轄之第二審地方法院合議庭。",
    "reason": "一、本件犯罪事實及證據名稱，均引用檢察官聲請簡易判決處刑\n    書之記載（如附件）。\n二、被告有犯罪事實欄所載前因施用毒品執行觀察、勒戒處分，\n    甫於民國99年12月29日執行完畢釋放之執行紀錄，此有臺灣\n    高等法院被告前案紀錄表1 份在卷可按，本件係其於觀察、\n    勒戒執行完畢釋放後，5 年內再犯施用第二級毒品罪，應由\n    本院依法論罪科刑，合先敘明。甲基安非他命屬毒品危害防\n    制條例第2 條第2 項第2 款所稱之第二級毒品，不得持有、\n    施用，被告竟持以施用，核其所為，係犯同條例第10條第2\n    項之施用第二級毒品罪。其施用前持有甲基安非他命之低度\n    行為，應為施用之高度行為所吸收，不另論罪。爰審酌被告\n    甫經觀察、勒戒，仍未能戒除毒癮，顯見其無戒毒悔改之意\n    ，惟念其施用毒品乃自戕行為，並兼衡其智識程度、生活狀\n    況及犯後態度等一切情狀，量處如主文所示之刑，並諭知易\n    科罰金之折算標準。\n三、應依刑事訴訟法第449 條第1 項前段、第3 項、第454 條第\n    2 項，毒品危害防制條例第10條第2 項，刑法第11條前段、\n    第41條第1 項前段，逕以簡易判決如主文。\n四、如不服本判決，得自收受送達後10日內，向本院提出上訴狀\n    （附繕本），上訴於本院管轄之第二審地方法院合議庭。"
  },
  "search": "臺灣臺南地方法院刑事簡易判決100年度簡字第547號聲請人臺灣臺南地方法院檢察署檢察官被告林正修上列被告因違反毒品危害防制條例案件，經檢察官聲請以簡易判決處刑（100年度毒偵字第425號），本院判決如下：主文林正修施用第二級毒品，處有期徒刑參月，如易科罰金，以新臺幣壹仟元折算壹日。事實及理由一、本件犯罪事實及證據名稱，均引用檢察官聲請簡易判決處刑書之記載（如附件）。二、被告有犯罪事實欄所載前因施用毒品執行觀察、勒戒處分，甫於民國99年12月29日執行完畢釋放之執行紀錄，此有臺灣高等法院被告前案紀錄表1份在卷可按，本件係其於觀察、勒戒執行完畢釋放後，5年內再犯施用第二級毒品罪，應由本院依法論罪科刑，合先敘明。甲基安非他命屬毒品危害防制條例第2條第2項第2款所稱之第二級毒品，不得持有、施用，被告竟持以施用，核其所為，係犯同條例第10條第2項之施用第二級毒品罪。其施用前持有甲基安非他命之低度行為，應為施用之高度行為所吸收，不另論罪。爰審酌被告甫經觀察、勒戒，仍未能戒除毒癮，顯見其無戒毒悔改之意，惟念其施用毒品乃自戕行為，並兼衡其智識程度、生活狀況及犯後態度等一切情狀，量處如主文所示之刑，並諭知易科罰金之折算標準。三、應依刑事訴訟法第449條第1項前段、第3項、第454條第2項，毒品危害防制條例第10條第2項，刑法第11條前段、第41條第1項前段，逕以簡易判決如主文。四、如不服本判決，得自收受送達後10日內，向本院提出上訴狀（附繕本），上訴於本院管轄之第二審地方法院合議庭。中華民國100年3月18日刑事第十庭法官羅郁棣以上正本證明與原本無異。書記官黃玉秀中華民國100年3月18日附錄所犯法條：毒品危害防制條例第10條第2項施用第一級毒品者，處6月以上5年以下有期徒刑。施用第二級毒品者，處3年以下有期徒刑。",
  "characters": {
    "judges": [
      "羅郁棣"
    ],
    "prosecutors": [

    ],
    "lawyers": [

    ],
    "clerks": [
      "黃玉秀"
    ],
    "plaintiffs": [

    ],
    "defendants": [
      "林正修"
    ],
    "prosecutor_office": [
      "臺灣臺南地方法院檢察署檢察官"
    ],
    "creditors": [

    ],
    "debtors": [

    ],
    "judicial_associate_officer": [

    ]
  },
  "adjudged_at": "2011-03-18",
  "created_at": "2016-02-13 19:16:11",
  "updated_at": "2016-02-13 19:16:11"
}