{
  "identify": "KSD-94-訴-2768-20050930-1",
  "court": {
    "name": "臺灣高雄地方法院",
    "code": "KSD"
  },
  "division": {
    "name": "刑事",
    "code": "M"
  },
  "year": 94,
  "word": "訴",
  "number": "2768",
  "jcheck": "1",
  "reason": "毒品危害防制條例",
  "content": "臺灣高雄地方法院刑事判決              94年度訴字第2768號\n公  訴  人  臺灣高雄地方法院檢察署檢察官\n被      告  甲○○\n上列被告違反毒品危害防制條例案件，經檢察官提起公訴（94年\n度毒偵字第4580號），本院合議庭裁定由受命法官獨任進行簡式\n審判程序，判決如下：\n    主  文\n甲○○施用第一級毒品，處有期徒刑陸月，如易科罰金，以佰\n元折算壹日。扣案之第一級毒品海洛因壹小包（淨重零點零公\n克，空包裝重零點壹玖公克）、含有第一級毒品海洛因陽性反應\n之塑膠杓子壹支均沒收銷燬之。\n    事  實\n一、甲○○前因施用毒品案件，經本院以93年度毒聲字第1257號\n    裁定送觀察、勒戒，因無繼續施用毒品傾而於民國93年8 月\n    25日執行完畢而釋放，復由臺灣高雄地方法院檢察署（下稱\n    高雄地檢署）檢察官於93年8 月26日以93年度毒偵字第2754\n    、2990號為不起訴處分確定。詎其仍不知悔改，明知海洛因\n    係毒品危害防制條例第2 條第2 項第1 款之第一級毒品，竟\n    於前開觀察、勒戒執行完畢釋放後5 年內，另基於施用第一\n    級毒品海洛因之犯意，於94年5 月13日21時許，在高雄市○\n    ○路、中華路口之錢櫃KTV2樓包廂內，以將海洛因摻入香菸\n    內點燃吸食之方式，施用第一級毒品海洛因1 次，嗣於94年\n    5 月16日中午12時50分許，在高雄市前鎮區○○○路80號，\n    為警查獲，並扣得海洛因1 小包（淨重0.03公克，空包裝重\n    0.19公克）公克及塑膠杓子1 支，復經警採尿送驗後呈嗎啡\n    陽性反應，始知悉上情。\n二、案經高雄市政府警察局前鎮分局報請臺灣高雄地方法院檢察\n    署檢察官偵查起訴。\n    理  由\n壹、程序部分：\n    本件被告甲○○所犯為死刑、無期徒刑或最輕本刑為3 年以\n    上有期徒刑以外之罪，其於準備程序中就被訴事實為有罪之\n    陳述，經法官告知簡式審判程序之旨，並聽取公訴人及被告\n    之意見後，依刑事訴訟法第273 條之1 第1 項規定，裁定由\n    受命法官獨任進行簡式審判程序，合先敘明。\n貳、實體部分：\n一、上揭事實，已據被告於本院審理中坦承不諱，且其於94年5\n    月16日所採驗之尿液，經高雄市立凱旋醫院以GC/MS 方法（\n    氣相層析/ 質譜儀法）檢驗，結果確呈第一級毒品海洛因代\n    謝後嗎啡之陽性反應，此有卷附該醫院94年5 月23日藥物尿\n    液檢驗報告1 紙可稽（參偵卷第4580號卷第20頁）；另扣案\n    之不明粉末1 小包，經送往法務部調查局鑑定，結果確含第\n    一級毒品海洛因成分，此有該局94年7 月26日調科壹字第22\n    0020578 號鑑定通知書1 紙在卷可佐（參偵卷第27頁）。又\n    扣案之塑膠杓子1 支，經送請高雄醫學大學附設中和紀念醫\n    院檢驗，結果呈第一級毒品海洛因之陽性反應，此有上開醫\n    院94年8 月30日0000-000號之檢驗報告1 份存卷可參（參本\n    院卷第13頁），而按海洛因係嗎啡經化學合成之半人工合成\n    品，毒性倍於嗎啡，其經吸食或施打入人體，經新陳代謝作\n    用又可分解成嗎啡，故海洛因在進入人體後，均以嗎啡形態\n    排於尿液中，故於吸食或施打海洛因之煙毒嫌疑犯尿液中，\n    可檢出嗎啡毒性反應；又一般人施打海洛因後，8 小時內約\n    有80% 量於尿中排出，24小時後剩餘量之90% 再排出，72小\n    時後仍有微量排出，而因人體代謝差異（即成癮者），其代\n    謝時間慢，故於120 小時內（即5 日內）利用較具公信力之\n    儀器（如氣相層析質譜儀）仍「可能」被檢出，此有憲兵司\n    令部80年5 月7 日（80）鑑驗字第1746號函說明存查在案，\n    故本件被告自承於查獲前之2 、3 日即94年5 月13日21時許\n    ，施用第一級毒品海洛因，揆諸前揭說明，尚在可檢出嗎啡\n    陽性反應之期間內，故核與被告自白相符，堪予採為論罪之\n    證據\n二、又被告前因施用毒品案件，經本院以93年度毒聲字第1257號\n    裁定送觀察、勒戒，因無繼續施用毒品傾向而於93年8 月25\n    日執行完畢釋放，復由高雄地檢署檢察官於93年8 月26日以\n    93 年 度毒偵字第2754、2990號為不起訴處分確定等情，有\n    該不起訴處分書、臺灣高等法院被告前案紀錄表、被告刑案\n    資料查註紀錄表、全國施用毒品案件紀錄表各1 份在卷可稽\n    ，被告於觀察、勒戒執行完畢釋放後，5 年內再為本件施用\n    毒品犯行，自應依法論罪科刑。是以\n    本件事證明確，被告犯行堪以認定。\n三、按海洛因係毒品危害防制條例第2 條第2 項第1 款所稱之第\n    一級毒品，是被告施用海洛因之行為，係犯該條例第10條第\n    1 項之施用第一級毒品罪。被告持有第一級毒品，嗣進而施\n    用之，持有之低度行為應為施用之高度行為所吸收，不另論\n    罪。\n四、爰審酌被告前已因施用毒品案件經觀察、勒戒，本應徹底戒\n    除毒癮，不料其竟仍繼續施用毒品，已如上述，顯見其並無\n    戒除毒害之決心，本不宜寬貸，惟念其施用毒品乃自戕一己\n    之身體健康，並具有病患性人格之特質，行為本身對社會所\n    造成之危害並非直接、巨大，且犯後終知能坦承犯行等一切\n    情狀，量處如主文所示之刑，以資懲儆。\n五、末按查獲之第一、二級毒品及專供製造或施用第一、二級毒\n    品之器具，不問屬於犯人與否，均沒收銷燬之，毒品危害防\n    制條例第18條第1 項前段定有明文。查扣案之不明粉末1 小\n    包，經鑑定結果確含第一級毒品海洛因之成分，業如上述，\n    且盛裝上開扣案毒品1 包之空包裝袋（重0.19公克），雖經\n    法務部調查局就之與其所盛裝之第一級毒品海洛因分別鑑析\n    其重量，有法務部調查局前開鑑定通知書1 紙在卷可憑，惟\n    因法務部調查局一般係以傾倒之方式，將包裝袋內之第一級\n    毒品海洛因倒出而與包裝袋分離而稱重，必要時，輔以刮杓\n    刮取袋內粉末，然無論依何種方式分離，包裝袋內均有極微\n    量之第一級毒品海洛因殘留，業經法務部調查局93年3 月19\n    日調科壹字第09300113060 號函釋在案，此為本院職務上已\n    知之事實，足認前開空包裝袋（重0.19公克），內含極微量\n    第一級毒品海洛因殘留而無法析離，均應整體視為查獲之第\n    一級毒品海洛因，依毒品危害防制條例第18條第1 項前段之\n    規定，不問屬於犯人與否，均宣告沒收銷燬之；而鑑驗所耗\n    損之毒品，既已費失，自無庸宣告沒收銷燬。又扣案之塑膠\n    杓子1 支經鑑定結果，確呈第一級毒品海洛因陽性反應，亦\n    如前述，顯見此等物品與第一級毒品海洛因無法析離，自應\n    視同第一級毒品海洛因，應依上開規定併予宣告沒收銷燬之\n    ，附此敘明。\n據上論斷，應依刑事訴訟法第273 條之1 第1 項、第284 條之1\n、第299 條第1 項前段，毒品危害防制條例第10條第1 項、第18\n條第1 項前段，刑法第11條前段、第41條第1 項前段，罰金罰鍰\n提高標準條例第2 條，判決如主文。\n本案經檢察官乙○○到庭執行職務\n中    華    民    國    94    年    9     月    30    日\n                  刑事第八庭      法  官  李育信\n以上正本證明與原本無異。\n如不服本判決，應於收受送達後10日內向本院提出上訴書狀。\n中    華    民    國    94    年    9     月    30    日\n                                  書記官  洪生輝\n附錄本案論罪科刑法條：\n毒品危害防制條例第10條第1項\n施用第一級毒品者，處6月以上5年以下有期徒刑。\n",
  "structure": {
    "main": "甲○○施用第一級毒品，處有期徒刑陸月，如易科罰金，以佰\n元折算壹日。扣案之第一級毒品海洛因壹小包（淨重零點零公\n克，空包裝重零點壹玖公克）、含有第一級毒品海洛因陽性反應\n之塑膠杓子壹支均沒收銷燬之。",
    "fact": "一、甲○○前因施用毒品案件，經本院以93年度毒聲字第1257號\n    裁定送觀察、勒戒，因無繼續施用毒品傾而於民國93年8 月\n    25日執行完畢而釋放，復由臺灣高雄地方法院檢察署（下稱\n    高雄地檢署）檢察官於93年8 月26日以93年度毒偵字第2754\n    、2990號為不起訴處分確定。詎其仍不知悔改，明知海洛因\n    係毒品危害防制條例第2 條第2 項第1 款之第一級毒品，竟\n    於前開觀察、勒戒執行完畢釋放後5 年內，另基於施用第一\n    級毒品海洛因之犯意，於94年5 月13日21時許，在高雄市○\n    ○路、中華路口之錢櫃KTV2樓包廂內，以將海洛因摻入香菸\n    內點燃吸食之方式，施用第一級毒品海洛因1 次，嗣於94年\n    5 月16日中午12時50分許，在高雄市前鎮區○○○路80號，\n    為警查獲，並扣得海洛因1 小包（淨重0.03公克，空包裝重\n    0.19公克）公克及塑膠杓子1 支，復經警採尿送驗後呈嗎啡\n    陽性反應，始知悉上情。\n二、案經高雄市政府警察局前鎮分局報請臺灣高雄地方法院檢察\n    署檢察官偵查起訴。",
    "reason": "壹、程序部分：\n    本件被告甲○○所犯為死刑、無期徒刑或最輕本刑為3 年以\n    上有期徒刑以外之罪，其於準備程序中就被訴事實為有罪之\n    陳述，經法官告知簡式審判程序之旨，並聽取公訴人及被告\n    之意見後，依刑事訴訟法第273 條之1 第1 項規定，裁定由\n    受命法官獨任進行簡式審判程序，合先敘明。\n貳、實體部分：\n一、上揭事實，已據被告於本院審理中坦承不諱，且其於94年5\n    月16日所採驗之尿液，經高雄市立凱旋醫院以GC/MS 方法（\n    氣相層析/ 質譜儀法）檢驗，結果確呈第一級毒品海洛因代\n    謝後嗎啡之陽性反應，此有卷附該醫院94年5 月23日藥物尿\n    液檢驗報告1 紙可稽（參偵卷第4580號卷第20頁）；另扣案\n    之不明粉末1 小包，經送往法務部調查局鑑定，結果確含第\n    一級毒品海洛因成分，此有該局94年7 月26日調科壹字第22\n    0020578 號鑑定通知書1 紙在卷可佐（參偵卷第27頁）。又\n    扣案之塑膠杓子1 支，經送請高雄醫學大學附設中和紀念醫\n    院檢驗，結果呈第一級毒品海洛因之陽性反應，此有上開醫\n    院94年8 月30日0000-000號之檢驗報告1 份存卷可參（參本\n    院卷第13頁），而按海洛因係嗎啡經化學合成之半人工合成\n    品，毒性倍於嗎啡，其經吸食或施打入人體，經新陳代謝作\n    用又可分解成嗎啡，故海洛因在進入人體後，均以嗎啡形態\n    排於尿液中，故於吸食或施打海洛因之煙毒嫌疑犯尿液中，\n    可檢出嗎啡毒性反應；又一般人施打海洛因後，8 小時內約\n    有80% 量於尿中排出，24小時後剩餘量之90% 再排出，72小\n    時後仍有微量排出，而因人體代謝差異（即成癮者），其代\n    謝時間慢，故於120 小時內（即5 日內）利用較具公信力之\n    儀器（如氣相層析質譜儀）仍「可能」被檢出，此有憲兵司\n    令部80年5 月7 日（80）鑑驗字第1746號函說明存查在案，\n    故本件被告自承於查獲前之2 、3 日即94年5 月13日21時許\n    ，施用第一級毒品海洛因，揆諸前揭說明，尚在可檢出嗎啡\n    陽性反應之期間內，故核與被告自白相符，堪予採為論罪之\n    證據\n二、又被告前因施用毒品案件，經本院以93年度毒聲字第1257號\n    裁定送觀察、勒戒，因無繼續施用毒品傾向而於93年8 月25\n    日執行完畢釋放，復由高雄地檢署檢察官於93年8 月26日以\n    93 年 度毒偵字第2754、2990號為不起訴處分確定等情，有\n    該不起訴處分書、臺灣高等法院被告前案紀錄表、被告刑案\n    資料查註紀錄表、全國施用毒品案件紀錄表各1 份在卷可稽\n    ，被告於觀察、勒戒執行完畢釋放後，5 年內再為本件施用\n    毒品犯行，自應依法論罪科刑。是以\n    本件事證明確，被告犯行堪以認定。\n三、按海洛因係毒品危害防制條例第2 條第2 項第1 款所稱之第\n    一級毒品，是被告施用海洛因之行為，係犯該條例第10條第\n    1 項之施用第一級毒品罪。被告持有第一級毒品，嗣進而施\n    用之，持有之低度行為應為施用之高度行為所吸收，不另論\n    罪。\n四、爰審酌被告前已因施用毒品案件經觀察、勒戒，本應徹底戒\n    除毒癮，不料其竟仍繼續施用毒品，已如上述，顯見其並無\n    戒除毒害之決心，本不宜寬貸，惟念其施用毒品乃自戕一己\n    之身體健康，並具有病患性人格之特質，行為本身對社會所\n    造成之危害並非直接、巨大，且犯後終知能坦承犯行等一切\n    情狀，量處如主文所示之刑，以資懲儆。\n五、末按查獲之第一、二級毒品及專供製造或施用第一、二級毒\n    品之器具，不問屬於犯人與否，均沒收銷燬之，毒品危害防\n    制條例第18條第1 項前段定有明文。查扣案之不明粉末1 小\n    包，經鑑定結果確含第一級毒品海洛因之成分，業如上述，\n    且盛裝上開扣案毒品1 包之空包裝袋（重0.19公克），雖經\n    法務部調查局就之與其所盛裝之第一級毒品海洛因分別鑑析\n    其重量，有法務部調查局前開鑑定通知書1 紙在卷可憑，惟\n    因法務部調查局一般係以傾倒之方式，將包裝袋內之第一級\n    毒品海洛因倒出而與包裝袋分離而稱重，必要時，輔以刮杓\n    刮取袋內粉末，然無論依何種方式分離，包裝袋內均有極微\n    量之第一級毒品海洛因殘留，業經法務部調查局93年3 月19\n    日調科壹字第09300113060 號函釋在案，此為本院職務上已\n    知之事實，足認前開空包裝袋（重0.19公克），內含極微量\n    第一級毒品海洛因殘留而無法析離，均應整體視為查獲之第\n    一級毒品海洛因，依毒品危害防制條例第18條第1 項前段之\n    規定，不問屬於犯人與否，均宣告沒收銷燬之；而鑑驗所耗\n    損之毒品，既已費失，自無庸宣告沒收銷燬。又扣案之塑膠\n    杓子1 支經鑑定結果，確呈第一級毒品海洛因陽性反應，亦\n    如前述，顯見此等物品與第一級毒品海洛因無法析離，自應\n    視同第一級毒品海洛因，應依上開規定併予宣告沒收銷燬之\n    ，附此敘明。\n據上論斷，應依刑事訴訟法第273 條之1 第1 項、第284 條之1\n、第299 條第1 項前段，毒品危害防制條例第10條第1 項、第18\n條第1 項前段，刑法第11條前段、第41條第1 項前段，罰金罰鍰\n提高標準條例第2 條，判決如主文。\n本案經檢察官乙○○到庭執行職務\n中    華    民    國    94    年    9     月    30    日\n                  刑事第八庭      法  官  李育信\n以上正本證明與原本無異。\n如不服本判決，應於收受送達後10日內向本院提出上訴書狀。"
  },
  "search": "臺灣高雄地方法院刑事判決94年度訴字第2768號公訴人臺灣高雄地方法院檢察署檢察官被告甲○○上列被告違反毒品危害防制條例案件，經檢察官提起公訴（94年度毒偵字第4580號），本院合議庭裁定由受命法官獨任進行簡式審判程序，判決如下：主文甲○○施用第一級毒品，處有期徒刑陸月，如易科罰金，以佰元折算壹日。扣案之第一級毒品海洛因壹小包（淨重零點零公克，空包裝重零點壹玖公克）、含有第一級毒品海洛因陽性反應之塑膠杓子壹支均沒收銷燬之。事實一、甲○○前因施用毒品案件，經本院以93年度毒聲字第1257號裁定送觀察、勒戒，因無繼續施用毒品傾而於民國93年8月25日執行完畢而釋放，復由臺灣高雄地方法院檢察署（下稱高雄地檢署）檢察官於93年8月26日以93年度毒偵字第2754、2990號為不起訴處分確定。詎其仍不知悔改，明知海洛因係毒品危害防制條例第2條第2項第1款之第一級毒品，竟於前開觀察、勒戒執行完畢釋放後5年內，另基於施用第一級毒品海洛因之犯意，於94年5月13日21時許，在高雄市○○路、中華路口之錢櫃KTV2樓包廂內，以將海洛因摻入香菸內點燃吸食之方式，施用第一級毒品海洛因1次，嗣於94年5月16日中午12時50分許，在高雄市前鎮區○○○路80號，為警查獲，並扣得海洛因1小包（淨重0.03公克，空包裝重0.19公克）公克及塑膠杓子1支，復經警採尿送驗後呈嗎啡陽性反應，始知悉上情。二、案經高雄市政府警察局前鎮分局報請臺灣高雄地方法院檢察署檢察官偵查起訴。理由壹、程序部分：本件被告甲○○所犯為死刑、無期徒刑或最輕本刑為3年以上有期徒刑以外之罪，其於準備程序中就被訴事實為有罪之陳述，經法官告知簡式審判程序之旨，並聽取公訴人及被告之意見後，依刑事訴訟法第273條之1第1項規定，裁定由受命法官獨任進行簡式審判程序，合先敘明。貳、實體部分：一、上揭事實，已據被告於本院審理中坦承不諱，且其於94年5月16日所採驗之尿液，經高雄市立凱旋醫院以GC/MS方法（氣相層析/質譜儀法）檢驗，結果確呈第一級毒品海洛因代謝後嗎啡之陽性反應，此有卷附該醫院94年5月23日藥物尿液檢驗報告1紙可稽（參偵卷第4580號卷第20頁）；另扣案之不明粉末1小包，經送往法務部調查局鑑定，結果確含第一級毒品海洛因成分，此有該局94年7月26日調科壹字第220020578號鑑定通知書1紙在卷可佐（參偵卷第27頁）。又扣案之塑膠杓子1支，經送請高雄醫學大學附設中和紀念醫院檢驗，結果呈第一級毒品海洛因之陽性反應，此有上開醫院94年8月30日0000-000號之檢驗報告1份存卷可參（參本院卷第13頁），而按海洛因係嗎啡經化學合成之半人工合成品，毒性倍於嗎啡，其經吸食或施打入人體，經新陳代謝作用又可分解成嗎啡，故海洛因在進入人體後，均以嗎啡形態排於尿液中，故於吸食或施打海洛因之煙毒嫌疑犯尿液中，可檢出嗎啡毒性反應；又一般人施打海洛因後，8小時內約有80%量於尿中排出，24小時後剩餘量之90%再排出，72小時後仍有微量排出，而因人體代謝差異（即成癮者），其代謝時間慢，故於120小時內（即5日內）利用較具公信力之儀器（如氣相層析質譜儀）仍「可能」被檢出，此有憲兵司令部80年5月7日（80）鑑驗字第1746號函說明存查在案，故本件被告自承於查獲前之2、3日即94年5月13日21時許，施用第一級毒品海洛因，揆諸前揭說明，尚在可檢出嗎啡陽性反應之期間內，故核與被告自白相符，堪予採為論罪之證據二、又被告前因施用毒品案件，經本院以93年度毒聲字第1257號裁定送觀察、勒戒，因無繼續施用毒品傾向而於93年8月25日執行完畢釋放，復由高雄地檢署檢察官於93年8月26日以93年度毒偵字第2754、2990號為不起訴處分確定等情，有該不起訴處分書、臺灣高等法院被告前案紀錄表、被告刑案資料查註紀錄表、全國施用毒品案件紀錄表各1份在卷可稽，被告於觀察、勒戒執行完畢釋放後，5年內再為本件施用毒品犯行，自應依法論罪科刑。是以本件事證明確，被告犯行堪以認定。三、按海洛因係毒品危害防制條例第2條第2項第1款所稱之第一級毒品，是被告施用海洛因之行為，係犯該條例第10條第1項之施用第一級毒品罪。被告持有第一級毒品，嗣進而施用之，持有之低度行為應為施用之高度行為所吸收，不另論罪。四、爰審酌被告前已因施用毒品案件經觀察、勒戒，本應徹底戒除毒癮，不料其竟仍繼續施用毒品，已如上述，顯見其並無戒除毒害之決心，本不宜寬貸，惟念其施用毒品乃自戕一己之身體健康，並具有病患性人格之特質，行為本身對社會所造成之危害並非直接、巨大，且犯後終知能坦承犯行等一切情狀，量處如主文所示之刑，以資懲儆。五、末按查獲之第一、二級毒品及專供製造或施用第一、二級毒品之器具，不問屬於犯人與否，均沒收銷燬之，毒品危害防制條例第18條第1項前段定有明文。查扣案之不明粉末1小包，經鑑定結果確含第一級毒品海洛因之成分，業如上述，且盛裝上開扣案毒品1包之空包裝袋（重0.19公克），雖經法務部調查局就之與其所盛裝之第一級毒品海洛因分別鑑析其重量，有法務部調查局前開鑑定通知書1紙在卷可憑，惟因法務部調查局一般係以傾倒之方式，將包裝袋內之第一級毒品海洛因倒出而與包裝袋分離而稱重，必要時，輔以刮杓刮取袋內粉末，然無論依何種方式分離，包裝袋內均有極微量之第一級毒品海洛因殘留，業經法務部調查局93年3月19日調科壹字第09300113060號函釋在案，此為本院職務上已知之事實，足認前開空包裝袋（重0.19公克），內含極微量第一級毒品海洛因殘留而無法析離，均應整體視為查獲之第一級毒品海洛因，依毒品危害防制條例第18條第1項前段之規定，不問屬於犯人與否，均宣告沒收銷燬之；而鑑驗所耗損之毒品，既已費失，自無庸宣告沒收銷燬。又扣案之塑膠杓子1支經鑑定結果，確呈第一級毒品海洛因陽性反應，亦如前述，顯見此等物品與第一級毒品海洛因無法析離，自應視同第一級毒品海洛因，應依上開規定併予宣告沒收銷燬之，附此敘明。據上論斷，應依刑事訴訟法第273條之1第1項、第284條之1、第299條第1項前段，毒品危害防制條例第10條第1項、第18條第1項前段，刑法第11條前段、第41條第1項前段，罰金罰鍰提高標準條例第2條，判決如主文。本案經檢察官乙○○到庭執行職務中華民國94年9月30日刑事第八庭法官李育信以上正本證明與原本無異。如不服本判決，應於收受送達後10日內向本院提出上訴書狀。中華民國94年9月30日書記官洪生輝附錄本案論罪科刑法條：毒品危害防制條例第10條第1項施用第一級毒品者，處6月以上5年以下有期徒刑。",
  "characters": {
    "judges": [
      "李育信"
    ],
    "prosecutors": [

    ],
    "lawyers": [

    ],
    "clerks": [
      "洪生輝"
    ],
    "plaintiffs": [

    ],
    "defendants": [
      "甲○○"
    ],
    "prosecutor_office": [
      "臺灣高雄地方法院檢察署檢察官"
    ],
    "creditors": [

    ],
    "debtors": [

    ],
    "judicial_associate_officer": [

    ]
  },
  "adjudged_at": "2005-09-30",
  "created_at": "2016-02-06 21:01:41",
  "updated_at": "2016-02-06 21:01:41"
}