{
  "identify": "TND-94-交簡-1095-20050930-1",
  "court": {
    "name": "臺灣臺南地方法院",
    "code": "TND"
  },
  "division": {
    "name": "刑事",
    "code": "M"
  },
  "year": 94,
  "word": "交簡",
  "number": "1095",
  "jcheck": "1",
  "reason": "公共危險",
  "content": "臺灣臺南地方法院刑事簡易判決        94年度交簡字第1095號\n聲  請  人  臺灣臺南地方法院檢察署檢察官\n被      告  甲○○\n上列被告因公共危險案件，經檢察官聲請以簡易判決處刑（\n94年度偵字第5463號），本院判決如下：\n    主  文\n甲○○服用麻醉藥品相類似之物，不能安全駕駛動力交通工具而\n駕駛，處罰金銀元壹萬肆仟元，如易服勞役，以銀元參佰元即新\n臺幣玖佰元折算壹日。\n    事實及理由\n一、本件犯罪事實、證據及理由均引用檢察官聲請簡易判決處刑\n    書之記載（如附件）。\n二、查吸食強力膠將導致注意力無法集中，視覺模糊，步履失調\n    ，產生幻覺、易失去自我控制能力，有似飲酒，論其性質屬\n    麻醉藥品之相類物（社會秩序維護法第六十六條第一款參照\n    ），核被告所為，係犯刑法第一百八十五條之三公共危險罪\n    。茲審酌被告之犯罪動機、目的及其吸食強力膠後、未顧及\n    大眾之交通安全駕駛動力交通工具之危害程度，並其犯後態\n    度等一切情狀，量處如主文所示之刑，並諭知如易服勞役之\n    折算標準，以資懲儆。\n三、依刑事訴訟法第四百四十九條第一項前段、第四百五十四條\n    第二項，刑法第一百八十五條之三、第四十二條第二項，罰\n    金罰鍰提高標準條例第二條，現行法規所定貨幣單位折算新\n    臺幣標準條例第二條，逕以簡易判決處刑如主文所示。\n四、如不服本判決，得於判決書送達之日起十日內，以書狀敘述\n    理由，向本院提出上訴。\n中    華    民    國    94    年    9     月    30    日\n                  刑事第八庭    法  官  洪士傑\n以上正本證明與原本無異。\n如不服本判決，應於送達後10日內，向本院提出上訴狀（應附繕\n本）。\n                                書記官  李佩珊\n中    華    民    國    94    年    10    月    3     日\n附錄法條：\n中華民國刑法第185條之3\n服用毒品、麻醉藥品、酒類或其他相類之物，不能安全駕駛動力\n交通工具而駕駛者，處1年以下有期徒刑、拘役或3萬元以下罰金\n。\n",
  "structure": {
    "main": "甲○○服用麻醉藥品相類似之物，不能安全駕駛動力交通工具而\n駕駛，處罰金銀元壹萬肆仟元，如易服勞役，以銀元參佰元即新\n臺幣玖佰元折算壹日。",
    "fact": "一、本件犯罪事實、證據及理由均引用檢察官聲請簡易判決處刑\n    書之記載（如附件）。\n二、查吸食強力膠將導致注意力無法集中，視覺模糊，步履失調\n    ，產生幻覺、易失去自我控制能力，有似飲酒，論其性質屬\n    麻醉藥品之相類物（社會秩序維護法第六十六條第一款參照\n    ），核被告所為，係犯刑法第一百八十五條之三公共危險罪\n    。茲審酌被告之犯罪動機、目的及其吸食強力膠後、未顧及\n    大眾之交通安全駕駛動力交通工具之危害程度，並其犯後態\n    度等一切情狀，量處如主文所示之刑，並諭知如易服勞役之\n    折算標準，以資懲儆。\n三、依刑事訴訟法第四百四十九條第一項前段、第四百五十四條\n    第二項，刑法第一百八十五條之三、第四十二條第二項，罰\n    金罰鍰提高標準條例第二條，現行法規所定貨幣單位折算新\n    臺幣標準條例第二條，逕以簡易判決處刑如主文所示。\n四、如不服本判決，得於判決書送達之日起十日內，以書狀敘述\n    理由，向本院提出上訴。",
    "reason": "一、本件犯罪事實、證據及理由均引用檢察官聲請簡易判決處刑\n    書之記載（如附件）。\n二、查吸食強力膠將導致注意力無法集中，視覺模糊，步履失調\n    ，產生幻覺、易失去自我控制能力，有似飲酒，論其性質屬\n    麻醉藥品之相類物（社會秩序維護法第六十六條第一款參照\n    ），核被告所為，係犯刑法第一百八十五條之三公共危險罪\n    。茲審酌被告之犯罪動機、目的及其吸食強力膠後、未顧及\n    大眾之交通安全駕駛動力交通工具之危害程度，並其犯後態\n    度等一切情狀，量處如主文所示之刑，並諭知如易服勞役之\n    折算標準，以資懲儆。\n三、依刑事訴訟法第四百四十九條第一項前段、第四百五十四條\n    第二項，刑法第一百八十五條之三、第四十二條第二項，罰\n    金罰鍰提高標準條例第二條，現行法規所定貨幣單位折算新\n    臺幣標準條例第二條，逕以簡易判決處刑如主文所示。\n四、如不服本判決，得於判決書送達之日起十日內，以書狀敘述\n    理由，向本院提出上訴。"
  },
  "search": "臺灣臺南地方法院刑事簡易判決94年度交簡字第1095號聲請人臺灣臺南地方法院檢察署檢察官被告甲○○上列被告因公共危險案件，經檢察官聲請以簡易判決處刑（94年度偵字第5463號），本院判決如下：主文甲○○服用麻醉藥品相類似之物，不能安全駕駛動力交通工具而駕駛，處罰金銀元壹萬肆仟元，如易服勞役，以銀元參佰元即新臺幣玖佰元折算壹日。事實及理由一、本件犯罪事實、證據及理由均引用檢察官聲請簡易判決處刑書之記載（如附件）。二、查吸食強力膠將導致注意力無法集中，視覺模糊，步履失調，產生幻覺、易失去自我控制能力，有似飲酒，論其性質屬麻醉藥品之相類物（社會秩序維護法第六十六條第一款參照），核被告所為，係犯刑法第一百八十五條之三公共危險罪。茲審酌被告之犯罪動機、目的及其吸食強力膠後、未顧及大眾之交通安全駕駛動力交通工具之危害程度，並其犯後態度等一切情狀，量處如主文所示之刑，並諭知如易服勞役之折算標準，以資懲儆。三、依刑事訴訟法第四百四十九條第一項前段、第四百五十四條第二項，刑法第一百八十五條之三、第四十二條第二項，罰金罰鍰提高標準條例第二條，現行法規所定貨幣單位折算新臺幣標準條例第二條，逕以簡易判決處刑如主文所示。四、如不服本判決，得於判決書送達之日起十日內，以書狀敘述理由，向本院提出上訴。中華民國94年9月30日刑事第八庭法官洪士傑以上正本證明與原本無異。如不服本判決，應於送達後10日內，向本院提出上訴狀（應附繕本）。書記官李佩珊中華民國94年10月3日附錄法條：中華民國刑法第185條之3服用毒品、麻醉藥品、酒類或其他相類之物，不能安全駕駛動力交通工具而駕駛者，處1年以下有期徒刑、拘役或3萬元以下罰金。",
  "characters": {
    "judges": [
      "洪士傑"
    ],
    "prosecutors": [

    ],
    "lawyers": [

    ],
    "clerks": [
      "李佩珊"
    ],
    "plaintiffs": [

    ],
    "defendants": [
      "甲○○"
    ],
    "prosecutor_office": [
      "臺灣臺南地方法院檢察署檢察官"
    ],
    "creditors": [

    ],
    "debtors": [

    ],
    "judicial_associate_officer": [

    ]
  },
  "adjudged_at": "2005-09-30",
  "created_at": "2016-02-06 21:02:14",
  "updated_at": "2016-02-06 21:02:14"
}