{
  "identify": "TND-94-簡-2266-20050930-1",
  "court": {
    "name": "臺灣臺南地方法院",
    "code": "TND"
  },
  "division": {
    "name": "刑事",
    "code": "M"
  },
  "year": 94,
  "word": "簡",
  "number": "2266",
  "jcheck": "1",
  "reason": "詐欺",
  "content": "臺灣臺南地方法院刑事簡易判決          94年度簡字第2266號\n    聲  請  人  臺灣臺南地方法院檢察署檢察官\n    被      告  甲○○\n右列被告因詐欺案件，經檢察官聲請以簡易判決處刑（94年度偵\n字第10347號），本院判決如左：\n        主  文\n甲○○幫助意圖為自己不法之所有，以詐術使人將本人之物交付\n，處有期徒刑貳月，如易科罰金，以參佰元折算壹日，緩刑參年\n。\n        事實及理由\n一、本件除尚乏證據足認向甲○○買受帳戶之不詳姓名成年男子\n    ，係與他人組成詐欺集團施詐，應僅堪認係渠一人獨自所為\n    ，檢察官聲請簡易判決處刑書此部分犯罪事實應予更正外，\n    其餘犯罪事實及證據均引用該處刑書之記載（如附件）。\n二、據上論斷，應依刑事訴訟法第四百四十九條第一項前段、第\n    四百五十一條之一第一項、第四項前段、第四百五十四條第\n    二項，刑法第三十條、第三百三十九條第一項、第四十一條\n    第一項前段、第七十四條第一款，罰金罰鍰提高標準條例第\n    一條前段、第二條，逕以簡易判決處如主文。\n三、本件係於檢察官緩刑宣告之請求及被告表示願受緩刑宣告而\n    為判決，依刑事訴訟法第四百五十五條之一第二項之規定，\n    被告及檢察官均不得上訴。\n中    華    民    國    94    年    9     月    30    日\n                  刑事第十庭  法  官   柯顯卿\n以上正本證明與原本無異。\n                              書記官   黃子起\n中    華    民    國    94    年    9     月    30    日\n附錄所犯法條：\n刑法第三百三十九條第一項：\n意圖為自己或第三人不法之所有，以詐術使人將本人或第三人之\n物交付者，處五年以下有期徒刑、拘役或科或併科一千元以下罰\n金。\n",
  "structure": {
    "main": "甲○○幫助意圖為自己不法之所有，以詐術使人將本人之物交付\n，處有期徒刑貳月，如易科罰金，以參佰元折算壹日，緩刑參年\n。",
    "fact": "一、本件除尚乏證據足認向甲○○買受帳戶之不詳姓名成年男子\n    ，係與他人組成詐欺集團施詐，應僅堪認係渠一人獨自所為\n    ，檢察官聲請簡易判決處刑書此部分犯罪事實應予更正外，\n    其餘犯罪事實及證據均引用該處刑書之記載（如附件）。\n二、據上論斷，應依刑事訴訟法第四百四十九條第一項前段、第\n    四百五十一條之一第一項、第四項前段、第四百五十四條第\n    二項，刑法第三十條、第三百三十九條第一項、第四十一條\n    第一項前段、第七十四條第一款，罰金罰鍰提高標準條例第\n    一條前段、第二條，逕以簡易判決處如主文。\n三、本件係於檢察官緩刑宣告之請求及被告表示願受緩刑宣告而\n    為判決，依刑事訴訟法第四百五十五條之一第二項之規定，\n    被告及檢察官均不得上訴。",
    "reason": "一、本件除尚乏證據足認向甲○○買受帳戶之不詳姓名成年男子\n    ，係與他人組成詐欺集團施詐，應僅堪認係渠一人獨自所為\n    ，檢察官聲請簡易判決處刑書此部分犯罪事實應予更正外，\n    其餘犯罪事實及證據均引用該處刑書之記載（如附件）。\n二、據上論斷，應依刑事訴訟法第四百四十九條第一項前段、第\n    四百五十一條之一第一項、第四項前段、第四百五十四條第\n    二項，刑法第三十條、第三百三十九條第一項、第四十一條\n    第一項前段、第七十四條第一款，罰金罰鍰提高標準條例第\n    一條前段、第二條，逕以簡易判決處如主文。\n三、本件係於檢察官緩刑宣告之請求及被告表示願受緩刑宣告而\n    為判決，依刑事訴訟法第四百五十五條之一第二項之規定，\n    被告及檢察官均不得上訴。"
  },
  "search": "臺灣臺南地方法院刑事簡易判決94年度簡字第2266號聲請人臺灣臺南地方法院檢察署檢察官被告甲○○右列被告因詐欺案件，經檢察官聲請以簡易判決處刑（94年度偵字第10347號），本院判決如左：主文甲○○幫助意圖為自己不法之所有，以詐術使人將本人之物交付，處有期徒刑貳月，如易科罰金，以參佰元折算壹日，緩刑參年。事實及理由一、本件除尚乏證據足認向甲○○買受帳戶之不詳姓名成年男子，係與他人組成詐欺集團施詐，應僅堪認係渠一人獨自所為，檢察官聲請簡易判決處刑書此部分犯罪事實應予更正外，其餘犯罪事實及證據均引用該處刑書之記載（如附件）。二、據上論斷，應依刑事訴訟法第四百四十九條第一項前段、第四百五十一條之一第一項、第四項前段、第四百五十四條第二項，刑法第三十條、第三百三十九條第一項、第四十一條第一項前段、第七十四條第一款，罰金罰鍰提高標準條例第一條前段、第二條，逕以簡易判決處如主文。三、本件係於檢察官緩刑宣告之請求及被告表示願受緩刑宣告而為判決，依刑事訴訟法第四百五十五條之一第二項之規定，被告及檢察官均不得上訴。中華民國94年9月30日刑事第十庭法官柯顯卿以上正本證明與原本無異。書記官黃子起中華民國94年9月30日附錄所犯法條：刑法第三百三十九條第一項：意圖為自己或第三人不法之所有，以詐術使人將本人或第三人之物交付者，處五年以下有期徒刑、拘役或科或併科一千元以下罰金。",
  "characters": {
    "judges": [
      "柯顯卿"
    ],
    "prosecutors": [

    ],
    "lawyers": [

    ],
    "clerks": [
      "黃子起"
    ],
    "plaintiffs": [

    ],
    "defendants": [
      "甲○○",
      "右列被告因詐欺案件，經檢察官聲請以簡易判決處刑（94年度偵",
      "字第10347號），本院判決如左："
    ],
    "prosecutor_office": [
      "臺灣臺南地方法院檢察署檢察官"
    ],
    "creditors": [

    ],
    "debtors": [

    ],
    "judicial_associate_officer": [

    ]
  },
  "adjudged_at": "2005-09-30",
  "created_at": "2016-02-06 20:52:33",
  "updated_at": "2016-02-06 20:52:33"
}