{
  "identify": "KSD-91-簡-349-20020930-1",
  "court": {
    "name": "臺灣高雄地方法院",
    "code": "KSD"
  },
  "division": {
    "name": "刑事",
    "code": "M"
  },
  "year": 91,
  "word": "簡",
  "number": "349",
  "jcheck": "1",
  "reason": "偽造文書",
  "content": "臺灣高雄地方法院刑事簡易判決                      九十一年度簡字第三四九號\n    聲  請  人  臺灣高雄地方法院檢察署檢察官\n    被      告  乙○○\n右列被告因偽造文書案件，經檢察官聲請以簡易判決處刑（九十一年度偵字第一一二\n二六號），本院判決如左：\n    主  文\n乙○○共同行使偽造國民身分證，足以生損害於公眾及他人，處有期徒刑參月，如易\n科罰金，以參佰元折算壹日。\n偽造之甲○○國民身分證壹枚，沒收。\n    事實及理由\n一、本件犯罪事實（除應增加綽號「阿龍」之成年男子為共同正犯外）及理由均引用\n    檢察官簡易判決聲請書之記載（如附件）。\n二、核被告所為，係犯刑法第二百十六條、第二百十二條之行使偽造特種文書罪，其\n    偽造特種文書之低度行為，已為其進而行使之高度行為所吸收，不復另論。又被\n    告與綽號「阿龍」之人，有犯意聯絡及行為分擔，為共同正犯。爰審酌被告犯罪\n    之動機、目的、手段、所生危害、犯後態度良好等一切情狀，量處如主文所示之\n    刑，並諭知易科罰金之折算標準，扣案偽造甲○○國民身分證一枚，係被告乙○\n    ○所有，供犯罪所用之物，應依刑法第三十八條第一項第二款宣告沒收。\n三、依刑事訴訟法第四百四十九條第一項、第四百五十條第一項、第四百五十四條第\n    二項，刑法第二十八條、第二百十六條、第二百十二條、第四十一條第一項、第\n    三十八條第一項第二款，罰金罰緩提高標準條例第一條前段、第二條，逕以簡易\n    判決處如主文所示之刑。\n如不服本判決，得自收受送達之日起十日內，向本院提起上訴。\n中      華      民      國    九十一    年      九      月      三十    日\n                                臺灣高雄地方法院簡易庭\n                                    法  官  何悅芳\n右為正本，係照原本作成，證明與原本無異。\n                                    書記官  顏宗貝\n中      華      民      國    九十一    年      九      月      三十    日\n附錄本案論罪科刑法條全文：\n刑法第二百十二條：偽造、變造護照、旅券、免許證、特許證及關於品行、能力、服\n                  務或其他相類之證書、介紹書，足以生損害於公眾或他人者，處\n                  一年以下有期徒刑、拘役或三百元以下罰金。\n刑法第二百十六條：行使第二百十條至第二百十五條之文書者，依偽造、變造文書或\n                  登載不實事項或使登載不實事項之規定處斷。\n",
  "structure": {
    "main": "乙○○共同行使偽造國民身分證，足以生損害於公眾及他人，處有期徒刑參月，如易\n科罰金，以參佰元折算壹日。\n偽造之甲○○國民身分證壹枚，沒收。",
    "fact": "一、本件犯罪事實（除應增加綽號「阿龍」之成年男子為共同正犯外）及理由均引用\n    檢察官簡易判決聲請書之記載（如附件）。\n二、核被告所為，係犯刑法第二百十六條、第二百十二條之行使偽造特種文書罪，其\n    偽造特種文書之低度行為，已為其進而行使之高度行為所吸收，不復另論。又被\n    告與綽號「阿龍」之人，有犯意聯絡及行為分擔，為共同正犯。爰審酌被告犯罪\n    之動機、目的、手段、所生危害、犯後態度良好等一切情狀，量處如主文所示之\n    刑，並諭知易科罰金之折算標準，扣案偽造甲○○國民身分證一枚，係被告乙○\n    ○所有，供犯罪所用之物，應依刑法第三十八條第一項第二款宣告沒收。\n三、依刑事訴訟法第四百四十九條第一項、第四百五十條第一項、第四百五十四條第\n    二項，刑法第二十八條、第二百十六條、第二百十二條、第四十一條第一項、第\n    三十八條第一項第二款，罰金罰緩提高標準條例第一條前段、第二條，逕以簡易\n    判決處如主文所示之刑。\n如不服本判決，得自收受送達之日起十日內，向本院提起上訴。",
    "reason": "一、本件犯罪事實（除應增加綽號「阿龍」之成年男子為共同正犯外）及理由均引用\n    檢察官簡易判決聲請書之記載（如附件）。\n二、核被告所為，係犯刑法第二百十六條、第二百十二條之行使偽造特種文書罪，其\n    偽造特種文書之低度行為，已為其進而行使之高度行為所吸收，不復另論。又被\n    告與綽號「阿龍」之人，有犯意聯絡及行為分擔，為共同正犯。爰審酌被告犯罪\n    之動機、目的、手段、所生危害、犯後態度良好等一切情狀，量處如主文所示之\n    刑，並諭知易科罰金之折算標準，扣案偽造甲○○國民身分證一枚，係被告乙○\n    ○所有，供犯罪所用之物，應依刑法第三十八條第一項第二款宣告沒收。\n三、依刑事訴訟法第四百四十九條第一項、第四百五十條第一項、第四百五十四條第\n    二項，刑法第二十八條、第二百十六條、第二百十二條、第四十一條第一項、第\n    三十八條第一項第二款，罰金罰緩提高標準條例第一條前段、第二條，逕以簡易\n    判決處如主文所示之刑。\n如不服本判決，得自收受送達之日起十日內，向本院提起上訴。"
  },
  "search": "臺灣高雄地方法院刑事簡易判決九十一年度簡字第三四九號聲請人臺灣高雄地方法院檢察署檢察官被告乙○○右列被告因偽造文書案件，經檢察官聲請以簡易判決處刑（九十一年度偵字第一一二二六號），本院判決如左：主文乙○○共同行使偽造國民身分證，足以生損害於公眾及他人，處有期徒刑參月，如易科罰金，以參佰元折算壹日。偽造之甲○○國民身分證壹枚，沒收。事實及理由一、本件犯罪事實（除應增加綽號「阿龍」之成年男子為共同正犯外）及理由均引用檢察官簡易判決聲請書之記載（如附件）。二、核被告所為，係犯刑法第二百十六條、第二百十二條之行使偽造特種文書罪，其偽造特種文書之低度行為，已為其進而行使之高度行為所吸收，不復另論。又被告與綽號「阿龍」之人，有犯意聯絡及行為分擔，為共同正犯。爰審酌被告犯罪之動機、目的、手段、所生危害、犯後態度良好等一切情狀，量處如主文所示之刑，並諭知易科罰金之折算標準，扣案偽造甲○○國民身分證一枚，係被告乙○○所有，供犯罪所用之物，應依刑法第三十八條第一項第二款宣告沒收。三、依刑事訴訟法第四百四十九條第一項、第四百五十條第一項、第四百五十四條第二項，刑法第二十八條、第二百十六條、第二百十二條、第四十一條第一項、第三十八條第一項第二款，罰金罰緩提高標準條例第一條前段、第二條，逕以簡易判決處如主文所示之刑。如不服本判決，得自收受送達之日起十日內，向本院提起上訴。中華民國九十一年九月三十日臺灣高雄地方法院簡易庭法官何悅芳右為正本，係照原本作成，證明與原本無異。書記官顏宗貝中華民國九十一年九月三十日附錄本案論罪科刑法條全文：刑法第二百十二條：偽造、變造護照、旅券、免許證、特許證及關於品行、能力、服務或其他相類之證書、介紹書，足以生損害於公眾或他人者，處一年以下有期徒刑、拘役或三百元以下罰金。刑法第二百十六條：行使第二百十條至第二百十五條之文書者，依偽造、變造文書或登載不實事項或使登載不實事項之規定處斷。",
  "characters": {
    "judges": [
      "何悅芳"
    ],
    "prosecutors": [

    ],
    "lawyers": [

    ],
    "clerks": [
      "顏宗貝"
    ],
    "plaintiffs": [

    ],
    "defendants": [
      "乙○○",
      "右列被告因偽造文書案件，經檢察官聲請以簡易判決處刑（九十一年度偵字第一一二",
      "二六號），本院判決如左："
    ],
    "prosecutor_office": [
      "臺灣高雄地方法院檢察署檢察官"
    ],
    "creditors": [

    ],
    "debtors": [

    ],
    "judicial_associate_officer": [

    ]
  },
  "adjudged_at": "2002-09-30",
  "created_at": "2016-02-04 18:11:44",
  "updated_at": "2016-02-04 18:11:44"
}