{
  "identify": "KSD-91-易-2803-20020930-1",
  "court": {
    "name": "臺灣高雄地方法院",
    "code": "KSD"
  },
  "division": {
    "name": "刑事",
    "code": "M"
  },
  "year": 91,
  "word": "易",
  "number": "2803",
  "jcheck": "1",
  "reason": "毒品危害防制條例",
  "content": "臺灣高雄地方法院刑事判決                        九十一年度易字第二八三號\n    公  訴  人  臺灣高雄地方法院檢察署檢察官\n    被      告  甲○○\n右列被告因違反毒品危害防制條例案件，經檢察官提起公訴（九十一年度毒偵字第三\n七二七號），本院判決如左：\n    主  文\n甲○○施用第二級毒品，處有期徒刑肆月，如易科罰金，以參佰元折算壹日。\n    事  實\n一、甲○○前於民國八十八年間因犯施用毒品案件，經本院於八十八年十月二十五日\n    以八十八年度毒聲字第七九三四號裁定送勒戒處所觀察、勒戒後，認有繼續施用\n    毒品之傾向，再由本院於八十八年十二月十日以八十八年度毒聲字第九二三八號\n    裁定令入戒治處所施以強制戒治，於強制戒治期滿後，經臺灣高雄地方法院檢察\n    署檢察官於九十年六月十三日以九十年度戒毒偵字第五四九一號為不起訴處分確\n    定。甲○○復於九十年十一月間又因施用第一級毒品海洛因，經台灣高雄地方法\n  院檢察署檢察官提出公訴，本院於九十一年六月十三日，以九十一年度訴字第一\n    ０一八號判處有期徒刑七月確定。惟甲○○仍不知悔改，其明知安非他命業經公\n    告列為毒品危害防制條例第二條第二項第二款之第二級毒品，不得非法持有、施\n    用，仍基於施用第二級毒品安非他命之犯意，於九十一年五月二十一日下午五時\n    許起回溯二十四小時內之某時，在高雄市前金區○○○路一五七號六樓之三，以\n    將第二級毒品安非他命置於吸食器燒烤吸食霧氣之方式，施用安非他命一次，嗣\n    於九十一年五月二十一日下午五時許，在高雄市前金區○○○路一五七號六樓之\n    三，為警緝獲並採驗尿液後發覺上情。\n二、案經高雄市政府警察局楠梓分局移送臺灣高雄地方法院檢察署檢察官偵查起訴。\n    理  由\n一、右揭犯罪事實，業據被告甲○○於本院審理時坦承不諱（參見本院九十一年九月\n    二十四日審判筆錄），被告於九十一年五月二十一日為警查獲時所採集之尿液，\n    經送驗結果，呈甲基安非他命陽性反應，有高雄市立凱旋醫院九十一年六月十四\n    日高市凱醫檢字第００四九二號煙毒尿液檢驗成績書一紙在卷可稽，被告上開自\n    白與事實相符，堪信為真實。再查，被告前於八十八年間因犯施用毒品案件，經\n    本院於八十八年十月二十五日以八十八年度毒聲字第七九三四號裁定送勒戒處所\n    觀察、勒戒後，認有繼續施用毒品之傾向，再由本院於八十八年十二月十日以八\n    十八年度毒聲字第九二三八號裁定令入戒治處所施以強制戒治，於強制戒治期滿\n    後，經臺灣高雄地方法院檢察署檢察官於九十年六月十三日以九十年度戒毒偵字\n    第六九九號為不起訴處分確定，復於九十年十一月間，又因施用第一級毒品，經\n    本院判處有期徒刑七月確定等事實，有該判決書正本及本院被告院內索引卡紀錄\n    表、臺灣高等法院被告全國前案紀錄表、臺灣高雄地方法院檢察署刑案資料查註\n    紀錄表各一份在卷可稽，被告於觀察勒戒、強制戒治期滿經檢察官不起訴處分後\n    ，五年內三犯毒品危害防制條例第十條之罪，本件事證明確，應依法予以論罪科\n    刑。\n二、核被告所為，係犯毒品危害防制條例第十條第二項之罪。被告持有第二級毒品，\n    進而施用，其持有之低度行為應被施用之高度行為所吸收，故不另論罪。爰審酌\n    被告於毒品危害防制條例施行後復因施用毒品，經觀察勒戒及強制戒治之處分，\n    並由檢察官為不起訴處分確定後，仍未戒絕毒品，再犯相同之罪，顯見其無戒毒\n    悔改之意，惟念其施用毒品乃自戕一己之身體健康，尚未害及他人，且其犯後已\n    坦承犯行，態度良好等一切情狀，量處如主文所示之刑，並諭知易科罰金折算之\n    標準。\n據上論斷，應依刑事訴訟法第二百九十九條第一項前段，毒品危害防制條例第十條第\n二項，刑法第十一條前段、第四十一條第一項，罰金罰鍰提高標準條例第二條，判決\n如主文。\n中        華      民       國     九十一    年     九     月    三十    日\n                                     臺灣高雄地方法院刑事庭\n                                         法  官  廖建瑜\n右正本證明與原本無異。\n如不服本判決，應於判決送達後十日內，向本院提出上訴狀。\n                                         書記官  王翌翔\n中        華      民       國     九十一    年     九     月    三十    日\n附錄論罪法條：\n毒品危害防制條例第十條第一項、第二項：\n施用第二級毒品者，處三年以下有期徒刑。\n",
  "structure": {
    "main": "甲○○施用第二級毒品，處有期徒刑肆月，如易科罰金，以參佰元折算壹日。",
    "fact": "一、甲○○前於民國八十八年間因犯施用毒品案件，經本院於八十八年十月二十五日\n    以八十八年度毒聲字第七九三四號裁定送勒戒處所觀察、勒戒後，認有繼續施用\n    毒品之傾向，再由本院於八十八年十二月十日以八十八年度毒聲字第九二三八號\n    裁定令入戒治處所施以強制戒治，於強制戒治期滿後，經臺灣高雄地方法院檢察\n    署檢察官於九十年六月十三日以九十年度戒毒偵字第五四九一號為不起訴處分確\n    定。甲○○復於九十年十一月間又因施用第一級毒品海洛因，經台灣高雄地方法\n  院檢察署檢察官提出公訴，本院於九十一年六月十三日，以九十一年度訴字第一\n    ０一八號判處有期徒刑七月確定。惟甲○○仍不知悔改，其明知安非他命業經公\n    告列為毒品危害防制條例第二條第二項第二款之第二級毒品，不得非法持有、施\n    用，仍基於施用第二級毒品安非他命之犯意，於九十一年五月二十一日下午五時\n    許起回溯二十四小時內之某時，在高雄市前金區○○○路一五七號六樓之三，以\n    將第二級毒品安非他命置於吸食器燒烤吸食霧氣之方式，施用安非他命一次，嗣\n    於九十一年五月二十一日下午五時許，在高雄市前金區○○○路一五七號六樓之\n    三，為警緝獲並採驗尿液後發覺上情。\n二、案經高雄市政府警察局楠梓分局移送臺灣高雄地方法院檢察署檢察官偵查起訴。",
    "reason": "一、右揭犯罪事實，業據被告甲○○於本院審理時坦承不諱（參見本院九十一年九月\n    二十四日審判筆錄），被告於九十一年五月二十一日為警查獲時所採集之尿液，\n    經送驗結果，呈甲基安非他命陽性反應，有高雄市立凱旋醫院九十一年六月十四\n    日高市凱醫檢字第００四九二號煙毒尿液檢驗成績書一紙在卷可稽，被告上開自\n    白與事實相符，堪信為真實。再查，被告前於八十八年間因犯施用毒品案件，經\n    本院於八十八年十月二十五日以八十八年度毒聲字第七九三四號裁定送勒戒處所\n    觀察、勒戒後，認有繼續施用毒品之傾向，再由本院於八十八年十二月十日以八\n    十八年度毒聲字第九二三八號裁定令入戒治處所施以強制戒治，於強制戒治期滿\n    後，經臺灣高雄地方法院檢察署檢察官於九十年六月十三日以九十年度戒毒偵字\n    第六九九號為不起訴處分確定，復於九十年十一月間，又因施用第一級毒品，經\n    本院判處有期徒刑七月確定等事實，有該判決書正本及本院被告院內索引卡紀錄\n    表、臺灣高等法院被告全國前案紀錄表、臺灣高雄地方法院檢察署刑案資料查註\n    紀錄表各一份在卷可稽，被告於觀察勒戒、強制戒治期滿經檢察官不起訴處分後\n    ，五年內三犯毒品危害防制條例第十條之罪，本件事證明確，應依法予以論罪科\n    刑。\n二、核被告所為，係犯毒品危害防制條例第十條第二項之罪。被告持有第二級毒品，\n    進而施用，其持有之低度行為應被施用之高度行為所吸收，故不另論罪。爰審酌\n    被告於毒品危害防制條例施行後復因施用毒品，經觀察勒戒及強制戒治之處分，\n    並由檢察官為不起訴處分確定後，仍未戒絕毒品，再犯相同之罪，顯見其無戒毒\n    悔改之意，惟念其施用毒品乃自戕一己之身體健康，尚未害及他人，且其犯後已\n    坦承犯行，態度良好等一切情狀，量處如主文所示之刑，並諭知易科罰金折算之\n    標準。\n據上論斷，應依刑事訴訟法第二百九十九條第一項前段，毒品危害防制條例第十條第\n二項，刑法第十一條前段、第四十一條第一項，罰金罰鍰提高標準條例第二條，判決\n如主文。\n中        華      民       國     九十一    年     九     月    三十    日\n                                     臺灣高雄地方法院刑事庭\n                                         法  官  廖建瑜\n右正本證明與原本無異。\n如不服本判決，應於判決送達後十日內，向本院提出上訴狀。\n                                         書記官  王翌翔"
  },
  "search": "臺灣高雄地方法院刑事判決九十一年度易字第二八三號公訴人臺灣高雄地方法院檢察署檢察官被告甲○○右列被告因違反毒品危害防制條例案件，經檢察官提起公訴（九十一年度毒偵字第三七二七號），本院判決如左：主文甲○○施用第二級毒品，處有期徒刑肆月，如易科罰金，以參佰元折算壹日。事實一、甲○○前於民國八十八年間因犯施用毒品案件，經本院於八十八年十月二十五日以八十八年度毒聲字第七九三四號裁定送勒戒處所觀察、勒戒後，認有繼續施用毒品之傾向，再由本院於八十八年十二月十日以八十八年度毒聲字第九二三八號裁定令入戒治處所施以強制戒治，於強制戒治期滿後，經臺灣高雄地方法院檢察署檢察官於九十年六月十三日以九十年度戒毒偵字第五四九一號為不起訴處分確定。甲○○復於九十年十一月間又因施用第一級毒品海洛因，經台灣高雄地方法院檢察署檢察官提出公訴，本院於九十一年六月十三日，以九十一年度訴字第一０一八號判處有期徒刑七月確定。惟甲○○仍不知悔改，其明知安非他命業經公告列為毒品危害防制條例第二條第二項第二款之第二級毒品，不得非法持有、施用，仍基於施用第二級毒品安非他命之犯意，於九十一年五月二十一日下午五時許起回溯二十四小時內之某時，在高雄市前金區○○○路一五七號六樓之三，以將第二級毒品安非他命置於吸食器燒烤吸食霧氣之方式，施用安非他命一次，嗣於九十一年五月二十一日下午五時許，在高雄市前金區○○○路一五七號六樓之三，為警緝獲並採驗尿液後發覺上情。二、案經高雄市政府警察局楠梓分局移送臺灣高雄地方法院檢察署檢察官偵查起訴。理由一、右揭犯罪事實，業據被告甲○○於本院審理時坦承不諱（參見本院九十一年九月二十四日審判筆錄），被告於九十一年五月二十一日為警查獲時所採集之尿液，經送驗結果，呈甲基安非他命陽性反應，有高雄市立凱旋醫院九十一年六月十四日高市凱醫檢字第００四九二號煙毒尿液檢驗成績書一紙在卷可稽，被告上開自白與事實相符，堪信為真實。再查，被告前於八十八年間因犯施用毒品案件，經本院於八十八年十月二十五日以八十八年度毒聲字第七九三四號裁定送勒戒處所觀察、勒戒後，認有繼續施用毒品之傾向，再由本院於八十八年十二月十日以八十八年度毒聲字第九二三八號裁定令入戒治處所施以強制戒治，於強制戒治期滿後，經臺灣高雄地方法院檢察署檢察官於九十年六月十三日以九十年度戒毒偵字第六九九號為不起訴處分確定，復於九十年十一月間，又因施用第一級毒品，經本院判處有期徒刑七月確定等事實，有該判決書正本及本院被告院內索引卡紀錄表、臺灣高等法院被告全國前案紀錄表、臺灣高雄地方法院檢察署刑案資料查註紀錄表各一份在卷可稽，被告於觀察勒戒、強制戒治期滿經檢察官不起訴處分後，五年內三犯毒品危害防制條例第十條之罪，本件事證明確，應依法予以論罪科刑。二、核被告所為，係犯毒品危害防制條例第十條第二項之罪。被告持有第二級毒品，進而施用，其持有之低度行為應被施用之高度行為所吸收，故不另論罪。爰審酌被告於毒品危害防制條例施行後復因施用毒品，經觀察勒戒及強制戒治之處分，並由檢察官為不起訴處分確定後，仍未戒絕毒品，再犯相同之罪，顯見其無戒毒悔改之意，惟念其施用毒品乃自戕一己之身體健康，尚未害及他人，且其犯後已坦承犯行，態度良好等一切情狀，量處如主文所示之刑，並諭知易科罰金折算之標準。據上論斷，應依刑事訴訟法第二百九十九條第一項前段，毒品危害防制條例第十條第二項，刑法第十一條前段、第四十一條第一項，罰金罰鍰提高標準條例第二條，判決如主文。中華民國九十一年九月三十日臺灣高雄地方法院刑事庭法官廖建瑜右正本證明與原本無異。如不服本判決，應於判決送達後十日內，向本院提出上訴狀。書記官王翌翔中華民國九十一年九月三十日附錄論罪法條：毒品危害防制條例第十條第一項、第二項：施用第二級毒品者，處三年以下有期徒刑。",
  "characters": {
    "judges": [
      "廖建瑜"
    ],
    "prosecutors": [

    ],
    "lawyers": [

    ],
    "clerks": [
      "王翌翔"
    ],
    "plaintiffs": [

    ],
    "defendants": [
      "甲○○",
      "右列被告因違反毒品危害防制條例案件，經檢察官提起公訴（九十一年度毒偵字第三",
      "七二七號），本院判決如左："
    ],
    "prosecutor_office": [
      "臺灣高雄地方法院檢察署檢察官"
    ],
    "creditors": [

    ],
    "debtors": [

    ],
    "judicial_associate_officer": [

    ]
  },
  "adjudged_at": "2002-09-30",
  "created_at": "2016-02-04 18:09:45",
  "updated_at": "2016-02-04 18:09:45"
}