{
  "identify": "KSD-99-重訴-265-20110817-1",
  "court": {
    "name": "臺灣高雄地方法院",
    "code": "KSD"
  },
  "division": {
    "name": "民事",
    "code": "V"
  },
  "year": 99,
  "word": "重訴",
  "number": "265",
  "jcheck": "1",
  "reason": "給付合夥利益分配款",
  "content": "臺灣高雄地方法院民事判決             99年度重訴字第265號\n原      告  吳興家\n訴訟代理人  張永昌律師\n            陳煜昇律師\n            李蔭敏\n被      告  許義郎\n訴訟代理人  杜立兆律師\n上列當事人間請求給付合夥利益分配款事件，經本院於民國100\n年7 月27日言詞辯論終結，判決如下：\n    主  文\n原告之訴及假執行之聲請均駁回。\n訴訟費用由原告負擔。\n    事實及理由\n一、原告主張：被告為高雄市林園區○○○路360 號建佑醫院之\n    執行事務合夥人暨院長，負責建佑醫院一切營運事項，而原\n    告自民國86年間開始在建佑醫院擔任醫師，進而於88年間成\n    為合夥人，以技術勞務出資，每年可按比例分配盈餘。原告\n    於93年至96年期間應分得如附表所示盈餘總計新臺幣（下同\n    ）25,640,697元，詎被告拒不給付，為此爰依民法第676 條\n    、第680 條、第541 條第1 項規定，提起本件訴訟等語。並\n    聲明：（一）被告應給付原告25,640,697元，及其中10,478\n    ,045元（即原先起訴部分）自99年8 月22日起訴狀繕本送達\n    翌日起、其餘15,162,652元（即擴張聲明部分）自100 年7\n    月4 日訴之變更暨陳述意見狀繕本送達翌日起，均至清償日\n    止，按週年利率5%計算之法定遲延利息。（二）如受勝訴判\n    決，願供擔保，聲請准予宣告假執行。\n二、被告抗辯：原告係基於僱傭關係而受僱於建佑醫院，按月依\n    執業績效領取薪資，而原告自93年1 月至96年10月31日離職\n    為止，已按月領得薪資共計35,377,354元，此即為原告應得\n    之全部報酬。原告並非建佑醫院之合夥人，兩造間並無合夥\n    關係，原告不得另行請求盈餘分配。建佑醫院於93至96年度\n    向稅捐機關申報之業務損益計算表以及申報所依據之聯合執\n    業合約書上，雖記載原告為合夥人且有分配盈餘，然此僅為\n    形式上報稅方便，內容並非真實情形，醫師以執行業務名義\n    申報所得報稅可繳納較少稅金。退步言之，縱認兩造間有合\n    夥關係，上述給付總額亦已超過原告所主張應得之盈餘分配\n    款，原告請求並無理由等語。並聲明：（一）原告之訴駁回\n    。（二）如受不利判決，願供擔保，聲請准予宣告免為假執\n    行。\n三、不爭執及爭執事項：\n（一）以下事項為兩造所不爭執，應堪作為本件判決之基礎：\n  １、原告於86至96年間在建佑醫院擔任醫師，被告為醫院負責\n      人。\n  ２、原告於93年1 月至96年10月間已按月領得薪資共計35,377\n      ,354元（明細如本院卷第47至49頁）。\n  ３、建佑醫院於93至96年度向稅捐機關申報之（更正後）業務\n      損益計算表所載合夥盈餘、原告合夥人應分配比例以及數\n      額如附表所示。\n（二）本件爭點在於：兩造間有無合夥關係存在？原告得否請求\n      被告給付93至96年間之合夥事業盈餘分配款？數額應為若\n      干？\n四、得心證之理由：\n（一）按合夥事業進行後，合夥財產可能多於或少於合夥債務與\n      出資之總和，而使合夥事業之經營出現盈餘或虧損，進而\n      發生如何將損益分配於合夥人之問題。依民法第677 條第\n      1 項規定，合夥人間損益分配之成數應依合夥契約定之，\n      未經約定者則按各合夥人出資額之比例定之。而分配利益\n      之時期，依民法第676 條規定，除契約令有訂定者外，應\n      於每屆事務年度終為之。復按當事人主張有利於己之事實\n      者，就其事實有舉證之責任，民事訴訟法第277 條前段亦\n      有明定。本件原告請求被告分配合夥盈餘，應先舉證兩造\n      間有合夥關係存在。\n（二）原告主張：除前揭每月所受領之薪資外，每年度尚得請求\n      合夥利益分配款，自88年度成為合夥人以後均未領取，雖\n      曾向被告詢問，但被告回稱沒有盈餘，原告礙於被告是軍\n      醫體系之學長而不敢質疑等語。惟原告自稱：兩造間從未\n      簽署合夥契約書，被告所提出93至96年度之聯合執業合約\n      書非屬真正（本院卷第164 至167 頁）等語，則如何認定\n      兩造間確有合夥關係存在，已有疑問。原告雖舉建佑醫院\n      於93至96年度向稅捐機關申報之業務損益計算表為證（本\n      院卷第66至74頁），被告則辯稱：其僅為報稅用途，內容\n      並非真實等語。本院認以目前社會現況而言，確有不少醫\n      師以執行業務所得之名義申報個人綜合所得稅，俾以減低\n      稅金，主管機關已研議自今年度起將駐診醫師所得性質由\n      執行業務所得改列為薪資所得，此為週知之事實。另參以\n      前開業務損益計算表上所列其他合夥人藍健台、賴家明、\n      朱家駿醫師，於本院審理時均證稱：彼等薪資是按照執行\n      業務績效發放，每月僅領取一份報酬，不用負責虧損也沒\n      有分配盈餘等語。則被告辯稱前開業務損益計算表僅供報\n      稅使用等語，應非無稽，尚難僅憑其載有合夥盈餘、原告\n      應分配比例以及數額等項目，即遽認原告為合夥人而得據\n      以請求盈餘分配。\n（三）綜據上述，本件原告請求被告給付合夥盈餘分配款，尚難\n      認為有理，應予駁回。至其假執行之聲請亦失所附麗，應\n      併予駁回。又本件事證已臻明確，兩造所提其他攻擊防禦\n      方法或證據，經核與判決結果不生影響，爰不逐一論列，\n      附此敘明。\n五、結論：本件原告之訴為無理由，應依民事訴訟法第78條，判\n    決如主文。\n中    華    民    國    100   年    8     月    17    日\n                          民事第一庭  法  官  譚德周\n以上正本係照原本作成。\n如對本判決上訴，須於判決送達後20日內向本院提出上訴狀。如\n委任律師提起上訴者，應一併繳納上訴審裁判費。\n中    華    民    國   100    年    8     月    17    日\n                                      書記官  鄭永媚\n附表：\n┌──┬──────┬───────┬───────┐\n│年度│合夥盈餘（新│原告應分配比例│原告應分得盈餘│\n│    │臺幣）      │              │（新臺幣）    │\n├──┼──────┼───────┼───────┤\n│93  │45,438,088元│11.8﹪        │5,361,694元   │\n├──┼──────┼───────┼───────┤\n│94  │40,782,782元│13.8﹪        │5,628,024元   │\n├──┼──────┼───────┼───────┤\n│95  │45,710,900元│14.8﹪        │6,765,213元   │\n├──┼──────┼───────┼───────┤\n│96  │53,282,202元│14.8﹪        │7,885,766元   │\n└──┴──────┴───────┴───────┘",
  "structure": {
    "main": "原告之訴及假執行之聲請均駁回。\n訴訟費用由原告負擔。",
    "fact": "一、原告主張：被告為高雄市林園區○○○路360 號建佑醫院之\n    執行事務合夥人暨院長，負責建佑醫院一切營運事項，而原\n    告自民國86年間開始在建佑醫院擔任醫師，進而於88年間成\n    為合夥人，以技術勞務出資，每年可按比例分配盈餘。原告\n    於93年至96年期間應分得如附表所示盈餘總計新臺幣（下同\n    ）25,640,697元，詎被告拒不給付，為此爰依民法第676 條\n    、第680 條、第541 條第1 項規定，提起本件訴訟等語。並\n    聲明：（一）被告應給付原告25,640,697元，及其中10,478\n    ,045元（即原先起訴部分）自99年8 月22日起訴狀繕本送達\n    翌日起、其餘15,162,652元（即擴張聲明部分）自100 年7\n    月4 日訴之變更暨陳述意見狀繕本送達翌日起，均至清償日\n    止，按週年利率5%計算之法定遲延利息。（二）如受勝訴判\n    決，願供擔保，聲請准予宣告假執行。\n二、被告抗辯：原告係基於僱傭關係而受僱於建佑醫院，按月依\n    執業績效領取薪資，而原告自93年1 月至96年10月31日離職\n    為止，已按月領得薪資共計35,377,354元，此即為原告應得\n    之全部報酬。原告並非建佑醫院之合夥人，兩造間並無合夥\n    關係，原告不得另行請求盈餘分配。建佑醫院於93至96年度\n    向稅捐機關申報之業務損益計算表以及申報所依據之聯合執\n    業合約書上，雖記載原告為合夥人且有分配盈餘，然此僅為\n    形式上報稅方便，內容並非真實情形，醫師以執行業務名義\n    申報所得報稅可繳納較少稅金。退步言之，縱認兩造間有合\n    夥關係，上述給付總額亦已超過原告所主張應得之盈餘分配\n    款，原告請求並無理由等語。並聲明：（一）原告之訴駁回\n    。（二）如受不利判決，願供擔保，聲請准予宣告免為假執\n    行。\n三、不爭執及爭執事項：\n（一）以下事項為兩造所不爭執，應堪作為本件判決之基礎：\n  １、原告於86至96年間在建佑醫院擔任醫師，被告為醫院負責\n      人。\n  ２、原告於93年1 月至96年10月間已按月領得薪資共計35,377\n      ,354元（明細如本院卷第47至49頁）。\n  ３、建佑醫院於93至96年度向稅捐機關申報之（更正後）業務\n      損益計算表所載合夥盈餘、原告合夥人應分配比例以及數\n      額如附表所示。\n（二）本件爭點在於：兩造間有無合夥關係存在？原告得否請求\n      被告給付93至96年間之合夥事業盈餘分配款？數額應為若\n      干？\n四、得心證之理由：\n（一）按合夥事業進行後，合夥財產可能多於或少於合夥債務與\n      出資之總和，而使合夥事業之經營出現盈餘或虧損，進而\n      發生如何將損益分配於合夥人之問題。依民法第677 條第\n      1 項規定，合夥人間損益分配之成數應依合夥契約定之，\n      未經約定者則按各合夥人出資額之比例定之。而分配利益\n      之時期，依民法第676 條規定，除契約令有訂定者外，應\n      於每屆事務年度終為之。復按當事人主張有利於己之事實\n      者，就其事實有舉證之責任，民事訴訟法第277 條前段亦\n      有明定。本件原告請求被告分配合夥盈餘，應先舉證兩造\n      間有合夥關係存在。\n（二）原告主張：除前揭每月所受領之薪資外，每年度尚得請求\n      合夥利益分配款，自88年度成為合夥人以後均未領取，雖\n      曾向被告詢問，但被告回稱沒有盈餘，原告礙於被告是軍\n      醫體系之學長而不敢質疑等語。惟原告自稱：兩造間從未\n      簽署合夥契約書，被告所提出93至96年度之聯合執業合約\n      書非屬真正（本院卷第164 至167 頁）等語，則如何認定\n      兩造間確有合夥關係存在，已有疑問。原告雖舉建佑醫院\n      於93至96年度向稅捐機關申報之業務損益計算表為證（本\n      院卷第66至74頁），被告則辯稱：其僅為報稅用途，內容\n      並非真實等語。本院認以目前社會現況而言，確有不少醫\n      師以執行業務所得之名義申報個人綜合所得稅，俾以減低\n      稅金，主管機關已研議自今年度起將駐診醫師所得性質由\n      執行業務所得改列為薪資所得，此為週知之事實。另參以\n      前開業務損益計算表上所列其他合夥人藍健台、賴家明、\n      朱家駿醫師，於本院審理時均證稱：彼等薪資是按照執行\n      業務績效發放，每月僅領取一份報酬，不用負責虧損也沒\n      有分配盈餘等語。則被告辯稱前開業務損益計算表僅供報\n      稅使用等語，應非無稽，尚難僅憑其載有合夥盈餘、原告\n      應分配比例以及數額等項目，即遽認原告為合夥人而得據\n      以請求盈餘分配。\n（三）綜據上述，本件原告請求被告給付合夥盈餘分配款，尚難\n      認為有理，應予駁回。至其假執行之聲請亦失所附麗，應\n      併予駁回。又本件事證已臻明確，兩造所提其他攻擊防禦\n      方法或證據，經核與判決結果不生影響，爰不逐一論列，\n      附此敘明。\n五、結論：本件原告之訴為無理由，應依民事訴訟法第78條，判\n    決如主文。",
    "reason": "一、原告主張：被告為高雄市林園區○○○路360 號建佑醫院之\n    執行事務合夥人暨院長，負責建佑醫院一切營運事項，而原\n    告自民國86年間開始在建佑醫院擔任醫師，進而於88年間成\n    為合夥人，以技術勞務出資，每年可按比例分配盈餘。原告\n    於93年至96年期間應分得如附表所示盈餘總計新臺幣（下同\n    ）25,640,697元，詎被告拒不給付，為此爰依民法第676 條\n    、第680 條、第541 條第1 項規定，提起本件訴訟等語。並\n    聲明：（一）被告應給付原告25,640,697元，及其中10,478\n    ,045元（即原先起訴部分）自99年8 月22日起訴狀繕本送達\n    翌日起、其餘15,162,652元（即擴張聲明部分）自100 年7\n    月4 日訴之變更暨陳述意見狀繕本送達翌日起，均至清償日\n    止，按週年利率5%計算之法定遲延利息。（二）如受勝訴判\n    決，願供擔保，聲請准予宣告假執行。\n二、被告抗辯：原告係基於僱傭關係而受僱於建佑醫院，按月依\n    執業績效領取薪資，而原告自93年1 月至96年10月31日離職\n    為止，已按月領得薪資共計35,377,354元，此即為原告應得\n    之全部報酬。原告並非建佑醫院之合夥人，兩造間並無合夥\n    關係，原告不得另行請求盈餘分配。建佑醫院於93至96年度\n    向稅捐機關申報之業務損益計算表以及申報所依據之聯合執\n    業合約書上，雖記載原告為合夥人且有分配盈餘，然此僅為\n    形式上報稅方便，內容並非真實情形，醫師以執行業務名義\n    申報所得報稅可繳納較少稅金。退步言之，縱認兩造間有合\n    夥關係，上述給付總額亦已超過原告所主張應得之盈餘分配\n    款，原告請求並無理由等語。並聲明：（一）原告之訴駁回\n    。（二）如受不利判決，願供擔保，聲請准予宣告免為假執\n    行。\n三、不爭執及爭執事項：\n（一）以下事項為兩造所不爭執，應堪作為本件判決之基礎：\n  １、原告於86至96年間在建佑醫院擔任醫師，被告為醫院負責\n      人。\n  ２、原告於93年1 月至96年10月間已按月領得薪資共計35,377\n      ,354元（明細如本院卷第47至49頁）。\n  ３、建佑醫院於93至96年度向稅捐機關申報之（更正後）業務\n      損益計算表所載合夥盈餘、原告合夥人應分配比例以及數\n      額如附表所示。\n（二）本件爭點在於：兩造間有無合夥關係存在？原告得否請求\n      被告給付93至96年間之合夥事業盈餘分配款？數額應為若\n      干？\n四、得心證之理由：\n（一）按合夥事業進行後，合夥財產可能多於或少於合夥債務與\n      出資之總和，而使合夥事業之經營出現盈餘或虧損，進而\n      發生如何將損益分配於合夥人之問題。依民法第677 條第\n      1 項規定，合夥人間損益分配之成數應依合夥契約定之，\n      未經約定者則按各合夥人出資額之比例定之。而分配利益\n      之時期，依民法第676 條規定，除契約令有訂定者外，應\n      於每屆事務年度終為之。復按當事人主張有利於己之事實\n      者，就其事實有舉證之責任，民事訴訟法第277 條前段亦\n      有明定。本件原告請求被告分配合夥盈餘，應先舉證兩造\n      間有合夥關係存在。\n（二）原告主張：除前揭每月所受領之薪資外，每年度尚得請求\n      合夥利益分配款，自88年度成為合夥人以後均未領取，雖\n      曾向被告詢問，但被告回稱沒有盈餘，原告礙於被告是軍\n      醫體系之學長而不敢質疑等語。惟原告自稱：兩造間從未\n      簽署合夥契約書，被告所提出93至96年度之聯合執業合約\n      書非屬真正（本院卷第164 至167 頁）等語，則如何認定\n      兩造間確有合夥關係存在，已有疑問。原告雖舉建佑醫院\n      於93至96年度向稅捐機關申報之業務損益計算表為證（本\n      院卷第66至74頁），被告則辯稱：其僅為報稅用途，內容\n      並非真實等語。本院認以目前社會現況而言，確有不少醫\n      師以執行業務所得之名義申報個人綜合所得稅，俾以減低\n      稅金，主管機關已研議自今年度起將駐診醫師所得性質由\n      執行業務所得改列為薪資所得，此為週知之事實。另參以\n      前開業務損益計算表上所列其他合夥人藍健台、賴家明、\n      朱家駿醫師，於本院審理時均證稱：彼等薪資是按照執行\n      業務績效發放，每月僅領取一份報酬，不用負責虧損也沒\n      有分配盈餘等語。則被告辯稱前開業務損益計算表僅供報\n      稅使用等語，應非無稽，尚難僅憑其載有合夥盈餘、原告\n      應分配比例以及數額等項目，即遽認原告為合夥人而得據\n      以請求盈餘分配。\n（三）綜據上述，本件原告請求被告給付合夥盈餘分配款，尚難\n      認為有理，應予駁回。至其假執行之聲請亦失所附麗，應\n      併予駁回。又本件事證已臻明確，兩造所提其他攻擊防禦\n      方法或證據，經核與判決結果不生影響，爰不逐一論列，\n      附此敘明。\n五、結論：本件原告之訴為無理由，應依民事訴訟法第78條，判\n    決如主文。"
  },
  "search": "臺灣高雄地方法院民事判決99年度重訴字第265號原告吳興家訴訟代理人張永昌律師陳煜昇律師李蔭敏被告許義郎訴訟代理人杜立兆律師上列當事人間請求給付合夥利益分配款事件，經本院於民國100年7月27日言詞辯論終結，判決如下：主文原告之訴及假執行之聲請均駁回。訴訟費用由原告負擔。事實及理由一、原告主張：被告為高雄市林園區○○○路360號建佑醫院之執行事務合夥人暨院長，負責建佑醫院一切營運事項，而原告自民國86年間開始在建佑醫院擔任醫師，進而於88年間成為合夥人，以技術勞務出資，每年可按比例分配盈餘。原告於93年至96年期間應分得如附表所示盈餘總計新臺幣（下同）25,640,697元，詎被告拒不給付，為此爰依民法第676條、第680條、第541條第1項規定，提起本件訴訟等語。並聲明：（一）被告應給付原告25,640,697元，及其中10,478,045元（即原先起訴部分）自99年8月22日起訴狀繕本送達翌日起、其餘15,162,652元（即擴張聲明部分）自100年7月4日訴之變更暨陳述意見狀繕本送達翌日起，均至清償日止，按週年利率5%計算之法定遲延利息。（二）如受勝訴判決，願供擔保，聲請准予宣告假執行。二、被告抗辯：原告係基於僱傭關係而受僱於建佑醫院，按月依執業績效領取薪資，而原告自93年1月至96年10月31日離職為止，已按月領得薪資共計35,377,354元，此即為原告應得之全部報酬。原告並非建佑醫院之合夥人，兩造間並無合夥關係，原告不得另行請求盈餘分配。建佑醫院於93至96年度向稅捐機關申報之業務損益計算表以及申報所依據之聯合執業合約書上，雖記載原告為合夥人且有分配盈餘，然此僅為形式上報稅方便，內容並非真實情形，醫師以執行業務名義申報所得報稅可繳納較少稅金。退步言之，縱認兩造間有合夥關係，上述給付總額亦已超過原告所主張應得之盈餘分配款，原告請求並無理由等語。並聲明：（一）原告之訴駁回。（二）如受不利判決，願供擔保，聲請准予宣告免為假執行。三、不爭執及爭執事項：（一）以下事項為兩造所不爭執，應堪作為本件判決之基礎：１、原告於86至96年間在建佑醫院擔任醫師，被告為醫院負責人。２、原告於93年1月至96年10月間已按月領得薪資共計35,377,354元（明細如本院卷第47至49頁）。３、建佑醫院於93至96年度向稅捐機關申報之（更正後）業務損益計算表所載合夥盈餘、原告合夥人應分配比例以及數額如附表所示。（二）本件爭點在於：兩造間有無合夥關係存在？原告得否請求被告給付93至96年間之合夥事業盈餘分配款？數額應為若干？四、得心證之理由：（一）按合夥事業進行後，合夥財產可能多於或少於合夥債務與出資之總和，而使合夥事業之經營出現盈餘或虧損，進而發生如何將損益分配於合夥人之問題。依民法第677條第1項規定，合夥人間損益分配之成數應依合夥契約定之，未經約定者則按各合夥人出資額之比例定之。而分配利益之時期，依民法第676條規定，除契約令有訂定者外，應於每屆事務年度終為之。復按當事人主張有利於己之事實者，就其事實有舉證之責任，民事訴訟法第277條前段亦有明定。本件原告請求被告分配合夥盈餘，應先舉證兩造間有合夥關係存在。（二）原告主張：除前揭每月所受領之薪資外，每年度尚得請求合夥利益分配款，自88年度成為合夥人以後均未領取，雖曾向被告詢問，但被告回稱沒有盈餘，原告礙於被告是軍醫體系之學長而不敢質疑等語。惟原告自稱：兩造間從未簽署合夥契約書，被告所提出93至96年度之聯合執業合約書非屬真正（本院卷第164至167頁）等語，則如何認定兩造間確有合夥關係存在，已有疑問。原告雖舉建佑醫院於93至96年度向稅捐機關申報之業務損益計算表為證（本院卷第66至74頁），被告則辯稱：其僅為報稅用途，內容並非真實等語。本院認以目前社會現況而言，確有不少醫師以執行業務所得之名義申報個人綜合所得稅，俾以減低稅金，主管機關已研議自今年度起將駐診醫師所得性質由執行業務所得改列為薪資所得，此為週知之事實。另參以前開業務損益計算表上所列其他合夥人藍健台、賴家明、朱家駿醫師，於本院審理時均證稱：彼等薪資是按照執行業務績效發放，每月僅領取一份報酬，不用負責虧損也沒有分配盈餘等語。則被告辯稱前開業務損益計算表僅供報稅使用等語，應非無稽，尚難僅憑其載有合夥盈餘、原告應分配比例以及數額等項目，即遽認原告為合夥人而得據以請求盈餘分配。（三）綜據上述，本件原告請求被告給付合夥盈餘分配款，尚難認為有理，應予駁回。至其假執行之聲請亦失所附麗，應併予駁回。又本件事證已臻明確，兩造所提其他攻擊防禦方法或證據，經核與判決結果不生影響，爰不逐一論列，附此敘明。五、結論：本件原告之訴為無理由，應依民事訴訟法第78條，判決如主文。中華民國100年8月17日民事第一庭法官譚德周以上正本係照原本作成。如對本判決上訴，須於判決送達後20日內向本院提出上訴狀。如委任律師提起上訴者，應一併繳納上訴審裁判費。中華民國100年8月17日書記官鄭永媚附表：┌──┬──────┬───────┬───────┐│年度│合夥盈餘（新│原告應分配比例│原告應分得盈餘│││臺幣）││（新臺幣）│├──┼──────┼───────┼───────┤│93│45,438,088元│11.8﹪│5,361,694元│├──┼──────┼───────┼───────┤│94│40,782,782元│13.8﹪│5,628,024元│├──┼──────┼───────┼───────┤│95│45,710,900元│14.8﹪│6,765,213元│├──┼──────┼───────┼───────┤│96│53,282,202元│14.8﹪│7,885,766元│└──┴──────┴───────┴───────┘",
  "characters": {
    "judges": [
      "譚德周"
    ],
    "prosecutors": [

    ],
    "lawyers": [
      "張永昌",
      "陳煜昇",
      "杜立兆",
      "委任"
    ],
    "clerks": [
      "鄭永媚"
    ],
    "plaintiffs": [
      "吳興家"
    ],
    "defendants": [
      "許義郎"
    ],
    "prosecutor_office": [

    ],
    "creditors": [

    ],
    "debtors": [

    ],
    "judicial_associate_officer": [

    ]
  },
  "adjudged_at": "2011-08-17",
  "created_at": "2016-02-12 16:51:53",
  "updated_at": "2016-02-12 16:51:53"
}