{
  "identify": "TCD-100-訴-30-20110818-2",
  "court": {
    "name": "臺灣臺中地方法院",
    "code": "TCD"
  },
  "division": {
    "name": "民事",
    "code": "V"
  },
  "year": 100,
  "word": "訴",
  "number": "30",
  "jcheck": "2",
  "reason": "給付貨款",
  "content": "臺灣臺中地方法院民事裁定  100年度訴字第30號\n原      告  嘉碁科技股份有限公司\n法定代理人  黃種齊\n訴訟代理人  嚴庚辰律師\n被      告  山汰科技企業有限公司\n法定代理人  王勝志\n訴訟代理人  鐘登科律師\n            廖奕婷律師\n上列當事人間請求給付貨款事件，本院於民國100年7月20日所為\n之判決，其正本應依職權更正如下：\n    主    文\n原判決正本被告欄中關於「山汱科技企業有限公司」記載，應更\n正為「山汰科技企業有限公司」。\n    理      由\n一、按判決如有誤寫、誤算或其他類此之顯然錯誤者，法院得依\n    聲請或依職權以裁定更正之，其正本與原本不符者亦同，民\n    事訴訟法第232條第1項定有明文。\n二、查本院前開之判決正本有如主文所示之顯然錯誤，應予更正\n    。\n三、依首開規定裁定如主文。\n中    華    民    國   100    年    8     月    18    日\n                  民事第四庭    法  官  夏一\n上正本係照原本作成\n如不服本裁定應於送達後10日內向本院提出抗告狀，並繳納抗告\n費新臺幣1,000元。\n中    華    民    國   100    年    8     月    18    日\n                                書記官  林玉門",
  "structure": {
    "main": "原判決正本被告欄中關於「山汱科技企業有限公司」記載，應更\n正為「山汰科技企業有限公司」。",
    "reason": "一、按判決如有誤寫、誤算或其他類此之顯然錯誤者，法院得依\n    聲請或依職權以裁定更正之，其正本與原本不符者亦同，民\n    事訴訟法第232條第1項定有明文。\n二、查本院前開之判決正本有如主文所示之顯然錯誤，應予更正\n    。\n三、依首開規定裁定如主文。"
  },
  "search": "臺灣臺中地方法院民事裁定100年度訴字第30號原告嘉碁科技股份有限公司法定代理人黃種齊訴訟代理人嚴庚辰律師被告山汰科技企業有限公司法定代理人王勝志訴訟代理人鐘登科律師廖奕婷律師上列當事人間請求給付貨款事件，本院於民國100年7月20日所為之判決，其正本應依職權更正如下：主文原判決正本被告欄中關於「山汱科技企業有限公司」記載，應更正為「山汰科技企業有限公司」。理由一、按判決如有誤寫、誤算或其他類此之顯然錯誤者，法院得依聲請或依職權以裁定更正之，其正本與原本不符者亦同，民事訴訟法第232條第1項定有明文。二、查本院前開之判決正本有如主文所示之顯然錯誤，應予更正。三、依首開規定裁定如主文。中華民國100年8月18日民事第四庭法官夏一上正本係照原本作成如不服本裁定應於送達後10日內向本院提出抗告狀，並繳納抗告費新臺幣1,000元。中華民國100年8月18日書記官林玉門",
  "characters": {
    "judges": [
      "夏一"
    ],
    "prosecutors": [

    ],
    "lawyers": [
      "嚴庚辰",
      "鐘登科",
      "廖奕婷"
    ],
    "clerks": [

    ],
    "plaintiffs": [
      "嘉碁科技股份有限公司"
    ],
    "defendants": [
      "山汰科技企業有限公司"
    ],
    "prosecutor_office": [

    ],
    "creditors": [

    ],
    "debtors": [

    ],
    "judicial_associate_officer": [

    ]
  },
  "adjudged_at": "2011-08-18",
  "created_at": "2016-02-12 16:42:48",
  "updated_at": "2016-02-12 16:42:48"
}