{
  "identify": "TPH-100-毒抗-251-20110818-1",
  "court": {
    "name": "臺灣高等法院",
    "code": "TPH"
  },
  "division": {
    "name": "刑事",
    "code": "M"
  },
  "year": 100,
  "word": "毒抗",
  "number": "251",
  "jcheck": "1",
  "reason": "毒品危害防制條例",
  "content": "臺灣高等法院刑事裁定                100年度毒抗字第251號\n抗  告  人\n即  被  告  陳家禛\n上列抗告人即被告因違反毒品危害防制條例案件(臺灣臺北地方\n法院檢察署100年度毒偵字第1419號)，不服臺灣臺北地方法院\n100年度毒聲字第428號，中華民國100年7月26日原審裁定（聲請\n案號：臺灣臺北地方法院檢察署100年度聲觀字第365號），提起\n抗告，本院裁定如下：\n    主  文\n抗告駁回。\n    理  由\n一、原裁定意旨略以：抗告人即被告陳家禎（下稱被告）基於施\n    用第二級毒品MDMA之犯意，於民國(下同)100年4月3日凌晨2\n    、3點在北市中正區○○○路○段84巷21號4樓之1非法施用第\n    二級毒品MDMA一次之事實，業經被告於原審中自白不諱(詳\n    原審卷第7頁背面筆錄)，而被告於100年4月3日為警查獲當\n    天自願配合警方採集之尿液，經送鑑定結果，確呈MDMA陽性\n    反應，有臺灣尖端先進生技醫藥股份有限公司出具之濫用藥\n    物檢驗報告、臺北市政府警察局偵辦毒品案件尿液檢體委驗\n    單、鑑定人結文等各影本一紙在卷可稽(詳偵查卷第5、6頁)\n    ，因認被告之自白與事實相符，被告有非法施用第2級毒品\n    之事實，堪以認定。又被告前因施用毒品案件經原審法院以\n    91年毒聲字第1466號裁定送觀察、勒戒後，因無施用毒品之\n    傾向，於91年9月12日釋放後，並經臺灣臺北地方法院檢察\n    署檢察官於91年9月13日以91年度毒偵字第1250號案不起訴\n    處分在案，有本院被告前案紀錄表乙份在卷可考，因認被告\n    於受觀察、勒戒執行完畢釋放後逾5年始再犯下本案，爰依\n    毒危害防制條例第20條第3、1項及觀察勒戒處分執行條例第\n    3條第1項規定，裁定將被告送勒戒處所觀察、勒戒。\n二、抗告意旨略以：被告為警查獲後非常懊悔，已主動至行政院\n    衛生署指定之醫療機構請求治療，至今已無毒癮，實無再令\n    入勒戒處所觀察、勒戒之必要；且被告目前正常上班，如進\n    入勒戒處所觀察、勒戒，其間即無法上班，公司不可能給如\n    此長假，公司若知道被告施用毒品，必予解職，被告即使勒\n    戒完畢回來後也無法回到原公司上班，被告生活將陷入困窘\n    ，為此請求鈞院撤銷原裁定，免除被告進入勒戒處所等語，\n    並提出聯合醫院松德院區100年7月11日藥物檢查檢驗報告及\n    醫療費用收據各乙紙為證。\n三、按MDMA為毒品危害防制條例第2條第2項第2款所規定之第二\n    級毒品，又按犯該條例第10條之施用第二級毒品罪者，檢察\n    官應聲請法院裁定，令被告入勒戒處所觀察、勒戒，其期間\n    不得逾2月，同條例第20條第1項定有明文。又毒品危害防制\n    條例第20條第1項關於觀察、勒戒之規定，係強制規定，除\n    合於同條例第21條第1項所定「於犯罪未發覺前，自動向行\n    政院衛生署指定之醫療機構請求治療，醫療機構免將請求治\n    療者送法院或檢察機關」之情形外，對於犯毒品危害防制條\n    例第10條之罪者，檢察官均應向法院提出聲請裁定令其入勒\n    戒處所觀察、勒戒，法院亦無不予裁定之理。\n四、經查，本件被告業於原審自白非法施用第2級毒品MDMA一次\n    ，並有臺灣尖端先進生技醫藥股份有限公司出具之濫用藥物\n    檢驗報告、臺北市政府警察局偵辦毒品案件尿液檢體委驗單\n    、鑑定人結文各影本1紙等證據在卷可稽，被告施用MDMA之\n    事實至堪認定，原審依檢察官之聲請，裁定令被告入勒戒處\n    所觀察、勒戒，其期間不得逾2月，核其認事用法，並無違\n    誤。被告提起本件抗告，理由雖如前述，惟其既有施用毒品\n    之行為，且未合於上開毒品危害防制條例第21條第1項規定\n    之情形，即應送觀察、勒戒，並無例外，不得以被告自行就\n    醫已無毒癮之事證免除其入勒戒處所觀察、勒戒之餘地。是\n    被告請求撤銷原裁定，免除其進入勒戒處所觀察、勒戒云云\n    ，尚屬無據；本件被告之抗告為無理由，應予駁回。\n據上論斷，應依刑事訴訟法第412條，裁定如主文。\n中    華    民    國   100    年    8     月    18    日\n                  刑事第二十五庭審判長法  官  黃瑞華\n                                      法  官  陳恆寬\n                                      法  官  陳德民\n以上正本證明與原本無異。\n不得再抗告。\n                                      書記官  丁淑蘭\n中    華    民    國   100    年    8     月    18    日",
  "structure": {
    "main": "抗告駁回。",
    "reason": "一、原裁定意旨略以：抗告人即被告陳家禎（下稱被告）基於施\n    用第二級毒品MDMA之犯意，於民國(下同)100年4月3日凌晨2\n    、3點在北市中正區○○○路○段84巷21號4樓之1非法施用第\n    二級毒品MDMA一次之事實，業經被告於原審中自白不諱(詳\n    原審卷第7頁背面筆錄)，而被告於100年4月3日為警查獲當\n    天自願配合警方採集之尿液，經送鑑定結果，確呈MDMA陽性\n    反應，有臺灣尖端先進生技醫藥股份有限公司出具之濫用藥\n    物檢驗報告、臺北市政府警察局偵辦毒品案件尿液檢體委驗\n    單、鑑定人結文等各影本一紙在卷可稽(詳偵查卷第5、6頁)\n    ，因認被告之自白與事實相符，被告有非法施用第2級毒品\n    之事實，堪以認定。又被告前因施用毒品案件經原審法院以\n    91年毒聲字第1466號裁定送觀察、勒戒後，因無施用毒品之\n    傾向，於91年9月12日釋放後，並經臺灣臺北地方法院檢察\n    署檢察官於91年9月13日以91年度毒偵字第1250號案不起訴\n    處分在案，有本院被告前案紀錄表乙份在卷可考，因認被告\n    於受觀察、勒戒執行完畢釋放後逾5年始再犯下本案，爰依\n    毒危害防制條例第20條第3、1項及觀察勒戒處分執行條例第\n    3條第1項規定，裁定將被告送勒戒處所觀察、勒戒。\n二、抗告意旨略以：被告為警查獲後非常懊悔，已主動至行政院\n    衛生署指定之醫療機構請求治療，至今已無毒癮，實無再令\n    入勒戒處所觀察、勒戒之必要；且被告目前正常上班，如進\n    入勒戒處所觀察、勒戒，其間即無法上班，公司不可能給如\n    此長假，公司若知道被告施用毒品，必予解職，被告即使勒\n    戒完畢回來後也無法回到原公司上班，被告生活將陷入困窘\n    ，為此請求鈞院撤銷原裁定，免除被告進入勒戒處所等語，\n    並提出聯合醫院松德院區100年7月11日藥物檢查檢驗報告及\n    醫療費用收據各乙紙為證。\n三、按MDMA為毒品危害防制條例第2條第2項第2款所規定之第二\n    級毒品，又按犯該條例第10條之施用第二級毒品罪者，檢察\n    官應聲請法院裁定，令被告入勒戒處所觀察、勒戒，其期間\n    不得逾2月，同條例第20條第1項定有明文。又毒品危害防制\n    條例第20條第1項關於觀察、勒戒之規定，係強制規定，除\n    合於同條例第21條第1項所定「於犯罪未發覺前，自動向行\n    政院衛生署指定之醫療機構請求治療，醫療機構免將請求治\n    療者送法院或檢察機關」之情形外，對於犯毒品危害防制條\n    例第10條之罪者，檢察官均應向法院提出聲請裁定令其入勒\n    戒處所觀察、勒戒，法院亦無不予裁定之理。\n四、經查，本件被告業於原審自白非法施用第2級毒品MDMA一次\n    ，並有臺灣尖端先進生技醫藥股份有限公司出具之濫用藥物\n    檢驗報告、臺北市政府警察局偵辦毒品案件尿液檢體委驗單\n    、鑑定人結文各影本1紙等證據在卷可稽，被告施用MDMA之\n    事實至堪認定，原審依檢察官之聲請，裁定令被告入勒戒處\n    所觀察、勒戒，其期間不得逾2月，核其認事用法，並無違\n    誤。被告提起本件抗告，理由雖如前述，惟其既有施用毒品\n    之行為，且未合於上開毒品危害防制條例第21條第1項規定\n    之情形，即應送觀察、勒戒，並無例外，不得以被告自行就\n    醫已無毒癮之事證免除其入勒戒處所觀察、勒戒之餘地。是\n    被告請求撤銷原裁定，免除其進入勒戒處所觀察、勒戒云云\n    ，尚屬無據；本件被告之抗告為無理由，應予駁回。\n據上論斷，應依刑事訴訟法第412條，裁定如主文。"
  },
  "search": "臺灣高等法院刑事裁定100年度毒抗字第251號抗告人即被告陳家禛上列抗告人即被告因違反毒品危害防制條例案件(臺灣臺北地方法院檢察署100年度毒偵字第1419號)，不服臺灣臺北地方法院100年度毒聲字第428號，中華民國100年7月26日原審裁定（聲請案號：臺灣臺北地方法院檢察署100年度聲觀字第365號），提起抗告，本院裁定如下：主文抗告駁回。理由一、原裁定意旨略以：抗告人即被告陳家禎（下稱被告）基於施用第二級毒品MDMA之犯意，於民國(下同)100年4月3日凌晨2、3點在北市中正區○○○路○段84巷21號4樓之1非法施用第二級毒品MDMA一次之事實，業經被告於原審中自白不諱(詳原審卷第7頁背面筆錄)，而被告於100年4月3日為警查獲當天自願配合警方採集之尿液，經送鑑定結果，確呈MDMA陽性反應，有臺灣尖端先進生技醫藥股份有限公司出具之濫用藥物檢驗報告、臺北市政府警察局偵辦毒品案件尿液檢體委驗單、鑑定人結文等各影本一紙在卷可稽(詳偵查卷第5、6頁)，因認被告之自白與事實相符，被告有非法施用第2級毒品之事實，堪以認定。又被告前因施用毒品案件經原審法院以91年毒聲字第1466號裁定送觀察、勒戒後，因無施用毒品之傾向，於91年9月12日釋放後，並經臺灣臺北地方法院檢察署檢察官於91年9月13日以91年度毒偵字第1250號案不起訴處分在案，有本院被告前案紀錄表乙份在卷可考，因認被告於受觀察、勒戒執行完畢釋放後逾5年始再犯下本案，爰依毒危害防制條例第20條第3、1項及觀察勒戒處分執行條例第3條第1項規定，裁定將被告送勒戒處所觀察、勒戒。二、抗告意旨略以：被告為警查獲後非常懊悔，已主動至行政院衛生署指定之醫療機構請求治療，至今已無毒癮，實無再令入勒戒處所觀察、勒戒之必要；且被告目前正常上班，如進入勒戒處所觀察、勒戒，其間即無法上班，公司不可能給如此長假，公司若知道被告施用毒品，必予解職，被告即使勒戒完畢回來後也無法回到原公司上班，被告生活將陷入困窘，為此請求鈞院撤銷原裁定，免除被告進入勒戒處所等語，並提出聯合醫院松德院區100年7月11日藥物檢查檢驗報告及醫療費用收據各乙紙為證。三、按MDMA為毒品危害防制條例第2條第2項第2款所規定之第二級毒品，又按犯該條例第10條之施用第二級毒品罪者，檢察官應聲請法院裁定，令被告入勒戒處所觀察、勒戒，其期間不得逾2月，同條例第20條第1項定有明文。又毒品危害防制條例第20條第1項關於觀察、勒戒之規定，係強制規定，除合於同條例第21條第1項所定「於犯罪未發覺前，自動向行政院衛生署指定之醫療機構請求治療，醫療機構免將請求治療者送法院或檢察機關」之情形外，對於犯毒品危害防制條例第10條之罪者，檢察官均應向法院提出聲請裁定令其入勒戒處所觀察、勒戒，法院亦無不予裁定之理。四、經查，本件被告業於原審自白非法施用第2級毒品MDMA一次，並有臺灣尖端先進生技醫藥股份有限公司出具之濫用藥物檢驗報告、臺北市政府警察局偵辦毒品案件尿液檢體委驗單、鑑定人結文各影本1紙等證據在卷可稽，被告施用MDMA之事實至堪認定，原審依檢察官之聲請，裁定令被告入勒戒處所觀察、勒戒，其期間不得逾2月，核其認事用法，並無違誤。被告提起本件抗告，理由雖如前述，惟其既有施用毒品之行為，且未合於上開毒品危害防制條例第21條第1項規定之情形，即應送觀察、勒戒，並無例外，不得以被告自行就醫已無毒癮之事證免除其入勒戒處所觀察、勒戒之餘地。是被告請求撤銷原裁定，免除其進入勒戒處所觀察、勒戒云云，尚屬無據；本件被告之抗告為無理由，應予駁回。據上論斷，應依刑事訴訟法第412條，裁定如主文。中華民國100年8月18日刑事第二十五庭審判長法官黃瑞華法官陳恆寬法官陳德民以上正本證明與原本無異。不得再抗告。書記官丁淑蘭中華民國100年8月18日",
  "characters": {
    "judges": [
      "黃瑞華",
      "陳恆寬",
      "陳德民"
    ],
    "prosecutors": [

    ],
    "lawyers": [

    ],
    "clerks": [
      "丁淑蘭"
    ],
    "plaintiffs": [

    ],
    "defendants": [
      "陳家禛"
    ],
    "prosecutor_office": [

    ],
    "creditors": [

    ],
    "debtors": [

    ],
    "judicial_associate_officer": [

    ]
  },
  "adjudged_at": "2011-08-18",
  "created_at": "2016-02-12 16:42:15",
  "updated_at": "2016-02-12 16:42:15"
}