{
  "identify": "CHD-94-訴-2201-20051222-1",
  "court": {
    "name": "臺灣彰化地方法院",
    "code": "CHD"
  },
  "division": {
    "name": "刑事",
    "code": "M"
  },
  "year": 94,
  "word": "訴",
  "number": "2201",
  "jcheck": "1",
  "reason": "毒品危害防制條例",
  "content": "臺灣彰化地方法院刑事判決              94年度訴字第2201號\n公  訴  人  臺灣彰化地方法院檢察署檢察官\n被      告  甲○○\n                    （另案在臺灣彰化監獄彰化分監執行中）\n上列被告因違反毒品危害防制條例案件，經檢察官提起公訴（94\n年度毒偵字第5893號），本院合議庭裁定由受命法官獨任進行簡\n式審判程序判決如下：\n    主  文\n甲○○連續施用第一級毒品，累犯，處有期徒刑玖月。\n    事實及理由\n一犯罪事實：\n  (一)甲○○曾因搶奪案件，經本院以92年度訴字第1266號判決處\n    有期徒刑6月確定，於民國93年9月2日執行完畢。另因施用\n    毒品案件，經本院以89年度毒聲字第2845號裁定送勒戒處所\n    觀察、勒戒後，認有繼續施用毒品之傾向，由本院以89年度\n    毒聲字第3282號裁定令入戒治處所強制戒治1年，再由本院\n    以90年度毒聲字第271號裁定停止戒治，於90年2月7日釋放\n    ，所餘戒治期間付保護管束，指揮書執行完畢日期原為90年\n    7月3日，復經本院以90年度毒聲字第1560號裁定撤銷停止戒\n    治及付保護管束，再令入戒治處所強制戒治，至90年12月1\n    日執行完畢釋放，於90年12月19日由臺灣彰化地方法院檢察\n    署檢察官以90年度戒毒偵字第1813、1814、1518、1816、\n    1831號不起訴處分確定。詎甲○○於前開強制戒治執行完畢\n    釋放後5年內，仍不知悔改，復基於概括犯意，自94年5月間\n    某日起至94年10月26日下午2時10分許回溯4日內之某時止（\n    應扣除自94年10月26日上午10時55分許為警查獲後起至同日\n    下午2時10分採尿前止之不可能施用毒品期間），在彰化縣\n    員林鎮○○路某樹林內等地連續施用第1級毒品海洛因多次\n    。嗣於94年10月26日上午10時55分許，為警在該鎮○○街\n    127巷28號旁查獲。\n  (二)案經彰化縣警察局員林分局報告臺灣彰化地方法院檢察署檢\n    察官偵查起訴。\n二證據：\n  (一)被告甲○○於本院坦承不諱之自白（本院卷第24頁）。\n  (二)卷附之彰化縣衛生局煙毒尿液檢驗成績書（按海洛因於人體\n    會代謝成嗎啡，因此涉嫌施用海洛因者，係檢驗其尿液中之\n    嗎啡反應）、代號與真實姓名對照認證單（偵查卷第19、20\n    頁）。\n三按海洛因屬毒品危害防制條例第2條第2項第1款所定之第1級毒\n  品，被告施用第1級毒品海洛因多次，核其所為，均係犯該條\n  例第10條第1項之罪。被告施用毒品前後持有毒品之低度行為\n  ，應為施用毒品之高度行為所吸收，不另論罪。被告先後多次\n  施用毒品行為，時間緊接、犯罪構成要件相同，顯係基於概括\n  犯意為之，應依刑法第56條連續犯規定論以一罪，並加重其刑\n  。查被告曾因搶奪案件，經本院以92年度訴字第1266號判決處\n  有期徒刑6月確定，於93年9月2日執行完畢，此有臺灣高等法\n  院被告全國前案紀錄表可按（本院卷第8頁），其受有期徒刑\n  之執行完畢，5年內再犯有期徒刑以上之罪，為累犯，應依刑\n  法第47條遞加重其刑。爰審酌被告素行欠佳，前曾施用毒品，\n  未思悔改，缺乏禁絕毒害決心，惟所犯係戕害自身健康，尚未\n  危害他人，於本院審理中坦承犯行，態度良好及其他一切情狀\n  ，量處如主文所示之刑，以資懲儆。\n四如不服本判決，得於判決送達後10日內向本院提出上訴狀，上\n  訴於上級法院（應附繕本，勿逕向上級法院提出上訴狀）。\n據上論斷，應依刑事訴訟法第273條之1第1項、第299條第1項前\n段，毒品危害防制條例第10條第1項，刑法第11條前段、第56條\n、第47條，判決如主文。\n本案經檢察官高如應到庭執行職務。\n中    華    民    國    94    年    12    月    22    日\n                  刑事第二庭    法  官  廖政勝\n以上正本證明與原本無異。\n中    華    民    國    94    年    12    月    22    日\n                                書記官  呂雅惠\n附錄本案論罪科刑法條全文：\n毒品危害防制條例第10條\n施用第一級毒品者，處六月以上五年以下有期徒刑。\n施用第二級毒品者，處三年以下有期徒刑。\n",
  "structure": {
    "main": "甲○○連續施用第一級毒品，累犯，處有期徒刑玖月。",
    "fact": "一犯罪事實：\n  (一)甲○○曾因搶奪案件，經本院以92年度訴字第1266號判決處\n    有期徒刑6月確定，於民國93年9月2日執行完畢。另因施用\n    毒品案件，經本院以89年度毒聲字第2845號裁定送勒戒處所\n    觀察、勒戒後，認有繼續施用毒品之傾向，由本院以89年度\n    毒聲字第3282號裁定令入戒治處所強制戒治1年，再由本院\n    以90年度毒聲字第271號裁定停止戒治，於90年2月7日釋放\n    ，所餘戒治期間付保護管束，指揮書執行完畢日期原為90年\n    7月3日，復經本院以90年度毒聲字第1560號裁定撤銷停止戒\n    治及付保護管束，再令入戒治處所強制戒治，至90年12月1\n    日執行完畢釋放，於90年12月19日由臺灣彰化地方法院檢察\n    署檢察官以90年度戒毒偵字第1813、1814、1518、1816、\n    1831號不起訴處分確定。詎甲○○於前開強制戒治執行完畢\n    釋放後5年內，仍不知悔改，復基於概括犯意，自94年5月間\n    某日起至94年10月26日下午2時10分許回溯4日內之某時止（\n    應扣除自94年10月26日上午10時55分許為警查獲後起至同日\n    下午2時10分採尿前止之不可能施用毒品期間），在彰化縣\n    員林鎮○○路某樹林內等地連續施用第1級毒品海洛因多次\n    。嗣於94年10月26日上午10時55分許，為警在該鎮○○街\n    127巷28號旁查獲。\n  (二)案經彰化縣警察局員林分局報告臺灣彰化地方法院檢察署檢\n    察官偵查起訴。\n二證據：\n  (一)被告甲○○於本院坦承不諱之自白（本院卷第24頁）。\n  (二)卷附之彰化縣衛生局煙毒尿液檢驗成績書（按海洛因於人體\n    會代謝成嗎啡，因此涉嫌施用海洛因者，係檢驗其尿液中之\n    嗎啡反應）、代號與真實姓名對照認證單（偵查卷第19、20\n    頁）。\n三按海洛因屬毒品危害防制條例第2條第2項第1款所定之第1級毒\n  品，被告施用第1級毒品海洛因多次，核其所為，均係犯該條\n  例第10條第1項之罪。被告施用毒品前後持有毒品之低度行為\n  ，應為施用毒品之高度行為所吸收，不另論罪。被告先後多次\n  施用毒品行為，時間緊接、犯罪構成要件相同，顯係基於概括\n  犯意為之，應依刑法第56條連續犯規定論以一罪，並加重其刑\n  。查被告曾因搶奪案件，經本院以92年度訴字第1266號判決處\n  有期徒刑6月確定，於93年9月2日執行完畢，此有臺灣高等法\n  院被告全國前案紀錄表可按（本院卷第8頁），其受有期徒刑\n  之執行完畢，5年內再犯有期徒刑以上之罪，為累犯，應依刑\n  法第47條遞加重其刑。爰審酌被告素行欠佳，前曾施用毒品，\n  未思悔改，缺乏禁絕毒害決心，惟所犯係戕害自身健康，尚未\n  危害他人，於本院審理中坦承犯行，態度良好及其他一切情狀\n  ，量處如主文所示之刑，以資懲儆。\n四如不服本判決，得於判決送達後10日內向本院提出上訴狀，上\n  訴於上級法院（應附繕本，勿逕向上級法院提出上訴狀）。\n據上論斷，應依刑事訴訟法第273條之1第1項、第299條第1項前\n段，毒品危害防制條例第10條第1項，刑法第11條前段、第56條\n、第47條，判決如主文。\n本案經檢察官高如應到庭執行職務。",
    "reason": "一犯罪事實：\n  (一)甲○○曾因搶奪案件，經本院以92年度訴字第1266號判決處\n    有期徒刑6月確定，於民國93年9月2日執行完畢。另因施用\n    毒品案件，經本院以89年度毒聲字第2845號裁定送勒戒處所\n    觀察、勒戒後，認有繼續施用毒品之傾向，由本院以89年度\n    毒聲字第3282號裁定令入戒治處所強制戒治1年，再由本院\n    以90年度毒聲字第271號裁定停止戒治，於90年2月7日釋放\n    ，所餘戒治期間付保護管束，指揮書執行完畢日期原為90年\n    7月3日，復經本院以90年度毒聲字第1560號裁定撤銷停止戒\n    治及付保護管束，再令入戒治處所強制戒治，至90年12月1\n    日執行完畢釋放，於90年12月19日由臺灣彰化地方法院檢察\n    署檢察官以90年度戒毒偵字第1813、1814、1518、1816、\n    1831號不起訴處分確定。詎甲○○於前開強制戒治執行完畢\n    釋放後5年內，仍不知悔改，復基於概括犯意，自94年5月間\n    某日起至94年10月26日下午2時10分許回溯4日內之某時止（\n    應扣除自94年10月26日上午10時55分許為警查獲後起至同日\n    下午2時10分採尿前止之不可能施用毒品期間），在彰化縣\n    員林鎮○○路某樹林內等地連續施用第1級毒品海洛因多次\n    。嗣於94年10月26日上午10時55分許，為警在該鎮○○街\n    127巷28號旁查獲。\n  (二)案經彰化縣警察局員林分局報告臺灣彰化地方法院檢察署檢\n    察官偵查起訴。\n二證據：\n  (一)被告甲○○於本院坦承不諱之自白（本院卷第24頁）。\n  (二)卷附之彰化縣衛生局煙毒尿液檢驗成績書（按海洛因於人體\n    會代謝成嗎啡，因此涉嫌施用海洛因者，係檢驗其尿液中之\n    嗎啡反應）、代號與真實姓名對照認證單（偵查卷第19、20\n    頁）。\n三按海洛因屬毒品危害防制條例第2條第2項第1款所定之第1級毒\n  品，被告施用第1級毒品海洛因多次，核其所為，均係犯該條\n  例第10條第1項之罪。被告施用毒品前後持有毒品之低度行為\n  ，應為施用毒品之高度行為所吸收，不另論罪。被告先後多次\n  施用毒品行為，時間緊接、犯罪構成要件相同，顯係基於概括\n  犯意為之，應依刑法第56條連續犯規定論以一罪，並加重其刑\n  。查被告曾因搶奪案件，經本院以92年度訴字第1266號判決處\n  有期徒刑6月確定，於93年9月2日執行完畢，此有臺灣高等法\n  院被告全國前案紀錄表可按（本院卷第8頁），其受有期徒刑\n  之執行完畢，5年內再犯有期徒刑以上之罪，為累犯，應依刑\n  法第47條遞加重其刑。爰審酌被告素行欠佳，前曾施用毒品，\n  未思悔改，缺乏禁絕毒害決心，惟所犯係戕害自身健康，尚未\n  危害他人，於本院審理中坦承犯行，態度良好及其他一切情狀\n  ，量處如主文所示之刑，以資懲儆。\n四如不服本判決，得於判決送達後10日內向本院提出上訴狀，上\n  訴於上級法院（應附繕本，勿逕向上級法院提出上訴狀）。\n據上論斷，應依刑事訴訟法第273條之1第1項、第299條第1項前\n段，毒品危害防制條例第10條第1項，刑法第11條前段、第56條\n、第47條，判決如主文。\n本案經檢察官高如應到庭執行職務。"
  },
  "search": "臺灣彰化地方法院刑事判決94年度訴字第2201號公訴人臺灣彰化地方法院檢察署檢察官被告甲○○（另案在臺灣彰化監獄彰化分監執行中）上列被告因違反毒品危害防制條例案件，經檢察官提起公訴（94年度毒偵字第5893號），本院合議庭裁定由受命法官獨任進行簡式審判程序判決如下：主文甲○○連續施用第一級毒品，累犯，處有期徒刑玖月。事實及理由一犯罪事實：(一)甲○○曾因搶奪案件，經本院以92年度訴字第1266號判決處有期徒刑6月確定，於民國93年9月2日執行完畢。另因施用毒品案件，經本院以89年度毒聲字第2845號裁定送勒戒處所觀察、勒戒後，認有繼續施用毒品之傾向，由本院以89年度毒聲字第3282號裁定令入戒治處所強制戒治1年，再由本院以90年度毒聲字第271號裁定停止戒治，於90年2月7日釋放，所餘戒治期間付保護管束，指揮書執行完畢日期原為90年7月3日，復經本院以90年度毒聲字第1560號裁定撤銷停止戒治及付保護管束，再令入戒治處所強制戒治，至90年12月1日執行完畢釋放，於90年12月19日由臺灣彰化地方法院檢察署檢察官以90年度戒毒偵字第1813、1814、1518、1816、1831號不起訴處分確定。詎甲○○於前開強制戒治執行完畢釋放後5年內，仍不知悔改，復基於概括犯意，自94年5月間某日起至94年10月26日下午2時10分許回溯4日內之某時止（應扣除自94年10月26日上午10時55分許為警查獲後起至同日下午2時10分採尿前止之不可能施用毒品期間），在彰化縣員林鎮○○路某樹林內等地連續施用第1級毒品海洛因多次。嗣於94年10月26日上午10時55分許，為警在該鎮○○街127巷28號旁查獲。(二)案經彰化縣警察局員林分局報告臺灣彰化地方法院檢察署檢察官偵查起訴。二證據：(一)被告甲○○於本院坦承不諱之自白（本院卷第24頁）。(二)卷附之彰化縣衛生局煙毒尿液檢驗成績書（按海洛因於人體會代謝成嗎啡，因此涉嫌施用海洛因者，係檢驗其尿液中之嗎啡反應）、代號與真實姓名對照認證單（偵查卷第19、20頁）。三按海洛因屬毒品危害防制條例第2條第2項第1款所定之第1級毒品，被告施用第1級毒品海洛因多次，核其所為，均係犯該條例第10條第1項之罪。被告施用毒品前後持有毒品之低度行為，應為施用毒品之高度行為所吸收，不另論罪。被告先後多次施用毒品行為，時間緊接、犯罪構成要件相同，顯係基於概括犯意為之，應依刑法第56條連續犯規定論以一罪，並加重其刑。查被告曾因搶奪案件，經本院以92年度訴字第1266號判決處有期徒刑6月確定，於93年9月2日執行完畢，此有臺灣高等法院被告全國前案紀錄表可按（本院卷第8頁），其受有期徒刑之執行完畢，5年內再犯有期徒刑以上之罪，為累犯，應依刑法第47條遞加重其刑。爰審酌被告素行欠佳，前曾施用毒品，未思悔改，缺乏禁絕毒害決心，惟所犯係戕害自身健康，尚未危害他人，於本院審理中坦承犯行，態度良好及其他一切情狀，量處如主文所示之刑，以資懲儆。四如不服本判決，得於判決送達後10日內向本院提出上訴狀，上訴於上級法院（應附繕本，勿逕向上級法院提出上訴狀）。據上論斷，應依刑事訴訟法第273條之1第1項、第299條第1項前段，毒品危害防制條例第10條第1項，刑法第11條前段、第56條、第47條，判決如主文。本案經檢察官高如應到庭執行職務。中華民國94年12月22日刑事第二庭法官廖政勝以上正本證明與原本無異。中華民國94年12月22日書記官呂雅惠附錄本案論罪科刑法條全文：毒品危害防制條例第10條施用第一級毒品者，處六月以上五年以下有期徒刑。施用第二級毒品者，處三年以下有期徒刑。",
  "characters": {
    "judges": [
      "廖政勝"
    ],
    "prosecutors": [
      "高如應"
    ],
    "lawyers": [

    ],
    "clerks": [
      "呂雅惠"
    ],
    "plaintiffs": [

    ],
    "defendants": [
      "甲○○"
    ],
    "prosecutor_office": [
      "臺灣彰化地方法院檢察署檢察官"
    ],
    "creditors": [

    ],
    "debtors": [

    ],
    "judicial_associate_officer": [

    ]
  },
  "adjudged_at": "2005-12-22",
  "created_at": "2016-02-07 03:00:24",
  "updated_at": "2016-02-07 03:00:24"
}