{
  "identify": "KSD-94-交簡-2950-20051222-1",
  "court": {
    "name": "臺灣高雄地方法院",
    "code": "KSD"
  },
  "division": {
    "name": "刑事",
    "code": "M"
  },
  "year": 94,
  "word": "交簡",
  "number": "2950",
  "jcheck": "1",
  "reason": "過失傷害",
  "content": "臺灣高雄地方法院刑事簡易判決        94年度交簡字第2950號\n聲  請  人  臺灣高雄地方法院檢察署檢察官\n被      告  甲○○\n上列被告因過失傷害案件，經檢察官聲請以簡易判決處刑（94年\n度偵字第11850 號），本院判決如下：\n    主  文\n甲○○因過失傷害人，處拘役參拾日，如易科罰金，以參佰元折\n算壹日。\n    事實及理由\n一、本件犯罪事實及證據，除犯罪事實「左膝部挫傷合併」應更\n    正為「左膝部挫傷合併紅腫」，並補充「甲○○領有普通重\n    型機車駕駛執照」；證據部分補充「被告甲○○之駕駛執照\n    查詢資料」外，餘均引用檢察官聲請簡易判決處刑書所載，\n    如附件。\n二、核被告所為，係犯刑法第284 條第1 項前段之過失傷害罪。\n    被告於肇事後，因受傷而隨即被送往高雄市邱綜合醫院急救\n    ，承辦員警再循線至該醫院對被告製作交通事故談話紀錄表\n    等情，業經被告於警詢中自陳在卷（見偵卷第6 頁），並有\n    該交通事故談話紀錄表在卷可稽（見偵卷第23頁），則被告\n    於向員警坦承肇事之前，員警即已知悉被告係肇事者，是被\n    告尚無自首情事，附此敘明。爰審酌被告駕駛機車不知小心\n    謹慎，而與告訴人發生車禍事故，並致告訴人受有傷害，行\n    為實不足取，惟念及其於犯後坦承犯行，態度尚可，且無任\n    何犯罪經論罪科刑之紀錄，有本院被告院內索引卡紀錄表、\n    臺灣高等法院被告前案紀錄表在卷可按，素行尚非不佳，復\n    參以被告因故未能與告訴人達成和解及告訴人因本件車禍事\n    故所受之傷害等一切情狀，量處如主文所示之刑，並諭知易\n    科罰金之折算標準，以資懲儆。\n三、依刑事訴訟法第449 條第1 項前段、第454 條第2 項，刑法\n    第284 條第1 項前段、第41條第1 項前段，罰金罰鍰提高標\n    準條例第1 條前段、第2 條，逕以簡易判決處刑。\n中    華    民    國    94    年    12    月    22    日\n                  交通法庭    法  官 陳君杰\n以上正本證明與原本無異。\n如不服本判決，應於判決送達後10日內，向本院提出上訴狀。\n中    華    民    國    94    年    12    月    22    日\n                              書記官 陳昱良\n附錄本判決論罪之法條：\n刑法第284條第1項\n因過失傷害人者，處6 月以下有期徒刑、拘役或500 元以下罰金\n，致重傷者，處1 年以下有期徒刑、拘役或500 百元以下罰金。\n",
  "structure": {
    "main": "甲○○因過失傷害人，處拘役參拾日，如易科罰金，以參佰元折\n算壹日。",
    "fact": "一、本件犯罪事實及證據，除犯罪事實「左膝部挫傷合併」應更\n    正為「左膝部挫傷合併紅腫」，並補充「甲○○領有普通重\n    型機車駕駛執照」；證據部分補充「被告甲○○之駕駛執照\n    查詢資料」外，餘均引用檢察官聲請簡易判決處刑書所載，\n    如附件。\n二、核被告所為，係犯刑法第284 條第1 項前段之過失傷害罪。\n    被告於肇事後，因受傷而隨即被送往高雄市邱綜合醫院急救\n    ，承辦員警再循線至該醫院對被告製作交通事故談話紀錄表\n    等情，業經被告於警詢中自陳在卷（見偵卷第6 頁），並有\n    該交通事故談話紀錄表在卷可稽（見偵卷第23頁），則被告\n    於向員警坦承肇事之前，員警即已知悉被告係肇事者，是被\n    告尚無自首情事，附此敘明。爰審酌被告駕駛機車不知小心\n    謹慎，而與告訴人發生車禍事故，並致告訴人受有傷害，行\n    為實不足取，惟念及其於犯後坦承犯行，態度尚可，且無任\n    何犯罪經論罪科刑之紀錄，有本院被告院內索引卡紀錄表、\n    臺灣高等法院被告前案紀錄表在卷可按，素行尚非不佳，復\n    參以被告因故未能與告訴人達成和解及告訴人因本件車禍事\n    故所受之傷害等一切情狀，量處如主文所示之刑，並諭知易\n    科罰金之折算標準，以資懲儆。\n三、依刑事訴訟法第449 條第1 項前段、第454 條第2 項，刑法\n    第284 條第1 項前段、第41條第1 項前段，罰金罰鍰提高標\n    準條例第1 條前段、第2 條，逕以簡易判決處刑。",
    "reason": "一、本件犯罪事實及證據，除犯罪事實「左膝部挫傷合併」應更\n    正為「左膝部挫傷合併紅腫」，並補充「甲○○領有普通重\n    型機車駕駛執照」；證據部分補充「被告甲○○之駕駛執照\n    查詢資料」外，餘均引用檢察官聲請簡易判決處刑書所載，\n    如附件。\n二、核被告所為，係犯刑法第284 條第1 項前段之過失傷害罪。\n    被告於肇事後，因受傷而隨即被送往高雄市邱綜合醫院急救\n    ，承辦員警再循線至該醫院對被告製作交通事故談話紀錄表\n    等情，業經被告於警詢中自陳在卷（見偵卷第6 頁），並有\n    該交通事故談話紀錄表在卷可稽（見偵卷第23頁），則被告\n    於向員警坦承肇事之前，員警即已知悉被告係肇事者，是被\n    告尚無自首情事，附此敘明。爰審酌被告駕駛機車不知小心\n    謹慎，而與告訴人發生車禍事故，並致告訴人受有傷害，行\n    為實不足取，惟念及其於犯後坦承犯行，態度尚可，且無任\n    何犯罪經論罪科刑之紀錄，有本院被告院內索引卡紀錄表、\n    臺灣高等法院被告前案紀錄表在卷可按，素行尚非不佳，復\n    參以被告因故未能與告訴人達成和解及告訴人因本件車禍事\n    故所受之傷害等一切情狀，量處如主文所示之刑，並諭知易\n    科罰金之折算標準，以資懲儆。\n三、依刑事訴訟法第449 條第1 項前段、第454 條第2 項，刑法\n    第284 條第1 項前段、第41條第1 項前段，罰金罰鍰提高標\n    準條例第1 條前段、第2 條，逕以簡易判決處刑。"
  },
  "search": "臺灣高雄地方法院刑事簡易判決94年度交簡字第2950號聲請人臺灣高雄地方法院檢察署檢察官被告甲○○上列被告因過失傷害案件，經檢察官聲請以簡易判決處刑（94年度偵字第11850號），本院判決如下：主文甲○○因過失傷害人，處拘役參拾日，如易科罰金，以參佰元折算壹日。事實及理由一、本件犯罪事實及證據，除犯罪事實「左膝部挫傷合併」應更正為「左膝部挫傷合併紅腫」，並補充「甲○○領有普通重型機車駕駛執照」；證據部分補充「被告甲○○之駕駛執照查詢資料」外，餘均引用檢察官聲請簡易判決處刑書所載，如附件。二、核被告所為，係犯刑法第284條第1項前段之過失傷害罪。被告於肇事後，因受傷而隨即被送往高雄市邱綜合醫院急救，承辦員警再循線至該醫院對被告製作交通事故談話紀錄表等情，業經被告於警詢中自陳在卷（見偵卷第6頁），並有該交通事故談話紀錄表在卷可稽（見偵卷第23頁），則被告於向員警坦承肇事之前，員警即已知悉被告係肇事者，是被告尚無自首情事，附此敘明。爰審酌被告駕駛機車不知小心謹慎，而與告訴人發生車禍事故，並致告訴人受有傷害，行為實不足取，惟念及其於犯後坦承犯行，態度尚可，且無任何犯罪經論罪科刑之紀錄，有本院被告院內索引卡紀錄表、臺灣高等法院被告前案紀錄表在卷可按，素行尚非不佳，復參以被告因故未能與告訴人達成和解及告訴人因本件車禍事故所受之傷害等一切情狀，量處如主文所示之刑，並諭知易科罰金之折算標準，以資懲儆。三、依刑事訴訟法第449條第1項前段、第454條第2項，刑法第284條第1項前段、第41條第1項前段，罰金罰鍰提高標準條例第1條前段、第2條，逕以簡易判決處刑。中華民國94年12月22日交通法庭法官陳君杰以上正本證明與原本無異。如不服本判決，應於判決送達後10日內，向本院提出上訴狀。中華民國94年12月22日書記官陳昱良附錄本判決論罪之法條：刑法第284條第1項因過失傷害人者，處6月以下有期徒刑、拘役或500元以下罰金，致重傷者，處1年以下有期徒刑、拘役或500百元以下罰金。",
  "characters": {
    "judges": [
      "陳君杰"
    ],
    "prosecutors": [

    ],
    "lawyers": [

    ],
    "clerks": [
      "陳昱良"
    ],
    "plaintiffs": [

    ],
    "defendants": [
      "甲○○"
    ],
    "prosecutor_office": [
      "臺灣高雄地方法院檢察署檢察官"
    ],
    "creditors": [

    ],
    "debtors": [

    ],
    "judicial_associate_officer": [

    ]
  },
  "adjudged_at": "2005-12-22",
  "created_at": "2016-02-07 03:06:10",
  "updated_at": "2016-02-07 03:06:10"
}