{
  "identify": "PCD-100-交易-50-20110124-1",
  "court": {
    "name": "臺灣新北地方法院",
    "code": "PCD"
  },
  "division": {
    "name": "刑事",
    "code": "M"
  },
  "year": 100,
  "word": "交易",
  "number": "50",
  "jcheck": "1",
  "reason": "過失傷害",
  "content": "臺灣板橋地方法院刑事判決             100年度交易字第50號\n聲  請  人  臺灣板橋地方法院檢察署檢察官\n被      告  鄭永恩\n上列被告因過失傷害案件，經檢察官聲請簡易判決處刑（99年度\n調偵字第1836號），本院認為不宜以簡易處刑，改依通常程序判\n決如下：\n    主  文\n本件公訴不受理。\n    理  由\n一、公訴意旨略稱：被告鄭永恩於民國99年4 月26日20時30分許\n    ，駕駛車牌號碼6425-PE 號自用小客車，由臺北縣板橋市（\n    現改制為新北市板橋區，下同）亞東醫院停車場出入口左轉\n    四川路二段欲往臺北市方向行駛時，本應注意汽車轉彎前，\n    應注意來往行人，並應注意車前狀況，隨時採取必要之安全\n    措施，而依當時天候雨、夜間有照明、路面濕潤無缺陷，並\n    無不能注意之情事，詎其竟疏未注意，左轉時不慎撞及同向\n    未依規定行走行人穿越道而穿越四川路二段之行人陳淑萍，\n    致告訴人陳淑萍跌倒在地，而受有右外踝骨折之傷害。因認\n    被告涉犯刑法第284 條第1 項前段之過失傷害罪嫌等語。\n二、按告訴乃論之罪，告訴人於第一審辯論終結前得撤回其告訴\n    ，又告訴經撤回者，應諭知不受理之判決，刑事訴訟法第23\n    8條第1項、第303條第3款定有明文。\n三、本件告訴人陳淑萍告訴被告鄭永恩過失傷害案件，聲請簡易\n    判決處刑書認被告係觸犯刑法第284 條第1 項前段之罪名，\n    依同法第287 條前段之規定，須告訴乃論。茲告訴人與被告\n    於本院調解程序調解成立，並於100 年1 月20日具狀撤回其\n    告訴，有本院調解筆錄及聲請撤回刑事告訴狀各1 紙附卷可\n    稽，揆諸前開說明，爰不經言詞辯論，逕為諭知不受理之判\n    決。\n四、據上論斷，應依刑事訴訟法第452 條、第303 條第3 款、第\n    307 條，判決如主文。\n中    華    民    國    100   年    1     月    24    日\n                  交通法庭  審判長法  官  曾淑娟\n                                  法  官  陳姵君\n                                  法  官  劉凱寧\n上列正本證明與原本無異。\n如不服本判決，應於判決送達後10日內敘明上訴理由，向本院提\n出上訴狀 (應附繕本) ，上訴於臺灣高等法院。其未敘述上訴理\n由者，應於上訴期間屆滿後20日內向本院補提理由書「切勿逕送\n上級法院」。\n                                  書記官  李逸翔\n中    華    民    國   100    年    1     月    25    日",
  "structure": {
    "main": "本件公訴不受理。",
    "reason": "一、公訴意旨略稱：被告鄭永恩於民國99年4 月26日20時30分許\n    ，駕駛車牌號碼6425-PE 號自用小客車，由臺北縣板橋市（\n    現改制為新北市板橋區，下同）亞東醫院停車場出入口左轉\n    四川路二段欲往臺北市方向行駛時，本應注意汽車轉彎前，\n    應注意來往行人，並應注意車前狀況，隨時採取必要之安全\n    措施，而依當時天候雨、夜間有照明、路面濕潤無缺陷，並\n    無不能注意之情事，詎其竟疏未注意，左轉時不慎撞及同向\n    未依規定行走行人穿越道而穿越四川路二段之行人陳淑萍，\n    致告訴人陳淑萍跌倒在地，而受有右外踝骨折之傷害。因認\n    被告涉犯刑法第284 條第1 項前段之過失傷害罪嫌等語。\n二、按告訴乃論之罪，告訴人於第一審辯論終結前得撤回其告訴\n    ，又告訴經撤回者，應諭知不受理之判決，刑事訴訟法第23\n    8條第1項、第303條第3款定有明文。\n三、本件告訴人陳淑萍告訴被告鄭永恩過失傷害案件，聲請簡易\n    判決處刑書認被告係觸犯刑法第284 條第1 項前段之罪名，\n    依同法第287 條前段之規定，須告訴乃論。茲告訴人與被告\n    於本院調解程序調解成立，並於100 年1 月20日具狀撤回其\n    告訴，有本院調解筆錄及聲請撤回刑事告訴狀各1 紙附卷可\n    稽，揆諸前開說明，爰不經言詞辯論，逕為諭知不受理之判\n    決。\n四、據上論斷，應依刑事訴訟法第452 條、第303 條第3 款、第\n    307 條，判決如主文。"
  },
  "search": "臺灣板橋地方法院刑事判決100年度交易字第50號聲請人臺灣板橋地方法院檢察署檢察官被告鄭永恩上列被告因過失傷害案件，經檢察官聲請簡易判決處刑（99年度調偵字第1836號），本院認為不宜以簡易處刑，改依通常程序判決如下：主文本件公訴不受理。理由一、公訴意旨略稱：被告鄭永恩於民國99年4月26日20時30分許，駕駛車牌號碼6425-PE號自用小客車，由臺北縣板橋市（現改制為新北市板橋區，下同）亞東醫院停車場出入口左轉四川路二段欲往臺北市方向行駛時，本應注意汽車轉彎前，應注意來往行人，並應注意車前狀況，隨時採取必要之安全措施，而依當時天候雨、夜間有照明、路面濕潤無缺陷，並無不能注意之情事，詎其竟疏未注意，左轉時不慎撞及同向未依規定行走行人穿越道而穿越四川路二段之行人陳淑萍，致告訴人陳淑萍跌倒在地，而受有右外踝骨折之傷害。因認被告涉犯刑法第284條第1項前段之過失傷害罪嫌等語。二、按告訴乃論之罪，告訴人於第一審辯論終結前得撤回其告訴，又告訴經撤回者，應諭知不受理之判決，刑事訴訟法第238條第1項、第303條第3款定有明文。三、本件告訴人陳淑萍告訴被告鄭永恩過失傷害案件，聲請簡易判決處刑書認被告係觸犯刑法第284條第1項前段之罪名，依同法第287條前段之規定，須告訴乃論。茲告訴人與被告於本院調解程序調解成立，並於100年1月20日具狀撤回其告訴，有本院調解筆錄及聲請撤回刑事告訴狀各1紙附卷可稽，揆諸前開說明，爰不經言詞辯論，逕為諭知不受理之判決。四、據上論斷，應依刑事訴訟法第452條、第303條第3款、第307條，判決如主文。中華民國100年1月24日交通法庭審判長法官曾淑娟法官陳姵君法官劉凱寧上列正本證明與原本無異。如不服本判決，應於判決送達後10日內敘明上訴理由，向本院提出上訴狀(應附繕本)，上訴於臺灣高等法院。其未敘述上訴理由者，應於上訴期間屆滿後20日內向本院補提理由書「切勿逕送上級法院」。書記官李逸翔中華民國100年1月25日",
  "characters": {
    "judges": [
      "曾淑娟",
      "陳姵君",
      "劉凱寧"
    ],
    "prosecutors": [

    ],
    "lawyers": [

    ],
    "clerks": [
      "李逸翔"
    ],
    "plaintiffs": [

    ],
    "defendants": [
      "鄭永恩"
    ],
    "prosecutor_office": [
      "臺灣板橋地方法院檢察署檢察官"
    ],
    "creditors": [

    ],
    "debtors": [

    ],
    "judicial_associate_officer": [

    ]
  },
  "adjudged_at": "2011-01-24",
  "created_at": "2016-02-13 06:42:18",
  "updated_at": "2016-02-13 06:42:18"
}