{
  "identify": "PCD-99-訴-3447-20110125-1",
  "court": {
    "name": "臺灣新北地方法院",
    "code": "PCD"
  },
  "division": {
    "name": "刑事",
    "code": "M"
  },
  "year": 99,
  "word": "訴",
  "number": "3447",
  "jcheck": "1",
  "reason": "偽證",
  "content": "臺灣板橋地方法院刑事判決              99年度訴字第3447號\n公  訴  人  臺灣板橋地方法院檢察署檢察官\n被      告  林茂隆\n選任辯護人  鄭佑祥律師\n            陳佳瑤律師\n上列被告因偽證案件，經檢察官提起公訴（99年度偵第17872 號\n），被告於準備程序中就被訴事實為有罪之陳述，經告知簡式審\n判程序之旨，並聽取當事人、辯護人之意見後，本院合議庭裁定\n由受命法官獨任進行簡式審判程序，並判決如下：\n    主  文\n林茂隆證人，於執行審判職務之公署審判時，於案情有重要關係\n之事項，供前具結，而為虛偽陳述，處有期徒刑陸月，減為有期\n徒刑參月。\n    事實及理由\n一、本件犯罪事實及證據，除犯罪事實一第3 行至第4 行之「臺\n    北縣」，因改制須配合更正為「新北市」，第8 行至第9 行\n    之「供前具結而虛偽證稱」，應補充為「對於案情有重要關\n    係之事項即紀蒼華是否連續販賣第一級毒品海洛因予林茂隆\n    部分，供前具結而虛偽證稱」，以及補充被告林茂隆於本院\n    準備程序及審理中之自白為證據外，餘均引用附件即起訴書\n    之記載。\n二、核被告所為，係犯刑法第168 條之偽證罪。又犯偽證罪，於\n    所虛偽陳述之案件裁判確定前自白者，減輕或免除其刑，刑\n    法第172 條定有明文。查本件被告所虛偽證述之案件即臺灣\n    宜蘭地方法院以94年度訴字第279 號審理該案被告紀蒼華所\n    犯毒品危害防制條例案件，經該法院於94年11月8 日判決後\n    ，臺灣宜蘭地方法院檢察署檢察官及紀蒼華均不服判決提起\n    上訴，而由臺灣高等法院於95年3 月29日以94年度上訴字第\n    4076號刑事判決駁回上訴，再由紀蒼華不服判決提起上訴，\n    經最高法院於97年12月19日以97年度台上字第6642號刑事判\n    決判處原判決撤銷，發回臺灣高等法院，復由臺灣高等法院\n    於99年4 月29日以98年度上更一字第16號刑事判決判處原判\n    決撤銷，紀蒼華連續販賣第一級毒品罪成立，而紀蒼華仍不\n    服判決，再向最高法院提出上訴（尚未分案）等情，有關於\n    紀蒼華之臺灣高等法院被告前案紀錄表、本院100 年1 月24\n    日公務電話紀錄各1 份在卷可按，足見被告所為虛偽證述之\n    案件迄今尚未確定，是本件被告於該案確定前既已於偵查中\n    及本院審理中自白其偽證犯行，即應依上開規定減輕其刑。\n三、審酌被告所犯偽證犯行之犯罪情節，有害國家司法權之正確\n    行使，造成司法資源之浪費及程序之延滯，然考量被告犯後\n    終能坦承犯行，態度尚可，且其犯罪動機係純為迴護紀蒼華\n    之故，以及檢察官之求刑範圍等一切情狀，量處如主文所示\n    之刑，以資懲儆。又被告犯罪時間在96年4 月24日以前，所\n    犯為刑法第168 條之偽證罪，經核與減刑條件並無不合，爰\n    依中華民國96年罪犯減刑條例第2 條第1 項第3 款之規定，\n    減其刑期二分之一。\n四、本判決係依刑事訴訟法第310 條之2 及第454 條所製作之簡\n    化判決，依法僅需記載犯罪事實、證據名稱及應適用之法條\n    ，並得以簡略方式為之，如認定之犯罪事實、證據及應適用\n    之法條，與檢察官起訴書之記載相同者，得引用之，附此敘\n    明。\n據上論斷，應依刑事訴訟法第273 條之1 第1 項、第299 條第1\n項前段、第310 條之2 、第454 條，刑法第168 條、第172 條，\n中華民國九十六年罪犯減刑條例第2 條第1 項第3 款、第7 條，\n判決如主文。\n本案經檢察官陳映蓁到庭執行職務。\n中    華    民    國   100    年    1     月    25    日\n                  刑事第二十一庭  法  官  李俊彥\n以上正本證明與原本無異。\n如不服本判決應於收受送達後10日內向本院提出上訴書狀，並應\n敘述具體理由；其未敘述上訴理由者，應於上訴期間屆滿後20日\n內向本院補提理由書（均須按他造當事人之人數附繕本）「切勿\n逕送上級法院」\n                                  書記官  林文達\n中    華    民    國   100    年    1     月    25    日\n附錄本案論罪科刑法條全文\n刑法第168條\n於執行審判職務之公署審判時或於檢察官偵查時，證人、鑑定人\n、通譯於案情有重要關係之事項，供前或供後具結，而為虛偽陳\n述者，處7 年以下有期徒刑。",
  "structure": {
    "main": "林茂隆證人，於執行審判職務之公署審判時，於案情有重要關係\n之事項，供前具結，而為虛偽陳述，處有期徒刑陸月，減為有期\n徒刑參月。",
    "fact": "一、本件犯罪事實及證據，除犯罪事實一第3 行至第4 行之「臺\n    北縣」，因改制須配合更正為「新北市」，第8 行至第9 行\n    之「供前具結而虛偽證稱」，應補充為「對於案情有重要關\n    係之事項即紀蒼華是否連續販賣第一級毒品海洛因予林茂隆\n    部分，供前具結而虛偽證稱」，以及補充被告林茂隆於本院\n    準備程序及審理中之自白為證據外，餘均引用附件即起訴書\n    之記載。\n二、核被告所為，係犯刑法第168 條之偽證罪。又犯偽證罪，於\n    所虛偽陳述之案件裁判確定前自白者，減輕或免除其刑，刑\n    法第172 條定有明文。查本件被告所虛偽證述之案件即臺灣\n    宜蘭地方法院以94年度訴字第279 號審理該案被告紀蒼華所\n    犯毒品危害防制條例案件，經該法院於94年11月8 日判決後\n    ，臺灣宜蘭地方法院檢察署檢察官及紀蒼華均不服判決提起\n    上訴，而由臺灣高等法院於95年3 月29日以94年度上訴字第\n    4076號刑事判決駁回上訴，再由紀蒼華不服判決提起上訴，\n    經最高法院於97年12月19日以97年度台上字第6642號刑事判\n    決判處原判決撤銷，發回臺灣高等法院，復由臺灣高等法院\n    於99年4 月29日以98年度上更一字第16號刑事判決判處原判\n    決撤銷，紀蒼華連續販賣第一級毒品罪成立，而紀蒼華仍不\n    服判決，再向最高法院提出上訴（尚未分案）等情，有關於\n    紀蒼華之臺灣高等法院被告前案紀錄表、本院100 年1 月24\n    日公務電話紀錄各1 份在卷可按，足見被告所為虛偽證述之\n    案件迄今尚未確定，是本件被告於該案確定前既已於偵查中\n    及本院審理中自白其偽證犯行，即應依上開規定減輕其刑。\n三、審酌被告所犯偽證犯行之犯罪情節，有害國家司法權之正確\n    行使，造成司法資源之浪費及程序之延滯，然考量被告犯後\n    終能坦承犯行，態度尚可，且其犯罪動機係純為迴護紀蒼華\n    之故，以及檢察官之求刑範圍等一切情狀，量處如主文所示\n    之刑，以資懲儆。又被告犯罪時間在96年4 月24日以前，所\n    犯為刑法第168 條之偽證罪，經核與減刑條件並無不合，爰\n    依中華民國96年罪犯減刑條例第2 條第1 項第3 款之規定，\n    減其刑期二分之一。\n四、本判決係依刑事訴訟法第310 條之2 及第454 條所製作之簡\n    化判決，依法僅需記載犯罪事實、證據名稱及應適用之法條\n    ，並得以簡略方式為之，如認定之犯罪事實、證據及應適用\n    之法條，與檢察官起訴書之記載相同者，得引用之，附此敘\n    明。\n據上論斷，應依刑事訴訟法第273 條之1 第1 項、第299 條第1\n項前段、第310 條之2 、第454 條，刑法第168 條、第172 條，\n中華民國九十六年罪犯減刑條例第2 條第1 項第3 款、第7 條，\n判決如主文。\n本案經檢察官陳映蓁到庭執行職務。",
    "reason": "一、本件犯罪事實及證據，除犯罪事實一第3 行至第4 行之「臺\n    北縣」，因改制須配合更正為「新北市」，第8 行至第9 行\n    之「供前具結而虛偽證稱」，應補充為「對於案情有重要關\n    係之事項即紀蒼華是否連續販賣第一級毒品海洛因予林茂隆\n    部分，供前具結而虛偽證稱」，以及補充被告林茂隆於本院\n    準備程序及審理中之自白為證據外，餘均引用附件即起訴書\n    之記載。\n二、核被告所為，係犯刑法第168 條之偽證罪。又犯偽證罪，於\n    所虛偽陳述之案件裁判確定前自白者，減輕或免除其刑，刑\n    法第172 條定有明文。查本件被告所虛偽證述之案件即臺灣\n    宜蘭地方法院以94年度訴字第279 號審理該案被告紀蒼華所\n    犯毒品危害防制條例案件，經該法院於94年11月8 日判決後\n    ，臺灣宜蘭地方法院檢察署檢察官及紀蒼華均不服判決提起\n    上訴，而由臺灣高等法院於95年3 月29日以94年度上訴字第\n    4076號刑事判決駁回上訴，再由紀蒼華不服判決提起上訴，\n    經最高法院於97年12月19日以97年度台上字第6642號刑事判\n    決判處原判決撤銷，發回臺灣高等法院，復由臺灣高等法院\n    於99年4 月29日以98年度上更一字第16號刑事判決判處原判\n    決撤銷，紀蒼華連續販賣第一級毒品罪成立，而紀蒼華仍不\n    服判決，再向最高法院提出上訴（尚未分案）等情，有關於\n    紀蒼華之臺灣高等法院被告前案紀錄表、本院100 年1 月24\n    日公務電話紀錄各1 份在卷可按，足見被告所為虛偽證述之\n    案件迄今尚未確定，是本件被告於該案確定前既已於偵查中\n    及本院審理中自白其偽證犯行，即應依上開規定減輕其刑。\n三、審酌被告所犯偽證犯行之犯罪情節，有害國家司法權之正確\n    行使，造成司法資源之浪費及程序之延滯，然考量被告犯後\n    終能坦承犯行，態度尚可，且其犯罪動機係純為迴護紀蒼華\n    之故，以及檢察官之求刑範圍等一切情狀，量處如主文所示\n    之刑，以資懲儆。又被告犯罪時間在96年4 月24日以前，所\n    犯為刑法第168 條之偽證罪，經核與減刑條件並無不合，爰\n    依中華民國96年罪犯減刑條例第2 條第1 項第3 款之規定，\n    減其刑期二分之一。\n四、本判決係依刑事訴訟法第310 條之2 及第454 條所製作之簡\n    化判決，依法僅需記載犯罪事實、證據名稱及應適用之法條\n    ，並得以簡略方式為之，如認定之犯罪事實、證據及應適用\n    之法條，與檢察官起訴書之記載相同者，得引用之，附此敘\n    明。\n據上論斷，應依刑事訴訟法第273 條之1 第1 項、第299 條第1\n項前段、第310 條之2 、第454 條，刑法第168 條、第172 條，\n中華民國九十六年罪犯減刑條例第2 條第1 項第3 款、第7 條，\n判決如主文。\n本案經檢察官陳映蓁到庭執行職務。"
  },
  "search": "臺灣板橋地方法院刑事判決99年度訴字第3447號公訴人臺灣板橋地方法院檢察署檢察官被告林茂隆選任辯護人鄭佑祥律師陳佳瑤律師上列被告因偽證案件，經檢察官提起公訴（99年度偵第17872號），被告於準備程序中就被訴事實為有罪之陳述，經告知簡式審判程序之旨，並聽取當事人、辯護人之意見後，本院合議庭裁定由受命法官獨任進行簡式審判程序，並判決如下：主文林茂隆證人，於執行審判職務之公署審判時，於案情有重要關係之事項，供前具結，而為虛偽陳述，處有期徒刑陸月，減為有期徒刑參月。事實及理由一、本件犯罪事實及證據，除犯罪事實一第3行至第4行之「臺北縣」，因改制須配合更正為「新北市」，第8行至第9行之「供前具結而虛偽證稱」，應補充為「對於案情有重要關係之事項即紀蒼華是否連續販賣第一級毒品海洛因予林茂隆部分，供前具結而虛偽證稱」，以及補充被告林茂隆於本院準備程序及審理中之自白為證據外，餘均引用附件即起訴書之記載。二、核被告所為，係犯刑法第168條之偽證罪。又犯偽證罪，於所虛偽陳述之案件裁判確定前自白者，減輕或免除其刑，刑法第172條定有明文。查本件被告所虛偽證述之案件即臺灣宜蘭地方法院以94年度訴字第279號審理該案被告紀蒼華所犯毒品危害防制條例案件，經該法院於94年11月8日判決後，臺灣宜蘭地方法院檢察署檢察官及紀蒼華均不服判決提起上訴，而由臺灣高等法院於95年3月29日以94年度上訴字第4076號刑事判決駁回上訴，再由紀蒼華不服判決提起上訴，經最高法院於97年12月19日以97年度台上字第6642號刑事判決判處原判決撤銷，發回臺灣高等法院，復由臺灣高等法院於99年4月29日以98年度上更一字第16號刑事判決判處原判決撤銷，紀蒼華連續販賣第一級毒品罪成立，而紀蒼華仍不服判決，再向最高法院提出上訴（尚未分案）等情，有關於紀蒼華之臺灣高等法院被告前案紀錄表、本院100年1月24日公務電話紀錄各1份在卷可按，足見被告所為虛偽證述之案件迄今尚未確定，是本件被告於該案確定前既已於偵查中及本院審理中自白其偽證犯行，即應依上開規定減輕其刑。三、審酌被告所犯偽證犯行之犯罪情節，有害國家司法權之正確行使，造成司法資源之浪費及程序之延滯，然考量被告犯後終能坦承犯行，態度尚可，且其犯罪動機係純為迴護紀蒼華之故，以及檢察官之求刑範圍等一切情狀，量處如主文所示之刑，以資懲儆。又被告犯罪時間在96年4月24日以前，所犯為刑法第168條之偽證罪，經核與減刑條件並無不合，爰依中華民國96年罪犯減刑條例第2條第1項第3款之規定，減其刑期二分之一。四、本判決係依刑事訴訟法第310條之2及第454條所製作之簡化判決，依法僅需記載犯罪事實、證據名稱及應適用之法條，並得以簡略方式為之，如認定之犯罪事實、證據及應適用之法條，與檢察官起訴書之記載相同者，得引用之，附此敘明。據上論斷，應依刑事訴訟法第273條之1第1項、第299條第1項前段、第310條之2、第454條，刑法第168條、第172條，中華民國九十六年罪犯減刑條例第2條第1項第3款、第7條，判決如主文。本案經檢察官陳映蓁到庭執行職務。中華民國100年1月25日刑事第二十一庭法官李俊彥以上正本證明與原本無異。如不服本判決應於收受送達後10日內向本院提出上訴書狀，並應敘述具體理由；其未敘述上訴理由者，應於上訴期間屆滿後20日內向本院補提理由書（均須按他造當事人之人數附繕本）「切勿逕送上級法院」書記官林文達中華民國100年1月25日附錄本案論罪科刑法條全文刑法第168條於執行審判職務之公署審判時或於檢察官偵查時，證人、鑑定人、通譯於案情有重要關係之事項，供前或供後具結，而為虛偽陳述者，處7年以下有期徒刑。",
  "characters": {
    "judges": [
      "李俊彥"
    ],
    "prosecutors": [
      "陳映蓁"
    ],
    "lawyers": [
      "鄭佑祥",
      "陳佳瑤"
    ],
    "clerks": [
      "林文達"
    ],
    "plaintiffs": [

    ],
    "defendants": [
      "林茂隆"
    ],
    "prosecutor_office": [
      "臺灣板橋地方法院檢察署檢察官"
    ],
    "creditors": [

    ],
    "debtors": [

    ],
    "judicial_associate_officer": [

    ]
  },
  "adjudged_at": "2011-01-25",
  "created_at": "2016-02-13 06:39:18",
  "updated_at": "2016-02-13 06:39:18"
}