{
  "identify": "TYD-99-訴-885-20110125-1",
  "court": {
    "name": "臺灣桃園地方法院",
    "code": "TYD"
  },
  "division": {
    "name": "刑事",
    "code": "M"
  },
  "year": 99,
  "word": "訴",
  "number": "885",
  "jcheck": "1",
  "reason": "毒品危害防制條例等",
  "content": "臺灣桃園地方法院刑事裁定               99年度訴字第885號\n公  訴  人  臺灣桃園地方法院檢察署檢察官\n被      告  羅盛銘\n選任辯護人  呂福元律師\n            魏釷沛律師\n被      告  黃彥博\n選任辯護人  葉志飛律師\n            黃柏承律師\n被      告  余聲慶\n選任辯護人  黃柏彰律師\n被      告  張家郡\n選任辯護人  連世昌律師\n上列被告因毒品危害防制條例等案件，經檢察官提起公訴，本院\n裁定如下：\n    主  文\n羅盛銘、黃彥博、余聲慶、張家郡均自民國壹佰年壹月貳拾玖日\n起延長羈押貳個月，並均自即日起解除禁止接見通信。\n    理  由\n一、被告羅盛銘、黃彥博、余聲慶、張家郡因違反毒品危害防制\n    條例等案件，經本院訊問後，認被告羅盛銘涉犯刑法第231\n    條第1 項意圖使女子與他人性交而媒介以營利罪、第231 條\n    之1 第1 項圖利強制使人為性交或猥褻罪、第305 條恐嚇罪\n    、第304 條強制罪、第277 條第1 條傷害罪；被告黃彥博涉\n    犯刑法第231 條第1 項意圖使女子與他人性交而媒介以營利\n    罪、第231 條之1 第1 項圖利強制使人為性交或猥褻罪、第\n    305 條恐嚇罪；被告余聲慶涉犯刑法第231 條第1 項意圖使\n    女子與他人性交而媒介以營利罪、第277 條第1 項傷害罪、\n    毒品危害防制條例第4 條第3 項、第8 條第3 項販賣、轉讓\n    第三級毒品罪；被告張家郡涉犯刑法第231 條第1 項意圖使\n    女子與他人性交而媒介以營利罪、第277 條第1 項傷害罪、\n    毒品危害防制條例第4 條第3 項、第8 條第3 項販賣、轉讓\n    第三級毒品罪，業據「星語酒店」、「一哥酒店」之酒店小\n    姐及購買、受讓毒品之人與傷害犯行之被害人證述明確，並\n    有扣案之本票、借據及監聽譯文等件在卷可稽，犯罪嫌疑均\n    屬重大，又被告羅盛銘、黃彥博所涉犯圖利強制使人為性交\n    或猥褻罪及被告余聲慶、張家郡所涉犯販賣第三級毒品罪，\n    均屬最輕本刑5 年以上有期徒刑之罪，其刑責既重，則逃匿\n    飾責之動機當益屬強烈，又被告羅盛銘、黃彥博、余聲慶、\n    張家郡否認犯行，所供核與渠所涉犯各該犯嫌之證人證述情\n    節相互迥異，有事實足認有勾串證人之虞，非予羈押顯難進\n    行追訴、審判，而有羈押之必要，於民國99年10月29日起執\n    行羈押，並均禁止接見通信。茲經本院訊問後，認被告羅盛\n    銘、黃彥博、余聲慶、張家郡除有勾串共犯及證人之虞此項\n    要件外，其餘羈押原因依然存在，且仍有繼續羈押之必要，\n    著自民國100 年1 月29日起延長羈押2 個月。另檢、辯雙方\n    於本院準備程序中所聲請傳喚之證人，於偵查階段均經訊問\n    ，相關事證當已鞏固，而無串證之虞，爰均自即日起解除禁\n    止接見通信。\n二、依刑事訴訟法第108 條第1 項裁定如主文。\n中    華    民    國    100    年    1    月    25    日\n                  刑事第十一庭審判長  法  官  蔡榮澤\n                                      法  官  汪曉君\n                                      法  官  林蕙芳\n以上正本證明與原本無異。\n如不服本裁定，應於裁定送達後5 日內向本院提出抗告狀。\n                                      書記官  莊凱男\n中    華    民    國   100    年    1     月    28    日",
  "structure": {
    "main": "羅盛銘、黃彥博、余聲慶、張家郡均自民國壹佰年壹月貳拾玖日\n起延長羈押貳個月，並均自即日起解除禁止接見通信。",
    "reason": "一、被告羅盛銘、黃彥博、余聲慶、張家郡因違反毒品危害防制\n    條例等案件，經本院訊問後，認被告羅盛銘涉犯刑法第231\n    條第1 項意圖使女子與他人性交而媒介以營利罪、第231 條\n    之1 第1 項圖利強制使人為性交或猥褻罪、第305 條恐嚇罪\n    、第304 條強制罪、第277 條第1 條傷害罪；被告黃彥博涉\n    犯刑法第231 條第1 項意圖使女子與他人性交而媒介以營利\n    罪、第231 條之1 第1 項圖利強制使人為性交或猥褻罪、第\n    305 條恐嚇罪；被告余聲慶涉犯刑法第231 條第1 項意圖使\n    女子與他人性交而媒介以營利罪、第277 條第1 項傷害罪、\n    毒品危害防制條例第4 條第3 項、第8 條第3 項販賣、轉讓\n    第三級毒品罪；被告張家郡涉犯刑法第231 條第1 項意圖使\n    女子與他人性交而媒介以營利罪、第277 條第1 項傷害罪、\n    毒品危害防制條例第4 條第3 項、第8 條第3 項販賣、轉讓\n    第三級毒品罪，業據「星語酒店」、「一哥酒店」之酒店小\n    姐及購買、受讓毒品之人與傷害犯行之被害人證述明確，並\n    有扣案之本票、借據及監聽譯文等件在卷可稽，犯罪嫌疑均\n    屬重大，又被告羅盛銘、黃彥博所涉犯圖利強制使人為性交\n    或猥褻罪及被告余聲慶、張家郡所涉犯販賣第三級毒品罪，\n    均屬最輕本刑5 年以上有期徒刑之罪，其刑責既重，則逃匿\n    飾責之動機當益屬強烈，又被告羅盛銘、黃彥博、余聲慶、\n    張家郡否認犯行，所供核與渠所涉犯各該犯嫌之證人證述情\n    節相互迥異，有事實足認有勾串證人之虞，非予羈押顯難進\n    行追訴、審判，而有羈押之必要，於民國99年10月29日起執\n    行羈押，並均禁止接見通信。茲經本院訊問後，認被告羅盛\n    銘、黃彥博、余聲慶、張家郡除有勾串共犯及證人之虞此項\n    要件外，其餘羈押原因依然存在，且仍有繼續羈押之必要，\n    著自民國100 年1 月29日起延長羈押2 個月。另檢、辯雙方\n    於本院準備程序中所聲請傳喚之證人，於偵查階段均經訊問\n    ，相關事證當已鞏固，而無串證之虞，爰均自即日起解除禁\n    止接見通信。\n二、依刑事訴訟法第108 條第1 項裁定如主文。"
  },
  "search": "臺灣桃園地方法院刑事裁定99年度訴字第885號公訴人臺灣桃園地方法院檢察署檢察官被告羅盛銘選任辯護人呂福元律師魏釷沛律師被告黃彥博選任辯護人葉志飛律師黃柏承律師被告余聲慶選任辯護人黃柏彰律師被告張家郡選任辯護人連世昌律師上列被告因毒品危害防制條例等案件，經檢察官提起公訴，本院裁定如下：主文羅盛銘、黃彥博、余聲慶、張家郡均自民國壹佰年壹月貳拾玖日起延長羈押貳個月，並均自即日起解除禁止接見通信。理由一、被告羅盛銘、黃彥博、余聲慶、張家郡因違反毒品危害防制條例等案件，經本院訊問後，認被告羅盛銘涉犯刑法第231條第1項意圖使女子與他人性交而媒介以營利罪、第231條之1第1項圖利強制使人為性交或猥褻罪、第305條恐嚇罪、第304條強制罪、第277條第1條傷害罪；被告黃彥博涉犯刑法第231條第1項意圖使女子與他人性交而媒介以營利罪、第231條之1第1項圖利強制使人為性交或猥褻罪、第305條恐嚇罪；被告余聲慶涉犯刑法第231條第1項意圖使女子與他人性交而媒介以營利罪、第277條第1項傷害罪、毒品危害防制條例第4條第3項、第8條第3項販賣、轉讓第三級毒品罪；被告張家郡涉犯刑法第231條第1項意圖使女子與他人性交而媒介以營利罪、第277條第1項傷害罪、毒品危害防制條例第4條第3項、第8條第3項販賣、轉讓第三級毒品罪，業據「星語酒店」、「一哥酒店」之酒店小姐及購買、受讓毒品之人與傷害犯行之被害人證述明確，並有扣案之本票、借據及監聽譯文等件在卷可稽，犯罪嫌疑均屬重大，又被告羅盛銘、黃彥博所涉犯圖利強制使人為性交或猥褻罪及被告余聲慶、張家郡所涉犯販賣第三級毒品罪，均屬最輕本刑5年以上有期徒刑之罪，其刑責既重，則逃匿飾責之動機當益屬強烈，又被告羅盛銘、黃彥博、余聲慶、張家郡否認犯行，所供核與渠所涉犯各該犯嫌之證人證述情節相互迥異，有事實足認有勾串證人之虞，非予羈押顯難進行追訴、審判，而有羈押之必要，於民國99年10月29日起執行羈押，並均禁止接見通信。茲經本院訊問後，認被告羅盛銘、黃彥博、余聲慶、張家郡除有勾串共犯及證人之虞此項要件外，其餘羈押原因依然存在，且仍有繼續羈押之必要，著自民國100年1月29日起延長羈押2個月。另檢、辯雙方於本院準備程序中所聲請傳喚之證人，於偵查階段均經訊問，相關事證當已鞏固，而無串證之虞，爰均自即日起解除禁止接見通信。二、依刑事訴訟法第108條第1項裁定如主文。中華民國100年1月25日刑事第十一庭審判長法官蔡榮澤法官汪曉君法官林蕙芳以上正本證明與原本無異。如不服本裁定，應於裁定送達後5日內向本院提出抗告狀。書記官莊凱男中華民國100年1月28日",
  "characters": {
    "judges": [
      "蔡榮澤",
      "汪曉君",
      "林蕙芳"
    ],
    "prosecutors": [

    ],
    "lawyers": [
      "呂福元",
      "魏釷沛",
      "葉志飛",
      "黃柏承",
      "黃柏彰",
      "連世昌"
    ],
    "clerks": [
      "莊凱男"
    ],
    "plaintiffs": [

    ],
    "defendants": [
      "羅盛銘",
      "黃彥博",
      "余聲慶",
      "張家郡"
    ],
    "prosecutor_office": [
      "臺灣桃園地方法院檢察署檢察官"
    ],
    "creditors": [

    ],
    "debtors": [

    ],
    "judicial_associate_officer": [

    ]
  },
  "adjudged_at": "2011-01-25",
  "created_at": "2016-02-13 06:43:55",
  "updated_at": "2016-02-13 06:43:55"
}