{
  "identify": "PCD-94-訴-1310-20050810-1",
  "court": {
    "name": "臺灣新北地方法院",
    "code": "PCD"
  },
  "division": {
    "name": "刑事",
    "code": "M"
  },
  "year": 94,
  "word": "訴",
  "number": "1310",
  "jcheck": "1",
  "reason": "大陸人民條例等",
  "content": "臺灣板橋地方法院刑事裁定              94年度訴字第1310號\n公  訴  人  臺灣板橋地方法院檢察署檢察官\n被      告  子○○\n                      村\n被      告  甲○○\n被      告  卯○○\n被      告  丙○\n                      司\n被      告  壬○○\n                      間\n被      告  丁○\n                      號\n被      告  丑○○\n被      告  癸○○\n被      告  乙○○\n被      告  戊○○\n被      告  寅○○\n                      坎下\n被      告  己○○\n被      告  庚○○\n                      隊2之4.\n被      告  辛○○\n上列被告等人因違反台灣地區與大陸地區人民關係條例大陸人民\n條例等案件，前經辯論終結，茲因尚有應行調查之處，應再開本\n件辯論，特此裁定。\n中    華    民    國    94    年    8     月    10    日\n                  刑事第五庭    法  官  許映鈞\n以上正本證明與原本無異。\n不得抗告。\n                                書記官  呂苗澂\n中    華    民    國    94    年    8     月    10    日\n",
  "structure": {
  },
  "search": "臺灣板橋地方法院刑事裁定94年度訴字第1310號公訴人臺灣板橋地方法院檢察署檢察官被告子○○村被告甲○○被告卯○○被告丙○司被告壬○○間被告丁○號被告丑○○被告癸○○被告乙○○被告戊○○被告寅○○坎下被告己○○被告庚○○隊2之4.被告辛○○上列被告等人因違反台灣地區與大陸地區人民關係條例大陸人民條例等案件，前經辯論終結，茲因尚有應行調查之處，應再開本件辯論，特此裁定。中華民國94年8月10日刑事第五庭法官許映鈞以上正本證明與原本無異。不得抗告。書記官呂苗澂中華民國94年8月10日",
  "characters": {
    "judges": [
      "許映鈞"
    ],
    "prosecutors": [

    ],
    "lawyers": [

    ],
    "clerks": [
      "呂苗澂"
    ],
    "plaintiffs": [

    ],
    "defendants": [
      "子○○",
      "甲○○",
      "被      告  卯○○",
      "被      告  丙○",
      "壬○○",
      "丁○",
      "丑○○",
      "被      告  癸○○",
      "被      告  乙○○",
      "被      告  戊○○",
      "被      告  寅○○",
      "己○○",
      "被      告  庚○○",
      "辛○○"
    ],
    "prosecutor_office": [
      "臺灣板橋地方法院檢察署檢察官"
    ],
    "creditors": [

    ],
    "debtors": [

    ],
    "judicial_associate_officer": [

    ]
  },
  "adjudged_at": "2005-08-10",
  "created_at": "2016-02-06 21:38:57",
  "updated_at": "2016-02-06 21:38:57"
}