{
  "identify": "TPH-94-訴易-22-20050810-1",
  "court": {
    "name": "臺灣高等法院",
    "code": "TPH"
  },
  "division": {
    "name": "民事",
    "code": "V"
  },
  "year": 94,
  "word": "訴易",
  "number": "22",
  "jcheck": "1",
  "reason": "侵權行為損害賠償",
  "content": "臺灣高等法院民事判決                  94年度訴易字第22號\n原      告  乙○○\n被      告  甲○○\n上列當事人間因侵權行為損害賠償事件，本院於94年7月27日言\n詞辯論終結，判決如下：\n    主  文\n被告應給付原告新臺幣271,118元，及自94年5月27日起，至清償\n日止，按年息5%計算之利息。\n原告其餘之訴駁回。\n訴訟費用由被告負擔3分之1，餘由原告負擔。\n    事  實  及 理 由\n一、原告主張：被告甲○○於民國92年7月25日上午10時10分許\n    ，騎乘車牌號碼ＡＶＬ─519號重型機車，沿臺北市華江橋\n    機車引道由西向東行駛，途經該引道下坡左彎道處，適伊騎\n    乘車牌號碼ＢＡＥ─900號重型機車經過該處，被告本應注\n    意機車在行經該彎道時不得超車之規定，而依當時情形又無\n    不能注意之情事，卻仍加速超越伊車，於超車時不慎機車右\n    照後鏡擦撞伊所騎乘重型機車左照後鏡，且被告機車右後車\n    輪擦撞伊機車左前車輪，致二車均倒地，伊因此受有右肱骨\n    幹粉碎性骨折及橈神經損傷等傷害。刑事部分，業經伊訴由\n    檢察官提起公訴，且經刑事庭判刑在案。爰依侵權行為之法\n    律關係請求損害賠償，並聲明：被告應給付原告新臺幣（下\n    同）706, 607元，及自附帶民事訴訟訴狀繕本送達被告翌日\n    起至清償日止，按年息5%之利息。\n二、被告則以：是原告撞到伊，並非伊撞到原告，醫藥費用支出\n    ，有證明伊就相信，原告主張半年無法工作，損失192, 000\n    元，太誇張，請求慰藉金50萬元，不合理。並聲明：原告之\n    訴駁回。\n三、兩造不爭之事實：\n    兩造騎機車於上開時地發生擦撞，兩車均倒地，原告造成前\n    開之傷害。\n四、得心證之理由：\n  (一)本件原告主張：被告於92年7月25日上午10時10分許，騎乘\n    車牌號碼ＡＶＬ─519號重型機車，沿臺北市華江橋機車引\n    道由西向東行駛，途經該引道下坡左彎道處，本應注意機車\n    在行經彎道時不得超車之規定，而依當時情形又無不能注意\n    之情事，卻仍加速欲超越在前之原告所騎機車，不慎機車右\n    照後鏡擦撞原告所騎乘重型機車左照後鏡，且被告機車右後\n    車輪擦撞原告之機車左前車輪，致二車均倒地，原告因此受\n    有右肱骨幹粉碎性骨折及橈神經損傷等傷害。上開事實經本\n    院94年度交上訴字第50號刑事判決認定，且判處被告罪刑在\n    案。復經原告提出診斷書附於刑事卷，於本件另提出台北市\n    立中興醫院醫療費用收據14紙、及上開刑事判決為據。\n  (二)被告雖抗辯是原告撞到伊，並非伊撞到原告云云，但查：\n  (1)被告與原告於前揭時地發生車禍，致原告受有上開傷害，除\n    據被告自認外，復據原告於偵查、原審及本院刑事庭到庭指\n    訴明確（見偵查卷第5、6、28頁、原審92年交訴字第139 號\n    卷第42頁反面、本院94交上訴字第50號卷33至36頁），且證\n    人江俊毅、許吉利對於當時發生車禍過程亦於原審刑事庭到\n    庭結證屬實（見原審刑事卷第64、66、67頁），並有道路交\n    通事故現場圖、道路交通事故補充資料表、交通事故談話紀\n    錄表、道路交通事故調查報告表(一)、(二)現場照片、臺北市立\n    中興醫院92年8月5日甲種、乙種診斷證明書等件附刑事卷可\n    證（見偵查卷第7至11、13至16、17至20、45頁）。\n  (2)被告騎乘機車行經臺北市華江橋機車引道下坡左轉彎道時，\n    其欲自後加速超越前車時，在轉彎行進中，機車手把向右偏\n    駛，致右照後鏡確有碰撞原告機車左照後鏡之情事，除據原\n    告於偵查中指訴：「於九十二年七月二十五日十時十分我騎\n    乘車號ＢＡＥ─900號重機車行經臺北市萬華區華江橋機車\n    引道（板橋往臺北方向）時，突遭車號ＡＶＬ─519號重機\n    車加速自我左方撞擊我左車後照鏡，致我機車倒地，我亦跌\n    落地下」（見偵查卷第5頁正反面頁），於原審刑事庭審理\n    時亦陳述：「我從右側超車，但我並無往被告方向靠過去，\n    我過被告車時，被告往我這邊靠撞到我，所以我就倒在那邊\n    」等語（見原審刑事卷第45頁反面）明確外，核與證人江俊\n    毅於原審刑事庭審理時證述：「我看到兩輛機車，在華江橋\n    往台北，機車引道有一個有弧度那邊，我騎乘引道右邊，有\n    兩台機車，在我前面，我騎乘在被害人（靠右邊）那台機車\n    的後方，被告的車在告訴人的左邊，在轉彎前，被告（在我\n    左前方，近被害人左方）的機車比告訴人的機車前面一點，\n    在轉彎處兩車幾乎平行，我在後面，我看到被告有將頭往右\n    看一看右邊的被害人機車，接著被告的機車往右靠一點，結\n    果被告機車後輪撞到告訴人機車的前輪，兩台機車倒下來」\n    等語相符（見原審刑事卷第66、67頁）。又事發當時，被告\n    之左方、前方均無車輛，業據被告、證人江俊毅分別於原審\n    刑事庭審理時、警詢中供述明確（見原審刑事卷第45頁、偵\n    查卷第13頁交通事故談話紀錄表）。按依道路交通管理規則\n    第101條第1款規定汽（機）車在行經彎道時不得超車，被告\n    在超越原告機車時，因疏未注意，其機車向右偏駛，致機車\n    右後照鏡不慎勾及原告所騎乘機車左後照鏡，兩車發生擦撞\n    ，致原告人車倒地受傷，其有過失甚明。被告雖辯稱係原告\n    撞到被告，並非被告撞到原告云云，惟未舉證以實其說，委\n    無可採信。而原告之傷勢與被告過失間有相當因果關係存在\n    。被告不法侵害原告之身體，既經認定，自應負賠償責任。\n五、茲所應審酌者，為原告所得請求被告賠償之金額，爰分述如\n    下：\n  (一)醫療費部分：\n    查原告因本件車禍受傷，支出醫療費用共計71,118元，有其\n    提出之台北市立中興醫院醫療費用收據132紙為據，核均屬\n    醫療必需，自應予准許。\n  (二)工作損害金部分：\n    原告主張受傷後不能工作，每月薪資32,000元，半年無法工\n    作，請求被告賠償此期間內之損失云云，惟原告所提出之薪\n    資轉帳存摺影本，係94年3月至7月之轉帳記錄，而本件車禍\n    係發生於92年7月間，原告主張係於車禍後6個月間無法工作\n    ，原告未能提出車禍前後之工作薪資所得，以證明原告於該\n    期間確有工作損失，則其請求工作損害金 192,000元自無從\n    准許。\n  (三)精神慰藉金部分：\n    查原告受傷多處，肉體、精神確受極大痛若，本院斟酌原告\n    之實際受傷並造成輕度肢障，被告甫服完兵役，及兩造之身\n    分、地位、經濟能力等，認為原告請求500,000元，尚嫌過\n    高，應予核減為200,000元，逾此數額之請求，為無理由。\n六、從而，原告基於侵權行為之損害賠償請求權，請求被告賠償\n    271,118元，及自附帶民事訴訟訴狀繕本送達被告翌日即 94\n    年 5月27日起，至清償日止，依法定利率計算之遲延利息部\n    分，洵屬正當，應予准許。逾此部分所為之請求，為無理由\n    ，應予駁回。\n七、結論：本件原告之訴，為一部有理由，一部無理由，依民事\n    訴訟法第79條判決如主文。\n中    華    民    國    94    年    8     月    10     日\n                  民事第二庭審判長法  官 吳謙仁\n                                  法  官 蘇瑞華\n                                  法  官 魏大喨\n正本係照原本作成。\n不得上訴。\n中    華    民    國    94    年    8     月    11    日\n                                  書記官 高澄純\n",
  "structure": {
    "fact": "一、原告主張：被告甲○○於民國92年7月25日上午10時10分許\n    ，騎乘車牌號碼ＡＶＬ─519號重型機車，沿臺北市華江橋\n    機車引道由西向東行駛，途經該引道下坡左彎道處，適伊騎\n    乘車牌號碼ＢＡＥ─900號重型機車經過該處，被告本應注\n    意機車在行經該彎道時不得超車之規定，而依當時情形又無\n    不能注意之情事，卻仍加速超越伊車，於超車時不慎機車右\n    照後鏡擦撞伊所騎乘重型機車左照後鏡，且被告機車右後車\n    輪擦撞伊機車左前車輪，致二車均倒地，伊因此受有右肱骨\n    幹粉碎性骨折及橈神經損傷等傷害。刑事部分，業經伊訴由\n    檢察官提起公訴，且經刑事庭判刑在案。爰依侵權行為之法\n    律關係請求損害賠償，並聲明：被告應給付原告新臺幣（下\n    同）706, 607元，及自附帶民事訴訟訴狀繕本送達被告翌日\n    起至清償日止，按年息5%之利息。\n二、被告則以：是原告撞到伊，並非伊撞到原告，醫藥費用支出\n    ，有證明伊就相信，原告主張半年無法工作，損失192, 000\n    元，太誇張，請求慰藉金50萬元，不合理。並聲明：原告之\n    訴駁回。\n三、兩造不爭之事實：\n    兩造騎機車於上開時地發生擦撞，兩車均倒地，原告造成前\n    開之傷害。\n四、得心證之理由：\n  (一)本件原告主張：被告於92年7月25日上午10時10分許，騎乘\n    車牌號碼ＡＶＬ─519號重型機車，沿臺北市華江橋機車引\n    道由西向東行駛，途經該引道下坡左彎道處，本應注意機車\n    在行經彎道時不得超車之規定，而依當時情形又無不能注意\n    之情事，卻仍加速欲超越在前之原告所騎機車，不慎機車右\n    照後鏡擦撞原告所騎乘重型機車左照後鏡，且被告機車右後\n    車輪擦撞原告之機車左前車輪，致二車均倒地，原告因此受\n    有右肱骨幹粉碎性骨折及橈神經損傷等傷害。上開事實經本\n    院94年度交上訴字第50號刑事判決認定，且判處被告罪刑在\n    案。復經原告提出診斷書附於刑事卷，於本件另提出台北市\n    立中興醫院醫療費用收據14紙、及上開刑事判決為據。\n  (二)被告雖抗辯是原告撞到伊，並非伊撞到原告云云，但查：\n  (1)被告與原告於前揭時地發生車禍，致原告受有上開傷害，除\n    據被告自認外，復據原告於偵查、原審及本院刑事庭到庭指\n    訴明確（見偵查卷第5、6、28頁、原審92年交訴字第139 號\n    卷第42頁反面、本院94交上訴字第50號卷33至36頁），且證\n    人江俊毅、許吉利對於當時發生車禍過程亦於原審刑事庭到\n    庭結證屬實（見原審刑事卷第64、66、67頁），並有道路交\n    通事故現場圖、道路交通事故補充資料表、交通事故談話紀\n    錄表、道路交通事故調查報告表(一)、(二)現場照片、臺北市立\n    中興醫院92年8月5日甲種、乙種診斷證明書等件附刑事卷可\n    證（見偵查卷第7至11、13至16、17至20、45頁）。\n  (2)被告騎乘機車行經臺北市華江橋機車引道下坡左轉彎道時，\n    其欲自後加速超越前車時，在轉彎行進中，機車手把向右偏\n    駛，致右照後鏡確有碰撞原告機車左照後鏡之情事，除據原\n    告於偵查中指訴：「於九十二年七月二十五日十時十分我騎\n    乘車號ＢＡＥ─900號重機車行經臺北市萬華區華江橋機車\n    引道（板橋往臺北方向）時，突遭車號ＡＶＬ─519號重機\n    車加速自我左方撞擊我左車後照鏡，致我機車倒地，我亦跌\n    落地下」（見偵查卷第5頁正反面頁），於原審刑事庭審理\n    時亦陳述：「我從右側超車，但我並無往被告方向靠過去，\n    我過被告車時，被告往我這邊靠撞到我，所以我就倒在那邊\n    」等語（見原審刑事卷第45頁反面）明確外，核與證人江俊\n    毅於原審刑事庭審理時證述：「我看到兩輛機車，在華江橋\n    往台北，機車引道有一個有弧度那邊，我騎乘引道右邊，有\n    兩台機車，在我前面，我騎乘在被害人（靠右邊）那台機車\n    的後方，被告的車在告訴人的左邊，在轉彎前，被告（在我\n    左前方，近被害人左方）的機車比告訴人的機車前面一點，\n    在轉彎處兩車幾乎平行，我在後面，我看到被告有將頭往右\n    看一看右邊的被害人機車，接著被告的機車往右靠一點，結\n    果被告機車後輪撞到告訴人機車的前輪，兩台機車倒下來」\n    等語相符（見原審刑事卷第66、67頁）。又事發當時，被告\n    之左方、前方均無車輛，業據被告、證人江俊毅分別於原審\n    刑事庭審理時、警詢中供述明確（見原審刑事卷第45頁、偵\n    查卷第13頁交通事故談話紀錄表）。按依道路交通管理規則\n    第101條第1款規定汽（機）車在行經彎道時不得超車，被告\n    在超越原告機車時，因疏未注意，其機車向右偏駛，致機車\n    右後照鏡不慎勾及原告所騎乘機車左後照鏡，兩車發生擦撞\n    ，致原告人車倒地受傷，其有過失甚明。被告雖辯稱係原告\n    撞到被告，並非被告撞到原告云云，惟未舉證以實其說，委\n    無可採信。而原告之傷勢與被告過失間有相當因果關係存在\n    。被告不法侵害原告之身體，既經認定，自應負賠償責任。\n五、茲所應審酌者，為原告所得請求被告賠償之金額，爰分述如\n    下：\n  (一)醫療費部分：\n    查原告因本件車禍受傷，支出醫療費用共計71,118元，有其\n    提出之台北市立中興醫院醫療費用收據132紙為據，核均屬\n    醫療必需，自應予准許。\n  (二)工作損害金部分：\n    原告主張受傷後不能工作，每月薪資32,000元，半年無法工\n    作，請求被告賠償此期間內之損失云云，惟原告所提出之薪\n    資轉帳存摺影本，係94年3月至7月之轉帳記錄，而本件車禍\n    係發生於92年7月間，原告主張係於車禍後6個月間無法工作\n    ，原告未能提出車禍前後之工作薪資所得，以證明原告於該\n    期間確有工作損失，則其請求工作損害金 192,000元自無從\n    准許。\n  (三)精神慰藉金部分：\n    查原告受傷多處，肉體、精神確受極大痛若，本院斟酌原告\n    之實際受傷並造成輕度肢障，被告甫服完兵役，及兩造之身\n    分、地位、經濟能力等，認為原告請求500,000元，尚嫌過\n    高，應予核減為200,000元，逾此數額之請求，為無理由。\n六、從而，原告基於侵權行為之損害賠償請求權，請求被告賠償\n    271,118元，及自附帶民事訴訟訴狀繕本送達被告翌日即 94\n    年 5月27日起，至清償日止，依法定利率計算之遲延利息部\n    分，洵屬正當，應予准許。逾此部分所為之請求，為無理由\n    ，應予駁回。\n七、結論：本件原告之訴，為一部有理由，一部無理由，依民事\n    訴訟法第79條判決如主文。"
  },
  "search": "臺灣高等法院民事判決94年度訴易字第22號原告乙○○被告甲○○上列當事人間因侵權行為損害賠償事件，本院於94年7月27日言詞辯論終結，判決如下：主文被告應給付原告新臺幣271,118元，及自94年5月27日起，至清償日止，按年息5%計算之利息。原告其餘之訴駁回。訴訟費用由被告負擔3分之1，餘由原告負擔。事實及理由一、原告主張：被告甲○○於民國92年7月25日上午10時10分許，騎乘車牌號碼ＡＶＬ─519號重型機車，沿臺北市華江橋機車引道由西向東行駛，途經該引道下坡左彎道處，適伊騎乘車牌號碼ＢＡＥ─900號重型機車經過該處，被告本應注意機車在行經該彎道時不得超車之規定，而依當時情形又無不能注意之情事，卻仍加速超越伊車，於超車時不慎機車右照後鏡擦撞伊所騎乘重型機車左照後鏡，且被告機車右後車輪擦撞伊機車左前車輪，致二車均倒地，伊因此受有右肱骨幹粉碎性骨折及橈神經損傷等傷害。刑事部分，業經伊訴由檢察官提起公訴，且經刑事庭判刑在案。爰依侵權行為之法律關係請求損害賠償，並聲明：被告應給付原告新臺幣（下同）706,607元，及自附帶民事訴訟訴狀繕本送達被告翌日起至清償日止，按年息5%之利息。二、被告則以：是原告撞到伊，並非伊撞到原告，醫藥費用支出，有證明伊就相信，原告主張半年無法工作，損失192,000元，太誇張，請求慰藉金50萬元，不合理。並聲明：原告之訴駁回。三、兩造不爭之事實：兩造騎機車於上開時地發生擦撞，兩車均倒地，原告造成前開之傷害。四、得心證之理由：(一)本件原告主張：被告於92年7月25日上午10時10分許，騎乘車牌號碼ＡＶＬ─519號重型機車，沿臺北市華江橋機車引道由西向東行駛，途經該引道下坡左彎道處，本應注意機車在行經彎道時不得超車之規定，而依當時情形又無不能注意之情事，卻仍加速欲超越在前之原告所騎機車，不慎機車右照後鏡擦撞原告所騎乘重型機車左照後鏡，且被告機車右後車輪擦撞原告之機車左前車輪，致二車均倒地，原告因此受有右肱骨幹粉碎性骨折及橈神經損傷等傷害。上開事實經本院94年度交上訴字第50號刑事判決認定，且判處被告罪刑在案。復經原告提出診斷書附於刑事卷，於本件另提出台北市立中興醫院醫療費用收據14紙、及上開刑事判決為據。(二)被告雖抗辯是原告撞到伊，並非伊撞到原告云云，但查：(1)被告與原告於前揭時地發生車禍，致原告受有上開傷害，除據被告自認外，復據原告於偵查、原審及本院刑事庭到庭指訴明確（見偵查卷第5、6、28頁、原審92年交訴字第139號卷第42頁反面、本院94交上訴字第50號卷33至36頁），且證人江俊毅、許吉利對於當時發生車禍過程亦於原審刑事庭到庭結證屬實（見原審刑事卷第64、66、67頁），並有道路交通事故現場圖、道路交通事故補充資料表、交通事故談話紀錄表、道路交通事故調查報告表(一)、(二)現場照片、臺北市立中興醫院92年8月5日甲種、乙種診斷證明書等件附刑事卷可證（見偵查卷第7至11、13至16、17至20、45頁）。(2)被告騎乘機車行經臺北市華江橋機車引道下坡左轉彎道時，其欲自後加速超越前車時，在轉彎行進中，機車手把向右偏駛，致右照後鏡確有碰撞原告機車左照後鏡之情事，除據原告於偵查中指訴：「於九十二年七月二十五日十時十分我騎乘車號ＢＡＥ─900號重機車行經臺北市萬華區華江橋機車引道（板橋往臺北方向）時，突遭車號ＡＶＬ─519號重機車加速自我左方撞擊我左車後照鏡，致我機車倒地，我亦跌落地下」（見偵查卷第5頁正反面頁），於原審刑事庭審理時亦陳述：「我從右側超車，但我並無往被告方向靠過去，我過被告車時，被告往我這邊靠撞到我，所以我就倒在那邊」等語（見原審刑事卷第45頁反面）明確外，核與證人江俊毅於原審刑事庭審理時證述：「我看到兩輛機車，在華江橋往台北，機車引道有一個有弧度那邊，我騎乘引道右邊，有兩台機車，在我前面，我騎乘在被害人（靠右邊）那台機車的後方，被告的車在告訴人的左邊，在轉彎前，被告（在我左前方，近被害人左方）的機車比告訴人的機車前面一點，在轉彎處兩車幾乎平行，我在後面，我看到被告有將頭往右看一看右邊的被害人機車，接著被告的機車往右靠一點，結果被告機車後輪撞到告訴人機車的前輪，兩台機車倒下來」等語相符（見原審刑事卷第66、67頁）。又事發當時，被告之左方、前方均無車輛，業據被告、證人江俊毅分別於原審刑事庭審理時、警詢中供述明確（見原審刑事卷第45頁、偵查卷第13頁交通事故談話紀錄表）。按依道路交通管理規則第101條第1款規定汽（機）車在行經彎道時不得超車，被告在超越原告機車時，因疏未注意，其機車向右偏駛，致機車右後照鏡不慎勾及原告所騎乘機車左後照鏡，兩車發生擦撞，致原告人車倒地受傷，其有過失甚明。被告雖辯稱係原告撞到被告，並非被告撞到原告云云，惟未舉證以實其說，委無可採信。而原告之傷勢與被告過失間有相當因果關係存在。被告不法侵害原告之身體，既經認定，自應負賠償責任。五、茲所應審酌者，為原告所得請求被告賠償之金額，爰分述如下：(一)醫療費部分：查原告因本件車禍受傷，支出醫療費用共計71,118元，有其提出之台北市立中興醫院醫療費用收據132紙為據，核均屬醫療必需，自應予准許。(二)工作損害金部分：原告主張受傷後不能工作，每月薪資32,000元，半年無法工作，請求被告賠償此期間內之損失云云，惟原告所提出之薪資轉帳存摺影本，係94年3月至7月之轉帳記錄，而本件車禍係發生於92年7月間，原告主張係於車禍後6個月間無法工作，原告未能提出車禍前後之工作薪資所得，以證明原告於該期間確有工作損失，則其請求工作損害金192,000元自無從准許。(三)精神慰藉金部分：查原告受傷多處，肉體、精神確受極大痛若，本院斟酌原告之實際受傷並造成輕度肢障，被告甫服完兵役，及兩造之身分、地位、經濟能力等，認為原告請求500,000元，尚嫌過高，應予核減為200,000元，逾此數額之請求，為無理由。六、從而，原告基於侵權行為之損害賠償請求權，請求被告賠償271,118元，及自附帶民事訴訟訴狀繕本送達被告翌日即94年5月27日起，至清償日止，依法定利率計算之遲延利息部分，洵屬正當，應予准許。逾此部分所為之請求，為無理由，應予駁回。七、結論：本件原告之訴，為一部有理由，一部無理由，依民事訴訟法第79條判決如主文。中華民國94年8月10日民事第二庭審判長法官吳謙仁法官蘇瑞華法官魏大喨正本係照原本作成。不得上訴。中華民國94年8月11日書記官高澄純",
  "characters": {
    "judges": [
      "吳謙仁",
      "蘇瑞華",
      "魏大喨"
    ],
    "prosecutors": [

    ],
    "lawyers": [

    ],
    "clerks": [
      "高澄純"
    ],
    "plaintiffs": [
      "乙○○"
    ],
    "defendants": [
      "甲○○"
    ],
    "prosecutor_office": [

    ],
    "creditors": [

    ],
    "debtors": [

    ],
    "judicial_associate_officer": [

    ]
  },
  "adjudged_at": "2005-08-10",
  "created_at": "2016-02-06 21:37:12",
  "updated_at": "2016-02-06 21:37:12"
}