{
  "identify": "KSD-93-簡-5743-20041126-1",
  "court": {
    "name": "臺灣高雄地方法院",
    "code": "KSD"
  },
  "division": {
    "name": "刑事",
    "code": "M"
  },
  "year": 93,
  "word": "簡",
  "number": "5743",
  "jcheck": "1",
  "reason": "竊盜",
  "content": "臺灣高雄地方法院刑事簡易判決                      九十三年簡字第五七四三號\n    聲  請  人  臺灣高雄地方法院檢察署檢察官\n    被      告  甲○○\n右列被告因竊盜案件，經檢察官聲請以簡易判決處刑（臺灣高雄地方法院檢察署九十\n三年度速偵字第一九四二號），本院判決如左：\n    主  文\n甲○○竊盜，處拘役貳拾日，如易科罰金，以佰元折算壹日。緩刑貳年。\n    事實及理由\n一、本件犯罪事實引用檢察官聲請簡易判決處刑書之記載（如附件）。\n二、前開犯罪事實，有１、被告於警訊及偵查中之自白。２、被害人之代理人乙○○\n    之指訴。３、贓物領據乙份及贓物照片二張附卷可資佐證，足證被告上開自白確\n    與事實相符，洵堪採為論罪科刑之依據。因此，本件罪證明確，被告犯行堪以認\n    定。\n三、核被告甲○○所為，係犯刑法第三百二十條第一項竊盜罪。爰審酌被告犯本罪之\n    動機、目的、手段，及其生活狀況、品行、智識程度及該衣褲（合計價值新台幣\n    二千二百四十四元）已經由被害人領回，損害已降低等一切情狀，量處如主文所\n    示之刑，並諭知易科罰金之折算標準，以示儆懲。末查，被告前未曾受有期徒刑\n    以上刑之宣告，有臺灣高等法院被告全國前紀錄表一紙附卷可稽，本院審酌被告\n    深具悔改之意，偶因一時貪念失虞致罹刑章，經此警、偵訊教訓，當知所警惕，\n    信無再犯之鋘，本院認所宣告之刑，以暫不執行為適當，爰併予宣告緩刑二年，\n    以啟自新。\n四、依刑事訴訟法第四百四十九條第一項前段、第三項、第四百五十四條第二項，刑\n    法第三百二十條第一項、第四十一條第一項前段、第七十四條第一款，罰金罰鍰\n    提高標準條例第一條前段、第二條，逕以簡易判決處刑如主文。\n五、如不服本判決，得自收受送達之日起十日內，向本院提起上訴。\n中      華      民      國    九十三  年    十一      月    二十六      日\n                                臺灣高雄地方法院高雄簡易庭\n                                    法  官  施添寶\n右正本證明與原本無異。\n如不服本判決，應於判決送達後十日內，向本院提出上訴狀。\n                                    書記官  陳威志\n中    華    民    國      九十三      年      十一      月    二十九  日\n附錄法條：\n刑法第三百二十條第一項\n意圖為自己或第三人不法之所有，而竊取他人之動產者，為竊盜罪，處五年以下有期\n徒刑、拘役或五百元以下罰金。\n",
  "structure": {
    "main": "甲○○竊盜，處拘役貳拾日，如易科罰金，以佰元折算壹日。緩刑貳年。",
    "fact": "一、本件犯罪事實引用檢察官聲請簡易判決處刑書之記載（如附件）。\n二、前開犯罪事實，有１、被告於警訊及偵查中之自白。２、被害人之代理人乙○○\n    之指訴。３、贓物領據乙份及贓物照片二張附卷可資佐證，足證被告上開自白確\n    與事實相符，洵堪採為論罪科刑之依據。因此，本件罪證明確，被告犯行堪以認\n    定。\n三、核被告甲○○所為，係犯刑法第三百二十條第一項竊盜罪。爰審酌被告犯本罪之\n    動機、目的、手段，及其生活狀況、品行、智識程度及該衣褲（合計價值新台幣\n    二千二百四十四元）已經由被害人領回，損害已降低等一切情狀，量處如主文所\n    示之刑，並諭知易科罰金之折算標準，以示儆懲。末查，被告前未曾受有期徒刑\n    以上刑之宣告，有臺灣高等法院被告全國前紀錄表一紙附卷可稽，本院審酌被告\n    深具悔改之意，偶因一時貪念失虞致罹刑章，經此警、偵訊教訓，當知所警惕，\n    信無再犯之鋘，本院認所宣告之刑，以暫不執行為適當，爰併予宣告緩刑二年，\n    以啟自新。\n四、依刑事訴訟法第四百四十九條第一項前段、第三項、第四百五十四條第二項，刑\n    法第三百二十條第一項、第四十一條第一項前段、第七十四條第一款，罰金罰鍰\n    提高標準條例第一條前段、第二條，逕以簡易判決處刑如主文。\n五、如不服本判決，得自收受送達之日起十日內，向本院提起上訴。",
    "reason": "一、本件犯罪事實引用檢察官聲請簡易判決處刑書之記載（如附件）。\n二、前開犯罪事實，有１、被告於警訊及偵查中之自白。２、被害人之代理人乙○○\n    之指訴。３、贓物領據乙份及贓物照片二張附卷可資佐證，足證被告上開自白確\n    與事實相符，洵堪採為論罪科刑之依據。因此，本件罪證明確，被告犯行堪以認\n    定。\n三、核被告甲○○所為，係犯刑法第三百二十條第一項竊盜罪。爰審酌被告犯本罪之\n    動機、目的、手段，及其生活狀況、品行、智識程度及該衣褲（合計價值新台幣\n    二千二百四十四元）已經由被害人領回，損害已降低等一切情狀，量處如主文所\n    示之刑，並諭知易科罰金之折算標準，以示儆懲。末查，被告前未曾受有期徒刑\n    以上刑之宣告，有臺灣高等法院被告全國前紀錄表一紙附卷可稽，本院審酌被告\n    深具悔改之意，偶因一時貪念失虞致罹刑章，經此警、偵訊教訓，當知所警惕，\n    信無再犯之鋘，本院認所宣告之刑，以暫不執行為適當，爰併予宣告緩刑二年，\n    以啟自新。\n四、依刑事訴訟法第四百四十九條第一項前段、第三項、第四百五十四條第二項，刑\n    法第三百二十條第一項、第四十一條第一項前段、第七十四條第一款，罰金罰鍰\n    提高標準條例第一條前段、第二條，逕以簡易判決處刑如主文。\n五、如不服本判決，得自收受送達之日起十日內，向本院提起上訴。"
  },
  "search": "臺灣高雄地方法院刑事簡易判決九十三年簡字第五七四三號聲請人臺灣高雄地方法院檢察署檢察官被告甲○○右列被告因竊盜案件，經檢察官聲請以簡易判決處刑（臺灣高雄地方法院檢察署九十三年度速偵字第一九四二號），本院判決如左：主文甲○○竊盜，處拘役貳拾日，如易科罰金，以佰元折算壹日。緩刑貳年。事實及理由一、本件犯罪事實引用檢察官聲請簡易判決處刑書之記載（如附件）。二、前開犯罪事實，有１、被告於警訊及偵查中之自白。２、被害人之代理人乙○○之指訴。３、贓物領據乙份及贓物照片二張附卷可資佐證，足證被告上開自白確與事實相符，洵堪採為論罪科刑之依據。因此，本件罪證明確，被告犯行堪以認定。三、核被告甲○○所為，係犯刑法第三百二十條第一項竊盜罪。爰審酌被告犯本罪之動機、目的、手段，及其生活狀況、品行、智識程度及該衣褲（合計價值新台幣二千二百四十四元）已經由被害人領回，損害已降低等一切情狀，量處如主文所示之刑，並諭知易科罰金之折算標準，以示儆懲。末查，被告前未曾受有期徒刑以上刑之宣告，有臺灣高等法院被告全國前紀錄表一紙附卷可稽，本院審酌被告深具悔改之意，偶因一時貪念失虞致罹刑章，經此警、偵訊教訓，當知所警惕，信無再犯之鋘，本院認所宣告之刑，以暫不執行為適當，爰併予宣告緩刑二年，以啟自新。四、依刑事訴訟法第四百四十九條第一項前段、第三項、第四百五十四條第二項，刑法第三百二十條第一項、第四十一條第一項前段、第七十四條第一款，罰金罰鍰提高標準條例第一條前段、第二條，逕以簡易判決處刑如主文。五、如不服本判決，得自收受送達之日起十日內，向本院提起上訴。中華民國九十三年十一月二十六日臺灣高雄地方法院高雄簡易庭法官施添寶右正本證明與原本無異。如不服本判決，應於判決送達後十日內，向本院提出上訴狀。書記官陳威志中華民國九十三年十一月二十九日附錄法條：刑法第三百二十條第一項意圖為自己或第三人不法之所有，而竊取他人之動產者，為竊盜罪，處五年以下有期徒刑、拘役或五百元以下罰金。",
  "characters": {
    "judges": [
      "施添寶"
    ],
    "prosecutors": [

    ],
    "lawyers": [

    ],
    "clerks": [
      "陳威志"
    ],
    "plaintiffs": [

    ],
    "defendants": [
      "甲○○",
      "右列被告因竊盜案件，經檢察官聲請以簡易判決處刑（臺灣高雄地方法院檢察署九十",
      "三年度速偵字第一九四二號），本院判決如左："
    ],
    "prosecutor_office": [
      "臺灣高雄地方法院檢察署檢察官"
    ],
    "creditors": [

    ],
    "debtors": [

    ],
    "judicial_associate_officer": [

    ]
  },
  "adjudged_at": "2004-11-26",
  "created_at": "2016-02-06 03:30:19",
  "updated_at": "2016-02-06 03:30:19"
}