{
  "identify": "KSD-94-訴-2835-20051020-1",
  "court": {
    "name": "臺灣高雄地方法院",
    "code": "KSD"
  },
  "division": {
    "name": "刑事",
    "code": "M"
  },
  "year": 94,
  "word": "訴",
  "number": "2835",
  "jcheck": "1",
  "reason": "毒品危害防制條例",
  "content": "臺灣高雄地方法院刑事判決              94年度訴字第2835號\n公  訴  人  臺灣高雄地方法院檢察署檢察官\n被      告  甲○○\n                    4號\n上列被告因毒品危害防制條例案件，經檢察官提起公訴（94年度\n毒偵字第5218號），本院判決如下：\n    主  文\n本件公訴不受理。\n    理  由\n一、公訴意旨略以：被告甲○○前因施用毒品案件，經送觀察、\n    勒戒後，認無繼續施用毒品之傾向，於民國87年6 月10日釋\n    放，並經本署檢察官於民國87年8 月28日為不起訴處分確定\n    。詎其於觀察、勒戒執行完畢後5 年內，復自87年5 月間起\n    ，至87年12月1 日下午11點多止，連續在高雄市○○區○○\n    路35 5號欣加坡汽車旅館231 號房間等處，施用第二級毒品\n    甲基安非他命；另於88年6 月28日及同年7 月1 日上午5 時\n    ，連續在高雄縣大寮鄉○○村○○街128 號9 樓房間內等處\n    ，施用第一級毒品海洛因，嗣分別為警於87年12月2 日凌晨\n    0 時30分許，在高雄市○○區○○路355 號欣加坡汽車旅館\n    231 號房間內，88年7 月1 日18時50分，在高雄縣大寮鄉○\n    ○村○○街128 號9 樓查獲，因認被告涉犯毒品危害防制條\n    例第10條第1 、2 項之連續施用第一級、第二級毒品罪嫌。\n二、按被告死亡者，法院應諭知不受理之判決；不受理之判決，\n    得不經言詞辯論為之，刑事訴訟法第303 條第5 款、第307\n    條分別定有明文。查本件被告業於91年8 月4 日死亡，有法\n    務部戶役政連結作業系統個人基本資料查詢單1 紙在卷可稽\n    ，並經本院向高雄縣鳳山市第二戶政事務所函查屬實，有該\n    事務所函附被告死亡登記申請書、高雄醫學大學附設中和紀\n    念醫院所開立被告死亡證明書各1 紙可佐，揆諸前開說明，\n    爰不經言詞辯論，逕為諭知不受理之判決。\n三、應依刑事訴訟法第303 條第5 款、第307 條，判決如主文。\n中    華    民    國    94    年    10    月    20    日\n                  鳳山刑事第2 庭   審判長法  官  邱明弘\n                                         法  官  廖建瑜\n                                         法  官  李嘉益\n以上正本證明與原本無異。\n如不服本判決，應於收受送達後10日內向本院提出上訴書狀。\n中    華    民    國    94    年    10    月    20    日\n                                         書記官  呂怜勳\n",
  "structure": {
    "main": "本件公訴不受理。",
    "reason": "一、公訴意旨略以：被告甲○○前因施用毒品案件，經送觀察、\n    勒戒後，認無繼續施用毒品之傾向，於民國87年6 月10日釋\n    放，並經本署檢察官於民國87年8 月28日為不起訴處分確定\n    。詎其於觀察、勒戒執行完畢後5 年內，復自87年5 月間起\n    ，至87年12月1 日下午11點多止，連續在高雄市○○區○○\n    路35 5號欣加坡汽車旅館231 號房間等處，施用第二級毒品\n    甲基安非他命；另於88年6 月28日及同年7 月1 日上午5 時\n    ，連續在高雄縣大寮鄉○○村○○街128 號9 樓房間內等處\n    ，施用第一級毒品海洛因，嗣分別為警於87年12月2 日凌晨\n    0 時30分許，在高雄市○○區○○路355 號欣加坡汽車旅館\n    231 號房間內，88年7 月1 日18時50分，在高雄縣大寮鄉○\n    ○村○○街128 號9 樓查獲，因認被告涉犯毒品危害防制條\n    例第10條第1 、2 項之連續施用第一級、第二級毒品罪嫌。\n二、按被告死亡者，法院應諭知不受理之判決；不受理之判決，\n    得不經言詞辯論為之，刑事訴訟法第303 條第5 款、第307\n    條分別定有明文。查本件被告業於91年8 月4 日死亡，有法\n    務部戶役政連結作業系統個人基本資料查詢單1 紙在卷可稽\n    ，並經本院向高雄縣鳳山市第二戶政事務所函查屬實，有該\n    事務所函附被告死亡登記申請書、高雄醫學大學附設中和紀\n    念醫院所開立被告死亡證明書各1 紙可佐，揆諸前開說明，\n    爰不經言詞辯論，逕為諭知不受理之判決。\n三、應依刑事訴訟法第303 條第5 款、第307 條，判決如主文。"
  },
  "search": "臺灣高雄地方法院刑事判決94年度訴字第2835號公訴人臺灣高雄地方法院檢察署檢察官被告甲○○4號上列被告因毒品危害防制條例案件，經檢察官提起公訴（94年度毒偵字第5218號），本院判決如下：主文本件公訴不受理。理由一、公訴意旨略以：被告甲○○前因施用毒品案件，經送觀察、勒戒後，認無繼續施用毒品之傾向，於民國87年6月10日釋放，並經本署檢察官於民國87年8月28日為不起訴處分確定。詎其於觀察、勒戒執行完畢後5年內，復自87年5月間起，至87年12月1日下午11點多止，連續在高雄市○○區○○路355號欣加坡汽車旅館231號房間等處，施用第二級毒品甲基安非他命；另於88年6月28日及同年7月1日上午5時，連續在高雄縣大寮鄉○○村○○街128號9樓房間內等處，施用第一級毒品海洛因，嗣分別為警於87年12月2日凌晨0時30分許，在高雄市○○區○○路355號欣加坡汽車旅館231號房間內，88年7月1日18時50分，在高雄縣大寮鄉○○村○○街128號9樓查獲，因認被告涉犯毒品危害防制條例第10條第1、2項之連續施用第一級、第二級毒品罪嫌。二、按被告死亡者，法院應諭知不受理之判決；不受理之判決，得不經言詞辯論為之，刑事訴訟法第303條第5款、第307條分別定有明文。查本件被告業於91年8月4日死亡，有法務部戶役政連結作業系統個人基本資料查詢單1紙在卷可稽，並經本院向高雄縣鳳山市第二戶政事務所函查屬實，有該事務所函附被告死亡登記申請書、高雄醫學大學附設中和紀念醫院所開立被告死亡證明書各1紙可佐，揆諸前開說明，爰不經言詞辯論，逕為諭知不受理之判決。三、應依刑事訴訟法第303條第5款、第307條，判決如主文。中華民國94年10月20日鳳山刑事第2庭審判長法官邱明弘法官廖建瑜法官李嘉益以上正本證明與原本無異。如不服本判決，應於收受送達後10日內向本院提出上訴書狀。中華民國94年10月20日書記官呂怜勳",
  "characters": {
    "judges": [
      "邱明弘",
      "廖建瑜",
      "李嘉益"
    ],
    "prosecutors": [

    ],
    "lawyers": [

    ],
    "clerks": [
      "呂怜勳"
    ],
    "plaintiffs": [

    ],
    "defendants": [
      "甲○○"
    ],
    "prosecutor_office": [
      "臺灣高雄地方法院檢察署檢察官"
    ],
    "creditors": [

    ],
    "debtors": [

    ],
    "judicial_associate_officer": [

    ]
  },
  "adjudged_at": "2005-10-20",
  "created_at": "2016-02-07 11:07:18",
  "updated_at": "2016-02-07 11:07:18"
}