{
  "identify": "SLD-91-交簡-139-20020114-1",
  "court": {
    "name": "臺灣士林地方法院",
    "code": "SLD"
  },
  "division": {
    "name": "刑事",
    "code": "M"
  },
  "year": 91,
  "word": "交簡",
  "number": "139",
  "jcheck": "1",
  "reason": "公共危險",
  "content": "臺灣士林地方法院刑事簡易判決                    九十一年度交簡字第一三九號\n    聲  請  人  臺灣士林地方法院檢察署檢察官\n    被      告  甲○○\n右列被告因公共危險案件，經檢察官聲請以簡易判決處刑（九十年度偵字第五七七六\n號），本院內湖簡易庭（九十年度湖交簡字第六七二號）改依通常程序審判（九十年\n度交易字第二００號），經訊問被告後被告自白犯罪，本院逕依簡易判決處刑：\n    主  文\n甲○○服用酒類，不能安全駕駛動力交通工具而駕駛，處罰金伍仟元，如易服勞役以\n佰元折算壹日。\n    事實及理由\n一本件犯罪事實及證據除引用檢察官聲請簡易判決處刑書之記載外，並補充：\n  被告於本院調查中自白犯罪，自承因飲酒後不能安全駕駛汽車而駕駛，致追撞行駛\n  在前之車號Ｈ六─三一三號營業小客車之事實。\n二依刑事訴訟法第四百五十二條、第四百四十九條第一項前段、第二項、第四百五十\n  四條第二項，刑法第一百八十五條之三、第四十二條第二項，罰金罰鍰提高標準條\n  例第二條，逕以簡易判決處如主文所示之刑。\n三如不服本件判決，自判決送達之日起十日內，得向本院提起上訴。\n中      華      民      國      九十一      年      一    月    十四    日\n                                臺灣士林地方法院刑事第二庭\n                                    法  官  王梅英\n右正本證明與原本無異。\n                                    書記官  廖春玉\n中      華      民      國      九十一      年      一    月    十六    日\n附錄本判決論罪科刑依據之法條：\n中華民國刑法第一百八十五條之三：\n  服用毒品、麻醉藥品、酒類或其他相類之物，不能安全駕駛動力交通工具而駕駛者\n  ，處一年以下有期徒刑、拘役或三萬元以下罰金。\n",
  "structure": {
    "main": "甲○○服用酒類，不能安全駕駛動力交通工具而駕駛，處罰金伍仟元，如易服勞役以\n佰元折算壹日。",
    "fact": "一本件犯罪事實及證據除引用檢察官聲請簡易判決處刑書之記載外，並補充：\n  被告於本院調查中自白犯罪，自承因飲酒後不能安全駕駛汽車而駕駛，致追撞行駛\n  在前之車號Ｈ六─三一三號營業小客車之事實。\n二依刑事訴訟法第四百五十二條、第四百四十九條第一項前段、第二項、第四百五十\n  四條第二項，刑法第一百八十五條之三、第四十二條第二項，罰金罰鍰提高標準條\n  例第二條，逕以簡易判決處如主文所示之刑。\n三如不服本件判決，自判決送達之日起十日內，得向本院提起上訴。",
    "reason": "一本件犯罪事實及證據除引用檢察官聲請簡易判決處刑書之記載外，並補充：\n  被告於本院調查中自白犯罪，自承因飲酒後不能安全駕駛汽車而駕駛，致追撞行駛\n  在前之車號Ｈ六─三一三號營業小客車之事實。\n二依刑事訴訟法第四百五十二條、第四百四十九條第一項前段、第二項、第四百五十\n  四條第二項，刑法第一百八十五條之三、第四十二條第二項，罰金罰鍰提高標準條\n  例第二條，逕以簡易判決處如主文所示之刑。\n三如不服本件判決，自判決送達之日起十日內，得向本院提起上訴。"
  },
  "search": "臺灣士林地方法院刑事簡易判決九十一年度交簡字第一三九號聲請人臺灣士林地方法院檢察署檢察官被告甲○○右列被告因公共危險案件，經檢察官聲請以簡易判決處刑（九十年度偵字第五七七六號），本院內湖簡易庭（九十年度湖交簡字第六七二號）改依通常程序審判（九十年度交易字第二００號），經訊問被告後被告自白犯罪，本院逕依簡易判決處刑：主文甲○○服用酒類，不能安全駕駛動力交通工具而駕駛，處罰金伍仟元，如易服勞役以佰元折算壹日。事實及理由一本件犯罪事實及證據除引用檢察官聲請簡易判決處刑書之記載外，並補充：被告於本院調查中自白犯罪，自承因飲酒後不能安全駕駛汽車而駕駛，致追撞行駛在前之車號Ｈ六─三一三號營業小客車之事實。二依刑事訴訟法第四百五十二條、第四百四十九條第一項前段、第二項、第四百五十四條第二項，刑法第一百八十五條之三、第四十二條第二項，罰金罰鍰提高標準條例第二條，逕以簡易判決處如主文所示之刑。三如不服本件判決，自判決送達之日起十日內，得向本院提起上訴。中華民國九十一年一月十四日臺灣士林地方法院刑事第二庭法官王梅英右正本證明與原本無異。書記官廖春玉中華民國九十一年一月十六日附錄本判決論罪科刑依據之法條：中華民國刑法第一百八十五條之三：服用毒品、麻醉藥品、酒類或其他相類之物，不能安全駕駛動力交通工具而駕駛者，處一年以下有期徒刑、拘役或三萬元以下罰金。",
  "characters": {
    "judges": [
      "王梅英"
    ],
    "prosecutors": [

    ],
    "lawyers": [

    ],
    "clerks": [
      "廖春玉"
    ],
    "plaintiffs": [

    ],
    "defendants": [
      "甲○○",
      "右列被告因公共危險案件，經檢察官聲請以簡易判決處刑（九十年度偵字第五七七六",
      "號），本院內湖簡易庭（九十年度湖交簡字第六七二號）改依通常程序審判（九十年",
      "度交易字第二００號），經訊問被告後被告自白犯罪，本院逕依簡易判決處刑："
    ],
    "prosecutor_office": [
      "臺灣士林地方法院檢察署檢察官"
    ],
    "creditors": [

    ],
    "debtors": [

    ],
    "judicial_associate_officer": [

    ]
  },
  "adjudged_at": "2002-01-14",
  "created_at": "2016-02-05 03:04:03",
  "updated_at": "2016-02-05 03:04:03"
}