{
  "identify": "TPD-91-簡-131-20020114-1",
  "court": {
    "name": "臺灣臺北地方法院",
    "code": "TPD"
  },
  "division": {
    "name": "刑事",
    "code": "M"
  },
  "year": 91,
  "word": "簡",
  "number": "131",
  "jcheck": "1",
  "reason": "台灣地區與大陸地區人民關係條例",
  "content": "臺灣臺北地方法院刑事簡易判決                      九十一年度簡字第一三一號\n    聲  請  人  臺灣臺北地方法院檢察署檢察官\n    被      告  甲○○\n右列被告因違反台灣地區與大陸地區人民關係條例案件，經檢察官聲請以簡易判決處\n刑（九十年度偵字第二三八九四號），本院判決如左：\n    主  文\n甲○○連續違反不得僱用大陸地區人民在臺灣地區從事未經許可之工作之規定，科罰\n金新台幣陸萬元，如易服勞役，以新台幣玖佰元即銀元參佰元折算壹日。\n    事實及理由\n一、本件犯罪事實、證據及應適用之法條，均引用檢察官聲請簡易判決處刑書之記載\n    （如附件），並補充記載如下，被告甲○○基於概括犯意，先於民國九十年六月\n    間某日，未經許可僱用大陸地區人民甯小美在其經營之「統帥自助餐店」從事打\n    雜之工作，復於同年七月一日僱用大陸地區人民王君飛從事洗菜、打掃之工作。\n    其先後多次犯行，時間緊密，犯罪構成要件相同，顯係基於概括犯意為之，為連\n    續犯，依刑法第五十六條規定，以一罪論，並加重其刑。\n二、爰審酌被告經警當場查獲前揭大陸地區人民後仍矢口否認犯罪，辯以不知其二人\n    為大陸地區人民，及其係因所營自助餐店極需人手幫忙始非法僱用大陸地區人民\n    之犯罪動機、目的及其犯罪之手段、犯罪所生之危害等一切情狀，量處如主文所\n    示之刑，並諭知易服勞役之折算標準。\n三、依刑事訴訟法第四百四十九條第一項前段、第三項、第四百五十四條第二項，台\n    灣地區與大陸地區人民關係條例第八十三條第一項，刑法第十一條前段、第五十\n    六條、第四十二條第二項、罰金罰鍰提高標準條例第二條、現行法規所定貨幣單\n    位折算新台幣條例第二條，逕以簡易判決處刑如主文。\n如不服本判決，得於判決送達之日起十日內，向本院提出上訴狀，上訴於本院第二審\n合議庭。\n中      華      民      國    九十一    年      一      月     十四     日\n                                      臺灣臺北地方法院刑事第九庭\n                                          法  官  沈君玲\n右正本證明與原本無異。\n                                          書記官  蔡梅蓮\n中      華      民      國    九十一    年      一      月     十七     日\n附錄本案論罪科刑法條全文：\n台灣地區與大陸地區人民關係條例第八十三條第一項\n違反第十五條第四款或第五款規定者，處二年以下有期徒刑、拘役或科或併科新台幣\n三十萬元以下罰金。\n意圖營利而違反第十五條第五款規定者，處三年以下有期徒刑、拘役或科或併科新台\n幣六十萬元以下罰金。\n法人之代表人、法人或自然人之代理人、受僱人或其他從業人員，因執行業務犯前二\n項之罪者，除處罰行為人外，對該法人或自然人並科以前三項所定之罰金。但法人之\n代表人或自然人對於違反之發生，已盡力為防止行為者，不在此限。\n臺灣地區與大陸地區人民關係條例第十五條第四款\n  左列行為不得為之：\n  一、使大陸地區人民非法進入臺灣地區。\n  二、招攬臺灣地區人民未經許可使之進入大陸地區。\n  三、使大陸地區人民從事未經許可或與許可目的不符之活動。\n  四、僱用大陸地區人民從事未經許可或與許可範圍不符之工作。\n  五、居間介紹他人為前款之行為。\n",
  "structure": {
    "main": "甲○○連續違反不得僱用大陸地區人民在臺灣地區從事未經許可之工作之規定，科罰\n金新台幣陸萬元，如易服勞役，以新台幣玖佰元即銀元參佰元折算壹日。",
    "fact": "一、本件犯罪事實、證據及應適用之法條，均引用檢察官聲請簡易判決處刑書之記載\n    （如附件），並補充記載如下，被告甲○○基於概括犯意，先於民國九十年六月\n    間某日，未經許可僱用大陸地區人民甯小美在其經營之「統帥自助餐店」從事打\n    雜之工作，復於同年七月一日僱用大陸地區人民王君飛從事洗菜、打掃之工作。\n    其先後多次犯行，時間緊密，犯罪構成要件相同，顯係基於概括犯意為之，為連\n    續犯，依刑法第五十六條規定，以一罪論，並加重其刑。\n二、爰審酌被告經警當場查獲前揭大陸地區人民後仍矢口否認犯罪，辯以不知其二人\n    為大陸地區人民，及其係因所營自助餐店極需人手幫忙始非法僱用大陸地區人民\n    之犯罪動機、目的及其犯罪之手段、犯罪所生之危害等一切情狀，量處如主文所\n    示之刑，並諭知易服勞役之折算標準。\n三、依刑事訴訟法第四百四十九條第一項前段、第三項、第四百五十四條第二項，台\n    灣地區與大陸地區人民關係條例第八十三條第一項，刑法第十一條前段、第五十\n    六條、第四十二條第二項、罰金罰鍰提高標準條例第二條、現行法規所定貨幣單\n    位折算新台幣條例第二條，逕以簡易判決處刑如主文。\n如不服本判決，得於判決送達之日起十日內，向本院提出上訴狀，上訴於本院第二審\n合議庭。",
    "reason": "一、本件犯罪事實、證據及應適用之法條，均引用檢察官聲請簡易判決處刑書之記載\n    （如附件），並補充記載如下，被告甲○○基於概括犯意，先於民國九十年六月\n    間某日，未經許可僱用大陸地區人民甯小美在其經營之「統帥自助餐店」從事打\n    雜之工作，復於同年七月一日僱用大陸地區人民王君飛從事洗菜、打掃之工作。\n    其先後多次犯行，時間緊密，犯罪構成要件相同，顯係基於概括犯意為之，為連\n    續犯，依刑法第五十六條規定，以一罪論，並加重其刑。\n二、爰審酌被告經警當場查獲前揭大陸地區人民後仍矢口否認犯罪，辯以不知其二人\n    為大陸地區人民，及其係因所營自助餐店極需人手幫忙始非法僱用大陸地區人民\n    之犯罪動機、目的及其犯罪之手段、犯罪所生之危害等一切情狀，量處如主文所\n    示之刑，並諭知易服勞役之折算標準。\n三、依刑事訴訟法第四百四十九條第一項前段、第三項、第四百五十四條第二項，台\n    灣地區與大陸地區人民關係條例第八十三條第一項，刑法第十一條前段、第五十\n    六條、第四十二條第二項、罰金罰鍰提高標準條例第二條、現行法規所定貨幣單\n    位折算新台幣條例第二條，逕以簡易判決處刑如主文。\n如不服本判決，得於判決送達之日起十日內，向本院提出上訴狀，上訴於本院第二審\n合議庭。"
  },
  "search": "臺灣臺北地方法院刑事簡易判決九十一年度簡字第一三一號聲請人臺灣臺北地方法院檢察署檢察官被告甲○○右列被告因違反台灣地區與大陸地區人民關係條例案件，經檢察官聲請以簡易判決處刑（九十年度偵字第二三八九四號），本院判決如左：主文甲○○連續違反不得僱用大陸地區人民在臺灣地區從事未經許可之工作之規定，科罰金新台幣陸萬元，如易服勞役，以新台幣玖佰元即銀元參佰元折算壹日。事實及理由一、本件犯罪事實、證據及應適用之法條，均引用檢察官聲請簡易判決處刑書之記載（如附件），並補充記載如下，被告甲○○基於概括犯意，先於民國九十年六月間某日，未經許可僱用大陸地區人民甯小美在其經營之「統帥自助餐店」從事打雜之工作，復於同年七月一日僱用大陸地區人民王君飛從事洗菜、打掃之工作。其先後多次犯行，時間緊密，犯罪構成要件相同，顯係基於概括犯意為之，為連續犯，依刑法第五十六條規定，以一罪論，並加重其刑。二、爰審酌被告經警當場查獲前揭大陸地區人民後仍矢口否認犯罪，辯以不知其二人為大陸地區人民，及其係因所營自助餐店極需人手幫忙始非法僱用大陸地區人民之犯罪動機、目的及其犯罪之手段、犯罪所生之危害等一切情狀，量處如主文所示之刑，並諭知易服勞役之折算標準。三、依刑事訴訟法第四百四十九條第一項前段、第三項、第四百五十四條第二項，台灣地區與大陸地區人民關係條例第八十三條第一項，刑法第十一條前段、第五十六條、第四十二條第二項、罰金罰鍰提高標準條例第二條、現行法規所定貨幣單位折算新台幣條例第二條，逕以簡易判決處刑如主文。如不服本判決，得於判決送達之日起十日內，向本院提出上訴狀，上訴於本院第二審合議庭。中華民國九十一年一月十四日臺灣臺北地方法院刑事第九庭法官沈君玲右正本證明與原本無異。書記官蔡梅蓮中華民國九十一年一月十七日附錄本案論罪科刑法條全文：台灣地區與大陸地區人民關係條例第八十三條第一項違反第十五條第四款或第五款規定者，處二年以下有期徒刑、拘役或科或併科新台幣三十萬元以下罰金。意圖營利而違反第十五條第五款規定者，處三年以下有期徒刑、拘役或科或併科新台幣六十萬元以下罰金。法人之代表人、法人或自然人之代理人、受僱人或其他從業人員，因執行業務犯前二項之罪者，除處罰行為人外，對該法人或自然人並科以前三項所定之罰金。但法人之代表人或自然人對於違反之發生，已盡力為防止行為者，不在此限。臺灣地區與大陸地區人民關係條例第十五條第四款左列行為不得為之：一、使大陸地區人民非法進入臺灣地區。二、招攬臺灣地區人民未經許可使之進入大陸地區。三、使大陸地區人民從事未經許可或與許可目的不符之活動。四、僱用大陸地區人民從事未經許可或與許可範圍不符之工作。五、居間介紹他人為前款之行為。",
  "characters": {
    "judges": [
      "沈君玲"
    ],
    "prosecutors": [

    ],
    "lawyers": [

    ],
    "clerks": [
      "蔡梅蓮"
    ],
    "plaintiffs": [

    ],
    "defendants": [
      "甲○○",
      "右列被告因違反台灣地區與大陸地區人民關係條例案件，經檢察官聲請以簡易判決處",
      "刑（九十年度偵字第二三八九四號），本院判決如左："
    ],
    "prosecutor_office": [
      "臺灣臺北地方法院檢察署檢察官"
    ],
    "creditors": [

    ],
    "debtors": [

    ],
    "judicial_associate_officer": [

    ]
  },
  "adjudged_at": "2002-01-14",
  "created_at": "2016-02-05 03:03:13",
  "updated_at": "2016-02-05 03:03:13"
}