{
  "identify": "TPD-100-審交易-172-20111222-1",
  "court": {
    "name": "臺灣臺北地方法院",
    "code": "TPD"
  },
  "division": {
    "name": "刑事",
    "code": "M"
  },
  "year": 100,
  "word": "審交易",
  "number": "172",
  "jcheck": "1",
  "reason": "過失傷害",
  "content": "臺灣臺北地方法院刑事判決          100年度審交易字第172號\n公  訴  人  臺灣臺北地方法院檢察署檢察官\n被      告  許金仙女\n上列被告因過失傷害案件，經檢察官提起公訴（100年度偵字第\n17511號），本院判決如下：\n    主    文\n本件公訴不受理。\n    理    由\n一、公訴意旨略以：被告許金仙女於民國100 年6 月16日下午2\n    時50分許，駕駛車牌號碼0330-F7 號自用小客車，由西向東\n    停靠在臺北市○○區○○路5 段深坑幹152 號前，欲橫越馬\n    路迴轉行駛，其本應注意在劃有分向限制線之上開路段，不\n    得迴車，按當時天候陰、日間自然光線、柏油路面、路面濕\n    潤、無缺陷、道路無障礙、視距良好等客觀環境，並無不能\n    注意之情狀，竟疏未注意，突然左轉欲穿越分向限制線而迴\n    向行駛，適有告訴人黃明烽駕駛車牌號碼080-HQR 號重型機\n    車，沿上開路段由西向東行駛，行至上址，見前車突然左轉\n    ，為閃避然已煞車不及，致人車倒地，受有四肢多處擦挫傷\n    等傷害，因認被告許金仙女涉犯刑法第284 條第1 項之過失\n    傷害罪嫌。\n二、按告訴乃論之罪，告訴人於第一審辯論終結前得撤回其告訴\n    ，又告訴經撤回者，法院應諭知不受理之判決，刑事訴訟法\n    第238條第1項、第303條第3款定有明文，且依同法第307條\n    規定，不受理判決得不經言詞辯論為之。\n三、本件被告許金仙女所涉過失傷害犯行，起訴書認係犯刑法第\n    284 條第1 項之罪，依同法第287 條前段之規定，須告訴乃\n    論。茲據告訴人黃明烽具狀撤回告訴，有刑事撤回告訴狀（\n    見本院卷第31頁）附卷可稽。揆諸前開說明，本件不經言詞\n    辯論，逕行諭知不受理之判決。\n四、據上論斷，應依刑事訴訟法第303條第3款、第307條，判決\n    如主文。\n中    華    民    國   100    年    12    月    22    日\n                  刑事第二十庭  法  官  顧正德\n上正本證明與原本無異。\n如不服本判決應於收受送達後10日內向本院提出上訴書狀，並應\n敘述具體理由；其未敘述上訴理由者，應於上訴期間屆滿後20日\n內向本院補提理由書（均須按他造當事人之人數附繕本）「切勿\n逕送上級法院」。告訴人或被害人如對於本判決不服者，應具備\n理由請求檢察官上訴，其上訴期間之計算係以檢察官收受判決正\n本之日期為準。\n                                書記官  郭錦賢\n中    華    民    國   100    年    12    月    22    日",
  "structure": {
    "main": "本件公訴不受理。",
    "reason": "一、公訴意旨略以：被告許金仙女於民國100 年6 月16日下午2\n    時50分許，駕駛車牌號碼0330-F7 號自用小客車，由西向東\n    停靠在臺北市○○區○○路5 段深坑幹152 號前，欲橫越馬\n    路迴轉行駛，其本應注意在劃有分向限制線之上開路段，不\n    得迴車，按當時天候陰、日間自然光線、柏油路面、路面濕\n    潤、無缺陷、道路無障礙、視距良好等客觀環境，並無不能\n    注意之情狀，竟疏未注意，突然左轉欲穿越分向限制線而迴\n    向行駛，適有告訴人黃明烽駕駛車牌號碼080-HQR 號重型機\n    車，沿上開路段由西向東行駛，行至上址，見前車突然左轉\n    ，為閃避然已煞車不及，致人車倒地，受有四肢多處擦挫傷\n    等傷害，因認被告許金仙女涉犯刑法第284 條第1 項之過失\n    傷害罪嫌。\n二、按告訴乃論之罪，告訴人於第一審辯論終結前得撤回其告訴\n    ，又告訴經撤回者，法院應諭知不受理之判決，刑事訴訟法\n    第238條第1項、第303條第3款定有明文，且依同法第307條\n    規定，不受理判決得不經言詞辯論為之。\n三、本件被告許金仙女所涉過失傷害犯行，起訴書認係犯刑法第\n    284 條第1 項之罪，依同法第287 條前段之規定，須告訴乃\n    論。茲據告訴人黃明烽具狀撤回告訴，有刑事撤回告訴狀（\n    見本院卷第31頁）附卷可稽。揆諸前開說明，本件不經言詞\n    辯論，逕行諭知不受理之判決。\n四、據上論斷，應依刑事訴訟法第303條第3款、第307條，判決\n    如主文。"
  },
  "search": "臺灣臺北地方法院刑事判決100年度審交易字第172號公訴人臺灣臺北地方法院檢察署檢察官被告許金仙女上列被告因過失傷害案件，經檢察官提起公訴（100年度偵字第17511號），本院判決如下：主文本件公訴不受理。理由一、公訴意旨略以：被告許金仙女於民國100年6月16日下午2時50分許，駕駛車牌號碼0330-F7號自用小客車，由西向東停靠在臺北市○○區○○路5段深坑幹152號前，欲橫越馬路迴轉行駛，其本應注意在劃有分向限制線之上開路段，不得迴車，按當時天候陰、日間自然光線、柏油路面、路面濕潤、無缺陷、道路無障礙、視距良好等客觀環境，並無不能注意之情狀，竟疏未注意，突然左轉欲穿越分向限制線而迴向行駛，適有告訴人黃明烽駕駛車牌號碼080-HQR號重型機車，沿上開路段由西向東行駛，行至上址，見前車突然左轉，為閃避然已煞車不及，致人車倒地，受有四肢多處擦挫傷等傷害，因認被告許金仙女涉犯刑法第284條第1項之過失傷害罪嫌。二、按告訴乃論之罪，告訴人於第一審辯論終結前得撤回其告訴，又告訴經撤回者，法院應諭知不受理之判決，刑事訴訟法第238條第1項、第303條第3款定有明文，且依同法第307條規定，不受理判決得不經言詞辯論為之。三、本件被告許金仙女所涉過失傷害犯行，起訴書認係犯刑法第284條第1項之罪，依同法第287條前段之規定，須告訴乃論。茲據告訴人黃明烽具狀撤回告訴，有刑事撤回告訴狀（見本院卷第31頁）附卷可稽。揆諸前開說明，本件不經言詞辯論，逕行諭知不受理之判決。四、據上論斷，應依刑事訴訟法第303條第3款、第307條，判決如主文。中華民國100年12月22日刑事第二十庭法官顧正德上正本證明與原本無異。如不服本判決應於收受送達後10日內向本院提出上訴書狀，並應敘述具體理由；其未敘述上訴理由者，應於上訴期間屆滿後20日內向本院補提理由書（均須按他造當事人之人數附繕本）「切勿逕送上級法院」。告訴人或被害人如對於本判決不服者，應具備理由請求檢察官上訴，其上訴期間之計算係以檢察官收受判決正本之日期為準。書記官郭錦賢中華民國100年12月22日",
  "characters": {
    "judges": [
      "顧正德"
    ],
    "prosecutors": [

    ],
    "lawyers": [

    ],
    "clerks": [
      "郭錦賢"
    ],
    "plaintiffs": [

    ],
    "defendants": [
      "許金仙女"
    ],
    "prosecutor_office": [
      "臺灣臺北地方法院檢察署檢察官"
    ],
    "creditors": [

    ],
    "debtors": [

    ],
    "judicial_associate_officer": [

    ]
  },
  "adjudged_at": "2011-12-22",
  "created_at": "2016-02-13 10:31:17",
  "updated_at": "2016-02-13 10:31:17"
}