{
  "identify": "MLD-91-易-303-20020531-1",
  "court": {
    "name": "臺灣苗栗地方法院",
    "code": "MLD"
  },
  "division": {
    "name": "刑事",
    "code": "M"
  },
  "year": 91,
  "word": "易",
  "number": "303",
  "jcheck": "1",
  "reason": "毒品危害防制條例",
  "content": "臺灣苗栗地方法院刑事判決              九十一年度易字第三三號\n    公  訴  人  臺灣苗栗地方法院檢察署檢察官\n    被      告  甲○○\n右列被告因違反毒品危害防制條例案件，經檢察官提起公訴（九十一年毒偵字第二五\n二號），本院判決如左：\n    主  文\n甲○○連續施用第二級毒品，累犯，處有期徒刑陸月，如易科罰金以參佰元折算壹日\n。\n    事  實\n一、甲○○曾因違反麻醉藥品管理條例，經台灣新竹地方法院判處有期徒刑三月，於\n    民國（下同）八十六年五月十四日縮刑期滿執行完畢，猶不知悔改，前再因施用\n    毒品案件，經本院於八十九年間以八十九年度毒聲字第一五四三號裁定送觀察、\n    勒戎後，認無繼續施用毒品之傾向，經台灣苗栗地方法檢察署檢察官於八十九年\n    九月三十日以八十九年度毒偵字第一九九九號處分不起訴確定在案，仍未知悔改\n    ，復基於施用第二級毒品安非他命之概括犯意，自九十年十二月中旬起至九十一\n    年一月二十日上午二十時止（起訴書原載為自九十年十二月間某日起至九十一年\n    二月中旬止，惟經公訴檢察官當庭更正為事實欄之犯罪時間），在苗栗縣頭份鎮\n    ○○里○鄰○○街一一三巷十號住處，先後多次以錫鉑紙上置放少許安非他命，\n    下再以底火燒烤冒煙，吸食煙霧之方式施用第二級毒品安非他命（吸食工具未經\n    扣案），經警於九十一年一月二十日採尿送驗後查獲，再經本院以九十一年度毒\n    聲字第二八六號裁定送觀察勒戒處所觀察、勒戒後，經台灣苗栗看守所附設觀察\n    勒戒所評估後，認有繼續施用毒品之傾向。再經本院於九十一年四月間以九十一\n    年度毒聲字第三五一號裁定令入戒治處所施以強制戒治一年。\n二、案經苗栗縣警察局竹南分局移送台灣苗栗地方法院檢察署檢察官偵查起訴。\n    理  由\n一、右揭犯罪事實業經被告甲○○於偵審中自白不諱，復有苗栗縣衛生局出具煙毒尿\n    液檢驗成績書一份、台灣苗栗看守所附設觀察勒戒處所九十一年四月十日苗所衛\n    字第０九一０００一四二二號函所附之「受觀察勒戒人有無繼續施用毒品判定資\n    料」及台灣苗栗地方法檢察署刑案資料查註紀錄、台灣高等法院被告全國前案紀\n    錄、台灣高等法院檢察署刑案紀錄簡覆表等資料載明被告經以八十九年度毒偵字\n    第一九九九號處分不起訴確定在案，事證明確，足見被告之自白與事實相符，被\n    告之犯行堪予認定。\n二、查安非他命為毒品危害防制條例第二條第二項第二款所規定之第二級毒品，不得\n    持有及施用，被告違反此項規定，核其所為係犯同條例第十條第二項之施用第二\n    級毒品罪。被告持有安非他命之低度行為為施用安非他命之高度行為所吸收，不\n    另論罪。其先後施用毒品行為，時間密接、犯罪構成要件相同，顯係基於概括犯\n    意為之，應依連續犯規定論以一罪，並加重其刑。又被告甲○○曾因違反麻醉藥\n    品管理條例，經台灣新竹地方法院判處有期徒刑三月，於八十六年五月十四日縮\n    刑期滿執行完畢，有台灣苗栗地方法檢察署刑案資料查註紀錄、台灣高等法院檢\n    察署刑案紀錄簡覆表及台灣高等法院被告全國前案紀錄各一份附卷足稽，其於有\n    期徒刑之執行完畢後，五年以內再犯有期徒刑以上之刑之罪，為累犯並依法遞加\n    重其刑。爰審酌被告坦承犯行，尚知悔改之態度及其品行、犯罪之動機、目的、\n    素行及犯罪所生之危害等一切情狀，量處如主文所示之刑，併諭知易科罰金之折\n    算標準，以示懲儆。另吸食工具錫鉑紙等物，未經扣案，且已經被告丟棄，不復\n    存在，有被告之供陳在卷足佐，爰不予宣告沒收，附此敘明。\n據上論斷，應依刑事訴訟法第二百九十九條第一項前段，毒品危害防制條例第十條第\n二項，刑法第十一條前段、第五十六條、第四十七條、第四十一條第一項前段，罰金\n罰鍰提高標準條例第二條，判決如主文。\n本案經檢察官陳傳宗到庭執行職務\n中          華        民        國    九十一年  五月    三十一    日\n                                            台灣苗栗地方法院刑事第一庭\n                                                法  官  陳鴻斌\n右正本證明與原本無異。\n如不服本判決，應於判決送達後十日內向本院提出上訴狀( 應附繕本 )。\n                                                書記官  陳爵星\n中      華      民      國     九十一     年     六     月     三     日\n論罪科刑法條：\n毒品危害防制條例第十條第二項\n施用第二級毒品者，處三年以下有期徒刑。\n",
  "structure": {
    "main": "甲○○連續施用第二級毒品，累犯，處有期徒刑陸月，如易科罰金以參佰元折算壹日\n。",
    "fact": "一、甲○○曾因違反麻醉藥品管理條例，經台灣新竹地方法院判處有期徒刑三月，於\n    民國（下同）八十六年五月十四日縮刑期滿執行完畢，猶不知悔改，前再因施用\n    毒品案件，經本院於八十九年間以八十九年度毒聲字第一五四三號裁定送觀察、\n    勒戎後，認無繼續施用毒品之傾向，經台灣苗栗地方法檢察署檢察官於八十九年\n    九月三十日以八十九年度毒偵字第一九九九號處分不起訴確定在案，仍未知悔改\n    ，復基於施用第二級毒品安非他命之概括犯意，自九十年十二月中旬起至九十一\n    年一月二十日上午二十時止（起訴書原載為自九十年十二月間某日起至九十一年\n    二月中旬止，惟經公訴檢察官當庭更正為事實欄之犯罪時間），在苗栗縣頭份鎮\n    ○○里○鄰○○街一一三巷十號住處，先後多次以錫鉑紙上置放少許安非他命，\n    下再以底火燒烤冒煙，吸食煙霧之方式施用第二級毒品安非他命（吸食工具未經\n    扣案），經警於九十一年一月二十日採尿送驗後查獲，再經本院以九十一年度毒\n    聲字第二八六號裁定送觀察勒戒處所觀察、勒戒後，經台灣苗栗看守所附設觀察\n    勒戒所評估後，認有繼續施用毒品之傾向。再經本院於九十一年四月間以九十一\n    年度毒聲字第三五一號裁定令入戒治處所施以強制戒治一年。\n二、案經苗栗縣警察局竹南分局移送台灣苗栗地方法院檢察署檢察官偵查起訴。",
    "reason": "一、右揭犯罪事實業經被告甲○○於偵審中自白不諱，復有苗栗縣衛生局出具煙毒尿\n    液檢驗成績書一份、台灣苗栗看守所附設觀察勒戒處所九十一年四月十日苗所衛\n    字第０九一０００一四二二號函所附之「受觀察勒戒人有無繼續施用毒品判定資\n    料」及台灣苗栗地方法檢察署刑案資料查註紀錄、台灣高等法院被告全國前案紀\n    錄、台灣高等法院檢察署刑案紀錄簡覆表等資料載明被告經以八十九年度毒偵字\n    第一九九九號處分不起訴確定在案，事證明確，足見被告之自白與事實相符，被\n    告之犯行堪予認定。\n二、查安非他命為毒品危害防制條例第二條第二項第二款所規定之第二級毒品，不得\n    持有及施用，被告違反此項規定，核其所為係犯同條例第十條第二項之施用第二\n    級毒品罪。被告持有安非他命之低度行為為施用安非他命之高度行為所吸收，不\n    另論罪。其先後施用毒品行為，時間密接、犯罪構成要件相同，顯係基於概括犯\n    意為之，應依連續犯規定論以一罪，並加重其刑。又被告甲○○曾因違反麻醉藥\n    品管理條例，經台灣新竹地方法院判處有期徒刑三月，於八十六年五月十四日縮\n    刑期滿執行完畢，有台灣苗栗地方法檢察署刑案資料查註紀錄、台灣高等法院檢\n    察署刑案紀錄簡覆表及台灣高等法院被告全國前案紀錄各一份附卷足稽，其於有\n    期徒刑之執行完畢後，五年以內再犯有期徒刑以上之刑之罪，為累犯並依法遞加\n    重其刑。爰審酌被告坦承犯行，尚知悔改之態度及其品行、犯罪之動機、目的、\n    素行及犯罪所生之危害等一切情狀，量處如主文所示之刑，併諭知易科罰金之折\n    算標準，以示懲儆。另吸食工具錫鉑紙等物，未經扣案，且已經被告丟棄，不復\n    存在，有被告之供陳在卷足佐，爰不予宣告沒收，附此敘明。\n據上論斷，應依刑事訴訟法第二百九十九條第一項前段，毒品危害防制條例第十條第\n二項，刑法第十一條前段、第五十六條、第四十七條、第四十一條第一項前段，罰金\n罰鍰提高標準條例第二條，判決如主文。\n本案經檢察官陳傳宗到庭執行職務\n中          華        民        國    九十一年  五月    三十一    日\n                                            台灣苗栗地方法院刑事第一庭\n                                                法  官  陳鴻斌\n右正本證明與原本無異。\n如不服本判決，應於判決送達後十日內向本院提出上訴狀( 應附繕本 )。\n                                                書記官  陳爵星"
  },
  "search": "臺灣苗栗地方法院刑事判決九十一年度易字第三三號公訴人臺灣苗栗地方法院檢察署檢察官被告甲○○右列被告因違反毒品危害防制條例案件，經檢察官提起公訴（九十一年毒偵字第二五二號），本院判決如左：主文甲○○連續施用第二級毒品，累犯，處有期徒刑陸月，如易科罰金以參佰元折算壹日。事實一、甲○○曾因違反麻醉藥品管理條例，經台灣新竹地方法院判處有期徒刑三月，於民國（下同）八十六年五月十四日縮刑期滿執行完畢，猶不知悔改，前再因施用毒品案件，經本院於八十九年間以八十九年度毒聲字第一五四三號裁定送觀察、勒戎後，認無繼續施用毒品之傾向，經台灣苗栗地方法檢察署檢察官於八十九年九月三十日以八十九年度毒偵字第一九九九號處分不起訴確定在案，仍未知悔改，復基於施用第二級毒品安非他命之概括犯意，自九十年十二月中旬起至九十一年一月二十日上午二十時止（起訴書原載為自九十年十二月間某日起至九十一年二月中旬止，惟經公訴檢察官當庭更正為事實欄之犯罪時間），在苗栗縣頭份鎮○○里○鄰○○街一一三巷十號住處，先後多次以錫鉑紙上置放少許安非他命，下再以底火燒烤冒煙，吸食煙霧之方式施用第二級毒品安非他命（吸食工具未經扣案），經警於九十一年一月二十日採尿送驗後查獲，再經本院以九十一年度毒聲字第二八六號裁定送觀察勒戒處所觀察、勒戒後，經台灣苗栗看守所附設觀察勒戒所評估後，認有繼續施用毒品之傾向。再經本院於九十一年四月間以九十一年度毒聲字第三五一號裁定令入戒治處所施以強制戒治一年。二、案經苗栗縣警察局竹南分局移送台灣苗栗地方法院檢察署檢察官偵查起訴。理由一、右揭犯罪事實業經被告甲○○於偵審中自白不諱，復有苗栗縣衛生局出具煙毒尿液檢驗成績書一份、台灣苗栗看守所附設觀察勒戒處所九十一年四月十日苗所衛字第０九一０００一四二二號函所附之「受觀察勒戒人有無繼續施用毒品判定資料」及台灣苗栗地方法檢察署刑案資料查註紀錄、台灣高等法院被告全國前案紀錄、台灣高等法院檢察署刑案紀錄簡覆表等資料載明被告經以八十九年度毒偵字第一九九九號處分不起訴確定在案，事證明確，足見被告之自白與事實相符，被告之犯行堪予認定。二、查安非他命為毒品危害防制條例第二條第二項第二款所規定之第二級毒品，不得持有及施用，被告違反此項規定，核其所為係犯同條例第十條第二項之施用第二級毒品罪。被告持有安非他命之低度行為為施用安非他命之高度行為所吸收，不另論罪。其先後施用毒品行為，時間密接、犯罪構成要件相同，顯係基於概括犯意為之，應依連續犯規定論以一罪，並加重其刑。又被告甲○○曾因違反麻醉藥品管理條例，經台灣新竹地方法院判處有期徒刑三月，於八十六年五月十四日縮刑期滿執行完畢，有台灣苗栗地方法檢察署刑案資料查註紀錄、台灣高等法院檢察署刑案紀錄簡覆表及台灣高等法院被告全國前案紀錄各一份附卷足稽，其於有期徒刑之執行完畢後，五年以內再犯有期徒刑以上之刑之罪，為累犯並依法遞加重其刑。爰審酌被告坦承犯行，尚知悔改之態度及其品行、犯罪之動機、目的、素行及犯罪所生之危害等一切情狀，量處如主文所示之刑，併諭知易科罰金之折算標準，以示懲儆。另吸食工具錫鉑紙等物，未經扣案，且已經被告丟棄，不復存在，有被告之供陳在卷足佐，爰不予宣告沒收，附此敘明。據上論斷，應依刑事訴訟法第二百九十九條第一項前段，毒品危害防制條例第十條第二項，刑法第十一條前段、第五十六條、第四十七條、第四十一條第一項前段，罰金罰鍰提高標準條例第二條，判決如主文。本案經檢察官陳傳宗到庭執行職務中華民國九十一年五月三十一日台灣苗栗地方法院刑事第一庭法官陳鴻斌右正本證明與原本無異。如不服本判決，應於判決送達後十日內向本院提出上訴狀(應附繕本)。書記官陳爵星中華民國九十一年六月三日論罪科刑法條：毒品危害防制條例第十條第二項施用第二級毒品者，處三年以下有期徒刑。",
  "characters": {
    "judges": [
      "陳鴻斌"
    ],
    "prosecutors": [
      "陳傳宗"
    ],
    "lawyers": [

    ],
    "clerks": [
      "陳爵星"
    ],
    "plaintiffs": [

    ],
    "defendants": [
      "甲○○",
      "右列被告因違反毒品危害防制條例案件，經檢察官提起公訴（九十一年毒偵字第二五",
      "二號），本院判決如左："
    ],
    "prosecutor_office": [
      "臺灣苗栗地方法院檢察署檢察官"
    ],
    "creditors": [

    ],
    "debtors": [

    ],
    "judicial_associate_officer": [

    ]
  },
  "adjudged_at": "2002-05-31",
  "created_at": "2016-02-04 13:40:08",
  "updated_at": "2016-02-04 13:40:08"
}