{
  "identify": "KLD-100-聲-697-20110706-1",
  "court": {
    "name": "臺灣基隆地方法院",
    "code": "KLD"
  },
  "division": {
    "name": "刑事",
    "code": "M"
  },
  "year": 100,
  "word": "聲",
  "number": "697",
  "jcheck": "1",
  "reason": "定應執行刑",
  "content": "臺灣基隆地方法院刑事裁定              100年度聲字第697號\n聲  請  人  臺灣基隆地方法院檢察署檢察官\n受  刑  人\n即  被  告  羅富友\n上列聲請人因受刑人即被告數罪併罰有二裁判以上，聲請定其應\n執行之刑（100 年度執聲字第555 號），本院裁定如下：\n    主  文\n羅富友犯如附表所示之罪，應執行拘役捌拾伍日，如易科罰金以\n新臺幣壹仟元折算壹日。\n    理  由\n一、本件受刑人即被告羅富友前於附表編號一至三所示犯罪時間\n    ，觸犯附表編號一至三所示各該罪名，經本院分別於附表編\n    號一至三所示判決日期，各處其宣告刑如附表編號一至三之\n    所示；其中，如附表編號一二所示犯罪，業經合併定刑為拘\n    役35日，如易科罰金，以新臺幣1,000 元折算1 日。又受刑\n    人所犯如附表編號一二所示犯罪，固悉於民國99年9 月15日\n    執行完畢（卷附臺灣高等法院被告前案紀錄表參照），惟受\n    刑人所犯如附表編號三所示犯罪，則迄未發監，亦未易科（\n    卷附臺灣高等法院被告前案紀錄表參照）。按「數罪併罰案\n    件之執行完畢，係指數罪定應執行之刑以後，已將該應執行\n    之刑全部執行完畢者」而言，若僅其中一罪之宣告刑經執行\n    完畢，而所併合處罰之數罪則猶有迄未執行或迄未執畢之餘\n    罪，則關此「數罪合併所定應執行之刑」，即與「執行未完\n    畢」無殊，並應就其各罪重新合併定其應執行之刑（最高法\n    院80年度臺抗字第435 號裁定意旨參照；最高法院78年2 月\n    28日78年度第二次刑事庭會議決議意旨參照）。茲受刑人所\n    犯如附表編號一二三所示犯罪，既屬刑法第53條所指之「數\n    罪併罰」案件，則檢察官本此而提出首開聲請，當亦於法有\n    據且無不當。爰依刑法第53條、第51條第6 款、第41條第1\n    項前段，酌定其應執行刑如主文之所示。\n二、依刑事訴訟法第477 條第1 項，刑法第53條、第51條第6 款\n    、第41條第1 項前段，裁定如主文。\n中    華    民    國   100    年    7     月    6     日\n                  刑事第五庭法  官  王慧惠\n以上正本證明與原本無異。\n對於本件裁定如有不服，應於收受送達後5日內，向本院提出抗\n告書狀，敘述抗告之理由，抗告於臺灣高等法院。\n中    華    民    國   100    年    7     月    6     日\n                            書記官  王一芳\n【附表】受刑人羅富友定應執行刑案件一覽表\n┌──────┬─────────────┬─────────────┬─────────────┐\n│編        號│            一            │            二            │            三            │\n├──────┼─────────────┼─────────────┼─────────────┤\n│罪        名│           傷害           │           恐嚇           │         公然侮辱         │\n├──────┼─────────────┼─────────────┼─────────────┤\n│宣   告   刑│         拘役１０日         │         拘役日         │         拘役日         │\n│            │    如易科罰金，以新臺    │    如易科罰金，以新臺    │    如易科罰金，以新臺    │\n│            │    幣1,000 元折算1 日    │    幣1,000 元折算1 日    │    幣1,000 元折算1 日    │\n├──────┼─────────────┴─────────────┼─────────────┤\n│曾否與他罪合│            編號一二曾經合併定刑為拘役日            │             否           │\n│併定其應執行│         如易科罰金，以新臺幣1,000元折算1 日          │                          │\n│之刑        │           （本院99年度聲字第807 號裁定）             │                          │\n├──────┼─────────────┬─────────────┼─────────────┤\n│犯 罪 日 期 │       99年2 月3 日       │       99年2 月3 日       │       98年12月18日       │\n├──────┼─────────────┼─────────────┼─────────────┤\n│偵查（自訴）│  臺灣基隆地方法院檢察署  │  臺灣基隆地方法院檢察署  │  臺灣基隆地方法院檢察署  │\n│機關年度及其│  99年度偵字第837 號      │  99年度偵字第720 號      │  99年度偵字第135 號      │\n│案號        │                          │                          │                          │\n├───┬──┼─────────────┼─────────────┼─────────────┤\n│      │ 法 │                          │                          │                          │\n│      │    │     臺灣基隆地方法院     │     臺灣基隆地方法院     │     臺灣基隆地方法院     │\n│      │ 院 │                          │                          │                          │\n│      ├──┼─────────────┼─────────────┼─────────────┤\n│最  後│ 案 │                          │                          │                          │\n│      │    │    99年基簡字第536 號    │    99年基簡字第882 號    │    100年簡上字第49號     │\n│      │ 號 │                          │                          │                          │\n│事實審├──┼─────────────┼─────────────┼─────────────┤\n│      │ 判 │                          │                          │                          │\n│      │ 決 │       99年5 月31日       │       99年6 月24日       │      100年5 月10日       │\n│      │ 日 │                          │                          │                          │\n│      │ 期 │                          │                          │                          │\n├───┼──┼─────────────┼─────────────┼─────────────┤\n│      │ 法 │                          │                          │                          │\n│      │    │     臺灣基隆地方法院     │     臺灣基隆地方法院     │     臺灣基隆地方法院     │\n│      │ 院 │                          │                          │                          │\n│確  定├──┼─────────────┼─────────────┼─────────────┤\n│      │ 案 │                          │                          │                          │\n│      │    │    99年基簡字第536 號    │    99年基簡字第882 號    │    100年簡上字第49號     │\n│      │ 號 │                          │                          │                          │\n│判  決├──┼─────────────┼─────────────┼─────────────┤\n│      │ 確 │                          │                          │                          │\n│      │ 定 │       99年7 月5 日       │       99年7 月26日       │      100年5 月10日       │\n│      │ 日 │                          │                          │       （不得上訴）       │\n│      │ 期 │                          │                          │                          │\n├───┴──┼─────────────┼─────────────┼─────────────┤\n│備        註│基隆地檢99年度執字第1713號│基隆地檢99年度執字第1936號│基隆地檢100 年執字第1802號│\n└──────┴─────────────┴─────────────┴─────────────┘",
  "structure": {
    "main": "羅富友犯如附表所示之罪，應執行拘役捌拾伍日，如易科罰金以\n新臺幣壹仟元折算壹日。",
    "reason": "一、本件受刑人即被告羅富友前於附表編號一至三所示犯罪時間\n    ，觸犯附表編號一至三所示各該罪名，經本院分別於附表編\n    號一至三所示判決日期，各處其宣告刑如附表編號一至三之\n    所示；其中，如附表編號一二所示犯罪，業經合併定刑為拘\n    役35日，如易科罰金，以新臺幣1,000 元折算1 日。又受刑\n    人所犯如附表編號一二所示犯罪，固悉於民國99年9 月15日\n    執行完畢（卷附臺灣高等法院被告前案紀錄表參照），惟受\n    刑人所犯如附表編號三所示犯罪，則迄未發監，亦未易科（\n    卷附臺灣高等法院被告前案紀錄表參照）。按「數罪併罰案\n    件之執行完畢，係指數罪定應執行之刑以後，已將該應執行\n    之刑全部執行完畢者」而言，若僅其中一罪之宣告刑經執行\n    完畢，而所併合處罰之數罪則猶有迄未執行或迄未執畢之餘\n    罪，則關此「數罪合併所定應執行之刑」，即與「執行未完\n    畢」無殊，並應就其各罪重新合併定其應執行之刑（最高法\n    院80年度臺抗字第435 號裁定意旨參照；最高法院78年2 月\n    28日78年度第二次刑事庭會議決議意旨參照）。茲受刑人所\n    犯如附表編號一二三所示犯罪，既屬刑法第53條所指之「數\n    罪併罰」案件，則檢察官本此而提出首開聲請，當亦於法有\n    據且無不當。爰依刑法第53條、第51條第6 款、第41條第1\n    項前段，酌定其應執行刑如主文之所示。\n二、依刑事訴訟法第477 條第1 項，刑法第53條、第51條第6 款\n    、第41條第1 項前段，裁定如主文。"
  },
  "search": "臺灣基隆地方法院刑事裁定100年度聲字第697號聲請人臺灣基隆地方法院檢察署檢察官受刑人即被告羅富友上列聲請人因受刑人即被告數罪併罰有二裁判以上，聲請定其應執行之刑（100年度執聲字第555號），本院裁定如下：主文羅富友犯如附表所示之罪，應執行拘役捌拾伍日，如易科罰金以新臺幣壹仟元折算壹日。理由一、本件受刑人即被告羅富友前於附表編號一至三所示犯罪時間，觸犯附表編號一至三所示各該罪名，經本院分別於附表編號一至三所示判決日期，各處其宣告刑如附表編號一至三之所示；其中，如附表編號一二所示犯罪，業經合併定刑為拘役35日，如易科罰金，以新臺幣1,000元折算1日。又受刑人所犯如附表編號一二所示犯罪，固悉於民國99年9月15日執行完畢（卷附臺灣高等法院被告前案紀錄表參照），惟受刑人所犯如附表編號三所示犯罪，則迄未發監，亦未易科（卷附臺灣高等法院被告前案紀錄表參照）。按「數罪併罰案件之執行完畢，係指數罪定應執行之刑以後，已將該應執行之刑全部執行完畢者」而言，若僅其中一罪之宣告刑經執行完畢，而所併合處罰之數罪則猶有迄未執行或迄未執畢之餘罪，則關此「數罪合併所定應執行之刑」，即與「執行未完畢」無殊，並應就其各罪重新合併定其應執行之刑（最高法院80年度臺抗字第435號裁定意旨參照；最高法院78年2月28日78年度第二次刑事庭會議決議意旨參照）。茲受刑人所犯如附表編號一二三所示犯罪，既屬刑法第53條所指之「數罪併罰」案件，則檢察官本此而提出首開聲請，當亦於法有據且無不當。爰依刑法第53條、第51條第6款、第41條第1項前段，酌定其應執行刑如主文之所示。二、依刑事訴訟法第477條第1項，刑法第53條、第51條第6款、第41條第1項前段，裁定如主文。中華民國100年7月6日刑事第五庭法官王慧惠以上正本證明與原本無異。對於本件裁定如有不服，應於收受送達後5日內，向本院提出抗告書狀，敘述抗告之理由，抗告於臺灣高等法院。中華民國100年7月6日書記官王一芳【附表】受刑人羅富友定應執行刑案件一覽表┌──────┬─────────────┬─────────────┬─────────────┐│編號│一│二│三│├──────┼─────────────┼─────────────┼─────────────┤│罪名│傷害│恐嚇│公然侮辱│├──────┼─────────────┼─────────────┼─────────────┤│宣告刑│拘役１０日│拘役日│拘役日│││如易科罰金，以新臺│如易科罰金，以新臺│如易科罰金，以新臺│││幣1,000元折算1日│幣1,000元折算1日│幣1,000元折算1日│├──────┼─────────────┴─────────────┼─────────────┤│曾否與他罪合│編號一二曾經合併定刑為拘役日│否││併定其應執行│如易科罰金，以新臺幣1,000元折算1日│││之刑│（本院99年度聲字第807號裁定）││├──────┼─────────────┬─────────────┼─────────────┤│犯罪日期│99年2月3日│99年2月3日│98年12月18日│├──────┼─────────────┼─────────────┼─────────────┤│偵查（自訴）│臺灣基隆地方法院檢察署│臺灣基隆地方法院檢察署│臺灣基隆地方法院檢察署││機關年度及其│99年度偵字第837號│99年度偵字第720號│99年度偵字第135號││案號││││├───┬──┼─────────────┼─────────────┼─────────────┤││法│││││││臺灣基隆地方法院│臺灣基隆地方法院│臺灣基隆地方法院│││院│││││├──┼─────────────┼─────────────┼─────────────┤│最後│案│││││││99年基簡字第536號│99年基簡字第882號│100年簡上字第49號│││號│││││事實審├──┼─────────────┼─────────────┼─────────────┤││判││││││決│99年5月31日│99年6月24日│100年5月10日│││日││││││期││││├───┼──┼─────────────┼─────────────┼─────────────┤││法│││││││臺灣基隆地方法院│臺灣基隆地方法院│臺灣基隆地方法院│││院│││││確定├──┼─────────────┼─────────────┼─────────────┤││案│││││││99年基簡字第536號│99年基簡字第882號│100年簡上字第49號│││號│││││判決├──┼─────────────┼─────────────┼─────────────┤││確││││││定│99年7月5日│99年7月26日│100年5月10日│││日│││（不得上訴）│││期││││├───┴──┼─────────────┼─────────────┼─────────────┤│備註│基隆地檢99年度執字第1713號│基隆地檢99年度執字第1936號│基隆地檢100年執字第1802號│└──────┴─────────────┴─────────────┴─────────────┘",
  "characters": {
    "judges": [
      "王慧惠"
    ],
    "prosecutors": [

    ],
    "lawyers": [

    ],
    "clerks": [
      "王一芳"
    ],
    "plaintiffs": [

    ],
    "defendants": [
      "羅富友"
    ],
    "prosecutor_office": [
      "臺灣基隆地方法院檢察署檢察官"
    ],
    "creditors": [

    ],
    "debtors": [

    ],
    "judicial_associate_officer": [

    ]
  },
  "adjudged_at": "2011-07-06",
  "created_at": "2016-02-14 03:06:47",
  "updated_at": "2016-02-14 03:06:47"
}