{
  "identify": "TCD-92-重訴-673-20040223-1",
  "court": {
    "name": "臺灣臺中地方法院",
    "code": "TCD"
  },
  "division": {
    "name": "民事",
    "code": "V"
  },
  "year": 92,
  "word": "重訴",
  "number": "673",
  "jcheck": "1",
  "reason": "清償借款",
  "content": "臺灣臺中地方法院民事判決  九十二年度重訴字第六七三號\n    原      告    聯信商業銀行股份有限公司\n    法定代理人    甲○○\n    訴訟代理人    丁○○\n    被      告    建恒海運股份有限公司\n?\n    兼法定代理人  乙○○\n?\n    被      告    丙○○\n右當事人間請求清償借款事件，於民國九十三年二月九日言詞辯論終結，本院判決如\n左：\n    主    文\n被告應連帶給付原告新台幣仟佰伍拾肆萬仟玖佰拾柒元，及自民國九十二年\n三月十一日起至清償日止，按年息百分之七點四五計算之利息，並自民國九十二年四\n月十二日起至清償日止，其逾期在六個月以內者，按上開利率百分之十，其逾期超過\n六個月者，按上開利率百分之二十計算之違約金。\n訴訟費用由被告連帶負擔。\n本判決第一項於原告以新台幣壹仟壹佰壹拾伍萬元為被告供擔保後，得假執行。\n    事    實\n甲、原告方面：\n一、聲明：求為判決除假執行擔保金額外，如主文所示。\n二、陳述略稱：被告建恒海運股份有限公司以其餘被告為連帶保證人，於民國九十年\n    四月二十五日向原告借用新台幣（下同）仟伍佰肆拾玖萬壹仟柒佰伍拾貳元、\n    貳仟捌佰萬零仟佰玖拾元二筆借款，約定利息均按年息百分之七點九點計\n    算，逾期清償在六個月以內者，按上開利率百分之十，在六個月以上者，按上開\n    利率百分之二十計付違約金，清償期為民國九十三年九月十一日。並約定被告若\n    有任何一宗債務不依約付息或清償本金時，無須經原告通知或催告，即喪失一切\n    債務之期限利益，全部債務視為到期，並立有借據二紙及授信約定書三紙在卷可\n    稽。詎被告建恆海運股份有限公司本息僅繳至九十二年三月十一日止，依約應視\n    為全部到期，尚欠原告如主文欄第一項所示本金、利息（調降為年息七點四五）\n    及違約金。被告乙○○、丙○○二人既為連帶保證人，原告並依連帶保證之法律\n    關係請求負連帶償還責任。故請求判決如聲明所示。\n三、證據：提出借據二及授信約定書三紙為證。\n乙、被告方面：\n    被告均未於言詞辯論期日到場，亦未提出書狀作何聲明或陳述。\n    理      由\n一、按訴狀送達後，原告不得將原訴變更或追加他訴，但擴張或減縮應受判決事項之\n    聲明者，不在此限，民事訴訟法第二百五十五條第一項第三款定有明文。經查：\n    本件原告起訴時原請求被告給付自九十二年四月十一日起算之利息，於訴訟進行\n    中，減縮聲明為自九十二年四月十二日起算之法定利息，依前揭法條所示，應予\n    准許，合先敘明。\n二、本件被告均未於言詞辯論期日到場，核無民事訴訟法第三百八十六條各款所列情\n    形，爰依原告之聲請，由其一造辯論而為判決。\n三、本件原告主張之事實，已據其提出借據二紙及授信約定書三紙為證，被告經合法\n    通知，既不於言詞辯論期日到庭爭執，復未提出書狀以供本院斟酌，自堪信原告\n    之主張為真正。\n四、從而原告依消費借貸及連帶保證契約請求被告連帶給付借款仟佰伍拾肆萬\n    仟玖佰拾柒元，及自九十二年三月十一日起至清償日止，按年息百分之七點四\n    五計算之利息，並自九十二年四月十二日起至清償日止，其逾期在六個月以內者\n    ，按上開利率百分之十，其逾期超過六個月者，按上開利率百分之二十計算之違\n    約金，為有理由，應予准許。\n五、原告陳明願供擔保，請求宣告假執行，核無不合，茲酌定相當之擔保金額，予以\n    准許。\n六、本件原告之訴為有理由，依民事訴訟法第三百八十五條第一項前段、第八十五條\n    第二項、第三百九十條第二項，判決如主文。\n中      華      民      國    九十三    年      二      月    二十三    日\n                                  臺灣臺中地方法院民事第四庭\n                                              法      官  王有民\n右為正本係照原本作成\n如對本判決上訴，須於判決送達後廿日內向本院提出上訴狀\n中      華      民      國    九十三    年      二      月    二十六    日\n                                              法院書記官\n",
  "structure": {
    "main": "被告應連帶給付原告新台幣仟佰伍拾肆萬仟玖佰拾柒元，及自民國九十二年\n三月十一日起至清償日止，按年息百分之七點四五計算之利息，並自民國九十二年四\n月十二日起至清償日止，其逾期在六個月以內者，按上開利率百分之十，其逾期超過\n六個月者，按上開利率百分之二十計算之違約金。\n訴訟費用由被告連帶負擔。\n本判決第一項於原告以新台幣壹仟壹佰壹拾伍萬元為被告供擔保後，得假執行。",
    "fact": "甲、原告方面：\n一、聲明：求為判決除假執行擔保金額外，如主文所示。\n二、陳述略稱：被告建恒海運股份有限公司以其餘被告為連帶保證人，於民國九十年\n    四月二十五日向原告借用新台幣（下同）仟伍佰肆拾玖萬壹仟柒佰伍拾貳元、\n    貳仟捌佰萬零仟佰玖拾元二筆借款，約定利息均按年息百分之七點九點計\n    算，逾期清償在六個月以內者，按上開利率百分之十，在六個月以上者，按上開\n    利率百分之二十計付違約金，清償期為民國九十三年九月十一日。並約定被告若\n    有任何一宗債務不依約付息或清償本金時，無須經原告通知或催告，即喪失一切\n    債務之期限利益，全部債務視為到期，並立有借據二紙及授信約定書三紙在卷可\n    稽。詎被告建恆海運股份有限公司本息僅繳至九十二年三月十一日止，依約應視\n    為全部到期，尚欠原告如主文欄第一項所示本金、利息（調降為年息七點四五）\n    及違約金。被告乙○○、丙○○二人既為連帶保證人，原告並依連帶保證之法律\n    關係請求負連帶償還責任。故請求判決如聲明所示。\n三、證據：提出借據二及授信約定書三紙為證。\n乙、被告方面：\n    被告均未於言詞辯論期日到場，亦未提出書狀作何聲明或陳述。",
    "reason": "一、按訴狀送達後，原告不得將原訴變更或追加他訴，但擴張或減縮應受判決事項之\n    聲明者，不在此限，民事訴訟法第二百五十五條第一項第三款定有明文。經查：\n    本件原告起訴時原請求被告給付自九十二年四月十一日起算之利息，於訴訟進行\n    中，減縮聲明為自九十二年四月十二日起算之法定利息，依前揭法條所示，應予\n    准許，合先敘明。\n二、本件被告均未於言詞辯論期日到場，核無民事訴訟法第三百八十六條各款所列情\n    形，爰依原告之聲請，由其一造辯論而為判決。\n三、本件原告主張之事實，已據其提出借據二紙及授信約定書三紙為證，被告經合法\n    通知，既不於言詞辯論期日到庭爭執，復未提出書狀以供本院斟酌，自堪信原告\n    之主張為真正。\n四、從而原告依消費借貸及連帶保證契約請求被告連帶給付借款仟佰伍拾肆萬\n    仟玖佰拾柒元，及自九十二年三月十一日起至清償日止，按年息百分之七點四\n    五計算之利息，並自九十二年四月十二日起至清償日止，其逾期在六個月以內者\n    ，按上開利率百分之十，其逾期超過六個月者，按上開利率百分之二十計算之違\n    約金，為有理由，應予准許。\n五、原告陳明願供擔保，請求宣告假執行，核無不合，茲酌定相當之擔保金額，予以\n    准許。\n六、本件原告之訴為有理由，依民事訴訟法第三百八十五條第一項前段、第八十五條\n    第二項、第三百九十條第二項，判決如主文。\n中      華      民      國    九十三    年      二      月    二十三    日\n                                  臺灣臺中地方法院民事第四庭\n                                              法      官  王有民\n右為正本係照原本作成\n如對本判決上訴，須於判決送達後廿日內向本院提出上訴狀"
  },
  "search": "臺灣臺中地方法院民事判決九十二年度重訴字第六七三號原告聯信商業銀行股份有限公司法定代理人甲○○訴訟代理人丁○○被告建恒海運股份有限公司?兼法定代理人乙○○?被告丙○○右當事人間請求清償借款事件，於民國九十三年二月九日言詞辯論終結，本院判決如左：主文被告應連帶給付原告新台幣仟佰伍拾肆萬仟玖佰拾柒元，及自民國九十二年三月十一日起至清償日止，按年息百分之七點四五計算之利息，並自民國九十二年四月十二日起至清償日止，其逾期在六個月以內者，按上開利率百分之十，其逾期超過六個月者，按上開利率百分之二十計算之違約金。訴訟費用由被告連帶負擔。本判決第一項於原告以新台幣壹仟壹佰壹拾伍萬元為被告供擔保後，得假執行。事實甲、原告方面：一、聲明：求為判決除假執行擔保金額外，如主文所示。二、陳述略稱：被告建恒海運股份有限公司以其餘被告為連帶保證人，於民國九十年四月二十五日向原告借用新台幣（下同）仟伍佰肆拾玖萬壹仟柒佰伍拾貳元、貳仟捌佰萬零仟佰玖拾元二筆借款，約定利息均按年息百分之七點九點計算，逾期清償在六個月以內者，按上開利率百分之十，在六個月以上者，按上開利率百分之二十計付違約金，清償期為民國九十三年九月十一日。並約定被告若有任何一宗債務不依約付息或清償本金時，無須經原告通知或催告，即喪失一切債務之期限利益，全部債務視為到期，並立有借據二紙及授信約定書三紙在卷可稽。詎被告建恆海運股份有限公司本息僅繳至九十二年三月十一日止，依約應視為全部到期，尚欠原告如主文欄第一項所示本金、利息（調降為年息七點四五）及違約金。被告乙○○、丙○○二人既為連帶保證人，原告並依連帶保證之法律關係請求負連帶償還責任。故請求判決如聲明所示。三、證據：提出借據二及授信約定書三紙為證。乙、被告方面：被告均未於言詞辯論期日到場，亦未提出書狀作何聲明或陳述。理由一、按訴狀送達後，原告不得將原訴變更或追加他訴，但擴張或減縮應受判決事項之聲明者，不在此限，民事訴訟法第二百五十五條第一項第三款定有明文。經查：本件原告起訴時原請求被告給付自九十二年四月十一日起算之利息，於訴訟進行中，減縮聲明為自九十二年四月十二日起算之法定利息，依前揭法條所示，應予准許，合先敘明。二、本件被告均未於言詞辯論期日到場，核無民事訴訟法第三百八十六條各款所列情形，爰依原告之聲請，由其一造辯論而為判決。三、本件原告主張之事實，已據其提出借據二紙及授信約定書三紙為證，被告經合法通知，既不於言詞辯論期日到庭爭執，復未提出書狀以供本院斟酌，自堪信原告之主張為真正。四、從而原告依消費借貸及連帶保證契約請求被告連帶給付借款仟佰伍拾肆萬仟玖佰拾柒元，及自九十二年三月十一日起至清償日止，按年息百分之七點四五計算之利息，並自九十二年四月十二日起至清償日止，其逾期在六個月以內者，按上開利率百分之十，其逾期超過六個月者，按上開利率百分之二十計算之違約金，為有理由，應予准許。五、原告陳明願供擔保，請求宣告假執行，核無不合，茲酌定相當之擔保金額，予以准許。六、本件原告之訴為有理由，依民事訴訟法第三百八十五條第一項前段、第八十五條第二項、第三百九十條第二項，判決如主文。中華民國九十三年二月二十三日臺灣臺中地方法院民事第四庭法官王有民右為正本係照原本作成如對本判決上訴，須於判決送達後廿日內向本院提出上訴狀中華民國九十三年二月二十六日法院書記官",
  "characters": {
    "judges": [
      "王有民"
    ],
    "prosecutors": [

    ],
    "lawyers": [

    ],
    "clerks": [
      "法院"
    ],
    "plaintiffs": [
      "聯信商業銀行股份有限公司"
    ],
    "defendants": [
      "建恒海運股份有限公司",
      "?",
      "丙○○",
      "右當事人間請求清償借款事件，於民國九十三年二月九日言詞辯論終結，本院判決如",
      "左："
    ],
    "prosecutor_office": [

    ],
    "creditors": [

    ],
    "debtors": [

    ],
    "judicial_associate_officer": [

    ]
  },
  "adjudged_at": "2004-02-23",
  "created_at": "2016-02-05 22:23:35",
  "updated_at": "2016-02-05 22:23:35"
}