{
  "identify": "TPH-100-聲-1859-20110627-1",
  "court": {
    "name": "臺灣高等法院",
    "code": "TPH"
  },
  "division": {
    "name": "刑事",
    "code": "M"
  },
  "year": 100,
  "word": "聲",
  "number": "1859",
  "jcheck": "1",
  "reason": "保護管束",
  "content": "臺灣高等法院刑事裁定                 100年度聲字第1859號\n聲  請  人  臺灣高等法院檢察署檢察官\n受  刑  人  簡炳源\n上列聲請人因受刑人竊盜等案件，聲請付保護管束（100 年度執\n聲付字第637號），本院裁定如下：\n    主  文\n簡炳源假釋中付保護管束。\n    理  由\n一、聲請意旨略以：受刑人簡炳源因違反毒品危害防制條例案件\n    ，經臺灣士林地方法院96年度易字第1002號判決判處有期徒\n    刑8月，減為有期徒刑4月確定。復因犯竊盜等罪，經本院97\n    年度上訴字第75號判決判處應執行刑為有期徒刑5 年確定。\n    上開各罪，經本院97年度聲字第2499號裁定定其應執行刑為\n    有期徒刑5年2月確定。於民國97年7月4日送監執行，嗣經法\n    務部於100年6月17日核准假釋在案，依刑法第93條第2 項規\n    定假釋出獄者，在假釋中付保護管束，爰依刑事訴訟法第48\n    1條第1項規定聲請裁定等語。\n二、按94年2月2日修正公布，95年7月1日施行之刑法第96條有關\n    保護管束之規定，其於修正前、後之文字用語，雖已略有不\n    同（即修正前係規定：「保安處分於裁判時併宣告之。但因\n    假釋或於刑之赦免後，付保安處分者，不在此限」，修正後\n    則規定：「保安處分於裁判時併宣告之。但本法或其他法律\n    另有規定者，不在此限」），然考其修正理由，上開文字之\n    更動並非意在排除假釋期間付保護管束之宣告；參以刑法第\n    93條第2 項「假釋出獄者，在假釋中付保護管束」之規定，\n    無論於修正前、後，其文字俱未變動，足見對於「假釋期間\n    宣告保護管束」而言，新、舊法律並未異其旨趣。茲修法前\n    、後就此部分之規範既無不同，上開文字用語之更動，即非\n    法律之修正可比，此亦非刑罰科刑規範變更範疇，自不生新\n    、舊法律比較適用之問題，應適用現行有效之法律規定。\n三、本院審核卷附法務部矯正署100年6月17日法授矯字第100011\n    20511 號函、法務部矯正署臺東監獄泰源分監假釋出獄人交\n    付保護管束名冊、刑案資料查註紀錄表等件，認聲請人之聲\n    請為正當，於法有據。\n據上論斷，應依刑事訴訟法第481條第1項，刑法第96條但書、第\n93條第2項，裁定如主文。\n中    華    民    國    100    年    6    月    27    日\n                  刑事第十五庭  審判長法  官  沈宜生\n                                      法  官  林明俊\n                                      法  官  吳炳桂\n以上正本證明與原本無異。\n不得抗告。\n                                      書記官  劉育君\n中    華    民    國   100    年    6     月    28    日",
  "structure": {
    "main": "簡炳源假釋中付保護管束。",
    "reason": "一、聲請意旨略以：受刑人簡炳源因違反毒品危害防制條例案件\n    ，經臺灣士林地方法院96年度易字第1002號判決判處有期徒\n    刑8月，減為有期徒刑4月確定。復因犯竊盜等罪，經本院97\n    年度上訴字第75號判決判處應執行刑為有期徒刑5 年確定。\n    上開各罪，經本院97年度聲字第2499號裁定定其應執行刑為\n    有期徒刑5年2月確定。於民國97年7月4日送監執行，嗣經法\n    務部於100年6月17日核准假釋在案，依刑法第93條第2 項規\n    定假釋出獄者，在假釋中付保護管束，爰依刑事訴訟法第48\n    1條第1項規定聲請裁定等語。\n二、按94年2月2日修正公布，95年7月1日施行之刑法第96條有關\n    保護管束之規定，其於修正前、後之文字用語，雖已略有不\n    同（即修正前係規定：「保安處分於裁判時併宣告之。但因\n    假釋或於刑之赦免後，付保安處分者，不在此限」，修正後\n    則規定：「保安處分於裁判時併宣告之。但本法或其他法律\n    另有規定者，不在此限」），然考其修正理由，上開文字之\n    更動並非意在排除假釋期間付保護管束之宣告；參以刑法第\n    93條第2 項「假釋出獄者，在假釋中付保護管束」之規定，\n    無論於修正前、後，其文字俱未變動，足見對於「假釋期間\n    宣告保護管束」而言，新、舊法律並未異其旨趣。茲修法前\n    、後就此部分之規範既無不同，上開文字用語之更動，即非\n    法律之修正可比，此亦非刑罰科刑規範變更範疇，自不生新\n    、舊法律比較適用之問題，應適用現行有效之法律規定。\n三、本院審核卷附法務部矯正署100年6月17日法授矯字第100011\n    20511 號函、法務部矯正署臺東監獄泰源分監假釋出獄人交\n    付保護管束名冊、刑案資料查註紀錄表等件，認聲請人之聲\n    請為正當，於法有據。\n據上論斷，應依刑事訴訟法第481條第1項，刑法第96條但書、第\n93條第2項，裁定如主文。"
  },
  "search": "臺灣高等法院刑事裁定100年度聲字第1859號聲請人臺灣高等法院檢察署檢察官受刑人簡炳源上列聲請人因受刑人竊盜等案件，聲請付保護管束（100年度執聲付字第637號），本院裁定如下：主文簡炳源假釋中付保護管束。理由一、聲請意旨略以：受刑人簡炳源因違反毒品危害防制條例案件，經臺灣士林地方法院96年度易字第1002號判決判處有期徒刑8月，減為有期徒刑4月確定。復因犯竊盜等罪，經本院97年度上訴字第75號判決判處應執行刑為有期徒刑5年確定。上開各罪，經本院97年度聲字第2499號裁定定其應執行刑為有期徒刑5年2月確定。於民國97年7月4日送監執行，嗣經法務部於100年6月17日核准假釋在案，依刑法第93條第2項規定假釋出獄者，在假釋中付保護管束，爰依刑事訴訟法第481條第1項規定聲請裁定等語。二、按94年2月2日修正公布，95年7月1日施行之刑法第96條有關保護管束之規定，其於修正前、後之文字用語，雖已略有不同（即修正前係規定：「保安處分於裁判時併宣告之。但因假釋或於刑之赦免後，付保安處分者，不在此限」，修正後則規定：「保安處分於裁判時併宣告之。但本法或其他法律另有規定者，不在此限」），然考其修正理由，上開文字之更動並非意在排除假釋期間付保護管束之宣告；參以刑法第93條第2項「假釋出獄者，在假釋中付保護管束」之規定，無論於修正前、後，其文字俱未變動，足見對於「假釋期間宣告保護管束」而言，新、舊法律並未異其旨趣。茲修法前、後就此部分之規範既無不同，上開文字用語之更動，即非法律之修正可比，此亦非刑罰科刑規範變更範疇，自不生新、舊法律比較適用之問題，應適用現行有效之法律規定。三、本院審核卷附法務部矯正署100年6月17日法授矯字第10001120511號函、法務部矯正署臺東監獄泰源分監假釋出獄人交付保護管束名冊、刑案資料查註紀錄表等件，認聲請人之聲請為正當，於法有據。據上論斷，應依刑事訴訟法第481條第1項，刑法第96條但書、第93條第2項，裁定如主文。中華民國100年6月27日刑事第十五庭審判長法官沈宜生法官林明俊法官吳炳桂以上正本證明與原本無異。不得抗告。書記官劉育君中華民國100年6月28日",
  "characters": {
    "judges": [
      "沈宜生",
      "林明俊",
      "吳炳桂"
    ],
    "prosecutors": [

    ],
    "lawyers": [

    ],
    "clerks": [
      "劉育君"
    ],
    "plaintiffs": [

    ],
    "defendants": [

    ],
    "prosecutor_office": [
      "臺灣高等法院檢察署檢察官"
    ],
    "creditors": [

    ],
    "debtors": [

    ],
    "judicial_associate_officer": [

    ]
  },
  "adjudged_at": "2011-06-27",
  "created_at": "2016-02-13 15:09:55",
  "updated_at": "2016-02-13 15:09:55"
}