{
  "identify": "CHD-100-訴-112-20110414-1",
  "court": {
    "name": "臺灣彰化地方法院",
    "code": "CHD"
  },
  "division": {
    "name": "刑事",
    "code": "M"
  },
  "year": 100,
  "word": "訴",
  "number": "112",
  "jcheck": "1",
  "reason": "違反毒品危害防制條例",
  "content": "臺灣彰化地方法院刑事判決              100年度訴字第112號\n公  訴  人  臺灣彰化地方法院檢察署檢察官\n被      告  施清文\n上列被告因違反毒品危害防制條例案件，經檢察官提起公訴（99\n年度毒偵字第2117號），本院依簡式審判程序判決如下：\n    主  文\n施清文施用第一級毒品，累犯，處有期徒刑捌月。又施用第二級\n毒品，累犯，處有期徒刑肆月；扣案之甲基安非他命壹包（驗餘\n淨重貳點零零壹公克）及其包裝袋沒收銷燬之。主刑部分應執\n行有期徒刑壹年。\n    犯罪事實\n一、施清文前於民國88年間，因施用毒品案件，經裁定移送觀察\n    、勒戒後，認無繼續施用毒品之傾向，於88年2月24日執行\n    完畢釋放；同年間，再因施用毒品案件，經本院以88年度毒\n    聲字第1518號裁定送觀察、勒戒後，認有繼續施用毒品之傾\n    向，再經以88年度毒聲字第1851號裁定令入戒治處所施以強\n    制戒治，嗣因執行成效經評定為合格，經本院以88年度毒聲\n    字第4032號裁定停止戒治，於88年10月21日停止戒治出監，\n    所餘戒治期間付保護管束，迄89年5月3日保護管束期滿未經\n    撤銷，強制戒治視為執行完畢，並由臺灣彰化地方法院檢察\n    署檢察官以89年度戒毒偵字第626號為不起訴處分確定。其\n    後又因重傷害案件，經本院以94年度訴字第1180號判處有期\n    徒刑1年9月，經上訴後，再經臺灣高等法院臺中分院以94年\n    上訴字第2675號判決上訴駁回確定，入監服刑後，於96年12\n    月11日假釋出監付保護管束，於97年3月29日保護管束期滿\n    未經撤銷其假釋，而視為執行完畢。\n二、詎施清文仍不思悔改，又基於施用第一級毒品海洛因之犯意\n    ，於99年11月2 日為警查獲前4 日內之某時，在其友人位於\n    彰化縣鹿港鎮「富麗大鎮」公寓大樓之住處內，以將海洛因\n    粉末摻入香菸內點燃吸食煙霧之方式，施用第一級毒品海洛\n    因1 次。又基於施用第二級毒品甲基安非他命之犯意，於99\n    年11月2 日下午約2 至3 時許，在同上地址，以將甲基安非\n    他命置於玻璃管內點火燒烤成煙霧狀後再吸入體內之方式，\n    施用第二級毒品甲基安非他命1 次。嗣於99年11月2 日下午\n    3 時8 分許，適被告騎車搭載友人鄭俊利，因闖紅燈之違規\n    則為，在彰化縣鹿港鎮○○路197 號前，經警攔停進行盤查\n    ，並當場在被告上衣口袋內之小鐵盒查獲被告所有之甲基安\n    非他命1 包（原毛重2.45公克，驗餘淨重2.0301公克），且\n    經警採取被告尿液檢體送驗，結果呈現嗎啡及甲基安非他命\n    之陽性反應，而查悉上情。\n三、案經彰化縣警察局報請臺灣彰化地方法院檢察署檢察官偵查\n    起訴。\n    理  由\n一、本件被告施清文所犯係死刑、無期徒刑、最輕本刑為3年以\n    上有期徒刑以外之罪，其於準備程序就前揭被訴事實為有罪\n    之陳述，經受命法官告知簡式審判程序之旨，並聽取其與公\n    訴人之意見後，本院認無不得或不宜改依簡式審判程序進行\n    之處，爰依刑事訴訟法第273條之1第1項、第284條之1，裁\n    定本案由受命法官獨任進行簡式審判程序，合先敘明。\n二、上開犯罪事實，有下列證據可資證明：\n    (一)彰化縣警察局委託檢驗尿液代號與真實姓名對照認證單\n        。\n    (二)詮昕科技股份有限公司濫用藥物尿液檢驗報告。\n    (三)扣案之甲基安非他命1包（驗餘淨重2.0301公克），及\n        行政院衛生署草屯療養院鑑定書。\n    (四)臺灣高等法院被告前案紀錄表，及偵卷所附刑案資料查\n        註紀錄表。\n    (五)被告於本院審理時之自白。\n    (六)關於毒品經人體代謝可檢出之期間，依文獻記載：毒品\n        施用後於尿液液中可檢出之時間，受施用劑量及頻率、\n        施用方式、飲水量之多寡、個人體質及代謝情況等因素\n        影響，因個案而異。一般可檢出之時間為海洛因服用後\n        2 至4 天，甲基安非他命為1 至5 天（行政院衛生署管\n        制藥品管理局92年3 月10日管檢字第0920001495號（參\n        照司法院編印法官辦理刑事案件參考手冊(一)毒品危害防\n        制條例部分，第141 至142 頁）。被告於本院審理時雖\n        陳稱只記得伊在為警查獲前幾天有施用海洛因，惟忘記\n        實際日期為何，然依上述文獻資料可推算被告施用海洛\n        因之日期係在為警查獲前4 日內。\n三、論罪科刑：\n    (一)按施用第一、二級毒品為犯罪行為，毒品危害防制條例\n        第10條第1項及第2項各定有處罰明文。故施用該毒品者\n        ，依前揭規定本應科以刑罰，惟基於施用毒品之人，兼\n        有病患屬性，乃於刑事政策上對合於一定條件之施用者\n        ，依同條例第20條、第23條之規定，施以觀察、勒戒及\n        強制戒治之治療，期以保安處分替代刑罰，戒斷其身、\n        心癮。嗣因其程序過於繁雜，上揭條例於民國92年7月\n        9日修正公布，自93年1月9日施行，將該條例第20條、\n        第23條之保安處分程序，單純區分為「初犯」、「5年\n        內再犯」及「5年後再犯」三種；依其立法理由之說明\n        ：「初犯」，經觀察、勒戒或強制戒治後，應為不起訴\n        處分或不付審理之裁定；經觀察、勒戒或強制戒治執行\n        完畢釋放後，「5年內再犯」者，因其再犯率甚高，原\n        實施之觀察、勒戒及強制戒治既已無法收其實效，爰依\n        法追訴或裁定交付審理。至於經觀察、勒戒或強制戒治\n        執行完畢釋放後，「5年後再犯」者，前所實施之觀察\n        、勒戒或強制戒治已足以遮斷其施用毒品之毒癮，為期\n        自新及協助其斷除毒癮，仍適用「初犯」規定，先經觀\n        察、勒戒或強制戒治之程序。從而依修正後之規定，僅\n        限於「初犯」及「5年後再犯」二種情形，始應先經觀\n        察、勒戒或強制戒治程序，不能逕行起訴，亦即設為施\n        用毒品罪起訴條件之限制。但倘被告於5年內已再犯，\n        經依法再為保安處分或追訴處罰者，縱其第3次（或第\n        3次以上）施用毒品之時間，在初犯之保安處分執行完\n        畢釋放後5年以後，即非屬「5年後再犯」之情形，且因\n        前有「5年內再犯」情形，顯見其再犯率甚高，原實施\n        之保安處分無法收其實效，毋庸仍予寬典處遇，而應依\n        該條例第10條逕予刑罰制裁；此為最高法院近來之統一\n        見解（最高法院99年度台非字第277號判決參照、同旨\n        見最高法院99年台上字第5726號、98年台非字第240、1\n        2號、98年台上字第7296號、97年台非字第540、406、3\n        42號判決）。查本件被告前因施用毒品案件，經送觀察\n        勒戒執行完畢釋放後5年內，仍因施用毒品犯行而再遭\n        送觀察勒戒、強制戒治等保安處分之執行（參見犯罪事\n        實欄所載），是本件被告於第一次觀察、勒戒後5 內，\n        又因施用毒品案件再受觀察、勒戒及強制戒治，是其並\n        不合於「5 年後再犯」之規定，揆諸上開說明，被告所\n        為已符合毒品危害防制條第23條第2 項之所定之追訴要\n        件，並無「初犯」規定之適用，自毋須再重新施予觀察\n        、勒戒之處遇程序，而應直接訴追處罰。\n    (二)核被告所為，係犯毒品危害防制條例第10條第1項之施\n        用第一級毒品罪，及同條第2項之施用第二級毒品罪。\n        被告於施用前持有第一、二級毒品之低度行為，應為施\n        用之高度行為所吸收，不另論罪。被告所犯前揭2罪，\n        犯意各別，行為互殊，應分論併罰。\n    (三)被告之前案紀錄，有臺灣高等法院被告前案紀錄表，及\n        偵卷所附刑案資料查註紀錄表在卷可參。其於上開案件\n        有期徒刑之刑執行完畢後5年以內故意再犯本件有期徒\n        刑刑以上之2罪，均為累犯，應各依刑法第47條第1項之\n        規定，加重其刑。\n    (四)爰審酌被告前曾施用毒品，經送觀察勒戒、強制戒治等\n        處分後，猶未能戒除毒癮，而再為本件施用毒品之犯行\n        ，尚乏禁絕毒害之決心，惟其於本院審理時尚能坦認犯\n        行，頗有悔悟之心，暨審酌被告之智識程度、素行紀錄\n        等一切情狀，量處如主文所示之刑，並定其應執行之刑\n        ，以資儆懲。\n四、沒收：\n    扣案之甲基安非他命1包（驗餘淨重2.0301公克），為第二\n    級毒品，該毒品與其無法析離之包裝袋，均應依毒品危害防\n    制條例第18條第1項前段宣告沒收銷燬之。\n五、如不服本判決應於收受判決後10日內向本院提出上訴書狀，\n    並應敘述具體理由。其未敘述上訴理由者，應於上訴期間屆\n    滿後20日內向本院補提理由書（須附繕本），切勿逕送上級\n    法院。\n據上論斷，應依刑事訴訟法第273條之1第1項、第299條第1項前\n段、第310條之2、第454條第1項，毒品危害防制條例第10條第1\n項、第2項、第18條第1項前段，刑法第11條、第47條第1項、第5\n1條第5款，判決如主文。\n本案經檢察官賴志盛到庭執行職務。\n中    華    民    國  100     年    4     月    14    日\n                  刑事第七庭          法  官  黃玉齡\n以上正本證明與原本無異。\n如不服本判決，應於收受判決後10日內向本院提出上訴書狀，並\n應敘述具體理由；其未敘述上訴理由者，應於上訴期間屆滿後20\n日內向本院補提理由書（均須按他造當事人之人數附繕本「切勿\n逕送上級法院」）。\n中    華    民    國  100     年    4     月    14    日\n                                      書記官  黃鏽金\n附錄論罪科刑法條：\n毒品危害防制條例第10條\n施用第一級毒品者，處 6 月以上 5 年以下有期徒刑。\n施用第二級毒品者，處 3 年以下有期徒刑。",
  "structure": {
    "main": "施清文施用第一級毒品，累犯，處有期徒刑捌月。又施用第二級\n毒品，累犯，處有期徒刑肆月；扣案之甲基安非他命壹包（驗餘\n淨重貳點零零壹公克）及其包裝袋沒收銷燬之。主刑部分應執\n行有期徒刑壹年。",
    "fact": "一、施清文前於民國88年間，因施用毒品案件，經裁定移送觀察\n    、勒戒後，認無繼續施用毒品之傾向，於88年2月24日執行\n    完畢釋放；同年間，再因施用毒品案件，經本院以88年度毒\n    聲字第1518號裁定送觀察、勒戒後，認有繼續施用毒品之傾\n    向，再經以88年度毒聲字第1851號裁定令入戒治處所施以強\n    制戒治，嗣因執行成效經評定為合格，經本院以88年度毒聲\n    字第4032號裁定停止戒治，於88年10月21日停止戒治出監，\n    所餘戒治期間付保護管束，迄89年5月3日保護管束期滿未經\n    撤銷，強制戒治視為執行完畢，並由臺灣彰化地方法院檢察\n    署檢察官以89年度戒毒偵字第626號為不起訴處分確定。其\n    後又因重傷害案件，經本院以94年度訴字第1180號判處有期\n    徒刑1年9月，經上訴後，再經臺灣高等法院臺中分院以94年\n    上訴字第2675號判決上訴駁回確定，入監服刑後，於96年12\n    月11日假釋出監付保護管束，於97年3月29日保護管束期滿\n    未經撤銷其假釋，而視為執行完畢。\n二、詎施清文仍不思悔改，又基於施用第一級毒品海洛因之犯意\n    ，於99年11月2 日為警查獲前4 日內之某時，在其友人位於\n    彰化縣鹿港鎮「富麗大鎮」公寓大樓之住處內，以將海洛因\n    粉末摻入香菸內點燃吸食煙霧之方式，施用第一級毒品海洛\n    因1 次。又基於施用第二級毒品甲基安非他命之犯意，於99\n    年11月2 日下午約2 至3 時許，在同上地址，以將甲基安非\n    他命置於玻璃管內點火燒烤成煙霧狀後再吸入體內之方式，\n    施用第二級毒品甲基安非他命1 次。嗣於99年11月2 日下午\n    3 時8 分許，適被告騎車搭載友人鄭俊利，因闖紅燈之違規\n    則為，在彰化縣鹿港鎮○○路197 號前，經警攔停進行盤查\n    ，並當場在被告上衣口袋內之小鐵盒查獲被告所有之甲基安\n    非他命1 包（原毛重2.45公克，驗餘淨重2.0301公克），且\n    經警採取被告尿液檢體送驗，結果呈現嗎啡及甲基安非他命\n    之陽性反應，而查悉上情。\n三、案經彰化縣警察局報請臺灣彰化地方法院檢察署檢察官偵查\n    起訴。\n    理  由\n一、本件被告施清文所犯係死刑、無期徒刑、最輕本刑為3年以\n    上有期徒刑以外之罪，其於準備程序就前揭被訴事實為有罪\n    之陳述，經受命法官告知簡式審判程序之旨，並聽取其與公\n    訴人之意見後，本院認無不得或不宜改依簡式審判程序進行\n    之處，爰依刑事訴訟法第273條之1第1項、第284條之1，裁\n    定本案由受命法官獨任進行簡式審判程序，合先敘明。\n二、上開犯罪事實，有下列證據可資證明：\n    (一)彰化縣警察局委託檢驗尿液代號與真實姓名對照認證單\n        。\n    (二)詮昕科技股份有限公司濫用藥物尿液檢驗報告。\n    (三)扣案之甲基安非他命1包（驗餘淨重2.0301公克），及\n        行政院衛生署草屯療養院鑑定書。\n    (四)臺灣高等法院被告前案紀錄表，及偵卷所附刑案資料查\n        註紀錄表。\n    (五)被告於本院審理時之自白。\n    (六)關於毒品經人體代謝可檢出之期間，依文獻記載：毒品\n        施用後於尿液液中可檢出之時間，受施用劑量及頻率、\n        施用方式、飲水量之多寡、個人體質及代謝情況等因素\n        影響，因個案而異。一般可檢出之時間為海洛因服用後\n        2 至4 天，甲基安非他命為1 至5 天（行政院衛生署管\n        制藥品管理局92年3 月10日管檢字第0920001495號（參\n        照司法院編印法官辦理刑事案件參考手冊(一)毒品危害防\n        制條例部分，第141 至142 頁）。被告於本院審理時雖\n        陳稱只記得伊在為警查獲前幾天有施用海洛因，惟忘記\n        實際日期為何，然依上述文獻資料可推算被告施用海洛\n        因之日期係在為警查獲前4 日內。\n三、論罪科刑：\n    (一)按施用第一、二級毒品為犯罪行為，毒品危害防制條例\n        第10條第1項及第2項各定有處罰明文。故施用該毒品者\n        ，依前揭規定本應科以刑罰，惟基於施用毒品之人，兼\n        有病患屬性，乃於刑事政策上對合於一定條件之施用者\n        ，依同條例第20條、第23條之規定，施以觀察、勒戒及\n        強制戒治之治療，期以保安處分替代刑罰，戒斷其身、\n        心癮。嗣因其程序過於繁雜，上揭條例於民國92年7月\n        9日修正公布，自93年1月9日施行，將該條例第20條、\n        第23條之保安處分程序，單純區分為「初犯」、「5年\n        內再犯」及「5年後再犯」三種；依其立法理由之說明\n        ：「初犯」，經觀察、勒戒或強制戒治後，應為不起訴\n        處分或不付審理之裁定；經觀察、勒戒或強制戒治執行\n        完畢釋放後，「5年內再犯」者，因其再犯率甚高，原\n        實施之觀察、勒戒及強制戒治既已無法收其實效，爰依\n        法追訴或裁定交付審理。至於經觀察、勒戒或強制戒治\n        執行完畢釋放後，「5年後再犯」者，前所實施之觀察\n        、勒戒或強制戒治已足以遮斷其施用毒品之毒癮，為期\n        自新及協助其斷除毒癮，仍適用「初犯」規定，先經觀\n        察、勒戒或強制戒治之程序。從而依修正後之規定，僅\n        限於「初犯」及「5年後再犯」二種情形，始應先經觀\n        察、勒戒或強制戒治程序，不能逕行起訴，亦即設為施\n        用毒品罪起訴條件之限制。但倘被告於5年內已再犯，\n        經依法再為保安處分或追訴處罰者，縱其第3次（或第\n        3次以上）施用毒品之時間，在初犯之保安處分執行完\n        畢釋放後5年以後，即非屬「5年後再犯」之情形，且因\n        前有「5年內再犯」情形，顯見其再犯率甚高，原實施\n        之保安處分無法收其實效，毋庸仍予寬典處遇，而應依\n        該條例第10條逕予刑罰制裁；此為最高法院近來之統一\n        見解（最高法院99年度台非字第277號判決參照、同旨\n        見最高法院99年台上字第5726號、98年台非字第240、1\n        2號、98年台上字第7296號、97年台非字第540、406、3\n        42號判決）。查本件被告前因施用毒品案件，經送觀察\n        勒戒執行完畢釋放後5年內，仍因施用毒品犯行而再遭\n        送觀察勒戒、強制戒治等保安處分之執行（參見犯罪事\n        實欄所載），是本件被告於第一次觀察、勒戒後5 內，\n        又因施用毒品案件再受觀察、勒戒及強制戒治，是其並\n        不合於「5 年後再犯」之規定，揆諸上開說明，被告所\n        為已符合毒品危害防制條第23條第2 項之所定之追訴要\n        件，並無「初犯」規定之適用，自毋須再重新施予觀察\n        、勒戒之處遇程序，而應直接訴追處罰。\n    (二)核被告所為，係犯毒品危害防制條例第10條第1項之施\n        用第一級毒品罪，及同條第2項之施用第二級毒品罪。\n        被告於施用前持有第一、二級毒品之低度行為，應為施\n        用之高度行為所吸收，不另論罪。被告所犯前揭2罪，\n        犯意各別，行為互殊，應分論併罰。\n    (三)被告之前案紀錄，有臺灣高等法院被告前案紀錄表，及\n        偵卷所附刑案資料查註紀錄表在卷可參。其於上開案件\n        有期徒刑之刑執行完畢後5年以內故意再犯本件有期徒\n        刑刑以上之2罪，均為累犯，應各依刑法第47條第1項之\n        規定，加重其刑。\n    (四)爰審酌被告前曾施用毒品，經送觀察勒戒、強制戒治等\n        處分後，猶未能戒除毒癮，而再為本件施用毒品之犯行\n        ，尚乏禁絕毒害之決心，惟其於本院審理時尚能坦認犯\n        行，頗有悔悟之心，暨審酌被告之智識程度、素行紀錄\n        等一切情狀，量處如主文所示之刑，並定其應執行之刑\n        ，以資儆懲。\n四、沒收：\n    扣案之甲基安非他命1包（驗餘淨重2.0301公克），為第二\n    級毒品，該毒品與其無法析離之包裝袋，均應依毒品危害防\n    制條例第18條第1項前段宣告沒收銷燬之。\n五、如不服本判決應於收受判決後10日內向本院提出上訴書狀，\n    並應敘述具體理由。其未敘述上訴理由者，應於上訴期間屆\n    滿後20日內向本院補提理由書（須附繕本），切勿逕送上級\n    法院。\n據上論斷，應依刑事訴訟法第273條之1第1項、第299條第1項前\n段、第310條之2、第454條第1項，毒品危害防制條例第10條第1\n項、第2項、第18條第1項前段，刑法第11條、第47條第1項、第5\n1條第5款，判決如主文。\n本案經檢察官賴志盛到庭執行職務。"
  },
  "search": "臺灣彰化地方法院刑事判決100年度訴字第112號公訴人臺灣彰化地方法院檢察署檢察官被告施清文上列被告因違反毒品危害防制條例案件，經檢察官提起公訴（99年度毒偵字第2117號），本院依簡式審判程序判決如下：主文施清文施用第一級毒品，累犯，處有期徒刑捌月。又施用第二級毒品，累犯，處有期徒刑肆月；扣案之甲基安非他命壹包（驗餘淨重貳點零零壹公克）及其包裝袋沒收銷燬之。主刑部分應執行有期徒刑壹年。犯罪事實一、施清文前於民國88年間，因施用毒品案件，經裁定移送觀察、勒戒後，認無繼續施用毒品之傾向，於88年2月24日執行完畢釋放；同年間，再因施用毒品案件，經本院以88年度毒聲字第1518號裁定送觀察、勒戒後，認有繼續施用毒品之傾向，再經以88年度毒聲字第1851號裁定令入戒治處所施以強制戒治，嗣因執行成效經評定為合格，經本院以88年度毒聲字第4032號裁定停止戒治，於88年10月21日停止戒治出監，所餘戒治期間付保護管束，迄89年5月3日保護管束期滿未經撤銷，強制戒治視為執行完畢，並由臺灣彰化地方法院檢察署檢察官以89年度戒毒偵字第626號為不起訴處分確定。其後又因重傷害案件，經本院以94年度訴字第1180號判處有期徒刑1年9月，經上訴後，再經臺灣高等法院臺中分院以94年上訴字第2675號判決上訴駁回確定，入監服刑後，於96年12月11日假釋出監付保護管束，於97年3月29日保護管束期滿未經撤銷其假釋，而視為執行完畢。二、詎施清文仍不思悔改，又基於施用第一級毒品海洛因之犯意，於99年11月2日為警查獲前4日內之某時，在其友人位於彰化縣鹿港鎮「富麗大鎮」公寓大樓之住處內，以將海洛因粉末摻入香菸內點燃吸食煙霧之方式，施用第一級毒品海洛因1次。又基於施用第二級毒品甲基安非他命之犯意，於99年11月2日下午約2至3時許，在同上地址，以將甲基安非他命置於玻璃管內點火燒烤成煙霧狀後再吸入體內之方式，施用第二級毒品甲基安非他命1次。嗣於99年11月2日下午3時8分許，適被告騎車搭載友人鄭俊利，因闖紅燈之違規則為，在彰化縣鹿港鎮○○路197號前，經警攔停進行盤查，並當場在被告上衣口袋內之小鐵盒查獲被告所有之甲基安非他命1包（原毛重2.45公克，驗餘淨重2.0301公克），且經警採取被告尿液檢體送驗，結果呈現嗎啡及甲基安非他命之陽性反應，而查悉上情。三、案經彰化縣警察局報請臺灣彰化地方法院檢察署檢察官偵查起訴。理由一、本件被告施清文所犯係死刑、無期徒刑、最輕本刑為3年以上有期徒刑以外之罪，其於準備程序就前揭被訴事實為有罪之陳述，經受命法官告知簡式審判程序之旨，並聽取其與公訴人之意見後，本院認無不得或不宜改依簡式審判程序進行之處，爰依刑事訴訟法第273條之1第1項、第284條之1，裁定本案由受命法官獨任進行簡式審判程序，合先敘明。二、上開犯罪事實，有下列證據可資證明：(一)彰化縣警察局委託檢驗尿液代號與真實姓名對照認證單。(二)詮昕科技股份有限公司濫用藥物尿液檢驗報告。(三)扣案之甲基安非他命1包（驗餘淨重2.0301公克），及行政院衛生署草屯療養院鑑定書。(四)臺灣高等法院被告前案紀錄表，及偵卷所附刑案資料查註紀錄表。(五)被告於本院審理時之自白。(六)關於毒品經人體代謝可檢出之期間，依文獻記載：毒品施用後於尿液液中可檢出之時間，受施用劑量及頻率、施用方式、飲水量之多寡、個人體質及代謝情況等因素影響，因個案而異。一般可檢出之時間為海洛因服用後2至4天，甲基安非他命為1至5天（行政院衛生署管制藥品管理局92年3月10日管檢字第0920001495號（參照司法院編印法官辦理刑事案件參考手冊(一)毒品危害防制條例部分，第141至142頁）。被告於本院審理時雖陳稱只記得伊在為警查獲前幾天有施用海洛因，惟忘記實際日期為何，然依上述文獻資料可推算被告施用海洛因之日期係在為警查獲前4日內。三、論罪科刑：(一)按施用第一、二級毒品為犯罪行為，毒品危害防制條例第10條第1項及第2項各定有處罰明文。故施用該毒品者，依前揭規定本應科以刑罰，惟基於施用毒品之人，兼有病患屬性，乃於刑事政策上對合於一定條件之施用者，依同條例第20條、第23條之規定，施以觀察、勒戒及強制戒治之治療，期以保安處分替代刑罰，戒斷其身、心癮。嗣因其程序過於繁雜，上揭條例於民國92年7月9日修正公布，自93年1月9日施行，將該條例第20條、第23條之保安處分程序，單純區分為「初犯」、「5年內再犯」及「5年後再犯」三種；依其立法理由之說明：「初犯」，經觀察、勒戒或強制戒治後，應為不起訴處分或不付審理之裁定；經觀察、勒戒或強制戒治執行完畢釋放後，「5年內再犯」者，因其再犯率甚高，原實施之觀察、勒戒及強制戒治既已無法收其實效，爰依法追訴或裁定交付審理。至於經觀察、勒戒或強制戒治執行完畢釋放後，「5年後再犯」者，前所實施之觀察、勒戒或強制戒治已足以遮斷其施用毒品之毒癮，為期自新及協助其斷除毒癮，仍適用「初犯」規定，先經觀察、勒戒或強制戒治之程序。從而依修正後之規定，僅限於「初犯」及「5年後再犯」二種情形，始應先經觀察、勒戒或強制戒治程序，不能逕行起訴，亦即設為施用毒品罪起訴條件之限制。但倘被告於5年內已再犯，經依法再為保安處分或追訴處罰者，縱其第3次（或第3次以上）施用毒品之時間，在初犯之保安處分執行完畢釋放後5年以後，即非屬「5年後再犯」之情形，且因前有「5年內再犯」情形，顯見其再犯率甚高，原實施之保安處分無法收其實效，毋庸仍予寬典處遇，而應依該條例第10條逕予刑罰制裁；此為最高法院近來之統一見解（最高法院99年度台非字第277號判決參照、同旨見最高法院99年台上字第5726號、98年台非字第240、12號、98年台上字第7296號、97年台非字第540、406、342號判決）。查本件被告前因施用毒品案件，經送觀察勒戒執行完畢釋放後5年內，仍因施用毒品犯行而再遭送觀察勒戒、強制戒治等保安處分之執行（參見犯罪事實欄所載），是本件被告於第一次觀察、勒戒後5內，又因施用毒品案件再受觀察、勒戒及強制戒治，是其並不合於「5年後再犯」之規定，揆諸上開說明，被告所為已符合毒品危害防制條第23條第2項之所定之追訴要件，並無「初犯」規定之適用，自毋須再重新施予觀察、勒戒之處遇程序，而應直接訴追處罰。(二)核被告所為，係犯毒品危害防制條例第10條第1項之施用第一級毒品罪，及同條第2項之施用第二級毒品罪。被告於施用前持有第一、二級毒品之低度行為，應為施用之高度行為所吸收，不另論罪。被告所犯前揭2罪，犯意各別，行為互殊，應分論併罰。(三)被告之前案紀錄，有臺灣高等法院被告前案紀錄表，及偵卷所附刑案資料查註紀錄表在卷可參。其於上開案件有期徒刑之刑執行完畢後5年以內故意再犯本件有期徒刑刑以上之2罪，均為累犯，應各依刑法第47條第1項之規定，加重其刑。(四)爰審酌被告前曾施用毒品，經送觀察勒戒、強制戒治等處分後，猶未能戒除毒癮，而再為本件施用毒品之犯行，尚乏禁絕毒害之決心，惟其於本院審理時尚能坦認犯行，頗有悔悟之心，暨審酌被告之智識程度、素行紀錄等一切情狀，量處如主文所示之刑，並定其應執行之刑，以資儆懲。四、沒收：扣案之甲基安非他命1包（驗餘淨重2.0301公克），為第二級毒品，該毒品與其無法析離之包裝袋，均應依毒品危害防制條例第18條第1項前段宣告沒收銷燬之。五、如不服本判決應於收受判決後10日內向本院提出上訴書狀，並應敘述具體理由。其未敘述上訴理由者，應於上訴期間屆滿後20日內向本院補提理由書（須附繕本），切勿逕送上級法院。據上論斷，應依刑事訴訟法第273條之1第1項、第299條第1項前段、第310條之2、第454條第1項，毒品危害防制條例第10條第1項、第2項、第18條第1項前段，刑法第11條、第47條第1項、第51條第5款，判決如主文。本案經檢察官賴志盛到庭執行職務。中華民國100年4月14日刑事第七庭法官黃玉齡以上正本證明與原本無異。如不服本判決，應於收受判決後10日內向本院提出上訴書狀，並應敘述具體理由；其未敘述上訴理由者，應於上訴期間屆滿後20日內向本院補提理由書（均須按他造當事人之人數附繕本「切勿逕送上級法院」）。中華民國100年4月14日書記官黃鏽金附錄論罪科刑法條：毒品危害防制條例第10條施用第一級毒品者，處6月以上5年以下有期徒刑。施用第二級毒品者，處3年以下有期徒刑。",
  "characters": {
    "judges": [
      "黃玉齡"
    ],
    "prosecutors": [
      "賴志盛"
    ],
    "lawyers": [

    ],
    "clerks": [
      "黃鏽金"
    ],
    "plaintiffs": [

    ],
    "defendants": [
      "施清文"
    ],
    "prosecutor_office": [
      "臺灣彰化地方法院檢察署檢察官"
    ],
    "creditors": [

    ],
    "debtors": [

    ],
    "judicial_associate_officer": [

    ]
  },
  "adjudged_at": "2011-04-14",
  "created_at": "2016-02-12 07:53:58",
  "updated_at": "2016-02-12 07:53:58"
}