{
  "identify": "KSD-100-審易-837-20110414-1",
  "court": {
    "name": "臺灣高雄地方法院",
    "code": "KSD"
  },
  "division": {
    "name": "刑事",
    "code": "M"
  },
  "year": 100,
  "word": "審易",
  "number": "837",
  "jcheck": "1",
  "reason": "竊盜",
  "content": "臺灣高雄地方法院刑事判決            100年度審易字第837號\n公  訴  人  臺灣高雄地方法院檢察署檢察官\n被      告  蔡禮安\n上列被告因竊盜案件，經檢察官提起公訴（100 年度偵字第4151\n號），被告於準備程序中就被訴事實為有罪之陳述，經本院告知\n簡式審判程序之旨，並聽取被告與公訴人之意見後，本院裁定進\n行簡式審判程序，判決如下：\n    主  文\n蔡禮安犯夜間侵入住宅竊盜罪，累犯，處有期徒刑柒月。\n    事實及理由\n一、犯罪事實：\n    蔡禮安前於民國94、95年間，因竊盜、施用毒品等案件，分\n    別經本院以94年度訴字第320 號判決處有期徒刑8 月確定、\n    95 年 簡字第2505號判決處有期徒刑5 月確定；上開2 罪嗣\n    經合併定應執行刑，於96年4 月22日縮刑期滿執行完畢。詎\n    其仍不知悔改，復基於意圖為自己不法所有及竊盜之犯意，\n    於99年12月23日下午9 時許，騎乘車號WFR-446 號輕型機車\n    行經楊正信位於高雄市○○區○○街110 號住處前時，見該\n    處大門未鎖，趁四下無人注意之際，徒手開門侵入1 樓客廳\n    ，竊取楊正信所有之MP3 隨身聽1 臺（含耳機），得手後，\n    尚未離去現場之前，即遭楊正信發覺並驅趕，蔡禮安遂急忙\n    騎車離開現場。嗣蔡禮安因毒品案件遭通緝，於100 年1 月\n    24日中午12時55分許，在高雄市小港區○○○路與康莊路口\n    ，經警盤查，在前開機車置物箱內扣得上開MP3 隨身聽1 臺\n    ，而知悉上情。\n二、證據名稱：\n    上開犯罪事實，有下列證據可資證明：\n  (一)證人即被害人楊正信於警詢中之指述。\n  (二)高雄市政府警察局小港分局扣押筆錄暨扣押物品目錄表1 份\n    查獲照片4 張、贓物認領保管單1 紙。\n  (三)被告之自白。\n三、應適用之法條與科刑：\n  (一)被告行為後，刑法第321 條已於100 年1 月10日修正，並於\n    100 年1 月28日公布生效，新修正刑法第321 條除就原條文\n    第1 項第1 款刪除「夜間」之構成要件外，原法定刑「6 月\n    以上、5 年以下有期徒刑」，修正後提高為「6  月以上、5\n    年以下有期徒刑，得併科新臺幣10萬元以下罰金」，是比較\n    修正前、後之法條規定，新法並非有利於被告，自應適用本\n    件被告行為時即修正前之規定加以處罰。又按修正前刑法第\n    321 條第1 項第1 款之夜間侵入住宅竊盜罪，其所謂「住宅\n    」，乃指人類日常居住之場所而言，而稱夜間者，為日出前\n    ，日沒後；從而，被告為本件犯行時，係在99年12月23日下\n    午9 時許之夜間，犯罪地點為被害楊正信之住處，是核被告\n    上開所為，係犯修正前刑法第321 條第1 項第1 款之夜間侵\n    入住宅竊盜罪。再夜間侵入住宅竊盜之加重竊盜犯行，本質\n    即含有侵入住宅之內涵，自毋庸在加重竊盜罪外，另論以侵\n    入住宅罪，併此敘明。又被告前有如犯罪事實欄所述經判處\n    有期徒刑並執行完畢之情形，此有臺灣高等法院被告前案紀\n    錄表在卷可佐，其於徒刑執行完畢5 年之內故意再犯本件有\n    期徒刑以上之罪，為累犯，應依法加重其刑。\n  (二)爰審酌被告正值青壯之年，竟不思以正當手段獲取財物，而\n    任意竊取他人之物，實有可議，且被告前有多次施用毒品、\n    竊盜等前科及執行紀錄，有被告院內裁判案件紀錄表及前揭\n    臺灣高等法院被告前案紀錄表各1 份在卷可按，足見其平日\n    素行非佳，惟念其犯罪後尚知坦承全部犯行，態度尚可，所\n    竊之物價值非鉅，且已發還被害人，有卷附贓物認領保管單\n    可稽，損害業已減輕，並綜合考量被告係國中肄業、職業工\n    、家境小康（見警卷教育程度欄、職業欄及家庭經濟狀況欄\n    之記載），及其上開犯罪所施用之手段、犯案情節等一切情\n    狀，量處如主文所示之刑，以資懲儆。\n據上論斷，應依刑事訴訟法第273  條之1 第1 項、第284 條之1\n、第299 條第1 項前段，修正前刑法第321 條第1 項第1 款、刑\n法第2 條第1 項前段、第47條第1 項，判決如主文。\n本案經檢察官李怡增到庭執行職務。\n中    華    民    國   100    年    4     月    14    日\n                  刑事第十庭  法  官    呂明燕\n以上正本證明與原本無異。\n如不服本判決應於收受本判決後10日內向本院提出上訴書狀，並\n應敘述具體理由，如未敘述上訴理由者，應於上訴期間屆滿後20\n日內補提理由書狀於本院（均須按他造當事人之人數附繕本）「\n切勿逕送上級法院」。\n中    華    民    國   100    年    4     月    14    日\n                              書記官    張琇晴\n附錄本判決論罪科刑之法條：\n修正前中華民國刑法第321條（加重竊盜罪）\n犯竊盜罪而有左列情形之一者，處6 月以上、5 年以下有期徒刑\n：\n  一、於夜間侵入住宅或有人居住之建築物、船艦或隱匿其內而\n      犯之者。\n  二、毀越門扇、牆垣或其他安全設備而犯之者。\n  三、攜帶兇器而犯之者。\n  四、結夥三人以上而犯之者。\n  五、乘火災、水災或其他災害之際而犯之者。\n  六、在車站或埠頭而犯之者。\n前項之未遂犯罰之。",
  "structure": {
    "main": "蔡禮安犯夜間侵入住宅竊盜罪，累犯，處有期徒刑柒月。",
    "fact": "一、犯罪事實：\n    蔡禮安前於民國94、95年間，因竊盜、施用毒品等案件，分\n    別經本院以94年度訴字第320 號判決處有期徒刑8 月確定、\n    95 年 簡字第2505號判決處有期徒刑5 月確定；上開2 罪嗣\n    經合併定應執行刑，於96年4 月22日縮刑期滿執行完畢。詎\n    其仍不知悔改，復基於意圖為自己不法所有及竊盜之犯意，\n    於99年12月23日下午9 時許，騎乘車號WFR-446 號輕型機車\n    行經楊正信位於高雄市○○區○○街110 號住處前時，見該\n    處大門未鎖，趁四下無人注意之際，徒手開門侵入1 樓客廳\n    ，竊取楊正信所有之MP3 隨身聽1 臺（含耳機），得手後，\n    尚未離去現場之前，即遭楊正信發覺並驅趕，蔡禮安遂急忙\n    騎車離開現場。嗣蔡禮安因毒品案件遭通緝，於100 年1 月\n    24日中午12時55分許，在高雄市小港區○○○路與康莊路口\n    ，經警盤查，在前開機車置物箱內扣得上開MP3 隨身聽1 臺\n    ，而知悉上情。\n二、證據名稱：\n    上開犯罪事實，有下列證據可資證明：\n  (一)證人即被害人楊正信於警詢中之指述。\n  (二)高雄市政府警察局小港分局扣押筆錄暨扣押物品目錄表1 份\n    查獲照片4 張、贓物認領保管單1 紙。\n  (三)被告之自白。\n三、應適用之法條與科刑：\n  (一)被告行為後，刑法第321 條已於100 年1 月10日修正，並於\n    100 年1 月28日公布生效，新修正刑法第321 條除就原條文\n    第1 項第1 款刪除「夜間」之構成要件外，原法定刑「6 月\n    以上、5 年以下有期徒刑」，修正後提高為「6  月以上、5\n    年以下有期徒刑，得併科新臺幣10萬元以下罰金」，是比較\n    修正前、後之法條規定，新法並非有利於被告，自應適用本\n    件被告行為時即修正前之規定加以處罰。又按修正前刑法第\n    321 條第1 項第1 款之夜間侵入住宅竊盜罪，其所謂「住宅\n    」，乃指人類日常居住之場所而言，而稱夜間者，為日出前\n    ，日沒後；從而，被告為本件犯行時，係在99年12月23日下\n    午9 時許之夜間，犯罪地點為被害楊正信之住處，是核被告\n    上開所為，係犯修正前刑法第321 條第1 項第1 款之夜間侵\n    入住宅竊盜罪。再夜間侵入住宅竊盜之加重竊盜犯行，本質\n    即含有侵入住宅之內涵，自毋庸在加重竊盜罪外，另論以侵\n    入住宅罪，併此敘明。又被告前有如犯罪事實欄所述經判處\n    有期徒刑並執行完畢之情形，此有臺灣高等法院被告前案紀\n    錄表在卷可佐，其於徒刑執行完畢5 年之內故意再犯本件有\n    期徒刑以上之罪，為累犯，應依法加重其刑。\n  (二)爰審酌被告正值青壯之年，竟不思以正當手段獲取財物，而\n    任意竊取他人之物，實有可議，且被告前有多次施用毒品、\n    竊盜等前科及執行紀錄，有被告院內裁判案件紀錄表及前揭\n    臺灣高等法院被告前案紀錄表各1 份在卷可按，足見其平日\n    素行非佳，惟念其犯罪後尚知坦承全部犯行，態度尚可，所\n    竊之物價值非鉅，且已發還被害人，有卷附贓物認領保管單\n    可稽，損害業已減輕，並綜合考量被告係國中肄業、職業工\n    、家境小康（見警卷教育程度欄、職業欄及家庭經濟狀況欄\n    之記載），及其上開犯罪所施用之手段、犯案情節等一切情\n    狀，量處如主文所示之刑，以資懲儆。\n據上論斷，應依刑事訴訟法第273  條之1 第1 項、第284 條之1\n、第299 條第1 項前段，修正前刑法第321 條第1 項第1 款、刑\n法第2 條第1 項前段、第47條第1 項，判決如主文。\n本案經檢察官李怡增到庭執行職務。",
    "reason": "一、犯罪事實：\n    蔡禮安前於民國94、95年間，因竊盜、施用毒品等案件，分\n    別經本院以94年度訴字第320 號判決處有期徒刑8 月確定、\n    95 年 簡字第2505號判決處有期徒刑5 月確定；上開2 罪嗣\n    經合併定應執行刑，於96年4 月22日縮刑期滿執行完畢。詎\n    其仍不知悔改，復基於意圖為自己不法所有及竊盜之犯意，\n    於99年12月23日下午9 時許，騎乘車號WFR-446 號輕型機車\n    行經楊正信位於高雄市○○區○○街110 號住處前時，見該\n    處大門未鎖，趁四下無人注意之際，徒手開門侵入1 樓客廳\n    ，竊取楊正信所有之MP3 隨身聽1 臺（含耳機），得手後，\n    尚未離去現場之前，即遭楊正信發覺並驅趕，蔡禮安遂急忙\n    騎車離開現場。嗣蔡禮安因毒品案件遭通緝，於100 年1 月\n    24日中午12時55分許，在高雄市小港區○○○路與康莊路口\n    ，經警盤查，在前開機車置物箱內扣得上開MP3 隨身聽1 臺\n    ，而知悉上情。\n二、證據名稱：\n    上開犯罪事實，有下列證據可資證明：\n  (一)證人即被害人楊正信於警詢中之指述。\n  (二)高雄市政府警察局小港分局扣押筆錄暨扣押物品目錄表1 份\n    查獲照片4 張、贓物認領保管單1 紙。\n  (三)被告之自白。\n三、應適用之法條與科刑：\n  (一)被告行為後，刑法第321 條已於100 年1 月10日修正，並於\n    100 年1 月28日公布生效，新修正刑法第321 條除就原條文\n    第1 項第1 款刪除「夜間」之構成要件外，原法定刑「6 月\n    以上、5 年以下有期徒刑」，修正後提高為「6  月以上、5\n    年以下有期徒刑，得併科新臺幣10萬元以下罰金」，是比較\n    修正前、後之法條規定，新法並非有利於被告，自應適用本\n    件被告行為時即修正前之規定加以處罰。又按修正前刑法第\n    321 條第1 項第1 款之夜間侵入住宅竊盜罪，其所謂「住宅\n    」，乃指人類日常居住之場所而言，而稱夜間者，為日出前\n    ，日沒後；從而，被告為本件犯行時，係在99年12月23日下\n    午9 時許之夜間，犯罪地點為被害楊正信之住處，是核被告\n    上開所為，係犯修正前刑法第321 條第1 項第1 款之夜間侵\n    入住宅竊盜罪。再夜間侵入住宅竊盜之加重竊盜犯行，本質\n    即含有侵入住宅之內涵，自毋庸在加重竊盜罪外，另論以侵\n    入住宅罪，併此敘明。又被告前有如犯罪事實欄所述經判處\n    有期徒刑並執行完畢之情形，此有臺灣高等法院被告前案紀\n    錄表在卷可佐，其於徒刑執行完畢5 年之內故意再犯本件有\n    期徒刑以上之罪，為累犯，應依法加重其刑。\n  (二)爰審酌被告正值青壯之年，竟不思以正當手段獲取財物，而\n    任意竊取他人之物，實有可議，且被告前有多次施用毒品、\n    竊盜等前科及執行紀錄，有被告院內裁判案件紀錄表及前揭\n    臺灣高等法院被告前案紀錄表各1 份在卷可按，足見其平日\n    素行非佳，惟念其犯罪後尚知坦承全部犯行，態度尚可，所\n    竊之物價值非鉅，且已發還被害人，有卷附贓物認領保管單\n    可稽，損害業已減輕，並綜合考量被告係國中肄業、職業工\n    、家境小康（見警卷教育程度欄、職業欄及家庭經濟狀況欄\n    之記載），及其上開犯罪所施用之手段、犯案情節等一切情\n    狀，量處如主文所示之刑，以資懲儆。\n據上論斷，應依刑事訴訟法第273  條之1 第1 項、第284 條之1\n、第299 條第1 項前段，修正前刑法第321 條第1 項第1 款、刑\n法第2 條第1 項前段、第47條第1 項，判決如主文。\n本案經檢察官李怡增到庭執行職務。"
  },
  "search": "臺灣高雄地方法院刑事判決100年度審易字第837號公訴人臺灣高雄地方法院檢察署檢察官被告蔡禮安上列被告因竊盜案件，經檢察官提起公訴（100年度偵字第4151號），被告於準備程序中就被訴事實為有罪之陳述，經本院告知簡式審判程序之旨，並聽取被告與公訴人之意見後，本院裁定進行簡式審判程序，判決如下：主文蔡禮安犯夜間侵入住宅竊盜罪，累犯，處有期徒刑柒月。事實及理由一、犯罪事實：蔡禮安前於民國94、95年間，因竊盜、施用毒品等案件，分別經本院以94年度訴字第320號判決處有期徒刑8月確定、95年簡字第2505號判決處有期徒刑5月確定；上開2罪嗣經合併定應執行刑，於96年4月22日縮刑期滿執行完畢。詎其仍不知悔改，復基於意圖為自己不法所有及竊盜之犯意，於99年12月23日下午9時許，騎乘車號WFR-446號輕型機車行經楊正信位於高雄市○○區○○街110號住處前時，見該處大門未鎖，趁四下無人注意之際，徒手開門侵入1樓客廳，竊取楊正信所有之MP3隨身聽1臺（含耳機），得手後，尚未離去現場之前，即遭楊正信發覺並驅趕，蔡禮安遂急忙騎車離開現場。嗣蔡禮安因毒品案件遭通緝，於100年1月24日中午12時55分許，在高雄市小港區○○○路與康莊路口，經警盤查，在前開機車置物箱內扣得上開MP3隨身聽1臺，而知悉上情。二、證據名稱：上開犯罪事實，有下列證據可資證明：(一)證人即被害人楊正信於警詢中之指述。(二)高雄市政府警察局小港分局扣押筆錄暨扣押物品目錄表1份查獲照片4張、贓物認領保管單1紙。(三)被告之自白。三、應適用之法條與科刑：(一)被告行為後，刑法第321條已於100年1月10日修正，並於100年1月28日公布生效，新修正刑法第321條除就原條文第1項第1款刪除「夜間」之構成要件外，原法定刑「6月以上、5年以下有期徒刑」，修正後提高為「6月以上、5年以下有期徒刑，得併科新臺幣10萬元以下罰金」，是比較修正前、後之法條規定，新法並非有利於被告，自應適用本件被告行為時即修正前之規定加以處罰。又按修正前刑法第321條第1項第1款之夜間侵入住宅竊盜罪，其所謂「住宅」，乃指人類日常居住之場所而言，而稱夜間者，為日出前，日沒後；從而，被告為本件犯行時，係在99年12月23日下午9時許之夜間，犯罪地點為被害楊正信之住處，是核被告上開所為，係犯修正前刑法第321條第1項第1款之夜間侵入住宅竊盜罪。再夜間侵入住宅竊盜之加重竊盜犯行，本質即含有侵入住宅之內涵，自毋庸在加重竊盜罪外，另論以侵入住宅罪，併此敘明。又被告前有如犯罪事實欄所述經判處有期徒刑並執行完畢之情形，此有臺灣高等法院被告前案紀錄表在卷可佐，其於徒刑執行完畢5年之內故意再犯本件有期徒刑以上之罪，為累犯，應依法加重其刑。(二)爰審酌被告正值青壯之年，竟不思以正當手段獲取財物，而任意竊取他人之物，實有可議，且被告前有多次施用毒品、竊盜等前科及執行紀錄，有被告院內裁判案件紀錄表及前揭臺灣高等法院被告前案紀錄表各1份在卷可按，足見其平日素行非佳，惟念其犯罪後尚知坦承全部犯行，態度尚可，所竊之物價值非鉅，且已發還被害人，有卷附贓物認領保管單可稽，損害業已減輕，並綜合考量被告係國中肄業、職業工、家境小康（見警卷教育程度欄、職業欄及家庭經濟狀況欄之記載），及其上開犯罪所施用之手段、犯案情節等一切情狀，量處如主文所示之刑，以資懲儆。據上論斷，應依刑事訴訟法第273條之1第1項、第284條之1、第299條第1項前段，修正前刑法第321條第1項第1款、刑法第2條第1項前段、第47條第1項，判決如主文。本案經檢察官李怡增到庭執行職務。中華民國100年4月14日刑事第十庭法官呂明燕以上正本證明與原本無異。如不服本判決應於收受本判決後10日內向本院提出上訴書狀，並應敘述具體理由，如未敘述上訴理由者，應於上訴期間屆滿後20日內補提理由書狀於本院（均須按他造當事人之人數附繕本）「切勿逕送上級法院」。中華民國100年4月14日書記官張琇晴附錄本判決論罪科刑之法條：修正前中華民國刑法第321條（加重竊盜罪）犯竊盜罪而有左列情形之一者，處6月以上、5年以下有期徒刑：一、於夜間侵入住宅或有人居住之建築物、船艦或隱匿其內而犯之者。二、毀越門扇、牆垣或其他安全設備而犯之者。三、攜帶兇器而犯之者。四、結夥三人以上而犯之者。五、乘火災、水災或其他災害之際而犯之者。六、在車站或埠頭而犯之者。前項之未遂犯罰之。",
  "characters": {
    "judges": [
      "呂明燕"
    ],
    "prosecutors": [
      "李怡增"
    ],
    "lawyers": [

    ],
    "clerks": [
      "張琇晴"
    ],
    "plaintiffs": [

    ],
    "defendants": [
      "蔡禮安"
    ],
    "prosecutor_office": [
      "臺灣高雄地方法院檢察署檢察官"
    ],
    "creditors": [

    ],
    "debtors": [

    ],
    "judicial_associate_officer": [

    ]
  },
  "adjudged_at": "2011-04-14",
  "created_at": "2016-02-12 07:55:19",
  "updated_at": "2016-02-12 07:55:19"
}