{
  "identify": "ULD-100-易-157-20110413-1",
  "court": {
    "name": "臺灣雲林地方法院",
    "code": "ULD"
  },
  "division": {
    "name": "刑事",
    "code": "M"
  },
  "year": 100,
  "word": "易",
  "number": "157",
  "jcheck": "1",
  "reason": "家庭暴力防治法",
  "content": "臺灣雲林地方法院刑事判決              100年度易字第157號\n公  訴  人  臺灣雲林地方法院檢察署檢察官\n被      告  黃皓熙\n上列被告因家庭暴力防治法案件，經檢察官提起公訴（99年度偵\n字第6006號），被告於準備程序期日就被訴事實為有罪陳述，本\n院進行簡式審判程序，並判決如下：\n    主  文\n黃皓熙犯違反保護令罪，累犯，處拘役貳拾日，如易科罰金，以\n新臺幣壹仟元折算壹日。\n    事  實\n一、黃皓熙曾因偽造文書案件，經本院以96年度虎簡字第487 號\n    判處有期徒刑4 月確定，於民國97年10月3 日縮刑期滿執行\n    完畢。又黃皓熙與吳佳蓉曾為夫妻關係，雙方於95年12月28\n    日離婚，2 人具有家庭暴力防治法第3 條第1 款所定之家庭\n    成員關係。黃皓熙明知吳佳蓉已依家庭暴力防治法規定向本\n    院聲請保護令，經本院於99年7 月21日核發99年度家護字第\n    368 號民事通常保護令，命黃皓熙不得對吳佳蓉實施身體或\n    精神上不法侵害行為、直接或間接為騷擾、接觸之聯絡行為\n    ，及應遠離下列處所100 公尺：(1)雲林縣虎尾鎮○○里○○\n    街100 號；(2)雲林縣虎尾鎮○○里○○路174 號「萬國印鋪\n    店」，有效期間為1 年。詎黃皓熙於收受上開保護令後，為\n    能於99年8 月17日入監服刑前探視女兒，不顧前開通常保護\n    令之命令內容，基於違反保護令之單一犯意，於99年8 月13\n    日晚間9 時30分許，騎乘機車接續至雲林縣虎尾鎮○○里○\n    ○路174 號「萬國印鋪店」門口後，復至雲林縣虎尾鎮○○\n    里○○街100 號之門口，違反遠離處所之命令。\n二、案經吳佳蓉訴由雲林縣警察局虎尾分局報告臺灣雲林地方法\n    院檢察署檢察官偵查起訴。\n    理  由\n一、本件被告所犯為死刑、無期徒刑、最輕本刑為三年以上有期\n    徒刑以外之罪，亦非屬高等法院管轄之第一審案件，其於準\n    備程序進行中，先就被訴事實為有罪之陳述，經法官告知簡\n    式審判程序之旨，並聽取公訴檢察官之意見後，依刑事訴訟\n    法第273 條之1 第1 項、第273 條之2 等規定，裁定進行簡\n    式審判程序，且不受同法第159 條第1 項、第161 條之2 、\n    第161 條之3 、第163 條之1 及第164 條至第170 條所規定\n    證據能力認定及調查方式之限制，合先敘明。\n二、對於上開犯罪事實，業據被告於本院審理時供認不諱，核與\n    告訴人吳佳蓉於警詢時之指述及檢察官訊問時之證述（警卷\n    第4 頁至第6 頁，偵卷第13、14頁）情節大致相符，並有上\n    開本院99年度家護字第368 號民事通常保護令影本、送達證\n    書影本各1 份（警卷第7 頁，偵卷第21頁）在卷可佐，足認\n    被告上開自白與事實相符，而得採信。是本件事證明確，被\n    告之犯行堪以認定，應依法論科。\n三、論罪科刑：\n  (一)被告與告訴人吳佳蓉於95年12月28日離婚，其係告訴人之前\n    配偶，2 人間具有家庭暴力防治法第3 條第1 款所定之家庭\n    成員關係。本院曾以民事通常保護令（99年度家護字第368\n    號）裁定禁止被告對告訴人實施身體或精神上不法侵害行為\n    、直接或間接為騷擾、接觸之聯絡行為，及至少應遠離(1)雲\n    林縣虎尾鎮○○里○○街100 號；(2)雲林縣虎尾鎮○○里○\n    ○路174 號「萬國印鋪店」100 公尺，有效期間為1 年。而\n    被告明知上開保護令之內容，仍違反保護令，於99年8 月13\n    日晚間9 時30分許，前後前往上開2 個處所門口，核被告所\n    為，係違反家庭暴力防治法第61條第4 款之違反保護令罪。\n  (二)被告雖先後至雲林縣虎尾鎮○○里○○路174 號「萬國印鋪\n    店」、雲林縣虎尾鎮○○里○○街100 號之門口處，為違反\n    保護令裁定所禁止之行為，然被告係出於探視女兒之目的，\n    於緊密之時間內，接近保護令內容所命應遠離之2 個處所，\n    顯係基於同一違反保護令之犯意所為，又侵害手法相同，堪\n    認各行為之獨立性極為薄弱，依一般社會客觀觀念，難以強\n    行分開，在法律上評價應為數個舉動之接續施行，應屬接續\n    犯，而僅論以一違反保護令罪。\n  (三)再查，被告有前述犯罪事實欄所記載之前科紀錄，此有臺灣\n    高等法院被告前案紀錄表1 份附卷足憑，故被告於受有期徒\n    刑執行完畢後，5 年內故意再犯本件有期徒刑以上之罪，依\n    刑法第47條第1 項規定，為累犯，應依法加重其刑。\n  (四)爰審酌被告事實欄之前科紀錄，已如前述，又因公共危險及\n    恐嚇案件，於99年8 月17日入監服刑，此有臺灣高等法院被\n    告前案紀錄表1 份在卷可參，是其所稱違反保護令之動機，\n    在於入監前探視女兒等情，與告訴人偵訊時證述一致，應為\n    實在。雖被告未經深思熟慮，採取了不適當的方式，而違反\n    保護令，但念其目的非在於不法侵害，而是出於父女天性，\n    思念女兒之情，又其違反保護令之情節尚屬輕微，復於審理\n    時能知坦承犯行，態度良好，顯見應有悔意；此外，告訴人\n    於審理時也表示願意讓被告以事先打電話約定方式探視女兒\n    ，相信被告不至於再有違反保護令之行為，兼衡被告自陳有\n    正當工作等一切情狀，量處如主文所示之刑，併諭知易科罰\n    金之折算標準。\n四、據上論斷，應依刑事訴訟法第273 條之1 第1 項、第299 條\n    第1 項前段，家庭暴力防治法第61條第4 款，刑法第11條前\n    段、第47條第1 項、第41條第1 項前段，判決如主文。\n本案經檢察官莊珂惠到庭執行職務。\n中    華    民    國   100    年    4     月    13    日\n                  刑事第三庭    法  官  蕭雅毓\n以上正本證明與原本無異。\n如不服本判決應於收受判決後10日內向本院提出上訴書狀，並應\n敘述具體理由；其未敘述上訴理由者，應於上訴期間屆滿後20日\n內向本院補提理由書（均須按他造當事人之人數附繕本）。「切\n勿逕送上級法院」。\n                                書記官  鍾宜津\n中    華    民    國   100    年    4     月    13    日\n附錄本案論罪科刑法條全文：\n家庭暴力防治法第61條（違反保護令罪）：\n違反法院依第14條第1 項、第16條第3 項所為之下列裁定者，為\n本法所稱違反保護令罪，處3 年以下有期徒刑、拘役或科或併科\n新臺幣10萬元以下罰金：\n一、禁止實施家庭暴力。\n二、禁止騷擾、接觸、跟蹤、通話、通信或其他非必要之聯絡行\n    為。\n三、遷出住居所。\n四、遠離住居所、工作場所、學校或其他特定場所。\n五、完成加害人處遇計畫。",
  "structure": {
    "main": "黃皓熙犯違反保護令罪，累犯，處拘役貳拾日，如易科罰金，以\n新臺幣壹仟元折算壹日。",
    "fact": "一、黃皓熙曾因偽造文書案件，經本院以96年度虎簡字第487 號\n    判處有期徒刑4 月確定，於民國97年10月3 日縮刑期滿執行\n    完畢。又黃皓熙與吳佳蓉曾為夫妻關係，雙方於95年12月28\n    日離婚，2 人具有家庭暴力防治法第3 條第1 款所定之家庭\n    成員關係。黃皓熙明知吳佳蓉已依家庭暴力防治法規定向本\n    院聲請保護令，經本院於99年7 月21日核發99年度家護字第\n    368 號民事通常保護令，命黃皓熙不得對吳佳蓉實施身體或\n    精神上不法侵害行為、直接或間接為騷擾、接觸之聯絡行為\n    ，及應遠離下列處所100 公尺：(1)雲林縣虎尾鎮○○里○○\n    街100 號；(2)雲林縣虎尾鎮○○里○○路174 號「萬國印鋪\n    店」，有效期間為1 年。詎黃皓熙於收受上開保護令後，為\n    能於99年8 月17日入監服刑前探視女兒，不顧前開通常保護\n    令之命令內容，基於違反保護令之單一犯意，於99年8 月13\n    日晚間9 時30分許，騎乘機車接續至雲林縣虎尾鎮○○里○\n    ○路174 號「萬國印鋪店」門口後，復至雲林縣虎尾鎮○○\n    里○○街100 號之門口，違反遠離處所之命令。\n二、案經吳佳蓉訴由雲林縣警察局虎尾分局報告臺灣雲林地方法\n    院檢察署檢察官偵查起訴。",
    "reason": "一、本件被告所犯為死刑、無期徒刑、最輕本刑為三年以上有期\n    徒刑以外之罪，亦非屬高等法院管轄之第一審案件，其於準\n    備程序進行中，先就被訴事實為有罪之陳述，經法官告知簡\n    式審判程序之旨，並聽取公訴檢察官之意見後，依刑事訴訟\n    法第273 條之1 第1 項、第273 條之2 等規定，裁定進行簡\n    式審判程序，且不受同法第159 條第1 項、第161 條之2 、\n    第161 條之3 、第163 條之1 及第164 條至第170 條所規定\n    證據能力認定及調查方式之限制，合先敘明。\n二、對於上開犯罪事實，業據被告於本院審理時供認不諱，核與\n    告訴人吳佳蓉於警詢時之指述及檢察官訊問時之證述（警卷\n    第4 頁至第6 頁，偵卷第13、14頁）情節大致相符，並有上\n    開本院99年度家護字第368 號民事通常保護令影本、送達證\n    書影本各1 份（警卷第7 頁，偵卷第21頁）在卷可佐，足認\n    被告上開自白與事實相符，而得採信。是本件事證明確，被\n    告之犯行堪以認定，應依法論科。\n三、論罪科刑：\n  (一)被告與告訴人吳佳蓉於95年12月28日離婚，其係告訴人之前\n    配偶，2 人間具有家庭暴力防治法第3 條第1 款所定之家庭\n    成員關係。本院曾以民事通常保護令（99年度家護字第368\n    號）裁定禁止被告對告訴人實施身體或精神上不法侵害行為\n    、直接或間接為騷擾、接觸之聯絡行為，及至少應遠離(1)雲\n    林縣虎尾鎮○○里○○街100 號；(2)雲林縣虎尾鎮○○里○\n    ○路174 號「萬國印鋪店」100 公尺，有效期間為1 年。而\n    被告明知上開保護令之內容，仍違反保護令，於99年8 月13\n    日晚間9 時30分許，前後前往上開2 個處所門口，核被告所\n    為，係違反家庭暴力防治法第61條第4 款之違反保護令罪。\n  (二)被告雖先後至雲林縣虎尾鎮○○里○○路174 號「萬國印鋪\n    店」、雲林縣虎尾鎮○○里○○街100 號之門口處，為違反\n    保護令裁定所禁止之行為，然被告係出於探視女兒之目的，\n    於緊密之時間內，接近保護令內容所命應遠離之2 個處所，\n    顯係基於同一違反保護令之犯意所為，又侵害手法相同，堪\n    認各行為之獨立性極為薄弱，依一般社會客觀觀念，難以強\n    行分開，在法律上評價應為數個舉動之接續施行，應屬接續\n    犯，而僅論以一違反保護令罪。\n  (三)再查，被告有前述犯罪事實欄所記載之前科紀錄，此有臺灣\n    高等法院被告前案紀錄表1 份附卷足憑，故被告於受有期徒\n    刑執行完畢後，5 年內故意再犯本件有期徒刑以上之罪，依\n    刑法第47條第1 項規定，為累犯，應依法加重其刑。\n  (四)爰審酌被告事實欄之前科紀錄，已如前述，又因公共危險及\n    恐嚇案件，於99年8 月17日入監服刑，此有臺灣高等法院被\n    告前案紀錄表1 份在卷可參，是其所稱違反保護令之動機，\n    在於入監前探視女兒等情，與告訴人偵訊時證述一致，應為\n    實在。雖被告未經深思熟慮，採取了不適當的方式，而違反\n    保護令，但念其目的非在於不法侵害，而是出於父女天性，\n    思念女兒之情，又其違反保護令之情節尚屬輕微，復於審理\n    時能知坦承犯行，態度良好，顯見應有悔意；此外，告訴人\n    於審理時也表示願意讓被告以事先打電話約定方式探視女兒\n    ，相信被告不至於再有違反保護令之行為，兼衡被告自陳有\n    正當工作等一切情狀，量處如主文所示之刑，併諭知易科罰\n    金之折算標準。\n四、據上論斷，應依刑事訴訟法第273 條之1 第1 項、第299 條\n    第1 項前段，家庭暴力防治法第61條第4 款，刑法第11條前\n    段、第47條第1 項、第41條第1 項前段，判決如主文。\n本案經檢察官莊珂惠到庭執行職務。\n中    華    民    國   100    年    4     月    13    日\n                  刑事第三庭    法  官  蕭雅毓\n以上正本證明與原本無異。\n如不服本判決應於收受判決後10日內向本院提出上訴書狀，並應\n敘述具體理由；其未敘述上訴理由者，應於上訴期間屆滿後20日\n內向本院補提理由書（均須按他造當事人之人數附繕本）。「切\n勿逕送上級法院」。\n                                書記官  鍾宜津"
  },
  "search": "臺灣雲林地方法院刑事判決100年度易字第157號公訴人臺灣雲林地方法院檢察署檢察官被告黃皓熙上列被告因家庭暴力防治法案件，經檢察官提起公訴（99年度偵字第6006號），被告於準備程序期日就被訴事實為有罪陳述，本院進行簡式審判程序，並判決如下：主文黃皓熙犯違反保護令罪，累犯，處拘役貳拾日，如易科罰金，以新臺幣壹仟元折算壹日。事實一、黃皓熙曾因偽造文書案件，經本院以96年度虎簡字第487號判處有期徒刑4月確定，於民國97年10月3日縮刑期滿執行完畢。又黃皓熙與吳佳蓉曾為夫妻關係，雙方於95年12月28日離婚，2人具有家庭暴力防治法第3條第1款所定之家庭成員關係。黃皓熙明知吳佳蓉已依家庭暴力防治法規定向本院聲請保護令，經本院於99年7月21日核發99年度家護字第368號民事通常保護令，命黃皓熙不得對吳佳蓉實施身體或精神上不法侵害行為、直接或間接為騷擾、接觸之聯絡行為，及應遠離下列處所100公尺：(1)雲林縣虎尾鎮○○里○○街100號；(2)雲林縣虎尾鎮○○里○○路174號「萬國印鋪店」，有效期間為1年。詎黃皓熙於收受上開保護令後，為能於99年8月17日入監服刑前探視女兒，不顧前開通常保護令之命令內容，基於違反保護令之單一犯意，於99年8月13日晚間9時30分許，騎乘機車接續至雲林縣虎尾鎮○○里○○路174號「萬國印鋪店」門口後，復至雲林縣虎尾鎮○○里○○街100號之門口，違反遠離處所之命令。二、案經吳佳蓉訴由雲林縣警察局虎尾分局報告臺灣雲林地方法院檢察署檢察官偵查起訴。理由一、本件被告所犯為死刑、無期徒刑、最輕本刑為三年以上有期徒刑以外之罪，亦非屬高等法院管轄之第一審案件，其於準備程序進行中，先就被訴事實為有罪之陳述，經法官告知簡式審判程序之旨，並聽取公訴檢察官之意見後，依刑事訴訟法第273條之1第1項、第273條之2等規定，裁定進行簡式審判程序，且不受同法第159條第1項、第161條之2、第161條之3、第163條之1及第164條至第170條所規定證據能力認定及調查方式之限制，合先敘明。二、對於上開犯罪事實，業據被告於本院審理時供認不諱，核與告訴人吳佳蓉於警詢時之指述及檢察官訊問時之證述（警卷第4頁至第6頁，偵卷第13、14頁）情節大致相符，並有上開本院99年度家護字第368號民事通常保護令影本、送達證書影本各1份（警卷第7頁，偵卷第21頁）在卷可佐，足認被告上開自白與事實相符，而得採信。是本件事證明確，被告之犯行堪以認定，應依法論科。三、論罪科刑：(一)被告與告訴人吳佳蓉於95年12月28日離婚，其係告訴人之前配偶，2人間具有家庭暴力防治法第3條第1款所定之家庭成員關係。本院曾以民事通常保護令（99年度家護字第368號）裁定禁止被告對告訴人實施身體或精神上不法侵害行為、直接或間接為騷擾、接觸之聯絡行為，及至少應遠離(1)雲林縣虎尾鎮○○里○○街100號；(2)雲林縣虎尾鎮○○里○○路174號「萬國印鋪店」100公尺，有效期間為1年。而被告明知上開保護令之內容，仍違反保護令，於99年8月13日晚間9時30分許，前後前往上開2個處所門口，核被告所為，係違反家庭暴力防治法第61條第4款之違反保護令罪。(二)被告雖先後至雲林縣虎尾鎮○○里○○路174號「萬國印鋪店」、雲林縣虎尾鎮○○里○○街100號之門口處，為違反保護令裁定所禁止之行為，然被告係出於探視女兒之目的，於緊密之時間內，接近保護令內容所命應遠離之2個處所，顯係基於同一違反保護令之犯意所為，又侵害手法相同，堪認各行為之獨立性極為薄弱，依一般社會客觀觀念，難以強行分開，在法律上評價應為數個舉動之接續施行，應屬接續犯，而僅論以一違反保護令罪。(三)再查，被告有前述犯罪事實欄所記載之前科紀錄，此有臺灣高等法院被告前案紀錄表1份附卷足憑，故被告於受有期徒刑執行完畢後，5年內故意再犯本件有期徒刑以上之罪，依刑法第47條第1項規定，為累犯，應依法加重其刑。(四)爰審酌被告事實欄之前科紀錄，已如前述，又因公共危險及恐嚇案件，於99年8月17日入監服刑，此有臺灣高等法院被告前案紀錄表1份在卷可參，是其所稱違反保護令之動機，在於入監前探視女兒等情，與告訴人偵訊時證述一致，應為實在。雖被告未經深思熟慮，採取了不適當的方式，而違反保護令，但念其目的非在於不法侵害，而是出於父女天性，思念女兒之情，又其違反保護令之情節尚屬輕微，復於審理時能知坦承犯行，態度良好，顯見應有悔意；此外，告訴人於審理時也表示願意讓被告以事先打電話約定方式探視女兒，相信被告不至於再有違反保護令之行為，兼衡被告自陳有正當工作等一切情狀，量處如主文所示之刑，併諭知易科罰金之折算標準。四、據上論斷，應依刑事訴訟法第273條之1第1項、第299條第1項前段，家庭暴力防治法第61條第4款，刑法第11條前段、第47條第1項、第41條第1項前段，判決如主文。本案經檢察官莊珂惠到庭執行職務。中華民國100年4月13日刑事第三庭法官蕭雅毓以上正本證明與原本無異。如不服本判決應於收受判決後10日內向本院提出上訴書狀，並應敘述具體理由；其未敘述上訴理由者，應於上訴期間屆滿後20日內向本院補提理由書（均須按他造當事人之人數附繕本）。「切勿逕送上級法院」。書記官鍾宜津中華民國100年4月13日附錄本案論罪科刑法條全文：家庭暴力防治法第61條（違反保護令罪）：違反法院依第14條第1項、第16條第3項所為之下列裁定者，為本法所稱違反保護令罪，處3年以下有期徒刑、拘役或科或併科新臺幣10萬元以下罰金：一、禁止實施家庭暴力。二、禁止騷擾、接觸、跟蹤、通話、通信或其他非必要之聯絡行為。三、遷出住居所。四、遠離住居所、工作場所、學校或其他特定場所。五、完成加害人處遇計畫。",
  "characters": {
    "judges": [
      "蕭雅毓"
    ],
    "prosecutors": [
      "莊珂惠"
    ],
    "lawyers": [

    ],
    "clerks": [
      "鍾宜津"
    ],
    "plaintiffs": [

    ],
    "defendants": [
      "黃皓熙"
    ],
    "prosecutor_office": [
      "臺灣雲林地方法院檢察署檢察官"
    ],
    "creditors": [

    ],
    "debtors": [

    ],
    "judicial_associate_officer": [

    ]
  },
  "adjudged_at": "2011-04-13",
  "created_at": "2016-02-12 07:53:26",
  "updated_at": "2016-02-12 07:53:26"
}