{
  "identify": "KSD-94-交簡-1969-20050714-1",
  "court": {
    "name": "臺灣高雄地方法院",
    "code": "KSD"
  },
  "division": {
    "name": "刑事",
    "code": "M"
  },
  "year": 94,
  "word": "交簡",
  "number": "1969",
  "jcheck": "1",
  "reason": "公共危險",
  "content": "臺灣高雄地方法院刑事簡易判決        94年度交簡字第1969號\n聲  請  人  臺灣高雄地方法院檢察署檢察官\n被      告  甲○○  男  民國5.\n上列被告因公共危險案件，經檢察官聲請簡易判決處刑（94年度\n偵字第13931 號），本院判決如下：\n    主  文\n甲○○服用酒類，不能安全駕駛動力交通工具而駕駛，處拘役參\n拾日，如易科罰金，以參佰元折算壹日。\n    事實及理由\n一、甲○○明知飲酒可能造成不能安全駕駛之結果，於民國94年\n    6 月5 日13時許，在高雄縣彌陀鄉某處，與同事飲用酒類，\n    當酒後客觀上已達不能安全駕駛之程度下，於94年6 月5 日\n    15時10分前之某時，仍駕駛車牌號碼ZE─5360號自小客車上\n    路，沿高雄縣彌陀鄉往高雄市楠梓區方向行駛，俟於94年 6\n    月5 日15時10分許，行經高雄市○○區○○路、德惠路口時\n    ，欲左轉六合二路，適乙○○駕駛車牌號碼XC─5091號自小\n    客車，沿德民路由東向西方向行駛至德惠路口，欲左轉楠梓\n    加工區第四出入口，兩車因而互撞，嗣於94年6 月5 日15時\n    44分、16時38分、16時55分許，經警施以3 次酒精濃度測試\n    ，測出其呼氣酒精濃度為每公升0.66毫克、0.77毫克及0.89\n    毫克，因而查悉上情。\n二、本件證據部分，引用檢察官聲請簡易判決處刑書之記載（如\n    附件）。\n三、按刑法第185條之3係抽象危險犯，非實害犯，行為人客觀上\n    已達不能安全駕駛之程度，且主觀上知其飲酒可能造成不能\n    安全駕駛結果，竟仍放任自己駕駛，即應認有故意，而該當\n    該罪。至於是否達『不能安全駕駛之程度』之認定，應依具\n    體個案之實際情形判斷之，依目前醫學一致見解，吐氣酒精\n    濃度達每公升0.25毫克以上時，將使駕駛人產生複雜之技巧\n    障礙、駕駛能力變壞之行為表現，肇事比率比一般未飲酒時\n    高出2倍；吐氣酒精濃度達每公升0.5毫克以上時，將使駕駛\n    人產生說話含糊、腳步不穩之行為表現，肇事比率比一般未\n    飲酒時高出7 倍；吐氣酒精濃度達每公升0.55毫克以上時，\n    將使駕駛人產生平衡感與判斷力障礙升高之行為表現，肇事\n    比率比一般未飲酒時高出10倍；甚而如吐氣酒精濃度達每公\n    升0.75毫克時，駕駛人將產生明顯酒醉、步履蹣跚之行為狀\n    態，其肇事比率比一般高25倍，並認為吐氣酒精濃度達每公\n    升0.55毫克以上時，即達絕對『不能安全駕駛之程度』。因\n    該0.55毫克之數值，係經由實際偵測所得之統計值，為經驗\n    科學上所肯定之客觀實驗數據，是以該數值作為絕對不能安\n    全駕駛之標準，不僅不違反經驗法則，且免舉證之困難。準\n    此，若吐氣酒精濃度達每公升0.55毫克以上時，應認已達絕\n    對不能安全駕駛之程度，若數值在此之下，仍須輔以客觀事\n    實，方可認定是否已達不能安全駕駛之程度，並應由檢察官\n    就此負舉證責任。\n四、本件被告呼氣酒精濃度為每公升0.66毫克、0.77毫克及0.89\n    毫克，應已達絕對不能安全駕駛之程度，與被告酒後是否清\n    醒無關，故本件事證明確，被告犯行洵堪認定。核其所為，\n    係犯刑法第185 條之3 之服用酒類不能安全駕駛動力交通工\n    具而駕駛罪。爰審酌被告在酒後已達絕對不能安全駕駛狀態\n    下，猶貿然駕車上路，並發生車禍，已對其他用路人之安全\n    構成極大威脅，行為實有非議之處，並參以被告坦承犯行，\n    及其呼氣酒精濃度達公升0.66毫克、0.77毫克及0.89毫克等\n    一切情狀，量處如主文所示之刑，併諭知易科罰金之折算標\n    準。\n五、依刑事訴訟法第449條第1項前段、第454條第2項，刑法第18\n    5條之3、第41條第1項前段，罰金罰鍰提高標準條例第2條，\n    逕以簡易判決處如主文所示之刑。\n六、如不服本判決，應於判決書送達之日起10日內，向本院提出\n    上訴狀。\n中    華    民    國    94    年    7     月    14    日\n                  交通法庭    法  官  方百正\n以上正本證明與原本無異。\n中    華    民    國    94    年    7     月    14    日\n                              書記官  郭素蓉\n附錄法條：\n中華民國刑法第185條之3\n服用毒品、麻醉藥品、酒類或其他相類之物，不能安全駕駛動力\n交通工具而駕駛者，處一年以下有期徒刑、拘役或三萬元以下罰\n",
  "structure": {
    "main": "甲○○服用酒類，不能安全駕駛動力交通工具而駕駛，處拘役參\n拾日，如易科罰金，以參佰元折算壹日。",
    "fact": "一、甲○○明知飲酒可能造成不能安全駕駛之結果，於民國94年\n    6 月5 日13時許，在高雄縣彌陀鄉某處，與同事飲用酒類，\n    當酒後客觀上已達不能安全駕駛之程度下，於94年6 月5 日\n    15時10分前之某時，仍駕駛車牌號碼ZE─5360號自小客車上\n    路，沿高雄縣彌陀鄉往高雄市楠梓區方向行駛，俟於94年 6\n    月5 日15時10分許，行經高雄市○○區○○路、德惠路口時\n    ，欲左轉六合二路，適乙○○駕駛車牌號碼XC─5091號自小\n    客車，沿德民路由東向西方向行駛至德惠路口，欲左轉楠梓\n    加工區第四出入口，兩車因而互撞，嗣於94年6 月5 日15時\n    44分、16時38分、16時55分許，經警施以3 次酒精濃度測試\n    ，測出其呼氣酒精濃度為每公升0.66毫克、0.77毫克及0.89\n    毫克，因而查悉上情。\n二、本件證據部分，引用檢察官聲請簡易判決處刑書之記載（如\n    附件）。\n三、按刑法第185條之3係抽象危險犯，非實害犯，行為人客觀上\n    已達不能安全駕駛之程度，且主觀上知其飲酒可能造成不能\n    安全駕駛結果，竟仍放任自己駕駛，即應認有故意，而該當\n    該罪。至於是否達『不能安全駕駛之程度』之認定，應依具\n    體個案之實際情形判斷之，依目前醫學一致見解，吐氣酒精\n    濃度達每公升0.25毫克以上時，將使駕駛人產生複雜之技巧\n    障礙、駕駛能力變壞之行為表現，肇事比率比一般未飲酒時\n    高出2倍；吐氣酒精濃度達每公升0.5毫克以上時，將使駕駛\n    人產生說話含糊、腳步不穩之行為表現，肇事比率比一般未\n    飲酒時高出7 倍；吐氣酒精濃度達每公升0.55毫克以上時，\n    將使駕駛人產生平衡感與判斷力障礙升高之行為表現，肇事\n    比率比一般未飲酒時高出10倍；甚而如吐氣酒精濃度達每公\n    升0.75毫克時，駕駛人將產生明顯酒醉、步履蹣跚之行為狀\n    態，其肇事比率比一般高25倍，並認為吐氣酒精濃度達每公\n    升0.55毫克以上時，即達絕對『不能安全駕駛之程度』。因\n    該0.55毫克之數值，係經由實際偵測所得之統計值，為經驗\n    科學上所肯定之客觀實驗數據，是以該數值作為絕對不能安\n    全駕駛之標準，不僅不違反經驗法則，且免舉證之困難。準\n    此，若吐氣酒精濃度達每公升0.55毫克以上時，應認已達絕\n    對不能安全駕駛之程度，若數值在此之下，仍須輔以客觀事\n    實，方可認定是否已達不能安全駕駛之程度，並應由檢察官\n    就此負舉證責任。\n四、本件被告呼氣酒精濃度為每公升0.66毫克、0.77毫克及0.89\n    毫克，應已達絕對不能安全駕駛之程度，與被告酒後是否清\n    醒無關，故本件事證明確，被告犯行洵堪認定。核其所為，\n    係犯刑法第185 條之3 之服用酒類不能安全駕駛動力交通工\n    具而駕駛罪。爰審酌被告在酒後已達絕對不能安全駕駛狀態\n    下，猶貿然駕車上路，並發生車禍，已對其他用路人之安全\n    構成極大威脅，行為實有非議之處，並參以被告坦承犯行，\n    及其呼氣酒精濃度達公升0.66毫克、0.77毫克及0.89毫克等\n    一切情狀，量處如主文所示之刑，併諭知易科罰金之折算標\n    準。\n五、依刑事訴訟法第449條第1項前段、第454條第2項，刑法第18\n    5條之3、第41條第1項前段，罰金罰鍰提高標準條例第2條，\n    逕以簡易判決處如主文所示之刑。\n六、如不服本判決，應於判決書送達之日起10日內，向本院提出\n    上訴狀。",
    "reason": "一、甲○○明知飲酒可能造成不能安全駕駛之結果，於民國94年\n    6 月5 日13時許，在高雄縣彌陀鄉某處，與同事飲用酒類，\n    當酒後客觀上已達不能安全駕駛之程度下，於94年6 月5 日\n    15時10分前之某時，仍駕駛車牌號碼ZE─5360號自小客車上\n    路，沿高雄縣彌陀鄉往高雄市楠梓區方向行駛，俟於94年 6\n    月5 日15時10分許，行經高雄市○○區○○路、德惠路口時\n    ，欲左轉六合二路，適乙○○駕駛車牌號碼XC─5091號自小\n    客車，沿德民路由東向西方向行駛至德惠路口，欲左轉楠梓\n    加工區第四出入口，兩車因而互撞，嗣於94年6 月5 日15時\n    44分、16時38分、16時55分許，經警施以3 次酒精濃度測試\n    ，測出其呼氣酒精濃度為每公升0.66毫克、0.77毫克及0.89\n    毫克，因而查悉上情。\n二、本件證據部分，引用檢察官聲請簡易判決處刑書之記載（如\n    附件）。\n三、按刑法第185條之3係抽象危險犯，非實害犯，行為人客觀上\n    已達不能安全駕駛之程度，且主觀上知其飲酒可能造成不能\n    安全駕駛結果，竟仍放任自己駕駛，即應認有故意，而該當\n    該罪。至於是否達『不能安全駕駛之程度』之認定，應依具\n    體個案之實際情形判斷之，依目前醫學一致見解，吐氣酒精\n    濃度達每公升0.25毫克以上時，將使駕駛人產生複雜之技巧\n    障礙、駕駛能力變壞之行為表現，肇事比率比一般未飲酒時\n    高出2倍；吐氣酒精濃度達每公升0.5毫克以上時，將使駕駛\n    人產生說話含糊、腳步不穩之行為表現，肇事比率比一般未\n    飲酒時高出7 倍；吐氣酒精濃度達每公升0.55毫克以上時，\n    將使駕駛人產生平衡感與判斷力障礙升高之行為表現，肇事\n    比率比一般未飲酒時高出10倍；甚而如吐氣酒精濃度達每公\n    升0.75毫克時，駕駛人將產生明顯酒醉、步履蹣跚之行為狀\n    態，其肇事比率比一般高25倍，並認為吐氣酒精濃度達每公\n    升0.55毫克以上時，即達絕對『不能安全駕駛之程度』。因\n    該0.55毫克之數值，係經由實際偵測所得之統計值，為經驗\n    科學上所肯定之客觀實驗數據，是以該數值作為絕對不能安\n    全駕駛之標準，不僅不違反經驗法則，且免舉證之困難。準\n    此，若吐氣酒精濃度達每公升0.55毫克以上時，應認已達絕\n    對不能安全駕駛之程度，若數值在此之下，仍須輔以客觀事\n    實，方可認定是否已達不能安全駕駛之程度，並應由檢察官\n    就此負舉證責任。\n四、本件被告呼氣酒精濃度為每公升0.66毫克、0.77毫克及0.89\n    毫克，應已達絕對不能安全駕駛之程度，與被告酒後是否清\n    醒無關，故本件事證明確，被告犯行洵堪認定。核其所為，\n    係犯刑法第185 條之3 之服用酒類不能安全駕駛動力交通工\n    具而駕駛罪。爰審酌被告在酒後已達絕對不能安全駕駛狀態\n    下，猶貿然駕車上路，並發生車禍，已對其他用路人之安全\n    構成極大威脅，行為實有非議之處，並參以被告坦承犯行，\n    及其呼氣酒精濃度達公升0.66毫克、0.77毫克及0.89毫克等\n    一切情狀，量處如主文所示之刑，併諭知易科罰金之折算標\n    準。\n五、依刑事訴訟法第449條第1項前段、第454條第2項，刑法第18\n    5條之3、第41條第1項前段，罰金罰鍰提高標準條例第2條，\n    逕以簡易判決處如主文所示之刑。\n六、如不服本判決，應於判決書送達之日起10日內，向本院提出\n    上訴狀。"
  },
  "search": "臺灣高雄地方法院刑事簡易判決94年度交簡字第1969號聲請人臺灣高雄地方法院檢察署檢察官被告甲○○男民國5.上列被告因公共危險案件，經檢察官聲請簡易判決處刑（94年度偵字第13931號），本院判決如下：主文甲○○服用酒類，不能安全駕駛動力交通工具而駕駛，處拘役參拾日，如易科罰金，以參佰元折算壹日。事實及理由一、甲○○明知飲酒可能造成不能安全駕駛之結果，於民國94年6月5日13時許，在高雄縣彌陀鄉某處，與同事飲用酒類，當酒後客觀上已達不能安全駕駛之程度下，於94年6月5日15時10分前之某時，仍駕駛車牌號碼ZE─5360號自小客車上路，沿高雄縣彌陀鄉往高雄市楠梓區方向行駛，俟於94年6月5日15時10分許，行經高雄市○○區○○路、德惠路口時，欲左轉六合二路，適乙○○駕駛車牌號碼XC─5091號自小客車，沿德民路由東向西方向行駛至德惠路口，欲左轉楠梓加工區第四出入口，兩車因而互撞，嗣於94年6月5日15時44分、16時38分、16時55分許，經警施以3次酒精濃度測試，測出其呼氣酒精濃度為每公升0.66毫克、0.77毫克及0.89毫克，因而查悉上情。二、本件證據部分，引用檢察官聲請簡易判決處刑書之記載（如附件）。三、按刑法第185條之3係抽象危險犯，非實害犯，行為人客觀上已達不能安全駕駛之程度，且主觀上知其飲酒可能造成不能安全駕駛結果，竟仍放任自己駕駛，即應認有故意，而該當該罪。至於是否達『不能安全駕駛之程度』之認定，應依具體個案之實際情形判斷之，依目前醫學一致見解，吐氣酒精濃度達每公升0.25毫克以上時，將使駕駛人產生複雜之技巧障礙、駕駛能力變壞之行為表現，肇事比率比一般未飲酒時高出2倍；吐氣酒精濃度達每公升0.5毫克以上時，將使駕駛人產生說話含糊、腳步不穩之行為表現，肇事比率比一般未飲酒時高出7倍；吐氣酒精濃度達每公升0.55毫克以上時，將使駕駛人產生平衡感與判斷力障礙升高之行為表現，肇事比率比一般未飲酒時高出10倍；甚而如吐氣酒精濃度達每公升0.75毫克時，駕駛人將產生明顯酒醉、步履蹣跚之行為狀態，其肇事比率比一般高25倍，並認為吐氣酒精濃度達每公升0.55毫克以上時，即達絕對『不能安全駕駛之程度』。因該0.55毫克之數值，係經由實際偵測所得之統計值，為經驗科學上所肯定之客觀實驗數據，是以該數值作為絕對不能安全駕駛之標準，不僅不違反經驗法則，且免舉證之困難。準此，若吐氣酒精濃度達每公升0.55毫克以上時，應認已達絕對不能安全駕駛之程度，若數值在此之下，仍須輔以客觀事實，方可認定是否已達不能安全駕駛之程度，並應由檢察官就此負舉證責任。四、本件被告呼氣酒精濃度為每公升0.66毫克、0.77毫克及0.89毫克，應已達絕對不能安全駕駛之程度，與被告酒後是否清醒無關，故本件事證明確，被告犯行洵堪認定。核其所為，係犯刑法第185條之3之服用酒類不能安全駕駛動力交通工具而駕駛罪。爰審酌被告在酒後已達絕對不能安全駕駛狀態下，猶貿然駕車上路，並發生車禍，已對其他用路人之安全構成極大威脅，行為實有非議之處，並參以被告坦承犯行，及其呼氣酒精濃度達公升0.66毫克、0.77毫克及0.89毫克等一切情狀，量處如主文所示之刑，併諭知易科罰金之折算標準。五、依刑事訴訟法第449條第1項前段、第454條第2項，刑法第185條之3、第41條第1項前段，罰金罰鍰提高標準條例第2條，逕以簡易判決處如主文所示之刑。六、如不服本判決，應於判決書送達之日起10日內，向本院提出上訴狀。中華民國94年7月14日交通法庭法官方百正以上正本證明與原本無異。中華民國94年7月14日書記官郭素蓉附錄法條：中華民國刑法第185條之3服用毒品、麻醉藥品、酒類或其他相類之物，不能安全駕駛動力交通工具而駕駛者，處一年以下有期徒刑、拘役或三萬元以下罰",
  "characters": {
    "judges": [
      "方百正"
    ],
    "prosecutors": [

    ],
    "lawyers": [

    ],
    "clerks": [
      "郭素蓉"
    ],
    "plaintiffs": [

    ],
    "defendants": [
      "甲○○  男  民國5."
    ],
    "prosecutor_office": [
      "臺灣高雄地方法院檢察署檢察官"
    ],
    "creditors": [

    ],
    "debtors": [

    ],
    "judicial_associate_officer": [

    ]
  },
  "adjudged_at": "2005-07-14",
  "created_at": "2016-02-07 08:31:49",
  "updated_at": "2016-02-07 08:31:49"
}