{
  "identify": "CYD-94-嘉簡-1104-20050927-1",
  "court": {
    "name": "臺灣嘉義地方法院",
    "code": "CYD"
  },
  "division": {
    "name": "刑事",
    "code": "M"
  },
  "year": 94,
  "word": "嘉簡",
  "number": "1104",
  "jcheck": "1",
  "reason": "詐欺",
  "content": "臺灣嘉義地方法院刑事簡易判決        94年度嘉簡字第1104號\n聲  請  人  臺灣嘉義地方法院檢察署檢察官\n被      告  甲○○\n上列被告因詐欺案件，經檢察官聲請以簡易判決處刑 (94年度偵\n字第4742），本院判決如下：\n    主  文\n甲○○幫助意圖為自己不法之所有，以詐術使人將本人之物交付\n，處有期徒刑月，如易科罰金，以佰元折算壹日。\n    事實及理由\n一、本案犯罪事實及證據，除證據部分補充台灣高等法院被告前\n    案紀錄表一份外，其餘均引用檢察官聲請簡易判決處刑書之\n    記載（如附件）。\n二、查於金融機構開設帳戶，請領存摺及金融卡一事，係針對個\n    人身分之社會信用而予以資金流通，具有強烈之屬人性，而\n    金融帳戶為個人理財之工具，申請開設金融帳戶並無任何特\n    殊之限制，一般民眾皆得以存入最低開戶金額之方式申請之\n    ，且一人得在不同之金融機構申請數個存款帳戶使用，一般\n    具行為能力之人向金融機關申辦存款帳戶，並非難事，且無\n    須支付手續費用，此屬眾所週知之事，故如非為詐騙財物、\n    洗錢等不法目的，依常情應無支付金錢購買他人之帳戶存褶\n    、提款卡及印章之理，此等行為客觀上已屬可疑，有為隱瞞\n    某種作為流程及行為人身份曝光等不法意圖應可預見；次查\n    ，被告甲○○為年滿20歲之成年人，心智正常無缺陷，具相\n    當知識，可預見該年籍姓名均不詳綽號「阿偉」之成年人蒐\n    集他人之存摺帳戶、提款卡使用，將可能藉收購之存摺帳戶\n    、提款卡遂行財產上犯罪之目的；且明知提供銀行帳戶給不\n    明人士，易為歹徒作為財產犯罪之工具，竟仍以新台幣2000\n    元代價，提供帳戶予綽號「阿偉」之人使用，其顯有幫助詐\n    欺之【不確定故意】（亦即「行為人對於構成犯罪之事實，\n    預見其發生而其發生並不違背其本意者」），灼然至明。且\n    其所為提供帳戶予他人之行為屬刑法詐欺取財構成要件以外\n    之行為。\n三、核被告所為，係犯刑法第339條第1項詐欺取財罪之幫助犯。\n    又被告係基於幫助之犯意為之，為幫助犯，應依刑法第30條\n    第2項依正犯之刑減輕之。爰審酌被告將帳戶存摺交予綽號\n    「阿偉」之成年男子，供不法之徒犯罪詐欺他人財物，且使\n    警察機關追查真正幕後詐欺正犯憑添困擾、助長犯罪，對被\n    害人所受之財產上之損害非輕，犯後尚能坦認犯行之態度等\n    一切情狀，量處如主文所示之刑，並諭知易科罰金之折算標\n    準，以資懲儆。\n四、依刑事訴訟法第449條第1項前段、第454條第2項，刑法第\n    339條第1項、第30條、第41條第1項前段，罰金罰鍰提高標\n    準條例第1條前段、第2條，逕以簡易判決如主文。\n五、如對本判決上訴，須於判決送達後10日內向本院提出上訴狀\n    （應附繕本）\n中    華    民    國    94    年    9     月    27    日\n                  刑事第二庭    法  官  洪嘉蘭\n以上正本證明與原本無異。\n中    華    民    國    94    年    9     月    27    日\n                                書記官  吳明蓉\n附錄法條:\n中華民國刑法第339條第1項\n意圖為自己或第三人不法之所有，以詐術使人將本人或第三人之\n物交付者，處五年以下有期徒刑、拘役或科或併科一千元以下罰\n金。\n",
  "structure": {
    "main": "甲○○幫助意圖為自己不法之所有，以詐術使人將本人之物交付\n，處有期徒刑月，如易科罰金，以佰元折算壹日。",
    "fact": "一、本案犯罪事實及證據，除證據部分補充台灣高等法院被告前\n    案紀錄表一份外，其餘均引用檢察官聲請簡易判決處刑書之\n    記載（如附件）。\n二、查於金融機構開設帳戶，請領存摺及金融卡一事，係針對個\n    人身分之社會信用而予以資金流通，具有強烈之屬人性，而\n    金融帳戶為個人理財之工具，申請開設金融帳戶並無任何特\n    殊之限制，一般民眾皆得以存入最低開戶金額之方式申請之\n    ，且一人得在不同之金融機構申請數個存款帳戶使用，一般\n    具行為能力之人向金融機關申辦存款帳戶，並非難事，且無\n    須支付手續費用，此屬眾所週知之事，故如非為詐騙財物、\n    洗錢等不法目的，依常情應無支付金錢購買他人之帳戶存褶\n    、提款卡及印章之理，此等行為客觀上已屬可疑，有為隱瞞\n    某種作為流程及行為人身份曝光等不法意圖應可預見；次查\n    ，被告甲○○為年滿20歲之成年人，心智正常無缺陷，具相\n    當知識，可預見該年籍姓名均不詳綽號「阿偉」之成年人蒐\n    集他人之存摺帳戶、提款卡使用，將可能藉收購之存摺帳戶\n    、提款卡遂行財產上犯罪之目的；且明知提供銀行帳戶給不\n    明人士，易為歹徒作為財產犯罪之工具，竟仍以新台幣2000\n    元代價，提供帳戶予綽號「阿偉」之人使用，其顯有幫助詐\n    欺之【不確定故意】（亦即「行為人對於構成犯罪之事實，\n    預見其發生而其發生並不違背其本意者」），灼然至明。且\n    其所為提供帳戶予他人之行為屬刑法詐欺取財構成要件以外\n    之行為。\n三、核被告所為，係犯刑法第339條第1項詐欺取財罪之幫助犯。\n    又被告係基於幫助之犯意為之，為幫助犯，應依刑法第30條\n    第2項依正犯之刑減輕之。爰審酌被告將帳戶存摺交予綽號\n    「阿偉」之成年男子，供不法之徒犯罪詐欺他人財物，且使\n    警察機關追查真正幕後詐欺正犯憑添困擾、助長犯罪，對被\n    害人所受之財產上之損害非輕，犯後尚能坦認犯行之態度等\n    一切情狀，量處如主文所示之刑，並諭知易科罰金之折算標\n    準，以資懲儆。\n四、依刑事訴訟法第449條第1項前段、第454條第2項，刑法第\n    339條第1項、第30條、第41條第1項前段，罰金罰鍰提高標\n    準條例第1條前段、第2條，逕以簡易判決如主文。\n五、如對本判決上訴，須於判決送達後10日內向本院提出上訴狀\n    （應附繕本）",
    "reason": "一、本案犯罪事實及證據，除證據部分補充台灣高等法院被告前\n    案紀錄表一份外，其餘均引用檢察官聲請簡易判決處刑書之\n    記載（如附件）。\n二、查於金融機構開設帳戶，請領存摺及金融卡一事，係針對個\n    人身分之社會信用而予以資金流通，具有強烈之屬人性，而\n    金融帳戶為個人理財之工具，申請開設金融帳戶並無任何特\n    殊之限制，一般民眾皆得以存入最低開戶金額之方式申請之\n    ，且一人得在不同之金融機構申請數個存款帳戶使用，一般\n    具行為能力之人向金融機關申辦存款帳戶，並非難事，且無\n    須支付手續費用，此屬眾所週知之事，故如非為詐騙財物、\n    洗錢等不法目的，依常情應無支付金錢購買他人之帳戶存褶\n    、提款卡及印章之理，此等行為客觀上已屬可疑，有為隱瞞\n    某種作為流程及行為人身份曝光等不法意圖應可預見；次查\n    ，被告甲○○為年滿20歲之成年人，心智正常無缺陷，具相\n    當知識，可預見該年籍姓名均不詳綽號「阿偉」之成年人蒐\n    集他人之存摺帳戶、提款卡使用，將可能藉收購之存摺帳戶\n    、提款卡遂行財產上犯罪之目的；且明知提供銀行帳戶給不\n    明人士，易為歹徒作為財產犯罪之工具，竟仍以新台幣2000\n    元代價，提供帳戶予綽號「阿偉」之人使用，其顯有幫助詐\n    欺之【不確定故意】（亦即「行為人對於構成犯罪之事實，\n    預見其發生而其發生並不違背其本意者」），灼然至明。且\n    其所為提供帳戶予他人之行為屬刑法詐欺取財構成要件以外\n    之行為。\n三、核被告所為，係犯刑法第339條第1項詐欺取財罪之幫助犯。\n    又被告係基於幫助之犯意為之，為幫助犯，應依刑法第30條\n    第2項依正犯之刑減輕之。爰審酌被告將帳戶存摺交予綽號\n    「阿偉」之成年男子，供不法之徒犯罪詐欺他人財物，且使\n    警察機關追查真正幕後詐欺正犯憑添困擾、助長犯罪，對被\n    害人所受之財產上之損害非輕，犯後尚能坦認犯行之態度等\n    一切情狀，量處如主文所示之刑，並諭知易科罰金之折算標\n    準，以資懲儆。\n四、依刑事訴訟法第449條第1項前段、第454條第2項，刑法第\n    339條第1項、第30條、第41條第1項前段，罰金罰鍰提高標\n    準條例第1條前段、第2條，逕以簡易判決如主文。\n五、如對本判決上訴，須於判決送達後10日內向本院提出上訴狀\n    （應附繕本）"
  },
  "search": "臺灣嘉義地方法院刑事簡易判決94年度嘉簡字第1104號聲請人臺灣嘉義地方法院檢察署檢察官被告甲○○上列被告因詐欺案件，經檢察官聲請以簡易判決處刑(94年度偵字第4742），本院判決如下：主文甲○○幫助意圖為自己不法之所有，以詐術使人將本人之物交付，處有期徒刑月，如易科罰金，以佰元折算壹日。事實及理由一、本案犯罪事實及證據，除證據部分補充台灣高等法院被告前案紀錄表一份外，其餘均引用檢察官聲請簡易判決處刑書之記載（如附件）。二、查於金融機構開設帳戶，請領存摺及金融卡一事，係針對個人身分之社會信用而予以資金流通，具有強烈之屬人性，而金融帳戶為個人理財之工具，申請開設金融帳戶並無任何特殊之限制，一般民眾皆得以存入最低開戶金額之方式申請之，且一人得在不同之金融機構申請數個存款帳戶使用，一般具行為能力之人向金融機關申辦存款帳戶，並非難事，且無須支付手續費用，此屬眾所週知之事，故如非為詐騙財物、洗錢等不法目的，依常情應無支付金錢購買他人之帳戶存褶、提款卡及印章之理，此等行為客觀上已屬可疑，有為隱瞞某種作為流程及行為人身份曝光等不法意圖應可預見；次查，被告甲○○為年滿20歲之成年人，心智正常無缺陷，具相當知識，可預見該年籍姓名均不詳綽號「阿偉」之成年人蒐集他人之存摺帳戶、提款卡使用，將可能藉收購之存摺帳戶、提款卡遂行財產上犯罪之目的；且明知提供銀行帳戶給不明人士，易為歹徒作為財產犯罪之工具，竟仍以新台幣2000元代價，提供帳戶予綽號「阿偉」之人使用，其顯有幫助詐欺之【不確定故意】（亦即「行為人對於構成犯罪之事實，預見其發生而其發生並不違背其本意者」），灼然至明。且其所為提供帳戶予他人之行為屬刑法詐欺取財構成要件以外之行為。三、核被告所為，係犯刑法第339條第1項詐欺取財罪之幫助犯。又被告係基於幫助之犯意為之，為幫助犯，應依刑法第30條第2項依正犯之刑減輕之。爰審酌被告將帳戶存摺交予綽號「阿偉」之成年男子，供不法之徒犯罪詐欺他人財物，且使警察機關追查真正幕後詐欺正犯憑添困擾、助長犯罪，對被害人所受之財產上之損害非輕，犯後尚能坦認犯行之態度等一切情狀，量處如主文所示之刑，並諭知易科罰金之折算標準，以資懲儆。四、依刑事訴訟法第449條第1項前段、第454條第2項，刑法第339條第1項、第30條、第41條第1項前段，罰金罰鍰提高標準條例第1條前段、第2條，逕以簡易判決如主文。五、如對本判決上訴，須於判決送達後10日內向本院提出上訴狀（應附繕本）中華民國94年9月27日刑事第二庭法官洪嘉蘭以上正本證明與原本無異。中華民國94年9月27日書記官吳明蓉附錄法條:中華民國刑法第339條第1項意圖為自己或第三人不法之所有，以詐術使人將本人或第三人之物交付者，處五年以下有期徒刑、拘役或科或併科一千元以下罰金。",
  "characters": {
    "judges": [
      "洪嘉蘭"
    ],
    "prosecutors": [

    ],
    "lawyers": [

    ],
    "clerks": [
      "吳明蓉"
    ],
    "plaintiffs": [

    ],
    "defendants": [
      "甲○○"
    ],
    "prosecutor_office": [
      "臺灣嘉義地方法院檢察署檢察官"
    ],
    "creditors": [

    ],
    "debtors": [

    ],
    "judicial_associate_officer": [

    ]
  },
  "adjudged_at": "2005-09-27",
  "created_at": "2016-02-06 19:48:38",
  "updated_at": "2016-02-06 19:48:38"
}