{
  "identify": "KLD-94-訴-134-20050927-2",
  "court": {
    "name": "臺灣基隆地方法院",
    "code": "KLD"
  },
  "division": {
    "name": "民事",
    "code": "V"
  },
  "year": 94,
  "word": "訴",
  "number": "134",
  "jcheck": "2",
  "reason": "清償債務",
  "content": "臺灣基隆地方法院民事判決               94年度訴字第134號\n原      告  合作金庫銀行股份有限公司\n法定代理人  戊○○\n訴訟代理人  丁○○\n            丙○○\n被      告  乙○○\n            甲○○\n上列當事人間請求清償債務事件，本院於94年9月20日言詞辯論\n終結，判決如下：\n    主  文\n被告應連帶給付原告新台幣貳佰肆拾貳萬玖仟捌佰陸拾貳元，及\n自民國85年8月16日起至清償日止，按年息百分之十一點二五計\n算之利息，暨按上開利率百分之二十計算之違約金。\n訴訟費用新臺幣貳萬陸仟壹佰伍拾柒元由被告連帶負擔。\n    事實及理由\n一、本件兩造合意由本院為第一審管轄法院，有授信約定書第12\n    條約定附卷可按，且未據被告抗辯有民事訴訟法第28條第2\n    項顯失公平之情形，本院依法應有管轄權，合先敘明。\n二、被告均經合法通知，未於言詞辯論期日到場，亦未提出書狀\n    作何聲明或陳述，核無民事訴訟法第386條所列各款情形，\n    爰依原告之聲請，由其一造辯論而為判決。\n三、原告起訴主張：被告乙○○於民國82年1月29日邀同被告甲\n    ○○為連帶保證人，向原告借用新臺幣（下同）5,200,000\n    元，借款期間自82年1月29日起至97年1月29日止，約定利息\n    按原告基本放款利率百分之八點五五加碼年息百分之三計算\n    ，並採浮動利率，隨原告基本放款利率調整，本息自85 年2\n    月29日起以每一個月為一期共分144期平均攤還。並約定如\n    未按期償還，除按原借款利率給付遲延利息外，並自約定攤\n    還日起，逾期六個月以內者，按上開利率百分之十，逾期超\n    過六個月以上者，按上開利率百分之二十計算之違約金。詎\n    被告乙○○未依約攤還本息，依約視為債務全部到期，經原\n    告聲請台灣高雄地方法院85年度執字第10289號強制執行被\n    告乙○○名下財產，於85年9月13日實行分配，受償執行費\n    用及部分本息計3,992,387元，尚有2,429,862元（內含至85\n    年8月15日之違約金）及如主文第一項所示之利息及違約金\n    未受清償。而被告甲○○為連帶保證人，自應負連帶清償責\n    任。為此提起本件訴訟。其訴之聲明如主文第一項所示。\n四、本件原告主張之上開事實，業據提出借據暨受信約定書、台\n    灣高雄地院85年執字第10289號強制執行分配表各1件（均為\n    影本）為證，被告經合法通知，未於言詞辯論期日到場爭執\n    或提出書狀以供參酌，本院審酌原告提出之證據與其主張內\n    容相符，認原告之主張為真實。\n五、從而，原告依消費借貸及連帶保證之法律關係，請求被告連\n    帶給付如主文第一項所示之欠款、利息及違約金，為有理由\n    ，應予准許。\n六、據上論結，本件原告之訴為有理由，依民事訴訟法第385條\n    第1項前段、第87條第1項、第85條第2項，判決如主文。\n中    華    民    國    94    年    9     月    27    日\n                  民事庭法  官  林李達\n以上正本係照原本作成。\n對於本件判決如有不服，應於收受送達後20日內向本院提出上訴\n書狀，敘述上訴之理由，上訴於臺灣高等法院，並按他造當事人\n之人數附具繕本。\n中    華    民    國    94    年    9     月    29    日\n                        書記官  黃錫煒\n",
  "structure": {
    "main": "被告應連帶給付原告新台幣貳佰肆拾貳萬玖仟捌佰陸拾貳元，及\n自民國85年8月16日起至清償日止，按年息百分之十一點二五計\n算之利息，暨按上開利率百分之二十計算之違約金。\n訴訟費用新臺幣貳萬陸仟壹佰伍拾柒元由被告連帶負擔。",
    "fact": "一、本件兩造合意由本院為第一審管轄法院，有授信約定書第12\n    條約定附卷可按，且未據被告抗辯有民事訴訟法第28條第2\n    項顯失公平之情形，本院依法應有管轄權，合先敘明。\n二、被告均經合法通知，未於言詞辯論期日到場，亦未提出書狀\n    作何聲明或陳述，核無民事訴訟法第386條所列各款情形，\n    爰依原告之聲請，由其一造辯論而為判決。\n三、原告起訴主張：被告乙○○於民國82年1月29日邀同被告甲\n    ○○為連帶保證人，向原告借用新臺幣（下同）5,200,000\n    元，借款期間自82年1月29日起至97年1月29日止，約定利息\n    按原告基本放款利率百分之八點五五加碼年息百分之三計算\n    ，並採浮動利率，隨原告基本放款利率調整，本息自85 年2\n    月29日起以每一個月為一期共分144期平均攤還。並約定如\n    未按期償還，除按原借款利率給付遲延利息外，並自約定攤\n    還日起，逾期六個月以內者，按上開利率百分之十，逾期超\n    過六個月以上者，按上開利率百分之二十計算之違約金。詎\n    被告乙○○未依約攤還本息，依約視為債務全部到期，經原\n    告聲請台灣高雄地方法院85年度執字第10289號強制執行被\n    告乙○○名下財產，於85年9月13日實行分配，受償執行費\n    用及部分本息計3,992,387元，尚有2,429,862元（內含至85\n    年8月15日之違約金）及如主文第一項所示之利息及違約金\n    未受清償。而被告甲○○為連帶保證人，自應負連帶清償責\n    任。為此提起本件訴訟。其訴之聲明如主文第一項所示。\n四、本件原告主張之上開事實，業據提出借據暨受信約定書、台\n    灣高雄地院85年執字第10289號強制執行分配表各1件（均為\n    影本）為證，被告經合法通知，未於言詞辯論期日到場爭執\n    或提出書狀以供參酌，本院審酌原告提出之證據與其主張內\n    容相符，認原告之主張為真實。\n五、從而，原告依消費借貸及連帶保證之法律關係，請求被告連\n    帶給付如主文第一項所示之欠款、利息及違約金，為有理由\n    ，應予准許。\n六、據上論結，本件原告之訴為有理由，依民事訴訟法第385條\n    第1項前段、第87條第1項、第85條第2項，判決如主文。",
    "reason": "一、本件兩造合意由本院為第一審管轄法院，有授信約定書第12\n    條約定附卷可按，且未據被告抗辯有民事訴訟法第28條第2\n    項顯失公平之情形，本院依法應有管轄權，合先敘明。\n二、被告均經合法通知，未於言詞辯論期日到場，亦未提出書狀\n    作何聲明或陳述，核無民事訴訟法第386條所列各款情形，\n    爰依原告之聲請，由其一造辯論而為判決。\n三、原告起訴主張：被告乙○○於民國82年1月29日邀同被告甲\n    ○○為連帶保證人，向原告借用新臺幣（下同）5,200,000\n    元，借款期間自82年1月29日起至97年1月29日止，約定利息\n    按原告基本放款利率百分之八點五五加碼年息百分之三計算\n    ，並採浮動利率，隨原告基本放款利率調整，本息自85 年2\n    月29日起以每一個月為一期共分144期平均攤還。並約定如\n    未按期償還，除按原借款利率給付遲延利息外，並自約定攤\n    還日起，逾期六個月以內者，按上開利率百分之十，逾期超\n    過六個月以上者，按上開利率百分之二十計算之違約金。詎\n    被告乙○○未依約攤還本息，依約視為債務全部到期，經原\n    告聲請台灣高雄地方法院85年度執字第10289號強制執行被\n    告乙○○名下財產，於85年9月13日實行分配，受償執行費\n    用及部分本息計3,992,387元，尚有2,429,862元（內含至85\n    年8月15日之違約金）及如主文第一項所示之利息及違約金\n    未受清償。而被告甲○○為連帶保證人，自應負連帶清償責\n    任。為此提起本件訴訟。其訴之聲明如主文第一項所示。\n四、本件原告主張之上開事實，業據提出借據暨受信約定書、台\n    灣高雄地院85年執字第10289號強制執行分配表各1件（均為\n    影本）為證，被告經合法通知，未於言詞辯論期日到場爭執\n    或提出書狀以供參酌，本院審酌原告提出之證據與其主張內\n    容相符，認原告之主張為真實。\n五、從而，原告依消費借貸及連帶保證之法律關係，請求被告連\n    帶給付如主文第一項所示之欠款、利息及違約金，為有理由\n    ，應予准許。\n六、據上論結，本件原告之訴為有理由，依民事訴訟法第385條\n    第1項前段、第87條第1項、第85條第2項，判決如主文。"
  },
  "search": "臺灣基隆地方法院民事判決94年度訴字第134號原告合作金庫銀行股份有限公司法定代理人戊○○訴訟代理人丁○○丙○○被告乙○○甲○○上列當事人間請求清償債務事件，本院於94年9月20日言詞辯論終結，判決如下：主文被告應連帶給付原告新台幣貳佰肆拾貳萬玖仟捌佰陸拾貳元，及自民國85年8月16日起至清償日止，按年息百分之十一點二五計算之利息，暨按上開利率百分之二十計算之違約金。訴訟費用新臺幣貳萬陸仟壹佰伍拾柒元由被告連帶負擔。事實及理由一、本件兩造合意由本院為第一審管轄法院，有授信約定書第12條約定附卷可按，且未據被告抗辯有民事訴訟法第28條第2項顯失公平之情形，本院依法應有管轄權，合先敘明。二、被告均經合法通知，未於言詞辯論期日到場，亦未提出書狀作何聲明或陳述，核無民事訴訟法第386條所列各款情形，爰依原告之聲請，由其一造辯論而為判決。三、原告起訴主張：被告乙○○於民國82年1月29日邀同被告甲○○為連帶保證人，向原告借用新臺幣（下同）5,200,000元，借款期間自82年1月29日起至97年1月29日止，約定利息按原告基本放款利率百分之八點五五加碼年息百分之三計算，並採浮動利率，隨原告基本放款利率調整，本息自85年2月29日起以每一個月為一期共分144期平均攤還。並約定如未按期償還，除按原借款利率給付遲延利息外，並自約定攤還日起，逾期六個月以內者，按上開利率百分之十，逾期超過六個月以上者，按上開利率百分之二十計算之違約金。詎被告乙○○未依約攤還本息，依約視為債務全部到期，經原告聲請台灣高雄地方法院85年度執字第10289號強制執行被告乙○○名下財產，於85年9月13日實行分配，受償執行費用及部分本息計3,992,387元，尚有2,429,862元（內含至85年8月15日之違約金）及如主文第一項所示之利息及違約金未受清償。而被告甲○○為連帶保證人，自應負連帶清償責任。為此提起本件訴訟。其訴之聲明如主文第一項所示。四、本件原告主張之上開事實，業據提出借據暨受信約定書、台灣高雄地院85年執字第10289號強制執行分配表各1件（均為影本）為證，被告經合法通知，未於言詞辯論期日到場爭執或提出書狀以供參酌，本院審酌原告提出之證據與其主張內容相符，認原告之主張為真實。五、從而，原告依消費借貸及連帶保證之法律關係，請求被告連帶給付如主文第一項所示之欠款、利息及違約金，為有理由，應予准許。六、據上論結，本件原告之訴為有理由，依民事訴訟法第385條第1項前段、第87條第1項、第85條第2項，判決如主文。中華民國94年9月27日民事庭法官林李達以上正本係照原本作成。對於本件判決如有不服，應於收受送達後20日內向本院提出上訴書狀，敘述上訴之理由，上訴於臺灣高等法院，並按他造當事人之人數附具繕本。中華民國94年9月29日書記官黃錫煒",
  "characters": {
    "judges": [
      "林李達"
    ],
    "prosecutors": [

    ],
    "lawyers": [

    ],
    "clerks": [
      "黃錫煒"
    ],
    "plaintiffs": [
      "合作金庫銀行股份有限公司"
    ],
    "defendants": [
      "乙○○"
    ],
    "prosecutor_office": [

    ],
    "creditors": [

    ],
    "debtors": [

    ],
    "judicial_associate_officer": [

    ]
  },
  "adjudged_at": "2005-09-27",
  "created_at": "2016-02-06 19:42:50",
  "updated_at": "2016-02-06 19:42:50"
}