{
  "identify": "KSD-94-簡-5526-20050927-1",
  "court": {
    "name": "臺灣高雄地方法院",
    "code": "KSD"
  },
  "division": {
    "name": "刑事",
    "code": "M"
  },
  "year": 94,
  "word": "簡",
  "number": "5526",
  "jcheck": "1",
  "reason": "竊盜",
  "content": "臺灣高雄地方法院刑事簡易判決          94年度簡字第5526號\n聲  請  人  臺灣高雄地方法院檢察署檢察官\n被      告  乙○○\n上列被告因竊盜案件，經檢察官聲請以簡易判決處刑（94年度速\n偵字第1285號），本院判決如下：\n    主  文\n乙○○竊盜，處拘役參拾日，如易科罰金，以參佰元折算壹日。\n    事實及理由\n一、本件犯罪事實及證據，均引用檢察官聲請簡易判決處刑書之\n    記載（如附件）。\n二、核被告所為，係犯刑法第 320 條第 1 項之普通竊盜罪。爰\n    審酌被告貪圖一時小利，即侵害他人財產權益，造成告訴人\n    甲○○之損失及不便，洵值非難，惟念被告並無前科，此有\n    卷附臺灣高等法院被告前案紀錄表1 紙附卷可按，素行尚佳\n    ，且犯後坦承犯行，態度尚可，失竊財物價值約僅新台幣3\n    千5 百元，並已由告訴人領回等一切情狀，量處如主文所示\n    之刑，並諭知如易科罰金之折算標準。\n三、依刑事訴訟法第449 條第1 項、第3 項、第454 條第2 項，\n    刑法第320 條第1 項、第41條第1 項前段，罰金罰鍰提高標\n    準條例第1 條前段、第2 條，逕以簡易判決處刑如主文。\n四、如不服本判決，得自收受送達之日起10日內，向本院提起上\n    訴。\n中    華    民    國    94    年    9     月    27    日\n                    高雄簡易庭  法  官  林瑋桓\n以上正本，係照原本作成，證明與原本無異。\n中    華    民    國    94    年    9     月    27    日\n                                書記官  謝群育\n附錄本判決論罪之法條：\n刑法第320條第1項\n  意圖為自己或第三人不法之所有，而竊取他人之動產者，為竊\n  盜罪，處5 年以下有期徒刑、拘役或500元以下罰金。\n",
  "structure": {
    "main": "乙○○竊盜，處拘役參拾日，如易科罰金，以參佰元折算壹日。",
    "fact": "一、本件犯罪事實及證據，均引用檢察官聲請簡易判決處刑書之\n    記載（如附件）。\n二、核被告所為，係犯刑法第 320 條第 1 項之普通竊盜罪。爰\n    審酌被告貪圖一時小利，即侵害他人財產權益，造成告訴人\n    甲○○之損失及不便，洵值非難，惟念被告並無前科，此有\n    卷附臺灣高等法院被告前案紀錄表1 紙附卷可按，素行尚佳\n    ，且犯後坦承犯行，態度尚可，失竊財物價值約僅新台幣3\n    千5 百元，並已由告訴人領回等一切情狀，量處如主文所示\n    之刑，並諭知如易科罰金之折算標準。\n三、依刑事訴訟法第449 條第1 項、第3 項、第454 條第2 項，\n    刑法第320 條第1 項、第41條第1 項前段，罰金罰鍰提高標\n    準條例第1 條前段、第2 條，逕以簡易判決處刑如主文。\n四、如不服本判決，得自收受送達之日起10日內，向本院提起上\n    訴。",
    "reason": "一、本件犯罪事實及證據，均引用檢察官聲請簡易判決處刑書之\n    記載（如附件）。\n二、核被告所為，係犯刑法第 320 條第 1 項之普通竊盜罪。爰\n    審酌被告貪圖一時小利，即侵害他人財產權益，造成告訴人\n    甲○○之損失及不便，洵值非難，惟念被告並無前科，此有\n    卷附臺灣高等法院被告前案紀錄表1 紙附卷可按，素行尚佳\n    ，且犯後坦承犯行，態度尚可，失竊財物價值約僅新台幣3\n    千5 百元，並已由告訴人領回等一切情狀，量處如主文所示\n    之刑，並諭知如易科罰金之折算標準。\n三、依刑事訴訟法第449 條第1 項、第3 項、第454 條第2 項，\n    刑法第320 條第1 項、第41條第1 項前段，罰金罰鍰提高標\n    準條例第1 條前段、第2 條，逕以簡易判決處刑如主文。\n四、如不服本判決，得自收受送達之日起10日內，向本院提起上\n    訴。"
  },
  "search": "臺灣高雄地方法院刑事簡易判決94年度簡字第5526號聲請人臺灣高雄地方法院檢察署檢察官被告乙○○上列被告因竊盜案件，經檢察官聲請以簡易判決處刑（94年度速偵字第1285號），本院判決如下：主文乙○○竊盜，處拘役參拾日，如易科罰金，以參佰元折算壹日。事實及理由一、本件犯罪事實及證據，均引用檢察官聲請簡易判決處刑書之記載（如附件）。二、核被告所為，係犯刑法第320條第1項之普通竊盜罪。爰審酌被告貪圖一時小利，即侵害他人財產權益，造成告訴人甲○○之損失及不便，洵值非難，惟念被告並無前科，此有卷附臺灣高等法院被告前案紀錄表1紙附卷可按，素行尚佳，且犯後坦承犯行，態度尚可，失竊財物價值約僅新台幣3千5百元，並已由告訴人領回等一切情狀，量處如主文所示之刑，並諭知如易科罰金之折算標準。三、依刑事訴訟法第449條第1項、第3項、第454條第2項，刑法第320條第1項、第41條第1項前段，罰金罰鍰提高標準條例第1條前段、第2條，逕以簡易判決處刑如主文。四、如不服本判決，得自收受送達之日起10日內，向本院提起上訴。中華民國94年9月27日高雄簡易庭法官林瑋桓以上正本，係照原本作成，證明與原本無異。中華民國94年9月27日書記官謝群育附錄本判決論罪之法條：刑法第320條第1項意圖為自己或第三人不法之所有，而竊取他人之動產者，為竊盜罪，處5年以下有期徒刑、拘役或500元以下罰金。",
  "characters": {
    "judges": [
      "林瑋桓"
    ],
    "prosecutors": [

    ],
    "lawyers": [

    ],
    "clerks": [
      "謝群育"
    ],
    "plaintiffs": [

    ],
    "defendants": [
      "乙○○"
    ],
    "prosecutor_office": [
      "臺灣高雄地方法院檢察署檢察官"
    ],
    "creditors": [

    ],
    "debtors": [

    ],
    "judicial_associate_officer": [

    ]
  },
  "adjudged_at": "2005-09-27",
  "created_at": "2016-02-06 19:47:07",
  "updated_at": "2016-02-06 19:47:07"
}