{
  "identify": "KSD-94-簡-247-20050125-1",
  "court": {
    "name": "臺灣高雄地方法院",
    "code": "KSD"
  },
  "division": {
    "name": "刑事",
    "code": "M"
  },
  "year": 94,
  "word": "簡",
  "number": "247",
  "jcheck": "1",
  "reason": "違反動產擔保交易法",
  "content": "臺灣高雄地方法院刑事簡易判決                      九十四年度簡字第二四七號\n    聲  請  人  臺灣高雄地方法院檢察署檢察官\n    被      告  甲○○  男  四.\n右列被告因違反動產擔保交易法案件，經檢察官聲請以簡易判決處刑（九十三年度偵\n緝字第二三一０號），本院判決如左：\n    主  文\n甲○○動產擔保交易之債務人，意圖不法之利益，將標的物遷移，致生損害於債權人\n，處拘役伍拾日，如易科罰金，以佰元折算壹日。\n    事實及理由\n一、本件犯罪事實及證據均引用檢察官聲請簡易判決處刑書之記載（如附件）。\n二、被告甲○○將已設定動產抵押之標的物，即車牌號碼為ＺＬ—九三一九號自用小\n    客車，遷移他去，離開約定之停放地點，並交予胞兄余明福使用，致生損害於債\n    權人台新國際商業銀行股份有限公司（下稱台新公司），核其所為，係違反動產\n    擔保交易法第三十八條之動產擔保交易債務人，意圖不法利益，將標的物遷移，\n    致生損害於債權人罪。爰審酌被告未按期繳納分期款，並違反動產擔保交易契約\n    ，將上開車輛遷移，致台新公司追償無著，且事後仍未與台新公司和解，尚有新\n    台幣七十四萬四千六百十五元貸款未清償，及其犯罪手段、所得、動機等一切情\n    狀，量處如主文所示之刑，併諭知易科罰金之折算標準。\n三、依刑事訴訟法第四百四十九條第一項、第三項、第四百五十四條第二項，動產擔\n    保交易法第三十八條，刑法第十一條前段、第四十一條第一項前段，罰金罰鍰提\n    高標準條例第一條前段、第二條，判決如主文。\n四、如不服本判決，得自收受送達之日起十日內，向本院提起上訴。\n中      華      民      國    九十四    年      一      月    二十五    日\n                                  臺灣高雄地方法院高雄簡易庭\n                                        法      官  李育信\n右為正本，係照原本作成，證明與原本無異。\n如不服本判決，得自收受送達之日起十日內，向本院提起上訴。\n                                        法院書記官  洪生輝\n中      華      民      國    九十四    年      一      月    三十一    日\n附錄本判決論罪之法條：\n動擔保交易法第三十八條\n  動產擔保交易之債務人，意圖不法之利益，將標的物遷移、出賣、出質、移轉、抵\n  押或為其他處分，致生損害於債權人者，處三年以下有期徒刑、拘役或科或併科六\n  千元以下之罰金。\n",
  "structure": {
    "main": "甲○○動產擔保交易之債務人，意圖不法之利益，將標的物遷移，致生損害於債權人\n，處拘役伍拾日，如易科罰金，以佰元折算壹日。",
    "fact": "一、本件犯罪事實及證據均引用檢察官聲請簡易判決處刑書之記載（如附件）。\n二、被告甲○○將已設定動產抵押之標的物，即車牌號碼為ＺＬ—九三一九號自用小\n    客車，遷移他去，離開約定之停放地點，並交予胞兄余明福使用，致生損害於債\n    權人台新國際商業銀行股份有限公司（下稱台新公司），核其所為，係違反動產\n    擔保交易法第三十八條之動產擔保交易債務人，意圖不法利益，將標的物遷移，\n    致生損害於債權人罪。爰審酌被告未按期繳納分期款，並違反動產擔保交易契約\n    ，將上開車輛遷移，致台新公司追償無著，且事後仍未與台新公司和解，尚有新\n    台幣七十四萬四千六百十五元貸款未清償，及其犯罪手段、所得、動機等一切情\n    狀，量處如主文所示之刑，併諭知易科罰金之折算標準。\n三、依刑事訴訟法第四百四十九條第一項、第三項、第四百五十四條第二項，動產擔\n    保交易法第三十八條，刑法第十一條前段、第四十一條第一項前段，罰金罰鍰提\n    高標準條例第一條前段、第二條，判決如主文。\n四、如不服本判決，得自收受送達之日起十日內，向本院提起上訴。",
    "reason": "一、本件犯罪事實及證據均引用檢察官聲請簡易判決處刑書之記載（如附件）。\n二、被告甲○○將已設定動產抵押之標的物，即車牌號碼為ＺＬ—九三一九號自用小\n    客車，遷移他去，離開約定之停放地點，並交予胞兄余明福使用，致生損害於債\n    權人台新國際商業銀行股份有限公司（下稱台新公司），核其所為，係違反動產\n    擔保交易法第三十八條之動產擔保交易債務人，意圖不法利益，將標的物遷移，\n    致生損害於債權人罪。爰審酌被告未按期繳納分期款，並違反動產擔保交易契約\n    ，將上開車輛遷移，致台新公司追償無著，且事後仍未與台新公司和解，尚有新\n    台幣七十四萬四千六百十五元貸款未清償，及其犯罪手段、所得、動機等一切情\n    狀，量處如主文所示之刑，併諭知易科罰金之折算標準。\n三、依刑事訴訟法第四百四十九條第一項、第三項、第四百五十四條第二項，動產擔\n    保交易法第三十八條，刑法第十一條前段、第四十一條第一項前段，罰金罰鍰提\n    高標準條例第一條前段、第二條，判決如主文。\n四、如不服本判決，得自收受送達之日起十日內，向本院提起上訴。"
  },
  "search": "臺灣高雄地方法院刑事簡易判決九十四年度簡字第二四七號聲請人臺灣高雄地方法院檢察署檢察官被告甲○○男四.右列被告因違反動產擔保交易法案件，經檢察官聲請以簡易判決處刑（九十三年度偵緝字第二三一０號），本院判決如左：主文甲○○動產擔保交易之債務人，意圖不法之利益，將標的物遷移，致生損害於債權人，處拘役伍拾日，如易科罰金，以佰元折算壹日。事實及理由一、本件犯罪事實及證據均引用檢察官聲請簡易判決處刑書之記載（如附件）。二、被告甲○○將已設定動產抵押之標的物，即車牌號碼為ＺＬ—九三一九號自用小客車，遷移他去，離開約定之停放地點，並交予胞兄余明福使用，致生損害於債權人台新國際商業銀行股份有限公司（下稱台新公司），核其所為，係違反動產擔保交易法第三十八條之動產擔保交易債務人，意圖不法利益，將標的物遷移，致生損害於債權人罪。爰審酌被告未按期繳納分期款，並違反動產擔保交易契約，將上開車輛遷移，致台新公司追償無著，且事後仍未與台新公司和解，尚有新台幣七十四萬四千六百十五元貸款未清償，及其犯罪手段、所得、動機等一切情狀，量處如主文所示之刑，併諭知易科罰金之折算標準。三、依刑事訴訟法第四百四十九條第一項、第三項、第四百五十四條第二項，動產擔保交易法第三十八條，刑法第十一條前段、第四十一條第一項前段，罰金罰鍰提高標準條例第一條前段、第二條，判決如主文。四、如不服本判決，得自收受送達之日起十日內，向本院提起上訴。中華民國九十四年一月二十五日臺灣高雄地方法院高雄簡易庭法官李育信右為正本，係照原本作成，證明與原本無異。如不服本判決，得自收受送達之日起十日內，向本院提起上訴。法院書記官洪生輝中華民國九十四年一月三十一日附錄本判決論罪之法條：動擔保交易法第三十八條動產擔保交易之債務人，意圖不法之利益，將標的物遷移、出賣、出質、移轉、抵押或為其他處分，致生損害於債權人者，處三年以下有期徒刑、拘役或科或併科六千元以下之罰金。",
  "characters": {
    "judges": [
      "李育信"
    ],
    "prosecutors": [

    ],
    "lawyers": [

    ],
    "clerks": [
      "法院"
    ],
    "plaintiffs": [

    ],
    "defendants": [
      "甲○○  男  四.",
      "右列被告因違反動產擔保交易法案件，經檢察官聲請以簡易判決處刑（九十三年度偵",
      "緝字第二三一０號），本院判決如左："
    ],
    "prosecutor_office": [
      "臺灣高雄地方法院檢察署檢察官"
    ],
    "creditors": [

    ],
    "debtors": [

    ],
    "judicial_associate_officer": [

    ]
  },
  "adjudged_at": "2005-01-25",
  "created_at": "2016-02-07 02:17:11",
  "updated_at": "2016-02-07 02:17:11"
}