{
  "identify": "TPD-93-訴-4800-20050125-1",
  "court": {
    "name": "臺灣臺北地方法院",
    "code": "TPD"
  },
  "division": {
    "name": "民事",
    "code": "V"
  },
  "year": 93,
  "word": "訴",
  "number": "4800",
  "jcheck": "1",
  "reason": "清償借款等",
  "content": "臺灣臺北地方法院民事判決     93年度訴字第4800號\n原      告  內政部營建署\n法定代理人  丁○○\n訴訟代理人  丙○○\n            乙○○\n            甲○○\n            己○○\n被      告  戊○○\n上列當事人間清償借款等事件，本院於中華民國94年1月18日言\n詞辯論終結，判決如下：\n    主    文\n被告應給付原告新台幣壹佰肆拾萬仟佰拾貳元，及其中\n新台幣玖拾壹萬玖仟肆佰壹拾元，自民國九十三年六月一日起至\n清償日止，按年息百分之五計算之利息，並自民國九十三年六月\n一日起至清償日止，就逾期欠繳利息按上開利率百分之二十加付\n違約金。\n原告其餘之訴駁回。\n訴訟費用由被告負擔。\n    事    實\n甲、原告方面：\n一、聲明：被告應給付原告新台幣（下同）1,433,332元，及其\n    中919,410元，自民國93年6月1日起至清償日止，按年息百\n    分之五計算之利息，並自93年6月1日起至清償日止，就逾期\n    欠繳本息按上開利率百分之五十加付違約金。\n二、陳述：被告戊○○於民國（下同）84年3月8日向原告借款新\n    台幣（下同）1,000, 000元，約定利息按年息5.3%計算，借\n    款期限自84年3月8日起至104年3月8日止，按月攤還本息，\n    如有遲延履行時，除按上開利率計付利息外，亦應就逾期欠\n    繳本息部分按日加收上開利率百分之五十之違約金。又被告\n    如有國宅貸款契約書第8條之情事者，被告即喪失期限利益\n    ，本債務視為全部到期。詎料被告自89年11月8日起即未依\n    約繳息，屢經原告催討，均未獲清償，依上開契約第8條第5\n    款約定，被告如積欠本息達三期未清償時，即喪失期限之利\n    益，債務視為全部到期。經原告聲請台灣台南地方法院拍賣\n    其所提供之抵押物結果，僅分配至93年5月31日之利息、違\n    約金及本金，尚積欠如主文第一項所示之本金、利息及違約\n    金未清償，爰依消費借貸之法律關係，訴請被告返還消費借\n    貸款。\n三、證據：提出借據及國宅貸款契約書、放款帳卡、撥款傳票、\n    放款利率變動表、台南地方法院民事執行處強制執行金額計\n    算書分配表影本等件為證。\n乙、被告方面：\n    被告戊○○未於言詞辯論期日到場，亦未提出書狀作何聲明\n    或陳述。\n    理    由\n甲、程序方面：\n一、原告起訴時其法定代理人原為柯鄉黨，嗣於訴訟繫屬中變更\n    為丁○○，並具狀向本院聲明承受訴訟，核無不合，應予准\n    許。\n二、本件被告經合法通知，均未於言詞辯論期日到場，經原告依\n    民事訴訟法第385條聲請一造辯論判決，核無民事訴訟法第\n    386條所列各款情形，爰依原告之聲請，由其一造辯論而為\n    判決。\n乙、得心證之理由：\n一、本件原告主張之上開事實，已據其提出借據及國宅貸款契約\n    書、放款帳卡、撥款傳票、放款利率變動表、台南地方法院\n    民事執行處強制執行金額計算書分配表為證，核屬相符，自\n    堪信原告之主張為真實。\n二、惟按民法第252條規定：約定之違約金額過高者，法院得減\n    至相當之數額。查原告另請求依兩造貸款契約第四條第二款\n    約定：借款人按期攤還之金額到期未能償付時，應就逾期欠\n    繳本息部分，按日加收原貸款利率百分之五十之逾期違約金\n    部分，與一般金融機構均係按貸款利息之年利率百分之十到\n    二十計算違約金之行情相較，顯然過高，而本件係承購國民\n    較諸市場行情亦無偏低之情形，而無收取較高違約金之風險\n    考量，是本院爰依前揭規定將其酌減為就逾期欠繳利息部分\n    ，按日加收原貸款利率百分之二十之逾期違約金，始為公平\n    。從而，原告依消費借貸之法律關係，請求被告給付如主文\n    第一項所示之本金、利息及違約金為有理由，應予准許，逾\n    此範圍之請求，即失所據，應予駁回。\n三、據上論結，本件原告之訴為一部有理由、一部無理由，依民\n    事訴訟法第三百八十五條第一項前段、第七十九條，判決如\n    主文。\n中    華    民    國    94    年    1     月    25    日\n                            民事第一庭    法  官  王貞秀\n以上正本係照原本作成\n如對本判決上訴，須於判決送達後20日內向本院提出上訴狀\n中    華    民    國    94    年    1     月    25    日\n                                          書記官  劉寶鈴\n",
  "structure": {
    "main": "被告應給付原告新台幣壹佰肆拾萬仟佰拾貳元，及其中\n新台幣玖拾壹萬玖仟肆佰壹拾元，自民國九十三年六月一日起至\n清償日止，按年息百分之五計算之利息，並自民國九十三年六月\n一日起至清償日止，就逾期欠繳利息按上開利率百分之二十加付\n違約金。\n原告其餘之訴駁回。\n訴訟費用由被告負擔。",
    "fact": "甲、原告方面：\n一、聲明：被告應給付原告新台幣（下同）1,433,332元，及其\n    中919,410元，自民國93年6月1日起至清償日止，按年息百\n    分之五計算之利息，並自93年6月1日起至清償日止，就逾期\n    欠繳本息按上開利率百分之五十加付違約金。\n二、陳述：被告戊○○於民國（下同）84年3月8日向原告借款新\n    台幣（下同）1,000, 000元，約定利息按年息5.3%計算，借\n    款期限自84年3月8日起至104年3月8日止，按月攤還本息，\n    如有遲延履行時，除按上開利率計付利息外，亦應就逾期欠\n    繳本息部分按日加收上開利率百分之五十之違約金。又被告\n    如有國宅貸款契約書第8條之情事者，被告即喪失期限利益\n    ，本債務視為全部到期。詎料被告自89年11月8日起即未依\n    約繳息，屢經原告催討，均未獲清償，依上開契約第8條第5\n    款約定，被告如積欠本息達三期未清償時，即喪失期限之利\n    益，債務視為全部到期。經原告聲請台灣台南地方法院拍賣\n    其所提供之抵押物結果，僅分配至93年5月31日之利息、違\n    約金及本金，尚積欠如主文第一項所示之本金、利息及違約\n    金未清償，爰依消費借貸之法律關係，訴請被告返還消費借\n    貸款。\n三、證據：提出借據及國宅貸款契約書、放款帳卡、撥款傳票、\n    放款利率變動表、台南地方法院民事執行處強制執行金額計\n    算書分配表影本等件為證。\n乙、被告方面：\n    被告戊○○未於言詞辯論期日到場，亦未提出書狀作何聲明\n    或陳述。",
    "reason": "甲、程序方面：\n一、原告起訴時其法定代理人原為柯鄉黨，嗣於訴訟繫屬中變更\n    為丁○○，並具狀向本院聲明承受訴訟，核無不合，應予准\n    許。\n二、本件被告經合法通知，均未於言詞辯論期日到場，經原告依\n    民事訴訟法第385條聲請一造辯論判決，核無民事訴訟法第\n    386條所列各款情形，爰依原告之聲請，由其一造辯論而為\n    判決。\n乙、得心證之理由：\n一、本件原告主張之上開事實，已據其提出借據及國宅貸款契約\n    書、放款帳卡、撥款傳票、放款利率變動表、台南地方法院\n    民事執行處強制執行金額計算書分配表為證，核屬相符，自\n    堪信原告之主張為真實。\n二、惟按民法第252條規定：約定之違約金額過高者，法院得減\n    至相當之數額。查原告另請求依兩造貸款契約第四條第二款\n    約定：借款人按期攤還之金額到期未能償付時，應就逾期欠\n    繳本息部分，按日加收原貸款利率百分之五十之逾期違約金\n    部分，與一般金融機構均係按貸款利息之年利率百分之十到\n    二十計算違約金之行情相較，顯然過高，而本件係承購國民\n    較諸市場行情亦無偏低之情形，而無收取較高違約金之風險\n    考量，是本院爰依前揭規定將其酌減為就逾期欠繳利息部分\n    ，按日加收原貸款利率百分之二十之逾期違約金，始為公平\n    。從而，原告依消費借貸之法律關係，請求被告給付如主文\n    第一項所示之本金、利息及違約金為有理由，應予准許，逾\n    此範圍之請求，即失所據，應予駁回。\n三、據上論結，本件原告之訴為一部有理由、一部無理由，依民\n    事訴訟法第三百八十五條第一項前段、第七十九條，判決如\n    主文。\n中    華    民    國    94    年    1     月    25    日\n                            民事第一庭    法  官  王貞秀\n以上正本係照原本作成\n如對本判決上訴，須於判決送達後20日內向本院提出上訴狀"
  },
  "search": "臺灣臺北地方法院民事判決93年度訴字第4800號原告內政部營建署法定代理人丁○○訴訟代理人丙○○乙○○甲○○己○○被告戊○○上列當事人間清償借款等事件，本院於中華民國94年1月18日言詞辯論終結，判決如下：主文被告應給付原告新台幣壹佰肆拾萬仟佰拾貳元，及其中新台幣玖拾壹萬玖仟肆佰壹拾元，自民國九十三年六月一日起至清償日止，按年息百分之五計算之利息，並自民國九十三年六月一日起至清償日止，就逾期欠繳利息按上開利率百分之二十加付違約金。原告其餘之訴駁回。訴訟費用由被告負擔。事實甲、原告方面：一、聲明：被告應給付原告新台幣（下同）1,433,332元，及其中919,410元，自民國93年6月1日起至清償日止，按年息百分之五計算之利息，並自93年6月1日起至清償日止，就逾期欠繳本息按上開利率百分之五十加付違約金。二、陳述：被告戊○○於民國（下同）84年3月8日向原告借款新台幣（下同）1,000,000元，約定利息按年息5.3%計算，借款期限自84年3月8日起至104年3月8日止，按月攤還本息，如有遲延履行時，除按上開利率計付利息外，亦應就逾期欠繳本息部分按日加收上開利率百分之五十之違約金。又被告如有國宅貸款契約書第8條之情事者，被告即喪失期限利益，本債務視為全部到期。詎料被告自89年11月8日起即未依約繳息，屢經原告催討，均未獲清償，依上開契約第8條第5款約定，被告如積欠本息達三期未清償時，即喪失期限之利益，債務視為全部到期。經原告聲請台灣台南地方法院拍賣其所提供之抵押物結果，僅分配至93年5月31日之利息、違約金及本金，尚積欠如主文第一項所示之本金、利息及違約金未清償，爰依消費借貸之法律關係，訴請被告返還消費借貸款。三、證據：提出借據及國宅貸款契約書、放款帳卡、撥款傳票、放款利率變動表、台南地方法院民事執行處強制執行金額計算書分配表影本等件為證。乙、被告方面：被告戊○○未於言詞辯論期日到場，亦未提出書狀作何聲明或陳述。理由甲、程序方面：一、原告起訴時其法定代理人原為柯鄉黨，嗣於訴訟繫屬中變更為丁○○，並具狀向本院聲明承受訴訟，核無不合，應予准許。二、本件被告經合法通知，均未於言詞辯論期日到場，經原告依民事訴訟法第385條聲請一造辯論判決，核無民事訴訟法第386條所列各款情形，爰依原告之聲請，由其一造辯論而為判決。乙、得心證之理由：一、本件原告主張之上開事實，已據其提出借據及國宅貸款契約書、放款帳卡、撥款傳票、放款利率變動表、台南地方法院民事執行處強制執行金額計算書分配表為證，核屬相符，自堪信原告之主張為真實。二、惟按民法第252條規定：約定之違約金額過高者，法院得減至相當之數額。查原告另請求依兩造貸款契約第四條第二款約定：借款人按期攤還之金額到期未能償付時，應就逾期欠繳本息部分，按日加收原貸款利率百分之五十之逾期違約金部分，與一般金融機構均係按貸款利息之年利率百分之十到二十計算違約金之行情相較，顯然過高，而本件係承購國民較諸市場行情亦無偏低之情形，而無收取較高違約金之風險考量，是本院爰依前揭規定將其酌減為就逾期欠繳利息部分，按日加收原貸款利率百分之二十之逾期違約金，始為公平。從而，原告依消費借貸之法律關係，請求被告給付如主文第一項所示之本金、利息及違約金為有理由，應予准許，逾此範圍之請求，即失所據，應予駁回。三、據上論結，本件原告之訴為一部有理由、一部無理由，依民事訴訟法第三百八十五條第一項前段、第七十九條，判決如主文。中華民國94年1月25日民事第一庭法官王貞秀以上正本係照原本作成如對本判決上訴，須於判決送達後20日內向本院提出上訴狀中華民國94年1月25日書記官劉寶鈴",
  "characters": {
    "judges": [
      "王貞秀"
    ],
    "prosecutors": [

    ],
    "lawyers": [

    ],
    "clerks": [
      "劉寶鈴"
    ],
    "plaintiffs": [
      "內政部營建署"
    ],
    "defendants": [
      "戊○○"
    ],
    "prosecutor_office": [

    ],
    "creditors": [

    ],
    "debtors": [

    ],
    "judicial_associate_officer": [

    ]
  },
  "adjudged_at": "2005-01-25",
  "created_at": "2016-02-07 02:17:29",
  "updated_at": "2016-02-07 02:17:29"
}