{
  "identify": "PCD-99-訴-2512-20110301-2",
  "court": {
    "name": "臺灣新北地方法院",
    "code": "PCD"
  },
  "division": {
    "name": "民事",
    "code": "V"
  },
  "year": 99,
  "word": "訴",
  "number": "2512",
  "jcheck": "2",
  "reason": "租佃爭議",
  "content": "臺灣板橋地方法院民事判決              99年度訴字第2512號\n原      告  戊○○\n訴訟代理人  吳誠修律師\n            林維堯律師\n被      告  丁○\n            甲○○\n            丙○○\n上二人共同\n訴訟代理人  張世興律師\n複  代理人  許宏宇律師\n被      告  乙○○\n                        號\n上列當事人間請求租佃爭議事件，本院於中華民國100年2 月22日\n言詞辯論終結，判決如下：\n    主  文\n原告之訴駁回。\n訴訟費用由原告負擔。\n    事實及理由\n壹、程序方面：\n一、按訴狀送達後，原告不得將原訴變更或追加他訴。但有下列\n    各款情形之一者，不在此限：…二請求之基礎事實同一者。\n    …七不甚礙被告之防禦及訴訟之終結者，民事訴訟法第255\n    條第1 項第2 、7 款定有明文。查本件原告起訴，其聲明原\n    為：(一)先位部分：被告丁○、甲○○、丙○○、乙○○、己\n    ○○應將新北市○○區○○段辛○小段20-2地號土地（下稱\n    系爭土地）分割出如起訴狀附圖一A 部分所示面積699 平方\n    公尺，並將其所有權全部移轉登記與原告；(二)備位部分：1.\n    被告5 人應就系爭土地協同原告向新北市庚○區公所辦理自\n    98年1 月1 日起至103 年12月31日止之耕地三七五租約登記\n    。2.被告5 人應將系爭土地如起訴狀附圖二20-2D 部分所示\n    面積2,047 平方公尺交付原告耕作。嗣於民國100 年2 月22\n    日言詞辯論期日變更其聲明為：被告甲○○、丙○○、乙○\n    ○應將系爭土地移轉349.5 平方公尺與原告，被告丁○應將\n    系爭土地移轉349.5 平方公尺與原告；並撤回其備位聲明及\n    對己○○部分之訴。被告丁○、甲○○、丙○○與己○○對\n    於上開撤回部分均表示同意，自應准許；被告丁○、甲○○\n    、丙○○對於上開聲明變更部分雖均表示不同意，惟原告所\n    為上開訴之變更，其請求之基礎事實係屬同一，且無礙被告\n    丁○、甲○○、丙○○之防禦及本件訴訟之終結，亦應予准\n    許。\n二、被告乙○○經合法通知，未於言詞辯論期日到場，核無民事\n    訴訟法第386 條所列各款情形，爰依原告之聲請，由其一造\n    辯論而為判決。\n貳、實體方面：\n一、原告主張：\n  (一)坐落新北市○○區○○段辛○小段20地號土地（下稱辛○小\n    段20地號土地）原係李長成、李欉共有，應有部分各2 分之\n    1 ，在政府遷台實施耕地三七五減租條例後，即由李長成出\n    租予原告之被繼承人李國耕作，因李欉對該租約並無爭議且\n    亦將土地交付李國耕作而視為承認租約，李國亡故後，由原\n    告單獨繼承，並向新北市庚○區公所辦理租約登記繼續耕作\n    。嗣上開土地因政府開闢二重洪道而分割同段20地號土地、\n    20-1地號土地及系爭土地等3 筆土地，其中20地號、20 -1\n    地號土地由政府徵收，僅餘系爭土地面積2,727 平方公尺，\n    為本件耕地三七五租約之標的。\n  (二)72年5 月25日，李長成、李欉與原告訂立調解協定書，（下\n    稱系爭調解協定書），其中第2 條約定：「未被徵收土地即\n    逕為分割辛○小段20-2地號面積2,727 平方公尺之內甲方（\n    按即李長成、李欉）取得1,549 平方公尺，乙方（按即原告\n    ）取得699 平方公尺，丙方（按即第三人陳尻鬨）取得479\n    平方公尺……其位置如附圖，未被徵收土地如能分割過戶時\n    雙方同意辦理分割過戶，如不能分割過戶時，按分配位置各\n    分別取得其土地、分管其業，分納稅課，各自由管理使用，\n    如乙、丙方出賣其土地時，甲方同意無條件齊全過戶文件，\n    以利出售…，甲方確認乙、丙方應有分配額及其位置，決不\n    藉任何事由否認之。」亦即在72年5 月25日訂立系爭調解協\n    定書時，業佃雙方已分配土地，但因當時法令不能辦理分割\n    ，所以未終止耕地三七五租約，只是各按分配位置分管其業\n    ，惟已約定如能分割過戶時雙方同意辦理分割過戶，多年來\n    相安無事，並每6 年由庚○鄉公所辦理租約登記。\n  (三)李長成於93年6 月3 日過世，其就系爭土地之應有部分由被\n    告丁○取得其2 分之1 ，即應有部分4 分之1 ，訴外人李宴\n    仁、李鎮源取得應有部分共4 分之1 ，但李宴仁、李鎮源取\n    得部分遭法院強制執行拍賣，由己○○應買取得；李欉則於\n    90年7 月7 日死亡，由被告甲○○、丙○○、乙○○繼承，\n    各取得應有部分6 分之1 。又原告與李成長、李欉訂立系爭\n    調解協定書當時之農業發展條例規定農地不能細分，所以才\n    會約定如能分割過戶時雙方同意辦理分割過戶，嗣農業發展\n    條例於89年1 月26日修正，同年月28日生效，原告得依系爭\n    調解協定書之約定請求。而被告丁○之被繼承人李長成依系\n    爭調解協定書所負應移轉系爭土地699 平方公尺之2 分之1\n    即349.5 平方公尺之義務，在李長成死亡後，應由全體繼承\n    人負連帶責任，故縱訴外人李宴仁、李鎮源就系爭土地之應\n    有部分4 分之1 遭法院拍賣由己○○應買取得，己○○並稱\n    系爭調協議書為債權契約，其非契約當事人，不受系爭調解\n    協定書之拘束，但就李長成所負移轉系爭土地349.5 平方公\n    尺之義務，既由被告丁○繼承而負連帶給付義務，依民法第\n    273 條規定，原告自得請求被告丁○移轉系爭土地349.5 平\n    方公尺予原告，另系爭土地之349.5 平方公尺則由被告甲○\n    ○、丙○○、乙○○負責移轉。\n  (四)併為聲明：被告甲○○、丙○○、乙○○應將系爭土地移轉\n    349.5 平方公尺與原告，被告丁○應將系爭土地移轉349.5\n    平方公尺與原告。\n二、被告丁○則抗辯：\n  (一)兩造間曾因本件實體法律關係引發訴訟，經鈞院97年度訴字\n    第2498號（98年4 月30日判決）、台灣高等法院98年度上字\n    第699 號（98年12月8 日判決）民事判決確定，已認定兩造\n    間之租佃關係於72年5 月25日簽立系爭調解協定書時已合意\n    消滅，原告復依確定之終局判決或經裁判之訴訟標的更行起\n    訴，在法律上顯無理由。\n  (二)林國（即原告祖父）未經業主李長成、李欉同意擅將系爭耕\n    地轉租予陳尻鬨耕作，因積欠租金達2 年以上，經李長成、\n    李欉依法終止租約，60年2 月22日由新北市庚○區耕地租佃\n    委員會調解成立，佃農林阿喜（林國次子）、陳尻鬨願將系\n    爭土地交還業主收回自耕，有調解筆錄可稽，故兩造間租佃\n    關係已不存在。又縱系爭調解協定書內容有效，然亦已因原\n    告15年不行使請求權而消滅，被告可拒絕履行，故本件原告\n    之訴為無理由。\n  (三)併為答辯聲明：原告之訴駁回。\n三、被告甲○○、丙○○則抗辯：\n  (一)按債權之主體，以締結契約之當事人為準（最高法院17年上\n    字第906 號判例參照）。查系爭調解協定書之締約當事人既\n    非己○○，且與己○○無任何關係，依前開判例意旨及債權\n    相對性原則，系爭調解協定書對己○○即無任何拘束力，原\n    告請求被告與己○○分割出系爭土地並移轉登記，顯無理由\n    。\n  (二)台灣高等法院98年度上字第699 號確定判決認定：「兩造間\n    之租佃關係於72年5 月25日簽立系爭調解協定書時已合意消\n    滅」，依爭點效理論，對原告有拘束力，原告不得作相反之\n    主張。又「耕地三七五減租條例第6 條第1 項載：『本條例\n    施行後耕地租約應一律以書面為之，租約之訂立、變更、終\n    止或換訂，應由出租人會同承租人申請登記』云云，係為保\n    護佃農及謀舉證上便利而設，非謂凡租約之訂立、變更、終\n    止或換訂，須經登記，始能生效。」最高法院51年台上字第\n    2629號著有判例。因此，新北市庚○區公所之耕地租約登記\n    ，不影響原告就系爭土地租佃關係於72年5 月25日即因簽立\n    系爭調解協定書時已合意消滅之法律效力，亦即原告就系爭\n    土地無租佃關係存在。另耕地三七五減租條例第25條規定：\n    「在耕地租期屆滿前，出租人縱將其所有權讓典與第三人，\n    其租佃契約對於受讓受典人仍繼續有效，受讓受典人應會同\n    原承租人申請為租約變更之登記。」其規定係在「在耕地租\n    期屆滿前」，然己○○係於系爭土地租佃關係消滅後之98年\n    8 月20日始因法院拍賣受讓所有權，亦與上開規定要件不符\n    ，自無該條規定之適用。\n  (三)併為答辯聲明：原告之訴駁回。\n三、本件辛○小段20地號土地係李長成、李欉共有，應有部分各\n    2 分之1 ，原由李長成依耕地三七五減租條例出租予李國耕\n    作，李欉對該租約無爭議且將土地交付李國耕作視為承認租\n    約。李國亡故後，由原告單獨繼承，並向新北市庚○區公所\n    辦理租約登記繼續耕作，嗣上開土地因政府開闢二重洪道而\n    分割同段20地號土地、20-1地號土地及系爭土地等3 筆土地\n    ，其中20地號、20-1地號土地由政府徵收，僅餘系爭土地面\n    積2,727 平方公尺；72年5 月25日，李長成、李欉與原告、\n    陳尻鬨訂立爭調解協定書，約定：系爭土地由李長成、李欉\n    （甲方）取得1,549 平方公尺，原告（乙方）取得699 平方\n    公尺，人陳尻鬨（丙方）取得479 平方公尺，原告分配位置\n    如起訴狀附圖一A 部分；嗣李長成於93年6 月3 日死亡，由\n    被告丁○繼承取得系爭土地應有部分4 分之1 ，訴外人李宴\n    仁、李鎮源繼承取得系爭土地應有部分共4 分之1 ，李宴仁\n    、李鎮源取得部分經本院拍賣，由己○○買受取得，李欉則\n    於90年7 月7 日死亡，由被告甲○○、丙○○、乙○○繼承\n    ，各取得應有部分6 分之1 ；及本院97年度訴字第2498號、\n    台灣高等法院98年度上字第699 號確定判決已認定：兩造間\n    之租佃關係於72年5 月25日簽立系爭調解協定書時已合意消\n    滅等情，有耕地租約、系爭調解協定書、土地登記謄本、本\n    院民事執行處拍賣通知及本院97年度訴字第2498號、台灣高\n    等法院98年度上字第699 號民事判決等件影本在卷可稽（見\n    本院卷第108 至117 頁、第134 至156 頁），並為兩造所不\n    爭執，自堪認此部分事實為真實。\n四、原告主張被告丁○之被繼承人李長成依系爭調解協定書所負\n    應移轉系爭土地699 平方公尺之2 分之1 即349.5 平方公尺\n    之義務，在李長成死亡後，應由全體繼承人負連帶責任，其\n    得請求被告丁○移轉系爭土地349.5 平方公尺予原告，另系\n    爭土地之349.5 平方公尺由被告甲○○、丙○○、乙○○負\n    責移轉等語，則為被告丁○、甲○○、丙○○所否認，並以\n    前開情詞置辯。是本件應審究者為：(一)本件訴訟是否就已確\n    定之訴訟標的更行起訴？(二)原告依系爭調解協定書所生之請\n    求權是否已罹於時效而消滅？(三)被告丁○與被告甲○○、丙\n    ○○、乙○○是否有移轉系爭土地各349.5 平方公尺與原告\n    之義務？\n五、關於本件訴訟是否就已確定之訴訟標的更行起訴部分：\n  (一)按「除別有規定外，確定之終局判決就經裁判之訴訟標的，\n    有既判力」，民事訴訟法第400 條第1 項定有明文。又訴訟\n    標的於確定之終局判決中經裁判者，依（舊）民事訴訟法第\n    399 條第1 項規定，當事人固不得就該法律關係更行起訴，\n    惟此係指確定終局判決所裁判之訴訟標的，與更行起訴之法\n    律關係相同者而言，若更行起訴之法律關係，與確定判決所\n    裁判之訴訟標的，僅有因果關係，則二者並非相同，即無該\n    條項之適用，最高法院著有51年台上字第1041號判例可資參\n    照。\n  (二)經查，本院97年度訴字第2498號及台灣高等法院98年度上字\n    第699 號租佃爭議事件，係本件被告丁○以本件原告自72年\n    5 月25日起迄今數十年未繳納租金，經其催告後已終止系爭\n    租賃契約為由，請求原告應將系爭土地上之木屋拆除，並將\n    土地返還予上訴人及其他共有人全體，經法院審理結果，認\n    兩造間之租佃關係於72年5 月25日簽立系爭調解協定書時已\n    合意消滅，判決被告丁○敗訴確定，而本件訴訟則係原告本\n    於系爭調解協定書之約定請求被告移轉系爭土地內之699 平\n    方公尺，二者訴訟標的並不相同，自無本件訴訟標的為確定\n    判決之效力所及之情事。被告丁○抗辯：本件實體法律關係\n    已於前開判決確定，原告復依確定之終局判決或經裁判之訴\n    訟標的更行起訴，在法律上顯無理由云云，並非可採。\n六、關於原告依系爭調解協定書所生之請求權是否已罹於時效而\n    消滅部分：\n  (一)按「請求權，因15年間不行使而消滅」；「消滅時效，自請\n    求權可行使時起算」，民法第為125 條前段、第128 條前段\n    分別定有明文。次按89年1 月26日修正前之農業發展條例第\n    30條前段規定：「每宗耕地不得分割及移轉為共有」，同日\n    修正後之同條例第16條規定：「每宗耕地分割後每人所有面\n    積未達○‧二五公頃者，不得分割。但有下列情形之一者，\n    不在此限︰…五耕地三七五租約，租佃雙方協議以分割方式\n    終止租約者，得分割為租佃雙方單獨所有。」\n  (二)查系爭調解協定書於72年5 月25日簽立時，因農業發展條例\n    有上開第30條之明文，原告尚不能行使其依系爭調解協定書\n    所約定之分割移轉系爭土地請求權，嗣農業發展條例於89年\n    1 月26日修正、同月28日生效後，已有上開第16條之增訂，\n    原告之分割移轉請求權自斯時起始能行使，迄至其於99年10\n    月25日向本院提出民事準備一狀時止（見本院卷第96頁），\n    尚未滿15年，其本件請求權尚未罹於時效。是被告丁○另抗\n    辯：系爭調解協定書內容縱屬有效，已因原告15年不行使請\n    求權而消滅，其得拒絕履行云云，亦非可採。\n七、關於被告丁○與被告甲○○、丙○○、乙○○是否有移轉系\n    爭土地各349.5 平方公尺與原告之義務部分：\n  (一)按債權契約為特定人間之權利義務關係，僅債權人得向債務\n    人請求給付，不得以之對抗契約以外之第三人，此為債之相\n    對性原則（最高法院96年度台上字第1809號判決意旨參照）\n    。本件系爭調解協定書係李長成、李欉與原告、陳尻鬨所訂\n    立，屬其等間債之契約關係，於李長成、李欉先後死亡後，\n    其等之繼承人即被告等人固應民法第1148條第1 項前段：「\n    繼承人自繼承開始時，除本法另有規定外，承受被繼承人財\n    產上之一切權利、義務。」之規定，分別繼承上開調解協定\n    書所負之義務，惟訴外人李宴仁、李鎮源自李長成所繼承系\n    爭土地應有部分4 分之1 部分既已經由本院拍賣而由己○○\n    應買取得，而己○○非契約之當事人，並不受系爭調協議書\n    約定之拘束，此亦為原告所不爭執，故原告不得依系爭調解\n    協定書之約定條款請求己○○履行債務，應無疑義。\n  (二)次按因可歸責於債務人之事由致給付不能者，債權雖仍存在\n    ，但其內容已變為損害賠償請求權，不復以原定之給付為標\n    的，此觀民法第226 條第1 項之規定自明（最高法院84年度\n    台上字第469 號判決意旨參照）。查系爭調解協定書第2 條\n    約定：「未被徵收土地即逕為分割辛○小段20-2地號面積27\n    27平方公尺之內甲方（即李長成、李欉）取得1,549 平方公\n    尺，乙方（即原告）取得699 平方公尺，丙方（即陳尻鬨）\n    取得479 平方公尺，其位置如附圖，未被徵收土地如能分割\n    過戶時雙方同意辦理分割過戶，如不能分割過戶時，按分配\n    位置各分別取得其土地、分管其業，分納稅課，各自由管理\n    使用，如乙、丙方出賣其土地時，甲方同意無條件齊全過戶\n    文件，以利出售，其出售所需費用以及增值稅由乙、丙方自\n    行負，甲方確認乙、丙方應有分配額及其位置，決不藉任何\n    事由否認之，而甲方自不得將乙、丙方分配取得之土地出賣\n    、設押或其他對于乙方有不利之行為，如有是事，願負法律\n    上完全責任。」等語，可見李長成、李欉與原告、陳尻鬨間\n    已協議就系爭土地劃分為3 部分，由原告終局取得如起訴狀\n    附圖一A 所示699 平方公尺之特定部分，是原告對被告之債\n    權應為該特定部分之分割移轉請求權，至為灼然。次查，系\n    爭土地應有部分之4 分之1 既已由不受系爭調解協定書拘束\n    之己○○所取得，原告不得依系爭調解協定書之約定請求己\n    ○○分割移轉上開特定部分之土地，且因系爭土地之分割於\n    原告與己○○等共有人間必須共同為之，無法由被告自行分\n    割，而將如起訴狀附圖一A 所示699 平方公尺之特定部分移\n    轉與原告，可知被告之分割移轉義務已陷於給付不能之狀況\n    ，原告自亦不得請求被告就該特定部分為分割，並為所有權\n    移轉登記甚明，倘原告認此種情形係有可歸責於債務人即被\n    告之事由，亦僅能依民法第226 條第1 項規定，請求被告負\n    損害賠償責任，要不能變更請求被告應移轉其等就系爭土地\n    應有部分之其他相同面積土地，原告為此變更請求，於法顯\n    然無據，並不足採。\n五、綜上所述，原告依系爭調解協定書之約定，請求被告甲○○\n    、丙○○、乙○○應將系爭土地移轉349.5 平方公尺與原告\n    及被告丁○應將系爭土地移轉349.5 平方公尺與原告，為無\n    理由，應予駁回。\n六、本件事證已臻明確，兩造其餘主張、陳述及所提證據，經本\n    院審酌後，認均與本件判斷結果無影響，毋庸再予一一審酌\n    ，附此敘明。\n據上論結，本件原告之訴為無理由，依民事訴訟法民事訴訟法第\n385 條第1項前段、第78條，判決如主文。\n中    華    民    國    100   年    3     月    1     日\n                  民事第一庭    法  官  高文淵\n上列正本係照原本作成\n如對本判決上訴，須於判決送達後20日內向本院提出上訴狀\n中    華    民    國    100   年    3     月    1     日\n                                書記官  黃瀅螢\n",
  "structure": {
    "main": "原告之訴駁回。\n訴訟費用由原告負擔。",
    "fact": "壹、程序方面：\n一、按訴狀送達後，原告不得將原訴變更或追加他訴。但有下列\n    各款情形之一者，不在此限：…二請求之基礎事實同一者。\n    …七不甚礙被告之防禦及訴訟之終結者，民事訴訟法第255\n    條第1 項第2 、7 款定有明文。查本件原告起訴，其聲明原\n    為：(一)先位部分：被告丁○、甲○○、丙○○、乙○○、己\n    ○○應將新北市○○區○○段辛○小段20-2地號土地（下稱\n    系爭土地）分割出如起訴狀附圖一A 部分所示面積699 平方\n    公尺，並將其所有權全部移轉登記與原告；(二)備位部分：1.\n    被告5 人應就系爭土地協同原告向新北市庚○區公所辦理自\n    98年1 月1 日起至103 年12月31日止之耕地三七五租約登記\n    。2.被告5 人應將系爭土地如起訴狀附圖二20-2D 部分所示\n    面積2,047 平方公尺交付原告耕作。嗣於民國100 年2 月22\n    日言詞辯論期日變更其聲明為：被告甲○○、丙○○、乙○\n    ○應將系爭土地移轉349.5 平方公尺與原告，被告丁○應將\n    系爭土地移轉349.5 平方公尺與原告；並撤回其備位聲明及\n    對己○○部分之訴。被告丁○、甲○○、丙○○與己○○對\n    於上開撤回部分均表示同意，自應准許；被告丁○、甲○○\n    、丙○○對於上開聲明變更部分雖均表示不同意，惟原告所\n    為上開訴之變更，其請求之基礎事實係屬同一，且無礙被告\n    丁○、甲○○、丙○○之防禦及本件訴訟之終結，亦應予准\n    許。\n二、被告乙○○經合法通知，未於言詞辯論期日到場，核無民事\n    訴訟法第386 條所列各款情形，爰依原告之聲請，由其一造\n    辯論而為判決。\n貳、實體方面：\n一、原告主張：\n  (一)坐落新北市○○區○○段辛○小段20地號土地（下稱辛○小\n    段20地號土地）原係李長成、李欉共有，應有部分各2 分之\n    1 ，在政府遷台實施耕地三七五減租條例後，即由李長成出\n    租予原告之被繼承人李國耕作，因李欉對該租約並無爭議且\n    亦將土地交付李國耕作而視為承認租約，李國亡故後，由原\n    告單獨繼承，並向新北市庚○區公所辦理租約登記繼續耕作\n    。嗣上開土地因政府開闢二重洪道而分割同段20地號土地、\n    20-1地號土地及系爭土地等3 筆土地，其中20地號、20 -1\n    地號土地由政府徵收，僅餘系爭土地面積2,727 平方公尺，\n    為本件耕地三七五租約之標的。\n  (二)72年5 月25日，李長成、李欉與原告訂立調解協定書，（下\n    稱系爭調解協定書），其中第2 條約定：「未被徵收土地即\n    逕為分割辛○小段20-2地號面積2,727 平方公尺之內甲方（\n    按即李長成、李欉）取得1,549 平方公尺，乙方（按即原告\n    ）取得699 平方公尺，丙方（按即第三人陳尻鬨）取得479\n    平方公尺……其位置如附圖，未被徵收土地如能分割過戶時\n    雙方同意辦理分割過戶，如不能分割過戶時，按分配位置各\n    分別取得其土地、分管其業，分納稅課，各自由管理使用，\n    如乙、丙方出賣其土地時，甲方同意無條件齊全過戶文件，\n    以利出售…，甲方確認乙、丙方應有分配額及其位置，決不\n    藉任何事由否認之。」亦即在72年5 月25日訂立系爭調解協\n    定書時，業佃雙方已分配土地，但因當時法令不能辦理分割\n    ，所以未終止耕地三七五租約，只是各按分配位置分管其業\n    ，惟已約定如能分割過戶時雙方同意辦理分割過戶，多年來\n    相安無事，並每6 年由庚○鄉公所辦理租約登記。\n  (三)李長成於93年6 月3 日過世，其就系爭土地之應有部分由被\n    告丁○取得其2 分之1 ，即應有部分4 分之1 ，訴外人李宴\n    仁、李鎮源取得應有部分共4 分之1 ，但李宴仁、李鎮源取\n    得部分遭法院強制執行拍賣，由己○○應買取得；李欉則於\n    90年7 月7 日死亡，由被告甲○○、丙○○、乙○○繼承，\n    各取得應有部分6 分之1 。又原告與李成長、李欉訂立系爭\n    調解協定書當時之農業發展條例規定農地不能細分，所以才\n    會約定如能分割過戶時雙方同意辦理分割過戶，嗣農業發展\n    條例於89年1 月26日修正，同年月28日生效，原告得依系爭\n    調解協定書之約定請求。而被告丁○之被繼承人李長成依系\n    爭調解協定書所負應移轉系爭土地699 平方公尺之2 分之1\n    即349.5 平方公尺之義務，在李長成死亡後，應由全體繼承\n    人負連帶責任，故縱訴外人李宴仁、李鎮源就系爭土地之應\n    有部分4 分之1 遭法院拍賣由己○○應買取得，己○○並稱\n    系爭調協議書為債權契約，其非契約當事人，不受系爭調解\n    協定書之拘束，但就李長成所負移轉系爭土地349.5 平方公\n    尺之義務，既由被告丁○繼承而負連帶給付義務，依民法第\n    273 條規定，原告自得請求被告丁○移轉系爭土地349.5 平\n    方公尺予原告，另系爭土地之349.5 平方公尺則由被告甲○\n    ○、丙○○、乙○○負責移轉。\n  (四)併為聲明：被告甲○○、丙○○、乙○○應將系爭土地移轉\n    349.5 平方公尺與原告，被告丁○應將系爭土地移轉349.5\n    平方公尺與原告。\n二、被告丁○則抗辯：\n  (一)兩造間曾因本件實體法律關係引發訴訟，經鈞院97年度訴字\n    第2498號（98年4 月30日判決）、台灣高等法院98年度上字\n    第699 號（98年12月8 日判決）民事判決確定，已認定兩造\n    間之租佃關係於72年5 月25日簽立系爭調解協定書時已合意\n    消滅，原告復依確定之終局判決或經裁判之訴訟標的更行起\n    訴，在法律上顯無理由。\n  (二)林國（即原告祖父）未經業主李長成、李欉同意擅將系爭耕\n    地轉租予陳尻鬨耕作，因積欠租金達2 年以上，經李長成、\n    李欉依法終止租約，60年2 月22日由新北市庚○區耕地租佃\n    委員會調解成立，佃農林阿喜（林國次子）、陳尻鬨願將系\n    爭土地交還業主收回自耕，有調解筆錄可稽，故兩造間租佃\n    關係已不存在。又縱系爭調解協定書內容有效，然亦已因原\n    告15年不行使請求權而消滅，被告可拒絕履行，故本件原告\n    之訴為無理由。\n  (三)併為答辯聲明：原告之訴駁回。\n三、被告甲○○、丙○○則抗辯：\n  (一)按債權之主體，以締結契約之當事人為準（最高法院17年上\n    字第906 號判例參照）。查系爭調解協定書之締約當事人既\n    非己○○，且與己○○無任何關係，依前開判例意旨及債權\n    相對性原則，系爭調解協定書對己○○即無任何拘束力，原\n    告請求被告與己○○分割出系爭土地並移轉登記，顯無理由\n    。\n  (二)台灣高等法院98年度上字第699 號確定判決認定：「兩造間\n    之租佃關係於72年5 月25日簽立系爭調解協定書時已合意消\n    滅」，依爭點效理論，對原告有拘束力，原告不得作相反之\n    主張。又「耕地三七五減租條例第6 條第1 項載：『本條例\n    施行後耕地租約應一律以書面為之，租約之訂立、變更、終\n    止或換訂，應由出租人會同承租人申請登記』云云，係為保\n    護佃農及謀舉證上便利而設，非謂凡租約之訂立、變更、終\n    止或換訂，須經登記，始能生效。」最高法院51年台上字第\n    2629號著有判例。因此，新北市庚○區公所之耕地租約登記\n    ，不影響原告就系爭土地租佃關係於72年5 月25日即因簽立\n    系爭調解協定書時已合意消滅之法律效力，亦即原告就系爭\n    土地無租佃關係存在。另耕地三七五減租條例第25條規定：\n    「在耕地租期屆滿前，出租人縱將其所有權讓典與第三人，\n    其租佃契約對於受讓受典人仍繼續有效，受讓受典人應會同\n    原承租人申請為租約變更之登記。」其規定係在「在耕地租\n    期屆滿前」，然己○○係於系爭土地租佃關係消滅後之98年\n    8 月20日始因法院拍賣受讓所有權，亦與上開規定要件不符\n    ，自無該條規定之適用。\n  (三)併為答辯聲明：原告之訴駁回。\n三、本件辛○小段20地號土地係李長成、李欉共有，應有部分各\n    2 分之1 ，原由李長成依耕地三七五減租條例出租予李國耕\n    作，李欉對該租約無爭議且將土地交付李國耕作視為承認租\n    約。李國亡故後，由原告單獨繼承，並向新北市庚○區公所\n    辦理租約登記繼續耕作，嗣上開土地因政府開闢二重洪道而\n    分割同段20地號土地、20-1地號土地及系爭土地等3 筆土地\n    ，其中20地號、20-1地號土地由政府徵收，僅餘系爭土地面\n    積2,727 平方公尺；72年5 月25日，李長成、李欉與原告、\n    陳尻鬨訂立爭調解協定書，約定：系爭土地由李長成、李欉\n    （甲方）取得1,549 平方公尺，原告（乙方）取得699 平方\n    公尺，人陳尻鬨（丙方）取得479 平方公尺，原告分配位置\n    如起訴狀附圖一A 部分；嗣李長成於93年6 月3 日死亡，由\n    被告丁○繼承取得系爭土地應有部分4 分之1 ，訴外人李宴\n    仁、李鎮源繼承取得系爭土地應有部分共4 分之1 ，李宴仁\n    、李鎮源取得部分經本院拍賣，由己○○買受取得，李欉則\n    於90年7 月7 日死亡，由被告甲○○、丙○○、乙○○繼承\n    ，各取得應有部分6 分之1 ；及本院97年度訴字第2498號、\n    台灣高等法院98年度上字第699 號確定判決已認定：兩造間\n    之租佃關係於72年5 月25日簽立系爭調解協定書時已合意消\n    滅等情，有耕地租約、系爭調解協定書、土地登記謄本、本\n    院民事執行處拍賣通知及本院97年度訴字第2498號、台灣高\n    等法院98年度上字第699 號民事判決等件影本在卷可稽（見\n    本院卷第108 至117 頁、第134 至156 頁），並為兩造所不\n    爭執，自堪認此部分事實為真實。\n四、原告主張被告丁○之被繼承人李長成依系爭調解協定書所負\n    應移轉系爭土地699 平方公尺之2 分之1 即349.5 平方公尺\n    之義務，在李長成死亡後，應由全體繼承人負連帶責任，其\n    得請求被告丁○移轉系爭土地349.5 平方公尺予原告，另系\n    爭土地之349.5 平方公尺由被告甲○○、丙○○、乙○○負\n    責移轉等語，則為被告丁○、甲○○、丙○○所否認，並以\n    前開情詞置辯。是本件應審究者為：(一)本件訴訟是否就已確\n    定之訴訟標的更行起訴？(二)原告依系爭調解協定書所生之請\n    求權是否已罹於時效而消滅？(三)被告丁○與被告甲○○、丙\n    ○○、乙○○是否有移轉系爭土地各349.5 平方公尺與原告\n    之義務？\n五、關於本件訴訟是否就已確定之訴訟標的更行起訴部分：\n  (一)按「除別有規定外，確定之終局判決就經裁判之訴訟標的，\n    有既判力」，民事訴訟法第400 條第1 項定有明文。又訴訟\n    標的於確定之終局判決中經裁判者，依（舊）民事訴訟法第\n    399 條第1 項規定，當事人固不得就該法律關係更行起訴，\n    惟此係指確定終局判決所裁判之訴訟標的，與更行起訴之法\n    律關係相同者而言，若更行起訴之法律關係，與確定判決所\n    裁判之訴訟標的，僅有因果關係，則二者並非相同，即無該\n    條項之適用，最高法院著有51年台上字第1041號判例可資參\n    照。\n  (二)經查，本院97年度訴字第2498號及台灣高等法院98年度上字\n    第699 號租佃爭議事件，係本件被告丁○以本件原告自72年\n    5 月25日起迄今數十年未繳納租金，經其催告後已終止系爭\n    租賃契約為由，請求原告應將系爭土地上之木屋拆除，並將\n    土地返還予上訴人及其他共有人全體，經法院審理結果，認\n    兩造間之租佃關係於72年5 月25日簽立系爭調解協定書時已\n    合意消滅，判決被告丁○敗訴確定，而本件訴訟則係原告本\n    於系爭調解協定書之約定請求被告移轉系爭土地內之699 平\n    方公尺，二者訴訟標的並不相同，自無本件訴訟標的為確定\n    判決之效力所及之情事。被告丁○抗辯：本件實體法律關係\n    已於前開判決確定，原告復依確定之終局判決或經裁判之訴\n    訟標的更行起訴，在法律上顯無理由云云，並非可採。\n六、關於原告依系爭調解協定書所生之請求權是否已罹於時效而\n    消滅部分：\n  (一)按「請求權，因15年間不行使而消滅」；「消滅時效，自請\n    求權可行使時起算」，民法第為125 條前段、第128 條前段\n    分別定有明文。次按89年1 月26日修正前之農業發展條例第\n    30條前段規定：「每宗耕地不得分割及移轉為共有」，同日\n    修正後之同條例第16條規定：「每宗耕地分割後每人所有面\n    積未達○‧二五公頃者，不得分割。但有下列情形之一者，\n    不在此限︰…五耕地三七五租約，租佃雙方協議以分割方式\n    終止租約者，得分割為租佃雙方單獨所有。」\n  (二)查系爭調解協定書於72年5 月25日簽立時，因農業發展條例\n    有上開第30條之明文，原告尚不能行使其依系爭調解協定書\n    所約定之分割移轉系爭土地請求權，嗣農業發展條例於89年\n    1 月26日修正、同月28日生效後，已有上開第16條之增訂，\n    原告之分割移轉請求權自斯時起始能行使，迄至其於99年10\n    月25日向本院提出民事準備一狀時止（見本院卷第96頁），\n    尚未滿15年，其本件請求權尚未罹於時效。是被告丁○另抗\n    辯：系爭調解協定書內容縱屬有效，已因原告15年不行使請\n    求權而消滅，其得拒絕履行云云，亦非可採。\n七、關於被告丁○與被告甲○○、丙○○、乙○○是否有移轉系\n    爭土地各349.5 平方公尺與原告之義務部分：\n  (一)按債權契約為特定人間之權利義務關係，僅債權人得向債務\n    人請求給付，不得以之對抗契約以外之第三人，此為債之相\n    對性原則（最高法院96年度台上字第1809號判決意旨參照）\n    。本件系爭調解協定書係李長成、李欉與原告、陳尻鬨所訂\n    立，屬其等間債之契約關係，於李長成、李欉先後死亡後，\n    其等之繼承人即被告等人固應民法第1148條第1 項前段：「\n    繼承人自繼承開始時，除本法另有規定外，承受被繼承人財\n    產上之一切權利、義務。」之規定，分別繼承上開調解協定\n    書所負之義務，惟訴外人李宴仁、李鎮源自李長成所繼承系\n    爭土地應有部分4 分之1 部分既已經由本院拍賣而由己○○\n    應買取得，而己○○非契約之當事人，並不受系爭調協議書\n    約定之拘束，此亦為原告所不爭執，故原告不得依系爭調解\n    協定書之約定條款請求己○○履行債務，應無疑義。\n  (二)次按因可歸責於債務人之事由致給付不能者，債權雖仍存在\n    ，但其內容已變為損害賠償請求權，不復以原定之給付為標\n    的，此觀民法第226 條第1 項之規定自明（最高法院84年度\n    台上字第469 號判決意旨參照）。查系爭調解協定書第2 條\n    約定：「未被徵收土地即逕為分割辛○小段20-2地號面積27\n    27平方公尺之內甲方（即李長成、李欉）取得1,549 平方公\n    尺，乙方（即原告）取得699 平方公尺，丙方（即陳尻鬨）\n    取得479 平方公尺，其位置如附圖，未被徵收土地如能分割\n    過戶時雙方同意辦理分割過戶，如不能分割過戶時，按分配\n    位置各分別取得其土地、分管其業，分納稅課，各自由管理\n    使用，如乙、丙方出賣其土地時，甲方同意無條件齊全過戶\n    文件，以利出售，其出售所需費用以及增值稅由乙、丙方自\n    行負，甲方確認乙、丙方應有分配額及其位置，決不藉任何\n    事由否認之，而甲方自不得將乙、丙方分配取得之土地出賣\n    、設押或其他對于乙方有不利之行為，如有是事，願負法律\n    上完全責任。」等語，可見李長成、李欉與原告、陳尻鬨間\n    已協議就系爭土地劃分為3 部分，由原告終局取得如起訴狀\n    附圖一A 所示699 平方公尺之特定部分，是原告對被告之債\n    權應為該特定部分之分割移轉請求權，至為灼然。次查，系\n    爭土地應有部分之4 分之1 既已由不受系爭調解協定書拘束\n    之己○○所取得，原告不得依系爭調解協定書之約定請求己\n    ○○分割移轉上開特定部分之土地，且因系爭土地之分割於\n    原告與己○○等共有人間必須共同為之，無法由被告自行分\n    割，而將如起訴狀附圖一A 所示699 平方公尺之特定部分移\n    轉與原告，可知被告之分割移轉義務已陷於給付不能之狀況\n    ，原告自亦不得請求被告就該特定部分為分割，並為所有權\n    移轉登記甚明，倘原告認此種情形係有可歸責於債務人即被\n    告之事由，亦僅能依民法第226 條第1 項規定，請求被告負\n    損害賠償責任，要不能變更請求被告應移轉其等就系爭土地\n    應有部分之其他相同面積土地，原告為此變更請求，於法顯\n    然無據，並不足採。\n五、綜上所述，原告依系爭調解協定書之約定，請求被告甲○○\n    、丙○○、乙○○應將系爭土地移轉349.5 平方公尺與原告\n    及被告丁○應將系爭土地移轉349.5 平方公尺與原告，為無\n    理由，應予駁回。\n六、本件事證已臻明確，兩造其餘主張、陳述及所提證據，經本\n    院審酌後，認均與本件判斷結果無影響，毋庸再予一一審酌\n    ，附此敘明。\n據上論結，本件原告之訴為無理由，依民事訴訟法民事訴訟法第\n385 條第1項前段、第78條，判決如主文。",
    "reason": "壹、程序方面：\n一、按訴狀送達後，原告不得將原訴變更或追加他訴。但有下列\n    各款情形之一者，不在此限：…二請求之基礎事實同一者。\n    …七不甚礙被告之防禦及訴訟之終結者，民事訴訟法第255\n    條第1 項第2 、7 款定有明文。查本件原告起訴，其聲明原\n    為：(一)先位部分：被告丁○、甲○○、丙○○、乙○○、己\n    ○○應將新北市○○區○○段辛○小段20-2地號土地（下稱\n    系爭土地）分割出如起訴狀附圖一A 部分所示面積699 平方\n    公尺，並將其所有權全部移轉登記與原告；(二)備位部分：1.\n    被告5 人應就系爭土地協同原告向新北市庚○區公所辦理自\n    98年1 月1 日起至103 年12月31日止之耕地三七五租約登記\n    。2.被告5 人應將系爭土地如起訴狀附圖二20-2D 部分所示\n    面積2,047 平方公尺交付原告耕作。嗣於民國100 年2 月22\n    日言詞辯論期日變更其聲明為：被告甲○○、丙○○、乙○\n    ○應將系爭土地移轉349.5 平方公尺與原告，被告丁○應將\n    系爭土地移轉349.5 平方公尺與原告；並撤回其備位聲明及\n    對己○○部分之訴。被告丁○、甲○○、丙○○與己○○對\n    於上開撤回部分均表示同意，自應准許；被告丁○、甲○○\n    、丙○○對於上開聲明變更部分雖均表示不同意，惟原告所\n    為上開訴之變更，其請求之基礎事實係屬同一，且無礙被告\n    丁○、甲○○、丙○○之防禦及本件訴訟之終結，亦應予准\n    許。\n二、被告乙○○經合法通知，未於言詞辯論期日到場，核無民事\n    訴訟法第386 條所列各款情形，爰依原告之聲請，由其一造\n    辯論而為判決。\n貳、實體方面：\n一、原告主張：\n  (一)坐落新北市○○區○○段辛○小段20地號土地（下稱辛○小\n    段20地號土地）原係李長成、李欉共有，應有部分各2 分之\n    1 ，在政府遷台實施耕地三七五減租條例後，即由李長成出\n    租予原告之被繼承人李國耕作，因李欉對該租約並無爭議且\n    亦將土地交付李國耕作而視為承認租約，李國亡故後，由原\n    告單獨繼承，並向新北市庚○區公所辦理租約登記繼續耕作\n    。嗣上開土地因政府開闢二重洪道而分割同段20地號土地、\n    20-1地號土地及系爭土地等3 筆土地，其中20地號、20 -1\n    地號土地由政府徵收，僅餘系爭土地面積2,727 平方公尺，\n    為本件耕地三七五租約之標的。\n  (二)72年5 月25日，李長成、李欉與原告訂立調解協定書，（下\n    稱系爭調解協定書），其中第2 條約定：「未被徵收土地即\n    逕為分割辛○小段20-2地號面積2,727 平方公尺之內甲方（\n    按即李長成、李欉）取得1,549 平方公尺，乙方（按即原告\n    ）取得699 平方公尺，丙方（按即第三人陳尻鬨）取得479\n    平方公尺……其位置如附圖，未被徵收土地如能分割過戶時\n    雙方同意辦理分割過戶，如不能分割過戶時，按分配位置各\n    分別取得其土地、分管其業，分納稅課，各自由管理使用，\n    如乙、丙方出賣其土地時，甲方同意無條件齊全過戶文件，\n    以利出售…，甲方確認乙、丙方應有分配額及其位置，決不\n    藉任何事由否認之。」亦即在72年5 月25日訂立系爭調解協\n    定書時，業佃雙方已分配土地，但因當時法令不能辦理分割\n    ，所以未終止耕地三七五租約，只是各按分配位置分管其業\n    ，惟已約定如能分割過戶時雙方同意辦理分割過戶，多年來\n    相安無事，並每6 年由庚○鄉公所辦理租約登記。\n  (三)李長成於93年6 月3 日過世，其就系爭土地之應有部分由被\n    告丁○取得其2 分之1 ，即應有部分4 分之1 ，訴外人李宴\n    仁、李鎮源取得應有部分共4 分之1 ，但李宴仁、李鎮源取\n    得部分遭法院強制執行拍賣，由己○○應買取得；李欉則於\n    90年7 月7 日死亡，由被告甲○○、丙○○、乙○○繼承，\n    各取得應有部分6 分之1 。又原告與李成長、李欉訂立系爭\n    調解協定書當時之農業發展條例規定農地不能細分，所以才\n    會約定如能分割過戶時雙方同意辦理分割過戶，嗣農業發展\n    條例於89年1 月26日修正，同年月28日生效，原告得依系爭\n    調解協定書之約定請求。而被告丁○之被繼承人李長成依系\n    爭調解協定書所負應移轉系爭土地699 平方公尺之2 分之1\n    即349.5 平方公尺之義務，在李長成死亡後，應由全體繼承\n    人負連帶責任，故縱訴外人李宴仁、李鎮源就系爭土地之應\n    有部分4 分之1 遭法院拍賣由己○○應買取得，己○○並稱\n    系爭調協議書為債權契約，其非契約當事人，不受系爭調解\n    協定書之拘束，但就李長成所負移轉系爭土地349.5 平方公\n    尺之義務，既由被告丁○繼承而負連帶給付義務，依民法第\n    273 條規定，原告自得請求被告丁○移轉系爭土地349.5 平\n    方公尺予原告，另系爭土地之349.5 平方公尺則由被告甲○\n    ○、丙○○、乙○○負責移轉。\n  (四)併為聲明：被告甲○○、丙○○、乙○○應將系爭土地移轉\n    349.5 平方公尺與原告，被告丁○應將系爭土地移轉349.5\n    平方公尺與原告。\n二、被告丁○則抗辯：\n  (一)兩造間曾因本件實體法律關係引發訴訟，經鈞院97年度訴字\n    第2498號（98年4 月30日判決）、台灣高等法院98年度上字\n    第699 號（98年12月8 日判決）民事判決確定，已認定兩造\n    間之租佃關係於72年5 月25日簽立系爭調解協定書時已合意\n    消滅，原告復依確定之終局判決或經裁判之訴訟標的更行起\n    訴，在法律上顯無理由。\n  (二)林國（即原告祖父）未經業主李長成、李欉同意擅將系爭耕\n    地轉租予陳尻鬨耕作，因積欠租金達2 年以上，經李長成、\n    李欉依法終止租約，60年2 月22日由新北市庚○區耕地租佃\n    委員會調解成立，佃農林阿喜（林國次子）、陳尻鬨願將系\n    爭土地交還業主收回自耕，有調解筆錄可稽，故兩造間租佃\n    關係已不存在。又縱系爭調解協定書內容有效，然亦已因原\n    告15年不行使請求權而消滅，被告可拒絕履行，故本件原告\n    之訴為無理由。\n  (三)併為答辯聲明：原告之訴駁回。\n三、被告甲○○、丙○○則抗辯：\n  (一)按債權之主體，以締結契約之當事人為準（最高法院17年上\n    字第906 號判例參照）。查系爭調解協定書之締約當事人既\n    非己○○，且與己○○無任何關係，依前開判例意旨及債權\n    相對性原則，系爭調解協定書對己○○即無任何拘束力，原\n    告請求被告與己○○分割出系爭土地並移轉登記，顯無理由\n    。\n  (二)台灣高等法院98年度上字第699 號確定判決認定：「兩造間\n    之租佃關係於72年5 月25日簽立系爭調解協定書時已合意消\n    滅」，依爭點效理論，對原告有拘束力，原告不得作相反之\n    主張。又「耕地三七五減租條例第6 條第1 項載：『本條例\n    施行後耕地租約應一律以書面為之，租約之訂立、變更、終\n    止或換訂，應由出租人會同承租人申請登記』云云，係為保\n    護佃農及謀舉證上便利而設，非謂凡租約之訂立、變更、終\n    止或換訂，須經登記，始能生效。」最高法院51年台上字第\n    2629號著有判例。因此，新北市庚○區公所之耕地租約登記\n    ，不影響原告就系爭土地租佃關係於72年5 月25日即因簽立\n    系爭調解協定書時已合意消滅之法律效力，亦即原告就系爭\n    土地無租佃關係存在。另耕地三七五減租條例第25條規定：\n    「在耕地租期屆滿前，出租人縱將其所有權讓典與第三人，\n    其租佃契約對於受讓受典人仍繼續有效，受讓受典人應會同\n    原承租人申請為租約變更之登記。」其規定係在「在耕地租\n    期屆滿前」，然己○○係於系爭土地租佃關係消滅後之98年\n    8 月20日始因法院拍賣受讓所有權，亦與上開規定要件不符\n    ，自無該條規定之適用。\n  (三)併為答辯聲明：原告之訴駁回。\n三、本件辛○小段20地號土地係李長成、李欉共有，應有部分各\n    2 分之1 ，原由李長成依耕地三七五減租條例出租予李國耕\n    作，李欉對該租約無爭議且將土地交付李國耕作視為承認租\n    約。李國亡故後，由原告單獨繼承，並向新北市庚○區公所\n    辦理租約登記繼續耕作，嗣上開土地因政府開闢二重洪道而\n    分割同段20地號土地、20-1地號土地及系爭土地等3 筆土地\n    ，其中20地號、20-1地號土地由政府徵收，僅餘系爭土地面\n    積2,727 平方公尺；72年5 月25日，李長成、李欉與原告、\n    陳尻鬨訂立爭調解協定書，約定：系爭土地由李長成、李欉\n    （甲方）取得1,549 平方公尺，原告（乙方）取得699 平方\n    公尺，人陳尻鬨（丙方）取得479 平方公尺，原告分配位置\n    如起訴狀附圖一A 部分；嗣李長成於93年6 月3 日死亡，由\n    被告丁○繼承取得系爭土地應有部分4 分之1 ，訴外人李宴\n    仁、李鎮源繼承取得系爭土地應有部分共4 分之1 ，李宴仁\n    、李鎮源取得部分經本院拍賣，由己○○買受取得，李欉則\n    於90年7 月7 日死亡，由被告甲○○、丙○○、乙○○繼承\n    ，各取得應有部分6 分之1 ；及本院97年度訴字第2498號、\n    台灣高等法院98年度上字第699 號確定判決已認定：兩造間\n    之租佃關係於72年5 月25日簽立系爭調解協定書時已合意消\n    滅等情，有耕地租約、系爭調解協定書、土地登記謄本、本\n    院民事執行處拍賣通知及本院97年度訴字第2498號、台灣高\n    等法院98年度上字第699 號民事判決等件影本在卷可稽（見\n    本院卷第108 至117 頁、第134 至156 頁），並為兩造所不\n    爭執，自堪認此部分事實為真實。\n四、原告主張被告丁○之被繼承人李長成依系爭調解協定書所負\n    應移轉系爭土地699 平方公尺之2 分之1 即349.5 平方公尺\n    之義務，在李長成死亡後，應由全體繼承人負連帶責任，其\n    得請求被告丁○移轉系爭土地349.5 平方公尺予原告，另系\n    爭土地之349.5 平方公尺由被告甲○○、丙○○、乙○○負\n    責移轉等語，則為被告丁○、甲○○、丙○○所否認，並以\n    前開情詞置辯。是本件應審究者為：(一)本件訴訟是否就已確\n    定之訴訟標的更行起訴？(二)原告依系爭調解協定書所生之請\n    求權是否已罹於時效而消滅？(三)被告丁○與被告甲○○、丙\n    ○○、乙○○是否有移轉系爭土地各349.5 平方公尺與原告\n    之義務？\n五、關於本件訴訟是否就已確定之訴訟標的更行起訴部分：\n  (一)按「除別有規定外，確定之終局判決就經裁判之訴訟標的，\n    有既判力」，民事訴訟法第400 條第1 項定有明文。又訴訟\n    標的於確定之終局判決中經裁判者，依（舊）民事訴訟法第\n    399 條第1 項規定，當事人固不得就該法律關係更行起訴，\n    惟此係指確定終局判決所裁判之訴訟標的，與更行起訴之法\n    律關係相同者而言，若更行起訴之法律關係，與確定判決所\n    裁判之訴訟標的，僅有因果關係，則二者並非相同，即無該\n    條項之適用，最高法院著有51年台上字第1041號判例可資參\n    照。\n  (二)經查，本院97年度訴字第2498號及台灣高等法院98年度上字\n    第699 號租佃爭議事件，係本件被告丁○以本件原告自72年\n    5 月25日起迄今數十年未繳納租金，經其催告後已終止系爭\n    租賃契約為由，請求原告應將系爭土地上之木屋拆除，並將\n    土地返還予上訴人及其他共有人全體，經法院審理結果，認\n    兩造間之租佃關係於72年5 月25日簽立系爭調解協定書時已\n    合意消滅，判決被告丁○敗訴確定，而本件訴訟則係原告本\n    於系爭調解協定書之約定請求被告移轉系爭土地內之699 平\n    方公尺，二者訴訟標的並不相同，自無本件訴訟標的為確定\n    判決之效力所及之情事。被告丁○抗辯：本件實體法律關係\n    已於前開判決確定，原告復依確定之終局判決或經裁判之訴\n    訟標的更行起訴，在法律上顯無理由云云，並非可採。\n六、關於原告依系爭調解協定書所生之請求權是否已罹於時效而\n    消滅部分：\n  (一)按「請求權，因15年間不行使而消滅」；「消滅時效，自請\n    求權可行使時起算」，民法第為125 條前段、第128 條前段\n    分別定有明文。次按89年1 月26日修正前之農業發展條例第\n    30條前段規定：「每宗耕地不得分割及移轉為共有」，同日\n    修正後之同條例第16條規定：「每宗耕地分割後每人所有面\n    積未達○‧二五公頃者，不得分割。但有下列情形之一者，\n    不在此限︰…五耕地三七五租約，租佃雙方協議以分割方式\n    終止租約者，得分割為租佃雙方單獨所有。」\n  (二)查系爭調解協定書於72年5 月25日簽立時，因農業發展條例\n    有上開第30條之明文，原告尚不能行使其依系爭調解協定書\n    所約定之分割移轉系爭土地請求權，嗣農業發展條例於89年\n    1 月26日修正、同月28日生效後，已有上開第16條之增訂，\n    原告之分割移轉請求權自斯時起始能行使，迄至其於99年10\n    月25日向本院提出民事準備一狀時止（見本院卷第96頁），\n    尚未滿15年，其本件請求權尚未罹於時效。是被告丁○另抗\n    辯：系爭調解協定書內容縱屬有效，已因原告15年不行使請\n    求權而消滅，其得拒絕履行云云，亦非可採。\n七、關於被告丁○與被告甲○○、丙○○、乙○○是否有移轉系\n    爭土地各349.5 平方公尺與原告之義務部分：\n  (一)按債權契約為特定人間之權利義務關係，僅債權人得向債務\n    人請求給付，不得以之對抗契約以外之第三人，此為債之相\n    對性原則（最高法院96年度台上字第1809號判決意旨參照）\n    。本件系爭調解協定書係李長成、李欉與原告、陳尻鬨所訂\n    立，屬其等間債之契約關係，於李長成、李欉先後死亡後，\n    其等之繼承人即被告等人固應民法第1148條第1 項前段：「\n    繼承人自繼承開始時，除本法另有規定外，承受被繼承人財\n    產上之一切權利、義務。」之規定，分別繼承上開調解協定\n    書所負之義務，惟訴外人李宴仁、李鎮源自李長成所繼承系\n    爭土地應有部分4 分之1 部分既已經由本院拍賣而由己○○\n    應買取得，而己○○非契約之當事人，並不受系爭調協議書\n    約定之拘束，此亦為原告所不爭執，故原告不得依系爭調解\n    協定書之約定條款請求己○○履行債務，應無疑義。\n  (二)次按因可歸責於債務人之事由致給付不能者，債權雖仍存在\n    ，但其內容已變為損害賠償請求權，不復以原定之給付為標\n    的，此觀民法第226 條第1 項之規定自明（最高法院84年度\n    台上字第469 號判決意旨參照）。查系爭調解協定書第2 條\n    約定：「未被徵收土地即逕為分割辛○小段20-2地號面積27\n    27平方公尺之內甲方（即李長成、李欉）取得1,549 平方公\n    尺，乙方（即原告）取得699 平方公尺，丙方（即陳尻鬨）\n    取得479 平方公尺，其位置如附圖，未被徵收土地如能分割\n    過戶時雙方同意辦理分割過戶，如不能分割過戶時，按分配\n    位置各分別取得其土地、分管其業，分納稅課，各自由管理\n    使用，如乙、丙方出賣其土地時，甲方同意無條件齊全過戶\n    文件，以利出售，其出售所需費用以及增值稅由乙、丙方自\n    行負，甲方確認乙、丙方應有分配額及其位置，決不藉任何\n    事由否認之，而甲方自不得將乙、丙方分配取得之土地出賣\n    、設押或其他對于乙方有不利之行為，如有是事，願負法律\n    上完全責任。」等語，可見李長成、李欉與原告、陳尻鬨間\n    已協議就系爭土地劃分為3 部分，由原告終局取得如起訴狀\n    附圖一A 所示699 平方公尺之特定部分，是原告對被告之債\n    權應為該特定部分之分割移轉請求權，至為灼然。次查，系\n    爭土地應有部分之4 分之1 既已由不受系爭調解協定書拘束\n    之己○○所取得，原告不得依系爭調解協定書之約定請求己\n    ○○分割移轉上開特定部分之土地，且因系爭土地之分割於\n    原告與己○○等共有人間必須共同為之，無法由被告自行分\n    割，而將如起訴狀附圖一A 所示699 平方公尺之特定部分移\n    轉與原告，可知被告之分割移轉義務已陷於給付不能之狀況\n    ，原告自亦不得請求被告就該特定部分為分割，並為所有權\n    移轉登記甚明，倘原告認此種情形係有可歸責於債務人即被\n    告之事由，亦僅能依民法第226 條第1 項規定，請求被告負\n    損害賠償責任，要不能變更請求被告應移轉其等就系爭土地\n    應有部分之其他相同面積土地，原告為此變更請求，於法顯\n    然無據，並不足採。\n五、綜上所述，原告依系爭調解協定書之約定，請求被告甲○○\n    、丙○○、乙○○應將系爭土地移轉349.5 平方公尺與原告\n    及被告丁○應將系爭土地移轉349.5 平方公尺與原告，為無\n    理由，應予駁回。\n六、本件事證已臻明確，兩造其餘主張、陳述及所提證據，經本\n    院審酌後，認均與本件判斷結果無影響，毋庸再予一一審酌\n    ，附此敘明。\n據上論結，本件原告之訴為無理由，依民事訴訟法民事訴訟法第\n385 條第1項前段、第78條，判決如主文。"
  },
  "search": "臺灣板橋地方法院民事判決99年度訴字第2512號原告戊○○訴訟代理人吳誠修律師林維堯律師被告丁○甲○○丙○○上二人共同訴訟代理人張世興律師複代理人許宏宇律師被告乙○○號上列當事人間請求租佃爭議事件，本院於中華民國100年2月22日言詞辯論終結，判決如下：主文原告之訴駁回。訴訟費用由原告負擔。事實及理由壹、程序方面：一、按訴狀送達後，原告不得將原訴變更或追加他訴。但有下列各款情形之一者，不在此限：…二請求之基礎事實同一者。…七不甚礙被告之防禦及訴訟之終結者，民事訴訟法第255條第1項第2、7款定有明文。查本件原告起訴，其聲明原為：(一)先位部分：被告丁○、甲○○、丙○○、乙○○、己○○應將新北市○○區○○段辛○小段20-2地號土地（下稱系爭土地）分割出如起訴狀附圖一A部分所示面積699平方公尺，並將其所有權全部移轉登記與原告；(二)備位部分：1.被告5人應就系爭土地協同原告向新北市庚○區公所辦理自98年1月1日起至103年12月31日止之耕地三七五租約登記。2.被告5人應將系爭土地如起訴狀附圖二20-2D部分所示面積2,047平方公尺交付原告耕作。嗣於民國100年2月22日言詞辯論期日變更其聲明為：被告甲○○、丙○○、乙○○應將系爭土地移轉349.5平方公尺與原告，被告丁○應將系爭土地移轉349.5平方公尺與原告；並撤回其備位聲明及對己○○部分之訴。被告丁○、甲○○、丙○○與己○○對於上開撤回部分均表示同意，自應准許；被告丁○、甲○○、丙○○對於上開聲明變更部分雖均表示不同意，惟原告所為上開訴之變更，其請求之基礎事實係屬同一，且無礙被告丁○、甲○○、丙○○之防禦及本件訴訟之終結，亦應予准許。二、被告乙○○經合法通知，未於言詞辯論期日到場，核無民事訴訟法第386條所列各款情形，爰依原告之聲請，由其一造辯論而為判決。貳、實體方面：一、原告主張：(一)坐落新北市○○區○○段辛○小段20地號土地（下稱辛○小段20地號土地）原係李長成、李欉共有，應有部分各2分之1，在政府遷台實施耕地三七五減租條例後，即由李長成出租予原告之被繼承人李國耕作，因李欉對該租約並無爭議且亦將土地交付李國耕作而視為承認租約，李國亡故後，由原告單獨繼承，並向新北市庚○區公所辦理租約登記繼續耕作。嗣上開土地因政府開闢二重洪道而分割同段20地號土地、20-1地號土地及系爭土地等3筆土地，其中20地號、20-1地號土地由政府徵收，僅餘系爭土地面積2,727平方公尺，為本件耕地三七五租約之標的。(二)72年5月25日，李長成、李欉與原告訂立調解協定書，（下稱系爭調解協定書），其中第2條約定：「未被徵收土地即逕為分割辛○小段20-2地號面積2,727平方公尺之內甲方（按即李長成、李欉）取得1,549平方公尺，乙方（按即原告）取得699平方公尺，丙方（按即第三人陳尻鬨）取得479平方公尺……其位置如附圖，未被徵收土地如能分割過戶時雙方同意辦理分割過戶，如不能分割過戶時，按分配位置各分別取得其土地、分管其業，分納稅課，各自由管理使用，如乙、丙方出賣其土地時，甲方同意無條件齊全過戶文件，以利出售…，甲方確認乙、丙方應有分配額及其位置，決不藉任何事由否認之。」亦即在72年5月25日訂立系爭調解協定書時，業佃雙方已分配土地，但因當時法令不能辦理分割，所以未終止耕地三七五租約，只是各按分配位置分管其業，惟已約定如能分割過戶時雙方同意辦理分割過戶，多年來相安無事，並每6年由庚○鄉公所辦理租約登記。(三)李長成於93年6月3日過世，其就系爭土地之應有部分由被告丁○取得其2分之1，即應有部分4分之1，訴外人李宴仁、李鎮源取得應有部分共4分之1，但李宴仁、李鎮源取得部分遭法院強制執行拍賣，由己○○應買取得；李欉則於90年7月7日死亡，由被告甲○○、丙○○、乙○○繼承，各取得應有部分6分之1。又原告與李成長、李欉訂立系爭調解協定書當時之農業發展條例規定農地不能細分，所以才會約定如能分割過戶時雙方同意辦理分割過戶，嗣農業發展條例於89年1月26日修正，同年月28日生效，原告得依系爭調解協定書之約定請求。而被告丁○之被繼承人李長成依系爭調解協定書所負應移轉系爭土地699平方公尺之2分之1即349.5平方公尺之義務，在李長成死亡後，應由全體繼承人負連帶責任，故縱訴外人李宴仁、李鎮源就系爭土地之應有部分4分之1遭法院拍賣由己○○應買取得，己○○並稱系爭調協議書為債權契約，其非契約當事人，不受系爭調解協定書之拘束，但就李長成所負移轉系爭土地349.5平方公尺之義務，既由被告丁○繼承而負連帶給付義務，依民法第273條規定，原告自得請求被告丁○移轉系爭土地349.5平方公尺予原告，另系爭土地之349.5平方公尺則由被告甲○○、丙○○、乙○○負責移轉。(四)併為聲明：被告甲○○、丙○○、乙○○應將系爭土地移轉349.5平方公尺與原告，被告丁○應將系爭土地移轉349.5平方公尺與原告。二、被告丁○則抗辯：(一)兩造間曾因本件實體法律關係引發訴訟，經鈞院97年度訴字第2498號（98年4月30日判決）、台灣高等法院98年度上字第699號（98年12月8日判決）民事判決確定，已認定兩造間之租佃關係於72年5月25日簽立系爭調解協定書時已合意消滅，原告復依確定之終局判決或經裁判之訴訟標的更行起訴，在法律上顯無理由。(二)林國（即原告祖父）未經業主李長成、李欉同意擅將系爭耕地轉租予陳尻鬨耕作，因積欠租金達2年以上，經李長成、李欉依法終止租約，60年2月22日由新北市庚○區耕地租佃委員會調解成立，佃農林阿喜（林國次子）、陳尻鬨願將系爭土地交還業主收回自耕，有調解筆錄可稽，故兩造間租佃關係已不存在。又縱系爭調解協定書內容有效，然亦已因原告15年不行使請求權而消滅，被告可拒絕履行，故本件原告之訴為無理由。(三)併為答辯聲明：原告之訴駁回。三、被告甲○○、丙○○則抗辯：(一)按債權之主體，以締結契約之當事人為準（最高法院17年上字第906號判例參照）。查系爭調解協定書之締約當事人既非己○○，且與己○○無任何關係，依前開判例意旨及債權相對性原則，系爭調解協定書對己○○即無任何拘束力，原告請求被告與己○○分割出系爭土地並移轉登記，顯無理由。(二)台灣高等法院98年度上字第699號確定判決認定：「兩造間之租佃關係於72年5月25日簽立系爭調解協定書時已合意消滅」，依爭點效理論，對原告有拘束力，原告不得作相反之主張。又「耕地三七五減租條例第6條第1項載：『本條例施行後耕地租約應一律以書面為之，租約之訂立、變更、終止或換訂，應由出租人會同承租人申請登記』云云，係為保護佃農及謀舉證上便利而設，非謂凡租約之訂立、變更、終止或換訂，須經登記，始能生效。」最高法院51年台上字第2629號著有判例。因此，新北市庚○區公所之耕地租約登記，不影響原告就系爭土地租佃關係於72年5月25日即因簽立系爭調解協定書時已合意消滅之法律效力，亦即原告就系爭土地無租佃關係存在。另耕地三七五減租條例第25條規定：「在耕地租期屆滿前，出租人縱將其所有權讓典與第三人，其租佃契約對於受讓受典人仍繼續有效，受讓受典人應會同原承租人申請為租約變更之登記。」其規定係在「在耕地租期屆滿前」，然己○○係於系爭土地租佃關係消滅後之98年8月20日始因法院拍賣受讓所有權，亦與上開規定要件不符，自無該條規定之適用。(三)併為答辯聲明：原告之訴駁回。三、本件辛○小段20地號土地係李長成、李欉共有，應有部分各2分之1，原由李長成依耕地三七五減租條例出租予李國耕作，李欉對該租約無爭議且將土地交付李國耕作視為承認租約。李國亡故後，由原告單獨繼承，並向新北市庚○區公所辦理租約登記繼續耕作，嗣上開土地因政府開闢二重洪道而分割同段20地號土地、20-1地號土地及系爭土地等3筆土地，其中20地號、20-1地號土地由政府徵收，僅餘系爭土地面積2,727平方公尺；72年5月25日，李長成、李欉與原告、陳尻鬨訂立爭調解協定書，約定：系爭土地由李長成、李欉（甲方）取得1,549平方公尺，原告（乙方）取得699平方公尺，人陳尻鬨（丙方）取得479平方公尺，原告分配位置如起訴狀附圖一A部分；嗣李長成於93年6月3日死亡，由被告丁○繼承取得系爭土地應有部分4分之1，訴外人李宴仁、李鎮源繼承取得系爭土地應有部分共4分之1，李宴仁、李鎮源取得部分經本院拍賣，由己○○買受取得，李欉則於90年7月7日死亡，由被告甲○○、丙○○、乙○○繼承，各取得應有部分6分之1；及本院97年度訴字第2498號、台灣高等法院98年度上字第699號確定判決已認定：兩造間之租佃關係於72年5月25日簽立系爭調解協定書時已合意消滅等情，有耕地租約、系爭調解協定書、土地登記謄本、本院民事執行處拍賣通知及本院97年度訴字第2498號、台灣高等法院98年度上字第699號民事判決等件影本在卷可稽（見本院卷第108至117頁、第134至156頁），並為兩造所不爭執，自堪認此部分事實為真實。四、原告主張被告丁○之被繼承人李長成依系爭調解協定書所負應移轉系爭土地699平方公尺之2分之1即349.5平方公尺之義務，在李長成死亡後，應由全體繼承人負連帶責任，其得請求被告丁○移轉系爭土地349.5平方公尺予原告，另系爭土地之349.5平方公尺由被告甲○○、丙○○、乙○○負責移轉等語，則為被告丁○、甲○○、丙○○所否認，並以前開情詞置辯。是本件應審究者為：(一)本件訴訟是否就已確定之訴訟標的更行起訴？(二)原告依系爭調解協定書所生之請求權是否已罹於時效而消滅？(三)被告丁○與被告甲○○、丙○○、乙○○是否有移轉系爭土地各349.5平方公尺與原告之義務？五、關於本件訴訟是否就已確定之訴訟標的更行起訴部分：(一)按「除別有規定外，確定之終局判決就經裁判之訴訟標的，有既判力」，民事訴訟法第400條第1項定有明文。又訴訟標的於確定之終局判決中經裁判者，依（舊）民事訴訟法第399條第1項規定，當事人固不得就該法律關係更行起訴，惟此係指確定終局判決所裁判之訴訟標的，與更行起訴之法律關係相同者而言，若更行起訴之法律關係，與確定判決所裁判之訴訟標的，僅有因果關係，則二者並非相同，即無該條項之適用，最高法院著有51年台上字第1041號判例可資參照。(二)經查，本院97年度訴字第2498號及台灣高等法院98年度上字第699號租佃爭議事件，係本件被告丁○以本件原告自72年5月25日起迄今數十年未繳納租金，經其催告後已終止系爭租賃契約為由，請求原告應將系爭土地上之木屋拆除，並將土地返還予上訴人及其他共有人全體，經法院審理結果，認兩造間之租佃關係於72年5月25日簽立系爭調解協定書時已合意消滅，判決被告丁○敗訴確定，而本件訴訟則係原告本於系爭調解協定書之約定請求被告移轉系爭土地內之699平方公尺，二者訴訟標的並不相同，自無本件訴訟標的為確定判決之效力所及之情事。被告丁○抗辯：本件實體法律關係已於前開判決確定，原告復依確定之終局判決或經裁判之訴訟標的更行起訴，在法律上顯無理由云云，並非可採。六、關於原告依系爭調解協定書所生之請求權是否已罹於時效而消滅部分：(一)按「請求權，因15年間不行使而消滅」；「消滅時效，自請求權可行使時起算」，民法第為125條前段、第128條前段分別定有明文。次按89年1月26日修正前之農業發展條例第30條前段規定：「每宗耕地不得分割及移轉為共有」，同日修正後之同條例第16條規定：「每宗耕地分割後每人所有面積未達○‧二五公頃者，不得分割。但有下列情形之一者，不在此限︰…五耕地三七五租約，租佃雙方協議以分割方式終止租約者，得分割為租佃雙方單獨所有。」(二)查系爭調解協定書於72年5月25日簽立時，因農業發展條例有上開第30條之明文，原告尚不能行使其依系爭調解協定書所約定之分割移轉系爭土地請求權，嗣農業發展條例於89年1月26日修正、同月28日生效後，已有上開第16條之增訂，原告之分割移轉請求權自斯時起始能行使，迄至其於99年10月25日向本院提出民事準備一狀時止（見本院卷第96頁），尚未滿15年，其本件請求權尚未罹於時效。是被告丁○另抗辯：系爭調解協定書內容縱屬有效，已因原告15年不行使請求權而消滅，其得拒絕履行云云，亦非可採。七、關於被告丁○與被告甲○○、丙○○、乙○○是否有移轉系爭土地各349.5平方公尺與原告之義務部分：(一)按債權契約為特定人間之權利義務關係，僅債權人得向債務人請求給付，不得以之對抗契約以外之第三人，此為債之相對性原則（最高法院96年度台上字第1809號判決意旨參照）。本件系爭調解協定書係李長成、李欉與原告、陳尻鬨所訂立，屬其等間債之契約關係，於李長成、李欉先後死亡後，其等之繼承人即被告等人固應民法第1148條第1項前段：「繼承人自繼承開始時，除本法另有規定外，承受被繼承人財產上之一切權利、義務。」之規定，分別繼承上開調解協定書所負之義務，惟訴外人李宴仁、李鎮源自李長成所繼承系爭土地應有部分4分之1部分既已經由本院拍賣而由己○○應買取得，而己○○非契約之當事人，並不受系爭調協議書約定之拘束，此亦為原告所不爭執，故原告不得依系爭調解協定書之約定條款請求己○○履行債務，應無疑義。(二)次按因可歸責於債務人之事由致給付不能者，債權雖仍存在，但其內容已變為損害賠償請求權，不復以原定之給付為標的，此觀民法第226條第1項之規定自明（最高法院84年度台上字第469號判決意旨參照）。查系爭調解協定書第2條約定：「未被徵收土地即逕為分割辛○小段20-2地號面積2727平方公尺之內甲方（即李長成、李欉）取得1,549平方公尺，乙方（即原告）取得699平方公尺，丙方（即陳尻鬨）取得479平方公尺，其位置如附圖，未被徵收土地如能分割過戶時雙方同意辦理分割過戶，如不能分割過戶時，按分配位置各分別取得其土地、分管其業，分納稅課，各自由管理使用，如乙、丙方出賣其土地時，甲方同意無條件齊全過戶文件，以利出售，其出售所需費用以及增值稅由乙、丙方自行負，甲方確認乙、丙方應有分配額及其位置，決不藉任何事由否認之，而甲方自不得將乙、丙方分配取得之土地出賣、設押或其他對于乙方有不利之行為，如有是事，願負法律上完全責任。」等語，可見李長成、李欉與原告、陳尻鬨間已協議就系爭土地劃分為3部分，由原告終局取得如起訴狀附圖一A所示699平方公尺之特定部分，是原告對被告之債權應為該特定部分之分割移轉請求權，至為灼然。次查，系爭土地應有部分之4分之1既已由不受系爭調解協定書拘束之己○○所取得，原告不得依系爭調解協定書之約定請求己○○分割移轉上開特定部分之土地，且因系爭土地之分割於原告與己○○等共有人間必須共同為之，無法由被告自行分割，而將如起訴狀附圖一A所示699平方公尺之特定部分移轉與原告，可知被告之分割移轉義務已陷於給付不能之狀況，原告自亦不得請求被告就該特定部分為分割，並為所有權移轉登記甚明，倘原告認此種情形係有可歸責於債務人即被告之事由，亦僅能依民法第226條第1項規定，請求被告負損害賠償責任，要不能變更請求被告應移轉其等就系爭土地應有部分之其他相同面積土地，原告為此變更請求，於法顯然無據，並不足採。五、綜上所述，原告依系爭調解協定書之約定，請求被告甲○○、丙○○、乙○○應將系爭土地移轉349.5平方公尺與原告及被告丁○應將系爭土地移轉349.5平方公尺與原告，為無理由，應予駁回。六、本件事證已臻明確，兩造其餘主張、陳述及所提證據，經本院審酌後，認均與本件判斷結果無影響，毋庸再予一一審酌，附此敘明。據上論結，本件原告之訴為無理由，依民事訴訟法民事訴訟法第385條第1項前段、第78條，判決如主文。中華民國100年3月1日民事第一庭法官高文淵上列正本係照原本作成如對本判決上訴，須於判決送達後20日內向本院提出上訴狀中華民國100年3月1日書記官黃瀅螢",
  "characters": {
    "judges": [
      "高文淵"
    ],
    "prosecutors": [

    ],
    "lawyers": [
      "吳誠修",
      "林維堯",
      "張世興",
      "許宏宇"
    ],
    "clerks": [
      "黃瀅螢"
    ],
    "plaintiffs": [
      "戊"
    ],
    "defendants": [
      "丁○",
      "乙○○"
    ],
    "prosecutor_office": [

    ],
    "creditors": [

    ],
    "debtors": [

    ],
    "judicial_associate_officer": [

    ]
  },
  "adjudged_at": "2011-03-01",
  "created_at": "2016-02-12 05:36:19",
  "updated_at": "2016-02-12 05:36:19"
}