{
  "identify": "TPD-91-附民-174-20020718-1",
  "court": {
    "name": "臺灣臺北地方法院",
    "code": "TPD"
  },
  "division": {
    "name": "刑事",
    "code": "M"
  },
  "year": 91,
  "word": "附民",
  "number": "174",
  "jcheck": "1",
  "reason": "因贓物案附帶民訴",
  "content": "臺灣臺北地方法院刑事附帶民事訴訟判決            九十一年度附民字第一七四號\n    原      告  交通部郵政總局  設：台北市大安區○○○路○段五五號\n    法定代理人  鄭文政\n    訴訟代理人  官朝永律師\n    被      告  甲○○\n右列被告因九十一年度易更(一)字第一號贓物案件，經原告提起附帶民事訴訟，本院判\n決如左：\n    主  文\n原告之訴及假執行之聲請均駁回。\n    事  實\n一、原告訴之聲明及陳述均如附件之刑事附帶民事訴訟起訴狀所載。\n二、被告未為任何聲明或陳述，亦未提出任何書狀。\n    理  由\n一、按刑事訴訟諭知無罪之判決者，對於附帶民事訴訟部分以判決駁回原告之訴，刑\n    事訴訟法第五百零三條第一項前段定有明文。\n二、本件被告被訴贓物案件，業經本院於民國九十一年七月十八日以九十一年度易更\n    (一)字第一號判決諭知無罪，依照上開說明，原告之訴，自應予以駁回。假執行之\n    聲請，失所依據，併予駁回。\n據上論斷，應依刑事訴訟法第五百零三條第一項前段，判決如主文。\n中      華      民      國    九十一    年      七      月     十八     日\n                                      臺灣臺北地方法院刑事第三庭\n                                          法  官  葉建廷\n右正本證明與原本無異\n對於本判決如不服非對刑事判決上訴時不得上訴，並應於送達後十日內向本院提出上\n訴狀\n                                          書記官  許婉如\n中      華      民      國    九十一    年      七      月     十八     日\n",
  "structure": {
    "main": "原告之訴及假執行之聲請均駁回。",
    "fact": "一、原告訴之聲明及陳述均如附件之刑事附帶民事訴訟起訴狀所載。\n二、被告未為任何聲明或陳述，亦未提出任何書狀。",
    "reason": "一、按刑事訴訟諭知無罪之判決者，對於附帶民事訴訟部分以判決駁回原告之訴，刑\n    事訴訟法第五百零三條第一項前段定有明文。\n二、本件被告被訴贓物案件，業經本院於民國九十一年七月十八日以九十一年度易更\n    (一)字第一號判決諭知無罪，依照上開說明，原告之訴，自應予以駁回。假執行之\n    聲請，失所依據，併予駁回。\n據上論斷，應依刑事訴訟法第五百零三條第一項前段，判決如主文。\n中      華      民      國    九十一    年      七      月     十八     日\n                                      臺灣臺北地方法院刑事第三庭\n                                          法  官  葉建廷\n右正本證明與原本無異\n對於本判決如不服非對刑事判決上訴時不得上訴，並應於送達後十日內向本院提出上\n訴狀\n                                          書記官  許婉如"
  },
  "search": "臺灣臺北地方法院刑事附帶民事訴訟判決九十一年度附民字第一七四號原告交通部郵政總局設：台北市大安區○○○路○段五五號法定代理人鄭文政訴訟代理人官朝永律師被告甲○○右列被告因九十一年度易更(一)字第一號贓物案件，經原告提起附帶民事訴訟，本院判決如左：主文原告之訴及假執行之聲請均駁回。事實一、原告訴之聲明及陳述均如附件之刑事附帶民事訴訟起訴狀所載。二、被告未為任何聲明或陳述，亦未提出任何書狀。理由一、按刑事訴訟諭知無罪之判決者，對於附帶民事訴訟部分以判決駁回原告之訴，刑事訴訟法第五百零三條第一項前段定有明文。二、本件被告被訴贓物案件，業經本院於民國九十一年七月十八日以九十一年度易更(一)字第一號判決諭知無罪，依照上開說明，原告之訴，自應予以駁回。假執行之聲請，失所依據，併予駁回。據上論斷，應依刑事訴訟法第五百零三條第一項前段，判決如主文。中華民國九十一年七月十八日臺灣臺北地方法院刑事第三庭法官葉建廷右正本證明與原本無異對於本判決如不服非對刑事判決上訴時不得上訴，並應於送達後十日內向本院提出上訴狀書記官許婉如中華民國九十一年七月十八日",
  "characters": {
    "judges": [
      "葉建廷"
    ],
    "prosecutors": [

    ],
    "lawyers": [
      "官朝永"
    ],
    "clerks": [
      "許婉如"
    ],
    "plaintiffs": [
      "交通部郵政總局"
    ],
    "defendants": [
      "甲○○",
      "右列被告因九十一年度易更(一)字第一號贓物案件，經原告提起附帶民事訴訟，本院判",
      "決如左："
    ],
    "prosecutor_office": [

    ],
    "creditors": [

    ],
    "debtors": [

    ],
    "judicial_associate_officer": [

    ]
  },
  "adjudged_at": "2002-07-18",
  "created_at": "2016-02-05 16:32:07",
  "updated_at": "2016-02-05 16:32:07"
}