{
  "identify": "TCB-90-訴-1610-20020703-3",
  "court": {
    "name": "臺中高等行政法院",
    "code": "TCB"
  },
  "division": {
    "name": "行政",
    "code": "A"
  },
  "year": 90,
  "word": "訴",
  "number": "1610",
  "jcheck": "3",
  "reason": "返還公法上不當得利",
  "content": "臺中高等行政法院裁定                              九十年度訴字第一六一○號\n    原      告  台中市政府\n    代  表  人  甲○○        .\n    訴訟代理人  黃英傑  律師\n    複  代理人  陳盈壽  律師\n                辰○○\n    被      告  乙○○\n                丙○○\n                丁○○\n                戊○○\n                己○○\n                庚○○\n                辛○○\n                壬○○\n                癸○○\n    右  九  人\n    訴訟代理人  黃幼蘭  律師\n    複代理人    羅豐胤  律師\n    右  一  人\n    複代理人    卯○○\n    被      告  子○○\n                丑○○\n    右  二人共同\n    訴訟代理人  柳正村  律師\n    被      告  寅○○\n右當事人間因返還公法上不當得利事件，本院於民國九十一年五月六日所為之判決，\n應裁定更正如左：\n    主  文\n原判決正本中為判決之法官「黃淑玲」，應更正為林秋華。\n    理  由\n一、按判決如有誤寫、誤算或其他類此之顯然錯誤者，法院得隨時或依聲請以裁定更\n    正之，民事訴訟法第二百三十二條第一項定有明文，並為行政訴訟法第二百十八\n    條所準用。\n二、查本院前開之判決正本有如主文所示之顯然錯誤，應予更正。\n三、依首開規定裁定如主文。\n中    華    民    國    九十一      年      七        月    三      日\n                 臺 中 高 等 行 政 法 院   第 四 庭\n                                審 判 長 法  官  沈 應 南\n                                         法  官  林 秋 華\n                                         法  官  許 武 峰\n右正本證明與原本無異。\n本裁定不得抗告。\n中    華    民    國    九十一      年      七        月    三      日\n                                法  院 書 記 官  廖 倩 慧\n",
  "structure": {
    "main": "原判決正本中為判決之法官「黃淑玲」，應更正為林秋華。",
    "reason": "一、按判決如有誤寫、誤算或其他類此之顯然錯誤者，法院得隨時或依聲請以裁定更\n    正之，民事訴訟法第二百三十二條第一項定有明文，並為行政訴訟法第二百十八\n    條所準用。\n二、查本院前開之判決正本有如主文所示之顯然錯誤，應予更正。\n三、依首開規定裁定如主文。"
  },
  "search": "臺中高等行政法院裁定九十年度訴字第一六一○號原告台中市政府代表人甲○○.訴訟代理人黃英傑律師複代理人陳盈壽律師辰○○被告乙○○丙○○丁○○戊○○己○○庚○○辛○○壬○○癸○○右九人訴訟代理人黃幼蘭律師複代理人羅豐胤律師右一人複代理人卯○○被告子○○丑○○右二人共同訴訟代理人柳正村律師被告寅○○右當事人間因返還公法上不當得利事件，本院於民國九十一年五月六日所為之判決，應裁定更正如左：主文原判決正本中為判決之法官「黃淑玲」，應更正為林秋華。理由一、按判決如有誤寫、誤算或其他類此之顯然錯誤者，法院得隨時或依聲請以裁定更正之，民事訴訟法第二百三十二條第一項定有明文，並為行政訴訟法第二百十八條所準用。二、查本院前開之判決正本有如主文所示之顯然錯誤，應予更正。三、依首開規定裁定如主文。中華民國九十一年七月三日臺中高等行政法院第四庭審判長法官沈應南法官林秋華法官許武峰右正本證明與原本無異。本裁定不得抗告。中華民國九十一年七月三日法院書記官廖倩慧",
  "characters": {
    "judges": [
      "沈應南",
      "林秋華",
      "許武峰"
    ],
    "prosecutors": [

    ],
    "lawyers": [

    ],
    "clerks": [

    ],
    "plaintiffs": [
      "台中市政府"
    ],
    "defendants": [
      "乙○○",
      "子○○",
      "寅○○",
      "右當事人間因返還公法上不當得利事件，本院於民國九十一年五月六日所為之判決，",
      "應裁定更正如左："
    ],
    "prosecutor_office": [

    ],
    "creditors": [

    ],
    "debtors": [

    ],
    "judicial_associate_officer": [

    ]
  },
  "adjudged_at": "2002-07-03",
  "created_at": "2016-02-05 16:42:41",
  "updated_at": "2016-02-05 16:42:41"
}