{
  "identify": "TYD-100-聲-2902-20110816-1",
  "court": {
    "name": "臺灣桃園地方法院",
    "code": "TYD"
  },
  "division": {
    "name": "刑事",
    "code": "M"
  },
  "year": 100,
  "word": "聲",
  "number": "2902",
  "jcheck": "1",
  "reason": "聲請沒收",
  "content": "臺灣桃園地方法院刑事裁定             100年度聲字第2902號\n聲  請  人  臺灣桃園地方法院檢察署檢察官\n被      告  黃竹君\n上列聲請人聲請沒收事件，本院裁定如下：\n    主  文\n扣案之第二級毒品甲基安非他命壹包（驗餘毛重零點肆陸玖公克\n），沒收銷燬之。\n    理  由\n一、按違禁物得單獨宣告沒收，刑法第40條第2項定有明文。復\n    按安非他命屬毒品危害防制條例第2條第2項第2款所列之第\n    二級毒品，不得非法持有或施用；而查獲之毒品，不問屬於\n    犯人與否，均沒收銷燬之，毒品危害防制條例第18條第1項\n    前段，亦定有明文。\n二、聲請意旨略以：本案被告施用毒品案件，業經臺灣桃園地方\n    法院檢察署檢察官為不起訴處分在案；然扣案之被告所有之\n    安非他命1 包（毛重0.48公克）尚未處理，且甲基安非他命\n    係屬違禁物品，爰依上揭規定聲請宣告沒收銷燬。\n三、經查，扣案之顆粒1 包，經送臺灣檢驗科技股份有限公司鑑\n    定結果檢出第二級毒品甲基安非他命成份，確為第二級毒品\n    甲基安非他命，此有該公司民國99年9 月7 日、\n    UL/2010/80605 號鑑定書1 件存卷可參。而上開扣案毒品1\n    包原毛重0.48公克，並經取樣鑑析用罄0.0110公克，驗餘毛\n    重0.469 公克。是除鑑析用罄部分外，聲請意旨以上開扣案\n    毒品為違禁物，聲請單獨宣告沒收，核無不合，應予准許。\n    爰依毒品危害防制條例第18條第1 項前段，刑法第40條第2\n    項，裁定如主文。\n中    華    民    國   100    年    8     月    16    日\n                  刑事第十庭    法  官  華奕超\n以上正本證明與原本無異。\n如不服本裁定，應於送達後5 日內，向本院提出抗告狀。\n                                書記官  徐珮綾\n中    華    民    國   100    年    8     月    16    日",
  "structure": {
    "main": "扣案之第二級毒品甲基安非他命壹包（驗餘毛重零點肆陸玖公克\n），沒收銷燬之。",
    "reason": "一、按違禁物得單獨宣告沒收，刑法第40條第2項定有明文。復\n    按安非他命屬毒品危害防制條例第2條第2項第2款所列之第\n    二級毒品，不得非法持有或施用；而查獲之毒品，不問屬於\n    犯人與否，均沒收銷燬之，毒品危害防制條例第18條第1項\n    前段，亦定有明文。\n二、聲請意旨略以：本案被告施用毒品案件，業經臺灣桃園地方\n    法院檢察署檢察官為不起訴處分在案；然扣案之被告所有之\n    安非他命1 包（毛重0.48公克）尚未處理，且甲基安非他命\n    係屬違禁物品，爰依上揭規定聲請宣告沒收銷燬。\n三、經查，扣案之顆粒1 包，經送臺灣檢驗科技股份有限公司鑑\n    定結果檢出第二級毒品甲基安非他命成份，確為第二級毒品\n    甲基安非他命，此有該公司民國99年9 月7 日、\n    UL/2010/80605 號鑑定書1 件存卷可參。而上開扣案毒品1\n    包原毛重0.48公克，並經取樣鑑析用罄0.0110公克，驗餘毛\n    重0.469 公克。是除鑑析用罄部分外，聲請意旨以上開扣案\n    毒品為違禁物，聲請單獨宣告沒收，核無不合，應予准許。\n    爰依毒品危害防制條例第18條第1 項前段，刑法第40條第2\n    項，裁定如主文。"
  },
  "search": "臺灣桃園地方法院刑事裁定100年度聲字第2902號聲請人臺灣桃園地方法院檢察署檢察官被告黃竹君上列聲請人聲請沒收事件，本院裁定如下：主文扣案之第二級毒品甲基安非他命壹包（驗餘毛重零點肆陸玖公克），沒收銷燬之。理由一、按違禁物得單獨宣告沒收，刑法第40條第2項定有明文。復按安非他命屬毒品危害防制條例第2條第2項第2款所列之第二級毒品，不得非法持有或施用；而查獲之毒品，不問屬於犯人與否，均沒收銷燬之，毒品危害防制條例第18條第1項前段，亦定有明文。二、聲請意旨略以：本案被告施用毒品案件，業經臺灣桃園地方法院檢察署檢察官為不起訴處分在案；然扣案之被告所有之安非他命1包（毛重0.48公克）尚未處理，且甲基安非他命係屬違禁物品，爰依上揭規定聲請宣告沒收銷燬。三、經查，扣案之顆粒1包，經送臺灣檢驗科技股份有限公司鑑定結果檢出第二級毒品甲基安非他命成份，確為第二級毒品甲基安非他命，此有該公司民國99年9月7日、UL/2010/80605號鑑定書1件存卷可參。而上開扣案毒品1包原毛重0.48公克，並經取樣鑑析用罄0.0110公克，驗餘毛重0.469公克。是除鑑析用罄部分外，聲請意旨以上開扣案毒品為違禁物，聲請單獨宣告沒收，核無不合，應予准許。爰依毒品危害防制條例第18條第1項前段，刑法第40條第2項，裁定如主文。中華民國100年8月16日刑事第十庭法官華奕超以上正本證明與原本無異。如不服本裁定，應於送達後5日內，向本院提出抗告狀。書記官徐珮綾中華民國100年8月16日",
  "characters": {
    "judges": [
      "華奕超"
    ],
    "prosecutors": [

    ],
    "lawyers": [

    ],
    "clerks": [
      "徐珮綾"
    ],
    "plaintiffs": [

    ],
    "defendants": [
      "黃竹君"
    ],
    "prosecutor_office": [
      "臺灣桃園地方法院檢察署檢察官"
    ],
    "creditors": [

    ],
    "debtors": [

    ],
    "judicial_associate_officer": [

    ]
  },
  "adjudged_at": "2011-08-16",
  "created_at": "2016-02-12 16:22:47",
  "updated_at": "2016-02-12 16:22:47"
}