{
  "identify": "KSD-100-訴緝-160-20111104-1",
  "court": {
    "name": "臺灣高雄地方法院",
    "code": "KSD"
  },
  "division": {
    "name": "刑事",
    "code": "M"
  },
  "year": 100,
  "word": "訴緝",
  "number": "160",
  "jcheck": "1",
  "reason": "殺人未遂等",
  "content": "臺灣高雄地方法院刑事判決            100年度訴緝字第160號\n公  訴  人  臺灣高雄地方法院檢察署檢察官\n被      告  翁碩建\n上列被告因殺人未遂等案件，經檢察官提起公訴（76年度偵字第\n6331號），本院判決如下：\n    主  文\n本件免訴。\n    理  由\n一、公訴意旨略以：如起訴書所載（如附件）。\n二、按案件時效已完成者，應諭知免訴之判決，並得不經言詞辯\n    論為之，刑事訴訟法第302條第2款、第307 條分別定有明文\n    。又於民國94年1月7日刑法修正施行前，其追訴權或行刑權\n    時效已進行而未完成者，比較修正前後之條文，適用最有利\n    於行為人之規定，亦為刑法施行法第8條之1所明定。本件被\n    告行為（75年1月9日）後追訴權時效即開始進行，惟時效完\n    成前，刑法已於94年2月2日修正公布，並自95年7月1日起生\n    效施行。被告翁碩建所涉上開罪名，其法定刑為死刑、無期\n    徒刑或10年以上有期徒刑，依修正前刑法第80條第1項第1款\n    規定，追訴權時效期間為20年，修正後同條款則加長為30年\n    ，比較新舊法結果，以修正前之規定較有利於被告，依前開\n    刑法施行法第8條之1規定，自應適用被告行為時之舊法計算\n    其追訴權時效期間；另關於時效之停止進行及其期間之計算\n    ，亦應一體適用修正施行前刑法第83條之規定。\n三、次按本件被告行為時之刑法第271條第2項、第1 項殺人未遂\n    罪嫌，法定刑為死刑、無期徒刑或10年以上有期徒刑，是依\n    修正前刑法第80條第1項第1款規定，其追訴權時效期間為20\n    年，惟其追訴權時效如依法律之規定，偵查、起訴或審判之\n    程序，不能開始或繼續時，停止其進行，其時效之停止，自\n    停止原因消滅之日起與停止前已經過之期間，一併計算，停\n    止原因繼續存在之期間，如達於上開20年追訴權時效期間4\n    分之1（即5年）時，其停止原因視為消滅，刑法第80條第1\n    項第1 款、第83條分別定有明文，又前開停止時效進行之事\n    由，包括因被告通緝致審判程序不能開始或繼續之情形，亦\n    經司法院29年院字第1963號著有解釋。\n四、經查：被告前於75年1月9日間因涉犯刑法第271條第2項、第\n    1 項之罪，經檢察官提起公訴，嗣因被告逃匿，由本院於76\n    年7 月10日通緝在案，以致審判程序不能開始、繼續，其追\n    訴權時效期間，依修正前刑法第80條第1項第1款為20年；但\n    因被告逃匿，經本院通緝，致審判不能進行，應一併計算該\n    項追訴期間4分之1，合計為25年。而本件被告犯罪成立之日\n    為75年1月9日，開始實施偵查日為76年5 月18日（見76年度\n    偵字第6331號偵查卷之臺灣高雄地方法院檢察署收案戳章）\n    ，於76年5 月30日提起公訴，並於76年6月9日繫屬本院（見\n    76年度訴字第795 號收案戳章），嗣被告逃匿，由本院於76\n    年7月10日發佈通緝（見本院高隴刑世字第619號通緝書稿，\n    見76年度訴字第795 號卷第27頁），致審判程序無法進行，\n    依大法官釋字第138 號解釋意旨，此時追訴權時效即無不行\n    使之情形，自不生時效進行問題，亦應予加計，即犯罪行為\n    終了日（75年1月9日）+追訴權期間（25年）+實施偵查日至\n    通緝發佈日（1 月23日），但須扣除起訴後至法院繫屬期間\n    （11日），是本件被告之追訴權時效期間應至100年2月21日\n    完成，揆諸前揭說明，爰不經言詞辯論，逕為免訴之諭知。\n據上論結，應依刑事訴訟法第302條第2款、第307條判決如主文\n。\n中    華    民    國    100    年    11    月    4    日\n                  刑事第七庭    審判長法  官  陳  箐\n                                      法  官  吳佳穎\n                                      法  官  曾建豪\n以上正本證明與原本無異。\n如不服本判決應於收受送達後10日內向本院提出上訴書狀，並應\n敘述具體理由；如未敘述上訴理由者，應於上訴期間屆滿後20日\n內向本院補提理由書（均須按他造當事人之人數附繕本）「切勿\n逕送上級法院」。\n中    華    民    國   100    年    11    月    4     日\n                                      書記官  秦富潔",
  "structure": {
    "main": "本件免訴。",
    "reason": "一、公訴意旨略以：如起訴書所載（如附件）。\n二、按案件時效已完成者，應諭知免訴之判決，並得不經言詞辯\n    論為之，刑事訴訟法第302條第2款、第307 條分別定有明文\n    。又於民國94年1月7日刑法修正施行前，其追訴權或行刑權\n    時效已進行而未完成者，比較修正前後之條文，適用最有利\n    於行為人之規定，亦為刑法施行法第8條之1所明定。本件被\n    告行為（75年1月9日）後追訴權時效即開始進行，惟時效完\n    成前，刑法已於94年2月2日修正公布，並自95年7月1日起生\n    效施行。被告翁碩建所涉上開罪名，其法定刑為死刑、無期\n    徒刑或10年以上有期徒刑，依修正前刑法第80條第1項第1款\n    規定，追訴權時效期間為20年，修正後同條款則加長為30年\n    ，比較新舊法結果，以修正前之規定較有利於被告，依前開\n    刑法施行法第8條之1規定，自應適用被告行為時之舊法計算\n    其追訴權時效期間；另關於時效之停止進行及其期間之計算\n    ，亦應一體適用修正施行前刑法第83條之規定。\n三、次按本件被告行為時之刑法第271條第2項、第1 項殺人未遂\n    罪嫌，法定刑為死刑、無期徒刑或10年以上有期徒刑，是依\n    修正前刑法第80條第1項第1款規定，其追訴權時效期間為20\n    年，惟其追訴權時效如依法律之規定，偵查、起訴或審判之\n    程序，不能開始或繼續時，停止其進行，其時效之停止，自\n    停止原因消滅之日起與停止前已經過之期間，一併計算，停\n    止原因繼續存在之期間，如達於上開20年追訴權時效期間4\n    分之1（即5年）時，其停止原因視為消滅，刑法第80條第1\n    項第1 款、第83條分別定有明文，又前開停止時效進行之事\n    由，包括因被告通緝致審判程序不能開始或繼續之情形，亦\n    經司法院29年院字第1963號著有解釋。\n四、經查：被告前於75年1月9日間因涉犯刑法第271條第2項、第\n    1 項之罪，經檢察官提起公訴，嗣因被告逃匿，由本院於76\n    年7 月10日通緝在案，以致審判程序不能開始、繼續，其追\n    訴權時效期間，依修正前刑法第80條第1項第1款為20年；但\n    因被告逃匿，經本院通緝，致審判不能進行，應一併計算該\n    項追訴期間4分之1，合計為25年。而本件被告犯罪成立之日\n    為75年1月9日，開始實施偵查日為76年5 月18日（見76年度\n    偵字第6331號偵查卷之臺灣高雄地方法院檢察署收案戳章）\n    ，於76年5 月30日提起公訴，並於76年6月9日繫屬本院（見\n    76年度訴字第795 號收案戳章），嗣被告逃匿，由本院於76\n    年7月10日發佈通緝（見本院高隴刑世字第619號通緝書稿，\n    見76年度訴字第795 號卷第27頁），致審判程序無法進行，\n    依大法官釋字第138 號解釋意旨，此時追訴權時效即無不行\n    使之情形，自不生時效進行問題，亦應予加計，即犯罪行為\n    終了日（75年1月9日）+追訴權期間（25年）+實施偵查日至\n    通緝發佈日（1 月23日），但須扣除起訴後至法院繫屬期間\n    （11日），是本件被告之追訴權時效期間應至100年2月21日\n    完成，揆諸前揭說明，爰不經言詞辯論，逕為免訴之諭知。\n據上論結，應依刑事訴訟法第302條第2款、第307條判決如主文\n。"
  },
  "search": "臺灣高雄地方法院刑事判決100年度訴緝字第160號公訴人臺灣高雄地方法院檢察署檢察官被告翁碩建上列被告因殺人未遂等案件，經檢察官提起公訴（76年度偵字第6331號），本院判決如下：主文本件免訴。理由一、公訴意旨略以：如起訴書所載（如附件）。二、按案件時效已完成者，應諭知免訴之判決，並得不經言詞辯論為之，刑事訴訟法第302條第2款、第307條分別定有明文。又於民國94年1月7日刑法修正施行前，其追訴權或行刑權時效已進行而未完成者，比較修正前後之條文，適用最有利於行為人之規定，亦為刑法施行法第8條之1所明定。本件被告行為（75年1月9日）後追訴權時效即開始進行，惟時效完成前，刑法已於94年2月2日修正公布，並自95年7月1日起生效施行。被告翁碩建所涉上開罪名，其法定刑為死刑、無期徒刑或10年以上有期徒刑，依修正前刑法第80條第1項第1款規定，追訴權時效期間為20年，修正後同條款則加長為30年，比較新舊法結果，以修正前之規定較有利於被告，依前開刑法施行法第8條之1規定，自應適用被告行為時之舊法計算其追訴權時效期間；另關於時效之停止進行及其期間之計算，亦應一體適用修正施行前刑法第83條之規定。三、次按本件被告行為時之刑法第271條第2項、第1項殺人未遂罪嫌，法定刑為死刑、無期徒刑或10年以上有期徒刑，是依修正前刑法第80條第1項第1款規定，其追訴權時效期間為20年，惟其追訴權時效如依法律之規定，偵查、起訴或審判之程序，不能開始或繼續時，停止其進行，其時效之停止，自停止原因消滅之日起與停止前已經過之期間，一併計算，停止原因繼續存在之期間，如達於上開20年追訴權時效期間4分之1（即5年）時，其停止原因視為消滅，刑法第80條第1項第1款、第83條分別定有明文，又前開停止時效進行之事由，包括因被告通緝致審判程序不能開始或繼續之情形，亦經司法院29年院字第1963號著有解釋。四、經查：被告前於75年1月9日間因涉犯刑法第271條第2項、第1項之罪，經檢察官提起公訴，嗣因被告逃匿，由本院於76年7月10日通緝在案，以致審判程序不能開始、繼續，其追訴權時效期間，依修正前刑法第80條第1項第1款為20年；但因被告逃匿，經本院通緝，致審判不能進行，應一併計算該項追訴期間4分之1，合計為25年。而本件被告犯罪成立之日為75年1月9日，開始實施偵查日為76年5月18日（見76年度偵字第6331號偵查卷之臺灣高雄地方法院檢察署收案戳章），於76年5月30日提起公訴，並於76年6月9日繫屬本院（見76年度訴字第795號收案戳章），嗣被告逃匿，由本院於76年7月10日發佈通緝（見本院高隴刑世字第619號通緝書稿，見76年度訴字第795號卷第27頁），致審判程序無法進行，依大法官釋字第138號解釋意旨，此時追訴權時效即無不行使之情形，自不生時效進行問題，亦應予加計，即犯罪行為終了日（75年1月9日）+追訴權期間（25年）+實施偵查日至通緝發佈日（1月23日），但須扣除起訴後至法院繫屬期間（11日），是本件被告之追訴權時效期間應至100年2月21日完成，揆諸前揭說明，爰不經言詞辯論，逕為免訴之諭知。據上論結，應依刑事訴訟法第302條第2款、第307條判決如主文。中華民國100年11月4日刑事第七庭審判長法官陳箐法官吳佳穎法官曾建豪以上正本證明與原本無異。如不服本判決應於收受送達後10日內向本院提出上訴書狀，並應敘述具體理由；如未敘述上訴理由者，應於上訴期間屆滿後20日內向本院補提理由書（均須按他造當事人之人數附繕本）「切勿逕送上級法院」。中華民國100年11月4日書記官秦富潔",
  "characters": {
    "judges": [
      "陳箐",
      "吳佳穎",
      "曾建豪"
    ],
    "prosecutors": [

    ],
    "lawyers": [

    ],
    "clerks": [

    ],
    "plaintiffs": [

    ],
    "defendants": [
      "翁碩建"
    ],
    "prosecutor_office": [
      "臺灣高雄地方法院檢察署檢察官"
    ],
    "creditors": [

    ],
    "debtors": [

    ],
    "judicial_associate_officer": [

    ]
  },
  "adjudged_at": "2011-11-04",
  "created_at": "2016-02-13 00:26:37",
  "updated_at": "2016-02-13 00:26:37"
}