{
  "identify": "PTD-100-簡-1876-20111104-1",
  "court": {
    "name": "臺灣屏東地方法院",
    "code": "PTD"
  },
  "division": {
    "name": "刑事",
    "code": "M"
  },
  "year": 100,
  "word": "簡",
  "number": "1876",
  "jcheck": "1",
  "reason": "違反家庭暴力防治法",
  "content": "臺灣屏東地方法院刑事簡易判決         100年度簡字第1876號\n聲  請  人  臺灣屏東地方法院檢察署檢察官\n被      告  陳金生\n上列被告因違反家庭暴力防治法案件，經檢察官聲請以簡易判決\n處刑（100 年度偵字第8064號），本院判決如下：\n    主      文\n陳金生犯違反保護令罪，處拘役拾日，如易科罰金，以新臺幣\n壹仟元折算壹日。\n    事實及理由\n一、本案認定被告陳金生之犯罪事實及證據，除犯罪事實欄第1\n    行內應補充「（自民國68或69年起同居至100 年7 月12日）\n    」外，餘與檢察官聲請簡易判決處刑書之記載相同，茲引用\n    之（如附件）。\n二、按家庭暴力防治法所稱之家庭暴力，係指家庭成員間實施身\n    體或精神上不法侵害之行為；又家庭暴力罪，指家庭成員間\n    故意實施家庭暴力行為而成立其他法律所規定之犯罪，家庭\n    暴力防治法第2 條第1 款、第2 款分別定有明文。本案被告\n    與告訴人吳玉英係同居人關係，並同居約30餘年，業據被告\n    及告訴人陳述無訛，渠等顯具有家庭暴力防治法第3 條第2\n    款所定之家庭成員關係，是核被告毆傷告訴人之行為，係犯\n    家庭暴力防治法第61條第1 款之違反保護令罪及刑法第277\n    條第1 項之傷害罪。被告以一行為觸犯上開2 罪，為想像競\n    合犯，應從較重之違反保護令罪論處。爰審酌被告於收受本\n    院所核發之民事暫時保護令後，竟漠視保護令所表彰之國家\n    公權力及對被害人保護之作用，對被害人為本件犯行，實屬\n    可議，惟念其尚知坦承犯行，頗有悔意，又其素行良好、無\n    前科，有臺灣高等法院被告前案紀錄表在卷可按，暨考量其\n    違反保護令之犯罪動機、手段、告訴人所受傷勢非重及其智\n    識程度、生活狀況等一切情狀，量處如主文所示之刑，並諭\n    知易科罰金之折算標準。\n三、應依刑事訴訟法第449 條第1 項前段、第454 條第2 項，家\n    庭暴力防治法第61條第1 款，刑法第11條前段、第55條、第\n    277 條第1 項、41條第1 項前段，逕以簡易判決處如主文所\n    示之刑。\n中    華    民    國   100    年    11    月    4     日\n                  刑事第二庭    法  官  陳秀慧\n以上正本證明與原本無異。\n如不服本判決，得於判決書送達之翌日起10日內，以書狀敘述理\n由，向本庭提出上訴。\n中    華    民    國   100    年    11    月    4     日\n                                書記官  蔡語珊\n附錄本判決論罪科刑法條全文\n家庭暴力防治法第61條：\n違反法院依第14條第1 項、第16條第3 項所為之下列裁定者，為\n本法所稱違反保護令罪，處3 年以下有期徒刑、拘役或科或併科\n新臺幣10萬元以下罰金：\n一、禁止實施家庭暴力。\n二、禁止騷擾、接觸、跟蹤、通話、通信或其他非必要之聯絡行\n    為。\n三、遷出住居所。\n四、遠離住居所、工作場所、學校或其他特定場所。\n五、完成加害人處遇計畫。\n刑法第277條：\n傷害人之身體或健康者，處3 年以下有期徒刑、拘役或1 千元以\n下罰金。\n犯前項之罪因而致人於死者，處無期徒刑或7 年以上有期徒刑；\n致重傷者，處3 年以上10年以下有期徒刑。",
  "structure": {
    "main": "陳金生犯違反保護令罪，處拘役拾日，如易科罰金，以新臺幣\n壹仟元折算壹日。",
    "fact": "一、本案認定被告陳金生之犯罪事實及證據，除犯罪事實欄第1\n    行內應補充「（自民國68或69年起同居至100 年7 月12日）\n    」外，餘與檢察官聲請簡易判決處刑書之記載相同，茲引用\n    之（如附件）。\n二、按家庭暴力防治法所稱之家庭暴力，係指家庭成員間實施身\n    體或精神上不法侵害之行為；又家庭暴力罪，指家庭成員間\n    故意實施家庭暴力行為而成立其他法律所規定之犯罪，家庭\n    暴力防治法第2 條第1 款、第2 款分別定有明文。本案被告\n    與告訴人吳玉英係同居人關係，並同居約30餘年，業據被告\n    及告訴人陳述無訛，渠等顯具有家庭暴力防治法第3 條第2\n    款所定之家庭成員關係，是核被告毆傷告訴人之行為，係犯\n    家庭暴力防治法第61條第1 款之違反保護令罪及刑法第277\n    條第1 項之傷害罪。被告以一行為觸犯上開2 罪，為想像競\n    合犯，應從較重之違反保護令罪論處。爰審酌被告於收受本\n    院所核發之民事暫時保護令後，竟漠視保護令所表彰之國家\n    公權力及對被害人保護之作用，對被害人為本件犯行，實屬\n    可議，惟念其尚知坦承犯行，頗有悔意，又其素行良好、無\n    前科，有臺灣高等法院被告前案紀錄表在卷可按，暨考量其\n    違反保護令之犯罪動機、手段、告訴人所受傷勢非重及其智\n    識程度、生活狀況等一切情狀，量處如主文所示之刑，並諭\n    知易科罰金之折算標準。\n三、應依刑事訴訟法第449 條第1 項前段、第454 條第2 項，家\n    庭暴力防治法第61條第1 款，刑法第11條前段、第55條、第\n    277 條第1 項、41條第1 項前段，逕以簡易判決處如主文所\n    示之刑。",
    "reason": "一、本案認定被告陳金生之犯罪事實及證據，除犯罪事實欄第1\n    行內應補充「（自民國68或69年起同居至100 年7 月12日）\n    」外，餘與檢察官聲請簡易判決處刑書之記載相同，茲引用\n    之（如附件）。\n二、按家庭暴力防治法所稱之家庭暴力，係指家庭成員間實施身\n    體或精神上不法侵害之行為；又家庭暴力罪，指家庭成員間\n    故意實施家庭暴力行為而成立其他法律所規定之犯罪，家庭\n    暴力防治法第2 條第1 款、第2 款分別定有明文。本案被告\n    與告訴人吳玉英係同居人關係，並同居約30餘年，業據被告\n    及告訴人陳述無訛，渠等顯具有家庭暴力防治法第3 條第2\n    款所定之家庭成員關係，是核被告毆傷告訴人之行為，係犯\n    家庭暴力防治法第61條第1 款之違反保護令罪及刑法第277\n    條第1 項之傷害罪。被告以一行為觸犯上開2 罪，為想像競\n    合犯，應從較重之違反保護令罪論處。爰審酌被告於收受本\n    院所核發之民事暫時保護令後，竟漠視保護令所表彰之國家\n    公權力及對被害人保護之作用，對被害人為本件犯行，實屬\n    可議，惟念其尚知坦承犯行，頗有悔意，又其素行良好、無\n    前科，有臺灣高等法院被告前案紀錄表在卷可按，暨考量其\n    違反保護令之犯罪動機、手段、告訴人所受傷勢非重及其智\n    識程度、生活狀況等一切情狀，量處如主文所示之刑，並諭\n    知易科罰金之折算標準。\n三、應依刑事訴訟法第449 條第1 項前段、第454 條第2 項，家\n    庭暴力防治法第61條第1 款，刑法第11條前段、第55條、第\n    277 條第1 項、41條第1 項前段，逕以簡易判決處如主文所\n    示之刑。"
  },
  "search": "臺灣屏東地方法院刑事簡易判決100年度簡字第1876號聲請人臺灣屏東地方法院檢察署檢察官被告陳金生上列被告因違反家庭暴力防治法案件，經檢察官聲請以簡易判決處刑（100年度偵字第8064號），本院判決如下：主文陳金生犯違反保護令罪，處拘役拾日，如易科罰金，以新臺幣壹仟元折算壹日。事實及理由一、本案認定被告陳金生之犯罪事實及證據，除犯罪事實欄第1行內應補充「（自民國68或69年起同居至100年7月12日）」外，餘與檢察官聲請簡易判決處刑書之記載相同，茲引用之（如附件）。二、按家庭暴力防治法所稱之家庭暴力，係指家庭成員間實施身體或精神上不法侵害之行為；又家庭暴力罪，指家庭成員間故意實施家庭暴力行為而成立其他法律所規定之犯罪，家庭暴力防治法第2條第1款、第2款分別定有明文。本案被告與告訴人吳玉英係同居人關係，並同居約30餘年，業據被告及告訴人陳述無訛，渠等顯具有家庭暴力防治法第3條第2款所定之家庭成員關係，是核被告毆傷告訴人之行為，係犯家庭暴力防治法第61條第1款之違反保護令罪及刑法第277條第1項之傷害罪。被告以一行為觸犯上開2罪，為想像競合犯，應從較重之違反保護令罪論處。爰審酌被告於收受本院所核發之民事暫時保護令後，竟漠視保護令所表彰之國家公權力及對被害人保護之作用，對被害人為本件犯行，實屬可議，惟念其尚知坦承犯行，頗有悔意，又其素行良好、無前科，有臺灣高等法院被告前案紀錄表在卷可按，暨考量其違反保護令之犯罪動機、手段、告訴人所受傷勢非重及其智識程度、生活狀況等一切情狀，量處如主文所示之刑，並諭知易科罰金之折算標準。三、應依刑事訴訟法第449條第1項前段、第454條第2項，家庭暴力防治法第61條第1款，刑法第11條前段、第55條、第277條第1項、41條第1項前段，逕以簡易判決處如主文所示之刑。中華民國100年11月4日刑事第二庭法官陳秀慧以上正本證明與原本無異。如不服本判決，得於判決書送達之翌日起10日內，以書狀敘述理由，向本庭提出上訴。中華民國100年11月4日書記官蔡語珊附錄本判決論罪科刑法條全文家庭暴力防治法第61條：違反法院依第14條第1項、第16條第3項所為之下列裁定者，為本法所稱違反保護令罪，處3年以下有期徒刑、拘役或科或併科新臺幣10萬元以下罰金：一、禁止實施家庭暴力。二、禁止騷擾、接觸、跟蹤、通話、通信或其他非必要之聯絡行為。三、遷出住居所。四、遠離住居所、工作場所、學校或其他特定場所。五、完成加害人處遇計畫。刑法第277條：傷害人之身體或健康者，處3年以下有期徒刑、拘役或1千元以下罰金。犯前項之罪因而致人於死者，處無期徒刑或7年以上有期徒刑；致重傷者，處3年以上10年以下有期徒刑。",
  "characters": {
    "judges": [
      "陳秀慧"
    ],
    "prosecutors": [

    ],
    "lawyers": [

    ],
    "clerks": [
      "蔡語珊"
    ],
    "plaintiffs": [

    ],
    "defendants": [
      "陳金生"
    ],
    "prosecutor_office": [
      "臺灣屏東地方法院檢察署檢察官"
    ],
    "creditors": [

    ],
    "debtors": [

    ],
    "judicial_associate_officer": [

    ]
  },
  "adjudged_at": "2011-11-04",
  "created_at": "2016-02-13 00:27:21",
  "updated_at": "2016-02-13 00:27:21"
}