{
  "identify": "KSD-94-訴-2126-20050804-1",
  "court": {
    "name": "臺灣高雄地方法院",
    "code": "KSD"
  },
  "division": {
    "name": "刑事",
    "code": "M"
  },
  "year": 94,
  "word": "訴",
  "number": "2126",
  "jcheck": "1",
  "reason": "毒品危害防制條例",
  "content": "臺灣高雄地方法院刑事裁定              94年度訴字第2126號\n公  訴  人  臺灣高雄地方法院檢察署檢察官\n被      告  甲○○  男  37歲.\n即  具保人\n                      號\n上列被告因毒品危害防制條例案件，本院裁定如下：\n    主  文\n甲○○繳納之保證金新臺幣貳萬元，沒入之。\n    理  由\n一、按具保之被告逃匿者，應命具保人繳納指定之保證金額，並\n    沒入之。不繳納者，強制執行。保證金已繳納者，沒入之；\n    沒入保證金，以法院之裁定行之，刑事訴訟法第118 條第1\n    項、第121 條第1 項分別定有明文。\n二、本件被告即具保人因毒品危害防制條例案件，經臺灣高雄地\n    方法院檢察署檢察官於民國94年7 月1 日指定保證金額新臺\n    幣2 萬元，由被告即具保人繳納現金後，已將被告釋放，然\n    被告經本院依其住所傳喚、拘提均未到案，此有個人基本資\n    料查詢結果、臺灣高雄地方法院法務部在監在押資料表、高\n    雄縣政府警察局湖內分局94年7 月28日高縣湖警字第094000\n    07170 號函及所附之拘票、報告書各一紙、本院送達證書1\n    份附卷可稽，並有本院準備程序筆錄可按，足認被告顯已逃\n    匿，揆諸前揭規定，自應將被告即具保人繳納之上開保證金\n    沒入之。\n三、依刑事訴訟法第118 條、第121 條第1 項，裁定如主文。\n中    華    民    國    94    年    8     月    4     日\n            刑事第十五庭   審判長法  官  莊松泉\n                                 法  官  林永村\n                                 法  官  林揚奇\n以上正本證明與原本無異。\n如不服本裁定，應於收受送達後5日內向本院提出抗告狀。\n中    華    民    國    94    年    8     月    4     日\n                                 書記官  于耀文\n",
  "structure": {
    "main": "甲○○繳納之保證金新臺幣貳萬元，沒入之。",
    "reason": "一、按具保之被告逃匿者，應命具保人繳納指定之保證金額，並\n    沒入之。不繳納者，強制執行。保證金已繳納者，沒入之；\n    沒入保證金，以法院之裁定行之，刑事訴訟法第118 條第1\n    項、第121 條第1 項分別定有明文。\n二、本件被告即具保人因毒品危害防制條例案件，經臺灣高雄地\n    方法院檢察署檢察官於民國94年7 月1 日指定保證金額新臺\n    幣2 萬元，由被告即具保人繳納現金後，已將被告釋放，然\n    被告經本院依其住所傳喚、拘提均未到案，此有個人基本資\n    料查詢結果、臺灣高雄地方法院法務部在監在押資料表、高\n    雄縣政府警察局湖內分局94年7 月28日高縣湖警字第094000\n    07170 號函及所附之拘票、報告書各一紙、本院送達證書1\n    份附卷可稽，並有本院準備程序筆錄可按，足認被告顯已逃\n    匿，揆諸前揭規定，自應將被告即具保人繳納之上開保證金\n    沒入之。\n三、依刑事訴訟法第118 條、第121 條第1 項，裁定如主文。"
  },
  "search": "臺灣高雄地方法院刑事裁定94年度訴字第2126號公訴人臺灣高雄地方法院檢察署檢察官被告甲○○男37歲.即具保人號上列被告因毒品危害防制條例案件，本院裁定如下：主文甲○○繳納之保證金新臺幣貳萬元，沒入之。理由一、按具保之被告逃匿者，應命具保人繳納指定之保證金額，並沒入之。不繳納者，強制執行。保證金已繳納者，沒入之；沒入保證金，以法院之裁定行之，刑事訴訟法第118條第1項、第121條第1項分別定有明文。二、本件被告即具保人因毒品危害防制條例案件，經臺灣高雄地方法院檢察署檢察官於民國94年7月1日指定保證金額新臺幣2萬元，由被告即具保人繳納現金後，已將被告釋放，然被告經本院依其住所傳喚、拘提均未到案，此有個人基本資料查詢結果、臺灣高雄地方法院法務部在監在押資料表、高雄縣政府警察局湖內分局94年7月28日高縣湖警字第09400007170號函及所附之拘票、報告書各一紙、本院送達證書1份附卷可稽，並有本院準備程序筆錄可按，足認被告顯已逃匿，揆諸前揭規定，自應將被告即具保人繳納之上開保證金沒入之。三、依刑事訴訟法第118條、第121條第1項，裁定如主文。中華民國94年8月4日刑事第十五庭審判長法官莊松泉法官林永村法官林揚奇以上正本證明與原本無異。如不服本裁定，應於收受送達後5日內向本院提出抗告狀。中華民國94年8月4日書記官于耀文",
  "characters": {
    "judges": [
      "莊松泉",
      "林永村",
      "林揚奇"
    ],
    "prosecutors": [

    ],
    "lawyers": [

    ],
    "clerks": [
      "于耀文"
    ],
    "plaintiffs": [

    ],
    "defendants": [
      "甲○○  男  37歲.",
      "即  具保人"
    ],
    "prosecutor_office": [
      "臺灣高雄地方法院檢察署檢察官"
    ],
    "creditors": [

    ],
    "debtors": [

    ],
    "judicial_associate_officer": [

    ]
  },
  "adjudged_at": "2005-08-04",
  "created_at": "2016-02-06 22:28:22",
  "updated_at": "2016-02-06 22:28:22"
}