{
  "identify": "SCD-94-竹交簡-367-20050804-1",
  "court": {
    "name": "臺灣新竹地方法院",
    "code": "SCD"
  },
  "division": {
    "name": "刑事",
    "code": "M"
  },
  "year": 94,
  "word": "竹交簡",
  "number": "367",
  "jcheck": "1",
  "reason": "公共危險",
  "content": "臺灣新竹地方法院刑事簡易判決       94年度竹交簡字第367號\n聲  請  人  臺灣新竹地方法院檢察署檢察官\n被      告  甲○○\n上列被告因公共危險案件，經檢察官聲請以簡易判決處刑（94年\n度速偵字第456號），本院判決如下︰\n    主  文\n甲○○服用酒類，不能安全駕駛動力交通工具而駕駛，處罰金壹\n萬元，如易服勞役，以佰元折算壹日。\n    事實及理由\n一、本件犯罪事實：甲○○於民國94年3 月17日中午12時許，在\n    苗栗縣某不詳地點之友人住處內飲用1 瓶米酒後，已達不能\n    安全駕駛動力交通工具之狀態，仍於當日晚上8 時許，騎乘\n    IIQ-895號重型機車上路欲前往新竹市，嗣於同日晚上10 時\n    10分許，行經新竹市○區○○里○○街與南門街口時為警攔\n    停盤查，經檢測其吐氣所含酒精濃度為每公升0.80毫克而查\n    獲上情。案經新竹市警察局第三分局報告臺灣新竹地方法院\n    檢察署檢察官偵查聲請簡易判決處刑。\n二、證據：\n  (一)被告於偵查中之供述（見偵查卷第9至11頁、第22頁）。\n  (二)被告吐氣所含酒精濃度為每公升0.80毫克，有吐氣酒精濃度\n    測試紀錄紙（見偵查卷第12頁）。\n  (三)被告駕駛有蛇行，車身搖擺不定，轉彎半徑過大或過小等駕\n    駛操控力欠佳之情形，經命作平衡動作，腳步不穩，顯然無\n    法正常駕駛，在查獲、測試或訊問過程，有意識模糊，注意\n    力無法集中、呆滯木僵等情事，有刑法第185條之3案件測試\n    觀察紀錄表足佐（見偵查卷第13頁）。\n  (四)被告於查獲後之94年3 月17日晚上10時25分，經命其檢測雙\n    腳併攏，兩手緊貼大腿將1 腳向前抬高離地15公分，並停止\n    不動30秒，雙手向前平伸，閉眼、輪流使用左右手的食指指\n    尖觸摸鼻尖，閉雙眼，30秒內朗誦阿拉伯數字，由1001到10\n    30等項目，均不合格，有汽機車駕駛人酒後生理協調平衡檢\n    測紀錄表（見偵查卷第14頁），另就用筆在2 個同心圓之間\n    的0.5 公分環狀帶內另畫圓之檢測項目，上開汽機車駕駛人\n    酒後生理協調平衡檢測紀錄表雖未勾選「合格」或「不合格\n    」，然被告所畫筆畫扭曲顫抖並不成圓，是此項目檢測結果\n    應屬不合格，附此敘明。\n  (五)被告於警詢中雖辯稱為警查獲時意識很清楚，可以正常駕車\n    ，惟於檢察官訊問時已對其所犯公共危險罪認罪，按酒精濃\n    度呼氣已達每公升0.55毫克時，肇事率為一般正常人之10倍\n    ，有法務部88年5 月18日所發之法88檢字第001669號函在卷\n    為憑，被告吐氣所含酒精濃度為每公升0.80毫克業如前述，\n    參以被告前揭蛇行，車身搖擺不定，轉彎半徑過大或過小，\n    腳步不穩，意識模糊，注意力無法集中、呆滯木僵及雙腳併\n    攏，1 腳抬高，閉眼使用指尖觸摸鼻尖、朗誦阿拉伯數字，\n    另畫圓等檢測項目，均不合格之測試結果，堪認被告確已達\n    不能安全駕駛動力交通工具之狀態甚明。\n三、爰審酌被告無視酒後不得駕車之禁令仍於酒後駕車上路，嚴\n    重影響其他用路人之安全，酒測濃度為每公升0.80毫克，坦\n    承酒後不能安全駕車之犯行，態度尚佳等一切情狀，量處如\n    主文所示之刑，並諭知易服勞役之折算標準，以資懲儆。\n四、依刑事訴訟法第449條第1項前段，刑法第185條之3、第42條\n    第2項，罰金罰鍰提高標準條例第2條，逕以簡易判決如主文\n    。\n五、如不服本判決，得自判決送達後10日內，向本院提起上訴。\n中    華    民    國    94    年    8     月    4     日\n                  新竹簡易庭法  官  黃美盈\n以上正本證明與原本無異。\n中    華    民    國    94    年    8     月    8     日\n                            書記官  吳尚文\n附錄本案論罪科刑法條：\n刑法第185條之3\n服用毒品、麻醉藥品、酒類或其他相類之物，不能安全駕駛動力\n交通工具而駕駛者，處一年以下有期徒刑、拘役或三萬元以下罰\n金。\n",
  "structure": {
    "main": "甲○○服用酒類，不能安全駕駛動力交通工具而駕駛，處罰金壹\n萬元，如易服勞役，以佰元折算壹日。",
    "fact": "一、本件犯罪事實：甲○○於民國94年3 月17日中午12時許，在\n    苗栗縣某不詳地點之友人住處內飲用1 瓶米酒後，已達不能\n    安全駕駛動力交通工具之狀態，仍於當日晚上8 時許，騎乘\n    IIQ-895號重型機車上路欲前往新竹市，嗣於同日晚上10 時\n    10分許，行經新竹市○區○○里○○街與南門街口時為警攔\n    停盤查，經檢測其吐氣所含酒精濃度為每公升0.80毫克而查\n    獲上情。案經新竹市警察局第三分局報告臺灣新竹地方法院\n    檢察署檢察官偵查聲請簡易判決處刑。\n二、證據：\n  (一)被告於偵查中之供述（見偵查卷第9至11頁、第22頁）。\n  (二)被告吐氣所含酒精濃度為每公升0.80毫克，有吐氣酒精濃度\n    測試紀錄紙（見偵查卷第12頁）。\n  (三)被告駕駛有蛇行，車身搖擺不定，轉彎半徑過大或過小等駕\n    駛操控力欠佳之情形，經命作平衡動作，腳步不穩，顯然無\n    法正常駕駛，在查獲、測試或訊問過程，有意識模糊，注意\n    力無法集中、呆滯木僵等情事，有刑法第185條之3案件測試\n    觀察紀錄表足佐（見偵查卷第13頁）。\n  (四)被告於查獲後之94年3 月17日晚上10時25分，經命其檢測雙\n    腳併攏，兩手緊貼大腿將1 腳向前抬高離地15公分，並停止\n    不動30秒，雙手向前平伸，閉眼、輪流使用左右手的食指指\n    尖觸摸鼻尖，閉雙眼，30秒內朗誦阿拉伯數字，由1001到10\n    30等項目，均不合格，有汽機車駕駛人酒後生理協調平衡檢\n    測紀錄表（見偵查卷第14頁），另就用筆在2 個同心圓之間\n    的0.5 公分環狀帶內另畫圓之檢測項目，上開汽機車駕駛人\n    酒後生理協調平衡檢測紀錄表雖未勾選「合格」或「不合格\n    」，然被告所畫筆畫扭曲顫抖並不成圓，是此項目檢測結果\n    應屬不合格，附此敘明。\n  (五)被告於警詢中雖辯稱為警查獲時意識很清楚，可以正常駕車\n    ，惟於檢察官訊問時已對其所犯公共危險罪認罪，按酒精濃\n    度呼氣已達每公升0.55毫克時，肇事率為一般正常人之10倍\n    ，有法務部88年5 月18日所發之法88檢字第001669號函在卷\n    為憑，被告吐氣所含酒精濃度為每公升0.80毫克業如前述，\n    參以被告前揭蛇行，車身搖擺不定，轉彎半徑過大或過小，\n    腳步不穩，意識模糊，注意力無法集中、呆滯木僵及雙腳併\n    攏，1 腳抬高，閉眼使用指尖觸摸鼻尖、朗誦阿拉伯數字，\n    另畫圓等檢測項目，均不合格之測試結果，堪認被告確已達\n    不能安全駕駛動力交通工具之狀態甚明。\n三、爰審酌被告無視酒後不得駕車之禁令仍於酒後駕車上路，嚴\n    重影響其他用路人之安全，酒測濃度為每公升0.80毫克，坦\n    承酒後不能安全駕車之犯行，態度尚佳等一切情狀，量處如\n    主文所示之刑，並諭知易服勞役之折算標準，以資懲儆。\n四、依刑事訴訟法第449條第1項前段，刑法第185條之3、第42條\n    第2項，罰金罰鍰提高標準條例第2條，逕以簡易判決如主文\n    。\n五、如不服本判決，得自判決送達後10日內，向本院提起上訴。",
    "reason": "一、本件犯罪事實：甲○○於民國94年3 月17日中午12時許，在\n    苗栗縣某不詳地點之友人住處內飲用1 瓶米酒後，已達不能\n    安全駕駛動力交通工具之狀態，仍於當日晚上8 時許，騎乘\n    IIQ-895號重型機車上路欲前往新竹市，嗣於同日晚上10 時\n    10分許，行經新竹市○區○○里○○街與南門街口時為警攔\n    停盤查，經檢測其吐氣所含酒精濃度為每公升0.80毫克而查\n    獲上情。案經新竹市警察局第三分局報告臺灣新竹地方法院\n    檢察署檢察官偵查聲請簡易判決處刑。\n二、證據：\n  (一)被告於偵查中之供述（見偵查卷第9至11頁、第22頁）。\n  (二)被告吐氣所含酒精濃度為每公升0.80毫克，有吐氣酒精濃度\n    測試紀錄紙（見偵查卷第12頁）。\n  (三)被告駕駛有蛇行，車身搖擺不定，轉彎半徑過大或過小等駕\n    駛操控力欠佳之情形，經命作平衡動作，腳步不穩，顯然無\n    法正常駕駛，在查獲、測試或訊問過程，有意識模糊，注意\n    力無法集中、呆滯木僵等情事，有刑法第185條之3案件測試\n    觀察紀錄表足佐（見偵查卷第13頁）。\n  (四)被告於查獲後之94年3 月17日晚上10時25分，經命其檢測雙\n    腳併攏，兩手緊貼大腿將1 腳向前抬高離地15公分，並停止\n    不動30秒，雙手向前平伸，閉眼、輪流使用左右手的食指指\n    尖觸摸鼻尖，閉雙眼，30秒內朗誦阿拉伯數字，由1001到10\n    30等項目，均不合格，有汽機車駕駛人酒後生理協調平衡檢\n    測紀錄表（見偵查卷第14頁），另就用筆在2 個同心圓之間\n    的0.5 公分環狀帶內另畫圓之檢測項目，上開汽機車駕駛人\n    酒後生理協調平衡檢測紀錄表雖未勾選「合格」或「不合格\n    」，然被告所畫筆畫扭曲顫抖並不成圓，是此項目檢測結果\n    應屬不合格，附此敘明。\n  (五)被告於警詢中雖辯稱為警查獲時意識很清楚，可以正常駕車\n    ，惟於檢察官訊問時已對其所犯公共危險罪認罪，按酒精濃\n    度呼氣已達每公升0.55毫克時，肇事率為一般正常人之10倍\n    ，有法務部88年5 月18日所發之法88檢字第001669號函在卷\n    為憑，被告吐氣所含酒精濃度為每公升0.80毫克業如前述，\n    參以被告前揭蛇行，車身搖擺不定，轉彎半徑過大或過小，\n    腳步不穩，意識模糊，注意力無法集中、呆滯木僵及雙腳併\n    攏，1 腳抬高，閉眼使用指尖觸摸鼻尖、朗誦阿拉伯數字，\n    另畫圓等檢測項目，均不合格之測試結果，堪認被告確已達\n    不能安全駕駛動力交通工具之狀態甚明。\n三、爰審酌被告無視酒後不得駕車之禁令仍於酒後駕車上路，嚴\n    重影響其他用路人之安全，酒測濃度為每公升0.80毫克，坦\n    承酒後不能安全駕車之犯行，態度尚佳等一切情狀，量處如\n    主文所示之刑，並諭知易服勞役之折算標準，以資懲儆。\n四、依刑事訴訟法第449條第1項前段，刑法第185條之3、第42條\n    第2項，罰金罰鍰提高標準條例第2條，逕以簡易判決如主文\n    。\n五、如不服本判決，得自判決送達後10日內，向本院提起上訴。"
  },
  "search": "臺灣新竹地方法院刑事簡易判決94年度竹交簡字第367號聲請人臺灣新竹地方法院檢察署檢察官被告甲○○上列被告因公共危險案件，經檢察官聲請以簡易判決處刑（94年度速偵字第456號），本院判決如下︰主文甲○○服用酒類，不能安全駕駛動力交通工具而駕駛，處罰金壹萬元，如易服勞役，以佰元折算壹日。事實及理由一、本件犯罪事實：甲○○於民國94年3月17日中午12時許，在苗栗縣某不詳地點之友人住處內飲用1瓶米酒後，已達不能安全駕駛動力交通工具之狀態，仍於當日晚上8時許，騎乘IIQ-895號重型機車上路欲前往新竹市，嗣於同日晚上10時10分許，行經新竹市○區○○里○○街與南門街口時為警攔停盤查，經檢測其吐氣所含酒精濃度為每公升0.80毫克而查獲上情。案經新竹市警察局第三分局報告臺灣新竹地方法院檢察署檢察官偵查聲請簡易判決處刑。二、證據：(一)被告於偵查中之供述（見偵查卷第9至11頁、第22頁）。(二)被告吐氣所含酒精濃度為每公升0.80毫克，有吐氣酒精濃度測試紀錄紙（見偵查卷第12頁）。(三)被告駕駛有蛇行，車身搖擺不定，轉彎半徑過大或過小等駕駛操控力欠佳之情形，經命作平衡動作，腳步不穩，顯然無法正常駕駛，在查獲、測試或訊問過程，有意識模糊，注意力無法集中、呆滯木僵等情事，有刑法第185條之3案件測試觀察紀錄表足佐（見偵查卷第13頁）。(四)被告於查獲後之94年3月17日晚上10時25分，經命其檢測雙腳併攏，兩手緊貼大腿將1腳向前抬高離地15公分，並停止不動30秒，雙手向前平伸，閉眼、輪流使用左右手的食指指尖觸摸鼻尖，閉雙眼，30秒內朗誦阿拉伯數字，由1001到1030等項目，均不合格，有汽機車駕駛人酒後生理協調平衡檢測紀錄表（見偵查卷第14頁），另就用筆在2個同心圓之間的0.5公分環狀帶內另畫圓之檢測項目，上開汽機車駕駛人酒後生理協調平衡檢測紀錄表雖未勾選「合格」或「不合格」，然被告所畫筆畫扭曲顫抖並不成圓，是此項目檢測結果應屬不合格，附此敘明。(五)被告於警詢中雖辯稱為警查獲時意識很清楚，可以正常駕車，惟於檢察官訊問時已對其所犯公共危險罪認罪，按酒精濃度呼氣已達每公升0.55毫克時，肇事率為一般正常人之10倍，有法務部88年5月18日所發之法88檢字第001669號函在卷為憑，被告吐氣所含酒精濃度為每公升0.80毫克業如前述，參以被告前揭蛇行，車身搖擺不定，轉彎半徑過大或過小，腳步不穩，意識模糊，注意力無法集中、呆滯木僵及雙腳併攏，1腳抬高，閉眼使用指尖觸摸鼻尖、朗誦阿拉伯數字，另畫圓等檢測項目，均不合格之測試結果，堪認被告確已達不能安全駕駛動力交通工具之狀態甚明。三、爰審酌被告無視酒後不得駕車之禁令仍於酒後駕車上路，嚴重影響其他用路人之安全，酒測濃度為每公升0.80毫克，坦承酒後不能安全駕車之犯行，態度尚佳等一切情狀，量處如主文所示之刑，並諭知易服勞役之折算標準，以資懲儆。四、依刑事訴訟法第449條第1項前段，刑法第185條之3、第42條第2項，罰金罰鍰提高標準條例第2條，逕以簡易判決如主文。五、如不服本判決，得自判決送達後10日內，向本院提起上訴。中華民國94年8月4日新竹簡易庭法官黃美盈以上正本證明與原本無異。中華民國94年8月8日書記官吳尚文附錄本案論罪科刑法條：刑法第185條之3服用毒品、麻醉藥品、酒類或其他相類之物，不能安全駕駛動力交通工具而駕駛者，處一年以下有期徒刑、拘役或三萬元以下罰金。",
  "characters": {
    "judges": [
      "黃美盈"
    ],
    "prosecutors": [

    ],
    "lawyers": [

    ],
    "clerks": [
      "吳尚文"
    ],
    "plaintiffs": [

    ],
    "defendants": [
      "甲○○"
    ],
    "prosecutor_office": [
      "臺灣新竹地方法院檢察署檢察官"
    ],
    "creditors": [

    ],
    "debtors": [

    ],
    "judicial_associate_officer": [

    ]
  },
  "adjudged_at": "2005-08-04",
  "created_at": "2016-02-06 22:22:29",
  "updated_at": "2016-02-06 22:22:29"
}