{
  "identify": "TPD-93-簡-1331-20040701-1",
  "court": {
    "name": "臺灣臺北地方法院",
    "code": "TPD"
  },
  "division": {
    "name": "刑事",
    "code": "M"
  },
  "year": 93,
  "word": "簡",
  "number": "1331",
  "jcheck": "1",
  "reason": "毒品危害防制條例",
  "content": "臺灣臺北地方法院刑事簡易判決                    九十三年度簡字第一三三一號\n      聲  請  人  臺灣臺北地方法院檢察署檢察官\n      被      告  甲○○\n右列被告因毒品危害防制條例案件，經檢察官聲請以簡易判決處刑（九十三年度毒偵\n字第一七五號），本院判決如左：\n    主  文\n甲○○施用第二級毒品，處有期徒刑伍月，如易科罰金以佰元折算壹日。\n    事實及理由\n一、本件被告甲○○之犯罪事實、證據及所犯法條均詳如檢察官聲請簡易判決處刑書\n    記載（如附件）。\n二、審酌被告前已有違反麻醉藥品管理條例等多項犯罪前科，有臺灣高等法院被告全\n    國前案紀錄表及臺灣臺北地方法院檢察署刑案資料查註紀錄表各一件附卷可稽，\n    素行非佳，且係施用毒品而經觀察、勒戒、戒治後，又再犯相同罪行，顯見意志\n    甚為不堅，惟其犯罪係戕害自身，尚未害及他人，所犯情節非重等一切情狀，量\n    處如主文所示之刑，並諭知易科罰金之折算標準。\n三、依刑事訴訟法第四百四十九條第一項前段、第三項、第四百五十四條第二項，毒\n    品危害防制條例第十條第二項，刑法第十一條前段、第四十一條第一項前段，罰\n    金罰鍰提高標準條例第二條，逕以簡易判決處刑如主文。\n四、如不服本件判決，得自收受送達之日起十日內，向本院提起上訴。\n中      華      民      國    九十三    年      七      月      一      日\n                                      臺灣臺北地方法院刑事第九庭\n                                          法  官  官信成\n右正本證明與原本無異。\n如不服本判決，應於送達後十日內，向本院提出上訴狀。\n                                          書記官  蔡嘉萍\n中      華      民      國    九十三    年      七      月      一      日\n附本案論罪科刑依據之法條：毒品危害防制條例第十條第二項\n毒品危害防制條例第十條\n施用第一級毒品者，處六月以上五年以下有期徒刑。\n施用第二級毒品者，處三年以下有期徒刑。\n附件：\n臺灣臺北地方法院檢察署檢察官聲請簡易判決處刑書  九十三年度毒偵字第一七五號\n     被      告  甲○○      男  四十四歲（民國○○○年○月○○○日生）\n                             住臺北市○○區○○街四三一巷三九號\n                             身分證統一編號：Ａ一二八七五一八四號\n右被告因違反毒品危害防制條例案件，業經偵查終結，認為宜以簡易判決處刑，茲將\n犯罪事實及證據並所犯法條分敘如左：\n          犯罪事實\n一、甲○○前因施用第二級毒品安非他命案件，經臺灣臺北地方法院以八十八年度毒\n    聲字第三八五號裁定送執行觀察勒戒後，因有繼續施用毒品之傾向，再由該院以\n    八十八年度毒聲字第八二六號裁定令入戒治處所施以強制戒治，後經該院再以八\n    十八年度毒聲字第二八一九號裁定停止戒治，所餘戒治期間，付保護管束，於民\n    國八十九年三月六日執行保護管束期滿，經本署檢察官於同年六月七日以八十九\n    年戒毒偵字第一六六號號為不起訴處分確定。詎甲○○猶不知悔改，強制戒治執\n    行完畢後於五年內，即於九十二年十二月十七日為本署採尿時回溯九十六小時內\n    某時，在不詳處所再施用第二級毒品安非他命，嗣因其為假釋付保護管束者，於\n    同年十七日，經本署觀護人室採集其尿液送驗結果呈第二級毒品安非他命之陽性\n    反應，始悉上情。\n二、案經本署觀護人告發偵辦。\n        證據並所犯法條\n一、證據：（一）臺灣檢驗科技股份有限公司九十二年十二月二十四日濫用藥物尿液\n    檢驗報告、本署受保護管束人尿液檢體監管紀錄表各一份。(二）本署檢察官八\n    十九年戒毒偵字第一六六號不起訴處分書、檢察官執行保護管束指揮書、臺灣宜\n    蘭監獄假釋證明書、全國刑案資料查註紀錄表、全國施用毒品案件記錄表、在監\n    所最新資料報表各一份及本署八十八年度偵字第四二一三號影卷一宗。\n二、核被告甲○○所為，係犯違反毒品危害防制條例第十條第二項施用第二級毒品罪\n    嫌。\n三、爰依毒品危害防制條例第二十三條第二項、刑事訴訟法第四百五十一條第一項等\n    規定聲請逕以簡易判決處刑。\n    此  致\n臺灣臺北地方法院\n中      華      民      國    九十三    年      三      月    二十七    日\n                                  檢  察  官    陳  重  言\n右正本證明與原本無異\n中      華      民      國    九十三    年      五      月     十四     日\n                                   書  記  官    楊  和  宗\n",
  "structure": {
    "main": "甲○○施用第二級毒品，處有期徒刑伍月，如易科罰金以佰元折算壹日。",
    "fact": "一、本件被告甲○○之犯罪事實、證據及所犯法條均詳如檢察官聲請簡易判決處刑書\n    記載（如附件）。\n二、審酌被告前已有違反麻醉藥品管理條例等多項犯罪前科，有臺灣高等法院被告全\n    國前案紀錄表及臺灣臺北地方法院檢察署刑案資料查註紀錄表各一件附卷可稽，\n    素行非佳，且係施用毒品而經觀察、勒戒、戒治後，又再犯相同罪行，顯見意志\n    甚為不堅，惟其犯罪係戕害自身，尚未害及他人，所犯情節非重等一切情狀，量\n    處如主文所示之刑，並諭知易科罰金之折算標準。\n三、依刑事訴訟法第四百四十九條第一項前段、第三項、第四百五十四條第二項，毒\n    品危害防制條例第十條第二項，刑法第十一條前段、第四十一條第一項前段，罰\n    金罰鍰提高標準條例第二條，逕以簡易判決處刑如主文。\n四、如不服本件判決，得自收受送達之日起十日內，向本院提起上訴。",
    "reason": "一、本件被告甲○○之犯罪事實、證據及所犯法條均詳如檢察官聲請簡易判決處刑書\n    記載（如附件）。\n二、審酌被告前已有違反麻醉藥品管理條例等多項犯罪前科，有臺灣高等法院被告全\n    國前案紀錄表及臺灣臺北地方法院檢察署刑案資料查註紀錄表各一件附卷可稽，\n    素行非佳，且係施用毒品而經觀察、勒戒、戒治後，又再犯相同罪行，顯見意志\n    甚為不堅，惟其犯罪係戕害自身，尚未害及他人，所犯情節非重等一切情狀，量\n    處如主文所示之刑，並諭知易科罰金之折算標準。\n三、依刑事訴訟法第四百四十九條第一項前段、第三項、第四百五十四條第二項，毒\n    品危害防制條例第十條第二項，刑法第十一條前段、第四十一條第一項前段，罰\n    金罰鍰提高標準條例第二條，逕以簡易判決處刑如主文。\n四、如不服本件判決，得自收受送達之日起十日內，向本院提起上訴。"
  },
  "search": "臺灣臺北地方法院刑事簡易判決九十三年度簡字第一三三一號聲請人臺灣臺北地方法院檢察署檢察官被告甲○○右列被告因毒品危害防制條例案件，經檢察官聲請以簡易判決處刑（九十三年度毒偵字第一七五號），本院判決如左：主文甲○○施用第二級毒品，處有期徒刑伍月，如易科罰金以佰元折算壹日。事實及理由一、本件被告甲○○之犯罪事實、證據及所犯法條均詳如檢察官聲請簡易判決處刑書記載（如附件）。二、審酌被告前已有違反麻醉藥品管理條例等多項犯罪前科，有臺灣高等法院被告全國前案紀錄表及臺灣臺北地方法院檢察署刑案資料查註紀錄表各一件附卷可稽，素行非佳，且係施用毒品而經觀察、勒戒、戒治後，又再犯相同罪行，顯見意志甚為不堅，惟其犯罪係戕害自身，尚未害及他人，所犯情節非重等一切情狀，量處如主文所示之刑，並諭知易科罰金之折算標準。三、依刑事訴訟法第四百四十九條第一項前段、第三項、第四百五十四條第二項，毒品危害防制條例第十條第二項，刑法第十一條前段、第四十一條第一項前段，罰金罰鍰提高標準條例第二條，逕以簡易判決處刑如主文。四、如不服本件判決，得自收受送達之日起十日內，向本院提起上訴。中華民國九十三年七月一日臺灣臺北地方法院刑事第九庭法官官信成右正本證明與原本無異。如不服本判決，應於送達後十日內，向本院提出上訴狀。書記官蔡嘉萍中華民國九十三年七月一日附本案論罪科刑依據之法條：毒品危害防制條例第十條第二項毒品危害防制條例第十條施用第一級毒品者，處六月以上五年以下有期徒刑。施用第二級毒品者，處三年以下有期徒刑。附件：臺灣臺北地方法院檢察署檢察官聲請簡易判決處刑書九十三年度毒偵字第一七五號被告甲○○男四十四歲（民國○○○年○月○○○日生）住臺北市○○區○○街四三一巷三九號身分證統一編號：Ａ一二八七五一八四號右被告因違反毒品危害防制條例案件，業經偵查終結，認為宜以簡易判決處刑，茲將犯罪事實及證據並所犯法條分敘如左：犯罪事實一、甲○○前因施用第二級毒品安非他命案件，經臺灣臺北地方法院以八十八年度毒聲字第三八五號裁定送執行觀察勒戒後，因有繼續施用毒品之傾向，再由該院以八十八年度毒聲字第八二六號裁定令入戒治處所施以強制戒治，後經該院再以八十八年度毒聲字第二八一九號裁定停止戒治，所餘戒治期間，付保護管束，於民國八十九年三月六日執行保護管束期滿，經本署檢察官於同年六月七日以八十九年戒毒偵字第一六六號號為不起訴處分確定。詎甲○○猶不知悔改，強制戒治執行完畢後於五年內，即於九十二年十二月十七日為本署採尿時回溯九十六小時內某時，在不詳處所再施用第二級毒品安非他命，嗣因其為假釋付保護管束者，於同年十七日，經本署觀護人室採集其尿液送驗結果呈第二級毒品安非他命之陽性反應，始悉上情。二、案經本署觀護人告發偵辦。證據並所犯法條一、證據：（一）臺灣檢驗科技股份有限公司九十二年十二月二十四日濫用藥物尿液檢驗報告、本署受保護管束人尿液檢體監管紀錄表各一份。(二）本署檢察官八十九年戒毒偵字第一六六號不起訴處分書、檢察官執行保護管束指揮書、臺灣宜蘭監獄假釋證明書、全國刑案資料查註紀錄表、全國施用毒品案件記錄表、在監所最新資料報表各一份及本署八十八年度偵字第四二一三號影卷一宗。二、核被告甲○○所為，係犯違反毒品危害防制條例第十條第二項施用第二級毒品罪嫌。三、爰依毒品危害防制條例第二十三條第二項、刑事訴訟法第四百五十一條第一項等規定聲請逕以簡易判決處刑。此致臺灣臺北地方法院中華民國九十三年三月二十七日檢察官陳重言右正本證明與原本無異中華民國九十三年五月十四日書記官楊和宗",
  "characters": {
    "judges": [
      "官信成"
    ],
    "prosecutors": [

    ],
    "lawyers": [

    ],
    "clerks": [
      "蔡嘉萍"
    ],
    "plaintiffs": [

    ],
    "defendants": [
      "甲○○",
      "右列被告因毒品危害防制條例案件，經檢察官聲請以簡易判決處刑（九十三年度毒偵",
      "字第一七五號），本院判決如左：",
      "甲○○      男  四十四歲（民國○○○年○月○○○日生）"
    ],
    "prosecutor_office": [
      "臺灣臺北地方法院檢察署檢察官"
    ],
    "creditors": [

    ],
    "debtors": [

    ],
    "judicial_associate_officer": [

    ]
  },
  "adjudged_at": "2004-07-01",
  "created_at": "2016-02-06 12:19:28",
  "updated_at": "2016-02-06 12:19:28"
}