{
  "identify": "KSD-93-簡-2675-20040609-1",
  "court": {
    "name": "臺灣高雄地方法院",
    "code": "KSD"
  },
  "division": {
    "name": "刑事",
    "code": "M"
  },
  "year": 93,
  "word": "簡",
  "number": "2675",
  "jcheck": "1",
  "reason": "竊盜",
  "content": "臺灣高雄地方法院刑事簡易判決                    九十三年度簡字第二六七五號\n    聲  請  人  臺灣高雄地方法院檢察署檢察官\n    被      告  甲○○\n右列被告因竊盜案件，經檢察官聲請以簡易判決處刑（民國九十三年度偵字第七○一\n四號），本院判決如左：\n    主  文\n甲○○竊盜，累犯，處有期徒刑參月，如易科罰金，以佰元折算壹日。\n    事實及理由\n一、本件犯罪事實及證據均引用檢察官聲請簡易判決處刑書之記載（如附件）。\n二、核被告甲○○竊取乙○○所有之行動電話之所為，係犯刑法第三百二十條第一項\n    之竊盜罪。又被告前於民國八十八年間亦因竊盜案件，經臺灣高等法院高雄分院\n    於八十九年八月三日以八十九年度上易字第四六○號刑事判決判處有期徒刑六月\n    而確定在案，並於九十二年三月二十四日入監執行完畢等情，有臺灣高雄地方法\n    院檢察署刑案資料查註紀錄表及臺灣高等法院被告全國前案紀錄表各一份附卷可\n    稽，然其竟不知悔改，於前開徒刑執行完畢後五年內，復再犯本件有期徒刑以上\n    之罪，為累犯，應依刑法第四十七條之規定，加重其刑。爰審酌被告不思努力工\n    作，以合法之手段賺取金錢購買手機，竟竊取他人之手機，行為確有不當，然念\n    其犯後已坦承犯行，所竊得之手機價值不高等一切情狀，量處如主文所示之刑，\n    並諭知易科罰金之折算標準，以示懲儆。\n三、依刑事訴訟法第四百四十九條第一項、第三項、第四百五十四條第二項，刑法第\n    三百二十條第一項、第四十七條、第四十一條第一項前段，罰金罰鍰提高標準條\n    例第一條前段、第二條，逕以簡易判決處如主文所示之刑。\n四、如不服本判決，得自收受送達之日起十日內，向本院提起上訴。\n中      華      民      國    九十三    年    六      月        九      日\n                                臺灣高雄地方法院高雄簡易庭\n                                    法  官    林靜梅\n右正本證明與原本無異。\n如不服本判決，得於判決書送達之日起十日內，以書狀敘述理由，向本庭提出上訴。\n                                    書記官    洪生輝\n中    華    民    國      九十三      年    六      月      十      日\n附錄本案論罪科刑法條：\n刑法第三百二十條第一項\n意圖為自己或第三人不法之所有，而竊取他人之動產者，為竊盜罪，處五年以下有期\n徒刑、拘役或五百元以下罰金。\n",
  "structure": {
    "main": "甲○○竊盜，累犯，處有期徒刑參月，如易科罰金，以佰元折算壹日。",
    "fact": "一、本件犯罪事實及證據均引用檢察官聲請簡易判決處刑書之記載（如附件）。\n二、核被告甲○○竊取乙○○所有之行動電話之所為，係犯刑法第三百二十條第一項\n    之竊盜罪。又被告前於民國八十八年間亦因竊盜案件，經臺灣高等法院高雄分院\n    於八十九年八月三日以八十九年度上易字第四六○號刑事判決判處有期徒刑六月\n    而確定在案，並於九十二年三月二十四日入監執行完畢等情，有臺灣高雄地方法\n    院檢察署刑案資料查註紀錄表及臺灣高等法院被告全國前案紀錄表各一份附卷可\n    稽，然其竟不知悔改，於前開徒刑執行完畢後五年內，復再犯本件有期徒刑以上\n    之罪，為累犯，應依刑法第四十七條之規定，加重其刑。爰審酌被告不思努力工\n    作，以合法之手段賺取金錢購買手機，竟竊取他人之手機，行為確有不當，然念\n    其犯後已坦承犯行，所竊得之手機價值不高等一切情狀，量處如主文所示之刑，\n    並諭知易科罰金之折算標準，以示懲儆。\n三、依刑事訴訟法第四百四十九條第一項、第三項、第四百五十四條第二項，刑法第\n    三百二十條第一項、第四十七條、第四十一條第一項前段，罰金罰鍰提高標準條\n    例第一條前段、第二條，逕以簡易判決處如主文所示之刑。\n四、如不服本判決，得自收受送達之日起十日內，向本院提起上訴。",
    "reason": "一、本件犯罪事實及證據均引用檢察官聲請簡易判決處刑書之記載（如附件）。\n二、核被告甲○○竊取乙○○所有之行動電話之所為，係犯刑法第三百二十條第一項\n    之竊盜罪。又被告前於民國八十八年間亦因竊盜案件，經臺灣高等法院高雄分院\n    於八十九年八月三日以八十九年度上易字第四六○號刑事判決判處有期徒刑六月\n    而確定在案，並於九十二年三月二十四日入監執行完畢等情，有臺灣高雄地方法\n    院檢察署刑案資料查註紀錄表及臺灣高等法院被告全國前案紀錄表各一份附卷可\n    稽，然其竟不知悔改，於前開徒刑執行完畢後五年內，復再犯本件有期徒刑以上\n    之罪，為累犯，應依刑法第四十七條之規定，加重其刑。爰審酌被告不思努力工\n    作，以合法之手段賺取金錢購買手機，竟竊取他人之手機，行為確有不當，然念\n    其犯後已坦承犯行，所竊得之手機價值不高等一切情狀，量處如主文所示之刑，\n    並諭知易科罰金之折算標準，以示懲儆。\n三、依刑事訴訟法第四百四十九條第一項、第三項、第四百五十四條第二項，刑法第\n    三百二十條第一項、第四十七條、第四十一條第一項前段，罰金罰鍰提高標準條\n    例第一條前段、第二條，逕以簡易判決處如主文所示之刑。\n四、如不服本判決，得自收受送達之日起十日內，向本院提起上訴。"
  },
  "search": "臺灣高雄地方法院刑事簡易判決九十三年度簡字第二六七五號聲請人臺灣高雄地方法院檢察署檢察官被告甲○○右列被告因竊盜案件，經檢察官聲請以簡易判決處刑（民國九十三年度偵字第七○一四號），本院判決如左：主文甲○○竊盜，累犯，處有期徒刑參月，如易科罰金，以佰元折算壹日。事實及理由一、本件犯罪事實及證據均引用檢察官聲請簡易判決處刑書之記載（如附件）。二、核被告甲○○竊取乙○○所有之行動電話之所為，係犯刑法第三百二十條第一項之竊盜罪。又被告前於民國八十八年間亦因竊盜案件，經臺灣高等法院高雄分院於八十九年八月三日以八十九年度上易字第四六○號刑事判決判處有期徒刑六月而確定在案，並於九十二年三月二十四日入監執行完畢等情，有臺灣高雄地方法院檢察署刑案資料查註紀錄表及臺灣高等法院被告全國前案紀錄表各一份附卷可稽，然其竟不知悔改，於前開徒刑執行完畢後五年內，復再犯本件有期徒刑以上之罪，為累犯，應依刑法第四十七條之規定，加重其刑。爰審酌被告不思努力工作，以合法之手段賺取金錢購買手機，竟竊取他人之手機，行為確有不當，然念其犯後已坦承犯行，所竊得之手機價值不高等一切情狀，量處如主文所示之刑，並諭知易科罰金之折算標準，以示懲儆。三、依刑事訴訟法第四百四十九條第一項、第三項、第四百五十四條第二項，刑法第三百二十條第一項、第四十七條、第四十一條第一項前段，罰金罰鍰提高標準條例第一條前段、第二條，逕以簡易判決處如主文所示之刑。四、如不服本判決，得自收受送達之日起十日內，向本院提起上訴。中華民國九十三年六月九日臺灣高雄地方法院高雄簡易庭法官林靜梅右正本證明與原本無異。如不服本判決，得於判決書送達之日起十日內，以書狀敘述理由，向本庭提出上訴。書記官洪生輝中華民國九十三年六月十日附錄本案論罪科刑法條：刑法第三百二十條第一項意圖為自己或第三人不法之所有，而竊取他人之動產者，為竊盜罪，處五年以下有期徒刑、拘役或五百元以下罰金。",
  "characters": {
    "judges": [
      "林靜梅"
    ],
    "prosecutors": [

    ],
    "lawyers": [

    ],
    "clerks": [
      "洪生輝"
    ],
    "plaintiffs": [

    ],
    "defendants": [
      "甲○○",
      "右列被告因竊盜案件，經檢察官聲請以簡易判決處刑（民國九十三年度偵字第七○一",
      "四號），本院判決如左："
    ],
    "prosecutor_office": [
      "臺灣高雄地方法院檢察署檢察官"
    ],
    "creditors": [

    ],
    "debtors": [

    ],
    "judicial_associate_officer": [

    ]
  },
  "adjudged_at": "2004-06-09",
  "created_at": "2016-02-06 08:45:37",
  "updated_at": "2016-02-06 08:45:37"
}