{
  "identify": "SLD-100-審易-911-20110714-1",
  "court": {
    "name": "臺灣士林地方法院",
    "code": "SLD"
  },
  "division": {
    "name": "刑事",
    "code": "M"
  },
  "year": 100,
  "word": "審易",
  "number": "911",
  "jcheck": "1",
  "reason": "違反性騷擾防治法",
  "content": "臺灣士林地方法院刑事判決            100年度審易字第911號\n公  訴  人  臺灣士林地方法院檢察署檢察官\n被      告  張彥煌\n上列被告因違反性騷擾防治法案件，經檢察官提起公訴（100 年\n度偵字第3604號），本院判決如下：\n    主  文\n本件公訴不受理。\n    理  由\n一、公訴意旨如附件檢察官起訴書之記載。\n二、按告訴乃論之罪，告訴人於第一審辯論終結前，得撤回其告\n    訴，又告訴經撤回者，應諭知不受理之判決，並得不經言詞\n    辯論為之，刑事訴訟法第238 條第1 項、第303 條第3 款、\n    第307 條分別定有明文。\n三、經查，本件告訴人A 男（真實姓名、年籍均詳卷）告訴被告\n    張彥煌違反性騷擾防治法案件，公訴人認被告係犯性騷擾防\n    治法第25條第1 項之性騷擾罪嫌，依同法第25條第2 項之規\n    定，須告訴乃論。茲已據告訴人A 男於民國100 年6 月10日\n    具狀撤回告訴，有刑事撤回告訴狀乙紙在卷可稽（見本院卷\n    第17頁），依照上開說明，本件爰不經言詞辯論，逕為不受\n    理之諭知。\n據上論斷，應依刑事訴訟法第303 條第3 款、第307 條，判決如\n主文。\n本案經檢察官孟玉梅到庭執行職務。\n中    華    民    國    100   年    7     月    14    日\n                  刑事第一庭法  官  洪英花\n以上正本證明與原本無異。\n如不服本判決應於收受判決後10日內向本院提出上訴書狀，並應\n敘述具體理由；其未敘述上訴理由者，應於上訴期間屆滿後20日\n內向本院補提理由書。\n                            書記官  張茹茵\n中    華    民    國    100   年    7     月    15    日",
  "structure": {
    "main": "本件公訴不受理。",
    "reason": "一、公訴意旨如附件檢察官起訴書之記載。\n二、按告訴乃論之罪，告訴人於第一審辯論終結前，得撤回其告\n    訴，又告訴經撤回者，應諭知不受理之判決，並得不經言詞\n    辯論為之，刑事訴訟法第238 條第1 項、第303 條第3 款、\n    第307 條分別定有明文。\n三、經查，本件告訴人A 男（真實姓名、年籍均詳卷）告訴被告\n    張彥煌違反性騷擾防治法案件，公訴人認被告係犯性騷擾防\n    治法第25條第1 項之性騷擾罪嫌，依同法第25條第2 項之規\n    定，須告訴乃論。茲已據告訴人A 男於民國100 年6 月10日\n    具狀撤回告訴，有刑事撤回告訴狀乙紙在卷可稽（見本院卷\n    第17頁），依照上開說明，本件爰不經言詞辯論，逕為不受\n    理之諭知。\n據上論斷，應依刑事訴訟法第303 條第3 款、第307 條，判決如\n主文。\n本案經檢察官孟玉梅到庭執行職務。"
  },
  "search": "臺灣士林地方法院刑事判決100年度審易字第911號公訴人臺灣士林地方法院檢察署檢察官被告張彥煌上列被告因違反性騷擾防治法案件，經檢察官提起公訴（100年度偵字第3604號），本院判決如下：主文本件公訴不受理。理由一、公訴意旨如附件檢察官起訴書之記載。二、按告訴乃論之罪，告訴人於第一審辯論終結前，得撤回其告訴，又告訴經撤回者，應諭知不受理之判決，並得不經言詞辯論為之，刑事訴訟法第238條第1項、第303條第3款、第307條分別定有明文。三、經查，本件告訴人A男（真實姓名、年籍均詳卷）告訴被告張彥煌違反性騷擾防治法案件，公訴人認被告係犯性騷擾防治法第25條第1項之性騷擾罪嫌，依同法第25條第2項之規定，須告訴乃論。茲已據告訴人A男於民國100年6月10日具狀撤回告訴，有刑事撤回告訴狀乙紙在卷可稽（見本院卷第17頁），依照上開說明，本件爰不經言詞辯論，逕為不受理之諭知。據上論斷，應依刑事訴訟法第303條第3款、第307條，判決如主文。本案經檢察官孟玉梅到庭執行職務。中華民國100年7月14日刑事第一庭法官洪英花以上正本證明與原本無異。如不服本判決應於收受判決後10日內向本院提出上訴書狀，並應敘述具體理由；其未敘述上訴理由者，應於上訴期間屆滿後20日內向本院補提理由書。書記官張茹茵中華民國100年7月15日",
  "characters": {
    "judges": [
      "洪英花"
    ],
    "prosecutors": [
      "孟玉梅"
    ],
    "lawyers": [

    ],
    "clerks": [
      "張茹茵"
    ],
    "plaintiffs": [

    ],
    "defendants": [
      "張彥煌"
    ],
    "prosecutor_office": [
      "臺灣士林地方法院檢察署檢察官"
    ],
    "creditors": [

    ],
    "debtors": [

    ],
    "judicial_associate_officer": [

    ]
  },
  "adjudged_at": "2011-07-14",
  "created_at": "2016-02-14 00:34:45",
  "updated_at": "2016-02-14 00:34:45"
}