{
  "identify": "TCD-100-中簡-1694-20110714-1",
  "court": {
    "name": "臺灣臺中地方法院",
    "code": "TCD"
  },
  "division": {
    "name": "刑事",
    "code": "M"
  },
  "year": 100,
  "word": "中簡",
  "number": "1694",
  "jcheck": "1",
  "reason": "詐欺",
  "content": "臺灣臺中地方法院刑事簡易判決       100年度中簡字第1694號\n聲  請  人  臺灣臺中地方法院檢察署檢察官\n被      告  葉易鑫\n上列被告因詐欺案件，經檢察官聲請以簡易判決處刑（100年度\n偵字第6489號），本院判決如下：\n    主  文\n葉易鑫幫助意圖為自己不法之所有，以詐術使人將本人之物交付\n，處有期徒刑肆月，如易科罰金，以新臺幣壹仟元折算壹日。\n    事實及理由\n一、本件除於犯罪事實欄一、(二)被害人張敬釩匯款時間應更正為\n    「10時17分許」外，其餘犯罪事實、證據及應適用之法條，\n    均引用附件檢察官聲請簡易判決處刑書之記載。\n二、爰審酌被告葉易鑫為國中畢業擔任工人之男子，因需款孔急\n    ，竟任意將其渣打國際商業銀行文心分行帳戶存摺、金融卡\n    及密碼提供予自稱「阿肥」及其所屬之詐欺集團使用，助長\n    詐騙財產犯罪之風氣，造成無辜受騙民眾受有金錢損失，執\n    法人員亦難以追查詐騙集團成員之真實身分，並實際造成被\n    害人呂文華新臺幣（下同）53,000元、張敬釩74,000元、黃\n    淞豐43,000元之損害非輕，且犯後仍否認犯行，亦未賠償被\n    害人損失，態度難謂良好等一切情狀，量處如主文所示之刑\n    ，並諭知易科罰金之折算標準。\n三、依刑事訴訟法第第449條第1項前段、第454條第2項，刑法第\n    30條第1項前段、第2項、第339條第1項、第41條第1項前段\n    ，刑法施行法第1條之1，逕以簡易判決處刑如主文。\n四、如不服本件判決，得附繕本自收受送達之日起10日內，向本\n    院提起上訴。\n中    華    民    國   100    年    7     月    14    日\n                  臺中簡易庭   法  官  蕭一弘\n以上正本證明與原本無異。\n如不服本判決，應於收受送達後10日內向本院提出上訴書狀（應\n附繕本）。\n                               書記官   黃士益\n中    華    民    國   100    年    7     月    14    日\n附錄本案所犯法條全文\n中華民國刑法第339條：\n意圖為自己或第三人不法之所有，以詐術使人將本人或第三人之\n物交付者，處5年以下有期徒刑、拘役或科或併科1千元以下罰金\n。\n以前項方法得財產上不法之利益或使第三人得之者，亦同。\n前二項之未遂犯罰之。\n附件：\n臺灣臺中地方法院檢察署檢察官聲請簡易判決處刑書      興股\n                                     100年度偵字第6489號\n    被      告  葉易鑫  男  27歲（民國○○年○月○○日生）\n                        住臺中市○○區○○路1段192之33號\n                        2樓之1\n                        國民身分證統一編號：Ｚ000000000號\n上列被告因詐欺案件，業經偵查終結，認為宜聲請以簡易判決處\n刑，茲將犯罪事實及證據並所犯法條分敘如下：\n        犯罪事實\n一、葉易鑫能預見其提供帳戶予不相識之人使用，可能幫助不詳\n    之犯罪集團掩飾其自己犯罪所得財物，竟仍不違其本意，而\n    基於幫助他人違犯詐欺犯行之犯意，於民國99年7、8月間之\n    某日，在臺中市○○區○○路「建功公園」內，將其所申辦\n    之渣打國際商業銀行文心分行開設之帳戶（帳號：000-0000\n    000000000號）之存摺、提款卡及密碼，交付與某真實姓名\n    、年籍不詳，自稱「阿肥」之人，供作該犯罪集團成員為詐\n    欺犯行時之帳戶，以此方式幫助該犯罪集團成員遂行詐欺犯\n    行。嗣該犯罪集團遂分別於下列時、地，為詐騙犯行：\n  (一)於99年12月22日下午5時21分許，該詐騙集團成員以電話向\n    呂文華佯稱為「奇摩拍賣」賣家，因呂文華之前匯款之帳號\n    為分期付款專用，要依照其指示才不會被自動扣款云云，致\n    呂文華陷於錯誤，遂於同日晚上10時2分許，匯款新臺幣（\n    下同）5萬3000元至葉易鑫申辦之上開帳戶內，隨即遭詐騙\n    集團成員提領一空；\n  (二)於99年12月22日晚上6時46分許，該詐騙集團成員以電話向\n    張敬釩佯稱因張敬釩先前在網路上購買410元之商品，而所\n    簽名欄位為12期連續扣款410元，若要取消這筆交易需提供\n    個人帳戶，致張敬釩陷於錯誤，遂於同日晚上10時22分許，\n    匯款7萬4000元至葉易鑫申辦之上開帳戶內，隨即遭詐騙集\n    團成員提領一空；\n  (三)於99年12月22日晚上7時19分許，該詐騙集團成員以電話向\n    黃淞豐佯稱其為「郵局人員」，並自稱「陳嘉琪」，因先前\n    黃淞豐網購匯款操作錯誤成分期付款，要求其取消付款轉帳\n    作業，致黃淞豐陷於錯誤，於同日晚上8時53分許，匯款4萬\n    3000元至葉易鑫申辦之上開帳戶內，隨即遭詐騙集團成員提\n    領一空。\n    嗣經呂文華、張敬釩、黃淞豐發覺可疑，報警處理而循線查\n    獲。\n二、案經臺中市政府警察局霧峰分局報告偵辦。\n        證據並所犯法條\n一、訊據被告葉易鑫矢口否認有何詐欺犯行，辯稱略以：「因為\n    之前要辦貸款，信用不好，我去找報紙的貸款，對方說貸款\n    百分之百會過。他還說帳號存簿跟提款卡要給他。他還說辦\n    下來會有佣金。我也給他提款卡密碼了」云云。惟查：上開\n    犯罪事實，業據被害人呂文華、張敬釩、黃淞豐於警詢時指\n    訴在卷，並有被害人匯款之渣打國際商業銀行自動櫃員機交\n    易明細表數紙、渣打國際商業銀行股份有限公司文心分行\n    100年 1月26日渣打商銀SCB文心字第1000000003號函及其附\n    件附卷可稽。則上開被害人均遭詐騙集團成員詐騙，並將上\n    開款項匯款入被告所申設之上開帳戶等情，堪已認定。而被\n    告雖辯稱係因申辦貸款而提供帳戶，然竟於警詢時表示「對\n    方電話我忘記了」等語，而無法提供對方資料，則被告所言\n    是否與真實相符，容有可疑。況縱認被告所辯屬實，然被告\n    於警詢時表示略以：「對方跟我說要貸款多少，我就跟對方\n    說要貸款新臺幣20萬元，對方說可以，要求我需提供提款卡\n    比較快核准，約一星期後可以核准貸款金額」等語，經本署\n    庭詢時詢問被告何意，被告竟表示「他說卡給他貸款比較好\n    過」、「我不瞭解」等語，以提款卡係帳戶內金錢之提領工\n    具，顯與貸款無關；並參以被告自承之前曾向銀行貸款時未\n    曾提供提款卡、且也怕對方拿提款卡作為犯罪使用等情，是\n    被告應可預見提款卡提供他人使用將幫助他人實施詐欺犯罪\n    ，但因需款孔急，仍將其帳戶存摺、提款卡交付他人，顯具\n    縱有人以其金融帳戶實施詐欺犯罪亦不違背其本意之幫助意\n    思甚明。是被告所辯，委無可採。本件事證明確，被告犯嫌\n    堪以認定。\n二、核被告所為，係犯刑法第30條第1項、第339條第1項之幫助\n    詐欺罪嫌。\n三、依刑事訴訟法第451條第1項聲請逕以簡易判決處刑。\n    此    致\n臺灣臺中地方法院\n中    華    民    國   100    年    6     月    15    日\n                              檢  察  官      林  蓉  蓉\n本件正本證明與原本無異\n中    華    民    國   100    年    6     月    24    日\n                              書  記  官      羅  文  宏\n附錄本案所犯法條全文\n中華民國刑法第339條\n意圖為自己或第三人不法之所有，以詐術使人將本人或第三人之\n物交付者，處5年以下有期徒刑、拘役或科或併科1千元以下罰金\n。\n以前項方法得財產上不法之利益或使第三人得之者，亦同。\n前二項之未遂犯罰之。\n當事人注意事項：\n（一）本件係依據刑事訴訟法簡易程序辦理，法院簡易庭得不傳\n      喚被告、輔佐人、告訴人、告發人等出庭即以簡易判決處\n      刑。\n（二）被告、告訴人、被害人對告訴乃論案件，得儘速試行和解\n      ，如已達成民事和解而要撤回告訴，請告訴人寄送撤回告\n      訴狀至臺灣臺中地方法院簡易庭。\n（三）被告、告訴人、被害人對本案案件認有受傳喚到庭陳述意\n      見之必要時，請即以書狀向臺灣臺中地方法院簡易庭陳明\n      。",
  "structure": {
    "main": "葉易鑫幫助意圖為自己不法之所有，以詐術使人將本人之物交付\n，處有期徒刑肆月，如易科罰金，以新臺幣壹仟元折算壹日。",
    "fact": "一、本件除於犯罪事實欄一、(二)被害人張敬釩匯款時間應更正為\n    「10時17分許」外，其餘犯罪事實、證據及應適用之法條，\n    均引用附件檢察官聲請簡易判決處刑書之記載。\n二、爰審酌被告葉易鑫為國中畢業擔任工人之男子，因需款孔急\n    ，竟任意將其渣打國際商業銀行文心分行帳戶存摺、金融卡\n    及密碼提供予自稱「阿肥」及其所屬之詐欺集團使用，助長\n    詐騙財產犯罪之風氣，造成無辜受騙民眾受有金錢損失，執\n    法人員亦難以追查詐騙集團成員之真實身分，並實際造成被\n    害人呂文華新臺幣（下同）53,000元、張敬釩74,000元、黃\n    淞豐43,000元之損害非輕，且犯後仍否認犯行，亦未賠償被\n    害人損失，態度難謂良好等一切情狀，量處如主文所示之刑\n    ，並諭知易科罰金之折算標準。\n三、依刑事訴訟法第第449條第1項前段、第454條第2項，刑法第\n    30條第1項前段、第2項、第339條第1項、第41條第1項前段\n    ，刑法施行法第1條之1，逕以簡易判決處刑如主文。\n四、如不服本件判決，得附繕本自收受送達之日起10日內，向本\n    院提起上訴。",
    "reason": "一、本件除於犯罪事實欄一、(二)被害人張敬釩匯款時間應更正為\n    「10時17分許」外，其餘犯罪事實、證據及應適用之法條，\n    均引用附件檢察官聲請簡易判決處刑書之記載。\n二、爰審酌被告葉易鑫為國中畢業擔任工人之男子，因需款孔急\n    ，竟任意將其渣打國際商業銀行文心分行帳戶存摺、金融卡\n    及密碼提供予自稱「阿肥」及其所屬之詐欺集團使用，助長\n    詐騙財產犯罪之風氣，造成無辜受騙民眾受有金錢損失，執\n    法人員亦難以追查詐騙集團成員之真實身分，並實際造成被\n    害人呂文華新臺幣（下同）53,000元、張敬釩74,000元、黃\n    淞豐43,000元之損害非輕，且犯後仍否認犯行，亦未賠償被\n    害人損失，態度難謂良好等一切情狀，量處如主文所示之刑\n    ，並諭知易科罰金之折算標準。\n三、依刑事訴訟法第第449條第1項前段、第454條第2項，刑法第\n    30條第1項前段、第2項、第339條第1項、第41條第1項前段\n    ，刑法施行法第1條之1，逕以簡易判決處刑如主文。\n四、如不服本件判決，得附繕本自收受送達之日起10日內，向本\n    院提起上訴。"
  },
  "search": "臺灣臺中地方法院刑事簡易判決100年度中簡字第1694號聲請人臺灣臺中地方法院檢察署檢察官被告葉易鑫上列被告因詐欺案件，經檢察官聲請以簡易判決處刑（100年度偵字第6489號），本院判決如下：主文葉易鑫幫助意圖為自己不法之所有，以詐術使人將本人之物交付，處有期徒刑肆月，如易科罰金，以新臺幣壹仟元折算壹日。事實及理由一、本件除於犯罪事實欄一、(二)被害人張敬釩匯款時間應更正為「10時17分許」外，其餘犯罪事實、證據及應適用之法條，均引用附件檢察官聲請簡易判決處刑書之記載。二、爰審酌被告葉易鑫為國中畢業擔任工人之男子，因需款孔急，竟任意將其渣打國際商業銀行文心分行帳戶存摺、金融卡及密碼提供予自稱「阿肥」及其所屬之詐欺集團使用，助長詐騙財產犯罪之風氣，造成無辜受騙民眾受有金錢損失，執法人員亦難以追查詐騙集團成員之真實身分，並實際造成被害人呂文華新臺幣（下同）53,000元、張敬釩74,000元、黃淞豐43,000元之損害非輕，且犯後仍否認犯行，亦未賠償被害人損失，態度難謂良好等一切情狀，量處如主文所示之刑，並諭知易科罰金之折算標準。三、依刑事訴訟法第第449條第1項前段、第454條第2項，刑法第30條第1項前段、第2項、第339條第1項、第41條第1項前段，刑法施行法第1條之1，逕以簡易判決處刑如主文。四、如不服本件判決，得附繕本自收受送達之日起10日內，向本院提起上訴。中華民國100年7月14日臺中簡易庭法官蕭一弘以上正本證明與原本無異。如不服本判決，應於收受送達後10日內向本院提出上訴書狀（應附繕本）。書記官黃士益中華民國100年7月14日附錄本案所犯法條全文中華民國刑法第339條：意圖為自己或第三人不法之所有，以詐術使人將本人或第三人之物交付者，處5年以下有期徒刑、拘役或科或併科1千元以下罰金。以前項方法得財產上不法之利益或使第三人得之者，亦同。前二項之未遂犯罰之。附件：臺灣臺中地方法院檢察署檢察官聲請簡易判決處刑書興股100年度偵字第6489號被告葉易鑫男27歲（民國○○年○月○○日生）住臺中市○○區○○路1段192之33號2樓之1國民身分證統一編號：Ｚ000000000號上列被告因詐欺案件，業經偵查終結，認為宜聲請以簡易判決處刑，茲將犯罪事實及證據並所犯法條分敘如下：犯罪事實一、葉易鑫能預見其提供帳戶予不相識之人使用，可能幫助不詳之犯罪集團掩飾其自己犯罪所得財物，竟仍不違其本意，而基於幫助他人違犯詐欺犯行之犯意，於民國99年7、8月間之某日，在臺中市○○區○○路「建功公園」內，將其所申辦之渣打國際商業銀行文心分行開設之帳戶（帳號：000-0000000000000號）之存摺、提款卡及密碼，交付與某真實姓名、年籍不詳，自稱「阿肥」之人，供作該犯罪集團成員為詐欺犯行時之帳戶，以此方式幫助該犯罪集團成員遂行詐欺犯行。嗣該犯罪集團遂分別於下列時、地，為詐騙犯行：(一)於99年12月22日下午5時21分許，該詐騙集團成員以電話向呂文華佯稱為「奇摩拍賣」賣家，因呂文華之前匯款之帳號為分期付款專用，要依照其指示才不會被自動扣款云云，致呂文華陷於錯誤，遂於同日晚上10時2分許，匯款新臺幣（下同）5萬3000元至葉易鑫申辦之上開帳戶內，隨即遭詐騙集團成員提領一空；(二)於99年12月22日晚上6時46分許，該詐騙集團成員以電話向張敬釩佯稱因張敬釩先前在網路上購買410元之商品，而所簽名欄位為12期連續扣款410元，若要取消這筆交易需提供個人帳戶，致張敬釩陷於錯誤，遂於同日晚上10時22分許，匯款7萬4000元至葉易鑫申辦之上開帳戶內，隨即遭詐騙集團成員提領一空；(三)於99年12月22日晚上7時19分許，該詐騙集團成員以電話向黃淞豐佯稱其為「郵局人員」，並自稱「陳嘉琪」，因先前黃淞豐網購匯款操作錯誤成分期付款，要求其取消付款轉帳作業，致黃淞豐陷於錯誤，於同日晚上8時53分許，匯款4萬3000元至葉易鑫申辦之上開帳戶內，隨即遭詐騙集團成員提領一空。嗣經呂文華、張敬釩、黃淞豐發覺可疑，報警處理而循線查獲。二、案經臺中市政府警察局霧峰分局報告偵辦。證據並所犯法條一、訊據被告葉易鑫矢口否認有何詐欺犯行，辯稱略以：「因為之前要辦貸款，信用不好，我去找報紙的貸款，對方說貸款百分之百會過。他還說帳號存簿跟提款卡要給他。他還說辦下來會有佣金。我也給他提款卡密碼了」云云。惟查：上開犯罪事實，業據被害人呂文華、張敬釩、黃淞豐於警詢時指訴在卷，並有被害人匯款之渣打國際商業銀行自動櫃員機交易明細表數紙、渣打國際商業銀行股份有限公司文心分行100年1月26日渣打商銀SCB文心字第1000000003號函及其附件附卷可稽。則上開被害人均遭詐騙集團成員詐騙，並將上開款項匯款入被告所申設之上開帳戶等情，堪已認定。而被告雖辯稱係因申辦貸款而提供帳戶，然竟於警詢時表示「對方電話我忘記了」等語，而無法提供對方資料，則被告所言是否與真實相符，容有可疑。況縱認被告所辯屬實，然被告於警詢時表示略以：「對方跟我說要貸款多少，我就跟對方說要貸款新臺幣20萬元，對方說可以，要求我需提供提款卡比較快核准，約一星期後可以核准貸款金額」等語，經本署庭詢時詢問被告何意，被告竟表示「他說卡給他貸款比較好過」、「我不瞭解」等語，以提款卡係帳戶內金錢之提領工具，顯與貸款無關；並參以被告自承之前曾向銀行貸款時未曾提供提款卡、且也怕對方拿提款卡作為犯罪使用等情，是被告應可預見提款卡提供他人使用將幫助他人實施詐欺犯罪，但因需款孔急，仍將其帳戶存摺、提款卡交付他人，顯具縱有人以其金融帳戶實施詐欺犯罪亦不違背其本意之幫助意思甚明。是被告所辯，委無可採。本件事證明確，被告犯嫌堪以認定。二、核被告所為，係犯刑法第30條第1項、第339條第1項之幫助詐欺罪嫌。三、依刑事訴訟法第451條第1項聲請逕以簡易判決處刑。此致臺灣臺中地方法院中華民國100年6月15日檢察官林蓉蓉本件正本證明與原本無異中華民國100年6月24日書記官羅文宏附錄本案所犯法條全文中華民國刑法第339條意圖為自己或第三人不法之所有，以詐術使人將本人或第三人之物交付者，處5年以下有期徒刑、拘役或科或併科1千元以下罰金。以前項方法得財產上不法之利益或使第三人得之者，亦同。前二項之未遂犯罰之。當事人注意事項：（一）本件係依據刑事訴訟法簡易程序辦理，法院簡易庭得不傳喚被告、輔佐人、告訴人、告發人等出庭即以簡易判決處刑。（二）被告、告訴人、被害人對告訴乃論案件，得儘速試行和解，如已達成民事和解而要撤回告訴，請告訴人寄送撤回告訴狀至臺灣臺中地方法院簡易庭。（三）被告、告訴人、被害人對本案案件認有受傳喚到庭陳述意見之必要時，請即以書狀向臺灣臺中地方法院簡易庭陳明。",
  "characters": {
    "judges": [
      "蕭一弘"
    ],
    "prosecutors": [

    ],
    "lawyers": [

    ],
    "clerks": [
      "黃士益"
    ],
    "plaintiffs": [

    ],
    "defendants": [
      "葉易鑫",
      "葉易鑫  男  27歲（民國○○年○月○○日生）"
    ],
    "prosecutor_office": [
      "臺灣臺中地方法院檢察署檢察官"
    ],
    "creditors": [

    ],
    "debtors": [

    ],
    "judicial_associate_officer": [

    ]
  },
  "adjudged_at": "2011-07-14",
  "created_at": "2016-02-14 00:25:02",
  "updated_at": "2016-02-14 00:25:02"
}