{
  "identify": "TPD-100-交易-230-20110714-1",
  "court": {
    "name": "臺灣臺北地方法院",
    "code": "TPD"
  },
  "division": {
    "name": "刑事",
    "code": "M"
  },
  "year": 100,
  "word": "交易",
  "number": "230",
  "jcheck": "1",
  "reason": "過失傷害",
  "content": "臺灣臺北地方法院刑事判決            100年度交易字第230號\n公  訴  人  臺灣臺北地方法院檢察署檢察官\n被      告  馬詩祺\n上列被告因過失傷害案件，經檢察官提起公訴（100 年度調偵字\n第414 號），本院判決如下：\n    主  文\n本件公訴不受理。\n    理  由\n一、公訴意旨如起訴書所載 （如附件） 。\n二、按告訴乃論之罪，告訴人於第一審辯論終結前得撤回其告訴\n    ，又告訴經撤回者，法院應諭知不受理之判決，刑事訴訟法\n    第238 條第1 項、第303 條第3 款定有明文。\n三、經查，本件被告馬詩祺因過失傷害案件，經檢察官提起公訴\n    ，認係犯刑法第284 條第1 項前段之普通過失傷害罪（起訴\n    書雖引用刑法第284 條第2 項之業務過失傷害罪嫌，惟已經\n    本案蒞庭檢察官當庭更正為刑法第284 條第1 項前段之普通\n    過失傷害罪嫌，應予敘明），依同法第287 條前段規定，須\n    告訴乃論。茲據告訴人鄭錦松於民國100 年7 月7 日具狀撤\n    回本件告訴，有刑事撤回告訴狀1 份在卷可稽。依上說明，\n    爰不經言詞辯論，逕為不受理之諭知。\n據上論斷，應依刑事訴訟法第303 條第3 款、第307 條，判決如\n主文。\n中    華    民    國   100    年    7     月    14    日\n                          臺灣臺北地方法院刑事第十七庭\n                                      法  官  賴淑美\n上正本證明與原本無異。\n如不服本判決應於收受送達後10日內向本院提出上訴書狀，並應\n敘述具體理由；其未敘述上訴理由者，應於上訴期間屆滿後20日\n內向本院補提理由書（均須按他造當事人之人數附繕本）「切勿\n逕送上級法院」。告訴人或被害人如對於本判決不服者，應具備\n理由請求檢察官上訴，其上訴期間之計算係以檢察官收受判決正\n本之日期為準。\n                                      書記官  許翠燕\n中    華    民    國   100    年    7     月    15    日",
  "structure": {
    "main": "本件公訴不受理。",
    "reason": "一、公訴意旨如起訴書所載 （如附件） 。\n二、按告訴乃論之罪，告訴人於第一審辯論終結前得撤回其告訴\n    ，又告訴經撤回者，法院應諭知不受理之判決，刑事訴訟法\n    第238 條第1 項、第303 條第3 款定有明文。\n三、經查，本件被告馬詩祺因過失傷害案件，經檢察官提起公訴\n    ，認係犯刑法第284 條第1 項前段之普通過失傷害罪（起訴\n    書雖引用刑法第284 條第2 項之業務過失傷害罪嫌，惟已經\n    本案蒞庭檢察官當庭更正為刑法第284 條第1 項前段之普通\n    過失傷害罪嫌，應予敘明），依同法第287 條前段規定，須\n    告訴乃論。茲據告訴人鄭錦松於民國100 年7 月7 日具狀撤\n    回本件告訴，有刑事撤回告訴狀1 份在卷可稽。依上說明，\n    爰不經言詞辯論，逕為不受理之諭知。\n據上論斷，應依刑事訴訟法第303 條第3 款、第307 條，判決如\n主文。"
  },
  "search": "臺灣臺北地方法院刑事判決100年度交易字第230號公訴人臺灣臺北地方法院檢察署檢察官被告馬詩祺上列被告因過失傷害案件，經檢察官提起公訴（100年度調偵字第414號），本院判決如下：主文本件公訴不受理。理由一、公訴意旨如起訴書所載（如附件）。二、按告訴乃論之罪，告訴人於第一審辯論終結前得撤回其告訴，又告訴經撤回者，法院應諭知不受理之判決，刑事訴訟法第238條第1項、第303條第3款定有明文。三、經查，本件被告馬詩祺因過失傷害案件，經檢察官提起公訴，認係犯刑法第284條第1項前段之普通過失傷害罪（起訴書雖引用刑法第284條第2項之業務過失傷害罪嫌，惟已經本案蒞庭檢察官當庭更正為刑法第284條第1項前段之普通過失傷害罪嫌，應予敘明），依同法第287條前段規定，須告訴乃論。茲據告訴人鄭錦松於民國100年7月7日具狀撤回本件告訴，有刑事撤回告訴狀1份在卷可稽。依上說明，爰不經言詞辯論，逕為不受理之諭知。據上論斷，應依刑事訴訟法第303條第3款、第307條，判決如主文。中華民國100年7月14日臺灣臺北地方法院刑事第十七庭法官賴淑美上正本證明與原本無異。如不服本判決應於收受送達後10日內向本院提出上訴書狀，並應敘述具體理由；其未敘述上訴理由者，應於上訴期間屆滿後20日內向本院補提理由書（均須按他造當事人之人數附繕本）「切勿逕送上級法院」。告訴人或被害人如對於本判決不服者，應具備理由請求檢察官上訴，其上訴期間之計算係以檢察官收受判決正本之日期為準。書記官許翠燕中華民國100年7月15日",
  "characters": {
    "judges": [
      "賴淑美"
    ],
    "prosecutors": [

    ],
    "lawyers": [

    ],
    "clerks": [
      "許翠燕"
    ],
    "plaintiffs": [

    ],
    "defendants": [
      "馬詩祺"
    ],
    "prosecutor_office": [
      "臺灣臺北地方法院檢察署檢察官"
    ],
    "creditors": [

    ],
    "debtors": [

    ],
    "judicial_associate_officer": [

    ]
  },
  "adjudged_at": "2011-07-14",
  "created_at": "2016-02-14 00:36:41",
  "updated_at": "2016-02-14 00:36:41"
}