{
  "identify": "TYD-100-桃簡-1679-20110714-1",
  "court": {
    "name": "臺灣桃園地方法院",
    "code": "TYD"
  },
  "division": {
    "name": "刑事",
    "code": "M"
  },
  "year": 100,
  "word": "桃簡",
  "number": "1679",
  "jcheck": "1",
  "reason": "侵占",
  "content": "臺灣桃園地方法院刑事簡易判決       100年度桃簡字第1679號\n聲  請  人  臺灣桃園地方法院檢察署檢察官\n被      告  彭顗文原名彭春芳.\n上列被告因侵占案件，經檢察官聲請以簡易判決處刑（100年度\n偵字第13156 號），本院判決如下：\n    主      文\n彭顗文意圖為自己不法之所有，而侵占遺失物，處罰金新臺幣伍\n仟元，如易服勞役，以新臺幣壹仟元折算壹日。\n    事實及理由\n一、本件犯罪事實及證據，均引用檢察官聲請簡易判決處刑書（\n    如附件）之記載。\n二、核被告所為，係犯刑法第337 條之侵占遺失物罪。本件被告\n    所侵占之名片夾等物，係屬被害人遺失之物，業據被害人傅\n    震華於警詢中證述綦詳，是核其所為，係犯刑法第337 條之\n    侵占遺失物罪，聲請人認係犯侵占離本人所持有之物罪，容\n    有未洽。爰審酌被告所侵占之物品價值非鉅，且遺失物已由\n    被害人領回，犯罪後坦承犯行，犯後態度尚可及犯罪動機、\n    目的、手段暨犯罪所生之侵害等一切情狀，量處如主文所示\n    之刑，並諭知易服勞役之折算標準，以示懲儆。\n三、依刑事訴訟法第449 條第1 項前段、第3 項、第454 條第2\n    項，刑法第337 條、第42條第3 項前段，刑法施行法第1 條\n    之1 第1 項、第2 項前段，逕以簡易判決處刑如主文。\n四、如不服本判決，得於判決書送達之翌日起10日內，以書狀敘\n    述理由，向本院提出上訴。\n中    華    民    國    100     年    7     月   14   日\n                              刑事第二庭  法  官  李麗珍\n以上正本證明與原本無異。\n如不服本判決，得於判決書送達之翌日起10日內，以書狀敘述理\n由，向本庭提出上訴（應附繕本）。\n                                          書記官  李靜華\n中    華    民    國   100    年    8     月    3     日\n附錄法條:\n中華民國刑法第337條\n（侵占遺失物罪）\n意圖為自己或第三人不法之所有，而侵占遺失物、漂流物或其他\n離本人所持有之物者，處 5 百元以下罰金。",
  "structure": {
    "main": "彭顗文意圖為自己不法之所有，而侵占遺失物，處罰金新臺幣伍\n仟元，如易服勞役，以新臺幣壹仟元折算壹日。",
    "fact": "一、本件犯罪事實及證據，均引用檢察官聲請簡易判決處刑書（\n    如附件）之記載。\n二、核被告所為，係犯刑法第337 條之侵占遺失物罪。本件被告\n    所侵占之名片夾等物，係屬被害人遺失之物，業據被害人傅\n    震華於警詢中證述綦詳，是核其所為，係犯刑法第337 條之\n    侵占遺失物罪，聲請人認係犯侵占離本人所持有之物罪，容\n    有未洽。爰審酌被告所侵占之物品價值非鉅，且遺失物已由\n    被害人領回，犯罪後坦承犯行，犯後態度尚可及犯罪動機、\n    目的、手段暨犯罪所生之侵害等一切情狀，量處如主文所示\n    之刑，並諭知易服勞役之折算標準，以示懲儆。\n三、依刑事訴訟法第449 條第1 項前段、第3 項、第454 條第2\n    項，刑法第337 條、第42條第3 項前段，刑法施行法第1 條\n    之1 第1 項、第2 項前段，逕以簡易判決處刑如主文。\n四、如不服本判決，得於判決書送達之翌日起10日內，以書狀敘\n    述理由，向本院提出上訴。",
    "reason": "一、本件犯罪事實及證據，均引用檢察官聲請簡易判決處刑書（\n    如附件）之記載。\n二、核被告所為，係犯刑法第337 條之侵占遺失物罪。本件被告\n    所侵占之名片夾等物，係屬被害人遺失之物，業據被害人傅\n    震華於警詢中證述綦詳，是核其所為，係犯刑法第337 條之\n    侵占遺失物罪，聲請人認係犯侵占離本人所持有之物罪，容\n    有未洽。爰審酌被告所侵占之物品價值非鉅，且遺失物已由\n    被害人領回，犯罪後坦承犯行，犯後態度尚可及犯罪動機、\n    目的、手段暨犯罪所生之侵害等一切情狀，量處如主文所示\n    之刑，並諭知易服勞役之折算標準，以示懲儆。\n三、依刑事訴訟法第449 條第1 項前段、第3 項、第454 條第2\n    項，刑法第337 條、第42條第3 項前段，刑法施行法第1 條\n    之1 第1 項、第2 項前段，逕以簡易判決處刑如主文。\n四、如不服本判決，得於判決書送達之翌日起10日內，以書狀敘\n    述理由，向本院提出上訴。"
  },
  "search": "臺灣桃園地方法院刑事簡易判決100年度桃簡字第1679號聲請人臺灣桃園地方法院檢察署檢察官被告彭顗文原名彭春芳.上列被告因侵占案件，經檢察官聲請以簡易判決處刑（100年度偵字第13156號），本院判決如下：主文彭顗文意圖為自己不法之所有，而侵占遺失物，處罰金新臺幣伍仟元，如易服勞役，以新臺幣壹仟元折算壹日。事實及理由一、本件犯罪事實及證據，均引用檢察官聲請簡易判決處刑書（如附件）之記載。二、核被告所為，係犯刑法第337條之侵占遺失物罪。本件被告所侵占之名片夾等物，係屬被害人遺失之物，業據被害人傅震華於警詢中證述綦詳，是核其所為，係犯刑法第337條之侵占遺失物罪，聲請人認係犯侵占離本人所持有之物罪，容有未洽。爰審酌被告所侵占之物品價值非鉅，且遺失物已由被害人領回，犯罪後坦承犯行，犯後態度尚可及犯罪動機、目的、手段暨犯罪所生之侵害等一切情狀，量處如主文所示之刑，並諭知易服勞役之折算標準，以示懲儆。三、依刑事訴訟法第449條第1項前段、第3項、第454條第2項，刑法第337條、第42條第3項前段，刑法施行法第1條之1第1項、第2項前段，逕以簡易判決處刑如主文。四、如不服本判決，得於判決書送達之翌日起10日內，以書狀敘述理由，向本院提出上訴。中華民國100年7月14日刑事第二庭法官李麗珍以上正本證明與原本無異。如不服本判決，得於判決書送達之翌日起10日內，以書狀敘述理由，向本庭提出上訴（應附繕本）。書記官李靜華中華民國100年8月3日附錄法條:中華民國刑法第337條（侵占遺失物罪）意圖為自己或第三人不法之所有，而侵占遺失物、漂流物或其他離本人所持有之物者，處5百元以下罰金。",
  "characters": {
    "judges": [
      "李麗珍"
    ],
    "prosecutors": [

    ],
    "lawyers": [

    ],
    "clerks": [
      "李靜華"
    ],
    "plaintiffs": [

    ],
    "defendants": [
      "彭顗文原名彭春芳."
    ],
    "prosecutor_office": [
      "臺灣桃園地方法院檢察署檢察官"
    ],
    "creditors": [

    ],
    "debtors": [

    ],
    "judicial_associate_officer": [

    ]
  },
  "adjudged_at": "2011-07-14",
  "created_at": "2016-02-14 00:21:01",
  "updated_at": "2016-02-14 00:21:01"
}