{
  "identify": "TYD-100-桃簡-1638-20110715-1",
  "court": {
    "name": "臺灣桃園地方法院",
    "code": "TYD"
  },
  "division": {
    "name": "刑事",
    "code": "M"
  },
  "year": 100,
  "word": "桃簡",
  "number": "1638",
  "jcheck": "1",
  "reason": "詐欺",
  "content": "臺灣桃園地方法院刑事簡易判決       100年度桃簡字第1638號\n聲  請  人  臺灣桃園地方法院檢察署檢察官\n被      告  楊世輝\n上列被告因詐欺案件，經檢察官聲請以簡易判決處刑（100 年度\n偵緝字第291 號），本院判決如下：\n    主  文\n楊世輝意圖為自己不法之所有，以詐術使人將本人之物交付，累\n犯，處有期徒刑參月，如易科罰金，以新臺幣壹仟元折算壹日。\n    事實及理由\n一、本件犯罪事實及證據，除補充被告前科為「楊世輝前因詐欺\n    案件，經本院以97年度桃簡字第1443號判決判處有期徒刑4\n    月確定；又因竊盜案件，經本院以97年度桃簡字第3229號判\n    決判處有期徒刑6 月確定；上開2 罪嗣經本院以98年度聲字\n    第823 號裁定定應執行刑為有期徒刑9 月確定，並於民國98\n    年11月25日縮刑期滿執行完畢（於本案構成累犯）。又因詐\n    欺案件，共2 罪，經臺灣臺北地方法院以100 年度簡字第19\n    71號判決判處應執行有期徒刑6 月（尚未確定）。」，並於\n    犯罪事實欄最末補充「嗣經林怡婷提供楊世輝之行動電話號\n    碼循線查獲，始悉上情。」；證據部份並補充「通聯調閱查\n    詢單」外，餘均引用檢察官聲請簡易判決處刑書之記載（如\n    附件）。\n二、論罪科刑\n  (一)核被告楊世輝所為，係犯刑法第339 條第1 項詐欺取財罪。\n    查被告有如前述事實欄所載之犯罪科刑紀錄及執行情形，有\n    卷附臺灣高等法院被告前案紀錄表可按，其於受此有期徒刑\n    執行完畢後5 年內，故意再犯本件有期徒刑以上之刑之罪，\n    為累犯，應依刑法第47條第1 項規定，依法加重其刑。\n  (二)本院爰審酌被告先前已有詐欺前科，並以類似手法騙取他人\n    手錶而經法院判決在案，有臺灣臺北地方法院100 年度簡字\n    第1971號判決暨所附起訴書，並有臺灣高等法院被告前案紀\n    錄表1 份在卷可參；其犯罪之動機係因貪圖錢財，被害人受\n    騙金額為新臺幣28,500元，惟被告犯後坦承犯行，態度尚可\n    等一切情狀，量處如主文欄所示之刑，並於斟酌被告之年齡\n    、學歷、職業及家庭經濟狀況等節後，諭知如主文所示之易\n    科罰金折算標準，以資懲儆。\n三、據上論斷，應依刑事訴訟法第449 第1 項前段、第3 項、第\n    454 條第2 項，刑法第339 條第1 項、第47條第1 項、第41\n    條第1 項前段，刑法施行法第1 條之1 第1 項、第2 項前段\n    ，逕以簡易判決處如主文所示之刑。\n四、如不服本判決，應於判決送達後10日內，向本院提出上訴狀\n    （應附繕本），上訴於本院合議庭。\n中    華    民    國  100     年    7     月    15    日\n                  刑事第二庭    法  官  丁俞尹\n以上正本證明與原本無異。\n如不服本判決，應於判決送達後10日內向本院提出上訴狀（應附\n繕本）。\n                                書記官  許正旻\n中    華    民    國   100    年    7     月    26    日\n附錄本案論罪科刑法條全文\n中華民國刑法第339 條\n(普通詐欺罪)\n意圖為自己或第三人不法之所有，以詐術使人將本人或第三人之\n物交付者，處5 年以下有期徒刑、拘役或科或併科1 千元以下罰\n金。\n以前項方法得財產上不法之利益或使第三人得之者，亦同。\n前二項之未遂犯罰之。",
  "structure": {
    "main": "楊世輝意圖為自己不法之所有，以詐術使人將本人之物交付，累\n犯，處有期徒刑參月，如易科罰金，以新臺幣壹仟元折算壹日。",
    "fact": "一、本件犯罪事實及證據，除補充被告前科為「楊世輝前因詐欺\n    案件，經本院以97年度桃簡字第1443號判決判處有期徒刑4\n    月確定；又因竊盜案件，經本院以97年度桃簡字第3229號判\n    決判處有期徒刑6 月確定；上開2 罪嗣經本院以98年度聲字\n    第823 號裁定定應執行刑為有期徒刑9 月確定，並於民國98\n    年11月25日縮刑期滿執行完畢（於本案構成累犯）。又因詐\n    欺案件，共2 罪，經臺灣臺北地方法院以100 年度簡字第19\n    71號判決判處應執行有期徒刑6 月（尚未確定）。」，並於\n    犯罪事實欄最末補充「嗣經林怡婷提供楊世輝之行動電話號\n    碼循線查獲，始悉上情。」；證據部份並補充「通聯調閱查\n    詢單」外，餘均引用檢察官聲請簡易判決處刑書之記載（如\n    附件）。\n二、論罪科刑\n  (一)核被告楊世輝所為，係犯刑法第339 條第1 項詐欺取財罪。\n    查被告有如前述事實欄所載之犯罪科刑紀錄及執行情形，有\n    卷附臺灣高等法院被告前案紀錄表可按，其於受此有期徒刑\n    執行完畢後5 年內，故意再犯本件有期徒刑以上之刑之罪，\n    為累犯，應依刑法第47條第1 項規定，依法加重其刑。\n  (二)本院爰審酌被告先前已有詐欺前科，並以類似手法騙取他人\n    手錶而經法院判決在案，有臺灣臺北地方法院100 年度簡字\n    第1971號判決暨所附起訴書，並有臺灣高等法院被告前案紀\n    錄表1 份在卷可參；其犯罪之動機係因貪圖錢財，被害人受\n    騙金額為新臺幣28,500元，惟被告犯後坦承犯行，態度尚可\n    等一切情狀，量處如主文欄所示之刑，並於斟酌被告之年齡\n    、學歷、職業及家庭經濟狀況等節後，諭知如主文所示之易\n    科罰金折算標準，以資懲儆。\n三、據上論斷，應依刑事訴訟法第449 第1 項前段、第3 項、第\n    454 條第2 項，刑法第339 條第1 項、第47條第1 項、第41\n    條第1 項前段，刑法施行法第1 條之1 第1 項、第2 項前段\n    ，逕以簡易判決處如主文所示之刑。\n四、如不服本判決，應於判決送達後10日內，向本院提出上訴狀\n    （應附繕本），上訴於本院合議庭。",
    "reason": "一、本件犯罪事實及證據，除補充被告前科為「楊世輝前因詐欺\n    案件，經本院以97年度桃簡字第1443號判決判處有期徒刑4\n    月確定；又因竊盜案件，經本院以97年度桃簡字第3229號判\n    決判處有期徒刑6 月確定；上開2 罪嗣經本院以98年度聲字\n    第823 號裁定定應執行刑為有期徒刑9 月確定，並於民國98\n    年11月25日縮刑期滿執行完畢（於本案構成累犯）。又因詐\n    欺案件，共2 罪，經臺灣臺北地方法院以100 年度簡字第19\n    71號判決判處應執行有期徒刑6 月（尚未確定）。」，並於\n    犯罪事實欄最末補充「嗣經林怡婷提供楊世輝之行動電話號\n    碼循線查獲，始悉上情。」；證據部份並補充「通聯調閱查\n    詢單」外，餘均引用檢察官聲請簡易判決處刑書之記載（如\n    附件）。\n二、論罪科刑\n  (一)核被告楊世輝所為，係犯刑法第339 條第1 項詐欺取財罪。\n    查被告有如前述事實欄所載之犯罪科刑紀錄及執行情形，有\n    卷附臺灣高等法院被告前案紀錄表可按，其於受此有期徒刑\n    執行完畢後5 年內，故意再犯本件有期徒刑以上之刑之罪，\n    為累犯，應依刑法第47條第1 項規定，依法加重其刑。\n  (二)本院爰審酌被告先前已有詐欺前科，並以類似手法騙取他人\n    手錶而經法院判決在案，有臺灣臺北地方法院100 年度簡字\n    第1971號判決暨所附起訴書，並有臺灣高等法院被告前案紀\n    錄表1 份在卷可參；其犯罪之動機係因貪圖錢財，被害人受\n    騙金額為新臺幣28,500元，惟被告犯後坦承犯行，態度尚可\n    等一切情狀，量處如主文欄所示之刑，並於斟酌被告之年齡\n    、學歷、職業及家庭經濟狀況等節後，諭知如主文所示之易\n    科罰金折算標準，以資懲儆。\n三、據上論斷，應依刑事訴訟法第449 第1 項前段、第3 項、第\n    454 條第2 項，刑法第339 條第1 項、第47條第1 項、第41\n    條第1 項前段，刑法施行法第1 條之1 第1 項、第2 項前段\n    ，逕以簡易判決處如主文所示之刑。\n四、如不服本判決，應於判決送達後10日內，向本院提出上訴狀\n    （應附繕本），上訴於本院合議庭。"
  },
  "search": "臺灣桃園地方法院刑事簡易判決100年度桃簡字第1638號聲請人臺灣桃園地方法院檢察署檢察官被告楊世輝上列被告因詐欺案件，經檢察官聲請以簡易判決處刑（100年度偵緝字第291號），本院判決如下：主文楊世輝意圖為自己不法之所有，以詐術使人將本人之物交付，累犯，處有期徒刑參月，如易科罰金，以新臺幣壹仟元折算壹日。事實及理由一、本件犯罪事實及證據，除補充被告前科為「楊世輝前因詐欺案件，經本院以97年度桃簡字第1443號判決判處有期徒刑4月確定；又因竊盜案件，經本院以97年度桃簡字第3229號判決判處有期徒刑6月確定；上開2罪嗣經本院以98年度聲字第823號裁定定應執行刑為有期徒刑9月確定，並於民國98年11月25日縮刑期滿執行完畢（於本案構成累犯）。又因詐欺案件，共2罪，經臺灣臺北地方法院以100年度簡字第1971號判決判處應執行有期徒刑6月（尚未確定）。」，並於犯罪事實欄最末補充「嗣經林怡婷提供楊世輝之行動電話號碼循線查獲，始悉上情。」；證據部份並補充「通聯調閱查詢單」外，餘均引用檢察官聲請簡易判決處刑書之記載（如附件）。二、論罪科刑(一)核被告楊世輝所為，係犯刑法第339條第1項詐欺取財罪。查被告有如前述事實欄所載之犯罪科刑紀錄及執行情形，有卷附臺灣高等法院被告前案紀錄表可按，其於受此有期徒刑執行完畢後5年內，故意再犯本件有期徒刑以上之刑之罪，為累犯，應依刑法第47條第1項規定，依法加重其刑。(二)本院爰審酌被告先前已有詐欺前科，並以類似手法騙取他人手錶而經法院判決在案，有臺灣臺北地方法院100年度簡字第1971號判決暨所附起訴書，並有臺灣高等法院被告前案紀錄表1份在卷可參；其犯罪之動機係因貪圖錢財，被害人受騙金額為新臺幣28,500元，惟被告犯後坦承犯行，態度尚可等一切情狀，量處如主文欄所示之刑，並於斟酌被告之年齡、學歷、職業及家庭經濟狀況等節後，諭知如主文所示之易科罰金折算標準，以資懲儆。三、據上論斷，應依刑事訴訟法第449第1項前段、第3項、第454條第2項，刑法第339條第1項、第47條第1項、第41條第1項前段，刑法施行法第1條之1第1項、第2項前段，逕以簡易判決處如主文所示之刑。四、如不服本判決，應於判決送達後10日內，向本院提出上訴狀（應附繕本），上訴於本院合議庭。中華民國100年7月15日刑事第二庭法官丁俞尹以上正本證明與原本無異。如不服本判決，應於判決送達後10日內向本院提出上訴狀（應附繕本）。書記官許正旻中華民國100年7月26日附錄本案論罪科刑法條全文中華民國刑法第339條(普通詐欺罪)意圖為自己或第三人不法之所有，以詐術使人將本人或第三人之物交付者，處5年以下有期徒刑、拘役或科或併科1千元以下罰金。以前項方法得財產上不法之利益或使第三人得之者，亦同。前二項之未遂犯罰之。",
  "characters": {
    "judges": [
      "丁俞尹"
    ],
    "prosecutors": [

    ],
    "lawyers": [

    ],
    "clerks": [
      "許正旻"
    ],
    "plaintiffs": [

    ],
    "defendants": [
      "楊世輝"
    ],
    "prosecutor_office": [
      "臺灣桃園地方法院檢察署檢察官"
    ],
    "creditors": [

    ],
    "debtors": [

    ],
    "judicial_associate_officer": [

    ]
  },
  "adjudged_at": "2011-07-15",
  "created_at": "2016-02-14 00:31:53",
  "updated_at": "2016-02-14 00:31:53"
}