{
  "identify": "CHD-100-簡-16-20110111-1",
  "court": {
    "name": "臺灣彰化地方法院",
    "code": "CHD"
  },
  "division": {
    "name": "刑事",
    "code": "M"
  },
  "year": 100,
  "word": "簡",
  "number": "16",
  "jcheck": "1",
  "reason": "違反毒品危害防制條例",
  "content": "臺灣彰化地方法院刑事簡易判決           100年度簡字第16號\n聲  請  人  臺灣彰化地方法院檢察署檢察官\n被      告  許世宏\n上列被告因違反毒品危害防制條例案件，經檢察官聲請以簡易判\n決處刑（99年度毒偵字第1802號），本院判決如下：\n    主  文\n許世宏施用第二級毒品，累犯，處有期徒伍月，如易科罰金，以\n新臺幣壹仟元折算壹日。扣案殘留有第二級毒品甲基安非他命之\n殘渣袋壹個沒收銷燬之。\n    犯罪事實及理由\n一、本案犯罪事實及證據，除犯罪事實欄一、第6 至7 行「詎猶\n    不知悔改，復基於施用第二級毒品甲基安非他命之犯意」補\n    充更正為「詎其猶不知悔改，於上開觀察、勒戒執行完畢釋\n    放後5 年內，復基於施用第二級毒品甲基安非他命之犯意」\n    ；證據部分應補充「彰化縣警察局芳苑分局委託檢驗尿液代\n    號與真實姓名對照認證單1 份」外，餘均引用檢察官聲請簡\n    易判決處刑書之記載（如附件）。\n二、按犯毒品危害防制條例第10條施用第一、二級毒品之罪者，\n    檢察官應先聲請法院裁定將被告令送勒戒處所觀察、勒戒，\n    經觀察、勒戒後，認無繼續施用毒品傾向者，應即釋放，並\n    為不起訴之處分或不付審理之裁定；認有繼續施用毒品傾向\n    者，應由檢察官聲請法院裁定令入戒治處所施以強制戒治，\n    且經觀察、勒戒或強制戒治執行完畢釋放後，5 年內再犯第\n    10條之罪，檢察官應依一般刑事訴訟程式予以起訴論罪科刑\n    ，此觀諸毒品危害防制條例第20條第1 項、第2 項、第23條\n    第2 項前段規定自明。經查，本案被告前因施用毒品案件，\n    經法院裁定送觀察、勒戒後，因評定認無繼續施用毒品傾向\n    ，於96年10月19日執行完畢釋放，有臺灣高等法院被告前案\n    紀錄表在卷可佐，其於觀察、勒戒執行完畢釋放後5 年內，\n    再犯本件施用毒品案件，依前述規定自應予以起訴論罪科刑\n    。\n三、扣案殘渣袋1 個，為被告所有原用以盛裝其本案施用之甲基\n    安非他命，業據被告於偵訊時供承明確，而其內之殘渣經彰\n    化縣警察局芳苑分局依聯勤204廠製造之檢驗試劑初步檢驗\n    結果，確呈甲基安非他命反應，亦有檢驗照片1張（警卷第6\n    頁）附卷可稽，堪認被告所述可信為真，因該殘渣袋內沾附\n    殘留之第二級毒品甲基安非他命與該塑膠袋在物理上應無法\n    徹底析離，是該殘渣袋1個，應與所沾附殘留之甲基安非他\n    命，併依毒品危害防制條例第18條第1項前段規定，宣告沒\n    收銷燬之，聲請人聲請依刑法第38條第1項第2款、第3項規\n    宣告沒收，尚有誤會，併此敘明。\n四、依刑事訴訟法第449 條第1 項前段、第450 條第1 項、第45\n    4 條第2 項，毒品危害防制條例第10條第2 項、第18條第1\n    項前段，刑法第11條前段、第47條第1 項、第41條第1 項前\n    段，逕以簡易判決處刑如主文。\n五、如不服本判決，得自收受送達之日起10日內向本院提出上訴\n    狀，上訴於本院第二審合議庭（須附繕本）。\n中    華    民    國    100   年    1     月    11    日\n                  刑事第二庭    法  官  江彥儀\n以上正本證明與原本無異。\n如不服本件判決，得自收受送達之日起10日內，表明上訴理由，\n向本庭提起上訴狀（須附繕本）。\n中    華    民    國    100   年    1     月    11    日\n                                書記官  黃明慧\n附錄本案論罪科刑法條:\n毒品危害防制條例第10條第2項\n施用第二級毒品者，處 3 年以下有期徒刑。",
  "structure": {
    "main": "許世宏施用第二級毒品，累犯，處有期徒伍月，如易科罰金，以\n新臺幣壹仟元折算壹日。扣案殘留有第二級毒品甲基安非他命之\n殘渣袋壹個沒收銷燬之。",
    "fact": "一、本案犯罪事實及證據，除犯罪事實欄一、第6 至7 行「詎猶\n    不知悔改，復基於施用第二級毒品甲基安非他命之犯意」補\n    充更正為「詎其猶不知悔改，於上開觀察、勒戒執行完畢釋\n    放後5 年內，復基於施用第二級毒品甲基安非他命之犯意」\n    ；證據部分應補充「彰化縣警察局芳苑分局委託檢驗尿液代\n    號與真實姓名對照認證單1 份」外，餘均引用檢察官聲請簡\n    易判決處刑書之記載（如附件）。\n二、按犯毒品危害防制條例第10條施用第一、二級毒品之罪者，\n    檢察官應先聲請法院裁定將被告令送勒戒處所觀察、勒戒，\n    經觀察、勒戒後，認無繼續施用毒品傾向者，應即釋放，並\n    為不起訴之處分或不付審理之裁定；認有繼續施用毒品傾向\n    者，應由檢察官聲請法院裁定令入戒治處所施以強制戒治，\n    且經觀察、勒戒或強制戒治執行完畢釋放後，5 年內再犯第\n    10條之罪，檢察官應依一般刑事訴訟程式予以起訴論罪科刑\n    ，此觀諸毒品危害防制條例第20條第1 項、第2 項、第23條\n    第2 項前段規定自明。經查，本案被告前因施用毒品案件，\n    經法院裁定送觀察、勒戒後，因評定認無繼續施用毒品傾向\n    ，於96年10月19日執行完畢釋放，有臺灣高等法院被告前案\n    紀錄表在卷可佐，其於觀察、勒戒執行完畢釋放後5 年內，\n    再犯本件施用毒品案件，依前述規定自應予以起訴論罪科刑\n    。\n三、扣案殘渣袋1 個，為被告所有原用以盛裝其本案施用之甲基\n    安非他命，業據被告於偵訊時供承明確，而其內之殘渣經彰\n    化縣警察局芳苑分局依聯勤204廠製造之檢驗試劑初步檢驗\n    結果，確呈甲基安非他命反應，亦有檢驗照片1張（警卷第6\n    頁）附卷可稽，堪認被告所述可信為真，因該殘渣袋內沾附\n    殘留之第二級毒品甲基安非他命與該塑膠袋在物理上應無法\n    徹底析離，是該殘渣袋1個，應與所沾附殘留之甲基安非他\n    命，併依毒品危害防制條例第18條第1項前段規定，宣告沒\n    收銷燬之，聲請人聲請依刑法第38條第1項第2款、第3項規\n    宣告沒收，尚有誤會，併此敘明。\n四、依刑事訴訟法第449 條第1 項前段、第450 條第1 項、第45\n    4 條第2 項，毒品危害防制條例第10條第2 項、第18條第1\n    項前段，刑法第11條前段、第47條第1 項、第41條第1 項前\n    段，逕以簡易判決處刑如主文。\n五、如不服本判決，得自收受送達之日起10日內向本院提出上訴\n    狀，上訴於本院第二審合議庭（須附繕本）。",
    "reason": "一、本案犯罪事實及證據，除犯罪事實欄一、第6 至7 行「詎猶\n    不知悔改，復基於施用第二級毒品甲基安非他命之犯意」補\n    充更正為「詎其猶不知悔改，於上開觀察、勒戒執行完畢釋\n    放後5 年內，復基於施用第二級毒品甲基安非他命之犯意」\n    ；證據部分應補充「彰化縣警察局芳苑分局委託檢驗尿液代\n    號與真實姓名對照認證單1 份」外，餘均引用檢察官聲請簡\n    易判決處刑書之記載（如附件）。\n二、按犯毒品危害防制條例第10條施用第一、二級毒品之罪者，\n    檢察官應先聲請法院裁定將被告令送勒戒處所觀察、勒戒，\n    經觀察、勒戒後，認無繼續施用毒品傾向者，應即釋放，並\n    為不起訴之處分或不付審理之裁定；認有繼續施用毒品傾向\n    者，應由檢察官聲請法院裁定令入戒治處所施以強制戒治，\n    且經觀察、勒戒或強制戒治執行完畢釋放後，5 年內再犯第\n    10條之罪，檢察官應依一般刑事訴訟程式予以起訴論罪科刑\n    ，此觀諸毒品危害防制條例第20條第1 項、第2 項、第23條\n    第2 項前段規定自明。經查，本案被告前因施用毒品案件，\n    經法院裁定送觀察、勒戒後，因評定認無繼續施用毒品傾向\n    ，於96年10月19日執行完畢釋放，有臺灣高等法院被告前案\n    紀錄表在卷可佐，其於觀察、勒戒執行完畢釋放後5 年內，\n    再犯本件施用毒品案件，依前述規定自應予以起訴論罪科刑\n    。\n三、扣案殘渣袋1 個，為被告所有原用以盛裝其本案施用之甲基\n    安非他命，業據被告於偵訊時供承明確，而其內之殘渣經彰\n    化縣警察局芳苑分局依聯勤204廠製造之檢驗試劑初步檢驗\n    結果，確呈甲基安非他命反應，亦有檢驗照片1張（警卷第6\n    頁）附卷可稽，堪認被告所述可信為真，因該殘渣袋內沾附\n    殘留之第二級毒品甲基安非他命與該塑膠袋在物理上應無法\n    徹底析離，是該殘渣袋1個，應與所沾附殘留之甲基安非他\n    命，併依毒品危害防制條例第18條第1項前段規定，宣告沒\n    收銷燬之，聲請人聲請依刑法第38條第1項第2款、第3項規\n    宣告沒收，尚有誤會，併此敘明。\n四、依刑事訴訟法第449 條第1 項前段、第450 條第1 項、第45\n    4 條第2 項，毒品危害防制條例第10條第2 項、第18條第1\n    項前段，刑法第11條前段、第47條第1 項、第41條第1 項前\n    段，逕以簡易判決處刑如主文。\n五、如不服本判決，得自收受送達之日起10日內向本院提出上訴\n    狀，上訴於本院第二審合議庭（須附繕本）。"
  },
  "search": "臺灣彰化地方法院刑事簡易判決100年度簡字第16號聲請人臺灣彰化地方法院檢察署檢察官被告許世宏上列被告因違反毒品危害防制條例案件，經檢察官聲請以簡易判決處刑（99年度毒偵字第1802號），本院判決如下：主文許世宏施用第二級毒品，累犯，處有期徒伍月，如易科罰金，以新臺幣壹仟元折算壹日。扣案殘留有第二級毒品甲基安非他命之殘渣袋壹個沒收銷燬之。犯罪事實及理由一、本案犯罪事實及證據，除犯罪事實欄一、第6至7行「詎猶不知悔改，復基於施用第二級毒品甲基安非他命之犯意」補充更正為「詎其猶不知悔改，於上開觀察、勒戒執行完畢釋放後5年內，復基於施用第二級毒品甲基安非他命之犯意」；證據部分應補充「彰化縣警察局芳苑分局委託檢驗尿液代號與真實姓名對照認證單1份」外，餘均引用檢察官聲請簡易判決處刑書之記載（如附件）。二、按犯毒品危害防制條例第10條施用第一、二級毒品之罪者，檢察官應先聲請法院裁定將被告令送勒戒處所觀察、勒戒，經觀察、勒戒後，認無繼續施用毒品傾向者，應即釋放，並為不起訴之處分或不付審理之裁定；認有繼續施用毒品傾向者，應由檢察官聲請法院裁定令入戒治處所施以強制戒治，且經觀察、勒戒或強制戒治執行完畢釋放後，5年內再犯第10條之罪，檢察官應依一般刑事訴訟程式予以起訴論罪科刑，此觀諸毒品危害防制條例第20條第1項、第2項、第23條第2項前段規定自明。經查，本案被告前因施用毒品案件，經法院裁定送觀察、勒戒後，因評定認無繼續施用毒品傾向，於96年10月19日執行完畢釋放，有臺灣高等法院被告前案紀錄表在卷可佐，其於觀察、勒戒執行完畢釋放後5年內，再犯本件施用毒品案件，依前述規定自應予以起訴論罪科刑。三、扣案殘渣袋1個，為被告所有原用以盛裝其本案施用之甲基安非他命，業據被告於偵訊時供承明確，而其內之殘渣經彰化縣警察局芳苑分局依聯勤204廠製造之檢驗試劑初步檢驗結果，確呈甲基安非他命反應，亦有檢驗照片1張（警卷第6頁）附卷可稽，堪認被告所述可信為真，因該殘渣袋內沾附殘留之第二級毒品甲基安非他命與該塑膠袋在物理上應無法徹底析離，是該殘渣袋1個，應與所沾附殘留之甲基安非他命，併依毒品危害防制條例第18條第1項前段規定，宣告沒收銷燬之，聲請人聲請依刑法第38條第1項第2款、第3項規宣告沒收，尚有誤會，併此敘明。四、依刑事訴訟法第449條第1項前段、第450條第1項、第454條第2項，毒品危害防制條例第10條第2項、第18條第1項前段，刑法第11條前段、第47條第1項、第41條第1項前段，逕以簡易判決處刑如主文。五、如不服本判決，得自收受送達之日起10日內向本院提出上訴狀，上訴於本院第二審合議庭（須附繕本）。中華民國100年1月11日刑事第二庭法官江彥儀以上正本證明與原本無異。如不服本件判決，得自收受送達之日起10日內，表明上訴理由，向本庭提起上訴狀（須附繕本）。中華民國100年1月11日書記官黃明慧附錄本案論罪科刑法條:毒品危害防制條例第10條第2項施用第二級毒品者，處3年以下有期徒刑。",
  "characters": {
    "judges": [
      "江彥儀"
    ],
    "prosecutors": [

    ],
    "lawyers": [

    ],
    "clerks": [
      "黃明慧"
    ],
    "plaintiffs": [

    ],
    "defendants": [
      "許世宏"
    ],
    "prosecutor_office": [
      "臺灣彰化地方法院檢察署檢察官"
    ],
    "creditors": [

    ],
    "debtors": [

    ],
    "judicial_associate_officer": [

    ]
  },
  "adjudged_at": "2011-01-11",
  "created_at": "2016-02-13 08:52:37",
  "updated_at": "2016-02-13 08:52:37"
}