{
  "identify": "TPH-100-上訴-33-20110110-1",
  "court": {
    "name": "臺灣高等法院",
    "code": "TPH"
  },
  "division": {
    "name": "刑事",
    "code": "M"
  },
  "year": 100,
  "word": "上訴",
  "number": "33",
  "jcheck": "1",
  "reason": "毒品危害防制條例",
  "content": "臺灣高等法院刑事判決                 100年度上訴字第33號\n上  訴  人\n即  被  告  李世光\n上列上訴人因違反毒品危害防制條例案件，不服臺灣板橋地方法\n院99年度訴字第3080號，中華民國99年11月30日第一審判決（起\n訴案號：臺灣板橋地方法院檢察署99年度毒偵字第4650號、第68\n93號），提起上訴，本院判決如下：\n    主  文\n上訴駁回。\n    理  由\n一、依刑事訴訟法第350條、第361條、第362條、第367條規定，\n    不服地方法院之第一審判決而上訴者，須提出上訴書狀，並\n    應敘述具體理由，為上訴必備之程式；其所提出之書狀未敘\n    述上訴理由，或僅曾以言詞陳述上訴理由者，均應於上訴期\n    間屆滿後20日內補提理由書於第一審法院。第一審法院經形\n    式審查，認逾期未補提上訴理由者，應定期間先命補正；逾\n    期未補正者，為上訴不合法律上之程式，應以裁定駁回。倘\n    已提出上訴理由，但所提非屬具體理由者，則由第二審法院\n    以上訴不合法律上之程式，判決駁回。而所謂具體理由，必\n    係依據卷內既有訴訟資料或提出新事證，指摘或表明第一審\n    判決有何採證認事、用法或量刑等足以影響判決本旨之不當\n    或違法，而構成應予撤銷之具體事由，始克當之（例如：依\n    憑證據法則具體指出所採證據何以不具證據能力，或依憑卷\n    證資料，明確指出所為證據證明力之判斷如何違背經驗、論\n    理法則）；倘僅泛言原判決認定事實錯誤、違背法令、量刑\n    失之過重或輕縱，而未依上揭意旨指出具體事由，或形式上\n    雖已指出具體事由，然該事由縱使屬實，亦不足以認為原判\n    決有何不當或違法者（例如：對不具有調查必要性之證據，\n    法院未依聲請調查亦未說明理由，或援用證據不當，但除去\n    該證據仍應為同一事實之認定），皆難謂係具體理由，俾與\n    第二審上訴制度旨在請求第二審法院撤銷、變更第一審不當\n    或違法之判決，以實現個案救濟之立法目的相契合，並節制\n    濫行上訴（最高法院97年度台上字第892號刑事判決意旨參\n    照）。\n二、被告上訴意旨略以：我已經在戒毒，如因服刑而中斷，可能\n    又回到原點，且家有高齡父親，現有正常上下班，我有心悔\n    改，請給予重新做人機會云云。\n三、經查：依被告於警詢時、偵查中及原審之自白、臺灣檢驗科\n    技股份有限公司以EIA酵素免疫分析法初步檢驗，再以GC/MS\n    氣相層析質譜儀法確認檢驗結果，確均呈鴉片類（嗎啡）陽\n    性反應乙節，亦有該公司民國（下同）99年6月10日、編號\n    ：UL/2010/60 081號及99年9月16日、編號：UL/2010/90093\n    號濫用藥物檢驗報告、代碼對照表、姓名對照表附卷可稽，\n    暨毒品海洛因四包（淨重共計0.29公克）、海洛因殘渣袋一\n    只、海洛因一包（驗餘淨重0.0660公克）、注射針筒四支、\n    分裝杓二支、分裝袋四十五只等物扣案可資佐證。前揭扣案\n    毒品經送鑑定後，確實均含有海洛因成分等情，復有新北市\n    政府警察局永和分局查獲涉嫌毒品危害防制條例毒品初步鑑\n    驗報告單、交通部民用航空局航空醫務中心99年9月7日航藥\n    鑑字第0995614號毒品鑑定書在卷可按，認定被告確有於99\n    年5月28日及99年8月26日施用第一級毒品之犯行。又查被告\n    前因施用第一級毒品案件，先後經臺灣板橋地方法院（下稱\n    板橋地院）以96年度訴字第4241號、96年度訴字第3937號刑\n    事判決各判處有期徒刑十月確定；上開二案件嗣經板橋地院\n    以97年度聲字第1280號裁定應執行有期徒刑一年六月確定。\n    經入監執行後，於98年7 月6日縮短刑期假釋出監，並付保\n    護管束，甫於98年9月1日執行完畢，其於5年內故意再犯本\n    件最重本刑有期徒刑之2罪，為累犯，均應加重其刑。原審\n    審酌被告曾有施用毒品之前科仍不知戒除，犯罪後坦承犯行\n    ，所犯之施用毒品犯行乃戕害自己身心健康，並未危及他人\n    暨檢察官對被告求處之刑等一切情狀，分別量處有期徒刑8\n    月、8月，並定應執行有期徒刑1年，均已詳敘其所憑證據、\n    認定理由及量刑依據。從形式上觀察，原判決已敘明審酌刑\n    法第57條所列事項之理由，並無認定事實錯誤、量刑瑕疵或\n    違背法令之情形。被告上訴意旨僅泛稱其已經在戒毒，如服\n    刑而中斷，可能又回到原點，且家有高齡父親，現有正常上\n    下班，其有心悔改，請給予重新做人機會云云，非依據卷內\n    訴訟資料或提出新事證，具體指摘或表明第一審判決有何足\n    以影響判決本旨之不當或違法，而構成應予撤銷之具體事由\n    ，與刑事訴訟法第361條第2項所稱「具體理由」，尚非相當\n    。揆諸上開說明，被告上訴應認違背刑事訴訟法第361條第2\n    項「上訴書狀應敘述具體理由」之規定，依同法第367條前\n    段規定，應以判決駁回上訴，並不經言詞辯論為之。\n四、據上論斷，應依刑事訴訟法第367條前段、第372條，判決如\n    主文。\n中    華    民    國   100    年    1     月    10    日\n                  刑事第十三庭審判長法  官  曾德水\n                                    法  官  王復生\n                                    法  官  楊貴雄\n以上正本證明與原本無異。\n如不服本判決，應於收受送達後10日內向本院提出上訴書狀，其\n未敘述上訴之理由者並得於提起上訴後10日內向本院補提理由書\n（均須按他造當事人之人數附繕本）「切勿逕送上級法院」。\n                                    書記官  邵淑津\n中    華    民    國   100    年    1     月    12    日",
  "structure": {
    "main": "上訴駁回。",
    "reason": "一、依刑事訴訟法第350條、第361條、第362條、第367條規定，\n    不服地方法院之第一審判決而上訴者，須提出上訴書狀，並\n    應敘述具體理由，為上訴必備之程式；其所提出之書狀未敘\n    述上訴理由，或僅曾以言詞陳述上訴理由者，均應於上訴期\n    間屆滿後20日內補提理由書於第一審法院。第一審法院經形\n    式審查，認逾期未補提上訴理由者，應定期間先命補正；逾\n    期未補正者，為上訴不合法律上之程式，應以裁定駁回。倘\n    已提出上訴理由，但所提非屬具體理由者，則由第二審法院\n    以上訴不合法律上之程式，判決駁回。而所謂具體理由，必\n    係依據卷內既有訴訟資料或提出新事證，指摘或表明第一審\n    判決有何採證認事、用法或量刑等足以影響判決本旨之不當\n    或違法，而構成應予撤銷之具體事由，始克當之（例如：依\n    憑證據法則具體指出所採證據何以不具證據能力，或依憑卷\n    證資料，明確指出所為證據證明力之判斷如何違背經驗、論\n    理法則）；倘僅泛言原判決認定事實錯誤、違背法令、量刑\n    失之過重或輕縱，而未依上揭意旨指出具體事由，或形式上\n    雖已指出具體事由，然該事由縱使屬實，亦不足以認為原判\n    決有何不當或違法者（例如：對不具有調查必要性之證據，\n    法院未依聲請調查亦未說明理由，或援用證據不當，但除去\n    該證據仍應為同一事實之認定），皆難謂係具體理由，俾與\n    第二審上訴制度旨在請求第二審法院撤銷、變更第一審不當\n    或違法之判決，以實現個案救濟之立法目的相契合，並節制\n    濫行上訴（最高法院97年度台上字第892號刑事判決意旨參\n    照）。\n二、被告上訴意旨略以：我已經在戒毒，如因服刑而中斷，可能\n    又回到原點，且家有高齡父親，現有正常上下班，我有心悔\n    改，請給予重新做人機會云云。\n三、經查：依被告於警詢時、偵查中及原審之自白、臺灣檢驗科\n    技股份有限公司以EIA酵素免疫分析法初步檢驗，再以GC/MS\n    氣相層析質譜儀法確認檢驗結果，確均呈鴉片類（嗎啡）陽\n    性反應乙節，亦有該公司民國（下同）99年6月10日、編號\n    ：UL/2010/60 081號及99年9月16日、編號：UL/2010/90093\n    號濫用藥物檢驗報告、代碼對照表、姓名對照表附卷可稽，\n    暨毒品海洛因四包（淨重共計0.29公克）、海洛因殘渣袋一\n    只、海洛因一包（驗餘淨重0.0660公克）、注射針筒四支、\n    分裝杓二支、分裝袋四十五只等物扣案可資佐證。前揭扣案\n    毒品經送鑑定後，確實均含有海洛因成分等情，復有新北市\n    政府警察局永和分局查獲涉嫌毒品危害防制條例毒品初步鑑\n    驗報告單、交通部民用航空局航空醫務中心99年9月7日航藥\n    鑑字第0995614號毒品鑑定書在卷可按，認定被告確有於99\n    年5月28日及99年8月26日施用第一級毒品之犯行。又查被告\n    前因施用第一級毒品案件，先後經臺灣板橋地方法院（下稱\n    板橋地院）以96年度訴字第4241號、96年度訴字第3937號刑\n    事判決各判處有期徒刑十月確定；上開二案件嗣經板橋地院\n    以97年度聲字第1280號裁定應執行有期徒刑一年六月確定。\n    經入監執行後，於98年7 月6日縮短刑期假釋出監，並付保\n    護管束，甫於98年9月1日執行完畢，其於5年內故意再犯本\n    件最重本刑有期徒刑之2罪，為累犯，均應加重其刑。原審\n    審酌被告曾有施用毒品之前科仍不知戒除，犯罪後坦承犯行\n    ，所犯之施用毒品犯行乃戕害自己身心健康，並未危及他人\n    暨檢察官對被告求處之刑等一切情狀，分別量處有期徒刑8\n    月、8月，並定應執行有期徒刑1年，均已詳敘其所憑證據、\n    認定理由及量刑依據。從形式上觀察，原判決已敘明審酌刑\n    法第57條所列事項之理由，並無認定事實錯誤、量刑瑕疵或\n    違背法令之情形。被告上訴意旨僅泛稱其已經在戒毒，如服\n    刑而中斷，可能又回到原點，且家有高齡父親，現有正常上\n    下班，其有心悔改，請給予重新做人機會云云，非依據卷內\n    訴訟資料或提出新事證，具體指摘或表明第一審判決有何足\n    以影響判決本旨之不當或違法，而構成應予撤銷之具體事由\n    ，與刑事訴訟法第361條第2項所稱「具體理由」，尚非相當\n    。揆諸上開說明，被告上訴應認違背刑事訴訟法第361條第2\n    項「上訴書狀應敘述具體理由」之規定，依同法第367條前\n    段規定，應以判決駁回上訴，並不經言詞辯論為之。\n四、據上論斷，應依刑事訴訟法第367條前段、第372條，判決如\n    主文。"
  },
  "search": "臺灣高等法院刑事判決100年度上訴字第33號上訴人即被告李世光上列上訴人因違反毒品危害防制條例案件，不服臺灣板橋地方法院99年度訴字第3080號，中華民國99年11月30日第一審判決（起訴案號：臺灣板橋地方法院檢察署99年度毒偵字第4650號、第6893號），提起上訴，本院判決如下：主文上訴駁回。理由一、依刑事訴訟法第350條、第361條、第362條、第367條規定，不服地方法院之第一審判決而上訴者，須提出上訴書狀，並應敘述具體理由，為上訴必備之程式；其所提出之書狀未敘述上訴理由，或僅曾以言詞陳述上訴理由者，均應於上訴期間屆滿後20日內補提理由書於第一審法院。第一審法院經形式審查，認逾期未補提上訴理由者，應定期間先命補正；逾期未補正者，為上訴不合法律上之程式，應以裁定駁回。倘已提出上訴理由，但所提非屬具體理由者，則由第二審法院以上訴不合法律上之程式，判決駁回。而所謂具體理由，必係依據卷內既有訴訟資料或提出新事證，指摘或表明第一審判決有何採證認事、用法或量刑等足以影響判決本旨之不當或違法，而構成應予撤銷之具體事由，始克當之（例如：依憑證據法則具體指出所採證據何以不具證據能力，或依憑卷證資料，明確指出所為證據證明力之判斷如何違背經驗、論理法則）；倘僅泛言原判決認定事實錯誤、違背法令、量刑失之過重或輕縱，而未依上揭意旨指出具體事由，或形式上雖已指出具體事由，然該事由縱使屬實，亦不足以認為原判決有何不當或違法者（例如：對不具有調查必要性之證據，法院未依聲請調查亦未說明理由，或援用證據不當，但除去該證據仍應為同一事實之認定），皆難謂係具體理由，俾與第二審上訴制度旨在請求第二審法院撤銷、變更第一審不當或違法之判決，以實現個案救濟之立法目的相契合，並節制濫行上訴（最高法院97年度台上字第892號刑事判決意旨參照）。二、被告上訴意旨略以：我已經在戒毒，如因服刑而中斷，可能又回到原點，且家有高齡父親，現有正常上下班，我有心悔改，請給予重新做人機會云云。三、經查：依被告於警詢時、偵查中及原審之自白、臺灣檢驗科技股份有限公司以EIA酵素免疫分析法初步檢驗，再以GC/MS氣相層析質譜儀法確認檢驗結果，確均呈鴉片類（嗎啡）陽性反應乙節，亦有該公司民國（下同）99年6月10日、編號：UL/2010/60081號及99年9月16日、編號：UL/2010/90093號濫用藥物檢驗報告、代碼對照表、姓名對照表附卷可稽，暨毒品海洛因四包（淨重共計0.29公克）、海洛因殘渣袋一只、海洛因一包（驗餘淨重0.0660公克）、注射針筒四支、分裝杓二支、分裝袋四十五只等物扣案可資佐證。前揭扣案毒品經送鑑定後，確實均含有海洛因成分等情，復有新北市政府警察局永和分局查獲涉嫌毒品危害防制條例毒品初步鑑驗報告單、交通部民用航空局航空醫務中心99年9月7日航藥鑑字第0995614號毒品鑑定書在卷可按，認定被告確有於99年5月28日及99年8月26日施用第一級毒品之犯行。又查被告前因施用第一級毒品案件，先後經臺灣板橋地方法院（下稱板橋地院）以96年度訴字第4241號、96年度訴字第3937號刑事判決各判處有期徒刑十月確定；上開二案件嗣經板橋地院以97年度聲字第1280號裁定應執行有期徒刑一年六月確定。經入監執行後，於98年7月6日縮短刑期假釋出監，並付保護管束，甫於98年9月1日執行完畢，其於5年內故意再犯本件最重本刑有期徒刑之2罪，為累犯，均應加重其刑。原審審酌被告曾有施用毒品之前科仍不知戒除，犯罪後坦承犯行，所犯之施用毒品犯行乃戕害自己身心健康，並未危及他人暨檢察官對被告求處之刑等一切情狀，分別量處有期徒刑8月、8月，並定應執行有期徒刑1年，均已詳敘其所憑證據、認定理由及量刑依據。從形式上觀察，原判決已敘明審酌刑法第57條所列事項之理由，並無認定事實錯誤、量刑瑕疵或違背法令之情形。被告上訴意旨僅泛稱其已經在戒毒，如服刑而中斷，可能又回到原點，且家有高齡父親，現有正常上下班，其有心悔改，請給予重新做人機會云云，非依據卷內訴訟資料或提出新事證，具體指摘或表明第一審判決有何足以影響判決本旨之不當或違法，而構成應予撤銷之具體事由，與刑事訴訟法第361條第2項所稱「具體理由」，尚非相當。揆諸上開說明，被告上訴應認違背刑事訴訟法第361條第2項「上訴書狀應敘述具體理由」之規定，依同法第367條前段規定，應以判決駁回上訴，並不經言詞辯論為之。四、據上論斷，應依刑事訴訟法第367條前段、第372條，判決如主文。中華民國100年1月10日刑事第十三庭審判長法官曾德水法官王復生法官楊貴雄以上正本證明與原本無異。如不服本判決，應於收受送達後10日內向本院提出上訴書狀，其未敘述上訴之理由者並得於提起上訴後10日內向本院補提理由書（均須按他造當事人之人數附繕本）「切勿逕送上級法院」。書記官邵淑津中華民國100年1月12日",
  "characters": {
    "judges": [
      "曾德水",
      "王復生",
      "楊貴雄"
    ],
    "prosecutors": [

    ],
    "lawyers": [

    ],
    "clerks": [
      "邵淑津"
    ],
    "plaintiffs": [

    ],
    "defendants": [
      "李世光"
    ],
    "prosecutor_office": [

    ],
    "creditors": [

    ],
    "debtors": [

    ],
    "judicial_associate_officer": [

    ]
  },
  "adjudged_at": "2011-01-10",
  "created_at": "2016-02-13 08:51:55",
  "updated_at": "2016-02-13 08:51:55"
}