{
  "identify": "MLD-94-苗簡-530-20051213-1",
  "court": {
    "name": "臺灣苗栗地方法院",
    "code": "MLD"
  },
  "division": {
    "name": "民事",
    "code": "V"
  },
  "year": 94,
  "word": "苗簡",
  "number": "530",
  "jcheck": "1",
  "reason": "清償借款",
  "content": "臺灣苗栗地方法院民事簡易判決         94年度苗簡字第530號\n原      告  美商花旗銀行股份有限公司\n法定代理人  丙○○\n訴訟代理人  甲○○\n            田永昌\n被      告  乙○○\n上列當事間請求清償借款事件，於民國94年11月29日辯論終結，\n本院判決如下：\n    主  文\n原告之訴駁回。\n訴訟費用由原告負擔。\n    事實及理由\n一、原告起訴主張：被告於民國93年11月4 日與原告訂立READY\n    CASH現金卡貸款契約，並持用原告所發行卡號0000-0000-00\n    00-0000 之現金卡，約定被告就使用系爭現金卡所生之債務\n    ，負全部給付責任，有現金卡申請書暨約定條款可證。被告\n    領用系爭現金卡後，約定上開借款額度動用期限自開戶日起\n    為期1 年，屆期如兩造對本合約之內容無異議，則無須另為\n    通知，得以同一內容延長1 年，不另換約，其後每年屆期時\n    亦同；上開借款額度由被告在原告開設之帳戶內，憑READY\n    CASH現金卡向已參加自動化服務機器跨行共用系統之本行或\n    其他金融機構自動化付款機隨時向原告取款，提領現金之利\n    息計算方式自提領入帳日起至清償日止，依提領金額按年息\n    18％計算，被告應自借款日起以1 個月為1 期清償借款，每\n    期最低應繳金額以尚欠交易金額之3 ％計算，若金額小於新\n    臺幣（下同）1,000 元以1,000 元計算，逾期未繳款，即喪\n    失期限利益，被告應將所欠消費借貸款全數一次清償；利息\n    按年息18％按月計付，逾期未繳款時，並加計自逾期之日起\n    以90日為計算上限，每逾一繳款截止日，應按月繳付當期應\n    負帳款扣除循環利息、調帳金額、各項手續費（含逾期滯納\n    金）或已付金額後之未繳清金額計算如附表所示之逾期滯納\n    金。詎被告至94年1 月15日止，現金卡款項尚餘107,329 元\n    未按期清償，迭經催討無效，爰依消費借貸之法律關係，請\n    求被告返還借款，並聲明：被告給應給付原告107,329 元及\n    自94年3 月4 日起至清償日止，按年息18% 計算之利息。\n二、被告則以：被告從未向原告申請現金卡，亦未向原告借錢，\n    且未收過相關帳單，申請書上之簽名並非被告所簽。又現居\n    地址、電話、聯絡人劉勝樟、公司的名稱、住址、電話等資\n    料均不正確。被告嗣後知悉訴外人林建志（即被告哥哥）拿\n    被告資料申請並予以盜刷，業經本院刑事庭93年度訴字第37\n    5 號偽造文書事件審理中，故此筆消費債務既非被告所借貸\n    ，自不必負擔該筆債務等語，資為抗辯，並聲明原告之訴駁\n    回。\n三、法院之判斷：\n（一）本件依訴外人林建志於94年2 月3 日本院93年度訴字第37\n      5 號之刑事案件準備程序中陳述：「因我另有冒用我弟弟\n      乙○○的名義去申請信用卡、現金卡，也有拿（原卷誤繕\n      為『那』）這些卡去消費或領錢，我要自首此部份之犯罪\n      事實。」；「我希望能一併處理冒名乙○○名義申請信用\n      卡等事，用乙○○名義的信用卡消費有繳錢」；「冒名乙\n      ○○部分之帳單寄到竹南鎮○○路十一號朋友家，所以我\n      家人都不知道我冒用上開二人之名義申請信用卡及現金卡\n      。」復又於苗栗縣警察局竹南分局調查筆錄中陳述：「乙\n      ○○是我弟弟，我們是住在一起，我沒有經過乙○○同意\n      趁他不在的時候，拿走他的身分證影印後再拿去申請金融\n      卡，時間我記不起來。」；「乙○○的部分是93年底利用\n      乙○○的證件申辦金融卡使用。」「該11張金融卡申請書\n      及消費明細簽名都是我簽的，他們（乙○○及林柏成）2\n      人不知情。」（見本院93年度訴字第375 號刑事案件卷第\n      34至36頁、第137 至139 頁），且經本院依職權調閱本院\n      刑事庭93年度訴字第375 號、93年度苗簡字第567 號、94\n      年度附民字第11號等刑事卷宗以及臺灣苗栗地方法院檢察\n      署93年度偵字第2147號偵查卷宗等卷查核屬實。而原告迄\n      未提出其他證據證明該現金卡及帳款係由被告所申請及借\n      貸，是以，被告上揭所辯應屬可信。\n（二）從而，原告據以提起本訴，訴請被告給付如訴之聲明所示\n      之借款及利息，為無理由，不應准許。\n四、本判決事證已臻明確，兩造其餘攻擊防禦及舉證，核與本判\n    決結果無影響，爰不另一一論述，附此序明。\n五、據上論結：本件原告之訴為無理由，依民事訴訟法第436 條\n    第2項、第78條，判決如主文。\n中    華    民    國    94    年    12    月    13    日\n                  苗栗簡易庭  法  官  林靜雯\n以上正本係照原本作成。\n如對本判決上訴，須於判決送達後20日內向本院提出上訴狀（均\n須按他造當事人之人數附繕本）。\n                              書記官  劉碧雯\n中    華    民    國    94    年    12    月    13    日\n",
  "structure": {
    "main": "原告之訴駁回。\n訴訟費用由原告負擔。",
    "fact": "一、原告起訴主張：被告於民國93年11月4 日與原告訂立READY\n    CASH現金卡貸款契約，並持用原告所發行卡號0000-0000-00\n    00-0000 之現金卡，約定被告就使用系爭現金卡所生之債務\n    ，負全部給付責任，有現金卡申請書暨約定條款可證。被告\n    領用系爭現金卡後，約定上開借款額度動用期限自開戶日起\n    為期1 年，屆期如兩造對本合約之內容無異議，則無須另為\n    通知，得以同一內容延長1 年，不另換約，其後每年屆期時\n    亦同；上開借款額度由被告在原告開設之帳戶內，憑READY\n    CASH現金卡向已參加自動化服務機器跨行共用系統之本行或\n    其他金融機構自動化付款機隨時向原告取款，提領現金之利\n    息計算方式自提領入帳日起至清償日止，依提領金額按年息\n    18％計算，被告應自借款日起以1 個月為1 期清償借款，每\n    期最低應繳金額以尚欠交易金額之3 ％計算，若金額小於新\n    臺幣（下同）1,000 元以1,000 元計算，逾期未繳款，即喪\n    失期限利益，被告應將所欠消費借貸款全數一次清償；利息\n    按年息18％按月計付，逾期未繳款時，並加計自逾期之日起\n    以90日為計算上限，每逾一繳款截止日，應按月繳付當期應\n    負帳款扣除循環利息、調帳金額、各項手續費（含逾期滯納\n    金）或已付金額後之未繳清金額計算如附表所示之逾期滯納\n    金。詎被告至94年1 月15日止，現金卡款項尚餘107,329 元\n    未按期清償，迭經催討無效，爰依消費借貸之法律關係，請\n    求被告返還借款，並聲明：被告給應給付原告107,329 元及\n    自94年3 月4 日起至清償日止，按年息18% 計算之利息。\n二、被告則以：被告從未向原告申請現金卡，亦未向原告借錢，\n    且未收過相關帳單，申請書上之簽名並非被告所簽。又現居\n    地址、電話、聯絡人劉勝樟、公司的名稱、住址、電話等資\n    料均不正確。被告嗣後知悉訴外人林建志（即被告哥哥）拿\n    被告資料申請並予以盜刷，業經本院刑事庭93年度訴字第37\n    5 號偽造文書事件審理中，故此筆消費債務既非被告所借貸\n    ，自不必負擔該筆債務等語，資為抗辯，並聲明原告之訴駁\n    回。\n三、法院之判斷：\n（一）本件依訴外人林建志於94年2 月3 日本院93年度訴字第37\n      5 號之刑事案件準備程序中陳述：「因我另有冒用我弟弟\n      乙○○的名義去申請信用卡、現金卡，也有拿（原卷誤繕\n      為『那』）這些卡去消費或領錢，我要自首此部份之犯罪\n      事實。」；「我希望能一併處理冒名乙○○名義申請信用\n      卡等事，用乙○○名義的信用卡消費有繳錢」；「冒名乙\n      ○○部分之帳單寄到竹南鎮○○路十一號朋友家，所以我\n      家人都不知道我冒用上開二人之名義申請信用卡及現金卡\n      。」復又於苗栗縣警察局竹南分局調查筆錄中陳述：「乙\n      ○○是我弟弟，我們是住在一起，我沒有經過乙○○同意\n      趁他不在的時候，拿走他的身分證影印後再拿去申請金融\n      卡，時間我記不起來。」；「乙○○的部分是93年底利用\n      乙○○的證件申辦金融卡使用。」「該11張金融卡申請書\n      及消費明細簽名都是我簽的，他們（乙○○及林柏成）2\n      人不知情。」（見本院93年度訴字第375 號刑事案件卷第\n      34至36頁、第137 至139 頁），且經本院依職權調閱本院\n      刑事庭93年度訴字第375 號、93年度苗簡字第567 號、94\n      年度附民字第11號等刑事卷宗以及臺灣苗栗地方法院檢察\n      署93年度偵字第2147號偵查卷宗等卷查核屬實。而原告迄\n      未提出其他證據證明該現金卡及帳款係由被告所申請及借\n      貸，是以，被告上揭所辯應屬可信。\n（二）從而，原告據以提起本訴，訴請被告給付如訴之聲明所示\n      之借款及利息，為無理由，不應准許。\n四、本判決事證已臻明確，兩造其餘攻擊防禦及舉證，核與本判\n    決結果無影響，爰不另一一論述，附此序明。\n五、據上論結：本件原告之訴為無理由，依民事訴訟法第436 條\n    第2項、第78條，判決如主文。",
    "reason": "一、原告起訴主張：被告於民國93年11月4 日與原告訂立READY\n    CASH現金卡貸款契約，並持用原告所發行卡號0000-0000-00\n    00-0000 之現金卡，約定被告就使用系爭現金卡所生之債務\n    ，負全部給付責任，有現金卡申請書暨約定條款可證。被告\n    領用系爭現金卡後，約定上開借款額度動用期限自開戶日起\n    為期1 年，屆期如兩造對本合約之內容無異議，則無須另為\n    通知，得以同一內容延長1 年，不另換約，其後每年屆期時\n    亦同；上開借款額度由被告在原告開設之帳戶內，憑READY\n    CASH現金卡向已參加自動化服務機器跨行共用系統之本行或\n    其他金融機構自動化付款機隨時向原告取款，提領現金之利\n    息計算方式自提領入帳日起至清償日止，依提領金額按年息\n    18％計算，被告應自借款日起以1 個月為1 期清償借款，每\n    期最低應繳金額以尚欠交易金額之3 ％計算，若金額小於新\n    臺幣（下同）1,000 元以1,000 元計算，逾期未繳款，即喪\n    失期限利益，被告應將所欠消費借貸款全數一次清償；利息\n    按年息18％按月計付，逾期未繳款時，並加計自逾期之日起\n    以90日為計算上限，每逾一繳款截止日，應按月繳付當期應\n    負帳款扣除循環利息、調帳金額、各項手續費（含逾期滯納\n    金）或已付金額後之未繳清金額計算如附表所示之逾期滯納\n    金。詎被告至94年1 月15日止，現金卡款項尚餘107,329 元\n    未按期清償，迭經催討無效，爰依消費借貸之法律關係，請\n    求被告返還借款，並聲明：被告給應給付原告107,329 元及\n    自94年3 月4 日起至清償日止，按年息18% 計算之利息。\n二、被告則以：被告從未向原告申請現金卡，亦未向原告借錢，\n    且未收過相關帳單，申請書上之簽名並非被告所簽。又現居\n    地址、電話、聯絡人劉勝樟、公司的名稱、住址、電話等資\n    料均不正確。被告嗣後知悉訴外人林建志（即被告哥哥）拿\n    被告資料申請並予以盜刷，業經本院刑事庭93年度訴字第37\n    5 號偽造文書事件審理中，故此筆消費債務既非被告所借貸\n    ，自不必負擔該筆債務等語，資為抗辯，並聲明原告之訴駁\n    回。\n三、法院之判斷：\n（一）本件依訴外人林建志於94年2 月3 日本院93年度訴字第37\n      5 號之刑事案件準備程序中陳述：「因我另有冒用我弟弟\n      乙○○的名義去申請信用卡、現金卡，也有拿（原卷誤繕\n      為『那』）這些卡去消費或領錢，我要自首此部份之犯罪\n      事實。」；「我希望能一併處理冒名乙○○名義申請信用\n      卡等事，用乙○○名義的信用卡消費有繳錢」；「冒名乙\n      ○○部分之帳單寄到竹南鎮○○路十一號朋友家，所以我\n      家人都不知道我冒用上開二人之名義申請信用卡及現金卡\n      。」復又於苗栗縣警察局竹南分局調查筆錄中陳述：「乙\n      ○○是我弟弟，我們是住在一起，我沒有經過乙○○同意\n      趁他不在的時候，拿走他的身分證影印後再拿去申請金融\n      卡，時間我記不起來。」；「乙○○的部分是93年底利用\n      乙○○的證件申辦金融卡使用。」「該11張金融卡申請書\n      及消費明細簽名都是我簽的，他們（乙○○及林柏成）2\n      人不知情。」（見本院93年度訴字第375 號刑事案件卷第\n      34至36頁、第137 至139 頁），且經本院依職權調閱本院\n      刑事庭93年度訴字第375 號、93年度苗簡字第567 號、94\n      年度附民字第11號等刑事卷宗以及臺灣苗栗地方法院檢察\n      署93年度偵字第2147號偵查卷宗等卷查核屬實。而原告迄\n      未提出其他證據證明該現金卡及帳款係由被告所申請及借\n      貸，是以，被告上揭所辯應屬可信。\n（二）從而，原告據以提起本訴，訴請被告給付如訴之聲明所示\n      之借款及利息，為無理由，不應准許。\n四、本判決事證已臻明確，兩造其餘攻擊防禦及舉證，核與本判\n    決結果無影響，爰不另一一論述，附此序明。\n五、據上論結：本件原告之訴為無理由，依民事訴訟法第436 條\n    第2項、第78條，判決如主文。"
  },
  "search": "臺灣苗栗地方法院民事簡易判決94年度苗簡字第530號原告美商花旗銀行股份有限公司法定代理人丙○○訴訟代理人甲○○田永昌被告乙○○上列當事間請求清償借款事件，於民國94年11月29日辯論終結，本院判決如下：主文原告之訴駁回。訴訟費用由原告負擔。事實及理由一、原告起訴主張：被告於民國93年11月4日與原告訂立READYCASH現金卡貸款契約，並持用原告所發行卡號0000-0000-0000-0000之現金卡，約定被告就使用系爭現金卡所生之債務，負全部給付責任，有現金卡申請書暨約定條款可證。被告領用系爭現金卡後，約定上開借款額度動用期限自開戶日起為期1年，屆期如兩造對本合約之內容無異議，則無須另為通知，得以同一內容延長1年，不另換約，其後每年屆期時亦同；上開借款額度由被告在原告開設之帳戶內，憑READYCASH現金卡向已參加自動化服務機器跨行共用系統之本行或其他金融機構自動化付款機隨時向原告取款，提領現金之利息計算方式自提領入帳日起至清償日止，依提領金額按年息18％計算，被告應自借款日起以1個月為1期清償借款，每期最低應繳金額以尚欠交易金額之3％計算，若金額小於新臺幣（下同）1,000元以1,000元計算，逾期未繳款，即喪失期限利益，被告應將所欠消費借貸款全數一次清償；利息按年息18％按月計付，逾期未繳款時，並加計自逾期之日起以90日為計算上限，每逾一繳款截止日，應按月繳付當期應負帳款扣除循環利息、調帳金額、各項手續費（含逾期滯納金）或已付金額後之未繳清金額計算如附表所示之逾期滯納金。詎被告至94年1月15日止，現金卡款項尚餘107,329元未按期清償，迭經催討無效，爰依消費借貸之法律關係，請求被告返還借款，並聲明：被告給應給付原告107,329元及自94年3月4日起至清償日止，按年息18%計算之利息。二、被告則以：被告從未向原告申請現金卡，亦未向原告借錢，且未收過相關帳單，申請書上之簽名並非被告所簽。又現居地址、電話、聯絡人劉勝樟、公司的名稱、住址、電話等資料均不正確。被告嗣後知悉訴外人林建志（即被告哥哥）拿被告資料申請並予以盜刷，業經本院刑事庭93年度訴字第375號偽造文書事件審理中，故此筆消費債務既非被告所借貸，自不必負擔該筆債務等語，資為抗辯，並聲明原告之訴駁回。三、法院之判斷：（一）本件依訴外人林建志於94年2月3日本院93年度訴字第375號之刑事案件準備程序中陳述：「因我另有冒用我弟弟乙○○的名義去申請信用卡、現金卡，也有拿（原卷誤繕為『那』）這些卡去消費或領錢，我要自首此部份之犯罪事實。」；「我希望能一併處理冒名乙○○名義申請信用卡等事，用乙○○名義的信用卡消費有繳錢」；「冒名乙○○部分之帳單寄到竹南鎮○○路十一號朋友家，所以我家人都不知道我冒用上開二人之名義申請信用卡及現金卡。」復又於苗栗縣警察局竹南分局調查筆錄中陳述：「乙○○是我弟弟，我們是住在一起，我沒有經過乙○○同意趁他不在的時候，拿走他的身分證影印後再拿去申請金融卡，時間我記不起來。」；「乙○○的部分是93年底利用乙○○的證件申辦金融卡使用。」「該11張金融卡申請書及消費明細簽名都是我簽的，他們（乙○○及林柏成）2人不知情。」（見本院93年度訴字第375號刑事案件卷第34至36頁、第137至139頁），且經本院依職權調閱本院刑事庭93年度訴字第375號、93年度苗簡字第567號、94年度附民字第11號等刑事卷宗以及臺灣苗栗地方法院檢察署93年度偵字第2147號偵查卷宗等卷查核屬實。而原告迄未提出其他證據證明該現金卡及帳款係由被告所申請及借貸，是以，被告上揭所辯應屬可信。（二）從而，原告據以提起本訴，訴請被告給付如訴之聲明所示之借款及利息，為無理由，不應准許。四、本判決事證已臻明確，兩造其餘攻擊防禦及舉證，核與本判決結果無影響，爰不另一一論述，附此序明。五、據上論結：本件原告之訴為無理由，依民事訴訟法第436條第2項、第78條，判決如主文。中華民國94年12月13日苗栗簡易庭法官林靜雯以上正本係照原本作成。如對本判決上訴，須於判決送達後20日內向本院提出上訴狀（均須按他造當事人之人數附繕本）。書記官劉碧雯中華民國94年12月13日",
  "characters": {
    "judges": [
      "林靜雯"
    ],
    "prosecutors": [

    ],
    "lawyers": [

    ],
    "clerks": [
      "劉碧雯"
    ],
    "plaintiffs": [
      "美商花旗銀行股份有限公司"
    ],
    "defendants": [
      "乙○○"
    ],
    "prosecutor_office": [

    ],
    "creditors": [

    ],
    "debtors": [

    ],
    "judicial_associate_officer": [

    ]
  },
  "adjudged_at": "2005-12-13",
  "created_at": "2016-02-07 02:41:41",
  "updated_at": "2016-02-07 02:41:41"
}