{
  "identify": "KLD-94-基簡-611-20051129-1",
  "court": {
    "name": "臺灣基隆地方法院",
    "code": "KLD"
  },
  "division": {
    "name": "民事",
    "code": "V"
  },
  "year": 94,
  "word": "基簡",
  "number": "611",
  "jcheck": "1",
  "reason": "遷讓房屋等",
  "content": "臺灣基隆地方法院民事裁定             94年度基簡字第611號\n原      告  甲○○\n被      告  乙○○\n上列當事人間遷讓房屋等事件，本院裁定如下：\n    主  文\n原告之訴及其假執行之聲請均駁回。\n訴訟費用由原告負擔。\n    理  由\n一、按提起民事訴訟，應依民事訴訟法第77條之13規定繳納裁判\n    費，此為必備之程式，又原告之訴，有民事訴訟法第249條\n    第1項所列各款情形之一，依其情形可以補正，經審判長定\n    期間命其補正而不補正者，法院應以裁定駁回之，亦為同法\n    條第1項所明定。\n二、本件原告起訴，僅繳納裁判費新台幣（以下同）1,000元，\n    亦未於訴狀載明系爭訴訟標的價額，使本院無從核定訴訟標\n    的價額，以裁定命其補繳裁判費，經本院於民國94年9月29\n    日年命原告於收受通知後五日內查報系爭訴訟標的價額，並\n    按系爭訴訟標的價額補繳裁判費，該項通知已於94年10月13\n    日年有送達證書附卷可憑，原告逾期迄未補正，其訴應認為\n    不合法，其假執行聲請亦缺乏宣告之依據，均應予駁回。\n三、依民事訴訟法第249條第1項第6款、第95條、第78條，裁定\n    如主文。\n中    華    民    國    94    年    11    月    29    日\n                  民事庭法  官  蔡聰明\n以上正本係照原本作成。\n如對本裁定抗告，應於本裁定送達後10日內向本院提出抗告狀，\n並繳納抗告裁判費新臺幣1000元。\n中    華    民    國    94    年    11    月    29    日\n                        書記官  王佩珠\n",
  "structure": {
    "main": "原告之訴及其假執行之聲請均駁回。\n訴訟費用由原告負擔。",
    "reason": "一、按提起民事訴訟，應依民事訴訟法第77條之13規定繳納裁判\n    費，此為必備之程式，又原告之訴，有民事訴訟法第249條\n    第1項所列各款情形之一，依其情形可以補正，經審判長定\n    期間命其補正而不補正者，法院應以裁定駁回之，亦為同法\n    條第1項所明定。\n二、本件原告起訴，僅繳納裁判費新台幣（以下同）1,000元，\n    亦未於訴狀載明系爭訴訟標的價額，使本院無從核定訴訟標\n    的價額，以裁定命其補繳裁判費，經本院於民國94年9月29\n    日年命原告於收受通知後五日內查報系爭訴訟標的價額，並\n    按系爭訴訟標的價額補繳裁判費，該項通知已於94年10月13\n    日年有送達證書附卷可憑，原告逾期迄未補正，其訴應認為\n    不合法，其假執行聲請亦缺乏宣告之依據，均應予駁回。\n三、依民事訴訟法第249條第1項第6款、第95條、第78條，裁定\n    如主文。"
  },
  "search": "臺灣基隆地方法院民事裁定94年度基簡字第611號原告甲○○被告乙○○上列當事人間遷讓房屋等事件，本院裁定如下：主文原告之訴及其假執行之聲請均駁回。訴訟費用由原告負擔。理由一、按提起民事訴訟，應依民事訴訟法第77條之13規定繳納裁判費，此為必備之程式，又原告之訴，有民事訴訟法第249條第1項所列各款情形之一，依其情形可以補正，經審判長定期間命其補正而不補正者，法院應以裁定駁回之，亦為同法條第1項所明定。二、本件原告起訴，僅繳納裁判費新台幣（以下同）1,000元，亦未於訴狀載明系爭訴訟標的價額，使本院無從核定訴訟標的價額，以裁定命其補繳裁判費，經本院於民國94年9月29日年命原告於收受通知後五日內查報系爭訴訟標的價額，並按系爭訴訟標的價額補繳裁判費，該項通知已於94年10月13日年有送達證書附卷可憑，原告逾期迄未補正，其訴應認為不合法，其假執行聲請亦缺乏宣告之依據，均應予駁回。三、依民事訴訟法第249條第1項第6款、第95條、第78條，裁定如主文。中華民國94年11月29日民事庭法官蔡聰明以上正本係照原本作成。如對本裁定抗告，應於本裁定送達後10日內向本院提出抗告狀，並繳納抗告裁判費新臺幣1000元。中華民國94年11月29日書記官王佩珠",
  "characters": {
    "judges": [
      "蔡聰明"
    ],
    "prosecutors": [

    ],
    "lawyers": [

    ],
    "clerks": [
      "王佩珠"
    ],
    "plaintiffs": [
      "甲○○"
    ],
    "defendants": [
      "乙○○"
    ],
    "prosecutor_office": [

    ],
    "creditors": [

    ],
    "debtors": [

    ],
    "judicial_associate_officer": [

    ]
  },
  "adjudged_at": "2005-11-29",
  "created_at": "2016-02-07 00:38:29",
  "updated_at": "2016-02-07 00:38:29"
}