{
  "identify": "TCD-94-保險-20-20051129-4",
  "court": {
    "name": "臺灣臺中地方法院",
    "code": "TCD"
  },
  "division": {
    "name": "民事",
    "code": "V"
  },
  "year": 94,
  "word": "保險",
  "number": "20",
  "jcheck": "4",
  "reason": "給付保險費",
  "content": "臺灣臺中地方法院民事裁定  94年度保險字第20號\n原      告  中建營造有限公司\n法定代理人  乙○○○\n訴訟代理人  吳紹貴    律師\n複  代理人  王朝揚    律師\n被      告  經濟部水利署\n法定代理人  丙○○\n訴訟代理人  甲○○\n複代理人    魏朝煥    律師\n當事人間給付保險費事件，本院於民國94年11月18日所為之判決\n，其正本應更正如左：\n    主    文\n原判決當事人欄之記載，應更正為如本裁定當事人欄之記載。\n    理      由\n一、按判決如有誤寫、誤算或其他類此之顯然錯誤者，法院得依\n    聲請或依職權以裁定更正之，其正本與原本不符者亦同，民\n    事訴訟法第232條第1項定有明文。\n二、查本院前開之判決正本有如主文所示之顯然錯誤，應予更正\n    。\n三、依首開規定裁定如主文。\n中    華    民    國    94    年    11    月    29    日\n                  民事第三庭    法  官  陳文爵\n正本係照原本作成。\n如不服本裁定應於送達後10日內向本院提出抗告狀，並繳納抗告\n費新臺幣1,000元。\n中    華    民    國    94    年    11    月    29    日\n                                書記官\n",
  "structure": {
    "main": "原判決當事人欄之記載，應更正為如本裁定當事人欄之記載。",
    "reason": "一、按判決如有誤寫、誤算或其他類此之顯然錯誤者，法院得依\n    聲請或依職權以裁定更正之，其正本與原本不符者亦同，民\n    事訴訟法第232條第1項定有明文。\n二、查本院前開之判決正本有如主文所示之顯然錯誤，應予更正\n    。\n三、依首開規定裁定如主文。"
  },
  "search": "臺灣臺中地方法院民事裁定94年度保險字第20號原告中建營造有限公司法定代理人乙○○○訴訟代理人吳紹貴律師複代理人王朝揚律師被告經濟部水利署法定代理人丙○○訴訟代理人甲○○複代理人魏朝煥律師當事人間給付保險費事件，本院於民國94年11月18日所為之判決，其正本應更正如左：主文原判決當事人欄之記載，應更正為如本裁定當事人欄之記載。理由一、按判決如有誤寫、誤算或其他類此之顯然錯誤者，法院得依聲請或依職權以裁定更正之，其正本與原本不符者亦同，民事訴訟法第232條第1項定有明文。二、查本院前開之判決正本有如主文所示之顯然錯誤，應予更正。三、依首開規定裁定如主文。中華民國94年11月29日民事第三庭法官陳文爵正本係照原本作成。如不服本裁定應於送達後10日內向本院提出抗告狀，並繳納抗告費新臺幣1,000元。中華民國94年11月29日書記官",
  "characters": {
    "judges": [
      "陳文爵"
    ],
    "prosecutors": [

    ],
    "lawyers": [

    ],
    "clerks": [

    ],
    "plaintiffs": [
      "中建營造有限公司"
    ],
    "defendants": [
      "經濟部水利署"
    ],
    "prosecutor_office": [

    ],
    "creditors": [

    ],
    "debtors": [

    ],
    "judicial_associate_officer": [

    ]
  },
  "adjudged_at": "2005-11-29",
  "created_at": "2016-02-07 00:33:58",
  "updated_at": "2016-02-07 00:33:58"
}