{
  "identify": "TND-94-易緝-77-20051129-1",
  "court": {
    "name": "臺灣臺南地方法院",
    "code": "TND"
  },
  "division": {
    "name": "刑事",
    "code": "M"
  },
  "year": 94,
  "word": "易緝",
  "number": "77",
  "jcheck": "1",
  "reason": "竊盜",
  "content": "臺灣臺南地方法院刑事判決              94年度易緝字第77號\n公  訴  人  臺灣臺南地方法院檢察署檢察官\n被      告  甲○○\n                    號七樓\n上列被告因竊盜案件，經檢察官提起公訴（92年度偵字第11758\n號），暨移送併辦（92年度偵字第10730號），被告於準備程序\n中為有罪之陳述，本院裁定進行簡式審判程序，判決如下：\n    主  文\n甲○○連續攜帶兇器竊盜，處有期徒刑貳年，緩刑伍年。\n    事  實\n一、甲○○基於意圖為自己不法所有之概括犯意，分別於(一)民國\n    九十二年十月二十日十四時五十分許，在臺北縣淡水鎮○○\n    路七十二巷六號前，見己○○所有之車號ＨＦ－８６６１號\n    自小貨車，停放路邊，鑰匙未拔下，即發動電門後駕車離去\n    ，而竊取之（該車已於九十二年十月二十七日十二時許，為\n    警在雲林縣尋獲）。又於(二)九十二年十月二十六日十七時五\n    十分許，在臺南市○○路○段一三三巷一三０號前，見戊○\n    ○所有之車牌號碼Ｄ５－０５８２號自小客車停放於路旁，\n    鑰匙未拔下，即徒手竊取之，並供己使用。嗣於同日十九時\n    二十分許，為警在臺南縣永康市○○街六十巷十二號前查獲\n    ，並扣得上開自小客車。詎甲○○仍不知悔改，復承前揭犯\n    意，於(三)九十二年十月二十九日十一時許，在臺北縣淡水鎮\n    ○○街一二０巷四十五弄口，見丙○○所有之車牌號碼ＧＶ\n    －８４０２號自小貨車，停於路旁，車窗未關，即徒手打開\n    車門，並以車內之一字起子插入電門旋轉發動後，竊得之（\n    該車已於九十二年十月三十日十五時三十分許，為丙○○自\n    行在臺北縣八里鄉廖添丁廟附近天橋下尋獲）。又於(四)九十\n    二年十月三十日十八時三十分許，在臺北縣八里鄉訊塘埔二\n    十三號前，見車牌號碼ＣＶ－３１７９號自小貨車使用人丁\n    ○○，將車停於路旁，鑰匙未拔下，即發動電門後，駕車逃\n    離現場。嗣於同日二十三時許，為警在臺北縣八里鄉台十五\n    線八里焚化廠前，為警查獲，並扣得該自小貨車，員警再依\n    甲○○所供而查知(一)(三)之犯行。\n二、案經臺南市警察局移送臺灣臺南地方法院檢察署檢察官偵查\n    起訴暨由臺灣士林地方法院檢察署移送併辦。\n    理  由\n一、上開犯罪事實有下列證據足資證明：\n  (一)被告自白。\n  (二)被害人己○○、戊○○、丙○○及丁○○指訴。\n  (三)贓物認領保管單一紙、臺南市警察局車輛失竊暨尋獲證明單\n    各一紙、車輛竊盜資料個別查詢報表一紙。\n  (四)臺北縣政府警察局贓物認領保管單、臺北縣政府車輛失竊電\n    腦輸入單、雲林縣警察局車輛尋獲電腦輸入單、ＣＶ－３１\n    ７９號自小貨車行車執照各一紙。\n  (五)查獲車輛照片共十一張。\n二、按一字起子係金屬製品，質硬型尖，客觀上足以危害他人生\n    命、身體之安全，被告持以行竊，核其所為編號(三)之犯行，\n    係犯刑法第三百二十一條第三項攜帶兇器竊盜罪。其餘所為\n    犯行，係犯同法第三百二十條第一項普通竊盜罪。被告先後\n    多次犯行，時間緊接，方法相同，觸犯構成要件相同之罪，\n    顯係基於概括犯意反覆而為，應依連續犯規定論以較重之加\n    重竊盜罪，並依法加重其刑。公訴人雖僅就被告所為編號(一)\n    犯行提起公訴，然檢察官就犯罪事實一部起訴者，效力及於\n    全部，本件未起訴部分與起訴部分有連續犯關係，已如前述\n    ，本院自應就屬裁判上一罪之他部一併加以審判。爰審酌被\n    告正值年盛力壯，不思以正途取財，反一再行竊，且未曾賠\n    償過被害人損失，殊為不該，惟被告犯後已知坦認犯行，並\n    深表悔意，態度良好，而被害人被竊車輛嗣後均已尋回，所\n    受損失程度尚非十分嚴重等一切情狀，量處如主文所示之刑\n    。末查，被告前因違反麻醉藥品管理條例等案件，經法院判\n    處應執行有期徒刑三年六月，於八十五年三月二十五日執行\n    完畢有後，五年以內未曾受有期徒刑以上刑之宣告，有被告\n    全國前案紀錄表附卷可按，本次被告雖連續行竊，惟據被告\n    供稱，當時因失業，為求生活，一時失慮而罹刑章，然目前\n    已有一份穩定工作，且該份工作已從事有二年之久，並提出\n    扣繳憑單及支領薪資證明等為證，本院認經此偵審程序，被\n    告當已知所警惕，信無再犯之虞，併宣告緩刑五年，以啟自\n    新。\n據上論斷，應依刑事訴訟法第二百九十九條第一項前段、第二百\n七十三條之一第一項，刑法第五十六條、第三百二十一條第一項\n第三款、第七十四條第二款，判決如主文。\n本案經檢察官乙○○到庭執行職務\n中    華    民    國    94    年    11    月    29    日\n                  刑事第五庭    法  官  包梅真\n以上正本證明與原本無異。\n如不服本判決，應於收受送達後10日內向本院提出上訴書狀（應\n附繕本）。\n                                書記官  張富\n中    華    民    國    94    年    11    月    30    日\n附錄法條：\n刑法第三百二十一條第一項第三款\n犯竊盜罪而有左列情形之一者，處六月以上、五年以下有期徒刑\n：\n二  毀越門扇、牆垣或其他安全設備而犯之者。\n",
  "structure": {
    "main": "甲○○連續攜帶兇器竊盜，處有期徒刑貳年，緩刑伍年。",
    "fact": "一、甲○○基於意圖為自己不法所有之概括犯意，分別於(一)民國\n    九十二年十月二十日十四時五十分許，在臺北縣淡水鎮○○\n    路七十二巷六號前，見己○○所有之車號ＨＦ－８６６１號\n    自小貨車，停放路邊，鑰匙未拔下，即發動電門後駕車離去\n    ，而竊取之（該車已於九十二年十月二十七日十二時許，為\n    警在雲林縣尋獲）。又於(二)九十二年十月二十六日十七時五\n    十分許，在臺南市○○路○段一三三巷一三０號前，見戊○\n    ○所有之車牌號碼Ｄ５－０５８２號自小客車停放於路旁，\n    鑰匙未拔下，即徒手竊取之，並供己使用。嗣於同日十九時\n    二十分許，為警在臺南縣永康市○○街六十巷十二號前查獲\n    ，並扣得上開自小客車。詎甲○○仍不知悔改，復承前揭犯\n    意，於(三)九十二年十月二十九日十一時許，在臺北縣淡水鎮\n    ○○街一二０巷四十五弄口，見丙○○所有之車牌號碼ＧＶ\n    －８４０２號自小貨車，停於路旁，車窗未關，即徒手打開\n    車門，並以車內之一字起子插入電門旋轉發動後，竊得之（\n    該車已於九十二年十月三十日十五時三十分許，為丙○○自\n    行在臺北縣八里鄉廖添丁廟附近天橋下尋獲）。又於(四)九十\n    二年十月三十日十八時三十分許，在臺北縣八里鄉訊塘埔二\n    十三號前，見車牌號碼ＣＶ－３１７９號自小貨車使用人丁\n    ○○，將車停於路旁，鑰匙未拔下，即發動電門後，駕車逃\n    離現場。嗣於同日二十三時許，為警在臺北縣八里鄉台十五\n    線八里焚化廠前，為警查獲，並扣得該自小貨車，員警再依\n    甲○○所供而查知(一)(三)之犯行。\n二、案經臺南市警察局移送臺灣臺南地方法院檢察署檢察官偵查\n    起訴暨由臺灣士林地方法院檢察署移送併辦。",
    "reason": "一、上開犯罪事實有下列證據足資證明：\n  (一)被告自白。\n  (二)被害人己○○、戊○○、丙○○及丁○○指訴。\n  (三)贓物認領保管單一紙、臺南市警察局車輛失竊暨尋獲證明單\n    各一紙、車輛竊盜資料個別查詢報表一紙。\n  (四)臺北縣政府警察局贓物認領保管單、臺北縣政府車輛失竊電\n    腦輸入單、雲林縣警察局車輛尋獲電腦輸入單、ＣＶ－３１\n    ７９號自小貨車行車執照各一紙。\n  (五)查獲車輛照片共十一張。\n二、按一字起子係金屬製品，質硬型尖，客觀上足以危害他人生\n    命、身體之安全，被告持以行竊，核其所為編號(三)之犯行，\n    係犯刑法第三百二十一條第三項攜帶兇器竊盜罪。其餘所為\n    犯行，係犯同法第三百二十條第一項普通竊盜罪。被告先後\n    多次犯行，時間緊接，方法相同，觸犯構成要件相同之罪，\n    顯係基於概括犯意反覆而為，應依連續犯規定論以較重之加\n    重竊盜罪，並依法加重其刑。公訴人雖僅就被告所為編號(一)\n    犯行提起公訴，然檢察官就犯罪事實一部起訴者，效力及於\n    全部，本件未起訴部分與起訴部分有連續犯關係，已如前述\n    ，本院自應就屬裁判上一罪之他部一併加以審判。爰審酌被\n    告正值年盛力壯，不思以正途取財，反一再行竊，且未曾賠\n    償過被害人損失，殊為不該，惟被告犯後已知坦認犯行，並\n    深表悔意，態度良好，而被害人被竊車輛嗣後均已尋回，所\n    受損失程度尚非十分嚴重等一切情狀，量處如主文所示之刑\n    。末查，被告前因違反麻醉藥品管理條例等案件，經法院判\n    處應執行有期徒刑三年六月，於八十五年三月二十五日執行\n    完畢有後，五年以內未曾受有期徒刑以上刑之宣告，有被告\n    全國前案紀錄表附卷可按，本次被告雖連續行竊，惟據被告\n    供稱，當時因失業，為求生活，一時失慮而罹刑章，然目前\n    已有一份穩定工作，且該份工作已從事有二年之久，並提出\n    扣繳憑單及支領薪資證明等為證，本院認經此偵審程序，被\n    告當已知所警惕，信無再犯之虞，併宣告緩刑五年，以啟自\n    新。\n據上論斷，應依刑事訴訟法第二百九十九條第一項前段、第二百\n七十三條之一第一項，刑法第五十六條、第三百二十一條第一項\n第三款、第七十四條第二款，判決如主文。\n本案經檢察官乙○○到庭執行職務\n中    華    民    國    94    年    11    月    29    日\n                  刑事第五庭    法  官  包梅真\n以上正本證明與原本無異。\n如不服本判決，應於收受送達後10日內向本院提出上訴書狀（應\n附繕本）。\n                                書記官  張富"
  },
  "search": "臺灣臺南地方法院刑事判決94年度易緝字第77號公訴人臺灣臺南地方法院檢察署檢察官被告甲○○號七樓上列被告因竊盜案件，經檢察官提起公訴（92年度偵字第11758號），暨移送併辦（92年度偵字第10730號），被告於準備程序中為有罪之陳述，本院裁定進行簡式審判程序，判決如下：主文甲○○連續攜帶兇器竊盜，處有期徒刑貳年，緩刑伍年。事實一、甲○○基於意圖為自己不法所有之概括犯意，分別於(一)民國九十二年十月二十日十四時五十分許，在臺北縣淡水鎮○○路七十二巷六號前，見己○○所有之車號ＨＦ－８６６１號自小貨車，停放路邊，鑰匙未拔下，即發動電門後駕車離去，而竊取之（該車已於九十二年十月二十七日十二時許，為警在雲林縣尋獲）。又於(二)九十二年十月二十六日十七時五十分許，在臺南市○○路○段一三三巷一三０號前，見戊○○所有之車牌號碼Ｄ５－０５８２號自小客車停放於路旁，鑰匙未拔下，即徒手竊取之，並供己使用。嗣於同日十九時二十分許，為警在臺南縣永康市○○街六十巷十二號前查獲，並扣得上開自小客車。詎甲○○仍不知悔改，復承前揭犯意，於(三)九十二年十月二十九日十一時許，在臺北縣淡水鎮○○街一二０巷四十五弄口，見丙○○所有之車牌號碼ＧＶ－８４０２號自小貨車，停於路旁，車窗未關，即徒手打開車門，並以車內之一字起子插入電門旋轉發動後，竊得之（該車已於九十二年十月三十日十五時三十分許，為丙○○自行在臺北縣八里鄉廖添丁廟附近天橋下尋獲）。又於(四)九十二年十月三十日十八時三十分許，在臺北縣八里鄉訊塘埔二十三號前，見車牌號碼ＣＶ－３１７９號自小貨車使用人丁○○，將車停於路旁，鑰匙未拔下，即發動電門後，駕車逃離現場。嗣於同日二十三時許，為警在臺北縣八里鄉台十五線八里焚化廠前，為警查獲，並扣得該自小貨車，員警再依甲○○所供而查知(一)(三)之犯行。二、案經臺南市警察局移送臺灣臺南地方法院檢察署檢察官偵查起訴暨由臺灣士林地方法院檢察署移送併辦。理由一、上開犯罪事實有下列證據足資證明：(一)被告自白。(二)被害人己○○、戊○○、丙○○及丁○○指訴。(三)贓物認領保管單一紙、臺南市警察局車輛失竊暨尋獲證明單各一紙、車輛竊盜資料個別查詢報表一紙。(四)臺北縣政府警察局贓物認領保管單、臺北縣政府車輛失竊電腦輸入單、雲林縣警察局車輛尋獲電腦輸入單、ＣＶ－３１７９號自小貨車行車執照各一紙。(五)查獲車輛照片共十一張。二、按一字起子係金屬製品，質硬型尖，客觀上足以危害他人生命、身體之安全，被告持以行竊，核其所為編號(三)之犯行，係犯刑法第三百二十一條第三項攜帶兇器竊盜罪。其餘所為犯行，係犯同法第三百二十條第一項普通竊盜罪。被告先後多次犯行，時間緊接，方法相同，觸犯構成要件相同之罪，顯係基於概括犯意反覆而為，應依連續犯規定論以較重之加重竊盜罪，並依法加重其刑。公訴人雖僅就被告所為編號(一)犯行提起公訴，然檢察官就犯罪事實一部起訴者，效力及於全部，本件未起訴部分與起訴部分有連續犯關係，已如前述，本院自應就屬裁判上一罪之他部一併加以審判。爰審酌被告正值年盛力壯，不思以正途取財，反一再行竊，且未曾賠償過被害人損失，殊為不該，惟被告犯後已知坦認犯行，並深表悔意，態度良好，而被害人被竊車輛嗣後均已尋回，所受損失程度尚非十分嚴重等一切情狀，量處如主文所示之刑。末查，被告前因違反麻醉藥品管理條例等案件，經法院判處應執行有期徒刑三年六月，於八十五年三月二十五日執行完畢有後，五年以內未曾受有期徒刑以上刑之宣告，有被告全國前案紀錄表附卷可按，本次被告雖連續行竊，惟據被告供稱，當時因失業，為求生活，一時失慮而罹刑章，然目前已有一份穩定工作，且該份工作已從事有二年之久，並提出扣繳憑單及支領薪資證明等為證，本院認經此偵審程序，被告當已知所警惕，信無再犯之虞，併宣告緩刑五年，以啟自新。據上論斷，應依刑事訴訟法第二百九十九條第一項前段、第二百七十三條之一第一項，刑法第五十六條、第三百二十一條第一項第三款、第七十四條第二款，判決如主文。本案經檢察官乙○○到庭執行職務中華民國94年11月29日刑事第五庭法官包梅真以上正本證明與原本無異。如不服本判決，應於收受送達後10日內向本院提出上訴書狀（應附繕本）。書記官張富中華民國94年11月30日附錄法條：刑法第三百二十一條第一項第三款犯竊盜罪而有左列情形之一者，處六月以上、五年以下有期徒刑：二毀越門扇、牆垣或其他安全設備而犯之者。",
  "characters": {
    "judges": [
      "包梅真"
    ],
    "prosecutors": [

    ],
    "lawyers": [

    ],
    "clerks": [
      "張富"
    ],
    "plaintiffs": [

    ],
    "defendants": [
      "甲○○"
    ],
    "prosecutor_office": [
      "臺灣臺南地方法院檢察署檢察官"
    ],
    "creditors": [

    ],
    "debtors": [

    ],
    "judicial_associate_officer": [

    ]
  },
  "adjudged_at": "2005-11-29",
  "created_at": "2016-02-07 00:47:19",
  "updated_at": "2016-02-07 00:47:19"
}