{
  "identify": "TPD-94-交易-550-20051130-1",
  "court": {
    "name": "臺灣臺北地方法院",
    "code": "TPD"
  },
  "division": {
    "name": "刑事",
    "code": "M"
  },
  "year": 94,
  "word": "交易",
  "number": "550",
  "jcheck": "1",
  "reason": "業務過失傷害",
  "content": "臺灣臺北地方法院刑事判決             94年度交易字第550號\n公  訴  人  臺灣臺北地方法院檢察署檢察官\n被      告  乙○○\n                      樓\n上列被告因業務過失傷害案件，經檢察官提起公訴（九十四年度\n偵字第一二五四一號），本院判決如下：\n    主  文\n本件公訴不受理。\n    理  由\n一、公訴意旨略以：被告乙○○為計程車司機，係以駕駛為其主\n    要業務之人，其於民國九十三年十一月十日七時三十分許，\n    駕駛車牌號碼七Ｑ—三八○號營業小客車，沿臺北市大安區\n    ○○○路由西向東行駛，行經忠孝東路、復興南路口欲右轉\n    時，本應注意轉彎時須注意後方來車，禮讓直行車先行，且\n    依當時情形，又無不能注意之情事，竟疏於注意，貿然右轉\n    ，適有告訴人甲○○○騎乘車牌號碼ＤＱＥ—三四○號機車\n    由西向東行經該路口，其左側車身遂遭被告車輛之右側車門\n    所撞，因而人車倒地，受有頭部外傷及身體多處擦傷、挫傷\n    等語，因認被告乙○○涉犯刑法第二百八十四條第二項前段\n    之業務過失傷害罪嫌。\n二、按告訴乃論之罪，告訴人於第一審辯論終結前得撤回其告訴\n    ，又告訴經撤回者，應諭知不受理之判決，並得不經言詞辯\n    論為之，刑事訴訟法第二百三十八條第一項、第三百零三條\n    第三款及第三百零七條分別定有明文。\n三、經查，本件業務過失傷害案件，公訴人認被告乙○○係涉犯\n    刑法第二百八十四條第二項前段之業務過失傷害罪嫌，依同\n    法第二百八十七條前段之規定，須告訴乃論。經查，告訴人\n    甲○○○於本院九十四年十一月二十四日準備程序時，已當\n    庭以言詞撤回其告訴，有準備程序筆錄在卷可參（見本院卷\n    第十一頁）可參，按諸上揭規定，本件爰不經言詞辯論，逕\n    為諭知不受理之判決。\n據上論斷，應依刑事訴訟法第三百零三條第三款、第三百零七條\n，判決如主文。\n中    華    民    國    94    年    11    月    30    日\n                  刑事第十四庭  審判長法  官  吳靜怡\n                                      法  官  孫萍萍\n                                      法  官  李家慧\n以上正本證明與原本無異\n如不服本判決，應於送達後10日內，向本院提出上訴狀\n中    華    民    國    94    年    11    月    30    日\n                                      書記官  林婉瑩\n",
  "structure": {
    "main": "本件公訴不受理。",
    "reason": "一、公訴意旨略以：被告乙○○為計程車司機，係以駕駛為其主\n    要業務之人，其於民國九十三年十一月十日七時三十分許，\n    駕駛車牌號碼七Ｑ—三八○號營業小客車，沿臺北市大安區\n    ○○○路由西向東行駛，行經忠孝東路、復興南路口欲右轉\n    時，本應注意轉彎時須注意後方來車，禮讓直行車先行，且\n    依當時情形，又無不能注意之情事，竟疏於注意，貿然右轉\n    ，適有告訴人甲○○○騎乘車牌號碼ＤＱＥ—三四○號機車\n    由西向東行經該路口，其左側車身遂遭被告車輛之右側車門\n    所撞，因而人車倒地，受有頭部外傷及身體多處擦傷、挫傷\n    等語，因認被告乙○○涉犯刑法第二百八十四條第二項前段\n    之業務過失傷害罪嫌。\n二、按告訴乃論之罪，告訴人於第一審辯論終結前得撤回其告訴\n    ，又告訴經撤回者，應諭知不受理之判決，並得不經言詞辯\n    論為之，刑事訴訟法第二百三十八條第一項、第三百零三條\n    第三款及第三百零七條分別定有明文。\n三、經查，本件業務過失傷害案件，公訴人認被告乙○○係涉犯\n    刑法第二百八十四條第二項前段之業務過失傷害罪嫌，依同\n    法第二百八十七條前段之規定，須告訴乃論。經查，告訴人\n    甲○○○於本院九十四年十一月二十四日準備程序時，已當\n    庭以言詞撤回其告訴，有準備程序筆錄在卷可參（見本院卷\n    第十一頁）可參，按諸上揭規定，本件爰不經言詞辯論，逕\n    為諭知不受理之判決。\n據上論斷，應依刑事訴訟法第三百零三條第三款、第三百零七條\n，判決如主文。"
  },
  "search": "臺灣臺北地方法院刑事判決94年度交易字第550號公訴人臺灣臺北地方法院檢察署檢察官被告乙○○樓上列被告因業務過失傷害案件，經檢察官提起公訴（九十四年度偵字第一二五四一號），本院判決如下：主文本件公訴不受理。理由一、公訴意旨略以：被告乙○○為計程車司機，係以駕駛為其主要業務之人，其於民國九十三年十一月十日七時三十分許，駕駛車牌號碼七Ｑ—三八○號營業小客車，沿臺北市大安區○○○路由西向東行駛，行經忠孝東路、復興南路口欲右轉時，本應注意轉彎時須注意後方來車，禮讓直行車先行，且依當時情形，又無不能注意之情事，竟疏於注意，貿然右轉，適有告訴人甲○○○騎乘車牌號碼ＤＱＥ—三四○號機車由西向東行經該路口，其左側車身遂遭被告車輛之右側車門所撞，因而人車倒地，受有頭部外傷及身體多處擦傷、挫傷等語，因認被告乙○○涉犯刑法第二百八十四條第二項前段之業務過失傷害罪嫌。二、按告訴乃論之罪，告訴人於第一審辯論終結前得撤回其告訴，又告訴經撤回者，應諭知不受理之判決，並得不經言詞辯論為之，刑事訴訟法第二百三十八條第一項、第三百零三條第三款及第三百零七條分別定有明文。三、經查，本件業務過失傷害案件，公訴人認被告乙○○係涉犯刑法第二百八十四條第二項前段之業務過失傷害罪嫌，依同法第二百八十七條前段之規定，須告訴乃論。經查，告訴人甲○○○於本院九十四年十一月二十四日準備程序時，已當庭以言詞撤回其告訴，有準備程序筆錄在卷可參（見本院卷第十一頁）可參，按諸上揭規定，本件爰不經言詞辯論，逕為諭知不受理之判決。據上論斷，應依刑事訴訟法第三百零三條第三款、第三百零七條，判決如主文。中華民國94年11月30日刑事第十四庭審判長法官吳靜怡法官孫萍萍法官李家慧以上正本證明與原本無異如不服本判決，應於送達後10日內，向本院提出上訴狀中華民國94年11月30日書記官林婉瑩",
  "characters": {
    "judges": [
      "吳靜怡",
      "孫萍萍",
      "李家慧"
    ],
    "prosecutors": [

    ],
    "lawyers": [

    ],
    "clerks": [
      "林婉瑩"
    ],
    "plaintiffs": [

    ],
    "defendants": [
      "乙○○"
    ],
    "prosecutor_office": [
      "臺灣臺北地方法院檢察署檢察官"
    ],
    "creditors": [

    ],
    "debtors": [

    ],
    "judicial_associate_officer": [

    ]
  },
  "adjudged_at": "2005-11-30",
  "created_at": "2016-02-07 00:40:46",
  "updated_at": "2016-02-07 00:40:46"
}