{
  "identify": "TPD-94-訴-4525-20051130-1",
  "court": {
    "name": "臺灣臺北地方法院",
    "code": "TPD"
  },
  "division": {
    "name": "民事",
    "code": "V"
  },
  "year": 94,
  "word": "訴",
  "number": "4525",
  "jcheck": "1",
  "reason": "清償借款",
  "content": "臺灣臺北地方法院民事判決              94年度訴字第4525號\n  原      告  華僑商業銀行股份有限公司\n  法定代理人  張兆順\n  訴訟代理人  丙○○\n  被      告  越泰華股份有限公司\n兼法定代理人  乙○○\n  被      告  甲○○\n  被      告  丁○○\n上列當事人間請求清償借款事件，本院於94年11月29日言詞辯論\n終結，判決如下：\n    主      文\n被告應連帶給付原告如附表所示之金額、利息及違約金。\n訴訟費用由被告連帶負擔。\n    事實及理由\n一、本件依兩造簽定約定書第9條暨保證書第4條之約定，合意由\n    本院管轄，合先敘明。又本件被告越泰華股份限公司 (下稱\n    越泰華公司)、乙○○、甲○○、丁○○經合法通知，未於\n    言詞辯論期日到場，核無民事訴訟法第386條各款所列情形\n    ，爰依原告之聲請，由其一造辯論為判決。\n二、原告主張：\n  (一)被告越華泰公司於民國94年3月18日邀同案被告乙○○、甲\n    ○○、丁○○為連帶保證人，向原告借貸新台幣 (下同)三\n    百萬元，約定依年利率百分之8.063計算之利息，借款期間\n    為3年，分36期按期平均攤還。\n  (二)詎料被告分別自94年7月18日起即未依約繳款，被告之借款\n    已屆清償期，依約定第5條第1項約定，被告越華泰公司業已\n    喪失期限利益，全部借款均視為到期，除應仍按約定利率計\n    付利息外，逾六個月以內者，按上開利率加計百分之十，逾\n    期六個月以上者，按上開利率加計百分之二十計算違約金。\n  (三)爰依消費借貸以及保證之法律關係，請求被告等人連帶給付\n    原告如附表所示金額，為此提起本件訴訟，聲明如主文所示\n    。\n三、原告主張之事實，業據其提出借據暨證書、約定書、放款歷\n    史交易明細表等證物為證，堪信為真實。從而原告依兩造約\n    定請求被告給付原告如附表所示之金額，為有理由，應予准\n    許。\n四、綜上所述，本件原告之訴為有理由，依民事訴訟法第385條\n    第1項前段、第85條第2項，判決如主文。\n中    華    民    國    94    年    11    月     30    日\n                      民事第六庭法  官  邱  琦\n以上正本係照原本作成\n如對本判決上訴，須於判決送達後20日內向本院提出上訴狀\n中    華    民    國    94    年    12    月    1    日\n                                書記官  林秀妙\n附表\n ┌─────┬──────┬────┬─────────────────────┐\n │債權本金  │利  息  計  │年利率  │違  約  金  計  算  期  間  及  利  率    │\n │          │算  期  間  │        ├──────────┬──────────┤\n │          │            │        │ 逾期六個月以內按約 │ 逾期六個月以上按約 │\n │          │            │        │ 定利率加百分之十   │ 定利率加百分之二十 │\n ├─────┼──────┼────┼──────────┼──────────┤\n │貳佰柒拾肆│自民國九十四│百分之八│自民國九十四年七月十│自民國九十五年一月十│\n │萬玖仟玖佰│年六月十八日│點○六三│九日起至九十五年一月│九日起至清償日止    │\n │玖拾捌元  │起至清償日止│        │十八日止            │                    │\n └─────┴──────┴────┴──────────┴──────────┘\n",
  "structure": {
    "main": "被告應連帶給付原告如附表所示之金額、利息及違約金。\n訴訟費用由被告連帶負擔。",
    "fact": "一、本件依兩造簽定約定書第9條暨保證書第4條之約定，合意由\n    本院管轄，合先敘明。又本件被告越泰華股份限公司 (下稱\n    越泰華公司)、乙○○、甲○○、丁○○經合法通知，未於\n    言詞辯論期日到場，核無民事訴訟法第386條各款所列情形\n    ，爰依原告之聲請，由其一造辯論為判決。\n二、原告主張：\n  (一)被告越華泰公司於民國94年3月18日邀同案被告乙○○、甲\n    ○○、丁○○為連帶保證人，向原告借貸新台幣 (下同)三\n    百萬元，約定依年利率百分之8.063計算之利息，借款期間\n    為3年，分36期按期平均攤還。\n  (二)詎料被告分別自94年7月18日起即未依約繳款，被告之借款\n    已屆清償期，依約定第5條第1項約定，被告越華泰公司業已\n    喪失期限利益，全部借款均視為到期，除應仍按約定利率計\n    付利息外，逾六個月以內者，按上開利率加計百分之十，逾\n    期六個月以上者，按上開利率加計百分之二十計算違約金。\n  (三)爰依消費借貸以及保證之法律關係，請求被告等人連帶給付\n    原告如附表所示金額，為此提起本件訴訟，聲明如主文所示\n    。\n三、原告主張之事實，業據其提出借據暨證書、約定書、放款歷\n    史交易明細表等證物為證，堪信為真實。從而原告依兩造約\n    定請求被告給付原告如附表所示之金額，為有理由，應予准\n    許。\n四、綜上所述，本件原告之訴為有理由，依民事訴訟法第385條\n    第1項前段、第85條第2項，判決如主文。",
    "reason": "一、本件依兩造簽定約定書第9條暨保證書第4條之約定，合意由\n    本院管轄，合先敘明。又本件被告越泰華股份限公司 (下稱\n    越泰華公司)、乙○○、甲○○、丁○○經合法通知，未於\n    言詞辯論期日到場，核無民事訴訟法第386條各款所列情形\n    ，爰依原告之聲請，由其一造辯論為判決。\n二、原告主張：\n  (一)被告越華泰公司於民國94年3月18日邀同案被告乙○○、甲\n    ○○、丁○○為連帶保證人，向原告借貸新台幣 (下同)三\n    百萬元，約定依年利率百分之8.063計算之利息，借款期間\n    為3年，分36期按期平均攤還。\n  (二)詎料被告分別自94年7月18日起即未依約繳款，被告之借款\n    已屆清償期，依約定第5條第1項約定，被告越華泰公司業已\n    喪失期限利益，全部借款均視為到期，除應仍按約定利率計\n    付利息外，逾六個月以內者，按上開利率加計百分之十，逾\n    期六個月以上者，按上開利率加計百分之二十計算違約金。\n  (三)爰依消費借貸以及保證之法律關係，請求被告等人連帶給付\n    原告如附表所示金額，為此提起本件訴訟，聲明如主文所示\n    。\n三、原告主張之事實，業據其提出借據暨證書、約定書、放款歷\n    史交易明細表等證物為證，堪信為真實。從而原告依兩造約\n    定請求被告給付原告如附表所示之金額，為有理由，應予准\n    許。\n四、綜上所述，本件原告之訴為有理由，依民事訴訟法第385條\n    第1項前段、第85條第2項，判決如主文。"
  },
  "search": "臺灣臺北地方法院民事判決94年度訴字第4525號原告華僑商業銀行股份有限公司法定代理人張兆順訴訟代理人丙○○被告越泰華股份有限公司兼法定代理人乙○○被告甲○○被告丁○○上列當事人間請求清償借款事件，本院於94年11月29日言詞辯論終結，判決如下：主文被告應連帶給付原告如附表所示之金額、利息及違約金。訴訟費用由被告連帶負擔。事實及理由一、本件依兩造簽定約定書第9條暨保證書第4條之約定，合意由本院管轄，合先敘明。又本件被告越泰華股份限公司(下稱越泰華公司)、乙○○、甲○○、丁○○經合法通知，未於言詞辯論期日到場，核無民事訴訟法第386條各款所列情形，爰依原告之聲請，由其一造辯論為判決。二、原告主張：(一)被告越華泰公司於民國94年3月18日邀同案被告乙○○、甲○○、丁○○為連帶保證人，向原告借貸新台幣(下同)三百萬元，約定依年利率百分之8.063計算之利息，借款期間為3年，分36期按期平均攤還。(二)詎料被告分別自94年7月18日起即未依約繳款，被告之借款已屆清償期，依約定第5條第1項約定，被告越華泰公司業已喪失期限利益，全部借款均視為到期，除應仍按約定利率計付利息外，逾六個月以內者，按上開利率加計百分之十，逾期六個月以上者，按上開利率加計百分之二十計算違約金。(三)爰依消費借貸以及保證之法律關係，請求被告等人連帶給付原告如附表所示金額，為此提起本件訴訟，聲明如主文所示。三、原告主張之事實，業據其提出借據暨證書、約定書、放款歷史交易明細表等證物為證，堪信為真實。從而原告依兩造約定請求被告給付原告如附表所示之金額，為有理由，應予准許。四、綜上所述，本件原告之訴為有理由，依民事訴訟法第385條第1項前段、第85條第2項，判決如主文。中華民國94年11月30日民事第六庭法官邱琦以上正本係照原本作成如對本判決上訴，須於判決送達後20日內向本院提出上訴狀中華民國94年12月1日書記官林秀妙附表┌─────┬──────┬────┬─────────────────────┐│債權本金│利息計│年利率│違約金計算期間及利率│││算期間│├──────────┬──────────┤││││逾期六個月以內按約│逾期六個月以上按約│││││定利率加百分之十│定利率加百分之二十│├─────┼──────┼────┼──────────┼──────────┤│貳佰柒拾肆│自民國九十四│百分之八│自民國九十四年七月十│自民國九十五年一月十││萬玖仟玖佰│年六月十八日│點○六三│九日起至九十五年一月│九日起至清償日止││玖拾捌元│起至清償日止││十八日止││└─────┴──────┴────┴──────────┴──────────┘",
  "characters": {
    "judges": [
      "邱琦"
    ],
    "prosecutors": [

    ],
    "lawyers": [

    ],
    "clerks": [
      "林秀妙"
    ],
    "plaintiffs": [
      "華僑商業銀行股份有限公司"
    ],
    "defendants": [
      "越泰華股份有限公司",
      "兼法定代理人  乙○○",
      "丁○○"
    ],
    "prosecutor_office": [

    ],
    "creditors": [

    ],
    "debtors": [

    ],
    "judicial_associate_officer": [

    ]
  },
  "adjudged_at": "2005-11-30",
  "created_at": "2016-02-07 00:42:53",
  "updated_at": "2016-02-07 00:42:53"
}