{
  "identify": "TPH-94-上易-2087-20051130-1",
  "court": {
    "name": "臺灣高等法院",
    "code": "TPH"
  },
  "division": {
    "name": "刑事",
    "code": "M"
  },
  "year": 94,
  "word": "上易",
  "number": "2087",
  "jcheck": "1",
  "reason": "違反商標法",
  "content": "臺灣高等法院刑事判決                94年度上易字第2087號\n上  訴  人\n即  被  告  甲○○\n選任辯護人  陳邦財  律師\n            鄧湘全  律師\n            陳怡如  律師\n上列上訴人因違反商標法案件，不服臺灣桃園地方法院93年度易\n字第609號，中華民國94年9月22日第一審判決（起訴案號：臺灣\n桃園地方法院檢察署92年度偵續字第180號），提起上訴，本院\n判決如下：\n    主  文\n上訴駁回。\n    事  實\n本審認定之事實與第一審判決書所記載之事實相同，茲引用之。\n    理  由\n一、按提起上訴，應自判決送達後10日內為之，刑事訴訟法第\n    349 條定有明文。\n二、本件上訴人即被告甲○○住所係在「桃園縣龍潭鄉○○路33\n    7號」，有原法院審判筆錄、法務部戶役政連線作業系統資\n    料（見原審卷第129頁、第146頁），及被告甲○○在上訴狀\n    內所自行書寫之住居所地址在卷可查（見本院卷第10頁）。\n三、原審向被告所住「桃園縣龍潭鄉○○路337號」地址送達刑\n    事判決，已據被告之兄李居興於民國（下同）94年10月11日\n    代為收受原審法院判決之送達，有送達證書在卷可稽（見原\n    審卷第147頁）。乃被告竟遲至同年11月3日始提起上訴（見\n    本院卷第10頁），已逾10日期間，按之上開規定，顯屬違背\n    法律上之程式，應由本院依同法第367條前段、第372條不經\n    辯論，判決如主文。\n中    華    民    國    94    年    11    月    30    日\n                  刑事第十三庭  審判長法  官  劉景星\n                                      法  官  陳志洋\n                                      法  官  陳博志\n以上正本證明與原本無異。\n不得上訴。\n                                      書記官  游桂\n中    華    民    國    94    年    12    月    2     日\n",
  "structure": {
    "main": "上訴駁回。",
    "fact": "本審認定之事實與第一審判決書所記載之事實相同，茲引用之。",
    "reason": "一、按提起上訴，應自判決送達後10日內為之，刑事訴訟法第\n    349 條定有明文。\n二、本件上訴人即被告甲○○住所係在「桃園縣龍潭鄉○○路33\n    7號」，有原法院審判筆錄、法務部戶役政連線作業系統資\n    料（見原審卷第129頁、第146頁），及被告甲○○在上訴狀\n    內所自行書寫之住居所地址在卷可查（見本院卷第10頁）。\n三、原審向被告所住「桃園縣龍潭鄉○○路337號」地址送達刑\n    事判決，已據被告之兄李居興於民國（下同）94年10月11日\n    代為收受原審法院判決之送達，有送達證書在卷可稽（見原\n    審卷第147頁）。乃被告竟遲至同年11月3日始提起上訴（見\n    本院卷第10頁），已逾10日期間，按之上開規定，顯屬違背\n    法律上之程式，應由本院依同法第367條前段、第372條不經\n    辯論，判決如主文。\n中    華    民    國    94    年    11    月    30    日\n                  刑事第十三庭  審判長法  官  劉景星\n                                      法  官  陳志洋\n                                      法  官  陳博志\n以上正本證明與原本無異。\n不得上訴。\n                                      書記官  游桂"
  },
  "search": "臺灣高等法院刑事判決94年度上易字第2087號上訴人即被告甲○○選任辯護人陳邦財律師鄧湘全律師陳怡如律師上列上訴人因違反商標法案件，不服臺灣桃園地方法院93年度易字第609號，中華民國94年9月22日第一審判決（起訴案號：臺灣桃園地方法院檢察署92年度偵續字第180號），提起上訴，本院判決如下：主文上訴駁回。事實本審認定之事實與第一審判決書所記載之事實相同，茲引用之。理由一、按提起上訴，應自判決送達後10日內為之，刑事訴訟法第349條定有明文。二、本件上訴人即被告甲○○住所係在「桃園縣龍潭鄉○○路337號」，有原法院審判筆錄、法務部戶役政連線作業系統資料（見原審卷第129頁、第146頁），及被告甲○○在上訴狀內所自行書寫之住居所地址在卷可查（見本院卷第10頁）。三、原審向被告所住「桃園縣龍潭鄉○○路337號」地址送達刑事判決，已據被告之兄李居興於民國（下同）94年10月11日代為收受原審法院判決之送達，有送達證書在卷可稽（見原審卷第147頁）。乃被告竟遲至同年11月3日始提起上訴（見本院卷第10頁），已逾10日期間，按之上開規定，顯屬違背法律上之程式，應由本院依同法第367條前段、第372條不經辯論，判決如主文。中華民國94年11月30日刑事第十三庭審判長法官劉景星法官陳志洋法官陳博志以上正本證明與原本無異。不得上訴。書記官游桂中華民國94年12月2日",
  "characters": {
    "judges": [
      "劉景星",
      "陳志洋",
      "陳博志"
    ],
    "prosecutors": [

    ],
    "lawyers": [

    ],
    "clerks": [
      "游桂"
    ],
    "plaintiffs": [

    ],
    "defendants": [
      "甲"
    ],
    "prosecutor_office": [

    ],
    "creditors": [

    ],
    "debtors": [

    ],
    "judicial_associate_officer": [

    ]
  },
  "adjudged_at": "2005-11-30",
  "created_at": "2016-02-07 00:37:05",
  "updated_at": "2016-02-07 00:37:05"
}