{
  "identify": "TYD-94-桃簡-1781-20051130-1",
  "court": {
    "name": "臺灣桃園地方法院",
    "code": "TYD"
  },
  "division": {
    "name": "刑事",
    "code": "M"
  },
  "year": 94,
  "word": "桃簡",
  "number": "1781",
  "jcheck": "1",
  "reason": "違反洗錢防制法",
  "content": "台灣桃園地方法院刑事簡易判決      94年度桃簡字第1781號\n聲  請  人  台灣桃園地方法院檢察署檢察官\n被      告  甲○○\n上列被告因違反洗錢防制法案件，經檢察官聲請以簡易判決處刑\n（94年度偵字第2087號），本院判決如下：\n    主      文\n甲○○幫助意圖為自己不法之所有，以詐術使人將本人之物交付\n，處有期徒刑陸月，如易科罰金以佰元折算壹日。\n    事實及理由\n一、本件應補充及更正本案僅出現被害人乙○○一人一次受騙之\n    事實，手法復係以電話為之，與利用印刷精美且係出諸多種\n    名義之信函向不特定大眾廣為詐騙，其背後必屬集團性並係\n    反覆行之之方式迥異，是以本案所見之施詐者未能遽認必以\n    詐欺為生，此外，經攬遍全卷，亦無證據可證明使用被告甲\n    ○○所出售存摺、提款卡之人係恃行騙營生，自難認之所為\n    構成常業詐欺等情外，餘犯罪事實及證據胥同於附件檢察官\n    聲請簡易判決處刑書之記載，茲引用之。\n二、被告甲○○係提供其帳戶之存摺及提款卡此類助力俾便該持\n    用之他人得以順利收取向被害人乙○○詐騙所得之贓款，故\n    核其所為係犯刑法第30條第1 項、第339 條第1 項之詐欺取\n    財罪之幫助犯。此部分犯情業據檢察官於聲請簡易判決處刑\n    書之「犯罪事實」欄內載明，要屬已聲請處刑，雖漏引應適\n    用之法條，對已聲請處刑之效力究不生影響。又如前述，既\n    無從認定該持用被告存摺及提款卡者係以詐欺為常業，自難\n    謂被告之舉另該當洗錢防制法第9 條第1 項洗錢罪之幫助犯\n    ，然依聲請處刑之旨，顯認此與經聲請處刑且由本院論罪之\n    幫助詐欺取財部分，有想像競合犯之裁判上一罪之關係，爰\n    不另為無罪之諭知。被告係幫助他人犯罪，為從犯，爰依刑\n    法第30條第2 項規定，減輕其刑。爰審酌被告僅貪圖區區1,\n    500 元之蠅頭小利即不惜將存摺及提款卡提供予他人充為犯\n    罪收贓之用，不僅助長詐欺等財產犯罪於社會上充斥橫行，\n    且因有「人頭戶」包藏掩飾致而查緝困難之故，主犯成員遂\n    有恃無恐，行徑乃更加囂張、狂放，直視法律為無物、若敝\n    屣馴致台灣漸成各種財產犯罪者之樂園，如入無人之境，是\n    見被告犯行所生之危害極鉅暨其犯後態度等情狀，量處如主\n    文所示之刑，並諭知易科罰金之折算標準。\n三、應依刑事訴訟法第449 條第1 項、第454 條第2 項，刑法第\n    339 條第1 項、第30條第1 項、第2 項、第41第1 項前段，\n    罰金罰鍰提高標準條例第1 條前段、第2 條，逕以簡易判決\n    處如主文所示之刑。\n四、如不服本判決，應於送達後10日內向本院提出上訴狀，上訴\n    於本院合議庭。\n中    華    民    國    94    年    11    月    30    日\n                  臺灣桃園地方法院刑事第11庭\n                      法  官  蔡榮澤\n上正本證明與原本無異。\n                      書記官  陳奕珽\n中    華    民    國    94    年    12    月    5     日\n附本件論罪科刑依據之法條：\n中華民國刑法第339條第1項\n意圖為自己或第三人不法之所有，以詐術使人將本人或第三人之\n物交付者，處五年以下有期徒刑、拘役或科或併科一千元以下罰\n金。\n",
  "structure": {
    "main": "甲○○幫助意圖為自己不法之所有，以詐術使人將本人之物交付\n，處有期徒刑陸月，如易科罰金以佰元折算壹日。",
    "fact": "一、本件應補充及更正本案僅出現被害人乙○○一人一次受騙之\n    事實，手法復係以電話為之，與利用印刷精美且係出諸多種\n    名義之信函向不特定大眾廣為詐騙，其背後必屬集團性並係\n    反覆行之之方式迥異，是以本案所見之施詐者未能遽認必以\n    詐欺為生，此外，經攬遍全卷，亦無證據可證明使用被告甲\n    ○○所出售存摺、提款卡之人係恃行騙營生，自難認之所為\n    構成常業詐欺等情外，餘犯罪事實及證據胥同於附件檢察官\n    聲請簡易判決處刑書之記載，茲引用之。\n二、被告甲○○係提供其帳戶之存摺及提款卡此類助力俾便該持\n    用之他人得以順利收取向被害人乙○○詐騙所得之贓款，故\n    核其所為係犯刑法第30條第1 項、第339 條第1 項之詐欺取\n    財罪之幫助犯。此部分犯情業據檢察官於聲請簡易判決處刑\n    書之「犯罪事實」欄內載明，要屬已聲請處刑，雖漏引應適\n    用之法條，對已聲請處刑之效力究不生影響。又如前述，既\n    無從認定該持用被告存摺及提款卡者係以詐欺為常業，自難\n    謂被告之舉另該當洗錢防制法第9 條第1 項洗錢罪之幫助犯\n    ，然依聲請處刑之旨，顯認此與經聲請處刑且由本院論罪之\n    幫助詐欺取財部分，有想像競合犯之裁判上一罪之關係，爰\n    不另為無罪之諭知。被告係幫助他人犯罪，為從犯，爰依刑\n    法第30條第2 項規定，減輕其刑。爰審酌被告僅貪圖區區1,\n    500 元之蠅頭小利即不惜將存摺及提款卡提供予他人充為犯\n    罪收贓之用，不僅助長詐欺等財產犯罪於社會上充斥橫行，\n    且因有「人頭戶」包藏掩飾致而查緝困難之故，主犯成員遂\n    有恃無恐，行徑乃更加囂張、狂放，直視法律為無物、若敝\n    屣馴致台灣漸成各種財產犯罪者之樂園，如入無人之境，是\n    見被告犯行所生之危害極鉅暨其犯後態度等情狀，量處如主\n    文所示之刑，並諭知易科罰金之折算標準。\n三、應依刑事訴訟法第449 條第1 項、第454 條第2 項，刑法第\n    339 條第1 項、第30條第1 項、第2 項、第41第1 項前段，\n    罰金罰鍰提高標準條例第1 條前段、第2 條，逕以簡易判決\n    處如主文所示之刑。\n四、如不服本判決，應於送達後10日內向本院提出上訴狀，上訴\n    於本院合議庭。",
    "reason": "一、本件應補充及更正本案僅出現被害人乙○○一人一次受騙之\n    事實，手法復係以電話為之，與利用印刷精美且係出諸多種\n    名義之信函向不特定大眾廣為詐騙，其背後必屬集團性並係\n    反覆行之之方式迥異，是以本案所見之施詐者未能遽認必以\n    詐欺為生，此外，經攬遍全卷，亦無證據可證明使用被告甲\n    ○○所出售存摺、提款卡之人係恃行騙營生，自難認之所為\n    構成常業詐欺等情外，餘犯罪事實及證據胥同於附件檢察官\n    聲請簡易判決處刑書之記載，茲引用之。\n二、被告甲○○係提供其帳戶之存摺及提款卡此類助力俾便該持\n    用之他人得以順利收取向被害人乙○○詐騙所得之贓款，故\n    核其所為係犯刑法第30條第1 項、第339 條第1 項之詐欺取\n    財罪之幫助犯。此部分犯情業據檢察官於聲請簡易判決處刑\n    書之「犯罪事實」欄內載明，要屬已聲請處刑，雖漏引應適\n    用之法條，對已聲請處刑之效力究不生影響。又如前述，既\n    無從認定該持用被告存摺及提款卡者係以詐欺為常業，自難\n    謂被告之舉另該當洗錢防制法第9 條第1 項洗錢罪之幫助犯\n    ，然依聲請處刑之旨，顯認此與經聲請處刑且由本院論罪之\n    幫助詐欺取財部分，有想像競合犯之裁判上一罪之關係，爰\n    不另為無罪之諭知。被告係幫助他人犯罪，為從犯，爰依刑\n    法第30條第2 項規定，減輕其刑。爰審酌被告僅貪圖區區1,\n    500 元之蠅頭小利即不惜將存摺及提款卡提供予他人充為犯\n    罪收贓之用，不僅助長詐欺等財產犯罪於社會上充斥橫行，\n    且因有「人頭戶」包藏掩飾致而查緝困難之故，主犯成員遂\n    有恃無恐，行徑乃更加囂張、狂放，直視法律為無物、若敝\n    屣馴致台灣漸成各種財產犯罪者之樂園，如入無人之境，是\n    見被告犯行所生之危害極鉅暨其犯後態度等情狀，量處如主\n    文所示之刑，並諭知易科罰金之折算標準。\n三、應依刑事訴訟法第449 條第1 項、第454 條第2 項，刑法第\n    339 條第1 項、第30條第1 項、第2 項、第41第1 項前段，\n    罰金罰鍰提高標準條例第1 條前段、第2 條，逕以簡易判決\n    處如主文所示之刑。\n四、如不服本判決，應於送達後10日內向本院提出上訴狀，上訴\n    於本院合議庭。"
  },
  "search": "台灣桃園地方法院刑事簡易判決94年度桃簡字第1781號聲請人台灣桃園地方法院檢察署檢察官被告甲○○上列被告因違反洗錢防制法案件，經檢察官聲請以簡易判決處刑（94年度偵字第2087號），本院判決如下：主文甲○○幫助意圖為自己不法之所有，以詐術使人將本人之物交付，處有期徒刑陸月，如易科罰金以佰元折算壹日。事實及理由一、本件應補充及更正本案僅出現被害人乙○○一人一次受騙之事實，手法復係以電話為之，與利用印刷精美且係出諸多種名義之信函向不特定大眾廣為詐騙，其背後必屬集團性並係反覆行之之方式迥異，是以本案所見之施詐者未能遽認必以詐欺為生，此外，經攬遍全卷，亦無證據可證明使用被告甲○○所出售存摺、提款卡之人係恃行騙營生，自難認之所為構成常業詐欺等情外，餘犯罪事實及證據胥同於附件檢察官聲請簡易判決處刑書之記載，茲引用之。二、被告甲○○係提供其帳戶之存摺及提款卡此類助力俾便該持用之他人得以順利收取向被害人乙○○詐騙所得之贓款，故核其所為係犯刑法第30條第1項、第339條第1項之詐欺取財罪之幫助犯。此部分犯情業據檢察官於聲請簡易判決處刑書之「犯罪事實」欄內載明，要屬已聲請處刑，雖漏引應適用之法條，對已聲請處刑之效力究不生影響。又如前述，既無從認定該持用被告存摺及提款卡者係以詐欺為常業，自難謂被告之舉另該當洗錢防制法第9條第1項洗錢罪之幫助犯，然依聲請處刑之旨，顯認此與經聲請處刑且由本院論罪之幫助詐欺取財部分，有想像競合犯之裁判上一罪之關係，爰不另為無罪之諭知。被告係幫助他人犯罪，為從犯，爰依刑法第30條第2項規定，減輕其刑。爰審酌被告僅貪圖區區1,500元之蠅頭小利即不惜將存摺及提款卡提供予他人充為犯罪收贓之用，不僅助長詐欺等財產犯罪於社會上充斥橫行，且因有「人頭戶」包藏掩飾致而查緝困難之故，主犯成員遂有恃無恐，行徑乃更加囂張、狂放，直視法律為無物、若敝屣馴致台灣漸成各種財產犯罪者之樂園，如入無人之境，是見被告犯行所生之危害極鉅暨其犯後態度等情狀，量處如主文所示之刑，並諭知易科罰金之折算標準。三、應依刑事訴訟法第449條第1項、第454條第2項，刑法第339條第1項、第30條第1項、第2項、第41第1項前段，罰金罰鍰提高標準條例第1條前段、第2條，逕以簡易判決處如主文所示之刑。四、如不服本判決，應於送達後10日內向本院提出上訴狀，上訴於本院合議庭。中華民國94年11月30日臺灣桃園地方法院刑事第11庭法官蔡榮澤上正本證明與原本無異。書記官陳奕珽中華民國94年12月5日附本件論罪科刑依據之法條：中華民國刑法第339條第1項意圖為自己或第三人不法之所有，以詐術使人將本人或第三人之物交付者，處五年以下有期徒刑、拘役或科或併科一千元以下罰金。",
  "characters": {
    "judges": [
      "蔡榮澤"
    ],
    "prosecutors": [

    ],
    "lawyers": [

    ],
    "clerks": [
      "陳奕珽"
    ],
    "plaintiffs": [

    ],
    "defendants": [
      "甲○○"
    ],
    "prosecutor_office": [
      "台灣桃園地方法院檢察署檢察官"
    ],
    "creditors": [

    ],
    "debtors": [

    ],
    "judicial_associate_officer": [

    ]
  },
  "adjudged_at": "2005-11-30",
  "created_at": "2016-02-07 00:45:04",
  "updated_at": "2016-02-07 00:45:04"
}