{
  "identify": "TCD-100-中簡-2184-20110909-1",
  "court": {
    "name": "臺灣臺中地方法院",
    "code": "TCD"
  },
  "division": {
    "name": "刑事",
    "code": "M"
  },
  "year": 100,
  "word": "中簡",
  "number": "2184",
  "jcheck": "1",
  "reason": "毒品危害防制條例",
  "content": "臺灣臺中地方法院刑事簡易判決       100年度中簡字第2184號\n聲  請  人  臺灣臺中地方法院檢察署檢察官\n被      告  高德儒\n上列被告因違反毒品危害防制條例案件，經檢察官聲請以簡易判\n決處刑（100 年度偵字第15913號），本院判決如下：\n    主    文\n高德儒持有第二級毒品，處拘役伍拾日，如易科罰金，以新臺幣\n壹仟元折算壹日。扣案之含第二級毒品亞甲基雙氧甲基安非他命\n成分之碎錠壹包（驗餘淨重零點貳陸捌公克）沒收銷燬之。\n    犯罪事實及理由\n一、本案犯罪事實及證據均引用檢察官聲請簡易判決處刑書之記\n    載（如附件）。\n二、核被告所為，係違反毒品危害防制條例第11條第2 項持有第\n    二級毒品罪。扣案之碎錠1 包，經送檢驗結果，檢出第二級\n    毒品3,4-亞甲基雙氧甲基安非他命（MDMA）及成分，驗餘淨\n    重0.2680公克，此有行政院衛生署草屯療養院100 年7 月19\n    日草療鑑字第1000700101號鑑定書1 份在卷可稽，核屬毒品\n    危害防制條例第2 條第1 項第2 款之第二級毒品，應依毒品\n    危害防制條例第18條第1 項前段規定，宣告沒收銷燬（前開\n    錠劑經鑑定結果，兼含第三級毒品對- 氯安非他命（Para-\n    Chloroamphetamine ）成分，固有前開鑑定書可佐，惟既無\n    從與前開第二級毒品成分析離區隔，仍應整體視為第二級毒\n    品予以沒收銷燬之）。\n三、依刑事訴訟法第449 條第1 項、第450 條第1 項、第454 條\n    、第299 條第1 項前段，毒品危害防制條例第11條第2 項、\n    第18條第1 項前段，刑法第11條、第41條第1 項前段，判決\n    如主文。\n四、如不服本簡易判決，得於簡易判決書送達之日起10日內，以\n    書狀敘述理由，向本庭提出上訴（須附繕本）。\n中    華    民    國   100    年    9     月    9     日\n                  臺中簡易庭  法  官  胡宜如\n以上正本證明與原本無異。\n                              書記官  張禎庭\n中    華    民    國   100    年    9     月    9     日\n附錄本案論罪科刑法條：\n毒品危害防制條例第11條\n持有第一級毒品者，處3 年以下有期徒刑、拘役或新臺幣5 萬元\n以下罰金。\n持有第二級毒品者，處2 年以下有期徒刑、拘役或新臺幣3 萬元\n以下罰金。\n持有第一級毒品純質淨重十公克以上者，處1 年以上7 年以下有\n期徒刑，得併科新臺幣1 百萬元以下罰金。\n持有第二級毒品純質淨重二十公克以上者，處6 月以上5 年以下\n有期徒刑，得併科新臺幣70萬元以下罰金。\n持有第三級毒品純質淨重二十公克以上者，處3 年以下有期徒刑\n，得併科新臺幣30萬元以下罰金。\n持有第四級毒品純質淨重二十公克以上者，處1 年以下有期徒刑\n，得併科新臺幣10萬元以下罰金。\n持有專供製造或施用第一級、第二級毒品之器具者，處1 年以下\n有期徒刑、拘役或新臺幣1 萬元以下罰金。",
  "structure": {
    "main": "高德儒持有第二級毒品，處拘役伍拾日，如易科罰金，以新臺幣\n壹仟元折算壹日。扣案之含第二級毒品亞甲基雙氧甲基安非他命\n成分之碎錠壹包（驗餘淨重零點貳陸捌公克）沒收銷燬之。",
    "fact": "一、本案犯罪事實及證據均引用檢察官聲請簡易判決處刑書之記\n    載（如附件）。\n二、核被告所為，係違反毒品危害防制條例第11條第2 項持有第\n    二級毒品罪。扣案之碎錠1 包，經送檢驗結果，檢出第二級\n    毒品3,4-亞甲基雙氧甲基安非他命（MDMA）及成分，驗餘淨\n    重0.2680公克，此有行政院衛生署草屯療養院100 年7 月19\n    日草療鑑字第1000700101號鑑定書1 份在卷可稽，核屬毒品\n    危害防制條例第2 條第1 項第2 款之第二級毒品，應依毒品\n    危害防制條例第18條第1 項前段規定，宣告沒收銷燬（前開\n    錠劑經鑑定結果，兼含第三級毒品對- 氯安非他命（Para-\n    Chloroamphetamine ）成分，固有前開鑑定書可佐，惟既無\n    從與前開第二級毒品成分析離區隔，仍應整體視為第二級毒\n    品予以沒收銷燬之）。\n三、依刑事訴訟法第449 條第1 項、第450 條第1 項、第454 條\n    、第299 條第1 項前段，毒品危害防制條例第11條第2 項、\n    第18條第1 項前段，刑法第11條、第41條第1 項前段，判決\n    如主文。\n四、如不服本簡易判決，得於簡易判決書送達之日起10日內，以\n    書狀敘述理由，向本庭提出上訴（須附繕本）。",
    "reason": "一、本案犯罪事實及證據均引用檢察官聲請簡易判決處刑書之記\n    載（如附件）。\n二、核被告所為，係違反毒品危害防制條例第11條第2 項持有第\n    二級毒品罪。扣案之碎錠1 包，經送檢驗結果，檢出第二級\n    毒品3,4-亞甲基雙氧甲基安非他命（MDMA）及成分，驗餘淨\n    重0.2680公克，此有行政院衛生署草屯療養院100 年7 月19\n    日草療鑑字第1000700101號鑑定書1 份在卷可稽，核屬毒品\n    危害防制條例第2 條第1 項第2 款之第二級毒品，應依毒品\n    危害防制條例第18條第1 項前段規定，宣告沒收銷燬（前開\n    錠劑經鑑定結果，兼含第三級毒品對- 氯安非他命（Para-\n    Chloroamphetamine ）成分，固有前開鑑定書可佐，惟既無\n    從與前開第二級毒品成分析離區隔，仍應整體視為第二級毒\n    品予以沒收銷燬之）。\n三、依刑事訴訟法第449 條第1 項、第450 條第1 項、第454 條\n    、第299 條第1 項前段，毒品危害防制條例第11條第2 項、\n    第18條第1 項前段，刑法第11條、第41條第1 項前段，判決\n    如主文。\n四、如不服本簡易判決，得於簡易判決書送達之日起10日內，以\n    書狀敘述理由，向本庭提出上訴（須附繕本）。"
  },
  "search": "臺灣臺中地方法院刑事簡易判決100年度中簡字第2184號聲請人臺灣臺中地方法院檢察署檢察官被告高德儒上列被告因違反毒品危害防制條例案件，經檢察官聲請以簡易判決處刑（100年度偵字第15913號），本院判決如下：主文高德儒持有第二級毒品，處拘役伍拾日，如易科罰金，以新臺幣壹仟元折算壹日。扣案之含第二級毒品亞甲基雙氧甲基安非他命成分之碎錠壹包（驗餘淨重零點貳陸捌公克）沒收銷燬之。犯罪事實及理由一、本案犯罪事實及證據均引用檢察官聲請簡易判決處刑書之記載（如附件）。二、核被告所為，係違反毒品危害防制條例第11條第2項持有第二級毒品罪。扣案之碎錠1包，經送檢驗結果，檢出第二級毒品3,4-亞甲基雙氧甲基安非他命（MDMA）及成分，驗餘淨重0.2680公克，此有行政院衛生署草屯療養院100年7月19日草療鑑字第1000700101號鑑定書1份在卷可稽，核屬毒品危害防制條例第2條第1項第2款之第二級毒品，應依毒品危害防制條例第18條第1項前段規定，宣告沒收銷燬（前開錠劑經鑑定結果，兼含第三級毒品對-氯安非他命（Para-Chloroamphetamine）成分，固有前開鑑定書可佐，惟既無從與前開第二級毒品成分析離區隔，仍應整體視為第二級毒品予以沒收銷燬之）。三、依刑事訴訟法第449條第1項、第450條第1項、第454條、第299條第1項前段，毒品危害防制條例第11條第2項、第18條第1項前段，刑法第11條、第41條第1項前段，判決如主文。四、如不服本簡易判決，得於簡易判決書送達之日起10日內，以書狀敘述理由，向本庭提出上訴（須附繕本）。中華民國100年9月9日臺中簡易庭法官胡宜如以上正本證明與原本無異。書記官張禎庭中華民國100年9月9日附錄本案論罪科刑法條：毒品危害防制條例第11條持有第一級毒品者，處3年以下有期徒刑、拘役或新臺幣5萬元以下罰金。持有第二級毒品者，處2年以下有期徒刑、拘役或新臺幣3萬元以下罰金。持有第一級毒品純質淨重十公克以上者，處1年以上7年以下有期徒刑，得併科新臺幣1百萬元以下罰金。持有第二級毒品純質淨重二十公克以上者，處6月以上5年以下有期徒刑，得併科新臺幣70萬元以下罰金。持有第三級毒品純質淨重二十公克以上者，處3年以下有期徒刑，得併科新臺幣30萬元以下罰金。持有第四級毒品純質淨重二十公克以上者，處1年以下有期徒刑，得併科新臺幣10萬元以下罰金。持有專供製造或施用第一級、第二級毒品之器具者，處1年以下有期徒刑、拘役或新臺幣1萬元以下罰金。",
  "characters": {
    "judges": [
      "胡宜如"
    ],
    "prosecutors": [

    ],
    "lawyers": [

    ],
    "clerks": [
      "張禎庭"
    ],
    "plaintiffs": [

    ],
    "defendants": [
      "高德儒"
    ],
    "prosecutor_office": [
      "臺灣臺中地方法院檢察署檢察官"
    ],
    "creditors": [

    ],
    "debtors": [

    ],
    "judicial_associate_officer": [

    ]
  },
  "adjudged_at": "2011-09-09",
  "created_at": "2016-02-12 13:14:36",
  "updated_at": "2016-02-12 13:14:36"
}