{
  "identify": "TND-100-聲-1801-20110909-1",
  "court": {
    "name": "臺灣臺南地方法院",
    "code": "TND"
  },
  "division": {
    "name": "刑事",
    "code": "M"
  },
  "year": 100,
  "word": "聲",
  "number": "1801",
  "jcheck": "1",
  "reason": "專科沒收",
  "content": "臺灣臺南地方法院刑事裁定             100年度聲字第1801號\n聲  請  人  臺灣臺南地方法院檢察署檢察官\n被      告  鄭淑霞\n上列聲請人因被告違反商標法案件，單獨聲請宣告沒收（100年\n度聲沒字第334號、96年度偵字第17651號），本院裁定如下：\n    主  文\n扣案仿ＬＶ皮包壹個、仿ＧＵＣＣＩ手提包伍個、絲巾貳條、仿\nＣＯＡＣＨ皮包伍個、仿ＢＵＲＢＥＲＲＹ皮包貳個、仿ＣＨＡ\nＮＥＬ絲巾壹條、仿ＭＩＵＭＩＵ皮包貳個均沒收。\n    理  由\n一、本件聲請意旨略以：被告鄭淑霞因違反商標法案件，經臺灣\n    臺南地方法院檢察署檢察官為不起訴處分（96年度偵字第17\n    651號）確定，有該不起訴處分書在卷可按，而扣案仿ＬＶ\n    皮包一個、仿ＧＵＣＣＩ手提包五個、絲巾二條、仿ＣＯＡ\n    ＣＨ皮包五個、仿ＢＵＲＢＥＲＲＹ皮包二個、仿ＣＨＡＮ\n    ＥＬ絲巾一條、仿ＭＩＵＭＩＵ皮包二個係被告犯商標法第\n    八十二條所販賣之物，依同法第八十三條規定不論屬於犯人\n    與否沒收之，上開皮包係被告所有且供犯罪所用，經被告供\n    承在卷，單獨聲請法院宣告沒收。\n二、按檢察官依刑事訴訟法第二百五十三條或第二百五十三條之\n    一為不起訴或緩起訴之處分者，對供犯罪所用、供犯罪預備\n    或因犯罪所得之物，以屬於被告者為限，得單獨聲請法院宣\n    告沒收，刑事訴訟法第二百五十九條之一定有明文。\n三、經核屬實，參照上揭法條規定，本件聲請核無不合，應予准\n    許，裁定如主文。\n中    華    民    國   100    年    9     月    9     日\n                  刑事第九庭    法  官  鍾邦久\n以上正本證明與原本無異\n如不服本裁定應於送達後5日內向本院提出抗告狀\n                                書記官  鄭梅君\n中    華    民    國   100    年    9     月    9     日",
  "structure": {
    "main": "扣案仿ＬＶ皮包壹個、仿ＧＵＣＣＩ手提包伍個、絲巾貳條、仿\nＣＯＡＣＨ皮包伍個、仿ＢＵＲＢＥＲＲＹ皮包貳個、仿ＣＨＡ\nＮＥＬ絲巾壹條、仿ＭＩＵＭＩＵ皮包貳個均沒收。",
    "reason": "一、本件聲請意旨略以：被告鄭淑霞因違反商標法案件，經臺灣\n    臺南地方法院檢察署檢察官為不起訴處分（96年度偵字第17\n    651號）確定，有該不起訴處分書在卷可按，而扣案仿ＬＶ\n    皮包一個、仿ＧＵＣＣＩ手提包五個、絲巾二條、仿ＣＯＡ\n    ＣＨ皮包五個、仿ＢＵＲＢＥＲＲＹ皮包二個、仿ＣＨＡＮ\n    ＥＬ絲巾一條、仿ＭＩＵＭＩＵ皮包二個係被告犯商標法第\n    八十二條所販賣之物，依同法第八十三條規定不論屬於犯人\n    與否沒收之，上開皮包係被告所有且供犯罪所用，經被告供\n    承在卷，單獨聲請法院宣告沒收。\n二、按檢察官依刑事訴訟法第二百五十三條或第二百五十三條之\n    一為不起訴或緩起訴之處分者，對供犯罪所用、供犯罪預備\n    或因犯罪所得之物，以屬於被告者為限，得單獨聲請法院宣\n    告沒收，刑事訴訟法第二百五十九條之一定有明文。\n三、經核屬實，參照上揭法條規定，本件聲請核無不合，應予准\n    許，裁定如主文。"
  },
  "search": "臺灣臺南地方法院刑事裁定100年度聲字第1801號聲請人臺灣臺南地方法院檢察署檢察官被告鄭淑霞上列聲請人因被告違反商標法案件，單獨聲請宣告沒收（100年度聲沒字第334號、96年度偵字第17651號），本院裁定如下：主文扣案仿ＬＶ皮包壹個、仿ＧＵＣＣＩ手提包伍個、絲巾貳條、仿ＣＯＡＣＨ皮包伍個、仿ＢＵＲＢＥＲＲＹ皮包貳個、仿ＣＨＡＮＥＬ絲巾壹條、仿ＭＩＵＭＩＵ皮包貳個均沒收。理由一、本件聲請意旨略以：被告鄭淑霞因違反商標法案件，經臺灣臺南地方法院檢察署檢察官為不起訴處分（96年度偵字第17651號）確定，有該不起訴處分書在卷可按，而扣案仿ＬＶ皮包一個、仿ＧＵＣＣＩ手提包五個、絲巾二條、仿ＣＯＡＣＨ皮包五個、仿ＢＵＲＢＥＲＲＹ皮包二個、仿ＣＨＡＮＥＬ絲巾一條、仿ＭＩＵＭＩＵ皮包二個係被告犯商標法第八十二條所販賣之物，依同法第八十三條規定不論屬於犯人與否沒收之，上開皮包係被告所有且供犯罪所用，經被告供承在卷，單獨聲請法院宣告沒收。二、按檢察官依刑事訴訟法第二百五十三條或第二百五十三條之一為不起訴或緩起訴之處分者，對供犯罪所用、供犯罪預備或因犯罪所得之物，以屬於被告者為限，得單獨聲請法院宣告沒收，刑事訴訟法第二百五十九條之一定有明文。三、經核屬實，參照上揭法條規定，本件聲請核無不合，應予准許，裁定如主文。中華民國100年9月9日刑事第九庭法官鍾邦久以上正本證明與原本無異如不服本裁定應於送達後5日內向本院提出抗告狀書記官鄭梅君中華民國100年9月9日",
  "characters": {
    "judges": [
      "鍾邦久"
    ],
    "prosecutors": [

    ],
    "lawyers": [

    ],
    "clerks": [
      "鄭梅君"
    ],
    "plaintiffs": [

    ],
    "defendants": [
      "鄭淑霞"
    ],
    "prosecutor_office": [
      "臺灣臺南地方法院檢察署檢察官"
    ],
    "creditors": [

    ],
    "debtors": [

    ],
    "judicial_associate_officer": [

    ]
  },
  "adjudged_at": "2011-09-09",
  "created_at": "2016-02-12 13:17:39",
  "updated_at": "2016-02-12 13:17:39"
}