{
  "identify": "TPD-94-易-845-20050630-1",
  "court": {
    "name": "臺灣臺北地方法院",
    "code": "TPD"
  },
  "division": {
    "name": "刑事",
    "code": "M"
  },
  "year": 94,
  "word": "易",
  "number": "845",
  "jcheck": "1",
  "reason": "竊盜",
  "content": "臺灣臺北地方法院刑事判決               94年度易字第845號\n公  訴  人  臺灣臺北地方法院檢察署檢察官\n被      告  丙○○\n            甲○○\n上列被告因加重竊盜案件，經檢察官提起公訴（九十四年度偵字\n第八九三七號），被告於準備程序中就被訴事實為有罪之陳述，\n經告以簡式審判之旨，並聽取當事人之意見後，經本院合議庭裁\n定以簡式審判程序審理，本院判決如下：\n    主  文\n丙○○、甲○○共同攜帶凶器於夜間侵入住宅竊盜，未遂，各處\n有期徒刑肆月，如易科罰金，均以參佰元折算壹日。\n    事  實\n一、丙○○、甲○○共同基於意圖為自己不法所有之犯意聯絡，\n    於民國九十四年五月二十一日凌晨二時許，一同至乙○○居\n    住之台北市○○區○○街二段四十巷六號一樓之住處，由丙\n    ○○持客觀上具有危險性而足供兇器使用之螺絲起子一把，\n    欲撬開該住處大門之鑰匙孔，惟未能撬開，而改以其在門邊\n    所拾獲不知何人所有之壓克力條將門鎖勾開後共同侵入其內\n    （門鎖並未損壞），翻動屋內之物品以尋找有價值之物品，\n    而著手竊盜。嗣因路過民眾發覺報警，為警當場查獲而未得\n    逞。\n二、案經台北市警察局萬華分局報請臺灣臺北地方法院檢察署檢\n    察官偵查起訴，嗣由本院合議庭裁定由受命法官獨任進行簡\n    式審判程序。\n    理  由\n一、訊據被告丙○○、甲○○對於上揭事實於本院審理時均坦承\n    不諱（見本院九十四年六月十七日審判筆錄第二至四頁），\n    核與被害人乙○○指述之情形相符，並有有壓克力條一支扣\n    案可資佐證，足徵被告出於任意性之自白與事實相符，本案\n    事證已臻明確，被告之犯行堪以認定，應予依法論科。\n二、按刑法第三百二十一條第一項第三款之攜帶兇器竊盜罪，係\n    以行為人攜帶兇器竊盜為其加重條件，此所謂兇器，其種類\n    並無限制，凡客觀上足對人之生命、身體、安全構成威脅，\n    具有危險性之兇器均屬之，且祇須行竊時攜帶此種具有危險\n    性之兇器為已足，並不以攜帶之初有行兇之意圖為必要。而\n    螺絲起子為足以殺傷人生命、身體之器械，顯為具有危險性\n    之兇器（最高法院七十九年臺上字第五二五三號判例參照）\n    。是核被告所為，係犯刑法第三百二十一條第二項、第一項\n    第一款、第三款之攜帶凶器於夜間侵入住宅竊盜未遂罪。起\n    訴書漏未論及被告有同法第三百二十一條第二項、第一項第\n    三款之攜帶凶器竊盜之情形，應予補充。被告二人間，有犯\n    意聯絡及行為分擔，為共同正犯。又被告已著手實施竊盜行\n    為，惟未得手，即為警查獲，為未遂犯，茲依刑法第二十六\n    條前段規定，減輕其刑。爰審酌被告之犯罪動機、目的、手\n    段、所生之危害、智識程度、平日之素行、及其犯後坦承犯\n    罪，態度良好等一切情狀，量處如主文所示之刑，並諭知易\n    科罰金之折算標準，以示懲儆。又被告行竊時所用之螺絲起\n    子，雖係被告丙○○所有供犯罪所用之物，惟被告丙○○供\n    承業已丟棄滅失（見本院九十四年六月十七日審判筆錄），\n    爰不為沒收之諭知。至扣案之壓克力條一支雖係供被告犯罪\n    所用之物，惟被告否認為其所有，復無其他證據證明係被告\n    所有，又非違禁物，亦不予宣告沒收，附此敘明。\n據上論斷，應依刑事訴訟法第二百七十三條之一第一項、第二百\n九十九條第一項前段，刑法第第二十八條、第三百二十一條第二\n項、第一項第一款、第三款、第二十六條前段、第四十一條第一\n項前段、罰金罰鍰提高標準條例第二條，判決如主文。\n本案經檢察官李傳侯到庭執行職務\n中    華    民    國    94    年    6     月    30    日\n                  刑事第五庭    法  官  李宜娟\n以上正本證明與原本無異。\n如不服本判決，應於判決送達後10日內向本院提出上訴狀（應抄\n附繕本）。告訴人或被害人如對於本判決不服者，應具備理由請\n求檢察官上訴，其上訴期間之計算係以檢察官收受判決正本之日\n期為準。\n                                書記官  游秀珠\n中    華    民    國    94    年    7     月    5     日\n附錄本案論罪科刑法條：\n刑法第三百二十一條：犯竊盜罪而有左列情形之一者，處六月以\n上、五年以下有期徒刑：\n一  於夜間侵入住宅或有人居住之建築物、船艦或隱匿其內而犯之\n    者。\n二  毀越門扇、牆垣或其他安全設備而犯之者。\n三  攜帶兇器而犯之者。\n四  結夥三人以上而犯之者。\n五  乘火災、水災或其他災害之際而犯之者。\n六  在車站或埠頭而犯之者。\n前項之未遂犯罰之。\n",
  "structure": {
    "main": "丙○○、甲○○共同攜帶凶器於夜間侵入住宅竊盜，未遂，各處\n有期徒刑肆月，如易科罰金，均以參佰元折算壹日。",
    "fact": "一、丙○○、甲○○共同基於意圖為自己不法所有之犯意聯絡，\n    於民國九十四年五月二十一日凌晨二時許，一同至乙○○居\n    住之台北市○○區○○街二段四十巷六號一樓之住處，由丙\n    ○○持客觀上具有危險性而足供兇器使用之螺絲起子一把，\n    欲撬開該住處大門之鑰匙孔，惟未能撬開，而改以其在門邊\n    所拾獲不知何人所有之壓克力條將門鎖勾開後共同侵入其內\n    （門鎖並未損壞），翻動屋內之物品以尋找有價值之物品，\n    而著手竊盜。嗣因路過民眾發覺報警，為警當場查獲而未得\n    逞。\n二、案經台北市警察局萬華分局報請臺灣臺北地方法院檢察署檢\n    察官偵查起訴，嗣由本院合議庭裁定由受命法官獨任進行簡\n    式審判程序。",
    "reason": "一、訊據被告丙○○、甲○○對於上揭事實於本院審理時均坦承\n    不諱（見本院九十四年六月十七日審判筆錄第二至四頁），\n    核與被害人乙○○指述之情形相符，並有有壓克力條一支扣\n    案可資佐證，足徵被告出於任意性之自白與事實相符，本案\n    事證已臻明確，被告之犯行堪以認定，應予依法論科。\n二、按刑法第三百二十一條第一項第三款之攜帶兇器竊盜罪，係\n    以行為人攜帶兇器竊盜為其加重條件，此所謂兇器，其種類\n    並無限制，凡客觀上足對人之生命、身體、安全構成威脅，\n    具有危險性之兇器均屬之，且祇須行竊時攜帶此種具有危險\n    性之兇器為已足，並不以攜帶之初有行兇之意圖為必要。而\n    螺絲起子為足以殺傷人生命、身體之器械，顯為具有危險性\n    之兇器（最高法院七十九年臺上字第五二五三號判例參照）\n    。是核被告所為，係犯刑法第三百二十一條第二項、第一項\n    第一款、第三款之攜帶凶器於夜間侵入住宅竊盜未遂罪。起\n    訴書漏未論及被告有同法第三百二十一條第二項、第一項第\n    三款之攜帶凶器竊盜之情形，應予補充。被告二人間，有犯\n    意聯絡及行為分擔，為共同正犯。又被告已著手實施竊盜行\n    為，惟未得手，即為警查獲，為未遂犯，茲依刑法第二十六\n    條前段規定，減輕其刑。爰審酌被告之犯罪動機、目的、手\n    段、所生之危害、智識程度、平日之素行、及其犯後坦承犯\n    罪，態度良好等一切情狀，量處如主文所示之刑，並諭知易\n    科罰金之折算標準，以示懲儆。又被告行竊時所用之螺絲起\n    子，雖係被告丙○○所有供犯罪所用之物，惟被告丙○○供\n    承業已丟棄滅失（見本院九十四年六月十七日審判筆錄），\n    爰不為沒收之諭知。至扣案之壓克力條一支雖係供被告犯罪\n    所用之物，惟被告否認為其所有，復無其他證據證明係被告\n    所有，又非違禁物，亦不予宣告沒收，附此敘明。\n據上論斷，應依刑事訴訟法第二百七十三條之一第一項、第二百\n九十九條第一項前段，刑法第第二十八條、第三百二十一條第二\n項、第一項第一款、第三款、第二十六條前段、第四十一條第一\n項前段、罰金罰鍰提高標準條例第二條，判決如主文。\n本案經檢察官李傳侯到庭執行職務\n中    華    民    國    94    年    6     月    30    日\n                  刑事第五庭    法  官  李宜娟\n以上正本證明與原本無異。\n如不服本判決，應於判決送達後10日內向本院提出上訴狀（應抄\n附繕本）。告訴人或被害人如對於本判決不服者，應具備理由請\n求檢察官上訴，其上訴期間之計算係以檢察官收受判決正本之日\n期為準。\n                                書記官  游秀珠"
  },
  "search": "臺灣臺北地方法院刑事判決94年度易字第845號公訴人臺灣臺北地方法院檢察署檢察官被告丙○○甲○○上列被告因加重竊盜案件，經檢察官提起公訴（九十四年度偵字第八九三七號），被告於準備程序中就被訴事實為有罪之陳述，經告以簡式審判之旨，並聽取當事人之意見後，經本院合議庭裁定以簡式審判程序審理，本院判決如下：主文丙○○、甲○○共同攜帶凶器於夜間侵入住宅竊盜，未遂，各處有期徒刑肆月，如易科罰金，均以參佰元折算壹日。事實一、丙○○、甲○○共同基於意圖為自己不法所有之犯意聯絡，於民國九十四年五月二十一日凌晨二時許，一同至乙○○居住之台北市○○區○○街二段四十巷六號一樓之住處，由丙○○持客觀上具有危險性而足供兇器使用之螺絲起子一把，欲撬開該住處大門之鑰匙孔，惟未能撬開，而改以其在門邊所拾獲不知何人所有之壓克力條將門鎖勾開後共同侵入其內（門鎖並未損壞），翻動屋內之物品以尋找有價值之物品，而著手竊盜。嗣因路過民眾發覺報警，為警當場查獲而未得逞。二、案經台北市警察局萬華分局報請臺灣臺北地方法院檢察署檢察官偵查起訴，嗣由本院合議庭裁定由受命法官獨任進行簡式審判程序。理由一、訊據被告丙○○、甲○○對於上揭事實於本院審理時均坦承不諱（見本院九十四年六月十七日審判筆錄第二至四頁），核與被害人乙○○指述之情形相符，並有有壓克力條一支扣案可資佐證，足徵被告出於任意性之自白與事實相符，本案事證已臻明確，被告之犯行堪以認定，應予依法論科。二、按刑法第三百二十一條第一項第三款之攜帶兇器竊盜罪，係以行為人攜帶兇器竊盜為其加重條件，此所謂兇器，其種類並無限制，凡客觀上足對人之生命、身體、安全構成威脅，具有危險性之兇器均屬之，且祇須行竊時攜帶此種具有危險性之兇器為已足，並不以攜帶之初有行兇之意圖為必要。而螺絲起子為足以殺傷人生命、身體之器械，顯為具有危險性之兇器（最高法院七十九年臺上字第五二五三號判例參照）。是核被告所為，係犯刑法第三百二十一條第二項、第一項第一款、第三款之攜帶凶器於夜間侵入住宅竊盜未遂罪。起訴書漏未論及被告有同法第三百二十一條第二項、第一項第三款之攜帶凶器竊盜之情形，應予補充。被告二人間，有犯意聯絡及行為分擔，為共同正犯。又被告已著手實施竊盜行為，惟未得手，即為警查獲，為未遂犯，茲依刑法第二十六條前段規定，減輕其刑。爰審酌被告之犯罪動機、目的、手段、所生之危害、智識程度、平日之素行、及其犯後坦承犯罪，態度良好等一切情狀，量處如主文所示之刑，並諭知易科罰金之折算標準，以示懲儆。又被告行竊時所用之螺絲起子，雖係被告丙○○所有供犯罪所用之物，惟被告丙○○供承業已丟棄滅失（見本院九十四年六月十七日審判筆錄），爰不為沒收之諭知。至扣案之壓克力條一支雖係供被告犯罪所用之物，惟被告否認為其所有，復無其他證據證明係被告所有，又非違禁物，亦不予宣告沒收，附此敘明。據上論斷，應依刑事訴訟法第二百七十三條之一第一項、第二百九十九條第一項前段，刑法第第二十八條、第三百二十一條第二項、第一項第一款、第三款、第二十六條前段、第四十一條第一項前段、罰金罰鍰提高標準條例第二條，判決如主文。本案經檢察官李傳侯到庭執行職務中華民國94年6月30日刑事第五庭法官李宜娟以上正本證明與原本無異。如不服本判決，應於判決送達後10日內向本院提出上訴狀（應抄附繕本）。告訴人或被害人如對於本判決不服者，應具備理由請求檢察官上訴，其上訴期間之計算係以檢察官收受判決正本之日期為準。書記官游秀珠中華民國94年7月5日附錄本案論罪科刑法條：刑法第三百二十一條：犯竊盜罪而有左列情形之一者，處六月以上、五年以下有期徒刑：一於夜間侵入住宅或有人居住之建築物、船艦或隱匿其內而犯之者。二毀越門扇、牆垣或其他安全設備而犯之者。三攜帶兇器而犯之者。四結夥三人以上而犯之者。五乘火災、水災或其他災害之際而犯之者。六在車站或埠頭而犯之者。前項之未遂犯罰之。",
  "characters": {
    "judges": [
      "李宜娟"
    ],
    "prosecutors": [
      "李傳侯"
    ],
    "lawyers": [

    ],
    "clerks": [
      "游秀珠"
    ],
    "plaintiffs": [

    ],
    "defendants": [
      "丙○○"
    ],
    "prosecutor_office": [
      "臺灣臺北地方法院檢察署檢察官"
    ],
    "creditors": [

    ],
    "debtors": [

    ],
    "judicial_associate_officer": [

    ]
  },
  "adjudged_at": "2005-06-30",
  "created_at": "2016-02-07 06:23:10",
  "updated_at": "2016-02-07 06:23:10"
}