{
  "identify": "TPD-94-訴-2302-20050630-1",
  "court": {
    "name": "臺灣臺北地方法院",
    "code": "TPD"
  },
  "division": {
    "name": "民事",
    "code": "V"
  },
  "year": 94,
  "word": "訴",
  "number": "2302",
  "jcheck": "1",
  "reason": "返還消費借貸款",
  "content": "臺灣臺北地方法院民事判決              94年度訴字第2302號\n原        告  華僑商業銀行股份有限公司\n法 定代理 人  乙○○\n訴 訟代理 人  甲○○\n被        告  宇富工程有限公司\n兼法定代理人  丙○○\n被        告  丁○○\n上列當事人間返還消費借貸款事件，本院於中華民國94年6 月24\n日言詞辯論終結，判決如下：\n    主      文\n被告應連帶給付原告新臺幣貳佰玖拾壹萬陸仟零伍拾玖元，及如\n附表一所示之利息及違約金。\n訴訟費用由被告連帶負擔。\n    事實及理由\n一、按當事人得以合意定第一審管轄法院，但以關於由一定法律\n    關係而生之訴訟為限，前項合意，應以文書為之，民事訴訟\n    法第24條定有明文。據本件兩造所簽訂之約定書第9 條約定\n    ，兩造合意以本院為本契約涉訟時之第一審管轄法院，是以\n    原告向本院提起本件返還消費借款之訴，核與首揭規定相符\n    ，本院自有管轄權。又被告經合法通知，未於言詞辯論期日\n    到場被告經合法通知，未於言詞辯論期日到場，核無民事訴\n    訟法第386 條各款所列情事，爰依原告之聲請，由其一造辯\n    論而為判決，合先敘明。\n二、原告主張：被告宇富工程有限公司（下稱宇富公司）於民國\n    93年12月8 日邀同被告丙○○、丁○○為連帶保證人，向伊\n    借款新臺幣（下同）300 萬元，約定借款期間自93年12月8\n    日起至98年12月8 日止，利息按伊銀行基本放款利率加碼年\n    利率3.85％計算，如伊調整基本放款利率時，自調整日起，\n    改按調整後之基本放款利率加計前開加碼利率調整計付，並\n    自借款日起，以1 個月為1 期，共分60期，按期平均攤還本\n    息，如被告宇富公司遲延給付本金或利息時，除依上開利率\n    計息外，其逾期在6 個月以內者，按照上開利率之1 成加付\n    違約金，逾期超過6 個月者，其超過6 個月部分，按上開利\n    率之2 成加付違約金，並約定如有1 期未繳者，債務視為全\n    部到期，應立即清償全部借款並繳付利息及違約金；詎被告\n    宇富公司於94年3 月25日經票據交換所列為拒絕往來戶，自\n    94年2 月8 日起即未依約還款，則本件借款視為全部到期，\n    共積欠2,916,059 元，及按前開約定機動計算之利息、違約\n    金迄未清償，爰依據消費借貸契約及連帶保證契約關係，求\n    為命如主文第1 項所示之判決等語。被告則未於言詞辯論期\n    日到場，亦未提出準備書狀作何聲明或陳述。\n三、經查，原告前開主張，業據其提出借據、約定書、票據退摽\n    票及拒絕往來資訊、保證書往來明細資料查詢表、存款牌告\n    利率變動記錄表各1 份為證，且被告經合法通知，均未於言\n    詞辯論期日到場，復未提出書狀作何聲明或陳述，自堪信原\n    告之主張為真實。\n四、從而，原告依據消費借貸契約及連帶保證契約關係，請求被\n    告連帶清償如主文第1 項所示之金額及附表一之利息、違約\n    金，即無不合，應予准許。\n五、據上論結，本件原告之訴為有理由。依民事訴訟法第385 條\n    第1 項前段、第85條第2項，判決如主文。\n中    華    民    國    94    年    6     月    30    日\n                  臺灣臺北地方法院民事第一庭\n                        審判長法  官  詹文馨\n                              法  官  楊絮雲\n                              法  官  林晏如\n以上正本係照原本作成。\n如對本判決上訴，須於判決送達後20日內向本院提出上訴狀。\n中    華    民    國    94    年    6     月    30    日\n                          法院書記官  高菁菁\n",
  "structure": {
    "main": "被告應連帶給付原告新臺幣貳佰玖拾壹萬陸仟零伍拾玖元，及如\n附表一所示之利息及違約金。\n訴訟費用由被告連帶負擔。",
    "fact": "一、按當事人得以合意定第一審管轄法院，但以關於由一定法律\n    關係而生之訴訟為限，前項合意，應以文書為之，民事訴訟\n    法第24條定有明文。據本件兩造所簽訂之約定書第9 條約定\n    ，兩造合意以本院為本契約涉訟時之第一審管轄法院，是以\n    原告向本院提起本件返還消費借款之訴，核與首揭規定相符\n    ，本院自有管轄權。又被告經合法通知，未於言詞辯論期日\n    到場被告經合法通知，未於言詞辯論期日到場，核無民事訴\n    訟法第386 條各款所列情事，爰依原告之聲請，由其一造辯\n    論而為判決，合先敘明。\n二、原告主張：被告宇富工程有限公司（下稱宇富公司）於民國\n    93年12月8 日邀同被告丙○○、丁○○為連帶保證人，向伊\n    借款新臺幣（下同）300 萬元，約定借款期間自93年12月8\n    日起至98年12月8 日止，利息按伊銀行基本放款利率加碼年\n    利率3.85％計算，如伊調整基本放款利率時，自調整日起，\n    改按調整後之基本放款利率加計前開加碼利率調整計付，並\n    自借款日起，以1 個月為1 期，共分60期，按期平均攤還本\n    息，如被告宇富公司遲延給付本金或利息時，除依上開利率\n    計息外，其逾期在6 個月以內者，按照上開利率之1 成加付\n    違約金，逾期超過6 個月者，其超過6 個月部分，按上開利\n    率之2 成加付違約金，並約定如有1 期未繳者，債務視為全\n    部到期，應立即清償全部借款並繳付利息及違約金；詎被告\n    宇富公司於94年3 月25日經票據交換所列為拒絕往來戶，自\n    94年2 月8 日起即未依約還款，則本件借款視為全部到期，\n    共積欠2,916,059 元，及按前開約定機動計算之利息、違約\n    金迄未清償，爰依據消費借貸契約及連帶保證契約關係，求\n    為命如主文第1 項所示之判決等語。被告則未於言詞辯論期\n    日到場，亦未提出準備書狀作何聲明或陳述。\n三、經查，原告前開主張，業據其提出借據、約定書、票據退摽\n    票及拒絕往來資訊、保證書往來明細資料查詢表、存款牌告\n    利率變動記錄表各1 份為證，且被告經合法通知，均未於言\n    詞辯論期日到場，復未提出書狀作何聲明或陳述，自堪信原\n    告之主張為真實。\n四、從而，原告依據消費借貸契約及連帶保證契約關係，請求被\n    告連帶清償如主文第1 項所示之金額及附表一之利息、違約\n    金，即無不合，應予准許。\n五、據上論結，本件原告之訴為有理由。依民事訴訟法第385 條\n    第1 項前段、第85條第2項，判決如主文。",
    "reason": "一、按當事人得以合意定第一審管轄法院，但以關於由一定法律\n    關係而生之訴訟為限，前項合意，應以文書為之，民事訴訟\n    法第24條定有明文。據本件兩造所簽訂之約定書第9 條約定\n    ，兩造合意以本院為本契約涉訟時之第一審管轄法院，是以\n    原告向本院提起本件返還消費借款之訴，核與首揭規定相符\n    ，本院自有管轄權。又被告經合法通知，未於言詞辯論期日\n    到場被告經合法通知，未於言詞辯論期日到場，核無民事訴\n    訟法第386 條各款所列情事，爰依原告之聲請，由其一造辯\n    論而為判決，合先敘明。\n二、原告主張：被告宇富工程有限公司（下稱宇富公司）於民國\n    93年12月8 日邀同被告丙○○、丁○○為連帶保證人，向伊\n    借款新臺幣（下同）300 萬元，約定借款期間自93年12月8\n    日起至98年12月8 日止，利息按伊銀行基本放款利率加碼年\n    利率3.85％計算，如伊調整基本放款利率時，自調整日起，\n    改按調整後之基本放款利率加計前開加碼利率調整計付，並\n    自借款日起，以1 個月為1 期，共分60期，按期平均攤還本\n    息，如被告宇富公司遲延給付本金或利息時，除依上開利率\n    計息外，其逾期在6 個月以內者，按照上開利率之1 成加付\n    違約金，逾期超過6 個月者，其超過6 個月部分，按上開利\n    率之2 成加付違約金，並約定如有1 期未繳者，債務視為全\n    部到期，應立即清償全部借款並繳付利息及違約金；詎被告\n    宇富公司於94年3 月25日經票據交換所列為拒絕往來戶，自\n    94年2 月8 日起即未依約還款，則本件借款視為全部到期，\n    共積欠2,916,059 元，及按前開約定機動計算之利息、違約\n    金迄未清償，爰依據消費借貸契約及連帶保證契約關係，求\n    為命如主文第1 項所示之判決等語。被告則未於言詞辯論期\n    日到場，亦未提出準備書狀作何聲明或陳述。\n三、經查，原告前開主張，業據其提出借據、約定書、票據退摽\n    票及拒絕往來資訊、保證書往來明細資料查詢表、存款牌告\n    利率變動記錄表各1 份為證，且被告經合法通知，均未於言\n    詞辯論期日到場，復未提出書狀作何聲明或陳述，自堪信原\n    告之主張為真實。\n四、從而，原告依據消費借貸契約及連帶保證契約關係，請求被\n    告連帶清償如主文第1 項所示之金額及附表一之利息、違約\n    金，即無不合，應予准許。\n五、據上論結，本件原告之訴為有理由。依民事訴訟法第385 條\n    第1 項前段、第85條第2項，判決如主文。"
  },
  "search": "臺灣臺北地方法院民事判決94年度訴字第2302號原告華僑商業銀行股份有限公司法定代理人乙○○訴訟代理人甲○○被告宇富工程有限公司兼法定代理人丙○○被告丁○○上列當事人間返還消費借貸款事件，本院於中華民國94年6月24日言詞辯論終結，判決如下：主文被告應連帶給付原告新臺幣貳佰玖拾壹萬陸仟零伍拾玖元，及如附表一所示之利息及違約金。訴訟費用由被告連帶負擔。事實及理由一、按當事人得以合意定第一審管轄法院，但以關於由一定法律關係而生之訴訟為限，前項合意，應以文書為之，民事訴訟法第24條定有明文。據本件兩造所簽訂之約定書第9條約定，兩造合意以本院為本契約涉訟時之第一審管轄法院，是以原告向本院提起本件返還消費借款之訴，核與首揭規定相符，本院自有管轄權。又被告經合法通知，未於言詞辯論期日到場被告經合法通知，未於言詞辯論期日到場，核無民事訴訟法第386條各款所列情事，爰依原告之聲請，由其一造辯論而為判決，合先敘明。二、原告主張：被告宇富工程有限公司（下稱宇富公司）於民國93年12月8日邀同被告丙○○、丁○○為連帶保證人，向伊借款新臺幣（下同）300萬元，約定借款期間自93年12月8日起至98年12月8日止，利息按伊銀行基本放款利率加碼年利率3.85％計算，如伊調整基本放款利率時，自調整日起，改按調整後之基本放款利率加計前開加碼利率調整計付，並自借款日起，以1個月為1期，共分60期，按期平均攤還本息，如被告宇富公司遲延給付本金或利息時，除依上開利率計息外，其逾期在6個月以內者，按照上開利率之1成加付違約金，逾期超過6個月者，其超過6個月部分，按上開利率之2成加付違約金，並約定如有1期未繳者，債務視為全部到期，應立即清償全部借款並繳付利息及違約金；詎被告宇富公司於94年3月25日經票據交換所列為拒絕往來戶，自94年2月8日起即未依約還款，則本件借款視為全部到期，共積欠2,916,059元，及按前開約定機動計算之利息、違約金迄未清償，爰依據消費借貸契約及連帶保證契約關係，求為命如主文第1項所示之判決等語。被告則未於言詞辯論期日到場，亦未提出準備書狀作何聲明或陳述。三、經查，原告前開主張，業據其提出借據、約定書、票據退摽票及拒絕往來資訊、保證書往來明細資料查詢表、存款牌告利率變動記錄表各1份為證，且被告經合法通知，均未於言詞辯論期日到場，復未提出書狀作何聲明或陳述，自堪信原告之主張為真實。四、從而，原告依據消費借貸契約及連帶保證契約關係，請求被告連帶清償如主文第1項所示之金額及附表一之利息、違約金，即無不合，應予准許。五、據上論結，本件原告之訴為有理由。依民事訴訟法第385條第1項前段、第85條第2項，判決如主文。中華民國94年6月30日臺灣臺北地方法院民事第一庭審判長法官詹文馨法官楊絮雲法官林晏如以上正本係照原本作成。如對本判決上訴，須於判決送達後20日內向本院提出上訴狀。中華民國94年6月30日法院書記官高菁菁",
  "characters": {
    "judges": [
      "詹文馨",
      "楊絮雲",
      "林晏如"
    ],
    "prosecutors": [

    ],
    "lawyers": [

    ],
    "clerks": [
      "法院"
    ],
    "plaintiffs": [
      "華僑商業銀行股份有限公司"
    ],
    "defendants": [
      "宇富工程有限公司",
      "兼法定代理人  丙○○",
      "被        告  丁○○"
    ],
    "prosecutor_office": [

    ],
    "creditors": [

    ],
    "debtors": [

    ],
    "judicial_associate_officer": [

    ]
  },
  "adjudged_at": "2005-06-30",
  "created_at": "2016-02-07 06:12:20",
  "updated_at": "2016-02-07 06:12:20"
}