{
  "identify": "TYD-93-訴緝-149-20050630-2",
  "court": {
    "name": "臺灣桃園地方法院",
    "code": "TYD"
  },
  "division": {
    "name": "刑事",
    "code": "M"
  },
  "year": 93,
  "word": "訴緝",
  "number": "149",
  "jcheck": "2",
  "reason": "毒品危害防制條例",
  "content": "臺灣桃園地方法院刑事判決             93年度訴緝字第149號\n公  訴  人  臺灣桃園地方法院檢察署檢察官\n被      告  甲○○  男  28歲.\n                      號6樓(.\n上列被告因違反毒品危害防制條例案件，經檢察官提起公訴（九\n十三年度毒偵字第一一三九號）及移送併案審理（九十四年度毒\n偵字第一一五號），被告於本院準備程序時就被訴事實為有罪之\n陳述，經告知簡式審判程序之旨及聽取當事人之意見後，本院合\n議庭裁定由受命法官獨任進行簡式審判程序，判決如下：\n    主  文\n甲○○連續施用第一級毒品，處有期徒刑捌月。扣案第一級毒品\n海洛因壹包（淨重零點壹壹公克）沒收銷燬之。又施用第二級毒\n品，處有期徒刑肆月。應執行有期徒刑拾月。扣案第一級毒品海\n洛因壹包（淨重零點壹壹公克）沒收銷燬之。\n    事  實\n一、甲○○前於民國九十年間，因施用毒品案件，經本院於九十\n    年十一月三十日，以九十年度毒聲字第四八○四號裁定令其\n    入勒戒處所施以觀察、勒戒後，認其無繼續施用傾向，於九\n    十一年九月十九日執行完畢出所。詎其仍不知悔改，復另基\n    於施用第一級毒品海洛因及第二級毒品安非他命之犯意，於\n    前開觀察、勒戒執行完畢後之五年內即九十三年二月二十五\n    日某時，在其位於桃園縣中壢市○○○路二二三巷八九弄二\n    十四號六樓住處施用第二級毒品安非他命一次，另自九十三\n    年二月二十五日某時起迄同年十二月四日止，在其並前揭住\n    處，連續施用第一級毒品海洛因多次。嗣為警分別於(一)九十\n    三年二月二十五日下午五時四十分許，在桃園縣中壢市○○\n    路六十號前查獲，並扣得第一級毒品海洛因一包（淨重零點\n    一一公克）及(二)九十三年十二月四日，在桃園縣中壢市○○\n    ○街四四七號九樓之十查獲。\n二、案經桃園縣政府警察局中壢分局報請臺灣桃園地方法院檢察\n    署檢察官偵查起訴及移送併案審理。\n    理  由\n一、訊之被告甲○○對有於上開時、地，施用第一級毒品海洛因\n    及第二級毒品安非他命之犯行，於本院審理時坦承不諱，而\n    被告於九十三年二月二十五日為警查獲時，所採集之尿液經\n    送驗結果，確呈安非他命及嗎啡陽性反應，而於同年十二月\n    四日為警查獲所採之尿液經鑑驗結果，則呈嗎啡陽性反應等\n    情，分有桃園縣衛生局不法藥物尿液檢定書及昭信科技顧問\n    股份有限公司所出具之濫用藥物檢體檢驗報告各一紙在卷足\n    憑。而被告於九十三年二月二十五日為警查獲時，自其身上\n    起出不明白色粉末一包，經鑑定結果，認該不明白色粉末確\n    係第一級毒品海洛因無訛，有法務部調查局九十三年三月二\n    十二日調科壹字第○八○○○七四四八號鑑定通知書一紙在\n    卷足憑。是堪認被告自白與事實相符，得採為本案論罪科刑\n    之依據。而被告前於九十年間，因施用毒品案件，經本院裁\n    定送觀察、勒戒後，甫於九十一年九月十九日執行完畢出所\n    ，有臺灣高等法院被告全國前案紀錄表一紙在卷足憑，其於\n    前開觀察、勒戒執行完畢後五年內再犯本案施用毒品之罪，\n    公訴人對之提起公訴，於法自屬有據，併此敘明。綜上，本\n    件事證明確，被告犯行洵堪認定，應依法論科。\n二、核被告所為，係犯毒品危害防制條例第十條第一項施用第一\n    級毒品罪及同條第二項之施用第二級毒品罪。被告施用第一\n    級毒品海洛因、第二級毒品安非他命前後持有第一級毒品海\n    洛因、第二級毒品安非他命之行為，為施用第一級毒品海洛\n    因、第二級毒品安非他命所吸收，不另論罪。被告先後多次\n    施用第一級毒品之行為，時間緊接，觸犯構成要件相同之行\n    為，顯係基於概括犯意反覆為之，為連續犯，應依刑法第五\n    十六條規定論以一罪，並加重其刑。被告所犯上開二罪，犯\n    意各別，罪名不同，應分論併罰之。另公訴人雖僅就被告九\n    十三年二月二十五日某時施用第一級毒品海洛因及第二級毒\n    品安非他命之犯行提起公訴，而未論及被告自同年月二十六\n    日起迄十二月四日止亦有多次施用第一級毒品海洛因之犯行\n    ，然該部分事實與公訴人提起公訴之犯罪事實既有連續犯之\n    裁判上一罪關係，本院自應併予審究，附此敘明。爰審酌被\n    告坦承犯行，並表示悔改之意，犯後態度良好，犯罪之動機\n    及目的在於追求刺激，曾數度施用毒品並經強制戒治，仍未\n    能革除惡習，復連續施用毒品，足見其等戒毒意志不堅，與\n    所生危害等一切情狀，分別量處如主文所示之刑。並定其應\n    執行之刑。至扣案第一級毒品海洛因一包（淨重零點一一公\n    克），為當場查獲之毒品，爰依毒品危害防制條例第十八條\n    第一項前段宣告沒收銷燬之。\n據上論斷，應依刑事訴訟法第二百七十三條之一第一項、第二百\n九十九條第一項前段，毒品危害防制條例第十條第一項、第二項\n、第十八條第一項前段，刑法第十一條、第五十六條、第五十一\n條第五款，判決如主文。\n本案經檢察官廖先志到庭執行職務。\n中    華    民    國  九十四  年    六    月  三十    日\n               臺灣桃園地方法院刑事第十庭\n                     法  官  柯姿佐\n以上正本證明與原本無異。\n如不服本判決，應於判決送達後10日內向本院提出上訴狀（應附\n繕本），上訴於臺灣高等法院。\n                     書記官  張淑芬\n中    華    民    國  九十四  年    七    月    一    日\n附錄論罪科刑法條\n毒品危害防制條例第10條\n施用第一級毒品者，處 6 月以上 5 年以下有期徒刑。\n施用第二級毒品者，處 3 年以下有期徒刑。\n",
  "structure": {
    "main": "甲○○連續施用第一級毒品，處有期徒刑捌月。扣案第一級毒品\n海洛因壹包（淨重零點壹壹公克）沒收銷燬之。又施用第二級毒\n品，處有期徒刑肆月。應執行有期徒刑拾月。扣案第一級毒品海\n洛因壹包（淨重零點壹壹公克）沒收銷燬之。",
    "fact": "一、甲○○前於民國九十年間，因施用毒品案件，經本院於九十\n    年十一月三十日，以九十年度毒聲字第四八○四號裁定令其\n    入勒戒處所施以觀察、勒戒後，認其無繼續施用傾向，於九\n    十一年九月十九日執行完畢出所。詎其仍不知悔改，復另基\n    於施用第一級毒品海洛因及第二級毒品安非他命之犯意，於\n    前開觀察、勒戒執行完畢後之五年內即九十三年二月二十五\n    日某時，在其位於桃園縣中壢市○○○路二二三巷八九弄二\n    十四號六樓住處施用第二級毒品安非他命一次，另自九十三\n    年二月二十五日某時起迄同年十二月四日止，在其並前揭住\n    處，連續施用第一級毒品海洛因多次。嗣為警分別於(一)九十\n    三年二月二十五日下午五時四十分許，在桃園縣中壢市○○\n    路六十號前查獲，並扣得第一級毒品海洛因一包（淨重零點\n    一一公克）及(二)九十三年十二月四日，在桃園縣中壢市○○\n    ○街四四七號九樓之十查獲。\n二、案經桃園縣政府警察局中壢分局報請臺灣桃園地方法院檢察\n    署檢察官偵查起訴及移送併案審理。",
    "reason": "一、訊之被告甲○○對有於上開時、地，施用第一級毒品海洛因\n    及第二級毒品安非他命之犯行，於本院審理時坦承不諱，而\n    被告於九十三年二月二十五日為警查獲時，所採集之尿液經\n    送驗結果，確呈安非他命及嗎啡陽性反應，而於同年十二月\n    四日為警查獲所採之尿液經鑑驗結果，則呈嗎啡陽性反應等\n    情，分有桃園縣衛生局不法藥物尿液檢定書及昭信科技顧問\n    股份有限公司所出具之濫用藥物檢體檢驗報告各一紙在卷足\n    憑。而被告於九十三年二月二十五日為警查獲時，自其身上\n    起出不明白色粉末一包，經鑑定結果，認該不明白色粉末確\n    係第一級毒品海洛因無訛，有法務部調查局九十三年三月二\n    十二日調科壹字第○八○○○七四四八號鑑定通知書一紙在\n    卷足憑。是堪認被告自白與事實相符，得採為本案論罪科刑\n    之依據。而被告前於九十年間，因施用毒品案件，經本院裁\n    定送觀察、勒戒後，甫於九十一年九月十九日執行完畢出所\n    ，有臺灣高等法院被告全國前案紀錄表一紙在卷足憑，其於\n    前開觀察、勒戒執行完畢後五年內再犯本案施用毒品之罪，\n    公訴人對之提起公訴，於法自屬有據，併此敘明。綜上，本\n    件事證明確，被告犯行洵堪認定，應依法論科。\n二、核被告所為，係犯毒品危害防制條例第十條第一項施用第一\n    級毒品罪及同條第二項之施用第二級毒品罪。被告施用第一\n    級毒品海洛因、第二級毒品安非他命前後持有第一級毒品海\n    洛因、第二級毒品安非他命之行為，為施用第一級毒品海洛\n    因、第二級毒品安非他命所吸收，不另論罪。被告先後多次\n    施用第一級毒品之行為，時間緊接，觸犯構成要件相同之行\n    為，顯係基於概括犯意反覆為之，為連續犯，應依刑法第五\n    十六條規定論以一罪，並加重其刑。被告所犯上開二罪，犯\n    意各別，罪名不同，應分論併罰之。另公訴人雖僅就被告九\n    十三年二月二十五日某時施用第一級毒品海洛因及第二級毒\n    品安非他命之犯行提起公訴，而未論及被告自同年月二十六\n    日起迄十二月四日止亦有多次施用第一級毒品海洛因之犯行\n    ，然該部分事實與公訴人提起公訴之犯罪事實既有連續犯之\n    裁判上一罪關係，本院自應併予審究，附此敘明。爰審酌被\n    告坦承犯行，並表示悔改之意，犯後態度良好，犯罪之動機\n    及目的在於追求刺激，曾數度施用毒品並經強制戒治，仍未\n    能革除惡習，復連續施用毒品，足見其等戒毒意志不堅，與\n    所生危害等一切情狀，分別量處如主文所示之刑。並定其應\n    執行之刑。至扣案第一級毒品海洛因一包（淨重零點一一公\n    克），為當場查獲之毒品，爰依毒品危害防制條例第十八條\n    第一項前段宣告沒收銷燬之。\n據上論斷，應依刑事訴訟法第二百七十三條之一第一項、第二百\n九十九條第一項前段，毒品危害防制條例第十條第一項、第二項\n、第十八條第一項前段，刑法第十一條、第五十六條、第五十一\n條第五款，判決如主文。\n本案經檢察官廖先志到庭執行職務。\n中    華    民    國  九十四  年    六    月  三十    日\n               臺灣桃園地方法院刑事第十庭\n                     法  官  柯姿佐\n以上正本證明與原本無異。\n如不服本判決，應於判決送達後10日內向本院提出上訴狀（應附\n繕本），上訴於臺灣高等法院。\n                     書記官  張淑芬"
  },
  "search": "臺灣桃園地方法院刑事判決93年度訴緝字第149號公訴人臺灣桃園地方法院檢察署檢察官被告甲○○男28歲.號6樓(.上列被告因違反毒品危害防制條例案件，經檢察官提起公訴（九十三年度毒偵字第一一三九號）及移送併案審理（九十四年度毒偵字第一一五號），被告於本院準備程序時就被訴事實為有罪之陳述，經告知簡式審判程序之旨及聽取當事人之意見後，本院合議庭裁定由受命法官獨任進行簡式審判程序，判決如下：主文甲○○連續施用第一級毒品，處有期徒刑捌月。扣案第一級毒品海洛因壹包（淨重零點壹壹公克）沒收銷燬之。又施用第二級毒品，處有期徒刑肆月。應執行有期徒刑拾月。扣案第一級毒品海洛因壹包（淨重零點壹壹公克）沒收銷燬之。事實一、甲○○前於民國九十年間，因施用毒品案件，經本院於九十年十一月三十日，以九十年度毒聲字第四八○四號裁定令其入勒戒處所施以觀察、勒戒後，認其無繼續施用傾向，於九十一年九月十九日執行完畢出所。詎其仍不知悔改，復另基於施用第一級毒品海洛因及第二級毒品安非他命之犯意，於前開觀察、勒戒執行完畢後之五年內即九十三年二月二十五日某時，在其位於桃園縣中壢市○○○路二二三巷八九弄二十四號六樓住處施用第二級毒品安非他命一次，另自九十三年二月二十五日某時起迄同年十二月四日止，在其並前揭住處，連續施用第一級毒品海洛因多次。嗣為警分別於(一)九十三年二月二十五日下午五時四十分許，在桃園縣中壢市○○路六十號前查獲，並扣得第一級毒品海洛因一包（淨重零點一一公克）及(二)九十三年十二月四日，在桃園縣中壢市○○○街四四七號九樓之十查獲。二、案經桃園縣政府警察局中壢分局報請臺灣桃園地方法院檢察署檢察官偵查起訴及移送併案審理。理由一、訊之被告甲○○對有於上開時、地，施用第一級毒品海洛因及第二級毒品安非他命之犯行，於本院審理時坦承不諱，而被告於九十三年二月二十五日為警查獲時，所採集之尿液經送驗結果，確呈安非他命及嗎啡陽性反應，而於同年十二月四日為警查獲所採之尿液經鑑驗結果，則呈嗎啡陽性反應等情，分有桃園縣衛生局不法藥物尿液檢定書及昭信科技顧問股份有限公司所出具之濫用藥物檢體檢驗報告各一紙在卷足憑。而被告於九十三年二月二十五日為警查獲時，自其身上起出不明白色粉末一包，經鑑定結果，認該不明白色粉末確係第一級毒品海洛因無訛，有法務部調查局九十三年三月二十二日調科壹字第○八○○○七四四八號鑑定通知書一紙在卷足憑。是堪認被告自白與事實相符，得採為本案論罪科刑之依據。而被告前於九十年間，因施用毒品案件，經本院裁定送觀察、勒戒後，甫於九十一年九月十九日執行完畢出所，有臺灣高等法院被告全國前案紀錄表一紙在卷足憑，其於前開觀察、勒戒執行完畢後五年內再犯本案施用毒品之罪，公訴人對之提起公訴，於法自屬有據，併此敘明。綜上，本件事證明確，被告犯行洵堪認定，應依法論科。二、核被告所為，係犯毒品危害防制條例第十條第一項施用第一級毒品罪及同條第二項之施用第二級毒品罪。被告施用第一級毒品海洛因、第二級毒品安非他命前後持有第一級毒品海洛因、第二級毒品安非他命之行為，為施用第一級毒品海洛因、第二級毒品安非他命所吸收，不另論罪。被告先後多次施用第一級毒品之行為，時間緊接，觸犯構成要件相同之行為，顯係基於概括犯意反覆為之，為連續犯，應依刑法第五十六條規定論以一罪，並加重其刑。被告所犯上開二罪，犯意各別，罪名不同，應分論併罰之。另公訴人雖僅就被告九十三年二月二十五日某時施用第一級毒品海洛因及第二級毒品安非他命之犯行提起公訴，而未論及被告自同年月二十六日起迄十二月四日止亦有多次施用第一級毒品海洛因之犯行，然該部分事實與公訴人提起公訴之犯罪事實既有連續犯之裁判上一罪關係，本院自應併予審究，附此敘明。爰審酌被告坦承犯行，並表示悔改之意，犯後態度良好，犯罪之動機及目的在於追求刺激，曾數度施用毒品並經強制戒治，仍未能革除惡習，復連續施用毒品，足見其等戒毒意志不堅，與所生危害等一切情狀，分別量處如主文所示之刑。並定其應執行之刑。至扣案第一級毒品海洛因一包（淨重零點一一公克），為當場查獲之毒品，爰依毒品危害防制條例第十八條第一項前段宣告沒收銷燬之。據上論斷，應依刑事訴訟法第二百七十三條之一第一項、第二百九十九條第一項前段，毒品危害防制條例第十條第一項、第二項、第十八條第一項前段，刑法第十一條、第五十六條、第五十一條第五款，判決如主文。本案經檢察官廖先志到庭執行職務。中華民國九十四年六月三十日臺灣桃園地方法院刑事第十庭法官柯姿佐以上正本證明與原本無異。如不服本判決，應於判決送達後10日內向本院提出上訴狀（應附繕本），上訴於臺灣高等法院。書記官張淑芬中華民國九十四年七月一日附錄論罪科刑法條毒品危害防制條例第10條施用第一級毒品者，處6月以上5年以下有期徒刑。施用第二級毒品者，處3年以下有期徒刑。",
  "characters": {
    "judges": [
      "柯姿佐"
    ],
    "prosecutors": [
      "廖先志"
    ],
    "lawyers": [

    ],
    "clerks": [
      "張淑芬"
    ],
    "plaintiffs": [

    ],
    "defendants": [
      "甲○○  男  28歲."
    ],
    "prosecutor_office": [
      "臺灣桃園地方法院檢察署檢察官"
    ],
    "creditors": [

    ],
    "debtors": [

    ],
    "judicial_associate_officer": [

    ]
  },
  "adjudged_at": "2005-06-30",
  "created_at": "2016-02-07 06:25:41",
  "updated_at": "2016-02-07 06:25:41"
}