{
  "identify": "KSD-93-簡-553-20040206-1",
  "court": {
    "name": "臺灣高雄地方法院",
    "code": "KSD"
  },
  "division": {
    "name": "刑事",
    "code": "M"
  },
  "year": 93,
  "word": "簡",
  "number": "553",
  "jcheck": "1",
  "reason": "竊盜",
  "content": "臺灣高雄地方法院刑事簡易判決                      九十三年度簡字第五五三號\n    聲  請  人  臺灣高雄地方法院檢察署檢察官\n    被      告  乙○○\n右列被告因竊盜案件，經檢察官聲請以簡易判決處刑（民國九十二年度偵字第二四六\n○○號），本院判決如左：\n    主  文\n乙○○竊盜，處拘役參拾日，如易科罰金，以參佰元折算壹日。\n    事實及理由\n一、本件犯罪事實、證據及應適用之法條，均引用檢察官聲請簡易判決處刑書之記載\n    （如附件）。\n二、前開犯罪事實有：（一）被告乙○○於警訊及偵查中之自白、（二）證人甲○○\n    之證述、（三）高雄市政府警察局左營分局扣押筆錄、搜索筆錄、扣押物品目錄\n    表及贓物認領保管收據等各一份在卷可證，足證被告自白與事實相符，洵堪採為\n    論罪科刑之依據。本件事證明確，被告犯行堪以認定。\n三、核被告乙○○所為，係犯刑法第三百二十條第一項之竊盜罪。爰審酌被告素行並\n    非良好，有臺灣高雄地方法院檢察署刑案資料查註資料表、本院被告院內索引卡\n    紀錄表及臺灣高等法院被告全國前案紀錄表各一份可資為憑，及其犯本罪之動機\n    、目的、手段，暨其犯罪所得為一千八百元，且已發還被害人，所生危害尚非嚴\n    重等一切情狀，量處如主文所示之刑，並諭知易科罰金之折算標準，以示儆懲。\n四、依刑事訴訟法第四百四十九條第一項、第四百五十四條第二項，刑法第三百二十\n    條第一項、第四十一條第一項前段、罰金罰鍰提高標準條例第一條前段、第二條\n    ，以簡易判決處刑如主文。\n五、如不服本判決，得自收受送達之日起十日內，向本院提起上訴。\n中      華      民      國    九十三    年      二      月      六      日\n                                  臺灣高雄地方法院高雄簡易庭\n                                      法  官    黃惠玲\n右正本證明與原本無異。\n如不服本判決，應於判決送達後十日內，向本院提出上訴狀。\n                                      書記官    林秀珍\n中    華    民    國      九十三      年      二      月      九      日\n附錄本判決論罪之法條：\n刑法第三百二十條第一項\n意圖為自己或第三人不法之所有，而竊取他人之動產者，為竊盜罪，處五年以下有期\n徒刑、拘役或五百元以下罰金。\n",
  "structure": {
    "main": "乙○○竊盜，處拘役參拾日，如易科罰金，以參佰元折算壹日。",
    "fact": "一、本件犯罪事實、證據及應適用之法條，均引用檢察官聲請簡易判決處刑書之記載\n    （如附件）。\n二、前開犯罪事實有：（一）被告乙○○於警訊及偵查中之自白、（二）證人甲○○\n    之證述、（三）高雄市政府警察局左營分局扣押筆錄、搜索筆錄、扣押物品目錄\n    表及贓物認領保管收據等各一份在卷可證，足證被告自白與事實相符，洵堪採為\n    論罪科刑之依據。本件事證明確，被告犯行堪以認定。\n三、核被告乙○○所為，係犯刑法第三百二十條第一項之竊盜罪。爰審酌被告素行並\n    非良好，有臺灣高雄地方法院檢察署刑案資料查註資料表、本院被告院內索引卡\n    紀錄表及臺灣高等法院被告全國前案紀錄表各一份可資為憑，及其犯本罪之動機\n    、目的、手段，暨其犯罪所得為一千八百元，且已發還被害人，所生危害尚非嚴\n    重等一切情狀，量處如主文所示之刑，並諭知易科罰金之折算標準，以示儆懲。\n四、依刑事訴訟法第四百四十九條第一項、第四百五十四條第二項，刑法第三百二十\n    條第一項、第四十一條第一項前段、罰金罰鍰提高標準條例第一條前段、第二條\n    ，以簡易判決處刑如主文。\n五、如不服本判決，得自收受送達之日起十日內，向本院提起上訴。",
    "reason": "一、本件犯罪事實、證據及應適用之法條，均引用檢察官聲請簡易判決處刑書之記載\n    （如附件）。\n二、前開犯罪事實有：（一）被告乙○○於警訊及偵查中之自白、（二）證人甲○○\n    之證述、（三）高雄市政府警察局左營分局扣押筆錄、搜索筆錄、扣押物品目錄\n    表及贓物認領保管收據等各一份在卷可證，足證被告自白與事實相符，洵堪採為\n    論罪科刑之依據。本件事證明確，被告犯行堪以認定。\n三、核被告乙○○所為，係犯刑法第三百二十條第一項之竊盜罪。爰審酌被告素行並\n    非良好，有臺灣高雄地方法院檢察署刑案資料查註資料表、本院被告院內索引卡\n    紀錄表及臺灣高等法院被告全國前案紀錄表各一份可資為憑，及其犯本罪之動機\n    、目的、手段，暨其犯罪所得為一千八百元，且已發還被害人，所生危害尚非嚴\n    重等一切情狀，量處如主文所示之刑，並諭知易科罰金之折算標準，以示儆懲。\n四、依刑事訴訟法第四百四十九條第一項、第四百五十四條第二項，刑法第三百二十\n    條第一項、第四十一條第一項前段、罰金罰鍰提高標準條例第一條前段、第二條\n    ，以簡易判決處刑如主文。\n五、如不服本判決，得自收受送達之日起十日內，向本院提起上訴。"
  },
  "search": "臺灣高雄地方法院刑事簡易判決九十三年度簡字第五五三號聲請人臺灣高雄地方法院檢察署檢察官被告乙○○右列被告因竊盜案件，經檢察官聲請以簡易判決處刑（民國九十二年度偵字第二四六○○號），本院判決如左：主文乙○○竊盜，處拘役參拾日，如易科罰金，以參佰元折算壹日。事實及理由一、本件犯罪事實、證據及應適用之法條，均引用檢察官聲請簡易判決處刑書之記載（如附件）。二、前開犯罪事實有：（一）被告乙○○於警訊及偵查中之自白、（二）證人甲○○之證述、（三）高雄市政府警察局左營分局扣押筆錄、搜索筆錄、扣押物品目錄表及贓物認領保管收據等各一份在卷可證，足證被告自白與事實相符，洵堪採為論罪科刑之依據。本件事證明確，被告犯行堪以認定。三、核被告乙○○所為，係犯刑法第三百二十條第一項之竊盜罪。爰審酌被告素行並非良好，有臺灣高雄地方法院檢察署刑案資料查註資料表、本院被告院內索引卡紀錄表及臺灣高等法院被告全國前案紀錄表各一份可資為憑，及其犯本罪之動機、目的、手段，暨其犯罪所得為一千八百元，且已發還被害人，所生危害尚非嚴重等一切情狀，量處如主文所示之刑，並諭知易科罰金之折算標準，以示儆懲。四、依刑事訴訟法第四百四十九條第一項、第四百五十四條第二項，刑法第三百二十條第一項、第四十一條第一項前段、罰金罰鍰提高標準條例第一條前段、第二條，以簡易判決處刑如主文。五、如不服本判決，得自收受送達之日起十日內，向本院提起上訴。中華民國九十三年二月六日臺灣高雄地方法院高雄簡易庭法官黃惠玲右正本證明與原本無異。如不服本判決，應於判決送達後十日內，向本院提出上訴狀。書記官林秀珍中華民國九十三年二月九日附錄本判決論罪之法條：刑法第三百二十條第一項意圖為自己或第三人不法之所有，而竊取他人之動產者，為竊盜罪，處五年以下有期徒刑、拘役或五百元以下罰金。",
  "characters": {
    "judges": [
      "黃惠玲"
    ],
    "prosecutors": [

    ],
    "lawyers": [

    ],
    "clerks": [
      "林秀珍"
    ],
    "plaintiffs": [

    ],
    "defendants": [
      "乙○○",
      "右列被告因竊盜案件，經檢察官聲請以簡易判決處刑（民國九十二年度偵字第二四六",
      "○○號），本院判決如左："
    ],
    "prosecutor_office": [
      "臺灣高雄地方法院檢察署檢察官"
    ],
    "creditors": [

    ],
    "debtors": [

    ],
    "judicial_associate_officer": [

    ]
  },
  "adjudged_at": "2004-02-06",
  "created_at": "2016-02-05 22:07:37",
  "updated_at": "2016-02-05 22:07:37"
}