{
  "identify": "KSD-93-交簡-2200-20040906-1",
  "court": {
    "name": "臺灣高雄地方法院",
    "code": "KSD"
  },
  "division": {
    "name": "刑事",
    "code": "M"
  },
  "year": 93,
  "word": "交簡",
  "number": "2200",
  "jcheck": "1",
  "reason": "公共危險",
  "content": "臺灣高雄地方法院刑事簡易判決                  九十三年度交簡字第二二號\n    聲  請  人  臺灣高雄地方法院檢察署檢察官\n    被      告  甲○○\n右列被告因公共危險等案件，經檢察官聲請以簡易判決處刑（九十三年度偵字第一○\n三七五號），本院判決如左：\n    主  文\n甲○○服用酒類，不能安全駕駛動力交通工具而駕駛，累犯，處拘役陸拾日，如易科\n罰金，以參佰元折算壹日。\n    事實及理由\n一、本案犯罪事實、證據及理由除於犯罪事實增列甲○○曾因違反肅清煙毒條例案件\n    ，經本院以八十五年度訴字第一四九五號判處有期徒刑三年二月確定，嗣於假釋\n    中更犯違反毒品危害防制條例及竊盜等案件，經本院分別以八十八年度訴字第二\n    ○六四號、八十九年度易字第九二四號判處有期徒刑八月、罰金五千元確定，接\n    續執行而於民國九十一年一月二十八日縮短刑期執行完畢外，其餘均引用附件檢\n    察官聲請簡易判決處刑書之記載。\n二、核被告甲○○所為，係犯刑法第一百八十五條之三之服用酒類不能安全駕駛動力\n    交通工具而駕駛罪。被告曾因違反肅清煙毒條例，經判處有期徒刑三年二月確定\n    ，嗣於假釋中更犯違反毒品危害防制條例及竊盜等案件，經分別判處有期徒刑八\n    月、罰金五千元確定，接續執行而於九十一年一月二十八日縮短刑期執行完畢，\n    有卷附臺灣高等法院被告全國前案紀錄表可按，其受有期徒刑執行完畢，五年內\n    再犯有期徒刑以上之罪，為累犯，應依法加重其刑。爰審酌被告酒後已無法安全\n    駕駛，惟仍無視他人安全而為之，致生交通事故，然其犯後已坦認犯行，態度尚\n    佳，及其肇事所生損害等一切情狀，量處如主文所示之刑，並諭知易科罰金之折\n    算標準，以資懲儆。\n三、應依刑事訴訟法第四百四十九條第一項、第三項、第四百五十四條第二項，刑法\n    第一百八十五條之三、第四十七條、第四十一條第一項，罰金罰鍰提高標準條例\n    第二條，逕以簡易判決處刑如主文。\n四、如不服本判決，得自收受送達之日起十日內，向本院提起上訴。\n中      華      民      國      九十三      年      九    月      六    日\n                                  臺灣高雄地方法院交通法庭\n                          法  官    洪珮婷\n右正本證明與原本無異。\n如不服本判決，應於判決送達後十日內，向本院提出上訴狀。\n                                      書記官    于耀文\n中    華    民    國      九十三      年      九      月        七      日\n附錄法條：\n中華民國刑法第一百八十五條之三\n服用毒品、麻醉藥品、酒類或其他相類之物，不能安全駕駛動力交通工具而駕駛者，\n處一年以下有期徒刑、拘役或三萬元以下罰金。\n",
  "structure": {
    "main": "甲○○服用酒類，不能安全駕駛動力交通工具而駕駛，累犯，處拘役陸拾日，如易科\n罰金，以參佰元折算壹日。",
    "fact": "一、本案犯罪事實、證據及理由除於犯罪事實增列甲○○曾因違反肅清煙毒條例案件\n    ，經本院以八十五年度訴字第一四九五號判處有期徒刑三年二月確定，嗣於假釋\n    中更犯違反毒品危害防制條例及竊盜等案件，經本院分別以八十八年度訴字第二\n    ○六四號、八十九年度易字第九二四號判處有期徒刑八月、罰金五千元確定，接\n    續執行而於民國九十一年一月二十八日縮短刑期執行完畢外，其餘均引用附件檢\n    察官聲請簡易判決處刑書之記載。\n二、核被告甲○○所為，係犯刑法第一百八十五條之三之服用酒類不能安全駕駛動力\n    交通工具而駕駛罪。被告曾因違反肅清煙毒條例，經判處有期徒刑三年二月確定\n    ，嗣於假釋中更犯違反毒品危害防制條例及竊盜等案件，經分別判處有期徒刑八\n    月、罰金五千元確定，接續執行而於九十一年一月二十八日縮短刑期執行完畢，\n    有卷附臺灣高等法院被告全國前案紀錄表可按，其受有期徒刑執行完畢，五年內\n    再犯有期徒刑以上之罪，為累犯，應依法加重其刑。爰審酌被告酒後已無法安全\n    駕駛，惟仍無視他人安全而為之，致生交通事故，然其犯後已坦認犯行，態度尚\n    佳，及其肇事所生損害等一切情狀，量處如主文所示之刑，並諭知易科罰金之折\n    算標準，以資懲儆。\n三、應依刑事訴訟法第四百四十九條第一項、第三項、第四百五十四條第二項，刑法\n    第一百八十五條之三、第四十七條、第四十一條第一項，罰金罰鍰提高標準條例\n    第二條，逕以簡易判決處刑如主文。\n四、如不服本判決，得自收受送達之日起十日內，向本院提起上訴。",
    "reason": "一、本案犯罪事實、證據及理由除於犯罪事實增列甲○○曾因違反肅清煙毒條例案件\n    ，經本院以八十五年度訴字第一四九五號判處有期徒刑三年二月確定，嗣於假釋\n    中更犯違反毒品危害防制條例及竊盜等案件，經本院分別以八十八年度訴字第二\n    ○六四號、八十九年度易字第九二四號判處有期徒刑八月、罰金五千元確定，接\n    續執行而於民國九十一年一月二十八日縮短刑期執行完畢外，其餘均引用附件檢\n    察官聲請簡易判決處刑書之記載。\n二、核被告甲○○所為，係犯刑法第一百八十五條之三之服用酒類不能安全駕駛動力\n    交通工具而駕駛罪。被告曾因違反肅清煙毒條例，經判處有期徒刑三年二月確定\n    ，嗣於假釋中更犯違反毒品危害防制條例及竊盜等案件，經分別判處有期徒刑八\n    月、罰金五千元確定，接續執行而於九十一年一月二十八日縮短刑期執行完畢，\n    有卷附臺灣高等法院被告全國前案紀錄表可按，其受有期徒刑執行完畢，五年內\n    再犯有期徒刑以上之罪，為累犯，應依法加重其刑。爰審酌被告酒後已無法安全\n    駕駛，惟仍無視他人安全而為之，致生交通事故，然其犯後已坦認犯行，態度尚\n    佳，及其肇事所生損害等一切情狀，量處如主文所示之刑，並諭知易科罰金之折\n    算標準，以資懲儆。\n三、應依刑事訴訟法第四百四十九條第一項、第三項、第四百五十四條第二項，刑法\n    第一百八十五條之三、第四十七條、第四十一條第一項，罰金罰鍰提高標準條例\n    第二條，逕以簡易判決處刑如主文。\n四、如不服本判決，得自收受送達之日起十日內，向本院提起上訴。"
  },
  "search": "臺灣高雄地方法院刑事簡易判決九十三年度交簡字第二二號聲請人臺灣高雄地方法院檢察署檢察官被告甲○○右列被告因公共危險等案件，經檢察官聲請以簡易判決處刑（九十三年度偵字第一○三七五號），本院判決如左：主文甲○○服用酒類，不能安全駕駛動力交通工具而駕駛，累犯，處拘役陸拾日，如易科罰金，以參佰元折算壹日。事實及理由一、本案犯罪事實、證據及理由除於犯罪事實增列甲○○曾因違反肅清煙毒條例案件，經本院以八十五年度訴字第一四九五號判處有期徒刑三年二月確定，嗣於假釋中更犯違反毒品危害防制條例及竊盜等案件，經本院分別以八十八年度訴字第二○六四號、八十九年度易字第九二四號判處有期徒刑八月、罰金五千元確定，接續執行而於民國九十一年一月二十八日縮短刑期執行完畢外，其餘均引用附件檢察官聲請簡易判決處刑書之記載。二、核被告甲○○所為，係犯刑法第一百八十五條之三之服用酒類不能安全駕駛動力交通工具而駕駛罪。被告曾因違反肅清煙毒條例，經判處有期徒刑三年二月確定，嗣於假釋中更犯違反毒品危害防制條例及竊盜等案件，經分別判處有期徒刑八月、罰金五千元確定，接續執行而於九十一年一月二十八日縮短刑期執行完畢，有卷附臺灣高等法院被告全國前案紀錄表可按，其受有期徒刑執行完畢，五年內再犯有期徒刑以上之罪，為累犯，應依法加重其刑。爰審酌被告酒後已無法安全駕駛，惟仍無視他人安全而為之，致生交通事故，然其犯後已坦認犯行，態度尚佳，及其肇事所生損害等一切情狀，量處如主文所示之刑，並諭知易科罰金之折算標準，以資懲儆。三、應依刑事訴訟法第四百四十九條第一項、第三項、第四百五十四條第二項，刑法第一百八十五條之三、第四十七條、第四十一條第一項，罰金罰鍰提高標準條例第二條，逕以簡易判決處刑如主文。四、如不服本判決，得自收受送達之日起十日內，向本院提起上訴。中華民國九十三年九月六日臺灣高雄地方法院交通法庭法官洪珮婷右正本證明與原本無異。如不服本判決，應於判決送達後十日內，向本院提出上訴狀。書記官于耀文中華民國九十三年九月七日附錄法條：中華民國刑法第一百八十五條之三服用毒品、麻醉藥品、酒類或其他相類之物，不能安全駕駛動力交通工具而駕駛者，處一年以下有期徒刑、拘役或三萬元以下罰金。",
  "characters": {
    "judges": [
      "洪珮婷"
    ],
    "prosecutors": [

    ],
    "lawyers": [

    ],
    "clerks": [
      "于耀文"
    ],
    "plaintiffs": [

    ],
    "defendants": [
      "甲○○",
      "右列被告因公共危險等案件，經檢察官聲請以簡易判決處刑（九十三年度偵字第一○",
      "三七五號），本院判決如左："
    ],
    "prosecutor_office": [
      "臺灣高雄地方法院檢察署檢察官"
    ],
    "creditors": [

    ],
    "debtors": [

    ],
    "judicial_associate_officer": [

    ]
  },
  "adjudged_at": "2004-09-06",
  "created_at": "2016-02-06 00:37:21",
  "updated_at": "2016-02-06 00:37:21"
}