{
  "identify": "TND-91-易-104-20020906-1",
  "court": {
    "name": "臺灣南投地方法院",
    "code": "TND"
  },
  "division": {
    "name": "刑事",
    "code": "M"
  },
  "year": 91,
  "word": "易",
  "number": "104",
  "jcheck": "1",
  "reason": "違反動產擔保交易法",
  "content": "臺灣臺南地方法院刑事判決                          九十一年度易字第一四號\n    公  訴  人  臺灣台南地方法院檢察署檢察官\n    被      告  甲○○\n右列被告因違反動產擔保交易法案件，經檢察官提起公訴 (九十年度偵字第一二三七\n九號)，本院判決如左：\n    主  文\n甲○○動產擔保交易之債務人，意圖不法之利益，將標的物移轉，致生損害於債權人\n，處罰金陸仟元，如易服勞役，以參佰元折算壹日，緩刑貳年。\n    事  實\n一、甲○○於民國八十九年七月二十四日，以動產擔保交易附條件買賣之方式，向聲\n    寶股份有限公司善化服務站（以下稱聲寶公司）購買電腦一台，為動產擔保交易\n    之債務人。約定總價金新台幣（下同）三萬三千六百元，每月一期，共十期，頭\n    期款為三千四百五十元，以後每期付款三千三百五十元，標的物存放地點為台南\n    市○○路○段二０九號四樓，在價金未付清之前，標的物所有權仍屬於出賣人所\n    有，買受人僅得依約占有使用，不得任意遷移、出賣、出質、移轉、抵押或為其\n    他處分。詎甲○○在取得標的物之後，僅付款七期後，即拒不付款，尚欠一萬零\n    五十元，且意圖不法之利益將該標的物移轉他人，逃匿不知去向，致出賣人追索\n    無著受有損害。\n二、案經聲寶公司訴請台灣台南地方法院檢察署檢察官偵查起訴。\n    理  由\n一、右揭事實，業據被告甲○○於本院審理中坦承不諱，核與告訴人聲寶公司代理人\n    黃昭榮指訴綦詳，並有附條件買賣契約書一紙附卷可稽，被告自白核與事實相符\n    ，事證明確，其犯行堪以認定。\n二、核被告甲○○所為，係犯動產擔保交易法第三十八條意圖不法之利益，將標的物\n    移轉，致生損害於債權人之罪。爰審酌被告犯罪之動機、目的、手段、所生危害\n    、犯後坦承犯行，及已繳清貨款等一切情狀，量處如主文所示之刑，並諭知易服\n    勞役之折算標準，以資懲儆。又被告未曾受過有期徒刑以上刑之宣告，此有台灣\n    高等法院被告全國前案紀錄表一紙在卷可證，其因一時失慮致罹刑章，經此科刑\n    之教訓，當知所警惕而無再犯之虞，本院認其受刑之宣告以暫不執行為適當，爰\n    併宣告緩刑二年，以啟自新。\n據上論斷，應依刑事訴訟法第二百九十九條第一項前段，動產擔保交易法第三十八條\n，刑法第十一條前段、第四十二條第二項、第七十四條第一款，罰金罰鍰提高標準條\n例第一條前段、第二條，判決如主文。\n本案經檢察官柯怡伶到庭執行職務\n中    華    民    國      九十一      年      九      月      六      日\n                                  臺灣臺南地方法院刑事第四庭\n                                          法  官   鍾邦久\n右正本證明與原本無異。\n如不服本判決，應於判決送達後十日內，向本院提出上訴狀。\n                                          書記官   張豐榮\n中    華    民    國      九十一      年      九      月      六      日\n",
  "structure": {
    "main": "甲○○動產擔保交易之債務人，意圖不法之利益，將標的物移轉，致生損害於債權人\n，處罰金陸仟元，如易服勞役，以參佰元折算壹日，緩刑貳年。",
    "fact": "一、甲○○於民國八十九年七月二十四日，以動產擔保交易附條件買賣之方式，向聲\n    寶股份有限公司善化服務站（以下稱聲寶公司）購買電腦一台，為動產擔保交易\n    之債務人。約定總價金新台幣（下同）三萬三千六百元，每月一期，共十期，頭\n    期款為三千四百五十元，以後每期付款三千三百五十元，標的物存放地點為台南\n    市○○路○段二０九號四樓，在價金未付清之前，標的物所有權仍屬於出賣人所\n    有，買受人僅得依約占有使用，不得任意遷移、出賣、出質、移轉、抵押或為其\n    他處分。詎甲○○在取得標的物之後，僅付款七期後，即拒不付款，尚欠一萬零\n    五十元，且意圖不法之利益將該標的物移轉他人，逃匿不知去向，致出賣人追索\n    無著受有損害。\n二、案經聲寶公司訴請台灣台南地方法院檢察署檢察官偵查起訴。",
    "reason": "一、右揭事實，業據被告甲○○於本院審理中坦承不諱，核與告訴人聲寶公司代理人\n    黃昭榮指訴綦詳，並有附條件買賣契約書一紙附卷可稽，被告自白核與事實相符\n    ，事證明確，其犯行堪以認定。\n二、核被告甲○○所為，係犯動產擔保交易法第三十八條意圖不法之利益，將標的物\n    移轉，致生損害於債權人之罪。爰審酌被告犯罪之動機、目的、手段、所生危害\n    、犯後坦承犯行，及已繳清貨款等一切情狀，量處如主文所示之刑，並諭知易服\n    勞役之折算標準，以資懲儆。又被告未曾受過有期徒刑以上刑之宣告，此有台灣\n    高等法院被告全國前案紀錄表一紙在卷可證，其因一時失慮致罹刑章，經此科刑\n    之教訓，當知所警惕而無再犯之虞，本院認其受刑之宣告以暫不執行為適當，爰\n    併宣告緩刑二年，以啟自新。\n據上論斷，應依刑事訴訟法第二百九十九條第一項前段，動產擔保交易法第三十八條\n，刑法第十一條前段、第四十二條第二項、第七十四條第一款，罰金罰鍰提高標準條\n例第一條前段、第二條，判決如主文。\n本案經檢察官柯怡伶到庭執行職務\n中    華    民    國      九十一      年      九      月      六      日\n                                  臺灣臺南地方法院刑事第四庭\n                                          法  官   鍾邦久\n右正本證明與原本無異。\n如不服本判決，應於判決送達後十日內，向本院提出上訴狀。\n                                          書記官   張豐榮"
  },
  "search": "臺灣臺南地方法院刑事判決九十一年度易字第一四號公訴人臺灣台南地方法院檢察署檢察官被告甲○○右列被告因違反動產擔保交易法案件，經檢察官提起公訴(九十年度偵字第一二三七九號)，本院判決如左：主文甲○○動產擔保交易之債務人，意圖不法之利益，將標的物移轉，致生損害於債權人，處罰金陸仟元，如易服勞役，以參佰元折算壹日，緩刑貳年。事實一、甲○○於民國八十九年七月二十四日，以動產擔保交易附條件買賣之方式，向聲寶股份有限公司善化服務站（以下稱聲寶公司）購買電腦一台，為動產擔保交易之債務人。約定總價金新台幣（下同）三萬三千六百元，每月一期，共十期，頭期款為三千四百五十元，以後每期付款三千三百五十元，標的物存放地點為台南市○○路○段二０九號四樓，在價金未付清之前，標的物所有權仍屬於出賣人所有，買受人僅得依約占有使用，不得任意遷移、出賣、出質、移轉、抵押或為其他處分。詎甲○○在取得標的物之後，僅付款七期後，即拒不付款，尚欠一萬零五十元，且意圖不法之利益將該標的物移轉他人，逃匿不知去向，致出賣人追索無著受有損害。二、案經聲寶公司訴請台灣台南地方法院檢察署檢察官偵查起訴。理由一、右揭事實，業據被告甲○○於本院審理中坦承不諱，核與告訴人聲寶公司代理人黃昭榮指訴綦詳，並有附條件買賣契約書一紙附卷可稽，被告自白核與事實相符，事證明確，其犯行堪以認定。二、核被告甲○○所為，係犯動產擔保交易法第三十八條意圖不法之利益，將標的物移轉，致生損害於債權人之罪。爰審酌被告犯罪之動機、目的、手段、所生危害、犯後坦承犯行，及已繳清貨款等一切情狀，量處如主文所示之刑，並諭知易服勞役之折算標準，以資懲儆。又被告未曾受過有期徒刑以上刑之宣告，此有台灣高等法院被告全國前案紀錄表一紙在卷可證，其因一時失慮致罹刑章，經此科刑之教訓，當知所警惕而無再犯之虞，本院認其受刑之宣告以暫不執行為適當，爰併宣告緩刑二年，以啟自新。據上論斷，應依刑事訴訟法第二百九十九條第一項前段，動產擔保交易法第三十八條，刑法第十一條前段、第四十二條第二項、第七十四條第一款，罰金罰鍰提高標準條例第一條前段、第二條，判決如主文。本案經檢察官柯怡伶到庭執行職務中華民國九十一年九月六日臺灣臺南地方法院刑事第四庭法官鍾邦久右正本證明與原本無異。如不服本判決，應於判決送達後十日內，向本院提出上訴狀。書記官張豐榮中華民國九十一年九月六日",
  "characters": {
    "judges": [
      "鍾邦久"
    ],
    "prosecutors": [
      "柯怡伶"
    ],
    "lawyers": [

    ],
    "clerks": [
      "張豐榮"
    ],
    "plaintiffs": [

    ],
    "defendants": [
      "甲○○",
      "右列被告因違反動產擔保交易法案件，經檢察官提起公訴 (九十年度偵字第一二三七",
      "九號)，本院判決如左："
    ],
    "prosecutor_office": [
      "臺灣台南地方法院檢察署檢察官"
    ],
    "creditors": [

    ],
    "debtors": [

    ],
    "judicial_associate_officer": [

    ]
  },
  "adjudged_at": "2002-09-06",
  "created_at": "2016-02-04 17:48:43",
  "updated_at": "2016-02-04 17:48:43"
}