{
  "identify": "TPD-100-聲-1211-20110509-1",
  "court": {
    "name": "臺灣臺北地方法院",
    "code": "TPD"
  },
  "division": {
    "name": "刑事",
    "code": "M"
  },
  "year": 100,
  "word": "聲",
  "number": "1211",
  "jcheck": "1",
  "reason": "聲請單獨宣告沒收扣押物",
  "content": "臺灣臺北地方法院刑事裁定             100年度聲字第1211號\n聲  請  人  臺灣臺北地方法院檢察署檢察官\n被      告  童光明\n上列聲請人因違禁物事件，聲請單獨宣告沒收（100 年度聲沒字\n第185 號），本院裁定如下：\n    主  文\n第二級毒品安非他命壹包（淨重參點柒公克），沒收銷燬之。\n    理  由\n一、按違禁物得單獨宣告沒收，刑法第40條但書定有明文。又按\n    查獲之毒品及專供製造或施用毒品之器具，不問屬於犯人與\n    否，均沒收銷燬之，毒品危害防制條例第18條第1 項前段亦\n    定有明文。\n二、聲請意旨略以：被告童光明前因違反毒品危害防制條例案件\n    ，經本院裁定送觀察、勒戒及強制戒治後，因認無繼續施用\n    毒品傾向之情，業經聲請人以99年度戒毒偵字第82號為不起\n    訴處分。而查扣之透明晶體1 包，經送驗含安非他命成分，\n    屬毒品危害防制條例第2 條第2 項第2 款規定之毒品，係違\n    禁物，依刑法第40條第2 項及毒品危害防制條例第18條第1\n    項前段之規定，爰請依法宣告沒收銷燬等情。\n三、經查：本件扣押毒品（毛重4.06公克，淨重3.71公克，取樣\n    0.01公克化鑑用罄，驗餘淨重3.70克）係第二級毒品安非他\n    命無訛，此有臺北市政府警察局96年7 月29日北市鑑毒字第\n    192 號鑑驗通知書附卷可稽（見97年度毒偵字第2381號卷第\n    67頁），是故上開扣押之物均確屬違禁物無訛，本院認其聲\n    請為正當，爰依刑事訴訟法第220 條、毒品危害防制條例第\n    18條第1 項前段、刑法第40條第2 項，裁定如主文。\n中    華    民    國   100    年    5     月    9     日\n                    刑事第十六庭  法  官  葉藍鸚\n以上正本證明與原本無異。\n如不服本裁定，應於裁定送達後5日內向本院提出抗告狀。\n                                  書記官  黃芝凌\n中    華    民    國   100    年    5     月    9     日",
  "structure": {
    "main": "第二級毒品安非他命壹包（淨重參點柒公克），沒收銷燬之。",
    "reason": "一、按違禁物得單獨宣告沒收，刑法第40條但書定有明文。又按\n    查獲之毒品及專供製造或施用毒品之器具，不問屬於犯人與\n    否，均沒收銷燬之，毒品危害防制條例第18條第1 項前段亦\n    定有明文。\n二、聲請意旨略以：被告童光明前因違反毒品危害防制條例案件\n    ，經本院裁定送觀察、勒戒及強制戒治後，因認無繼續施用\n    毒品傾向之情，業經聲請人以99年度戒毒偵字第82號為不起\n    訴處分。而查扣之透明晶體1 包，經送驗含安非他命成分，\n    屬毒品危害防制條例第2 條第2 項第2 款規定之毒品，係違\n    禁物，依刑法第40條第2 項及毒品危害防制條例第18條第1\n    項前段之規定，爰請依法宣告沒收銷燬等情。\n三、經查：本件扣押毒品（毛重4.06公克，淨重3.71公克，取樣\n    0.01公克化鑑用罄，驗餘淨重3.70克）係第二級毒品安非他\n    命無訛，此有臺北市政府警察局96年7 月29日北市鑑毒字第\n    192 號鑑驗通知書附卷可稽（見97年度毒偵字第2381號卷第\n    67頁），是故上開扣押之物均確屬違禁物無訛，本院認其聲\n    請為正當，爰依刑事訴訟法第220 條、毒品危害防制條例第\n    18條第1 項前段、刑法第40條第2 項，裁定如主文。"
  },
  "search": "臺灣臺北地方法院刑事裁定100年度聲字第1211號聲請人臺灣臺北地方法院檢察署檢察官被告童光明上列聲請人因違禁物事件，聲請單獨宣告沒收（100年度聲沒字第185號），本院裁定如下：主文第二級毒品安非他命壹包（淨重參點柒公克），沒收銷燬之。理由一、按違禁物得單獨宣告沒收，刑法第40條但書定有明文。又按查獲之毒品及專供製造或施用毒品之器具，不問屬於犯人與否，均沒收銷燬之，毒品危害防制條例第18條第1項前段亦定有明文。二、聲請意旨略以：被告童光明前因違反毒品危害防制條例案件，經本院裁定送觀察、勒戒及強制戒治後，因認無繼續施用毒品傾向之情，業經聲請人以99年度戒毒偵字第82號為不起訴處分。而查扣之透明晶體1包，經送驗含安非他命成分，屬毒品危害防制條例第2條第2項第2款規定之毒品，係違禁物，依刑法第40條第2項及毒品危害防制條例第18條第1項前段之規定，爰請依法宣告沒收銷燬等情。三、經查：本件扣押毒品（毛重4.06公克，淨重3.71公克，取樣0.01公克化鑑用罄，驗餘淨重3.70克）係第二級毒品安非他命無訛，此有臺北市政府警察局96年7月29日北市鑑毒字第192號鑑驗通知書附卷可稽（見97年度毒偵字第2381號卷第67頁），是故上開扣押之物均確屬違禁物無訛，本院認其聲請為正當，爰依刑事訴訟法第220條、毒品危害防制條例第18條第1項前段、刑法第40條第2項，裁定如主文。中華民國100年5月9日刑事第十六庭法官葉藍鸚以上正本證明與原本無異。如不服本裁定，應於裁定送達後5日內向本院提出抗告狀。書記官黃芝凌中華民國100年5月9日",
  "characters": {
    "judges": [
      "葉藍鸚"
    ],
    "prosecutors": [

    ],
    "lawyers": [

    ],
    "clerks": [
      "黃芝凌"
    ],
    "plaintiffs": [

    ],
    "defendants": [
      "童光明"
    ],
    "prosecutor_office": [
      "臺灣臺北地方法院檢察署檢察官"
    ],
    "creditors": [

    ],
    "debtors": [

    ],
    "judicial_associate_officer": [

    ]
  },
  "adjudged_at": "2011-05-09",
  "created_at": "2016-02-12 00:28:27",
  "updated_at": "2016-02-12 00:28:27"
}