{
  "identify": "PCD-94-聲-1694-20050812-1",
  "court": {
    "name": "臺灣新北地方法院",
    "code": "PCD"
  },
  "division": {
    "name": "刑事",
    "code": "M"
  },
  "year": 94,
  "word": "聲",
  "number": "1694",
  "jcheck": "1",
  "reason": "沒入保證金",
  "content": "臺灣板橋地方法院刑事裁定              94年度聲字第1694號\n聲  請  人  臺灣板橋地方法院檢察署檢察官\n被      告  甲○○\n具  保  人  乙○○\n上列具保人因被告偽造文書案件，聲請人聲請沒入保證金（94\n年度執聲沒字第453號），本院裁定如下：\n    主  文\n乙○○繳納之保證金新臺幣壹萬元沒入之。\n    理  由\n一、按具保之被告逃匿者，應命具保人繳納指定之保證金額，並\n    沒入之；不繳納者，強制執行；保證金已繳納者，沒入之，\n    刑事訴訟法第一百十八條、第一百二十一條第一項分別定有\n    明文。\n二、本件聲請意旨略以：具保人乙○○因被告甲○○偽造文書案\n    件，經依法院指定之保證金額新臺幣一萬元，出具現金保證\n    後，將被告釋放，茲因該被告逃匿，依刑事訴訟法第一百十\n    八條之規定，應沒入具保人繳納之保證金（93刑保字第236\n    號）等語。\n三、經查：被告經臺灣板橋地方法院檢察署檢察官依法傳喚、拘\n    提，均未到案執行，具保人經通知亦未遵期通知或帶同被告\n    到案接受執行等情，有送達證書二紙、臺灣臺北地方法院檢\n    察署九十四年二月二十五日北檢退九四執助五六字第九四０\n    八號函、臺灣板橋地方法院檢察署通知書一件及法務部戶役\n    政連結作業系統查詢資料二紙在卷可稽。且被告迄今仍逃匿\n    中，尚未到案執行，復經本院依職權查證屬實，有臺灣高等\n    法院在監在押全國紀錄表一份附卷足憑，被告已然逃匿，揆\n    諸前揭說明，自應將具保人原繳納上開保證金沒入之。\n四、依刑事訴訟法第一百十八條、第一百二十一條第一項，裁定\n    如主文。\n中    華    民    國    94    年    8     月    12    日\n                  刑事第十二庭  法  官  劉元斐\n上列正本證明與原本無異。\n如不服本裁定，應於裁定送達後五日內向本院提出抗告狀。\n                                書記官  郭玉芬\n中    華    民    國    94    年    8     月    12    日\n",
  "structure": {
    "main": "乙○○繳納之保證金新臺幣壹萬元沒入之。",
    "reason": "一、按具保之被告逃匿者，應命具保人繳納指定之保證金額，並\n    沒入之；不繳納者，強制執行；保證金已繳納者，沒入之，\n    刑事訴訟法第一百十八條、第一百二十一條第一項分別定有\n    明文。\n二、本件聲請意旨略以：具保人乙○○因被告甲○○偽造文書案\n    件，經依法院指定之保證金額新臺幣一萬元，出具現金保證\n    後，將被告釋放，茲因該被告逃匿，依刑事訴訟法第一百十\n    八條之規定，應沒入具保人繳納之保證金（93刑保字第236\n    號）等語。\n三、經查：被告經臺灣板橋地方法院檢察署檢察官依法傳喚、拘\n    提，均未到案執行，具保人經通知亦未遵期通知或帶同被告\n    到案接受執行等情，有送達證書二紙、臺灣臺北地方法院檢\n    察署九十四年二月二十五日北檢退九四執助五六字第九四０\n    八號函、臺灣板橋地方法院檢察署通知書一件及法務部戶役\n    政連結作業系統查詢資料二紙在卷可稽。且被告迄今仍逃匿\n    中，尚未到案執行，復經本院依職權查證屬實，有臺灣高等\n    法院在監在押全國紀錄表一份附卷足憑，被告已然逃匿，揆\n    諸前揭說明，自應將具保人原繳納上開保證金沒入之。\n四、依刑事訴訟法第一百十八條、第一百二十一條第一項，裁定\n    如主文。"
  },
  "search": "臺灣板橋地方法院刑事裁定94年度聲字第1694號聲請人臺灣板橋地方法院檢察署檢察官被告甲○○具保人乙○○上列具保人因被告偽造文書案件，聲請人聲請沒入保證金（94年度執聲沒字第453號），本院裁定如下：主文乙○○繳納之保證金新臺幣壹萬元沒入之。理由一、按具保之被告逃匿者，應命具保人繳納指定之保證金額，並沒入之；不繳納者，強制執行；保證金已繳納者，沒入之，刑事訴訟法第一百十八條、第一百二十一條第一項分別定有明文。二、本件聲請意旨略以：具保人乙○○因被告甲○○偽造文書案件，經依法院指定之保證金額新臺幣一萬元，出具現金保證後，將被告釋放，茲因該被告逃匿，依刑事訴訟法第一百十八條之規定，應沒入具保人繳納之保證金（93刑保字第236號）等語。三、經查：被告經臺灣板橋地方法院檢察署檢察官依法傳喚、拘提，均未到案執行，具保人經通知亦未遵期通知或帶同被告到案接受執行等情，有送達證書二紙、臺灣臺北地方法院檢察署九十四年二月二十五日北檢退九四執助五六字第九四０八號函、臺灣板橋地方法院檢察署通知書一件及法務部戶役政連結作業系統查詢資料二紙在卷可稽。且被告迄今仍逃匿中，尚未到案執行，復經本院依職權查證屬實，有臺灣高等法院在監在押全國紀錄表一份附卷足憑，被告已然逃匿，揆諸前揭說明，自應將具保人原繳納上開保證金沒入之。四、依刑事訴訟法第一百十八條、第一百二十一條第一項，裁定如主文。中華民國94年8月12日刑事第十二庭法官劉元斐上列正本證明與原本無異。如不服本裁定，應於裁定送達後五日內向本院提出抗告狀。書記官郭玉芬中華民國94年8月12日",
  "characters": {
    "judges": [
      "劉元斐"
    ],
    "prosecutors": [

    ],
    "lawyers": [

    ],
    "clerks": [
      "郭玉芬"
    ],
    "plaintiffs": [

    ],
    "defendants": [
      "甲○○",
      "具  保  人  乙○○"
    ],
    "prosecutor_office": [
      "臺灣板橋地方法院檢察署檢察官"
    ],
    "creditors": [

    ],
    "debtors": [

    ],
    "judicial_associate_officer": [

    ]
  },
  "adjudged_at": "2005-08-12",
  "created_at": "2016-02-06 21:50:45",
  "updated_at": "2016-02-06 21:50:45"
}