{
  "identify": "PTD-94-易-150-20050811-2",
  "court": {
    "name": "臺灣屏東地方法院",
    "code": "PTD"
  },
  "division": {
    "name": "刑事",
    "code": "M"
  },
  "year": 94,
  "word": "易",
  "number": "150",
  "jcheck": "2",
  "reason": "恐嚇取財",
  "content": "臺灣屏東地方法院刑事判決               94年度易字第150號\n公  訴  人  臺灣屏東地方法院檢察署檢察官\n被      告  乙○○\n選任辯護人  謝信義律師\n上列被告因恐嚇取財案件，於中華民國94年8 月11日17時許，在\n本院第六法庭宣示判決，出席職員如下：\n          法  官  許心\n          書記官  林香如\n          通  譯  鍾耀\n法官起立朗讀判決主文、犯罪事實要旨、處罰條文、附記事項，\n及告以上訴限制、期間並提出上訴狀之法院，且諭知記載其內容\n：\n一、主  文：\n乙○○意圖為自己不法之所有，以恐嚇使人將第三人之物交付，\n處有期徒刑壹年。緩刑年，緩刑期內付保護管束。扣案之水果\n刀壹支沒收。\n二、犯罪事實要旨：\n    乙○○罹患精神分裂症，對於外界事務之知覺、理會及判斷\n    作用，較一般人平均人之程度為弱，為精神耗弱之人，竟意\n    圖為自己不法之所有，於民國94年2 月7 日1 時36分許，攜\n    帶其所有之水果刀1 把，進入屏東市○○街○段57巷「翁財\n    記超商」店內，將水果刀握在胸前，並站在櫃臺前對著站在\n    櫃臺內側之店員甲○○恫嚇稱：把收銀機打開，錢拿出來等\n    語，致甲○○心生畏懼，因而將收銀機打開，並後退至櫃臺\n    角落未敢移動，任憑黃青龍進入櫃臺內側取走收銀機內之現\n    金共計新台幣3140元，得手後，迅速逃離現場。嗣經警接獲\n    報案後，於上開超商斜對面巷口查獲乙○○，並扣得前開水\n    果刀1 把。\n三、處罰條文：\n    刑法第346 條第1 項、第74條第1 款、第93條第1 項、第38\n    條第1 項第2 款，罰金罰鍰提高標準條例第1 條前段，判決\n    如主文。\n四、協商判決除有刑事訴訟法第454 條之4 第1 項第1 款於本訊\n    問程序終結前，被告撤銷協商合意或檢察官撤回協商聲請者\n    ；第2 款被告協商之意思非出於自由意志者；第4 款被告所\n    犯之罪非第455 條之2 第1 項所定得以協商判決者；第6 款\n    被告有其他較重之裁判上一罪之犯罪事實者；第7 款法院認\n    應諭知免刑或免訴、不受理者情形之一，及違反同條第2 項\n    「法院應於協商合意範圍內為判決；法院為協商判決所科之\n    刑，以宣告緩刑或2 年以下有期徒刑、拘役或罰金為限」之\n    規定者外，不得上訴。\n五、本件如得上訴，而如不服本件判決，得自收受判決送達之日\n    起10日內，向本院提出上訴書狀，上訴於第二審法院。\n中    華    民    國    94    年    8     月    11    日\n                  刑事第六庭    書記官  林香如\n                                法  官  許心\n以上正本證明與原本無異。\n中    華    民    國    94    年    8     月    11    日\n                                書記官  林香如\n",
  "structure": {
  },
  "search": "臺灣屏東地方法院刑事判決94年度易字第150號公訴人臺灣屏東地方法院檢察署檢察官被告乙○○選任辯護人謝信義律師上列被告因恐嚇取財案件，於中華民國94年8月11日17時許，在本院第六法庭宣示判決，出席職員如下：法官許心書記官林香如通譯鍾耀法官起立朗讀判決主文、犯罪事實要旨、處罰條文、附記事項，及告以上訴限制、期間並提出上訴狀之法院，且諭知記載其內容：一、主文：乙○○意圖為自己不法之所有，以恐嚇使人將第三人之物交付，處有期徒刑壹年。緩刑年，緩刑期內付保護管束。扣案之水果刀壹支沒收。二、犯罪事實要旨：乙○○罹患精神分裂症，對於外界事務之知覺、理會及判斷作用，較一般人平均人之程度為弱，為精神耗弱之人，竟意圖為自己不法之所有，於民國94年2月7日1時36分許，攜帶其所有之水果刀1把，進入屏東市○○街○段57巷「翁財記超商」店內，將水果刀握在胸前，並站在櫃臺前對著站在櫃臺內側之店員甲○○恫嚇稱：把收銀機打開，錢拿出來等語，致甲○○心生畏懼，因而將收銀機打開，並後退至櫃臺角落未敢移動，任憑黃青龍進入櫃臺內側取走收銀機內之現金共計新台幣3140元，得手後，迅速逃離現場。嗣經警接獲報案後，於上開超商斜對面巷口查獲乙○○，並扣得前開水果刀1把。三、處罰條文：刑法第346條第1項、第74條第1款、第93條第1項、第38條第1項第2款，罰金罰鍰提高標準條例第1條前段，判決如主文。四、協商判決除有刑事訴訟法第454條之4第1項第1款於本訊問程序終結前，被告撤銷協商合意或檢察官撤回協商聲請者；第2款被告協商之意思非出於自由意志者；第4款被告所犯之罪非第455條之2第1項所定得以協商判決者；第6款被告有其他較重之裁判上一罪之犯罪事實者；第7款法院認應諭知免刑或免訴、不受理者情形之一，及違反同條第2項「法院應於協商合意範圍內為判決；法院為協商判決所科之刑，以宣告緩刑或2年以下有期徒刑、拘役或罰金為限」之規定者外，不得上訴。五、本件如得上訴，而如不服本件判決，得自收受判決送達之日起10日內，向本院提出上訴書狀，上訴於第二審法院。中華民國94年8月11日刑事第六庭書記官林香如法官許心以上正本證明與原本無異。中華民國94年8月11日書記官林香如",
  "characters": {
    "judges": [
      "許心",
      "許心"
    ],
    "prosecutors": [

    ],
    "lawyers": [
      "謝信義"
    ],
    "clerks": [
      "林香如",
      "林香如"
    ],
    "plaintiffs": [

    ],
    "defendants": [
      "乙○○"
    ],
    "prosecutor_office": [
      "臺灣屏東地方法院檢察署檢察官"
    ],
    "creditors": [

    ],
    "debtors": [

    ],
    "judicial_associate_officer": [

    ]
  },
  "adjudged_at": "2005-08-11",
  "created_at": "2016-02-06 21:52:19",
  "updated_at": "2016-02-06 21:52:19"
}