{
  "identify": "TPD-94-簡-1504-20050812-1",
  "court": {
    "name": "臺灣臺北地方法院",
    "code": "TPD"
  },
  "division": {
    "name": "刑事",
    "code": "M"
  },
  "year": 94,
  "word": "簡",
  "number": "1504",
  "jcheck": "1",
  "reason": "家庭暴力罪之傷害",
  "content": "臺灣臺北地方法院刑事簡易判決          94年度簡字第1504號\n聲  請  人  臺灣臺北地方法院檢察署檢察官\n被      告  甲○○\n上列被告因家庭暴力罪之傷害案件，經檢察官聲請以簡易判決處\n刑（94年度偵字第10810號），本院判決如下：\n    主      文\n甲○○傷害人之身體，處拘役拾日，如易科罰金，以參佰元折算\n壹日。\n    事實及理由\n一、本件犯罪事實、證據及應適用之法條，除「傅靜萱」係「傅\n    萱」之誤，應予更正外，均引用檢察官聲請簡易判決處刑\n    書之記載（如附件）。\n二、被告與告訴人原係夫妻，具有家庭暴力防治法第3條第1款所\n    定之家庭成員關係。核被告所為，係犯刑法第277條第1項之\n    傷害罪，並為家庭暴力防治法第2條第2項所稱之家庭暴力罪\n    。爰審酌被告於行為時，不思理性溝通，竟出手毆打自己配\n    偶，其犯罪動機、目的及手段，對告訴人身心造成之創傷等\n    情，量處如主文所示之刑，並諭知易科罰金之折算標準，以\n    示懲儆。\n三、依刑事訴訟法第449條第1項前段、第3項、第454條第2項，\n    刑法第277條第1項、第41條第1項前段，罰金罰鍰提高標準\n    條例第1條前段、第2條，以簡易判決處刑如主文。\n如不服本判決，應於判決送達後10日內，向本庭提出上訴狀，上\n訴於本院合議庭。\n中    華    民    國    94    年    8     月    12    日\n                  刑事第六庭    法  官  余學淵\n以上正本證明與原本無異。\n如不服本判決，應於判決送達後10日內向本院提出上訴狀（應抄\n附繕本）。告訴人或被害人如對於本判決不服者，應具備理由請\n求檢察官上訴，其上訴期間之計算係以檢察官收受判決正本之日\n期為準。\n                                書記官  黃瓊玉\n中    華    民    國    94    年    8     月    12    日\n附錄本案論罪科刑法條全文：\n中華民國刑法第277條（普通傷害罪）\n傷害人之身體或健康者，處三年以下有期徒刑、拘役或一千元以\n下罰金。\n犯前項之罪因而致人於死者，處無期徒刑或七年以上有期徒刑；\n致重傷者，處三年以上十年以下有期徒刑。\n",
  "structure": {
    "main": "甲○○傷害人之身體，處拘役拾日，如易科罰金，以參佰元折算\n壹日。",
    "fact": "一、本件犯罪事實、證據及應適用之法條，除「傅靜萱」係「傅\n    萱」之誤，應予更正外，均引用檢察官聲請簡易判決處刑\n    書之記載（如附件）。\n二、被告與告訴人原係夫妻，具有家庭暴力防治法第3條第1款所\n    定之家庭成員關係。核被告所為，係犯刑法第277條第1項之\n    傷害罪，並為家庭暴力防治法第2條第2項所稱之家庭暴力罪\n    。爰審酌被告於行為時，不思理性溝通，竟出手毆打自己配\n    偶，其犯罪動機、目的及手段，對告訴人身心造成之創傷等\n    情，量處如主文所示之刑，並諭知易科罰金之折算標準，以\n    示懲儆。\n三、依刑事訴訟法第449條第1項前段、第3項、第454條第2項，\n    刑法第277條第1項、第41條第1項前段，罰金罰鍰提高標準\n    條例第1條前段、第2條，以簡易判決處刑如主文。\n如不服本判決，應於判決送達後10日內，向本庭提出上訴狀，上\n訴於本院合議庭。",
    "reason": "一、本件犯罪事實、證據及應適用之法條，除「傅靜萱」係「傅\n    萱」之誤，應予更正外，均引用檢察官聲請簡易判決處刑\n    書之記載（如附件）。\n二、被告與告訴人原係夫妻，具有家庭暴力防治法第3條第1款所\n    定之家庭成員關係。核被告所為，係犯刑法第277條第1項之\n    傷害罪，並為家庭暴力防治法第2條第2項所稱之家庭暴力罪\n    。爰審酌被告於行為時，不思理性溝通，竟出手毆打自己配\n    偶，其犯罪動機、目的及手段，對告訴人身心造成之創傷等\n    情，量處如主文所示之刑，並諭知易科罰金之折算標準，以\n    示懲儆。\n三、依刑事訴訟法第449條第1項前段、第3項、第454條第2項，\n    刑法第277條第1項、第41條第1項前段，罰金罰鍰提高標準\n    條例第1條前段、第2條，以簡易判決處刑如主文。\n如不服本判決，應於判決送達後10日內，向本庭提出上訴狀，上\n訴於本院合議庭。"
  },
  "search": "臺灣臺北地方法院刑事簡易判決94年度簡字第1504號聲請人臺灣臺北地方法院檢察署檢察官被告甲○○上列被告因家庭暴力罪之傷害案件，經檢察官聲請以簡易判決處刑（94年度偵字第10810號），本院判決如下：主文甲○○傷害人之身體，處拘役拾日，如易科罰金，以參佰元折算壹日。事實及理由一、本件犯罪事實、證據及應適用之法條，除「傅靜萱」係「傅萱」之誤，應予更正外，均引用檢察官聲請簡易判決處刑書之記載（如附件）。二、被告與告訴人原係夫妻，具有家庭暴力防治法第3條第1款所定之家庭成員關係。核被告所為，係犯刑法第277條第1項之傷害罪，並為家庭暴力防治法第2條第2項所稱之家庭暴力罪。爰審酌被告於行為時，不思理性溝通，竟出手毆打自己配偶，其犯罪動機、目的及手段，對告訴人身心造成之創傷等情，量處如主文所示之刑，並諭知易科罰金之折算標準，以示懲儆。三、依刑事訴訟法第449條第1項前段、第3項、第454條第2項，刑法第277條第1項、第41條第1項前段，罰金罰鍰提高標準條例第1條前段、第2條，以簡易判決處刑如主文。如不服本判決，應於判決送達後10日內，向本庭提出上訴狀，上訴於本院合議庭。中華民國94年8月12日刑事第六庭法官余學淵以上正本證明與原本無異。如不服本判決，應於判決送達後10日內向本院提出上訴狀（應抄附繕本）。告訴人或被害人如對於本判決不服者，應具備理由請求檢察官上訴，其上訴期間之計算係以檢察官收受判決正本之日期為準。書記官黃瓊玉中華民國94年8月12日附錄本案論罪科刑法條全文：中華民國刑法第277條（普通傷害罪）傷害人之身體或健康者，處三年以下有期徒刑、拘役或一千元以下罰金。犯前項之罪因而致人於死者，處無期徒刑或七年以上有期徒刑；致重傷者，處三年以上十年以下有期徒刑。",
  "characters": {
    "judges": [
      "余學淵"
    ],
    "prosecutors": [

    ],
    "lawyers": [

    ],
    "clerks": [
      "黃瓊玉"
    ],
    "plaintiffs": [

    ],
    "defendants": [
      "甲○○"
    ],
    "prosecutor_office": [
      "臺灣臺北地方法院檢察署檢察官"
    ],
    "creditors": [

    ],
    "debtors": [

    ],
    "judicial_associate_officer": [

    ]
  },
  "adjudged_at": "2005-08-12",
  "created_at": "2016-02-06 21:52:54",
  "updated_at": "2016-02-06 21:52:54"
}