{
  "identify": "KSH-100-上訴-221-20110412-1",
  "court": {
    "name": "臺灣高等法院",
    "code": "KSH"
  },
  "division": {
    "name": "刑事",
    "code": "M"
  },
  "year": 100,
  "word": "上訴",
  "number": "221",
  "jcheck": "1",
  "reason": "違反槍砲彈藥刀械管制條例",
  "content": "臺灣高等法院高雄分院刑事判決        100年度上訴字第221號\n上  訴  人\n即  被  告  洪福來\n指定辯護人  李靜怡律師\n上列上訴人因違反槍砲彈藥刀械管制條例案件，不服臺灣高雄地\n方法院99年度訴字第1667號中華民國99年12月30日第一審判決（\n起訴案號：臺灣高雄地方法院檢察署99年度偵字第16205 號），\n提起上訴，本院判決如下：\n     主  文\n原判決撤銷。\n洪福來犯非法持有空氣槍罪，處有期徒刑拾月，併科罰金新臺幣\n萬元，罰金如易服勞役，以新臺幣壹仟元折算壹日。扣案之空\n氣槍壹支（槍枝管制編號：高鑑0000000000）、瓦斯\n鋼瓶玖支、瓦斯鋼瓶專用彈匣貳支、金色鋼珠彈壹瓶、銀色鋼珠\n彈壹瓶均沒收。\n    事  實\n一、洪福來明知具殺傷力之空氣槍，係槍砲彈藥刀械管制條例所\n    列管之違禁物，未經中央主管機關之許可，不得非法持有，\n    竟於民國99年4 月某日，在高雄市○○區○○路與中華路之\n    跳蚤市場，以新臺幣4000元之代價，向真實姓名不詳之人購\n    買具殺傷力之空氣槍1支（槍枝管制編號：高鑑0000000000\n    號）、瓦斯鋼瓶9支、瓦斯鋼瓶專用彈匣2支、金色鋼珠彈1\n    瓶、銀色鋼珠彈1瓶等物而非法持有之。嗣洪福來於99年5月\n    5 日20時40分許，將上開物品及海洛因、安非他命等物置於\n    紙袋內，行經高雄市○○區○○路26號前為警攔查，洪福來\n    主動向查緝員警表示紙袋內有空氣槍1 支、瓦斯鋼瓶9 支、\n    瓦斯鋼瓶專用彈匣2 支、金色鋼珠彈1 瓶、銀色鋼珠彈1 瓶\n    等情，自首而願接受裁判，經警方打開紙袋後，發現並扣得\n    上開空氣槍1 支、瓦斯鋼瓶9 支、瓦斯鋼瓶專用彈匣2 支、\n    金色鋼珠彈1 瓶、銀色鋼珠彈1 瓶及海洛因、安非他命（所\n    涉犯毒品危害防制條例部分，由檢察官另案偵查起訴），始\n    悉上情。\n二、案經高雄市政府警察局左營分局報告臺灣高雄地方法院檢察\n    署檢察官偵查起訴。\n    理  由\n甲、證據能力部分：\n一、按「法院或檢察官得囑託醫院、學校或其他相當之機關、團\n    體為鑑定，或審查他人之鑑定，並準用第203 條至第206 條\n    之1 之規定」、「鑑定之經過及其結果，應命鑑定人以言詞\n    或書面報告」，刑事訴訟法第208 條第1 項前段、第206 條\n    第1 項分別定有明文，是經檢察官囑託相當之機關為鑑定後\n    ，經鑑定人以書面報告其鑑定之結果者，該鑑定書面雖屬被\n    告以外之人於審判外之書面陳述，惟其屬刑事訴訟法第159\n    條第1 項所謂之「法律有規定者」，故不受該條項規定「不\n    得作為證據」之限制，而具有證據能力；又檢察官因實務現\n    實需求，就特定案件類型認當然有鑑定之必要者，基於檢察\n    一體原則，得由該管檢察長概括選任鑑定機關，是司法警察\n    等偵查輔助人員於案件未移送檢察官偵辦前之調查犯罪階段\n    ，依據檢察長之概括授權，先行將證物送請檢察機關預先核\n    定之專責鑑定人或鑑定機關實施鑑定，該鑑定人或鑑定機關\n    亦應視同受承辦檢察官所選任或囑託而執行鑑定業務。經查\n    本案卷附高雄縣政府警察局99年5 月12日高縣警鑑字第0990\n    077006號槍彈鑑定書，係高雄市政府警察局左營分局依檢察\n    機關事先概括授權囑託而送請高雄縣政府警察局所為之書面\n    鑑定報告，揆之上開說明，自具有證據能力。\n二、次按被告以外之人於審判外之陳述，雖不符刑事訴訟法第15\n    9 條之1 至第159 條之4 之規定，而經當事人於審判程序同\n    意作為證據，法院審酌該言詞陳述或書面陳述作成時之情況\n    ，認為適當者，亦得為證據；當事人、代理人或辯護人於法\n    院調查證據時，知有第159 條第1 項不得為證據之情形，而\n    未於言詞辯論終結前聲明異議者，視為有前項之同意，刑事\n    訴訟法第159 條之5 定有明文。查本案判決所引用具傳聞性\n    質之各項證據資料，業據本院於審判期日依法踐行調查證據\n    程序，公訴人、被告及辯護人就其餘證據之證據能力均未爭\n    執，且於言詞辯論終結前亦未聲明異議，復查無依法應排除\n    證據能力之情形，依上開規定，應有證據能力。\n乙、實體部分\n一、訊據被告固坦承於上揭時地持有扣案空氣槍（槍枝管制編號\n    ：高鑑0000000000）1 枝、瓦斯鋼瓶9 支、瓦斯鋼瓶專用彈\n    匣2 支及可供上述空氣發射用之金色鋼珠彈1 瓶、銀色鋼珠\n    彈1 瓶等情，惟辯稱不知扣案之空氣槍具有殺傷力云云。惟\n    查：\n  (一)被告於99年5 月5 日20時40分許，持裝有空氣槍1 支、瓦斯\n    鋼瓶9 支、瓦斯鋼瓶專用彈匣2 支、金色鋼珠彈1 瓶、銀色\n    鋼珠彈1 瓶、海洛因及安非他命等物（毒品部分另案偵辦）\n    置於紙袋內，於高雄市○○區○○路26號前為警攔查，並扣\n    得上開物品等情，有扣案槍枝、鋼珠可資佐證，以及查獲員\n    警黃泰櫻製作之職務報告書、高雄市政府警察局左營分局自\n    願性搜索同意筆錄、搜索扣押筆錄、扣押物品目錄表及現場\n    查獲照片在卷可憑（見警卷第15至23頁），並為被告所肯認\n    ，此部分事實堪以認定。\n  (二)又該扣案之空氣槍，經送高雄縣政府警察局以檢視法、性能\n    檢驗法及動能測試法鑑定鑑定結果，認：「送鑑手槍1 枝（\n    槍枝管制編號0000000000號），係氣體動力式槍枝，以小型\n    高壓氣體鋼瓶內氣體為發射動力，經以金屬彈丸（直徑約4.\n    5 mm、重約0.35公克）測試，其中最大發射速度為142 公尺\n    / 秒，計算其動能焦耳為3.5 焦耳，換算其單位面積動能為\n    22焦耳/ 平方公分。…依據司法院81年6 月11日秘台廳(二)字\n    第06985 號函釋，殺傷力的標準為在最具威力的適當距離，\n    以彈丸可穿入人體皮肉層之動能為基準。另依據美國軍醫總\n    署定義，彈丸撞擊動能達58呎磅（約為78.6焦耳），則足以\n    使人喪失戰鬥能力；內政部警政署刑事警察局對活豬作射擊\n    測試結果，彈丸單位動能面積達24焦耳/ 平方公分，則足以\n    穿入豬隻皮肉層；依日本科學警察研究所之研究結果，彈丸\n    單位面積動能達20焦耳/ 平方公分則足以穿入人體皮肉層。\n    」，有該局99年5 月12日刑鑑字第0990077006號槍彈鑑定書\n    乙份在卷足憑（見偵卷第11至14頁）。再依被告聲請送法務\n    部調查局鑑定，鑑定結果：送鑑槍枝（槍枝管制編號000000\n    0000）為KWC 系列之遊戲類空氣手槍，以塑膠及金屬材質零\n    件組合製成，於彈夾之氣瓶艙配置CO2/12g 小鋼瓶為動力來\n    源，可經由槍枝內襯管發射球形彈丸，未改裝改造為打擊底\n    火方式發射子彈。本案另送鑑彈夾2 個、直徑約4.5mm 重約\n    0.35g 鋼珠2 瓶，經任取其中1 個未經使用小鋼瓶供器操作\n    機械性能良好，再任取其中1 個未經使用小鋼瓶重新供氣並\n    裝填前述送鑑鋼珠射擊，能擊發，以彈速測定儀於槍口前方\n    1 公尺處射擊3 次每次3 發，第一次測得發射鋼珠速度依序\n    為141 、143 、143 公尺/ 秒，換算彈丸單位面積動能依序\n    為21.89 、22.51 、22.51 焦耳/ 平方公分；第二次測得發\n    射鋼珠速度依序為144 、145 、145 公尺/ 秒，換算彈丸單\n    位面積動能依序為22.82 、23.14 、23.14 焦耳/ 平方公分\n    ；第三次測得發射鋼珠速度依序為144 、140 、136 公尺/\n    秒，換算彈丸單位面積動能依序為22.82 、21.57 、20.36\n    焦耳/ 平方公分。本案送鑑槍枝經實際試射情況及結果，認\n    能發射適合之球形彈丸於近距離具殺傷力，亦有該局99年10\n    月11日調科參字第09900478820 號鑑定通知書在卷可佐（見\n    原審審訴卷第54、55頁）。是依前開說明，扣案空氣槍發射\n    金屬彈丸既足以穿入人體皮肉層，顯具有殺傷力，應堪認定\n    。\n  (三)再者，被告於原審準備程序時供稱：我買來是要打鳥，我站\n    在樹下打小鳥，距離約超過150 公分，我打小鳥之前，有把\n    空氣槍往前方地上濕泥巴地打，距離約有4.5 公尺，我打完\n    後就覺得應該可以打得到天空的小鳥等詞（原審審訴卷第30\n    頁），扣案空氣槍既經被告試射，且被告認為該空氣槍足以\n    打到小鳥等情觀之，顯見被告斯時清楚知悉該扣案空氣槍之\n    射擊威力遠較一般坊間販售無殺傷力之玩具空氣槍為大。況\n    且，槍枝以發射彈丸為目的，本有一定之破壞性，乃屬攻擊\n    性武器，本案扣案之物品除空氣槍外，另有金色鋼珠彈1 瓶\n    、銀色鋼珠彈1 瓶，有扣押物品清單附卷可稽，可見被告持\n    有該空氣槍之目的，有裝填鋼珠使用之意圖甚明，而裝填鋼\n    珠使用，因鋼珠之重量較重，須有較強之動能始能擊發，且\n    鋼珠為鐵製品，其殺傷力較塑膠製之BB彈強，顯非一般玩具\n    空氣槍之正常用途，足認被告於持有系爭槍枝時，已明知該\n    槍枝非屬一般玩具空氣槍，而係具有相當之攻擊性槍械無疑\n    ，被告辯稱不知扣案之空氣槍具有殺傷力云云，顯非可採。\n    而被告既然明知扣案空氣槍具有一定攻擊力，對其擊發後得\n    劃破人體皮肉層之殺傷力，更應有所認識，此乃普通之常識\n    ，自不能空言徒託未將扣案槍枝送鑑前，即無從得知其殺傷\n    力云云置辯，此部分辯解，亦屬無據。\n  (四)綜上所陳，本案事證明確，應依法論科。\n二、論罪科刑：\n  (一)新舊法比較\n    按被告行為後，槍砲彈藥刀械管制條例業於100 年1 月5 日\n    經修正公布，並於同月7 日生效，其第8 條第6 項增訂：「\n    犯第1 項、第2 項或第4 項有關空氣槍之罪，其情節輕微者\n    ，得減輕其刑。」經比較新舊法律，修正後之規定有利被告\n    ，爰依刑法第2 條第1 項但書之規定，適用新法之規定。\n  (二)核被告所為，係犯槍砲彈藥刀械管制條例第8 條第4 項之非\n    法持有空氣槍罪（公訴意旨誤載為係犯槍砲彈藥刀械管制條\n    例第8 條第4 項之未經許可寄藏具殺傷力空氣槍罪，惟經公\n    訴人於原審99年10月4 日準備程序中更正，見原審審訴卷第\n    27頁）。被告自99年4 月間某日起至99年5 月5 日為警查獲\n    為止，其持有上開空氣槍之行為，為繼續犯，自應論以單一\n    之持有行為。\n  (三)按刑法第62條所稱自首，指行為人自行申告自己尚未被發覺\n    之犯罪行為，而自願接受法院裁判之行為。其申告之內容，\n    僅須足以使刑事追訴機關憑以查明犯罪之真相即可，不以事\n    實真相完全相符為必要；又所謂「未發覺之罪」，應指刑事\n    追訴機關（司法警察〈官〉、檢察官或其他有偵查犯罪職權\n    之公務員）尚「未知悉」犯罪事實及犯人而言；此一「知悉\n    」，固不以確知某人為犯罪行為人為必要，只須有確切之根\n    據得為合理之可疑者，即足當之；惟如僅為主觀上之單純懷\n    疑或推測，尚難謂為發覺，最高法院72 年 度台上字第641\n    號、75年度台上字第1634號判例意旨可資參照。被告上開為\n    警查獲之情形，業據證人即查獲本案之警察黃泰櫻於原審審\n    理中證述：在距離本案2 個月前查緝被告毒品案時，曾發現\n    一個空的槍盒，盒子上印著一把槍，我們懷疑被告持有槍枝\n    ，沒有其他線民舉報被告持有槍枝，我們在被告居住附近公\n    園觀察很久一段時間，發現被告提紙袋要離開，被告看到我\n    們也不跑，問被告有什麼，他蹲下來主動說裡面有海洛因、\n    玩具槍等語明確（見原審卷第29至31頁）。查證人黃泰櫻係\n    本案發生前2 個月發現被告持有空的槍盒進而懷疑被告持有\n    槍枝，然持有槍盒原因甚多，可能係拾獲，或係為裝載其他\n    物品之用，亦未必持有槍盒即得推論係持有槍枝，且該槍枝\n    即係具有殺傷力，此從員警在當時僅發現空槍盒而未發現任\n    何槍枝可證，故員警因被告持有空槍盒，而將被告當作調查\n    之對象，此應屬單純主觀上之懷疑，復無其他線索，難謂已\n    達合理可疑之程度。是以證人黃泰櫻暨其他員警雖於事實欄\n    所述時、地攔檢盤查被告，然因空氣槍係藏放於被告紙袋之\n    中，均未外露而為員警所知悉，則在被告交出空氣槍前，員\n    警對於被告未經許可持有具殺傷力之空氣槍之犯行，尚難謂\n    有何確切之根據得為合理之可疑。且警察執行臨檢時未持搜\n    索票，亦無附帶搜索，緊急搜索情形，而係被告主動告知紙\n    袋裡有空氣槍，而以此方式坦承持有空氣槍，則被告在警方\n    尚未能確定係被告持有扣案之空氣槍前，即向警察承認該空\n    氣槍係其持有，應符合自首規定，爰依刑法第62條規定，減\n    輕其刑。又被告雖係對於未發覺之罪自首而受裁判，然並未\n    「報繳」其持有之空氣槍，核與槍砲彈藥刀械管制條例第18\n    條第1 項之規定減輕或免除其刑之構成要件未合，自無從適\n    用該條項之規定，併此敘明。\n  (四)查被告未循正當管道取得合法槍枝，其行為雖無足取，惟其\n    僅出於休閒、娛樂等動機而持有，對他人生命、身體、自由\n    、財產等法益之危險非高，是上開空氣槍雖具殺傷力，惟經\n    法務部調查局鑑驗後，其換算彈丸單位面積動能依序為22.8\n    2 、21.57 、20.36 焦耳/ 平方公分，已如上述，僅逾足以\n    穿入人體皮肉層之20焦耳/ 平方公分些許，足認其殺傷力較\n    低，對他人生命、身體、自由、財產等法益之危險甚低，且\n    卷內亦無證據顯示被告曾持該空氣槍從事任何非法行為之意\n    圖，對社會治安之危險性尚屬輕微，其犯罪情節輕微，爰依\n    修正後槍砲彈藥刀械管制條例第8 條第6 項規定減輕其刑，\n    並遞減之。又本件既已審酌被告犯罪情節輕微，依上開規定\n    予以減輕其刑，即無情輕法重，再適用刑法第59條酌減其刑\n    之餘地。\n三、對原判決之審查：\n    原審據以論處被告非法持有空氣槍罪刑，固非無見；惟查：\n    按被告行為後，槍砲彈藥刀械管制條例修正第8條規定，業\n    已增訂第6項：「犯第1項、第2項或第4項有關空氣槍之罪，\n    其情節輕微者，得減輕其刑」，並經公布生效，被告非法持\n    有空氣槍之犯罪情節，尚屬輕微，已如前述，原審未及適用\n    修正後之上開規定以減輕其刑，容有未合，被告上訴否認犯\n    罪雖不可採，然其執此上訴指摘原判決不當，為有理由，自\n    應由本院將原判決撤銷改判。\n四、量刑及沒收\n  (一)爰審酌被告未經許可，擅自持有具有殺傷力之空氣槍，對於\n    他人生命、身體以及社會治安造成潛在之危險與不安，實有\n    可議，惟念持有之空氣槍僅1 支，且殺傷力尚非十分強大等\n    一切情狀，量處如主文第2 項所示之刑，並審酌被告前揭情\n    狀，就罰金刑部分，依刑法第42條第3 項前段規定，諭知如\n    主文第2 項所示易服勞役之折算標準，以資懲儆。\n  (二)扣案空氣槍（槍枝管制編號：高鑑0000000000）1 枝具有殺\n    傷力，業已認定如前，屬違禁物，應依刑法第38條第1 項第\n    1 款規定宣告沒收；扣案之瓦斯鋼瓶9 支、瓦斯鋼瓶專用彈\n    匣2 支及可供上述空氣發射用之金色鋼珠彈1 瓶、銀色鋼珠\n    彈1 瓶，均係被告所有、供上開空氣槍使用之物，業據被告\n    於原審審理時供明無誤（見原審審訴卷第27頁），爰依刑法\n    第38條第1 項第2 款規定宣告沒收。至同時扣案之第一級毒\n    品海洛因9 包、第二級毒品安非他命1 包等物，核與本案犯\n    罪無關，爰不予宣告沒收，附此敘明之。\n據上論斷，應依刑事訴訟法第364 條、第369 條第1 項前段、第\n299 條第1 項前段，槍砲彈藥刀械管制條例第8 條第4 項、第6\n項，刑法第11條前段、第62條前段、第42條第3 項前段、第38條\n第1 項第1 款、第2 款，判決如主文。\n本案經檢察官陳宗吟到庭執行職務。\n中    華    民    國    100   年    4     月    12    日\n                  刑事第七庭    審判長法  官  莊飛宗\n                                      法  官  謝宏宗\n                                      法  官  蔡廣昇\n以上正本證明與原本無異。\n如不服本判決應於收受本判決後10日內向本院提出上訴書狀，其\n未敘述上訴理由者，並得於提起上訴後10日內向本院補提理由書\n狀（均須按他造當事人之人數附繕本）「切勿逕送上級法院」。\n中    華    民    國   100    年    4     月    12    日\n                                      書記官  曾允志\n附錄本判決論罪科刑法條：\n修正後槍砲彈藥刀械管制條例第8條第1項、第4項、第6項\n未經許可，製造、販賣或運輸鋼筆槍、瓦斯槍、麻醉槍、獵槍、\n空氣槍或第 4 條第 1 項第 1 款所定其他可發射金屬或子彈具\n有殺傷力之各式槍砲者，處無期徒刑或 5 年以上有期徒刑，併\n科新臺幣 1 千萬元以下罰金。\n未經許可，持有、寄藏或意圖販賣而陳列第1 項所列槍枝者，處\n3 年以上10年以下有期徒刑，併科新臺幣7 百萬元以下罰金。\n犯第 1 項、第 2 項或第 4 項有關空氣槍之罪，其情節輕微者\n，得減輕其刑。",
  "structure": {
    "main": "原判決撤銷。\n洪福來犯非法持有空氣槍罪，處有期徒刑拾月，併科罰金新臺幣\n萬元，罰金如易服勞役，以新臺幣壹仟元折算壹日。扣案之空\n氣槍壹支（槍枝管制編號：高鑑0000000000）、瓦斯\n鋼瓶玖支、瓦斯鋼瓶專用彈匣貳支、金色鋼珠彈壹瓶、銀色鋼珠\n彈壹瓶均沒收。",
    "fact": "一、洪福來明知具殺傷力之空氣槍，係槍砲彈藥刀械管制條例所\n    列管之違禁物，未經中央主管機關之許可，不得非法持有，\n    竟於民國99年4 月某日，在高雄市○○區○○路與中華路之\n    跳蚤市場，以新臺幣4000元之代價，向真實姓名不詳之人購\n    買具殺傷力之空氣槍1支（槍枝管制編號：高鑑0000000000\n    號）、瓦斯鋼瓶9支、瓦斯鋼瓶專用彈匣2支、金色鋼珠彈1\n    瓶、銀色鋼珠彈1瓶等物而非法持有之。嗣洪福來於99年5月\n    5 日20時40分許，將上開物品及海洛因、安非他命等物置於\n    紙袋內，行經高雄市○○區○○路26號前為警攔查，洪福來\n    主動向查緝員警表示紙袋內有空氣槍1 支、瓦斯鋼瓶9 支、\n    瓦斯鋼瓶專用彈匣2 支、金色鋼珠彈1 瓶、銀色鋼珠彈1 瓶\n    等情，自首而願接受裁判，經警方打開紙袋後，發現並扣得\n    上開空氣槍1 支、瓦斯鋼瓶9 支、瓦斯鋼瓶專用彈匣2 支、\n    金色鋼珠彈1 瓶、銀色鋼珠彈1 瓶及海洛因、安非他命（所\n    涉犯毒品危害防制條例部分，由檢察官另案偵查起訴），始\n    悉上情。\n二、案經高雄市政府警察局左營分局報告臺灣高雄地方法院檢察\n    署檢察官偵查起訴。",
    "reason": "甲、證據能力部分：\n一、按「法院或檢察官得囑託醫院、學校或其他相當之機關、團\n    體為鑑定，或審查他人之鑑定，並準用第203 條至第206 條\n    之1 之規定」、「鑑定之經過及其結果，應命鑑定人以言詞\n    或書面報告」，刑事訴訟法第208 條第1 項前段、第206 條\n    第1 項分別定有明文，是經檢察官囑託相當之機關為鑑定後\n    ，經鑑定人以書面報告其鑑定之結果者，該鑑定書面雖屬被\n    告以外之人於審判外之書面陳述，惟其屬刑事訴訟法第159\n    條第1 項所謂之「法律有規定者」，故不受該條項規定「不\n    得作為證據」之限制，而具有證據能力；又檢察官因實務現\n    實需求，就特定案件類型認當然有鑑定之必要者，基於檢察\n    一體原則，得由該管檢察長概括選任鑑定機關，是司法警察\n    等偵查輔助人員於案件未移送檢察官偵辦前之調查犯罪階段\n    ，依據檢察長之概括授權，先行將證物送請檢察機關預先核\n    定之專責鑑定人或鑑定機關實施鑑定，該鑑定人或鑑定機關\n    亦應視同受承辦檢察官所選任或囑託而執行鑑定業務。經查\n    本案卷附高雄縣政府警察局99年5 月12日高縣警鑑字第0990\n    077006號槍彈鑑定書，係高雄市政府警察局左營分局依檢察\n    機關事先概括授權囑託而送請高雄縣政府警察局所為之書面\n    鑑定報告，揆之上開說明，自具有證據能力。\n二、次按被告以外之人於審判外之陳述，雖不符刑事訴訟法第15\n    9 條之1 至第159 條之4 之規定，而經當事人於審判程序同\n    意作為證據，法院審酌該言詞陳述或書面陳述作成時之情況\n    ，認為適當者，亦得為證據；當事人、代理人或辯護人於法\n    院調查證據時，知有第159 條第1 項不得為證據之情形，而\n    未於言詞辯論終結前聲明異議者，視為有前項之同意，刑事\n    訴訟法第159 條之5 定有明文。查本案判決所引用具傳聞性\n    質之各項證據資料，業據本院於審判期日依法踐行調查證據\n    程序，公訴人、被告及辯護人就其餘證據之證據能力均未爭\n    執，且於言詞辯論終結前亦未聲明異議，復查無依法應排除\n    證據能力之情形，依上開規定，應有證據能力。\n乙、實體部分\n一、訊據被告固坦承於上揭時地持有扣案空氣槍（槍枝管制編號\n    ：高鑑0000000000）1 枝、瓦斯鋼瓶9 支、瓦斯鋼瓶專用彈\n    匣2 支及可供上述空氣發射用之金色鋼珠彈1 瓶、銀色鋼珠\n    彈1 瓶等情，惟辯稱不知扣案之空氣槍具有殺傷力云云。惟\n    查：\n  (一)被告於99年5 月5 日20時40分許，持裝有空氣槍1 支、瓦斯\n    鋼瓶9 支、瓦斯鋼瓶專用彈匣2 支、金色鋼珠彈1 瓶、銀色\n    鋼珠彈1 瓶、海洛因及安非他命等物（毒品部分另案偵辦）\n    置於紙袋內，於高雄市○○區○○路26號前為警攔查，並扣\n    得上開物品等情，有扣案槍枝、鋼珠可資佐證，以及查獲員\n    警黃泰櫻製作之職務報告書、高雄市政府警察局左營分局自\n    願性搜索同意筆錄、搜索扣押筆錄、扣押物品目錄表及現場\n    查獲照片在卷可憑（見警卷第15至23頁），並為被告所肯認\n    ，此部分事實堪以認定。\n  (二)又該扣案之空氣槍，經送高雄縣政府警察局以檢視法、性能\n    檢驗法及動能測試法鑑定鑑定結果，認：「送鑑手槍1 枝（\n    槍枝管制編號0000000000號），係氣體動力式槍枝，以小型\n    高壓氣體鋼瓶內氣體為發射動力，經以金屬彈丸（直徑約4.\n    5 mm、重約0.35公克）測試，其中最大發射速度為142 公尺\n    / 秒，計算其動能焦耳為3.5 焦耳，換算其單位面積動能為\n    22焦耳/ 平方公分。…依據司法院81年6 月11日秘台廳(二)字\n    第06985 號函釋，殺傷力的標準為在最具威力的適當距離，\n    以彈丸可穿入人體皮肉層之動能為基準。另依據美國軍醫總\n    署定義，彈丸撞擊動能達58呎磅（約為78.6焦耳），則足以\n    使人喪失戰鬥能力；內政部警政署刑事警察局對活豬作射擊\n    測試結果，彈丸單位動能面積達24焦耳/ 平方公分，則足以\n    穿入豬隻皮肉層；依日本科學警察研究所之研究結果，彈丸\n    單位面積動能達20焦耳/ 平方公分則足以穿入人體皮肉層。\n    」，有該局99年5 月12日刑鑑字第0990077006號槍彈鑑定書\n    乙份在卷足憑（見偵卷第11至14頁）。再依被告聲請送法務\n    部調查局鑑定，鑑定結果：送鑑槍枝（槍枝管制編號000000\n    0000）為KWC 系列之遊戲類空氣手槍，以塑膠及金屬材質零\n    件組合製成，於彈夾之氣瓶艙配置CO2/12g 小鋼瓶為動力來\n    源，可經由槍枝內襯管發射球形彈丸，未改裝改造為打擊底\n    火方式發射子彈。本案另送鑑彈夾2 個、直徑約4.5mm 重約\n    0.35g 鋼珠2 瓶，經任取其中1 個未經使用小鋼瓶供器操作\n    機械性能良好，再任取其中1 個未經使用小鋼瓶重新供氣並\n    裝填前述送鑑鋼珠射擊，能擊發，以彈速測定儀於槍口前方\n    1 公尺處射擊3 次每次3 發，第一次測得發射鋼珠速度依序\n    為141 、143 、143 公尺/ 秒，換算彈丸單位面積動能依序\n    為21.89 、22.51 、22.51 焦耳/ 平方公分；第二次測得發\n    射鋼珠速度依序為144 、145 、145 公尺/ 秒，換算彈丸單\n    位面積動能依序為22.82 、23.14 、23.14 焦耳/ 平方公分\n    ；第三次測得發射鋼珠速度依序為144 、140 、136 公尺/\n    秒，換算彈丸單位面積動能依序為22.82 、21.57 、20.36\n    焦耳/ 平方公分。本案送鑑槍枝經實際試射情況及結果，認\n    能發射適合之球形彈丸於近距離具殺傷力，亦有該局99年10\n    月11日調科參字第09900478820 號鑑定通知書在卷可佐（見\n    原審審訴卷第54、55頁）。是依前開說明，扣案空氣槍發射\n    金屬彈丸既足以穿入人體皮肉層，顯具有殺傷力，應堪認定\n    。\n  (三)再者，被告於原審準備程序時供稱：我買來是要打鳥，我站\n    在樹下打小鳥，距離約超過150 公分，我打小鳥之前，有把\n    空氣槍往前方地上濕泥巴地打，距離約有4.5 公尺，我打完\n    後就覺得應該可以打得到天空的小鳥等詞（原審審訴卷第30\n    頁），扣案空氣槍既經被告試射，且被告認為該空氣槍足以\n    打到小鳥等情觀之，顯見被告斯時清楚知悉該扣案空氣槍之\n    射擊威力遠較一般坊間販售無殺傷力之玩具空氣槍為大。況\n    且，槍枝以發射彈丸為目的，本有一定之破壞性，乃屬攻擊\n    性武器，本案扣案之物品除空氣槍外，另有金色鋼珠彈1 瓶\n    、銀色鋼珠彈1 瓶，有扣押物品清單附卷可稽，可見被告持\n    有該空氣槍之目的，有裝填鋼珠使用之意圖甚明，而裝填鋼\n    珠使用，因鋼珠之重量較重，須有較強之動能始能擊發，且\n    鋼珠為鐵製品，其殺傷力較塑膠製之BB彈強，顯非一般玩具\n    空氣槍之正常用途，足認被告於持有系爭槍枝時，已明知該\n    槍枝非屬一般玩具空氣槍，而係具有相當之攻擊性槍械無疑\n    ，被告辯稱不知扣案之空氣槍具有殺傷力云云，顯非可採。\n    而被告既然明知扣案空氣槍具有一定攻擊力，對其擊發後得\n    劃破人體皮肉層之殺傷力，更應有所認識，此乃普通之常識\n    ，自不能空言徒託未將扣案槍枝送鑑前，即無從得知其殺傷\n    力云云置辯，此部分辯解，亦屬無據。\n  (四)綜上所陳，本案事證明確，應依法論科。\n二、論罪科刑：\n  (一)新舊法比較\n    按被告行為後，槍砲彈藥刀械管制條例業於100 年1 月5 日\n    經修正公布，並於同月7 日生效，其第8 條第6 項增訂：「\n    犯第1 項、第2 項或第4 項有關空氣槍之罪，其情節輕微者\n    ，得減輕其刑。」經比較新舊法律，修正後之規定有利被告\n    ，爰依刑法第2 條第1 項但書之規定，適用新法之規定。\n  (二)核被告所為，係犯槍砲彈藥刀械管制條例第8 條第4 項之非\n    法持有空氣槍罪（公訴意旨誤載為係犯槍砲彈藥刀械管制條\n    例第8 條第4 項之未經許可寄藏具殺傷力空氣槍罪，惟經公\n    訴人於原審99年10月4 日準備程序中更正，見原審審訴卷第\n    27頁）。被告自99年4 月間某日起至99年5 月5 日為警查獲\n    為止，其持有上開空氣槍之行為，為繼續犯，自應論以單一\n    之持有行為。\n  (三)按刑法第62條所稱自首，指行為人自行申告自己尚未被發覺\n    之犯罪行為，而自願接受法院裁判之行為。其申告之內容，\n    僅須足以使刑事追訴機關憑以查明犯罪之真相即可，不以事\n    實真相完全相符為必要；又所謂「未發覺之罪」，應指刑事\n    追訴機關（司法警察〈官〉、檢察官或其他有偵查犯罪職權\n    之公務員）尚「未知悉」犯罪事實及犯人而言；此一「知悉\n    」，固不以確知某人為犯罪行為人為必要，只須有確切之根\n    據得為合理之可疑者，即足當之；惟如僅為主觀上之單純懷\n    疑或推測，尚難謂為發覺，最高法院72 年 度台上字第641\n    號、75年度台上字第1634號判例意旨可資參照。被告上開為\n    警查獲之情形，業據證人即查獲本案之警察黃泰櫻於原審審\n    理中證述：在距離本案2 個月前查緝被告毒品案時，曾發現\n    一個空的槍盒，盒子上印著一把槍，我們懷疑被告持有槍枝\n    ，沒有其他線民舉報被告持有槍枝，我們在被告居住附近公\n    園觀察很久一段時間，發現被告提紙袋要離開，被告看到我\n    們也不跑，問被告有什麼，他蹲下來主動說裡面有海洛因、\n    玩具槍等語明確（見原審卷第29至31頁）。查證人黃泰櫻係\n    本案發生前2 個月發現被告持有空的槍盒進而懷疑被告持有\n    槍枝，然持有槍盒原因甚多，可能係拾獲，或係為裝載其他\n    物品之用，亦未必持有槍盒即得推論係持有槍枝，且該槍枝\n    即係具有殺傷力，此從員警在當時僅發現空槍盒而未發現任\n    何槍枝可證，故員警因被告持有空槍盒，而將被告當作調查\n    之對象，此應屬單純主觀上之懷疑，復無其他線索，難謂已\n    達合理可疑之程度。是以證人黃泰櫻暨其他員警雖於事實欄\n    所述時、地攔檢盤查被告，然因空氣槍係藏放於被告紙袋之\n    中，均未外露而為員警所知悉，則在被告交出空氣槍前，員\n    警對於被告未經許可持有具殺傷力之空氣槍之犯行，尚難謂\n    有何確切之根據得為合理之可疑。且警察執行臨檢時未持搜\n    索票，亦無附帶搜索，緊急搜索情形，而係被告主動告知紙\n    袋裡有空氣槍，而以此方式坦承持有空氣槍，則被告在警方\n    尚未能確定係被告持有扣案之空氣槍前，即向警察承認該空\n    氣槍係其持有，應符合自首規定，爰依刑法第62條規定，減\n    輕其刑。又被告雖係對於未發覺之罪自首而受裁判，然並未\n    「報繳」其持有之空氣槍，核與槍砲彈藥刀械管制條例第18\n    條第1 項之規定減輕或免除其刑之構成要件未合，自無從適\n    用該條項之規定，併此敘明。\n  (四)查被告未循正當管道取得合法槍枝，其行為雖無足取，惟其\n    僅出於休閒、娛樂等動機而持有，對他人生命、身體、自由\n    、財產等法益之危險非高，是上開空氣槍雖具殺傷力，惟經\n    法務部調查局鑑驗後，其換算彈丸單位面積動能依序為22.8\n    2 、21.57 、20.36 焦耳/ 平方公分，已如上述，僅逾足以\n    穿入人體皮肉層之20焦耳/ 平方公分些許，足認其殺傷力較\n    低，對他人生命、身體、自由、財產等法益之危險甚低，且\n    卷內亦無證據顯示被告曾持該空氣槍從事任何非法行為之意\n    圖，對社會治安之危險性尚屬輕微，其犯罪情節輕微，爰依\n    修正後槍砲彈藥刀械管制條例第8 條第6 項規定減輕其刑，\n    並遞減之。又本件既已審酌被告犯罪情節輕微，依上開規定\n    予以減輕其刑，即無情輕法重，再適用刑法第59條酌減其刑\n    之餘地。\n三、對原判決之審查：\n    原審據以論處被告非法持有空氣槍罪刑，固非無見；惟查：\n    按被告行為後，槍砲彈藥刀械管制條例修正第8條規定，業\n    已增訂第6項：「犯第1項、第2項或第4項有關空氣槍之罪，\n    其情節輕微者，得減輕其刑」，並經公布生效，被告非法持\n    有空氣槍之犯罪情節，尚屬輕微，已如前述，原審未及適用\n    修正後之上開規定以減輕其刑，容有未合，被告上訴否認犯\n    罪雖不可採，然其執此上訴指摘原判決不當，為有理由，自\n    應由本院將原判決撤銷改判。\n四、量刑及沒收\n  (一)爰審酌被告未經許可，擅自持有具有殺傷力之空氣槍，對於\n    他人生命、身體以及社會治安造成潛在之危險與不安，實有\n    可議，惟念持有之空氣槍僅1 支，且殺傷力尚非十分強大等\n    一切情狀，量處如主文第2 項所示之刑，並審酌被告前揭情\n    狀，就罰金刑部分，依刑法第42條第3 項前段規定，諭知如\n    主文第2 項所示易服勞役之折算標準，以資懲儆。\n  (二)扣案空氣槍（槍枝管制編號：高鑑0000000000）1 枝具有殺\n    傷力，業已認定如前，屬違禁物，應依刑法第38條第1 項第\n    1 款規定宣告沒收；扣案之瓦斯鋼瓶9 支、瓦斯鋼瓶專用彈\n    匣2 支及可供上述空氣發射用之金色鋼珠彈1 瓶、銀色鋼珠\n    彈1 瓶，均係被告所有、供上開空氣槍使用之物，業據被告\n    於原審審理時供明無誤（見原審審訴卷第27頁），爰依刑法\n    第38條第1 項第2 款規定宣告沒收。至同時扣案之第一級毒\n    品海洛因9 包、第二級毒品安非他命1 包等物，核與本案犯\n    罪無關，爰不予宣告沒收，附此敘明之。\n據上論斷，應依刑事訴訟法第364 條、第369 條第1 項前段、第\n299 條第1 項前段，槍砲彈藥刀械管制條例第8 條第4 項、第6\n項，刑法第11條前段、第62條前段、第42條第3 項前段、第38條\n第1 項第1 款、第2 款，判決如主文。\n本案經檢察官陳宗吟到庭執行職務。\n中    華    民    國    100   年    4     月    12    日\n                  刑事第七庭    審判長法  官  莊飛宗\n                                      法  官  謝宏宗\n                                      法  官  蔡廣昇\n以上正本證明與原本無異。\n如不服本判決應於收受本判決後10日內向本院提出上訴書狀，其\n未敘述上訴理由者，並得於提起上訴後10日內向本院補提理由書\n狀（均須按他造當事人之人數附繕本）「切勿逕送上級法院」。"
  },
  "search": "臺灣高等法院高雄分院刑事判決100年度上訴字第221號上訴人即被告洪福來指定辯護人李靜怡律師上列上訴人因違反槍砲彈藥刀械管制條例案件，不服臺灣高雄地方法院99年度訴字第1667號中華民國99年12月30日第一審判決（起訴案號：臺灣高雄地方法院檢察署99年度偵字第16205號），提起上訴，本院判決如下：主文原判決撤銷。洪福來犯非法持有空氣槍罪，處有期徒刑拾月，併科罰金新臺幣萬元，罰金如易服勞役，以新臺幣壹仟元折算壹日。扣案之空氣槍壹支（槍枝管制編號：高鑑0000000000）、瓦斯鋼瓶玖支、瓦斯鋼瓶專用彈匣貳支、金色鋼珠彈壹瓶、銀色鋼珠彈壹瓶均沒收。事實一、洪福來明知具殺傷力之空氣槍，係槍砲彈藥刀械管制條例所列管之違禁物，未經中央主管機關之許可，不得非法持有，竟於民國99年4月某日，在高雄市○○區○○路與中華路之跳蚤市場，以新臺幣4000元之代價，向真實姓名不詳之人購買具殺傷力之空氣槍1支（槍枝管制編號：高鑑0000000000號）、瓦斯鋼瓶9支、瓦斯鋼瓶專用彈匣2支、金色鋼珠彈1瓶、銀色鋼珠彈1瓶等物而非法持有之。嗣洪福來於99年5月5日20時40分許，將上開物品及海洛因、安非他命等物置於紙袋內，行經高雄市○○區○○路26號前為警攔查，洪福來主動向查緝員警表示紙袋內有空氣槍1支、瓦斯鋼瓶9支、瓦斯鋼瓶專用彈匣2支、金色鋼珠彈1瓶、銀色鋼珠彈1瓶等情，自首而願接受裁判，經警方打開紙袋後，發現並扣得上開空氣槍1支、瓦斯鋼瓶9支、瓦斯鋼瓶專用彈匣2支、金色鋼珠彈1瓶、銀色鋼珠彈1瓶及海洛因、安非他命（所涉犯毒品危害防制條例部分，由檢察官另案偵查起訴），始悉上情。二、案經高雄市政府警察局左營分局報告臺灣高雄地方法院檢察署檢察官偵查起訴。理由甲、證據能力部分：一、按「法院或檢察官得囑託醫院、學校或其他相當之機關、團體為鑑定，或審查他人之鑑定，並準用第203條至第206條之1之規定」、「鑑定之經過及其結果，應命鑑定人以言詞或書面報告」，刑事訴訟法第208條第1項前段、第206條第1項分別定有明文，是經檢察官囑託相當之機關為鑑定後，經鑑定人以書面報告其鑑定之結果者，該鑑定書面雖屬被告以外之人於審判外之書面陳述，惟其屬刑事訴訟法第159條第1項所謂之「法律有規定者」，故不受該條項規定「不得作為證據」之限制，而具有證據能力；又檢察官因實務現實需求，就特定案件類型認當然有鑑定之必要者，基於檢察一體原則，得由該管檢察長概括選任鑑定機關，是司法警察等偵查輔助人員於案件未移送檢察官偵辦前之調查犯罪階段，依據檢察長之概括授權，先行將證物送請檢察機關預先核定之專責鑑定人或鑑定機關實施鑑定，該鑑定人或鑑定機關亦應視同受承辦檢察官所選任或囑託而執行鑑定業務。經查本案卷附高雄縣政府警察局99年5月12日高縣警鑑字第0990077006號槍彈鑑定書，係高雄市政府警察局左營分局依檢察機關事先概括授權囑託而送請高雄縣政府警察局所為之書面鑑定報告，揆之上開說明，自具有證據能力。二、次按被告以外之人於審判外之陳述，雖不符刑事訴訟法第159條之1至第159條之4之規定，而經當事人於審判程序同意作為證據，法院審酌該言詞陳述或書面陳述作成時之情況，認為適當者，亦得為證據；當事人、代理人或辯護人於法院調查證據時，知有第159條第1項不得為證據之情形，而未於言詞辯論終結前聲明異議者，視為有前項之同意，刑事訴訟法第159條之5定有明文。查本案判決所引用具傳聞性質之各項證據資料，業據本院於審判期日依法踐行調查證據程序，公訴人、被告及辯護人就其餘證據之證據能力均未爭執，且於言詞辯論終結前亦未聲明異議，復查無依法應排除證據能力之情形，依上開規定，應有證據能力。乙、實體部分一、訊據被告固坦承於上揭時地持有扣案空氣槍（槍枝管制編號：高鑑0000000000）1枝、瓦斯鋼瓶9支、瓦斯鋼瓶專用彈匣2支及可供上述空氣發射用之金色鋼珠彈1瓶、銀色鋼珠彈1瓶等情，惟辯稱不知扣案之空氣槍具有殺傷力云云。惟查：(一)被告於99年5月5日20時40分許，持裝有空氣槍1支、瓦斯鋼瓶9支、瓦斯鋼瓶專用彈匣2支、金色鋼珠彈1瓶、銀色鋼珠彈1瓶、海洛因及安非他命等物（毒品部分另案偵辦）置於紙袋內，於高雄市○○區○○路26號前為警攔查，並扣得上開物品等情，有扣案槍枝、鋼珠可資佐證，以及查獲員警黃泰櫻製作之職務報告書、高雄市政府警察局左營分局自願性搜索同意筆錄、搜索扣押筆錄、扣押物品目錄表及現場查獲照片在卷可憑（見警卷第15至23頁），並為被告所肯認，此部分事實堪以認定。(二)又該扣案之空氣槍，經送高雄縣政府警察局以檢視法、性能檢驗法及動能測試法鑑定鑑定結果，認：「送鑑手槍1枝（槍枝管制編號0000000000號），係氣體動力式槍枝，以小型高壓氣體鋼瓶內氣體為發射動力，經以金屬彈丸（直徑約4.5mm、重約0.35公克）測試，其中最大發射速度為142公尺/秒，計算其動能焦耳為3.5焦耳，換算其單位面積動能為22焦耳/平方公分。…依據司法院81年6月11日秘台廳(二)字第06985號函釋，殺傷力的標準為在最具威力的適當距離，以彈丸可穿入人體皮肉層之動能為基準。另依據美國軍醫總署定義，彈丸撞擊動能達58呎磅（約為78.6焦耳），則足以使人喪失戰鬥能力；內政部警政署刑事警察局對活豬作射擊測試結果，彈丸單位動能面積達24焦耳/平方公分，則足以穿入豬隻皮肉層；依日本科學警察研究所之研究結果，彈丸單位面積動能達20焦耳/平方公分則足以穿入人體皮肉層。」，有該局99年5月12日刑鑑字第0990077006號槍彈鑑定書乙份在卷足憑（見偵卷第11至14頁）。再依被告聲請送法務部調查局鑑定，鑑定結果：送鑑槍枝（槍枝管制編號0000000000）為KWC系列之遊戲類空氣手槍，以塑膠及金屬材質零件組合製成，於彈夾之氣瓶艙配置CO2/12g小鋼瓶為動力來源，可經由槍枝內襯管發射球形彈丸，未改裝改造為打擊底火方式發射子彈。本案另送鑑彈夾2個、直徑約4.5mm重約0.35g鋼珠2瓶，經任取其中1個未經使用小鋼瓶供器操作機械性能良好，再任取其中1個未經使用小鋼瓶重新供氣並裝填前述送鑑鋼珠射擊，能擊發，以彈速測定儀於槍口前方1公尺處射擊3次每次3發，第一次測得發射鋼珠速度依序為141、143、143公尺/秒，換算彈丸單位面積動能依序為21.89、22.51、22.51焦耳/平方公分；第二次測得發射鋼珠速度依序為144、145、145公尺/秒，換算彈丸單位面積動能依序為22.82、23.14、23.14焦耳/平方公分；第三次測得發射鋼珠速度依序為144、140、136公尺/秒，換算彈丸單位面積動能依序為22.82、21.57、20.36焦耳/平方公分。本案送鑑槍枝經實際試射情況及結果，認能發射適合之球形彈丸於近距離具殺傷力，亦有該局99年10月11日調科參字第09900478820號鑑定通知書在卷可佐（見原審審訴卷第54、55頁）。是依前開說明，扣案空氣槍發射金屬彈丸既足以穿入人體皮肉層，顯具有殺傷力，應堪認定。(三)再者，被告於原審準備程序時供稱：我買來是要打鳥，我站在樹下打小鳥，距離約超過150公分，我打小鳥之前，有把空氣槍往前方地上濕泥巴地打，距離約有4.5公尺，我打完後就覺得應該可以打得到天空的小鳥等詞（原審審訴卷第30頁），扣案空氣槍既經被告試射，且被告認為該空氣槍足以打到小鳥等情觀之，顯見被告斯時清楚知悉該扣案空氣槍之射擊威力遠較一般坊間販售無殺傷力之玩具空氣槍為大。況且，槍枝以發射彈丸為目的，本有一定之破壞性，乃屬攻擊性武器，本案扣案之物品除空氣槍外，另有金色鋼珠彈1瓶、銀色鋼珠彈1瓶，有扣押物品清單附卷可稽，可見被告持有該空氣槍之目的，有裝填鋼珠使用之意圖甚明，而裝填鋼珠使用，因鋼珠之重量較重，須有較強之動能始能擊發，且鋼珠為鐵製品，其殺傷力較塑膠製之BB彈強，顯非一般玩具空氣槍之正常用途，足認被告於持有系爭槍枝時，已明知該槍枝非屬一般玩具空氣槍，而係具有相當之攻擊性槍械無疑，被告辯稱不知扣案之空氣槍具有殺傷力云云，顯非可採。而被告既然明知扣案空氣槍具有一定攻擊力，對其擊發後得劃破人體皮肉層之殺傷力，更應有所認識，此乃普通之常識，自不能空言徒託未將扣案槍枝送鑑前，即無從得知其殺傷力云云置辯，此部分辯解，亦屬無據。(四)綜上所陳，本案事證明確，應依法論科。二、論罪科刑：(一)新舊法比較按被告行為後，槍砲彈藥刀械管制條例業於100年1月5日經修正公布，並於同月7日生效，其第8條第6項增訂：「犯第1項、第2項或第4項有關空氣槍之罪，其情節輕微者，得減輕其刑。」經比較新舊法律，修正後之規定有利被告，爰依刑法第2條第1項但書之規定，適用新法之規定。(二)核被告所為，係犯槍砲彈藥刀械管制條例第8條第4項之非法持有空氣槍罪（公訴意旨誤載為係犯槍砲彈藥刀械管制條例第8條第4項之未經許可寄藏具殺傷力空氣槍罪，惟經公訴人於原審99年10月4日準備程序中更正，見原審審訴卷第27頁）。被告自99年4月間某日起至99年5月5日為警查獲為止，其持有上開空氣槍之行為，為繼續犯，自應論以單一之持有行為。(三)按刑法第62條所稱自首，指行為人自行申告自己尚未被發覺之犯罪行為，而自願接受法院裁判之行為。其申告之內容，僅須足以使刑事追訴機關憑以查明犯罪之真相即可，不以事實真相完全相符為必要；又所謂「未發覺之罪」，應指刑事追訴機關（司法警察〈官〉、檢察官或其他有偵查犯罪職權之公務員）尚「未知悉」犯罪事實及犯人而言；此一「知悉」，固不以確知某人為犯罪行為人為必要，只須有確切之根據得為合理之可疑者，即足當之；惟如僅為主觀上之單純懷疑或推測，尚難謂為發覺，最高法院72年度台上字第641號、75年度台上字第1634號判例意旨可資參照。被告上開為警查獲之情形，業據證人即查獲本案之警察黃泰櫻於原審審理中證述：在距離本案2個月前查緝被告毒品案時，曾發現一個空的槍盒，盒子上印著一把槍，我們懷疑被告持有槍枝，沒有其他線民舉報被告持有槍枝，我們在被告居住附近公園觀察很久一段時間，發現被告提紙袋要離開，被告看到我們也不跑，問被告有什麼，他蹲下來主動說裡面有海洛因、玩具槍等語明確（見原審卷第29至31頁）。查證人黃泰櫻係本案發生前2個月發現被告持有空的槍盒進而懷疑被告持有槍枝，然持有槍盒原因甚多，可能係拾獲，或係為裝載其他物品之用，亦未必持有槍盒即得推論係持有槍枝，且該槍枝即係具有殺傷力，此從員警在當時僅發現空槍盒而未發現任何槍枝可證，故員警因被告持有空槍盒，而將被告當作調查之對象，此應屬單純主觀上之懷疑，復無其他線索，難謂已達合理可疑之程度。是以證人黃泰櫻暨其他員警雖於事實欄所述時、地攔檢盤查被告，然因空氣槍係藏放於被告紙袋之中，均未外露而為員警所知悉，則在被告交出空氣槍前，員警對於被告未經許可持有具殺傷力之空氣槍之犯行，尚難謂有何確切之根據得為合理之可疑。且警察執行臨檢時未持搜索票，亦無附帶搜索，緊急搜索情形，而係被告主動告知紙袋裡有空氣槍，而以此方式坦承持有空氣槍，則被告在警方尚未能確定係被告持有扣案之空氣槍前，即向警察承認該空氣槍係其持有，應符合自首規定，爰依刑法第62條規定，減輕其刑。又被告雖係對於未發覺之罪自首而受裁判，然並未「報繳」其持有之空氣槍，核與槍砲彈藥刀械管制條例第18條第1項之規定減輕或免除其刑之構成要件未合，自無從適用該條項之規定，併此敘明。(四)查被告未循正當管道取得合法槍枝，其行為雖無足取，惟其僅出於休閒、娛樂等動機而持有，對他人生命、身體、自由、財產等法益之危險非高，是上開空氣槍雖具殺傷力，惟經法務部調查局鑑驗後，其換算彈丸單位面積動能依序為22.82、21.57、20.36焦耳/平方公分，已如上述，僅逾足以穿入人體皮肉層之20焦耳/平方公分些許，足認其殺傷力較低，對他人生命、身體、自由、財產等法益之危險甚低，且卷內亦無證據顯示被告曾持該空氣槍從事任何非法行為之意圖，對社會治安之危險性尚屬輕微，其犯罪情節輕微，爰依修正後槍砲彈藥刀械管制條例第8條第6項規定減輕其刑，並遞減之。又本件既已審酌被告犯罪情節輕微，依上開規定予以減輕其刑，即無情輕法重，再適用刑法第59條酌減其刑之餘地。三、對原判決之審查：原審據以論處被告非法持有空氣槍罪刑，固非無見；惟查：按被告行為後，槍砲彈藥刀械管制條例修正第8條規定，業已增訂第6項：「犯第1項、第2項或第4項有關空氣槍之罪，其情節輕微者，得減輕其刑」，並經公布生效，被告非法持有空氣槍之犯罪情節，尚屬輕微，已如前述，原審未及適用修正後之上開規定以減輕其刑，容有未合，被告上訴否認犯罪雖不可採，然其執此上訴指摘原判決不當，為有理由，自應由本院將原判決撤銷改判。四、量刑及沒收(一)爰審酌被告未經許可，擅自持有具有殺傷力之空氣槍，對於他人生命、身體以及社會治安造成潛在之危險與不安，實有可議，惟念持有之空氣槍僅1支，且殺傷力尚非十分強大等一切情狀，量處如主文第2項所示之刑，並審酌被告前揭情狀，就罰金刑部分，依刑法第42條第3項前段規定，諭知如主文第2項所示易服勞役之折算標準，以資懲儆。(二)扣案空氣槍（槍枝管制編號：高鑑0000000000）1枝具有殺傷力，業已認定如前，屬違禁物，應依刑法第38條第1項第1款規定宣告沒收；扣案之瓦斯鋼瓶9支、瓦斯鋼瓶專用彈匣2支及可供上述空氣發射用之金色鋼珠彈1瓶、銀色鋼珠彈1瓶，均係被告所有、供上開空氣槍使用之物，業據被告於原審審理時供明無誤（見原審審訴卷第27頁），爰依刑法第38條第1項第2款規定宣告沒收。至同時扣案之第一級毒品海洛因9包、第二級毒品安非他命1包等物，核與本案犯罪無關，爰不予宣告沒收，附此敘明之。據上論斷，應依刑事訴訟法第364條、第369條第1項前段、第299條第1項前段，槍砲彈藥刀械管制條例第8條第4項、第6項，刑法第11條前段、第62條前段、第42條第3項前段、第38條第1項第1款、第2款，判決如主文。本案經檢察官陳宗吟到庭執行職務。中華民國100年4月12日刑事第七庭審判長法官莊飛宗法官謝宏宗法官蔡廣昇以上正本證明與原本無異。如不服本判決應於收受本判決後10日內向本院提出上訴書狀，其未敘述上訴理由者，並得於提起上訴後10日內向本院補提理由書狀（均須按他造當事人之人數附繕本）「切勿逕送上級法院」。中華民國100年4月12日書記官曾允志附錄本判決論罪科刑法條：修正後槍砲彈藥刀械管制條例第8條第1項、第4項、第6項未經許可，製造、販賣或運輸鋼筆槍、瓦斯槍、麻醉槍、獵槍、空氣槍或第4條第1項第1款所定其他可發射金屬或子彈具有殺傷力之各式槍砲者，處無期徒刑或5年以上有期徒刑，併科新臺幣1千萬元以下罰金。未經許可，持有、寄藏或意圖販賣而陳列第1項所列槍枝者，處3年以上10年以下有期徒刑，併科新臺幣7百萬元以下罰金。犯第1項、第2項或第4項有關空氣槍之罪，其情節輕微者，得減輕其刑。",
  "characters": {
    "judges": [
      "莊飛宗",
      "謝宏宗",
      "蔡廣昇"
    ],
    "prosecutors": [
      "陳宗吟"
    ],
    "lawyers": [
      "李靜怡"
    ],
    "clerks": [
      "曾允志"
    ],
    "plaintiffs": [

    ],
    "defendants": [
      "洪福來"
    ],
    "prosecutor_office": [

    ],
    "creditors": [

    ],
    "debtors": [

    ],
    "judicial_associate_officer": [

    ]
  },
  "adjudged_at": "2011-04-12",
  "created_at": "2016-02-12 09:47:08",
  "updated_at": "2016-02-12 09:47:08"
}