{
  "identify": "CYD-94-嘉簡-1463-20051223-1",
  "court": {
    "name": "臺灣嘉義地方法院",
    "code": "CYD"
  },
  "division": {
    "name": "刑事",
    "code": "M"
  },
  "year": 94,
  "word": "嘉簡",
  "number": "1463",
  "jcheck": "1",
  "reason": "違反家庭暴力防治法",
  "content": "臺灣嘉義地方法院刑事簡易判決\n94年度嘉簡字第1463號\n聲  請  人  臺灣嘉義地方法院檢察署檢察官\n被      告  甲○○\n                      號\n上列被告因違反家庭暴力防治法案件，經檢察官聲請以簡易判決\n處刑（94年度偵字第6484號），本院判決如下：\n    主  文\n甲○○違反臺灣嘉義地方法院於民國九十四年八月十六日以九十\n四年度家護字第四四六號裁定所核發「甲○○不得對翁碧鳳實施\n身體或精神上不法侵害之行為、甲○○不得直接或間接對於翁碧\n鳳為騷擾之聯絡行為」之保護令，處拘役伍拾日，如易科罰金，\n以參佰元折算壹日。緩刑貳年，緩刑期內付保護管束。\n    事實及理由\n一、本件犯罪事實及證據均引用檢察官聲請簡易判決處刑書之記\n    載（如附件）。\n二、查被告甲○○未曾受有期徒刑以上刑之宣告，有臺灣嘉義地\n    方法院檢察署刑案資料查註紀錄表及臺灣高等法院被告全國\n    前案紀錄表各1 份在卷可參，被告後坦認犯行，態度尚佳，\n    堪認其係因一時失慮偶罹刑典，經此之偵查審判程序，當知\n    所警惕，信無再犯之虞，本院認為本件所宣告之刑，以暫不\n    執行為適當，併予宣告緩刑2 年。被告違反保護令罪而受刑\n    之宣告，應依家庭暴力防治法第30 條第1項於緩刑期間付保\n    護管束。\n三、依刑事訴訟法第449條第1項前段、第450條第 1項、第454條\n    第2項，家庭暴力防治法第50條第1款、第2款、第30條第1項\n    ，刑法第11條前段、第41條第1項前段、第74條第1款，罰金\n    罰鍰提高標準條例第2條，逕以簡易判決處刑如主文。\n中    華    民    國    94    年    12    月    23    日\n                       嘉義簡易庭  法  官  游悅晨\n上列正本證明與原本無異。\n如不服本判決，應於判決送達後10日內向本院提出上訴狀（應附\n繕本）。告訴人或被害人如對於本判決不服者，應具備理由請求\n檢察官上訴，其上訴期間之計算係以檢察官收受判決正本之日期\n為準。\n中    華    民    國    94    年    12    月    23    日\n                                   書記官  李銷勳\n附錄本判決論罪科刑法條全文\n家庭暴力防治法第50條\n違反法院依第13條、第15條所為之下列裁定者，為本法所稱之違\n反保護令罪，處3年以下有期徒刑、拘役或科或併科新台幣 10萬\n元以下罰金︰\n一  禁止實施家庭暴力行為。\n二  禁止直接或間接騷擾、接觸、通話或其他連絡行為。\n三  命遷出住居所。\n四  遠離住居所、工作場所、學校或其他特定場所。\n五  命完成加害人處遇計畫：戒癮治療、精神治療、心理輔導或\n    其他治療、輔導。\n",
  "structure": {
    "main": "甲○○違反臺灣嘉義地方法院於民國九十四年八月十六日以九十\n四年度家護字第四四六號裁定所核發「甲○○不得對翁碧鳳實施\n身體或精神上不法侵害之行為、甲○○不得直接或間接對於翁碧\n鳳為騷擾之聯絡行為」之保護令，處拘役伍拾日，如易科罰金，\n以參佰元折算壹日。緩刑貳年，緩刑期內付保護管束。",
    "fact": "一、本件犯罪事實及證據均引用檢察官聲請簡易判決處刑書之記\n    載（如附件）。\n二、查被告甲○○未曾受有期徒刑以上刑之宣告，有臺灣嘉義地\n    方法院檢察署刑案資料查註紀錄表及臺灣高等法院被告全國\n    前案紀錄表各1 份在卷可參，被告後坦認犯行，態度尚佳，\n    堪認其係因一時失慮偶罹刑典，經此之偵查審判程序，當知\n    所警惕，信無再犯之虞，本院認為本件所宣告之刑，以暫不\n    執行為適當，併予宣告緩刑2 年。被告違反保護令罪而受刑\n    之宣告，應依家庭暴力防治法第30 條第1項於緩刑期間付保\n    護管束。\n三、依刑事訴訟法第449條第1項前段、第450條第 1項、第454條\n    第2項，家庭暴力防治法第50條第1款、第2款、第30條第1項\n    ，刑法第11條前段、第41條第1項前段、第74條第1款，罰金\n    罰鍰提高標準條例第2條，逕以簡易判決處刑如主文。",
    "reason": "一、本件犯罪事實及證據均引用檢察官聲請簡易判決處刑書之記\n    載（如附件）。\n二、查被告甲○○未曾受有期徒刑以上刑之宣告，有臺灣嘉義地\n    方法院檢察署刑案資料查註紀錄表及臺灣高等法院被告全國\n    前案紀錄表各1 份在卷可參，被告後坦認犯行，態度尚佳，\n    堪認其係因一時失慮偶罹刑典，經此之偵查審判程序，當知\n    所警惕，信無再犯之虞，本院認為本件所宣告之刑，以暫不\n    執行為適當，併予宣告緩刑2 年。被告違反保護令罪而受刑\n    之宣告，應依家庭暴力防治法第30 條第1項於緩刑期間付保\n    護管束。\n三、依刑事訴訟法第449條第1項前段、第450條第 1項、第454條\n    第2項，家庭暴力防治法第50條第1款、第2款、第30條第1項\n    ，刑法第11條前段、第41條第1項前段、第74條第1款，罰金\n    罰鍰提高標準條例第2條，逕以簡易判決處刑如主文。"
  },
  "search": "臺灣嘉義地方法院刑事簡易判決94年度嘉簡字第1463號聲請人臺灣嘉義地方法院檢察署檢察官被告甲○○號上列被告因違反家庭暴力防治法案件，經檢察官聲請以簡易判決處刑（94年度偵字第6484號），本院判決如下：主文甲○○違反臺灣嘉義地方法院於民國九十四年八月十六日以九十四年度家護字第四四六號裁定所核發「甲○○不得對翁碧鳳實施身體或精神上不法侵害之行為、甲○○不得直接或間接對於翁碧鳳為騷擾之聯絡行為」之保護令，處拘役伍拾日，如易科罰金，以參佰元折算壹日。緩刑貳年，緩刑期內付保護管束。事實及理由一、本件犯罪事實及證據均引用檢察官聲請簡易判決處刑書之記載（如附件）。二、查被告甲○○未曾受有期徒刑以上刑之宣告，有臺灣嘉義地方法院檢察署刑案資料查註紀錄表及臺灣高等法院被告全國前案紀錄表各1份在卷可參，被告後坦認犯行，態度尚佳，堪認其係因一時失慮偶罹刑典，經此之偵查審判程序，當知所警惕，信無再犯之虞，本院認為本件所宣告之刑，以暫不執行為適當，併予宣告緩刑2年。被告違反保護令罪而受刑之宣告，應依家庭暴力防治法第30條第1項於緩刑期間付保護管束。三、依刑事訴訟法第449條第1項前段、第450條第1項、第454條第2項，家庭暴力防治法第50條第1款、第2款、第30條第1項，刑法第11條前段、第41條第1項前段、第74條第1款，罰金罰鍰提高標準條例第2條，逕以簡易判決處刑如主文。中華民國94年12月23日嘉義簡易庭法官游悅晨上列正本證明與原本無異。如不服本判決，應於判決送達後10日內向本院提出上訴狀（應附繕本）。告訴人或被害人如對於本判決不服者，應具備理由請求檢察官上訴，其上訴期間之計算係以檢察官收受判決正本之日期為準。中華民國94年12月23日書記官李銷勳附錄本判決論罪科刑法條全文家庭暴力防治法第50條違反法院依第13條、第15條所為之下列裁定者，為本法所稱之違反保護令罪，處3年以下有期徒刑、拘役或科或併科新台幣10萬元以下罰金︰一禁止實施家庭暴力行為。二禁止直接或間接騷擾、接觸、通話或其他連絡行為。三命遷出住居所。四遠離住居所、工作場所、學校或其他特定場所。五命完成加害人處遇計畫：戒癮治療、精神治療、心理輔導或其他治療、輔導。",
  "characters": {
    "judges": [
      "游悅晨"
    ],
    "prosecutors": [

    ],
    "lawyers": [

    ],
    "clerks": [
      "李銷勳"
    ],
    "plaintiffs": [

    ],
    "defendants": [
      "甲○○"
    ],
    "prosecutor_office": [
      "臺灣嘉義地方法院檢察署檢察官"
    ],
    "creditors": [

    ],
    "debtors": [

    ],
    "judicial_associate_officer": [

    ]
  },
  "adjudged_at": "2005-12-23",
  "created_at": "2016-02-07 04:41:17",
  "updated_at": "2016-02-07 04:41:17"
}