{
  "identify": "KSD-94-簡-7537-20051223-1",
  "court": {
    "name": "臺灣高雄地方法院",
    "code": "KSD"
  },
  "division": {
    "name": "刑事",
    "code": "M"
  },
  "year": 94,
  "word": "簡",
  "number": "7537",
  "jcheck": "1",
  "reason": "竊盜",
  "content": "臺灣高雄地方法院刑事簡易判決          94年度簡字第7537號\n聲  請  人  臺灣高雄地方法院檢察署檢察官\n被      告  甲○○\n上列被告因竊盜案件，經檢察官聲請以簡易判決處刑（94年度偵\n字第24661 號），本院判決如下：\n    主  文\n甲○○竊盜，處拘役貳拾日，如易科罰金，以參佰元折算壹日。\n    事實及理由\n一、本件犯罪事實及證據，除將「民國95年6 月16日」更正為「\n    民國94年6 月16日」，並將「序號00000000000000」更正為\n    「序號000000000000000 」之外，餘均引用檢察官聲請簡易\n    判決處刑書之記載（詳如附件）。\n二、核被告甲○○所為，係犯刑法第320 條第1 項之竊盜罪。審\n    酌被告不思以正當途徑獲取財物，竟竊取他人行動電話變賣\n    圖利，其所竊得之財物價值尚屬非鉅，及其犯罪之動機（一\n    時貪念）、目的、智識程度（國小畢業）、手段（徒手竊取\n    ）、犯後否認犯行、尚無悔意等一切情狀，爰量處如主文所\n    示之刑，並諭知易科罰金之折算標準。\n三、據上論斷，應依刑事訴訟法第449 條第1 項前段、第3 項、\n    第454 條第2 項，刑法第320 條第1 項、第41條第1 項前段\n    ，罰金罰鍰提高標準條例第1 條前段、第2 條，逕以簡易判\n    決處刑如主文。\n四、如不服本判決，應於判決送達之日起10日內，向本院提出上\n    訴狀。\n中    華    民    國    94    年    12    月    23    日\n                  高雄簡易庭    法  官  孫啟強\n以上正本證明與原本無異。\n中    華    民    國    94    年    12    月    23    日\n                                書記官  吳金霞\n附錄本判決論罪科刑之法條：\n刑法第320條：\n意圖為自己或第三人不法之所有，而竊取他人之動產者，為竊盜\n罪，處5年以下有期徒刑、拘役或500元以下罰金。\n意圖為自己或第三人不法之利益，而竊佔他人之不動產者，依前\n項之規定處斷。\n前二項之未遂犯罰之。\n",
  "structure": {
    "main": "甲○○竊盜，處拘役貳拾日，如易科罰金，以參佰元折算壹日。",
    "fact": "一、本件犯罪事實及證據，除將「民國95年6 月16日」更正為「\n    民國94年6 月16日」，並將「序號00000000000000」更正為\n    「序號000000000000000 」之外，餘均引用檢察官聲請簡易\n    判決處刑書之記載（詳如附件）。\n二、核被告甲○○所為，係犯刑法第320 條第1 項之竊盜罪。審\n    酌被告不思以正當途徑獲取財物，竟竊取他人行動電話變賣\n    圖利，其所竊得之財物價值尚屬非鉅，及其犯罪之動機（一\n    時貪念）、目的、智識程度（國小畢業）、手段（徒手竊取\n    ）、犯後否認犯行、尚無悔意等一切情狀，爰量處如主文所\n    示之刑，並諭知易科罰金之折算標準。\n三、據上論斷，應依刑事訴訟法第449 條第1 項前段、第3 項、\n    第454 條第2 項，刑法第320 條第1 項、第41條第1 項前段\n    ，罰金罰鍰提高標準條例第1 條前段、第2 條，逕以簡易判\n    決處刑如主文。\n四、如不服本判決，應於判決送達之日起10日內，向本院提出上\n    訴狀。",
    "reason": "一、本件犯罪事實及證據，除將「民國95年6 月16日」更正為「\n    民國94年6 月16日」，並將「序號00000000000000」更正為\n    「序號000000000000000 」之外，餘均引用檢察官聲請簡易\n    判決處刑書之記載（詳如附件）。\n二、核被告甲○○所為，係犯刑法第320 條第1 項之竊盜罪。審\n    酌被告不思以正當途徑獲取財物，竟竊取他人行動電話變賣\n    圖利，其所竊得之財物價值尚屬非鉅，及其犯罪之動機（一\n    時貪念）、目的、智識程度（國小畢業）、手段（徒手竊取\n    ）、犯後否認犯行、尚無悔意等一切情狀，爰量處如主文所\n    示之刑，並諭知易科罰金之折算標準。\n三、據上論斷，應依刑事訴訟法第449 條第1 項前段、第3 項、\n    第454 條第2 項，刑法第320 條第1 項、第41條第1 項前段\n    ，罰金罰鍰提高標準條例第1 條前段、第2 條，逕以簡易判\n    決處刑如主文。\n四、如不服本判決，應於判決送達之日起10日內，向本院提出上\n    訴狀。"
  },
  "search": "臺灣高雄地方法院刑事簡易判決94年度簡字第7537號聲請人臺灣高雄地方法院檢察署檢察官被告甲○○上列被告因竊盜案件，經檢察官聲請以簡易判決處刑（94年度偵字第24661號），本院判決如下：主文甲○○竊盜，處拘役貳拾日，如易科罰金，以參佰元折算壹日。事實及理由一、本件犯罪事實及證據，除將「民國95年6月16日」更正為「民國94年6月16日」，並將「序號00000000000000」更正為「序號000000000000000」之外，餘均引用檢察官聲請簡易判決處刑書之記載（詳如附件）。二、核被告甲○○所為，係犯刑法第320條第1項之竊盜罪。審酌被告不思以正當途徑獲取財物，竟竊取他人行動電話變賣圖利，其所竊得之財物價值尚屬非鉅，及其犯罪之動機（一時貪念）、目的、智識程度（國小畢業）、手段（徒手竊取）、犯後否認犯行、尚無悔意等一切情狀，爰量處如主文所示之刑，並諭知易科罰金之折算標準。三、據上論斷，應依刑事訴訟法第449條第1項前段、第3項、第454條第2項，刑法第320條第1項、第41條第1項前段，罰金罰鍰提高標準條例第1條前段、第2條，逕以簡易判決處刑如主文。四、如不服本判決，應於判決送達之日起10日內，向本院提出上訴狀。中華民國94年12月23日高雄簡易庭法官孫啟強以上正本證明與原本無異。中華民國94年12月23日書記官吳金霞附錄本判決論罪科刑之法條：刑法第320條：意圖為自己或第三人不法之所有，而竊取他人之動產者，為竊盜罪，處5年以下有期徒刑、拘役或500元以下罰金。意圖為自己或第三人不法之利益，而竊佔他人之不動產者，依前項之規定處斷。前二項之未遂犯罰之。",
  "characters": {
    "judges": [
      "孫啟強"
    ],
    "prosecutors": [

    ],
    "lawyers": [

    ],
    "clerks": [
      "吳金霞"
    ],
    "plaintiffs": [

    ],
    "defendants": [
      "甲○○"
    ],
    "prosecutor_office": [
      "臺灣高雄地方法院檢察署檢察官"
    ],
    "creditors": [

    ],
    "debtors": [

    ],
    "judicial_associate_officer": [

    ]
  },
  "adjudged_at": "2005-12-23",
  "created_at": "2016-02-07 04:43:12",
  "updated_at": "2016-02-07 04:43:12"
}