{
  "identify": "KSD-100-簡-110-20110114-1",
  "court": {
    "name": "臺灣高雄地方法院",
    "code": "KSD"
  },
  "division": {
    "name": "刑事",
    "code": "M"
  },
  "year": 100,
  "word": "簡",
  "number": "110",
  "jcheck": "1",
  "reason": "竊盜",
  "content": "臺灣高雄地方法院刑事簡易判決          100年度簡字第110號\n聲  請  人  臺灣高雄地方法院檢察署檢察官\n被      告  陳清珠\n上列被告因竊盜案件，經檢察官聲請以簡易判決處刑（99年度偵\n字第35195 號），本院判決如下：\n    主  文\n陳清珠犯竊盜罪，累犯，處有期徒刑肆月，如易科罰金，以新臺\n幣壹仟元折算壹日。\n    事實及理由\n一、陳清珠前因施用毒品案件，經本院以94年度訴字第2297號判\n    決判處有期徒刑1 年確定，嗣經本院以96年度聲減字第285\n    號裁定減刑為有期徒刑6 月確定，於民國96年7 月16日縮短\n    刑期執行完畢（構成累犯）。詎仍不知悔改，意圖為自己不\n    法之所有，於99年11月19日13時15分許，在莊文明所經營，\n    位在高雄市○○區○○路300 巷15號之服飾店內，徒手打開\n    店內抽屜，竊取莊文明所有之現金新臺幣（以下同）3,800\n    元並將其藏匿於女用褲子中，再置入隨身手提包內，為莊文\n    明發現而報警，始悉上情。\n二、本件之證據，除「照片」應補充為「照片4 張」外，餘均引\n    用檢察官聲請簡易判決處刑書之記載（如附件）。\n三、核被告陳清珠所為，係犯刑法第320條第1項之竊盜罪。又被\n    告有如上所載之犯罪科刑及執行情形，有臺灣高等法院被告\n    前案紀錄表1份在卷可查，其於受有期徒刑執行完畢後，5年\n    內故意再犯本件有期徒刑以上之罪，為累犯，應依刑法第47\n    條第1項規定，加重其刑。爰審酌被告陳清珠所恣意竊取他\n    人之物，所為實不足取，且前有竊盜、毒品等前科紀錄，有\n    臺灣高等法院被告前案紀錄表1 紙在卷可參，惟念及其犯後\n    坦承犯行，態度尚可，所竊財物價值為現金紙鈔3800元等具\n    體一切情狀，量處如主文所示之刑，並審酌本案犯罪情節、\n    被告之資力及智識、教育程度（見警詢調查筆錄受詢問人欄\n    ），諭知如主文所示之易科罰金折算標準，以資懲儆。\n四、依刑事訴訟法第449 條第1 項前段、第3 項、第454 條第2\n    項，刑法第320 條第1 項、第47條第1 項、41條第1 項前段\n    ，刑法施行法第1 條之1 第1 項、第2 項前段，逕以簡易判\n    決如主文。\n五、如不服本件判決，得自收受送達之日起10日內，向本院提起\n    上訴狀，上訴於本院管轄之第二審地方法院合議庭。\n中    華    民    國   100    年    1     月    14    日\n                  高雄簡易庭  法  官    沈宗興\n以上正本證明與原本無異。\n如不服本判決，應於判決送達之日起10日內向本院提出上訴書狀\n。\n中    華    民    國   100    年    1     月    14    日\n                              書記官    楊雅蘭\n附錄本判決論罪之法條：\n中華民國刑法(94.02.02)第320條\n（普通竊盜罪、竊佔罪）\n意圖為自己或第三人不法之所有，而竊取他人之動產者，為竊盜\n罪，處5 年以下有期徒刑、拘役或 5 百元以下罰金。\n意圖為自己或第三人不法之利益，而竊佔他人之不動產者，依前\n項之規定處斷。\n前二項之未遂犯罰之。\n附件：\n臺灣高雄地方法院檢察署檢察官聲請簡易判決處刑書\n                                     99年度偵字第35195號\n    被      告  陳清珠  女  38歲（民國○○年○月○日生）\n                        住高雄市○○區○○街12之1號\n                        （另案在臺灣高雄第二監獄執行中）\n                        國民身分證統一編號：Ｚ000000000號\n上列被告因竊盜案件，業經偵查終結，認為宜以簡易判決處刑，\n茲將犯罪事實及證據並所犯法條分敘如下：\n            犯罪事實\n一、陳清珠前因施用毒品案件，經臺灣高雄地方法院以94年度訴\n    字第2297號判處有期徒刑1 年確定，嗣經確定判決減刑，應\n    執行有期徒刑6月確定，於民國96年7月16日縮短刑期執行完\n    畢。詎仍不知悔改，意圖為自己不法之所有，於99年11月19\n    日13時15分許，在莊文明所經營，位在高雄縣鳳山市○○路\n    300巷 15號之服飾店內，徒手打開店內抽屜，竊取莊文明所\n    有之現金新台幣3,800 元得手之際，為莊文明發現而報警查\n    獲上情。\n二、案經高雄縣政府警察局鳳山分局移送偵辦。\n            證據並所犯法條\n一、上開犯罪事實，業據被告陳清珠於警詢及本署偵查中自白不\n    諱，核與被害人莊文明之指述遭竊情節相符，復有警方搜索\n    扣押筆錄、扣押物品目錄表、贓物認領保管單及現場照片等\n    在卷可稽，本件事證明確，被告犯行堪以認定。\n二、核被告所為，係犯刑法第320條第1項普通竊盜罪嫌。又被告\n    於有期徒刑執行完畢後，5 年內故意再犯本件有期徒刑以上\n    之本罪，有本署刑案資料查註紀錄表在卷可參，為累犯，請\n    依刑法第47條第1項規定加重其刑。\n三、依刑事訴訟法第451條第1項聲請逕以簡易判決處刑。\n    此    致\n臺灣高雄地方法院\n中    華    民    國    99    年  11    月  29    日\n                        檢  察  官     蕭博文\n中華民國刑法第320條\n（普通竊盜罪、竊佔罪）\n意圖為自己或第三人不法之所有，而竊取他人之動產者，為竊盜\n罪，處5  年以下有期徒刑、拘役或 5 百元以下罰金。\n意圖為自己或第三人不法之利益，而竊佔他人之不動產者，依前\n項之規定處斷。\n前二項之未遂犯罰之。\n附記事項：本件係依刑事訴訟法簡易程序辦理，法院簡易庭得不\n傳喚被告、輔佐人、告訴人、告發人等出庭即以簡易判決處刑；\n被告、被害人、告訴人等對告訴乃論案件如已達成民事和解而要\n撤回告訴或對非告訴乃論案件認有受傳喚到庭陳述意見之必要時\n，請即另以書狀向簡易法庭陳述或請求傳訊。",
  "structure": {
    "main": "陳清珠犯竊盜罪，累犯，處有期徒刑肆月，如易科罰金，以新臺\n幣壹仟元折算壹日。",
    "fact": "一、陳清珠前因施用毒品案件，經本院以94年度訴字第2297號判\n    決判處有期徒刑1 年確定，嗣經本院以96年度聲減字第285\n    號裁定減刑為有期徒刑6 月確定，於民國96年7 月16日縮短\n    刑期執行完畢（構成累犯）。詎仍不知悔改，意圖為自己不\n    法之所有，於99年11月19日13時15分許，在莊文明所經營，\n    位在高雄市○○區○○路300 巷15號之服飾店內，徒手打開\n    店內抽屜，竊取莊文明所有之現金新臺幣（以下同）3,800\n    元並將其藏匿於女用褲子中，再置入隨身手提包內，為莊文\n    明發現而報警，始悉上情。\n二、本件之證據，除「照片」應補充為「照片4 張」外，餘均引\n    用檢察官聲請簡易判決處刑書之記載（如附件）。\n三、核被告陳清珠所為，係犯刑法第320條第1項之竊盜罪。又被\n    告有如上所載之犯罪科刑及執行情形，有臺灣高等法院被告\n    前案紀錄表1份在卷可查，其於受有期徒刑執行完畢後，5年\n    內故意再犯本件有期徒刑以上之罪，為累犯，應依刑法第47\n    條第1項規定，加重其刑。爰審酌被告陳清珠所恣意竊取他\n    人之物，所為實不足取，且前有竊盜、毒品等前科紀錄，有\n    臺灣高等法院被告前案紀錄表1 紙在卷可參，惟念及其犯後\n    坦承犯行，態度尚可，所竊財物價值為現金紙鈔3800元等具\n    體一切情狀，量處如主文所示之刑，並審酌本案犯罪情節、\n    被告之資力及智識、教育程度（見警詢調查筆錄受詢問人欄\n    ），諭知如主文所示之易科罰金折算標準，以資懲儆。\n四、依刑事訴訟法第449 條第1 項前段、第3 項、第454 條第2\n    項，刑法第320 條第1 項、第47條第1 項、41條第1 項前段\n    ，刑法施行法第1 條之1 第1 項、第2 項前段，逕以簡易判\n    決如主文。\n五、如不服本件判決，得自收受送達之日起10日內，向本院提起\n    上訴狀，上訴於本院管轄之第二審地方法院合議庭。",
    "reason": "一、陳清珠前因施用毒品案件，經本院以94年度訴字第2297號判\n    決判處有期徒刑1 年確定，嗣經本院以96年度聲減字第285\n    號裁定減刑為有期徒刑6 月確定，於民國96年7 月16日縮短\n    刑期執行完畢（構成累犯）。詎仍不知悔改，意圖為自己不\n    法之所有，於99年11月19日13時15分許，在莊文明所經營，\n    位在高雄市○○區○○路300 巷15號之服飾店內，徒手打開\n    店內抽屜，竊取莊文明所有之現金新臺幣（以下同）3,800\n    元並將其藏匿於女用褲子中，再置入隨身手提包內，為莊文\n    明發現而報警，始悉上情。\n二、本件之證據，除「照片」應補充為「照片4 張」外，餘均引\n    用檢察官聲請簡易判決處刑書之記載（如附件）。\n三、核被告陳清珠所為，係犯刑法第320條第1項之竊盜罪。又被\n    告有如上所載之犯罪科刑及執行情形，有臺灣高等法院被告\n    前案紀錄表1份在卷可查，其於受有期徒刑執行完畢後，5年\n    內故意再犯本件有期徒刑以上之罪，為累犯，應依刑法第47\n    條第1項規定，加重其刑。爰審酌被告陳清珠所恣意竊取他\n    人之物，所為實不足取，且前有竊盜、毒品等前科紀錄，有\n    臺灣高等法院被告前案紀錄表1 紙在卷可參，惟念及其犯後\n    坦承犯行，態度尚可，所竊財物價值為現金紙鈔3800元等具\n    體一切情狀，量處如主文所示之刑，並審酌本案犯罪情節、\n    被告之資力及智識、教育程度（見警詢調查筆錄受詢問人欄\n    ），諭知如主文所示之易科罰金折算標準，以資懲儆。\n四、依刑事訴訟法第449 條第1 項前段、第3 項、第454 條第2\n    項，刑法第320 條第1 項、第47條第1 項、41條第1 項前段\n    ，刑法施行法第1 條之1 第1 項、第2 項前段，逕以簡易判\n    決如主文。\n五、如不服本件判決，得自收受送達之日起10日內，向本院提起\n    上訴狀，上訴於本院管轄之第二審地方法院合議庭。"
  },
  "search": "臺灣高雄地方法院刑事簡易判決100年度簡字第110號聲請人臺灣高雄地方法院檢察署檢察官被告陳清珠上列被告因竊盜案件，經檢察官聲請以簡易判決處刑（99年度偵字第35195號），本院判決如下：主文陳清珠犯竊盜罪，累犯，處有期徒刑肆月，如易科罰金，以新臺幣壹仟元折算壹日。事實及理由一、陳清珠前因施用毒品案件，經本院以94年度訴字第2297號判決判處有期徒刑1年確定，嗣經本院以96年度聲減字第285號裁定減刑為有期徒刑6月確定，於民國96年7月16日縮短刑期執行完畢（構成累犯）。詎仍不知悔改，意圖為自己不法之所有，於99年11月19日13時15分許，在莊文明所經營，位在高雄市○○區○○路300巷15號之服飾店內，徒手打開店內抽屜，竊取莊文明所有之現金新臺幣（以下同）3,800元並將其藏匿於女用褲子中，再置入隨身手提包內，為莊文明發現而報警，始悉上情。二、本件之證據，除「照片」應補充為「照片4張」外，餘均引用檢察官聲請簡易判決處刑書之記載（如附件）。三、核被告陳清珠所為，係犯刑法第320條第1項之竊盜罪。又被告有如上所載之犯罪科刑及執行情形，有臺灣高等法院被告前案紀錄表1份在卷可查，其於受有期徒刑執行完畢後，5年內故意再犯本件有期徒刑以上之罪，為累犯，應依刑法第47條第1項規定，加重其刑。爰審酌被告陳清珠所恣意竊取他人之物，所為實不足取，且前有竊盜、毒品等前科紀錄，有臺灣高等法院被告前案紀錄表1紙在卷可參，惟念及其犯後坦承犯行，態度尚可，所竊財物價值為現金紙鈔3800元等具體一切情狀，量處如主文所示之刑，並審酌本案犯罪情節、被告之資力及智識、教育程度（見警詢調查筆錄受詢問人欄），諭知如主文所示之易科罰金折算標準，以資懲儆。四、依刑事訴訟法第449條第1項前段、第3項、第454條第2項，刑法第320條第1項、第47條第1項、41條第1項前段，刑法施行法第1條之1第1項、第2項前段，逕以簡易判決如主文。五、如不服本件判決，得自收受送達之日起10日內，向本院提起上訴狀，上訴於本院管轄之第二審地方法院合議庭。中華民國100年1月14日高雄簡易庭法官沈宗興以上正本證明與原本無異。如不服本判決，應於判決送達之日起10日內向本院提出上訴書狀。中華民國100年1月14日書記官楊雅蘭附錄本判決論罪之法條：中華民國刑法(94.02.02)第320條（普通竊盜罪、竊佔罪）意圖為自己或第三人不法之所有，而竊取他人之動產者，為竊盜罪，處5年以下有期徒刑、拘役或5百元以下罰金。意圖為自己或第三人不法之利益，而竊佔他人之不動產者，依前項之規定處斷。前二項之未遂犯罰之。附件：臺灣高雄地方法院檢察署檢察官聲請簡易判決處刑書99年度偵字第35195號被告陳清珠女38歲（民國○○年○月○日生）住高雄市○○區○○街12之1號（另案在臺灣高雄第二監獄執行中）國民身分證統一編號：Ｚ000000000號上列被告因竊盜案件，業經偵查終結，認為宜以簡易判決處刑，茲將犯罪事實及證據並所犯法條分敘如下：犯罪事實一、陳清珠前因施用毒品案件，經臺灣高雄地方法院以94年度訴字第2297號判處有期徒刑1年確定，嗣經確定判決減刑，應執行有期徒刑6月確定，於民國96年7月16日縮短刑期執行完畢。詎仍不知悔改，意圖為自己不法之所有，於99年11月19日13時15分許，在莊文明所經營，位在高雄縣鳳山市○○路300巷15號之服飾店內，徒手打開店內抽屜，竊取莊文明所有之現金新台幣3,800元得手之際，為莊文明發現而報警查獲上情。二、案經高雄縣政府警察局鳳山分局移送偵辦。證據並所犯法條一、上開犯罪事實，業據被告陳清珠於警詢及本署偵查中自白不諱，核與被害人莊文明之指述遭竊情節相符，復有警方搜索扣押筆錄、扣押物品目錄表、贓物認領保管單及現場照片等在卷可稽，本件事證明確，被告犯行堪以認定。二、核被告所為，係犯刑法第320條第1項普通竊盜罪嫌。又被告於有期徒刑執行完畢後，5年內故意再犯本件有期徒刑以上之本罪，有本署刑案資料查註紀錄表在卷可參，為累犯，請依刑法第47條第1項規定加重其刑。三、依刑事訴訟法第451條第1項聲請逕以簡易判決處刑。此致臺灣高雄地方法院中華民國99年11月29日檢察官蕭博文中華民國刑法第320條（普通竊盜罪、竊佔罪）意圖為自己或第三人不法之所有，而竊取他人之動產者，為竊盜罪，處5年以下有期徒刑、拘役或5百元以下罰金。意圖為自己或第三人不法之利益，而竊佔他人之不動產者，依前項之規定處斷。前二項之未遂犯罰之。附記事項：本件係依刑事訴訟法簡易程序辦理，法院簡易庭得不傳喚被告、輔佐人、告訴人、告發人等出庭即以簡易判決處刑；被告、被害人、告訴人等對告訴乃論案件如已達成民事和解而要撤回告訴或對非告訴乃論案件認有受傳喚到庭陳述意見之必要時，請即另以書狀向簡易法庭陳述或請求傳訊。",
  "characters": {
    "judges": [
      "沈宗興"
    ],
    "prosecutors": [

    ],
    "lawyers": [

    ],
    "clerks": [
      "楊雅蘭"
    ],
    "plaintiffs": [

    ],
    "defendants": [
      "陳清珠",
      "陳清珠  女  38歲（民國○○年○月○日生）"
    ],
    "prosecutor_office": [
      "臺灣高雄地方法院檢察署檢察官"
    ],
    "creditors": [

    ],
    "debtors": [

    ],
    "judicial_associate_officer": [

    ]
  },
  "adjudged_at": "2011-01-14",
  "created_at": "2016-02-13 03:20:48",
  "updated_at": "2016-02-13 03:20:48"
}