{
  "identify": "KSD-99-審簡-4248-20110307-1",
  "court": {
    "name": "臺灣高雄地方法院",
    "code": "KSD"
  },
  "division": {
    "name": "刑事",
    "code": "M"
  },
  "year": 99,
  "word": "審簡",
  "number": "4248",
  "jcheck": "1",
  "reason": "詐欺",
  "content": "臺灣高雄地方法院刑事簡易判決        99年度審簡字第4248號\n公  訴  人  臺灣高雄地方法院檢察署檢察官\n被      告  李鳳源\n上列被告因詐欺案件，經檢察官提起公訴（99年度偵字第28446\n號），被告自白犯罪，本院認為宜以簡易判決處刑，經本院合議\n庭裁定改依簡易判決處刑，判決如下：\n    主  文\n李鳳源幫助犯詐欺取財罪，累犯，處有期徒刑參月，如易科罰金\n，以新臺幣壹仟元折算壹日。\n    事實及理由\n一、犯罪事實：\n    李鳳源前於民國97年間因業務侵占案件，經本院以97年度易\n    字第805 號判處有期徒刑6 月確定。另於97年間因交付手機\n    門號之幫助詐欺案件，經本院以97年度審簡字第4837號判處\n    有期徒刑3 月確定，上開二罪，經本院以98年度審聲字第72\n    2 號裁定應執行刑為有期徒刑8 月，於99年3 月31日縮刑期\n    滿執行完畢。其明知詐欺集團之不法份子經常利用他人存款\n    帳戶、提款卡、密碼轉帳等方式，獲取不法利益並逃避執法\n    人員之追查，且依其社會經驗，應有相當之智識程度可預見\n    將自己所有存款帳戶存摺、提款卡連同密碼，交付與不相識\n    之成年人使用，有被犯罪集團利用作為詐財轉帳匯款或其他\n    財產犯罪之虞，竟以縱有人持其存款帳戶作為犯罪工具，亦\n    不違其本意之幫助犯意，於99年4 月9 日下午4 時許，在高\n    雄市○○路國統飯店前，將其所申設之華南商業銀行路竹分\n    行（下稱華南銀行）帳號000000000000000 號帳戶之提款卡\n    及密碼，交與真實姓名、年籍不詳，自稱「張經理」之成年\n    男子及其所屬犯罪集團使用。嗣該犯罪集團成員取得上開帳\n    戶後，即意圖為自己不法之所有，共同基於詐欺取財之犯意\n    聯絡，於99年4 月10日晚上7 時許，由該詐欺集團之不詳成\n    員撥打電話予張麗卿，佯稱：其網路購物物品有誤，須至提\n    款機查詢有無扣款云云，使張麗卿誤信為真而陷於錯誤，依\n    詐騙集團成員指示至自動櫃員機操作，於同日晚上7 時46分\n    許，至彰化縣員林鎮○○路○段之郵局將新臺幣（下同）29\n    ,989元轉帳至李鳳源上開華南銀行帳戶內，並旋即遭提領一\n    空。\n二、證據名稱：被告李鳳源於本院審理時之自白，證人即被害人\n    張麗卿於警詢時之證述，被害人提出之郵政自動櫃員機交易\n    明細表影本1 紙、上開華南銀行帳號000000000000000 號帳\n    戶之開戶基本資料及存款往來明細表暨對帳單1 份。\n三、按刑法上之幫助犯，係指以幫助之意思，對於正犯之犯罪行\n    為予以助力，而未參與實施犯罪之行為者而言，最高法院19\n    年上字第1984號、49年台上字第77號判例意旨可資參照，亦\n    即行為人如未參與實施犯罪構成要件之行為，且係出於幫助\n    之意思提供助力，即屬幫助犯，而非共同正犯。查本件被告\n    提供其所有之華南銀行帳戶提款卡及密碼與他人使用，使詐\n    欺集團作為實施詐欺取財之犯罪工具，其單純提供帳戶供人\n    使用之行為，並不等同於向被害人施加詐術之行為，且亦無\n    證據證明被告有參與詐欺取財犯行之構成要件行為，是被告\n    提供帳戶供人使用之行為，係對於該詐欺集團遂行詐欺取財\n    犯行，資以助力。是核被告所為，係犯刑法第30條第1 項前\n    段、第339 條第1 項之幫助詐欺取財罪。被告有如事實欄所\n    載受有期徒刑執行完畢之事實，有臺灣高等法院被告前案紀\n    錄表附卷可憑，其受徒刑執行完畢，5 年以內故意再犯本件\n    有期徒刑以上之罪，為累犯，應依刑法第47條第1 項規定，\n    加重其刑。又被告並未實際參與詐欺犯行，為幫助犯，所犯\n    情節較正犯輕微，爰依刑法第30條第2 項規定，按正犯之刑\n    減輕之，並依法先加後減。爰審酌被告前已因交付手機門號\n    之幫助詐欺案件，經本院以97年度審簡字第4837號判處有期\n    徒刑3 月確定，竟猶不知警惕，又交付金融帳戶與他人使用\n    ，其雖未實際參與詐欺取財犯行，然其提供金融帳戶供犯罪\n    集團使用，致被害人張麗卿受有29,989元之損害，其所為助\n    長詐欺集團財產犯罪之風氣，使詐財事件層出不窮發生，造\n    成社會互信受損，擾亂金融交易往來秩序，影響層面廣泛，\n    更使執法人員難以追查該詐欺集團，增加被害人求償之困難\n    ，且未賠償被害人之損害，實屬不該，惟念及被告於本院審\n    理時尚能坦承犯行，態度尚可，並考量其犯罪動機、目的、\n    被害人所受損害，及自稱家庭經濟狀況小康、大專畢業、現\n    從事電鍍業、月薪45,000元、每月尚有卡債、會錢及貸款需\n    繳納等一切情狀（見警卷第1 頁調查筆錄受詢問人欄、本院\n    審易字卷第16頁），量處如主文所示之刑，併諭知易科罰金\n    之折算標準，以示懲儆。\n四、依刑事訴訟法第449 條第2 項、第3 項、第454 條第1 項，\n    刑法第339 條第1 項、第30條第1 項前段、第2 項、第47條\n    第1 項、第41條第1 項前段，刑法施行法第1 條之1 第1 項\n    、第2 項前段，逕以簡易判決處刑如主文。\n五、如不服本判決，得自收受送達之日起10日內，向本院提起上\n    訴（須附繕本）。\n中    華    民    國    100   年    3     月    7     日\n                      高雄簡易庭      法  官  周佳佩\n以上正本證明與原本無異。\n中    華    民    國    100   年    3     月    7     日\n                                      書記官  李承悌\n附錄本案論罪科刑法條：\n刑法第339 條第1 項\n意圖為自己或第三人不法之所有，以詐術使人將本人或第三人之\n物交付者，處5 年以下有期徒刑、拘役或科或併科1 千元以下罰\n金。",
  "structure": {
    "main": "李鳳源幫助犯詐欺取財罪，累犯，處有期徒刑參月，如易科罰金\n，以新臺幣壹仟元折算壹日。",
    "fact": "一、犯罪事實：\n    李鳳源前於民國97年間因業務侵占案件，經本院以97年度易\n    字第805 號判處有期徒刑6 月確定。另於97年間因交付手機\n    門號之幫助詐欺案件，經本院以97年度審簡字第4837號判處\n    有期徒刑3 月確定，上開二罪，經本院以98年度審聲字第72\n    2 號裁定應執行刑為有期徒刑8 月，於99年3 月31日縮刑期\n    滿執行完畢。其明知詐欺集團之不法份子經常利用他人存款\n    帳戶、提款卡、密碼轉帳等方式，獲取不法利益並逃避執法\n    人員之追查，且依其社會經驗，應有相當之智識程度可預見\n    將自己所有存款帳戶存摺、提款卡連同密碼，交付與不相識\n    之成年人使用，有被犯罪集團利用作為詐財轉帳匯款或其他\n    財產犯罪之虞，竟以縱有人持其存款帳戶作為犯罪工具，亦\n    不違其本意之幫助犯意，於99年4 月9 日下午4 時許，在高\n    雄市○○路國統飯店前，將其所申設之華南商業銀行路竹分\n    行（下稱華南銀行）帳號000000000000000 號帳戶之提款卡\n    及密碼，交與真實姓名、年籍不詳，自稱「張經理」之成年\n    男子及其所屬犯罪集團使用。嗣該犯罪集團成員取得上開帳\n    戶後，即意圖為自己不法之所有，共同基於詐欺取財之犯意\n    聯絡，於99年4 月10日晚上7 時許，由該詐欺集團之不詳成\n    員撥打電話予張麗卿，佯稱：其網路購物物品有誤，須至提\n    款機查詢有無扣款云云，使張麗卿誤信為真而陷於錯誤，依\n    詐騙集團成員指示至自動櫃員機操作，於同日晚上7 時46分\n    許，至彰化縣員林鎮○○路○段之郵局將新臺幣（下同）29\n    ,989元轉帳至李鳳源上開華南銀行帳戶內，並旋即遭提領一\n    空。\n二、證據名稱：被告李鳳源於本院審理時之自白，證人即被害人\n    張麗卿於警詢時之證述，被害人提出之郵政自動櫃員機交易\n    明細表影本1 紙、上開華南銀行帳號000000000000000 號帳\n    戶之開戶基本資料及存款往來明細表暨對帳單1 份。\n三、按刑法上之幫助犯，係指以幫助之意思，對於正犯之犯罪行\n    為予以助力，而未參與實施犯罪之行為者而言，最高法院19\n    年上字第1984號、49年台上字第77號判例意旨可資參照，亦\n    即行為人如未參與實施犯罪構成要件之行為，且係出於幫助\n    之意思提供助力，即屬幫助犯，而非共同正犯。查本件被告\n    提供其所有之華南銀行帳戶提款卡及密碼與他人使用，使詐\n    欺集團作為實施詐欺取財之犯罪工具，其單純提供帳戶供人\n    使用之行為，並不等同於向被害人施加詐術之行為，且亦無\n    證據證明被告有參與詐欺取財犯行之構成要件行為，是被告\n    提供帳戶供人使用之行為，係對於該詐欺集團遂行詐欺取財\n    犯行，資以助力。是核被告所為，係犯刑法第30條第1 項前\n    段、第339 條第1 項之幫助詐欺取財罪。被告有如事實欄所\n    載受有期徒刑執行完畢之事實，有臺灣高等法院被告前案紀\n    錄表附卷可憑，其受徒刑執行完畢，5 年以內故意再犯本件\n    有期徒刑以上之罪，為累犯，應依刑法第47條第1 項規定，\n    加重其刑。又被告並未實際參與詐欺犯行，為幫助犯，所犯\n    情節較正犯輕微，爰依刑法第30條第2 項規定，按正犯之刑\n    減輕之，並依法先加後減。爰審酌被告前已因交付手機門號\n    之幫助詐欺案件，經本院以97年度審簡字第4837號判處有期\n    徒刑3 月確定，竟猶不知警惕，又交付金融帳戶與他人使用\n    ，其雖未實際參與詐欺取財犯行，然其提供金融帳戶供犯罪\n    集團使用，致被害人張麗卿受有29,989元之損害，其所為助\n    長詐欺集團財產犯罪之風氣，使詐財事件層出不窮發生，造\n    成社會互信受損，擾亂金融交易往來秩序，影響層面廣泛，\n    更使執法人員難以追查該詐欺集團，增加被害人求償之困難\n    ，且未賠償被害人之損害，實屬不該，惟念及被告於本院審\n    理時尚能坦承犯行，態度尚可，並考量其犯罪動機、目的、\n    被害人所受損害，及自稱家庭經濟狀況小康、大專畢業、現\n    從事電鍍業、月薪45,000元、每月尚有卡債、會錢及貸款需\n    繳納等一切情狀（見警卷第1 頁調查筆錄受詢問人欄、本院\n    審易字卷第16頁），量處如主文所示之刑，併諭知易科罰金\n    之折算標準，以示懲儆。\n四、依刑事訴訟法第449 條第2 項、第3 項、第454 條第1 項，\n    刑法第339 條第1 項、第30條第1 項前段、第2 項、第47條\n    第1 項、第41條第1 項前段，刑法施行法第1 條之1 第1 項\n    、第2 項前段，逕以簡易判決處刑如主文。\n五、如不服本判決，得自收受送達之日起10日內，向本院提起上\n    訴（須附繕本）。",
    "reason": "一、犯罪事實：\n    李鳳源前於民國97年間因業務侵占案件，經本院以97年度易\n    字第805 號判處有期徒刑6 月確定。另於97年間因交付手機\n    門號之幫助詐欺案件，經本院以97年度審簡字第4837號判處\n    有期徒刑3 月確定，上開二罪，經本院以98年度審聲字第72\n    2 號裁定應執行刑為有期徒刑8 月，於99年3 月31日縮刑期\n    滿執行完畢。其明知詐欺集團之不法份子經常利用他人存款\n    帳戶、提款卡、密碼轉帳等方式，獲取不法利益並逃避執法\n    人員之追查，且依其社會經驗，應有相當之智識程度可預見\n    將自己所有存款帳戶存摺、提款卡連同密碼，交付與不相識\n    之成年人使用，有被犯罪集團利用作為詐財轉帳匯款或其他\n    財產犯罪之虞，竟以縱有人持其存款帳戶作為犯罪工具，亦\n    不違其本意之幫助犯意，於99年4 月9 日下午4 時許，在高\n    雄市○○路國統飯店前，將其所申設之華南商業銀行路竹分\n    行（下稱華南銀行）帳號000000000000000 號帳戶之提款卡\n    及密碼，交與真實姓名、年籍不詳，自稱「張經理」之成年\n    男子及其所屬犯罪集團使用。嗣該犯罪集團成員取得上開帳\n    戶後，即意圖為自己不法之所有，共同基於詐欺取財之犯意\n    聯絡，於99年4 月10日晚上7 時許，由該詐欺集團之不詳成\n    員撥打電話予張麗卿，佯稱：其網路購物物品有誤，須至提\n    款機查詢有無扣款云云，使張麗卿誤信為真而陷於錯誤，依\n    詐騙集團成員指示至自動櫃員機操作，於同日晚上7 時46分\n    許，至彰化縣員林鎮○○路○段之郵局將新臺幣（下同）29\n    ,989元轉帳至李鳳源上開華南銀行帳戶內，並旋即遭提領一\n    空。\n二、證據名稱：被告李鳳源於本院審理時之自白，證人即被害人\n    張麗卿於警詢時之證述，被害人提出之郵政自動櫃員機交易\n    明細表影本1 紙、上開華南銀行帳號000000000000000 號帳\n    戶之開戶基本資料及存款往來明細表暨對帳單1 份。\n三、按刑法上之幫助犯，係指以幫助之意思，對於正犯之犯罪行\n    為予以助力，而未參與實施犯罪之行為者而言，最高法院19\n    年上字第1984號、49年台上字第77號判例意旨可資參照，亦\n    即行為人如未參與實施犯罪構成要件之行為，且係出於幫助\n    之意思提供助力，即屬幫助犯，而非共同正犯。查本件被告\n    提供其所有之華南銀行帳戶提款卡及密碼與他人使用，使詐\n    欺集團作為實施詐欺取財之犯罪工具，其單純提供帳戶供人\n    使用之行為，並不等同於向被害人施加詐術之行為，且亦無\n    證據證明被告有參與詐欺取財犯行之構成要件行為，是被告\n    提供帳戶供人使用之行為，係對於該詐欺集團遂行詐欺取財\n    犯行，資以助力。是核被告所為，係犯刑法第30條第1 項前\n    段、第339 條第1 項之幫助詐欺取財罪。被告有如事實欄所\n    載受有期徒刑執行完畢之事實，有臺灣高等法院被告前案紀\n    錄表附卷可憑，其受徒刑執行完畢，5 年以內故意再犯本件\n    有期徒刑以上之罪，為累犯，應依刑法第47條第1 項規定，\n    加重其刑。又被告並未實際參與詐欺犯行，為幫助犯，所犯\n    情節較正犯輕微，爰依刑法第30條第2 項規定，按正犯之刑\n    減輕之，並依法先加後減。爰審酌被告前已因交付手機門號\n    之幫助詐欺案件，經本院以97年度審簡字第4837號判處有期\n    徒刑3 月確定，竟猶不知警惕，又交付金融帳戶與他人使用\n    ，其雖未實際參與詐欺取財犯行，然其提供金融帳戶供犯罪\n    集團使用，致被害人張麗卿受有29,989元之損害，其所為助\n    長詐欺集團財產犯罪之風氣，使詐財事件層出不窮發生，造\n    成社會互信受損，擾亂金融交易往來秩序，影響層面廣泛，\n    更使執法人員難以追查該詐欺集團，增加被害人求償之困難\n    ，且未賠償被害人之損害，實屬不該，惟念及被告於本院審\n    理時尚能坦承犯行，態度尚可，並考量其犯罪動機、目的、\n    被害人所受損害，及自稱家庭經濟狀況小康、大專畢業、現\n    從事電鍍業、月薪45,000元、每月尚有卡債、會錢及貸款需\n    繳納等一切情狀（見警卷第1 頁調查筆錄受詢問人欄、本院\n    審易字卷第16頁），量處如主文所示之刑，併諭知易科罰金\n    之折算標準，以示懲儆。\n四、依刑事訴訟法第449 條第2 項、第3 項、第454 條第1 項，\n    刑法第339 條第1 項、第30條第1 項前段、第2 項、第47條\n    第1 項、第41條第1 項前段，刑法施行法第1 條之1 第1 項\n    、第2 項前段，逕以簡易判決處刑如主文。\n五、如不服本判決，得自收受送達之日起10日內，向本院提起上\n    訴（須附繕本）。"
  },
  "search": "臺灣高雄地方法院刑事簡易判決99年度審簡字第4248號公訴人臺灣高雄地方法院檢察署檢察官被告李鳳源上列被告因詐欺案件，經檢察官提起公訴（99年度偵字第28446號），被告自白犯罪，本院認為宜以簡易判決處刑，經本院合議庭裁定改依簡易判決處刑，判決如下：主文李鳳源幫助犯詐欺取財罪，累犯，處有期徒刑參月，如易科罰金，以新臺幣壹仟元折算壹日。事實及理由一、犯罪事實：李鳳源前於民國97年間因業務侵占案件，經本院以97年度易字第805號判處有期徒刑6月確定。另於97年間因交付手機門號之幫助詐欺案件，經本院以97年度審簡字第4837號判處有期徒刑3月確定，上開二罪，經本院以98年度審聲字第722號裁定應執行刑為有期徒刑8月，於99年3月31日縮刑期滿執行完畢。其明知詐欺集團之不法份子經常利用他人存款帳戶、提款卡、密碼轉帳等方式，獲取不法利益並逃避執法人員之追查，且依其社會經驗，應有相當之智識程度可預見將自己所有存款帳戶存摺、提款卡連同密碼，交付與不相識之成年人使用，有被犯罪集團利用作為詐財轉帳匯款或其他財產犯罪之虞，竟以縱有人持其存款帳戶作為犯罪工具，亦不違其本意之幫助犯意，於99年4月9日下午4時許，在高雄市○○路國統飯店前，將其所申設之華南商業銀行路竹分行（下稱華南銀行）帳號000000000000000號帳戶之提款卡及密碼，交與真實姓名、年籍不詳，自稱「張經理」之成年男子及其所屬犯罪集團使用。嗣該犯罪集團成員取得上開帳戶後，即意圖為自己不法之所有，共同基於詐欺取財之犯意聯絡，於99年4月10日晚上7時許，由該詐欺集團之不詳成員撥打電話予張麗卿，佯稱：其網路購物物品有誤，須至提款機查詢有無扣款云云，使張麗卿誤信為真而陷於錯誤，依詐騙集團成員指示至自動櫃員機操作，於同日晚上7時46分許，至彰化縣員林鎮○○路○段之郵局將新臺幣（下同）29,989元轉帳至李鳳源上開華南銀行帳戶內，並旋即遭提領一空。二、證據名稱：被告李鳳源於本院審理時之自白，證人即被害人張麗卿於警詢時之證述，被害人提出之郵政自動櫃員機交易明細表影本1紙、上開華南銀行帳號000000000000000號帳戶之開戶基本資料及存款往來明細表暨對帳單1份。三、按刑法上之幫助犯，係指以幫助之意思，對於正犯之犯罪行為予以助力，而未參與實施犯罪之行為者而言，最高法院19年上字第1984號、49年台上字第77號判例意旨可資參照，亦即行為人如未參與實施犯罪構成要件之行為，且係出於幫助之意思提供助力，即屬幫助犯，而非共同正犯。查本件被告提供其所有之華南銀行帳戶提款卡及密碼與他人使用，使詐欺集團作為實施詐欺取財之犯罪工具，其單純提供帳戶供人使用之行為，並不等同於向被害人施加詐術之行為，且亦無證據證明被告有參與詐欺取財犯行之構成要件行為，是被告提供帳戶供人使用之行為，係對於該詐欺集團遂行詐欺取財犯行，資以助力。是核被告所為，係犯刑法第30條第1項前段、第339條第1項之幫助詐欺取財罪。被告有如事實欄所載受有期徒刑執行完畢之事實，有臺灣高等法院被告前案紀錄表附卷可憑，其受徒刑執行完畢，5年以內故意再犯本件有期徒刑以上之罪，為累犯，應依刑法第47條第1項規定，加重其刑。又被告並未實際參與詐欺犯行，為幫助犯，所犯情節較正犯輕微，爰依刑法第30條第2項規定，按正犯之刑減輕之，並依法先加後減。爰審酌被告前已因交付手機門號之幫助詐欺案件，經本院以97年度審簡字第4837號判處有期徒刑3月確定，竟猶不知警惕，又交付金融帳戶與他人使用，其雖未實際參與詐欺取財犯行，然其提供金融帳戶供犯罪集團使用，致被害人張麗卿受有29,989元之損害，其所為助長詐欺集團財產犯罪之風氣，使詐財事件層出不窮發生，造成社會互信受損，擾亂金融交易往來秩序，影響層面廣泛，更使執法人員難以追查該詐欺集團，增加被害人求償之困難，且未賠償被害人之損害，實屬不該，惟念及被告於本院審理時尚能坦承犯行，態度尚可，並考量其犯罪動機、目的、被害人所受損害，及自稱家庭經濟狀況小康、大專畢業、現從事電鍍業、月薪45,000元、每月尚有卡債、會錢及貸款需繳納等一切情狀（見警卷第1頁調查筆錄受詢問人欄、本院審易字卷第16頁），量處如主文所示之刑，併諭知易科罰金之折算標準，以示懲儆。四、依刑事訴訟法第449條第2項、第3項、第454條第1項，刑法第339條第1項、第30條第1項前段、第2項、第47條第1項、第41條第1項前段，刑法施行法第1條之1第1項、第2項前段，逕以簡易判決處刑如主文。五、如不服本判決，得自收受送達之日起10日內，向本院提起上訴（須附繕本）。中華民國100年3月7日高雄簡易庭法官周佳佩以上正本證明與原本無異。中華民國100年3月7日書記官李承悌附錄本案論罪科刑法條：刑法第339條第1項意圖為自己或第三人不法之所有，以詐術使人將本人或第三人之物交付者，處5年以下有期徒刑、拘役或科或併科1千元以下罰金。",
  "characters": {
    "judges": [
      "周佳佩"
    ],
    "prosecutors": [

    ],
    "lawyers": [

    ],
    "clerks": [
      "李承悌"
    ],
    "plaintiffs": [

    ],
    "defendants": [
      "李鳳源"
    ],
    "prosecutor_office": [
      "臺灣高雄地方法院檢察署檢察官"
    ],
    "creditors": [

    ],
    "debtors": [

    ],
    "judicial_associate_officer": [

    ]
  },
  "adjudged_at": "2011-03-07",
  "created_at": "2016-02-13 21:33:06",
  "updated_at": "2016-02-13 21:33:06"
}