{
  "identify": "TND-100-交簡-492-20110307-1",
  "court": {
    "name": "臺灣臺南地方法院",
    "code": "TND"
  },
  "division": {
    "name": "刑事",
    "code": "M"
  },
  "year": 100,
  "word": "交簡",
  "number": "492",
  "jcheck": "1",
  "reason": "業務過失致死",
  "content": "臺灣臺南地方法院刑事簡易判決    100年度交簡字第492號\n公  訴  人  臺灣臺南地方法院檢察署檢察官\n被      告  步正雄\n上列被告因業務過失致死案件，經檢察官依通常程序提起公訴（\n99年度偵字第14656號），因被告自白犯罪，本院認為宜以簡易\n判決處刑，判決如下：\n    主  文\n步正雄業務過失致人於死，處有期徒刑陸月，如易科罰金，以新\n台幣壹仟元折算壹日；緩刑貳年。\n    理  由\n一、本件之犯罪事實及證據均引用檢察官起訴書之記載（如附件\n    ）。\n二、核被告步正雄所為，係犯刑法第276條第2項之罪。又其於肇\n    事後，犯罪未被有偵查權之公務員或機關發覺前，即向據報\n    到場處理之改制前台南縣警察局永康分局警員表明其係肇事\n    車輛之駕駛人而自首，並坦承犯行進而接受裁判，有道路交\n    通事故肇事人自首情形紀錄表1份附卷可參，爰依刑法第62\n    條前段自首之規定，減輕其刑（見相驗卷宗第19頁）。\n三、本院審酌被告駕駛車輛，本應謹慎小心，以維自身及參與道\n    路交通者之安全，竟疏於注意轉彎車應讓直行車先行而肇事\n    ，其過失程度經核非屬輕微，並造成被害人許佐榕死亡之結\n    果，所生損害巨大，惟念被告已與被害人家屬就民事賠償事\n    宜，達成和解，業據被害人家屬周素旬陳稱在卷，並有台南\n    縣新市鄉調解委員會調解筆錄1份附卷可參，及被告犯罪後\n    業已坦承犯行等一切情狀，量處如主文所示之刑，並諭知易\n    科罰金之折算標準。另被告前未曾受有期徒刑以上刑之宣告\n    ，復有臺灣高等法院被告全國前案紀錄表1紙在卷可按，其\n    經此教訓，當知謹慎，信無再犯之虞，並參酌公訴檢察官之\n    建議，本院認所宣告之刑，以暫不執行為適當，併諭知緩刑\n    2年，以勵自新。\n四、依刑事訴訟法第449條第2項、第454條第2項、第299條第1項\n    前段，刑法第276條第2項、第41條第1項前段、第62條前段\n    、第74條第1項第1款，刑法施行法第1條之1，逕以簡易判決\n    處刑如主文所示。\n五、本件判決係於檢察官及被告表明同意被告受科刑範圍內處刑\n    ，依刑事訴訟法第455條之1第2項之規定及意旨，檢察官及\n    被告均不得上訴。\n中    華    民    國   100    年    3     月    7     日\n                  交通法庭     法  官  陳淑勤\n以上正本證明與原本無異。\n不得上訴。\n中    華    民    國   100    年    3     月    7     日\n                               書記官  謝竣閎\n附錄本案論罪科刑法條全文--\n中華民國刑法第276條：\n因過失致人於死者，處2年以下有期徒刑、拘役或2千元以下罰金\n。\n從事業務之人，因業務上之過失犯前項之罪者，處5年以下有期\n徒刑或拘役，得併科3千元以下罰金。",
  "structure": {
    "main": "步正雄業務過失致人於死，處有期徒刑陸月，如易科罰金，以新\n台幣壹仟元折算壹日；緩刑貳年。",
    "reason": "一、本件之犯罪事實及證據均引用檢察官起訴書之記載（如附件\n    ）。\n二、核被告步正雄所為，係犯刑法第276條第2項之罪。又其於肇\n    事後，犯罪未被有偵查權之公務員或機關發覺前，即向據報\n    到場處理之改制前台南縣警察局永康分局警員表明其係肇事\n    車輛之駕駛人而自首，並坦承犯行進而接受裁判，有道路交\n    通事故肇事人自首情形紀錄表1份附卷可參，爰依刑法第62\n    條前段自首之規定，減輕其刑（見相驗卷宗第19頁）。\n三、本院審酌被告駕駛車輛，本應謹慎小心，以維自身及參與道\n    路交通者之安全，竟疏於注意轉彎車應讓直行車先行而肇事\n    ，其過失程度經核非屬輕微，並造成被害人許佐榕死亡之結\n    果，所生損害巨大，惟念被告已與被害人家屬就民事賠償事\n    宜，達成和解，業據被害人家屬周素旬陳稱在卷，並有台南\n    縣新市鄉調解委員會調解筆錄1份附卷可參，及被告犯罪後\n    業已坦承犯行等一切情狀，量處如主文所示之刑，並諭知易\n    科罰金之折算標準。另被告前未曾受有期徒刑以上刑之宣告\n    ，復有臺灣高等法院被告全國前案紀錄表1紙在卷可按，其\n    經此教訓，當知謹慎，信無再犯之虞，並參酌公訴檢察官之\n    建議，本院認所宣告之刑，以暫不執行為適當，併諭知緩刑\n    2年，以勵自新。\n四、依刑事訴訟法第449條第2項、第454條第2項、第299條第1項\n    前段，刑法第276條第2項、第41條第1項前段、第62條前段\n    、第74條第1項第1款，刑法施行法第1條之1，逕以簡易判決\n    處刑如主文所示。\n五、本件判決係於檢察官及被告表明同意被告受科刑範圍內處刑\n    ，依刑事訴訟法第455條之1第2項之規定及意旨，檢察官及\n    被告均不得上訴。"
  },
  "search": "臺灣臺南地方法院刑事簡易判決100年度交簡字第492號公訴人臺灣臺南地方法院檢察署檢察官被告步正雄上列被告因業務過失致死案件，經檢察官依通常程序提起公訴（99年度偵字第14656號），因被告自白犯罪，本院認為宜以簡易判決處刑，判決如下：主文步正雄業務過失致人於死，處有期徒刑陸月，如易科罰金，以新台幣壹仟元折算壹日；緩刑貳年。理由一、本件之犯罪事實及證據均引用檢察官起訴書之記載（如附件）。二、核被告步正雄所為，係犯刑法第276條第2項之罪。又其於肇事後，犯罪未被有偵查權之公務員或機關發覺前，即向據報到場處理之改制前台南縣警察局永康分局警員表明其係肇事車輛之駕駛人而自首，並坦承犯行進而接受裁判，有道路交通事故肇事人自首情形紀錄表1份附卷可參，爰依刑法第62條前段自首之規定，減輕其刑（見相驗卷宗第19頁）。三、本院審酌被告駕駛車輛，本應謹慎小心，以維自身及參與道路交通者之安全，竟疏於注意轉彎車應讓直行車先行而肇事，其過失程度經核非屬輕微，並造成被害人許佐榕死亡之結果，所生損害巨大，惟念被告已與被害人家屬就民事賠償事宜，達成和解，業據被害人家屬周素旬陳稱在卷，並有台南縣新市鄉調解委員會調解筆錄1份附卷可參，及被告犯罪後業已坦承犯行等一切情狀，量處如主文所示之刑，並諭知易科罰金之折算標準。另被告前未曾受有期徒刑以上刑之宣告，復有臺灣高等法院被告全國前案紀錄表1紙在卷可按，其經此教訓，當知謹慎，信無再犯之虞，並參酌公訴檢察官之建議，本院認所宣告之刑，以暫不執行為適當，併諭知緩刑2年，以勵自新。四、依刑事訴訟法第449條第2項、第454條第2項、第299條第1項前段，刑法第276條第2項、第41條第1項前段、第62條前段、第74條第1項第1款，刑法施行法第1條之1，逕以簡易判決處刑如主文所示。五、本件判決係於檢察官及被告表明同意被告受科刑範圍內處刑，依刑事訴訟法第455條之1第2項之規定及意旨，檢察官及被告均不得上訴。中華民國100年3月7日交通法庭法官陳淑勤以上正本證明與原本無異。不得上訴。中華民國100年3月7日書記官謝竣閎附錄本案論罪科刑法條全文--中華民國刑法第276條：因過失致人於死者，處2年以下有期徒刑、拘役或2千元以下罰金。從事業務之人，因業務上之過失犯前項之罪者，處5年以下有期徒刑或拘役，得併科3千元以下罰金。",
  "characters": {
    "judges": [
      "陳淑勤"
    ],
    "prosecutors": [

    ],
    "lawyers": [

    ],
    "clerks": [
      "謝竣閎"
    ],
    "plaintiffs": [

    ],
    "defendants": [
      "步正雄"
    ],
    "prosecutor_office": [
      "臺灣臺南地方法院檢察署檢察官"
    ],
    "creditors": [

    ],
    "debtors": [

    ],
    "judicial_associate_officer": [

    ]
  },
  "adjudged_at": "2011-03-07",
  "created_at": "2016-02-13 21:27:31",
  "updated_at": "2016-02-13 21:27:31"
}