{
  "identify": "ULD-100-訴-320-20110503-1",
  "court": {
    "name": "臺灣雲林地方法院",
    "code": "ULD"
  },
  "division": {
    "name": "刑事",
    "code": "M"
  },
  "year": 100,
  "word": "訴",
  "number": "320",
  "jcheck": "1",
  "reason": "違反毒品危害防制條例",
  "content": "臺灣雲林地方法院刑事判決              100年度訴字第320號\n公  訴  人  臺灣雲林地方法院檢察署檢察官\n被      告  李曜均\n上列被告因違反毒品危害防制條例案件，經檢察官提起公訴（\n100 年度毒偵字第435 號），於本院準備程序進行中，被告就被\n訴事實為有罪之陳述，經合議庭裁定由受命法官獨任進行簡式審\n判程序，判決如下：\n    主  文\n李曜均施用第一級毒品，累犯，處有期徒刑玖月。\n    事實及理由\n一、犯罪事實：\n  (一)李曜均前因施用毒品案件，經送觀察、勒戒後，認無繼續施\n    用毒品之傾向，於民國93年10月20日釋放，並由臺灣雲林地\n    方法院檢察署檢察官於同年月25日，以93年度毒偵字第1260\n    號為不起訴處分確定。其復於5 年內，再犯施用第一、二級\n    毒品案件，經本院以95年度訴字第23號分別判處有期徒刑8\n    月、4 月確定；又因竊盜案件，經本院以95年度六簡字第19\n    6 號判處有期徒刑3 月確定，上揭二案嗣經本院以95年度聲\n    字第781 號裁定應執行有期徒刑1 年1 月確定，於96年5 月\n    27日縮短刑期執行完畢。詎其不知警惕，基於施用第一級毒\n    品之犯意，於100 年1 月24日晚上8 至9 時之間，在雲林縣\n    崙背鄉水尾村水尾31之1 號其住處內，以針筒注射之方式，\n    施用第一級毒品海洛因1 次。嗣於同年1 月25日下午1 時45\n    分許，為警採尿送驗後，其結果呈可待因及嗎啡之陽性反應\n    ，始悉上情。\n  (二)案經雲林縣警察局台西分局報告臺灣雲林地方法院檢察署檢\n    察官偵查起訴。\n二、證據名稱：\n  (一)被告李曜均於警詢及本院審判中之自白供述。\n  (二)雲林縣警察局台西分局委託檢驗尿液代號與真實姓名對照認\n    證單、代號與真實姓名對照表、勘察採證同意書。\n  (三)詮昕科技股份有限公司濫用藥物尿液檢驗報告（報告編號：\n    00000000號）。\n  (四)刑案資料查註紀錄表、全國施用毒品案件紀錄表、矯正簡表\n    。\n三、論罪科刑之理由：\n  (一)核被告李曜均所為，係犯毒品危害防制條例第10條第1 項之\n    施用第一級毒品罪。被告持有海洛因之行為，為其後施用之\n    高度行為所吸收，不另論罪。\n  (二)被告前因施用第一、二級毒品案件，經本院以95年度訴字第\n    23號分別判處有期徒刑8 月、4 月確定；又因竊盜案件，經\n    本院以95年度六簡字第196 號判處有期徒刑3 月確定，上揭\n    二案嗣經本院以95年度聲字第781 號裁定應執行有期徒刑1\n    年1 月確定，於96年5 月27日縮短刑期執行完畢，有臺灣高\n    等法院被告前案紀錄表可參，其於5 年以內故意再犯本件有\n    期徒刑以上之罪，為累犯，應依刑法第47條第1 項之規定，\n    加重其刑。\n  (三)爰審酌被告前業因施用毒品犯行，經執行觀察勒戒完畢後，\n    又因施用第一、二級毒品案件，經本院判處有期徒刑確定，\n    並執行完畢，猶不知警惕、戒除毒癮，復犯本件施用毒品之\n    罪。惟其施用毒品係屬自戕之罪，又其原長期從事成衣整燙\n    業，但因僱主停業後，而屢次更易工作，嗣因結交施用毒品\n    之友人及自覺生活壓力過大，致一再沈淪毒害。另其未婚而\n    與女友育有一子，原與父母同住，其父對其仍有關懷及鼓勵\n    ，而其犯後坦承犯行，態度良好，仍有悔意等一切情狀，量\n    處如主文所示之刑，期收矯治之效。\n四、適用之法律：\n  (一)刑事訴訟法第273 條之1 第1 項、第299 條第1 項前段、第\n    310 條之2 、第454 條第1 項。\n  (二)毒品危害防制條例第10條第1 項。\n  (三)刑法第11條、第47條第1 項。\n本案經檢察官江柏青到庭執行職務。\n中    華    民    國    100    年    5    月    3     日\n                  刑事第五庭  法  官  吳基華\n以上正本證明與原本無異。\n如不服本判決應於收受判決後10日內向本院提出上訴書狀，並應\n敘述具體理由；其未敘述上訴理由者，應於上訴期間屆滿後20日\n內向本院補提理由書（均須按他造當事人之人數附繕本）。「切\n勿逕送上級法院」。\n                              書記官  李達成\n中    華    民    國   100    年    5     月    3     日\n附記論罪法條全文：毒品危害防制條例第10條第1項。\n毒品危害防制條例第10條\n施用第一級毒品者，處 6 月以上 5 年以下有期徒刑。\n施用第二級毒品者，處 3 年以下有期徒刑。",
  "structure": {
    "main": "李曜均施用第一級毒品，累犯，處有期徒刑玖月。",
    "fact": "一、犯罪事實：\n  (一)李曜均前因施用毒品案件，經送觀察、勒戒後，認無繼續施\n    用毒品之傾向，於民國93年10月20日釋放，並由臺灣雲林地\n    方法院檢察署檢察官於同年月25日，以93年度毒偵字第1260\n    號為不起訴處分確定。其復於5 年內，再犯施用第一、二級\n    毒品案件，經本院以95年度訴字第23號分別判處有期徒刑8\n    月、4 月確定；又因竊盜案件，經本院以95年度六簡字第19\n    6 號判處有期徒刑3 月確定，上揭二案嗣經本院以95年度聲\n    字第781 號裁定應執行有期徒刑1 年1 月確定，於96年5 月\n    27日縮短刑期執行完畢。詎其不知警惕，基於施用第一級毒\n    品之犯意，於100 年1 月24日晚上8 至9 時之間，在雲林縣\n    崙背鄉水尾村水尾31之1 號其住處內，以針筒注射之方式，\n    施用第一級毒品海洛因1 次。嗣於同年1 月25日下午1 時45\n    分許，為警採尿送驗後，其結果呈可待因及嗎啡之陽性反應\n    ，始悉上情。\n  (二)案經雲林縣警察局台西分局報告臺灣雲林地方法院檢察署檢\n    察官偵查起訴。\n二、證據名稱：\n  (一)被告李曜均於警詢及本院審判中之自白供述。\n  (二)雲林縣警察局台西分局委託檢驗尿液代號與真實姓名對照認\n    證單、代號與真實姓名對照表、勘察採證同意書。\n  (三)詮昕科技股份有限公司濫用藥物尿液檢驗報告（報告編號：\n    00000000號）。\n  (四)刑案資料查註紀錄表、全國施用毒品案件紀錄表、矯正簡表\n    。\n三、論罪科刑之理由：\n  (一)核被告李曜均所為，係犯毒品危害防制條例第10條第1 項之\n    施用第一級毒品罪。被告持有海洛因之行為，為其後施用之\n    高度行為所吸收，不另論罪。\n  (二)被告前因施用第一、二級毒品案件，經本院以95年度訴字第\n    23號分別判處有期徒刑8 月、4 月確定；又因竊盜案件，經\n    本院以95年度六簡字第196 號判處有期徒刑3 月確定，上揭\n    二案嗣經本院以95年度聲字第781 號裁定應執行有期徒刑1\n    年1 月確定，於96年5 月27日縮短刑期執行完畢，有臺灣高\n    等法院被告前案紀錄表可參，其於5 年以內故意再犯本件有\n    期徒刑以上之罪，為累犯，應依刑法第47條第1 項之規定，\n    加重其刑。\n  (三)爰審酌被告前業因施用毒品犯行，經執行觀察勒戒完畢後，\n    又因施用第一、二級毒品案件，經本院判處有期徒刑確定，\n    並執行完畢，猶不知警惕、戒除毒癮，復犯本件施用毒品之\n    罪。惟其施用毒品係屬自戕之罪，又其原長期從事成衣整燙\n    業，但因僱主停業後，而屢次更易工作，嗣因結交施用毒品\n    之友人及自覺生活壓力過大，致一再沈淪毒害。另其未婚而\n    與女友育有一子，原與父母同住，其父對其仍有關懷及鼓勵\n    ，而其犯後坦承犯行，態度良好，仍有悔意等一切情狀，量\n    處如主文所示之刑，期收矯治之效。\n四、適用之法律：\n  (一)刑事訴訟法第273 條之1 第1 項、第299 條第1 項前段、第\n    310 條之2 、第454 條第1 項。\n  (二)毒品危害防制條例第10條第1 項。\n  (三)刑法第11條、第47條第1 項。\n本案經檢察官江柏青到庭執行職務。",
    "reason": "一、犯罪事實：\n  (一)李曜均前因施用毒品案件，經送觀察、勒戒後，認無繼續施\n    用毒品之傾向，於民國93年10月20日釋放，並由臺灣雲林地\n    方法院檢察署檢察官於同年月25日，以93年度毒偵字第1260\n    號為不起訴處分確定。其復於5 年內，再犯施用第一、二級\n    毒品案件，經本院以95年度訴字第23號分別判處有期徒刑8\n    月、4 月確定；又因竊盜案件，經本院以95年度六簡字第19\n    6 號判處有期徒刑3 月確定，上揭二案嗣經本院以95年度聲\n    字第781 號裁定應執行有期徒刑1 年1 月確定，於96年5 月\n    27日縮短刑期執行完畢。詎其不知警惕，基於施用第一級毒\n    品之犯意，於100 年1 月24日晚上8 至9 時之間，在雲林縣\n    崙背鄉水尾村水尾31之1 號其住處內，以針筒注射之方式，\n    施用第一級毒品海洛因1 次。嗣於同年1 月25日下午1 時45\n    分許，為警採尿送驗後，其結果呈可待因及嗎啡之陽性反應\n    ，始悉上情。\n  (二)案經雲林縣警察局台西分局報告臺灣雲林地方法院檢察署檢\n    察官偵查起訴。\n二、證據名稱：\n  (一)被告李曜均於警詢及本院審判中之自白供述。\n  (二)雲林縣警察局台西分局委託檢驗尿液代號與真實姓名對照認\n    證單、代號與真實姓名對照表、勘察採證同意書。\n  (三)詮昕科技股份有限公司濫用藥物尿液檢驗報告（報告編號：\n    00000000號）。\n  (四)刑案資料查註紀錄表、全國施用毒品案件紀錄表、矯正簡表\n    。\n三、論罪科刑之理由：\n  (一)核被告李曜均所為，係犯毒品危害防制條例第10條第1 項之\n    施用第一級毒品罪。被告持有海洛因之行為，為其後施用之\n    高度行為所吸收，不另論罪。\n  (二)被告前因施用第一、二級毒品案件，經本院以95年度訴字第\n    23號分別判處有期徒刑8 月、4 月確定；又因竊盜案件，經\n    本院以95年度六簡字第196 號判處有期徒刑3 月確定，上揭\n    二案嗣經本院以95年度聲字第781 號裁定應執行有期徒刑1\n    年1 月確定，於96年5 月27日縮短刑期執行完畢，有臺灣高\n    等法院被告前案紀錄表可參，其於5 年以內故意再犯本件有\n    期徒刑以上之罪，為累犯，應依刑法第47條第1 項之規定，\n    加重其刑。\n  (三)爰審酌被告前業因施用毒品犯行，經執行觀察勒戒完畢後，\n    又因施用第一、二級毒品案件，經本院判處有期徒刑確定，\n    並執行完畢，猶不知警惕、戒除毒癮，復犯本件施用毒品之\n    罪。惟其施用毒品係屬自戕之罪，又其原長期從事成衣整燙\n    業，但因僱主停業後，而屢次更易工作，嗣因結交施用毒品\n    之友人及自覺生活壓力過大，致一再沈淪毒害。另其未婚而\n    與女友育有一子，原與父母同住，其父對其仍有關懷及鼓勵\n    ，而其犯後坦承犯行，態度良好，仍有悔意等一切情狀，量\n    處如主文所示之刑，期收矯治之效。\n四、適用之法律：\n  (一)刑事訴訟法第273 條之1 第1 項、第299 條第1 項前段、第\n    310 條之2 、第454 條第1 項。\n  (二)毒品危害防制條例第10條第1 項。\n  (三)刑法第11條、第47條第1 項。\n本案經檢察官江柏青到庭執行職務。"
  },
  "search": "臺灣雲林地方法院刑事判決100年度訴字第320號公訴人臺灣雲林地方法院檢察署檢察官被告李曜均上列被告因違反毒品危害防制條例案件，經檢察官提起公訴（100年度毒偵字第435號），於本院準備程序進行中，被告就被訴事實為有罪之陳述，經合議庭裁定由受命法官獨任進行簡式審判程序，判決如下：主文李曜均施用第一級毒品，累犯，處有期徒刑玖月。事實及理由一、犯罪事實：(一)李曜均前因施用毒品案件，經送觀察、勒戒後，認無繼續施用毒品之傾向，於民國93年10月20日釋放，並由臺灣雲林地方法院檢察署檢察官於同年月25日，以93年度毒偵字第1260號為不起訴處分確定。其復於5年內，再犯施用第一、二級毒品案件，經本院以95年度訴字第23號分別判處有期徒刑8月、4月確定；又因竊盜案件，經本院以95年度六簡字第196號判處有期徒刑3月確定，上揭二案嗣經本院以95年度聲字第781號裁定應執行有期徒刑1年1月確定，於96年5月27日縮短刑期執行完畢。詎其不知警惕，基於施用第一級毒品之犯意，於100年1月24日晚上8至9時之間，在雲林縣崙背鄉水尾村水尾31之1號其住處內，以針筒注射之方式，施用第一級毒品海洛因1次。嗣於同年1月25日下午1時45分許，為警採尿送驗後，其結果呈可待因及嗎啡之陽性反應，始悉上情。(二)案經雲林縣警察局台西分局報告臺灣雲林地方法院檢察署檢察官偵查起訴。二、證據名稱：(一)被告李曜均於警詢及本院審判中之自白供述。(二)雲林縣警察局台西分局委託檢驗尿液代號與真實姓名對照認證單、代號與真實姓名對照表、勘察採證同意書。(三)詮昕科技股份有限公司濫用藥物尿液檢驗報告（報告編號：00000000號）。(四)刑案資料查註紀錄表、全國施用毒品案件紀錄表、矯正簡表。三、論罪科刑之理由：(一)核被告李曜均所為，係犯毒品危害防制條例第10條第1項之施用第一級毒品罪。被告持有海洛因之行為，為其後施用之高度行為所吸收，不另論罪。(二)被告前因施用第一、二級毒品案件，經本院以95年度訴字第23號分別判處有期徒刑8月、4月確定；又因竊盜案件，經本院以95年度六簡字第196號判處有期徒刑3月確定，上揭二案嗣經本院以95年度聲字第781號裁定應執行有期徒刑1年1月確定，於96年5月27日縮短刑期執行完畢，有臺灣高等法院被告前案紀錄表可參，其於5年以內故意再犯本件有期徒刑以上之罪，為累犯，應依刑法第47條第1項之規定，加重其刑。(三)爰審酌被告前業因施用毒品犯行，經執行觀察勒戒完畢後，又因施用第一、二級毒品案件，經本院判處有期徒刑確定，並執行完畢，猶不知警惕、戒除毒癮，復犯本件施用毒品之罪。惟其施用毒品係屬自戕之罪，又其原長期從事成衣整燙業，但因僱主停業後，而屢次更易工作，嗣因結交施用毒品之友人及自覺生活壓力過大，致一再沈淪毒害。另其未婚而與女友育有一子，原與父母同住，其父對其仍有關懷及鼓勵，而其犯後坦承犯行，態度良好，仍有悔意等一切情狀，量處如主文所示之刑，期收矯治之效。四、適用之法律：(一)刑事訴訟法第273條之1第1項、第299條第1項前段、第310條之2、第454條第1項。(二)毒品危害防制條例第10條第1項。(三)刑法第11條、第47條第1項。本案經檢察官江柏青到庭執行職務。中華民國100年5月3日刑事第五庭法官吳基華以上正本證明與原本無異。如不服本判決應於收受判決後10日內向本院提出上訴書狀，並應敘述具體理由；其未敘述上訴理由者，應於上訴期間屆滿後20日內向本院補提理由書（均須按他造當事人之人數附繕本）。「切勿逕送上級法院」。書記官李達成中華民國100年5月3日附記論罪法條全文：毒品危害防制條例第10條第1項。毒品危害防制條例第10條施用第一級毒品者，處6月以上5年以下有期徒刑。施用第二級毒品者，處3年以下有期徒刑。",
  "characters": {
    "judges": [
      "吳基華"
    ],
    "prosecutors": [
      "江柏青"
    ],
    "lawyers": [

    ],
    "clerks": [
      "李達成"
    ],
    "plaintiffs": [

    ],
    "defendants": [
      "李曜均"
    ],
    "prosecutor_office": [
      "臺灣雲林地方法院檢察署檢察官"
    ],
    "creditors": [

    ],
    "debtors": [

    ],
    "judicial_associate_officer": [

    ]
  },
  "adjudged_at": "2011-05-03",
  "created_at": "2016-02-12 02:23:28",
  "updated_at": "2016-02-12 02:23:28"
}