{
  "identify": "CYD-100-訴-38-20110331-1",
  "court": {
    "name": "臺灣嘉義地方法院",
    "code": "CYD"
  },
  "division": {
    "name": "民事",
    "code": "V"
  },
  "year": 100,
  "word": "訴",
  "number": "38",
  "jcheck": "1",
  "reason": "返還就學貸款",
  "content": "臺灣嘉義地方法院民事判決               100年度訴字第38號\n原      告  臺灣銀行股份有限公司\n法定代理人  張明道\n訴訟代理人  黃文明\n複代理人    朱玉仁\n被      告  劉德椳\n            劉邦珍\n上列當事人間請求返還就學貸款事件，本院於民國100 年3 月24\n日言詞辯論終結，判決如下：\n    主    文\n被告應連帶給付原告新臺幣柒拾貳萬貳仟陸佰伍拾伍元，及自民\n國九十九年七月一日起至清償日止，按年息百分之二點六一計算\n之利息，暨自民國九十九年八月二日起至清償日止，其逾期在六\n個月以內者，按上開利率百分之十，逾期超過六個月者，按上開\n利率百分之二十計算之違約金。\n訴訟費用由被告連帶負擔。\n    事實及理由\n一、被告等合法通知，均未於言詞辯論期日到場，核無民事訴訟\n    法第386 條所列各款情形，爰依原告聲請，由其一造辯論而\n    為判決。\n二、原告起訴主張：被告即借款人劉德椳邀同被告劉邦珍為連帶\n    保證人向原告訂借就學貸款共13筆，金額總計為新臺幣（下\n    同）722,655 元，約定應於借款人該教育階段學業完成或服\n    義務兵役退伍後滿一年之日起分期償還本息，倘借款人不依\n    期償還本息時，除應自遲延日起按約定利率計付遲延利息外\n    ，另按遲延還本付息部份，應付未付本息自應還款之日起，\n    逾期6 （含）個月以內者，按逾期利率百分之10，逾期超過\n    6 個月以上者，就超過部分按逾期利率百分之20加計違約金\n    。詎被告劉德椳自99年8 月1 日起即未依約履行債務，迄今\n    尚欠本金722,655 元及自97年7 月1 日起至清償日止，按年\n    息2.61% 計算之利息，暨自99年8 月2 日起之違約金未還，\n    經原告催討未果，依據借據條款第8 條約定任何一宗不依約\n    清償或攤還本金時，即視為全部到期。另被告劉邦珍既為連\n    帶保證人，對本債務自應負連帶清償責任，為此依消費借貸\n    及連帶保證之法律關係，提起本件訴訟。並聲明：求為判決\n    如主文所示。\n三、被告等均未於言詞辯論期日到場，亦未提出書狀作何聲明或\n    陳述。\n四、法院之判斷：\n（一）按稱消費借貸者，謂當事人一方移轉金錢或其他代替物之\n      所有權於他方，而約定他方以種類、品質、數量相同之物\n      返還之契約，民法第474 條第1 項定有明文；又稱保證者\n      ，謂當事人約定，一方於他方之債務人不履行債務時，由\n      其代負履行責任之契約，亦為同法第739 條所明定；另保\n      證債務之所謂連帶，係指保證人與主債務人負同一債務，\n      對於債權人各負全部給付之責任者而言，此就民法第272\n      條第1 項規定連帶債務之文義參照觀之甚明（最高法院45\n      年台上字第1426號判例參照）；而連帶債務之債權人，依\n      同法第273 條第1 項規定，得對於債務人中之一人或數人\n      或其全體，同時或先後請求全部或一部之給付。\n（二）原告主張之上開事實，業據其提出與所述情節相符之放款\n      借據（就學貸款專用）、就學貸款撥款通知書、就學貸款\n      放出查詢單、就學貸款利率表等為證，核屬相符；被告等\n      對於原告主張之前開事實，均已於相當時期受合法之通知\n      ，而於言詞辯論期日不到場，亦未提出準備書狀爭執，依\n      民事訴訟法第280 條第3 項準用同條第1 項之規定，應視\n      同自認，則原告之主張，自堪信為真實。原告主張被告劉\n      德椳以被告劉邦珍為連帶保證人，向其借款未依約清償，\n      有如前述，則主債務人之被告劉德椳與任連帶保證人之被\n      告劉邦珍自應負同一清償之責。\n五、綜上所述，原告本於消費借貸及連帶保證契約之法律關係，\n    請求被告等應連帶給付722,655 元，及自99年7 月1 日起至\n    清償日止，按年息百分之2.61計算之利息，暨自民國99年8\n    月2 日起至清償日止，其逾期在6 個月以內者，按上開利率\n    百分之10，逾期超過6 個月者，按上開利率百分之20計算之\n    違約金，為有理由，應予准許。\n六、據上論結，本件原告之訴為有理由，依民事訴訟法第385 條\n    第1 項前段、第85條第2 項，判決如主文。\n中    華    民    國   100    年    3     月    31    日\n                  民事第二庭  法  官    柯月美\n以上正本係照原本作成。\n如對本判決上訴須於判決送達後20日內向本院提出上訴狀。\n如委任律師提起上訴者，應一併繳納上訴審裁判費。\n中    華    民    國   100    年    3     月    31    日\n                              書記官    黃怡禎",
  "structure": {
    "main": "被告應連帶給付原告新臺幣柒拾貳萬貳仟陸佰伍拾伍元，及自民\n國九十九年七月一日起至清償日止，按年息百分之二點六一計算\n之利息，暨自民國九十九年八月二日起至清償日止，其逾期在六\n個月以內者，按上開利率百分之十，逾期超過六個月者，按上開\n利率百分之二十計算之違約金。\n訴訟費用由被告連帶負擔。",
    "fact": "一、被告等合法通知，均未於言詞辯論期日到場，核無民事訴訟\n    法第386 條所列各款情形，爰依原告聲請，由其一造辯論而\n    為判決。\n二、原告起訴主張：被告即借款人劉德椳邀同被告劉邦珍為連帶\n    保證人向原告訂借就學貸款共13筆，金額總計為新臺幣（下\n    同）722,655 元，約定應於借款人該教育階段學業完成或服\n    義務兵役退伍後滿一年之日起分期償還本息，倘借款人不依\n    期償還本息時，除應自遲延日起按約定利率計付遲延利息外\n    ，另按遲延還本付息部份，應付未付本息自應還款之日起，\n    逾期6 （含）個月以內者，按逾期利率百分之10，逾期超過\n    6 個月以上者，就超過部分按逾期利率百分之20加計違約金\n    。詎被告劉德椳自99年8 月1 日起即未依約履行債務，迄今\n    尚欠本金722,655 元及自97年7 月1 日起至清償日止，按年\n    息2.61% 計算之利息，暨自99年8 月2 日起之違約金未還，\n    經原告催討未果，依據借據條款第8 條約定任何一宗不依約\n    清償或攤還本金時，即視為全部到期。另被告劉邦珍既為連\n    帶保證人，對本債務自應負連帶清償責任，為此依消費借貸\n    及連帶保證之法律關係，提起本件訴訟。並聲明：求為判決\n    如主文所示。\n三、被告等均未於言詞辯論期日到場，亦未提出書狀作何聲明或\n    陳述。\n四、法院之判斷：\n（一）按稱消費借貸者，謂當事人一方移轉金錢或其他代替物之\n      所有權於他方，而約定他方以種類、品質、數量相同之物\n      返還之契約，民法第474 條第1 項定有明文；又稱保證者\n      ，謂當事人約定，一方於他方之債務人不履行債務時，由\n      其代負履行責任之契約，亦為同法第739 條所明定；另保\n      證債務之所謂連帶，係指保證人與主債務人負同一債務，\n      對於債權人各負全部給付之責任者而言，此就民法第272\n      條第1 項規定連帶債務之文義參照觀之甚明（最高法院45\n      年台上字第1426號判例參照）；而連帶債務之債權人，依\n      同法第273 條第1 項規定，得對於債務人中之一人或數人\n      或其全體，同時或先後請求全部或一部之給付。\n（二）原告主張之上開事實，業據其提出與所述情節相符之放款\n      借據（就學貸款專用）、就學貸款撥款通知書、就學貸款\n      放出查詢單、就學貸款利率表等為證，核屬相符；被告等\n      對於原告主張之前開事實，均已於相當時期受合法之通知\n      ，而於言詞辯論期日不到場，亦未提出準備書狀爭執，依\n      民事訴訟法第280 條第3 項準用同條第1 項之規定，應視\n      同自認，則原告之主張，自堪信為真實。原告主張被告劉\n      德椳以被告劉邦珍為連帶保證人，向其借款未依約清償，\n      有如前述，則主債務人之被告劉德椳與任連帶保證人之被\n      告劉邦珍自應負同一清償之責。\n五、綜上所述，原告本於消費借貸及連帶保證契約之法律關係，\n    請求被告等應連帶給付722,655 元，及自99年7 月1 日起至\n    清償日止，按年息百分之2.61計算之利息，暨自民國99年8\n    月2 日起至清償日止，其逾期在6 個月以內者，按上開利率\n    百分之10，逾期超過6 個月者，按上開利率百分之20計算之\n    違約金，為有理由，應予准許。\n六、據上論結，本件原告之訴為有理由，依民事訴訟法第385 條\n    第1 項前段、第85條第2 項，判決如主文。",
    "reason": "一、被告等合法通知，均未於言詞辯論期日到場，核無民事訴訟\n    法第386 條所列各款情形，爰依原告聲請，由其一造辯論而\n    為判決。\n二、原告起訴主張：被告即借款人劉德椳邀同被告劉邦珍為連帶\n    保證人向原告訂借就學貸款共13筆，金額總計為新臺幣（下\n    同）722,655 元，約定應於借款人該教育階段學業完成或服\n    義務兵役退伍後滿一年之日起分期償還本息，倘借款人不依\n    期償還本息時，除應自遲延日起按約定利率計付遲延利息外\n    ，另按遲延還本付息部份，應付未付本息自應還款之日起，\n    逾期6 （含）個月以內者，按逾期利率百分之10，逾期超過\n    6 個月以上者，就超過部分按逾期利率百分之20加計違約金\n    。詎被告劉德椳自99年8 月1 日起即未依約履行債務，迄今\n    尚欠本金722,655 元及自97年7 月1 日起至清償日止，按年\n    息2.61% 計算之利息，暨自99年8 月2 日起之違約金未還，\n    經原告催討未果，依據借據條款第8 條約定任何一宗不依約\n    清償或攤還本金時，即視為全部到期。另被告劉邦珍既為連\n    帶保證人，對本債務自應負連帶清償責任，為此依消費借貸\n    及連帶保證之法律關係，提起本件訴訟。並聲明：求為判決\n    如主文所示。\n三、被告等均未於言詞辯論期日到場，亦未提出書狀作何聲明或\n    陳述。\n四、法院之判斷：\n（一）按稱消費借貸者，謂當事人一方移轉金錢或其他代替物之\n      所有權於他方，而約定他方以種類、品質、數量相同之物\n      返還之契約，民法第474 條第1 項定有明文；又稱保證者\n      ，謂當事人約定，一方於他方之債務人不履行債務時，由\n      其代負履行責任之契約，亦為同法第739 條所明定；另保\n      證債務之所謂連帶，係指保證人與主債務人負同一債務，\n      對於債權人各負全部給付之責任者而言，此就民法第272\n      條第1 項規定連帶債務之文義參照觀之甚明（最高法院45\n      年台上字第1426號判例參照）；而連帶債務之債權人，依\n      同法第273 條第1 項規定，得對於債務人中之一人或數人\n      或其全體，同時或先後請求全部或一部之給付。\n（二）原告主張之上開事實，業據其提出與所述情節相符之放款\n      借據（就學貸款專用）、就學貸款撥款通知書、就學貸款\n      放出查詢單、就學貸款利率表等為證，核屬相符；被告等\n      對於原告主張之前開事實，均已於相當時期受合法之通知\n      ，而於言詞辯論期日不到場，亦未提出準備書狀爭執，依\n      民事訴訟法第280 條第3 項準用同條第1 項之規定，應視\n      同自認，則原告之主張，自堪信為真實。原告主張被告劉\n      德椳以被告劉邦珍為連帶保證人，向其借款未依約清償，\n      有如前述，則主債務人之被告劉德椳與任連帶保證人之被\n      告劉邦珍自應負同一清償之責。\n五、綜上所述，原告本於消費借貸及連帶保證契約之法律關係，\n    請求被告等應連帶給付722,655 元，及自99年7 月1 日起至\n    清償日止，按年息百分之2.61計算之利息，暨自民國99年8\n    月2 日起至清償日止，其逾期在6 個月以內者，按上開利率\n    百分之10，逾期超過6 個月者，按上開利率百分之20計算之\n    違約金，為有理由，應予准許。\n六、據上論結，本件原告之訴為有理由，依民事訴訟法第385 條\n    第1 項前段、第85條第2 項，判決如主文。"
  },
  "search": "臺灣嘉義地方法院民事判決100年度訴字第38號原告臺灣銀行股份有限公司法定代理人張明道訴訟代理人黃文明複代理人朱玉仁被告劉德椳劉邦珍上列當事人間請求返還就學貸款事件，本院於民國100年3月24日言詞辯論終結，判決如下：主文被告應連帶給付原告新臺幣柒拾貳萬貳仟陸佰伍拾伍元，及自民國九十九年七月一日起至清償日止，按年息百分之二點六一計算之利息，暨自民國九十九年八月二日起至清償日止，其逾期在六個月以內者，按上開利率百分之十，逾期超過六個月者，按上開利率百分之二十計算之違約金。訴訟費用由被告連帶負擔。事實及理由一、被告等合法通知，均未於言詞辯論期日到場，核無民事訴訟法第386條所列各款情形，爰依原告聲請，由其一造辯論而為判決。二、原告起訴主張：被告即借款人劉德椳邀同被告劉邦珍為連帶保證人向原告訂借就學貸款共13筆，金額總計為新臺幣（下同）722,655元，約定應於借款人該教育階段學業完成或服義務兵役退伍後滿一年之日起分期償還本息，倘借款人不依期償還本息時，除應自遲延日起按約定利率計付遲延利息外，另按遲延還本付息部份，應付未付本息自應還款之日起，逾期6（含）個月以內者，按逾期利率百分之10，逾期超過6個月以上者，就超過部分按逾期利率百分之20加計違約金。詎被告劉德椳自99年8月1日起即未依約履行債務，迄今尚欠本金722,655元及自97年7月1日起至清償日止，按年息2.61%計算之利息，暨自99年8月2日起之違約金未還，經原告催討未果，依據借據條款第8條約定任何一宗不依約清償或攤還本金時，即視為全部到期。另被告劉邦珍既為連帶保證人，對本債務自應負連帶清償責任，為此依消費借貸及連帶保證之法律關係，提起本件訴訟。並聲明：求為判決如主文所示。三、被告等均未於言詞辯論期日到場，亦未提出書狀作何聲明或陳述。四、法院之判斷：（一）按稱消費借貸者，謂當事人一方移轉金錢或其他代替物之所有權於他方，而約定他方以種類、品質、數量相同之物返還之契約，民法第474條第1項定有明文；又稱保證者，謂當事人約定，一方於他方之債務人不履行債務時，由其代負履行責任之契約，亦為同法第739條所明定；另保證債務之所謂連帶，係指保證人與主債務人負同一債務，對於債權人各負全部給付之責任者而言，此就民法第272條第1項規定連帶債務之文義參照觀之甚明（最高法院45年台上字第1426號判例參照）；而連帶債務之債權人，依同法第273條第1項規定，得對於債務人中之一人或數人或其全體，同時或先後請求全部或一部之給付。（二）原告主張之上開事實，業據其提出與所述情節相符之放款借據（就學貸款專用）、就學貸款撥款通知書、就學貸款放出查詢單、就學貸款利率表等為證，核屬相符；被告等對於原告主張之前開事實，均已於相當時期受合法之通知，而於言詞辯論期日不到場，亦未提出準備書狀爭執，依民事訴訟法第280條第3項準用同條第1項之規定，應視同自認，則原告之主張，自堪信為真實。原告主張被告劉德椳以被告劉邦珍為連帶保證人，向其借款未依約清償，有如前述，則主債務人之被告劉德椳與任連帶保證人之被告劉邦珍自應負同一清償之責。五、綜上所述，原告本於消費借貸及連帶保證契約之法律關係，請求被告等應連帶給付722,655元，及自99年7月1日起至清償日止，按年息百分之2.61計算之利息，暨自民國99年8月2日起至清償日止，其逾期在6個月以內者，按上開利率百分之10，逾期超過6個月者，按上開利率百分之20計算之違約金，為有理由，應予准許。六、據上論結，本件原告之訴為有理由，依民事訴訟法第385條第1項前段、第85條第2項，判決如主文。中華民國100年3月31日民事第二庭法官柯月美以上正本係照原本作成。如對本判決上訴須於判決送達後20日內向本院提出上訴狀。如委任律師提起上訴者，應一併繳納上訴審裁判費。中華民國100年3月31日書記官黃怡禎",
  "characters": {
    "judges": [
      "柯月美"
    ],
    "prosecutors": [

    ],
    "lawyers": [
      "如委任"
    ],
    "clerks": [

    ],
    "plaintiffs": [
      "臺灣銀行股份有限公司"
    ],
    "defendants": [
      "劉德椳"
    ],
    "prosecutor_office": [

    ],
    "creditors": [

    ],
    "debtors": [

    ],
    "judicial_associate_officer": [

    ]
  },
  "adjudged_at": "2011-03-31",
  "created_at": "2016-02-13 22:43:57",
  "updated_at": "2016-02-13 22:43:57"
}