{
  "identify": "PCD-100-簡-2253-20110331-1",
  "court": {
    "name": "臺灣新北地方法院",
    "code": "PCD"
  },
  "division": {
    "name": "刑事",
    "code": "M"
  },
  "year": 100,
  "word": "簡",
  "number": "2253",
  "jcheck": "1",
  "reason": "毒品危害防制條例",
  "content": "臺灣板橋地方法院刑事簡易判決       100年度簡字第2253號\n聲  請  人  臺灣板橋地方法院檢察署檢察官\n被      告  賴建成\n上列被告因違反毒品危害防制條例案件，經檢察官聲請以簡易判\n決處刑（100年度毒偵字第1530號），本院判決如下：\n    主      文\n賴建成施用第二級毒品，累犯，處有期徒刑伍月，如易科罰金，\n以新臺幣壹仟元折算壹日。\n    事實及理由\n一、本件犯罪事實及證據，除證據部分應補充：「查被告固否認\n    施用毒品，惟其經警查獲後所採得之尿液檢體，經檢送臺灣\n    檢驗科技股份有限公司以酵素免疫分析法（EIA） 初驗及以\n    氣相層析質譜儀法（GC/MS） 複驗檢驗結果，發現確有安非\n    他命類陽性反應，有該公司出具之濫用藥物檢驗報告、新北\n    市政府警察局中和第二分局毒品案犯罪嫌犯人姓名及代碼對\n    照表1紙存卷可稽。按甲基安非他命經口服投與後約70%於24\n    小時內自尿中排出，約90%於96 小時內自尿中排出，由於甲\n    基安非他命成分之檢出與其投與方式、投與量、個人體質、\n    採集尿液檢體時間與檢測儀器之精密度等諸多因素有關，因\n    此僅憑尿液中呈安非他命陽性反應，並無法確實推算吸食時\n    間距採集時間之長短，惟依上述資料推斷，最長可能不會超\n    過4日，亦經行政院衛生署藥物食品檢驗81 年2月8日（81）\n    藥檢一字第001156號函示明確。被告上開所採尿液送驗結果\n    既有安非他命類陽性反應，顯見被告在經警採尿前之96小時\n    內某時點，確曾有施用第二級甲基安非他命之事實，是被告\n    施用第二級毒品之犯行，洵堪認定。」外，餘均引用附件檢\n    察官聲請簡易判決處刑書之記載。\n二、核被告賴建成所為，係犯毒品危害防制條例第10 條第2項施\n    用第二級毒品罪。其持有第二級毒品甲基安非他命之低度行\n    為，為施用之高度行為所吸收，不另論罪。又被告前有如附\n    件犯罪事實欄所載有期徒刑執畢紀錄，有臺灣高等法院被告\n    前案紀錄表1份在卷可稽，其受有期徒刑之執行完畢後，5年\n    內故意再犯本件有期徒刑以上之罪，為累犯，應依法加重其\n    刑。爰審酌被告前因毒品案件經觀察、勒戒後，猶再犯本案\n    ，顯見其並未戒除毒癮，惟念其施用毒品係自戕身心，對於\n    他人法益尚無具體危害，兼衡其犯罪動機、目的、手段、犯\n    後態度等一切情狀，量處如主文所示之刑，並諭知易科罰金\n    之折算標準，以資懲儆。\n三、依刑事訴訟法第449 條第1項前段、第3項、第454條第2項，\n    毒品危害防制條例第10 條第2項，刑法第11條前段、第47條\n    第1項、第41條第1項前段，逕以簡易判決處刑如主文。\n四、如不服本判決，得自收受送達之翌日起10日內向本院提出上\n    訴狀，上訴於本院第二審合議庭（須附繕本）。\n中    華    民    國   100    年    3     月    31    日\n                      刑事第二十二庭  法  官  徐子涵\n以上正本證明與原本無異。\n                                      書記官  藍淑芬\n中    華    民    國   100    年    3     月    31    日\n附錄本案論罪科刑法條全文：\n毒品危害防制條例第10條\n施用第一級毒品者，處 6 月以上 5 年以下有期徒刑。\n施用第二級毒品者，處 3 年以下有期徒刑。",
  "structure": {
    "main": "賴建成施用第二級毒品，累犯，處有期徒刑伍月，如易科罰金，\n以新臺幣壹仟元折算壹日。",
    "fact": "一、本件犯罪事實及證據，除證據部分應補充：「查被告固否認\n    施用毒品，惟其經警查獲後所採得之尿液檢體，經檢送臺灣\n    檢驗科技股份有限公司以酵素免疫分析法（EIA） 初驗及以\n    氣相層析質譜儀法（GC/MS） 複驗檢驗結果，發現確有安非\n    他命類陽性反應，有該公司出具之濫用藥物檢驗報告、新北\n    市政府警察局中和第二分局毒品案犯罪嫌犯人姓名及代碼對\n    照表1紙存卷可稽。按甲基安非他命經口服投與後約70%於24\n    小時內自尿中排出，約90%於96 小時內自尿中排出，由於甲\n    基安非他命成分之檢出與其投與方式、投與量、個人體質、\n    採集尿液檢體時間與檢測儀器之精密度等諸多因素有關，因\n    此僅憑尿液中呈安非他命陽性反應，並無法確實推算吸食時\n    間距採集時間之長短，惟依上述資料推斷，最長可能不會超\n    過4日，亦經行政院衛生署藥物食品檢驗81 年2月8日（81）\n    藥檢一字第001156號函示明確。被告上開所採尿液送驗結果\n    既有安非他命類陽性反應，顯見被告在經警採尿前之96小時\n    內某時點，確曾有施用第二級甲基安非他命之事實，是被告\n    施用第二級毒品之犯行，洵堪認定。」外，餘均引用附件檢\n    察官聲請簡易判決處刑書之記載。\n二、核被告賴建成所為，係犯毒品危害防制條例第10 條第2項施\n    用第二級毒品罪。其持有第二級毒品甲基安非他命之低度行\n    為，為施用之高度行為所吸收，不另論罪。又被告前有如附\n    件犯罪事實欄所載有期徒刑執畢紀錄，有臺灣高等法院被告\n    前案紀錄表1份在卷可稽，其受有期徒刑之執行完畢後，5年\n    內故意再犯本件有期徒刑以上之罪，為累犯，應依法加重其\n    刑。爰審酌被告前因毒品案件經觀察、勒戒後，猶再犯本案\n    ，顯見其並未戒除毒癮，惟念其施用毒品係自戕身心，對於\n    他人法益尚無具體危害，兼衡其犯罪動機、目的、手段、犯\n    後態度等一切情狀，量處如主文所示之刑，並諭知易科罰金\n    之折算標準，以資懲儆。\n三、依刑事訴訟法第449 條第1項前段、第3項、第454條第2項，\n    毒品危害防制條例第10 條第2項，刑法第11條前段、第47條\n    第1項、第41條第1項前段，逕以簡易判決處刑如主文。\n四、如不服本判決，得自收受送達之翌日起10日內向本院提出上\n    訴狀，上訴於本院第二審合議庭（須附繕本）。",
    "reason": "一、本件犯罪事實及證據，除證據部分應補充：「查被告固否認\n    施用毒品，惟其經警查獲後所採得之尿液檢體，經檢送臺灣\n    檢驗科技股份有限公司以酵素免疫分析法（EIA） 初驗及以\n    氣相層析質譜儀法（GC/MS） 複驗檢驗結果，發現確有安非\n    他命類陽性反應，有該公司出具之濫用藥物檢驗報告、新北\n    市政府警察局中和第二分局毒品案犯罪嫌犯人姓名及代碼對\n    照表1紙存卷可稽。按甲基安非他命經口服投與後約70%於24\n    小時內自尿中排出，約90%於96 小時內自尿中排出，由於甲\n    基安非他命成分之檢出與其投與方式、投與量、個人體質、\n    採集尿液檢體時間與檢測儀器之精密度等諸多因素有關，因\n    此僅憑尿液中呈安非他命陽性反應，並無法確實推算吸食時\n    間距採集時間之長短，惟依上述資料推斷，最長可能不會超\n    過4日，亦經行政院衛生署藥物食品檢驗81 年2月8日（81）\n    藥檢一字第001156號函示明確。被告上開所採尿液送驗結果\n    既有安非他命類陽性反應，顯見被告在經警採尿前之96小時\n    內某時點，確曾有施用第二級甲基安非他命之事實，是被告\n    施用第二級毒品之犯行，洵堪認定。」外，餘均引用附件檢\n    察官聲請簡易判決處刑書之記載。\n二、核被告賴建成所為，係犯毒品危害防制條例第10 條第2項施\n    用第二級毒品罪。其持有第二級毒品甲基安非他命之低度行\n    為，為施用之高度行為所吸收，不另論罪。又被告前有如附\n    件犯罪事實欄所載有期徒刑執畢紀錄，有臺灣高等法院被告\n    前案紀錄表1份在卷可稽，其受有期徒刑之執行完畢後，5年\n    內故意再犯本件有期徒刑以上之罪，為累犯，應依法加重其\n    刑。爰審酌被告前因毒品案件經觀察、勒戒後，猶再犯本案\n    ，顯見其並未戒除毒癮，惟念其施用毒品係自戕身心，對於\n    他人法益尚無具體危害，兼衡其犯罪動機、目的、手段、犯\n    後態度等一切情狀，量處如主文所示之刑，並諭知易科罰金\n    之折算標準，以資懲儆。\n三、依刑事訴訟法第449 條第1項前段、第3項、第454條第2項，\n    毒品危害防制條例第10 條第2項，刑法第11條前段、第47條\n    第1項、第41條第1項前段，逕以簡易判決處刑如主文。\n四、如不服本判決，得自收受送達之翌日起10日內向本院提出上\n    訴狀，上訴於本院第二審合議庭（須附繕本）。"
  },
  "search": "臺灣板橋地方法院刑事簡易判決100年度簡字第2253號聲請人臺灣板橋地方法院檢察署檢察官被告賴建成上列被告因違反毒品危害防制條例案件，經檢察官聲請以簡易判決處刑（100年度毒偵字第1530號），本院判決如下：主文賴建成施用第二級毒品，累犯，處有期徒刑伍月，如易科罰金，以新臺幣壹仟元折算壹日。事實及理由一、本件犯罪事實及證據，除證據部分應補充：「查被告固否認施用毒品，惟其經警查獲後所採得之尿液檢體，經檢送臺灣檢驗科技股份有限公司以酵素免疫分析法（EIA）初驗及以氣相層析質譜儀法（GC/MS）複驗檢驗結果，發現確有安非他命類陽性反應，有該公司出具之濫用藥物檢驗報告、新北市政府警察局中和第二分局毒品案犯罪嫌犯人姓名及代碼對照表1紙存卷可稽。按甲基安非他命經口服投與後約70%於24小時內自尿中排出，約90%於96小時內自尿中排出，由於甲基安非他命成分之檢出與其投與方式、投與量、個人體質、採集尿液檢體時間與檢測儀器之精密度等諸多因素有關，因此僅憑尿液中呈安非他命陽性反應，並無法確實推算吸食時間距採集時間之長短，惟依上述資料推斷，最長可能不會超過4日，亦經行政院衛生署藥物食品檢驗81年2月8日（81）藥檢一字第001156號函示明確。被告上開所採尿液送驗結果既有安非他命類陽性反應，顯見被告在經警採尿前之96小時內某時點，確曾有施用第二級甲基安非他命之事實，是被告施用第二級毒品之犯行，洵堪認定。」外，餘均引用附件檢察官聲請簡易判決處刑書之記載。二、核被告賴建成所為，係犯毒品危害防制條例第10條第2項施用第二級毒品罪。其持有第二級毒品甲基安非他命之低度行為，為施用之高度行為所吸收，不另論罪。又被告前有如附件犯罪事實欄所載有期徒刑執畢紀錄，有臺灣高等法院被告前案紀錄表1份在卷可稽，其受有期徒刑之執行完畢後，5年內故意再犯本件有期徒刑以上之罪，為累犯，應依法加重其刑。爰審酌被告前因毒品案件經觀察、勒戒後，猶再犯本案，顯見其並未戒除毒癮，惟念其施用毒品係自戕身心，對於他人法益尚無具體危害，兼衡其犯罪動機、目的、手段、犯後態度等一切情狀，量處如主文所示之刑，並諭知易科罰金之折算標準，以資懲儆。三、依刑事訴訟法第449條第1項前段、第3項、第454條第2項，毒品危害防制條例第10條第2項，刑法第11條前段、第47條第1項、第41條第1項前段，逕以簡易判決處刑如主文。四、如不服本判決，得自收受送達之翌日起10日內向本院提出上訴狀，上訴於本院第二審合議庭（須附繕本）。中華民國100年3月31日刑事第二十二庭法官徐子涵以上正本證明與原本無異。書記官藍淑芬中華民國100年3月31日附錄本案論罪科刑法條全文：毒品危害防制條例第10條施用第一級毒品者，處6月以上5年以下有期徒刑。施用第二級毒品者，處3年以下有期徒刑。",
  "characters": {
    "judges": [
      "徐子涵"
    ],
    "prosecutors": [

    ],
    "lawyers": [

    ],
    "clerks": [
      "藍淑芬"
    ],
    "plaintiffs": [

    ],
    "defendants": [
      "賴建成"
    ],
    "prosecutor_office": [
      "臺灣板橋地方法院檢察署檢察官"
    ],
    "creditors": [

    ],
    "debtors": [

    ],
    "judicial_associate_officer": [

    ]
  },
  "adjudged_at": "2011-03-31",
  "created_at": "2016-02-13 23:06:44",
  "updated_at": "2016-02-13 23:06:44"
}