{
  "identify": "PTD-99-婚-204-20110331-1",
  "court": {
    "name": "臺灣屏東地方法院",
    "code": "PTD"
  },
  "division": {
    "name": "民事",
    "code": "V"
  },
  "year": 99,
  "word": "婚",
  "number": "204",
  "jcheck": "1",
  "reason": "離婚",
  "content": "臺灣屏東地方法院民事判決               99年度婚字第204號\n原      告  張垂炎\n訴訟代理人  孫智仁律師\n被      告  李碧芬\n上列當事人間請求離婚事件，本院於民國100 年3 月21日言詞辯\n論終結，判決如下：\n    主  文\n准原告與被告離婚。\n訴訟費用由被告負擔。\n    事實及理由\n一、被告經合法通知，未於言詞辯論期日到場，核無民事訴訟法\n    第386 條各款所列情形，爰依原告之聲請，由其一造辯論而\n    為判決。\n二、原告主張：兩造於民國90年9 月17日在大陸地區結婚，婚後\n    原告旋即回臺，之後原告欲洽辦被告來臺團聚事宜，被告旋\n    即不知去向，原告找尋當初婚姻之介紹人，介紹人亦不知去\n    向，被告未曾來臺，雙方分居多年，被告對原告不予聞問，\n    足認其已無維持婚姻之意願，兩造無從繼續保持共同生活之\n    圓滿及幸福，婚姻難以繼續維持，為此爰依民法第1052條第\n    2 項規定訴請離婚，而聲明：如主文第1 項所示。被告則未\n    於言詞辯論期日到場，亦未提出書狀作何陳述或答辯。\n三、原告主張之上開事實，業據其提出戶籍謄本、大陸地區結婚\n    公證書、財團法人海峽交流基會證明影本各1 件為證，並經\n    證人即原告之妹張金葉到庭證述：原告有跟伊提及，是因朋\n    友介紹去大陸辦理結婚，但被告沒有過來臺灣，原告有去找\n    過當初之介紹人但找不到等語明確（本院卷第42頁）。再本\n    院依職權調取被告之入出境資料，查知被告於兩造結婚後並\n    未入境臺灣等情，有內政部入出國及移民署移署出停泰字第\n    0990080934號函附之出入境資料查詢列印程式畫面在卷足憑\n    。本院綜合上開事證，堪信原告之主張為真實。\n四、按夫妻之一方為臺灣地區人民，一方為大陸地區人民者，判\n    決離婚之事由，依臺灣地區之法律，臺灣地區與大陸地區人\n    民關係條例第52條第2 項定有明文。本件原告係臺灣地區人\n    民，被告為大陸地區人民，則原告訴請判決離婚事件，自應\n    適用臺灣地區之法律。另按夫妻之一方，有民法第1052條第\n    1 項以外之重大事由，難以維持婚姻者，夫妻之一方得請求\n    離婚。但其事由應由夫妻之一方負責者，僅他方得請求離婚\n    ，此為民法第1052條第2 項所明定。蓋婚姻以雙方共同生活\n    、相互扶持為目的，並以深摯情感為基礎，如夫妻雙方婚姻\n    生活之感情基礎業已破裂，且客觀上亦難以期待其回復者，\n    即可認有難以維持婚姻之重大事由，而無強求其繼續維持婚\n    姻關係之必要。另婚姻如有難以維持之重大事由，於夫妻雙\n    方就該事由均須負責時，應比較衡量雙方之有責程度，僅責\n    任較輕之一方得向責任較重之他方請求離婚，如雙方之有責\n    程度相同，則雙方均得請求離婚，始符民法第1052條第2 項\n    規定之立法本旨。本件兩造於90年9 月17日在大陸地區結婚\n    後，惟之後被告並未來臺，且失聯迄今，致雙方分居已近10\n    年，夫妻間誠摯互信、相互扶持之情感基礎已然喪失，兩造\n    之婚姻實僅徒具形式而無實質意義，客觀上尚難期冀任何人\n    倘處於同一境況仍能有維持婚姻之意願，系爭婚姻關係明顯\n    已生破綻而無回復之望，故原告主張系爭婚姻有難以維持之\n    重大事由，應屬可採。而究其原因，被告失聯拒絕來臺，致\n    兩造分居多年，夫妻情感日趨淡薄，婚姻破綻難以繼續維持\n    ，被告有責程度自屬較重。從而，原告依民法第1052條第2\n    項規定，請求判決離婚，於法尚無不合，應予准許。\n五、據上論斷，本件原告之訴，為有理由，依民事訴訟法第385\n    條第1 項前段、第78條，判決如主文。\n中    華    民    國   100    年    3     月    31    日\n                        家事庭法  官  趙家光\n以上正本係照原本作成。\n如對本判決上訴，須於判決送達後20日內向本院提出上訴狀並表\n明上訴理由，如於宣示後送達前提出上訴者須於送達後10日內補\n提上訴理由書（須附繕本）。\n如委任律師提起上訴者，應一併繳納上訴審裁判費。\n中    華    民    國  100     年    3     月    31    日\n                              書記官  簡慧瑛",
  "structure": {
    "main": "准原告與被告離婚。\n訴訟費用由被告負擔。",
    "fact": "一、被告經合法通知，未於言詞辯論期日到場，核無民事訴訟法\n    第386 條各款所列情形，爰依原告之聲請，由其一造辯論而\n    為判決。\n二、原告主張：兩造於民國90年9 月17日在大陸地區結婚，婚後\n    原告旋即回臺，之後原告欲洽辦被告來臺團聚事宜，被告旋\n    即不知去向，原告找尋當初婚姻之介紹人，介紹人亦不知去\n    向，被告未曾來臺，雙方分居多年，被告對原告不予聞問，\n    足認其已無維持婚姻之意願，兩造無從繼續保持共同生活之\n    圓滿及幸福，婚姻難以繼續維持，為此爰依民法第1052條第\n    2 項規定訴請離婚，而聲明：如主文第1 項所示。被告則未\n    於言詞辯論期日到場，亦未提出書狀作何陳述或答辯。\n三、原告主張之上開事實，業據其提出戶籍謄本、大陸地區結婚\n    公證書、財團法人海峽交流基會證明影本各1 件為證，並經\n    證人即原告之妹張金葉到庭證述：原告有跟伊提及，是因朋\n    友介紹去大陸辦理結婚，但被告沒有過來臺灣，原告有去找\n    過當初之介紹人但找不到等語明確（本院卷第42頁）。再本\n    院依職權調取被告之入出境資料，查知被告於兩造結婚後並\n    未入境臺灣等情，有內政部入出國及移民署移署出停泰字第\n    0990080934號函附之出入境資料查詢列印程式畫面在卷足憑\n    。本院綜合上開事證，堪信原告之主張為真實。\n四、按夫妻之一方為臺灣地區人民，一方為大陸地區人民者，判\n    決離婚之事由，依臺灣地區之法律，臺灣地區與大陸地區人\n    民關係條例第52條第2 項定有明文。本件原告係臺灣地區人\n    民，被告為大陸地區人民，則原告訴請判決離婚事件，自應\n    適用臺灣地區之法律。另按夫妻之一方，有民法第1052條第\n    1 項以外之重大事由，難以維持婚姻者，夫妻之一方得請求\n    離婚。但其事由應由夫妻之一方負責者，僅他方得請求離婚\n    ，此為民法第1052條第2 項所明定。蓋婚姻以雙方共同生活\n    、相互扶持為目的，並以深摯情感為基礎，如夫妻雙方婚姻\n    生活之感情基礎業已破裂，且客觀上亦難以期待其回復者，\n    即可認有難以維持婚姻之重大事由，而無強求其繼續維持婚\n    姻關係之必要。另婚姻如有難以維持之重大事由，於夫妻雙\n    方就該事由均須負責時，應比較衡量雙方之有責程度，僅責\n    任較輕之一方得向責任較重之他方請求離婚，如雙方之有責\n    程度相同，則雙方均得請求離婚，始符民法第1052條第2 項\n    規定之立法本旨。本件兩造於90年9 月17日在大陸地區結婚\n    後，惟之後被告並未來臺，且失聯迄今，致雙方分居已近10\n    年，夫妻間誠摯互信、相互扶持之情感基礎已然喪失，兩造\n    之婚姻實僅徒具形式而無實質意義，客觀上尚難期冀任何人\n    倘處於同一境況仍能有維持婚姻之意願，系爭婚姻關係明顯\n    已生破綻而無回復之望，故原告主張系爭婚姻有難以維持之\n    重大事由，應屬可採。而究其原因，被告失聯拒絕來臺，致\n    兩造分居多年，夫妻情感日趨淡薄，婚姻破綻難以繼續維持\n    ，被告有責程度自屬較重。從而，原告依民法第1052條第2\n    項規定，請求判決離婚，於法尚無不合，應予准許。\n五、據上論斷，本件原告之訴，為有理由，依民事訴訟法第385\n    條第1 項前段、第78條，判決如主文。",
    "reason": "一、被告經合法通知，未於言詞辯論期日到場，核無民事訴訟法\n    第386 條各款所列情形，爰依原告之聲請，由其一造辯論而\n    為判決。\n二、原告主張：兩造於民國90年9 月17日在大陸地區結婚，婚後\n    原告旋即回臺，之後原告欲洽辦被告來臺團聚事宜，被告旋\n    即不知去向，原告找尋當初婚姻之介紹人，介紹人亦不知去\n    向，被告未曾來臺，雙方分居多年，被告對原告不予聞問，\n    足認其已無維持婚姻之意願，兩造無從繼續保持共同生活之\n    圓滿及幸福，婚姻難以繼續維持，為此爰依民法第1052條第\n    2 項規定訴請離婚，而聲明：如主文第1 項所示。被告則未\n    於言詞辯論期日到場，亦未提出書狀作何陳述或答辯。\n三、原告主張之上開事實，業據其提出戶籍謄本、大陸地區結婚\n    公證書、財團法人海峽交流基會證明影本各1 件為證，並經\n    證人即原告之妹張金葉到庭證述：原告有跟伊提及，是因朋\n    友介紹去大陸辦理結婚，但被告沒有過來臺灣，原告有去找\n    過當初之介紹人但找不到等語明確（本院卷第42頁）。再本\n    院依職權調取被告之入出境資料，查知被告於兩造結婚後並\n    未入境臺灣等情，有內政部入出國及移民署移署出停泰字第\n    0990080934號函附之出入境資料查詢列印程式畫面在卷足憑\n    。本院綜合上開事證，堪信原告之主張為真實。\n四、按夫妻之一方為臺灣地區人民，一方為大陸地區人民者，判\n    決離婚之事由，依臺灣地區之法律，臺灣地區與大陸地區人\n    民關係條例第52條第2 項定有明文。本件原告係臺灣地區人\n    民，被告為大陸地區人民，則原告訴請判決離婚事件，自應\n    適用臺灣地區之法律。另按夫妻之一方，有民法第1052條第\n    1 項以外之重大事由，難以維持婚姻者，夫妻之一方得請求\n    離婚。但其事由應由夫妻之一方負責者，僅他方得請求離婚\n    ，此為民法第1052條第2 項所明定。蓋婚姻以雙方共同生活\n    、相互扶持為目的，並以深摯情感為基礎，如夫妻雙方婚姻\n    生活之感情基礎業已破裂，且客觀上亦難以期待其回復者，\n    即可認有難以維持婚姻之重大事由，而無強求其繼續維持婚\n    姻關係之必要。另婚姻如有難以維持之重大事由，於夫妻雙\n    方就該事由均須負責時，應比較衡量雙方之有責程度，僅責\n    任較輕之一方得向責任較重之他方請求離婚，如雙方之有責\n    程度相同，則雙方均得請求離婚，始符民法第1052條第2 項\n    規定之立法本旨。本件兩造於90年9 月17日在大陸地區結婚\n    後，惟之後被告並未來臺，且失聯迄今，致雙方分居已近10\n    年，夫妻間誠摯互信、相互扶持之情感基礎已然喪失，兩造\n    之婚姻實僅徒具形式而無實質意義，客觀上尚難期冀任何人\n    倘處於同一境況仍能有維持婚姻之意願，系爭婚姻關係明顯\n    已生破綻而無回復之望，故原告主張系爭婚姻有難以維持之\n    重大事由，應屬可採。而究其原因，被告失聯拒絕來臺，致\n    兩造分居多年，夫妻情感日趨淡薄，婚姻破綻難以繼續維持\n    ，被告有責程度自屬較重。從而，原告依民法第1052條第2\n    項規定，請求判決離婚，於法尚無不合，應予准許。\n五、據上論斷，本件原告之訴，為有理由，依民事訴訟法第385\n    條第1 項前段、第78條，判決如主文。"
  },
  "search": "臺灣屏東地方法院民事判決99年度婚字第204號原告張垂炎訴訟代理人孫智仁律師被告李碧芬上列當事人間請求離婚事件，本院於民國100年3月21日言詞辯論終結，判決如下：主文准原告與被告離婚。訴訟費用由被告負擔。事實及理由一、被告經合法通知，未於言詞辯論期日到場，核無民事訴訟法第386條各款所列情形，爰依原告之聲請，由其一造辯論而為判決。二、原告主張：兩造於民國90年9月17日在大陸地區結婚，婚後原告旋即回臺，之後原告欲洽辦被告來臺團聚事宜，被告旋即不知去向，原告找尋當初婚姻之介紹人，介紹人亦不知去向，被告未曾來臺，雙方分居多年，被告對原告不予聞問，足認其已無維持婚姻之意願，兩造無從繼續保持共同生活之圓滿及幸福，婚姻難以繼續維持，為此爰依民法第1052條第2項規定訴請離婚，而聲明：如主文第1項所示。被告則未於言詞辯論期日到場，亦未提出書狀作何陳述或答辯。三、原告主張之上開事實，業據其提出戶籍謄本、大陸地區結婚公證書、財團法人海峽交流基會證明影本各1件為證，並經證人即原告之妹張金葉到庭證述：原告有跟伊提及，是因朋友介紹去大陸辦理結婚，但被告沒有過來臺灣，原告有去找過當初之介紹人但找不到等語明確（本院卷第42頁）。再本院依職權調取被告之入出境資料，查知被告於兩造結婚後並未入境臺灣等情，有內政部入出國及移民署移署出停泰字第0990080934號函附之出入境資料查詢列印程式畫面在卷足憑。本院綜合上開事證，堪信原告之主張為真實。四、按夫妻之一方為臺灣地區人民，一方為大陸地區人民者，判決離婚之事由，依臺灣地區之法律，臺灣地區與大陸地區人民關係條例第52條第2項定有明文。本件原告係臺灣地區人民，被告為大陸地區人民，則原告訴請判決離婚事件，自應適用臺灣地區之法律。另按夫妻之一方，有民法第1052條第1項以外之重大事由，難以維持婚姻者，夫妻之一方得請求離婚。但其事由應由夫妻之一方負責者，僅他方得請求離婚，此為民法第1052條第2項所明定。蓋婚姻以雙方共同生活、相互扶持為目的，並以深摯情感為基礎，如夫妻雙方婚姻生活之感情基礎業已破裂，且客觀上亦難以期待其回復者，即可認有難以維持婚姻之重大事由，而無強求其繼續維持婚姻關係之必要。另婚姻如有難以維持之重大事由，於夫妻雙方就該事由均須負責時，應比較衡量雙方之有責程度，僅責任較輕之一方得向責任較重之他方請求離婚，如雙方之有責程度相同，則雙方均得請求離婚，始符民法第1052條第2項規定之立法本旨。本件兩造於90年9月17日在大陸地區結婚後，惟之後被告並未來臺，且失聯迄今，致雙方分居已近10年，夫妻間誠摯互信、相互扶持之情感基礎已然喪失，兩造之婚姻實僅徒具形式而無實質意義，客觀上尚難期冀任何人倘處於同一境況仍能有維持婚姻之意願，系爭婚姻關係明顯已生破綻而無回復之望，故原告主張系爭婚姻有難以維持之重大事由，應屬可採。而究其原因，被告失聯拒絕來臺，致兩造分居多年，夫妻情感日趨淡薄，婚姻破綻難以繼續維持，被告有責程度自屬較重。從而，原告依民法第1052條第2項規定，請求判決離婚，於法尚無不合，應予准許。五、據上論斷，本件原告之訴，為有理由，依民事訴訟法第385條第1項前段、第78條，判決如主文。中華民國100年3月31日家事庭法官趙家光以上正本係照原本作成。如對本判決上訴，須於判決送達後20日內向本院提出上訴狀並表明上訴理由，如於宣示後送達前提出上訴者須於送達後10日內補提上訴理由書（須附繕本）。如委任律師提起上訴者，應一併繳納上訴審裁判費。中華民國100年3月31日書記官簡慧瑛",
  "characters": {
    "judges": [
      "趙家光"
    ],
    "prosecutors": [

    ],
    "lawyers": [
      "孫智仁",
      "如委任"
    ],
    "clerks": [

    ],
    "plaintiffs": [
      "張垂炎"
    ],
    "defendants": [
      "李碧芬"
    ],
    "prosecutor_office": [

    ],
    "creditors": [

    ],
    "debtors": [

    ],
    "judicial_associate_officer": [

    ]
  },
  "adjudged_at": "2011-03-31",
  "created_at": "2016-02-13 22:44:32",
  "updated_at": "2016-02-13 22:44:32"
}