{
  "identify": "TPD-99-交易-893-20110331-1",
  "court": {
    "name": "臺灣臺北地方法院",
    "code": "TPD"
  },
  "division": {
    "name": "刑事",
    "code": "M"
  },
  "year": 99,
  "word": "交易",
  "number": "893",
  "jcheck": "1",
  "reason": "過失傷害",
  "content": "臺灣臺北地方法院刑事判決             99年度交易字第893號\n公  訴  人  臺灣臺北地方法院檢察署檢察官\n被      告  蕭明\n選任辯護人  陳君沛律師\n上列被告因過失傷害案件，經檢察官聲請簡易判決處刑（99年度\n偵字第21036 號），本院認不宜逕以簡易判決處刑，改依通常程\n序審理，判決如下：\n    主  文\n本件公訴不受理。\n    理  由\n一、公訴意旨略以：被告蕭明於民國99年1 月9 日9 時許，駕\n    駛車號8N-6719 號自小客車，沿臺北縣新店市○○路往中正\n    路方向行駛，本應注意轉彎車應讓直行車先行，且應注意車\n    前狀況，以隨時採取必要之安全措施，而依當時天候、路況\n    等情形亦無不能注意之情事，於左轉進法務部調查局側門時\n    ，竟疏未注意，適有告訴人劉子維騎乘車號DST-922 重型機\n    車、附載其子即被害人劉瀚謙在對向之三民路直行，惟被告\n    仍貿然左轉，致與告訴人劉子維發生碰撞，因而人車倒地，\n    致告訴人劉子維受有左膝挫擦傷、左前臂、腕挫傷以及右腕\n    挫傷之傷害、被害人劉瀚謙受有左側外踝遠端腓骨生板開放\n    性骨折併脛骨遠端內踝生長板骨折、左側脛骨幹中段骨折之\n    傷害。是因認被告涉犯刑法第284 條第1 項前段之過失傷害\n    罪嫌等語。\n二、按告訴乃論之罪，告訴人於第一審辯論終結前得撤回其告訴\n    ，又告訴經撤回者，應諭知不受理之判決，刑事訴訟法第23\n    8 條第1 項、第303 條第3 款分別定有明文。\n三、查本件告訴人告訴被告過失傷害案件，起訴書認係觸犯刑法\n    第284 條第1 項前段之過失傷害罪，依同法第287 條之規定\n    ，須告訴乃論。本案被告因涉犯前揭過失傷害行為，致告訴\n    人劉子維及被害人劉瀚謙受傷，經告訴人劉子維為自己及以\n    法定代理人身分為被害人劉瀚謙獨立提起告訴（見偵卷第11\n    頁），茲因被告與告訴人劉子維業已達成和解，告訴人已於\n    100 年3 月24日具狀撤回告訴（此有刑事聲請狀、告訴人提\n    出之撤回告訴狀在卷可參），依照首開說明，\n    本件爰不經言詞辯論，逕為諭知不受理之判決。\n據上論斷，應依到事訴訟法第452 條、第303 條第3 款、第307\n條，判決如主文。\n中    華    民    國   100    年    3     月    31    日\n                  刑事第十八庭  法  官  陳思帆\n上正本證明與原本無異。\n如不服本判決應於收受送達後10日內向本院提出上訴書狀，並應\n敘述具體理由；其未敘述上訴理由者，應於上訴期間屆滿後20日\n內向本院補提理由書（均須按他造當事人之人數附繕本）「切勿\n逕送上級法院」。告訴人或被害人如對於本判決不服者，應具備\n理由請求檢察官上訴，其上訴期間之計算係以檢察官收受判決正\n本之日期為準。\n                                書記官  林素霜\n中    華    民    國    100   年    4     月     1    日",
  "structure": {
    "main": "本件公訴不受理。",
    "reason": "一、公訴意旨略以：被告蕭明於民國99年1 月9 日9 時許，駕\n    駛車號8N-6719 號自小客車，沿臺北縣新店市○○路往中正\n    路方向行駛，本應注意轉彎車應讓直行車先行，且應注意車\n    前狀況，以隨時採取必要之安全措施，而依當時天候、路況\n    等情形亦無不能注意之情事，於左轉進法務部調查局側門時\n    ，竟疏未注意，適有告訴人劉子維騎乘車號DST-922 重型機\n    車、附載其子即被害人劉瀚謙在對向之三民路直行，惟被告\n    仍貿然左轉，致與告訴人劉子維發生碰撞，因而人車倒地，\n    致告訴人劉子維受有左膝挫擦傷、左前臂、腕挫傷以及右腕\n    挫傷之傷害、被害人劉瀚謙受有左側外踝遠端腓骨生板開放\n    性骨折併脛骨遠端內踝生長板骨折、左側脛骨幹中段骨折之\n    傷害。是因認被告涉犯刑法第284 條第1 項前段之過失傷害\n    罪嫌等語。\n二、按告訴乃論之罪，告訴人於第一審辯論終結前得撤回其告訴\n    ，又告訴經撤回者，應諭知不受理之判決，刑事訴訟法第23\n    8 條第1 項、第303 條第3 款分別定有明文。\n三、查本件告訴人告訴被告過失傷害案件，起訴書認係觸犯刑法\n    第284 條第1 項前段之過失傷害罪，依同法第287 條之規定\n    ，須告訴乃論。本案被告因涉犯前揭過失傷害行為，致告訴\n    人劉子維及被害人劉瀚謙受傷，經告訴人劉子維為自己及以\n    法定代理人身分為被害人劉瀚謙獨立提起告訴（見偵卷第11\n    頁），茲因被告與告訴人劉子維業已達成和解，告訴人已於\n    100 年3 月24日具狀撤回告訴（此有刑事聲請狀、告訴人提\n    出之撤回告訴狀在卷可參），依照首開說明，\n    本件爰不經言詞辯論，逕為諭知不受理之判決。\n據上論斷，應依到事訴訟法第452 條、第303 條第3 款、第307\n條，判決如主文。"
  },
  "search": "臺灣臺北地方法院刑事判決99年度交易字第893號公訴人臺灣臺北地方法院檢察署檢察官被告蕭明選任辯護人陳君沛律師上列被告因過失傷害案件，經檢察官聲請簡易判決處刑（99年度偵字第21036號），本院認不宜逕以簡易判決處刑，改依通常程序審理，判決如下：主文本件公訴不受理。理由一、公訴意旨略以：被告蕭明於民國99年1月9日9時許，駕駛車號8N-6719號自小客車，沿臺北縣新店市○○路往中正路方向行駛，本應注意轉彎車應讓直行車先行，且應注意車前狀況，以隨時採取必要之安全措施，而依當時天候、路況等情形亦無不能注意之情事，於左轉進法務部調查局側門時，竟疏未注意，適有告訴人劉子維騎乘車號DST-922重型機車、附載其子即被害人劉瀚謙在對向之三民路直行，惟被告仍貿然左轉，致與告訴人劉子維發生碰撞，因而人車倒地，致告訴人劉子維受有左膝挫擦傷、左前臂、腕挫傷以及右腕挫傷之傷害、被害人劉瀚謙受有左側外踝遠端腓骨生板開放性骨折併脛骨遠端內踝生長板骨折、左側脛骨幹中段骨折之傷害。是因認被告涉犯刑法第284條第1項前段之過失傷害罪嫌等語。二、按告訴乃論之罪，告訴人於第一審辯論終結前得撤回其告訴，又告訴經撤回者，應諭知不受理之判決，刑事訴訟法第238條第1項、第303條第3款分別定有明文。三、查本件告訴人告訴被告過失傷害案件，起訴書認係觸犯刑法第284條第1項前段之過失傷害罪，依同法第287條之規定，須告訴乃論。本案被告因涉犯前揭過失傷害行為，致告訴人劉子維及被害人劉瀚謙受傷，經告訴人劉子維為自己及以法定代理人身分為被害人劉瀚謙獨立提起告訴（見偵卷第11頁），茲因被告與告訴人劉子維業已達成和解，告訴人已於100年3月24日具狀撤回告訴（此有刑事聲請狀、告訴人提出之撤回告訴狀在卷可參），依照首開說明，本件爰不經言詞辯論，逕為諭知不受理之判決。據上論斷，應依到事訴訟法第452條、第303條第3款、第307條，判決如主文。中華民國100年3月31日刑事第十八庭法官陳思帆上正本證明與原本無異。如不服本判決應於收受送達後10日內向本院提出上訴書狀，並應敘述具體理由；其未敘述上訴理由者，應於上訴期間屆滿後20日內向本院補提理由書（均須按他造當事人之人數附繕本）「切勿逕送上級法院」。告訴人或被害人如對於本判決不服者，應具備理由請求檢察官上訴，其上訴期間之計算係以檢察官收受判決正本之日期為準。書記官林素霜中華民國100年4月1日",
  "characters": {
    "judges": [
      "陳思帆"
    ],
    "prosecutors": [

    ],
    "lawyers": [
      "陳君沛"
    ],
    "clerks": [
      "林素霜"
    ],
    "plaintiffs": [

    ],
    "defendants": [
      "蕭明"
    ],
    "prosecutor_office": [
      "臺灣臺北地方法院檢察署檢察官"
    ],
    "creditors": [

    ],
    "debtors": [

    ],
    "judicial_associate_officer": [

    ]
  },
  "adjudged_at": "2011-03-31",
  "created_at": "2016-02-13 23:13:46",
  "updated_at": "2016-02-13 23:13:46"
}