{
  "identify": "TYD-100-訴緝-4-20110331-1",
  "court": {
    "name": "臺灣桃園地方法院",
    "code": "TYD"
  },
  "division": {
    "name": "刑事",
    "code": "M"
  },
  "year": 100,
  "word": "訴緝",
  "number": "4",
  "jcheck": "1",
  "reason": "偽造有價證券等",
  "content": "臺灣桃園地方法院刑事裁定              100年度訴緝字第4號\n公  訴  人  臺灣桃園地方法院檢察署檢察官\n被      告  賴騰欽\n指定辯護人  邵良正律師\n上列被告因偽造有價證券等案件，經檢察官提起公訴，本院裁定\n如下：\n    主  文\n賴騰欽自民國壹佰年肆月拾伍日起延長羈押貳月。\n    理  由\n一、本件被告賴騰欽因偽造有價證券等案件，經本院認有刑事訴\n    訟法第101 條第1 項第1 款之情形，非予羈押，顯難進行審\n    判或執行，而有羈押必要，於民國100 年1 月15日起執行羈\n    押。\n二、按被告經法官訊問後，認為犯罪嫌疑重大，而有左列情形之\n    一，非予羈押，顯難進行追訴、審判或執行者，得羈押之︰\n    一、逃亡或有事實足認為有逃亡之虞者。刑事訴訟法第101\n    條第1 項第1 款定有明文。經查，本件被告因偽造有價證券\n    等，前經本院訊問後，認被告涉犯刑法第320 條第1 項竊盜\n    罪嫌、第201 條第1 項偽造有價證券罪嫌、第339 條第1 項\n    詐欺取財罪嫌，有證人施慶銘、楊燦忠、劉曾獻代之證述、\n    國泰世華銀行、花蓮區中小企業銀行之函覆、中租迪和股份\n    有限公司之函覆、退票理由單影本4 紙等證據可查，足認犯\n    罪嫌疑重大，被告於偵查及本院審理時均係經通緝始到案，\n    堪認確有逃亡之事實，本院審酌被告所涉犯罪事實對社會侵\n    犯之危害性及國家刑罰權遂行之公益考量，認對被告維持羈\n    押處分係適當、必要，且經司法追訴之國家與社會公益，及\n    被告人身自由之私益兩相利益衡量後，認對被告維持羈押處\n    分尚屬適當、必要，合乎比例原則，茲本院以前項原因依然\n    存在，認有繼續羈押之必要，應自100 年4 月15日起，延長\n    羈押2 月。\n三、依刑事訴訟法第108 條第1 項，裁定如主文。\n中    華    民    國   100    年    3     月    31    日\n                  刑事第七庭審判長  法  官  鄭吉雄\n                                    法  官  蔡羽玄\n                                    法  官  廣于霙\n以上正本證明與原本無異。\n如不服本裁定，應於裁定送達後5 日內向本院提出抗告狀。\n                                    書記官  劉寶霞\n中    華    民    國   100    年    4     月    11    日",
  "structure": {
    "main": "賴騰欽自民國壹佰年肆月拾伍日起延長羈押貳月。",
    "reason": "一、本件被告賴騰欽因偽造有價證券等案件，經本院認有刑事訴\n    訟法第101 條第1 項第1 款之情形，非予羈押，顯難進行審\n    判或執行，而有羈押必要，於民國100 年1 月15日起執行羈\n    押。\n二、按被告經法官訊問後，認為犯罪嫌疑重大，而有左列情形之\n    一，非予羈押，顯難進行追訴、審判或執行者，得羈押之︰\n    一、逃亡或有事實足認為有逃亡之虞者。刑事訴訟法第101\n    條第1 項第1 款定有明文。經查，本件被告因偽造有價證券\n    等，前經本院訊問後，認被告涉犯刑法第320 條第1 項竊盜\n    罪嫌、第201 條第1 項偽造有價證券罪嫌、第339 條第1 項\n    詐欺取財罪嫌，有證人施慶銘、楊燦忠、劉曾獻代之證述、\n    國泰世華銀行、花蓮區中小企業銀行之函覆、中租迪和股份\n    有限公司之函覆、退票理由單影本4 紙等證據可查，足認犯\n    罪嫌疑重大，被告於偵查及本院審理時均係經通緝始到案，\n    堪認確有逃亡之事實，本院審酌被告所涉犯罪事實對社會侵\n    犯之危害性及國家刑罰權遂行之公益考量，認對被告維持羈\n    押處分係適當、必要，且經司法追訴之國家與社會公益，及\n    被告人身自由之私益兩相利益衡量後，認對被告維持羈押處\n    分尚屬適當、必要，合乎比例原則，茲本院以前項原因依然\n    存在，認有繼續羈押之必要，應自100 年4 月15日起，延長\n    羈押2 月。\n三、依刑事訴訟法第108 條第1 項，裁定如主文。"
  },
  "search": "臺灣桃園地方法院刑事裁定100年度訴緝字第4號公訴人臺灣桃園地方法院檢察署檢察官被告賴騰欽指定辯護人邵良正律師上列被告因偽造有價證券等案件，經檢察官提起公訴，本院裁定如下：主文賴騰欽自民國壹佰年肆月拾伍日起延長羈押貳月。理由一、本件被告賴騰欽因偽造有價證券等案件，經本院認有刑事訴訟法第101條第1項第1款之情形，非予羈押，顯難進行審判或執行，而有羈押必要，於民國100年1月15日起執行羈押。二、按被告經法官訊問後，認為犯罪嫌疑重大，而有左列情形之一，非予羈押，顯難進行追訴、審判或執行者，得羈押之︰一、逃亡或有事實足認為有逃亡之虞者。刑事訴訟法第101條第1項第1款定有明文。經查，本件被告因偽造有價證券等，前經本院訊問後，認被告涉犯刑法第320條第1項竊盜罪嫌、第201條第1項偽造有價證券罪嫌、第339條第1項詐欺取財罪嫌，有證人施慶銘、楊燦忠、劉曾獻代之證述、國泰世華銀行、花蓮區中小企業銀行之函覆、中租迪和股份有限公司之函覆、退票理由單影本4紙等證據可查，足認犯罪嫌疑重大，被告於偵查及本院審理時均係經通緝始到案，堪認確有逃亡之事實，本院審酌被告所涉犯罪事實對社會侵犯之危害性及國家刑罰權遂行之公益考量，認對被告維持羈押處分係適當、必要，且經司法追訴之國家與社會公益，及被告人身自由之私益兩相利益衡量後，認對被告維持羈押處分尚屬適當、必要，合乎比例原則，茲本院以前項原因依然存在，認有繼續羈押之必要，應自100年4月15日起，延長羈押2月。三、依刑事訴訟法第108條第1項，裁定如主文。中華民國100年3月31日刑事第七庭審判長法官鄭吉雄法官蔡羽玄法官廣于霙以上正本證明與原本無異。如不服本裁定，應於裁定送達後5日內向本院提出抗告狀。書記官劉寶霞中華民國100年4月11日",
  "characters": {
    "judges": [
      "鄭吉雄",
      "蔡羽玄",
      "廣于霙"
    ],
    "prosecutors": [

    ],
    "lawyers": [
      "邵良正"
    ],
    "clerks": [
      "劉寶霞"
    ],
    "plaintiffs": [

    ],
    "defendants": [
      "賴騰欽"
    ],
    "prosecutor_office": [
      "臺灣桃園地方法院檢察署檢察官"
    ],
    "creditors": [

    ],
    "debtors": [

    ],
    "judicial_associate_officer": [

    ]
  },
  "adjudged_at": "2011-03-31",
  "created_at": "2016-02-13 23:05:55",
  "updated_at": "2016-02-13 23:05:55"
}