{
  "identify": "TND-100-簡-703-20110418-1",
  "court": {
    "name": "臺灣臺南地方法院",
    "code": "TND"
  },
  "division": {
    "name": "刑事",
    "code": "M"
  },
  "year": 100,
  "word": "簡",
  "number": "703",
  "jcheck": "1",
  "reason": "賭博",
  "content": "臺灣臺南地方法院刑事簡易判決          100年度簡字第703號\n聲  請  人  臺灣臺南地方法院檢察署檢察官\n被      告  徐信勇\n上列被告因賭博案件，經檢察官聲請以簡易判決處刑（100年度\n偵字第2970號），本院判決如下：\n    主  文\n徐信勇犯圖利聚眾賭博罪，處有期徒刑肆月，如易科罰金，以新\n臺幣壹仟元折算壹日。扣案之傳真機壹台、六合彩簽單陸張均沒\n收。\n    事實及理由\n一、本件犯罪事實及證據，引用檢察官聲請簡易判決處刑書所載\n    （如附件）。\n二、核被告徐信勇所為，係犯刑法第266條第1項之賭博財物罪、\n    同法第268條之意圖營利，供給賭博場所、聚眾賭博罪。按\n    刑事法若干犯罪行為態樣，本質上原具有反覆、延續實行之\n    特徵，立法時既予特別歸類，定為犯罪構成要件之行為要素\n    ，則行為人基於概括之犯意，在密切接近之一定時、地持續\n    實行之複次行為，倘依社會通念，於客觀上認為符合一個反\n    覆、延續性之行為觀念者，於刑法評價上，即應僅成立一罪\n    ，俾免有重複評價、刑度超過罪責與不法內涵之疑慮；學理\n    上所稱「集合犯」之職業性、營業性或收集性等具有重複特\n    質之犯罪均屬之，例如經營、從事業務、收集、販賣、製造\n    、散布等行為概念者是（最高法院95年度台上字第1079號判\n    決意旨參照）。查被告自民國99年12月間起至100年2月17日\n    為警查獲時止，在臺南市○○區○○路80巷4號住處，多次\n    反覆持續公然賭博暨提供賭博場所及聚眾賭博以牟利，而反\n    覆實行數個同種類行為未曾間斷，是其行為於概念上各應評\n    價為集合犯之包括一罪，而僅論以一罪。被告以一行為同時\n    觸犯上開3罪，為想像競合犯，應依刑法第55條之規定，從\n    一情節較重之意圖營利聚眾賭博罪處斷。爰審酌被告提供場\n    所，經營「六合彩」賭博及公然賭博，敗壞社會風氣，助長\n    僥倖心理，有礙社會善良風俗，影響社會正常經濟活動，兼\n    衡其經營期間為3個月，賭博之金額與獲取之報酬均非高額\n    ，且犯罪後坦承犯行等一切情狀，量處如主文所示之刑，並\n    諭知如易科罰金之折算標準。另扣案之傳真機1台、六合彩\n    簽單6張，為被告所有供其經營六合彩賭博所用之物，業據\n    被告供明在卷（見偵查卷第13頁），爰依刑法第38條第1項\n    第2款規定宣告沒收。\n三、依刑事訴訟法第449條第1項前段、第450條第1項、第454條\n    第2項，刑法第266條第1項前段、第268條、第55條、第41條\n    第1項前段、第38條第1項第2款，刑法施行法第1條之1，逕\n    以簡易判決處刑如主文。\n四、對於本件判決如有不服，應於收受送達10日內，向本院提出\n    上訴書狀。\n中    華    民    國   100    年    4     月    18    日\n                  刑事第二庭  法  官  張銘晃\n以上正本證明與原本無異。\n如不服本判決，應於收受判決正本送達之翌日起10日內，向本庭\n提出上訴狀，上訴於本院合議庭（須附繕本）。\n                              書記官  鄭梅君\n中    華    民    國   100    年    4     月    18    日\n附錄本案論罪科刑法條全文：\n刑法第266條\n在公共場所或公眾得出入之場所賭博財物者，處1千元以下罰金\n。但以供人暫時娛樂之物為賭者，不在此限。\n當場賭博之器具與在賭檯或兌換籌碼處之財物，不問屬於犯人與\n否，沒收之。\n刑法第268條\n意圖營利，供給賭博場所或聚眾賭博者，處3年以下有期徒刑，\n得併科3千元以下罰金。",
  "structure": {
    "main": "徐信勇犯圖利聚眾賭博罪，處有期徒刑肆月，如易科罰金，以新\n臺幣壹仟元折算壹日。扣案之傳真機壹台、六合彩簽單陸張均沒\n收。",
    "fact": "一、本件犯罪事實及證據，引用檢察官聲請簡易判決處刑書所載\n    （如附件）。\n二、核被告徐信勇所為，係犯刑法第266條第1項之賭博財物罪、\n    同法第268條之意圖營利，供給賭博場所、聚眾賭博罪。按\n    刑事法若干犯罪行為態樣，本質上原具有反覆、延續實行之\n    特徵，立法時既予特別歸類，定為犯罪構成要件之行為要素\n    ，則行為人基於概括之犯意，在密切接近之一定時、地持續\n    實行之複次行為，倘依社會通念，於客觀上認為符合一個反\n    覆、延續性之行為觀念者，於刑法評價上，即應僅成立一罪\n    ，俾免有重複評價、刑度超過罪責與不法內涵之疑慮；學理\n    上所稱「集合犯」之職業性、營業性或收集性等具有重複特\n    質之犯罪均屬之，例如經營、從事業務、收集、販賣、製造\n    、散布等行為概念者是（最高法院95年度台上字第1079號判\n    決意旨參照）。查被告自民國99年12月間起至100年2月17日\n    為警查獲時止，在臺南市○○區○○路80巷4號住處，多次\n    反覆持續公然賭博暨提供賭博場所及聚眾賭博以牟利，而反\n    覆實行數個同種類行為未曾間斷，是其行為於概念上各應評\n    價為集合犯之包括一罪，而僅論以一罪。被告以一行為同時\n    觸犯上開3罪，為想像競合犯，應依刑法第55條之規定，從\n    一情節較重之意圖營利聚眾賭博罪處斷。爰審酌被告提供場\n    所，經營「六合彩」賭博及公然賭博，敗壞社會風氣，助長\n    僥倖心理，有礙社會善良風俗，影響社會正常經濟活動，兼\n    衡其經營期間為3個月，賭博之金額與獲取之報酬均非高額\n    ，且犯罪後坦承犯行等一切情狀，量處如主文所示之刑，並\n    諭知如易科罰金之折算標準。另扣案之傳真機1台、六合彩\n    簽單6張，為被告所有供其經營六合彩賭博所用之物，業據\n    被告供明在卷（見偵查卷第13頁），爰依刑法第38條第1項\n    第2款規定宣告沒收。\n三、依刑事訴訟法第449條第1項前段、第450條第1項、第454條\n    第2項，刑法第266條第1項前段、第268條、第55條、第41條\n    第1項前段、第38條第1項第2款，刑法施行法第1條之1，逕\n    以簡易判決處刑如主文。\n四、對於本件判決如有不服，應於收受送達10日內，向本院提出\n    上訴書狀。",
    "reason": "一、本件犯罪事實及證據，引用檢察官聲請簡易判決處刑書所載\n    （如附件）。\n二、核被告徐信勇所為，係犯刑法第266條第1項之賭博財物罪、\n    同法第268條之意圖營利，供給賭博場所、聚眾賭博罪。按\n    刑事法若干犯罪行為態樣，本質上原具有反覆、延續實行之\n    特徵，立法時既予特別歸類，定為犯罪構成要件之行為要素\n    ，則行為人基於概括之犯意，在密切接近之一定時、地持續\n    實行之複次行為，倘依社會通念，於客觀上認為符合一個反\n    覆、延續性之行為觀念者，於刑法評價上，即應僅成立一罪\n    ，俾免有重複評價、刑度超過罪責與不法內涵之疑慮；學理\n    上所稱「集合犯」之職業性、營業性或收集性等具有重複特\n    質之犯罪均屬之，例如經營、從事業務、收集、販賣、製造\n    、散布等行為概念者是（最高法院95年度台上字第1079號判\n    決意旨參照）。查被告自民國99年12月間起至100年2月17日\n    為警查獲時止，在臺南市○○區○○路80巷4號住處，多次\n    反覆持續公然賭博暨提供賭博場所及聚眾賭博以牟利，而反\n    覆實行數個同種類行為未曾間斷，是其行為於概念上各應評\n    價為集合犯之包括一罪，而僅論以一罪。被告以一行為同時\n    觸犯上開3罪，為想像競合犯，應依刑法第55條之規定，從\n    一情節較重之意圖營利聚眾賭博罪處斷。爰審酌被告提供場\n    所，經營「六合彩」賭博及公然賭博，敗壞社會風氣，助長\n    僥倖心理，有礙社會善良風俗，影響社會正常經濟活動，兼\n    衡其經營期間為3個月，賭博之金額與獲取之報酬均非高額\n    ，且犯罪後坦承犯行等一切情狀，量處如主文所示之刑，並\n    諭知如易科罰金之折算標準。另扣案之傳真機1台、六合彩\n    簽單6張，為被告所有供其經營六合彩賭博所用之物，業據\n    被告供明在卷（見偵查卷第13頁），爰依刑法第38條第1項\n    第2款規定宣告沒收。\n三、依刑事訴訟法第449條第1項前段、第450條第1項、第454條\n    第2項，刑法第266條第1項前段、第268條、第55條、第41條\n    第1項前段、第38條第1項第2款，刑法施行法第1條之1，逕\n    以簡易判決處刑如主文。\n四、對於本件判決如有不服，應於收受送達10日內，向本院提出\n    上訴書狀。"
  },
  "search": "臺灣臺南地方法院刑事簡易判決100年度簡字第703號聲請人臺灣臺南地方法院檢察署檢察官被告徐信勇上列被告因賭博案件，經檢察官聲請以簡易判決處刑（100年度偵字第2970號），本院判決如下：主文徐信勇犯圖利聚眾賭博罪，處有期徒刑肆月，如易科罰金，以新臺幣壹仟元折算壹日。扣案之傳真機壹台、六合彩簽單陸張均沒收。事實及理由一、本件犯罪事實及證據，引用檢察官聲請簡易判決處刑書所載（如附件）。二、核被告徐信勇所為，係犯刑法第266條第1項之賭博財物罪、同法第268條之意圖營利，供給賭博場所、聚眾賭博罪。按刑事法若干犯罪行為態樣，本質上原具有反覆、延續實行之特徵，立法時既予特別歸類，定為犯罪構成要件之行為要素，則行為人基於概括之犯意，在密切接近之一定時、地持續實行之複次行為，倘依社會通念，於客觀上認為符合一個反覆、延續性之行為觀念者，於刑法評價上，即應僅成立一罪，俾免有重複評價、刑度超過罪責與不法內涵之疑慮；學理上所稱「集合犯」之職業性、營業性或收集性等具有重複特質之犯罪均屬之，例如經營、從事業務、收集、販賣、製造、散布等行為概念者是（最高法院95年度台上字第1079號判決意旨參照）。查被告自民國99年12月間起至100年2月17日為警查獲時止，在臺南市○○區○○路80巷4號住處，多次反覆持續公然賭博暨提供賭博場所及聚眾賭博以牟利，而反覆實行數個同種類行為未曾間斷，是其行為於概念上各應評價為集合犯之包括一罪，而僅論以一罪。被告以一行為同時觸犯上開3罪，為想像競合犯，應依刑法第55條之規定，從一情節較重之意圖營利聚眾賭博罪處斷。爰審酌被告提供場所，經營「六合彩」賭博及公然賭博，敗壞社會風氣，助長僥倖心理，有礙社會善良風俗，影響社會正常經濟活動，兼衡其經營期間為3個月，賭博之金額與獲取之報酬均非高額，且犯罪後坦承犯行等一切情狀，量處如主文所示之刑，並諭知如易科罰金之折算標準。另扣案之傳真機1台、六合彩簽單6張，為被告所有供其經營六合彩賭博所用之物，業據被告供明在卷（見偵查卷第13頁），爰依刑法第38條第1項第2款規定宣告沒收。三、依刑事訴訟法第449條第1項前段、第450條第1項、第454條第2項，刑法第266條第1項前段、第268條、第55條、第41條第1項前段、第38條第1項第2款，刑法施行法第1條之1，逕以簡易判決處刑如主文。四、對於本件判決如有不服，應於收受送達10日內，向本院提出上訴書狀。中華民國100年4月18日刑事第二庭法官張銘晃以上正本證明與原本無異。如不服本判決，應於收受判決正本送達之翌日起10日內，向本庭提出上訴狀，上訴於本院合議庭（須附繕本）。書記官鄭梅君中華民國100年4月18日附錄本案論罪科刑法條全文：刑法第266條在公共場所或公眾得出入之場所賭博財物者，處1千元以下罰金。但以供人暫時娛樂之物為賭者，不在此限。當場賭博之器具與在賭檯或兌換籌碼處之財物，不問屬於犯人與否，沒收之。刑法第268條意圖營利，供給賭博場所或聚眾賭博者，處3年以下有期徒刑，得併科3千元以下罰金。",
  "characters": {
    "judges": [
      "張銘晃"
    ],
    "prosecutors": [

    ],
    "lawyers": [

    ],
    "clerks": [
      "鄭梅君"
    ],
    "plaintiffs": [

    ],
    "defendants": [
      "徐信勇"
    ],
    "prosecutor_office": [
      "臺灣臺南地方法院檢察署檢察官"
    ],
    "creditors": [

    ],
    "debtors": [

    ],
    "judicial_associate_officer": [

    ]
  },
  "adjudged_at": "2011-04-18",
  "created_at": "2016-02-12 08:51:36",
  "updated_at": "2016-02-12 08:51:36"
}