{
  "identify": "TPD-99-執消債更-27-20110418",
  "court": {
    "name": "臺灣臺北地方法院",
    "code": "TPD"
  },
  "division": {
    "name": "民事",
    "code": "V"
  },
  "year": 99,
  "word": "執消債更",
  "number": "27",
  "jcheck": "",
  "reason": "更生事件",
  "content": "臺灣臺北地方法院民事裁定          99年度執消債更字第27號\n聲  請  人\n即債務人    李依琳\n代  理  人  杜冠民律師\n相  對  人\n即債權人    國泰世華商業銀行股份有限公司\n法定代理人  汪國華\n代  理  人  馮佳慧\n相  對  人\n即債權人    澳商澳盛銀行集團股份有限公司台北分公司\n法定代理人  經天瑞\n相  對  人\n即債權人    渣打國際商業銀行股份有限公司\n法定代理人  曾璟璇\n相  對  人\n即債權人    遠東國際商業銀行股份有限公司\n法定代理人  洪信德\n相  對  人\n即債權人    台北富邦商業銀行股份有限公司\n法定代理人  韓蔚廷\n相  對  人\n即債權人    台新國際商業銀行股份有限公司\n法定代理人  蔡榮棟\n相  對  人\n即債權人    豐（台灣）商業銀行股份有限公司\n法定代理人  李鐘培\n相  對  人\n即債權人    日盛國際商業銀行股份有限公司\n法定代理人  陳棠\n相  對  人\n即債權人    大眾商業銀行股份有限公司\n法定代理人  陳建平\n代  理  人  李如鵑\n相  對  人\n即債權人    聯邦商業銀行股份有限公司\n法定代理人  李憲章\n代  理  人  陳偉介\n上列當事人間聲請消費者債務清理事件，本院於民國100年3月31\n日所為之裁定，應裁定更正如下：\n    主  文\n原裁定之附件一更生方案中第貳欄清償分配表關於編號 1之債權\n人「豐（台灣）商業銀行股份有限公司」之記載，應更正為「\n澳商澳盛銀行集團股份有限公司台北分公司」。\n    理  由\n一、按裁定如有誤寫、誤算或其他類此之顯然錯誤者，法院得依\n    聲請或依職權以裁定更正，此觀民事訴訟法第 239條準用同\n    法第232條第1項前段規定自明。又關於更生或清算之程序，\n    除消費者債務清理條例別有規定外，準用民事訴訟法之規定\n    ，消費者債務清理條例第15條亦定有明文。\n二、查本院前開裁定之附件一更生方案有如主文所示之顯然錯誤\n    ，應予更正。\n三、依首開規定裁定如主文。\n四、如不服本裁定，應於裁定送達後10日內，以書狀向本院司法\n    事務官提出異議。\n中    華    民    國   100    年    4     月    18    日\n                民事執行處司法事務官  林夢雯",
  "structure": {
    "main": "原裁定之附件一更生方案中第貳欄清償分配表關於編號 1之債權\n人「豐（台灣）商業銀行股份有限公司」之記載，應更正為「\n澳商澳盛銀行集團股份有限公司台北分公司」。",
    "reason": "一、按裁定如有誤寫、誤算或其他類此之顯然錯誤者，法院得依\n    聲請或依職權以裁定更正，此觀民事訴訟法第 239條準用同\n    法第232條第1項前段規定自明。又關於更生或清算之程序，\n    除消費者債務清理條例別有規定外，準用民事訴訟法之規定\n    ，消費者債務清理條例第15條亦定有明文。\n二、查本院前開裁定之附件一更生方案有如主文所示之顯然錯誤\n    ，應予更正。\n三、依首開規定裁定如主文。\n四、如不服本裁定，應於裁定送達後10日內，以書狀向本院司法\n    事務官提出異議。"
  },
  "search": "臺灣臺北地方法院民事裁定99年度執消債更字第27號聲請人即債務人李依琳代理人杜冠民律師相對人即債權人國泰世華商業銀行股份有限公司法定代理人汪國華代理人馮佳慧相對人即債權人澳商澳盛銀行集團股份有限公司台北分公司法定代理人經天瑞相對人即債權人渣打國際商業銀行股份有限公司法定代理人曾璟璇相對人即債權人遠東國際商業銀行股份有限公司法定代理人洪信德相對人即債權人台北富邦商業銀行股份有限公司法定代理人韓蔚廷相對人即債權人台新國際商業銀行股份有限公司法定代理人蔡榮棟相對人即債權人豐（台灣）商業銀行股份有限公司法定代理人李鐘培相對人即債權人日盛國際商業銀行股份有限公司法定代理人陳棠相對人即債權人大眾商業銀行股份有限公司法定代理人陳建平代理人李如鵑相對人即債權人聯邦商業銀行股份有限公司法定代理人李憲章代理人陳偉介上列當事人間聲請消費者債務清理事件，本院於民國100年3月31日所為之裁定，應裁定更正如下：主文原裁定之附件一更生方案中第貳欄清償分配表關於編號1之債權人「豐（台灣）商業銀行股份有限公司」之記載，應更正為「澳商澳盛銀行集團股份有限公司台北分公司」。理由一、按裁定如有誤寫、誤算或其他類此之顯然錯誤者，法院得依聲請或依職權以裁定更正，此觀民事訴訟法第239條準用同法第232條第1項前段規定自明。又關於更生或清算之程序，除消費者債務清理條例別有規定外，準用民事訴訟法之規定，消費者債務清理條例第15條亦定有明文。二、查本院前開裁定之附件一更生方案有如主文所示之顯然錯誤，應予更正。三、依首開規定裁定如主文。四、如不服本裁定，應於裁定送達後10日內，以書狀向本院司法事務官提出異議。中華民國100年4月18日民事執行處司法事務官林夢雯",
  "characters": {
    "judges": [

    ],
    "prosecutors": [

    ],
    "lawyers": [
      "杜冠民"
    ],
    "clerks": [

    ],
    "plaintiffs": [

    ],
    "defendants": [

    ],
    "prosecutor_office": [
      "即債務人"
    ],
    "creditors": [
      "國泰世華商業銀行股份有限公司",
      "澳商澳盛銀行集團股份有限公司台北分公司",
      "渣打國際商業銀行股份有限公司",
      "遠東國際商業銀行股份有限公司",
      "台北富邦商業銀行股份有限公司",
      "台新國際商業銀行股份有限公司",
      "日盛國際商業銀行股份有限公司",
      "大眾商業銀行股份有限公司",
      "聯邦商業銀行股份有限公司"
    ],
    "debtors": [

    ],
    "judicial_associate_officer": [
      "林夢雯"
    ]
  },
  "adjudged_at": "2011-04-18",
  "created_at": "2016-02-12 08:45:47",
  "updated_at": "2016-02-12 08:45:47"
}