{
  "identify": "TYD-93-桃簡-1937-20041124-1",
  "court": {
    "name": "臺灣桃園地方法院",
    "code": "TYD"
  },
  "division": {
    "name": "刑事",
    "code": "M"
  },
  "year": 93,
  "word": "桃簡",
  "number": "1937",
  "jcheck": "1",
  "reason": "違反替代役實施條例",
  "content": "臺灣桃園地方法院刑事簡易判決                  九十三年度桃簡字第一九三七號\n    聲  請  人  臺灣桃園地方法院檢察署檢察官\n    被      告  甲○○  男  二.\n右被告因違反替代役實施條例案件，經檢察官聲請簡易判決處刑（九十三年度偵字第\n一六三四八號），本院判決如左：\n    主  文\n甲○○替代役役男擅離職役累計逾七日，處拘役拾日，如易科罰金，以佰元折算\n壹日。\n    事  實\n一、甲○○為依據替代役實施條例服役之替代役役男，並於民國九十三年六月三日入\n    伍受訓一月後，分發至位於桃園縣八德市○○路大湳營區之內政部警政署保安警\n    察第一總隊第六大隊第四中隊服役。詎甲○○休假後，因與女友吵架，竟未依規\n    定於九十三年九月十四日十七時收假回營或辦理請假手續即擅離職役，而於九十\n    三年九月二十一日下午十七時無故曠職，累計已逾七日，經內政部警政署保安警\n    察第一總隊第六大隊發佈離役通報。\n二、案經內政部警政署保安警察第一總隊移送臺灣桃園地方法院檢察署檢察官聲請簡\n    易判決處刑。\n    理  由\n一、左列證據足以證明被告甲○○前揭犯行：\n（一）被告於警訊時、偵查中之自白。\n（二）內政部警政署保安警察第一總隊第六大隊離役通報、被告役籍表、離役時間累\n      計紀錄表。\n二、核被告所為，係犯違反替代役實施條例第五十二條之擅離職役逾七日罪。爰審酌\n    被告之素行、所服替代役本即較一般兵役輕鬆竟仍擅自離役之犯罪動機、手段及\n    所生替代役制度之危害、犯罪後之態度等一切情狀，量處如主文所示之刑，並諭\n    知易科罰金之折算標準，以示懲戒。\n三、依刑事訴訟法第四百四十九條第一項前段、第三項，替代役實施條例第五十二條\n    ，刑法第十一條前段、第四十一條第一項前段，罰金罰鍰提高標準條例第二條，\n    逕以簡易判決處刑如主文。\n四、如不服本件判決，得自收受送達之日起十日內，向本院提起上訴。\n中      華      民      國    九十三    年     十一     月    二十四    日\n                                      臺灣桃園地方法院刑事第一庭\n                                          法  官  曾淑華\n右正本證明與原本無異。\n                                          書記官  林怡君\n中      華      民      國    九十三    年     十一     月    二十四    日\n",
  "structure": {
    "main": "甲○○替代役役男擅離職役累計逾七日，處拘役拾日，如易科罰金，以佰元折算\n壹日。",
    "fact": "一、甲○○為依據替代役實施條例服役之替代役役男，並於民國九十三年六月三日入\n    伍受訓一月後，分發至位於桃園縣八德市○○路大湳營區之內政部警政署保安警\n    察第一總隊第六大隊第四中隊服役。詎甲○○休假後，因與女友吵架，竟未依規\n    定於九十三年九月十四日十七時收假回營或辦理請假手續即擅離職役，而於九十\n    三年九月二十一日下午十七時無故曠職，累計已逾七日，經內政部警政署保安警\n    察第一總隊第六大隊發佈離役通報。\n二、案經內政部警政署保安警察第一總隊移送臺灣桃園地方法院檢察署檢察官聲請簡\n    易判決處刑。",
    "reason": "一、左列證據足以證明被告甲○○前揭犯行：\n（一）被告於警訊時、偵查中之自白。\n（二）內政部警政署保安警察第一總隊第六大隊離役通報、被告役籍表、離役時間累\n      計紀錄表。\n二、核被告所為，係犯違反替代役實施條例第五十二條之擅離職役逾七日罪。爰審酌\n    被告之素行、所服替代役本即較一般兵役輕鬆竟仍擅自離役之犯罪動機、手段及\n    所生替代役制度之危害、犯罪後之態度等一切情狀，量處如主文所示之刑，並諭\n    知易科罰金之折算標準，以示懲戒。\n三、依刑事訴訟法第四百四十九條第一項前段、第三項，替代役實施條例第五十二條\n    ，刑法第十一條前段、第四十一條第一項前段，罰金罰鍰提高標準條例第二條，\n    逕以簡易判決處刑如主文。\n四、如不服本件判決，得自收受送達之日起十日內，向本院提起上訴。\n中      華      民      國    九十三    年     十一     月    二十四    日\n                                      臺灣桃園地方法院刑事第一庭\n                                          法  官  曾淑華\n右正本證明與原本無異。\n                                          書記官  林怡君"
  },
  "search": "臺灣桃園地方法院刑事簡易判決九十三年度桃簡字第一九三七號聲請人臺灣桃園地方法院檢察署檢察官被告甲○○男二.右被告因違反替代役實施條例案件，經檢察官聲請簡易判決處刑（九十三年度偵字第一六三四八號），本院判決如左：主文甲○○替代役役男擅離職役累計逾七日，處拘役拾日，如易科罰金，以佰元折算壹日。事實一、甲○○為依據替代役實施條例服役之替代役役男，並於民國九十三年六月三日入伍受訓一月後，分發至位於桃園縣八德市○○路大湳營區之內政部警政署保安警察第一總隊第六大隊第四中隊服役。詎甲○○休假後，因與女友吵架，竟未依規定於九十三年九月十四日十七時收假回營或辦理請假手續即擅離職役，而於九十三年九月二十一日下午十七時無故曠職，累計已逾七日，經內政部警政署保安警察第一總隊第六大隊發佈離役通報。二、案經內政部警政署保安警察第一總隊移送臺灣桃園地方法院檢察署檢察官聲請簡易判決處刑。理由一、左列證據足以證明被告甲○○前揭犯行：（一）被告於警訊時、偵查中之自白。（二）內政部警政署保安警察第一總隊第六大隊離役通報、被告役籍表、離役時間累計紀錄表。二、核被告所為，係犯違反替代役實施條例第五十二條之擅離職役逾七日罪。爰審酌被告之素行、所服替代役本即較一般兵役輕鬆竟仍擅自離役之犯罪動機、手段及所生替代役制度之危害、犯罪後之態度等一切情狀，量處如主文所示之刑，並諭知易科罰金之折算標準，以示懲戒。三、依刑事訴訟法第四百四十九條第一項前段、第三項，替代役實施條例第五十二條，刑法第十一條前段、第四十一條第一項前段，罰金罰鍰提高標準條例第二條，逕以簡易判決處刑如主文。四、如不服本件判決，得自收受送達之日起十日內，向本院提起上訴。中華民國九十三年十一月二十四日臺灣桃園地方法院刑事第一庭法官曾淑華右正本證明與原本無異。書記官林怡君中華民國九十三年十一月二十四日",
  "characters": {
    "judges": [
      "曾淑華"
    ],
    "prosecutors": [

    ],
    "lawyers": [

    ],
    "clerks": [
      "林怡君"
    ],
    "plaintiffs": [

    ],
    "defendants": [
      "甲○○  男  二.",
      "右被告因違反替代役實施條例案件，經檢察官聲請簡易判決處刑（九十三年度偵字第",
      "一六三四八號），本院判決如左："
    ],
    "prosecutor_office": [
      "臺灣桃園地方法院檢察署檢察官"
    ],
    "creditors": [

    ],
    "debtors": [

    ],
    "judicial_associate_officer": [

    ]
  },
  "adjudged_at": "2004-11-24",
  "created_at": "2016-02-06 04:03:40",
  "updated_at": "2016-02-06 04:03:40"
}