{
  "identify": "TPD-100-簡-3889-20111216-1",
  "court": {
    "name": "臺灣臺北地方法院",
    "code": "TPD"
  },
  "division": {
    "name": "刑事",
    "code": "M"
  },
  "year": 100,
  "word": "簡",
  "number": "3889",
  "jcheck": "1",
  "reason": "竊盜",
  "content": "臺灣臺北地方法院刑事簡易判決         100年度簡字第3889號\n聲  請  人  臺灣臺北地方法院檢察署檢察官\n被      告  徐海明\n上列被告因竊盜案件，經檢察官聲請以簡易判決處刑（100年度\n偵字第15855號），本院判決如下：\n    主  文\n徐海明犯竊盜罪，處拘役伍拾日，如易科罰金，以新臺幣壹仟元\n折算壹日。緩刑年。\n    事實及理由\n一、徐海明於民國100年7月21日晚上11時28分許，行經臺北市○\n    ○區○○街114巷2號前，因見王世輝所有之陸製煨湯爐1只\n    置放在上址門口，無人看管之際，竟竟基於意圖為自己不法\n    所有、損壞他人之物之犯意,徒手將該煨湯爐翻倒致破裂，\n    以此方式毀損該煨湯爐，竊取該湯爐內裝設之鐵架1個，得\n    手後，旋即離去。嗣於同日晚上11時38分許，王世輝發覺後\n    報警處理，經警調閱上址附近監視器錄影畫面後，循線在臺\n    北市○○區○○路91號管理室查獲徐海明，並當場扣得上開\n    鐵架1個（業據王世輝領回）。案經王世輝訴由臺北市政府\n    警察局中正第二分局報請臺灣臺北地方法院檢察署檢察官偵\n    查後，聲請以簡易判決處刑。\n二、上揭犯罪事實，業據被告徐海明坦承不諱，核與證人即告訴\n    人王世輝於警詢中證述之情節相符，並有臺北市政府警察局\n    中正第二分局物品發還領據單、監視器畫面翻拍照片、扣案\n    物品及現場照片附卷可稽。足見被告之自白與事實相符，自\n    可採為認定事實之依據。本件事證明確，被告犯行，洵堪認\n    定，應依法論科。\n三、核被告所為，係犯刑法第320條第1項之竊盜罪、第354條之\n    損壞他人物品罪。被告以一行為，同時觸犯數罪名，為想像\n    競合犯，應依刑法第55條之規定，從一重之竊盜罪處斷。又\n    檢察官聲請簡易判決處刑，雖未載明被告毀損該陸製煨湯爐\n    之部分，惟此部分與前揭竊盜部分具有想像競合犯之裁判上\n    一罪關係，且聲請簡易判決處刑與起訴有同一效力，刑事訴\n    訟法第451條第2項定有明文，故依刑事訴訟法第267條之意\n    旨，自應為聲請簡易判決處刑效力所及，本院自得併予審理\n    。爰審酌被告任意竊取他人財物，侵害他人之財產安全，所\n    為雖有不該，惟考量其犯後坦承犯行，尚知悔悟，且於行竊\n    後不久即被發覺，竊盜所得物品業據告訴人領回，有復已與\n    告訴人達成和解，賠償其所受之損害，已減低犯罪所造之損\n    害，及其犯罪動機、目的及被告之年齡等一切情狀，量處如\n    主文所示之刑，併諭知易科罰金之折算標準。\n四、末查，被告雖曾於71年、73年間，因竊盜、贓物案件，經法\n    院分別判處有期徒刑3月、4月確定，並分別於71年1月7日、\n    74年1月15日執行完畢；復於於95年間，因贓物案件，經本\n    院以96年度簡字第580號判處罰金新臺幣12,000元確定，甫\n    於96年5月18日罰金繳納完畢等情，有臺灣高等法院被告前\n    案紀錄表可按，惟尚不構成累犯，且其於前案所宣告之有期\n    徒刑執行完畢後之5年內，並未曾因故意犯罪受有期徒刑以\n    上刑之宣告，亦有臺灣高等法院被告前案紀錄表在卷可按，\n    而本件所宣告之刑，距其前案有期徒刑執行完畢時已逾10年\n    ；又其於本案警詢、偵查中雖否認主觀上有何竊盜故意，惟\n    對於本件竊取告訴人所有上開鐵架之案發過程，自始均供承\n    明確，復於本院訊問時時，坦承犯行，本件諒係因一時失慮\n    ，致罹刑章。參以，被告犯後業將所竊之物返還告訴人，並\n    與告訴人達成和解，賠償其所受之損害，足認其犯後尚知悔\n    悟，而告訴人亦表明不再追究被告之行為（惟並未具狀撤回\n    告訴），願給予被告改過之機會，有本院100年12月2日筆錄\n    、本院簡易庭民事調解紀錄表附卷可佐，本院認被告經此教\n    訓，應已知警惕，而無再犯之虞。復審酌被告之年齡、教育\n    程度國小畢業、家庭經濟狀況貧寒，平日擔任保全工作，並\n    兼以撿拾回收物為生等一切情狀，其所受之宣告刑，足認以\n    暫不執行為適當，爰依刑法第74條第1項第2款之規定，予以\n    宣告緩刑3年，以啟自新。\n五、據上論斷，依刑事訴訟法第449條第1項、第3項、第450條第\n    1項，刑法第320條第1項、第354條、第55條、第41條第1項\n    前段、第74條第1項第2款，刑法施行法第1條之1，逕以簡易\n    判決處刑如主文。\n六、如不服本判決，得自收受送達之翌日起10日內，向本院提出\n    上訴書狀敘明上訴理由，上訴於本為第二審合議庭（須附繕\n    本）。\n中    華    民    國   100    年    12    月    16    日\n                  刑事第四庭    法  官  李殷君\n以上正本證明與原本無異。\n                                書記官  殷玉芬\n中    華    民    國   100    年    12    月    19    日\n附錄本判決論罪科刑法條全文：\n中華民國刑法第320條\n意圖為自己或第三人不法之所有，而竊取他人之動產者，為竊盜\n罪，處5年以下有期徒刑、拘役或5百元以下罰金。\n意圖為自己或第三人不法之利益，而竊佔他人之不動產者，依前\n項之規定處斷。\n前二項之未遂犯罰之。\n中華民國刑法第354條\n毀棄、損壞前二條以外之他人之物或致令不堪用，足以生損害於\n公眾或他人者，處2年以下有期徒刑、拘役或5百元以下罰金。",
  "structure": {
    "main": "徐海明犯竊盜罪，處拘役伍拾日，如易科罰金，以新臺幣壹仟元\n折算壹日。緩刑年。",
    "fact": "一、徐海明於民國100年7月21日晚上11時28分許，行經臺北市○\n    ○區○○街114巷2號前，因見王世輝所有之陸製煨湯爐1只\n    置放在上址門口，無人看管之際，竟竟基於意圖為自己不法\n    所有、損壞他人之物之犯意,徒手將該煨湯爐翻倒致破裂，\n    以此方式毀損該煨湯爐，竊取該湯爐內裝設之鐵架1個，得\n    手後，旋即離去。嗣於同日晚上11時38分許，王世輝發覺後\n    報警處理，經警調閱上址附近監視器錄影畫面後，循線在臺\n    北市○○區○○路91號管理室查獲徐海明，並當場扣得上開\n    鐵架1個（業據王世輝領回）。案經王世輝訴由臺北市政府\n    警察局中正第二分局報請臺灣臺北地方法院檢察署檢察官偵\n    查後，聲請以簡易判決處刑。\n二、上揭犯罪事實，業據被告徐海明坦承不諱，核與證人即告訴\n    人王世輝於警詢中證述之情節相符，並有臺北市政府警察局\n    中正第二分局物品發還領據單、監視器畫面翻拍照片、扣案\n    物品及現場照片附卷可稽。足見被告之自白與事實相符，自\n    可採為認定事實之依據。本件事證明確，被告犯行，洵堪認\n    定，應依法論科。\n三、核被告所為，係犯刑法第320條第1項之竊盜罪、第354條之\n    損壞他人物品罪。被告以一行為，同時觸犯數罪名，為想像\n    競合犯，應依刑法第55條之規定，從一重之竊盜罪處斷。又\n    檢察官聲請簡易判決處刑，雖未載明被告毀損該陸製煨湯爐\n    之部分，惟此部分與前揭竊盜部分具有想像競合犯之裁判上\n    一罪關係，且聲請簡易判決處刑與起訴有同一效力，刑事訴\n    訟法第451條第2項定有明文，故依刑事訴訟法第267條之意\n    旨，自應為聲請簡易判決處刑效力所及，本院自得併予審理\n    。爰審酌被告任意竊取他人財物，侵害他人之財產安全，所\n    為雖有不該，惟考量其犯後坦承犯行，尚知悔悟，且於行竊\n    後不久即被發覺，竊盜所得物品業據告訴人領回，有復已與\n    告訴人達成和解，賠償其所受之損害，已減低犯罪所造之損\n    害，及其犯罪動機、目的及被告之年齡等一切情狀，量處如\n    主文所示之刑，併諭知易科罰金之折算標準。\n四、末查，被告雖曾於71年、73年間，因竊盜、贓物案件，經法\n    院分別判處有期徒刑3月、4月確定，並分別於71年1月7日、\n    74年1月15日執行完畢；復於於95年間，因贓物案件，經本\n    院以96年度簡字第580號判處罰金新臺幣12,000元確定，甫\n    於96年5月18日罰金繳納完畢等情，有臺灣高等法院被告前\n    案紀錄表可按，惟尚不構成累犯，且其於前案所宣告之有期\n    徒刑執行完畢後之5年內，並未曾因故意犯罪受有期徒刑以\n    上刑之宣告，亦有臺灣高等法院被告前案紀錄表在卷可按，\n    而本件所宣告之刑，距其前案有期徒刑執行完畢時已逾10年\n    ；又其於本案警詢、偵查中雖否認主觀上有何竊盜故意，惟\n    對於本件竊取告訴人所有上開鐵架之案發過程，自始均供承\n    明確，復於本院訊問時時，坦承犯行，本件諒係因一時失慮\n    ，致罹刑章。參以，被告犯後業將所竊之物返還告訴人，並\n    與告訴人達成和解，賠償其所受之損害，足認其犯後尚知悔\n    悟，而告訴人亦表明不再追究被告之行為（惟並未具狀撤回\n    告訴），願給予被告改過之機會，有本院100年12月2日筆錄\n    、本院簡易庭民事調解紀錄表附卷可佐，本院認被告經此教\n    訓，應已知警惕，而無再犯之虞。復審酌被告之年齡、教育\n    程度國小畢業、家庭經濟狀況貧寒，平日擔任保全工作，並\n    兼以撿拾回收物為生等一切情狀，其所受之宣告刑，足認以\n    暫不執行為適當，爰依刑法第74條第1項第2款之規定，予以\n    宣告緩刑3年，以啟自新。\n五、據上論斷，依刑事訴訟法第449條第1項、第3項、第450條第\n    1項，刑法第320條第1項、第354條、第55條、第41條第1項\n    前段、第74條第1項第2款，刑法施行法第1條之1，逕以簡易\n    判決處刑如主文。\n六、如不服本判決，得自收受送達之翌日起10日內，向本院提出\n    上訴書狀敘明上訴理由，上訴於本為第二審合議庭（須附繕\n    本）。",
    "reason": "一、徐海明於民國100年7月21日晚上11時28分許，行經臺北市○\n    ○區○○街114巷2號前，因見王世輝所有之陸製煨湯爐1只\n    置放在上址門口，無人看管之際，竟竟基於意圖為自己不法\n    所有、損壞他人之物之犯意,徒手將該煨湯爐翻倒致破裂，\n    以此方式毀損該煨湯爐，竊取該湯爐內裝設之鐵架1個，得\n    手後，旋即離去。嗣於同日晚上11時38分許，王世輝發覺後\n    報警處理，經警調閱上址附近監視器錄影畫面後，循線在臺\n    北市○○區○○路91號管理室查獲徐海明，並當場扣得上開\n    鐵架1個（業據王世輝領回）。案經王世輝訴由臺北市政府\n    警察局中正第二分局報請臺灣臺北地方法院檢察署檢察官偵\n    查後，聲請以簡易判決處刑。\n二、上揭犯罪事實，業據被告徐海明坦承不諱，核與證人即告訴\n    人王世輝於警詢中證述之情節相符，並有臺北市政府警察局\n    中正第二分局物品發還領據單、監視器畫面翻拍照片、扣案\n    物品及現場照片附卷可稽。足見被告之自白與事實相符，自\n    可採為認定事實之依據。本件事證明確，被告犯行，洵堪認\n    定，應依法論科。\n三、核被告所為，係犯刑法第320條第1項之竊盜罪、第354條之\n    損壞他人物品罪。被告以一行為，同時觸犯數罪名，為想像\n    競合犯，應依刑法第55條之規定，從一重之竊盜罪處斷。又\n    檢察官聲請簡易判決處刑，雖未載明被告毀損該陸製煨湯爐\n    之部分，惟此部分與前揭竊盜部分具有想像競合犯之裁判上\n    一罪關係，且聲請簡易判決處刑與起訴有同一效力，刑事訴\n    訟法第451條第2項定有明文，故依刑事訴訟法第267條之意\n    旨，自應為聲請簡易判決處刑效力所及，本院自得併予審理\n    。爰審酌被告任意竊取他人財物，侵害他人之財產安全，所\n    為雖有不該，惟考量其犯後坦承犯行，尚知悔悟，且於行竊\n    後不久即被發覺，竊盜所得物品業據告訴人領回，有復已與\n    告訴人達成和解，賠償其所受之損害，已減低犯罪所造之損\n    害，及其犯罪動機、目的及被告之年齡等一切情狀，量處如\n    主文所示之刑，併諭知易科罰金之折算標準。\n四、末查，被告雖曾於71年、73年間，因竊盜、贓物案件，經法\n    院分別判處有期徒刑3月、4月確定，並分別於71年1月7日、\n    74年1月15日執行完畢；復於於95年間，因贓物案件，經本\n    院以96年度簡字第580號判處罰金新臺幣12,000元確定，甫\n    於96年5月18日罰金繳納完畢等情，有臺灣高等法院被告前\n    案紀錄表可按，惟尚不構成累犯，且其於前案所宣告之有期\n    徒刑執行完畢後之5年內，並未曾因故意犯罪受有期徒刑以\n    上刑之宣告，亦有臺灣高等法院被告前案紀錄表在卷可按，\n    而本件所宣告之刑，距其前案有期徒刑執行完畢時已逾10年\n    ；又其於本案警詢、偵查中雖否認主觀上有何竊盜故意，惟\n    對於本件竊取告訴人所有上開鐵架之案發過程，自始均供承\n    明確，復於本院訊問時時，坦承犯行，本件諒係因一時失慮\n    ，致罹刑章。參以，被告犯後業將所竊之物返還告訴人，並\n    與告訴人達成和解，賠償其所受之損害，足認其犯後尚知悔\n    悟，而告訴人亦表明不再追究被告之行為（惟並未具狀撤回\n    告訴），願給予被告改過之機會，有本院100年12月2日筆錄\n    、本院簡易庭民事調解紀錄表附卷可佐，本院認被告經此教\n    訓，應已知警惕，而無再犯之虞。復審酌被告之年齡、教育\n    程度國小畢業、家庭經濟狀況貧寒，平日擔任保全工作，並\n    兼以撿拾回收物為生等一切情狀，其所受之宣告刑，足認以\n    暫不執行為適當，爰依刑法第74條第1項第2款之規定，予以\n    宣告緩刑3年，以啟自新。\n五、據上論斷，依刑事訴訟法第449條第1項、第3項、第450條第\n    1項，刑法第320條第1項、第354條、第55條、第41條第1項\n    前段、第74條第1項第2款，刑法施行法第1條之1，逕以簡易\n    判決處刑如主文。\n六、如不服本判決，得自收受送達之翌日起10日內，向本院提出\n    上訴書狀敘明上訴理由，上訴於本為第二審合議庭（須附繕\n    本）。"
  },
  "search": "臺灣臺北地方法院刑事簡易判決100年度簡字第3889號聲請人臺灣臺北地方法院檢察署檢察官被告徐海明上列被告因竊盜案件，經檢察官聲請以簡易判決處刑（100年度偵字第15855號），本院判決如下：主文徐海明犯竊盜罪，處拘役伍拾日，如易科罰金，以新臺幣壹仟元折算壹日。緩刑年。事實及理由一、徐海明於民國100年7月21日晚上11時28分許，行經臺北市○○區○○街114巷2號前，因見王世輝所有之陸製煨湯爐1只置放在上址門口，無人看管之際，竟竟基於意圖為自己不法所有、損壞他人之物之犯意,徒手將該煨湯爐翻倒致破裂，以此方式毀損該煨湯爐，竊取該湯爐內裝設之鐵架1個，得手後，旋即離去。嗣於同日晚上11時38分許，王世輝發覺後報警處理，經警調閱上址附近監視器錄影畫面後，循線在臺北市○○區○○路91號管理室查獲徐海明，並當場扣得上開鐵架1個（業據王世輝領回）。案經王世輝訴由臺北市政府警察局中正第二分局報請臺灣臺北地方法院檢察署檢察官偵查後，聲請以簡易判決處刑。二、上揭犯罪事實，業據被告徐海明坦承不諱，核與證人即告訴人王世輝於警詢中證述之情節相符，並有臺北市政府警察局中正第二分局物品發還領據單、監視器畫面翻拍照片、扣案物品及現場照片附卷可稽。足見被告之自白與事實相符，自可採為認定事實之依據。本件事證明確，被告犯行，洵堪認定，應依法論科。三、核被告所為，係犯刑法第320條第1項之竊盜罪、第354條之損壞他人物品罪。被告以一行為，同時觸犯數罪名，為想像競合犯，應依刑法第55條之規定，從一重之竊盜罪處斷。又檢察官聲請簡易判決處刑，雖未載明被告毀損該陸製煨湯爐之部分，惟此部分與前揭竊盜部分具有想像競合犯之裁判上一罪關係，且聲請簡易判決處刑與起訴有同一效力，刑事訴訟法第451條第2項定有明文，故依刑事訴訟法第267條之意旨，自應為聲請簡易判決處刑效力所及，本院自得併予審理。爰審酌被告任意竊取他人財物，侵害他人之財產安全，所為雖有不該，惟考量其犯後坦承犯行，尚知悔悟，且於行竊後不久即被發覺，竊盜所得物品業據告訴人領回，有復已與告訴人達成和解，賠償其所受之損害，已減低犯罪所造之損害，及其犯罪動機、目的及被告之年齡等一切情狀，量處如主文所示之刑，併諭知易科罰金之折算標準。四、末查，被告雖曾於71年、73年間，因竊盜、贓物案件，經法院分別判處有期徒刑3月、4月確定，並分別於71年1月7日、74年1月15日執行完畢；復於於95年間，因贓物案件，經本院以96年度簡字第580號判處罰金新臺幣12,000元確定，甫於96年5月18日罰金繳納完畢等情，有臺灣高等法院被告前案紀錄表可按，惟尚不構成累犯，且其於前案所宣告之有期徒刑執行完畢後之5年內，並未曾因故意犯罪受有期徒刑以上刑之宣告，亦有臺灣高等法院被告前案紀錄表在卷可按，而本件所宣告之刑，距其前案有期徒刑執行完畢時已逾10年；又其於本案警詢、偵查中雖否認主觀上有何竊盜故意，惟對於本件竊取告訴人所有上開鐵架之案發過程，自始均供承明確，復於本院訊問時時，坦承犯行，本件諒係因一時失慮，致罹刑章。參以，被告犯後業將所竊之物返還告訴人，並與告訴人達成和解，賠償其所受之損害，足認其犯後尚知悔悟，而告訴人亦表明不再追究被告之行為（惟並未具狀撤回告訴），願給予被告改過之機會，有本院100年12月2日筆錄、本院簡易庭民事調解紀錄表附卷可佐，本院認被告經此教訓，應已知警惕，而無再犯之虞。復審酌被告之年齡、教育程度國小畢業、家庭經濟狀況貧寒，平日擔任保全工作，並兼以撿拾回收物為生等一切情狀，其所受之宣告刑，足認以暫不執行為適當，爰依刑法第74條第1項第2款之規定，予以宣告緩刑3年，以啟自新。五、據上論斷，依刑事訴訟法第449條第1項、第3項、第450條第1項，刑法第320條第1項、第354條、第55條、第41條第1項前段、第74條第1項第2款，刑法施行法第1條之1，逕以簡易判決處刑如主文。六、如不服本判決，得自收受送達之翌日起10日內，向本院提出上訴書狀敘明上訴理由，上訴於本為第二審合議庭（須附繕本）。中華民國100年12月16日刑事第四庭法官李殷君以上正本證明與原本無異。書記官殷玉芬中華民國100年12月19日附錄本判決論罪科刑法條全文：中華民國刑法第320條意圖為自己或第三人不法之所有，而竊取他人之動產者，為竊盜罪，處5年以下有期徒刑、拘役或5百元以下罰金。意圖為自己或第三人不法之利益，而竊佔他人之不動產者，依前項之規定處斷。前二項之未遂犯罰之。中華民國刑法第354條毀棄、損壞前二條以外之他人之物或致令不堪用，足以生損害於公眾或他人者，處2年以下有期徒刑、拘役或5百元以下罰金。",
  "characters": {
    "judges": [
      "李殷君"
    ],
    "prosecutors": [

    ],
    "lawyers": [

    ],
    "clerks": [
      "殷玉芬"
    ],
    "plaintiffs": [

    ],
    "defendants": [
      "徐海明"
    ],
    "prosecutor_office": [
      "臺灣臺北地方法院檢察署檢察官"
    ],
    "creditors": [

    ],
    "debtors": [

    ],
    "judicial_associate_officer": [

    ]
  },
  "adjudged_at": "2011-12-16",
  "created_at": "2016-02-13 10:18:02",
  "updated_at": "2016-02-13 10:18:02"
}