{
  "identify": "TPH-99-上易-2497-20110112-1",
  "court": {
    "name": "臺灣高等法院",
    "code": "TPH"
  },
  "division": {
    "name": "刑事",
    "code": "M"
  },
  "year": 99,
  "word": "上易",
  "number": "2497",
  "jcheck": "1",
  "reason": "詐欺",
  "content": "臺灣高等法院刑事判決                99年度上易字第2497號\n上  訴  人\n即  被  告  沈聰志\n上列上訴人因詐欺案件，不服臺灣臺北地方法院99年度易字第15\n83號，中華民國99年9月30日第一審判決（起訴案號：臺灣臺北\n地方法院檢察署99年度偵緝字第838號、第839號），提起上訴，\n本院判決如下：\n    主  文\n上訴駁回。\n沈聰志緩刑參年。\n    事    實\n一、沈聰志在得預見將其金融機構開立帳戶之提款卡及密碼持交\n    不相識之人使用，其帳戶有遭人利用作為詐騙工具可能之情\n    形下，仍基於幫助詐欺取財之犯意，於民國九十八年九月十\n    九日前之九十九年間某日某時許，在臺北縣三重市○○路○\n    段七八號天台廣場之合作金庫前，將其前於九十三年四月二\n    十日至臺北市○○區○○路一二七號之華南商業銀行股份有\n    限公司（下稱華南銀行）雙園分行所申請開立，帳號000\n    000000000號帳戶之提款卡及密碼，以不詳代價，\n    持交予姓名、年籍均不詳之成年人使用。俟該姓名、年籍均\n    不詳之成年人所屬之犯罪集團取得沈聰志所交付之上開帳戶\n    提款卡及密碼後，即基於詐欺取財之犯意，分別於如附表所\n    示詐騙時間、以如附表所示之詐騙手法，詐騙如附表所示被\n    害人，致如附表所示被害人均因此陷於錯誤，轉帳匯款如附\n    表所示金額至沈聰志上開華南銀行雙園分行帳戶中。嗣經如\n    附表所示被害人在依指示操作後，察覺帳戶存款業遭轉出短\n    少，始知受騙，報警處理循線查獲沈聰志。\n二、案經如附表所示被害人分別報請臺中縣政府警察局太平分局\n    及高雄縣政府警察局湖內分局轉至臺北縣政府警察局新莊分\n    局移送臺灣板橋地方法院檢察署檢察官偵查後，簽請臺灣高\n    等法院檢察署准予移轉臺灣臺北地方法院檢察署檢察官偵查\n    起訴。\n    理    由\n一、訊據上訴人即被告沈聰志固坦承有至華南銀行雙園分行開立\n    上開帳戶之事實，然矢口否認涉有上開犯行，辯稱：其上開\n    帳戶提款卡及密碼資料，係其在應徵阿秋檳榔之司機時遭人\n    詐騙，並未持交他人使用云云。經查：\n  (一)上開華南銀行雙園分行帳戶係被告於九十三年四月二十日，\n    間親自前往開立，嗣遭真實姓名、年籍不詳之成年人用以作\n    為詐騙如附表所示被害人轉帳匯款之人頭帳戶使用之事實，\n    業經被告於警詢、偵查及原審審理時坦認在卷，並經如附表\n    編號一所示被害人即證人李佳真於警詢時證述：「我於九十\n    八年九月十九日十四時十七分左右，接獲自稱為ＰＣＨＯＭ\n    Ｅ的電話，謊稱被害人日前於網路購物，因作業上疏失，導\n    致每個月將會扣除固定款項至約定帳戶，要求被害人立即前\n    往ＡＴＭ解除設定‧‧‧」、「我與歹徒共電話二次，第一\n    次歹徒是在九十八年九月十九日十四時十七分左右，用電話\n    與我聯絡，詢問我是有網路購物，並確認我網路購物的明細\n    ，會有一單位與我聯絡扣款是否要取消，隨即掛斷電話。」\n    、「歹徒第二次是在九十八年九月十九日二十時五分，用電\n    話聯絡‧‧‧自稱一名郵局員工向我說，他們是幫ＰＣＨＯ\n    ＭＥ執行扣款，他們接到通知說我要扣款，要我到ＡＴＭ操\n    作取消扣款‧‧‧」、「‧‧‧第五筆及第六筆分別在九十\n    八年九月十九日二十一時四十二分及二十二時二十九分，在\n    台中縣大里市○○路二八二號玉山銀行大里分行轉帳至華南\n    商業銀行雙園分行，帳號為00000000000000\n    00，分別轉入新臺幣二二０二三元及新臺幣二二五五二元\n    。」等語（臺灣臺北地方法院檢察署九十九年度偵字第二七\n    五五九號卷第九頁、第十頁）；以及如附表編號二所示被害\n    人即證人謝茂隆於警詢時證述：「我是於九十八年九月十九\n    日晚上二十一時四十八分許在高雄縣阿蓮鄉○○路一九四號\n    在家接到一通‧‧‧詐騙電話而至阿蓮郵局前提款機匯款而\n    遭詐騙。」、「‧‧‧對方女子謊稱之前在網路購物，稱當\n    初所購買的貨物已付清並聲稱當初會計登錄錯誤，誤登為分\n    期付款為十二期，並問我要不要取消，我就向他說取消，他\n    並說要代我向台新銀行講並說台新銀行會與我聯絡，後來就\n    有一位男子自稱是台新銀行的人員，要我拿台新銀行的金融\n    卡至郵局提款機查詢餘額後向對方說餘額還有多少，對方就\n    叫我將金融卡插入提款機並依對方指示操作轉帳，共轉出金\n    額二九九八八元，對方就詢問我轉入的帳號是多少，我就跟\n    他說是0000000000000000‧‧‧」等語綦\n    詳（臺灣臺北地方法院檢察署九十九年度偵字第二七五五九\n    號卷第二三頁、第二四頁）。並有華南銀行雙園分行九十八\n    年十月十三日華雙存字第０九八００四０三號函暨函覆之被\n    告上開帳戶開戶資料及存款往來明細暨對帳單各一份（臺灣\n    板橋地方法院檢察署九十九年度偵字第二六五三號卷第二二\n    頁至第二四頁）、如附表編號一所示被害人即證人李佳真之\n    台中縣警察局霧峰分局國光派出所受理詐騙帳戶通報警示簡\n    便格式表、受理刑事案件報案三聯單、金融機構聯防機制通\n    報單、內政部警政署反詐騙案件紀錄表各一份、玉山銀行自\n    動櫃員機轉帳交易明細表二份（臺灣臺北地方法院檢察署九\n    十九年度偵字第二七五五九號卷第一一頁、第一五頁、第一\n    八頁、第二０頁、第二一頁）；如附表編號二所示被害人即\n    證人謝茂隆之高雄縣政府警察局湖內分局阿蓮分駐所受理各\n    類案件紀錄表、受理詐騙帳戶通報警示簡便格式表、受理刑\n    事案件報案三聯單、內政部警政署反詐騙案件紀錄表、金融\n    機構協助受詐騙民眾通知疑似警示帳戶通報單、郵局自動櫃\n    員機交易明細表各一份（臺灣臺北地方法院檢察署九十九年\n    度偵字第二七五五九號卷第二二頁、第二六頁至第三０頁）\n    在卷可稽，此部分之事實，已堪認定。\n  (二)至被告對於其上開華南銀行雙園分行帳戶提款卡及密碼，何\n    以落入詐騙集團成員手中，遭人用作詐騙證人李佳真、謝茂\n    隆轉帳匯款人頭帳戶使用之緣由，固一再辯稱：係應徵工作\n    遭人詐騙所致云云。然核諸被告對於其循報載徵人廣告應徵\n    工作，致將其上開華南銀行雙園分行帳戶提款卡及密碼持交\n    對方之過程，除供稱：係應徵阿秋檳榔之司機云云外，對於\n    日後所欲任職之該家公司行號或個人獨資商號之正確全銜、\n    公司地址、工作地點、前來拿取其上開華南銀行雙園分行帳\n    戶提款卡及密碼者之真實姓名、年籍資料及在公司之職稱等\n    細節，均無所悉，亦經被告於原審審理時供述不諱（原審卷\n    第二七頁），此均與一般求職者應徵時均係前往公司所在地\n    ，由公司主管進行面試，洽談日後工作時間、地址、待遇，\n    待確定錄取正式上班後，始須提供個人帳戶資料供公司薪資\n    轉帳之常情相悖。再者，被告於原審準備程序中及審理時，\n    辯稱：其在交付帳戶提款卡及密碼後，翌日中午仍未接獲上\n    班通知，察覺遭詐騙後，隨即去電華南銀行詢問，因華南銀\n    行行員答稱該帳戶業已結清，遂將該帳戶存摺丟棄，未報警\n    處理云云（見原審卷第一一頁反面、第二七頁），亦顯與常\n    情有違。況以被告已逾五十歲，在本件案發前，曾陸續從事\n    果菜批發、房地產及計程車駕駛等工作，其先前應徵房地產\n    工作時，該公司並未要求須提供存摺、提款卡及密碼等資料\n    ，具有相當之社會歷練及工作經驗，豈有在明知個人提款卡\n    、密碼等資料係攸關個人金融信用之重要資料，且事前既不\n    知公司所在地點、名稱等基本資料，又對該名前來拿取其上\n    開華南銀行雙園分行帳戶提款卡及密碼者之來歷背景及職稱\n    ，毫無所悉之情形下，輕易聽信在接獲錄取通知正式上班前\n    ，即須先行持交提款卡及密碼供薪資轉帳之謬論之理。\n  (三)再者，自被告上開華南銀行雙園分行帳戶，自開戶後，迄於\n    其在上開時、地持交帳戶提款卡及密碼予真實姓名、年籍均\n    不詳之成年人之前，業已甚少使用該帳戶一節，亦經被告於\n    偵查中坦認在卷（九十九年度偵緝字第八三八號卷第二五頁\n    ），以及依上開華南銀行存款往來明細表暨對帳單所示（臺\n    灣板橋地方法院檢察署九十九年度偵字第二六五三號卷第二\n    四頁），被告上開華南銀行雙園分行帳戶，在如附表編號一\n    所示之被害人即證人李佳真遭詐騙轉帳匯入第一筆新臺幣（\n    下同）二萬二千零二十三元後之帳戶餘額為二萬二千零三十\n    一元，可徵被告將該帳戶提款卡及密碼持交真實姓名、年籍\n    均不詳之成年人之前之帳戶餘額僅有八元等情觀之，足認被\n    告上開華南銀行雙園分行帳戶提款卡及密碼，在其將之持交\n    真實姓名、年籍均不詳之成年人使用前，對被告而言，顯非\n    與其日常金融交易息息相關之經常使用性帳戶，而係一閒置\n    帳戶，此與一般出售或或出租帳戶存摺、提款卡及密碼等資\n    料，均係以新開立帳戶，或業已開立惟已閒置無用之帳戶持\n    交他人作為轉帳匯款人頭帳戶使用者之行為模式，並無二致\n    。總此，堪認被告上開所辯，均係事後卸責之詞，不足採信\n    。被告上開華南銀行雙園分行之提款卡及密碼，顯係被告以\n    不詳代價將之提供真實姓名、年籍均不詳之成年人使用，致\n    遭詐騙集團成員用作詐騙證人李佳真、謝茂隆之人頭帳戶使\n    用甚明。\n  (四)按一般國人向金融機構開設帳戶，並無任何法令限制，若係\n    用於正當用途者，當可光明正大自行申請使用，而帳戶係為\n    存提款及轉帳匯款之用，倘刻意收集他人帳戶使用者，依一\n    般常識極易判斷係為藉此躲避遭人循線追查之目的而為，自\n    可產生與不法犯罪目的相關之合理懷疑。而見諸各大平面及\n    電子媒體報導，或以中獎、退稅、信用卡款對帳、提款卡密\n    碼外洩，疑似遭人盜領存款或家人遭綁架等事由，利用人頭\n    帳戶作為轉帳帳戶，謊騙被害人至金融機構櫃檯電匯，抑或\n    持提款卡至自動櫃員機依其指示操作，使被害人在不知情之\n    狀況下依指示操作匯出款項後，隨即將之提領一空之詐騙手\n    法，層出不窮，以被告係一智慮成熟並具相當社會經驗之成\n    年人而言，對此一犯罪型態，自難諉為不知。況帳戶存摺、\n    印章、提款卡及密碼條等，均係關乎個人金融信用及隱私之\n    重要物件之一，縱親如父母子女或夫妻，衡常若非出於特殊\n    事由或目的，即無任意將之交由他方保管或使用，遑論係為\n    獲取相當對價而將之出租或售予不相熟識之第三人使用。職\n    是，被告在與向其收受上開華南銀行雙園分行帳戶提款卡及\n    密碼之真實姓名、年籍均不詳之成年男子素不相識，且不知\n    該人來歷是否正當之情形下，出於獲取不詳代價之目的，將\n    上開帳戶提款卡及密碼提供該成年男子使用時，其對於上開\n    帳戶可能遭人用以上開手段詐騙他人轉帳匯款之人頭帳戶使\n    用，當無不能預見之可能。被告在此預見及認知下，仍將其\n    上開帳戶提款卡、密碼持交該真實姓名、年籍均不詳之成年\n    人使用，容任詐欺取財結果之發生，其主觀上顯有幫助他人\n    遂行詐欺取財之不確定故意甚明。從而，被告上開幫助詐欺\n    取財犯行，洵堪認定，本件事證明確，應予依法論處。\n二、核被告所為，係幫助犯刑法第三百三十九條第一項之詐欺取\n    財罪。其幫助他人犯罪，為幫助犯，應依刑法第三十條第二\n    項規定，按正犯之刑減輕之。被告以一行為，幫助他人詐騙\n    如附表所示被害人，侵害數法益，為想像競合犯，應依刑法\n    第五十五條規定，從一重處斷。\n三、原審以被告罪證明確，而適用刑法第三十條、第三百三十九\n    條第一項、第四十一條第一項前段、第五十五條，刑法施行\n    法第一條之一，並審酌被告犯罪之動機、目的、手段，將其\n    上開華南銀行雙園分行帳戶提款卡及密碼提供他人使用，致\n    如附表編號一、二所示之被害人即證人李佳真、謝茂隆分別\n    遭詐騙轉帳匯款如附表所示之金額至被告上開華南銀行雙園\n    分行帳戶中，旋即遭提領一空，危害社會經濟秩序、雖非實\n    際遂行詐欺犯行之人，然犯後飾詞狡辯，在法院行準備程序\n    後，具狀表明欲與被害人和解之意，要求法院傳喚被害人到\n    庭，俾與被害人洽談和解事宜，此有陳報狀一份在卷可稽，\n    俟被害人即證人謝茂榮自高雄縣阿蓮鄉遠道北上至法院開庭\n    時，又翻異前詞，稱僅願賠償被害人前來開庭之損失即一千\n    元，不知悔改之態度等一切情狀，量處有期徒刑四月，並諭\n    知易科罰金之折算標準。\n四、經核原判決上開認事用法，洵無違誤，量刑亦屬妥適。被告\n    上訴意旨以並沒有賣帳戶給詐欺集團，是去應徵工作，他說\n    要我的帳號作為徵信與薪資轉帳，所以才提供帳戶給他們等\n    語。惟查：個人之帳戶存摺、印章、提款卡及密碼條等，均\n    係關乎個人金融信用及隱私之重要物件之一，衡情若非出於\n    特殊事由或目的，即無任意將之交由他人保管或使用，遑論\n    係為獲取相當對價而將之出租或售予不相熟識之第三人使用\n    。本件被告已逾五十歲，在本件案發前，曾陸續從事果菜批\n    發、房地產及計程車駕駛等工作，被告亦坦承其先前應徵房\n    地產工作時，該公司並未要求須提供存摺、提款卡及密碼等\n    資料，被告既為一智慮成熟並具相當社會歷練及工作經驗之\n    人，在與向其收受上開華南銀行雙園分行帳戶提款卡及密碼\n    之真實姓名、年籍均不詳之成年男子素不相識，且不知該人\n    來歷是否正當之情形下，出於獲取不詳代價之目的，將上開\n    帳戶提款卡及密碼提供該成年男子使用時，其對於上開帳戶\n    可能遭人用以上開手段詐騙他人轉帳匯款之人頭帳戶使用，\n    當無不能預見之可能；且被告於原審審理時亦坦承當時心想\n    被騙的話最多也只是去華南銀行把帳戶取消等語（見原審卷\n    第11頁反面），被告在此預見及認知下，仍將其上開帳戶提\n    款卡、密碼持交該真實姓名、年籍均不詳之成年人使用，且\n    在交付帳號之隔天因聯絡不上面試之人，而去電華南銀行查\n    詢所交付帳戶之現況，在得知有他人結清、註銷自己所有之\n    上開帳戶後，卻未報警處理，顯亦有違常情，被告容任詐欺\n    取財結果之發生，其主觀上顯有幫助他人遂行詐欺取財之不\n    確定故意甚明。而按證據之取捨與證據之證明力如何，均屬\n    事實審法院得自由裁量、判斷之職權，茍其此項裁量、判斷\n    ，並不悖乎通常一般人日常生活經驗之定則或論理法則，又\n    於判決內論敘其何以作此判斷之心證理由者，即不得任意指\n    摘其為違法。茲原判決已詳敘就卷內證據調查之結果，而為\n    綜合判斷、取捨，認被告確有如事實欄所載之犯行，其得心\n    證的理由已說明甚詳，且所為論斷從形式上觀察，亦難認有\n    違背經驗法則、論理法則，或有其他違背法令之情形，自不\n    容任意指為違法，被告提起上訴仍對原審取捨證據及判斷其\n    證明力職權之適法行使，砌詞指摘原判決不當而否認犯行，\n    自屬卸責之詞，委無可採。\n五、末查被告前未曾因故意犯罪受有期徒刑以上刑之宣告，有本\n    院被告前案紀錄表在卷可查，本院以被告因一時失慮致犯刑\n    章，惟幫助詐取之金額非鉅，犯罪情節尚非重大，且犯後業\n    與被害人謝茂隆成立調解，允諾分期賠償被害人謝茂隆所受\n    之損害，並於九十九年十二月二十四日賠償第一期和解金額\n    一萬元，有和解書附卷為憑，經此次偵審程序及科刑判決之\n    教訓後，應已足收警惕之效，信無再犯之虞，本院認前開對\n    被告所宣告之刑，以暫不執行為適當，爰依法諭知緩刑三年\n    ，以啟自新。\n據上論斷，應依刑事訴訟法第368條、刑法第74條第1款，判決如\n主文。\n本案經檢察官劉斐玲到庭執行職務。\n中    華    民    國    100    年    1    月    12    日\n                  刑事第十六庭  審判長法  官  陳晴教\n                                      法  官  王敏慧\n                                      法  官  吳啟民\n以上正本證明與原本無異。\n不得上訴。\n                                      書記官  胡新涓\n中    華    民    國   100    年    1     月    13    日\n附錄：本案論罪科刑法條全文\n中華民國刑法第三百三十九條：\n意圖為自己或第三人不法之所有，以詐術使人將本人或第三人之\n物交付者，處五年以下有期徒刑、拘役或科或併科一千元以下罰\n金。\n以前項方法得財產上不法之利益或使第三人得之者，亦同。\n前二項之未遂犯罰之。\n【附表】\n ┌──┬───────┬───────────────────┬───┬───────┐\n │編號│ 來電詐騙時間 │詐        騙           手           法│被害人│備註          │\n ├──┼───────┼───────────────────┼───┼───────┤\n │    │              │真實姓名、年籍均不詳之成年人，自稱係  │      │玉山銀行自動櫃│\n │    │              │PCHOME服務人員，撥打電話予被害人，謊稱│      │員機交易明細表│\n │    │              │被害人日前網路購物，因作業疏失，導致每│      │一份（98偵字第│\n │    │              │月均會固定扣款至指定帳戶，被害人需依指│      │27559號卷第20 │\n │    │98年9月19日下 │示至ATM（自動櫃員機）解除設定云云，使 │      │頁）          │\n │ 一 │午2時17分許、 │被害人陷於錯誤，信以為真，依指示至自動│李佳真│              │\n │    │同年月日晚上8 │櫃員機操作接續匯款，其中二筆於98年9 月│      │              │\n │    │時5分許       │19日晚上9時42分許及同年月日晚上10時29 │      │              │\n │    │              │分許，在台中縣大里市○○路二八二號之玉│      │              │\n │    │              │山銀行大里分行自動櫃員機轉帳匯款新臺幣│      │              │\n │    │              │（下同）22023元及22552元，共44575元（ │      │              │\n │    │              │起訴書誤載為47575元）至被告上開華南銀 │      │              │\n │    │              │行雙園分行帳戶中。                    │      │              │\n ├──┼───────┼───────────────────┼───┼───────┤\n │    │              │真實姓名、年籍均不詳之成年女子，自稱係│      │郵政自動櫃員機│\n │    │              │網路購物服務人員，撥打電話予被害人，謊│      │交易明細表一份│\n │    │              │稱被害人日前網路購物雖已付清，然因會計│      │（98偵字第2755│\n │    │98年9月19日晚 │登錄作業錯誤，誤登為十二期分期付款，是│      │9號卷第29頁） │\n │ 二 │上9時48分許   │否欲取消分期付款云云，以及真實姓名、年│謝茂隆│              │\n │    │              │籍均不詳之成年男子，自稱係台新銀行人員│      │              │\n │    │              │，要求被害人需持台新銀行金融卡至郵局提│      │              │\n │    │              │款機查詢餘額，告知餘額後依指示操作云云│      │              │\n │    │              │，使被害人陷於錯誤，信以為真，依指示至│      │              │\n │    │              │自動櫃員機操作，於98年9月19日晚上9時48│      │              │\n │    │              │分許，在高雄縣阿蓮鄉之阿蓮郵局自動櫃員│      │              │\n │    │              │機轉帳匯款29988元至被告上開華南銀行雙 │      │              │\n │    │              │園分行帳戶中。                        │      │              │\n ├──┴───────┴───────────────────┴───┴───────┤\n │合計：74563元                                                                       │\n └──────────────────────────────────────────┘",
  "structure": {
    "main": "上訴駁回。\n沈聰志緩刑參年。",
    "fact": "一、沈聰志在得預見將其金融機構開立帳戶之提款卡及密碼持交\n    不相識之人使用，其帳戶有遭人利用作為詐騙工具可能之情\n    形下，仍基於幫助詐欺取財之犯意，於民國九十八年九月十\n    九日前之九十九年間某日某時許，在臺北縣三重市○○路○\n    段七八號天台廣場之合作金庫前，將其前於九十三年四月二\n    十日至臺北市○○區○○路一二七號之華南商業銀行股份有\n    限公司（下稱華南銀行）雙園分行所申請開立，帳號000\n    000000000號帳戶之提款卡及密碼，以不詳代價，\n    持交予姓名、年籍均不詳之成年人使用。俟該姓名、年籍均\n    不詳之成年人所屬之犯罪集團取得沈聰志所交付之上開帳戶\n    提款卡及密碼後，即基於詐欺取財之犯意，分別於如附表所\n    示詐騙時間、以如附表所示之詐騙手法，詐騙如附表所示被\n    害人，致如附表所示被害人均因此陷於錯誤，轉帳匯款如附\n    表所示金額至沈聰志上開華南銀行雙園分行帳戶中。嗣經如\n    附表所示被害人在依指示操作後，察覺帳戶存款業遭轉出短\n    少，始知受騙，報警處理循線查獲沈聰志。\n二、案經如附表所示被害人分別報請臺中縣政府警察局太平分局\n    及高雄縣政府警察局湖內分局轉至臺北縣政府警察局新莊分\n    局移送臺灣板橋地方法院檢察署檢察官偵查後，簽請臺灣高\n    等法院檢察署准予移轉臺灣臺北地方法院檢察署檢察官偵查\n    起訴。",
    "reason": "一、訊據上訴人即被告沈聰志固坦承有至華南銀行雙園分行開立\n    上開帳戶之事實，然矢口否認涉有上開犯行，辯稱：其上開\n    帳戶提款卡及密碼資料，係其在應徵阿秋檳榔之司機時遭人\n    詐騙，並未持交他人使用云云。經查：\n  (一)上開華南銀行雙園分行帳戶係被告於九十三年四月二十日，\n    間親自前往開立，嗣遭真實姓名、年籍不詳之成年人用以作\n    為詐騙如附表所示被害人轉帳匯款之人頭帳戶使用之事實，\n    業經被告於警詢、偵查及原審審理時坦認在卷，並經如附表\n    編號一所示被害人即證人李佳真於警詢時證述：「我於九十\n    八年九月十九日十四時十七分左右，接獲自稱為ＰＣＨＯＭ\n    Ｅ的電話，謊稱被害人日前於網路購物，因作業上疏失，導\n    致每個月將會扣除固定款項至約定帳戶，要求被害人立即前\n    往ＡＴＭ解除設定‧‧‧」、「我與歹徒共電話二次，第一\n    次歹徒是在九十八年九月十九日十四時十七分左右，用電話\n    與我聯絡，詢問我是有網路購物，並確認我網路購物的明細\n    ，會有一單位與我聯絡扣款是否要取消，隨即掛斷電話。」\n    、「歹徒第二次是在九十八年九月十九日二十時五分，用電\n    話聯絡‧‧‧自稱一名郵局員工向我說，他們是幫ＰＣＨＯ\n    ＭＥ執行扣款，他們接到通知說我要扣款，要我到ＡＴＭ操\n    作取消扣款‧‧‧」、「‧‧‧第五筆及第六筆分別在九十\n    八年九月十九日二十一時四十二分及二十二時二十九分，在\n    台中縣大里市○○路二八二號玉山銀行大里分行轉帳至華南\n    商業銀行雙園分行，帳號為00000000000000\n    00，分別轉入新臺幣二二０二三元及新臺幣二二五五二元\n    。」等語（臺灣臺北地方法院檢察署九十九年度偵字第二七\n    五五九號卷第九頁、第十頁）；以及如附表編號二所示被害\n    人即證人謝茂隆於警詢時證述：「我是於九十八年九月十九\n    日晚上二十一時四十八分許在高雄縣阿蓮鄉○○路一九四號\n    在家接到一通‧‧‧詐騙電話而至阿蓮郵局前提款機匯款而\n    遭詐騙。」、「‧‧‧對方女子謊稱之前在網路購物，稱當\n    初所購買的貨物已付清並聲稱當初會計登錄錯誤，誤登為分\n    期付款為十二期，並問我要不要取消，我就向他說取消，他\n    並說要代我向台新銀行講並說台新銀行會與我聯絡，後來就\n    有一位男子自稱是台新銀行的人員，要我拿台新銀行的金融\n    卡至郵局提款機查詢餘額後向對方說餘額還有多少，對方就\n    叫我將金融卡插入提款機並依對方指示操作轉帳，共轉出金\n    額二九九八八元，對方就詢問我轉入的帳號是多少，我就跟\n    他說是0000000000000000‧‧‧」等語綦\n    詳（臺灣臺北地方法院檢察署九十九年度偵字第二七五五九\n    號卷第二三頁、第二四頁）。並有華南銀行雙園分行九十八\n    年十月十三日華雙存字第０九八００四０三號函暨函覆之被\n    告上開帳戶開戶資料及存款往來明細暨對帳單各一份（臺灣\n    板橋地方法院檢察署九十九年度偵字第二六五三號卷第二二\n    頁至第二四頁）、如附表編號一所示被害人即證人李佳真之\n    台中縣警察局霧峰分局國光派出所受理詐騙帳戶通報警示簡\n    便格式表、受理刑事案件報案三聯單、金融機構聯防機制通\n    報單、內政部警政署反詐騙案件紀錄表各一份、玉山銀行自\n    動櫃員機轉帳交易明細表二份（臺灣臺北地方法院檢察署九\n    十九年度偵字第二七五五九號卷第一一頁、第一五頁、第一\n    八頁、第二０頁、第二一頁）；如附表編號二所示被害人即\n    證人謝茂隆之高雄縣政府警察局湖內分局阿蓮分駐所受理各\n    類案件紀錄表、受理詐騙帳戶通報警示簡便格式表、受理刑\n    事案件報案三聯單、內政部警政署反詐騙案件紀錄表、金融\n    機構協助受詐騙民眾通知疑似警示帳戶通報單、郵局自動櫃\n    員機交易明細表各一份（臺灣臺北地方法院檢察署九十九年\n    度偵字第二七五五九號卷第二二頁、第二六頁至第三０頁）\n    在卷可稽，此部分之事實，已堪認定。\n  (二)至被告對於其上開華南銀行雙園分行帳戶提款卡及密碼，何\n    以落入詐騙集團成員手中，遭人用作詐騙證人李佳真、謝茂\n    隆轉帳匯款人頭帳戶使用之緣由，固一再辯稱：係應徵工作\n    遭人詐騙所致云云。然核諸被告對於其循報載徵人廣告應徵\n    工作，致將其上開華南銀行雙園分行帳戶提款卡及密碼持交\n    對方之過程，除供稱：係應徵阿秋檳榔之司機云云外，對於\n    日後所欲任職之該家公司行號或個人獨資商號之正確全銜、\n    公司地址、工作地點、前來拿取其上開華南銀行雙園分行帳\n    戶提款卡及密碼者之真實姓名、年籍資料及在公司之職稱等\n    細節，均無所悉，亦經被告於原審審理時供述不諱（原審卷\n    第二七頁），此均與一般求職者應徵時均係前往公司所在地\n    ，由公司主管進行面試，洽談日後工作時間、地址、待遇，\n    待確定錄取正式上班後，始須提供個人帳戶資料供公司薪資\n    轉帳之常情相悖。再者，被告於原審準備程序中及審理時，\n    辯稱：其在交付帳戶提款卡及密碼後，翌日中午仍未接獲上\n    班通知，察覺遭詐騙後，隨即去電華南銀行詢問，因華南銀\n    行行員答稱該帳戶業已結清，遂將該帳戶存摺丟棄，未報警\n    處理云云（見原審卷第一一頁反面、第二七頁），亦顯與常\n    情有違。況以被告已逾五十歲，在本件案發前，曾陸續從事\n    果菜批發、房地產及計程車駕駛等工作，其先前應徵房地產\n    工作時，該公司並未要求須提供存摺、提款卡及密碼等資料\n    ，具有相當之社會歷練及工作經驗，豈有在明知個人提款卡\n    、密碼等資料係攸關個人金融信用之重要資料，且事前既不\n    知公司所在地點、名稱等基本資料，又對該名前來拿取其上\n    開華南銀行雙園分行帳戶提款卡及密碼者之來歷背景及職稱\n    ，毫無所悉之情形下，輕易聽信在接獲錄取通知正式上班前\n    ，即須先行持交提款卡及密碼供薪資轉帳之謬論之理。\n  (三)再者，自被告上開華南銀行雙園分行帳戶，自開戶後，迄於\n    其在上開時、地持交帳戶提款卡及密碼予真實姓名、年籍均\n    不詳之成年人之前，業已甚少使用該帳戶一節，亦經被告於\n    偵查中坦認在卷（九十九年度偵緝字第八三八號卷第二五頁\n    ），以及依上開華南銀行存款往來明細表暨對帳單所示（臺\n    灣板橋地方法院檢察署九十九年度偵字第二六五三號卷第二\n    四頁），被告上開華南銀行雙園分行帳戶，在如附表編號一\n    所示之被害人即證人李佳真遭詐騙轉帳匯入第一筆新臺幣（\n    下同）二萬二千零二十三元後之帳戶餘額為二萬二千零三十\n    一元，可徵被告將該帳戶提款卡及密碼持交真實姓名、年籍\n    均不詳之成年人之前之帳戶餘額僅有八元等情觀之，足認被\n    告上開華南銀行雙園分行帳戶提款卡及密碼，在其將之持交\n    真實姓名、年籍均不詳之成年人使用前，對被告而言，顯非\n    與其日常金融交易息息相關之經常使用性帳戶，而係一閒置\n    帳戶，此與一般出售或或出租帳戶存摺、提款卡及密碼等資\n    料，均係以新開立帳戶，或業已開立惟已閒置無用之帳戶持\n    交他人作為轉帳匯款人頭帳戶使用者之行為模式，並無二致\n    。總此，堪認被告上開所辯，均係事後卸責之詞，不足採信\n    。被告上開華南銀行雙園分行之提款卡及密碼，顯係被告以\n    不詳代價將之提供真實姓名、年籍均不詳之成年人使用，致\n    遭詐騙集團成員用作詐騙證人李佳真、謝茂隆之人頭帳戶使\n    用甚明。\n  (四)按一般國人向金融機構開設帳戶，並無任何法令限制，若係\n    用於正當用途者，當可光明正大自行申請使用，而帳戶係為\n    存提款及轉帳匯款之用，倘刻意收集他人帳戶使用者，依一\n    般常識極易判斷係為藉此躲避遭人循線追查之目的而為，自\n    可產生與不法犯罪目的相關之合理懷疑。而見諸各大平面及\n    電子媒體報導，或以中獎、退稅、信用卡款對帳、提款卡密\n    碼外洩，疑似遭人盜領存款或家人遭綁架等事由，利用人頭\n    帳戶作為轉帳帳戶，謊騙被害人至金融機構櫃檯電匯，抑或\n    持提款卡至自動櫃員機依其指示操作，使被害人在不知情之\n    狀況下依指示操作匯出款項後，隨即將之提領一空之詐騙手\n    法，層出不窮，以被告係一智慮成熟並具相當社會經驗之成\n    年人而言，對此一犯罪型態，自難諉為不知。況帳戶存摺、\n    印章、提款卡及密碼條等，均係關乎個人金融信用及隱私之\n    重要物件之一，縱親如父母子女或夫妻，衡常若非出於特殊\n    事由或目的，即無任意將之交由他方保管或使用，遑論係為\n    獲取相當對價而將之出租或售予不相熟識之第三人使用。職\n    是，被告在與向其收受上開華南銀行雙園分行帳戶提款卡及\n    密碼之真實姓名、年籍均不詳之成年男子素不相識，且不知\n    該人來歷是否正當之情形下，出於獲取不詳代價之目的，將\n    上開帳戶提款卡及密碼提供該成年男子使用時，其對於上開\n    帳戶可能遭人用以上開手段詐騙他人轉帳匯款之人頭帳戶使\n    用，當無不能預見之可能。被告在此預見及認知下，仍將其\n    上開帳戶提款卡、密碼持交該真實姓名、年籍均不詳之成年\n    人使用，容任詐欺取財結果之發生，其主觀上顯有幫助他人\n    遂行詐欺取財之不確定故意甚明。從而，被告上開幫助詐欺\n    取財犯行，洵堪認定，本件事證明確，應予依法論處。\n二、核被告所為，係幫助犯刑法第三百三十九條第一項之詐欺取\n    財罪。其幫助他人犯罪，為幫助犯，應依刑法第三十條第二\n    項規定，按正犯之刑減輕之。被告以一行為，幫助他人詐騙\n    如附表所示被害人，侵害數法益，為想像競合犯，應依刑法\n    第五十五條規定，從一重處斷。\n三、原審以被告罪證明確，而適用刑法第三十條、第三百三十九\n    條第一項、第四十一條第一項前段、第五十五條，刑法施行\n    法第一條之一，並審酌被告犯罪之動機、目的、手段，將其\n    上開華南銀行雙園分行帳戶提款卡及密碼提供他人使用，致\n    如附表編號一、二所示之被害人即證人李佳真、謝茂隆分別\n    遭詐騙轉帳匯款如附表所示之金額至被告上開華南銀行雙園\n    分行帳戶中，旋即遭提領一空，危害社會經濟秩序、雖非實\n    際遂行詐欺犯行之人，然犯後飾詞狡辯，在法院行準備程序\n    後，具狀表明欲與被害人和解之意，要求法院傳喚被害人到\n    庭，俾與被害人洽談和解事宜，此有陳報狀一份在卷可稽，\n    俟被害人即證人謝茂榮自高雄縣阿蓮鄉遠道北上至法院開庭\n    時，又翻異前詞，稱僅願賠償被害人前來開庭之損失即一千\n    元，不知悔改之態度等一切情狀，量處有期徒刑四月，並諭\n    知易科罰金之折算標準。\n四、經核原判決上開認事用法，洵無違誤，量刑亦屬妥適。被告\n    上訴意旨以並沒有賣帳戶給詐欺集團，是去應徵工作，他說\n    要我的帳號作為徵信與薪資轉帳，所以才提供帳戶給他們等\n    語。惟查：個人之帳戶存摺、印章、提款卡及密碼條等，均\n    係關乎個人金融信用及隱私之重要物件之一，衡情若非出於\n    特殊事由或目的，即無任意將之交由他人保管或使用，遑論\n    係為獲取相當對價而將之出租或售予不相熟識之第三人使用\n    。本件被告已逾五十歲，在本件案發前，曾陸續從事果菜批\n    發、房地產及計程車駕駛等工作，被告亦坦承其先前應徵房\n    地產工作時，該公司並未要求須提供存摺、提款卡及密碼等\n    資料，被告既為一智慮成熟並具相當社會歷練及工作經驗之\n    人，在與向其收受上開華南銀行雙園分行帳戶提款卡及密碼\n    之真實姓名、年籍均不詳之成年男子素不相識，且不知該人\n    來歷是否正當之情形下，出於獲取不詳代價之目的，將上開\n    帳戶提款卡及密碼提供該成年男子使用時，其對於上開帳戶\n    可能遭人用以上開手段詐騙他人轉帳匯款之人頭帳戶使用，\n    當無不能預見之可能；且被告於原審審理時亦坦承當時心想\n    被騙的話最多也只是去華南銀行把帳戶取消等語（見原審卷\n    第11頁反面），被告在此預見及認知下，仍將其上開帳戶提\n    款卡、密碼持交該真實姓名、年籍均不詳之成年人使用，且\n    在交付帳號之隔天因聯絡不上面試之人，而去電華南銀行查\n    詢所交付帳戶之現況，在得知有他人結清、註銷自己所有之\n    上開帳戶後，卻未報警處理，顯亦有違常情，被告容任詐欺\n    取財結果之發生，其主觀上顯有幫助他人遂行詐欺取財之不\n    確定故意甚明。而按證據之取捨與證據之證明力如何，均屬\n    事實審法院得自由裁量、判斷之職權，茍其此項裁量、判斷\n    ，並不悖乎通常一般人日常生活經驗之定則或論理法則，又\n    於判決內論敘其何以作此判斷之心證理由者，即不得任意指\n    摘其為違法。茲原判決已詳敘就卷內證據調查之結果，而為\n    綜合判斷、取捨，認被告確有如事實欄所載之犯行，其得心\n    證的理由已說明甚詳，且所為論斷從形式上觀察，亦難認有\n    違背經驗法則、論理法則，或有其他違背法令之情形，自不\n    容任意指為違法，被告提起上訴仍對原審取捨證據及判斷其\n    證明力職權之適法行使，砌詞指摘原判決不當而否認犯行，\n    自屬卸責之詞，委無可採。\n五、末查被告前未曾因故意犯罪受有期徒刑以上刑之宣告，有本\n    院被告前案紀錄表在卷可查，本院以被告因一時失慮致犯刑\n    章，惟幫助詐取之金額非鉅，犯罪情節尚非重大，且犯後業\n    與被害人謝茂隆成立調解，允諾分期賠償被害人謝茂隆所受\n    之損害，並於九十九年十二月二十四日賠償第一期和解金額\n    一萬元，有和解書附卷為憑，經此次偵審程序及科刑判決之\n    教訓後，應已足收警惕之效，信無再犯之虞，本院認前開對\n    被告所宣告之刑，以暫不執行為適當，爰依法諭知緩刑三年\n    ，以啟自新。\n據上論斷，應依刑事訴訟法第368條、刑法第74條第1款，判決如\n主文。\n本案經檢察官劉斐玲到庭執行職務。\n中    華    民    國    100    年    1    月    12    日\n                  刑事第十六庭  審判長法  官  陳晴教\n                                      法  官  王敏慧\n                                      法  官  吳啟民\n以上正本證明與原本無異。\n不得上訴。\n                                      書記官  胡新涓"
  },
  "search": "臺灣高等法院刑事判決99年度上易字第2497號上訴人即被告沈聰志上列上訴人因詐欺案件，不服臺灣臺北地方法院99年度易字第1583號，中華民國99年9月30日第一審判決（起訴案號：臺灣臺北地方法院檢察署99年度偵緝字第838號、第839號），提起上訴，本院判決如下：主文上訴駁回。沈聰志緩刑參年。事實一、沈聰志在得預見將其金融機構開立帳戶之提款卡及密碼持交不相識之人使用，其帳戶有遭人利用作為詐騙工具可能之情形下，仍基於幫助詐欺取財之犯意，於民國九十八年九月十九日前之九十九年間某日某時許，在臺北縣三重市○○路○段七八號天台廣場之合作金庫前，將其前於九十三年四月二十日至臺北市○○區○○路一二七號之華南商業銀行股份有限公司（下稱華南銀行）雙園分行所申請開立，帳號000000000000號帳戶之提款卡及密碼，以不詳代價，持交予姓名、年籍均不詳之成年人使用。俟該姓名、年籍均不詳之成年人所屬之犯罪集團取得沈聰志所交付之上開帳戶提款卡及密碼後，即基於詐欺取財之犯意，分別於如附表所示詐騙時間、以如附表所示之詐騙手法，詐騙如附表所示被害人，致如附表所示被害人均因此陷於錯誤，轉帳匯款如附表所示金額至沈聰志上開華南銀行雙園分行帳戶中。嗣經如附表所示被害人在依指示操作後，察覺帳戶存款業遭轉出短少，始知受騙，報警處理循線查獲沈聰志。二、案經如附表所示被害人分別報請臺中縣政府警察局太平分局及高雄縣政府警察局湖內分局轉至臺北縣政府警察局新莊分局移送臺灣板橋地方法院檢察署檢察官偵查後，簽請臺灣高等法院檢察署准予移轉臺灣臺北地方法院檢察署檢察官偵查起訴。理由一、訊據上訴人即被告沈聰志固坦承有至華南銀行雙園分行開立上開帳戶之事實，然矢口否認涉有上開犯行，辯稱：其上開帳戶提款卡及密碼資料，係其在應徵阿秋檳榔之司機時遭人詐騙，並未持交他人使用云云。經查：(一)上開華南銀行雙園分行帳戶係被告於九十三年四月二十日，間親自前往開立，嗣遭真實姓名、年籍不詳之成年人用以作為詐騙如附表所示被害人轉帳匯款之人頭帳戶使用之事實，業經被告於警詢、偵查及原審審理時坦認在卷，並經如附表編號一所示被害人即證人李佳真於警詢時證述：「我於九十八年九月十九日十四時十七分左右，接獲自稱為ＰＣＨＯＭＥ的電話，謊稱被害人日前於網路購物，因作業上疏失，導致每個月將會扣除固定款項至約定帳戶，要求被害人立即前往ＡＴＭ解除設定‧‧‧」、「我與歹徒共電話二次，第一次歹徒是在九十八年九月十九日十四時十七分左右，用電話與我聯絡，詢問我是有網路購物，並確認我網路購物的明細，會有一單位與我聯絡扣款是否要取消，隨即掛斷電話。」、「歹徒第二次是在九十八年九月十九日二十時五分，用電話聯絡‧‧‧自稱一名郵局員工向我說，他們是幫ＰＣＨＯＭＥ執行扣款，他們接到通知說我要扣款，要我到ＡＴＭ操作取消扣款‧‧‧」、「‧‧‧第五筆及第六筆分別在九十八年九月十九日二十一時四十二分及二十二時二十九分，在台中縣大里市○○路二八二號玉山銀行大里分行轉帳至華南商業銀行雙園分行，帳號為0000000000000000，分別轉入新臺幣二二０二三元及新臺幣二二五五二元。」等語（臺灣臺北地方法院檢察署九十九年度偵字第二七五五九號卷第九頁、第十頁）；以及如附表編號二所示被害人即證人謝茂隆於警詢時證述：「我是於九十八年九月十九日晚上二十一時四十八分許在高雄縣阿蓮鄉○○路一九四號在家接到一通‧‧‧詐騙電話而至阿蓮郵局前提款機匯款而遭詐騙。」、「‧‧‧對方女子謊稱之前在網路購物，稱當初所購買的貨物已付清並聲稱當初會計登錄錯誤，誤登為分期付款為十二期，並問我要不要取消，我就向他說取消，他並說要代我向台新銀行講並說台新銀行會與我聯絡，後來就有一位男子自稱是台新銀行的人員，要我拿台新銀行的金融卡至郵局提款機查詢餘額後向對方說餘額還有多少，對方就叫我將金融卡插入提款機並依對方指示操作轉帳，共轉出金額二九九八八元，對方就詢問我轉入的帳號是多少，我就跟他說是0000000000000000‧‧‧」等語綦詳（臺灣臺北地方法院檢察署九十九年度偵字第二七五五九號卷第二三頁、第二四頁）。並有華南銀行雙園分行九十八年十月十三日華雙存字第０九八００四０三號函暨函覆之被告上開帳戶開戶資料及存款往來明細暨對帳單各一份（臺灣板橋地方法院檢察署九十九年度偵字第二六五三號卷第二二頁至第二四頁）、如附表編號一所示被害人即證人李佳真之台中縣警察局霧峰分局國光派出所受理詐騙帳戶通報警示簡便格式表、受理刑事案件報案三聯單、金融機構聯防機制通報單、內政部警政署反詐騙案件紀錄表各一份、玉山銀行自動櫃員機轉帳交易明細表二份（臺灣臺北地方法院檢察署九十九年度偵字第二七五五九號卷第一一頁、第一五頁、第一八頁、第二０頁、第二一頁）；如附表編號二所示被害人即證人謝茂隆之高雄縣政府警察局湖內分局阿蓮分駐所受理各類案件紀錄表、受理詐騙帳戶通報警示簡便格式表、受理刑事案件報案三聯單、內政部警政署反詐騙案件紀錄表、金融機構協助受詐騙民眾通知疑似警示帳戶通報單、郵局自動櫃員機交易明細表各一份（臺灣臺北地方法院檢察署九十九年度偵字第二七五五九號卷第二二頁、第二六頁至第三０頁）在卷可稽，此部分之事實，已堪認定。(二)至被告對於其上開華南銀行雙園分行帳戶提款卡及密碼，何以落入詐騙集團成員手中，遭人用作詐騙證人李佳真、謝茂隆轉帳匯款人頭帳戶使用之緣由，固一再辯稱：係應徵工作遭人詐騙所致云云。然核諸被告對於其循報載徵人廣告應徵工作，致將其上開華南銀行雙園分行帳戶提款卡及密碼持交對方之過程，除供稱：係應徵阿秋檳榔之司機云云外，對於日後所欲任職之該家公司行號或個人獨資商號之正確全銜、公司地址、工作地點、前來拿取其上開華南銀行雙園分行帳戶提款卡及密碼者之真實姓名、年籍資料及在公司之職稱等細節，均無所悉，亦經被告於原審審理時供述不諱（原審卷第二七頁），此均與一般求職者應徵時均係前往公司所在地，由公司主管進行面試，洽談日後工作時間、地址、待遇，待確定錄取正式上班後，始須提供個人帳戶資料供公司薪資轉帳之常情相悖。再者，被告於原審準備程序中及審理時，辯稱：其在交付帳戶提款卡及密碼後，翌日中午仍未接獲上班通知，察覺遭詐騙後，隨即去電華南銀行詢問，因華南銀行行員答稱該帳戶業已結清，遂將該帳戶存摺丟棄，未報警處理云云（見原審卷第一一頁反面、第二七頁），亦顯與常情有違。況以被告已逾五十歲，在本件案發前，曾陸續從事果菜批發、房地產及計程車駕駛等工作，其先前應徵房地產工作時，該公司並未要求須提供存摺、提款卡及密碼等資料，具有相當之社會歷練及工作經驗，豈有在明知個人提款卡、密碼等資料係攸關個人金融信用之重要資料，且事前既不知公司所在地點、名稱等基本資料，又對該名前來拿取其上開華南銀行雙園分行帳戶提款卡及密碼者之來歷背景及職稱，毫無所悉之情形下，輕易聽信在接獲錄取通知正式上班前，即須先行持交提款卡及密碼供薪資轉帳之謬論之理。(三)再者，自被告上開華南銀行雙園分行帳戶，自開戶後，迄於其在上開時、地持交帳戶提款卡及密碼予真實姓名、年籍均不詳之成年人之前，業已甚少使用該帳戶一節，亦經被告於偵查中坦認在卷（九十九年度偵緝字第八三八號卷第二五頁），以及依上開華南銀行存款往來明細表暨對帳單所示（臺灣板橋地方法院檢察署九十九年度偵字第二六五三號卷第二四頁），被告上開華南銀行雙園分行帳戶，在如附表編號一所示之被害人即證人李佳真遭詐騙轉帳匯入第一筆新臺幣（下同）二萬二千零二十三元後之帳戶餘額為二萬二千零三十一元，可徵被告將該帳戶提款卡及密碼持交真實姓名、年籍均不詳之成年人之前之帳戶餘額僅有八元等情觀之，足認被告上開華南銀行雙園分行帳戶提款卡及密碼，在其將之持交真實姓名、年籍均不詳之成年人使用前，對被告而言，顯非與其日常金融交易息息相關之經常使用性帳戶，而係一閒置帳戶，此與一般出售或或出租帳戶存摺、提款卡及密碼等資料，均係以新開立帳戶，或業已開立惟已閒置無用之帳戶持交他人作為轉帳匯款人頭帳戶使用者之行為模式，並無二致。總此，堪認被告上開所辯，均係事後卸責之詞，不足採信。被告上開華南銀行雙園分行之提款卡及密碼，顯係被告以不詳代價將之提供真實姓名、年籍均不詳之成年人使用，致遭詐騙集團成員用作詐騙證人李佳真、謝茂隆之人頭帳戶使用甚明。(四)按一般國人向金融機構開設帳戶，並無任何法令限制，若係用於正當用途者，當可光明正大自行申請使用，而帳戶係為存提款及轉帳匯款之用，倘刻意收集他人帳戶使用者，依一般常識極易判斷係為藉此躲避遭人循線追查之目的而為，自可產生與不法犯罪目的相關之合理懷疑。而見諸各大平面及電子媒體報導，或以中獎、退稅、信用卡款對帳、提款卡密碼外洩，疑似遭人盜領存款或家人遭綁架等事由，利用人頭帳戶作為轉帳帳戶，謊騙被害人至金融機構櫃檯電匯，抑或持提款卡至自動櫃員機依其指示操作，使被害人在不知情之狀況下依指示操作匯出款項後，隨即將之提領一空之詐騙手法，層出不窮，以被告係一智慮成熟並具相當社會經驗之成年人而言，對此一犯罪型態，自難諉為不知。況帳戶存摺、印章、提款卡及密碼條等，均係關乎個人金融信用及隱私之重要物件之一，縱親如父母子女或夫妻，衡常若非出於特殊事由或目的，即無任意將之交由他方保管或使用，遑論係為獲取相當對價而將之出租或售予不相熟識之第三人使用。職是，被告在與向其收受上開華南銀行雙園分行帳戶提款卡及密碼之真實姓名、年籍均不詳之成年男子素不相識，且不知該人來歷是否正當之情形下，出於獲取不詳代價之目的，將上開帳戶提款卡及密碼提供該成年男子使用時，其對於上開帳戶可能遭人用以上開手段詐騙他人轉帳匯款之人頭帳戶使用，當無不能預見之可能。被告在此預見及認知下，仍將其上開帳戶提款卡、密碼持交該真實姓名、年籍均不詳之成年人使用，容任詐欺取財結果之發生，其主觀上顯有幫助他人遂行詐欺取財之不確定故意甚明。從而，被告上開幫助詐欺取財犯行，洵堪認定，本件事證明確，應予依法論處。二、核被告所為，係幫助犯刑法第三百三十九條第一項之詐欺取財罪。其幫助他人犯罪，為幫助犯，應依刑法第三十條第二項規定，按正犯之刑減輕之。被告以一行為，幫助他人詐騙如附表所示被害人，侵害數法益，為想像競合犯，應依刑法第五十五條規定，從一重處斷。三、原審以被告罪證明確，而適用刑法第三十條、第三百三十九條第一項、第四十一條第一項前段、第五十五條，刑法施行法第一條之一，並審酌被告犯罪之動機、目的、手段，將其上開華南銀行雙園分行帳戶提款卡及密碼提供他人使用，致如附表編號一、二所示之被害人即證人李佳真、謝茂隆分別遭詐騙轉帳匯款如附表所示之金額至被告上開華南銀行雙園分行帳戶中，旋即遭提領一空，危害社會經濟秩序、雖非實際遂行詐欺犯行之人，然犯後飾詞狡辯，在法院行準備程序後，具狀表明欲與被害人和解之意，要求法院傳喚被害人到庭，俾與被害人洽談和解事宜，此有陳報狀一份在卷可稽，俟被害人即證人謝茂榮自高雄縣阿蓮鄉遠道北上至法院開庭時，又翻異前詞，稱僅願賠償被害人前來開庭之損失即一千元，不知悔改之態度等一切情狀，量處有期徒刑四月，並諭知易科罰金之折算標準。四、經核原判決上開認事用法，洵無違誤，量刑亦屬妥適。被告上訴意旨以並沒有賣帳戶給詐欺集團，是去應徵工作，他說要我的帳號作為徵信與薪資轉帳，所以才提供帳戶給他們等語。惟查：個人之帳戶存摺、印章、提款卡及密碼條等，均係關乎個人金融信用及隱私之重要物件之一，衡情若非出於特殊事由或目的，即無任意將之交由他人保管或使用，遑論係為獲取相當對價而將之出租或售予不相熟識之第三人使用。本件被告已逾五十歲，在本件案發前，曾陸續從事果菜批發、房地產及計程車駕駛等工作，被告亦坦承其先前應徵房地產工作時，該公司並未要求須提供存摺、提款卡及密碼等資料，被告既為一智慮成熟並具相當社會歷練及工作經驗之人，在與向其收受上開華南銀行雙園分行帳戶提款卡及密碼之真實姓名、年籍均不詳之成年男子素不相識，且不知該人來歷是否正當之情形下，出於獲取不詳代價之目的，將上開帳戶提款卡及密碼提供該成年男子使用時，其對於上開帳戶可能遭人用以上開手段詐騙他人轉帳匯款之人頭帳戶使用，當無不能預見之可能；且被告於原審審理時亦坦承當時心想被騙的話最多也只是去華南銀行把帳戶取消等語（見原審卷第11頁反面），被告在此預見及認知下，仍將其上開帳戶提款卡、密碼持交該真實姓名、年籍均不詳之成年人使用，且在交付帳號之隔天因聯絡不上面試之人，而去電華南銀行查詢所交付帳戶之現況，在得知有他人結清、註銷自己所有之上開帳戶後，卻未報警處理，顯亦有違常情，被告容任詐欺取財結果之發生，其主觀上顯有幫助他人遂行詐欺取財之不確定故意甚明。而按證據之取捨與證據之證明力如何，均屬事實審法院得自由裁量、判斷之職權，茍其此項裁量、判斷，並不悖乎通常一般人日常生活經驗之定則或論理法則，又於判決內論敘其何以作此判斷之心證理由者，即不得任意指摘其為違法。茲原判決已詳敘就卷內證據調查之結果，而為綜合判斷、取捨，認被告確有如事實欄所載之犯行，其得心證的理由已說明甚詳，且所為論斷從形式上觀察，亦難認有違背經驗法則、論理法則，或有其他違背法令之情形，自不容任意指為違法，被告提起上訴仍對原審取捨證據及判斷其證明力職權之適法行使，砌詞指摘原判決不當而否認犯行，自屬卸責之詞，委無可採。五、末查被告前未曾因故意犯罪受有期徒刑以上刑之宣告，有本院被告前案紀錄表在卷可查，本院以被告因一時失慮致犯刑章，惟幫助詐取之金額非鉅，犯罪情節尚非重大，且犯後業與被害人謝茂隆成立調解，允諾分期賠償被害人謝茂隆所受之損害，並於九十九年十二月二十四日賠償第一期和解金額一萬元，有和解書附卷為憑，經此次偵審程序及科刑判決之教訓後，應已足收警惕之效，信無再犯之虞，本院認前開對被告所宣告之刑，以暫不執行為適當，爰依法諭知緩刑三年，以啟自新。據上論斷，應依刑事訴訟法第368條、刑法第74條第1款，判決如主文。本案經檢察官劉斐玲到庭執行職務。中華民國100年1月12日刑事第十六庭審判長法官陳晴教法官王敏慧法官吳啟民以上正本證明與原本無異。不得上訴。書記官胡新涓中華民國100年1月13日附錄：本案論罪科刑法條全文中華民國刑法第三百三十九條：意圖為自己或第三人不法之所有，以詐術使人將本人或第三人之物交付者，處五年以下有期徒刑、拘役或科或併科一千元以下罰金。以前項方法得財產上不法之利益或使第三人得之者，亦同。前二項之未遂犯罰之。【附表】┌──┬───────┬───────────────────┬───┬───────┐│編號│來電詐騙時間│詐騙手法│被害人│備註│├──┼───────┼───────────────────┼───┼───────┤│││真實姓名、年籍均不詳之成年人，自稱係││玉山銀行自動櫃││││PCHOME服務人員，撥打電話予被害人，謊稱││員機交易明細表││││被害人日前網路購物，因作業疏失，導致每││一份（98偵字第││││月均會固定扣款至指定帳戶，被害人需依指││27559號卷第20│││98年9月19日下│示至ATM（自動櫃員機）解除設定云云，使││頁）││一│午2時17分許、│被害人陷於錯誤，信以為真，依指示至自動│李佳真││││同年月日晚上8│櫃員機操作接續匯款，其中二筆於98年9月│││││時5分許│19日晚上9時42分許及同年月日晚上10時29││││││分許，在台中縣大里市○○路二八二號之玉││││││山銀行大里分行自動櫃員機轉帳匯款新臺幣││││││（下同）22023元及22552元，共44575元（││││││起訴書誤載為47575元）至被告上開華南銀││││││行雙園分行帳戶中。│││├──┼───────┼───────────────────┼───┼───────┤│││真實姓名、年籍均不詳之成年女子，自稱係││郵政自動櫃員機││││網路購物服務人員，撥打電話予被害人，謊││交易明細表一份││││稱被害人日前網路購物雖已付清，然因會計││（98偵字第2755│││98年9月19日晚│登錄作業錯誤，誤登為十二期分期付款，是││9號卷第29頁）││二│上9時48分許│否欲取消分期付款云云，以及真實姓名、年│謝茂隆│││││籍均不詳之成年男子，自稱係台新銀行人員││││││，要求被害人需持台新銀行金融卡至郵局提││││││款機查詢餘額，告知餘額後依指示操作云云││││││，使被害人陷於錯誤，信以為真，依指示至││││││自動櫃員機操作，於98年9月19日晚上9時48││││││分許，在高雄縣阿蓮鄉之阿蓮郵局自動櫃員││││││機轉帳匯款29988元至被告上開華南銀行雙││││││園分行帳戶中。│││├──┴───────┴───────────────────┴───┴───────┤│合計：74563元│└──────────────────────────────────────────┘",
  "characters": {
    "judges": [
      "陳晴教",
      "王敏慧",
      "吳啟民"
    ],
    "prosecutors": [
      "劉斐玲"
    ],
    "lawyers": [

    ],
    "clerks": [
      "胡新涓"
    ],
    "plaintiffs": [

    ],
    "defendants": [
      "沈聰志"
    ],
    "prosecutor_office": [

    ],
    "creditors": [

    ],
    "debtors": [

    ],
    "judicial_associate_officer": [

    ]
  },
  "adjudged_at": "2011-01-12",
  "created_at": "2016-02-13 07:03:11",
  "updated_at": "2016-02-13 07:03:11"
}