{
  "identify": "TPH-99-上更(一)-216-20110112-1",
  "court": {
    "name": "臺灣高等法院",
    "code": "TPH"
  },
  "division": {
    "name": "刑事",
    "code": "M"
  },
  "year": 99,
  "word": "上更(一)",
  "number": "216",
  "jcheck": "1",
  "reason": "侵占等",
  "content": "臺灣高等法院刑事判決             99年度上更(一)字第216號\n上  訴  人\n即  自訴人  羅彩樺原名羅雲嬌.\n自訴代理人  林辰彥律師\n            謝玉玲律師\n            林傳哲律師\n被      告  陳重陽\n            張富傑 原名張銀.\n            許開鴻\n            翁金川\n            盧玉麟\n            孫磊樺\n            蘇雅鈴\n上列上訴人因被告等偽造文書等案件，不服臺灣臺北地方法院95\n年度自字第81號，中華民國96年11月12日第一審判決，提起上訴\n，經本院判決後，由最高法院發回更審，本院裁定如下：\n    主  文\n原判決撤銷，發回臺灣臺北地方法院。\n    理  由\n一、自訴人於原審之自訴意旨，如附件自訴狀、刑事自訴補充理\n    由（一）、（二）狀、影本所載。\n二、原判決略以：本件自訴人自訴被告等人之犯罪事實，無非係\n    以被告陳重陽係崇實優質房屋仲介股份有限公司北新加盟店\n    （以下簡稱崇實房屋北新加盟店）經理，於民國（下同）85\n    年2月26日受自訴人之委託與被告張富傑（原名張銀得）簽\n    定不動產買賣契約，將自訴人所有坐落臺北縣板橋市○○段\n    1460、1461、1462地號土地及其上3211建號之建物，門牌號\n    碼為臺北縣板橋市○○街110巷3號1樓之房屋，以新臺幣（\n    下同）1,438萬元之價格出賣予被告張富傑，嗣被告張富傑\n    以此房、地於85年6月29日向被告翁金川、許開鴻、盧玉麟\n    、孫磊樺、蘇雅鈴等人所任職之臺北區中小企業銀行（經改\n    制為臺北國際商業銀行後，現改制為永豐商業銀行）萬華分\n    行設定最高限額抵押權申請貸款，嗣被告翁金川等5人並未\n    將貸得金額撥入自訴人之帳戶內，卻於85年7月3日及同年月\n    5日逕自將貸款金額先清償原設定於系爭房地之第1順位抵押\n    權債權人後，復將餘款撥入被告張富傑之帳戶內，因而認定\n    被告等人共犯刑法詐欺取財、業務侵占貸款款項等罪嫌，另\n    以被告等人為達成上述犯罪目地，竟於核准撥款時，未經自\n    訴人親為對保手續即逕自偽造對保書，以遂行對保手續，因\n    認被告等人共涉偽造私文書罪嫌。惟查：\n(一)、被告陳重陽、張富傑被訴部分：\n１. 查上訴人即自訴人前於85年10月15日即向原審對被告陳重陽\n    、張富傑及案外人陳重陽之妻鄒樹芝提起自訴。其自訴意旨\n    略以：自訴人羅雲嬌於85年2月26日，與被告張富傑間互有\n    買賣，均委託崇實房屋北新加盟店經理陳重陽及其店中代書\n    鄒樹芝代辦理買賣過戶及向銀行貸款事宜，約定銀行撥款時\n    應通知自訴人協同撥款，如銀行尚未撥款，則另設定抵押權\n    以確保自訴人權益。當被告陳重陽得知被告張富傑需向銀行\n    貸款850萬元，認有機可乘，於簽約時把「正本」分開給自\n    訴人過目無誤，簽章後，於裝訂時即抽換首頁金額，將買賣\n    金額由950萬元改為1,438萬元，附件部份並偽填自訴人與張\n    銀得互有付款。其間自訴人曾以電話詢問被告鄒樹芝有關貸\n    款辦理情形，鄒樹芝謊稱銀行尚未撥款，於85年7月13日送\n    設定抵押權，惟實際上，被告陳重陽、張富傑、鄒樹芝已於\n    85年7月3日同赴台北區中小企業銀行辦妥貸款手續，且扣除\n    第1順位抵押後，所剩餘之375萬元，全數由被告鄒樹芝領出\n    匯入被告陳重陽帳戶，而未交付自訴人作買賣價金之尾款，\n    因認被告三人涉有共犯偽造文書、詐欺取財、背信等罪嫌。\n    經臺灣臺北地方法院於86年3月12日，以85年度自字第1023\n    號判決案外人鄒樹芝及被告陳重陽、張富傑均無罪，再經本\n    院於87年4月14日以86年度上訴字第2171號判決、最高法院\n    於89年6月15日以89年度台上字第3379號判決駁回上訴確定\n    。\n２. 自訴人復於87年12月29日以被告陳重陽及案外人鄒樹芝涉犯\n    刑法行使偽造私文書及詐欺取財罪嫌，具狀向臺灣臺北地方\n    法院檢察署提出告訴，經該署檢察官以88年度偵字第718號\n    為不起訴處分，自訴人聲請再議，經臺灣高等法院檢察署檢\n    察長認仍有續查之必要，乃簽分他案續行辦理，嗣自訴人於\n    檢察官偵查中，另以被告陳重陽於85年2月26日受告訴人羅\n    雲嬌（即本件自訴人）委託，辦理告訴人與被告張富傑間關\n    於告訴人所有坐落於臺北縣板橋市○○街110巷3號1樓房屋\n    買賣之房屋過戶及銀行貸款事宜，被告陳重陽明知告訴人與\n    被告張富傑成交之價金為950萬元，由被告陳重陽代為領取\n    銀行核撥之房屋貸款並扣除第1順位抵押權之債權額後，本\n    應將餘款3,708,467元交予賣方即告訴人，被告陳重陽竟意\n    圖為自己不法之所有，並與被告張富傑共同基於偽造私文書\n    之犯意聯絡，於同年7月20日共同偽造85年7月5日之尾款託\n    管同意書、85年7月22日之尾款取回證明書及85年7月5日之\n    羅雲嬌未到場交屋證明書共3紙，由被告陳重陽將所持有之\n    款項侵占入己，因認被告陳重陽涉犯刑法第216條、第210條\n    之行使偽造私文書罪嫌、刑法第336條之業務侵占罪嫌；被\n    告張富傑涉犯刑法第216條、第210條之行使偽造私文書罪嫌\n    而追加告訴，經檢察官偵查後，以被告陳重陽明知其代為領\n    取銀行核撥之房屋貸款於扣除第1順位抵押權之債權額後，\n    餘款3,708,467元本應交予賣方羅雲嬌（即本件自訴人羅彩\n    樺），竟與被告張富傑於85年7月20日共同偽造85年7月5日\n    之尾款託管同意書、85年7月22日之尾款取回證明書及85年7\n    月5日之羅雲嬌未到場交屋之證明書共3紙，由被告陳重陽將\n    前揭自己持有之款項侵占入己，被告陳重陽、張富傑並於臺\n    灣臺北地方法院另案審理中，連續提出前開偽造之文書，因\n    認涉犯刑法行使偽造私文書及業務侵占罪嫌，而於92年3月\n    21日以91年度調偵字第471號、92年度偵字第8813號提起公\n    訴，惟經臺灣臺北地方法院審理後，於93 年6月5日以92年\n    度訴字第1230號判決被告陳重陽被訴偽造文書部分無罪、被\n    訴業務侵占部分免訴，被告張富傑無罪，並經本院於93年10\n    月8日以93年度上訴字第2215號判決上訴駁回確定在案。上\n    揭情事，有前開各判決、本院被告前案紀錄表在卷可按。\n３. 次查，雖本件自訴代理人於原審審理時陳述之詐欺取財、偽\n    造私文書罪之犯罪時間分別為85年8月22日、85年6月24日，\n    惟徵諸自訴人所提出之不動產買賣契約書、抵押權設定契約\n    書、土地登記謄本、借據、臺北區中小企業銀行歷史明細檔\n    查詢單（戶名：張銀得、帳號：0000000000000）等證據，\n    堪認本件自訴人自訴被告陳重陽、張富傑涉犯詐欺取財、行\n    使偽造私文書、業務侵占罪之行為之事項，核與上揭臺灣臺\n    北地方法院85年度自字第1230號、92年度訴字第1230號、本\n    院86年度上訴字第2171號、93年度上訴字第2215號、最高法\n    院89年度台上字第3379號判決所認定起訴範圍之詐欺取財、\n    行使偽造私文書、業務侵占罪等情為社會事實同一，其行為\n    人（除鄒樹芝外）、行為時間、地點及行為內容均屬相同，\n    故本件自訴事實與上開確定判決認定之犯罪事實，均為同一\n    案件，應堪認定。而前開判決既已判決確定，基於審判不可\n    分之關係，該確定判決之既判力，自應及於本件自訴被告陳\n    重陽、張富傑之犯罪事實。是自訴人於95年6月23日就同一\n    案件事實提起自訴，揆諸前揭規定，自訴人就此部分自訴，\n    尚非合法，應諭知免訴判決。\n(二)、被告許開鴻、翁金川、盧玉麟、孫磊樺、蘇雅玲被訴部分：\n１. 查本件上訴人即自訴人前於87年2月16日，即以被告翁金川、\n    許開鴻、盧玉麟、孫磊樺、蘇雅鈴等人（下稱被告翁金川等\n     5人）於任職臺北區中小企業銀行時，因被告張富傑意圖為\n    自己不法所有於85年2月26日，以950萬元向自訴人購買臺北\n    縣板橋市○○街11巷3號1樓房屋及其座落基地為由，致告訴\n    人陷於錯誤而同意出售，詎被告翁金川等5人明知張富傑不\n    欲履行契約，亦無移交居住接掌之權力，竟與張富傑共同基\n    於奪占自訴人房屋之犯意聯絡，於85年6月24日共同偽造價\n    金為1,400萬元之買賣契約，並於所有權尚未移轉於張富傑\n    前，即同意張富傑以上述房、地申請貸款，並由明知上情亦\n    具共同犯意之吳鳳珠任連帶保證人，並於自訴人上開房地上\n    ，設定第二順位抵押權500萬元，並撥款予張富傑，且未經\n    其同意而將475萬元匯入自訴人帳戶內，偽造台北區中小企\n    業銀行劃收申請書放款代收人傳票。嗣張富傑就其所貸款項\n    無法清償，被告翁金川等人即以臺北區中小企業銀行名義聲\n    請法院執行拍賣上開房、地，並請陳仲洲、吳宗南任名義人\n    前往拍得上開房、地，復陳仲洲、吳宗南亦多次恐嚇要自訴\n    人搬遷，否則將自訴人屍填大海等語，而被告翁金川等即以\n    此方式奪取自訴人上開房、地。因認被告翁金川等涉有瀆職\n    、偽造公文書、私文書、恐嚇、詐欺、背信等罪嫌云云，而\n    向臺灣板橋地方法院檢察署提出告訴，經該署檢察官調查後\n    認被告翁金川等5人被訴瀆職、偽造公文書、私文書、詐欺\n    、背信等犯罪嫌疑不足，於88 年1月28日以87年度偵字第\n    19134號不起訴處分書為不起訴處分，嗣自訴人不服該處分\n    而聲請再議，經臺灣高等法院檢察署檢察長調查審酌後，亦\n    認被告翁金川等5人犯罪嫌疑不足，於88年4月29日以88年度\n    議字第1281號處分書駁回再議確定等情，有上開不起訴處分\n    書、駁回再議處分書各1 件附卷可稽。\n２. 核本件自訴人自訴被告翁金川等5人涉犯幫助詐欺取財等犯\n    罪行為之事實，與自訴人於上揭偵查案件中被告被訴之犯罪\n    事實相同，其行為人、行為時間、地點及行為內容均屬相同\n    ，雖就買賣金額、貸款金額記載略有出入，但就本件自訴人\n    卷附所示之不動產買賣契約書、抵押權設定契約書、土地登\n    記謄本、借據、臺北區中小企業銀行歷史明細檔查詢單（戶\n    名：張銀得、帳號：0000000000000）等證據與前開偵查案\n    件中所附證據參酌對照後均屬相同資料，堪認本件自訴案件\n    所訴事實與前開偵查案件中所認定事實均屬相同。則本案自\n    訴人於95年6月23日再以被告翁金川、許開鴻、盧玉麟、孫\n    磊樺及蘇雅鈴等人之同一犯罪事實提起自訴（有臺灣臺北地\n    方法院收文戳記可憑），其此部分所為自訴，係對檢察官依\n    刑事訴訟法第228條規定開始偵查之同一案件，為不起訴處\n    分確定後，再行自訴，依照上開說明，應諭知不受理之判決\n    。\n(三)、另自訴人於自訴狀及補充理由狀上雖載其與被告張富傑所簽\n    定之買賣契約係基於虛偽之意思表示而屬無效，故系爭房地\n    所有權仍屬自訴人所有而未移轉於被告張富傑，然被告翁金\n    川等5人明知自訴人與臺北區中小企業銀行間並無債權債務\n    關係，亦無積欠任何款項未給付，仍行使假債權而將其所有\n    系爭之房地，向法院聲請拍賣受償，致使案外人陳仲洲、吳\n    宗南共同以750萬標得系爭房地，並由臺北區中小企業銀行\n    萬華分行分配領走此款項，而獲得不法利益，因認被告翁金\n    川等5人涉犯刑法第339條之3第1項、第2項之詐欺罪及同法\n    第336條第2項業務侵占罪嫌。惟按刑法第339條之3第1項、\n    第2項之非法以電腦設備相關設備製作不實財產權得喪變更\n    紀錄取得他人財產及不法利益罪，其構成要件乃以行為人將\n    虛偽資料或不正指令輸入電腦或其相關設備，而製作不實之\n    財產紀錄以取得他人之財產或因此獲得不法利益始相當，又\n    刑法第336條第2項之業務侵占罪係意圖為自己或第三人不法\n    之所有，將因業務上持有之物品，變異原持有之意思為所有\n    之意思，而加以侵占為構成要件，然據自訴狀及自訴補充理\n    由狀所載，自訴人之主張係被告翁金川等5人以虛偽之債權\n    向法院聲請拍賣自訴人所有之房地，並將拍賣所得750萬元\n    款項領走未返還於自訴人，並非被告翁金川等5人以電腦設\n    備或相關設備製作不實財產權得喪變更紀錄，且被告翁金川\n    等5人自始即以行使其訴訟上之權利而為主張，亦無為自訴\n    人持有之意思而占有，顯與刑法第339條之3第1項、第2項非\n    法以電腦設備相關設備製作不實財產權得喪變更紀錄取財罪\n    及第336條第2項業務侵占罪之構成要件無涉，是自訴狀另引\n    上開法條為論罪依據，容有誤會，本院於裁判時得僅就被告\n    被訴之事實範圍內審理，不受自訴狀所引犯罪法條之拘束，\n    本院對自訴事實之法律評價不受自訴人引用法條或自訴人之\n    法律判斷之限制，而應依自訴之社會事實作為法律評價之基\n    準，是本院審酌此自訴事實與前開告訴案件中所訴之犯罪事\n    實，衡為相同之事實，且為前開不起訴處分書及駁回再議處\n    分書於理由中詳加論述，而為前開不起訴處分效力所包括，\n    自不因自訴人於自訴狀中引用之法條不同而受拘束，仍屬刑\n    事訴訟法第323條所規定之不得提起自訴之案件，依法自應\n    為不受理判決。\n三、惟查，原判決係以自訴人自訴陳重陽、張富傑之犯罪事實，\n    核與臺灣台北地方法院85年度自字第1023號（原判決誤載為\n    85年度自字第1230號）、本院86年度上訴字第2171號、最高\n    法院89年度台上字第3379號、臺灣台北地方法院92年度訴字\n    第1230號、本院93年度上訴字第2215號等刑事確定判決，係\n    屬社會事實相同之同一案件，本件關於陳重陽、張富傑部分\n    為該等確定刑事判決之既判力所及，而就彼等二人部分為免\n    訴之諭知；另就自訴人自訴被告許開鴻、翁金川、盧玉麟、\n    孫磊樺、蘇雅玲之犯罪事實，核與台灣板橋地方法院檢察署\n    87年度偵字第19134號不起訴處分書、臺灣高等法院檢察署\n    88年度議字第1281號處分書，係屬事實相同之同一案件，上\n    訴人此部分之自訴，係對檢察官開始偵查之同一案件，為不\n    起訴處分後再行自訴，依刑事訴訟法第323條第1 項之規定\n    ，而就被告許開鴻、翁金川、盧玉麟、孫磊樺、蘇雅鈴等五\n    人為不受理之諭知，固非無見。惟對於自訴人於自訴狀所載\n    之自訴事實（二）所載：被告陳重陽意圖為自己不法之所有\n    ，與被告張富傑與被告許開鴻等人為共同侵害自訴人出售係\n    爭房屋土地給張富傑所應得之價款及貸款，於核准撥款前，\n    未曾對於自訴人辦理合法之對保手續，則被告等為達成上述\n    犯罪目的，顯有未經上訴人親自為對保手續，而逕自偽造上\n    訴人名義之對保書，以遂行對保手續之情，與前開被告陳重\n    陽、張富傑之刑事確定刑決、前開被告許開鴻等人之不起訴\n    處分內容是否係屬同一案件，原判決未予論述；再者，就此\n    部分，業經本院函詢永豐商業銀行萬華分行查詢有關自訴人\n    與被告張富傑（原名張銀得）於85年6月29日因系爭房地買\n    賣向該銀行設定最高限額抵押授權申請貸款留存資料，經該\n    行函覆稱並無借貸申請書、撥款同意書及對保書暨撥款同意\n    書等文件，有該行99年7月15日永豐銀萬華分行（99）字第8\n    號函在卷可稽（見本院卷第132頁）；再經本院函調該行信\n    用部門有關徵信及授信作業手冊等相關資料，該行函覆：「\n    三、2.『貸款申請書』即本行於99年7月15日函復所提供之\n    『授信申請書』。3.本案並無『撥款同意書』之文件。4.本\n    案並無『對保書暨撥款同意書』之文件」，亦檢附該行於85\n    年6月間有關貸款之徵信及授信作業手冊（核貸通知、簽約\n    對保、設定擔保物權、撥付貸款、帳務處理等手續應注意事\n    項），此有該行99年10月8日永豐銀萬華分行（99）字第11\n    號函附卷可按（本院卷第198頁）。由上開函查結果可知，\n    該行並無借貸申請書、撥款同意書、對保書暨撥款同意書等\n    文件，自無從證明被告陳重陽、張富傑、許開鴻、翁金川、\n    盧玉麟、孫磊樺、蘇雅鈴等人有自訴意旨所稱被告等人未經\n    自訴人親自為對保手續，而逕自偽造上訴人名義之對保書，\n    以遂行對保手續等行為，則自訴人自訴被告等此部分之犯罪\n    嫌疑顯有不足，則本件是否仍可依刑事訴訟法第302條第1款\n    、第323條第1項規定，遽為免訴及自訴不受理判決，抑或應\n    就此部分另行處理，自有再加研求之餘地。自訴人指摘原判\n    決不當，非無理由，爰由本院將原判決撤銷發回原審法院另\n    為適當之處理，並不經言詞辯論為之。\n四、據上論斷，應依刑事訴訟法第369條第1項但書、第372條，\n    判決如主文。\n中    華    民    國  100    年    1    月    12    日\n            刑事第二十三庭審判長法  官  童有德\n                                法  官  陳祐治\n                                法  官  徐蘭萍\n以上正本證明與原本無異。\n如不服本判決，應於收受送達後10日內向本院提出上訴書狀，其\n未敘述上訴之理由者並得於提起上訴後10日內向本院補提理由書\n（均須按他造當事人之人數附繕本）「切勿逕送上級法院」。\n                                書記官  林月蓉\n中    華    民    國  100    年    1    月    12    日",
  "structure": {
    "main": "原判決撤銷，發回臺灣臺北地方法院。",
    "reason": "一、自訴人於原審之自訴意旨，如附件自訴狀、刑事自訴補充理\n    由（一）、（二）狀、影本所載。\n二、原判決略以：本件自訴人自訴被告等人之犯罪事實，無非係\n    以被告陳重陽係崇實優質房屋仲介股份有限公司北新加盟店\n    （以下簡稱崇實房屋北新加盟店）經理，於民國（下同）85\n    年2月26日受自訴人之委託與被告張富傑（原名張銀得）簽\n    定不動產買賣契約，將自訴人所有坐落臺北縣板橋市○○段\n    1460、1461、1462地號土地及其上3211建號之建物，門牌號\n    碼為臺北縣板橋市○○街110巷3號1樓之房屋，以新臺幣（\n    下同）1,438萬元之價格出賣予被告張富傑，嗣被告張富傑\n    以此房、地於85年6月29日向被告翁金川、許開鴻、盧玉麟\n    、孫磊樺、蘇雅鈴等人所任職之臺北區中小企業銀行（經改\n    制為臺北國際商業銀行後，現改制為永豐商業銀行）萬華分\n    行設定最高限額抵押權申請貸款，嗣被告翁金川等5人並未\n    將貸得金額撥入自訴人之帳戶內，卻於85年7月3日及同年月\n    5日逕自將貸款金額先清償原設定於系爭房地之第1順位抵押\n    權債權人後，復將餘款撥入被告張富傑之帳戶內，因而認定\n    被告等人共犯刑法詐欺取財、業務侵占貸款款項等罪嫌，另\n    以被告等人為達成上述犯罪目地，竟於核准撥款時，未經自\n    訴人親為對保手續即逕自偽造對保書，以遂行對保手續，因\n    認被告等人共涉偽造私文書罪嫌。惟查：\n(一)、被告陳重陽、張富傑被訴部分：\n１. 查上訴人即自訴人前於85年10月15日即向原審對被告陳重陽\n    、張富傑及案外人陳重陽之妻鄒樹芝提起自訴。其自訴意旨\n    略以：自訴人羅雲嬌於85年2月26日，與被告張富傑間互有\n    買賣，均委託崇實房屋北新加盟店經理陳重陽及其店中代書\n    鄒樹芝代辦理買賣過戶及向銀行貸款事宜，約定銀行撥款時\n    應通知自訴人協同撥款，如銀行尚未撥款，則另設定抵押權\n    以確保自訴人權益。當被告陳重陽得知被告張富傑需向銀行\n    貸款850萬元，認有機可乘，於簽約時把「正本」分開給自\n    訴人過目無誤，簽章後，於裝訂時即抽換首頁金額，將買賣\n    金額由950萬元改為1,438萬元，附件部份並偽填自訴人與張\n    銀得互有付款。其間自訴人曾以電話詢問被告鄒樹芝有關貸\n    款辦理情形，鄒樹芝謊稱銀行尚未撥款，於85年7月13日送\n    設定抵押權，惟實際上，被告陳重陽、張富傑、鄒樹芝已於\n    85年7月3日同赴台北區中小企業銀行辦妥貸款手續，且扣除\n    第1順位抵押後，所剩餘之375萬元，全數由被告鄒樹芝領出\n    匯入被告陳重陽帳戶，而未交付自訴人作買賣價金之尾款，\n    因認被告三人涉有共犯偽造文書、詐欺取財、背信等罪嫌。\n    經臺灣臺北地方法院於86年3月12日，以85年度自字第1023\n    號判決案外人鄒樹芝及被告陳重陽、張富傑均無罪，再經本\n    院於87年4月14日以86年度上訴字第2171號判決、最高法院\n    於89年6月15日以89年度台上字第3379號判決駁回上訴確定\n    。\n２. 自訴人復於87年12月29日以被告陳重陽及案外人鄒樹芝涉犯\n    刑法行使偽造私文書及詐欺取財罪嫌，具狀向臺灣臺北地方\n    法院檢察署提出告訴，經該署檢察官以88年度偵字第718號\n    為不起訴處分，自訴人聲請再議，經臺灣高等法院檢察署檢\n    察長認仍有續查之必要，乃簽分他案續行辦理，嗣自訴人於\n    檢察官偵查中，另以被告陳重陽於85年2月26日受告訴人羅\n    雲嬌（即本件自訴人）委託，辦理告訴人與被告張富傑間關\n    於告訴人所有坐落於臺北縣板橋市○○街110巷3號1樓房屋\n    買賣之房屋過戶及銀行貸款事宜，被告陳重陽明知告訴人與\n    被告張富傑成交之價金為950萬元，由被告陳重陽代為領取\n    銀行核撥之房屋貸款並扣除第1順位抵押權之債權額後，本\n    應將餘款3,708,467元交予賣方即告訴人，被告陳重陽竟意\n    圖為自己不法之所有，並與被告張富傑共同基於偽造私文書\n    之犯意聯絡，於同年7月20日共同偽造85年7月5日之尾款託\n    管同意書、85年7月22日之尾款取回證明書及85年7月5日之\n    羅雲嬌未到場交屋證明書共3紙，由被告陳重陽將所持有之\n    款項侵占入己，因認被告陳重陽涉犯刑法第216條、第210條\n    之行使偽造私文書罪嫌、刑法第336條之業務侵占罪嫌；被\n    告張富傑涉犯刑法第216條、第210條之行使偽造私文書罪嫌\n    而追加告訴，經檢察官偵查後，以被告陳重陽明知其代為領\n    取銀行核撥之房屋貸款於扣除第1順位抵押權之債權額後，\n    餘款3,708,467元本應交予賣方羅雲嬌（即本件自訴人羅彩\n    樺），竟與被告張富傑於85年7月20日共同偽造85年7月5日\n    之尾款託管同意書、85年7月22日之尾款取回證明書及85年7\n    月5日之羅雲嬌未到場交屋之證明書共3紙，由被告陳重陽將\n    前揭自己持有之款項侵占入己，被告陳重陽、張富傑並於臺\n    灣臺北地方法院另案審理中，連續提出前開偽造之文書，因\n    認涉犯刑法行使偽造私文書及業務侵占罪嫌，而於92年3月\n    21日以91年度調偵字第471號、92年度偵字第8813號提起公\n    訴，惟經臺灣臺北地方法院審理後，於93 年6月5日以92年\n    度訴字第1230號判決被告陳重陽被訴偽造文書部分無罪、被\n    訴業務侵占部分免訴，被告張富傑無罪，並經本院於93年10\n    月8日以93年度上訴字第2215號判決上訴駁回確定在案。上\n    揭情事，有前開各判決、本院被告前案紀錄表在卷可按。\n３. 次查，雖本件自訴代理人於原審審理時陳述之詐欺取財、偽\n    造私文書罪之犯罪時間分別為85年8月22日、85年6月24日，\n    惟徵諸自訴人所提出之不動產買賣契約書、抵押權設定契約\n    書、土地登記謄本、借據、臺北區中小企業銀行歷史明細檔\n    查詢單（戶名：張銀得、帳號：0000000000000）等證據，\n    堪認本件自訴人自訴被告陳重陽、張富傑涉犯詐欺取財、行\n    使偽造私文書、業務侵占罪之行為之事項，核與上揭臺灣臺\n    北地方法院85年度自字第1230號、92年度訴字第1230號、本\n    院86年度上訴字第2171號、93年度上訴字第2215號、最高法\n    院89年度台上字第3379號判決所認定起訴範圍之詐欺取財、\n    行使偽造私文書、業務侵占罪等情為社會事實同一，其行為\n    人（除鄒樹芝外）、行為時間、地點及行為內容均屬相同，\n    故本件自訴事實與上開確定判決認定之犯罪事實，均為同一\n    案件，應堪認定。而前開判決既已判決確定，基於審判不可\n    分之關係，該確定判決之既判力，自應及於本件自訴被告陳\n    重陽、張富傑之犯罪事實。是自訴人於95年6月23日就同一\n    案件事實提起自訴，揆諸前揭規定，自訴人就此部分自訴，\n    尚非合法，應諭知免訴判決。\n(二)、被告許開鴻、翁金川、盧玉麟、孫磊樺、蘇雅玲被訴部分：\n１. 查本件上訴人即自訴人前於87年2月16日，即以被告翁金川、\n    許開鴻、盧玉麟、孫磊樺、蘇雅鈴等人（下稱被告翁金川等\n     5人）於任職臺北區中小企業銀行時，因被告張富傑意圖為\n    自己不法所有於85年2月26日，以950萬元向自訴人購買臺北\n    縣板橋市○○街11巷3號1樓房屋及其座落基地為由，致告訴\n    人陷於錯誤而同意出售，詎被告翁金川等5人明知張富傑不\n    欲履行契約，亦無移交居住接掌之權力，竟與張富傑共同基\n    於奪占自訴人房屋之犯意聯絡，於85年6月24日共同偽造價\n    金為1,400萬元之買賣契約，並於所有權尚未移轉於張富傑\n    前，即同意張富傑以上述房、地申請貸款，並由明知上情亦\n    具共同犯意之吳鳳珠任連帶保證人，並於自訴人上開房地上\n    ，設定第二順位抵押權500萬元，並撥款予張富傑，且未經\n    其同意而將475萬元匯入自訴人帳戶內，偽造台北區中小企\n    業銀行劃收申請書放款代收人傳票。嗣張富傑就其所貸款項\n    無法清償，被告翁金川等人即以臺北區中小企業銀行名義聲\n    請法院執行拍賣上開房、地，並請陳仲洲、吳宗南任名義人\n    前往拍得上開房、地，復陳仲洲、吳宗南亦多次恐嚇要自訴\n    人搬遷，否則將自訴人屍填大海等語，而被告翁金川等即以\n    此方式奪取自訴人上開房、地。因認被告翁金川等涉有瀆職\n    、偽造公文書、私文書、恐嚇、詐欺、背信等罪嫌云云，而\n    向臺灣板橋地方法院檢察署提出告訴，經該署檢察官調查後\n    認被告翁金川等5人被訴瀆職、偽造公文書、私文書、詐欺\n    、背信等犯罪嫌疑不足，於88 年1月28日以87年度偵字第\n    19134號不起訴處分書為不起訴處分，嗣自訴人不服該處分\n    而聲請再議，經臺灣高等法院檢察署檢察長調查審酌後，亦\n    認被告翁金川等5人犯罪嫌疑不足，於88年4月29日以88年度\n    議字第1281號處分書駁回再議確定等情，有上開不起訴處分\n    書、駁回再議處分書各1 件附卷可稽。\n２. 核本件自訴人自訴被告翁金川等5人涉犯幫助詐欺取財等犯\n    罪行為之事實，與自訴人於上揭偵查案件中被告被訴之犯罪\n    事實相同，其行為人、行為時間、地點及行為內容均屬相同\n    ，雖就買賣金額、貸款金額記載略有出入，但就本件自訴人\n    卷附所示之不動產買賣契約書、抵押權設定契約書、土地登\n    記謄本、借據、臺北區中小企業銀行歷史明細檔查詢單（戶\n    名：張銀得、帳號：0000000000000）等證據與前開偵查案\n    件中所附證據參酌對照後均屬相同資料，堪認本件自訴案件\n    所訴事實與前開偵查案件中所認定事實均屬相同。則本案自\n    訴人於95年6月23日再以被告翁金川、許開鴻、盧玉麟、孫\n    磊樺及蘇雅鈴等人之同一犯罪事實提起自訴（有臺灣臺北地\n    方法院收文戳記可憑），其此部分所為自訴，係對檢察官依\n    刑事訴訟法第228條規定開始偵查之同一案件，為不起訴處\n    分確定後，再行自訴，依照上開說明，應諭知不受理之判決\n    。\n(三)、另自訴人於自訴狀及補充理由狀上雖載其與被告張富傑所簽\n    定之買賣契約係基於虛偽之意思表示而屬無效，故系爭房地\n    所有權仍屬自訴人所有而未移轉於被告張富傑，然被告翁金\n    川等5人明知自訴人與臺北區中小企業銀行間並無債權債務\n    關係，亦無積欠任何款項未給付，仍行使假債權而將其所有\n    系爭之房地，向法院聲請拍賣受償，致使案外人陳仲洲、吳\n    宗南共同以750萬標得系爭房地，並由臺北區中小企業銀行\n    萬華分行分配領走此款項，而獲得不法利益，因認被告翁金\n    川等5人涉犯刑法第339條之3第1項、第2項之詐欺罪及同法\n    第336條第2項業務侵占罪嫌。惟按刑法第339條之3第1項、\n    第2項之非法以電腦設備相關設備製作不實財產權得喪變更\n    紀錄取得他人財產及不法利益罪，其構成要件乃以行為人將\n    虛偽資料或不正指令輸入電腦或其相關設備，而製作不實之\n    財產紀錄以取得他人之財產或因此獲得不法利益始相當，又\n    刑法第336條第2項之業務侵占罪係意圖為自己或第三人不法\n    之所有，將因業務上持有之物品，變異原持有之意思為所有\n    之意思，而加以侵占為構成要件，然據自訴狀及自訴補充理\n    由狀所載，自訴人之主張係被告翁金川等5人以虛偽之債權\n    向法院聲請拍賣自訴人所有之房地，並將拍賣所得750萬元\n    款項領走未返還於自訴人，並非被告翁金川等5人以電腦設\n    備或相關設備製作不實財產權得喪變更紀錄，且被告翁金川\n    等5人自始即以行使其訴訟上之權利而為主張，亦無為自訴\n    人持有之意思而占有，顯與刑法第339條之3第1項、第2項非\n    法以電腦設備相關設備製作不實財產權得喪變更紀錄取財罪\n    及第336條第2項業務侵占罪之構成要件無涉，是自訴狀另引\n    上開法條為論罪依據，容有誤會，本院於裁判時得僅就被告\n    被訴之事實範圍內審理，不受自訴狀所引犯罪法條之拘束，\n    本院對自訴事實之法律評價不受自訴人引用法條或自訴人之\n    法律判斷之限制，而應依自訴之社會事實作為法律評價之基\n    準，是本院審酌此自訴事實與前開告訴案件中所訴之犯罪事\n    實，衡為相同之事實，且為前開不起訴處分書及駁回再議處\n    分書於理由中詳加論述，而為前開不起訴處分效力所包括，\n    自不因自訴人於自訴狀中引用之法條不同而受拘束，仍屬刑\n    事訴訟法第323條所規定之不得提起自訴之案件，依法自應\n    為不受理判決。\n三、惟查，原判決係以自訴人自訴陳重陽、張富傑之犯罪事實，\n    核與臺灣台北地方法院85年度自字第1023號（原判決誤載為\n    85年度自字第1230號）、本院86年度上訴字第2171號、最高\n    法院89年度台上字第3379號、臺灣台北地方法院92年度訴字\n    第1230號、本院93年度上訴字第2215號等刑事確定判決，係\n    屬社會事實相同之同一案件，本件關於陳重陽、張富傑部分\n    為該等確定刑事判決之既判力所及，而就彼等二人部分為免\n    訴之諭知；另就自訴人自訴被告許開鴻、翁金川、盧玉麟、\n    孫磊樺、蘇雅玲之犯罪事實，核與台灣板橋地方法院檢察署\n    87年度偵字第19134號不起訴處分書、臺灣高等法院檢察署\n    88年度議字第1281號處分書，係屬事實相同之同一案件，上\n    訴人此部分之自訴，係對檢察官開始偵查之同一案件，為不\n    起訴處分後再行自訴，依刑事訴訟法第323條第1 項之規定\n    ，而就被告許開鴻、翁金川、盧玉麟、孫磊樺、蘇雅鈴等五\n    人為不受理之諭知，固非無見。惟對於自訴人於自訴狀所載\n    之自訴事實（二）所載：被告陳重陽意圖為自己不法之所有\n    ，與被告張富傑與被告許開鴻等人為共同侵害自訴人出售係\n    爭房屋土地給張富傑所應得之價款及貸款，於核准撥款前，\n    未曾對於自訴人辦理合法之對保手續，則被告等為達成上述\n    犯罪目的，顯有未經上訴人親自為對保手續，而逕自偽造上\n    訴人名義之對保書，以遂行對保手續之情，與前開被告陳重\n    陽、張富傑之刑事確定刑決、前開被告許開鴻等人之不起訴\n    處分內容是否係屬同一案件，原判決未予論述；再者，就此\n    部分，業經本院函詢永豐商業銀行萬華分行查詢有關自訴人\n    與被告張富傑（原名張銀得）於85年6月29日因系爭房地買\n    賣向該銀行設定最高限額抵押授權申請貸款留存資料，經該\n    行函覆稱並無借貸申請書、撥款同意書及對保書暨撥款同意\n    書等文件，有該行99年7月15日永豐銀萬華分行（99）字第8\n    號函在卷可稽（見本院卷第132頁）；再經本院函調該行信\n    用部門有關徵信及授信作業手冊等相關資料，該行函覆：「\n    三、2.『貸款申請書』即本行於99年7月15日函復所提供之\n    『授信申請書』。3.本案並無『撥款同意書』之文件。4.本\n    案並無『對保書暨撥款同意書』之文件」，亦檢附該行於85\n    年6月間有關貸款之徵信及授信作業手冊（核貸通知、簽約\n    對保、設定擔保物權、撥付貸款、帳務處理等手續應注意事\n    項），此有該行99年10月8日永豐銀萬華分行（99）字第11\n    號函附卷可按（本院卷第198頁）。由上開函查結果可知，\n    該行並無借貸申請書、撥款同意書、對保書暨撥款同意書等\n    文件，自無從證明被告陳重陽、張富傑、許開鴻、翁金川、\n    盧玉麟、孫磊樺、蘇雅鈴等人有自訴意旨所稱被告等人未經\n    自訴人親自為對保手續，而逕自偽造上訴人名義之對保書，\n    以遂行對保手續等行為，則自訴人自訴被告等此部分之犯罪\n    嫌疑顯有不足，則本件是否仍可依刑事訴訟法第302條第1款\n    、第323條第1項規定，遽為免訴及自訴不受理判決，抑或應\n    就此部分另行處理，自有再加研求之餘地。自訴人指摘原判\n    決不當，非無理由，爰由本院將原判決撤銷發回原審法院另\n    為適當之處理，並不經言詞辯論為之。\n四、據上論斷，應依刑事訴訟法第369條第1項但書、第372條，\n    判決如主文。"
  },
  "search": "臺灣高等法院刑事判決99年度上更(一)字第216號上訴人即自訴人羅彩樺原名羅雲嬌.自訴代理人林辰彥律師謝玉玲律師林傳哲律師被告陳重陽張富傑原名張銀.許開鴻翁金川盧玉麟孫磊樺蘇雅鈴上列上訴人因被告等偽造文書等案件，不服臺灣臺北地方法院95年度自字第81號，中華民國96年11月12日第一審判決，提起上訴，經本院判決後，由最高法院發回更審，本院裁定如下：主文原判決撤銷，發回臺灣臺北地方法院。理由一、自訴人於原審之自訴意旨，如附件自訴狀、刑事自訴補充理由（一）、（二）狀、影本所載。二、原判決略以：本件自訴人自訴被告等人之犯罪事實，無非係以被告陳重陽係崇實優質房屋仲介股份有限公司北新加盟店（以下簡稱崇實房屋北新加盟店）經理，於民國（下同）85年2月26日受自訴人之委託與被告張富傑（原名張銀得）簽定不動產買賣契約，將自訴人所有坐落臺北縣板橋市○○段1460、1461、1462地號土地及其上3211建號之建物，門牌號碼為臺北縣板橋市○○街110巷3號1樓之房屋，以新臺幣（下同）1,438萬元之價格出賣予被告張富傑，嗣被告張富傑以此房、地於85年6月29日向被告翁金川、許開鴻、盧玉麟、孫磊樺、蘇雅鈴等人所任職之臺北區中小企業銀行（經改制為臺北國際商業銀行後，現改制為永豐商業銀行）萬華分行設定最高限額抵押權申請貸款，嗣被告翁金川等5人並未將貸得金額撥入自訴人之帳戶內，卻於85年7月3日及同年月5日逕自將貸款金額先清償原設定於系爭房地之第1順位抵押權債權人後，復將餘款撥入被告張富傑之帳戶內，因而認定被告等人共犯刑法詐欺取財、業務侵占貸款款項等罪嫌，另以被告等人為達成上述犯罪目地，竟於核准撥款時，未經自訴人親為對保手續即逕自偽造對保書，以遂行對保手續，因認被告等人共涉偽造私文書罪嫌。惟查：(一)、被告陳重陽、張富傑被訴部分：１.查上訴人即自訴人前於85年10月15日即向原審對被告陳重陽、張富傑及案外人陳重陽之妻鄒樹芝提起自訴。其自訴意旨略以：自訴人羅雲嬌於85年2月26日，與被告張富傑間互有買賣，均委託崇實房屋北新加盟店經理陳重陽及其店中代書鄒樹芝代辦理買賣過戶及向銀行貸款事宜，約定銀行撥款時應通知自訴人協同撥款，如銀行尚未撥款，則另設定抵押權以確保自訴人權益。當被告陳重陽得知被告張富傑需向銀行貸款850萬元，認有機可乘，於簽約時把「正本」分開給自訴人過目無誤，簽章後，於裝訂時即抽換首頁金額，將買賣金額由950萬元改為1,438萬元，附件部份並偽填自訴人與張銀得互有付款。其間自訴人曾以電話詢問被告鄒樹芝有關貸款辦理情形，鄒樹芝謊稱銀行尚未撥款，於85年7月13日送設定抵押權，惟實際上，被告陳重陽、張富傑、鄒樹芝已於85年7月3日同赴台北區中小企業銀行辦妥貸款手續，且扣除第1順位抵押後，所剩餘之375萬元，全數由被告鄒樹芝領出匯入被告陳重陽帳戶，而未交付自訴人作買賣價金之尾款，因認被告三人涉有共犯偽造文書、詐欺取財、背信等罪嫌。經臺灣臺北地方法院於86年3月12日，以85年度自字第1023號判決案外人鄒樹芝及被告陳重陽、張富傑均無罪，再經本院於87年4月14日以86年度上訴字第2171號判決、最高法院於89年6月15日以89年度台上字第3379號判決駁回上訴確定。２.自訴人復於87年12月29日以被告陳重陽及案外人鄒樹芝涉犯刑法行使偽造私文書及詐欺取財罪嫌，具狀向臺灣臺北地方法院檢察署提出告訴，經該署檢察官以88年度偵字第718號為不起訴處分，自訴人聲請再議，經臺灣高等法院檢察署檢察長認仍有續查之必要，乃簽分他案續行辦理，嗣自訴人於檢察官偵查中，另以被告陳重陽於85年2月26日受告訴人羅雲嬌（即本件自訴人）委託，辦理告訴人與被告張富傑間關於告訴人所有坐落於臺北縣板橋市○○街110巷3號1樓房屋買賣之房屋過戶及銀行貸款事宜，被告陳重陽明知告訴人與被告張富傑成交之價金為950萬元，由被告陳重陽代為領取銀行核撥之房屋貸款並扣除第1順位抵押權之債權額後，本應將餘款3,708,467元交予賣方即告訴人，被告陳重陽竟意圖為自己不法之所有，並與被告張富傑共同基於偽造私文書之犯意聯絡，於同年7月20日共同偽造85年7月5日之尾款託管同意書、85年7月22日之尾款取回證明書及85年7月5日之羅雲嬌未到場交屋證明書共3紙，由被告陳重陽將所持有之款項侵占入己，因認被告陳重陽涉犯刑法第216條、第210條之行使偽造私文書罪嫌、刑法第336條之業務侵占罪嫌；被告張富傑涉犯刑法第216條、第210條之行使偽造私文書罪嫌而追加告訴，經檢察官偵查後，以被告陳重陽明知其代為領取銀行核撥之房屋貸款於扣除第1順位抵押權之債權額後，餘款3,708,467元本應交予賣方羅雲嬌（即本件自訴人羅彩樺），竟與被告張富傑於85年7月20日共同偽造85年7月5日之尾款託管同意書、85年7月22日之尾款取回證明書及85年7月5日之羅雲嬌未到場交屋之證明書共3紙，由被告陳重陽將前揭自己持有之款項侵占入己，被告陳重陽、張富傑並於臺灣臺北地方法院另案審理中，連續提出前開偽造之文書，因認涉犯刑法行使偽造私文書及業務侵占罪嫌，而於92年3月21日以91年度調偵字第471號、92年度偵字第8813號提起公訴，惟經臺灣臺北地方法院審理後，於93年6月5日以92年度訴字第1230號判決被告陳重陽被訴偽造文書部分無罪、被訴業務侵占部分免訴，被告張富傑無罪，並經本院於93年10月8日以93年度上訴字第2215號判決上訴駁回確定在案。上揭情事，有前開各判決、本院被告前案紀錄表在卷可按。３.次查，雖本件自訴代理人於原審審理時陳述之詐欺取財、偽造私文書罪之犯罪時間分別為85年8月22日、85年6月24日，惟徵諸自訴人所提出之不動產買賣契約書、抵押權設定契約書、土地登記謄本、借據、臺北區中小企業銀行歷史明細檔查詢單（戶名：張銀得、帳號：0000000000000）等證據，堪認本件自訴人自訴被告陳重陽、張富傑涉犯詐欺取財、行使偽造私文書、業務侵占罪之行為之事項，核與上揭臺灣臺北地方法院85年度自字第1230號、92年度訴字第1230號、本院86年度上訴字第2171號、93年度上訴字第2215號、最高法院89年度台上字第3379號判決所認定起訴範圍之詐欺取財、行使偽造私文書、業務侵占罪等情為社會事實同一，其行為人（除鄒樹芝外）、行為時間、地點及行為內容均屬相同，故本件自訴事實與上開確定判決認定之犯罪事實，均為同一案件，應堪認定。而前開判決既已判決確定，基於審判不可分之關係，該確定判決之既判力，自應及於本件自訴被告陳重陽、張富傑之犯罪事實。是自訴人於95年6月23日就同一案件事實提起自訴，揆諸前揭規定，自訴人就此部分自訴，尚非合法，應諭知免訴判決。(二)、被告許開鴻、翁金川、盧玉麟、孫磊樺、蘇雅玲被訴部分：１.查本件上訴人即自訴人前於87年2月16日，即以被告翁金川、許開鴻、盧玉麟、孫磊樺、蘇雅鈴等人（下稱被告翁金川等5人）於任職臺北區中小企業銀行時，因被告張富傑意圖為自己不法所有於85年2月26日，以950萬元向自訴人購買臺北縣板橋市○○街11巷3號1樓房屋及其座落基地為由，致告訴人陷於錯誤而同意出售，詎被告翁金川等5人明知張富傑不欲履行契約，亦無移交居住接掌之權力，竟與張富傑共同基於奪占自訴人房屋之犯意聯絡，於85年6月24日共同偽造價金為1,400萬元之買賣契約，並於所有權尚未移轉於張富傑前，即同意張富傑以上述房、地申請貸款，並由明知上情亦具共同犯意之吳鳳珠任連帶保證人，並於自訴人上開房地上，設定第二順位抵押權500萬元，並撥款予張富傑，且未經其同意而將475萬元匯入自訴人帳戶內，偽造台北區中小企業銀行劃收申請書放款代收人傳票。嗣張富傑就其所貸款項無法清償，被告翁金川等人即以臺北區中小企業銀行名義聲請法院執行拍賣上開房、地，並請陳仲洲、吳宗南任名義人前往拍得上開房、地，復陳仲洲、吳宗南亦多次恐嚇要自訴人搬遷，否則將自訴人屍填大海等語，而被告翁金川等即以此方式奪取自訴人上開房、地。因認被告翁金川等涉有瀆職、偽造公文書、私文書、恐嚇、詐欺、背信等罪嫌云云，而向臺灣板橋地方法院檢察署提出告訴，經該署檢察官調查後認被告翁金川等5人被訴瀆職、偽造公文書、私文書、詐欺、背信等犯罪嫌疑不足，於88年1月28日以87年度偵字第19134號不起訴處分書為不起訴處分，嗣自訴人不服該處分而聲請再議，經臺灣高等法院檢察署檢察長調查審酌後，亦認被告翁金川等5人犯罪嫌疑不足，於88年4月29日以88年度議字第1281號處分書駁回再議確定等情，有上開不起訴處分書、駁回再議處分書各1件附卷可稽。２.核本件自訴人自訴被告翁金川等5人涉犯幫助詐欺取財等犯罪行為之事實，與自訴人於上揭偵查案件中被告被訴之犯罪事實相同，其行為人、行為時間、地點及行為內容均屬相同，雖就買賣金額、貸款金額記載略有出入，但就本件自訴人卷附所示之不動產買賣契約書、抵押權設定契約書、土地登記謄本、借據、臺北區中小企業銀行歷史明細檔查詢單（戶名：張銀得、帳號：0000000000000）等證據與前開偵查案件中所附證據參酌對照後均屬相同資料，堪認本件自訴案件所訴事實與前開偵查案件中所認定事實均屬相同。則本案自訴人於95年6月23日再以被告翁金川、許開鴻、盧玉麟、孫磊樺及蘇雅鈴等人之同一犯罪事實提起自訴（有臺灣臺北地方法院收文戳記可憑），其此部分所為自訴，係對檢察官依刑事訴訟法第228條規定開始偵查之同一案件，為不起訴處分確定後，再行自訴，依照上開說明，應諭知不受理之判決。(三)、另自訴人於自訴狀及補充理由狀上雖載其與被告張富傑所簽定之買賣契約係基於虛偽之意思表示而屬無效，故系爭房地所有權仍屬自訴人所有而未移轉於被告張富傑，然被告翁金川等5人明知自訴人與臺北區中小企業銀行間並無債權債務關係，亦無積欠任何款項未給付，仍行使假債權而將其所有系爭之房地，向法院聲請拍賣受償，致使案外人陳仲洲、吳宗南共同以750萬標得系爭房地，並由臺北區中小企業銀行萬華分行分配領走此款項，而獲得不法利益，因認被告翁金川等5人涉犯刑法第339條之3第1項、第2項之詐欺罪及同法第336條第2項業務侵占罪嫌。惟按刑法第339條之3第1項、第2項之非法以電腦設備相關設備製作不實財產權得喪變更紀錄取得他人財產及不法利益罪，其構成要件乃以行為人將虛偽資料或不正指令輸入電腦或其相關設備，而製作不實之財產紀錄以取得他人之財產或因此獲得不法利益始相當，又刑法第336條第2項之業務侵占罪係意圖為自己或第三人不法之所有，將因業務上持有之物品，變異原持有之意思為所有之意思，而加以侵占為構成要件，然據自訴狀及自訴補充理由狀所載，自訴人之主張係被告翁金川等5人以虛偽之債權向法院聲請拍賣自訴人所有之房地，並將拍賣所得750萬元款項領走未返還於自訴人，並非被告翁金川等5人以電腦設備或相關設備製作不實財產權得喪變更紀錄，且被告翁金川等5人自始即以行使其訴訟上之權利而為主張，亦無為自訴人持有之意思而占有，顯與刑法第339條之3第1項、第2項非法以電腦設備相關設備製作不實財產權得喪變更紀錄取財罪及第336條第2項業務侵占罪之構成要件無涉，是自訴狀另引上開法條為論罪依據，容有誤會，本院於裁判時得僅就被告被訴之事實範圍內審理，不受自訴狀所引犯罪法條之拘束，本院對自訴事實之法律評價不受自訴人引用法條或自訴人之法律判斷之限制，而應依自訴之社會事實作為法律評價之基準，是本院審酌此自訴事實與前開告訴案件中所訴之犯罪事實，衡為相同之事實，且為前開不起訴處分書及駁回再議處分書於理由中詳加論述，而為前開不起訴處分效力所包括，自不因自訴人於自訴狀中引用之法條不同而受拘束，仍屬刑事訴訟法第323條所規定之不得提起自訴之案件，依法自應為不受理判決。三、惟查，原判決係以自訴人自訴陳重陽、張富傑之犯罪事實，核與臺灣台北地方法院85年度自字第1023號（原判決誤載為85年度自字第1230號）、本院86年度上訴字第2171號、最高法院89年度台上字第3379號、臺灣台北地方法院92年度訴字第1230號、本院93年度上訴字第2215號等刑事確定判決，係屬社會事實相同之同一案件，本件關於陳重陽、張富傑部分為該等確定刑事判決之既判力所及，而就彼等二人部分為免訴之諭知；另就自訴人自訴被告許開鴻、翁金川、盧玉麟、孫磊樺、蘇雅玲之犯罪事實，核與台灣板橋地方法院檢察署87年度偵字第19134號不起訴處分書、臺灣高等法院檢察署88年度議字第1281號處分書，係屬事實相同之同一案件，上訴人此部分之自訴，係對檢察官開始偵查之同一案件，為不起訴處分後再行自訴，依刑事訴訟法第323條第1項之規定，而就被告許開鴻、翁金川、盧玉麟、孫磊樺、蘇雅鈴等五人為不受理之諭知，固非無見。惟對於自訴人於自訴狀所載之自訴事實（二）所載：被告陳重陽意圖為自己不法之所有，與被告張富傑與被告許開鴻等人為共同侵害自訴人出售係爭房屋土地給張富傑所應得之價款及貸款，於核准撥款前，未曾對於自訴人辦理合法之對保手續，則被告等為達成上述犯罪目的，顯有未經上訴人親自為對保手續，而逕自偽造上訴人名義之對保書，以遂行對保手續之情，與前開被告陳重陽、張富傑之刑事確定刑決、前開被告許開鴻等人之不起訴處分內容是否係屬同一案件，原判決未予論述；再者，就此部分，業經本院函詢永豐商業銀行萬華分行查詢有關自訴人與被告張富傑（原名張銀得）於85年6月29日因系爭房地買賣向該銀行設定最高限額抵押授權申請貸款留存資料，經該行函覆稱並無借貸申請書、撥款同意書及對保書暨撥款同意書等文件，有該行99年7月15日永豐銀萬華分行（99）字第8號函在卷可稽（見本院卷第132頁）；再經本院函調該行信用部門有關徵信及授信作業手冊等相關資料，該行函覆：「三、2.『貸款申請書』即本行於99年7月15日函復所提供之『授信申請書』。3.本案並無『撥款同意書』之文件。4.本案並無『對保書暨撥款同意書』之文件」，亦檢附該行於85年6月間有關貸款之徵信及授信作業手冊（核貸通知、簽約對保、設定擔保物權、撥付貸款、帳務處理等手續應注意事項），此有該行99年10月8日永豐銀萬華分行（99）字第11號函附卷可按（本院卷第198頁）。由上開函查結果可知，該行並無借貸申請書、撥款同意書、對保書暨撥款同意書等文件，自無從證明被告陳重陽、張富傑、許開鴻、翁金川、盧玉麟、孫磊樺、蘇雅鈴等人有自訴意旨所稱被告等人未經自訴人親自為對保手續，而逕自偽造上訴人名義之對保書，以遂行對保手續等行為，則自訴人自訴被告等此部分之犯罪嫌疑顯有不足，則本件是否仍可依刑事訴訟法第302條第1款、第323條第1項規定，遽為免訴及自訴不受理判決，抑或應就此部分另行處理，自有再加研求之餘地。自訴人指摘原判決不當，非無理由，爰由本院將原判決撤銷發回原審法院另為適當之處理，並不經言詞辯論為之。四、據上論斷，應依刑事訴訟法第369條第1項但書、第372條，判決如主文。中華民國100年1月12日刑事第二十三庭審判長法官童有德法官陳祐治法官徐蘭萍以上正本證明與原本無異。如不服本判決，應於收受送達後10日內向本院提出上訴書狀，其未敘述上訴之理由者並得於提起上訴後10日內向本院補提理由書（均須按他造當事人之人數附繕本）「切勿逕送上級法院」。書記官林月蓉中華民國100年1月12日",
  "characters": {
    "judges": [
      "童有德",
      "陳祐治",
      "徐蘭萍"
    ],
    "prosecutors": [

    ],
    "lawyers": [
      "林辰彥",
      "謝玉玲",
      "林傳哲"
    ],
    "clerks": [
      "林月蓉"
    ],
    "plaintiffs": [

    ],
    "defendants": [
      "陳重陽"
    ],
    "prosecutor_office": [

    ],
    "creditors": [

    ],
    "debtors": [

    ],
    "judicial_associate_officer": [

    ]
  },
  "adjudged_at": "2011-01-12",
  "created_at": "2016-02-13 07:13:41",
  "updated_at": "2016-02-13 07:13:41"
}